Workbook

Sheet Parametros
B2: Producto | C2: Convenios
B4: Año | C4: 2026
B6: Lista Fechas | C6: =EOMONTH(DATE($C$4,1,1),0) -> 46053 | E6: Segmentos | F6: Renta_Alta
C7: =EOMONTH(C6,1) -> 46081 | F7: Masivo
C8: =EOMONTH(C7,1) -> 46112 | F8: Consumo_Inicial
C9: =EOMONTH(C8,1) -> 46142 | F9: Total_Producto
C10: =EOMONTH(C9,1) -> 46173
C11: =EOMONTH(C10,1) -> 46203
C12: =EOMONTH(C11,1) -> 46234
C13: =EOMONTH(C12,1) -> 46265
C14: =EOMONTH(C13,1) -> 46295
C15: =EOMONTH(C14,1) -> 46326
C16: =EOMONTH(C15,1) -> 46356
C17: =EOMONTH(C16,1) -> 46387

Sheet Total_Producto_Check
D1: REAL | AZ1: PRESUPUESTO | BO1: Acumulado | BW1: Saldo Prom Acumulado
BO2: =DATE(YEAR(BO6),1,1) -> 46023 | BP2: =DATE(YEAR(BP6),1,1) -> 46023 | BQ2: =DATE(YEAR(BQ6),1,1) -> 46023 | BR2: =DATE(YEAR(BR6),1,1) -> 45658 | BS2: =DATE(YEAR(BS6),1,1) -> 45292 | BT2: =DATE(YEAR(BT6),1,1) -> 44927
C3: N° dias T.Imp | D3: =DAY(D6) -> 31 | E3: =DAY(E6) -> 28 | F3: =DAY(F6) -> 31 | G3: =DAY(G6) -> 30 | H3: =DAY(H6) -> 31 | I3: =DAY(I6) -> 30 | J3: =DAY(J6) -> 31 | K3: =DAY(K6) -> 31 | ... BK3: =DAY(BK6) -> 31 | BO3: =AVERAGEIFS($D3:$BM3,$D$6:$BM$6,">="&BO$2,$D$6:$BM$6,"<="&BO$6,$D$5:$BM$5,BO$5) -> 30 | BP3: =AVERAGEIFS($D3:$BM3,$D$6:$BM$6,">="&BP$2,$D$6:$BM$6,"<="&BP$6,$D$5:$BM$5,BP$5) -> 30 | BQ3: =AVERAGEIFS($D3:$BM3,$D$6:$BM$6,">="&BQ$2,$D$6:$BM$6,"<="&BQ$6,$D$5:$BM$5,BQ$5) -> 29.5 | BR3: =AVERAGEIFS($D3:$BM3,$D$6:$BM$6,">="&BR$2,$D$6:$BM$6,"<="&BR$6,$D$5:$BM$5,BR$5) -> 30 | BS3: =AVERAGEIFS($D3:$BM3,$D$6:$BM$6,">="&BS$2,$D$6:$BM$6,"<="&BS$6,$D$5:$BM$5,BS$5) -> 30.333333 | BT3: =AVERAGEIFS($D3:$BM3,$D$6:$BM$6,">="&BT$2,$D$6:$BM$6,"<="&BT$6,$D$5:$BM$5,BT$5) -> 30
C4: N° dias FTP | D4: =DAY(D6) -> 31 | E4: =DAY(E6) -> 28 | F4: =DAY(F6) -> 31 | G4: =DAY(G6) -> 30 | H4: =DAY(H6) -> 31 | I4: =DAY(I6) -> 30 | J4: =DAY(J6) -> 31 | K4: =DAY(K6) -> 31 | ... BK4: =DAY(BK6) -> 31 | BO4: =AVERAGEIFS($D4:$BM4,$D$6:$BM$6,">="&BO$2,$D$6:$BM$6,"<="&BO$6,$D$5:$BM$5,BO$5) -> 30 | BP4: =AVERAGEIFS($D4:$BM4,$D$6:$BM$6,">="&BP$2,$D$6:$BM$6,"<="&BP$6,$D$5:$BM$5,BP$5) -> 30 | BQ4: =AVERAGEIFS($D4:$BM4,$D$6:$BM$6,">="&BQ$2,$D$6:$BM$6,"<="&BQ$6,$D$5:$BM$5,BQ$5) -> 29.5 | BR4: =AVERAGEIFS($D4:$BM4,$D$6:$BM$6,">="&BR$2,$D$6:$BM$6,"<="&BR$6,$D$5:$BM$5,BR$5) -> 30 | BS4: =AVERAGEIFS($D4:$BM4,$D$6:$BM$6,">="&BS$2,$D$6:$BM$6,"<="&BS$6,$D$5:$BM$5,BS$5) -> 30.333333 | BT4: =AVERAGEIFS($D4:$BM4,$D$6:$BM$6,">="&BT$2,$D$6:$BM$6,"<="&BT$6,$D$5:$BM$5,BT$5) -> 30
C5: Tipo | D5: R | E5: R | F5: R | G5: R | H5: R | I5: R | J5: R | K5: R | L5: R | M5: R | N5: R | O5: R | P5: R | Q5: R | R5: R | S5: R | T5: R | U5: R | V5: R | W5: R | X5: R | Y5: R | Z5: R | AA5: R | AB5: R | AC5: R | AD5: R | AE5: R | AF5: R | AG5: R | AH5: R | AI5: R | AJ5: R | AK5: R | AL5: R | AM5: R | AN5: R | AO5: R | AP5: R | AQ5: R | AR5: R | AS5: R | AT5: R | AU5: R | AV5: R | AW5: R | AX5: R | AY5: R | AZ5: P | BA5: P | BB5: P | BC5: P | BD5: P | BE5: P | BF5: P | BG5: P | BH5: P | BI5: P | BJ5: P | BK5: P | BO5: R | BP5: P | BQ5: R | BR5: R | BS5: R | BT5: R
C6: Total Tarjetas | D6: 44957 | E6: 44985 | F6: 45016 | G6: 45046 | H6: 45077 | I6: 45107 | J6: 45138 | K6: 45169 | L6: 45199 | M6: 45230 | N6: 45260 | O6: 45291 | P6: 45322 | Q6: 45351 | R6: 45382 | S6: 45412 | T6: 45443 | U6: 45473 | V6: 45504 | W6: 45535 | X6: 45565 | Y6: 45596 | Z6: 45626 | AA6: 45657 | AB6: 45688 | AC6: 45716 | AD6: 45747 | AE6: 45777 | AF6: 45808 | AG6: 45838 | AH6: 45869 | AI6: 45900 | AJ6: 45930 | AK6: 45961 | AL6: 45991 | AM6: 46022 | AN6: 46053 | AO6: 46081 | AP6: 46112 | AQ6: 46142 | AR6: 46173 | AS6: 46203 | AT6: 46234 | AU6: 46265 | AV6: 46295 | AW6: 46326 | AX6: 46356 | AY6: 46387 | AZ6: 46053 | BA6: 46081 | BB6: 46112 | BC6: 46142 | BD6: 46173 | BE6: 46203 | BF6: 46234 | BG6: 46265 | BH6: 46295 | BI6: 46326 | BJ6: 46356 | BK6: 46387 | BO6: =Desempeño_Financiero!$B$1 -> 46112 | BP6: =BO6 -> 46112 | BQ6: =EOMONTH(BO6,-1) -> 46081 | BR6: =EOMONTH(BO6,-12) -> 45747 | BS6: =EOMONTH(BO6,-24) -> 45382 | BT6: =EOMONTH(BO6,-36) -> 45016 | BW6: =BO6 -> 46112 | BX6: =BP6 -> 46112 | BY6: =BQ6 -> 46081 | BZ6: =BR6 -> 45747 | CA6: =BS6 -> 45382 | CB6: =BT6 -> 45016
A8: SALDO_FDP | C8: Vigente | D8: =RA_TC!D8+MA_TC!D8+CI_TC!D8 -> 0 | E8: =RA_TC!E8+MA_TC!E8+CI_TC!E8 -> 0 | F8: =RA_TC!F8+MA_TC!F8+CI_TC!F8 -> 0 | G8: =RA_TC!G8+MA_TC!G8+CI_TC!G8 -> 0 | H8: =RA_TC!H8+MA_TC!H8+CI_TC!H8 -> 0 | I8: =RA_TC!I8+MA_TC!I8+CI_TC!I8 -> 0 | J8: =RA_TC!J8+MA_TC!J8+CI_TC!J8 -> 0 | K8: =RA_TC!K8+MA_TC!K8+CI_TC!K8 -> 0 | ... BK8: =RA_TC!BK8+MA_TC!BK8+CI_TC!BK8 -> 6101726.9 | BO8: =_xlfn.XLOOKUP(BO$6,$D$6:$BM$6,$D8:$BM8,,0,1) -> 0 | BP8: =_xlfn.XLOOKUP(BP$6,$D$6:$BM$6,$D8:$BM8,,0,-1) -> 5475782.9 | BQ8: =_xlfn.XLOOKUP(BQ$6,$D$6:$BM$6,$D8:$BM8,,0,1) -> 0 | BR8: =_xlfn.XLOOKUP(BR$6,$D$6:$BM$6,$D8:$BM8,,0,1) -> 0 | BS8: =_xlfn.XLOOKUP(BS$6,$D$6:$BM$6,$D8:$BM8,,0,1) -> 0 | BT8: =_xlfn.XLOOKUP(BT$6,$D$6:$BM$6,$D8:$BM8,,0,1) -> 0
A9: SALDO_FDP | C9: Refinanciado | D9: =RA_TC!D9+MA_TC!D9+CI_TC!D9 -> 0 | E9: =RA_TC!E9+MA_TC!E9+CI_TC!E9 -> 0 | F9: =RA_TC!F9+MA_TC!F9+CI_TC!F9 -> 0 | G9: =RA_TC!G9+MA_TC!G9+CI_TC!G9 -> 0 | H9: =RA_TC!H9+MA_TC!H9+CI_TC!H9 -> 0 | I9: =RA_TC!I9+MA_TC!I9+CI_TC!I9 -> 0 | J9: =RA_TC!J9+MA_TC!J9+CI_TC!J9 -> 0 | K9: =RA_TC!K9+MA_TC!K9+CI_TC!K9 -> 0 | ... BK9: =RA_TC!BK9+MA_TC!BK9+CI_TC!BK9 -> 191034.16 | BO9: =_xlfn.XLOOKUP(BO$6,$D$6:$BM$6,$D9:$BM9,,0,1) -> 0 | BP9: =_xlfn.XLOOKUP(BP$6,$D$6:$BM$6,$D9:$BM9,,0,-1) -> 187857.74 | BQ9: =_xlfn.XLOOKUP(BQ$6,$D$6:$BM$6,$D9:$BM9,,0,1) -> 0 | BR9: =_xlfn.XLOOKUP(BR$6,$D$6:$BM$6,$D9:$BM9,,0,1) -> 0 | BS9: =_xlfn.XLOOKUP(BS$6,$D$6:$BM$6,$D9:$BM9,,0,1) -> 0 | BT9: =_xlfn.XLOOKUP(BT$6,$D$6:$BM$6,$D9:$BM9,,0,1) -> 0
A10: SALDO_FDP | C10: Vencido y Judicial | D10: =RA_TC!D10+MA_TC!D10+CI_TC!D10 -> 0 | E10: =RA_TC!E10+MA_TC!E10+CI_TC!E10 -> 0 | F10: =RA_TC!F10+MA_TC!F10+CI_TC!F10 -> 0 | G10: =RA_TC!G10+MA_TC!G10+CI_TC!G10 -> 0 | H10: =RA_TC!H10+MA_TC!H10+CI_TC!H10 -> 0 | I10: =RA_TC!I10+MA_TC!I10+CI_TC!I10 -> 0 | J10: =RA_TC!J10+MA_TC!J10+CI_TC!J10 -> 0 | K10: =RA_TC!K10+MA_TC!K10+CI_TC!K10 -> 0 | ... BK10: =RA_TC!BK10+MA_TC!BK10+CI_TC!BK10 -> 255200.78 | BO10: =_xlfn.XLOOKUP(BO$6,$D$6:$BM$6,$D10:$BM10,,0,1) -> 0 | BP10: =_xlfn.XLOOKUP(BP$6,$D$6:$BM$6,$D10:$BM10,,0,-1) -> 242951.26 | BQ10: =_xlfn.XLOOKUP(BQ$6,$D$6:$BM$6,$D10:$BM10,,0,1) -> 0 | BR10: =_xlfn.XLOOKUP(BR$6,$D$6:$BM$6,$D10:$BM10,,0,1) -> 0 | BS10: =_xlfn.XLOOKUP(BS$6,$D$6:$BM$6,$D10:$BM10,,0,1) -> 0 | BT10: =_xlfn.XLOOKUP(BT$6,$D$6:$BM$6,$D10:$BM10,,0,1) -> 0
C11: Saldo FdP | D11: =SUM(D8:D10) -> 0 | E11: =SUM(E8:E10) -> 0 | F11: =SUM(F8:F10) -> 0 | G11: =SUM(G8:G10) -> 0 | H11: =SUM(H8:H10) -> 0 | I11: =SUM(I8:I10) -> 0 | J11: =SUM(J8:J10) -> 0 | K11: =SUM(K8:K10) -> 0 | ... BK11: =SUM(BK8:BK10) -> 6547961.9 | BO11: =SUM(BO8:BO10) -> 0 | BP11: =SUM(BP8:BP10) -> 5906591.9 | BQ11: =SUM(BQ8:BQ10) -> 0 | BR11: =SUM(BR8:BR10) -> 0 | BS11: =SUM(BS8:BS10) -> 0 | BT11: =SUM(BT8:BT10) -> 0
D12: ='[1]Desempeño Finan_ TC_Cartera_Evo'!AY10-D11 -> 6751883.9 | E12: ='[1]Desempeño Finan_ TC_Cartera_Evo'!AZ10-E11 -> 6868384.2 | F12: ='[1]Desempeño Finan_ TC_Cartera_Evo'!BA10-F11 -> 7072870.9 | G12: ='[1]Desempeño Finan_ TC_Cartera_Evo'!BB10-G11 -> 7128656.3 | H12: ='[1]Desempeño Finan_ TC_Cartera_Evo'!BC10-H11 -> 7315435.6 | I12: ='[1]Desempeño Finan_ TC_Cartera_Evo'!BD10-I11 -> 7388523.1 | J12: ='[1]Desempeño Finan_ TC_Cartera_Evo'!BE10-J11 -> 7356182.5 | K12: ='[1]Desempeño Finan_ TC_Cartera_Evo'!BF10-K11 -> 7370654.4 | ... BK12: ='[1]Desempeño Finan_ TC_Cartera_Evo'!DF10-BK11 -> 0
A14: SALDO_PROM | C14: Vigente | D14: =RA_TC!D14+MA_TC!D14+CI_TC!D14 -> 0 | E14: =RA_TC!E14+MA_TC!E14+CI_TC!E14 -> 0 | F14: =RA_TC!F14+MA_TC!F14+CI_TC!F14 -> 0 | G14: =RA_TC!G14+MA_TC!G14+CI_TC!G14 -> 0 | H14: =RA_TC!H14+MA_TC!H14+CI_TC!H14 -> 0 | I14: =RA_TC!I14+MA_TC!I14+CI_TC!I14 -> 0 | J14: =RA_TC!J14+MA_TC!J14+CI_TC!J14 -> 0 | K14: =RA_TC!K14+MA_TC!K14+CI_TC!K14 -> 0 | ... BK14: =RA_TC!BK14+MA_TC!BK14+CI_TC!BK14 -> 5993248.4 | BO14: =IFERROR(AVERAGEIFS($D14:$BM14,$D$6:$BM$6,">="&BO$2,$D$6:$BM$6,"<="&BO$6,$D$5:$BM$5,BO$5,$D14:$BM14,"<>0"),0) -> 0 | BP14: =IFERROR(AVERAGEIFS($D14:$BM14,$D$6:$BM$6,">="&BP$2,$D$6:$BM$6,"<="&BP$6,$D$5:$BM$5,BP$5,$D14:$BM14,"<>0"),0) -> 5394716 | BQ14: =IFERROR(AVERAGEIFS($D14:$BM14,$D$6:$BM$6,">="&BQ$2,$D$6:$BM$6,"<="&BQ$6,$D$5:$BM$5,BQ$5,$D14:$BM14,"<>0"),0) -> 0 | BR14: =IFERROR(AVERAGEIFS($D14:$BM14,$D$6:$BM$6,">="&BR$2,$D$6:$BM$6,"<="&BR$6,$D$5:$BM$5,BR$5,$D14:$BM14,"<>0"),0) -> 0 | BS14: =IFERROR(AVERAGEIFS($D14:$BM14,$D$6:$BM$6,">="&BS$2,$D$6:$BM$6,"<="&BS$6,$D$5:$BM$5,BS$5,$D14:$BM14,"<>0"),0) -> 0 | BT14: =IFERROR(AVERAGEIFS($D14:$BM14,$D$6:$BM$6,">="&BT$2,$D$6:$BM$6,"<="&BT$6,$D$5:$BM$5,BT$5,$D14:$BM14,"<>0"),0) -> 0 | BW14: =SUMIFS($D14:$BM14,$D$6:$BM$6,">="&BO$2,$D$6:$BM$6,"<="&BO$6,$D$5:$BM$5,BO$5) -> 0 | BX14: =SUMIFS($D14:$BM14,$D$6:$BM$6,">="&BP$2,$D$6:$BM$6,"<="&BP$6,$D$5:$BM$5,BP$5) -> 16184148 | BY14: =SUMIFS($D14:$BM14,$D$6:$BM$6,">="&BQ$2,$D$6:$BM$6,"<="&BQ$6,$D$5:$BM$5,BQ$5) -> 0 | BZ14: =SUMIFS($D14:$BM14,$D$6:$BM$6,">="&BR$2,$D$6:$BM$6,"<="&BR$6,$D$5:$BM$5,BR$5) -> 0 | CA14: =SUMIFS($D14:$BM14,$D$6:$BM$6,">="&BS$2,$D$6:$BM$6,"<="&BS$6,$D$5:$BM$5,BS$5) -> 0 | CB14: =SUMIFS($D14:$BM14,$D$6:$BM$6,">="&BT$2,$D$6:$BM$6,"<="&BT$6,$D$5:$BM$5,BT$5) -> 0
A15: SALDO_PROM | C15: Refinanciado | D15: =RA_TC!D15+MA_TC!D15+CI_TC!D15 -> 0 | E15: =RA_TC!E15+MA_TC!E15+CI_TC!E15 -> 0 | F15: =RA_TC!F15+MA_TC!F15+CI_TC!F15 -> 0 | G15: =RA_TC!G15+MA_TC!G15+CI_TC!G15 -> 0 | H15: =RA_TC!H15+MA_TC!H15+CI_TC!H15 -> 0 | I15: =RA_TC!I15+MA_TC!I15+CI_TC!I15 -> 0 | J15: =RA_TC!J15+MA_TC!J15+CI_TC!J15 -> 0 | K15: =RA_TC!K15+MA_TC!K15+CI_TC!K15 -> 0 | ... BK15: =RA_TC!BK15+MA_TC!BK15+CI_TC!BK15 -> 183040.35 | BO15: =IFERROR(AVERAGEIFS($D15:$BM15,$D$6:$BM$6,">="&BO$2,$D$6:$BM$6,"<="&BO$6,$D$5:$BM$5,BO$5,$D15:$BM15,"<>0"),0) -> 0 | BP15: =IFERROR(AVERAGEIFS($D15:$BM15,$D$6:$BM$6,">="&BP$2,$D$6:$BM$6,"<="&BP$6,$D$5:$BM$5,BP$5,$D15:$BM15,"<>0"),0) -> 183585.17 | BQ15: =IFERROR(AVERAGEIFS($D15:$BM15,$D$6:$BM$6,">="&BQ$2,$D$6:$BM$6,"<="&BQ$6,$D$5:$BM$5,BQ$5,$D15:$BM15,"<>0"),0) -> 0 | BR15: =IFERROR(AVERAGEIFS($D15:$BM15,$D$6:$BM$6,">="&BR$2,$D$6:$BM$6,"<="&BR$6,$D$5:$BM$5,BR$5,$D15:$BM15,"<>0"),0) -> 0 | BS15: =IFERROR(AVERAGEIFS($D15:$BM15,$D$6:$BM$6,">="&BS$2,$D$6:$BM$6,"<="&BS$6,$D$5:$BM$5,BS$5,$D15:$BM15,"<>0"),0) -> 0 | BT15: =IFERROR(AVERAGEIFS($D15:$BM15,$D$6:$BM$6,">="&BT$2,$D$6:$BM$6,"<="&BT$6,$D$5:$BM$5,BT$5,$D15:$BM15,"<>0"),0) -> 0 | BW15: =SUMIFS($D15:$BM15,$D$6:$BM$6,">="&BO$2,$D$6:$BM$6,"<="&BO$6,$D$5:$BM$5,BO$5) -> 0 | BX15: =SUMIFS($D15:$BM15,$D$6:$BM$6,">="&BP$2,$D$6:$BM$6,"<="&BP$6,$D$5:$BM$5,BP$5) -> 550755.5 | BY15: =SUMIFS($D15:$BM15,$D$6:$BM$6,">="&BQ$2,$D$6:$BM$6,"<="&BQ$6,$D$5:$BM$5,BQ$5) -> 0 | BZ15: =SUMIFS($D15:$BM15,$D$6:$BM$6,">="&BR$2,$D$6:$BM$6,"<="&BR$6,$D$5:$BM$5,BR$5) -> 0 | CA15: =SUMIFS($D15:$BM15,$D$6:$BM$6,">="&BS$2,$D$6:$BM$6,"<="&BS$6,$D$5:$BM$5,BS$5) -> 0 | CB15: =SUMIFS($D15:$BM15,$D$6:$BM$6,">="&BT$2,$D$6:$BM$6,"<="&BT$6,$D$5:$BM$5,BT$5) -> 0
A16: SALDO_PROM | C16: Vencido y Judicial | D16: =RA_TC!D16+MA_TC!D16+CI_TC!D16 -> 0 | E16: =RA_TC!E16+MA_TC!E16+CI_TC!E16 -> 0 | F16: =RA_TC!F16+MA_TC!F16+CI_TC!F16 -> 0 | G16: =RA_TC!G16+MA_TC!G16+CI_TC!G16 -> 0 | H16: =RA_TC!H16+MA_TC!H16+CI_TC!H16 -> 0 | I16: =RA_TC!I16+MA_TC!I16+CI_TC!I16 -> 0 | J16: =RA_TC!J16+MA_TC!J16+CI_TC!J16 -> 0 | K16: =RA_TC!K16+MA_TC!K16+CI_TC!K16 -> 0 | ... BK16: =RA_TC!BK16+MA_TC!BK16+CI_TC!BK16 -> 276079.3 | BO16: =IFERROR(AVERAGEIFS($D16:$BM16,$D$6:$BM$6,">="&BO$2,$D$6:$BM$6,"<="&BO$6,$D$5:$BM$5,BO$5,$D16:$BM16,"<>0"),0) -> 0 | BP16: =IFERROR(AVERAGEIFS($D16:$BM16,$D$6:$BM$6,">="&BP$2,$D$6:$BM$6,"<="&BP$6,$D$5:$BM$5,BP$5,$D16:$BM16,"<>0"),0) -> 269886.41 | BQ16: =IFERROR(AVERAGEIFS($D16:$BM16,$D$6:$BM$6,">="&BQ$2,$D$6:$BM$6,"<="&BQ$6,$D$5:$BM$5,BQ$5,$D16:$BM16,"<>0"),0) -> 0 | BR16: =IFERROR(AVERAGEIFS($D16:$BM16,$D$6:$BM$6,">="&BR$2,$D$6:$BM$6,"<="&BR$6,$D$5:$BM$5,BR$5,$D16:$BM16,"<>0"),0) -> 0 | BS16: =IFERROR(AVERAGEIFS($D16:$BM16,$D$6:$BM$6,">="&BS$2,$D$6:$BM$6,"<="&BS$6,$D$5:$BM$5,BS$5,$D16:$BM16,"<>0"),0) -> 0 | BT16: =IFERROR(AVERAGEIFS($D16:$BM16,$D$6:$BM$6,">="&BT$2,$D$6:$BM$6,"<="&BT$6,$D$5:$BM$5,BT$5,$D16:$BM16,"<>0"),0) -> 0 | BW16: =SUMIFS($D16:$BM16,$D$6:$BM$6,">="&BO$2,$D$6:$BM$6,"<="&BO$6,$D$5:$BM$5,BO$5) -> 0 | BX16: =SUMIFS($D16:$BM16,$D$6:$BM$6,">="&BP$2,$D$6:$BM$6,"<="&BP$6,$D$5:$BM$5,BP$5) -> 809659.23 | BY16: =SUMIFS($D16:$BM16,$D$6:$BM$6,">="&BQ$2,$D$6:$BM$6,"<="&BQ$6,$D$5:$BM$5,BQ$5) -> 0 | BZ16: =SUMIFS($D16:$BM16,$D$6:$BM$6,">="&BR$2,$D$6:$BM$6,"<="&BR$6,$D$5:$BM$5,BR$5) -> 0 | CA16: =SUMIFS($D16:$BM16,$D$6:$BM$6,">="&BS$2,$D$6:$BM$6,"<="&BS$6,$D$5:$BM$5,BS$5) -> 0 | CB16: =SUMIFS($D16:$BM16,$D$6:$BM$6,">="&BT$2,$D$6:$BM$6,"<="&BT$6,$D$5:$BM$5,BT$5) -> 0
C17: Saldo Prom | D17: =SUM(D14:D16) -> 0 | E17: =SUM(E14:E16) -> 0 | F17: =SUM(F14:F16) -> 0 | G17: =SUM(G14:G16) -> 0 | H17: =SUM(H14:H16) -> 0 | I17: =SUM(I14:I16) -> 0 | J17: =SUM(J14:J16) -> 0 | K17: =SUM(K14:K16) -> 0 | ... BK17: =SUM(BK14:BK16) -> 6452368.1 | BO17: =SUM(BO14:BO16) -> 0 | BP17: =SUM(BP14:BP16) -> 5848187.6 | BQ17: =SUM(BQ14:BQ16) -> 0 | BR17: =SUM(BR14:BR16) -> 0 | BS17: =SUM(BS14:BS16) -> 0 | BT17: =SUM(BT14:BT16) -> 0 | BW17: =SUM(BW14:BW16) -> 0 | BX17: =SUM(BX14:BX16) -> 17544563 | BY17: =SUM(BY14:BY16) -> 0 | BZ17: =SUM(BZ14:BZ16) -> 0 | CA17: =SUM(CA14:CA16) -> 0 | CB17: =SUM(CB14:CB16) -> 0
D18: ='[1]Desempeño Finan_ TC_Cartera_Evo'!AY15-D17 -> 6606767.9 | E18: ='[1]Desempeño Finan_ TC_Cartera_Evo'!AZ15-E17 -> 6718626.3 | F18: ='[1]Desempeño Finan_ TC_Cartera_Evo'!BA15-F17 -> 6908092.8 | G18: ='[1]Desempeño Finan_ TC_Cartera_Evo'!BB15-G17 -> 7032104.8 | H18: ='[1]Desempeño Finan_ TC_Cartera_Evo'!BC15-H17 -> 7150778.6 | I18: ='[1]Desempeño Finan_ TC_Cartera_Evo'!BD15-I17 -> 7292178.2 | J18: ='[1]Desempeño Finan_ TC_Cartera_Evo'!BE15-J17 -> 7258431.2 | K18: ='[1]Desempeño Finan_ TC_Cartera_Evo'!BF15-K17 -> 7293848.5 | ... BK18: ='[1]Desempeño Finan_ TC_Cartera_Evo'!DF15-BK17 -> 0
C20: Vigente | D20: =IFERROR(((1+D38/D14)^(360/D$3))-1,0) -> 0 | E20: =IFERROR(((1+E38/E14)^(360/E$3))-1,0) -> 0 | F20: =IFERROR(((1+F38/F14)^(360/F$3))-1,0) -> 0 | G20: =IFERROR(((1+G38/G14)^(360/G$3))-1,0) -> 0 | H20: =IFERROR(((1+H38/H14)^(360/H$3))-1,0) -> 0 | I20: =IFERROR(((1+I38/I14)^(360/I$3))-1,0) -> 0 | J20: =IFERROR(((1+J38/J14)^(360/J$3))-1,0) -> 0 | K20: =IFERROR(((1+K38/K14)^(360/K$3))-1,0) -> 0 | ... BK20: =IFERROR(((1+BK38/BK14)^(360/BK$3))-1,0) -> 0.26667291 | BO20: =IFERROR(((1+BO38/BW14)^(360/BO$3))-1,0) -> 0 | BP20: =IFERROR(((1+BP38/BX14)^(360/BP$3))-1,0) -> 0.25696584 | BQ20: =IFERROR(((1+BQ38/BY14)^(360/BQ$3))-1,0) -> 0 | BR20: =IFERROR(((1+BR38/BZ14)^(360/BR$3))-1,0) -> 0 | BS20: =IFERROR(((1+BS38/CA14)^(360/BS$3))-1,0) -> 0 | BT20: =IFERROR(((1+BT38/CB14)^(360/BT$3))-1,0) -> 0
C21: Refinanciado | D21: =IFERROR(((1+D39/D15)^(360/D$3))-1,0) -> 0 | E21: =IFERROR(((1+E39/E15)^(360/E$3))-1,0) -> 0 | F21: =IFERROR(((1+F39/F15)^(360/F$3))-1,0) -> 0 | G21: =IFERROR(((1+G39/G15)^(360/G$3))-1,0) -> 0 | H21: =IFERROR(((1+H39/H15)^(360/H$3))-1,0) -> 0 | I21: =IFERROR(((1+I39/I15)^(360/I$3))-1,0) -> 0 | J21: =IFERROR(((1+J39/J15)^(360/J$3))-1,0) -> 0 | K21: =IFERROR(((1+K39/K15)^(360/K$3))-1,0) -> 0 | ... BK21: =IFERROR(((1+BK39/BK15)^(360/BK$3))-1,0) -> 0.10692987 | BO21: =IFERROR(((1+BO39/BW15)^(360/BO$3))-1,0) -> 0 | BP21: =IFERROR(((1+BP39/BX15)^(360/BP$3))-1,0) -> 0.10616469 | BQ21: =IFERROR(((1+BQ39/BY15)^(360/BQ$3))-1,0) -> 0 | BR21: =IFERROR(((1+BR39/BZ15)^(360/BR$3))-1,0) -> 0 | BS21: =IFERROR(((1+BS39/CA15)^(360/BS$3))-1,0) -> 0 | BT21: =IFERROR(((1+BT39/CB15)^(360/BT$3))-1,0) -> 0
C22: Vencido y Judicial | D22: =IFERROR(((1+D40/D16)^(360/D$3))-1,0) -> 0 | E22: =IFERROR(((1+E40/E16)^(360/E$3))-1,0) -> 0 | F22: =IFERROR(((1+F40/F16)^(360/F$3))-1,0) -> 0 | G22: =IFERROR(((1+G40/G16)^(360/G$3))-1,0) -> 0 | H22: =IFERROR(((1+H40/H16)^(360/H$3))-1,0) -> 0 | I22: =IFERROR(((1+I40/I16)^(360/I$3))-1,0) -> 0 | J22: =IFERROR(((1+J40/J16)^(360/J$3))-1,0) -> 0 | K22: =IFERROR(((1+K40/K16)^(360/K$3))-1,0) -> 0 | ... BK22: =IFERROR(((1+BK40/BK16)^(360/BK$3))-1,0) -> 0.19048324 | BO22: =IFERROR(((1+BO40/BW16)^(360/BO$3))-1,0) -> 0 | BP22: =IFERROR(((1+BP40/BX16)^(360/BP$3))-1,0) -> 0.20328197 | BQ22: =IFERROR(((1+BQ40/BY16)^(360/BQ$3))-1,0) -> 0 | BR22: =IFERROR(((1+BR40/BZ16)^(360/BR$3))-1,0) -> 0 | BS22: =IFERROR(((1+BS40/CA16)^(360/BS$3))-1,0) -> 0 | BT22: =IFERROR(((1+BT40/CB16)^(360/BT$3))-1,0) -> 0
C23: Tasa Implicita | D23: =IFERROR(((1+D41/D17)^(360/D$3))-1,0) -> 0 | E23: =IFERROR(((1+E41/E17)^(360/E$3))-1,0) -> 0 | F23: =IFERROR(((1+F41/F17)^(360/F$3))-1,0) -> 0 | G23: =IFERROR(((1+G41/G17)^(360/G$3))-1,0) -> 0 | H23: =IFERROR(((1+H41/H17)^(360/H$3))-1,0) -> 0 | I23: =IFERROR(((1+I41/I17)^(360/I$3))-1,0) -> 0 | J23: =IFERROR(((1+J41/J17)^(360/J$3))-1,0) -> 0 | K23: =IFERROR(((1+K41/K17)^(360/K$3))-1,0) -> 0 | ... BK23: =IFERROR(((1+BK41/BK17)^(360/BK$3))-1,0) -> 0.25852793 | BO23: =IFERROR(((1+BO41/BW17)^(360/BO$3))-1,0) -> 0 | BP23: =IFERROR(((1+BP41/BX17)^(360/BP$3))-1,0) -> 0.24944315 | BQ23: =IFERROR(((1+BQ41/BY17)^(360/BQ$3))-1,0) -> 0 | BR23: =IFERROR(((1+BR41/BZ17)^(360/BR$3))-1,0) -> 0 | BS23: =IFERROR(((1+BS41/CA17)^(360/BS$3))-1,0) -> 0 | BT23: =IFERROR(((1+BT41/CB17)^(360/BT$3))-1,0) -> 0
C26: Vigente | D26: =-IFERROR(((1-D44/D14)^(360/D$4))-1,0) -> 0 | E26: =-IFERROR(((1-E44/E14)^(360/E$4))-1,0) -> 0 | F26: =-IFERROR(((1-F44/F14)^(360/F$4))-1,0) -> 0 | G26: =-IFERROR(((1-G44/G14)^(360/G$4))-1,0) -> 0 | H26: =-IFERROR(((1-H44/H14)^(360/H$4))-1,0) -> 0 | I26: =-IFERROR(((1-I44/I14)^(360/I$4))-1,0) -> 0 | J26: =-IFERROR(((1-J44/J14)^(360/J$4))-1,0) -> 0 | K26: =-IFERROR(((1-K44/K14)^(360/K$4))-1,0) -> 0 | ... BK26: =-IFERROR(((1-BK44/BK14)^(360/BK$4))-1,0) -> -0.047972923 | BO26: =-IFERROR(((1-BO44/BW14)^(360/BO$4))-1,0) -> 0 | BP26: =-IFERROR(((1-BP44/BX14)^(360/BP$4))-1,0) -> -0.049891884 | BQ26: =-IFERROR(((1-BQ44/BY14)^(360/BQ$4))-1,0) -> 0 | BR26: =-IFERROR(((1-BR44/BZ14)^(360/BR$4))-1,0) -> 0 | BS26: =-IFERROR(((1-BS44/CA14)^(360/BS$4))-1,0) -> 0 | BT26: =-IFERROR(((1-BT44/CB14)^(360/BT$4))-1,0) -> 0
C27: Refinanciado | D27: =-IFERROR(((1-D45/D15)^(360/D$4))-1,0) -> 0 | E27: =-IFERROR(((1-E45/E15)^(360/E$4))-1,0) -> 0 | F27: =-IFERROR(((1-F45/F15)^(360/F$4))-1,0) -> 0 | G27: =-IFERROR(((1-G45/G15)^(360/G$4))-1,0) -> 0 | H27: =-IFERROR(((1-H45/H15)^(360/H$4))-1,0) -> 0 | I27: =-IFERROR(((1-I45/I15)^(360/I$4))-1,0) -> 0 | J27: =-IFERROR(((1-J45/J15)^(360/J$4))-1,0) -> 0 | K27: =-IFERROR(((1-K45/K15)^(360/K$4))-1,0) -> 0 | ... BK27: =-IFERROR(((1-BK45/BK15)^(360/BK$4))-1,0) -> -0.051397622 | BO27: =-IFERROR(((1-BO45/BW15)^(360/BO$4))-1,0) -> 0 | BP27: =-IFERROR(((1-BP45/BX15)^(360/BP$4))-1,0) -> -0.049363761 | BQ27: =-IFERROR(((1-BQ45/BY15)^(360/BQ$4))-1,0) -> 0 | BR27: =-IFERROR(((1-BR45/BZ15)^(360/BR$4))-1,0) -> 0 | BS27: =-IFERROR(((1-BS45/CA15)^(360/BS$4))-1,0) -> 0 | BT27: =-IFERROR(((1-BT45/CB15)^(360/BT$4))-1,0) -> 0
C28: Vencido y Judicial | D28: =-IFERROR(((1-D46/D16)^(360/D$4))-1,0) -> 0 | E28: =-IFERROR(((1-E46/E16)^(360/E$4))-1,0) -> 0 | F28: =-IFERROR(((1-F46/F16)^(360/F$4))-1,0) -> 0 | G28: =-IFERROR(((1-G46/G16)^(360/G$4))-1,0) -> 0 | H28: =-IFERROR(((1-H46/H16)^(360/H$4))-1,0) -> 0 | I28: =-IFERROR(((1-I46/I16)^(360/I$4))-1,0) -> 0 | J28: =-IFERROR(((1-J46/J16)^(360/J$4))-1,0) -> 0 | K28: =-IFERROR(((1-K46/K16)^(360/K$4))-1,0) -> 0 | ... BK28: =-IFERROR(((1-BK46/BK16)^(360/BK$4))-1,0) -> -0.048039665 | BO28: =-IFERROR(((1-BO46/BW16)^(360/BO$4))-1,0) -> 0 | BP28: =-IFERROR(((1-BP46/BX16)^(360/BP$4))-1,0) -> -0.047114159 | BQ28: =-IFERROR(((1-BQ46/BY16)^(360/BQ$4))-1,0) -> 0 | BR28: =-IFERROR(((1-BR46/BZ16)^(360/BR$4))-1,0) -> 0 | BS28: =-IFERROR(((1-BS46/CA16)^(360/BS$4))-1,0) -> 0 | BT28: =-IFERROR(((1-BT46/CB16)^(360/BT$4))-1,0) -> 0
C29: Tasa FTP | D29: =-IFERROR(((1-D47/D17)^(360/D$4))-1,0) -> 0 | E29: =-IFERROR(((1-E47/E17)^(360/E$4))-1,0) -> 0 | F29: =-IFERROR(((1-F47/F17)^(360/F$4))-1,0) -> 0 | G29: =-IFERROR(((1-G47/G17)^(360/G$4))-1,0) -> 0 | H29: =-IFERROR(((1-H47/H17)^(360/H$4))-1,0) -> 0 | I29: =-IFERROR(((1-I47/I17)^(360/I$4))-1,0) -> 0 | J29: =-IFERROR(((1-J47/J17)^(360/J$4))-1,0) -> 0 | K29: =-IFERROR(((1-K47/K17)^(360/K$4))-1,0) -> 0 | ... BK29: =-IFERROR(((1-BK47/BK17)^(360/BK$4))-1,0) -> -0.04807279 | BO29: =-IFERROR(((1-BO47/BW17)^(360/BO$4))-1,0) -> 0 | BP29: =-IFERROR(((1-BP47/BX17)^(360/BP$4))-1,0) -> -0.049746966 | BQ29: =-IFERROR(((1-BQ47/BY17)^(360/BQ$4))-1,0) -> 0 | BR29: =-IFERROR(((1-BR47/BZ17)^(360/BR$4))-1,0) -> 0 | BS29: =-IFERROR(((1-BS47/CA17)^(360/BS$4))-1,0) -> 0 | BT29: =-IFERROR(((1-BT47/CB17)^(360/BT$4))-1,0) -> 0
C32: Vigente | D32: =D20+D26 -> 0 | E32: =E20+E26 -> 0 | F32: =F20+F26 -> 0 | G32: =G20+G26 -> 0 | H32: =H20+H26 -> 0 | I32: =I20+I26 -> 0 | J32: =J20+J26 -> 0 | K32: =K20+K26 -> 0 | ... BK32: =BK20+BK26 -> 0.21869999 | BO32: =BO20+BO26 -> 0 | BP32: =BP20+BP26 -> 0.20707396 | BQ32: =BQ20+BQ26 -> 0 | BR32: =BR20+BR26 -> 0 | BS32: =BS20+BS26 -> 0 | BT32: =BT20+BT26 -> 0
C33: Refinanciado | D33: =D21+D27 -> 0 | E33: =E21+E27 -> 0 | F33: =F21+F27 -> 0 | G33: =G21+G27 -> 0 | H33: =H21+H27 -> 0 | I33: =I21+I27 -> 0 | J33: =J21+J27 -> 0 | K33: =K21+K27 -> 0 | ... BK33: =BK21+BK27 -> 0.055532249 | BO33: =BO21+BO27 -> 0 | BP33: =BP21+BP27 -> 0.05680093 | BQ33: =BQ21+BQ27 -> 0 | BR33: =BR21+BR27 -> 0 | BS33: =BS21+BS27 -> 0 | BT33: =BT21+BT27 -> 0
C34: Vencido y Judicial | D34: =D22+D28 -> 0 | E34: =E22+E28 -> 0 | F34: =F22+F28 -> 0 | G34: =G22+G28 -> 0 | H34: =H22+H28 -> 0 | I34: =I22+I28 -> 0 | J34: =J22+J28 -> 0 | K34: =K22+K28 -> 0 | ... BK34: =BK22+BK28 -> 0.14244358 | BO34: =BO22+BO28 -> 0 | BP34: =BP22+BP28 -> 0.15616781 | BQ34: =BQ22+BQ28 -> 0 | BR34: =BR22+BR28 -> 0 | BS34: =BS22+BS28 -> 0 | BT34: =BT22+BT28 -> 0
C35: Spread | D35: =D23+D29 -> 0 | E35: =E23+E29 -> 0 | F35: =F23+F29 -> 0 | G35: =G23+G29 -> 0 | H35: =H23+H29 -> 0 | I35: =I23+I29 -> 0 | J35: =J23+J29 -> 0 | K35: =K23+K29 -> 0 | ... BK35: =BK23+BK29 -> 0.21045514 | BO35: =BO23+BO29 -> 0 | BP35: =BP23+BP29 -> 0.19969618 | BQ35: =BQ23+BQ29 -> 0 | BR35: =BR23+BR29 -> 0 | BS35: =BS23+BS29 -> 0 | BT35: =BT23+BT29 -> 0
A38: Ingreso_Financiero | C38: Vigente | D38: =RA_TC!D38+MA_TC!D38+CI_TC!D38 -> 0 | E38: =RA_TC!E38+MA_TC!E38+CI_TC!E38 -> 0 | F38: =RA_TC!F38+MA_TC!F38+CI_TC!F38 -> 0 | G38: =RA_TC!G38+MA_TC!G38+CI_TC!G38 -> 0 | H38: =RA_TC!H38+MA_TC!H38+CI_TC!H38 -> 0 | I38: =RA_TC!I38+MA_TC!I38+CI_TC!I38 -> 0 | J38: =RA_TC!J38+MA_TC!J38+CI_TC!J38 -> 0 | K38: =RA_TC!K38+MA_TC!K38+CI_TC!K38 -> 0 | ... BK38: =RA_TC!BK38+MA_TC!BK38+CI_TC!BK38 -> 123249.5 | BO38: =SUMIFS($D38:$BM38,$D$6:$BM$6,">="&BO$2,$D$6:$BM$6,"<="&BO$6,$D$5:$BM$5,BO$5) -> 0 | BP38: =SUMIFS($D38:$BM38,$D$6:$BM$6,">="&BP$2,$D$6:$BM$6,"<="&BP$6,$D$5:$BM$5,BP$5) -> 311401.9 | BQ38: =SUMIFS($D38:$BM38,$D$6:$BM$6,">="&BQ$2,$D$6:$BM$6,"<="&BQ$6,$D$5:$BM$5,BQ$5) -> 0 | BR38: =SUMIFS($D38:$BM38,$D$6:$BM$6,">="&BR$2,$D$6:$BM$6,"<="&BR$6,$D$5:$BM$5,BR$5) -> 0 | BS38: =SUMIFS($D38:$BM38,$D$6:$BM$6,">="&BS$2,$D$6:$BM$6,"<="&BS$6,$D$5:$BM$5,BS$5) -> 0 | BT38: =SUMIFS($D38:$BM38,$D$6:$BM$6,">="&BT$2,$D$6:$BM$6,"<="&BT$6,$D$5:$BM$5,BT$5) -> 0
A39: Ingreso_Financiero | C39: Refinanciado | D39: =RA_TC!D39+MA_TC!D39+CI_TC!D39 -> 0 | E39: =RA_TC!E39+MA_TC!E39+CI_TC!E39 -> 0 | F39: =RA_TC!F39+MA_TC!F39+CI_TC!F39 -> 0 | G39: =RA_TC!G39+MA_TC!G39+CI_TC!G39 -> 0 | H39: =RA_TC!H39+MA_TC!H39+CI_TC!H39 -> 0 | I39: =RA_TC!I39+MA_TC!I39+CI_TC!I39 -> 0 | J39: =RA_TC!J39+MA_TC!J39+CI_TC!J39 -> 0 | K39: =RA_TC!K39+MA_TC!K39+CI_TC!K39 -> 0 | ... BK39: =RA_TC!BK39+MA_TC!BK39+CI_TC!BK39 -> 1608.2712 | BO39: =SUMIFS($D39:$BM39,$D$6:$BM$6,">="&BO$2,$D$6:$BM$6,"<="&BO$6,$D$5:$BM$5,BO$5) -> 0 | BP39: =SUMIFS($D39:$BM39,$D$6:$BM$6,">="&BP$2,$D$6:$BM$6,"<="&BP$6,$D$5:$BM$5,BP$5) -> 4650.4042 | BQ39: =SUMIFS($D39:$BM39,$D$6:$BM$6,">="&BQ$2,$D$6:$BM$6,"<="&BQ$6,$D$5:$BM$5,BQ$5) -> 0 | BR39: =SUMIFS($D39:$BM39,$D$6:$BM$6,">="&BR$2,$D$6:$BM$6,"<="&BR$6,$D$5:$BM$5,BR$5) -> 0 | BS39: =SUMIFS($D39:$BM39,$D$6:$BM$6,">="&BS$2,$D$6:$BM$6,"<="&BS$6,$D$5:$BM$5,BS$5) -> 0 | BT39: =SUMIFS($D39:$BM39,$D$6:$BM$6,">="&BT$2,$D$6:$BM$6,"<="&BT$6,$D$5:$BM$5,BT$5) -> 0
A40: Ingreso_Financiero | C40: Vencido y Judicial | D40: =RA_TC!D40+MA_TC!D40+CI_TC!D40 -> 0 | E40: =RA_TC!E40+MA_TC!E40+CI_TC!E40 -> 0 | F40: =RA_TC!F40+MA_TC!F40+CI_TC!F40 -> 0 | G40: =RA_TC!G40+MA_TC!G40+CI_TC!G40 -> 0 | H40: =RA_TC!H40+MA_TC!H40+CI_TC!H40 -> 0 | I40: =RA_TC!I40+MA_TC!I40+CI_TC!I40 -> 0 | J40: =RA_TC!J40+MA_TC!J40+CI_TC!J40 -> 0 | K40: =RA_TC!K40+MA_TC!K40+CI_TC!K40 -> 0 | ... BK40: =RA_TC!BK40+MA_TC!BK40+CI_TC!BK40 -> 4176.4046 | BO40: =SUMIFS($D40:$BM40,$D$6:$BM$6,">="&BO$2,$D$6:$BM$6,"<="&BO$6,$D$5:$BM$5,BO$5) -> 0 | BP40: =SUMIFS($D40:$BM40,$D$6:$BM$6,">="&BP$2,$D$6:$BM$6,"<="&BP$6,$D$5:$BM$5,BP$5) -> 12582.578 | BQ40: =SUMIFS($D40:$BM40,$D$6:$BM$6,">="&BQ$2,$D$6:$BM$6,"<="&BQ$6,$D$5:$BM$5,BQ$5) -> 0 | BR40: =SUMIFS($D40:$BM40,$D$6:$BM$6,">="&BR$2,$D$6:$BM$6,"<="&BR$6,$D$5:$BM$5,BR$5) -> 0 | BS40: =SUMIFS($D40:$BM40,$D$6:$BM$6,">="&BS$2,$D$6:$BM$6,"<="&BS$6,$D$5:$BM$5,BS$5) -> 0 | BT40: =SUMIFS($D40:$BM40,$D$6:$BM$6,">="&BT$2,$D$6:$BM$6,"<="&BT$6,$D$5:$BM$5,BT$5) -> 0
C41: Ingreso Financiero | D41: =SUM(D38:D40) -> 0 | E41: =SUM(E38:E40) -> 0 | F41: =SUM(F38:F40) -> 0 | G41: =SUM(G38:G40) -> 0 | H41: =SUM(H38:H40) -> 0 | I41: =SUM(I38:I40) -> 0 | J41: =SUM(J38:J40) -> 0 | K41: =SUM(K38:K40) -> 0 | ... BK41: =SUM(BK38:BK40) -> 129034.17 | BO41: =SUM(BO38:BO40) -> 0 | BP41: =SUM(BP38:BP40) -> 328634.88 | BQ41: =SUM(BQ38:BQ40) -> 0 | BR41: =SUM(BR38:BR40) -> 0 | BS41: =SUM(BS38:BS40) -> 0 | BT41: =SUM(BT38:BT40) -> 0
A44: FTP | C44: Vigente | D44: =RA_TC!D44+MA_TC!D44+CI_TC!D44 -> 0 | E44: =RA_TC!E44+MA_TC!E44+CI_TC!E44 -> 0 | F44: =RA_TC!F44+MA_TC!F44+CI_TC!F44 -> 0 | G44: =RA_TC!G44+MA_TC!G44+CI_TC!G44 -> 0 | H44: =RA_TC!H44+MA_TC!H44+CI_TC!H44 -> 0 | I44: =RA_TC!I44+MA_TC!I44+CI_TC!I44 -> 0 | J44: =RA_TC!J44+MA_TC!J44+CI_TC!J44 -> 0 | K44: =RA_TC!K44+MA_TC!K44+CI_TC!K44 -> 0 | ... BK44: =RA_TC!BK44+MA_TC!BK44+CI_TC!BK44 -> -24231.448 | BO44: =SUMIFS($D44:$BM44,$D$6:$BM$6,">="&BO$2,$D$6:$BM$6,"<="&BO$6,$D$5:$BM$5,BO$5) -> 0 | BP44: =SUMIFS($D44:$BM44,$D$6:$BM$6,">="&BP$2,$D$6:$BM$6,"<="&BP$6,$D$5:$BM$5,BP$5) -> -65796.78 | BQ44: =SUMIFS($D44:$BM44,$D$6:$BM$6,">="&BQ$2,$D$6:$BM$6,"<="&BQ$6,$D$5:$BM$5,BQ$5) -> 0 | BR44: =SUMIFS($D44:$BM44,$D$6:$BM$6,">="&BR$2,$D$6:$BM$6,"<="&BR$6,$D$5:$BM$5,BR$5) -> 0 | BS44: =SUMIFS($D44:$BM44,$D$6:$BM$6,">="&BS$2,$D$6:$BM$6,"<="&BS$6,$D$5:$BM$5,BS$5) -> 0 | BT44: =SUMIFS($D44:$BM44,$D$6:$BM$6,">="&BT$2,$D$6:$BM$6,"<="&BT$6,$D$5:$BM$5,BT$5) -> 0
A45: FTP | C45: Refinanciado | D45: =RA_TC!D45+MA_TC!D45+CI_TC!D45 -> 0 | E45: =RA_TC!E45+MA_TC!E45+CI_TC!E45 -> 0 | F45: =RA_TC!F45+MA_TC!F45+CI_TC!F45 -> 0 | G45: =RA_TC!G45+MA_TC!G45+CI_TC!G45 -> 0 | H45: =RA_TC!H45+MA_TC!H45+CI_TC!H45 -> 0 | I45: =RA_TC!I45+MA_TC!I45+CI_TC!I45 -> 0 | J45: =RA_TC!J45+MA_TC!J45+CI_TC!J45 -> 0 | K45: =RA_TC!K45+MA_TC!K45+CI_TC!K45 -> 0 | ... BK45: =RA_TC!BK45+MA_TC!BK45+CI_TC!BK45 -> -791.69451 | BO45: =SUMIFS($D45:$BM45,$D$6:$BM$6,">="&BO$2,$D$6:$BM$6,"<="&BO$6,$D$5:$BM$5,BO$5) -> 0 | BP45: =SUMIFS($D45:$BM45,$D$6:$BM$6,">="&BP$2,$D$6:$BM$6,"<="&BP$6,$D$5:$BM$5,BP$5) -> -2215.9145 | BQ45: =SUMIFS($D45:$BM45,$D$6:$BM$6,">="&BQ$2,$D$6:$BM$6,"<="&BQ$6,$D$5:$BM$5,BQ$5) -> 0 | BR45: =SUMIFS($D45:$BM45,$D$6:$BM$6,">="&BR$2,$D$6:$BM$6,"<="&BR$6,$D$5:$BM$5,BR$5) -> 0 | BS45: =SUMIFS($D45:$BM45,$D$6:$BM$6,">="&BS$2,$D$6:$BM$6,"<="&BS$6,$D$5:$BM$5,BS$5) -> 0 | BT45: =SUMIFS($D45:$BM45,$D$6:$BM$6,">="&BT$2,$D$6:$BM$6,"<="&BT$6,$D$5:$BM$5,BT$5) -> 0
A46: FTP | C46: Vencido y Judicial | D46: =RA_TC!D46+MA_TC!D46+CI_TC!D46 -> 0 | E46: =RA_TC!E46+MA_TC!E46+CI_TC!E46 -> 0 | F46: =RA_TC!F46+MA_TC!F46+CI_TC!F46 -> 0 | G46: =RA_TC!G46+MA_TC!G46+CI_TC!G46 -> 0 | H46: =RA_TC!H46+MA_TC!H46+CI_TC!H46 -> 0 | I46: =RA_TC!I46+MA_TC!I46+CI_TC!I46 -> 0 | J46: =RA_TC!J46+MA_TC!J46+CI_TC!J46 -> 0 | K46: =RA_TC!K46+MA_TC!K46+CI_TC!K46 -> 0 | ... BK46: =RA_TC!BK46+MA_TC!BK46+CI_TC!BK46 -> -1117.7431 | BO46: =SUMIFS($D46:$BM46,$D$6:$BM$6,">="&BO$2,$D$6:$BM$6,"<="&BO$6,$D$5:$BM$5,BO$5) -> 0 | BP46: =SUMIFS($D46:$BM46,$D$6:$BM$6,">="&BP$2,$D$6:$BM$6,"<="&BP$6,$D$5:$BM$5,BP$5) -> -3112.2211 | BQ46: =SUMIFS($D46:$BM46,$D$6:$BM$6,">="&BQ$2,$D$6:$BM$6,"<="&BQ$6,$D$5:$BM$5,BQ$5) -> 0 | BR46: =SUMIFS($D46:$BM46,$D$6:$BM$6,">="&BR$2,$D$6:$BM$6,"<="&BR$6,$D$5:$BM$5,BR$5) -> 0 | BS46: =SUMIFS($D46:$BM46,$D$6:$BM$6,">="&BS$2,$D$6:$BM$6,"<="&BS$6,$D$5:$BM$5,BS$5) -> 0 | BT46: =SUMIFS($D46:$BM46,$D$6:$BM$6,">="&BT$2,$D$6:$BM$6,"<="&BT$6,$D$5:$BM$5,BT$5) -> 0
C47: Costo de Fondos | D47: =SUM(D44:D46) -> 0 | E47: =SUM(E44:E46) -> 0 | F47: =SUM(F44:F46) -> 0 | G47: =SUM(G44:G46) -> 0 | H47: =SUM(H44:H46) -> 0 | I47: =SUM(I44:I46) -> 0 | J47: =SUM(J44:J46) -> 0 | K47: =SUM(K44:K46) -> 0 | ... BK47: =SUM(BK44:BK46) -> -26140.886 | BO47: =SUM(BO44:BO46) -> 0 | BP47: =SUM(BP44:BP46) -> -71124.915 | BQ47: =SUM(BQ44:BQ46) -> 0 | BR47: =SUM(BR44:BR46) -> 0 | BS47: =SUM(BS44:BS46) -> 0 | BT47: =SUM(BT44:BT46) -> 0
C50: Vigente | D50: =D38+D44 -> 0 | E50: =E38+E44 -> 0 | F50: =F38+F44 -> 0 | G50: =G38+G44 -> 0 | H50: =H38+H44 -> 0 | I50: =I38+I44 -> 0 | J50: =J38+J44 -> 0 | K50: =K38+K44 -> 0 | ... BK50: =BK38+BK44 -> 99018.049 | BO50: =BO38+BO44 -> 0 | BP50: =BP38+BP44 -> 245605.12 | BQ50: =BQ38+BQ44 -> 0 | BR50: =BR38+BR44 -> 0 | BS50: =BS38+BS44 -> 0 | BT50: =BT38+BT44 -> 0
C51: Refinanciado | D51: =D39+D45 -> 0 | E51: =E39+E45 -> 0 | F51: =F39+F45 -> 0 | G51: =G39+G45 -> 0 | H51: =H39+H45 -> 0 | I51: =I39+I45 -> 0 | J51: =J39+J45 -> 0 | K51: =K39+K45 -> 0 | ... BK51: =BK39+BK45 -> 816.57668 | BO51: =BO39+BO45 -> 0 | BP51: =BP39+BP45 -> 2434.4896 | BQ51: =BQ39+BQ45 -> 0 | BR51: =BR39+BR45 -> 0 | BS51: =BS39+BS45 -> 0 | BT51: =BT39+BT45 -> 0
C52: Vencido y Judicial | D52: =D40+D46 -> 0 | E52: =E40+E46 -> 0 | F52: =F40+F46 -> 0 | G52: =G40+G46 -> 0 | H52: =H40+H46 -> 0 | I52: =I40+I46 -> 0 | J52: =J40+J46 -> 0 | K52: =K40+K46 -> 0 | ... BK52: =BK40+BK46 -> 3058.6616 | BO52: =BO40+BO46 -> 0 | BP52: =BP40+BP46 -> 9470.3565 | BQ52: =BQ40+BQ46 -> 0 | BR52: =BR40+BR46 -> 0 | BS52: =BS40+BS46 -> 0 | BT52: =BT40+BT46 -> 0
C53: Resultado Financiero Bruto | D53: =D41+D47 -> 0 | E53: =E41+E47 -> 0 | F53: =F41+F47 -> 0 | G53: =G41+G47 -> 0 | H53: =H41+H47 -> 0 | I53: =I41+I47 -> 0 | J53: =J41+J47 -> 0 | K53: =K41+K47 -> 0 | ... BK53: =BK41+BK47 -> 102893.29 | BO53: =SUM(BO50:BO52) -> 0 | BP53: =SUM(BP50:BP52) -> 257509.96 | BQ53: =SUM(BQ50:BQ52) -> 0 | BR53: =SUM(BR50:BR52) -> 0 | BS53: =SUM(BS50:BS52) -> 0 | BT53: =SUM(BT50:BT52) -> 0
D54: ='[1]Desempeño Finan_ TC_Cartera_Evo'!AY41-D53 -> 97535.966 | E54: ='[1]Desempeño Finan_ TC_Cartera_Evo'!AZ41-E53 -> 77623.166 | F54: ='[1]Desempeño Finan_ TC_Cartera_Evo'!BA41-F53 -> 95522.077 | G54: ='[1]Desempeño Finan_ TC_Cartera_Evo'!BB41-G53 -> 96428.353 | H54: ='[1]Desempeño Finan_ TC_Cartera_Evo'!BC41-H53 -> 98918.341 | I54: ='[1]Desempeño Finan_ TC_Cartera_Evo'!BD41-I53 -> 94876.148 | J54: ='[1]Desempeño Finan_ TC_Cartera_Evo'!BE41-J53 -> 98307.531 | K54: ='[1]Desempeño Finan_ TC_Cartera_Evo'!BF41-K53 -> 96521.736 | ... BK54: ='[1]Desempeño Finan_ TC_Cartera_Evo'!DF41-BK53 -> 0
A56: Gasto_Provision | C56: Provisiones Cartera | D56: =RA_TC!D56+MA_TC!D56+CI_TC!D56 -> 0 | E56: =RA_TC!E56+MA_TC!E56+CI_TC!E56 -> 0 | F56: =RA_TC!F56+MA_TC!F56+CI_TC!F56 -> 0 | G56: =RA_TC!G56+MA_TC!G56+CI_TC!G56 -> 0 | H56: =RA_TC!H56+MA_TC!H56+CI_TC!H56 -> 0 | I56: =RA_TC!I56+MA_TC!I56+CI_TC!I56 -> 0 | J56: =RA_TC!J56+MA_TC!J56+CI_TC!J56 -> 0 | K56: =RA_TC!K56+MA_TC!K56+CI_TC!K56 -> 0 | ... BK56: =RA_TC!BK56+MA_TC!BK56+CI_TC!BK56 -> -61394.976 | BO56: =SUMIFS($D56:$BM56,$D$6:$BM$6,">="&BO$2,$D$6:$BM$6,"<="&BO$6,$D$5:$BM$5,BO$5) -> 0 | BP56: =SUMIFS($D56:$BM56,$D$6:$BM$6,">="&BP$2,$D$6:$BM$6,"<="&BP$6,$D$5:$BM$5,BP$5) -> -169498.18 | BQ56: =SUMIFS($D56:$BM56,$D$6:$BM$6,">="&BQ$2,$D$6:$BM$6,"<="&BQ$6,$D$5:$BM$5,BQ$5) -> 0 | BR56: =SUMIFS($D56:$BM56,$D$6:$BM$6,">="&BR$2,$D$6:$BM$6,"<="&BR$6,$D$5:$BM$5,BR$5) -> 0 | BS56: =SUMIFS($D56:$BM56,$D$6:$BM$6,">="&BS$2,$D$6:$BM$6,"<="&BS$6,$D$5:$BM$5,BS$5) -> 0 | BT56: =SUMIFS($D56:$BM56,$D$6:$BM$6,">="&BT$2,$D$6:$BM$6,"<="&BT$6,$D$5:$BM$5,BT$5) -> 0
A57: Recupero | C57: Recupero de Castigos | D57: =RA_TC!D57+MA_TC!D57+CI_TC!D57 -> 0 | E57: =RA_TC!E57+MA_TC!E57+CI_TC!E57 -> 0 | F57: =RA_TC!F57+MA_TC!F57+CI_TC!F57 -> 0 | G57: =RA_TC!G57+MA_TC!G57+CI_TC!G57 -> 0 | H57: =RA_TC!H57+MA_TC!H57+CI_TC!H57 -> 0 | I57: =RA_TC!I57+MA_TC!I57+CI_TC!I57 -> 0 | J57: =RA_TC!J57+MA_TC!J57+CI_TC!J57 -> 0 | K57: =RA_TC!K57+MA_TC!K57+CI_TC!K57 -> 0 | ... BK57: =RA_TC!BK57+MA_TC!BK57+CI_TC!BK57 -> 4191.8326 | BO57: =SUMIFS($D57:$BM57,$D$6:$BM$6,">="&BO$2,$D$6:$BM$6,"<="&BO$6,$D$5:$BM$5,BO$5) -> 0 | BP57: =SUMIFS($D57:$BM57,$D$6:$BM$6,">="&BP$2,$D$6:$BM$6,"<="&BP$6,$D$5:$BM$5,BP$5) -> 12489.434 | BQ57: =SUMIFS($D57:$BM57,$D$6:$BM$6,">="&BQ$2,$D$6:$BM$6,"<="&BQ$6,$D$5:$BM$5,BQ$5) -> 0 | BR57: =SUMIFS($D57:$BM57,$D$6:$BM$6,">="&BR$2,$D$6:$BM$6,"<="&BR$6,$D$5:$BM$5,BR$5) -> 0 | BS57: =SUMIFS($D57:$BM57,$D$6:$BM$6,">="&BS$2,$D$6:$BM$6,"<="&BS$6,$D$5:$BM$5,BS$5) -> 0 | BT57: =SUMIFS($D57:$BM57,$D$6:$BM$6,">="&BT$2,$D$6:$BM$6,"<="&BT$6,$D$5:$BM$5,BT$5) -> 0
C58: Provisiones Netas | D58: =SUM(D56:D57) -> 0 | E58: =SUM(E56:E57) -> 0 | F58: =SUM(F56:F57) -> 0 | G58: =SUM(G56:G57) -> 0 | H58: =SUM(H56:H57) -> 0 | I58: =SUM(I56:I57) -> 0 | J58: =SUM(J56:J57) -> 0 | K58: =SUM(K56:K57) -> 0 | ... BK58: =SUM(BK56:BK57) -> -57203.143 | BO58: =SUM(BO56:BO57) -> 0 | BP58: =SUM(BP56:BP57) -> -157008.75 | BQ58: =SUM(BQ56:BQ57) -> 0 | BR58: =SUM(BR56:BR57) -> 0 | BS58: =SUM(BS56:BS57) -> 0 | BT58: =SUM(BT56:BT57) -> 0
C60: Resultado Financiero Neto | D60: =D53+D58 -> 0 | E60: =E53+E58 -> 0 | F60: =F53+F58 -> 0 | G60: =G53+G58 -> 0 | H60: =H53+H58 -> 0 | I60: =I53+I58 -> 0 | J60: =J53+J58 -> 0 | K60: =K53+K58 -> 0 | ... BK60: =BK53+BK58 -> 45690.145 | BO60: =BO53+BO58 -> 0 | BP60: =BP53+BP58 -> 100501.21 | BQ60: =BQ53+BQ58 -> 0 | BR60: =BR53+BR58 -> 0 | BS60: =BS53+BS58 -> 0 | BT60: =BT53+BT58 -> 0
D61: ='[1]Desempeño Finan_ TC_Cartera_Evo'!AY54-D60 -> 23902.077 | E61: ='[1]Desempeño Finan_ TC_Cartera_Evo'!AZ54-E60 -> 17868.051 | F61: ='[1]Desempeño Finan_ TC_Cartera_Evo'!BA54-F60 -> 19643.33 | G61: ='[1]Desempeño Finan_ TC_Cartera_Evo'!BB54-G60 -> 24739.543 | H61: ='[1]Desempeño Finan_ TC_Cartera_Evo'!BC54-H60 -> -8020.1399 | I61: ='[1]Desempeño Finan_ TC_Cartera_Evo'!BD54-I60 -> -16049.58 | J61: ='[1]Desempeño Finan_ TC_Cartera_Evo'!BE54-J60 -> -14874.227 | K61: ='[1]Desempeño Finan_ TC_Cartera_Evo'!BF54-K60 -> -42497.683 | ... AO61: ='[1]Desempeño Finan_ TC_Cartera_Evo'!CJ54-AO60 -> 39107.046
A63: INOF | C63: Renovación | D63: =RA_TC!D63+MA_TC!D63+CI_TC!D63 -> 0 | E63: =RA_TC!E63+MA_TC!E63+CI_TC!E63 -> 0 | F63: =RA_TC!F63+MA_TC!F63+CI_TC!F63 -> 0 | G63: =RA_TC!G63+MA_TC!G63+CI_TC!G63 -> 0 | H63: =RA_TC!H63+MA_TC!H63+CI_TC!H63 -> 0 | I63: =RA_TC!I63+MA_TC!I63+CI_TC!I63 -> 0 | J63: =RA_TC!J63+MA_TC!J63+CI_TC!J63 -> 0 | K63: =RA_TC!K63+MA_TC!K63+CI_TC!K63 -> 0 | ... BK63: =RA_TC!BK63+MA_TC!BK63+CI_TC!BK63 -> 1018.6851 | BO63: =SUMIFS($D63:$BM63,$D$6:$BM$6,">="&BO$2,$D$6:$BM$6,"<="&BO$6,$D$5:$BM$5,BO$5) -> 0 | BP63: =SUMIFS($D63:$BM63,$D$6:$BM$6,">="&BP$2,$D$6:$BM$6,"<="&BP$6,$D$5:$BM$5,BP$5) -> 3438.8276 | BQ63: =SUMIFS($D63:$BM63,$D$6:$BM$6,">="&BQ$2,$D$6:$BM$6,"<="&BQ$6,$D$5:$BM$5,BQ$5) -> 0 | BR63: =SUMIFS($D63:$BM63,$D$6:$BM$6,">="&BR$2,$D$6:$BM$6,"<="&BR$6,$D$5:$BM$5,BR$5) -> 0 | BS63: =SUMIFS($D63:$BM63,$D$6:$BM$6,">="&BS$2,$D$6:$BM$6,"<="&BS$6,$D$5:$BM$5,BS$5) -> 0 | BT63: =SUMIFS($D63:$BM63,$D$6:$BM$6,">="&BT$2,$D$6:$BM$6,"<="&BT$6,$D$5:$BM$5,BT$5) -> 0
A64: INOF | C64: Reposición TC | D64: =RA_TC!D64+MA_TC!D64+CI_TC!D64 -> 0 | E64: =RA_TC!E64+MA_TC!E64+CI_TC!E64 -> 0 | F64: =RA_TC!F64+MA_TC!F64+CI_TC!F64 -> 0 | G64: =RA_TC!G64+MA_TC!G64+CI_TC!G64 -> 0 | H64: =RA_TC!H64+MA_TC!H64+CI_TC!H64 -> 0 | I64: =RA_TC!I64+MA_TC!I64+CI_TC!I64 -> 0 | J64: =RA_TC!J64+MA_TC!J64+CI_TC!J64 -> 0 | K64: =RA_TC!K64+MA_TC!K64+CI_TC!K64 -> 0 | ... BK64: =RA_TC!BK64+MA_TC!BK64+CI_TC!BK64 -> 170.99453 | BO64: =SUMIFS($D64:$BM64,$D$6:$BM$6,">="&BO$2,$D$6:$BM$6,"<="&BO$6,$D$5:$BM$5,BO$5) -> 0 | BP64: =SUMIFS($D64:$BM64,$D$6:$BM$6,">="&BP$2,$D$6:$BM$6,"<="&BP$6,$D$5:$BM$5,BP$5) -> 505.89849 | BQ64: =SUMIFS($D64:$BM64,$D$6:$BM$6,">="&BQ$2,$D$6:$BM$6,"<="&BQ$6,$D$5:$BM$5,BQ$5) -> 0 | BR64: =SUMIFS($D64:$BM64,$D$6:$BM$6,">="&BR$2,$D$6:$BM$6,"<="&BR$6,$D$5:$BM$5,BR$5) -> 0 | BS64: =SUMIFS($D64:$BM64,$D$6:$BM$6,">="&BS$2,$D$6:$BM$6,"<="&BS$6,$D$5:$BM$5,BS$5) -> 0 | BT64: =SUMIFS($D64:$BM64,$D$6:$BM$6,">="&BT$2,$D$6:$BM$6,"<="&BT$6,$D$5:$BM$5,BT$5) -> 0
A65: INOF | C65: Comisión Mora | D65: =RA_TC!D65+MA_TC!D65+CI_TC!D65 -> 0 | E65: =RA_TC!E65+MA_TC!E65+CI_TC!E65 -> 0 | F65: =RA_TC!F65+MA_TC!F65+CI_TC!F65 -> 0 | G65: =RA_TC!G65+MA_TC!G65+CI_TC!G65 -> 0 | H65: =RA_TC!H65+MA_TC!H65+CI_TC!H65 -> 0 | I65: =RA_TC!I65+MA_TC!I65+CI_TC!I65 -> 0 | J65: =RA_TC!J65+MA_TC!J65+CI_TC!J65 -> 0 | K65: =RA_TC!K65+MA_TC!K65+CI_TC!K65 -> 0 | ... BK65: =RA_TC!BK65+MA_TC!BK65+CI_TC!BK65 -> 0 | BO65: =SUMIFS($D65:$BM65,$D$6:$BM$6,">="&BO$2,$D$6:$BM$6,"<="&BO$6,$D$5:$BM$5,BO$5) -> 0 | BP65: =SUMIFS($D65:$BM65,$D$6:$BM$6,">="&BP$2,$D$6:$BM$6,"<="&BP$6,$D$5:$BM$5,BP$5) -> 0 | BQ65: =SUMIFS($D65:$BM65,$D$6:$BM$6,">="&BQ$2,$D$6:$BM$6,"<="&BQ$6,$D$5:$BM$5,BQ$5) -> 0 | BR65: =SUMIFS($D65:$BM65,$D$6:$BM$6,">="&BR$2,$D$6:$BM$6,"<="&BR$6,$D$5:$BM$5,BR$5) -> 0 | BS65: =SUMIFS($D65:$BM65,$D$6:$BM$6,">="&BS$2,$D$6:$BM$6,"<="&BS$6,$D$5:$BM$5,BS$5) -> 0 | BT65: =SUMIFS($D65:$BM65,$D$6:$BM$6,">="&BT$2,$D$6:$BM$6,"<="&BT$6,$D$5:$BM$5,BT$5) -> 0
A66: INOF | C66: Comision Apple | D66: =RA_TC!D66+MA_TC!D66+CI_TC!D66 -> 0 | E66: =RA_TC!E66+MA_TC!E66+CI_TC!E66 -> 0 | F66: =RA_TC!F66+MA_TC!F66+CI_TC!F66 -> 0 | G66: =RA_TC!G66+MA_TC!G66+CI_TC!G66 -> 0 | H66: =RA_TC!H66+MA_TC!H66+CI_TC!H66 -> 0 | I66: =RA_TC!I66+MA_TC!I66+CI_TC!I66 -> 0 | J66: =RA_TC!J66+MA_TC!J66+CI_TC!J66 -> 0 | K66: =RA_TC!K66+MA_TC!K66+CI_TC!K66 -> 0 | ... BK66: =RA_TC!BK66+MA_TC!BK66+CI_TC!BK66 -> 2059.7728 | BO66: =SUMIFS($D66:$BM66,$D$6:$BM$6,">="&BO$2,$D$6:$BM$6,"<="&BO$6,$D$5:$BM$5,BO$5) -> 0 | BP66: =SUMIFS($D66:$BM66,$D$6:$BM$6,">="&BP$2,$D$6:$BM$6,"<="&BP$6,$D$5:$BM$5,BP$5) -> 4659.2695 | BQ66: =SUMIFS($D66:$BM66,$D$6:$BM$6,">="&BQ$2,$D$6:$BM$6,"<="&BQ$6,$D$5:$BM$5,BQ$5) -> 0 | BR66: =SUMIFS($D66:$BM66,$D$6:$BM$6,">="&BR$2,$D$6:$BM$6,"<="&BR$6,$D$5:$BM$5,BR$5) -> 0 | BS66: =SUMIFS($D66:$BM66,$D$6:$BM$6,">="&BS$2,$D$6:$BM$6,"<="&BS$6,$D$5:$BM$5,BS$5) -> 0 | BT66: =SUMIFS($D66:$BM66,$D$6:$BM$6,">="&BT$2,$D$6:$BM$6,"<="&BT$6,$D$5:$BM$5,BT$5) -> 0
A67: INOF | C67: Comisión Disposición de Efectivo | D67: =RA_TC!D67+MA_TC!D67+CI_TC!D67 -> 0 | E67: =RA_TC!E67+MA_TC!E67+CI_TC!E67 -> 0 | F67: =RA_TC!F67+MA_TC!F67+CI_TC!F67 -> 0 | G67: =RA_TC!G67+MA_TC!G67+CI_TC!G67 -> 0 | H67: =RA_TC!H67+MA_TC!H67+CI_TC!H67 -> 0 | I67: =RA_TC!I67+MA_TC!I67+CI_TC!I67 -> 0 | J67: =RA_TC!J67+MA_TC!J67+CI_TC!J67 -> 0 | K67: =RA_TC!K67+MA_TC!K67+CI_TC!K67 -> 0 | ... BK67: =RA_TC!BK67+MA_TC!BK67+CI_TC!BK67 -> 28.075114 | BO67: =SUMIFS($D67:$BM67,$D$6:$BM$6,">="&BO$2,$D$6:$BM$6,"<="&BO$6,$D$5:$BM$5,BO$5) -> 0 | BP67: =SUMIFS($D67:$BM67,$D$6:$BM$6,">="&BP$2,$D$6:$BM$6,"<="&BP$6,$D$5:$BM$5,BP$5) -> 84.225342 | BQ67: =SUMIFS($D67:$BM67,$D$6:$BM$6,">="&BQ$2,$D$6:$BM$6,"<="&BQ$6,$D$5:$BM$5,BQ$5) -> 0 | BR67: =SUMIFS($D67:$BM67,$D$6:$BM$6,">="&BR$2,$D$6:$BM$6,"<="&BR$6,$D$5:$BM$5,BR$5) -> 0 | BS67: =SUMIFS($D67:$BM67,$D$6:$BM$6,">="&BS$2,$D$6:$BM$6,"<="&BS$6,$D$5:$BM$5,BS$5) -> 0 | BT67: =SUMIFS($D67:$BM67,$D$6:$BM$6,">="&BT$2,$D$6:$BM$6,"<="&BT$6,$D$5:$BM$5,BT$5) -> 0
A68: INOF | C68: Comisión Establecimiento | D68: =RA_TC!D68+MA_TC!D68+CI_TC!D68 -> 0 | E68: =RA_TC!E68+MA_TC!E68+CI_TC!E68 -> 0 | F68: =RA_TC!F68+MA_TC!F68+CI_TC!F68 -> 0 | G68: =RA_TC!G68+MA_TC!G68+CI_TC!G68 -> 0 | H68: =RA_TC!H68+MA_TC!H68+CI_TC!H68 -> 0 | I68: =RA_TC!I68+MA_TC!I68+CI_TC!I68 -> 0 | J68: =RA_TC!J68+MA_TC!J68+CI_TC!J68 -> 0 | K68: =RA_TC!K68+MA_TC!K68+CI_TC!K68 -> 0 | ... BK68: =RA_TC!BK68+MA_TC!BK68+CI_TC!BK68 -> 24104.822 | BO68: =SUMIFS($D68:$BM68,$D$6:$BM$6,">="&BO$2,$D$6:$BM$6,"<="&BO$6,$D$5:$BM$5,BO$5) -> 0 | BP68: =SUMIFS($D68:$BM68,$D$6:$BM$6,">="&BP$2,$D$6:$BM$6,"<="&BP$6,$D$5:$BM$5,BP$5) -> 60694.843 | BQ68: =SUMIFS($D68:$BM68,$D$6:$BM$6,">="&BQ$2,$D$6:$BM$6,"<="&BQ$6,$D$5:$BM$5,BQ$5) -> 0 | BR68: =SUMIFS($D68:$BM68,$D$6:$BM$6,">="&BR$2,$D$6:$BM$6,"<="&BR$6,$D$5:$BM$5,BR$5) -> 0 | BS68: =SUMIFS($D68:$BM68,$D$6:$BM$6,">="&BS$2,$D$6:$BM$6,"<="&BS$6,$D$5:$BM$5,BS$5) -> 0 | BT68: =SUMIFS($D68:$BM68,$D$6:$BM$6,">="&BT$2,$D$6:$BM$6,"<="&BT$6,$D$5:$BM$5,BT$5) -> 0
A69: INOF | C69: Seguros Neto | D69: =RA_TC!D69+MA_TC!D69+CI_TC!D69 -> 0 | E69: =RA_TC!E69+MA_TC!E69+CI_TC!E69 -> 0 | F69: =RA_TC!F69+MA_TC!F69+CI_TC!F69 -> 0 | G69: =RA_TC!G69+MA_TC!G69+CI_TC!G69 -> 0 | H69: =RA_TC!H69+MA_TC!H69+CI_TC!H69 -> 0 | I69: =RA_TC!I69+MA_TC!I69+CI_TC!I69 -> 0 | J69: =RA_TC!J69+MA_TC!J69+CI_TC!J69 -> 0 | K69: =RA_TC!K69+MA_TC!K69+CI_TC!K69 -> 0 | ... BK69: =RA_TC!BK69+MA_TC!BK69+CI_TC!BK69 -> 9150.2625 | BO69: =SUMIFS($D69:$BM69,$D$6:$BM$6,">="&BO$2,$D$6:$BM$6,"<="&BO$6,$D$5:$BM$5,BO$5) -> 0 | BP69: =SUMIFS($D69:$BM69,$D$6:$BM$6,">="&BP$2,$D$6:$BM$6,"<="&BP$6,$D$5:$BM$5,BP$5) -> 22800 | BQ69: =SUMIFS($D69:$BM69,$D$6:$BM$6,">="&BQ$2,$D$6:$BM$6,"<="&BQ$6,$D$5:$BM$5,BQ$5) -> 0 | BR69: =SUMIFS($D69:$BM69,$D$6:$BM$6,">="&BR$2,$D$6:$BM$6,"<="&BR$6,$D$5:$BM$5,BR$5) -> 0 | BS69: =SUMIFS($D69:$BM69,$D$6:$BM$6,">="&BS$2,$D$6:$BM$6,"<="&BS$6,$D$5:$BM$5,BS$5) -> 0 | BT69: =SUMIFS($D69:$BM69,$D$6:$BM$6,">="&BT$2,$D$6:$BM$6,"<="&BT$6,$D$5:$BM$5,BT$5) -> 0
A70: INOF | C70: Comisión Vencidos | D70: =RA_TC!D70+MA_TC!D70+CI_TC!D70 -> 0 | E70: =RA_TC!E70+MA_TC!E70+CI_TC!E70 -> 0 | F70: =RA_TC!F70+MA_TC!F70+CI_TC!F70 -> 0 | G70: =RA_TC!G70+MA_TC!G70+CI_TC!G70 -> 0 | H70: =RA_TC!H70+MA_TC!H70+CI_TC!H70 -> 0 | I70: =RA_TC!I70+MA_TC!I70+CI_TC!I70 -> 0 | J70: =RA_TC!J70+MA_TC!J70+CI_TC!J70 -> 0 | K70: =RA_TC!K70+MA_TC!K70+CI_TC!K70 -> 0 | ... BK70: =RA_TC!BK70+MA_TC!BK70+CI_TC!BK70 -> 0 | BO70: =SUMIFS($D70:$BM70,$D$6:$BM$6,">="&BO$2,$D$6:$BM$6,"<="&BO$6,$D$5:$BM$5,BO$5) -> 0 | BP70: =SUMIFS($D70:$BM70,$D$6:$BM$6,">="&BP$2,$D$6:$BM$6,"<="&BP$6,$D$5:$BM$5,BP$5) -> 0 | BQ70: =SUMIFS($D70:$BM70,$D$6:$BM$6,">="&BQ$2,$D$6:$BM$6,"<="&BQ$6,$D$5:$BM$5,BQ$5) -> 0 | BR70: =SUMIFS($D70:$BM70,$D$6:$BM$6,">="&BR$2,$D$6:$BM$6,"<="&BR$6,$D$5:$BM$5,BR$5) -> 0 | BS70: =SUMIFS($D70:$BM70,$D$6:$BM$6,">="&BS$2,$D$6:$BM$6,"<="&BS$6,$D$5:$BM$5,BS$5) -> 0 | BT70: =SUMIFS($D70:$BM70,$D$6:$BM$6,">="&BT$2,$D$6:$BM$6,"<="&BT$6,$D$5:$BM$5,BT$5) -> 0
A71: INOF | C71: Comision Socios | D71: =RA_TC!D71+MA_TC!D71+CI_TC!D71 -> 0 | E71: =RA_TC!E71+MA_TC!E71+CI_TC!E71 -> 0 | F71: =RA_TC!F71+MA_TC!F71+CI_TC!F71 -> 0 | G71: =RA_TC!G71+MA_TC!G71+CI_TC!G71 -> 0 | H71: =RA_TC!H71+MA_TC!H71+CI_TC!H71 -> 0 | I71: =RA_TC!I71+MA_TC!I71+CI_TC!I71 -> 0 | J71: =RA_TC!J71+MA_TC!J71+CI_TC!J71 -> 0 | K71: =RA_TC!K71+MA_TC!K71+CI_TC!K71 -> 0 | ... BK71: =RA_TC!BK71+MA_TC!BK71+CI_TC!BK71 -> -165 | BO71: =SUMIFS($D71:$BM71,$D$6:$BM$6,">="&BO$2,$D$6:$BM$6,"<="&BO$6,$D$5:$BM$5,BO$5) -> 0 | BP71: =SUMIFS($D71:$BM71,$D$6:$BM$6,">="&BP$2,$D$6:$BM$6,"<="&BP$6,$D$5:$BM$5,BP$5) -> -495 | BQ71: =SUMIFS($D71:$BM71,$D$6:$BM$6,">="&BQ$2,$D$6:$BM$6,"<="&BQ$6,$D$5:$BM$5,BQ$5) -> 0 | BR71: =SUMIFS($D71:$BM71,$D$6:$BM$6,">="&BR$2,$D$6:$BM$6,"<="&BR$6,$D$5:$BM$5,BR$5) -> 0 | BS71: =SUMIFS($D71:$BM71,$D$6:$BM$6,">="&BS$2,$D$6:$BM$6,"<="&BS$6,$D$5:$BM$5,BS$5) -> 0 | BT71: =SUMIFS($D71:$BM71,$D$6:$BM$6,">="&BT$2,$D$6:$BM$6,"<="&BT$6,$D$5:$BM$5,BT$5) -> 0
A72: INOF | C72: Duplicidad EECC | D72: =RA_TC!D72+MA_TC!D72+CI_TC!D72 -> 0 | E72: =RA_TC!E72+MA_TC!E72+CI_TC!E72 -> 0 | F72: =RA_TC!F72+MA_TC!F72+CI_TC!F72 -> 0 | G72: =RA_TC!G72+MA_TC!G72+CI_TC!G72 -> 0 | H72: =RA_TC!H72+MA_TC!H72+CI_TC!H72 -> 0 | I72: =RA_TC!I72+MA_TC!I72+CI_TC!I72 -> 0 | J72: =RA_TC!J72+MA_TC!J72+CI_TC!J72 -> 0 | K72: =RA_TC!K72+MA_TC!K72+CI_TC!K72 -> 0 | ... BK72: =RA_TC!BK72+MA_TC!BK72+CI_TC!BK72 -> 0 | BO72: =SUMIFS($D72:$BM72,$D$6:$BM$6,">="&BO$2,$D$6:$BM$6,"<="&BO$6,$D$5:$BM$5,BO$5) -> 0 | BP72: =SUMIFS($D72:$BM72,$D$6:$BM$6,">="&BP$2,$D$6:$BM$6,"<="&BP$6,$D$5:$BM$5,BP$5) -> 0 | BQ72: =SUMIFS($D72:$BM72,$D$6:$BM$6,">="&BQ$2,$D$6:$BM$6,"<="&BQ$6,$D$5:$BM$5,BQ$5) -> 0 | BR72: =SUMIFS($D72:$BM72,$D$6:$BM$6,">="&BR$2,$D$6:$BM$6,"<="&BR$6,$D$5:$BM$5,BR$5) -> 0 | BS72: =SUMIFS($D72:$BM72,$D$6:$BM$6,">="&BS$2,$D$6:$BM$6,"<="&BS$6,$D$5:$BM$5,BS$5) -> 0 | BT72: =SUMIFS($D72:$BM72,$D$6:$BM$6,">="&BT$2,$D$6:$BM$6,"<="&BT$6,$D$5:$BM$5,BT$5) -> 0
A73: INOF | C73: Portes | D73: =RA_TC!D73+MA_TC!D73+CI_TC!D73 -> 0 | E73: =RA_TC!E73+MA_TC!E73+CI_TC!E73 -> 0 | F73: =RA_TC!F73+MA_TC!F73+CI_TC!F73 -> 0 | G73: =RA_TC!G73+MA_TC!G73+CI_TC!G73 -> 0 | H73: =RA_TC!H73+MA_TC!H73+CI_TC!H73 -> 0 | I73: =RA_TC!I73+MA_TC!I73+CI_TC!I73 -> 0 | J73: =RA_TC!J73+MA_TC!J73+CI_TC!J73 -> 0 | K73: =RA_TC!K73+MA_TC!K73+CI_TC!K73 -> 0 | ... BK73: =RA_TC!BK73+MA_TC!BK73+CI_TC!BK73 -> 79.182878 | BO73: =SUMIFS($D73:$BM73,$D$6:$BM$6,">="&BO$2,$D$6:$BM$6,"<="&BO$6,$D$5:$BM$5,BO$5) -> 0 | BP73: =SUMIFS($D73:$BM73,$D$6:$BM$6,">="&BP$2,$D$6:$BM$6,"<="&BP$6,$D$5:$BM$5,BP$5) -> 237.54863 | BQ73: =SUMIFS($D73:$BM73,$D$6:$BM$6,">="&BQ$2,$D$6:$BM$6,"<="&BQ$6,$D$5:$BM$5,BQ$5) -> 0 | BR73: =SUMIFS($D73:$BM73,$D$6:$BM$6,">="&BR$2,$D$6:$BM$6,"<="&BR$6,$D$5:$BM$5,BR$5) -> 0 | BS73: =SUMIFS($D73:$BM73,$D$6:$BM$6,">="&BS$2,$D$6:$BM$6,"<="&BS$6,$D$5:$BM$5,BS$5) -> 0 | BT73: =SUMIFS($D73:$BM73,$D$6:$BM$6,">="&BT$2,$D$6:$BM$6,"<="&BT$6,$D$5:$BM$5,BT$5) -> 0
A74: INOF | C74: Incentivos Marcas | D74: =RA_TC!D74+MA_TC!D74+CI_TC!D74 -> 0 | E74: =RA_TC!E74+MA_TC!E74+CI_TC!E74 -> 0 | F74: =RA_TC!F74+MA_TC!F74+CI_TC!F74 -> 0 | G74: =RA_TC!G74+MA_TC!G74+CI_TC!G74 -> 0 | H74: =RA_TC!H74+MA_TC!H74+CI_TC!H74 -> 0 | I74: =RA_TC!I74+MA_TC!I74+CI_TC!I74 -> 0 | J74: =RA_TC!J74+MA_TC!J74+CI_TC!J74 -> 0 | K74: =RA_TC!K74+MA_TC!K74+CI_TC!K74 -> 0 | ... BK74: =RA_TC!BK74+MA_TC!BK74+CI_TC!BK74 -> 1028.5 | BO74: =SUMIFS($D74:$BM74,$D$6:$BM$6,">="&BO$2,$D$6:$BM$6,"<="&BO$6,$D$5:$BM$5,BO$5) -> 0 | BP74: =SUMIFS($D74:$BM74,$D$6:$BM$6,">="&BP$2,$D$6:$BM$6,"<="&BP$6,$D$5:$BM$5,BP$5) -> 1064.5 | BQ74: =SUMIFS($D74:$BM74,$D$6:$BM$6,">="&BQ$2,$D$6:$BM$6,"<="&BQ$6,$D$5:$BM$5,BQ$5) -> 0 | BR74: =SUMIFS($D74:$BM74,$D$6:$BM$6,">="&BR$2,$D$6:$BM$6,"<="&BR$6,$D$5:$BM$5,BR$5) -> 0 | BS74: =SUMIFS($D74:$BM74,$D$6:$BM$6,">="&BS$2,$D$6:$BM$6,"<="&BS$6,$D$5:$BM$5,BS$5) -> 0 | BT74: =SUMIFS($D74:$BM74,$D$6:$BM$6,">="&BT$2,$D$6:$BM$6,"<="&BT$6,$D$5:$BM$5,BT$5) -> 0
... A79: INOF | C79: Comisión Establecimiento TEBCA | D79: =RA_TC!D79+MA_TC!D79+CI_TC!D79 -> 0 | E79: =RA_TC!E79+MA_TC!E79+CI_TC!E79 -> 0 | F79: =RA_TC!F79+MA_TC!F79+CI_TC!F79 -> 0 | G79: =RA_TC!G79+MA_TC!G79+CI_TC!G79 -> 0 | H79: =RA_TC!H79+MA_TC!H79+CI_TC!H79 -> 0 | I79: =RA_TC!I79+MA_TC!I79+CI_TC!I79 -> 0 | J79: =RA_TC!J79+MA_TC!J79+CI_TC!J79 -> 0 | K79: =RA_TC!K79+MA_TC!K79+CI_TC!K79 -> 0 | ... BK79: =RA_TC!BK79+MA_TC!BK79+CI_TC!BK79 -> 0 | BO79: =SUMIFS($D79:$BM79,$D$6:$BM$6,">="&BO$2,$D$6:$BM$6,"<="&BO$6,$D$5:$BM$5,BO$5) -> 0 | BP79: =SUMIFS($D79:$BM79,$D$6:$BM$6,">="&BP$2,$D$6:$BM$6,"<="&BP$6,$D$5:$BM$5,BP$5) -> 0 | BQ79: =SUMIFS($D79:$BM79,$D$6:$BM$6,">="&BQ$2,$D$6:$BM$6,"<="&BQ$6,$D$5:$BM$5,BQ$5) -> 0 | BR79: =SUMIFS($D79:$BM79,$D$6:$BM$6,">="&BR$2,$D$6:$BM$6,"<="&BR$6,$D$5:$BM$5,BR$5) -> 0 | BS79: =SUMIFS($D79:$BM79,$D$6:$BM$6,">="&BS$2,$D$6:$BM$6,"<="&BS$6,$D$5:$BM$5,BS$5) -> 0 | BT79: =SUMIFS($D79:$BM79,$D$6:$BM$6,">="&BT$2,$D$6:$BM$6,"<="&BT$6,$D$5:$BM$5,BT$5) -> 0
A80: INOF | D80: =RA_TC!D80+MA_TC!D80+CI_TC!D80 -> 0 | E80: =RA_TC!E80+MA_TC!E80+CI_TC!E80 -> 0 | F80: =RA_TC!F80+MA_TC!F80+CI_TC!F80 -> 0 | G80: =RA_TC!G80+MA_TC!G80+CI_TC!G80 -> 0 | H80: =RA_TC!H80+MA_TC!H80+CI_TC!H80 -> 0 | I80: =RA_TC!I80+MA_TC!I80+CI_TC!I80 -> 0 | J80: =RA_TC!J80+MA_TC!J80+CI_TC!J80 -> 0 | K80: =RA_TC!K80+MA_TC!K80+CI_TC!K80 -> 0 | ... BK80: =RA_TC!BK80+MA_TC!BK80+CI_TC!BK80 -> 0 | BO80: =SUMIFS($D80:$BM80,$D$6:$BM$6,">="&BO$2,$D$6:$BM$6,"<="&BO$6,$D$5:$BM$5,BO$5) -> 0 | BP80: =SUMIFS($D80:$BM80,$D$6:$BM$6,">="&BP$2,$D$6:$BM$6,"<="&BP$6,$D$5:$BM$5,BP$5) -> 0 | BQ80: =SUMIFS($D80:$BM80,$D$6:$BM$6,">="&BQ$2,$D$6:$BM$6,"<="&BQ$6,$D$5:$BM$5,BQ$5) -> 0 | BR80: =SUMIFS($D80:$BM80,$D$6:$BM$6,">="&BR$2,$D$6:$BM$6,"<="&BR$6,$D$5:$BM$5,BR$5) -> 0 | BS80: =SUMIFS($D80:$BM80,$D$6:$BM$6,">="&BS$2,$D$6:$BM$6,"<="&BS$6,$D$5:$BM$5,BS$5) -> 0 | BT80: =SUMIFS($D80:$BM80,$D$6:$BM$6,">="&BT$2,$D$6:$BM$6,"<="&BT$6,$D$5:$BM$5,BT$5) -> 0
A81: INOF | D81: =RA_TC!D81+MA_TC!D81+CI_TC!D81 -> 0 | E81: =RA_TC!E81+MA_TC!E81+CI_TC!E81 -> 0 | F81: =RA_TC!F81+MA_TC!F81+CI_TC!F81 -> 0 | G81: =RA_TC!G81+MA_TC!G81+CI_TC!G81 -> 0 | H81: =RA_TC!H81+MA_TC!H81+CI_TC!H81 -> 0 | I81: =RA_TC!I81+MA_TC!I81+CI_TC!I81 -> 0 | J81: =RA_TC!J81+MA_TC!J81+CI_TC!J81 -> 0 | K81: =RA_TC!K81+MA_TC!K81+CI_TC!K81 -> 0 | ... BK81: =RA_TC!BK81+MA_TC!BK81+CI_TC!BK81 -> 0 | BO81: =SUMIFS($D81:$BM81,$D$6:$BM$6,">="&BO$2,$D$6:$BM$6,"<="&BO$6,$D$5:$BM$5,BO$5) -> 0 | BP81: =SUMIFS($D81:$BM81,$D$6:$BM$6,">="&BP$2,$D$6:$BM$6,"<="&BP$6,$D$5:$BM$5,BP$5) -> 0 | BQ81: =SUMIFS($D81:$BM81,$D$6:$BM$6,">="&BQ$2,$D$6:$BM$6,"<="&BQ$6,$D$5:$BM$5,BQ$5) -> 0 | BR81: =SUMIFS($D81:$BM81,$D$6:$BM$6,">="&BR$2,$D$6:$BM$6,"<="&BR$6,$D$5:$BM$5,BR$5) -> 0 | BS81: =SUMIFS($D81:$BM81,$D$6:$BM$6,">="&BS$2,$D$6:$BM$6,"<="&BS$6,$D$5:$BM$5,BS$5) -> 0 | BT81: =SUMIFS($D81:$BM81,$D$6:$BM$6,">="&BT$2,$D$6:$BM$6,"<="&BT$6,$D$5:$BM$5,BT$5) -> 0
A82: INOF | D82: =RA_TC!D82+MA_TC!D82+CI_TC!D82 -> 0 | E82: =RA_TC!E82+MA_TC!E82+CI_TC!E82 -> 0 | F82: =RA_TC!F82+MA_TC!F82+CI_TC!F82 -> 0 | G82: =RA_TC!G82+MA_TC!G82+CI_TC!G82 -> 0 | H82: =RA_TC!H82+MA_TC!H82+CI_TC!H82 -> 0 | I82: =RA_TC!I82+MA_TC!I82+CI_TC!I82 -> 0 | J82: =RA_TC!J82+MA_TC!J82+CI_TC!J82 -> 0 | K82: =RA_TC!K82+MA_TC!K82+CI_TC!K82 -> 0 | ... BK82: =RA_TC!BK82+MA_TC!BK82+CI_TC!BK82 -> 0 | BO82: =SUMIFS($D82:$BM82,$D$6:$BM$6,">="&BO$2,$D$6:$BM$6,"<="&BO$6,$D$5:$BM$5,BO$5) -> 0 | BP82: =SUMIFS($D82:$BM82,$D$6:$BM$6,">="&BP$2,$D$6:$BM$6,"<="&BP$6,$D$5:$BM$5,BP$5) -> 0 | BQ82: =SUMIFS($D82:$BM82,$D$6:$BM$6,">="&BQ$2,$D$6:$BM$6,"<="&BQ$6,$D$5:$BM$5,BQ$5) -> 0 | BR82: =SUMIFS($D82:$BM82,$D$6:$BM$6,">="&BR$2,$D$6:$BM$6,"<="&BR$6,$D$5:$BM$5,BR$5) -> 0 | BS82: =SUMIFS($D82:$BM82,$D$6:$BM$6,">="&BS$2,$D$6:$BM$6,"<="&BS$6,$D$5:$BM$5,BS$5) -> 0 | BT82: =SUMIFS($D82:$BM82,$D$6:$BM$6,">="&BT$2,$D$6:$BM$6,"<="&BT$6,$D$5:$BM$5,BT$5) -> 0
C83: INOF | D83: =SUM(D63:D82) -> 0 | E83: =SUM(E63:E82) -> 0 | F83: =SUM(F63:F82) -> 0 | G83: =SUM(G63:G82) -> 0 | H83: =SUM(H63:H82) -> 0 | I83: =SUM(I63:I82) -> 0 | J83: =SUM(J63:J82) -> 0 | K83: =SUM(K63:K82) -> 0 | ... BK83: =SUM(BK63:BK82) -> 31501.388 | BO83: =SUM(BO63:BO82) -> 0 | BP83: =SUM(BP63:BP82) -> 75134.826 | BQ83: =SUM(BQ63:BQ82) -> 0 | BR83: =SUM(BR63:BR82) -> 0 | BS83: =SUM(BS63:BS82) -> 0 | BT83: =SUM(BT63:BT82) -> 0
D84: ='[1]Desempeño Finan_ TC_Cartera_Evo'!AY73-D83 -> 24885.683 | E84: ='[1]Desempeño Finan_ TC_Cartera_Evo'!AZ73-E83 -> 23833.458 | F84: ='[1]Desempeño Finan_ TC_Cartera_Evo'!BA73-F83 -> 23057.638 | G84: ='[1]Desempeño Finan_ TC_Cartera_Evo'!BB73-G83 -> 21642.544 | H84: ='[1]Desempeño Finan_ TC_Cartera_Evo'!BC73-H83 -> 22488.043 | I84: ='[1]Desempeño Finan_ TC_Cartera_Evo'!BD73-I83 -> 21586.832 | J84: ='[1]Desempeño Finan_ TC_Cartera_Evo'!BE73-J83 -> 23303.233 | K84: ='[1]Desempeño Finan_ TC_Cartera_Evo'!BF73-K83 -> 20446.984 | ... BK84: ='[1]Desempeño Finan_ TC_Cartera_Evo'!DF73-BK83 -> 0
A86: Gastos Operativos | C86: Gasto Directo | D86: =RA_TC!D86+MA_TC!D86+CI_TC!D86 -> 0 | E86: =RA_TC!E86+MA_TC!E86+CI_TC!E86 -> 0 | F86: =RA_TC!F86+MA_TC!F86+CI_TC!F86 -> 0 | G86: =RA_TC!G86+MA_TC!G86+CI_TC!G86 -> 0 | H86: =RA_TC!H86+MA_TC!H86+CI_TC!H86 -> 0 | I86: =RA_TC!I86+MA_TC!I86+CI_TC!I86 -> 0 | J86: =RA_TC!J86+MA_TC!J86+CI_TC!J86 -> 0 | K86: =RA_TC!K86+MA_TC!K86+CI_TC!K86 -> 0 | ... BK86: =RA_TC!BK86+MA_TC!BK86+CI_TC!BK86 -> -32002.516 | BO86: =SUMIFS($D86:$BM86,$D$6:$BM$6,">="&BO$2,$D$6:$BM$6,"<="&BO$6,$D$5:$BM$5,BO$5) -> 0 | BP86: =SUMIFS($D86:$BM86,$D$6:$BM$6,">="&BP$2,$D$6:$BM$6,"<="&BP$6,$D$5:$BM$5,BP$5) -> -86610.717 | BQ86: =SUMIFS($D86:$BM86,$D$6:$BM$6,">="&BQ$2,$D$6:$BM$6,"<="&BQ$6,$D$5:$BM$5,BQ$5) -> 0 | BR86: =SUMIFS($D86:$BM86,$D$6:$BM$6,">="&BR$2,$D$6:$BM$6,"<="&BR$6,$D$5:$BM$5,BR$5) -> 0 | BS86: =SUMIFS($D86:$BM86,$D$6:$BM$6,">="&BS$2,$D$6:$BM$6,"<="&BS$6,$D$5:$BM$5,BS$5) -> 0 | BT86: =SUMIFS($D86:$BM86,$D$6:$BM$6,">="&BT$2,$D$6:$BM$6,"<="&BT$6,$D$5:$BM$5,BT$5) -> 0
A87: Gastos Operativos | C87: Gasto Canal | D87: =RA_TC!D87+MA_TC!D87+CI_TC!D87 -> 0 | E87: =RA_TC!E87+MA_TC!E87+CI_TC!E87 -> 0 | F87: =RA_TC!F87+MA_TC!F87+CI_TC!F87 -> 0 | G87: =RA_TC!G87+MA_TC!G87+CI_TC!G87 -> 0 | H87: =RA_TC!H87+MA_TC!H87+CI_TC!H87 -> 0 | I87: =RA_TC!I87+MA_TC!I87+CI_TC!I87 -> 0 | J87: =RA_TC!J87+MA_TC!J87+CI_TC!J87 -> 0 | K87: =RA_TC!K87+MA_TC!K87+CI_TC!K87 -> 0 | ... BK87: =RA_TC!BK87+MA_TC!BK87+CI_TC!BK87 -> -9283.7668 | BO87: =SUMIFS($D87:$BM87,$D$6:$BM$6,">="&BO$2,$D$6:$BM$6,"<="&BO$6,$D$5:$BM$5,BO$5) -> 0 | BP87: =SUMIFS($D87:$BM87,$D$6:$BM$6,">="&BP$2,$D$6:$BM$6,"<="&BP$6,$D$5:$BM$5,BP$5) -> -29502.628 | BQ87: =SUMIFS($D87:$BM87,$D$6:$BM$6,">="&BQ$2,$D$6:$BM$6,"<="&BQ$6,$D$5:$BM$5,BQ$5) -> 0 | BR87: =SUMIFS($D87:$BM87,$D$6:$BM$6,">="&BR$2,$D$6:$BM$6,"<="&BR$6,$D$5:$BM$5,BR$5) -> 0 | BS87: =SUMIFS($D87:$BM87,$D$6:$BM$6,">="&BS$2,$D$6:$BM$6,"<="&BS$6,$D$5:$BM$5,BS$5) -> 0 | BT87: =SUMIFS($D87:$BM87,$D$6:$BM$6,">="&BT$2,$D$6:$BM$6,"<="&BT$6,$D$5:$BM$5,BT$5) -> 0
A88: Gastos Operativos | C88: Gasto Indirecto | D88: =RA_TC!D88+MA_TC!D88+CI_TC!D88 -> 0 | E88: =RA_TC!E88+MA_TC!E88+CI_TC!E88 -> 0 | F88: =RA_TC!F88+MA_TC!F88+CI_TC!F88 -> 0 | G88: =RA_TC!G88+MA_TC!G88+CI_TC!G88 -> 0 | H88: =RA_TC!H88+MA_TC!H88+CI_TC!H88 -> 0 | I88: =RA_TC!I88+MA_TC!I88+CI_TC!I88 -> 0 | J88: =RA_TC!J88+MA_TC!J88+CI_TC!J88 -> 0 | K88: =RA_TC!K88+MA_TC!K88+CI_TC!K88 -> 0 | ... BK88: =RA_TC!BK88+MA_TC!BK88+CI_TC!BK88 -> -9633.9385 | BO88: =SUMIFS($D88:$BM88,$D$6:$BM$6,">="&BO$2,$D$6:$BM$6,"<="&BO$6,$D$5:$BM$5,BO$5) -> 0 | BP88: =SUMIFS($D88:$BM88,$D$6:$BM$6,">="&BP$2,$D$6:$BM$6,"<="&BP$6,$D$5:$BM$5,BP$5) -> -27118.722 | BQ88: =SUMIFS($D88:$BM88,$D$6:$BM$6,">="&BQ$2,$D$6:$BM$6,"<="&BQ$6,$D$5:$BM$5,BQ$5) -> 0 | BR88: =SUMIFS($D88:$BM88,$D$6:$BM$6,">="&BR$2,$D$6:$BM$6,"<="&BR$6,$D$5:$BM$5,BR$5) -> 0 | BS88: =SUMIFS($D88:$BM88,$D$6:$BM$6,">="&BS$2,$D$6:$BM$6,"<="&BS$6,$D$5:$BM$5,BS$5) -> 0 | BT88: =SUMIFS($D88:$BM88,$D$6:$BM$6,">="&BT$2,$D$6:$BM$6,"<="&BT$6,$D$5:$BM$5,BT$5) -> 0
C89: Gastos Operativos | D89: =SUM(D86:D88) -> 0 | E89: =SUM(E86:E88) -> 0 | F89: =SUM(F86:F88) -> 0 | G89: =SUM(G86:G88) -> 0 | H89: =SUM(H86:H88) -> 0 | I89: =SUM(I86:I88) -> 0 | J89: =SUM(J86:J88) -> 0 | K89: =SUM(K86:K88) -> 0 | ... BK89: =SUM(BK86:BK88) -> -50920.222 | BO89: =SUM(BO86:BO88) -> 0 | BP89: =SUM(BP86:BP88) -> -143232.07 | BQ89: =SUM(BQ86:BQ88) -> 0 | BR89: =SUM(BR86:BR88) -> 0 | BS89: =SUM(BS86:BS88) -> 0 | BT89: =SUM(BT86:BT88) -> 0
D90: ='[1]Desempeño Finan_ TC_Cartera_Evo'!AY78-D89 -> -36742.702 | E90: ='[1]Desempeño Finan_ TC_Cartera_Evo'!AZ78-E89 -> -37519.209 | F90: ='[1]Desempeño Finan_ TC_Cartera_Evo'!BA78-F89 -> -37664.856 | G90: ='[1]Desempeño Finan_ TC_Cartera_Evo'!BB78-G89 -> -34676.505 | H90: ='[1]Desempeño Finan_ TC_Cartera_Evo'!BC78-H89 -> -39510.781 | I90: ='[1]Desempeño Finan_ TC_Cartera_Evo'!BD78-I89 -> -38426.27 | J90: ='[1]Desempeño Finan_ TC_Cartera_Evo'!BE78-J89 -> -37061.806 | K90: ='[1]Desempeño Finan_ TC_Cartera_Evo'!BF78-K89 -> -39489.352 | ... BK90: ='[1]Desempeño Finan_ TC_Cartera_Evo'!DF78-BK89 -> -136.23348
A91: Extraordinarios | C91: Donaciones | D91: =RA_TC!D91+MA_TC!D91+CI_TC!D91 -> 0 | E91: =RA_TC!E91+MA_TC!E91+CI_TC!E91 -> 0 | F91: =RA_TC!F91+MA_TC!F91+CI_TC!F91 -> 0 | G91: =RA_TC!G91+MA_TC!G91+CI_TC!G91 -> 0 | H91: =RA_TC!H91+MA_TC!H91+CI_TC!H91 -> 0 | I91: =RA_TC!I91+MA_TC!I91+CI_TC!I91 -> 0 | J91: =RA_TC!J91+MA_TC!J91+CI_TC!J91 -> 0 | K91: =RA_TC!K91+MA_TC!K91+CI_TC!K91 -> 0 | ... BK91: =RA_TC!BK91+MA_TC!BK91+CI_TC!BK91 -> 0 | BO91: =SUMIFS($D91:$BM91,$D$6:$BM$6,">="&BO$2,$D$6:$BM$6,"<="&BO$6,$D$5:$BM$5,BO$5) -> 0 | BP91: =SUMIFS($D91:$BM91,$D$6:$BM$6,">="&BP$2,$D$6:$BM$6,"<="&BP$6,$D$5:$BM$5,BP$5) -> 0 | BQ91: =SUMIFS($D91:$BM91,$D$6:$BM$6,">="&BQ$2,$D$6:$BM$6,"<="&BQ$6,$D$5:$BM$5,BQ$5) -> 0 | BR91: =SUMIFS($D91:$BM91,$D$6:$BM$6,">="&BR$2,$D$6:$BM$6,"<="&BR$6,$D$5:$BM$5,BR$5) -> 0 | BS91: =SUMIFS($D91:$BM91,$D$6:$BM$6,">="&BS$2,$D$6:$BM$6,"<="&BS$6,$D$5:$BM$5,BS$5) -> 0 | BT91: =SUMIFS($D91:$BM91,$D$6:$BM$6,">="&BT$2,$D$6:$BM$6,"<="&BT$6,$D$5:$BM$5,BT$5) -> 0
A92: Extraordinarios | C92: Otros | D92: =RA_TC!D92+MA_TC!D92+CI_TC!D92 -> 0 | E92: =RA_TC!E92+MA_TC!E92+CI_TC!E92 -> 0 | F92: =RA_TC!F92+MA_TC!F92+CI_TC!F92 -> 0 | G92: =RA_TC!G92+MA_TC!G92+CI_TC!G92 -> 0 | H92: =RA_TC!H92+MA_TC!H92+CI_TC!H92 -> 0 | I92: =RA_TC!I92+MA_TC!I92+CI_TC!I92 -> 0 | J92: =RA_TC!J92+MA_TC!J92+CI_TC!J92 -> 0 | K92: =RA_TC!K92+MA_TC!K92+CI_TC!K92 -> 0 | ... BK92: =RA_TC!BK92+MA_TC!BK92+CI_TC!BK92 -> -1435.6451 | BO92: =SUMIFS($D92:$BM92,$D$6:$BM$6,">="&BO$2,$D$6:$BM$6,"<="&BO$6,$D$5:$BM$5,BO$5) -> 0 | BP92: =SUMIFS($D92:$BM92,$D$6:$BM$6,">="&BP$2,$D$6:$BM$6,"<="&BP$6,$D$5:$BM$5,BP$5) -> -4321.2798 | BQ92: =SUMIFS($D92:$BM92,$D$6:$BM$6,">="&BQ$2,$D$6:$BM$6,"<="&BQ$6,$D$5:$BM$5,BQ$5) -> 0 | BR92: =SUMIFS($D92:$BM92,$D$6:$BM$6,">="&BR$2,$D$6:$BM$6,"<="&BR$6,$D$5:$BM$5,BR$5) -> 0 | BS92: =SUMIFS($D92:$BM92,$D$6:$BM$6,">="&BS$2,$D$6:$BM$6,"<="&BS$6,$D$5:$BM$5,BS$5) -> 0 | BT92: =SUMIFS($D92:$BM92,$D$6:$BM$6,">="&BT$2,$D$6:$BM$6,"<="&BT$6,$D$5:$BM$5,BT$5) -> 0
C93: Extraordinarios | D93: =SUM(D91:D92) -> 0 | E93: =SUM(E91:E92) -> 0 | F93: =SUM(F91:F92) -> 0 | G93: =SUM(G91:G92) -> 0 | H93: =SUM(H91:H92) -> 0 | I93: =SUM(I91:I92) -> 0 | J93: =SUM(J91:J92) -> 0 | K93: =SUM(K91:K92) -> 0 | ... BK93: =SUM(BK91:BK92) -> -1435.6451 | BO93: =SUM(BO91:BO92) -> 0 | BP93: =SUM(BP91:BP92) -> -4321.2798 | BQ93: =SUM(BQ91:BQ92) -> 0 | BR93: =SUM(BR91:BR92) -> 0 | BS93: =SUM(BS91:BS92) -> 0 | BT93: =SUM(BT91:BT92) -> 0
D94: ='[1]Desempeño Finan_ TC_Cartera_Evo'!AY87-D93 -> -645.12418 | E94: ='[1]Desempeño Finan_ TC_Cartera_Evo'!AZ87-E93 -> -398.04468 | F94: ='[1]Desempeño Finan_ TC_Cartera_Evo'!BA87-F93 -> -375.08824 | G94: ='[1]Desempeño Finan_ TC_Cartera_Evo'!BB87-G93 -> -608.00921 | H94: ='[1]Desempeño Finan_ TC_Cartera_Evo'!BC87-H93 -> -952.31297 | I94: ='[1]Desempeño Finan_ TC_Cartera_Evo'!BD87-I93 -> -1389.125 | J94: ='[1]Desempeño Finan_ TC_Cartera_Evo'!BE87-J93 -> -1121.8325 | K94: ='[1]Desempeño Finan_ TC_Cartera_Evo'!BF87-K93 -> -3374.3511 | ... BK94: ='[1]Desempeño Finan_ TC_Cartera_Evo'!DF87-BK93 -> 0
A95: ROF | C95: Venta de Cartera | D95: =RA_TC!D95+MA_TC!D95+CI_TC!D95 -> 0 | E95: =RA_TC!E95+MA_TC!E95+CI_TC!E95 -> 0 | F95: =RA_TC!F95+MA_TC!F95+CI_TC!F95 -> 0 | G95: =RA_TC!G95+MA_TC!G95+CI_TC!G95 -> 0 | H95: =RA_TC!H95+MA_TC!H95+CI_TC!H95 -> 0 | I95: =RA_TC!I95+MA_TC!I95+CI_TC!I95 -> 0 | J95: =RA_TC!J95+MA_TC!J95+CI_TC!J95 -> 0 | K95: =RA_TC!K95+MA_TC!K95+CI_TC!K95 -> 0 | ... BK95: =RA_TC!BK95+MA_TC!BK95+CI_TC!BK95 -> 0 | BO95: =SUMIFS($D95:$BM95,$D$6:$BM$6,">="&BO$2,$D$6:$BM$6,"<="&BO$6,$D$5:$BM$5,BO$5) -> 0 | BP95: =SUMIFS($D95:$BM95,$D$6:$BM$6,">="&BP$2,$D$6:$BM$6,"<="&BP$6,$D$5:$BM$5,BP$5) -> 0 | BQ95: =SUMIFS($D95:$BM95,$D$6:$BM$6,">="&BQ$2,$D$6:$BM$6,"<="&BQ$6,$D$5:$BM$5,BQ$5) -> 0 | BR95: =SUMIFS($D95:$BM95,$D$6:$BM$6,">="&BR$2,$D$6:$BM$6,"<="&BR$6,$D$5:$BM$5,BR$5) -> 0 | BS95: =SUMIFS($D95:$BM95,$D$6:$BM$6,">="&BS$2,$D$6:$BM$6,"<="&BS$6,$D$5:$BM$5,BS$5) -> 0 | BT95: =SUMIFS($D95:$BM95,$D$6:$BM$6,">="&BT$2,$D$6:$BM$6,"<="&BT$6,$D$5:$BM$5,BT$5) -> 0
A96: ROF | C96: Inversiones | D96: =RA_TC!D96+MA_TC!D96+CI_TC!D96 -> 0 | E96: =RA_TC!E96+MA_TC!E96+CI_TC!E96 -> 0 | F96: =RA_TC!F96+MA_TC!F96+CI_TC!F96 -> 0 | G96: =RA_TC!G96+MA_TC!G96+CI_TC!G96 -> 0 | H96: =RA_TC!H96+MA_TC!H96+CI_TC!H96 -> 0 | I96: =RA_TC!I96+MA_TC!I96+CI_TC!I96 -> 0 | J96: =RA_TC!J96+MA_TC!J96+CI_TC!J96 -> 0 | K96: =RA_TC!K96+MA_TC!K96+CI_TC!K96 -> 0 | ... BK96: =RA_TC!BK96+MA_TC!BK96+CI_TC!BK96 -> 1882.8292
C97: ROF | D97: =SUM(D95:D96) -> 0 | E97: =SUM(E95:E96) -> 0 | F97: =SUM(F95:F96) -> 0 | G97: =SUM(G95:G96) -> 0 | H97: =SUM(H95:H96) -> 0 | I97: =SUM(I95:I96) -> 0 | J97: =SUM(J95:J96) -> 0 | K97: =SUM(K95:K96) -> 0 | ... BK97: =SUM(BK95:BK96) -> 1882.8292 | BO97: =SUM(BO95) -> 0 | BP97: =SUM(BP95) -> 0 | BQ97: =SUM(BQ95) -> 0 | BR97: =SUM(BR95) -> 0 | BS97: =SUM(BS95) -> 0 | BT97: =SUM(BT95) -> 0
D98: ='[1]Desempeño Finan_ TC_Cartera_Evo'!AY85-D97 -> 1977.9717 | E98: ='[1]Desempeño Finan_ TC_Cartera_Evo'!AZ85-E97 -> 1842.5911 | F98: ='[1]Desempeño Finan_ TC_Cartera_Evo'!BA85-F97 -> 2412.3341 | G98: ='[1]Desempeño Finan_ TC_Cartera_Evo'!BB85-G97 -> 3552.0352 | H98: ='[1]Desempeño Finan_ TC_Cartera_Evo'!BC85-H97 -> 2312.0859 | I98: ='[1]Desempeño Finan_ TC_Cartera_Evo'!BD85-I97 -> 3391.9408 | J98: ='[1]Desempeño Finan_ TC_Cartera_Evo'!BE85-J97 -> 2530.0881 | K98: ='[1]Desempeño Finan_ TC_Cartera_Evo'!BF85-K97 -> 10675.012 | ... BK98: ='[1]Desempeño Finan_ TC_Cartera_Evo'!DF85-BK97 -> 0
C99: UAI | D99: =D60+D83+D89+D93+D97 -> 0 | E99: =E60+E83+E89+E93+E97 -> 0 | F99: =F60+F83+F89+F93+F97 -> 0 | G99: =G60+G83+G89+G93+G97 -> 0 | H99: =H60+H83+H89+H93+H97 -> 0 | I99: =I60+I83+I89+I93+I97 -> 0 | J99: =J60+J83+J89+J93+J97 -> 0 | K99: =K60+K83+K89+K93+K97 -> 0 | ... BK99: =BK60+BK83+BK89+BK93+BK97 -> 26718.495 | BO99: =BO60+BO83+BO89+BO93+BO97 -> 0 | BP99: =BP60+BP83+BP89+BP93+BP97 -> 28082.691 | BQ99: =BQ60+BQ83+BQ89+BQ93+BQ97 -> 0 | BR99: =BR60+BR83+BR89+BR93+BR97 -> 0 | BS99: =BS60+BS83+BS89+BS93+BS97 -> 0 | BT99: =BT60+BT83+BT89+BT93+BT97 -> 0
D100: ='[1]Desempeño Finan_ TC_Cartera_Evo'!AY89-D99 -> 13377.905 | E100: ='[1]Desempeño Finan_ TC_Cartera_Evo'!AZ89-E99 -> 5626.8468 | F100: ='[1]Desempeño Finan_ TC_Cartera_Evo'!BA89-F99 -> 7073.3574 | G100: ='[1]Desempeño Finan_ TC_Cartera_Evo'!BB89-G99 -> 14649.607 | H100: ='[1]Desempeño Finan_ TC_Cartera_Evo'!BC89-H99 -> -23683.105 | I100: ='[1]Desempeño Finan_ TC_Cartera_Evo'!BD89-I99 -> -30886.201 | J100: ='[1]Desempeño Finan_ TC_Cartera_Evo'!BE89-J99 -> -27224.545 | K100: ='[1]Desempeño Finan_ TC_Cartera_Evo'!BF89-K99 -> -54239.39 | ... BK100: ='[1]Desempeño Finan_ TC_Cartera_Evo'!DF89-BK99 -> -136.23348
C103: Prom SFdP | D103: =D11 -> 0 | E103: =IFERROR(AVERAGE(D11:E11),0) -> 0 | F103: =IFERROR(AVERAGE(E11:F11),0) -> 0 | G103: =IFERROR(AVERAGE(F11:G11),0) -> 0 | H103: =IFERROR(AVERAGE(G11:H11),0) -> 0 | I103: =IFERROR(AVERAGE(H11:I11),0) -> 0 | J103: =IFERROR(AVERAGE(I11:J11),0) -> 0 | K103: =IFERROR(AVERAGE(J11:K11),0) -> 0 | L103: =IFERROR(AVERAGE(K11:L11),0) -> 0 | ... AY103: =IFERROR(AVERAGE(AX11:AY11),0) -> 0 | AZ103: =AZ11 -> 5873351.1 | BA103: =IFERROR(AVERAGE(AZ11:BA11),0) -> 5890643.5 | BB103: =IFERROR(AVERAGE(BA11:BB11),0) -> 5907264 | BC103: =IFERROR(AVERAGE(BB11:BC11),0) -> 5973055.3 | BD103: =IFERROR(AVERAGE(BC11:BD11),0) -> 6093453.4 | BE103: =IFERROR(AVERAGE(BD11:BE11),0) -> 6175530.1 | BF103: =IFERROR(AVERAGE(BE11:BF11),0) -> 6229094.8 | BG103: =IFERROR(AVERAGE(BF11:BG11),0) -> 6284667.3 | BH103: =IFERROR(AVERAGE(BG11:BH11),0) -> 6324353.9 | ... BK103: =IFERROR(AVERAGE(BJ11:BK11),0) -> 6517599.4 | BO103: =IFERROR(AVERAGEIFS($D11:$BM11,$D$6:$BM$6,">="&EOMONTH(BO$2,-1),$D$6:$BM$6,"<="&BO$6,$D$5:$BM$5,BO$5,$D11:$BM11,"<>0"),0) -> 0 | BP103: =IFERROR(AVERAGEIFS($D11:$BM11,$D$6:$BM$6,">="&EOMONTH(BP$2,-1),$D$6:$BM$6,"<="&BP$6,$D$5:$BM$5,BP$5,$D11:$BM11,"<>0"),0) -> 5895959.7 | BQ103: =IFERROR(AVERAGEIFS($D11:$BM11,$D$6:$BM$6,">="&EOMONTH(BQ$2,-1),$D$6:$BM$6,"<="&BQ$6,$D$5:$BM$5,BQ$5,$D11:$BM11,"<>0"),0) -> 0 | BR103: =IFERROR(AVERAGEIFS($D11:$BM11,$D$6:$BM$6,">="&EOMONTH(BR$2,-1),$D$6:$BM$6,"<="&BR$6,$D$5:$BM$5,BR$5,$D11:$BM11,"<>0"),0) -> 0 | BS103: =IFERROR(AVERAGEIFS($D11:$BM11,$D$6:$BM$6,">="&EOMONTH(BS$2,-1),$D$6:$BM$6,"<="&BS$6,$D$5:$BM$5,BS$5,$D11:$BM11,"<>0"),0) -> 0 | BT103: =IFERROR(AVERAGEIFS($D11:$BM11,$D$6:$BM$6,">="&EOMONTH(BT$2,-1),$D$6:$BM$6,"<="&BT$6,$D$5:$BM$5,BT$5,$D11:$BM11,"<>0"),0) -> 0

Sheet Desempeño_Financiero
B1: 46112 | D1: Mensual | W1: Acumulado
B2: Desempeño Financiero
B3: En S/. Miles | C3: N° dias T.Imp | D3: =DAY(D6) -> 31 | E3: =DAY(E6) -> 31 | F3: =DAY(F6) -> 28 | G3: =DAY(G6) -> 31 | H3: =DAY(H6) -> 31 | I3: =DAY(I6) -> 31
C4: N° dias FTP | D4: =DAY(D6) -> 31 | E4: =DAY(E6) -> 31 | F4: =DAY(F6) -> 28 | G4: =DAY(G6) -> 31 | H4: =DAY(H6) -> 31 | I4: =DAY(I6) -> 31
C5: Tipo | D5: R | E5: P | F5: R | G5: R | H5: R | I5: R | K5: Variación S/. | Q5: Variación % | AD5: Variación S/. | AJ5: Variación %
C6: Total_Producto | D6: =$B$1 -> 46112 | E6: =D6 -> 46112 | F6: =EOMONTH(D6,-1) -> 46081 | G6: =EOMONTH(D6,-12) -> 45747 | H6: =EOMONTH(D6,-24) -> 45382 | I6: =EOMONTH(D6,-36) -> 45016 | K6: =E6 -> 46112 | L6: =F6 -> 46081 | M6: =G6 -> 45747 | N6: =H6 -> 45382 | O6: =I6 -> 45016 | Q6: =K6 -> 46112 | R6: =L6 -> 46081 | S6: =M6 -> 45747 | T6: =N6 -> 45382 | U6: =O6 -> 45016 | W6: =$B$1 -> 46112 | X6: =W6 -> 46112 | Y6: =EOMONTH(W6,-1) -> 46081 | Z6: =EOMONTH(W6,-12) -> 45747 | AA6: =EOMONTH(W6,-24) -> 45382 | AB6: =EOMONTH(W6,-36) -> 45016 | AD6: =X6 -> 46112 | AE6: =Y6 -> 46081 | AF6: =Z6 -> 45747 | AG6: =AA6 -> 45382 | AH6: =AB6 -> 45016 | AJ6: =AD6 -> 46112 | AK6: =AE6 -> 46081 | AL6: =AF6 -> 45747 | AM6: =AG6 -> 45382 | AN6: =AH6 -> 45016
A8: SALDO_FDP | C8: Vigente | D8: {=_xlfn.XLOOKUP(1, (INDIRECT("'"&$C$6&"'!$6:$6")=D$6)* (INDIRECT("'"&$C$6&"'!$5:$5")=D$5), INDIRECT("'"&$C$6&"'!"&ROW()&":"&ROW()) )} -> 0 | E8: {=_xlfn.XLOOKUP(1, (INDIRECT("'"&$C$6&"'!$6:$6")=E$6)* (INDIRECT("'"&$C$6&"'!$5:$5")=E$5), INDIRECT("'"&$C$6&"'!"&ROW()&":"&ROW()) )} -> 5475782.9 | F8: {=_xlfn.XLOOKUP(1, (INDIRECT("'"&$C$6&"'!$6:$6")=F$6)* (INDIRECT("'"&$C$6&"'!$5:$5")=F$5), INDIRECT("'"&$C$6&"'!"&ROW()&":"&ROW()) )} -> 0 | G8: {=_xlfn.XLOOKUP(1, (INDIRECT("'"&$C$6&"'!$6:$6")=G$6)* (INDIRECT("'"&$C$6&"'!$5:$5")=G$5), INDIRECT("'"&$C$6&"'!"&ROW()&":"&ROW()) )} -> 0 | H8: {=_xlfn.XLOOKUP(1, (INDIRECT("'"&$C$6&"'!$6:$6")=H$6)* (INDIRECT("'"&$C$6&"'!$5:$5")=H$5), INDIRECT("'"&$C$6&"'!"&ROW()&":"&ROW()) )} -> 0 | I8: {=_xlfn.XLOOKUP(1, (INDIRECT("'"&$C$6&"'!$6:$6")=I$6)* (INDIRECT("'"&$C$6&"'!$5:$5")=I$5), INDIRECT("'"&$C$6&"'!"&ROW()&":"&ROW()) )} -> 0 | K8: =$D8-E8 -> -5475782.9 | L8: =$D8-F8 -> 0 | M8: =$D8-G8 -> 0 | N8: =$D8-H8 -> 0 | O8: =$D8-I8 -> 0 | Q8: =IFERROR($D8/E8-1,0) -> -1 | R8: =IFERROR($D8/F8-1,0) -> 0 | S8: =IFERROR($D8/G8-1,0) -> 0 | T8: =IFERROR($D8/H8-1,0) -> 0 | U8: =IFERROR($D8/I8-1,0) -> 0 | W8: {=INDIRECT("'"&$C$6&"'!"&ADDRESS(ROW(),COLUMN()+44))} -> 0 | X8: {=INDIRECT("'"&$C$6&"'!"&ADDRESS(ROW(),COLUMN()+44))} -> 5475782.9 | Y8: {=INDIRECT("'"&$C$6&"'!"&ADDRESS(ROW(),COLUMN()+44))} -> 0 | Z8: {=INDIRECT("'"&$C$6&"'!"&ADDRESS(ROW(),COLUMN()+44))} -> 0 | AA8: {=INDIRECT("'"&$C$6&"'!"&ADDRESS(ROW(),COLUMN()+44))} -> 0 | AB8: {=INDIRECT("'"&$C$6&"'!"&ADDRESS(ROW(),COLUMN()+44))} -> 0 | AD8: =$W8-X8 -> -5475782.9 | AE8: =$W8-Y8 -> 0 | AF8: =$W8-Z8 -> 0 | AG8: =$W8-AA8 -> 0 | AH8: =$W8-AB8 -> 0 | AJ8: =IFERROR($W8/X8-1,0) -> -1 | AK8: =IFERROR($W8/Y8-1,0) -> 0 | AL8: =IFERROR($W8/Z8-1,0) -> 0 | AM8: =IFERROR($W8/AA8-1,0) -> 0 | AN8: =IFERROR($W8/AB8-1,0) -> 0
A9: SALDO_FDP | C9: Refinanciado | D9: {=_xlfn.XLOOKUP(1, (INDIRECT("'"&$C$6&"'!$6:$6")=D$6)* (INDIRECT("'"&$C$6&"'!$5:$5")=D$5), INDIRECT("'"&$C$6&"'!"&ROW()&":"&ROW()) )} -> 0 | E9: {=_xlfn.XLOOKUP(1, (INDIRECT("'"&$C$6&"'!$6:$6")=E$6)* (INDIRECT("'"&$C$6&"'!$5:$5")=E$5), INDIRECT("'"&$C$6&"'!"&ROW()&":"&ROW()) )} -> 187857.74 | F9: {=_xlfn.XLOOKUP(1, (INDIRECT("'"&$C$6&"'!$6:$6")=F$6)* (INDIRECT("'"&$C$6&"'!$5:$5")=F$5), INDIRECT("'"&$C$6&"'!"&ROW()&":"&ROW()) )} -> 0 | G9: {=_xlfn.XLOOKUP(1, (INDIRECT("'"&$C$6&"'!$6:$6")=G$6)* (INDIRECT("'"&$C$6&"'!$5:$5")=G$5), INDIRECT("'"&$C$6&"'!"&ROW()&":"&ROW()) )} -> 0 | H9: {=_xlfn.XLOOKUP(1, (INDIRECT("'"&$C$6&"'!$6:$6")=H$6)* (INDIRECT("'"&$C$6&"'!$5:$5")=H$5), INDIRECT("'"&$C$6&"'!"&ROW()&":"&ROW()) )} -> 0 | I9: {=_xlfn.XLOOKUP(1, (INDIRECT("'"&$C$6&"'!$6:$6")=I$6)* (INDIRECT("'"&$C$6&"'!$5:$5")=I$5), INDIRECT("'"&$C$6&"'!"&ROW()&":"&ROW()) )} -> 0 | K9: =$D9-E9 -> -187857.74 | L9: =$D9-F9 -> 0 | M9: =$D9-G9 -> 0 | N9: =$D9-H9 -> 0 | O9: =$D9-I9 -> 0 | Q9: =IFERROR($D9/E9-1,0) -> -1 | R9: =IFERROR($D9/F9-1,0) -> 0 | S9: =IFERROR($D9/G9-1,0) -> 0 | T9: =IFERROR($D9/H9-1,0) -> 0 | U9: =IFERROR($D9/I9-1,0) -> 0 | W9: {=INDIRECT("'"&$C$6&"'!"&ADDRESS(ROW(),COLUMN()+44))} -> 0 | X9: {=INDIRECT("'"&$C$6&"'!"&ADDRESS(ROW(),COLUMN()+44))} -> 187857.74 | Y9: {=INDIRECT("'"&$C$6&"'!"&ADDRESS(ROW(),COLUMN()+44))} -> 0 | Z9: {=INDIRECT("'"&$C$6&"'!"&ADDRESS(ROW(),COLUMN()+44))} -> 0 | AA9: {=INDIRECT("'"&$C$6&"'!"&ADDRESS(ROW(),COLUMN()+44))} -> 0 | AB9: {=INDIRECT("'"&$C$6&"'!"&ADDRESS(ROW(),COLUMN()+44))} -> 0 | AD9: =$W9-X9 -> -187857.74 | AE9: =$W9-Y9 -> 0 | AF9: =$W9-Z9 -> 0 | AG9: =$W9-AA9 -> 0 | AH9: =$W9-AB9 -> 0 | AJ9: =IFERROR($W9/X9-1,0) -> -1 | AK9: =IFERROR($W9/Y9-1,0) -> 0 | AL9: =IFERROR($W9/Z9-1,0) -> 0 | AM9: =IFERROR($W9/AA9-1,0) -> 0 | AN9: =IFERROR($W9/AB9-1,0) -> 0
A10: SALDO_FDP | C10: Vencido y Judicial | D10: {=_xlfn.XLOOKUP(1, (INDIRECT("'"&$C$6&"'!$6:$6")=D$6)* (INDIRECT("'"&$C$6&"'!$5:$5")=D$5), INDIRECT("'"&$C$6&"'!"&ROW()&":"&ROW()) )} -> 0 | E10: {=_xlfn.XLOOKUP(1, (INDIRECT("'"&$C$6&"'!$6:$6")=E$6)* (INDIRECT("'"&$C$6&"'!$5:$5")=E$5), INDIRECT("'"&$C$6&"'!"&ROW()&":"&ROW()) )} -> 242951.26 | F10: {=_xlfn.XLOOKUP(1, (INDIRECT("'"&$C$6&"'!$6:$6")=F$6)* (INDIRECT("'"&$C$6&"'!$5:$5")=F$5), INDIRECT("'"&$C$6&"'!"&ROW()&":"&ROW()) )} -> 0 | G10: {=_xlfn.XLOOKUP(1, (INDIRECT("'"&$C$6&"'!$6:$6")=G$6)* (INDIRECT("'"&$C$6&"'!$5:$5")=G$5), INDIRECT("'"&$C$6&"'!"&ROW()&":"&ROW()) )} -> 0 | H10: {=_xlfn.XLOOKUP(1, (INDIRECT("'"&$C$6&"'!$6:$6")=H$6)* (INDIRECT("'"&$C$6&"'!$5:$5")=H$5), INDIRECT("'"&$C$6&"'!"&ROW()&":"&ROW()) )} -> 0 | I10: {=_xlfn.XLOOKUP(1, (INDIRECT("'"&$C$6&"'!$6:$6")=I$6)* (INDIRECT("'"&$C$6&"'!$5:$5")=I$5), INDIRECT("'"&$C$6&"'!"&ROW()&":"&ROW()) )} -> 0 | K10: =$D10-E10 -> -242951.26 | L10: =$D10-F10 -> 0 | M10: =$D10-G10 -> 0 | N10: =$D10-H10 -> 0 | O10: =$D10-I10 -> 0 | Q10: =IFERROR($D10/E10-1,0) -> -1 | R10: =IFERROR($D10/F10-1,0) -> 0 | S10: =IFERROR($D10/G10-1,0) -> 0 | T10: =IFERROR($D10/H10-1,0) -> 0 | U10: =IFERROR($D10/I10-1,0) -> 0 | W10: {=INDIRECT("'"&$C$6&"'!"&ADDRESS(ROW(),COLUMN()+44))} -> 0 | X10: {=INDIRECT("'"&$C$6&"'!"&ADDRESS(ROW(),COLUMN()+44))} -> 242951.26 | Y10: {=INDIRECT("'"&$C$6&"'!"&ADDRESS(ROW(),COLUMN()+44))} -> 0 | Z10: {=INDIRECT("'"&$C$6&"'!"&ADDRESS(ROW(),COLUMN()+44))} -> 0 | AA10: {=INDIRECT("'"&$C$6&"'!"&ADDRESS(ROW(),COLUMN()+44))} -> 0 | AB10: {=INDIRECT("'"&$C$6&"'!"&ADDRESS(ROW(),COLUMN()+44))} -> 0 | AD10: =$W10-X10 -> -242951.26 | AE10: =$W10-Y10 -> 0 | AF10: =$W10-Z10 -> 0 | AG10: =$W10-AA10 -> 0 | AH10: =$W10-AB10 -> 0 | AJ10: =IFERROR($W10/X10-1,0) -> -1 | AK10: =IFERROR($W10/Y10-1,0) -> 0 | AL10: =IFERROR($W10/Z10-1,0) -> 0 | AM10: =IFERROR($W10/AA10-1,0) -> 0 | AN10: =IFERROR($W10/AB10-1,0) -> 0
C11: Saldo FdP | D11: =SUM(D8:D10) -> 0 | E11: =SUM(E8:E10) -> 5906591.9 | F11: =SUM(F8:F10) -> 0 | G11: =SUM(G8:G10) -> 0 | H11: =SUM(H8:H10) -> 0 | I11: =SUM(I8:I10) -> 0 | K11: =$D11-E11 -> -5906591.9 | L11: =$D11-F11 -> 0 | M11: =$D11-G11 -> 0 | N11: =$D11-H11 -> 0 | O11: =$D11-I11 -> 0 | Q11: =IFERROR($D11/E11-1,0) -> -1 | R11: =IFERROR($D11/F11-1,0) -> 0 | S11: =IFERROR($D11/G11-1,0) -> 0 | T11: =IFERROR($D11/H11-1,0) -> 0 | U11: =IFERROR($D11/I11-1,0) -> 0 | W11: =SUM(W8:W10) -> 0 | X11: =SUM(X8:X10) -> 5906591.9 | Y11: =SUM(Y8:Y10) -> 0 | Z11: =SUM(Z8:Z10) -> 0 | AA11: =SUM(AA8:AA10) -> 0 | AB11: =SUM(AB8:AB10) -> 0 | AD11: =$W11-X11 -> -5906591.9 | AE11: =$W11-Y11 -> 0 | AF11: =$W11-Z11 -> 0 | AG11: =$W11-AA11 -> 0 | AH11: =$W11-AB11 -> 0 | AJ11: =IFERROR($W11/X11-1,0) -> -1 | AK11: =IFERROR($W11/Y11-1,0) -> 0 | AL11: =IFERROR($W11/Z11-1,0) -> 0 | AM11: =IFERROR($W11/AA11-1,0) -> 0 | AN11: =IFERROR($W11/AB11-1,0) -> 0
A14: SALDO_PROM | C14: Vigente | D14: {=_xlfn.XLOOKUP(1, (INDIRECT("'"&$C$6&"'!$6:$6")=D$6)* (INDIRECT("'"&$C$6&"'!$5:$5")=D$5), INDIRECT("'"&$C$6&"'!"&ROW()&":"&ROW()) )} -> 0 | E14: {=_xlfn.XLOOKUP(1, (INDIRECT("'"&$C$6&"'!$6:$6")=E$6)* (INDIRECT("'"&$C$6&"'!$5:$5")=E$5), INDIRECT("'"&$C$6&"'!"&ROW()&":"&ROW()) )} -> 5396941.1 | F14: {=_xlfn.XLOOKUP(1, (INDIRECT("'"&$C$6&"'!$6:$6")=F$6)* (INDIRECT("'"&$C$6&"'!$5:$5")=F$5), INDIRECT("'"&$C$6&"'!"&ROW()&":"&ROW()) )} -> 0 | G14: {=_xlfn.XLOOKUP(1, (INDIRECT("'"&$C$6&"'!$6:$6")=G$6)* (INDIRECT("'"&$C$6&"'!$5:$5")=G$5), INDIRECT("'"&$C$6&"'!"&ROW()&":"&ROW()) )} -> 0 | H14: {=_xlfn.XLOOKUP(1, (INDIRECT("'"&$C$6&"'!$6:$6")=H$6)* (INDIRECT("'"&$C$6&"'!$5:$5")=H$5), INDIRECT("'"&$C$6&"'!"&ROW()&":"&ROW()) )} -> 0 | I14: {=_xlfn.XLOOKUP(1, (INDIRECT("'"&$C$6&"'!$6:$6")=I$6)* (INDIRECT("'"&$C$6&"'!$5:$5")=I$5), INDIRECT("'"&$C$6&"'!"&ROW()&":"&ROW()) )} -> 0 | K14: =$D14-E14 -> -5396941.1 | L14: =$D14-F14 -> 0 | M14: =$D14-G14 -> 0 | N14: =$D14-H14 -> 0 | O14: =$D14-I14 -> 0 | Q14: =IFERROR($D14/E14-1,0) -> -1 | R14: =IFERROR($D14/F14-1,0) -> 0 | S14: =IFERROR($D14/G14-1,0) -> 0 | T14: =IFERROR($D14/H14-1,0) -> 0 | U14: =IFERROR($D14/I14-1,0) -> 0 | W14: {=INDIRECT("'"&$C$6&"'!"&ADDRESS(ROW(),COLUMN()+44))} -> 0 | X14: {=INDIRECT("'"&$C$6&"'!"&ADDRESS(ROW(),COLUMN()+44))} -> 5394716 | Y14: {=INDIRECT("'"&$C$6&"'!"&ADDRESS(ROW(),COLUMN()+44))} -> 0 | Z14: {=INDIRECT("'"&$C$6&"'!"&ADDRESS(ROW(),COLUMN()+44))} -> 0 | AA14: {=INDIRECT("'"&$C$6&"'!"&ADDRESS(ROW(),COLUMN()+44))} -> 0 | AB14: {=INDIRECT("'"&$C$6&"'!"&ADDRESS(ROW(),COLUMN()+44))} -> 0 | AD14: =$W14-X14 -> -5394716 | AE14: =$W14-Y14 -> 0 | AF14: =$W14-Z14 -> 0 | AG14: =$W14-AA14 -> 0 | AH14: =$W14-AB14 -> 0 | AJ14: =IFERROR($W14/X14-1,0) -> -1 | AK14: =IFERROR($W14/Y14-1,0) -> 0 | AL14: =IFERROR($W14/Z14-1,0) -> 0 | AM14: =IFERROR($W14/AA14-1,0) -> 0 | AN14: =IFERROR($W14/AB14-1,0) -> 0
A15: SALDO_PROM | C15: Refinanciado | D15: {=_xlfn.XLOOKUP(1, (INDIRECT("'"&$C$6&"'!$6:$6")=D$6)* (INDIRECT("'"&$C$6&"'!$5:$5")=D$5), INDIRECT("'"&$C$6&"'!"&ROW()&":"&ROW()) )} -> 0 | E15: {=_xlfn.XLOOKUP(1, (INDIRECT("'"&$C$6&"'!$6:$6")=E$6)* (INDIRECT("'"&$C$6&"'!$5:$5")=E$5), INDIRECT("'"&$C$6&"'!"&ROW()&":"&ROW()) )} -> 182009.82 | F15: {=_xlfn.XLOOKUP(1, (INDIRECT("'"&$C$6&"'!$6:$6")=F$6)* (INDIRECT("'"&$C$6&"'!$5:$5")=F$5), INDIRECT("'"&$C$6&"'!"&ROW()&":"&ROW()) )} -> 0 | G15: {=_xlfn.XLOOKUP(1, (INDIRECT("'"&$C$6&"'!$6:$6")=G$6)* (INDIRECT("'"&$C$6&"'!$5:$5")=G$5), INDIRECT("'"&$C$6&"'!"&ROW()&":"&ROW()) )} -> 0 | H15: {=_xlfn.XLOOKUP(1, (INDIRECT("'"&$C$6&"'!$6:$6")=H$6)* (INDIRECT("'"&$C$6&"'!$5:$5")=H$5), INDIRECT("'"&$C$6&"'!"&ROW()&":"&ROW()) )} -> 0 | I15: {=_xlfn.XLOOKUP(1, (INDIRECT("'"&$C$6&"'!$6:$6")=I$6)* (INDIRECT("'"&$C$6&"'!$5:$5")=I$5), INDIRECT("'"&$C$6&"'!"&ROW()&":"&ROW()) )} -> 0 | K15: =$D15-E15 -> -182009.82 | L15: =$D15-F15 -> 0 | M15: =$D15-G15 -> 0 | N15: =$D15-H15 -> 0 | O15: =$D15-I15 -> 0 | Q15: =IFERROR($D15/E15-1,0) -> -1 | R15: =IFERROR($D15/F15-1,0) -> 0 | S15: =IFERROR($D15/G15-1,0) -> 0 | T15: =IFERROR($D15/H15-1,0) -> 0 | U15: =IFERROR($D15/I15-1,0) -> 0 | W15: {=INDIRECT("'"&$C$6&"'!"&ADDRESS(ROW(),COLUMN()+44))} -> 0 | X15: {=INDIRECT("'"&$C$6&"'!"&ADDRESS(ROW(),COLUMN()+44))} -> 183585.17 | Y15: {=INDIRECT("'"&$C$6&"'!"&ADDRESS(ROW(),COLUMN()+44))} -> 0 | Z15: {=INDIRECT("'"&$C$6&"'!"&ADDRESS(ROW(),COLUMN()+44))} -> 0 | AA15: {=INDIRECT("'"&$C$6&"'!"&ADDRESS(ROW(),COLUMN()+44))} -> 0 | AB15: {=INDIRECT("'"&$C$6&"'!"&ADDRESS(ROW(),COLUMN()+44))} -> 0 | AD15: =$W15-X15 -> -183585.17 | AE15: =$W15-Y15 -> 0 | AF15: =$W15-Z15 -> 0 | AG15: =$W15-AA15 -> 0 | AH15: =$W15-AB15 -> 0 | AJ15: =IFERROR($W15/X15-1,0) -> -1 | AK15: =IFERROR($W15/Y15-1,0) -> 0 | AL15: =IFERROR($W15/Z15-1,0) -> 0 | AM15: =IFERROR($W15/AA15-1,0) -> 0 | AN15: =IFERROR($W15/AB15-1,0) -> 0
A16: SALDO_PROM | C16: Vencido y Judicial | D16: {=_xlfn.XLOOKUP(1, (INDIRECT("'"&$C$6&"'!$6:$6")=D$6)* (INDIRECT("'"&$C$6&"'!$5:$5")=D$5), INDIRECT("'"&$C$6&"'!"&ROW()&":"&ROW()) )} -> 0 | E16: {=_xlfn.XLOOKUP(1, (INDIRECT("'"&$C$6&"'!$6:$6")=E$6)* (INDIRECT("'"&$C$6&"'!$5:$5")=E$5), INDIRECT("'"&$C$6&"'!"&ROW()&":"&ROW()) )} -> 271222.21 | F16: {=_xlfn.XLOOKUP(1, (INDIRECT("'"&$C$6&"'!$6:$6")=F$6)* (INDIRECT("'"&$C$6&"'!$5:$5")=F$5), INDIRECT("'"&$C$6&"'!"&ROW()&":"&ROW()) )} -> 0 | G16: {=_xlfn.XLOOKUP(1, (INDIRECT("'"&$C$6&"'!$6:$6")=G$6)* (INDIRECT("'"&$C$6&"'!$5:$5")=G$5), INDIRECT("'"&$C$6&"'!"&ROW()&":"&ROW()) )} -> 0 | H16: {=_xlfn.XLOOKUP(1, (INDIRECT("'"&$C$6&"'!$6:$6")=H$6)* (INDIRECT("'"&$C$6&"'!$5:$5")=H$5), INDIRECT("'"&$C$6&"'!"&ROW()&":"&ROW()) )} -> 0 | I16: {=_xlfn.XLOOKUP(1, (INDIRECT("'"&$C$6&"'!$6:$6")=I$6)* (INDIRECT("'"&$C$6&"'!$5:$5")=I$5), INDIRECT("'"&$C$6&"'!"&ROW()&":"&ROW()) )} -> 0 | K16: =$D16-E16 -> -271222.21 | L16: =$D16-F16 -> 0 | M16: =$D16-G16 -> 0 | N16: =$D16-H16 -> 0 | O16: =$D16-I16 -> 0 | Q16: =IFERROR($D16/E16-1,0) -> -1 | R16: =IFERROR($D16/F16-1,0) -> 0 | S16: =IFERROR($D16/G16-1,0) -> 0 | T16: =IFERROR($D16/H16-1,0) -> 0 | U16: =IFERROR($D16/I16-1,0) -> 0 | W16: {=INDIRECT("'"&$C$6&"'!"&ADDRESS(ROW(),COLUMN()+44))} -> 0 | X16: {=INDIRECT("'"&$C$6&"'!"&ADDRESS(ROW(),COLUMN()+44))} -> 269886.41 | Y16: {=INDIRECT("'"&$C$6&"'!"&ADDRESS(ROW(),COLUMN()+44))} -> 0 | Z16: {=INDIRECT("'"&$C$6&"'!"&ADDRESS(ROW(),COLUMN()+44))} -> 0 | AA16: {=INDIRECT("'"&$C$6&"'!"&ADDRESS(ROW(),COLUMN()+44))} -> 0 | AB16: {=INDIRECT("'"&$C$6&"'!"&ADDRESS(ROW(),COLUMN()+44))} -> 0 | AD16: =$W16-X16 -> -269886.41 | AE16: =$W16-Y16 -> 0 | AF16: =$W16-Z16 -> 0 | AG16: =$W16-AA16 -> 0 | AH16: =$W16-AB16 -> 0 | AJ16: =IFERROR($W16/X16-1,0) -> -1 | AK16: =IFERROR($W16/Y16-1,0) -> 0 | AL16: =IFERROR($W16/Z16-1,0) -> 0 | AM16: =IFERROR($W16/AA16-1,0) -> 0 | AN16: =IFERROR($W16/AB16-1,0) -> 0
C17: Saldo Prom | D17: =SUM(D14:D16) -> 0 | E17: =SUM(E14:E16) -> 5850173.1 | F17: =SUM(F14:F16) -> 0 | G17: =SUM(G14:G16) -> 0 | H17: =SUM(H14:H16) -> 0 | I17: =SUM(I14:I16) -> 0 | K17: =$D17-E17 -> -5850173.1 | L17: =$D17-F17 -> 0 | M17: =$D17-G17 -> 0 | N17: =$D17-H17 -> 0 | O17: =$D17-I17 -> 0 | Q17: =IFERROR($D17/E17-1,0) -> -1 | R17: =IFERROR($D17/F17-1,0) -> 0 | S17: =IFERROR($D17/G17-1,0) -> 0 | T17: =IFERROR($D17/H17-1,0) -> 0 | U17: =IFERROR($D17/I17-1,0) -> 0 | W17: =SUM(W14:W16) -> 0 | X17: =SUM(X14:X16) -> 5848187.6 | Y17: =SUM(Y14:Y16) -> 0 | Z17: =SUM(Z14:Z16) -> 0 | AA17: =SUM(AA14:AA16) -> 0 | AB17: =SUM(AB14:AB16) -> 0 | AD17: =$W17-X17 -> -5848187.6 | AE17: =$W17-Y17 -> 0 | AF17: =$W17-Z17 -> 0 | AG17: =$W17-AA17 -> 0 | AH17: =$W17-AB17 -> 0 | AJ17: =IFERROR($W17/X17-1,0) -> -1 | AK17: =IFERROR($W17/Y17-1,0) -> 0 | AL17: =IFERROR($W17/Z17-1,0) -> 0 | AM17: =IFERROR($W17/AA17-1,0) -> 0 | AN17: =IFERROR($W17/AB17-1,0) -> 0
C20: Vigente | D20: =IFERROR(((1+D38/D14)^(360/D$3))-1,0) -> 0 | E20: =IFERROR(((1+E38/E14)^(360/E$3))-1,0) -> 0.26524722 | F20: =IFERROR(((1+F38/F14)^(360/F$3))-1,0) -> 0 | G20: =IFERROR(((1+G38/G14)^(360/G$3))-1,0) -> 0 | H20: =IFERROR(((1+H38/H14)^(360/H$3))-1,0) -> 0 | I20: =IFERROR(((1+I38/I14)^(360/I$3))-1,0) -> 0 | Q20: =($D20-E20)*10000 -> -2652.4722 | R20: =($D20-F20)*10000 -> 0 | S20: =($D20-G20)*10000 -> 0 | T20: =($D20-H20)*10000 -> 0 | U20: =($D20-I20)*10000 -> 0 | W20: {=INDIRECT("'"&$C$6&"'!"&ADDRESS(ROW(),COLUMN()+44))} -> 0 | X20: {=INDIRECT("'"&$C$6&"'!"&ADDRESS(ROW(),COLUMN()+44))} -> 0.25696584 | Y20: {=INDIRECT("'"&$C$6&"'!"&ADDRESS(ROW(),COLUMN()+44))} -> 0 | Z20: {=INDIRECT("'"&$C$6&"'!"&ADDRESS(ROW(),COLUMN()+44))} -> 0 | AA20: {=INDIRECT("'"&$C$6&"'!"&ADDRESS(ROW(),COLUMN()+44))} -> 0 | AB20: {=INDIRECT("'"&$C$6&"'!"&ADDRESS(ROW(),COLUMN()+44))} -> 0 | AJ20: =($W20-X20)*10000 -> -2569.6584 | AK20: =($W20-Y20)*10000 -> 0 | AL20: =($W20-Z20)*10000 -> 0 | AM20: =($W20-AA20)*10000 -> 0 | AN20: =($W20-AB20)*10000 -> 0
C21: Refinanciado | D21: =IFERROR(((1+D39/D15)^(360/D$3))-1,0) -> 0 | E21: =IFERROR(((1+E39/E15)^(360/E$3))-1,0) -> 0.10621592 | F21: =IFERROR(((1+F39/F15)^(360/F$3))-1,0) -> 0 | G21: =IFERROR(((1+G39/G15)^(360/G$3))-1,0) -> 0 | H21: =IFERROR(((1+H39/H15)^(360/H$3))-1,0) -> 0 | I21: =IFERROR(((1+I39/I15)^(360/I$3))-1,0) -> 0 | Q21: =($D21-E21)*10000 -> -1062.1592 | R21: =($D21-F21)*10000 -> 0 | S21: =($D21-G21)*10000 -> 0 | T21: =($D21-H21)*10000 -> 0 | U21: =($D21-I21)*10000 -> 0 | W21: {=INDIRECT("'"&$C$6&"'!"&ADDRESS(ROW(),COLUMN()+44))} -> 0 | X21: {=INDIRECT("'"&$C$6&"'!"&ADDRESS(ROW(),COLUMN()+44))} -> 0.10616469 | Y21: {=INDIRECT("'"&$C$6&"'!"&ADDRESS(ROW(),COLUMN()+44))} -> 0 | Z21: {=INDIRECT("'"&$C$6&"'!"&ADDRESS(ROW(),COLUMN()+44))} -> 0 | AA21: {=INDIRECT("'"&$C$6&"'!"&ADDRESS(ROW(),COLUMN()+44))} -> 0 | AB21: {=INDIRECT("'"&$C$6&"'!"&ADDRESS(ROW(),COLUMN()+44))} -> 0 | AJ21: =($W21-X21)*10000 -> -1061.6469 | AK21: =($W21-Y21)*10000 -> 0 | AL21: =($W21-Z21)*10000 -> 0 | AM21: =($W21-AA21)*10000 -> 0 | AN21: =($W21-AB21)*10000 -> 0
C22: Vencido y Judicial | D22: =IFERROR(((1+D40/D16)^(360/D$3))-1,0) -> 0 | E22: =IFERROR(((1+E40/E16)^(360/E$3))-1,0) -> 0.185023 | F22: =IFERROR(((1+F40/F16)^(360/F$3))-1,0) -> 0 | G22: =IFERROR(((1+G40/G16)^(360/G$3))-1,0) -> 0 | H22: =IFERROR(((1+H40/H16)^(360/H$3))-1,0) -> 0 | I22: =IFERROR(((1+I40/I16)^(360/I$3))-1,0) -> 0 | Q22: =($D22-E22)*10000 -> -1850.23 | R22: =($D22-F22)*10000 -> 0 | S22: =($D22-G22)*10000 -> 0 | T22: =($D22-H22)*10000 -> 0 | U22: =($D22-I22)*10000 -> 0 | W22: {=INDIRECT("'"&$C$6&"'!"&ADDRESS(ROW(),COLUMN()+44))} -> 0 | X22: {=INDIRECT("'"&$C$6&"'!"&ADDRESS(ROW(),COLUMN()+44))} -> 0.20328197 | Y22: {=INDIRECT("'"&$C$6&"'!"&ADDRESS(ROW(),COLUMN()+44))} -> 0 | Z22: {=INDIRECT("'"&$C$6&"'!"&ADDRESS(ROW(),COLUMN()+44))} -> 0 | AA22: {=INDIRECT("'"&$C$6&"'!"&ADDRESS(ROW(),COLUMN()+44))} -> 0 | AB22: {=INDIRECT("'"&$C$6&"'!"&ADDRESS(ROW(),COLUMN()+44))} -> 0 | AJ22: =($W22-X22)*10000 -> -2032.8197 | AK22: =($W22-Y22)*10000 -> 0 | AL22: =($W22-Z22)*10000 -> 0 | AM22: =($W22-AA22)*10000 -> 0 | AN22: =($W22-AB22)*10000 -> 0
C23: Tasa Implicita | D23: =IFERROR(((1+D41/D17)^(360/D$3))-1,0) -> 0 | E23: =IFERROR(((1+E41/E17)^(360/E$3))-1,0) -> 0.25618833 | F23: =IFERROR(((1+F41/F17)^(360/F$3))-1,0) -> 0 | G23: =IFERROR(((1+G41/G17)^(360/G$3))-1,0) -> 0 | H23: =IFERROR(((1+H41/H17)^(360/H$3))-1,0) -> 0 | I23: =IFERROR(((1+I41/I17)^(360/I$3))-1,0) -> 0 | Q23: =($D23-E23)*10000 -> -2561.8833 | R23: =($D23-F23)*10000 -> 0 | S23: =($D23-G23)*10000 -> 0 | T23: =($D23-H23)*10000 -> 0 | U23: =($D23-I23)*10000 -> 0 | W23: {=INDIRECT("'"&$C$6&"'!"&ADDRESS(ROW(),COLUMN()+44))} -> 0 | X23: {=INDIRECT("'"&$C$6&"'!"&ADDRESS(ROW(),COLUMN()+44))} -> 0.24944315 | Y23: {=INDIRECT("'"&$C$6&"'!"&ADDRESS(ROW(),COLUMN()+44))} -> 0 | Z23: {=INDIRECT("'"&$C$6&"'!"&ADDRESS(ROW(),COLUMN()+44))} -> 0 | AA23: {=INDIRECT("'"&$C$6&"'!"&ADDRESS(ROW(),COLUMN()+44))} -> 0 | AB23: {=INDIRECT("'"&$C$6&"'!"&ADDRESS(ROW(),COLUMN()+44))} -> 0 | AJ23: =($W23-X23)*10000 -> -2494.4315 | AK23: =($W23-Y23)*10000 -> 0 | AL23: =($W23-Z23)*10000 -> 0 | AM23: =($W23-AA23)*10000 -> 0 | AN23: =($W23-AB23)*10000 -> 0
C26: Vigente | D26: =-IFERROR(((1-D44/D14)^(360/D$4))-1,0) -> 0 | E26: =-IFERROR(((1-E44/E14)^(360/E$4))-1,0) -> -0.049630555 | F26: =-IFERROR(((1-F44/F14)^(360/F$4))-1,0) -> 0 | G26: =-IFERROR(((1-G44/G14)^(360/G$4))-1,0) -> 0 | H26: =-IFERROR(((1-H44/H14)^(360/H$4))-1,0) -> 0 | I26: =-IFERROR(((1-I44/I14)^(360/I$4))-1,0) -> 0 | Q26: =($D26-E26)*10000 -> 496.30555 | R26: =($D26-F26)*10000 -> 0 | S26: =($D26-G26)*10000 -> 0 | T26: =($D26-H26)*10000 -> 0 | U26: =($D26-I26)*10000 -> 0 | W26: {=INDIRECT("'"&$C$6&"'!"&ADDRESS(ROW(),COLUMN()+44))} -> 0 | X26: {=INDIRECT("'"&$C$6&"'!"&ADDRESS(ROW(),COLUMN()+44))} -> -0.049891884 | Y26: {=INDIRECT("'"&$C$6&"'!"&ADDRESS(ROW(),COLUMN()+44))} -> 0 | Z26: {=INDIRECT("'"&$C$6&"'!"&ADDRESS(ROW(),COLUMN()+44))} -> 0 | AA26: {=INDIRECT("'"&$C$6&"'!"&ADDRESS(ROW(),COLUMN()+44))} -> 0 | AB26: {=INDIRECT("'"&$C$6&"'!"&ADDRESS(ROW(),COLUMN()+44))} -> 0 | AJ26: =($W26-X26)*10000 -> 498.91884 | AK26: =($W26-Y26)*10000 -> 0 | AL26: =($W26-Z26)*10000 -> 0 | AM26: =($W26-AA26)*10000 -> 0 | AN26: =($W26-AB26)*10000 -> 0
C27: Refinanciado | D27: =-IFERROR(((1-D45/D15)^(360/D$4))-1,0) -> 0 | E27: =-IFERROR(((1-E45/E15)^(360/E$4))-1,0) -> -0.050547378 | F27: =-IFERROR(((1-F45/F15)^(360/F$4))-1,0) -> 0 | G27: =-IFERROR(((1-G45/G15)^(360/G$4))-1,0) -> 0 | H27: =-IFERROR(((1-H45/H15)^(360/H$4))-1,0) -> 0 | I27: =-IFERROR(((1-I45/I15)^(360/I$4))-1,0) -> 0 | Q27: =($D27-E27)*10000 -> 505.47378 | R27: =($D27-F27)*10000 -> 0 | S27: =($D27-G27)*10000 -> 0 | T27: =($D27-H27)*10000 -> 0 | U27: =($D27-I27)*10000 -> 0 | W27: {=INDIRECT("'"&$C$6&"'!"&ADDRESS(ROW(),COLUMN()+44))} -> 0 | X27: {=INDIRECT("'"&$C$6&"'!"&ADDRESS(ROW(),COLUMN()+44))} -> -0.049363761 | Y27: {=INDIRECT("'"&$C$6&"'!"&ADDRESS(ROW(),COLUMN()+44))} -> 0 | Z27: {=INDIRECT("'"&$C$6&"'!"&ADDRESS(ROW(),COLUMN()+44))} -> 0 | AA27: {=INDIRECT("'"&$C$6&"'!"&ADDRESS(ROW(),COLUMN()+44))} -> 0 | AB27: {=INDIRECT("'"&$C$6&"'!"&ADDRESS(ROW(),COLUMN()+44))} -> 0 | AJ27: =($W27-X27)*10000 -> 493.63761 | AK27: =($W27-Y27)*10000 -> 0 | AL27: =($W27-Z27)*10000 -> 0 | AM27: =($W27-AA27)*10000 -> 0 | AN27: =($W27-AB27)*10000 -> 0
C28: Vencido y Judicial | D28: =-IFERROR(((1-D46/D16)^(360/D$4))-1,0) -> 0 | E28: =-IFERROR(((1-E46/E16)^(360/E$4))-1,0) -> -0.046641557 | F28: =-IFERROR(((1-F46/F16)^(360/F$4))-1,0) -> 0 | G28: =-IFERROR(((1-G46/G16)^(360/G$4))-1,0) -> 0 | H28: =-IFERROR(((1-H46/H16)^(360/H$4))-1,0) -> 0 | I28: =-IFERROR(((1-I46/I16)^(360/I$4))-1,0) -> 0 | Q28: =($D28-E28)*10000 -> 466.41557 | R28: =($D28-F28)*10000 -> 0 | S28: =($D28-G28)*10000 -> 0 | T28: =($D28-H28)*10000 -> 0 | U28: =($D28-I28)*10000 -> 0 | W28: {=INDIRECT("'"&$C$6&"'!"&ADDRESS(ROW(),COLUMN()+44))} -> 0 | X28: {=INDIRECT("'"&$C$6&"'!"&ADDRESS(ROW(),COLUMN()+44))} -> -0.047114159 | Y28: {=INDIRECT("'"&$C$6&"'!"&ADDRESS(ROW(),COLUMN()+44))} -> 0 | Z28: {=INDIRECT("'"&$C$6&"'!"&ADDRESS(ROW(),COLUMN()+44))} -> 0 | AA28: {=INDIRECT("'"&$C$6&"'!"&ADDRESS(ROW(),COLUMN()+44))} -> 0 | AB28: {=INDIRECT("'"&$C$6&"'!"&ADDRESS(ROW(),COLUMN()+44))} -> 0 | AJ28: =($W28-X28)*10000 -> 471.14159 | AK28: =($W28-Y28)*10000 -> 0 | AL28: =($W28-Z28)*10000 -> 0 | AM28: =($W28-AA28)*10000 -> 0 | AN28: =($W28-AB28)*10000 -> 0
C29: Tasa FTP | D29: =-IFERROR(((1-D47/D17)^(360/D$4))-1,0) -> 0 | E29: =-IFERROR(((1-E47/E17)^(360/E$4))-1,0) -> -0.049520319 | F29: =-IFERROR(((1-F47/F17)^(360/F$4))-1,0) -> 0 | G29: =-IFERROR(((1-G47/G17)^(360/G$4))-1,0) -> 0 | H29: =-IFERROR(((1-H47/H17)^(360/H$4))-1,0) -> 0 | I29: =-IFERROR(((1-I47/I17)^(360/I$4))-1,0) -> 0 | Q29: =($D29-E29)*10000 -> 495.20319 | R29: =($D29-F29)*10000 -> 0 | S29: =($D29-G29)*10000 -> 0 | T29: =($D29-H29)*10000 -> 0 | U29: =($D29-I29)*10000 -> 0 | W29: {=INDIRECT("'"&$C$6&"'!"&ADDRESS(ROW(),COLUMN()+44))} -> 0 | X29: {=INDIRECT("'"&$C$6&"'!"&ADDRESS(ROW(),COLUMN()+44))} -> -0.049746966 | Y29: {=INDIRECT("'"&$C$6&"'!"&ADDRESS(ROW(),COLUMN()+44))} -> 0 | Z29: {=INDIRECT("'"&$C$6&"'!"&ADDRESS(ROW(),COLUMN()+44))} -> 0 | AA29: {=INDIRECT("'"&$C$6&"'!"&ADDRESS(ROW(),COLUMN()+44))} -> 0 | AB29: {=INDIRECT("'"&$C$6&"'!"&ADDRESS(ROW(),COLUMN()+44))} -> 0 | AJ29: =($W29-X29)*10000 -> 497.46966 | AK29: =($W29-Y29)*10000 -> 0 | AL29: =($W29-Z29)*10000 -> 0 | AM29: =($W29-AA29)*10000 -> 0 | AN29: =($W29-AB29)*10000 -> 0
C32: Vigente | D32: =D20+D26 -> 0 | E32: =E20+E26 -> 0.21561667 | F32: =F20+F26 -> 0 | G32: =G20+G26 -> 0 | H32: =H20+H26 -> 0 | I32: =I20+I26 -> 0 | Q32: =($D32-E32)*10000 -> -2156.1667 | R32: =($D32-F32)*10000 -> 0 | S32: =($D32-G32)*10000 -> 0 | T32: =($D32-H32)*10000 -> 0 | U32: =($D32-I32)*10000 -> 0 | W32: =W20+W26 -> 0 | X32: =X20+X26 -> 0.20707396 | Y32: =Y20+Y26 -> 0 | Z32: =Z20+Z26 -> 0 | AA32: =AA20+AA26 -> 0 | AB32: =AB20+AB26 -> 0 | AJ32: =($W32-X32)*10000 -> -2070.7396 | AK32: =($W32-Y32)*10000 -> 0 | AL32: =($W32-Z32)*10000 -> 0 | AM32: =($W32-AA32)*10000 -> 0 | AN32: =($W32-AB32)*10000 -> 0
C33: Refinanciado | D33: =D21+D27 -> 0 | E33: =E21+E27 -> 0.055668542 | F33: =F21+F27 -> 0 | G33: =G21+G27 -> 0 | H33: =H21+H27 -> 0 | I33: =I21+I27 -> 0 | Q33: =($D33-E33)*10000 -> -556.68542 | R33: =($D33-F33)*10000 -> 0 | S33: =($D33-G33)*10000 -> 0 | T33: =($D33-H33)*10000 -> 0 | U33: =($D33-I33)*10000 -> 0 | W33: =W21+W27 -> 0 | X33: =X21+X27 -> 0.05680093 | Y33: =Y21+Y27 -> 0 | Z33: =Z21+Z27 -> 0 | AA33: =AA21+AA27 -> 0 | AB33: =AB21+AB27 -> 0 | AJ33: =($W33-X33)*10000 -> -568.0093 | AK33: =($W33-Y33)*10000 -> 0 | AL33: =($W33-Z33)*10000 -> 0 | AM33: =($W33-AA33)*10000 -> 0 | AN33: =($W33-AB33)*10000 -> 0
C34: Vencido y Judicial | D34: =D22+D28 -> 0 | E34: =E22+E28 -> 0.13838144 | F34: =F22+F28 -> 0 | G34: =G22+G28 -> 0 | H34: =H22+H28 -> 0 | I34: =I22+I28 -> 0 | Q34: =($D34-E34)*10000 -> -1383.8144 | R34: =($D34-F34)*10000 -> 0 | S34: =($D34-G34)*10000 -> 0 | T34: =($D34-H34)*10000 -> 0 | U34: =($D34-I34)*10000 -> 0 | W34: =W22+W28 -> 0 | X34: =X22+X28 -> 0.15616781 | Y34: =Y22+Y28 -> 0 | Z34: =Z22+Z28 -> 0 | AA34: =AA22+AA28 -> 0 | AB34: =AB22+AB28 -> 0 | AJ34: =($W34-X34)*10000 -> -1561.6781 | AK34: =($W34-Y34)*10000 -> 0 | AL34: =($W34-Z34)*10000 -> 0 | AM34: =($W34-AA34)*10000 -> 0 | AN34: =($W34-AB34)*10000 -> 0
C35: Spread | D35: =D23+D29 -> 0 | E35: =E23+E29 -> 0.20666801 | F35: =F23+F29 -> 0 | G35: =G23+G29 -> 0 | H35: =H23+H29 -> 0 | I35: =I23+I29 -> 0 | Q35: =($D35-E35)*10000 -> -2066.6801 | R35: =($D35-F35)*10000 -> 0 | S35: =($D35-G35)*10000 -> 0 | T35: =($D35-H35)*10000 -> 0 | U35: =($D35-I35)*10000 -> 0 | W35: =W23+W29 -> 0 | X35: =X23+X29 -> 0.19969618 | Y35: =Y23+Y29 -> 0 | Z35: =Z23+Z29 -> 0 | AA35: =AA23+AA29 -> 0 | AB35: =AB23+AB29 -> 0 | AJ35: =($W35-X35)*10000 -> -1996.9618 | AK35: =($W35-Y35)*10000 -> 0 | AL35: =($W35-Z35)*10000 -> 0 | AM35: =($W35-AA35)*10000 -> 0 | AN35: =($W35-AB35)*10000 -> 0
A38: Ingreso_Financiero | C38: Vigente | D38: {=_xlfn.XLOOKUP(1, (INDIRECT("'"&$C$6&"'!$6:$6")=D$6)* (INDIRECT("'"&$C$6&"'!$5:$5")=D$5), INDIRECT("'"&$C$6&"'!"&ROW()&":"&ROW()) )} -> 0 | E38: {=_xlfn.XLOOKUP(1, (INDIRECT("'"&$C$6&"'!$6:$6")=E$6)* (INDIRECT("'"&$C$6&"'!$5:$5")=E$5), INDIRECT("'"&$C$6&"'!"&ROW()&":"&ROW()) )} -> 110452.49 | F38: {=_xlfn.XLOOKUP(1, (INDIRECT("'"&$C$6&"'!$6:$6")=F$6)* (INDIRECT("'"&$C$6&"'!$5:$5")=F$5), INDIRECT("'"&$C$6&"'!"&ROW()&":"&ROW()) )} -> 0 | G38: {=_xlfn.XLOOKUP(1, (INDIRECT("'"&$C$6&"'!$6:$6")=G$6)* (INDIRECT("'"&$C$6&"'!$5:$5")=G$5), INDIRECT("'"&$C$6&"'!"&ROW()&":"&ROW()) )} -> 0 | H38: {=_xlfn.XLOOKUP(1, (INDIRECT("'"&$C$6&"'!$6:$6")=H$6)* (INDIRECT("'"&$C$6&"'!$5:$5")=H$5), INDIRECT("'"&$C$6&"'!"&ROW()&":"&ROW()) )} -> 0 | I38: {=_xlfn.XLOOKUP(1, (INDIRECT("'"&$C$6&"'!$6:$6")=I$6)* (INDIRECT("'"&$C$6&"'!$5:$5")=I$5), INDIRECT("'"&$C$6&"'!"&ROW()&":"&ROW()) )} -> 0 | K38: =$D38-E38 -> -110452.49 | L38: =$D38-F38 -> 0 | M38: =$D38-G38 -> 0 | N38: =$D38-H38 -> 0 | O38: =$D38-I38 -> 0 | Q38: =IFERROR($D38/E38-1,0) -> -1 | R38: =IFERROR($D38/F38-1,0) -> 0 | S38: =IFERROR($D38/G38-1,0) -> 0 | T38: =IFERROR($D38/H38-1,0) -> 0 | U38: =IFERROR($D38/I38-1,0) -> 0 | W38: {=INDIRECT("'"&$C$6&"'!"&ADDRESS(ROW(),COLUMN()+44))} -> 0 | X38: {=INDIRECT("'"&$C$6&"'!"&ADDRESS(ROW(),COLUMN()+44))} -> 311401.9 | Y38: {=INDIRECT("'"&$C$6&"'!"&ADDRESS(ROW(),COLUMN()+44))} -> 0 | Z38: {=INDIRECT("'"&$C$6&"'!"&ADDRESS(ROW(),COLUMN()+44))} -> 0 | AA38: {=INDIRECT("'"&$C$6&"'!"&ADDRESS(ROW(),COLUMN()+44))} -> 0 | AB38: {=INDIRECT("'"&$C$6&"'!"&ADDRESS(ROW(),COLUMN()+44))} -> 0 | AD38: =$W38-X38 -> -311401.9 | AE38: =$W38-Y38 -> 0 | AF38: =$W38-Z38 -> 0 | AG38: =$W38-AA38 -> 0 | AH38: =$W38-AB38 -> 0 | AJ38: =IFERROR($W38/X38-1,0) -> -1 | AK38: =IFERROR($W38/Y38-1,0) -> 0 | AL38: =IFERROR($W38/Z38-1,0) -> 0 | AM38: =IFERROR($W38/AA38-1,0) -> 0 | AN38: =IFERROR($W38/AB38-1,0) -> 0
A39: Ingreso_Financiero | C39: Refinanciado | D39: {=_xlfn.XLOOKUP(1, (INDIRECT("'"&$C$6&"'!$6:$6")=D$6)* (INDIRECT("'"&$C$6&"'!$5:$5")=D$5), INDIRECT("'"&$C$6&"'!"&ROW()&":"&ROW()) )} -> 0 | E39: {=_xlfn.XLOOKUP(1, (INDIRECT("'"&$C$6&"'!$6:$6")=E$6)* (INDIRECT("'"&$C$6&"'!$5:$5")=E$5), INDIRECT("'"&$C$6&"'!"&ROW()&":"&ROW()) )} -> 1589.0159 | F39: {=_xlfn.XLOOKUP(1, (INDIRECT("'"&$C$6&"'!$6:$6")=F$6)* (INDIRECT("'"&$C$6&"'!$5:$5")=F$5), INDIRECT("'"&$C$6&"'!"&ROW()&":"&ROW()) )} -> 0 | G39: {=_xlfn.XLOOKUP(1, (INDIRECT("'"&$C$6&"'!$6:$6")=G$6)* (INDIRECT("'"&$C$6&"'!$5:$5")=G$5), INDIRECT("'"&$C$6&"'!"&ROW()&":"&ROW()) )} -> 0 | H39: {=_xlfn.XLOOKUP(1, (INDIRECT("'"&$C$6&"'!$6:$6")=H$6)* (INDIRECT("'"&$C$6&"'!$5:$5")=H$5), INDIRECT("'"&$C$6&"'!"&ROW()&":"&ROW()) )} -> 0 | I39: {=_xlfn.XLOOKUP(1, (INDIRECT("'"&$C$6&"'!$6:$6")=I$6)* (INDIRECT("'"&$C$6&"'!$5:$5")=I$5), INDIRECT("'"&$C$6&"'!"&ROW()&":"&ROW()) )} -> 0 | K39: =$D39-E39 -> -1589.0159 | L39: =$D39-F39 -> 0 | M39: =$D39-G39 -> 0 | N39: =$D39-H39 -> 0 | O39: =$D39-I39 -> 0 | Q39: =IFERROR($D39/E39-1,0) -> -1 | R39: =IFERROR($D39/F39-1,0) -> 0 | S39: =IFERROR($D39/G39-1,0) -> 0 | T39: =IFERROR($D39/H39-1,0) -> 0 | U39: =IFERROR($D39/I39-1,0) -> 0 | W39: {=INDIRECT("'"&$C$6&"'!"&ADDRESS(ROW(),COLUMN()+44))} -> 0 | X39: {=INDIRECT("'"&$C$6&"'!"&ADDRESS(ROW(),COLUMN()+44))} -> 4650.4042 | Y39: {=INDIRECT("'"&$C$6&"'!"&ADDRESS(ROW(),COLUMN()+44))} -> 0 | Z39: {=INDIRECT("'"&$C$6&"'!"&ADDRESS(ROW(),COLUMN()+44))} -> 0 | AA39: {=INDIRECT("'"&$C$6&"'!"&ADDRESS(ROW(),COLUMN()+44))} -> 0 | AB39: {=INDIRECT("'"&$C$6&"'!"&ADDRESS(ROW(),COLUMN()+44))} -> 0 | AD39: =$W39-X39 -> -4650.4042 | AE39: =$W39-Y39 -> 0 | AF39: =$W39-Z39 -> 0 | AG39: =$W39-AA39 -> 0 | AH39: =$W39-AB39 -> 0 | AJ39: =IFERROR($W39/X39-1,0) -> -1 | AK39: =IFERROR($W39/Y39-1,0) -> 0 | AL39: =IFERROR($W39/Z39-1,0) -> 0 | AM39: =IFERROR($W39/AA39-1,0) -> 0 | AN39: =IFERROR($W39/AB39-1,0) -> 0
A40: Ingreso_Financiero | C40: Vencido y Judicial | D40: {=_xlfn.XLOOKUP(1, (INDIRECT("'"&$C$6&"'!$6:$6")=D$6)* (INDIRECT("'"&$C$6&"'!$5:$5")=D$5), INDIRECT("'"&$C$6&"'!"&ROW()&":"&ROW()) )} -> 0 | E40: {=_xlfn.XLOOKUP(1, (INDIRECT("'"&$C$6&"'!$6:$6")=E$6)* (INDIRECT("'"&$C$6&"'!$5:$5")=E$5), INDIRECT("'"&$C$6&"'!"&ROW()&":"&ROW()) )} -> 3993.9591 | F40: {=_xlfn.XLOOKUP(1, (INDIRECT("'"&$C$6&"'!$6:$6")=F$6)* (INDIRECT("'"&$C$6&"'!$5:$5")=F$5), INDIRECT("'"&$C$6&"'!"&ROW()&":"&ROW()) )} -> 0 | G40: {=_xlfn.XLOOKUP(1, (INDIRECT("'"&$C$6&"'!$6:$6")=G$6)* (INDIRECT("'"&$C$6&"'!$5:$5")=G$5), INDIRECT("'"&$C$6&"'!"&ROW()&":"&ROW()) )} -> 0 | H40: {=_xlfn.XLOOKUP(1, (INDIRECT("'"&$C$6&"'!$6:$6")=H$6)* (INDIRECT("'"&$C$6&"'!$5:$5")=H$5), INDIRECT("'"&$C$6&"'!"&ROW()&":"&ROW()) )} -> 0 | I40: {=_xlfn.XLOOKUP(1, (INDIRECT("'"&$C$6&"'!$6:$6")=I$6)* (INDIRECT("'"&$C$6&"'!$5:$5")=I$5), INDIRECT("'"&$C$6&"'!"&ROW()&":"&ROW()) )} -> 0 | K40: =$D40-E40 -> -3993.9591 | L40: =$D40-F40 -> 0 | M40: =$D40-G40 -> 0 | N40: =$D40-H40 -> 0 | O40: =$D40-I40 -> 0 | Q40: =IFERROR($D40/E40-1,0) -> -1 | R40: =IFERROR($D40/F40-1,0) -> 0 | S40: =IFERROR($D40/G40-1,0) -> 0 | T40: =IFERROR($D40/H40-1,0) -> 0 | U40: =IFERROR($D40/I40-1,0) -> 0 | W40: {=INDIRECT("'"&$C$6&"'!"&ADDRESS(ROW(),COLUMN()+44))} -> 0 | X40: {=INDIRECT("'"&$C$6&"'!"&ADDRESS(ROW(),COLUMN()+44))} -> 12582.578 | Y40: {=INDIRECT("'"&$C$6&"'!"&ADDRESS(ROW(),COLUMN()+44))} -> 0 | Z40: {=INDIRECT("'"&$C$6&"'!"&ADDRESS(ROW(),COLUMN()+44))} -> 0 | AA40: {=INDIRECT("'"&$C$6&"'!"&ADDRESS(ROW(),COLUMN()+44))} -> 0 | AB40: {=INDIRECT("'"&$C$6&"'!"&ADDRESS(ROW(),COLUMN()+44))} -> 0 | AD40: =$W40-X40 -> -12582.578 | AE40: =$W40-Y40 -> 0 | AF40: =$W40-Z40 -> 0 | AG40: =$W40-AA40 -> 0 | AH40: =$W40-AB40 -> 0 | AJ40: =IFERROR($W40/X40-1,0) -> -1 | AK40: =IFERROR($W40/Y40-1,0) -> 0 | AL40: =IFERROR($W40/Z40-1,0) -> 0 | AM40: =IFERROR($W40/AA40-1,0) -> 0 | AN40: =IFERROR($W40/AB40-1,0) -> 0
C41: Ingreso Financiero | D41: =SUM(D38:D40) -> 0 | E41: =SUM(E38:E40) -> 116035.47 | F41: =SUM(F38:F40) -> 0 | G41: =SUM(G38:G40) -> 0 | H41: =SUM(H38:H40) -> 0 | I41: =SUM(I38:I40) -> 0 | K41: =$D41-E41 -> -116035.47 | L41: =$D41-F41 -> 0 | M41: =$D41-G41 -> 0 | N41: =$D41-H41 -> 0 | O41: =$D41-I41 -> 0 | Q41: =IFERROR($D41/E41-1,0) -> -1 | R41: =IFERROR($D41/F41-1,0) -> 0 | S41: =IFERROR($D41/G41-1,0) -> 0 | T41: =IFERROR($D41/H41-1,0) -> 0 | U41: =IFERROR($D41/I41-1,0) -> 0 | W41: =SUM(W38:W40) -> 0 | X41: =SUM(X38:X40) -> 328634.88 | Y41: =SUM(Y38:Y40) -> 0 | Z41: =SUM(Z38:Z40) -> 0 | AA41: =SUM(AA38:AA40) -> 0 | AB41: =SUM(AB38:AB40) -> 0 | AD41: =$W41-X41 -> -328634.88 | AE41: =$W41-Y41 -> 0 | AF41: =$W41-Z41 -> 0 | AG41: =$W41-AA41 -> 0 | AH41: =$W41-AB41 -> 0 | AJ41: =IFERROR($W41/X41-1,0) -> -1 | AK41: =IFERROR($W41/Y41-1,0) -> 0 | AL41: =IFERROR($W41/Z41-1,0) -> 0 | AM41: =IFERROR($W41/AA41-1,0) -> 0 | AN41: =IFERROR($W41/AB41-1,0) -> 0
A44: FTP | C44: Vigente | D44: {=_xlfn.XLOOKUP(1, (INDIRECT("'"&$C$6&"'!$6:$6")=D$6)* (INDIRECT("'"&$C$6&"'!$5:$5")=D$5), INDIRECT("'"&$C$6&"'!"&ROW()&":"&ROW()) )} -> 0 | E44: {=_xlfn.XLOOKUP(1, (INDIRECT("'"&$C$6&"'!$6:$6")=E$6)* (INDIRECT("'"&$C$6&"'!$5:$5")=E$5), INDIRECT("'"&$C$6&"'!"&ROW()&":"&ROW()) )} -> -22558.04 | F44: {=_xlfn.XLOOKUP(1, (INDIRECT("'"&$C$6&"'!$6:$6")=F$6)* (INDIRECT("'"&$C$6&"'!$5:$5")=F$5), INDIRECT("'"&$C$6&"'!"&ROW()&":"&ROW()) )} -> 0 | G44: {=_xlfn.XLOOKUP(1, (INDIRECT("'"&$C$6&"'!$6:$6")=G$6)* (INDIRECT("'"&$C$6&"'!$5:$5")=G$5), INDIRECT("'"&$C$6&"'!"&ROW()&":"&ROW()) )} -> 0 | H44: {=_xlfn.XLOOKUP(1, (INDIRECT("'"&$C$6&"'!$6:$6")=H$6)* (INDIRECT("'"&$C$6&"'!$5:$5")=H$5), INDIRECT("'"&$C$6&"'!"&ROW()&":"&ROW()) )} -> 0 | I44: {=_xlfn.XLOOKUP(1, (INDIRECT("'"&$C$6&"'!$6:$6")=I$6)* (INDIRECT("'"&$C$6&"'!$5:$5")=I$5), INDIRECT("'"&$C$6&"'!"&ROW()&":"&ROW()) )} -> 0 | K44: =$D44-E44 -> 22558.04 | L44: =$D44-F44 -> 0 | M44: =$D44-G44 -> 0 | N44: =$D44-H44 -> 0 | O44: =$D44-I44 -> 0 | Q44: =IFERROR($D44/E44-1,0) -> -1 | R44: =IFERROR($D44/F44-1,0) -> 0 | S44: =IFERROR($D44/G44-1,0) -> 0 | T44: =IFERROR($D44/H44-1,0) -> 0 | U44: =IFERROR($D44/I44-1,0) -> 0 | W44: {=INDIRECT("'"&$C$6&"'!"&ADDRESS(ROW(),COLUMN()+44))} -> 0 | X44: {=INDIRECT("'"&$C$6&"'!"&ADDRESS(ROW(),COLUMN()+44))} -> -65796.78 | Y44: {=INDIRECT("'"&$C$6&"'!"&ADDRESS(ROW(),COLUMN()+44))} -> 0 | Z44: {=INDIRECT("'"&$C$6&"'!"&ADDRESS(ROW(),COLUMN()+44))} -> 0 | AA44: {=INDIRECT("'"&$C$6&"'!"&ADDRESS(ROW(),COLUMN()+44))} -> 0 | AB44: {=INDIRECT("'"&$C$6&"'!"&ADDRESS(ROW(),COLUMN()+44))} -> 0 | AD44: =$W44-X44 -> 65796.78 | AE44: =$W44-Y44 -> 0 | AF44: =$W44-Z44 -> 0 | AG44: =$W44-AA44 -> 0 | AH44: =$W44-AB44 -> 0 | AJ44: =IFERROR($W44/X44-1,0) -> -1 | AK44: =IFERROR($W44/Y44-1,0) -> 0 | AL44: =IFERROR($W44/Z44-1,0) -> 0 | AM44: =IFERROR($W44/AA44-1,0) -> 0 | AN44: =IFERROR($W44/AB44-1,0) -> 0
A45: FTP | C45: Refinanciado | D45: {=_xlfn.XLOOKUP(1, (INDIRECT("'"&$C$6&"'!$6:$6")=D$6)* (INDIRECT("'"&$C$6&"'!$5:$5")=D$5), INDIRECT("'"&$C$6&"'!"&ROW()&":"&ROW()) )} -> 0 | E45: {=_xlfn.XLOOKUP(1, (INDIRECT("'"&$C$6&"'!$6:$6")=E$6)* (INDIRECT("'"&$C$6&"'!$5:$5")=E$5), INDIRECT("'"&$C$6&"'!"&ROW()&":"&ROW()) )} -> -774.50321 | F45: {=_xlfn.XLOOKUP(1, (INDIRECT("'"&$C$6&"'!$6:$6")=F$6)* (INDIRECT("'"&$C$6&"'!$5:$5")=F$5), INDIRECT("'"&$C$6&"'!"&ROW()&":"&ROW()) )} -> 0 | G45: {=_xlfn.XLOOKUP(1, (INDIRECT("'"&$C$6&"'!$6:$6")=G$6)* (INDIRECT("'"&$C$6&"'!$5:$5")=G$5), INDIRECT("'"&$C$6&"'!"&ROW()&":"&ROW()) )} -> 0 | H45: {=_xlfn.XLOOKUP(1, (INDIRECT("'"&$C$6&"'!$6:$6")=H$6)* (INDIRECT("'"&$C$6&"'!$5:$5")=H$5), INDIRECT("'"&$C$6&"'!"&ROW()&":"&ROW()) )} -> 0 | I45: {=_xlfn.XLOOKUP(1, (INDIRECT("'"&$C$6&"'!$6:$6")=I$6)* (INDIRECT("'"&$C$6&"'!$5:$5")=I$5), INDIRECT("'"&$C$6&"'!"&ROW()&":"&ROW()) )} -> 0 | K45: =$D45-E45 -> 774.50321 | L45: =$D45-F45 -> 0 | M45: =$D45-G45 -> 0 | N45: =$D45-H45 -> 0 | O45: =$D45-I45 -> 0 | Q45: =IFERROR($D45/E45-1,0) -> -1 | R45: =IFERROR($D45/F45-1,0) -> 0 | S45: =IFERROR($D45/G45-1,0) -> 0 | T45: =IFERROR($D45/H45-1,0) -> 0 | U45: =IFERROR($D45/I45-1,0) -> 0 | W45: {=INDIRECT("'"&$C$6&"'!"&ADDRESS(ROW(),COLUMN()+44))} -> 0 | X45: {=INDIRECT("'"&$C$6&"'!"&ADDRESS(ROW(),COLUMN()+44))} -> -2215.9145 | Y45: {=INDIRECT("'"&$C$6&"'!"&ADDRESS(ROW(),COLUMN()+44))} -> 0 | Z45: {=INDIRECT("'"&$C$6&"'!"&ADDRESS(ROW(),COLUMN()+44))} -> 0 | AA45: {=INDIRECT("'"&$C$6&"'!"&ADDRESS(ROW(),COLUMN()+44))} -> 0 | AB45: {=INDIRECT("'"&$C$6&"'!"&ADDRESS(ROW(),COLUMN()+44))} -> 0 | AD45: =$W45-X45 -> 2215.9145 | AE45: =$W45-Y45 -> 0 | AF45: =$W45-Z45 -> 0 | AG45: =$W45-AA45 -> 0 | AH45: =$W45-AB45 -> 0 | AJ45: =IFERROR($W45/X45-1,0) -> -1 | AK45: =IFERROR($W45/Y45-1,0) -> 0 | AL45: =IFERROR($W45/Z45-1,0) -> 0 | AM45: =IFERROR($W45/AA45-1,0) -> 0 | AN45: =IFERROR($W45/AB45-1,0) -> 0
A46: FTP | C46: Vencido y Judicial | D46: {=_xlfn.XLOOKUP(1, (INDIRECT("'"&$C$6&"'!$6:$6")=D$6)* (INDIRECT("'"&$C$6&"'!$5:$5")=D$5), INDIRECT("'"&$C$6&"'!"&ROW()&":"&ROW()) )} -> 0 | E46: {=_xlfn.XLOOKUP(1, (INDIRECT("'"&$C$6&"'!$6:$6")=E$6)* (INDIRECT("'"&$C$6&"'!$5:$5")=E$5), INDIRECT("'"&$C$6&"'!"&ROW()&":"&ROW()) )} -> -1066.7769 | F46: {=_xlfn.XLOOKUP(1, (INDIRECT("'"&$C$6&"'!$6:$6")=F$6)* (INDIRECT("'"&$C$6&"'!$5:$5")=F$5), INDIRECT("'"&$C$6&"'!"&ROW()&":"&ROW()) )} -> 0 | G46: {=_xlfn.XLOOKUP(1, (INDIRECT("'"&$C$6&"'!$6:$6")=G$6)* (INDIRECT("'"&$C$6&"'!$5:$5")=G$5), INDIRECT("'"&$C$6&"'!"&ROW()&":"&ROW()) )} -> 0 | H46: {=_xlfn.XLOOKUP(1, (INDIRECT("'"&$C$6&"'!$6:$6")=H$6)* (INDIRECT("'"&$C$6&"'!$5:$5")=H$5), INDIRECT("'"&$C$6&"'!"&ROW()&":"&ROW()) )} -> 0 | I46: {=_xlfn.XLOOKUP(1, (INDIRECT("'"&$C$6&"'!$6:$6")=I$6)* (INDIRECT("'"&$C$6&"'!$5:$5")=I$5), INDIRECT("'"&$C$6&"'!"&ROW()&":"&ROW()) )} -> 0 | K46: =$D46-E46 -> 1066.7769 | L46: =$D46-F46 -> 0 | M46: =$D46-G46 -> 0 | N46: =$D46-H46 -> 0 | O46: =$D46-I46 -> 0 | Q46: =IFERROR($D46/E46-1,0) -> -1 | R46: =IFERROR($D46/F46-1,0) -> 0 | S46: =IFERROR($D46/G46-1,0) -> 0 | T46: =IFERROR($D46/H46-1,0) -> 0 | U46: =IFERROR($D46/I46-1,0) -> 0 | W46: {=INDIRECT("'"&$C$6&"'!"&ADDRESS(ROW(),COLUMN()+44))} -> 0 | X46: {=INDIRECT("'"&$C$6&"'!"&ADDRESS(ROW(),COLUMN()+44))} -> -3112.2211 | Y46: {=INDIRECT("'"&$C$6&"'!"&ADDRESS(ROW(),COLUMN()+44))} -> 0 | Z46: {=INDIRECT("'"&$C$6&"'!"&ADDRESS(ROW(),COLUMN()+44))} -> 0 | AA46: {=INDIRECT("'"&$C$6&"'!"&ADDRESS(ROW(),COLUMN()+44))} -> 0 | AB46: {=INDIRECT("'"&$C$6&"'!"&ADDRESS(ROW(),COLUMN()+44))} -> 0 | AD46: =$W46-X46 -> 3112.2211 | AE46: =$W46-Y46 -> 0 | AF46: =$W46-Z46 -> 0 | AG46: =$W46-AA46 -> 0 | AH46: =$W46-AB46 -> 0 | AJ46: =IFERROR($W46/X46-1,0) -> -1 | AK46: =IFERROR($W46/Y46-1,0) -> 0 | AL46: =IFERROR($W46/Z46-1,0) -> 0 | AM46: =IFERROR($W46/AA46-1,0) -> 0 | AN46: =IFERROR($W46/AB46-1,0) -> 0
C47: Costo de Fondos | D47: =SUM(D44:D46) -> 0 | E47: =SUM(E44:E46) -> -24399.32 | F47: =SUM(F44:F46) -> 0 | G47: =SUM(G44:G46) -> 0 | H47: =SUM(H44:H46) -> 0 | I47: =SUM(I44:I46) -> 0 | K47: =$D47-E47 -> 24399.32 | L47: =$D47-F47 -> 0 | M47: =$D47-G47 -> 0 | N47: =$D47-H47 -> 0 | O47: =$D47-I47 -> 0 | Q47: =IFERROR($D47/E47-1,0) -> -1 | R47: =IFERROR($D47/F47-1,0) -> 0 | S47: =IFERROR($D47/G47-1,0) -> 0 | T47: =IFERROR($D47/H47-1,0) -> 0 | U47: =IFERROR($D47/I47-1,0) -> 0 | W47: =SUM(W44:W46) -> 0 | X47: =SUM(X44:X46) -> -71124.915 | Y47: =SUM(Y44:Y46) -> 0 | Z47: =SUM(Z44:Z46) -> 0 | AA47: =SUM(AA44:AA46) -> 0 | AB47: =SUM(AB44:AB46) -> 0 | AD47: =$W47-X47 -> 71124.915 | AE47: =$W47-Y47 -> 0 | AF47: =$W47-Z47 -> 0 | AG47: =$W47-AA47 -> 0 | AH47: =$W47-AB47 -> 0 | AJ47: =IFERROR($W47/X47-1,0) -> -1 | AK47: =IFERROR($W47/Y47-1,0) -> 0 | AL47: =IFERROR($W47/Z47-1,0) -> 0 | AM47: =IFERROR($W47/AA47-1,0) -> 0 | AN47: =IFERROR($W47/AB47-1,0) -> 0
C50: Vigente | D50: =D38+D44 -> 0 | E50: =E38+E44 -> 87894.452 | F50: =F38+F44 -> 0 | G50: =G38+G44 -> 0 | H50: =H38+H44 -> 0 | I50: =I38+I44 -> 0 | K50: =$D50-E50 -> -87894.452 | L50: =$D50-F50 -> 0 | M50: =$D50-G50 -> 0 | N50: =$D50-H50 -> 0 | O50: =$D50-I50 -> 0 | Q50: =IFERROR($D50/E50-1,0) -> -1 | R50: =IFERROR($D50/F50-1,0) -> 0 | S50: =IFERROR($D50/G50-1,0) -> 0 | T50: =IFERROR($D50/H50-1,0) -> 0 | U50: =IFERROR($D50/I50-1,0) -> 0 | W50: =W38+W44 -> 0 | X50: =X38+X44 -> 245605.12 | Y50: =Y38+Y44 -> 0 | Z50: =Z38+Z44 -> 0 | AA50: =AA38+AA44 -> 0 | AB50: =AB38+AB44 -> 0 | AD50: =$W50-X50 -> -245605.12 | AE50: =$W50-Y50 -> 0 | AF50: =$W50-Z50 -> 0 | AG50: =$W50-AA50 -> 0 | AH50: =$W50-AB50 -> 0 | AJ50: =IFERROR($W50/X50-1,0) -> -1 | AK50: =IFERROR($W50/Y50-1,0) -> 0 | AL50: =IFERROR($W50/Z50-1,0) -> 0 | AM50: =IFERROR($W50/AA50-1,0) -> 0 | AN50: =IFERROR($W50/AB50-1,0) -> 0
C51: Refinanciado | D51: =D39+D45 -> 0 | E51: =E39+E45 -> 814.51264 | F51: =F39+F45 -> 0 | G51: =G39+G45 -> 0 | H51: =H39+H45 -> 0 | I51: =I39+I45 -> 0 | K51: =$D51-E51 -> -814.51264 | L51: =$D51-F51 -> 0 | M51: =$D51-G51 -> 0 | N51: =$D51-H51 -> 0 | O51: =$D51-I51 -> 0 | Q51: =IFERROR($D51/E51-1,0) -> -1 | R51: =IFERROR($D51/F51-1,0) -> 0 | S51: =IFERROR($D51/G51-1,0) -> 0 | T51: =IFERROR($D51/H51-1,0) -> 0 | U51: =IFERROR($D51/I51-1,0) -> 0 | W51: =W39+W45 -> 0 | X51: =X39+X45 -> 2434.4896 | Y51: =Y39+Y45 -> 0 | Z51: =Z39+Z45 -> 0 | AA51: =AA39+AA45 -> 0 | AB51: =AB39+AB45 -> 0 | AD51: =$W51-X51 -> -2434.4896 | AE51: =$W51-Y51 -> 0 | AF51: =$W51-Z51 -> 0 | AG51: =$W51-AA51 -> 0 | AH51: =$W51-AB51 -> 0 | AJ51: =IFERROR($W51/X51-1,0) -> -1 | AK51: =IFERROR($W51/Y51-1,0) -> 0 | AL51: =IFERROR($W51/Z51-1,0) -> 0 | AM51: =IFERROR($W51/AA51-1,0) -> 0 | AN51: =IFERROR($W51/AB51-1,0) -> 0
C52: Vencido y Judicial | D52: =D40+D46 -> 0 | E52: =E40+E46 -> 2927.1822 | F52: =F40+F46 -> 0 | G52: =G40+G46 -> 0 | H52: =H40+H46 -> 0 | I52: =I40+I46 -> 0 | K52: =$D52-E52 -> -2927.1822 | L52: =$D52-F52 -> 0 | M52: =$D52-G52 -> 0 | N52: =$D52-H52 -> 0 | O52: =$D52-I52 -> 0 | Q52: =IFERROR($D52/E52-1,0) -> -1 | R52: =IFERROR($D52/F52-1,0) -> 0 | S52: =IFERROR($D52/G52-1,0) -> 0 | T52: =IFERROR($D52/H52-1,0) -> 0 | U52: =IFERROR($D52/I52-1,0) -> 0 | W52: =W40+W46 -> 0 | X52: =X40+X46 -> 9470.3565 | Y52: =Y40+Y46 -> 0 | Z52: =Z40+Z46 -> 0 | AA52: =AA40+AA46 -> 0 | AB52: =AB40+AB46 -> 0 | AD52: =$W52-X52 -> -9470.3565 | AE52: =$W52-Y52 -> 0 | AF52: =$W52-Z52 -> 0 | AG52: =$W52-AA52 -> 0 | AH52: =$W52-AB52 -> 0 | AJ52: =IFERROR($W52/X52-1,0) -> -1 | AK52: =IFERROR($W52/Y52-1,0) -> 0 | AL52: =IFERROR($W52/Z52-1,0) -> 0 | AM52: =IFERROR($W52/AA52-1,0) -> 0 | AN52: =IFERROR($W52/AB52-1,0) -> 0
C53: Resultado Financiero Bruto | D53: =D41+D47 -> 0 | E53: =E41+E47 -> 91636.147 | F53: =F41+F47 -> 0 | G53: =G41+G47 -> 0 | H53: =H41+H47 -> 0 | I53: =I41+I47 -> 0 | K53: =$D53-E53 -> -91636.147 | L53: =$D53-F53 -> 0 | M53: =$D53-G53 -> 0 | N53: =$D53-H53 -> 0 | O53: =$D53-I53 -> 0 | Q53: =IFERROR($D53/E53-1,0) -> -1 | R53: =IFERROR($D53/F53-1,0) -> 0 | S53: =IFERROR($D53/G53-1,0) -> 0 | T53: =IFERROR($D53/H53-1,0) -> 0 | U53: =IFERROR($D53/I53-1,0) -> 0 | W53: =W41+W47 -> 0 | X53: =X41+X47 -> 257509.96 | Y53: =Y41+Y47 -> 0 | Z53: =Z41+Z47 -> 0 | AA53: =AA41+AA47 -> 0 | AB53: =AB41+AB47 -> 0 | AD53: =$W53-X53 -> -257509.96 | AE53: =$W53-Y53 -> 0 | AF53: =$W53-Z53 -> 0 | AG53: =$W53-AA53 -> 0 | AH53: =$W53-AB53 -> 0 | AJ53: =IFERROR($W53/X53-1,0) -> -1 | AK53: =IFERROR($W53/Y53-1,0) -> 0 | AL53: =IFERROR($W53/Z53-1,0) -> 0 | AM53: =IFERROR($W53/AA53-1,0) -> 0 | AN53: =IFERROR($W53/AB53-1,0) -> 0
A56: Gasto_Provision | C56: Provisiones Cartera | D56: {=_xlfn.XLOOKUP(1, (INDIRECT("'"&$C$6&"'!$6:$6")=D$6)* (INDIRECT("'"&$C$6&"'!$5:$5")=D$5), INDIRECT("'"&$C$6&"'!"&ROW()&":"&ROW()) )} -> 0 | E56: {=_xlfn.XLOOKUP(1, (INDIRECT("'"&$C$6&"'!$6:$6")=E$6)* (INDIRECT("'"&$C$6&"'!$5:$5")=E$5), INDIRECT("'"&$C$6&"'!"&ROW()&":"&ROW()) )} -> -59770.804 | F56: {=_xlfn.XLOOKUP(1, (INDIRECT("'"&$C$6&"'!$6:$6")=F$6)* (INDIRECT("'"&$C$6&"'!$5:$5")=F$5), INDIRECT("'"&$C$6&"'!"&ROW()&":"&ROW()) )} -> 0 | G56: {=_xlfn.XLOOKUP(1, (INDIRECT("'"&$C$6&"'!$6:$6")=G$6)* (INDIRECT("'"&$C$6&"'!$5:$5")=G$5), INDIRECT("'"&$C$6&"'!"&ROW()&":"&ROW()) )} -> 0 | H56: {=_xlfn.XLOOKUP(1, (INDIRECT("'"&$C$6&"'!$6:$6")=H$6)* (INDIRECT("'"&$C$6&"'!$5:$5")=H$5), INDIRECT("'"&$C$6&"'!"&ROW()&":"&ROW()) )} -> 0 | I56: {=_xlfn.XLOOKUP(1, (INDIRECT("'"&$C$6&"'!$6:$6")=I$6)* (INDIRECT("'"&$C$6&"'!$5:$5")=I$5), INDIRECT("'"&$C$6&"'!"&ROW()&":"&ROW()) )} -> 0 | K56: =$D56-E56 -> 59770.804 | L56: =$D56-F56 -> 0 | M56: =$D56-G56 -> 0 | N56: =$D56-H56 -> 0 | O56: =$D56-I56 -> 0 | Q56: =IFERROR($D56/E56-1,0) -> -1 | R56: =IFERROR($D56/F56-1,0) -> 0 | S56: =IFERROR($D56/G56-1,0) -> 0 | T56: =IFERROR($D56/H56-1,0) -> 0 | U56: =IFERROR($D56/I56-1,0) -> 0 | W56: {=INDIRECT("'"&$C$6&"'!"&ADDRESS(ROW(),COLUMN()+44))} -> 0 | X56: {=INDIRECT("'"&$C$6&"'!"&ADDRESS(ROW(),COLUMN()+44))} -> -169498.18 | Y56: {=INDIRECT("'"&$C$6&"'!"&ADDRESS(ROW(),COLUMN()+44))} -> 0 | Z56: {=INDIRECT("'"&$C$6&"'!"&ADDRESS(ROW(),COLUMN()+44))} -> 0 | AA56: {=INDIRECT("'"&$C$6&"'!"&ADDRESS(ROW(),COLUMN()+44))} -> 0 | AB56: {=INDIRECT("'"&$C$6&"'!"&ADDRESS(ROW(),COLUMN()+44))} -> 0 | AD56: =$W56-X56 -> 169498.18 | AE56: =$W56-Y56 -> 0 | AF56: =$W56-Z56 -> 0 | AG56: =$W56-AA56 -> 0 | AH56: =$W56-AB56 -> 0 | AJ56: =IFERROR($W56/X56-1,0) -> -1 | AK56: =IFERROR($W56/Y56-1,0) -> 0 | AL56: =IFERROR($W56/Z56-1,0) -> 0 | AM56: =IFERROR($W56/AA56-1,0) -> 0 | AN56: =IFERROR($W56/AB56-1,0) -> 0
A57: Recupero | C57: Recupero de Castigos | D57: {=_xlfn.XLOOKUP(1, (INDIRECT("'"&$C$6&"'!$6:$6")=D$6)* (INDIRECT("'"&$C$6&"'!$5:$5")=D$5), INDIRECT("'"&$C$6&"'!"&ROW()&":"&ROW()) )} -> 0 | E57: {=_xlfn.XLOOKUP(1, (INDIRECT("'"&$C$6&"'!$6:$6")=E$6)* (INDIRECT("'"&$C$6&"'!$5:$5")=E$5), INDIRECT("'"&$C$6&"'!"&ROW()&":"&ROW()) )} -> 4547.2817 | F57: {=_xlfn.XLOOKUP(1, (INDIRECT("'"&$C$6&"'!$6:$6")=F$6)* (INDIRECT("'"&$C$6&"'!$5:$5")=F$5), INDIRECT("'"&$C$6&"'!"&ROW()&":"&ROW()) )} -> 0 | G57: {=_xlfn.XLOOKUP(1, (INDIRECT("'"&$C$6&"'!$6:$6")=G$6)* (INDIRECT("'"&$C$6&"'!$5:$5")=G$5), INDIRECT("'"&$C$6&"'!"&ROW()&":"&ROW()) )} -> 0 | H57: {=_xlfn.XLOOKUP(1, (INDIRECT("'"&$C$6&"'!$6:$6")=H$6)* (INDIRECT("'"&$C$6&"'!$5:$5")=H$5), INDIRECT("'"&$C$6&"'!"&ROW()&":"&ROW()) )} -> 0 | I57: {=_xlfn.XLOOKUP(1, (INDIRECT("'"&$C$6&"'!$6:$6")=I$6)* (INDIRECT("'"&$C$6&"'!$5:$5")=I$5), INDIRECT("'"&$C$6&"'!"&ROW()&":"&ROW()) )} -> 0 | K57: =$D57-E57 -> -4547.2817 | L57: =$D57-F57 -> 0 | M57: =$D57-G57 -> 0 | N57: =$D57-H57 -> 0 | O57: =$D57-I57 -> 0 | Q57: =IFERROR($D57/E57-1,0) -> -1 | R57: =IFERROR($D57/F57-1,0) -> 0 | S57: =IFERROR($D57/G57-1,0) -> 0 | T57: =IFERROR($D57/H57-1,0) -> 0 | U57: =IFERROR($D57/I57-1,0) -> 0 | W57: {=INDIRECT("'"&$C$6&"'!"&ADDRESS(ROW(),COLUMN()+44))} -> 0 | X57: {=INDIRECT("'"&$C$6&"'!"&ADDRESS(ROW(),COLUMN()+44))} -> 12489.434 | Y57: {=INDIRECT("'"&$C$6&"'!"&ADDRESS(ROW(),COLUMN()+44))} -> 0 | Z57: {=INDIRECT("'"&$C$6&"'!"&ADDRESS(ROW(),COLUMN()+44))} -> 0 | AA57: {=INDIRECT("'"&$C$6&"'!"&ADDRESS(ROW(),COLUMN()+44))} -> 0 | AB57: {=INDIRECT("'"&$C$6&"'!"&ADDRESS(ROW(),COLUMN()+44))} -> 0 | AD57: =$W57-X57 -> -12489.434 | AE57: =$W57-Y57 -> 0 | AF57: =$W57-Z57 -> 0 | AG57: =$W57-AA57 -> 0 | AH57: =$W57-AB57 -> 0 | AJ57: =IFERROR($W57/X57-1,0) -> -1 | AK57: =IFERROR($W57/Y57-1,0) -> 0 | AL57: =IFERROR($W57/Z57-1,0) -> 0 | AM57: =IFERROR($W57/AA57-1,0) -> 0 | AN57: =IFERROR($W57/AB57-1,0) -> 0
C58: Provisiones Netas | D58: =SUM(D56:D57) -> 0 | E58: =SUM(E56:E57) -> -55223.522 | F58: =SUM(F56:F57) -> 0 | G58: =SUM(G56:G57) -> 0 | H58: =SUM(H56:H57) -> 0 | I58: =SUM(I56:I57) -> 0 | K58: =$D58-E58 -> 55223.522 | L58: =$D58-F58 -> 0 | M58: =$D58-G58 -> 0 | N58: =$D58-H58 -> 0 | O58: =$D58-I58 -> 0 | Q58: =IFERROR($D58/E58-1,0) -> -1 | R58: =IFERROR($D58/F58-1,0) -> 0 | S58: =IFERROR($D58/G58-1,0) -> 0 | T58: =IFERROR($D58/H58-1,0) -> 0 | U58: =IFERROR($D58/I58-1,0) -> 0 | W58: =SUM(W56:W57) -> 0 | X58: =SUM(X56:X57) -> -157008.75 | Y58: =SUM(Y56:Y57) -> 0 | Z58: =SUM(Z56:Z57) -> 0 | AA58: =SUM(AA56:AA57) -> 0 | AB58: =SUM(AB56:AB57) -> 0 | AD58: =$W58-X58 -> 157008.75 | AE58: =$W58-Y58 -> 0 | AF58: =$W58-Z58 -> 0 | AG58: =$W58-AA58 -> 0 | AH58: =$W58-AB58 -> 0 | AJ58: =IFERROR($W58/X58-1,0) -> -1 | AK58: =IFERROR($W58/Y58-1,0) -> 0 | AL58: =IFERROR($W58/Z58-1,0) -> 0 | AM58: =IFERROR($W58/AA58-1,0) -> 0 | AN58: =IFERROR($W58/AB58-1,0) -> 0
C60: Resultado Financiero Neto | D60: =D53+D58 -> 0 | E60: =E53+E58 -> 36412.625 | F60: =F53+F58 -> 0 | G60: =G53+G58 -> 0 | H60: =H53+H58 -> 0 | I60: =I53+I58 -> 0 | K60: =$D60-E60 -> -36412.625 | L60: =$D60-F60 -> 0 | M60: =$D60-G60 -> 0 | N60: =$D60-H60 -> 0 | O60: =$D60-I60 -> 0 | Q60: =IFERROR($D60/E60-1,0) -> -1 | R60: =IFERROR($D60/F60-1,0) -> 0 | S60: =IFERROR($D60/G60-1,0) -> 0 | T60: =IFERROR($D60/H60-1,0) -> 0 | U60: =IFERROR($D60/I60-1,0) -> 0 | W60: =W53+W58 -> 0 | X60: =X53+X58 -> 100501.21 | Y60: =Y53+Y58 -> 0 | Z60: =Z53+Z58 -> 0 | AA60: =AA53+AA58 -> 0 | AB60: =AB53+AB58 -> 0 | AD60: =$W60-X60 -> -100501.21 | AE60: =$W60-Y60 -> 0 | AF60: =$W60-Z60 -> 0 | AG60: =$W60-AA60 -> 0 | AH60: =$W60-AB60 -> 0 | AJ60: =IFERROR($W60/X60-1,0) -> -1 | AK60: =IFERROR($W60/Y60-1,0) -> 0 | AL60: =IFERROR($W60/Z60-1,0) -> 0 | AM60: =IFERROR($W60/AA60-1,0) -> 0 | AN60: =IFERROR($W60/AB60-1,0) -> 0
A63: INOF | C63: Seguro de Desgravamen | D63: {=_xlfn.XLOOKUP(1, (INDIRECT("'"&$C$6&"'!$6:$6")=D$6)* (INDIRECT("'"&$C$6&"'!$5:$5")=D$5), INDIRECT("'"&$C$6&"'!"&ROW()&":"&ROW()) )} -> 0 | E63: {=_xlfn.XLOOKUP(1, (INDIRECT("'"&$C$6&"'!$6:$6")=E$6)* (INDIRECT("'"&$C$6&"'!$5:$5")=E$5), INDIRECT("'"&$C$6&"'!"&ROW()&":"&ROW()) )} -> 994.10186 | F63: {=_xlfn.XLOOKUP(1, (INDIRECT("'"&$C$6&"'!$6:$6")=F$6)* (INDIRECT("'"&$C$6&"'!$5:$5")=F$5), INDIRECT("'"&$C$6&"'!"&ROW()&":"&ROW()) )} -> 0 | G63: {=_xlfn.XLOOKUP(1, (INDIRECT("'"&$C$6&"'!$6:$6")=G$6)* (INDIRECT("'"&$C$6&"'!$5:$5")=G$5), INDIRECT("'"&$C$6&"'!"&ROW()&":"&ROW()) )} -> 0 | H63: {=_xlfn.XLOOKUP(1, (INDIRECT("'"&$C$6&"'!$6:$6")=H$6)* (INDIRECT("'"&$C$6&"'!$5:$5")=H$5), INDIRECT("'"&$C$6&"'!"&ROW()&":"&ROW()) )} -> 0 | I63: {=_xlfn.XLOOKUP(1, (INDIRECT("'"&$C$6&"'!$6:$6")=I$6)* (INDIRECT("'"&$C$6&"'!$5:$5")=I$5), INDIRECT("'"&$C$6&"'!"&ROW()&":"&ROW()) )} -> 0 | K63: =$D63-E63 -> -994.10186 | L63: =$D63-F63 -> 0 | M63: =$D63-G63 -> 0 | N63: =$D63-H63 -> 0 | O63: =$D63-I63 -> 0 | Q63: =IFERROR($D63/E63-1,0) -> -1 | R63: =IFERROR($D63/F63-1,0) -> 0 | S63: =IFERROR($D63/G63-1,0) -> 0 | T63: =IFERROR($D63/H63-1,0) -> 0 | U63: =IFERROR($D63/I63-1,0) -> 0 | W63: {=INDIRECT("'"&$C$6&"'!"&ADDRESS(ROW(),COLUMN()+44))} -> 0 | X63: {=INDIRECT("'"&$C$6&"'!"&ADDRESS(ROW(),COLUMN()+44))} -> 3438.8276 | Y63: {=INDIRECT("'"&$C$6&"'!"&ADDRESS(ROW(),COLUMN()+44))} -> 0 | Z63: {=INDIRECT("'"&$C$6&"'!"&ADDRESS(ROW(),COLUMN()+44))} -> 0 | AA63: {=INDIRECT("'"&$C$6&"'!"&ADDRESS(ROW(),COLUMN()+44))} -> 0 | AB63: {=INDIRECT("'"&$C$6&"'!"&ADDRESS(ROW(),COLUMN()+44))} -> 0 | AD63: =$W63-X63 -> -3438.8276 | AE63: =$W63-Y63 -> 0 | AF63: =$W63-Z63 -> 0 | AG63: =$W63-AA63 -> 0 | AH63: =$W63-AB63 -> 0 | AJ63: =IFERROR($W63/X63-1,0) -> -1 | AK63: =IFERROR($W63/Y63-1,0) -> 0 | AL63: =IFERROR($W63/Z63-1,0) -> 0 | AM63: =IFERROR($W63/AA63-1,0) -> 0 | AN63: =IFERROR($W63/AB63-1,0) -> 0
A64: INOF | C64: Comisiones | D64: {=_xlfn.XLOOKUP(1, (INDIRECT("'"&$C$6&"'!$6:$6")=D$6)* (INDIRECT("'"&$C$6&"'!$5:$5")=D$5), INDIRECT("'"&$C$6&"'!"&ROW()&":"&ROW()) )} -> 0 | E64: {=_xlfn.XLOOKUP(1, (INDIRECT("'"&$C$6&"'!$6:$6")=E$6)* (INDIRECT("'"&$C$6&"'!$5:$5")=E$5), INDIRECT("'"&$C$6&"'!"&ROW()&":"&ROW()) )} -> 173.76633 | F64: {=_xlfn.XLOOKUP(1, (INDIRECT("'"&$C$6&"'!$6:$6")=F$6)* (INDIRECT("'"&$C$6&"'!$5:$5")=F$5), INDIRECT("'"&$C$6&"'!"&ROW()&":"&ROW()) )} -> 0 | G64: {=_xlfn.XLOOKUP(1, (INDIRECT("'"&$C$6&"'!$6:$6")=G$6)* (INDIRECT("'"&$C$6&"'!$5:$5")=G$5), INDIRECT("'"&$C$6&"'!"&ROW()&":"&ROW()) )} -> 0 | H64: {=_xlfn.XLOOKUP(1, (INDIRECT("'"&$C$6&"'!$6:$6")=H$6)* (INDIRECT("'"&$C$6&"'!$5:$5")=H$5), INDIRECT("'"&$C$6&"'!"&ROW()&":"&ROW()) )} -> 0 | I64: {=_xlfn.XLOOKUP(1, (INDIRECT("'"&$C$6&"'!$6:$6")=I$6)* (INDIRECT("'"&$C$6&"'!$5:$5")=I$5), INDIRECT("'"&$C$6&"'!"&ROW()&":"&ROW()) )} -> 0 | K64: =$D64-E64 -> -173.76633 | L64: =$D64-F64 -> 0 | M64: =$D64-G64 -> 0 | N64: =$D64-H64 -> 0 | O64: =$D64-I64 -> 0 | Q64: =IFERROR($D64/E64-1,0) -> -1 | R64: =IFERROR($D64/F64-1,0) -> 0 | S64: =IFERROR($D64/G64-1,0) -> 0 | T64: =IFERROR($D64/H64-1,0) -> 0 | U64: =IFERROR($D64/I64-1,0) -> 0 | W64: {=INDIRECT("'"&$C$6&"'!"&ADDRESS(ROW(),COLUMN()+44))} -> 0 | X64: {=INDIRECT("'"&$C$6&"'!"&ADDRESS(ROW(),COLUMN()+44))} -> 505.89849 | Y64: {=INDIRECT("'"&$C$6&"'!"&ADDRESS(ROW(),COLUMN()+44))} -> 0 | Z64: {=INDIRECT("'"&$C$6&"'!"&ADDRESS(ROW(),COLUMN()+44))} -> 0 | AA64: {=INDIRECT("'"&$C$6&"'!"&ADDRESS(ROW(),COLUMN()+44))} -> 0 | AB64: {=INDIRECT("'"&$C$6&"'!"&ADDRESS(ROW(),COLUMN()+44))} -> 0 | AD64: =$W64-X64 -> -505.89849 | AE64: =$W64-Y64 -> 0 | AF64: =$W64-Z64 -> 0 | AG64: =$W64-AA64 -> 0 | AH64: =$W64-AB64 -> 0 | AJ64: =IFERROR($W64/X64-1,0) -> -1 | AK64: =IFERROR($W64/Y64-1,0) -> 0 | AL64: =IFERROR($W64/Z64-1,0) -> 0 | AM64: =IFERROR($W64/AA64-1,0) -> 0 | AN64: =IFERROR($W64/AB64-1,0) -> 0
A65: INOF | C65: Gastos de casilleros | D65: {=_xlfn.XLOOKUP(1, (INDIRECT("'"&$C$6&"'!$6:$6")=D$6)* (INDIRECT("'"&$C$6&"'!$5:$5")=D$5), INDIRECT("'"&$C$6&"'!"&ROW()&":"&ROW()) )} -> 0 | E65: {=_xlfn.XLOOKUP(1, (INDIRECT("'"&$C$6&"'!$6:$6")=E$6)* (INDIRECT("'"&$C$6&"'!$5:$5")=E$5), INDIRECT("'"&$C$6&"'!"&ROW()&":"&ROW()) )} -> 0 | F65: {=_xlfn.XLOOKUP(1, (INDIRECT("'"&$C$6&"'!$6:$6")=F$6)* (INDIRECT("'"&$C$6&"'!$5:$5")=F$5), INDIRECT("'"&$C$6&"'!"&ROW()&":"&ROW()) )} -> 0 | G65: {=_xlfn.XLOOKUP(1, (INDIRECT("'"&$C$6&"'!$6:$6")=G$6)* (INDIRECT("'"&$C$6&"'!$5:$5")=G$5), INDIRECT("'"&$C$6&"'!"&ROW()&":"&ROW()) )} -> 0 | H65: {=_xlfn.XLOOKUP(1, (INDIRECT("'"&$C$6&"'!$6:$6")=H$6)* (INDIRECT("'"&$C$6&"'!$5:$5")=H$5), INDIRECT("'"&$C$6&"'!"&ROW()&":"&ROW()) )} -> 0 | I65: {=_xlfn.XLOOKUP(1, (INDIRECT("'"&$C$6&"'!$6:$6")=I$6)* (INDIRECT("'"&$C$6&"'!$5:$5")=I$5), INDIRECT("'"&$C$6&"'!"&ROW()&":"&ROW()) )} -> 0 | K65: =$D65-E65 -> 0 | L65: =$D65-F65 -> 0 | M65: =$D65-G65 -> 0 | N65: =$D65-H65 -> 0 | O65: =$D65-I65 -> 0 | Q65: =IFERROR($D65/E65-1,0) -> 0 | R65: =IFERROR($D65/F65-1,0) -> 0 | S65: =IFERROR($D65/G65-1,0) -> 0 | T65: =IFERROR($D65/H65-1,0) -> 0 | U65: =IFERROR($D65/I65-1,0) -> 0 | W65: {=INDIRECT("'"&$C$6&"'!"&ADDRESS(ROW(),COLUMN()+44))} -> 0 | X65: {=INDIRECT("'"&$C$6&"'!"&ADDRESS(ROW(),COLUMN()+44))} -> 0 | Y65: {=INDIRECT("'"&$C$6&"'!"&ADDRESS(ROW(),COLUMN()+44))} -> 0 | Z65: {=INDIRECT("'"&$C$6&"'!"&ADDRESS(ROW(),COLUMN()+44))} -> 0 | AA65: {=INDIRECT("'"&$C$6&"'!"&ADDRESS(ROW(),COLUMN()+44))} -> 0 | AB65: {=INDIRECT("'"&$C$6&"'!"&ADDRESS(ROW(),COLUMN()+44))} -> 0 | AD65: =$W65-X65 -> 0 | AE65: =$W65-Y65 -> 0 | AF65: =$W65-Z65 -> 0 | AG65: =$W65-AA65 -> 0 | AH65: =$W65-AB65 -> 0 | AJ65: =IFERROR($W65/X65-1,0) -> 0 | AK65: =IFERROR($W65/Y65-1,0) -> 0 | AL65: =IFERROR($W65/Z65-1,0) -> 0 | AM65: =IFERROR($W65/AA65-1,0) -> 0 | AN65: =IFERROR($W65/AB65-1,0) -> 0
A66: INOF | D66: {=_xlfn.XLOOKUP(1, (INDIRECT("'"&$C$6&"'!$6:$6")=D$6)* (INDIRECT("'"&$C$6&"'!$5:$5")=D$5), INDIRECT("'"&$C$6&"'!"&ROW()&":"&ROW()) )} -> 0 | E66: {=_xlfn.XLOOKUP(1, (INDIRECT("'"&$C$6&"'!$6:$6")=E$6)* (INDIRECT("'"&$C$6&"'!$5:$5")=E$5), INDIRECT("'"&$C$6&"'!"&ROW()&":"&ROW()) )} -> 1488.1313 | F66: {=_xlfn.XLOOKUP(1, (INDIRECT("'"&$C$6&"'!$6:$6")=F$6)* (INDIRECT("'"&$C$6&"'!$5:$5")=F$5), INDIRECT("'"&$C$6&"'!"&ROW()&":"&ROW()) )} -> 0 | G66: {=_xlfn.XLOOKUP(1, (INDIRECT("'"&$C$6&"'!$6:$6")=G$6)* (INDIRECT("'"&$C$6&"'!$5:$5")=G$5), INDIRECT("'"&$C$6&"'!"&ROW()&":"&ROW()) )} -> 0 | H66: {=_xlfn.XLOOKUP(1, (INDIRECT("'"&$C$6&"'!$6:$6")=H$6)* (INDIRECT("'"&$C$6&"'!$5:$5")=H$5), INDIRECT("'"&$C$6&"'!"&ROW()&":"&ROW()) )} -> 0 | I66: {=_xlfn.XLOOKUP(1, (INDIRECT("'"&$C$6&"'!$6:$6")=I$6)* (INDIRECT("'"&$C$6&"'!$5:$5")=I$5), INDIRECT("'"&$C$6&"'!"&ROW()&":"&ROW()) )} -> 0 | K66: =$D66-E66 -> -1488.1313 | L66: =$D66-F66 -> 0 | M66: =$D66-G66 -> 0 | N66: =$D66-H66 -> 0 | O66: =$D66-I66 -> 0 | Q66: =IFERROR($D66/E66-1,0) -> -1 | R66: =IFERROR($D66/F66-1,0) -> 0 | S66: =IFERROR($D66/G66-1,0) -> 0 | T66: =IFERROR($D66/H66-1,0) -> 0 | U66: =IFERROR($D66/I66-1,0) -> 0 | W66: {=INDIRECT("'"&$C$6&"'!"&ADDRESS(ROW(),COLUMN()+44))} -> 0 | X66: {=INDIRECT("'"&$C$6&"'!"&ADDRESS(ROW(),COLUMN()+44))} -> 4659.2695 | Y66: {=INDIRECT("'"&$C$6&"'!"&ADDRESS(ROW(),COLUMN()+44))} -> 0 | Z66: {=INDIRECT("'"&$C$6&"'!"&ADDRESS(ROW(),COLUMN()+44))} -> 0 | AA66: {=INDIRECT("'"&$C$6&"'!"&ADDRESS(ROW(),COLUMN()+44))} -> 0 | AB66: {=INDIRECT("'"&$C$6&"'!"&ADDRESS(ROW(),COLUMN()+44))} -> 0 | AD66: =$W66-X66 -> -4659.2695 | AE66: =$W66-Y66 -> 0 | AF66: =$W66-Z66 -> 0 | AG66: =$W66-AA66 -> 0 | AH66: =$W66-AB66 -> 0 | AJ66: =IFERROR($W66/X66-1,0) -> -1 | AK66: =IFERROR($W66/Y66-1,0) -> 0 | AL66: =IFERROR($W66/Z66-1,0) -> 0 | AM66: =IFERROR($W66/AA66-1,0) -> 0 | AN66: =IFERROR($W66/AB66-1,0) -> 0
A67: INOF | D67: {=_xlfn.XLOOKUP(1, (INDIRECT("'"&$C$6&"'!$6:$6")=D$6)* (INDIRECT("'"&$C$6&"'!$5:$5")=D$5), INDIRECT("'"&$C$6&"'!"&ROW()&":"&ROW()) )} -> 0 | E67: {=_xlfn.XLOOKUP(1, (INDIRECT("'"&$C$6&"'!$6:$6")=E$6)* (INDIRECT("'"&$C$6&"'!$5:$5")=E$5), INDIRECT("'"&$C$6&"'!"&ROW()&":"&ROW()) )} -> 28.075114 | F67: {=_xlfn.XLOOKUP(1, (INDIRECT("'"&$C$6&"'!$6:$6")=F$6)* (INDIRECT("'"&$C$6&"'!$5:$5")=F$5), INDIRECT("'"&$C$6&"'!"&ROW()&":"&ROW()) )} -> 0 | G67: {=_xlfn.XLOOKUP(1, (INDIRECT("'"&$C$6&"'!$6:$6")=G$6)* (INDIRECT("'"&$C$6&"'!$5:$5")=G$5), INDIRECT("'"&$C$6&"'!"&ROW()&":"&ROW()) )} -> 0 | H67: {=_xlfn.XLOOKUP(1, (INDIRECT("'"&$C$6&"'!$6:$6")=H$6)* (INDIRECT("'"&$C$6&"'!$5:$5")=H$5), INDIRECT("'"&$C$6&"'!"&ROW()&":"&ROW()) )} -> 0 | I67: {=_xlfn.XLOOKUP(1, (INDIRECT("'"&$C$6&"'!$6:$6")=I$6)* (INDIRECT("'"&$C$6&"'!$5:$5")=I$5), INDIRECT("'"&$C$6&"'!"&ROW()&":"&ROW()) )} -> 0 | K67: =$D67-E67 -> -28.075114 | L67: =$D67-F67 -> 0 | M67: =$D67-G67 -> 0 | N67: =$D67-H67 -> 0 | O67: =$D67-I67 -> 0 | Q67: =IFERROR($D67/E67-1,0) -> -1 | R67: =IFERROR($D67/F67-1,0) -> 0 | S67: =IFERROR($D67/G67-1,0) -> 0 | T67: =IFERROR($D67/H67-1,0) -> 0 | U67: =IFERROR($D67/I67-1,0) -> 0 | W67: {=INDIRECT("'"&$C$6&"'!"&ADDRESS(ROW(),COLUMN()+44))} -> 0 | X67: {=INDIRECT("'"&$C$6&"'!"&ADDRESS(ROW(),COLUMN()+44))} -> 84.225342 | Y67: {=INDIRECT("'"&$C$6&"'!"&ADDRESS(ROW(),COLUMN()+44))} -> 0 | Z67: {=INDIRECT("'"&$C$6&"'!"&ADDRESS(ROW(),COLUMN()+44))} -> 0 | AA67: {=INDIRECT("'"&$C$6&"'!"&ADDRESS(ROW(),COLUMN()+44))} -> 0 | AB67: {=INDIRECT("'"&$C$6&"'!"&ADDRESS(ROW(),COLUMN()+44))} -> 0 | AD67: =$W67-X67 -> -84.225342 | AE67: =$W67-Y67 -> 0 | AF67: =$W67-Z67 -> 0 | AG67: =$W67-AA67 -> 0 | AH67: =$W67-AB67 -> 0 | AJ67: =IFERROR($W67/X67-1,0) -> -1 | AK67: =IFERROR($W67/Y67-1,0) -> 0 | AL67: =IFERROR($W67/Z67-1,0) -> 0 | AM67: =IFERROR($W67/AA67-1,0) -> 0 | AN67: =IFERROR($W67/AB67-1,0) -> 0
A68: INOF | D68: {=_xlfn.XLOOKUP(1, (INDIRECT("'"&$C$6&"'!$6:$6")=D$6)* (INDIRECT("'"&$C$6&"'!$5:$5")=D$5), INDIRECT("'"&$C$6&"'!"&ROW()&":"&ROW()) )} -> 0 | E68: {=_xlfn.XLOOKUP(1, (INDIRECT("'"&$C$6&"'!$6:$6")=E$6)* (INDIRECT("'"&$C$6&"'!$5:$5")=E$5), INDIRECT("'"&$C$6&"'!"&ROW()&":"&ROW()) )} -> 22276.732 | F68: {=_xlfn.XLOOKUP(1, (INDIRECT("'"&$C$6&"'!$6:$6")=F$6)* (INDIRECT("'"&$C$6&"'!$5:$5")=F$5), INDIRECT("'"&$C$6&"'!"&ROW()&":"&ROW()) )} -> 0 | G68: {=_xlfn.XLOOKUP(1, (INDIRECT("'"&$C$6&"'!$6:$6")=G$6)* (INDIRECT("'"&$C$6&"'!$5:$5")=G$5), INDIRECT("'"&$C$6&"'!"&ROW()&":"&ROW()) )} -> 0 | H68: {=_xlfn.XLOOKUP(1, (INDIRECT("'"&$C$6&"'!$6:$6")=H$6)* (INDIRECT("'"&$C$6&"'!$5:$5")=H$5), INDIRECT("'"&$C$6&"'!"&ROW()&":"&ROW()) )} -> 0 | I68: {=_xlfn.XLOOKUP(1, (INDIRECT("'"&$C$6&"'!$6:$6")=I$6)* (INDIRECT("'"&$C$6&"'!$5:$5")=I$5), INDIRECT("'"&$C$6&"'!"&ROW()&":"&ROW()) )} -> 0 | K68: =$D68-E68 -> -22276.732 | L68: =$D68-F68 -> 0 | M68: =$D68-G68 -> 0 | N68: =$D68-H68 -> 0 | O68: =$D68-I68 -> 0 | Q68: =IFERROR($D68/E68-1,0) -> -1 | R68: =IFERROR($D68/F68-1,0) -> 0 | S68: =IFERROR($D68/G68-1,0) -> 0 | T68: =IFERROR($D68/H68-1,0) -> 0 | U68: =IFERROR($D68/I68-1,0) -> 0 | W68: {=INDIRECT("'"&$C$6&"'!"&ADDRESS(ROW(),COLUMN()+44))} -> 0 | X68: {=INDIRECT("'"&$C$6&"'!"&ADDRESS(ROW(),COLUMN()+44))} -> 60694.843 | Y68: {=INDIRECT("'"&$C$6&"'!"&ADDRESS(ROW(),COLUMN()+44))} -> 0 | Z68: {=INDIRECT("'"&$C$6&"'!"&ADDRESS(ROW(),COLUMN()+44))} -> 0 | AA68: {=INDIRECT("'"&$C$6&"'!"&ADDRESS(ROW(),COLUMN()+44))} -> 0 | AB68: {=INDIRECT("'"&$C$6&"'!"&ADDRESS(ROW(),COLUMN()+44))} -> 0 | AD68: =$W68-X68 -> -60694.843 | AE68: =$W68-Y68 -> 0 | AF68: =$W68-Z68 -> 0 | AG68: =$W68-AA68 -> 0 | AH68: =$W68-AB68 -> 0 | AJ68: =IFERROR($W68/X68-1,0) -> -1 | AK68: =IFERROR($W68/Y68-1,0) -> 0 | AL68: =IFERROR($W68/Z68-1,0) -> 0 | AM68: =IFERROR($W68/AA68-1,0) -> 0 | AN68: =IFERROR($W68/AB68-1,0) -> 0
A69: INOF | D69: {=_xlfn.XLOOKUP(1, (INDIRECT("'"&$C$6&"'!$6:$6")=D$6)* (INDIRECT("'"&$C$6&"'!$5:$5")=D$5), INDIRECT("'"&$C$6&"'!"&ROW()&":"&ROW()) )} -> 0 | E69: {=_xlfn.XLOOKUP(1, (INDIRECT("'"&$C$6&"'!$6:$6")=E$6)* (INDIRECT("'"&$C$6&"'!$5:$5")=E$5), INDIRECT("'"&$C$6&"'!"&ROW()&":"&ROW()) )} -> 7600 | F69: {=_xlfn.XLOOKUP(1, (INDIRECT("'"&$C$6&"'!$6:$6")=F$6)* (INDIRECT("'"&$C$6&"'!$5:$5")=F$5), INDIRECT("'"&$C$6&"'!"&ROW()&":"&ROW()) )} -> 0 | G69: {=_xlfn.XLOOKUP(1, (INDIRECT("'"&$C$6&"'!$6:$6")=G$6)* (INDIRECT("'"&$C$6&"'!$5:$5")=G$5), INDIRECT("'"&$C$6&"'!"&ROW()&":"&ROW()) )} -> 0 | H69: {=_xlfn.XLOOKUP(1, (INDIRECT("'"&$C$6&"'!$6:$6")=H$6)* (INDIRECT("'"&$C$6&"'!$5:$5")=H$5), INDIRECT("'"&$C$6&"'!"&ROW()&":"&ROW()) )} -> 0 | I69: {=_xlfn.XLOOKUP(1, (INDIRECT("'"&$C$6&"'!$6:$6")=I$6)* (INDIRECT("'"&$C$6&"'!$5:$5")=I$5), INDIRECT("'"&$C$6&"'!"&ROW()&":"&ROW()) )} -> 0 | K69: =$D69-E69 -> -7600 | L69: =$D69-F69 -> 0 | M69: =$D69-G69 -> 0 | N69: =$D69-H69 -> 0 | O69: =$D69-I69 -> 0 | Q69: =IFERROR($D69/E69-1,0) -> -1 | R69: =IFERROR($D69/F69-1,0) -> 0 | S69: =IFERROR($D69/G69-1,0) -> 0 | T69: =IFERROR($D69/H69-1,0) -> 0 | U69: =IFERROR($D69/I69-1,0) -> 0 | W69: {=INDIRECT("'"&$C$6&"'!"&ADDRESS(ROW(),COLUMN()+44))} -> 0 | X69: {=INDIRECT("'"&$C$6&"'!"&ADDRESS(ROW(),COLUMN()+44))} -> 22800 | Y69: {=INDIRECT("'"&$C$6&"'!"&ADDRESS(ROW(),COLUMN()+44))} -> 0 | Z69: {=INDIRECT("'"&$C$6&"'!"&ADDRESS(ROW(),COLUMN()+44))} -> 0 | AA69: {=INDIRECT("'"&$C$6&"'!"&ADDRESS(ROW(),COLUMN()+44))} -> 0 | AB69: {=INDIRECT("'"&$C$6&"'!"&ADDRESS(ROW(),COLUMN()+44))} -> 0 | AD69: =$W69-X69 -> -22800 | AE69: =$W69-Y69 -> 0 | AF69: =$W69-Z69 -> 0 | AG69: =$W69-AA69 -> 0 | AH69: =$W69-AB69 -> 0 | AJ69: =IFERROR($W69/X69-1,0) -> -1 | AK69: =IFERROR($W69/Y69-1,0) -> 0 | AL69: =IFERROR($W69/Z69-1,0) -> 0 | AM69: =IFERROR($W69/AA69-1,0) -> 0 | AN69: =IFERROR($W69/AB69-1,0) -> 0
A70: INOF | D70: {=_xlfn.XLOOKUP(1, (INDIRECT("'"&$C$6&"'!$6:$6")=D$6)* (INDIRECT("'"&$C$6&"'!$5:$5")=D$5), INDIRECT("'"&$C$6&"'!"&ROW()&":"&ROW()) )} -> 0 | E70: {=_xlfn.XLOOKUP(1, (INDIRECT("'"&$C$6&"'!$6:$6")=E$6)* (INDIRECT("'"&$C$6&"'!$5:$5")=E$5), INDIRECT("'"&$C$6&"'!"&ROW()&":"&ROW()) )} -> 0 | F70: {=_xlfn.XLOOKUP(1, (INDIRECT("'"&$C$6&"'!$6:$6")=F$6)* (INDIRECT("'"&$C$6&"'!$5:$5")=F$5), INDIRECT("'"&$C$6&"'!"&ROW()&":"&ROW()) )} -> 0 | G70: {=_xlfn.XLOOKUP(1, (INDIRECT("'"&$C$6&"'!$6:$6")=G$6)* (INDIRECT("'"&$C$6&"'!$5:$5")=G$5), INDIRECT("'"&$C$6&"'!"&ROW()&":"&ROW()) )} -> 0 | H70: {=_xlfn.XLOOKUP(1, (INDIRECT("'"&$C$6&"'!$6:$6")=H$6)* (INDIRECT("'"&$C$6&"'!$5:$5")=H$5), INDIRECT("'"&$C$6&"'!"&ROW()&":"&ROW()) )} -> 0 | I70: {=_xlfn.XLOOKUP(1, (INDIRECT("'"&$C$6&"'!$6:$6")=I$6)* (INDIRECT("'"&$C$6&"'!$5:$5")=I$5), INDIRECT("'"&$C$6&"'!"&ROW()&":"&ROW()) )} -> 0 | K70: =$D70-E70 -> 0 | L70: =$D70-F70 -> 0 | M70: =$D70-G70 -> 0 | N70: =$D70-H70 -> 0 | O70: =$D70-I70 -> 0 | Q70: =IFERROR($D70/E70-1,0) -> 0 | R70: =IFERROR($D70/F70-1,0) -> 0 | S70: =IFERROR($D70/G70-1,0) -> 0 | T70: =IFERROR($D70/H70-1,0) -> 0 | U70: =IFERROR($D70/I70-1,0) -> 0 | W70: {=INDIRECT("'"&$C$6&"'!"&ADDRESS(ROW(),COLUMN()+44))} -> 0 | X70: {=INDIRECT("'"&$C$6&"'!"&ADDRESS(ROW(),COLUMN()+44))} -> 0 | Y70: {=INDIRECT("'"&$C$6&"'!"&ADDRESS(ROW(),COLUMN()+44))} -> 0 | Z70: {=INDIRECT("'"&$C$6&"'!"&ADDRESS(ROW(),COLUMN()+44))} -> 0 | AA70: {=INDIRECT("'"&$C$6&"'!"&ADDRESS(ROW(),COLUMN()+44))} -> 0 | AB70: {=INDIRECT("'"&$C$6&"'!"&ADDRESS(ROW(),COLUMN()+44))} -> 0 | AD70: =$W70-X70 -> 0 | AE70: =$W70-Y70 -> 0 | AF70: =$W70-Z70 -> 0 | AG70: =$W70-AA70 -> 0 | AH70: =$W70-AB70 -> 0 | AJ70: =IFERROR($W70/X70-1,0) -> 0 | AK70: =IFERROR($W70/Y70-1,0) -> 0 | AL70: =IFERROR($W70/Z70-1,0) -> 0 | AM70: =IFERROR($W70/AA70-1,0) -> 0 | AN70: =IFERROR($W70/AB70-1,0) -> 0
A71: INOF | D71: {=_xlfn.XLOOKUP(1, (INDIRECT("'"&$C$6&"'!$6:$6")=D$6)* (INDIRECT("'"&$C$6&"'!$5:$5")=D$5), INDIRECT("'"&$C$6&"'!"&ROW()&":"&ROW()) )} -> 0 | E71: {=_xlfn.XLOOKUP(1, (INDIRECT("'"&$C$6&"'!$6:$6")=E$6)* (INDIRECT("'"&$C$6&"'!$5:$5")=E$5), INDIRECT("'"&$C$6&"'!"&ROW()&":"&ROW()) )} -> -165 | F71: {=_xlfn.XLOOKUP(1, (INDIRECT("'"&$C$6&"'!$6:$6")=F$6)* (INDIRECT("'"&$C$6&"'!$5:$5")=F$5), INDIRECT("'"&$C$6&"'!"&ROW()&":"&ROW()) )} -> 0 | G71: {=_xlfn.XLOOKUP(1, (INDIRECT("'"&$C$6&"'!$6:$6")=G$6)* (INDIRECT("'"&$C$6&"'!$5:$5")=G$5), INDIRECT("'"&$C$6&"'!"&ROW()&":"&ROW()) )} -> 0 | H71: {=_xlfn.XLOOKUP(1, (INDIRECT("'"&$C$6&"'!$6:$6")=H$6)* (INDIRECT("'"&$C$6&"'!$5:$5")=H$5), INDIRECT("'"&$C$6&"'!"&ROW()&":"&ROW()) )} -> 0 | I71: {=_xlfn.XLOOKUP(1, (INDIRECT("'"&$C$6&"'!$6:$6")=I$6)* (INDIRECT("'"&$C$6&"'!$5:$5")=I$5), INDIRECT("'"&$C$6&"'!"&ROW()&":"&ROW()) )} -> 0 | K71: =$D71-E71 -> 165 | L71: =$D71-F71 -> 0 | M71: =$D71-G71 -> 0 | N71: =$D71-H71 -> 0 | O71: =$D71-I71 -> 0 | Q71: =IFERROR($D71/E71-1,0) -> -1 | R71: =IFERROR($D71/F71-1,0) -> 0 | S71: =IFERROR($D71/G71-1,0) -> 0 | T71: =IFERROR($D71/H71-1,0) -> 0 | U71: =IFERROR($D71/I71-1,0) -> 0 | W71: {=INDIRECT("'"&$C$6&"'!"&ADDRESS(ROW(),COLUMN()+44))} -> 0 | X71: {=INDIRECT("'"&$C$6&"'!"&ADDRESS(ROW(),COLUMN()+44))} -> -495 | Y71: {=INDIRECT("'"&$C$6&"'!"&ADDRESS(ROW(),COLUMN()+44))} -> 0 | Z71: {=INDIRECT("'"&$C$6&"'!"&ADDRESS(ROW(),COLUMN()+44))} -> 0 | AA71: {=INDIRECT("'"&$C$6&"'!"&ADDRESS(ROW(),COLUMN()+44))} -> 0 | AB71: {=INDIRECT("'"&$C$6&"'!"&ADDRESS(ROW(),COLUMN()+44))} -> 0 | AD71: =$W71-X71 -> 495 | AE71: =$W71-Y71 -> 0 | AF71: =$W71-Z71 -> 0 | AG71: =$W71-AA71 -> 0 | AH71: =$W71-AB71 -> 0 | AJ71: =IFERROR($W71/X71-1,0) -> -1 | AK71: =IFERROR($W71/Y71-1,0) -> 0 | AL71: =IFERROR($W71/Z71-1,0) -> 0 | AM71: =IFERROR($W71/AA71-1,0) -> 0 | AN71: =IFERROR($W71/AB71-1,0) -> 0
A72: INOF | D72: {=_xlfn.XLOOKUP(1, (INDIRECT("'"&$C$6&"'!$6:$6")=D$6)* (INDIRECT("'"&$C$6&"'!$5:$5")=D$5), INDIRECT("'"&$C$6&"'!"&ROW()&":"&ROW()) )} -> 0 | E72: {=_xlfn.XLOOKUP(1, (INDIRECT("'"&$C$6&"'!$6:$6")=E$6)* (INDIRECT("'"&$C$6&"'!$5:$5")=E$5), INDIRECT("'"&$C$6&"'!"&ROW()&":"&ROW()) )} -> 0 | F72: {=_xlfn.XLOOKUP(1, (INDIRECT("'"&$C$6&"'!$6:$6")=F$6)* (INDIRECT("'"&$C$6&"'!$5:$5")=F$5), INDIRECT("'"&$C$6&"'!"&ROW()&":"&ROW()) )} -> 0 | G72: {=_xlfn.XLOOKUP(1, (INDIRECT("'"&$C$6&"'!$6:$6")=G$6)* (INDIRECT("'"&$C$6&"'!$5:$5")=G$5), INDIRECT("'"&$C$6&"'!"&ROW()&":"&ROW()) )} -> 0 | H72: {=_xlfn.XLOOKUP(1, (INDIRECT("'"&$C$6&"'!$6:$6")=H$6)* (INDIRECT("'"&$C$6&"'!$5:$5")=H$5), INDIRECT("'"&$C$6&"'!"&ROW()&":"&ROW()) )} -> 0 | I72: {=_xlfn.XLOOKUP(1, (INDIRECT("'"&$C$6&"'!$6:$6")=I$6)* (INDIRECT("'"&$C$6&"'!$5:$5")=I$5), INDIRECT("'"&$C$6&"'!"&ROW()&":"&ROW()) )} -> 0 | K72: =$D72-E72 -> 0 | L72: =$D72-F72 -> 0 | M72: =$D72-G72 -> 0 | N72: =$D72-H72 -> 0 | O72: =$D72-I72 -> 0 | Q72: =IFERROR($D72/E72-1,0) -> 0 | R72: =IFERROR($D72/F72-1,0) -> 0 | S72: =IFERROR($D72/G72-1,0) -> 0 | T72: =IFERROR($D72/H72-1,0) -> 0 | U72: =IFERROR($D72/I72-1,0) -> 0 | W72: {=INDIRECT("'"&$C$6&"'!"&ADDRESS(ROW(),COLUMN()+44))} -> 0 | X72: {=INDIRECT("'"&$C$6&"'!"&ADDRESS(ROW(),COLUMN()+44))} -> 0 | Y72: {=INDIRECT("'"&$C$6&"'!"&ADDRESS(ROW(),COLUMN()+44))} -> 0 | Z72: {=INDIRECT("'"&$C$6&"'!"&ADDRESS(ROW(),COLUMN()+44))} -> 0 | AA72: {=INDIRECT("'"&$C$6&"'!"&ADDRESS(ROW(),COLUMN()+44))} -> 0 | AB72: {=INDIRECT("'"&$C$6&"'!"&ADDRESS(ROW(),COLUMN()+44))} -> 0 | AD72: =$W72-X72 -> 0 | AE72: =$W72-Y72 -> 0 | AF72: =$W72-Z72 -> 0 | AG72: =$W72-AA72 -> 0 | AH72: =$W72-AB72 -> 0 | AJ72: =IFERROR($W72/X72-1,0) -> 0 | AK72: =IFERROR($W72/Y72-1,0) -> 0 | AL72: =IFERROR($W72/Z72-1,0) -> 0 | AM72: =IFERROR($W72/AA72-1,0) -> 0 | AN72: =IFERROR($W72/AB72-1,0) -> 0
A73: INOF | D73: {=_xlfn.XLOOKUP(1, (INDIRECT("'"&$C$6&"'!$6:$6")=D$6)* (INDIRECT("'"&$C$6&"'!$5:$5")=D$5), INDIRECT("'"&$C$6&"'!"&ROW()&":"&ROW()) )} -> 0 | E73: {=_xlfn.XLOOKUP(1, (INDIRECT("'"&$C$6&"'!$6:$6")=E$6)* (INDIRECT("'"&$C$6&"'!$5:$5")=E$5), INDIRECT("'"&$C$6&"'!"&ROW()&":"&ROW()) )} -> 79.182878 | F73: {=_xlfn.XLOOKUP(1, (INDIRECT("'"&$C$6&"'!$6:$6")=F$6)* (INDIRECT("'"&$C$6&"'!$5:$5")=F$5), INDIRECT("'"&$C$6&"'!"&ROW()&":"&ROW()) )} -> 0 | G73: {=_xlfn.XLOOKUP(1, (INDIRECT("'"&$C$6&"'!$6:$6")=G$6)* (INDIRECT("'"&$C$6&"'!$5:$5")=G$5), INDIRECT("'"&$C$6&"'!"&ROW()&":"&ROW()) )} -> 0 | H73: {=_xlfn.XLOOKUP(1, (INDIRECT("'"&$C$6&"'!$6:$6")=H$6)* (INDIRECT("'"&$C$6&"'!$5:$5")=H$5), INDIRECT("'"&$C$6&"'!"&ROW()&":"&ROW()) )} -> 0 | I73: {=_xlfn.XLOOKUP(1, (INDIRECT("'"&$C$6&"'!$6:$6")=I$6)* (INDIRECT("'"&$C$6&"'!$5:$5")=I$5), INDIRECT("'"&$C$6&"'!"&ROW()&":"&ROW()) )} -> 0 | K73: =$D73-E73 -> -79.182878 | L73: =$D73-F73 -> 0 | M73: =$D73-G73 -> 0 | N73: =$D73-H73 -> 0 | O73: =$D73-I73 -> 0 | Q73: =IFERROR($D73/E73-1,0) -> -1 | R73: =IFERROR($D73/F73-1,0) -> 0 | S73: =IFERROR($D73/G73-1,0) -> 0 | T73: =IFERROR($D73/H73-1,0) -> 0 | U73: =IFERROR($D73/I73-1,0) -> 0 | W73: {=INDIRECT("'"&$C$6&"'!"&ADDRESS(ROW(),COLUMN()+44))} -> 0 | X73: {=INDIRECT("'"&$C$6&"'!"&ADDRESS(ROW(),COLUMN()+44))} -> 237.54863 | Y73: {=INDIRECT("'"&$C$6&"'!"&ADDRESS(ROW(),COLUMN()+44))} -> 0 | Z73: {=INDIRECT("'"&$C$6&"'!"&ADDRESS(ROW(),COLUMN()+44))} -> 0 | AA73: {=INDIRECT("'"&$C$6&"'!"&ADDRESS(ROW(),COLUMN()+44))} -> 0 | AB73: {=INDIRECT("'"&$C$6&"'!"&ADDRESS(ROW(),COLUMN()+44))} -> 0 | AD73: =$W73-X73 -> -237.54863 | AE73: =$W73-Y73 -> 0 | AF73: =$W73-Z73 -> 0 | AG73: =$W73-AA73 -> 0 | AH73: =$W73-AB73 -> 0 | AJ73: =IFERROR($W73/X73-1,0) -> -1 | AK73: =IFERROR($W73/Y73-1,0) -> 0 | AL73: =IFERROR($W73/Z73-1,0) -> 0 | AM73: =IFERROR($W73/AA73-1,0) -> 0 | AN73: =IFERROR($W73/AB73-1,0) -> 0
A74: INOF | D74: {=_xlfn.XLOOKUP(1, (INDIRECT("'"&$C$6&"'!$6:$6")=D$6)* (INDIRECT("'"&$C$6&"'!$5:$5")=D$5), INDIRECT("'"&$C$6&"'!"&ROW()&":"&ROW()) )} -> 0 | E74: {=_xlfn.XLOOKUP(1, (INDIRECT("'"&$C$6&"'!$6:$6")=E$6)* (INDIRECT("'"&$C$6&"'!$5:$5")=E$5), INDIRECT("'"&$C$6&"'!"&ROW()&":"&ROW()) )} -> 1021.5 | F74: {=_xlfn.XLOOKUP(1, (INDIRECT("'"&$C$6&"'!$6:$6")=F$6)* (INDIRECT("'"&$C$6&"'!$5:$5")=F$5), INDIRECT("'"&$C$6&"'!"&ROW()&":"&ROW()) )} -> 0 | G74: {=_xlfn.XLOOKUP(1, (INDIRECT("'"&$C$6&"'!$6:$6")=G$6)* (INDIRECT("'"&$C$6&"'!$5:$5")=G$5), INDIRECT("'"&$C$6&"'!"&ROW()&":"&ROW()) )} -> 0 | H74: {=_xlfn.XLOOKUP(1, (INDIRECT("'"&$C$6&"'!$6:$6")=H$6)* (INDIRECT("'"&$C$6&"'!$5:$5")=H$5), INDIRECT("'"&$C$6&"'!"&ROW()&":"&ROW()) )} -> 0 | I74: {=_xlfn.XLOOKUP(1, (INDIRECT("'"&$C$6&"'!$6:$6")=I$6)* (INDIRECT("'"&$C$6&"'!$5:$5")=I$5), INDIRECT("'"&$C$6&"'!"&ROW()&":"&ROW()) )} -> 0 | K74: =$D74-E74 -> -1021.5 | L74: =$D74-F74 -> 0 | M74: =$D74-G74 -> 0 | N74: =$D74-H74 -> 0 | O74: =$D74-I74 -> 0 | Q74: =IFERROR($D74/E74-1,0) -> -1 | R74: =IFERROR($D74/F74-1,0) -> 0 | S74: =IFERROR($D74/G74-1,0) -> 0 | T74: =IFERROR($D74/H74-1,0) -> 0 | U74: =IFERROR($D74/I74-1,0) -> 0 | W74: {=INDIRECT("'"&$C$6&"'!"&ADDRESS(ROW(),COLUMN()+44))} -> 0 | X74: {=INDIRECT("'"&$C$6&"'!"&ADDRESS(ROW(),COLUMN()+44))} -> 1064.5 | Y74: {=INDIRECT("'"&$C$6&"'!"&ADDRESS(ROW(),COLUMN()+44))} -> 0 | Z74: {=INDIRECT("'"&$C$6&"'!"&ADDRESS(ROW(),COLUMN()+44))} -> 0 | AA74: {=INDIRECT("'"&$C$6&"'!"&ADDRESS(ROW(),COLUMN()+44))} -> 0 | AB74: {=INDIRECT("'"&$C$6&"'!"&ADDRESS(ROW(),COLUMN()+44))} -> 0 | AD74: =$W74-X74 -> -1064.5 | AE74: =$W74-Y74 -> 0 | AF74: =$W74-Z74 -> 0 | AG74: =$W74-AA74 -> 0 | AH74: =$W74-AB74 -> 0 | AJ74: =IFERROR($W74/X74-1,0) -> -1 | AK74: =IFERROR($W74/Y74-1,0) -> 0 | AL74: =IFERROR($W74/Z74-1,0) -> 0 | AM74: =IFERROR($W74/AA74-1,0) -> 0 | AN74: =IFERROR($W74/AB74-1,0) -> 0
A75: INOF | D75: {=_xlfn.XLOOKUP(1, (INDIRECT("'"&$C$6&"'!$6:$6")=D$6)* (INDIRECT("'"&$C$6&"'!$5:$5")=D$5), INDIRECT("'"&$C$6&"'!"&ROW()&":"&ROW()) )} -> 0 | E75: {=_xlfn.XLOOKUP(1, (INDIRECT("'"&$C$6&"'!$6:$6")=E$6)* (INDIRECT("'"&$C$6&"'!$5:$5")=E$5), INDIRECT("'"&$C$6&"'!"&ROW()&":"&ROW()) )} -> 26.456371 | F75: {=_xlfn.XLOOKUP(1, (INDIRECT("'"&$C$6&"'!$6:$6")=F$6)* (INDIRECT("'"&$C$6&"'!$5:$5")=F$5), INDIRECT("'"&$C$6&"'!"&ROW()&":"&ROW()) )} -> 0 | G75: {=_xlfn.XLOOKUP(1, (INDIRECT("'"&$C$6&"'!$6:$6")=G$6)* (INDIRECT("'"&$C$6&"'!$5:$5")=G$5), INDIRECT("'"&$C$6&"'!"&ROW()&":"&ROW()) )} -> 0 | H75: {=_xlfn.XLOOKUP(1, (INDIRECT("'"&$C$6&"'!$6:$6")=H$6)* (INDIRECT("'"&$C$6&"'!$5:$5")=H$5), INDIRECT("'"&$C$6&"'!"&ROW()&":"&ROW()) )} -> 0 | I75: {=_xlfn.XLOOKUP(1, (INDIRECT("'"&$C$6&"'!$6:$6")=I$6)* (INDIRECT("'"&$C$6&"'!$5:$5")=I$5), INDIRECT("'"&$C$6&"'!"&ROW()&":"&ROW()) )} -> 0 | K75: =$D75-E75 -> -26.456371 | L75: =$D75-F75 -> 0 | M75: =$D75-G75 -> 0 | N75: =$D75-H75 -> 0 | O75: =$D75-I75 -> 0 | Q75: =IFERROR($D75/E75-1,0) -> -1 | R75: =IFERROR($D75/F75-1,0) -> 0 | S75: =IFERROR($D75/G75-1,0) -> 0 | T75: =IFERROR($D75/H75-1,0) -> 0 | U75: =IFERROR($D75/I75-1,0) -> 0 | W75: {=INDIRECT("'"&$C$6&"'!"&ADDRESS(ROW(),COLUMN()+44))} -> 0 | X75: {=INDIRECT("'"&$C$6&"'!"&ADDRESS(ROW(),COLUMN()+44))} -> 79.369113 | Y75: {=INDIRECT("'"&$C$6&"'!"&ADDRESS(ROW(),COLUMN()+44))} -> 0 | Z75: {=INDIRECT("'"&$C$6&"'!"&ADDRESS(ROW(),COLUMN()+44))} -> 0 | AA75: {=INDIRECT("'"&$C$6&"'!"&ADDRESS(ROW(),COLUMN()+44))} -> 0 | AB75: {=INDIRECT("'"&$C$6&"'!"&ADDRESS(ROW(),COLUMN()+44))} -> 0 | AD75: =$W75-X75 -> -79.369113 | AE75: =$W75-Y75 -> 0 | AF75: =$W75-Z75 -> 0 | AG75: =$W75-AA75 -> 0 | AH75: =$W75-AB75 -> 0 | AJ75: =IFERROR($W75/X75-1,0) -> -1 | AK75: =IFERROR($W75/Y75-1,0) -> 0 | AL75: =IFERROR($W75/Z75-1,0) -> 0 | AM75: =IFERROR($W75/AA75-1,0) -> 0 | AN75: =IFERROR($W75/AB75-1,0) -> 0
A76: INOF | D76: {=_xlfn.XLOOKUP(1, (INDIRECT("'"&$C$6&"'!$6:$6")=D$6)* (INDIRECT("'"&$C$6&"'!$5:$5")=D$5), INDIRECT("'"&$C$6&"'!"&ROW()&":"&ROW()) )} -> 0 | E76: {=_xlfn.XLOOKUP(1, (INDIRECT("'"&$C$6&"'!$6:$6")=E$6)* (INDIRECT("'"&$C$6&"'!$5:$5")=E$5), INDIRECT("'"&$C$6&"'!"&ROW()&":"&ROW()) )} -> 2274.8961 | F76: {=_xlfn.XLOOKUP(1, (INDIRECT("'"&$C$6&"'!$6:$6")=F$6)* (INDIRECT("'"&$C$6&"'!$5:$5")=F$5), INDIRECT("'"&$C$6&"'!"&ROW()&":"&ROW()) )} -> 0 | G76: {=_xlfn.XLOOKUP(1, (INDIRECT("'"&$C$6&"'!$6:$6")=G$6)* (INDIRECT("'"&$C$6&"'!$5:$5")=G$5), INDIRECT("'"&$C$6&"'!"&ROW()&":"&ROW()) )} -> 0 | H76: {=_xlfn.XLOOKUP(1, (INDIRECT("'"&$C$6&"'!$6:$6")=H$6)* (INDIRECT("'"&$C$6&"'!$5:$5")=H$5), INDIRECT("'"&$C$6&"'!"&ROW()&":"&ROW()) )} -> 0 | I76: {=_xlfn.XLOOKUP(1, (INDIRECT("'"&$C$6&"'!$6:$6")=I$6)* (INDIRECT("'"&$C$6&"'!$5:$5")=I$5), INDIRECT("'"&$C$6&"'!"&ROW()&":"&ROW()) )} -> 0 | K76: =$D76-E76 -> -2274.8961 | L76: =$D76-F76 -> 0 | M76: =$D76-G76 -> 0 | N76: =$D76-H76 -> 0 | O76: =$D76-I76 -> 0 | Q76: =IFERROR($D76/E76-1,0) -> -1 | R76: =IFERROR($D76/F76-1,0) -> 0 | S76: =IFERROR($D76/G76-1,0) -> 0 | T76: =IFERROR($D76/H76-1,0) -> 0 | U76: =IFERROR($D76/I76-1,0) -> 0 | W76: {=INDIRECT("'"&$C$6&"'!"&ADDRESS(ROW(),COLUMN()+44))} -> 0 | X76: {=INDIRECT("'"&$C$6&"'!"&ADDRESS(ROW(),COLUMN()+44))} -> 6288.1615 | Y76: {=INDIRECT("'"&$C$6&"'!"&ADDRESS(ROW(),COLUMN()+44))} -> 0 | Z76: {=INDIRECT("'"&$C$6&"'!"&ADDRESS(ROW(),COLUMN()+44))} -> 0 | AA76: {=INDIRECT("'"&$C$6&"'!"&ADDRESS(ROW(),COLUMN()+44))} -> 0 | AB76: {=INDIRECT("'"&$C$6&"'!"&ADDRESS(ROW(),COLUMN()+44))} -> 0 | AD76: =$W76-X76 -> -6288.1615 | AE76: =$W76-Y76 -> 0 | AF76: =$W76-Z76 -> 0 | AG76: =$W76-AA76 -> 0 | AH76: =$W76-AB76 -> 0 | AJ76: =IFERROR($W76/X76-1,0) -> -1 | AK76: =IFERROR($W76/Y76-1,0) -> 0 | AL76: =IFERROR($W76/Z76-1,0) -> 0 | AM76: =IFERROR($W76/AA76-1,0) -> 0 | AN76: =IFERROR($W76/AB76-1,0) -> 0
A77: INOF | D77: {=_xlfn.XLOOKUP(1, (INDIRECT("'"&$C$6&"'!$6:$6")=D$6)* (INDIRECT("'"&$C$6&"'!$5:$5")=D$5), INDIRECT("'"&$C$6&"'!"&ROW()&":"&ROW()) )} -> 0 | E77: {=_xlfn.XLOOKUP(1, (INDIRECT("'"&$C$6&"'!$6:$6")=E$6)* (INDIRECT("'"&$C$6&"'!$5:$5")=E$5), INDIRECT("'"&$C$6&"'!"&ROW()&":"&ROW()) )} -> -7689.9786 | F77: {=_xlfn.XLOOKUP(1, (INDIRECT("'"&$C$6&"'!$6:$6")=F$6)* (INDIRECT("'"&$C$6&"'!$5:$5")=F$5), INDIRECT("'"&$C$6&"'!"&ROW()&":"&ROW()) )} -> 0 | G77: {=_xlfn.XLOOKUP(1, (INDIRECT("'"&$C$6&"'!$6:$6")=G$6)* (INDIRECT("'"&$C$6&"'!$5:$5")=G$5), INDIRECT("'"&$C$6&"'!"&ROW()&":"&ROW()) )} -> 0 | H77: {=_xlfn.XLOOKUP(1, (INDIRECT("'"&$C$6&"'!$6:$6")=H$6)* (INDIRECT("'"&$C$6&"'!$5:$5")=H$5), INDIRECT("'"&$C$6&"'!"&ROW()&":"&ROW()) )} -> 0 | I77: {=_xlfn.XLOOKUP(1, (INDIRECT("'"&$C$6&"'!$6:$6")=I$6)* (INDIRECT("'"&$C$6&"'!$5:$5")=I$5), INDIRECT("'"&$C$6&"'!"&ROW()&":"&ROW()) )} -> 0 | K77: =$D77-E77 -> 7689.9786 | L77: =$D77-F77 -> 0 | M77: =$D77-G77 -> 0 | N77: =$D77-H77 -> 0 | O77: =$D77-I77 -> 0 | Q77: =IFERROR($D77/E77-1,0) -> -1 | R77: =IFERROR($D77/F77-1,0) -> 0 | S77: =IFERROR($D77/G77-1,0) -> 0 | T77: =IFERROR($D77/H77-1,0) -> 0 | U77: =IFERROR($D77/I77-1,0) -> 0 | W77: {=INDIRECT("'"&$C$6&"'!"&ADDRESS(ROW(),COLUMN()+44))} -> 0 | X77: {=INDIRECT("'"&$C$6&"'!"&ADDRESS(ROW(),COLUMN()+44))} -> -24222.817 | Y77: {=INDIRECT("'"&$C$6&"'!"&ADDRESS(ROW(),COLUMN()+44))} -> 0 | Z77: {=INDIRECT("'"&$C$6&"'!"&ADDRESS(ROW(),COLUMN()+44))} -> 0 | AA77: {=INDIRECT("'"&$C$6&"'!"&ADDRESS(ROW(),COLUMN()+44))} -> 0 | AB77: {=INDIRECT("'"&$C$6&"'!"&ADDRESS(ROW(),COLUMN()+44))} -> 0 | AD77: =$W77-X77 -> 24222.817 | AE77: =$W77-Y77 -> 0 | AF77: =$W77-Z77 -> 0 | AG77: =$W77-AA77 -> 0 | AH77: =$W77-AB77 -> 0 | AJ77: =IFERROR($W77/X77-1,0) -> -1 | AK77: =IFERROR($W77/Y77-1,0) -> 0 | AL77: =IFERROR($W77/Z77-1,0) -> 0 | AM77: =IFERROR($W77/AA77-1,0) -> 0 | AN77: =IFERROR($W77/AB77-1,0) -> 0
... A82: INOF | D82: {=_xlfn.XLOOKUP(1, (INDIRECT("'"&$C$6&"'!$6:$6")=D$6)* (INDIRECT("'"&$C$6&"'!$5:$5")=D$5), INDIRECT("'"&$C$6&"'!"&ROW()&":"&ROW()) )} -> 0 | E82: {=_xlfn.XLOOKUP(1, (INDIRECT("'"&$C$6&"'!$6:$6")=E$6)* (INDIRECT("'"&$C$6&"'!$5:$5")=E$5), INDIRECT("'"&$C$6&"'!"&ROW()&":"&ROW()) )} -> 0 | F82: {=_xlfn.XLOOKUP(1, (INDIRECT("'"&$C$6&"'!$6:$6")=F$6)* (INDIRECT("'"&$C$6&"'!$5:$5")=F$5), INDIRECT("'"&$C$6&"'!"&ROW()&":"&ROW()) )} -> 0 | G82: {=_xlfn.XLOOKUP(1, (INDIRECT("'"&$C$6&"'!$6:$6")=G$6)* (INDIRECT("'"&$C$6&"'!$5:$5")=G$5), INDIRECT("'"&$C$6&"'!"&ROW()&":"&ROW()) )} -> 0 | H82: {=_xlfn.XLOOKUP(1, (INDIRECT("'"&$C$6&"'!$6:$6")=H$6)* (INDIRECT("'"&$C$6&"'!$5:$5")=H$5), INDIRECT("'"&$C$6&"'!"&ROW()&":"&ROW()) )} -> 0 | I82: {=_xlfn.XLOOKUP(1, (INDIRECT("'"&$C$6&"'!$6:$6")=I$6)* (INDIRECT("'"&$C$6&"'!$5:$5")=I$5), INDIRECT("'"&$C$6&"'!"&ROW()&":"&ROW()) )} -> 0 | K82: =$D82-E82 -> 0 | L82: =$D82-F82 -> 0 | M82: =$D82-G82 -> 0 | N82: =$D82-H82 -> 0 | O82: =$D82-I82 -> 0 | Q82: =IFERROR($D82/E82-1,0) -> 0 | R82: =IFERROR($D82/F82-1,0) -> 0 | S82: =IFERROR($D82/G82-1,0) -> 0 | T82: =IFERROR($D82/H82-1,0) -> 0 | U82: =IFERROR($D82/I82-1,0) -> 0 | W82: {=INDIRECT("'"&$C$6&"'!"&ADDRESS(ROW(),COLUMN()+44))} -> 0 | X82: {=INDIRECT("'"&$C$6&"'!"&ADDRESS(ROW(),COLUMN()+44))} -> 0 | Y82: {=INDIRECT("'"&$C$6&"'!"&ADDRESS(ROW(),COLUMN()+44))} -> 0 | Z82: {=INDIRECT("'"&$C$6&"'!"&ADDRESS(ROW(),COLUMN()+44))} -> 0 | AA82: {=INDIRECT("'"&$C$6&"'!"&ADDRESS(ROW(),COLUMN()+44))} -> 0 | AB82: {=INDIRECT("'"&$C$6&"'!"&ADDRESS(ROW(),COLUMN()+44))} -> 0 | AD82: =$W82-X82 -> 0 | AE82: =$W82-Y82 -> 0 | AF82: =$W82-Z82 -> 0 | AG82: =$W82-AA82 -> 0 | AH82: =$W82-AB82 -> 0 | AJ82: =IFERROR($W82/X82-1,0) -> 0 | AK82: =IFERROR($W82/Y82-1,0) -> 0 | AL82: =IFERROR($W82/Z82-1,0) -> 0 | AM82: =IFERROR($W82/AA82-1,0) -> 0 | AN82: =IFERROR($W82/AB82-1,0) -> 0
C83: INOF | D83: =SUM(D63:D82) -> 0 | E83: =SUM(E63:E82) -> 28107.863 | F83: =SUM(F63:F82) -> 0 | G83: =SUM(G63:G82) -> 0 | H83: =SUM(H63:H82) -> 0 | I83: =SUM(I63:I82) -> 0 | K83: =$D83-E83 -> -28107.863 | L83: =$D83-F83 -> 0 | M83: =$D83-G83 -> 0 | N83: =$D83-H83 -> 0 | O83: =$D83-I83 -> 0 | Q83: =IFERROR($D83/E83-1,0) -> -1 | R83: =IFERROR($D83/F83-1,0) -> 0 | S83: =IFERROR($D83/G83-1,0) -> 0 | T83: =IFERROR($D83/H83-1,0) -> 0 | U83: =IFERROR($D83/I83-1,0) -> 0 | W83: =SUM(W63:W82) -> 0 | X83: =SUM(X63:X82) -> 75134.826 | Y83: =SUM(Y63:Y82) -> 0 | Z83: =SUM(Z63:Z82) -> 0 | AA83: =SUM(AA63:AA82) -> 0 | AB83: =SUM(AB63:AB82) -> 0 | AD83: =$W83-X83 -> -75134.826 | AE83: =$W83-Y83 -> 0 | AF83: =$W83-Z83 -> 0 | AG83: =$W83-AA83 -> 0 | AH83: =$W83-AB83 -> 0 | AJ83: =IFERROR($W83/X83-1,0) -> -1 | AK83: =IFERROR($W83/Y83-1,0) -> 0 | AL83: =IFERROR($W83/Z83-1,0) -> 0 | AM83: =IFERROR($W83/AA83-1,0) -> 0 | AN83: =IFERROR($W83/AB83-1,0) -> 0
A86: Gastos Operativos | C86: Gasto Directo | D86: {=_xlfn.XLOOKUP(1, (INDIRECT("'"&$C$6&"'!$6:$6")=D$6)* (INDIRECT("'"&$C$6&"'!$5:$5")=D$5), INDIRECT("'"&$C$6&"'!"&ROW()&":"&ROW()) )} -> 0 | E86: {=_xlfn.XLOOKUP(1, (INDIRECT("'"&$C$6&"'!$6:$6")=E$6)* (INDIRECT("'"&$C$6&"'!$5:$5")=E$5), INDIRECT("'"&$C$6&"'!"&ROW()&":"&ROW()) )} -> -30505.695 | F86: {=_xlfn.XLOOKUP(1, (INDIRECT("'"&$C$6&"'!$6:$6")=F$6)* (INDIRECT("'"&$C$6&"'!$5:$5")=F$5), INDIRECT("'"&$C$6&"'!"&ROW()&":"&ROW()) )} -> 0 | G86: {=_xlfn.XLOOKUP(1, (INDIRECT("'"&$C$6&"'!$6:$6")=G$6)* (INDIRECT("'"&$C$6&"'!$5:$5")=G$5), INDIRECT("'"&$C$6&"'!"&ROW()&":"&ROW()) )} -> 0 | H86: {=_xlfn.XLOOKUP(1, (INDIRECT("'"&$C$6&"'!$6:$6")=H$6)* (INDIRECT("'"&$C$6&"'!$5:$5")=H$5), INDIRECT("'"&$C$6&"'!"&ROW()&":"&ROW()) )} -> 0 | I86: {=_xlfn.XLOOKUP(1, (INDIRECT("'"&$C$6&"'!$6:$6")=I$6)* (INDIRECT("'"&$C$6&"'!$5:$5")=I$5), INDIRECT("'"&$C$6&"'!"&ROW()&":"&ROW()) )} -> 0 | K86: =$D86-E86 -> 30505.695 | L86: =$D86-F86 -> 0 | M86: =$D86-G86 -> 0 | N86: =$D86-H86 -> 0 | O86: =$D86-I86 -> 0 | Q86: =IFERROR($D86/E86-1,0) -> -1 | R86: =IFERROR($D86/F86-1,0) -> 0 | S86: =IFERROR($D86/G86-1,0) -> 0 | T86: =IFERROR($D86/H86-1,0) -> 0 | U86: =IFERROR($D86/I86-1,0) -> 0 | W86: {=INDIRECT("'"&$C$6&"'!"&ADDRESS(ROW(),COLUMN()+44))} -> 0 | X86: {=INDIRECT("'"&$C$6&"'!"&ADDRESS(ROW(),COLUMN()+44))} -> -86610.717 | Y86: {=INDIRECT("'"&$C$6&"'!"&ADDRESS(ROW(),COLUMN()+44))} -> 0 | Z86: {=INDIRECT("'"&$C$6&"'!"&ADDRESS(ROW(),COLUMN()+44))} -> 0 | AA86: {=INDIRECT("'"&$C$6&"'!"&ADDRESS(ROW(),COLUMN()+44))} -> 0 | AB86: {=INDIRECT("'"&$C$6&"'!"&ADDRESS(ROW(),COLUMN()+44))} -> 0 | AD86: =$W86-X86 -> 86610.717 | AE86: =$W86-Y86 -> 0 | AF86: =$W86-Z86 -> 0 | AG86: =$W86-AA86 -> 0 | AH86: =$W86-AB86 -> 0 | AJ86: =IFERROR($W86/X86-1,0) -> -1 | AK86: =IFERROR($W86/Y86-1,0) -> 0 | AL86: =IFERROR($W86/Z86-1,0) -> 0 | AM86: =IFERROR($W86/AA86-1,0) -> 0 | AN86: =IFERROR($W86/AB86-1,0) -> 0
A87: Gastos Operativos | C87: Gasto Canal | D87: {=_xlfn.XLOOKUP(1, (INDIRECT("'"&$C$6&"'!$6:$6")=D$6)* (INDIRECT("'"&$C$6&"'!$5:$5")=D$5), INDIRECT("'"&$C$6&"'!"&ROW()&":"&ROW()) )} -> 0 | E87: {=_xlfn.XLOOKUP(1, (INDIRECT("'"&$C$6&"'!$6:$6")=E$6)* (INDIRECT("'"&$C$6&"'!$5:$5")=E$5), INDIRECT("'"&$C$6&"'!"&ROW()&":"&ROW()) )} -> -10259.129 | F87: {=_xlfn.XLOOKUP(1, (INDIRECT("'"&$C$6&"'!$6:$6")=F$6)* (INDIRECT("'"&$C$6&"'!$5:$5")=F$5), INDIRECT("'"&$C$6&"'!"&ROW()&":"&ROW()) )} -> 0 | G87: {=_xlfn.XLOOKUP(1, (INDIRECT("'"&$C$6&"'!$6:$6")=G$6)* (INDIRECT("'"&$C$6&"'!$5:$5")=G$5), INDIRECT("'"&$C$6&"'!"&ROW()&":"&ROW()) )} -> 0 | H87: {=_xlfn.XLOOKUP(1, (INDIRECT("'"&$C$6&"'!$6:$6")=H$6)* (INDIRECT("'"&$C$6&"'!$5:$5")=H$5), INDIRECT("'"&$C$6&"'!"&ROW()&":"&ROW()) )} -> 0 | I87: {=_xlfn.XLOOKUP(1, (INDIRECT("'"&$C$6&"'!$6:$6")=I$6)* (INDIRECT("'"&$C$6&"'!$5:$5")=I$5), INDIRECT("'"&$C$6&"'!"&ROW()&":"&ROW()) )} -> 0 | K87: =$D87-E87 -> 10259.129 | L87: =$D87-F87 -> 0 | M87: =$D87-G87 -> 0 | N87: =$D87-H87 -> 0 | O87: =$D87-I87 -> 0 | Q87: =IFERROR($D87/E87-1,0) -> -1 | R87: =IFERROR($D87/F87-1,0) -> 0 | S87: =IFERROR($D87/G87-1,0) -> 0 | T87: =IFERROR($D87/H87-1,0) -> 0 | U87: =IFERROR($D87/I87-1,0) -> 0 | W87: {=INDIRECT("'"&$C$6&"'!"&ADDRESS(ROW(),COLUMN()+44))} -> 0 | X87: {=INDIRECT("'"&$C$6&"'!"&ADDRESS(ROW(),COLUMN()+44))} -> -29502.628 | Y87: {=INDIRECT("'"&$C$6&"'!"&ADDRESS(ROW(),COLUMN()+44))} -> 0 | Z87: {=INDIRECT("'"&$C$6&"'!"&ADDRESS(ROW(),COLUMN()+44))} -> 0 | AA87: {=INDIRECT("'"&$C$6&"'!"&ADDRESS(ROW(),COLUMN()+44))} -> 0 | AB87: {=INDIRECT("'"&$C$6&"'!"&ADDRESS(ROW(),COLUMN()+44))} -> 0 | AD87: =$W87-X87 -> 29502.628 | AE87: =$W87-Y87 -> 0 | AF87: =$W87-Z87 -> 0 | AG87: =$W87-AA87 -> 0 | AH87: =$W87-AB87 -> 0 | AJ87: =IFERROR($W87/X87-1,0) -> -1 | AK87: =IFERROR($W87/Y87-1,0) -> 0 | AL87: =IFERROR($W87/Z87-1,0) -> 0 | AM87: =IFERROR($W87/AA87-1,0) -> 0 | AN87: =IFERROR($W87/AB87-1,0) -> 0
A88: Gastos Operativos | C88: Gasto Indirecto | D88: {=_xlfn.XLOOKUP(1, (INDIRECT("'"&$C$6&"'!$6:$6")=D$6)* (INDIRECT("'"&$C$6&"'!$5:$5")=D$5), INDIRECT("'"&$C$6&"'!"&ROW()&":"&ROW()) )} -> 0 | E88: {=_xlfn.XLOOKUP(1, (INDIRECT("'"&$C$6&"'!$6:$6")=E$6)* (INDIRECT("'"&$C$6&"'!$5:$5")=E$5), INDIRECT("'"&$C$6&"'!"&ROW()&":"&ROW()) )} -> -9214.7214 | F88: {=_xlfn.XLOOKUP(1, (INDIRECT("'"&$C$6&"'!$6:$6")=F$6)* (INDIRECT("'"&$C$6&"'!$5:$5")=F$5), INDIRECT("'"&$C$6&"'!"&ROW()&":"&ROW()) )} -> 0 | G88: {=_xlfn.XLOOKUP(1, (INDIRECT("'"&$C$6&"'!$6:$6")=G$6)* (INDIRECT("'"&$C$6&"'!$5:$5")=G$5), INDIRECT("'"&$C$6&"'!"&ROW()&":"&ROW()) )} -> 0 | H88: {=_xlfn.XLOOKUP(1, (INDIRECT("'"&$C$6&"'!$6:$6")=H$6)* (INDIRECT("'"&$C$6&"'!$5:$5")=H$5), INDIRECT("'"&$C$6&"'!"&ROW()&":"&ROW()) )} -> 0 | I88: {=_xlfn.XLOOKUP(1, (INDIRECT("'"&$C$6&"'!$6:$6")=I$6)* (INDIRECT("'"&$C$6&"'!$5:$5")=I$5), INDIRECT("'"&$C$6&"'!"&ROW()&":"&ROW()) )} -> 0 | K88: =$D88-E88 -> 9214.7214 | L88: =$D88-F88 -> 0 | M88: =$D88-G88 -> 0 | N88: =$D88-H88 -> 0 | O88: =$D88-I88 -> 0 | Q88: =IFERROR($D88/E88-1,0) -> -1 | R88: =IFERROR($D88/F88-1,0) -> 0 | S88: =IFERROR($D88/G88-1,0) -> 0 | T88: =IFERROR($D88/H88-1,0) -> 0 | U88: =IFERROR($D88/I88-1,0) -> 0 | W88: {=INDIRECT("'"&$C$6&"'!"&ADDRESS(ROW(),COLUMN()+44))} -> 0 | X88: {=INDIRECT("'"&$C$6&"'!"&ADDRESS(ROW(),COLUMN()+44))} -> -27118.722 | Y88: {=INDIRECT("'"&$C$6&"'!"&ADDRESS(ROW(),COLUMN()+44))} -> 0 | Z88: {=INDIRECT("'"&$C$6&"'!"&ADDRESS(ROW(),COLUMN()+44))} -> 0 | AA88: {=INDIRECT("'"&$C$6&"'!"&ADDRESS(ROW(),COLUMN()+44))} -> 0 | AB88: {=INDIRECT("'"&$C$6&"'!"&ADDRESS(ROW(),COLUMN()+44))} -> 0 | AD88: =$W88-X88 -> 27118.722 | AE88: =$W88-Y88 -> 0 | AF88: =$W88-Z88 -> 0 | AG88: =$W88-AA88 -> 0 | AH88: =$W88-AB88 -> 0 | AJ88: =IFERROR($W88/X88-1,0) -> -1 | AK88: =IFERROR($W88/Y88-1,0) -> 0 | AL88: =IFERROR($W88/Z88-1,0) -> 0 | AM88: =IFERROR($W88/AA88-1,0) -> 0 | AN88: =IFERROR($W88/AB88-1,0) -> 0
C89: Gastos Operativos | D89: =SUM(D86:D88) -> 0 | E89: =SUM(E86:E88) -> -49979.546 | F89: =SUM(F86:F88) -> 0 | G89: =SUM(G86:G88) -> 0 | H89: =SUM(H86:H88) -> 0 | I89: =SUM(I86:I88) -> 0 | K89: =$D89-E89 -> 49979.546 | L89: =$D89-F89 -> 0 | M89: =$D89-G89 -> 0 | N89: =$D89-H89 -> 0 | O89: =$D89-I89 -> 0 | Q89: =IFERROR($D89/E89-1,0) -> -1 | R89: =IFERROR($D89/F89-1,0) -> 0 | S89: =IFERROR($D89/G89-1,0) -> 0 | T89: =IFERROR($D89/H89-1,0) -> 0 | U89: =IFERROR($D89/I89-1,0) -> 0 | W89: =SUM(W86:W88) -> 0 | X89: =SUM(X86:X88) -> -143232.07 | Y89: =SUM(Y86:Y88) -> 0 | Z89: =SUM(Z86:Z88) -> 0 | AA89: =SUM(AA86:AA88) -> 0 | AB89: =SUM(AB86:AB88) -> 0 | AD89: =$W89-X89 -> 143232.07 | AE89: =$W89-Y89 -> 0 | AF89: =$W89-Z89 -> 0 | AG89: =$W89-AA89 -> 0 | AH89: =$W89-AB89 -> 0 | AJ89: =IFERROR($W89/X89-1,0) -> -1 | AK89: =IFERROR($W89/Y89-1,0) -> 0 | AL89: =IFERROR($W89/Z89-1,0) -> 0 | AM89: =IFERROR($W89/AA89-1,0) -> 0 | AN89: =IFERROR($W89/AB89-1,0) -> 0
A91: Extraordinarios | C91: Donaciones | D91: {=_xlfn.XLOOKUP(1, (INDIRECT("'"&$C$6&"'!$6:$6")=D$6)* (INDIRECT("'"&$C$6&"'!$5:$5")=D$5), INDIRECT("'"&$C$6&"'!"&ROW()&":"&ROW()) )} -> 0 | E91: {=_xlfn.XLOOKUP(1, (INDIRECT("'"&$C$6&"'!$6:$6")=E$6)* (INDIRECT("'"&$C$6&"'!$5:$5")=E$5), INDIRECT("'"&$C$6&"'!"&ROW()&":"&ROW()) )} -> 0 | F91: {=_xlfn.XLOOKUP(1, (INDIRECT("'"&$C$6&"'!$6:$6")=F$6)* (INDIRECT("'"&$C$6&"'!$5:$5")=F$5), INDIRECT("'"&$C$6&"'!"&ROW()&":"&ROW()) )} -> 0 | G91: {=_xlfn.XLOOKUP(1, (INDIRECT("'"&$C$6&"'!$6:$6")=G$6)* (INDIRECT("'"&$C$6&"'!$5:$5")=G$5), INDIRECT("'"&$C$6&"'!"&ROW()&":"&ROW()) )} -> 0 | H91: {=_xlfn.XLOOKUP(1, (INDIRECT("'"&$C$6&"'!$6:$6")=H$6)* (INDIRECT("'"&$C$6&"'!$5:$5")=H$5), INDIRECT("'"&$C$6&"'!"&ROW()&":"&ROW()) )} -> 0 | I91: {=_xlfn.XLOOKUP(1, (INDIRECT("'"&$C$6&"'!$6:$6")=I$6)* (INDIRECT("'"&$C$6&"'!$5:$5")=I$5), INDIRECT("'"&$C$6&"'!"&ROW()&":"&ROW()) )} -> 0 | K91: =$D91-E91 -> 0 | L91: =$D91-F91 -> 0 | M91: =$D91-G91 -> 0 | N91: =$D91-H91 -> 0 | O91: =$D91-I91 -> 0 | Q91: =IFERROR($D91/E91-1,0) -> 0 | R91: =IFERROR($D91/F91-1,0) -> 0 | S91: =IFERROR($D91/G91-1,0) -> 0 | T91: =IFERROR($D91/H91-1,0) -> 0 | U91: =IFERROR($D91/I91-1,0) -> 0 | W91: {=INDIRECT("'"&$C$6&"'!"&ADDRESS(ROW(),COLUMN()+44))} -> 0 | X91: {=INDIRECT("'"&$C$6&"'!"&ADDRESS(ROW(),COLUMN()+44))} -> 0 | Y91: {=INDIRECT("'"&$C$6&"'!"&ADDRESS(ROW(),COLUMN()+44))} -> 0 | Z91: {=INDIRECT("'"&$C$6&"'!"&ADDRESS(ROW(),COLUMN()+44))} -> 0 | AA91: {=INDIRECT("'"&$C$6&"'!"&ADDRESS(ROW(),COLUMN()+44))} -> 0 | AB91: {=INDIRECT("'"&$C$6&"'!"&ADDRESS(ROW(),COLUMN()+44))} -> 0 | AD91: =$W91-X91 -> 0 | AE91: =$W91-Y91 -> 0 | AF91: =$W91-Z91 -> 0 | AG91: =$W91-AA91 -> 0 | AH91: =$W91-AB91 -> 0 | AJ91: =IFERROR($W91/X91-1,0) -> 0 | AK91: =IFERROR($W91/Y91-1,0) -> 0 | AL91: =IFERROR($W91/Z91-1,0) -> 0 | AM91: =IFERROR($W91/AA91-1,0) -> 0 | AN91: =IFERROR($W91/AB91-1,0) -> 0
A92: Extraordinarios | C92: Otros | D92: {=_xlfn.XLOOKUP(1, (INDIRECT("'"&$C$6&"'!$6:$6")=D$6)* (INDIRECT("'"&$C$6&"'!$5:$5")=D$5), INDIRECT("'"&$C$6&"'!"&ROW()&":"&ROW()) )} -> 0 | E92: {=_xlfn.XLOOKUP(1, (INDIRECT("'"&$C$6&"'!$6:$6")=E$6)* (INDIRECT("'"&$C$6&"'!$5:$5")=E$5), INDIRECT("'"&$C$6&"'!"&ROW()&":"&ROW()) )} -> -1502.1685 | F92: {=_xlfn.XLOOKUP(1, (INDIRECT("'"&$C$6&"'!$6:$6")=F$6)* (INDIRECT("'"&$C$6&"'!$5:$5")=F$5), INDIRECT("'"&$C$6&"'!"&ROW()&":"&ROW()) )} -> 0 | G92: {=_xlfn.XLOOKUP(1, (INDIRECT("'"&$C$6&"'!$6:$6")=G$6)* (INDIRECT("'"&$C$6&"'!$5:$5")=G$5), INDIRECT("'"&$C$6&"'!"&ROW()&":"&ROW()) )} -> 0 | H92: {=_xlfn.XLOOKUP(1, (INDIRECT("'"&$C$6&"'!$6:$6")=H$6)* (INDIRECT("'"&$C$6&"'!$5:$5")=H$5), INDIRECT("'"&$C$6&"'!"&ROW()&":"&ROW()) )} -> 0 | I92: {=_xlfn.XLOOKUP(1, (INDIRECT("'"&$C$6&"'!$6:$6")=I$6)* (INDIRECT("'"&$C$6&"'!$5:$5")=I$5), INDIRECT("'"&$C$6&"'!"&ROW()&":"&ROW()) )} -> 0 | K92: =$D92-E92 -> 1502.1685 | L92: =$D92-F92 -> 0 | M92: =$D92-G92 -> 0 | N92: =$D92-H92 -> 0 | O92: =$D92-I92 -> 0 | Q92: =IFERROR($D92/E92-1,0) -> -1 | R92: =IFERROR($D92/F92-1,0) -> 0 | S92: =IFERROR($D92/G92-1,0) -> 0 | T92: =IFERROR($D92/H92-1,0) -> 0 | U92: =IFERROR($D92/I92-1,0) -> 0 | W92: {=INDIRECT("'"&$C$6&"'!"&ADDRESS(ROW(),COLUMN()+44))} -> 0 | X92: {=INDIRECT("'"&$C$6&"'!"&ADDRESS(ROW(),COLUMN()+44))} -> -4321.2798 | Y92: {=INDIRECT("'"&$C$6&"'!"&ADDRESS(ROW(),COLUMN()+44))} -> 0 | Z92: {=INDIRECT("'"&$C$6&"'!"&ADDRESS(ROW(),COLUMN()+44))} -> 0 | AA92: {=INDIRECT("'"&$C$6&"'!"&ADDRESS(ROW(),COLUMN()+44))} -> 0 | AB92: {=INDIRECT("'"&$C$6&"'!"&ADDRESS(ROW(),COLUMN()+44))} -> 0 | AD92: =$W92-X92 -> 4321.2798 | AE92: =$W92-Y92 -> 0 | AF92: =$W92-Z92 -> 0 | AG92: =$W92-AA92 -> 0 | AH92: =$W92-AB92 -> 0 | AJ92: =IFERROR($W92/X92-1,0) -> -1 | AK92: =IFERROR($W92/Y92-1,0) -> 0 | AL92: =IFERROR($W92/Z92-1,0) -> 0 | AM92: =IFERROR($W92/AA92-1,0) -> 0 | AN92: =IFERROR($W92/AB92-1,0) -> 0
C93: Extraordinarios | D93: =SUM(D91:D92) -> 0 | E93: =SUM(E91:E92) -> -1502.1685 | F93: =SUM(F91:F92) -> 0 | G93: =SUM(G91:G92) -> 0 | H93: =SUM(H91:H92) -> 0 | I93: =SUM(I91:I92) -> 0 | K93: =$D93-E93 -> 1502.1685 | L93: =$D93-F93 -> 0 | M93: =$D93-G93 -> 0 | N93: =$D93-H93 -> 0 | O93: =$D93-I93 -> 0 | Q93: =IFERROR($D93/E93-1,0) -> -1 | R93: =IFERROR($D93/F93-1,0) -> 0 | S93: =IFERROR($D93/G93-1,0) -> 0 | T93: =IFERROR($D93/H93-1,0) -> 0 | U93: =IFERROR($D93/I93-1,0) -> 0 | W93: =SUM(W91:W92) -> 0 | X93: =SUM(X91:X92) -> -4321.2798 | Y93: =SUM(Y91:Y92) -> 0 | Z93: =SUM(Z91:Z92) -> 0 | AA93: =SUM(AA91:AA92) -> 0 | AB93: =SUM(AB91:AB92) -> 0 | AD93: =$W93-X93 -> 4321.2798 | AE93: =$W93-Y93 -> 0 | AF93: =$W93-Z93 -> 0 | AG93: =$W93-AA93 -> 0 | AH93: =$W93-AB93 -> 0 | AJ93: =IFERROR($W93/X93-1,0) -> -1 | AK93: =IFERROR($W93/Y93-1,0) -> 0 | AL93: =IFERROR($W93/Z93-1,0) -> 0 | AM93: =IFERROR($W93/AA93-1,0) -> 0 | AN93: =IFERROR($W93/AB93-1,0) -> 0
A95: ROF | C95: Venta de Cartera | D95: {=_xlfn.XLOOKUP(1, (INDIRECT("'"&$C$6&"'!$6:$6")=D$6)* (INDIRECT("'"&$C$6&"'!$5:$5")=D$5), INDIRECT("'"&$C$6&"'!"&ROW()&":"&ROW()) )} -> 0 | E95: {=_xlfn.XLOOKUP(1, (INDIRECT("'"&$C$6&"'!$6:$6")=E$6)* (INDIRECT("'"&$C$6&"'!$5:$5")=E$5), INDIRECT("'"&$C$6&"'!"&ROW()&":"&ROW()) )} -> 0 | F95: {=_xlfn.XLOOKUP(1, (INDIRECT("'"&$C$6&"'!$6:$6")=F$6)* (INDIRECT("'"&$C$6&"'!$5:$5")=F$5), INDIRECT("'"&$C$6&"'!"&ROW()&":"&ROW()) )} -> 0 | G95: {=_xlfn.XLOOKUP(1, (INDIRECT("'"&$C$6&"'!$6:$6")=G$6)* (INDIRECT("'"&$C$6&"'!$5:$5")=G$5), INDIRECT("'"&$C$6&"'!"&ROW()&":"&ROW()) )} -> 0 | H95: {=_xlfn.XLOOKUP(1, (INDIRECT("'"&$C$6&"'!$6:$6")=H$6)* (INDIRECT("'"&$C$6&"'!$5:$5")=H$5), INDIRECT("'"&$C$6&"'!"&ROW()&":"&ROW()) )} -> 0 | I95: {=_xlfn.XLOOKUP(1, (INDIRECT("'"&$C$6&"'!$6:$6")=I$6)* (INDIRECT("'"&$C$6&"'!$5:$5")=I$5), INDIRECT("'"&$C$6&"'!"&ROW()&":"&ROW()) )} -> 0 | K95: =$D95-E95 -> 0 | L95: =$D95-F95 -> 0 | M95: =$D95-G95 -> 0 | N95: =$D95-H95 -> 0 | O95: =$D95-I95 -> 0 | Q95: =IFERROR($D95/E95-1,0) -> 0 | R95: =IFERROR($D95/F95-1,0) -> 0 | S95: =IFERROR($D95/G95-1,0) -> 0 | T95: =IFERROR($D95/H95-1,0) -> 0 | U95: =IFERROR($D95/I95-1,0) -> 0 | W95: {=INDIRECT("'"&$C$6&"'!"&ADDRESS(ROW(),COLUMN()+44))} -> 0 | X95: {=INDIRECT("'"&$C$6&"'!"&ADDRESS(ROW(),COLUMN()+44))} -> 0 | Y95: {=INDIRECT("'"&$C$6&"'!"&ADDRESS(ROW(),COLUMN()+44))} -> 0 | Z95: {=INDIRECT("'"&$C$6&"'!"&ADDRESS(ROW(),COLUMN()+44))} -> 0 | AA95: {=INDIRECT("'"&$C$6&"'!"&ADDRESS(ROW(),COLUMN()+44))} -> 0 | AB95: {=INDIRECT("'"&$C$6&"'!"&ADDRESS(ROW(),COLUMN()+44))} -> 0 | AD95: =$W95-X95 -> 0 | AE95: =$W95-Y95 -> 0 | AF95: =$W95-Z95 -> 0 | AG95: =$W95-AA95 -> 0 | AH95: =$W95-AB95 -> 0 | AJ95: =IFERROR($W95/X95-1,0) -> 0 | AK95: =IFERROR($W95/Y95-1,0) -> 0 | AL95: =IFERROR($W95/Z95-1,0) -> 0 | AM95: =IFERROR($W95/AA95-1,0) -> 0 | AN95: =IFERROR($W95/AB95-1,0) -> 0
C96: ROF | D96: =SUM(D95:D95) -> 0 | E96: =SUM(E95:E95) -> 0 | F96: =SUM(F95:F95) -> 0 | G96: =SUM(G95:G95) -> 0 | H96: =SUM(H95:H95) -> 0 | I96: =SUM(I95:I95) -> 0 | K96: =$D96-E96 -> 0 | L96: =$D96-F96 -> 0 | M96: =$D96-G96 -> 0 | N96: =$D96-H96 -> 0 | O96: =$D96-I96 -> 0 | Q96: =IFERROR($D96/E96-1,0) -> 0 | R96: =IFERROR($D96/F96-1,0) -> 0 | S96: =IFERROR($D96/G96-1,0) -> 0 | T96: =IFERROR($D96/H96-1,0) -> 0 | U96: =IFERROR($D96/I96-1,0) -> 0 | W96: =SUM(W95:W95) -> 0 | X96: =SUM(X95:X95) -> 0 | Y96: =SUM(Y95:Y95) -> 0 | Z96: =SUM(Z95:Z95) -> 0 | AA96: =SUM(AA95:AA95) -> 0 | AB96: =SUM(AB95:AB95) -> 0 | AD96: =$W96-X96 -> 0 | AE96: =$W96-Y96 -> 0 | AF96: =$W96-Z96 -> 0 | AG96: =$W96-AA96 -> 0 | AH96: =$W96-AB96 -> 0 | AJ96: =IFERROR($W96/X96-1,0) -> 0 | AK96: =IFERROR($W96/Y96-1,0) -> 0 | AL96: =IFERROR($W96/Z96-1,0) -> 0 | AM96: =IFERROR($W96/AA96-1,0) -> 0 | AN96: =IFERROR($W96/AB96-1,0) -> 0
C98: UAI | D98: =D60+D83+D89+D93+D96 -> 0 | E98: =E60+E83+E89+E93+E96 -> 13038.774 | F98: =F60+F83+F89+F93+F96 -> 0 | G98: =G60+G83+G89+G93+G96 -> 0 | H98: =H60+H83+H89+H93+H96 -> 0 | I98: =I60+I83+I89+I93+I96 -> 0 | K98: =$D98-E98 -> -13038.774 | L98: =$D98-F98 -> 0 | M98: =$D98-G98 -> 0 | N98: =$D98-H98 -> 0 | O98: =$D98-I98 -> 0 | Q98: =IFERROR($D98/E98-1,0) -> -1 | R98: =IFERROR($D98/F98-1,0) -> 0 | S98: =IFERROR($D98/G98-1,0) -> 0 | T98: =IFERROR($D98/H98-1,0) -> 0 | U98: =IFERROR($D98/I98-1,0) -> 0 | W98: =W60+W83+W89+W93+W96 -> 0 | X98: =X60+X83+X89+X93+X96 -> 28082.691 | Y98: =Y60+Y83+Y89+Y93+Y96 -> 0 | Z98: =Z60+Z83+Z89+Z93+Z96 -> 0 | AA98: =AA60+AA83+AA89+AA93+AA96 -> 0 | AB98: =AB60+AB83+AB89+AB93+AB96 -> 0 | AD98: =$W98-X98 -> -28082.691 | AE98: =$W98-Y98 -> 0 | AF98: =$W98-Z98 -> 0 | AG98: =$W98-AA98 -> 0 | AH98: =$W98-AB98 -> 0 | AJ98: =IFERROR($W98/X98-1,0) -> -1 | AK98: =IFERROR($W98/Y98-1,0) -> 0 | AL98: =IFERROR($W98/Z98-1,0) -> 0 | AM98: =IFERROR($W98/AA98-1,0) -> 0 | AN98: =IFERROR($W98/AB98-1,0) -> 0
C102: Prom SFdP | D102: {=_xlfn.XLOOKUP(1, (INDIRECT("'"&$C$6&"'!$6:$6")=D$6)* (INDIRECT("'"&$C$6&"'!$5:$5")=D$5), INDIRECT("'"&$C$6&"'!"&ROW()&":"&ROW()) )} -> 0 | E102: {=_xlfn.XLOOKUP(1, (INDIRECT("'"&$C$6&"'!$6:$6")=E$6)* (INDIRECT("'"&$C$6&"'!$5:$5")=E$5), INDIRECT("'"&$C$6&"'!"&ROW()&":"&ROW()) )} -> 0 | F102: {=_xlfn.XLOOKUP(1, (INDIRECT("'"&$C$6&"'!$6:$6")=F$6)* (INDIRECT("'"&$C$6&"'!$5:$5")=F$5), INDIRECT("'"&$C$6&"'!"&ROW()&":"&ROW()) )} -> 0 | G102: {=_xlfn.XLOOKUP(1, (INDIRECT("'"&$C$6&"'!$6:$6")=G$6)* (INDIRECT("'"&$C$6&"'!$5:$5")=G$5), INDIRECT("'"&$C$6&"'!"&ROW()&":"&ROW()) )} -> 0 | H102: {=_xlfn.XLOOKUP(1, (INDIRECT("'"&$C$6&"'!$6:$6")=H$6)* (INDIRECT("'"&$C$6&"'!$5:$5")=H$5), INDIRECT("'"&$C$6&"'!"&ROW()&":"&ROW()) )} -> 0 | I102: {=_xlfn.XLOOKUP(1, (INDIRECT("'"&$C$6&"'!$6:$6")=I$6)* (INDIRECT("'"&$C$6&"'!$5:$5")=I$5), INDIRECT("'"&$C$6&"'!"&ROW()&":"&ROW()) )} -> 0 | W102: {=INDIRECT("'"&$C$6&"'!"&ADDRESS(ROW(),COLUMN()+44))} -> 0 | X102: {=INDIRECT("'"&$C$6&"'!"&ADDRESS(ROW(),COLUMN()+44))} -> 0 | Y102: {=INDIRECT("'"&$C$6&"'!"&ADDRESS(ROW(),COLUMN()+44))} -> 0 | Z102: {=INDIRECT("'"&$C$6&"'!"&ADDRESS(ROW(),COLUMN()+44))} -> 0 | AA102: {=INDIRECT("'"&$C$6&"'!"&ADDRESS(ROW(),COLUMN()+44))} -> 0 | AB102: {=INDIRECT("'"&$C$6&"'!"&ADDRESS(ROW(),COLUMN()+44))} -> 0

Sheet Indicadores
C1: Mensual | P1: Acumulado
J2: Variación % | W2: Variación %
B3: =Desempeño_Financiero!C6 -> Total_Producto | C3: =Desempeño_Financiero!D6 -> 46112 | D3: =Desempeño_Financiero!E6 -> 46112 | E3: =Desempeño_Financiero!F6 -> 46081 | F3: =Desempeño_Financiero!G6 -> 45747 | G3: =Desempeño_Financiero!H6 -> 45382 | H3: =Desempeño_Financiero!I6 -> 45016 | J3: =D3 -> 46112 | K3: =E3 -> 46081 | L3: =F3 -> 45747 | M3: =G3 -> 45382 | N3: =H3 -> 45016 | P3: =C3 -> 46112 | Q3: =D3 -> 46112 | R3: =E3 -> 46081 | S3: =F3 -> 45747 | T3: =G3 -> 45382 | U3: =H3 -> 45016 | W3: =Q3 -> 46112 | X3: =R3 -> 46081 | Y3: =S3 -> 45747 | Z3: =T3 -> 45382 | AA3: =U3 -> 45016
B5: Eficiencia | C5: =IFERROR((-Desempeño_Financiero!D89)/(Desempeño_Financiero!D53+Desempeño_Financiero!D83+Desempeño_Financiero!D96),0) -> 0 | D5: =IFERROR((-Desempeño_Financiero!E89)/(Desempeño_Financiero!E53+Desempeño_Financiero!E83+Desempeño_Financiero!E96),0) -> 0.4173866 | E5: =IFERROR((-Desempeño_Financiero!F89)/(Desempeño_Financiero!F53+Desempeño_Financiero!F83+Desempeño_Financiero!F96),0) -> 0 | F5: =IFERROR((-Desempeño_Financiero!G89)/(Desempeño_Financiero!G53+Desempeño_Financiero!G83+Desempeño_Financiero!G96),0) -> 0 | G5: =IFERROR((-Desempeño_Financiero!H89)/(Desempeño_Financiero!H53+Desempeño_Financiero!H83+Desempeño_Financiero!H96),0) -> 0 | H5: =IFERROR((-Desempeño_Financiero!I89)/(Desempeño_Financiero!I53+Desempeño_Financiero!I83+Desempeño_Financiero!I96),0) -> 0 | J5: =IFERROR(($C5-D5)*10000,0) -> -4173.866 | K5: =IFERROR(($C5-E5)*10000,0) -> 0 | L5: =IFERROR(($C5-F5)*10000,0) -> 0 | M5: =IFERROR(($C5-G5)*10000,0) -> 0 | N5: =IFERROR(($C5-H5)*10000,0) -> 0 | P5: =IFERROR((-Desempeño_Financiero!W89)/(Desempeño_Financiero!W53+Desempeño_Financiero!W83+Desempeño_Financiero!W96),0) -> 0 | Q5: =IFERROR((-Desempeño_Financiero!X89)/(Desempeño_Financiero!X53+Desempeño_Financiero!X83+Desempeño_Financiero!X96),0) -> 0.43058563 | R5: =IFERROR((-Desempeño_Financiero!Y89)/(Desempeño_Financiero!Y53+Desempeño_Financiero!Y83+Desempeño_Financiero!Y96),0) -> 0 | S5: =IFERROR((-Desempeño_Financiero!Z89)/(Desempeño_Financiero!Z53+Desempeño_Financiero!Z83+Desempeño_Financiero!Z96),0) -> 0 | T5: =IFERROR((-Desempeño_Financiero!AA89)/(Desempeño_Financiero!AA53+Desempeño_Financiero!AA83+Desempeño_Financiero!AA96),0) -> 0 | U5: =IFERROR((-Desempeño_Financiero!AB89)/(Desempeño_Financiero!AB53+Desempeño_Financiero!AB83+Desempeño_Financiero!AB96),0) -> 0 | W5: =IFERROR(($P5-Q5)*10000,0) -> -4305.8563 | X5: =IFERROR(($P5-R5)*10000,0) -> 0 | Y5: =IFERROR(($P5-S5)*10000,0) -> 0 | Z5: =IFERROR(($P5-T5)*10000,0) -> 0 | AA5: =IFERROR(($P5-U5)*10000,0) -> 0
B7: Rendimiento de Colocaciones | C7: =Desempeño_Financiero!D23 -> 0 | D7: =Desempeño_Financiero!E23 -> 0.25618833 | E7: =Desempeño_Financiero!F23 -> 0 | F7: =Desempeño_Financiero!G23 -> 0 | G7: =Desempeño_Financiero!H23 -> 0 | H7: =Desempeño_Financiero!I23 -> 0 | J7: =IFERROR(($C7-D7)*10000,0) -> -2561.8833 | K7: =IFERROR(($C7-E7)*10000,0) -> 0 | L7: =IFERROR(($C7-F7)*10000,0) -> 0 | M7: =IFERROR(($C7-G7)*10000,0) -> 0 | N7: =IFERROR(($C7-H7)*10000,0) -> 0 | P7: =Desempeño_Financiero!W23 -> 0 | Q7: =Desempeño_Financiero!X23 -> 0.24944315 | R7: =Desempeño_Financiero!Y23 -> 0 | S7: =Desempeño_Financiero!Z23 -> 0 | T7: =Desempeño_Financiero!AA23 -> 0 | U7: =Desempeño_Financiero!AB23 -> 0 | W7: =IFERROR(($P7-Q7)*10000,0) -> -2494.4315 | X7: =IFERROR(($P7-R7)*10000,0) -> 0 | Y7: =IFERROR(($P7-S7)*10000,0) -> 0 | Z7: =IFERROR(($P7-T7)*10000,0) -> 0 | AA7: =IFERROR(($P7-U7)*10000,0) -> 0
B9: INOF / Ingresos Totales | C9: =IFERROR((Desempeño_Financiero!D83)/(Desempeño_Financiero!D53+Desempeño_Financiero!D83+Desempeño_Financiero!D96),0) -> 0 | D9: =IFERROR((Desempeño_Financiero!E83)/(Desempeño_Financiero!E53+Desempeño_Financiero!E83+Desempeño_Financiero!E96),0) -> 0.23473294 | E9: =IFERROR((Desempeño_Financiero!F83)/(Desempeño_Financiero!F53+Desempeño_Financiero!F83+Desempeño_Financiero!F96),0) -> 0 | F9: =IFERROR((Desempeño_Financiero!G83)/(Desempeño_Financiero!G53+Desempeño_Financiero!G83+Desempeño_Financiero!G96),0) -> 0 | G9: =IFERROR((Desempeño_Financiero!H83)/(Desempeño_Financiero!H53+Desempeño_Financiero!H83+Desempeño_Financiero!H96),0) -> 0 | H9: =IFERROR((Desempeño_Financiero!I83)/(Desempeño_Financiero!I53+Desempeño_Financiero!I83+Desempeño_Financiero!I96),0) -> 0 | J9: =IFERROR(($C9-D9)*10000,0) -> -2347.3294 | K9: =IFERROR(($C9-E9)*10000,0) -> 0 | L9: =IFERROR(($C9-F9)*10000,0) -> 0 | M9: =IFERROR(($C9-G9)*10000,0) -> 0 | N9: =IFERROR(($C9-H9)*10000,0) -> 0 | P9: =IFERROR((Desempeño_Financiero!W83)/(Desempeño_Financiero!W53+Desempeño_Financiero!W83+Desempeño_Financiero!W96),0) -> 0 | Q9: =IFERROR((Desempeño_Financiero!X83)/(Desempeño_Financiero!X53+Desempeño_Financiero!X83+Desempeño_Financiero!X96),0) -> 0.22587105 | R9: =IFERROR((Desempeño_Financiero!Y83)/(Desempeño_Financiero!Y53+Desempeño_Financiero!Y83+Desempeño_Financiero!Y96),0) -> 0 | S9: =IFERROR((Desempeño_Financiero!Z83)/(Desempeño_Financiero!Z53+Desempeño_Financiero!Z83+Desempeño_Financiero!Z96),0) -> 0 | T9: =IFERROR((Desempeño_Financiero!AA83)/(Desempeño_Financiero!AA53+Desempeño_Financiero!AA83+Desempeño_Financiero!AA96),0) -> 0 | U9: =IFERROR((Desempeño_Financiero!AB83)/(Desempeño_Financiero!AB53+Desempeño_Financiero!AB83+Desempeño_Financiero!AB96),0) -> 0 | W9: =IFERROR(($P9-Q9)*10000,0) -> -2258.7105 | X9: =IFERROR(($P9-R9)*10000,0) -> 0 | Y9: =IFERROR(($P9-S9)*10000,0) -> 0 | Z9: =IFERROR(($P9-T9)*10000,0) -> 0 | AA9: =IFERROR(($P9-U9)*10000,0) -> 0
B11: INOF / Gasto Operativo | C11: =IFERROR((Desempeño_Financiero!D83/-Desempeño_Financiero!D89),0) -> 0 | D11: =IFERROR((Desempeño_Financiero!E83/-Desempeño_Financiero!E89),0) -> 0.56238733 | E11: =IFERROR((Desempeño_Financiero!F83/-Desempeño_Financiero!F89),0) -> 0 | F11: =IFERROR((Desempeño_Financiero!G83/-Desempeño_Financiero!G89),0) -> 0 | G11: =IFERROR((Desempeño_Financiero!H83/-Desempeño_Financiero!H89),0) -> 0 | H11: =IFERROR((Desempeño_Financiero!I83/-Desempeño_Financiero!I89),0) -> 0 | J11: =IFERROR(($C11-D11)*10000,0) -> -5623.8733 | K11: =IFERROR(($C11-E11)*10000,0) -> 0 | L11: =IFERROR(($C11-F11)*10000,0) -> 0 | M11: =IFERROR(($C11-G11)*10000,0) -> 0 | N11: =IFERROR(($C11-H11)*10000,0) -> 0 | P11: =IFERROR((Desempeño_Financiero!W83/-Desempeño_Financiero!W89),0) -> 0 | Q11: =IFERROR((Desempeño_Financiero!X83/-Desempeño_Financiero!X89),0) -> 0.52456708 | R11: =IFERROR((Desempeño_Financiero!Y83/-Desempeño_Financiero!Y89),0) -> 0 | S11: =IFERROR((Desempeño_Financiero!Z83/-Desempeño_Financiero!Z89),0) -> 0 | T11: =IFERROR((Desempeño_Financiero!AA83/-Desempeño_Financiero!AA89),0) -> 0 | U11: =IFERROR((Desempeño_Financiero!AB83/-Desempeño_Financiero!AB89),0) -> 0 | W11: =IFERROR(($P11-Q11)*10000,0) -> -5245.6708 | X11: =IFERROR(($P11-R11)*10000,0) -> 0 | Y11: =IFERROR(($P11-S11)*10000,0) -> 0 | Z11: =IFERROR(($P11-T11)*10000,0) -> 0 | AA11: =IFERROR(($P11-U11)*10000,0) -> 0
B13: Gasto Operativo / Activo | C13: =IFERROR(-Desempeño_Financiero!D89/Desempeño_Financiero!D17*12,0) -> 0 | D13: =IFERROR(-Desempeño_Financiero!E89/Desempeño_Financiero!E17*12,0) -> 0.10251911 | E13: =IFERROR(-Desempeño_Financiero!F89/Desempeño_Financiero!F17*12,0) -> 0 | F13: =IFERROR(-Desempeño_Financiero!G89/Desempeño_Financiero!G17*12,0) -> 0 | G13: =IFERROR(-Desempeño_Financiero!H89/Desempeño_Financiero!H17*12,0) -> 0 | H13: =IFERROR(-Desempeño_Financiero!I89/Desempeño_Financiero!I17*12,0) -> 0 | J13: =IFERROR(($C13-D13)*10000,0) -> -1025.1911 | K13: =IFERROR(($C13-E13)*10000,0) -> 0 | L13: =IFERROR(($C13-F13)*10000,0) -> 0 | M13: =IFERROR(($C13-G13)*10000,0) -> 0 | N13: =IFERROR(($C13-H13)*10000,0) -> 0 | P13: =IFERROR(-Desempeño_Financiero!W89/Desempeño_Financiero!W17*12,0) -> 0 | Q13: =IFERROR(-Desempeño_Financiero!X89/Desempeño_Financiero!X17*12,0) -> 0.29390042 | R13: =IFERROR(-Desempeño_Financiero!Y89/Desempeño_Financiero!Y17*12,0) -> 0 | S13: =IFERROR(-Desempeño_Financiero!Z89/Desempeño_Financiero!Z17*12,0) -> 0 | T13: =IFERROR(-Desempeño_Financiero!AA89/Desempeño_Financiero!AA17*12,0) -> 0 | U13: =IFERROR(-Desempeño_Financiero!AB89/Desempeño_Financiero!AB17*12,0) -> 0 | W13: =IFERROR(($P13-Q13)*10000,0) -> -2939.0042 | X13: =IFERROR(($P13-R13)*10000,0) -> 0 | Y13: =IFERROR(($P13-S13)*10000,0) -> 0 | Z13: =IFERROR(($P13-T13)*10000,0) -> 0 | AA13: =IFERROR(($P13-U13)*10000,0) -> 0
B15: Provisiones Brutas / Cartera Bruta | C15: =IFERROR(-Desempeño_Financiero!D56/Desempeño_Financiero!D102,0)*12 -> 0 | D15: =IFERROR(-Desempeño_Financiero!E56/Desempeño_Financiero!E102,0)*12 -> 0 | E15: =IFERROR(-Desempeño_Financiero!F56/Desempeño_Financiero!F102,0)*12 -> 0 | F15: =IFERROR(-Desempeño_Financiero!G56/Desempeño_Financiero!G102,0)*12 -> 0 | G15: =IFERROR(-Desempeño_Financiero!H56/Desempeño_Financiero!H102,0)*12 -> 0 | H15: =IFERROR(-Desempeño_Financiero!I56/Desempeño_Financiero!I102,0)*12 -> 0 | J15: =IFERROR(($C15-D15)*10000,0) -> 0 | K15: =IFERROR(($C15-E15)*10000,0) -> 0 | L15: =IFERROR(($C15-F15)*10000,0) -> 0 | M15: =IFERROR(($C15-G15)*10000,0) -> 0 | N15: =IFERROR(($C15-H15)*10000,0) -> 0 | P15: =IFERROR(-Desempeño_Financiero!W56/Desempeño_Financiero!W102,0)*12 -> 0 | Q15: =IFERROR(-Desempeño_Financiero!X56/Desempeño_Financiero!X102,0)*12 -> 0 | R15: =IFERROR(-Desempeño_Financiero!Y56/Desempeño_Financiero!Y102,0)*12 -> 0 | S15: =IFERROR(-Desempeño_Financiero!Z56/Desempeño_Financiero!Z102,0)*12 -> 0 | T15: =IFERROR(-Desempeño_Financiero!AA56/Desempeño_Financiero!AA102,0)*12 -> 0 | U15: =IFERROR(-Desempeño_Financiero!AB56/Desempeño_Financiero!AB102,0)*12 -> 0 | W15: =IFERROR(($P15-Q15)*10000,0) -> 0 | X15: =IFERROR(($P15-R15)*10000,0) -> 0 | Y15: =IFERROR(($P15-S15)*10000,0) -> 0 | Z15: =IFERROR(($P15-T15)*10000,0) -> 0 | AA15: =IFERROR(($P15-U15)*10000,0) -> 0
B17: ROE
B19: ROA

Sheet Evolutivos-->

Sheet Total_Producto
D1: REAL | AZ1: PRESUPUESTO | BO1: Acumulado | BW1: Saldo Prom Acumulado
BO2: =DATE(YEAR(BO6),1,1) -> 46023 | BP2: =DATE(YEAR(BP6),1,1) -> 46023 | BQ2: =DATE(YEAR(BQ6),1,1) -> 46023 | BR2: =DATE(YEAR(BR6),1,1) -> 45658 | BS2: =DATE(YEAR(BS6),1,1) -> 45292 | BT2: =DATE(YEAR(BT6),1,1) -> 44927
C3: N° dias T.Imp | D3: =DAY(D6) -> 31 | E3: =DAY(E6) -> 28 | F3: =DAY(F6) -> 31 | G3: =DAY(G6) -> 30 | H3: =DAY(H6) -> 31 | I3: =DAY(I6) -> 30 | J3: =DAY(J6) -> 31 | K3: =DAY(K6) -> 31 | ... BK3: =DAY(BK6) -> 31 | BO3: =AVERAGEIFS($D3:$BM3,$D$6:$BM$6,">="&BO$2,$D$6:$BM$6,"<="&BO$6,$D$5:$BM$5,BO$5) -> 30 | BP3: =AVERAGEIFS($D3:$BM3,$D$6:$BM$6,">="&BP$2,$D$6:$BM$6,"<="&BP$6,$D$5:$BM$5,BP$5) -> 30 | BQ3: =AVERAGEIFS($D3:$BM3,$D$6:$BM$6,">="&BQ$2,$D$6:$BM$6,"<="&BQ$6,$D$5:$BM$5,BQ$5) -> 29.5 | BR3: =AVERAGEIFS($D3:$BM3,$D$6:$BM$6,">="&BR$2,$D$6:$BM$6,"<="&BR$6,$D$5:$BM$5,BR$5) -> 30 | BS3: =AVERAGEIFS($D3:$BM3,$D$6:$BM$6,">="&BS$2,$D$6:$BM$6,"<="&BS$6,$D$5:$BM$5,BS$5) -> 30.333333 | BT3: =AVERAGEIFS($D3:$BM3,$D$6:$BM$6,">="&BT$2,$D$6:$BM$6,"<="&BT$6,$D$5:$BM$5,BT$5) -> 30
C4: N° dias FTP | D4: =DAY(D6) -> 31 | E4: =DAY(E6) -> 28 | F4: =DAY(F6) -> 31 | G4: =DAY(G6) -> 30 | H4: =DAY(H6) -> 31 | I4: =DAY(I6) -> 30 | J4: =DAY(J6) -> 31 | K4: =DAY(K6) -> 31 | ... BK4: =DAY(BK6) -> 31 | BO4: =AVERAGEIFS($D4:$BM4,$D$6:$BM$6,">="&BO$2,$D$6:$BM$6,"<="&BO$6,$D$5:$BM$5,BO$5) -> 30 | BP4: =AVERAGEIFS($D4:$BM4,$D$6:$BM$6,">="&BP$2,$D$6:$BM$6,"<="&BP$6,$D$5:$BM$5,BP$5) -> 30 | BQ4: =AVERAGEIFS($D4:$BM4,$D$6:$BM$6,">="&BQ$2,$D$6:$BM$6,"<="&BQ$6,$D$5:$BM$5,BQ$5) -> 29.5 | BR4: =AVERAGEIFS($D4:$BM4,$D$6:$BM$6,">="&BR$2,$D$6:$BM$6,"<="&BR$6,$D$5:$BM$5,BR$5) -> 30 | BS4: =AVERAGEIFS($D4:$BM4,$D$6:$BM$6,">="&BS$2,$D$6:$BM$6,"<="&BS$6,$D$5:$BM$5,BS$5) -> 30.333333 | BT4: =AVERAGEIFS($D4:$BM4,$D$6:$BM$6,">="&BT$2,$D$6:$BM$6,"<="&BT$6,$D$5:$BM$5,BT$5) -> 30
C5: Tipo | D5: R | E5: R | F5: R | G5: R | H5: R | I5: R | J5: R | K5: R | L5: R | M5: R | N5: R | O5: R | P5: R | Q5: R | R5: R | S5: R | T5: R | U5: R | V5: R | W5: R | X5: R | Y5: R | Z5: R | AA5: R | AB5: R | AC5: R | AD5: R | AE5: R | AF5: R | AG5: R | AH5: R | AI5: R | AJ5: R | AK5: R | AL5: R | AM5: R | AN5: R | AO5: R | AP5: R | AQ5: R | AR5: R | AS5: R | AT5: R | AU5: R | AV5: R | AW5: R | AX5: R | AY5: R | AZ5: P | BA5: P | BB5: P | BC5: P | BD5: P | BE5: P | BF5: P | BG5: P | BH5: P | BI5: P | BJ5: P | BK5: P | BO5: R | BP5: P | BQ5: R | BR5: R | BS5: R | BT5: R
C6: Total Tarjetas | D6: 44957 | E6: 44985 | F6: 45016 | G6: 45046 | H6: 45077 | I6: 45107 | J6: 45138 | K6: 45169 | L6: 45199 | M6: 45230 | N6: 45260 | O6: 45291 | P6: 45322 | Q6: 45351 | R6: 45382 | S6: 45412 | T6: 45443 | U6: 45473 | V6: 45504 | W6: 45535 | X6: 45565 | Y6: 45596 | Z6: 45626 | AA6: 45657 | AB6: 45688 | AC6: 45716 | AD6: 45747 | AE6: 45777 | AF6: 45808 | AG6: 45838 | AH6: 45869 | AI6: 45900 | AJ6: 45930 | AK6: 45961 | AL6: 45991 | AM6: 46022 | AN6: 46053 | AO6: 46081 | AP6: 46112 | AQ6: 46142 | AR6: 46173 | AS6: 46203 | AT6: 46234 | AU6: 46265 | AV6: 46295 | AW6: 46326 | AX6: 46356 | AY6: 46387 | AZ6: 46053 | BA6: 46081 | BB6: 46112 | BC6: 46142 | BD6: 46173 | BE6: 46203 | BF6: 46234 | BG6: 46265 | BH6: 46295 | BI6: 46326 | BJ6: 46356 | BK6: 46387 | BO6: =Desempeño_Financiero!$B$1 -> 46112 | BP6: =BO6 -> 46112 | BQ6: =EOMONTH(BO6,-1) -> 46081 | BR6: =EOMONTH(BO6,-12) -> 45747 | BS6: =EOMONTH(BO6,-24) -> 45382 | BT6: =EOMONTH(BO6,-36) -> 45016 | BW6: =BO6 -> 46112 | BX6: =BP6 -> 46112 | BY6: =BQ6 -> 46081 | BZ6: =BR6 -> 45747 | CA6: =BS6 -> 45382 | CB6: =BT6 -> 45016
A8: SALDO_FDP | C8: Vigente | D8: =RA_TC!D8+MA_TC!D8+CI_TC!D8 -> 0 | E8: =RA_TC!E8+MA_TC!E8+CI_TC!E8 -> 0 | F8: =RA_TC!F8+MA_TC!F8+CI_TC!F8 -> 0 | G8: =RA_TC!G8+MA_TC!G8+CI_TC!G8 -> 0 | H8: =RA_TC!H8+MA_TC!H8+CI_TC!H8 -> 0 | I8: =RA_TC!I8+MA_TC!I8+CI_TC!I8 -> 0 | J8: =RA_TC!J8+MA_TC!J8+CI_TC!J8 -> 0 | K8: =RA_TC!K8+MA_TC!K8+CI_TC!K8 -> 0 | ... BK8: =RA_TC!BK8+MA_TC!BK8+CI_TC!BK8 -> 6101726.9 | BO8: =_xlfn.XLOOKUP(BO$6,$D$6:$BM$6,$D8:$BM8,,0,1) -> 0 | BP8: =_xlfn.XLOOKUP(BP$6,$D$6:$BM$6,$D8:$BM8,,0,-1) -> 5475782.9 | BQ8: =_xlfn.XLOOKUP(BQ$6,$D$6:$BM$6,$D8:$BM8,,0,1) -> 0 | BR8: =_xlfn.XLOOKUP(BR$6,$D$6:$BM$6,$D8:$BM8,,0,1) -> 0 | BS8: =_xlfn.XLOOKUP(BS$6,$D$6:$BM$6,$D8:$BM8,,0,1) -> 0 | BT8: =_xlfn.XLOOKUP(BT$6,$D$6:$BM$6,$D8:$BM8,,0,1) -> 0
A9: SALDO_FDP | C9: Refinanciado | D9: =RA_TC!D9+MA_TC!D9+CI_TC!D9 -> 0 | E9: =RA_TC!E9+MA_TC!E9+CI_TC!E9 -> 0 | F9: =RA_TC!F9+MA_TC!F9+CI_TC!F9 -> 0 | G9: =RA_TC!G9+MA_TC!G9+CI_TC!G9 -> 0 | H9: =RA_TC!H9+MA_TC!H9+CI_TC!H9 -> 0 | I9: =RA_TC!I9+MA_TC!I9+CI_TC!I9 -> 0 | J9: =RA_TC!J9+MA_TC!J9+CI_TC!J9 -> 0 | K9: =RA_TC!K9+MA_TC!K9+CI_TC!K9 -> 0 | ... BK9: =RA_TC!BK9+MA_TC!BK9+CI_TC!BK9 -> 191034.16 | BO9: =_xlfn.XLOOKUP(BO$6,$D$6:$BM$6,$D9:$BM9,,0,1) -> 0 | BP9: =_xlfn.XLOOKUP(BP$6,$D$6:$BM$6,$D9:$BM9,,0,-1) -> 187857.74 | BQ9: =_xlfn.XLOOKUP(BQ$6,$D$6:$BM$6,$D9:$BM9,,0,1) -> 0 | BR9: =_xlfn.XLOOKUP(BR$6,$D$6:$BM$6,$D9:$BM9,,0,1) -> 0 | BS9: =_xlfn.XLOOKUP(BS$6,$D$6:$BM$6,$D9:$BM9,,0,1) -> 0 | BT9: =_xlfn.XLOOKUP(BT$6,$D$6:$BM$6,$D9:$BM9,,0,1) -> 0
A10: SALDO_FDP | C10: Vencido y Judicial | D10: =RA_TC!D10+MA_TC!D10+CI_TC!D10 -> 0 | E10: =RA_TC!E10+MA_TC!E10+CI_TC!E10 -> 0 | F10: =RA_TC!F10+MA_TC!F10+CI_TC!F10 -> 0 | G10: =RA_TC!G10+MA_TC!G10+CI_TC!G10 -> 0 | H10: =RA_TC!H10+MA_TC!H10+CI_TC!H10 -> 0 | I10: =RA_TC!I10+MA_TC!I10+CI_TC!I10 -> 0 | J10: =RA_TC!J10+MA_TC!J10+CI_TC!J10 -> 0 | K10: =RA_TC!K10+MA_TC!K10+CI_TC!K10 -> 0 | ... BK10: =RA_TC!BK10+MA_TC!BK10+CI_TC!BK10 -> 255200.78 | BO10: =_xlfn.XLOOKUP(BO$6,$D$6:$BM$6,$D10:$BM10,,0,1) -> 0 | BP10: =_xlfn.XLOOKUP(BP$6,$D$6:$BM$6,$D10:$BM10,,0,-1) -> 242951.26 | BQ10: =_xlfn.XLOOKUP(BQ$6,$D$6:$BM$6,$D10:$BM10,,0,1) -> 0 | BR10: =_xlfn.XLOOKUP(BR$6,$D$6:$BM$6,$D10:$BM10,,0,1) -> 0 | BS10: =_xlfn.XLOOKUP(BS$6,$D$6:$BM$6,$D10:$BM10,,0,1) -> 0 | BT10: =_xlfn.XLOOKUP(BT$6,$D$6:$BM$6,$D10:$BM10,,0,1) -> 0
C11: Saldo FdP | D11: =SUM(D8:D10) -> 0 | E11: =SUM(E8:E10) -> 0 | F11: =SUM(F8:F10) -> 0 | G11: =SUM(G8:G10) -> 0 | H11: =SUM(H8:H10) -> 0 | I11: =SUM(I8:I10) -> 0 | J11: =SUM(J8:J10) -> 0 | K11: =SUM(K8:K10) -> 0 | ... BK11: =SUM(BK8:BK10) -> 6547961.9 | BO11: =SUM(BO8:BO10) -> 0 | BP11: =SUM(BP8:BP10) -> 5906591.9 | BQ11: =SUM(BQ8:BQ10) -> 0 | BR11: =SUM(BR8:BR10) -> 0 | BS11: =SUM(BS8:BS10) -> 0 | BT11: =SUM(BT8:BT10) -> 0
A14: SALDO_PROM | C14: Vigente | D14: =RA_TC!D14+MA_TC!D14+CI_TC!D14 -> 0 | E14: =RA_TC!E14+MA_TC!E14+CI_TC!E14 -> 0 | F14: =RA_TC!F14+MA_TC!F14+CI_TC!F14 -> 0 | G14: =RA_TC!G14+MA_TC!G14+CI_TC!G14 -> 0 | H14: =RA_TC!H14+MA_TC!H14+CI_TC!H14 -> 0 | I14: =RA_TC!I14+MA_TC!I14+CI_TC!I14 -> 0 | J14: =RA_TC!J14+MA_TC!J14+CI_TC!J14 -> 0 | K14: =RA_TC!K14+MA_TC!K14+CI_TC!K14 -> 0 | ... BK14: =RA_TC!BK14+MA_TC!BK14+CI_TC!BK14 -> 5993248.4 | BO14: =IFERROR(AVERAGEIFS($D14:$BM14,$D$6:$BM$6,">="&BO$2,$D$6:$BM$6,"<="&BO$6,$D$5:$BM$5,BO$5,$D14:$BM14,"<>0"),0) -> 0 | BP14: =IFERROR(AVERAGEIFS($D14:$BM14,$D$6:$BM$6,">="&BP$2,$D$6:$BM$6,"<="&BP$6,$D$5:$BM$5,BP$5,$D14:$BM14,"<>0"),0) -> 5394716 | BQ14: =IFERROR(AVERAGEIFS($D14:$BM14,$D$6:$BM$6,">="&BQ$2,$D$6:$BM$6,"<="&BQ$6,$D$5:$BM$5,BQ$5,$D14:$BM14,"<>0"),0) -> 0 | BR14: =IFERROR(AVERAGEIFS($D14:$BM14,$D$6:$BM$6,">="&BR$2,$D$6:$BM$6,"<="&BR$6,$D$5:$BM$5,BR$5,$D14:$BM14,"<>0"),0) -> 0 | BS14: =IFERROR(AVERAGEIFS($D14:$BM14,$D$6:$BM$6,">="&BS$2,$D$6:$BM$6,"<="&BS$6,$D$5:$BM$5,BS$5,$D14:$BM14,"<>0"),0) -> 0 | BT14: =IFERROR(AVERAGEIFS($D14:$BM14,$D$6:$BM$6,">="&BT$2,$D$6:$BM$6,"<="&BT$6,$D$5:$BM$5,BT$5,$D14:$BM14,"<>0"),0) -> 0 | BW14: =SUMIFS($D14:$BM14,$D$6:$BM$6,">="&BO$2,$D$6:$BM$6,"<="&BO$6,$D$5:$BM$5,BO$5) -> 0 | BX14: =SUMIFS($D14:$BM14,$D$6:$BM$6,">="&BP$2,$D$6:$BM$6,"<="&BP$6,$D$5:$BM$5,BP$5) -> 16184148 | BY14: =SUMIFS($D14:$BM14,$D$6:$BM$6,">="&BQ$2,$D$6:$BM$6,"<="&BQ$6,$D$5:$BM$5,BQ$5) -> 0 | BZ14: =SUMIFS($D14:$BM14,$D$6:$BM$6,">="&BR$2,$D$6:$BM$6,"<="&BR$6,$D$5:$BM$5,BR$5) -> 0 | CA14: =SUMIFS($D14:$BM14,$D$6:$BM$6,">="&BS$2,$D$6:$BM$6,"<="&BS$6,$D$5:$BM$5,BS$5) -> 0 | CB14: =SUMIFS($D14:$BM14,$D$6:$BM$6,">="&BT$2,$D$6:$BM$6,"<="&BT$6,$D$5:$BM$5,BT$5) -> 0
A15: SALDO_PROM | C15: Refinanciado | D15: =RA_TC!D15+MA_TC!D15+CI_TC!D15 -> 0 | E15: =RA_TC!E15+MA_TC!E15+CI_TC!E15 -> 0 | F15: =RA_TC!F15+MA_TC!F15+CI_TC!F15 -> 0 | G15: =RA_TC!G15+MA_TC!G15+CI_TC!G15 -> 0 | H15: =RA_TC!H15+MA_TC!H15+CI_TC!H15 -> 0 | I15: =RA_TC!I15+MA_TC!I15+CI_TC!I15 -> 0 | J15: =RA_TC!J15+MA_TC!J15+CI_TC!J15 -> 0 | K15: =RA_TC!K15+MA_TC!K15+CI_TC!K15 -> 0 | ... BK15: =RA_TC!BK15+MA_TC!BK15+CI_TC!BK15 -> 183040.35 | BO15: =IFERROR(AVERAGEIFS($D15:$BM15,$D$6:$BM$6,">="&BO$2,$D$6:$BM$6,"<="&BO$6,$D$5:$BM$5,BO$5,$D15:$BM15,"<>0"),0) -> 0 | BP15: =IFERROR(AVERAGEIFS($D15:$BM15,$D$6:$BM$6,">="&BP$2,$D$6:$BM$6,"<="&BP$6,$D$5:$BM$5,BP$5,$D15:$BM15,"<>0"),0) -> 183585.17 | BQ15: =IFERROR(AVERAGEIFS($D15:$BM15,$D$6:$BM$6,">="&BQ$2,$D$6:$BM$6,"<="&BQ$6,$D$5:$BM$5,BQ$5,$D15:$BM15,"<>0"),0) -> 0 | BR15: =IFERROR(AVERAGEIFS($D15:$BM15,$D$6:$BM$6,">="&BR$2,$D$6:$BM$6,"<="&BR$6,$D$5:$BM$5,BR$5,$D15:$BM15,"<>0"),0) -> 0 | BS15: =IFERROR(AVERAGEIFS($D15:$BM15,$D$6:$BM$6,">="&BS$2,$D$6:$BM$6,"<="&BS$6,$D$5:$BM$5,BS$5,$D15:$BM15,"<>0"),0) -> 0 | BT15: =IFERROR(AVERAGEIFS($D15:$BM15,$D$6:$BM$6,">="&BT$2,$D$6:$BM$6,"<="&BT$6,$D$5:$BM$5,BT$5,$D15:$BM15,"<>0"),0) -> 0 | BW15: =SUMIFS($D15:$BM15,$D$6:$BM$6,">="&BO$2,$D$6:$BM$6,"<="&BO$6,$D$5:$BM$5,BO$5) -> 0 | BX15: =SUMIFS($D15:$BM15,$D$6:$BM$6,">="&BP$2,$D$6:$BM$6,"<="&BP$6,$D$5:$BM$5,BP$5) -> 550755.5 | BY15: =SUMIFS($D15:$BM15,$D$6:$BM$6,">="&BQ$2,$D$6:$BM$6,"<="&BQ$6,$D$5:$BM$5,BQ$5) -> 0 | BZ15: =SUMIFS($D15:$BM15,$D$6:$BM$6,">="&BR$2,$D$6:$BM$6,"<="&BR$6,$D$5:$BM$5,BR$5) -> 0 | CA15: =SUMIFS($D15:$BM15,$D$6:$BM$6,">="&BS$2,$D$6:$BM$6,"<="&BS$6,$D$5:$BM$5,BS$5) -> 0 | CB15: =SUMIFS($D15:$BM15,$D$6:$BM$6,">="&BT$2,$D$6:$BM$6,"<="&BT$6,$D$5:$BM$5,BT$5) -> 0
A16: SALDO_PROM | C16: Vencido y Judicial | D16: =RA_TC!D16+MA_TC!D16+CI_TC!D16 -> 0 | E16: =RA_TC!E16+MA_TC!E16+CI_TC!E16 -> 0 | F16: =RA_TC!F16+MA_TC!F16+CI_TC!F16 -> 0 | G16: =RA_TC!G16+MA_TC!G16+CI_TC!G16 -> 0 | H16: =RA_TC!H16+MA_TC!H16+CI_TC!H16 -> 0 | I16: =RA_TC!I16+MA_TC!I16+CI_TC!I16 -> 0 | J16: =RA_TC!J16+MA_TC!J16+CI_TC!J16 -> 0 | K16: =RA_TC!K16+MA_TC!K16+CI_TC!K16 -> 0 | ... BK16: =RA_TC!BK16+MA_TC!BK16+CI_TC!BK16 -> 276079.3 | BO16: =IFERROR(AVERAGEIFS($D16:$BM16,$D$6:$BM$6,">="&BO$2,$D$6:$BM$6,"<="&BO$6,$D$5:$BM$5,BO$5,$D16:$BM16,"<>0"),0) -> 0 | BP16: =IFERROR(AVERAGEIFS($D16:$BM16,$D$6:$BM$6,">="&BP$2,$D$6:$BM$6,"<="&BP$6,$D$5:$BM$5,BP$5,$D16:$BM16,"<>0"),0) -> 269886.41 | BQ16: =IFERROR(AVERAGEIFS($D16:$BM16,$D$6:$BM$6,">="&BQ$2,$D$6:$BM$6,"<="&BQ$6,$D$5:$BM$5,BQ$5,$D16:$BM16,"<>0"),0) -> 0 | BR16: =IFERROR(AVERAGEIFS($D16:$BM16,$D$6:$BM$6,">="&BR$2,$D$6:$BM$6,"<="&BR$6,$D$5:$BM$5,BR$5,$D16:$BM16,"<>0"),0) -> 0 | BS16: =IFERROR(AVERAGEIFS($D16:$BM16,$D$6:$BM$6,">="&BS$2,$D$6:$BM$6,"<="&BS$6,$D$5:$BM$5,BS$5,$D16:$BM16,"<>0"),0) -> 0 | BT16: =IFERROR(AVERAGEIFS($D16:$BM16,$D$6:$BM$6,">="&BT$2,$D$6:$BM$6,"<="&BT$6,$D$5:$BM$5,BT$5,$D16:$BM16,"<>0"),0) -> 0 | BW16: =SUMIFS($D16:$BM16,$D$6:$BM$6,">="&BO$2,$D$6:$BM$6,"<="&BO$6,$D$5:$BM$5,BO$5) -> 0 | BX16: =SUMIFS($D16:$BM16,$D$6:$BM$6,">="&BP$2,$D$6:$BM$6,"<="&BP$6,$D$5:$BM$5,BP$5) -> 809659.23 | BY16: =SUMIFS($D16:$BM16,$D$6:$BM$6,">="&BQ$2,$D$6:$BM$6,"<="&BQ$6,$D$5:$BM$5,BQ$5) -> 0 | BZ16: =SUMIFS($D16:$BM16,$D$6:$BM$6,">="&BR$2,$D$6:$BM$6,"<="&BR$6,$D$5:$BM$5,BR$5) -> 0 | CA16: =SUMIFS($D16:$BM16,$D$6:$BM$6,">="&BS$2,$D$6:$BM$6,"<="&BS$6,$D$5:$BM$5,BS$5) -> 0 | CB16: =SUMIFS($D16:$BM16,$D$6:$BM$6,">="&BT$2,$D$6:$BM$6,"<="&BT$6,$D$5:$BM$5,BT$5) -> 0
C17: Saldo Prom | D17: =SUM(D14:D16) -> 0 | E17: =SUM(E14:E16) -> 0 | F17: =SUM(F14:F16) -> 0 | G17: =SUM(G14:G16) -> 0 | H17: =SUM(H14:H16) -> 0 | I17: =SUM(I14:I16) -> 0 | J17: =SUM(J14:J16) -> 0 | K17: =SUM(K14:K16) -> 0 | ... BK17: =SUM(BK14:BK16) -> 6452368.1 | BO17: =SUM(BO14:BO16) -> 0 | BP17: =SUM(BP14:BP16) -> 5848187.6 | BQ17: =SUM(BQ14:BQ16) -> 0 | BR17: =SUM(BR14:BR16) -> 0 | BS17: =SUM(BS14:BS16) -> 0 | BT17: =SUM(BT14:BT16) -> 0 | BW17: =SUM(BW14:BW16) -> 0 | BX17: =SUM(BX14:BX16) -> 17544563 | BY17: =SUM(BY14:BY16) -> 0 | BZ17: =SUM(BZ14:BZ16) -> 0 | CA17: =SUM(CA14:CA16) -> 0 | CB17: =SUM(CB14:CB16) -> 0
C20: Vigente | D20: =IFERROR(((1+D38/D14)^(360/D$3))-1,0) -> 0 | E20: =IFERROR(((1+E38/E14)^(360/E$3))-1,0) -> 0 | F20: =IFERROR(((1+F38/F14)^(360/F$3))-1,0) -> 0 | G20: =IFERROR(((1+G38/G14)^(360/G$3))-1,0) -> 0 | H20: =IFERROR(((1+H38/H14)^(360/H$3))-1,0) -> 0 | I20: =IFERROR(((1+I38/I14)^(360/I$3))-1,0) -> 0 | J20: =IFERROR(((1+J38/J14)^(360/J$3))-1,0) -> 0 | K20: =IFERROR(((1+K38/K14)^(360/K$3))-1,0) -> 0 | ... BK20: =IFERROR(((1+BK38/BK14)^(360/BK$3))-1,0) -> 0.26667291 | BO20: =IFERROR(((1+BO38/BW14)^(360/BO$3))-1,0) -> 0 | BP20: =IFERROR(((1+BP38/BX14)^(360/BP$3))-1,0) -> 0.25696584 | BQ20: =IFERROR(((1+BQ38/BY14)^(360/BQ$3))-1,0) -> 0 | BR20: =IFERROR(((1+BR38/BZ14)^(360/BR$3))-1,0) -> 0 | BS20: =IFERROR(((1+BS38/CA14)^(360/BS$3))-1,0) -> 0 | BT20: =IFERROR(((1+BT38/CB14)^(360/BT$3))-1,0) -> 0
C21: Refinanciado | D21: =IFERROR(((1+D39/D15)^(360/D$3))-1,0) -> 0 | E21: =IFERROR(((1+E39/E15)^(360/E$3))-1,0) -> 0 | F21: =IFERROR(((1+F39/F15)^(360/F$3))-1,0) -> 0 | G21: =IFERROR(((1+G39/G15)^(360/G$3))-1,0) -> 0 | H21: =IFERROR(((1+H39/H15)^(360/H$3))-1,0) -> 0 | I21: =IFERROR(((1+I39/I15)^(360/I$3))-1,0) -> 0 | J21: =IFERROR(((1+J39/J15)^(360/J$3))-1,0) -> 0 | K21: =IFERROR(((1+K39/K15)^(360/K$3))-1,0) -> 0 | ... BK21: =IFERROR(((1+BK39/BK15)^(360/BK$3))-1,0) -> 0.10692987 | BO21: =IFERROR(((1+BO39/BW15)^(360/BO$3))-1,0) -> 0 | BP21: =IFERROR(((1+BP39/BX15)^(360/BP$3))-1,0) -> 0.10616469 | BQ21: =IFERROR(((1+BQ39/BY15)^(360/BQ$3))-1,0) -> 0 | BR21: =IFERROR(((1+BR39/BZ15)^(360/BR$3))-1,0) -> 0 | BS21: =IFERROR(((1+BS39/CA15)^(360/BS$3))-1,0) -> 0 | BT21: =IFERROR(((1+BT39/CB15)^(360/BT$3))-1,0) -> 0
C22: Vencido y Judicial | D22: =IFERROR(((1+D40/D16)^(360/D$3))-1,0) -> 0 | E22: =IFERROR(((1+E40/E16)^(360/E$3))-1,0) -> 0 | F22: =IFERROR(((1+F40/F16)^(360/F$3))-1,0) -> 0 | G22: =IFERROR(((1+G40/G16)^(360/G$3))-1,0) -> 0 | H22: =IFERROR(((1+H40/H16)^(360/H$3))-1,0) -> 0 | I22: =IFERROR(((1+I40/I16)^(360/I$3))-1,0) -> 0 | J22: =IFERROR(((1+J40/J16)^(360/J$3))-1,0) -> 0 | K22: =IFERROR(((1+K40/K16)^(360/K$3))-1,0) -> 0 | ... BK22: =IFERROR(((1+BK40/BK16)^(360/BK$3))-1,0) -> 0.19048324 | BO22: =IFERROR(((1+BO40/BW16)^(360/BO$3))-1,0) -> 0 | BP22: =IFERROR(((1+BP40/BX16)^(360/BP$3))-1,0) -> 0.20328197 | BQ22: =IFERROR(((1+BQ40/BY16)^(360/BQ$3))-1,0) -> 0 | BR22: =IFERROR(((1+BR40/BZ16)^(360/BR$3))-1,0) -> 0 | BS22: =IFERROR(((1+BS40/CA16)^(360/BS$3))-1,0) -> 0 | BT22: =IFERROR(((1+BT40/CB16)^(360/BT$3))-1,0) -> 0
C23: Tasa Implicita | D23: =IFERROR(((1+D41/D17)^(360/D$3))-1,0) -> 0 | E23: =IFERROR(((1+E41/E17)^(360/E$3))-1,0) -> 0 | F23: =IFERROR(((1+F41/F17)^(360/F$3))-1,0) -> 0 | G23: =IFERROR(((1+G41/G17)^(360/G$3))-1,0) -> 0 | H23: =IFERROR(((1+H41/H17)^(360/H$3))-1,0) -> 0 | I23: =IFERROR(((1+I41/I17)^(360/I$3))-1,0) -> 0 | J23: =IFERROR(((1+J41/J17)^(360/J$3))-1,0) -> 0 | K23: =IFERROR(((1+K41/K17)^(360/K$3))-1,0) -> 0 | ... BK23: =IFERROR(((1+BK41/BK17)^(360/BK$3))-1,0) -> 0.25852793 | BO23: =IFERROR(((1+BO41/BW17)^(360/BO$3))-1,0) -> 0 | BP23: =IFERROR(((1+BP41/BX17)^(360/BP$3))-1,0) -> 0.24944315 | BQ23: =IFERROR(((1+BQ41/BY17)^(360/BQ$3))-1,0) -> 0 | BR23: =IFERROR(((1+BR41/BZ17)^(360/BR$3))-1,0) -> 0 | BS23: =IFERROR(((1+BS41/CA17)^(360/BS$3))-1,0) -> 0 | BT23: =IFERROR(((1+BT41/CB17)^(360/BT$3))-1,0) -> 0
C26: Vigente | D26: =-IFERROR(((1-D44/D14)^(360/D$4))-1,0) -> 0 | E26: =-IFERROR(((1-E44/E14)^(360/E$4))-1,0) -> 0 | F26: =-IFERROR(((1-F44/F14)^(360/F$4))-1,0) -> 0 | G26: =-IFERROR(((1-G44/G14)^(360/G$4))-1,0) -> 0 | H26: =-IFERROR(((1-H44/H14)^(360/H$4))-1,0) -> 0 | I26: =-IFERROR(((1-I44/I14)^(360/I$4))-1,0) -> 0 | J26: =-IFERROR(((1-J44/J14)^(360/J$4))-1,0) -> 0 | K26: =-IFERROR(((1-K44/K14)^(360/K$4))-1,0) -> 0 | ... BK26: =-IFERROR(((1-BK44/BK14)^(360/BK$4))-1,0) -> -0.047972923 | BO26: =-IFERROR(((1-BO44/BW14)^(360/BO$4))-1,0) -> 0 | BP26: =-IFERROR(((1-BP44/BX14)^(360/BP$4))-1,0) -> -0.049891884 | BQ26: =-IFERROR(((1-BQ44/BY14)^(360/BQ$4))-1,0) -> 0 | BR26: =-IFERROR(((1-BR44/BZ14)^(360/BR$4))-1,0) -> 0 | BS26: =-IFERROR(((1-BS44/CA14)^(360/BS$4))-1,0) -> 0 | BT26: =-IFERROR(((1-BT44/CB14)^(360/BT$4))-1,0) -> 0
C27: Refinanciado | D27: =-IFERROR(((1-D45/D15)^(360/D$4))-1,0) -> 0 | E27: =-IFERROR(((1-E45/E15)^(360/E$4))-1,0) -> 0 | F27: =-IFERROR(((1-F45/F15)^(360/F$4))-1,0) -> 0 | G27: =-IFERROR(((1-G45/G15)^(360/G$4))-1,0) -> 0 | H27: =-IFERROR(((1-H45/H15)^(360/H$4))-1,0) -> 0 | I27: =-IFERROR(((1-I45/I15)^(360/I$4))-1,0) -> 0 | J27: =-IFERROR(((1-J45/J15)^(360/J$4))-1,0) -> 0 | K27: =-IFERROR(((1-K45/K15)^(360/K$4))-1,0) -> 0 | ... BK27: =-IFERROR(((1-BK45/BK15)^(360/BK$4))-1,0) -> -0.051397622 | BO27: =-IFERROR(((1-BO45/BW15)^(360/BO$4))-1,0) -> 0 | BP27: =-IFERROR(((1-BP45/BX15)^(360/BP$4))-1,0) -> -0.049363761 | BQ27: =-IFERROR(((1-BQ45/BY15)^(360/BQ$4))-1,0) -> 0 | BR27: =-IFERROR(((1-BR45/BZ15)^(360/BR$4))-1,0) -> 0 | BS27: =-IFERROR(((1-BS45/CA15)^(360/BS$4))-1,0) -> 0 | BT27: =-IFERROR(((1-BT45/CB15)^(360/BT$4))-1,0) -> 0
C28: Vencido y Judicial | D28: =-IFERROR(((1-D46/D16)^(360/D$4))-1,0) -> 0 | E28: =-IFERROR(((1-E46/E16)^(360/E$4))-1,0) -> 0 | F28: =-IFERROR(((1-F46/F16)^(360/F$4))-1,0) -> 0 | G28: =-IFERROR(((1-G46/G16)^(360/G$4))-1,0) -> 0 | H28: =-IFERROR(((1-H46/H16)^(360/H$4))-1,0) -> 0 | I28: =-IFERROR(((1-I46/I16)^(360/I$4))-1,0) -> 0 | J28: =-IFERROR(((1-J46/J16)^(360/J$4))-1,0) -> 0 | K28: =-IFERROR(((1-K46/K16)^(360/K$4))-1,0) -> 0 | ... BK28: =-IFERROR(((1-BK46/BK16)^(360/BK$4))-1,0) -> -0.048039665 | BO28: =-IFERROR(((1-BO46/BW16)^(360/BO$4))-1,0) -> 0 | BP28: =-IFERROR(((1-BP46/BX16)^(360/BP$4))-1,0) -> -0.047114159 | BQ28: =-IFERROR(((1-BQ46/BY16)^(360/BQ$4))-1,0) -> 0 | BR28: =-IFERROR(((1-BR46/BZ16)^(360/BR$4))-1,0) -> 0 | BS28: =-IFERROR(((1-BS46/CA16)^(360/BS$4))-1,0) -> 0 | BT28: =-IFERROR(((1-BT46/CB16)^(360/BT$4))-1,0) -> 0
C29: Tasa FTP | D29: =-IFERROR(((1-D47/D17)^(360/D$4))-1,0) -> 0 | E29: =-IFERROR(((1-E47/E17)^(360/E$4))-1,0) -> 0 | F29: =-IFERROR(((1-F47/F17)^(360/F$4))-1,0) -> 0 | G29: =-IFERROR(((1-G47/G17)^(360/G$4))-1,0) -> 0 | H29: =-IFERROR(((1-H47/H17)^(360/H$4))-1,0) -> 0 | I29: =-IFERROR(((1-I47/I17)^(360/I$4))-1,0) -> 0 | J29: =-IFERROR(((1-J47/J17)^(360/J$4))-1,0) -> 0 | K29: =-IFERROR(((1-K47/K17)^(360/K$4))-1,0) -> 0 | ... BK29: =-IFERROR(((1-BK47/BK17)^(360/BK$4))-1,0) -> -0.04807279 | BO29: =-IFERROR(((1-BO47/BW17)^(360/BO$4))-1,0) -> 0 | BP29: =-IFERROR(((1-BP47/BX17)^(360/BP$4))-1,0) -> -0.049746966 | BQ29: =-IFERROR(((1-BQ47/BY17)^(360/BQ$4))-1,0) -> 0 | BR29: =-IFERROR(((1-BR47/BZ17)^(360/BR$4))-1,0) -> 0 | BS29: =-IFERROR(((1-BS47/CA17)^(360/BS$4))-1,0) -> 0 | BT29: =-IFERROR(((1-BT47/CB17)^(360/BT$4))-1,0) -> 0
C32: Vigente | D32: =D20+D26 -> 0 | E32: =E20+E26 -> 0 | F32: =F20+F26 -> 0 | G32: =G20+G26 -> 0 | H32: =H20+H26 -> 0 | I32: =I20+I26 -> 0 | J32: =J20+J26 -> 0 | K32: =K20+K26 -> 0 | ... BK32: =BK20+BK26 -> 0.21869999 | BO32: =BO20+BO26 -> 0 | BP32: =BP20+BP26 -> 0.20707396 | BQ32: =BQ20+BQ26 -> 0 | BR32: =BR20+BR26 -> 0 | BS32: =BS20+BS26 -> 0 | BT32: =BT20+BT26 -> 0
C33: Refinanciado | D33: =D21+D27 -> 0 | E33: =E21+E27 -> 0 | F33: =F21+F27 -> 0 | G33: =G21+G27 -> 0 | H33: =H21+H27 -> 0 | I33: =I21+I27 -> 0 | J33: =J21+J27 -> 0 | K33: =K21+K27 -> 0 | ... BK33: =BK21+BK27 -> 0.055532249 | BO33: =BO21+BO27 -> 0 | BP33: =BP21+BP27 -> 0.05680093 | BQ33: =BQ21+BQ27 -> 0 | BR33: =BR21+BR27 -> 0 | BS33: =BS21+BS27 -> 0 | BT33: =BT21+BT27 -> 0
C34: Vencido y Judicial | D34: =D22+D28 -> 0 | E34: =E22+E28 -> 0 | F34: =F22+F28 -> 0 | G34: =G22+G28 -> 0 | H34: =H22+H28 -> 0 | I34: =I22+I28 -> 0 | J34: =J22+J28 -> 0 | K34: =K22+K28 -> 0 | ... BK34: =BK22+BK28 -> 0.14244358 | BO34: =BO22+BO28 -> 0 | BP34: =BP22+BP28 -> 0.15616781 | BQ34: =BQ22+BQ28 -> 0 | BR34: =BR22+BR28 -> 0 | BS34: =BS22+BS28 -> 0 | BT34: =BT22+BT28 -> 0
C35: Spread | D35: =D23+D29 -> 0 | E35: =E23+E29 -> 0 | F35: =F23+F29 -> 0 | G35: =G23+G29 -> 0 | H35: =H23+H29 -> 0 | I35: =I23+I29 -> 0 | J35: =J23+J29 -> 0 | K35: =K23+K29 -> 0 | ... BK35: =BK23+BK29 -> 0.21045514 | BO35: =BO23+BO29 -> 0 | BP35: =BP23+BP29 -> 0.19969618 | BQ35: =BQ23+BQ29 -> 0 | BR35: =BR23+BR29 -> 0 | BS35: =BS23+BS29 -> 0 | BT35: =BT23+BT29 -> 0
A38: Ingreso_Financiero | C38: Vigente | D38: =RA_TC!D38+MA_TC!D38+CI_TC!D38 -> 0 | E38: =RA_TC!E38+MA_TC!E38+CI_TC!E38 -> 0 | F38: =RA_TC!F38+MA_TC!F38+CI_TC!F38 -> 0 | G38: =RA_TC!G38+MA_TC!G38+CI_TC!G38 -> 0 | H38: =RA_TC!H38+MA_TC!H38+CI_TC!H38 -> 0 | I38: =RA_TC!I38+MA_TC!I38+CI_TC!I38 -> 0 | J38: =RA_TC!J38+MA_TC!J38+CI_TC!J38 -> 0 | K38: =RA_TC!K38+MA_TC!K38+CI_TC!K38 -> 0 | ... BK38: =RA_TC!BK38+MA_TC!BK38+CI_TC!BK38 -> 123249.5 | BO38: =SUMIFS($D38:$BM38,$D$6:$BM$6,">="&BO$2,$D$6:$BM$6,"<="&BO$6,$D$5:$BM$5,BO$5) -> 0 | BP38: =SUMIFS($D38:$BM38,$D$6:$BM$6,">="&BP$2,$D$6:$BM$6,"<="&BP$6,$D$5:$BM$5,BP$5) -> 311401.9 | BQ38: =SUMIFS($D38:$BM38,$D$6:$BM$6,">="&BQ$2,$D$6:$BM$6,"<="&BQ$6,$D$5:$BM$5,BQ$5) -> 0 | BR38: =SUMIFS($D38:$BM38,$D$6:$BM$6,">="&BR$2,$D$6:$BM$6,"<="&BR$6,$D$5:$BM$5,BR$5) -> 0 | BS38: =SUMIFS($D38:$BM38,$D$6:$BM$6,">="&BS$2,$D$6:$BM$6,"<="&BS$6,$D$5:$BM$5,BS$5) -> 0 | BT38: =SUMIFS($D38:$BM38,$D$6:$BM$6,">="&BT$2,$D$6:$BM$6,"<="&BT$6,$D$5:$BM$5,BT$5) -> 0
A39: Ingreso_Financiero | C39: Refinanciado | D39: =RA_TC!D39+MA_TC!D39+CI_TC!D39 -> 0 | E39: =RA_TC!E39+MA_TC!E39+CI_TC!E39 -> 0 | F39: =RA_TC!F39+MA_TC!F39+CI_TC!F39 -> 0 | G39: =RA_TC!G39+MA_TC!G39+CI_TC!G39 -> 0 | H39: =RA_TC!H39+MA_TC!H39+CI_TC!H39 -> 0 | I39: =RA_TC!I39+MA_TC!I39+CI_TC!I39 -> 0 | J39: =RA_TC!J39+MA_TC!J39+CI_TC!J39 -> 0 | K39: =RA_TC!K39+MA_TC!K39+CI_TC!K39 -> 0 | ... BK39: =RA_TC!BK39+MA_TC!BK39+CI_TC!BK39 -> 1608.2712 | BO39: =SUMIFS($D39:$BM39,$D$6:$BM$6,">="&BO$2,$D$6:$BM$6,"<="&BO$6,$D$5:$BM$5,BO$5) -> 0 | BP39: =SUMIFS($D39:$BM39,$D$6:$BM$6,">="&BP$2,$D$6:$BM$6,"<="&BP$6,$D$5:$BM$5,BP$5) -> 4650.4042 | BQ39: =SUMIFS($D39:$BM39,$D$6:$BM$6,">="&BQ$2,$D$6:$BM$6,"<="&BQ$6,$D$5:$BM$5,BQ$5) -> 0 | BR39: =SUMIFS($D39:$BM39,$D$6:$BM$6,">="&BR$2,$D$6:$BM$6,"<="&BR$6,$D$5:$BM$5,BR$5) -> 0 | BS39: =SUMIFS($D39:$BM39,$D$6:$BM$6,">="&BS$2,$D$6:$BM$6,"<="&BS$6,$D$5:$BM$5,BS$5) -> 0 | BT39: =SUMIFS($D39:$BM39,$D$6:$BM$6,">="&BT$2,$D$6:$BM$6,"<="&BT$6,$D$5:$BM$5,BT$5) -> 0
A40: Ingreso_Financiero | C40: Vencido y Judicial | D40: =RA_TC!D40+MA_TC!D40+CI_TC!D40 -> 0 | E40: =RA_TC!E40+MA_TC!E40+CI_TC!E40 -> 0 | F40: =RA_TC!F40+MA_TC!F40+CI_TC!F40 -> 0 | G40: =RA_TC!G40+MA_TC!G40+CI_TC!G40 -> 0 | H40: =RA_TC!H40+MA_TC!H40+CI_TC!H40 -> 0 | I40: =RA_TC!I40+MA_TC!I40+CI_TC!I40 -> 0 | J40: =RA_TC!J40+MA_TC!J40+CI_TC!J40 -> 0 | K40: =RA_TC!K40+MA_TC!K40+CI_TC!K40 -> 0 | ... BK40: =RA_TC!BK40+MA_TC!BK40+CI_TC!BK40 -> 4176.4046 | BO40: =SUMIFS($D40:$BM40,$D$6:$BM$6,">="&BO$2,$D$6:$BM$6,"<="&BO$6,$D$5:$BM$5,BO$5) -> 0 | BP40: =SUMIFS($D40:$BM40,$D$6:$BM$6,">="&BP$2,$D$6:$BM$6,"<="&BP$6,$D$5:$BM$5,BP$5) -> 12582.578 | BQ40: =SUMIFS($D40:$BM40,$D$6:$BM$6,">="&BQ$2,$D$6:$BM$6,"<="&BQ$6,$D$5:$BM$5,BQ$5) -> 0 | BR40: =SUMIFS($D40:$BM40,$D$6:$BM$6,">="&BR$2,$D$6:$BM$6,"<="&BR$6,$D$5:$BM$5,BR$5) -> 0 | BS40: =SUMIFS($D40:$BM40,$D$6:$BM$6,">="&BS$2,$D$6:$BM$6,"<="&BS$6,$D$5:$BM$5,BS$5) -> 0 | BT40: =SUMIFS($D40:$BM40,$D$6:$BM$6,">="&BT$2,$D$6:$BM$6,"<="&BT$6,$D$5:$BM$5,BT$5) -> 0
C41: Ingreso Financiero | D41: =SUM(D38:D40) -> 0 | E41: =SUM(E38:E40) -> 0 | F41: =SUM(F38:F40) -> 0 | G41: =SUM(G38:G40) -> 0 | H41: =SUM(H38:H40) -> 0 | I41: =SUM(I38:I40) -> 0 | J41: =SUM(J38:J40) -> 0 | K41: =SUM(K38:K40) -> 0 | ... BK41: =SUM(BK38:BK40) -> 129034.17 | BO41: =SUM(BO38:BO40) -> 0 | BP41: =SUM(BP38:BP40) -> 328634.88 | BQ41: =SUM(BQ38:BQ40) -> 0 | BR41: =SUM(BR38:BR40) -> 0 | BS41: =SUM(BS38:BS40) -> 0 | BT41: =SUM(BT38:BT40) -> 0
A44: FTP | C44: Vigente | D44: =RA_TC!D44+MA_TC!D44+CI_TC!D44 -> 0 | E44: =RA_TC!E44+MA_TC!E44+CI_TC!E44 -> 0 | F44: =RA_TC!F44+MA_TC!F44+CI_TC!F44 -> 0 | G44: =RA_TC!G44+MA_TC!G44+CI_TC!G44 -> 0 | H44: =RA_TC!H44+MA_TC!H44+CI_TC!H44 -> 0 | I44: =RA_TC!I44+MA_TC!I44+CI_TC!I44 -> 0 | J44: =RA_TC!J44+MA_TC!J44+CI_TC!J44 -> 0 | K44: =RA_TC!K44+MA_TC!K44+CI_TC!K44 -> 0 | ... BK44: =RA_TC!BK44+MA_TC!BK44+CI_TC!BK44 -> -24231.448 | BO44: =SUMIFS($D44:$BM44,$D$6:$BM$6,">="&BO$2,$D$6:$BM$6,"<="&BO$6,$D$5:$BM$5,BO$5) -> 0 | BP44: =SUMIFS($D44:$BM44,$D$6:$BM$6,">="&BP$2,$D$6:$BM$6,"<="&BP$6,$D$5:$BM$5,BP$5) -> -65796.78 | BQ44: =SUMIFS($D44:$BM44,$D$6:$BM$6,">="&BQ$2,$D$6:$BM$6,"<="&BQ$6,$D$5:$BM$5,BQ$5) -> 0 | BR44: =SUMIFS($D44:$BM44,$D$6:$BM$6,">="&BR$2,$D$6:$BM$6,"<="&BR$6,$D$5:$BM$5,BR$5) -> 0 | BS44: =SUMIFS($D44:$BM44,$D$6:$BM$6,">="&BS$2,$D$6:$BM$6,"<="&BS$6,$D$5:$BM$5,BS$5) -> 0 | BT44: =SUMIFS($D44:$BM44,$D$6:$BM$6,">="&BT$2,$D$6:$BM$6,"<="&BT$6,$D$5:$BM$5,BT$5) -> 0
A45: FTP | C45: Refinanciado | D45: =RA_TC!D45+MA_TC!D45+CI_TC!D45 -> 0 | E45: =RA_TC!E45+MA_TC!E45+CI_TC!E45 -> 0 | F45: =RA_TC!F45+MA_TC!F45+CI_TC!F45 -> 0 | G45: =RA_TC!G45+MA_TC!G45+CI_TC!G45 -> 0 | H45: =RA_TC!H45+MA_TC!H45+CI_TC!H45 -> 0 | I45: =RA_TC!I45+MA_TC!I45+CI_TC!I45 -> 0 | J45: =RA_TC!J45+MA_TC!J45+CI_TC!J45 -> 0 | K45: =RA_TC!K45+MA_TC!K45+CI_TC!K45 -> 0 | ... BK45: =RA_TC!BK45+MA_TC!BK45+CI_TC!BK45 -> -791.69451 | BO45: =SUMIFS($D45:$BM45,$D$6:$BM$6,">="&BO$2,$D$6:$BM$6,"<="&BO$6,$D$5:$BM$5,BO$5) -> 0 | BP45: =SUMIFS($D45:$BM45,$D$6:$BM$6,">="&BP$2,$D$6:$BM$6,"<="&BP$6,$D$5:$BM$5,BP$5) -> -2215.9145 | BQ45: =SUMIFS($D45:$BM45,$D$6:$BM$6,">="&BQ$2,$D$6:$BM$6,"<="&BQ$6,$D$5:$BM$5,BQ$5) -> 0 | BR45: =SUMIFS($D45:$BM45,$D$6:$BM$6,">="&BR$2,$D$6:$BM$6,"<="&BR$6,$D$5:$BM$5,BR$5) -> 0 | BS45: =SUMIFS($D45:$BM45,$D$6:$BM$6,">="&BS$2,$D$6:$BM$6,"<="&BS$6,$D$5:$BM$5,BS$5) -> 0 | BT45: =SUMIFS($D45:$BM45,$D$6:$BM$6,">="&BT$2,$D$6:$BM$6,"<="&BT$6,$D$5:$BM$5,BT$5) -> 0
A46: FTP | C46: Vencido y Judicial | D46: =RA_TC!D46+MA_TC!D46+CI_TC!D46 -> 0 | E46: =RA_TC!E46+MA_TC!E46+CI_TC!E46 -> 0 | F46: =RA_TC!F46+MA_TC!F46+CI_TC!F46 -> 0 | G46: =RA_TC!G46+MA_TC!G46+CI_TC!G46 -> 0 | H46: =RA_TC!H46+MA_TC!H46+CI_TC!H46 -> 0 | I46: =RA_TC!I46+MA_TC!I46+CI_TC!I46 -> 0 | J46: =RA_TC!J46+MA_TC!J46+CI_TC!J46 -> 0 | K46: =RA_TC!K46+MA_TC!K46+CI_TC!K46 -> 0 | ... BK46: =RA_TC!BK46+MA_TC!BK46+CI_TC!BK46 -> -1117.7431 | BO46: =SUMIFS($D46:$BM46,$D$6:$BM$6,">="&BO$2,$D$6:$BM$6,"<="&BO$6,$D$5:$BM$5,BO$5) -> 0 | BP46: =SUMIFS($D46:$BM46,$D$6:$BM$6,">="&BP$2,$D$6:$BM$6,"<="&BP$6,$D$5:$BM$5,BP$5) -> -3112.2211 | BQ46: =SUMIFS($D46:$BM46,$D$6:$BM$6,">="&BQ$2,$D$6:$BM$6,"<="&BQ$6,$D$5:$BM$5,BQ$5) -> 0 | BR46: =SUMIFS($D46:$BM46,$D$6:$BM$6,">="&BR$2,$D$6:$BM$6,"<="&BR$6,$D$5:$BM$5,BR$5) -> 0 | BS46: =SUMIFS($D46:$BM46,$D$6:$BM$6,">="&BS$2,$D$6:$BM$6,"<="&BS$6,$D$5:$BM$5,BS$5) -> 0 | BT46: =SUMIFS($D46:$BM46,$D$6:$BM$6,">="&BT$2,$D$6:$BM$6,"<="&BT$6,$D$5:$BM$5,BT$5) -> 0
C47: Costo de Fondos | D47: =SUM(D44:D46) -> 0 | E47: =SUM(E44:E46) -> 0 | F47: =SUM(F44:F46) -> 0 | G47: =SUM(G44:G46) -> 0 | H47: =SUM(H44:H46) -> 0 | I47: =SUM(I44:I46) -> 0 | J47: =SUM(J44:J46) -> 0 | K47: =SUM(K44:K46) -> 0 | ... BK47: =SUM(BK44:BK46) -> -26140.886 | BO47: =SUM(BO44:BO46) -> 0 | BP47: =SUM(BP44:BP46) -> -71124.915 | BQ47: =SUM(BQ44:BQ46) -> 0 | BR47: =SUM(BR44:BR46) -> 0 | BS47: =SUM(BS44:BS46) -> 0 | BT47: =SUM(BT44:BT46) -> 0
C50: Vigente | D50: =D38+D44 -> 0 | E50: =E38+E44 -> 0 | F50: =F38+F44 -> 0 | G50: =G38+G44 -> 0 | H50: =H38+H44 -> 0 | I50: =I38+I44 -> 0 | J50: =J38+J44 -> 0 | K50: =K38+K44 -> 0 | ... BK50: =BK38+BK44 -> 99018.049 | BO50: =BO38+BO44 -> 0 | BP50: =BP38+BP44 -> 245605.12 | BQ50: =BQ38+BQ44 -> 0 | BR50: =BR38+BR44 -> 0 | BS50: =BS38+BS44 -> 0 | BT50: =BT38+BT44 -> 0
C51: Refinanciado | D51: =D39+D45 -> 0 | E51: =E39+E45 -> 0 | F51: =F39+F45 -> 0 | G51: =G39+G45 -> 0 | H51: =H39+H45 -> 0 | I51: =I39+I45 -> 0 | J51: =J39+J45 -> 0 | K51: =K39+K45 -> 0 | ... BK51: =BK39+BK45 -> 816.57668 | BO51: =BO39+BO45 -> 0 | BP51: =BP39+BP45 -> 2434.4896 | BQ51: =BQ39+BQ45 -> 0 | BR51: =BR39+BR45 -> 0 | BS51: =BS39+BS45 -> 0 | BT51: =BT39+BT45 -> 0
C52: Vencido y Judicial | D52: =D40+D46 -> 0 | E52: =E40+E46 -> 0 | F52: =F40+F46 -> 0 | G52: =G40+G46 -> 0 | H52: =H40+H46 -> 0 | I52: =I40+I46 -> 0 | J52: =J40+J46 -> 0 | K52: =K40+K46 -> 0 | ... BK52: =BK40+BK46 -> 3058.6616 | BO52: =BO40+BO46 -> 0 | BP52: =BP40+BP46 -> 9470.3565 | BQ52: =BQ40+BQ46 -> 0 | BR52: =BR40+BR46 -> 0 | BS52: =BS40+BS46 -> 0 | BT52: =BT40+BT46 -> 0
C53: Resultado Financiero Bruto | D53: =D41+D47 -> 0 | E53: =E41+E47 -> 0 | F53: =F41+F47 -> 0 | G53: =G41+G47 -> 0 | H53: =H41+H47 -> 0 | I53: =I41+I47 -> 0 | J53: =J41+J47 -> 0 | K53: =K41+K47 -> 0 | ... BK53: =BK41+BK47 -> 102893.29 | BO53: =SUM(BO50:BO52) -> 0 | BP53: =SUM(BP50:BP52) -> 257509.96 | BQ53: =SUM(BQ50:BQ52) -> 0 | BR53: =SUM(BR50:BR52) -> 0 | BS53: =SUM(BS50:BS52) -> 0 | BT53: =SUM(BT50:BT52) -> 0
A56: Gasto_Provision | C56: Provisiones Cartera | D56: =RA_TC!D56+MA_TC!D56+CI_TC!D56 -> 0 | E56: =RA_TC!E56+MA_TC!E56+CI_TC!E56 -> 0 | F56: =RA_TC!F56+MA_TC!F56+CI_TC!F56 -> 0 | G56: =RA_TC!G56+MA_TC!G56+CI_TC!G56 -> 0 | H56: =RA_TC!H56+MA_TC!H56+CI_TC!H56 -> 0 | I56: =RA_TC!I56+MA_TC!I56+CI_TC!I56 -> 0 | J56: =RA_TC!J56+MA_TC!J56+CI_TC!J56 -> 0 | K56: =RA_TC!K56+MA_TC!K56+CI_TC!K56 -> 0 | ... BK56: =RA_TC!BK56+MA_TC!BK56+CI_TC!BK56 -> -61394.976 | BO56: =SUMIFS($D56:$BM56,$D$6:$BM$6,">="&BO$2,$D$6:$BM$6,"<="&BO$6,$D$5:$BM$5,BO$5) -> 0 | BP56: =SUMIFS($D56:$BM56,$D$6:$BM$6,">="&BP$2,$D$6:$BM$6,"<="&BP$6,$D$5:$BM$5,BP$5) -> -169498.18 | BQ56: =SUMIFS($D56:$BM56,$D$6:$BM$6,">="&BQ$2,$D$6:$BM$6,"<="&BQ$6,$D$5:$BM$5,BQ$5) -> 0 | BR56: =SUMIFS($D56:$BM56,$D$6:$BM$6,">="&BR$2,$D$6:$BM$6,"<="&BR$6,$D$5:$BM$5,BR$5) -> 0 | BS56: =SUMIFS($D56:$BM56,$D$6:$BM$6,">="&BS$2,$D$6:$BM$6,"<="&BS$6,$D$5:$BM$5,BS$5) -> 0 | BT56: =SUMIFS($D56:$BM56,$D$6:$BM$6,">="&BT$2,$D$6:$BM$6,"<="&BT$6,$D$5:$BM$5,BT$5) -> 0
