Workbook

Sheet Parametros
B2: Producto | C2: Convenios
B4: Año | C4: 2026
B6: Lista Fechas | C6: =EOMONTH(DATE($C$4,1,1),0) -> 46053 | E6: Segmentos | F6: Renta_Alta
C7: =EOMONTH(C6,1) -> 46081 | F7: Masivo
C8: =EOMONTH(C7,1) -> 46112 | F8: Consumo_Inicial
C9: =EOMONTH(C8,1) -> 46142 | F9: Total_Producto
C10: =EOMONTH(C9,1) -> 46173
C11: =EOMONTH(C10,1) -> 46203
C12: =EOMONTH(C11,1) -> 46234
C13: =EOMONTH(C12,1) -> 46265
C14: =EOMONTH(C13,1) -> 46295
C15: =EOMONTH(C14,1) -> 46326
C16: =EOMONTH(C15,1) -> 46356
C17: =EOMONTH(C16,1) -> 46387

Sheet Total_Producto_CHECK
D1: REAL | AZ1: PRESUPUESTO | BO1: Acumulado | BW1: Saldo Prom Acumulado
BO2: =DATE(YEAR(BO6),1,1) -> 46023 | BP2: =DATE(YEAR(BP6),1,1) -> 46023 | BQ2: =DATE(YEAR(BQ6),1,1) -> 46023 | BR2: =DATE(YEAR(BR6),1,1) -> 45658 | BS2: =DATE(YEAR(BS6),1,1) -> 45292 | BT2: =DATE(YEAR(BT6),1,1) -> 44927
C3: N° dias T.Imp | D3: 30 | E3: 30 | F3: 30 | G3: 30 | H3: 30 | I3: 30 | J3: 30 | K3: 30 | L3: 30 | M3: 30 | N3: 30 | O3: 30 | P3: 30 | Q3: 30 | R3: 30 | S3: 30 | T3: 30 | U3: 30 | V3: 30 | W3: 30 | X3: 30 | Y3: 30 | Z3: 30 | AA3: 30 | AB3: 30 | AC3: 30 | AD3: 30 | AE3: 30 | AF3: 30 | AG3: 30 | AH3: 30 | AI3: 30 | AJ3: 30 | AK3: 30 | AL3: 30 | AM3: 30 | AN3: 30 | AO3: 30 | AP3: 30 | AQ3: 30 | AR3: 30 | AS3: 30 | AT3: 30 | AU3: 30 | AV3: 30 | AW3: 30 | AX3: 30 | AY3: 30 | AZ3: 30 | BA3: 30 | BB3: 30 | BC3: 30 | BD3: 30 | BE3: 30 | BF3: 30 | BG3: 30 | BH3: 30 | BI3: 30 | BJ3: 30 | BK3: 30 | BO3: =AVERAGEIFS($D3:$BM3,$D$6:$BM$6,">="&BO$2,$D$6:$BM$6,"<="&BO$6,$D$5:$BM$5,BO$5) -> 30 | BP3: =AVERAGEIFS($D3:$BM3,$D$6:$BM$6,">="&BP$2,$D$6:$BM$6,"<="&BP$6,$D$5:$BM$5,BP$5) -> 30 | BQ3: =AVERAGEIFS($D3:$BM3,$D$6:$BM$6,">="&BQ$2,$D$6:$BM$6,"<="&BQ$6,$D$5:$BM$5,BQ$5) -> 30 | BR3: =AVERAGEIFS($D3:$BM3,$D$6:$BM$6,">="&BR$2,$D$6:$BM$6,"<="&BR$6,$D$5:$BM$5,BR$5) -> 30 | BS3: =AVERAGEIFS($D3:$BM3,$D$6:$BM$6,">="&BS$2,$D$6:$BM$6,"<="&BS$6,$D$5:$BM$5,BS$5) -> 30 | BT3: =AVERAGEIFS($D3:$BM3,$D$6:$BM$6,">="&BT$2,$D$6:$BM$6,"<="&BT$6,$D$5:$BM$5,BT$5) -> 30
C4: N° dias FTP | D4: =DAY(D6) -> 31 | E4: =DAY(E6) -> 28 | F4: =DAY(F6) -> 31 | G4: =DAY(G6) -> 30 | H4: =DAY(H6) -> 31 | I4: =DAY(I6) -> 30 | J4: =DAY(J6) -> 31 | K4: =DAY(K6) -> 31 | ... BK4: =DAY(BK6) -> 31 | BO4: =AVERAGEIFS($D4:$BM4,$D$6:$BM$6,">="&BO$2,$D$6:$BM$6,"<="&BO$6,$D$5:$BM$5,BO$5) -> 30.2 | BP4: =AVERAGEIFS($D4:$BM4,$D$6:$BM$6,">="&BP$2,$D$6:$BM$6,"<="&BP$6,$D$5:$BM$5,BP$5) -> 30.2 | BQ4: =AVERAGEIFS($D4:$BM4,$D$6:$BM$6,">="&BQ$2,$D$6:$BM$6,"<="&BQ$6,$D$5:$BM$5,BQ$5) -> 30 | BR4: =AVERAGEIFS($D4:$BM4,$D$6:$BM$6,">="&BR$2,$D$6:$BM$6,"<="&BR$6,$D$5:$BM$5,BR$5) -> 30.2 | BS4: =AVERAGEIFS($D4:$BM4,$D$6:$BM$6,">="&BS$2,$D$6:$BM$6,"<="&BS$6,$D$5:$BM$5,BS$5) -> 30.4 | BT4: =AVERAGEIFS($D4:$BM4,$D$6:$BM$6,">="&BT$2,$D$6:$BM$6,"<="&BT$6,$D$5:$BM$5,BT$5) -> 30.2
C5: Tipo | D5: R | E5: R | F5: R | G5: R | H5: R | I5: R | J5: R | K5: R | L5: R | M5: R | N5: R | O5: R | P5: R | Q5: R | R5: R | S5: R | T5: R | U5: R | V5: R | W5: R | X5: R | Y5: R | Z5: R | AA5: R | AB5: R | AC5: R | AD5: R | AE5: R | AF5: R | AG5: R | AH5: R | AI5: R | AJ5: R | AK5: R | AL5: R | AM5: R | AN5: R | AO5: R | AP5: R | AQ5: R | AR5: R | AS5: R | AT5: R | AU5: R | AV5: R | AW5: R | AX5: R | AY5: R | AZ5: P | BA5: P | BB5: P | BC5: P | BD5: P | BE5: P | BF5: P | BG5: P | BH5: P | BI5: P | BJ5: P | BK5: P | BO5: R | BP5: P | BQ5: R | BR5: R | BS5: R | BT5: R
C6: Total Convenios | D6: 44957 | E6: 44985 | F6: 45016 | G6: 45046 | H6: 45077 | I6: 45107 | J6: 45138 | K6: 45169 | L6: 45199 | M6: 45230 | N6: 45260 | O6: 45291 | P6: 45322 | Q6: 45351 | R6: 45382 | S6: 45412 | T6: 45443 | U6: 45473 | V6: 45504 | W6: 45535 | X6: 45565 | Y6: 45596 | Z6: 45626 | AA6: 45657 | AB6: 45688 | AC6: 45716 | AD6: 45747 | AE6: 45777 | AF6: 45808 | AG6: 45838 | AH6: 45869 | AI6: 45900 | AJ6: 45930 | AK6: 45961 | AL6: 45991 | AM6: 46022 | AN6: 46053 | AO6: 46081 | AP6: 46112 | AQ6: 46142 | AR6: 46173 | AS6: 46203 | AT6: 46234 | AU6: 46265 | AV6: 46295 | AW6: 46326 | AX6: 46356 | AY6: 46387 | AZ6: 46053 | BA6: 46081 | BB6: 46112 | BC6: 46142 | BD6: 46173 | BE6: 46203 | BF6: 46234 | BG6: 46265 | BH6: 46295 | BI6: 46326 | BJ6: 46356 | BK6: 46387 | BO6: =Desempeño_Financiero!$B$1 -> 46173 | BP6: =BO6 -> 46173 | BQ6: =EOMONTH(BO6,-1) -> 46142 | BR6: =EOMONTH(BO6,-12) -> 45808 | BS6: =EOMONTH(BO6,-24) -> 45443 | BT6: =EOMONTH(BO6,-36) -> 45077 | BW6: =BO6 -> 46173 | BX6: =BP6 -> 46173 | BY6: =BQ6 -> 46142 | BZ6: =BR6 -> 45808 | CA6: =BS6 -> 45443 | CB6: =BT6 -> 45077
A8: SALDO_FDP | C8: Vigente | D8: =Renta_Alta!D8+Masivo!D8+Consumo_Inicial!D8 -> 4679803.2 | E8: =Renta_Alta!E8+Masivo!E8+Consumo_Inicial!E8 -> 4747839.5 | F8: =Renta_Alta!F8+Masivo!F8+Consumo_Inicial!F8 -> 4827253.4 | G8: =Renta_Alta!G8+Masivo!G8+Consumo_Inicial!G8 -> 4875774.2 | H8: =Renta_Alta!H8+Masivo!H8+Consumo_Inicial!H8 -> 4938857 | I8: =Renta_Alta!I8+Masivo!I8+Consumo_Inicial!I8 -> 5002096.2 | J8: =Renta_Alta!J8+Masivo!J8+Consumo_Inicial!J8 -> 5048290.6 | K8: =Renta_Alta!K8+Masivo!K8+Consumo_Inicial!K8 -> 5124035.4 | ... BK8: =Renta_Alta!BK8+Masivo!BK8+Consumo_Inicial!BK8 -> 6111590.2 | BO8: =_xlfn.XLOOKUP(BO$6,$D$6:$BM$6,$D8:$BM8,,0,1) -> 5562013.9 | BP8: =_xlfn.XLOOKUP(BP$6,$D$6:$BM$6,$D8:$BM8,,0,-1) -> 5902822.3 | BQ8: =_xlfn.XLOOKUP(BQ$6,$D$6:$BM$6,$D8:$BM8,,0,1) -> 5548588.7 | BR8: =_xlfn.XLOOKUP(BR$6,$D$6:$BM$6,$D8:$BM8,,0,1) -> 5643386.7 | BS8: =_xlfn.XLOOKUP(BS$6,$D$6:$BM$6,$D8:$BM8,,0,1) -> 5684127.8 | BT8: =_xlfn.XLOOKUP(BT$6,$D$6:$BM$6,$D8:$BM8,,0,1) -> 4938857
A9: SALDO_FDP | C9: Refinanciado | D9: =Renta_Alta!D9+Masivo!D9+Consumo_Inicial!D9 -> 28879.687 | E9: =Renta_Alta!E9+Masivo!E9+Consumo_Inicial!E9 -> 29227.268 | F9: =Renta_Alta!F9+Masivo!F9+Consumo_Inicial!F9 -> 29811.06 | G9: =Renta_Alta!G9+Masivo!G9+Consumo_Inicial!G9 -> 29204.003 | H9: =Renta_Alta!H9+Masivo!H9+Consumo_Inicial!H9 -> 29479.237 | I9: =Renta_Alta!I9+Masivo!I9+Consumo_Inicial!I9 -> 29701.682 | J9: =Renta_Alta!J9+Masivo!J9+Consumo_Inicial!J9 -> 29449.713 | K9: =Renta_Alta!K9+Masivo!K9+Consumo_Inicial!K9 -> 28793.924 | ... BK9: =Renta_Alta!BK9+Masivo!BK9+Consumo_Inicial!BK9 -> 32247.399 | BO9: =_xlfn.XLOOKUP(BO$6,$D$6:$BM$6,$D9:$BM9,,0,1) -> 28277.739 | BP9: =_xlfn.XLOOKUP(BP$6,$D$6:$BM$6,$D9:$BM9,,0,-1) -> 30703.861 | BQ9: =_xlfn.XLOOKUP(BQ$6,$D$6:$BM$6,$D9:$BM9,,0,1) -> 28987.813 | BR9: =_xlfn.XLOOKUP(BR$6,$D$6:$BM$6,$D9:$BM9,,0,1) -> 28019.412 | BS9: =_xlfn.XLOOKUP(BS$6,$D$6:$BM$6,$D9:$BM9,,0,1) -> 22700.678 | BT9: =_xlfn.XLOOKUP(BT$6,$D$6:$BM$6,$D9:$BM9,,0,1) -> 29479.237
A10: SALDO_FDP | C10: Vencido y Judicial | D10: =Renta_Alta!D10+Masivo!D10+Consumo_Inicial!D10 -> 72271.196 | E10: =Renta_Alta!E10+Masivo!E10+Consumo_Inicial!E10 -> 73895.678 | F10: =Renta_Alta!F10+Masivo!F10+Consumo_Inicial!F10 -> 73945.9 | G10: =Renta_Alta!G10+Masivo!G10+Consumo_Inicial!G10 -> 71847.884 | H10: =Renta_Alta!H10+Masivo!H10+Consumo_Inicial!H10 -> 67763.653 | I10: =Renta_Alta!I10+Masivo!I10+Consumo_Inicial!I10 -> 63617.764 | J10: =Renta_Alta!J10+Masivo!J10+Consumo_Inicial!J10 -> 63955.171 | K10: =Renta_Alta!K10+Masivo!K10+Consumo_Inicial!K10 -> 61241.076 | ... BK10: =Renta_Alta!BK10+Masivo!BK10+Consumo_Inicial!BK10 -> 107955.09 | BO10: =_xlfn.XLOOKUP(BO$6,$D$6:$BM$6,$D10:$BM10,,0,1) -> 118475.52 | BP10: =_xlfn.XLOOKUP(BP$6,$D$6:$BM$6,$D10:$BM10,,0,-1) -> 110380.99 | BQ10: =_xlfn.XLOOKUP(BQ$6,$D$6:$BM$6,$D10:$BM10,,0,1) -> 118196.07 | BR10: =_xlfn.XLOOKUP(BR$6,$D$6:$BM$6,$D10:$BM10,,0,1) -> 92392.453 | BS10: =_xlfn.XLOOKUP(BS$6,$D$6:$BM$6,$D10:$BM10,,0,1) -> 66766.564 | BT10: =_xlfn.XLOOKUP(BT$6,$D$6:$BM$6,$D10:$BM10,,0,1) -> 67763.653
C11: Saldo FdP | D11: =SUM(D8:D10) -> 4780954.1 | E11: =SUM(E8:E10) -> 4850962.5 | F11: =SUM(F8:F10) -> 4931010.4 | G11: =SUM(G8:G10) -> 4976826.1 | H11: =SUM(H8:H10) -> 5036099.9 | I11: =SUM(I8:I10) -> 5095415.6 | J11: =SUM(J8:J10) -> 5141695.4 | K11: =SUM(K8:K10) -> 5214070.4 | ... BK11: =SUM(BK8:BK10) -> 6251792.7 | BO11: =SUM(BO8:BO10) -> 5708767.2 | BP11: =SUM(BP8:BP10) -> 6043907.2 | BQ11: =SUM(BQ8:BQ10) -> 5695772.5 | BR11: =SUM(BR8:BR10) -> 5763798.5 | BS11: =SUM(BS8:BS10) -> 5773595 | BT11: =SUM(BT8:BT10) -> 5036099.9
D12: ='[1]Desempeño Financiero (Evol)'!BE58 -> 4780954.1 | E12: ='[1]Desempeño Financiero (Evol)'!BF58 -> 4850962.5 | F12: ='[1]Desempeño Financiero (Evol)'!BG58 -> 4931010.4 | G12: ='[1]Desempeño Financiero (Evol)'!BH58 -> 4976826.1 | H12: ='[1]Desempeño Financiero (Evol)'!BI58 -> 5036099.9 | I12: ='[1]Desempeño Financiero (Evol)'!BJ58 -> 5095415.6 | J12: ='[1]Desempeño Financiero (Evol)'!BK58 -> 5141695.4 | K12: ='[1]Desempeño Financiero (Evol)'!BL58 -> 5214070.4 | ... AO12: ='[1]Desempeño Financiero (Evol)'!CP58 -> 5659441.5 | AZ12: ='[1]Desempeño Financiero (Evol)'!DA58 -> 5946181.6 | BA12: ='[1]Desempeño Financiero (Evol)'!DB58 -> 5964284.8 | BB12: ='[1]Desempeño Financiero (Evol)'!DC58 -> 5999599 | BC12: ='[1]Desempeño Financiero (Evol)'!DD58 -> 6021580.8 | BD12: ='[1]Desempeño Financiero (Evol)'!DE58 -> 6043907.2 | BE12: ='[1]Desempeño Financiero (Evol)'!DF58 -> 6073724.5 | BF12: ='[1]Desempeño Financiero (Evol)'!DG58 -> 6103604.6 | BG12: ='[1]Desempeño Financiero (Evol)'!DH58 -> 6132821.3 | ... BK12: ='[1]Desempeño Financiero (Evol)'!DL58 -> 6251792.7
D13: =D12-D11 -> 0.00012999959 | E13: =E12-E11 -> 0.00023000035 | F13: =F12-F11 -> -0.00026999973 | G13: =G12-G11 -> 0.000479999 | H13: =H12-H11 -> 0.00023999996 | I13: =I12-I11 -> -0.00018000044 | J13: =J12-J11 -> -0.00023999903 | K13: =K12-K11 -> -0.00026999973 | ... AO13: =AO12-AO11 -> 0 | AZ13: =AZ12-AZ11 -> 0 | BA13: =BA12-BA11 -> 0 | BB13: =BB12-BB11 -> 0 | BC13: =BC12-BC11 -> 0 | BD13: =BD12-BD11 -> 0 | BE13: =BE12-BE11 -> 0 | BF13: =BF12-BF11 -> 0 | BG13: =BG12-BG11 -> 0 | ... BK13: =BK12-BK11 -> 0
A14: SALDO_PROM | C14: Vigente | D14: =Renta_Alta!D14+Masivo!D14+Consumo_Inicial!D14 -> 4629670.8 | E14: =Renta_Alta!E14+Masivo!E14+Consumo_Inicial!E14 -> 4705225.3 | F14: =Renta_Alta!F14+Masivo!F14+Consumo_Inicial!F14 -> 4769089.5 | G14: =Renta_Alta!G14+Masivo!G14+Consumo_Inicial!G14 -> 4833539.3 | H14: =Renta_Alta!H14+Masivo!H14+Consumo_Inicial!H14 -> 4884944 | I14: =Renta_Alta!I14+Masivo!I14+Consumo_Inicial!I14 -> 4948509.1 | J14: =Renta_Alta!J14+Masivo!J14+Consumo_Inicial!J14 -> 5003780.5 | K14: =Renta_Alta!K14+Masivo!K14+Consumo_Inicial!K14 -> 5059584.1 | ... BK14: =Renta_Alta!BK14+Masivo!BK14+Consumo_Inicial!BK14 -> 6065753.3 | BO14: =IFERROR(AVERAGEIFS($D14:$BM14,$D$6:$BM$6,">="&BO$2,$D$6:$BM$6,"<="&BO$6,$D$5:$BM$5,BO$5,$D14:$BM14,"<>0"),0) -> 5501093.2 | BP14: =IFERROR(AVERAGEIFS($D14:$BM14,$D$6:$BM$6,">="&BP$2,$D$6:$BM$6,"<="&BP$6,$D$5:$BM$5,BP$5,$D14:$BM14,"<>0"),0) -> 5807134.7 | BQ14: =IFERROR(AVERAGEIFS($D14:$BM14,$D$6:$BM$6,">="&BQ$2,$D$6:$BM$6,"<="&BQ$6,$D$5:$BM$5,BQ$5,$D14:$BM14,"<>0"),0) -> 5496290.7 | BR14: =IFERROR(AVERAGEIFS($D14:$BM14,$D$6:$BM$6,">="&BR$2,$D$6:$BM$6,"<="&BR$6,$D$5:$BM$5,BR$5,$D14:$BM14,"<>0"),0) -> 5603111.6 | BS14: =IFERROR(AVERAGEIFS($D14:$BM14,$D$6:$BM$6,">="&BS$2,$D$6:$BM$6,"<="&BS$6,$D$5:$BM$5,BS$5,$D14:$BM14,"<>0"),0) -> 5448981.7 | BT14: =IFERROR(AVERAGEIFS($D14:$BM14,$D$6:$BM$6,">="&BT$2,$D$6:$BM$6,"<="&BT$6,$D$5:$BM$5,BT$5,$D14:$BM14,"<>0"),0) -> 4764493.8 | BW14: =SUMIFS($D14:$BM14,$D$6:$BM$6,">="&BO$2,$D$6:$BM$6,"<="&BO$6,$D$5:$BM$5,BO$5) -> 27505466 | BX14: =SUMIFS($D14:$BM14,$D$6:$BM$6,">="&BP$2,$D$6:$BM$6,"<="&BP$6,$D$5:$BM$5,BP$5) -> 29035674 | BY14: =SUMIFS($D14:$BM14,$D$6:$BM$6,">="&BQ$2,$D$6:$BM$6,"<="&BQ$6,$D$5:$BM$5,BQ$5) -> 21985163 | BZ14: =SUMIFS($D14:$BM14,$D$6:$BM$6,">="&BR$2,$D$6:$BM$6,"<="&BR$6,$D$5:$BM$5,BR$5) -> 28015558 | CA14: =SUMIFS($D14:$BM14,$D$6:$BM$6,">="&BS$2,$D$6:$BM$6,"<="&BS$6,$D$5:$BM$5,BS$5) -> 27244909 | CB14: =SUMIFS($D14:$BM14,$D$6:$BM$6,">="&BT$2,$D$6:$BM$6,"<="&BT$6,$D$5:$BM$5,BT$5) -> 23822469
A15: SALDO_PROM | C15: Refinanciado | D15: =Renta_Alta!D15+Masivo!D15+Consumo_Inicial!D15 -> 28843.465 | E15: =Renta_Alta!E15+Masivo!E15+Consumo_Inicial!E15 -> 28777.059 | F15: =Renta_Alta!F15+Masivo!F15+Consumo_Inicial!F15 -> 29102.631 | G15: =Renta_Alta!G15+Masivo!G15+Consumo_Inicial!G15 -> 29302.208 | H15: =Renta_Alta!H15+Masivo!H15+Consumo_Inicial!H15 -> 28758.026 | I15: =Renta_Alta!I15+Masivo!I15+Consumo_Inicial!I15 -> 29379.685 | J15: =Renta_Alta!J15+Masivo!J15+Consumo_Inicial!J15 -> 29306.467 | K15: =Renta_Alta!K15+Masivo!K15+Consumo_Inicial!K15 -> 28998.535 | ... BK15: =Renta_Alta!BK15+Masivo!BK15+Consumo_Inicial!BK15 -> 32005.544 | BO15: =IFERROR(AVERAGEIFS($D15:$BM15,$D$6:$BM$6,">="&BO$2,$D$6:$BM$6,"<="&BO$6,$D$5:$BM$5,BO$5,$D15:$BM15,"<>0"),0) -> 29506.608 | BP15: =IFERROR(AVERAGEIFS($D15:$BM15,$D$6:$BM$6,">="&BP$2,$D$6:$BM$6,"<="&BP$6,$D$5:$BM$5,BP$5,$D15:$BM15,"<>0"),0) -> 29715.91 | BQ15: =IFERROR(AVERAGEIFS($D15:$BM15,$D$6:$BM$6,">="&BQ$2,$D$6:$BM$6,"<="&BQ$6,$D$5:$BM$5,BQ$5,$D15:$BM15,"<>0"),0) -> 29784.706 | BR15: =IFERROR(AVERAGEIFS($D15:$BM15,$D$6:$BM$6,">="&BR$2,$D$6:$BM$6,"<="&BR$6,$D$5:$BM$5,BR$5,$D15:$BM15,"<>0"),0) -> 24117.375 | BS15: =IFERROR(AVERAGEIFS($D15:$BM15,$D$6:$BM$6,">="&BS$2,$D$6:$BM$6,"<="&BS$6,$D$5:$BM$5,BS$5,$D15:$BM15,"<>0"),0) -> 24880.929 | BT15: =IFERROR(AVERAGEIFS($D15:$BM15,$D$6:$BM$6,">="&BT$2,$D$6:$BM$6,"<="&BT$6,$D$5:$BM$5,BT$5,$D15:$BM15,"<>0"),0) -> 28956.678 | BW15: =SUMIFS($D15:$BM15,$D$6:$BM$6,">="&BO$2,$D$6:$BM$6,"<="&BO$6,$D$5:$BM$5,BO$5) -> 147533.04 | BX15: =SUMIFS($D15:$BM15,$D$6:$BM$6,">="&BP$2,$D$6:$BM$6,"<="&BP$6,$D$5:$BM$5,BP$5) -> 148579.55 | BY15: =SUMIFS($D15:$BM15,$D$6:$BM$6,">="&BQ$2,$D$6:$BM$6,"<="&BQ$6,$D$5:$BM$5,BQ$5) -> 119138.83 | BZ15: =SUMIFS($D15:$BM15,$D$6:$BM$6,">="&BR$2,$D$6:$BM$6,"<="&BR$6,$D$5:$BM$5,BR$5) -> 120586.87 | CA15: =SUMIFS($D15:$BM15,$D$6:$BM$6,">="&BS$2,$D$6:$BM$6,"<="&BS$6,$D$5:$BM$5,BS$5) -> 124404.64 | CB15: =SUMIFS($D15:$BM15,$D$6:$BM$6,">="&BT$2,$D$6:$BM$6,"<="&BT$6,$D$5:$BM$5,BT$5) -> 144783.39
A16: SALDO_PROM | C16: Vencido y Judicial | D16: =Renta_Alta!D16+Masivo!D16+Consumo_Inicial!D16 -> 81065.629 | E16: =Renta_Alta!E16+Masivo!E16+Consumo_Inicial!E16 -> 79227.39 | F16: =Renta_Alta!F16+Masivo!F16+Consumo_Inicial!F16 -> 80124.132 | G16: =Renta_Alta!G16+Masivo!G16+Consumo_Inicial!G16 -> 78310.975 | H16: =Renta_Alta!H16+Masivo!H16+Consumo_Inicial!H16 -> 75534.137 | I16: =Renta_Alta!I16+Masivo!I16+Consumo_Inicial!I16 -> 72466.009 | J16: =Renta_Alta!J16+Masivo!J16+Consumo_Inicial!J16 -> 67677.076 | K16: =Renta_Alta!K16+Masivo!K16+Consumo_Inicial!K16 -> 69255.945 | ... BK16: =Renta_Alta!BK16+Masivo!BK16+Consumo_Inicial!BK16 -> 107145.43 | BO16: =IFERROR(AVERAGEIFS($D16:$BM16,$D$6:$BM$6,">="&BO$2,$D$6:$BM$6,"<="&BO$6,$D$5:$BM$5,BO$5,$D16:$BM16,"<>0"),0) -> 126492.98 | BP16: =IFERROR(AVERAGEIFS($D16:$BM16,$D$6:$BM$6,">="&BP$2,$D$6:$BM$6,"<="&BP$6,$D$5:$BM$5,BP$5,$D16:$BM16,"<>0"),0) -> 113056.73 | BQ16: =IFERROR(AVERAGEIFS($D16:$BM16,$D$6:$BM$6,">="&BQ$2,$D$6:$BM$6,"<="&BQ$6,$D$5:$BM$5,BQ$5,$D16:$BM16,"<>0"),0) -> 127568.35 | BR16: =IFERROR(AVERAGEIFS($D16:$BM16,$D$6:$BM$6,">="&BR$2,$D$6:$BM$6,"<="&BR$6,$D$5:$BM$5,BR$5,$D16:$BM16,"<>0"),0) -> 98315.232 | BS16: =IFERROR(AVERAGEIFS($D16:$BM16,$D$6:$BM$6,">="&BS$2,$D$6:$BM$6,"<="&BS$6,$D$5:$BM$5,BS$5,$D16:$BM16,"<>0"),0) -> 75622.418 | BT16: =IFERROR(AVERAGEIFS($D16:$BM16,$D$6:$BM$6,">="&BT$2,$D$6:$BM$6,"<="&BT$6,$D$5:$BM$5,BT$5,$D16:$BM16,"<>0"),0) -> 78852.452 | BW16: =SUMIFS($D16:$BM16,$D$6:$BM$6,">="&BO$2,$D$6:$BM$6,"<="&BO$6,$D$5:$BM$5,BO$5) -> 632464.88 | BX16: =SUMIFS($D16:$BM16,$D$6:$BM$6,">="&BP$2,$D$6:$BM$6,"<="&BP$6,$D$5:$BM$5,BP$5) -> 565283.63 | BY16: =SUMIFS($D16:$BM16,$D$6:$BM$6,">="&BQ$2,$D$6:$BM$6,"<="&BQ$6,$D$5:$BM$5,BQ$5) -> 510273.4 | BZ16: =SUMIFS($D16:$BM16,$D$6:$BM$6,">="&BR$2,$D$6:$BM$6,"<="&BR$6,$D$5:$BM$5,BR$5) -> 491576.16 | CA16: =SUMIFS($D16:$BM16,$D$6:$BM$6,">="&BS$2,$D$6:$BM$6,"<="&BS$6,$D$5:$BM$5,BS$5) -> 378112.09 | CB16: =SUMIFS($D16:$BM16,$D$6:$BM$6,">="&BT$2,$D$6:$BM$6,"<="&BT$6,$D$5:$BM$5,BT$5) -> 394262.26
C17: Saldo Prom | D17: =SUM(D14:D16) -> 4739579.9 | E17: =SUM(E14:E16) -> 4813229.7 | F17: =SUM(F14:F16) -> 4878316.3 | G17: =SUM(G14:G16) -> 4941152.5 | H17: =SUM(H14:H16) -> 4989236.1 | I17: =SUM(I14:I16) -> 5050354.8 | J17: =SUM(J14:J16) -> 5100764.1 | K17: =SUM(K14:K16) -> 5157838.5 | ... BK17: =SUM(BK14:BK16) -> 6204904.2 | BO17: =SUM(BO14:BO16) -> 5657092.8 | BP17: =SUM(BP14:BP16) -> 5949907.4 | BQ17: =SUM(BQ14:BQ16) -> 5653643.7 | BR17: =SUM(BR14:BR16) -> 5725544.3 | BS17: =SUM(BS14:BS16) -> 5549485.1 | BT17: =SUM(BT14:BT16) -> 4872302.9 | BW17: =SUM(BW14:BW16) -> 28285464 | BX17: =SUM(BX14:BX16) -> 29749537 | BY17: =SUM(BY14:BY16) -> 22614575 | BZ17: =SUM(BZ14:BZ16) -> 28627721 | CA17: =SUM(CA14:CA16) -> 27747425 | CB17: =SUM(CB14:CB16) -> 24361515
D18: ='[1]Desempeño Financiero (Evol)'!BE106 -> 4739579.9 | E18: ='[1]Desempeño Financiero (Evol)'!BF106 -> 4813229.7 | F18: ='[1]Desempeño Financiero (Evol)'!BG106 -> 4878316.3 | G18: ='[1]Desempeño Financiero (Evol)'!BH106 -> 4941152.5 | H18: ='[1]Desempeño Financiero (Evol)'!BI106 -> 4989236.1 | I18: ='[1]Desempeño Financiero (Evol)'!BJ106 -> 5050354.8 | J18: ='[1]Desempeño Financiero (Evol)'!BK106 -> 5100764.1 | K18: ='[1]Desempeño Financiero (Evol)'!BL106 -> 5157838.5 | ... AO18: ='[1]Desempeño Financiero (Evol)'!CP106 -> 5648366.1 | AZ18: ='[1]Desempeño Financiero (Evol)'!DA106 -> 5901585.2 | BA18: ='[1]Desempeño Financiero (Evol)'!DB106 -> 5919552.7 | BB18: ='[1]Desempeño Financiero (Evol)'!DC106 -> 5953402.1 | BC18: ='[1]Desempeño Financiero (Evol)'!DD106 -> 5976419 | BD18: ='[1]Desempeño Financiero (Evol)'!DE106 -> 5998577.9 | BE18: ='[1]Desempeño Financiero (Evol)'!DF106 -> 6026956.8 | BF18: ='[1]Desempeño Financiero (Evol)'!DG106 -> 6056606.8 | BG18: ='[1]Desempeño Financiero (Evol)'!DH106 -> 6086825.1 | ... BK18: ='[1]Desempeño Financiero (Evol)'!DL106 -> 6204904.2
D19: =D18-D17 -> -0.00012999959 | E19: =E18-E17 -> -0.00039000064 | F19: =F18-F17 -> 0.00028000027 | G19: =G18-G17 -> 0.00011999998 | H19: =H18-H17 -> -0.00021999981 | I19: =I18-I17 -> 0.00029999949 | J19: =J18-J17 -> -0.00050999969 | K19: =K18-K17 -> -0.00022999942 | ... AO19: =AO18-AO17 -> 0 | AZ19: =AZ18-AZ17 -> 0 | BA19: =BA18-BA17 -> 0 | BB19: =BB18-BB17 -> 0 | BC19: =BC18-BC17 -> 0 | BD19: =BD18-BD17 -> 0 | BE19: =BE18-BE17 -> 0 | BF19: =BF18-BF17 -> 0 | BG19: =BG18-BG17 -> 0 | ... BK19: =BK18-BK17 -> 0
C20: Vigente | D20: =IFERROR(((1+D38/D14)^(360/D$3))-1,0) -> 0.12197166 | E20: =IFERROR(((1+E38/E14)^(360/E$3))-1,0) -> 0.11955985 | F20: =IFERROR(((1+F38/F14)^(360/F$3))-1,0) -> 0.11942598 | G20: =IFERROR(((1+G38/G14)^(360/G$3))-1,0) -> 0.11865279 | H20: =IFERROR(((1+H38/H14)^(360/H$3))-1,0) -> 0.11933461 | I20: =IFERROR(((1+I38/I14)^(360/I$3))-1,0) -> 0.12096763 | J20: =IFERROR(((1+J38/J14)^(360/J$3))-1,0) -> 0.12028552 | K20: =IFERROR(((1+K38/K14)^(360/K$3))-1,0) -> 0.1211712 | ... BK20: =IFERROR(((1+BK38/BK14)^(360/BK$3))-1,0) -> 0.11343738 | BO20: =IFERROR(((1+BO38/BW14)^(360/BO$3))-1,0) -> 0.11401334 | BP20: =IFERROR(((1+BP38/BX14)^(360/BP$3))-1,0) -> 0.1141319 | BQ20: =IFERROR(((1+BQ38/BY14)^(360/BQ$3))-1,0) -> 0.11417123 | BR20: =IFERROR(((1+BR38/BZ14)^(360/BR$3))-1,0) -> 0.11828543 | BS20: =IFERROR(((1+BS38/CA14)^(360/BS$3))-1,0) -> 0.11880864 | BT20: =IFERROR(((1+BT38/CB14)^(360/BT$3))-1,0) -> 0.11977102
C21: Refinanciado | D21: =IFERROR(((1+D39/D15)^(360/D$3))-1,0) -> 0.11559667 | E21: =IFERROR(((1+E39/E15)^(360/E$3))-1,0) -> 0.11204084 | F21: =IFERROR(((1+F39/F15)^(360/F$3))-1,0) -> 0.10748943 | G21: =IFERROR(((1+G39/G15)^(360/G$3))-1,0) -> 0.10999219 | H21: =IFERROR(((1+H39/H15)^(360/H$3))-1,0) -> 0.10262374 | I21: =IFERROR(((1+I39/I15)^(360/I$3))-1,0) -> 0.10562023 | J21: =IFERROR(((1+J39/J15)^(360/J$3))-1,0) -> 0.12399521 | K21: =IFERROR(((1+K39/K15)^(360/K$3))-1,0) -> 0.11668802 | ... BK21: =IFERROR(((1+BK39/BK15)^(360/BK$3))-1,0) -> 0.11182969 | BO21: =IFERROR(((1+BO39/BW15)^(360/BO$3))-1,0) -> 0.110952 | BP21: =IFERROR(((1+BP39/BX15)^(360/BP$3))-1,0) -> 0.11688993 | BQ21: =IFERROR(((1+BQ39/BY15)^(360/BQ$3))-1,0) -> 0.11170696 | BR21: =IFERROR(((1+BR39/BZ15)^(360/BR$3))-1,0) -> 0.11587421 | BS21: =IFERROR(((1+BS39/CA15)^(360/BS$3))-1,0) -> 0.11264979 | BT21: =IFERROR(((1+BT39/CB15)^(360/BT$3))-1,0) -> 0.10954141
C22: Vencido y Judicial | D22: =IFERROR(((1+D40/D16)^(360/D$3))-1,0) -> 0.042797696 | E22: =IFERROR(((1+E40/E16)^(360/E$3))-1,0) -> 0.0556634 | F22: =IFERROR(((1+F40/F16)^(360/F$3))-1,0) -> 0.038293088 | G22: =IFERROR(((1+G40/G16)^(360/G$3))-1,0) -> 0.046477681 | H22: =IFERROR(((1+H40/H16)^(360/H$3))-1,0) -> 0.044821992 | I22: =IFERROR(((1+I40/I16)^(360/I$3))-1,0) -> 0.047730938 | J22: =IFERROR(((1+J40/J16)^(360/J$3))-1,0) -> 0.034929191 | K22: =IFERROR(((1+K40/K16)^(360/K$3))-1,0) -> 0.028079141 | ... BK22: =IFERROR(((1+BK40/BK16)^(360/BK$3))-1,0) -> 0.036910738 | BO22: =IFERROR(((1+BO40/BW16)^(360/BO$3))-1,0) -> 0.025773005 | BP22: =IFERROR(((1+BP40/BX16)^(360/BP$3))-1,0) -> 0.033758698 | BQ22: =IFERROR(((1+BQ40/BY16)^(360/BQ$3))-1,0) -> 0.025986147 | BR22: =IFERROR(((1+BR40/BZ16)^(360/BR$3))-1,0) -> 0.02548946 | BS22: =IFERROR(((1+BS40/CA16)^(360/BS$3))-1,0) -> 0.034623467 | BT22: =IFERROR(((1+BT40/CB16)^(360/BT$3))-1,0) -> 0.045571915
C23: Tasa Implicita | D23: =IFERROR(((1+D41/D17)^(360/D$3))-1,0) -> 0.12053354 | E23: =IFERROR(((1+E41/E17)^(360/E$3))-1,0) -> 0.11843496 | F23: =IFERROR(((1+F41/F17)^(360/F$3))-1,0) -> 0.11797628 | G23: =IFERROR(((1+G41/G17)^(360/G$3))-1,0) -> 0.1174227 | H23: =IFERROR(((1+H41/H17)^(360/H$3))-1,0) -> 0.11807424 | I23: =IFERROR(((1+I41/I17)^(360/I$3))-1,0) -> 0.11979465 | J23: =IFERROR(((1+J41/J17)^(360/J$3))-1,0) -> 0.11913324 | K23: =IFERROR(((1+K41/K17)^(360/K$3))-1,0) -> 0.11984643 | ... BK23: =IFERROR(((1+BK41/BK17)^(360/BK$3))-1,0) -> 0.11206485 | BO23: =IFERROR(((1+BO41/BW17)^(360/BO$3))-1,0) -> 0.11195056 | BP23: =IFERROR(((1+BP41/BX17)^(360/BP$3))-1,0) -> 0.11256651 | BQ23: =IFERROR(((1+BQ41/BY17)^(360/BQ$3))-1,0) -> 0.11209416 | BR23: =IFERROR(((1+BR41/BZ17)^(360/BR$3))-1,0) -> 0.11661895 | BS23: =IFERROR(((1+BS41/CA17)^(360/BS$3))-1,0) -> 0.1175928 | BT23: =IFERROR(((1+BT41/CB17)^(360/BT$3))-1,0) -> 0.11847174
C26: Vigente | D26: =-IFERROR(((1-D44/D14)^(360/D$4))-1,0) -> -0.06076307 | E26: =-IFERROR(((1-E44/E14)^(360/E$4))-1,0) -> -0.062861897 | F26: =-IFERROR(((1-F44/F14)^(360/F$4))-1,0) -> -0.065107468 | G26: =-IFERROR(((1-G44/G14)^(360/G$4))-1,0) -> -0.067267469 | H26: =-IFERROR(((1-H44/H14)^(360/H$4))-1,0) -> -0.068542711 | I26: =-IFERROR(((1-I44/I14)^(360/I$4))-1,0) -> -0.069743013 | J26: =-IFERROR(((1-J44/J14)^(360/J$4))-1,0) -> -0.070496199 | K26: =-IFERROR(((1-K44/K14)^(360/K$4))-1,0) -> -0.071403096 | ... BK26: =-IFERROR(((1-BK44/BK14)^(360/BK$4))-1,0) -> -0.054024836 | BO26: =-IFERROR(((1-BO44/BW14)^(360/BO$4))-1,0) -> -0.05826649 | BP26: =-IFERROR(((1-BP44/BX14)^(360/BP$4))-1,0) -> -0.057861332 | BQ26: =-IFERROR(((1-BQ44/BY14)^(360/BQ$4))-1,0) -> -0.058509488 | BR26: =-IFERROR(((1-BR44/BZ14)^(360/BR$4))-1,0) -> -0.066763516 | BS26: =-IFERROR(((1-BS44/CA14)^(360/BS$4))-1,0) -> -0.072994066 | BT26: =-IFERROR(((1-BT44/CB14)^(360/BT$4))-1,0) -> -0.064995088
C27: Refinanciado | D27: =-IFERROR(((1-D45/D15)^(360/D$4))-1,0) -> -0.05371836 | E27: =-IFERROR(((1-E45/E15)^(360/E$4))-1,0) -> -0.055204536 | F27: =-IFERROR(((1-F45/F15)^(360/F$4))-1,0) -> -0.056860688 | G27: =-IFERROR(((1-G45/G15)^(360/G$4))-1,0) -> -0.05869645 | H27: =-IFERROR(((1-H45/H15)^(360/H$4))-1,0) -> -0.059672081 | I27: =-IFERROR(((1-I45/I15)^(360/I$4))-1,0) -> -0.061583078 | J27: =-IFERROR(((1-J45/J15)^(360/J$4))-1,0) -> -0.061633213 | K27: =-IFERROR(((1-K45/K15)^(360/K$4))-1,0) -> -0.063296429 | ... BK27: =-IFERROR(((1-BK45/BK15)^(360/BK$4))-1,0) -> -0.053097529 | BO27: =-IFERROR(((1-BO45/BW15)^(360/BO$4))-1,0) -> -0.061453176 | BP27: =-IFERROR(((1-BP45/BX15)^(360/BP$4))-1,0) -> -0.059392367 | BQ27: =-IFERROR(((1-BQ45/BY15)^(360/BQ$4))-1,0) -> -0.061534929 | BR27: =-IFERROR(((1-BR45/BZ15)^(360/BR$4))-1,0) -> -0.066536457 | BS27: =-IFERROR(((1-BS45/CA15)^(360/BS$4))-1,0) -> -0.068231684 | BT27: =-IFERROR(((1-BT45/CB15)^(360/BT$4))-1,0) -> -0.056855971
C28: Vencido y Judicial | D28: =-IFERROR(((1-D46/D16)^(360/D$4))-1,0) -> -0.035805183 | E28: =-IFERROR(((1-E46/E16)^(360/E$4))-1,0) -> -0.037732098 | F28: =-IFERROR(((1-F46/F16)^(360/F$4))-1,0) -> -0.040647537 | G28: =-IFERROR(((1-G46/G16)^(360/G$4))-1,0) -> -0.041280073 | H28: =-IFERROR(((1-H46/H16)^(360/H$4))-1,0) -> -0.039940912 | I28: =-IFERROR(((1-I46/I16)^(360/I$4))-1,0) -> -0.041064265 | J28: =-IFERROR(((1-J46/J16)^(360/J$4))-1,0) -> -0.044588397 | K28: =-IFERROR(((1-K46/K16)^(360/K$4))-1,0) -> -0.054704211 | ... BK28: =-IFERROR(((1-BK46/BK16)^(360/BK$4))-1,0) -> -0.061344815 | BO28: =-IFERROR(((1-BO46/BW16)^(360/BO$4))-1,0) -> -0.056001442 | BP28: =-IFERROR(((1-BP46/BX16)^(360/BP$4))-1,0) -> -0.059798829 | BQ28: =-IFERROR(((1-BQ46/BY16)^(360/BQ$4))-1,0) -> -0.055885258 | BR28: =-IFERROR(((1-BR46/BZ16)^(360/BR$4))-1,0) -> -0.066820171 | BS28: =-IFERROR(((1-BS46/CA16)^(360/BS$4))-1,0) -> -0.067442074 | BT28: =-IFERROR(((1-BT46/CB16)^(360/BT$4))-1,0) -> -0.039064413
C29: Tasa FTP | D29: =-IFERROR(((1-D47/D17)^(360/D$4))-1,0) -> -0.060288627 | E29: =-IFERROR(((1-E47/E17)^(360/E$4))-1,0) -> -0.062397832 | F29: =-IFERROR(((1-F47/F17)^(360/F$4))-1,0) -> -0.064652163 | G29: =-IFERROR(((1-G47/G17)^(360/G$4))-1,0) -> -0.06680001 | H29: =-IFERROR(((1-H47/H17)^(360/H$4))-1,0) -> -0.068053085 | I29: =-IFERROR(((1-I47/I17)^(360/I$4))-1,0) -> -0.069278822 | J29: =-IFERROR(((1-J47/J17)^(360/J$4))-1,0) -> -0.070097544 | K29: =-IFERROR(((1-K47/K17)^(360/K$4))-1,0) -> -0.071131558 | ... BK29: =-IFERROR(((1-BK47/BK17)^(360/BK$4))-1,0) -> -0.054146058 | BO29: =-IFERROR(((1-BO47/BW17)^(360/BO$4))-1,0) -> -0.058232392 | BP29: =-IFERROR(((1-BP47/BX17)^(360/BP$4))-1,0) -> -0.057905758 | BQ29: =-IFERROR(((1-BQ47/BY17)^(360/BQ$4))-1,0) -> -0.058466126 | BR29: =-IFERROR(((1-BR47/BZ17)^(360/BR$4))-1,0) -> -0.066763532 | BS29: =-IFERROR(((1-BS47/CA17)^(360/BS$4))-1,0) -> -0.072896838 | BT29: =-IFERROR(((1-BT47/CB17)^(360/BT$4))-1,0) -> -0.064522231
C32: Vigente | D32: =D20+D26 -> 0.061208594 | E32: =E20+E26 -> 0.056697957 | F32: =F20+F26 -> 0.054318512 | G32: =G20+G26 -> 0.051385325 | H32: =H20+H26 -> 0.0507919 | I32: =I20+I26 -> 0.051224617 | J32: =J20+J26 -> 0.049789316 | K32: =K20+K26 -> 0.049768103 | ... BK32: =BK20+BK26 -> 0.059412541 | BO32: =BO20+BO26 -> 0.055746847 | BP32: =BP20+BP26 -> 0.056270565 | BQ32: =BQ20+BQ26 -> 0.055661745 | BR32: =BR20+BR26 -> 0.051521917 | BS32: =BS20+BS26 -> 0.045814571 | BT32: =BT20+BT26 -> 0.054775931
C33: Refinanciado | D33: =D21+D27 -> 0.061878307 | E33: =E21+E27 -> 0.056836302 | F33: =F21+F27 -> 0.050628742 | G33: =G21+G27 -> 0.051295742 | H33: =H21+H27 -> 0.042951662 | I33: =I21+I27 -> 0.044037149 | J33: =J21+J27 -> 0.062361993 | K33: =K21+K27 -> 0.053391588 | ... BK33: =BK21+BK27 -> 0.058732161 | BO33: =BO21+BO27 -> 0.049498825 | BP33: =BP21+BP27 -> 0.057497558 | BQ33: =BQ21+BQ27 -> 0.05017203 | BR33: =BR21+BR27 -> 0.049337757 | BS33: =BS21+BS27 -> 0.044418103 | BT33: =BT21+BT27 -> 0.052685437
C34: Vencido y Judicial | D34: =D22+D28 -> 0.0069925127 | E34: =E22+E28 -> 0.017931301 | F34: =F22+F28 -> -0.0023544487 | G34: =G22+G28 -> 0.0051976077 | H34: =H22+H28 -> 0.0048810798 | I34: =I22+I28 -> 0.0066666737 | J34: =J22+J28 -> -0.0096592056 | K34: =K22+K28 -> -0.02662507 | ... BK34: =BK22+BK28 -> -0.024434077 | BO34: =BO22+BO28 -> -0.030228437 | BP34: =BP22+BP28 -> -0.026040131 | BQ34: =BQ22+BQ28 -> -0.029899111 | BR34: =BR22+BR28 -> -0.041330711 | BS34: =BS22+BS28 -> -0.032818607 | BT34: =BT22+BT28 -> 0.0065075024
C35: Spread | D35: =D23+D29 -> 0.060244916 | E35: =E23+E29 -> 0.056037131 | F35: =F23+F29 -> 0.053324117 | G35: =G23+G29 -> 0.050622688 | H35: =H23+H29 -> 0.050021155 | I35: =I23+I29 -> 0.050515827 | J35: =J23+J29 -> 0.049035699 | K35: =K23+K29 -> 0.048714875 | ... BK35: =BK23+BK29 -> 0.057918793 | BO35: =BO23+BO29 -> 0.053718171 | BP35: =BP23+BP29 -> 0.054660749 | BQ35: =BQ23+BQ29 -> 0.053628029 | BR35: =BR23+BR29 -> 0.049855419 | BS35: =BS23+BS29 -> 0.044695961 | BT35: =BT23+BT29 -> 0.053949511
A38: Ingreso_Financiero | C38: Vigente | D38: =Renta_Alta!D38+Masivo!D38+Consumo_Inicial!D38 -> 44615.058 | E38: =Renta_Alta!E38+Masivo!E38+Consumo_Inicial!E38 -> 44491.327 | F38: =Renta_Alta!F38+Masivo!F38+Consumo_Inicial!F38 -> 45047.235 | G38: =Renta_Alta!G38+Masivo!G38+Consumo_Inicial!G38 -> 45375.08 | H38: =Renta_Alta!H38+Masivo!H38+Consumo_Inicial!H38 -> 46108.016 | I38: =Renta_Alta!I38+Masivo!I38+Consumo_Inicial!I38 -> 47314.891 | J38: =Renta_Alta!J38+Masivo!J38+Consumo_Inicial!J38 -> 47587.132 | K38: =Renta_Alta!K38+Masivo!K38+Consumo_Inicial!K38 -> 48454.222 | ... BK38: =Renta_Alta!BK38+Masivo!BK38+Consumo_Inicial!BK38 -> 54558.663 | BO38: =SUMIFS($D38:$BM38,$D$6:$BM$6,">="&BO$2,$D$6:$BM$6,"<="&BO$6,$D$5:$BM$5,BO$5) -> 248595.08 | BP38: =SUMIFS($D38:$BM38,$D$6:$BM$6,">="&BP$2,$D$6:$BM$6,"<="&BP$6,$D$5:$BM$5,BP$5) -> 262684.96 | BQ38: =SUMIFS($D38:$BM38,$D$6:$BM$6,">="&BQ$2,$D$6:$BM$6,"<="&BQ$6,$D$5:$BM$5,BQ$5) -> 198964.45 | BR38: =SUMIFS($D38:$BM38,$D$6:$BM$6,">="&BR$2,$D$6:$BM$6,"<="&BR$6,$D$5:$BM$5,BR$5) -> 262223.38 | BS38: =SUMIFS($D38:$BM38,$D$6:$BM$6,">="&BS$2,$D$6:$BM$6,"<="&BS$6,$D$5:$BM$5,BS$5) -> 256082.12 | BT38: =SUMIFS($D38:$BM38,$D$6:$BM$6,">="&BT$2,$D$6:$BM$6,"<="&BT$6,$D$5:$BM$5,BT$5) -> 225636.72
A39: Ingreso_Financiero | C39: Refinanciado | D39: =Renta_Alta!D39+Masivo!D39+Consumo_Inicial!D39 -> 264.13281 | E39: =Renta_Alta!E39+Masivo!E39+Consumo_Inicial!E39 -> 255.7998 | F39: =Renta_Alta!F39+Masivo!F39+Consumo_Inicial!F39 -> 248.6607 | G39: =Renta_Alta!G39+Masivo!G39+Consumo_Inicial!G39 -> 255.92556 | H39: =Renta_Alta!H39+Masivo!H39+Consumo_Inicial!H39 -> 235.07602 | I39: =Renta_Alta!I39+Masivo!I39+Consumo_Inicial!I39 -> 246.85718 | J39: =Renta_Alta!J39+Masivo!J39+Consumo_Inicial!J39 -> 286.86302 | K39: =Renta_Alta!K39+Masivo!K39+Consumo_Inicial!K39 -> 267.93746 | ... BK39: =Renta_Alta!BK39+Masivo!BK39+Consumo_Inicial!BK39 -> 283.98689 | BO39: =SUMIFS($D39:$BM39,$D$6:$BM$6,">="&BO$2,$D$6:$BM$6,"<="&BO$6,$D$5:$BM$5,BO$5) -> 1299.2735 | BP39: =SUMIFS($D39:$BM39,$D$6:$BM$6,">="&BP$2,$D$6:$BM$6,"<="&BP$6,$D$5:$BM$5,BP$5) -> 1375.0881 | BQ39: =SUMIFS($D39:$BM39,$D$6:$BM$6,">="&BQ$2,$D$6:$BM$6,"<="&BQ$6,$D$5:$BM$5,BQ$5) -> 1056.0194 | BR39: =SUMIFS($D39:$BM39,$D$6:$BM$6,">="&BR$2,$D$6:$BM$6,"<="&BR$6,$D$5:$BM$5,BR$5) -> 1106.7919 | BS39: =SUMIFS($D39:$BM39,$D$6:$BM$6,">="&BS$2,$D$6:$BM$6,"<="&BS$6,$D$5:$BM$5,BS$5) -> 1111.5611 | BT39: =SUMIFS($D39:$BM39,$D$6:$BM$6,">="&BT$2,$D$6:$BM$6,"<="&BT$6,$D$5:$BM$5,BT$5) -> 1259.5949
A40: Ingreso_Financiero | C40: Vencido y Judicial | D40: =Renta_Alta!D40+Masivo!D40+Consumo_Inicial!D40 -> 283.59766 | E40: =Renta_Alta!E40+Masivo!E40+Consumo_Inicial!E40 -> 358.45001 | F40: =Renta_Alta!F40+Masivo!F40+Consumo_Inicial!F40 -> 251.30268 | G40: =Renta_Alta!G40+Masivo!G40+Consumo_Inicial!G40 -> 297.03378 | H40: =Renta_Alta!H40+Masivo!H40+Consumo_Inicial!H40 -> 276.49731 | I40: =Renta_Alta!I40+Masivo!I40+Consumo_Inicial!I40 -> 282.11934 | J40: =Renta_Alta!J40+Masivo!J40+Consumo_Inicial!J40 -> 193.90707 | K40: =Renta_Alta!K40+Masivo!K40+Consumo_Inicial!K40 -> 160.00505 | ... BK40: =Renta_Alta!BK40+Masivo!BK40+Consumo_Inicial!BK40 -> 324.12066 | BO40: =SUMIFS($D40:$BM40,$D$6:$BM$6,">="&BO$2,$D$6:$BM$6,"<="&BO$6,$D$5:$BM$5,BO$5) -> 1342.59 | BP40: =SUMIFS($D40:$BM40,$D$6:$BM$6,">="&BP$2,$D$6:$BM$6,"<="&BP$6,$D$5:$BM$5,BP$5) -> 1566.1821 | BQ40: =SUMIFS($D40:$BM40,$D$6:$BM$6,">="&BQ$2,$D$6:$BM$6,"<="&BQ$6,$D$5:$BM$5,BQ$5) -> 1092.0568 | BR40: =SUMIFS($D40:$BM40,$D$6:$BM$6,">="&BR$2,$D$6:$BM$6,"<="&BR$6,$D$5:$BM$5,BR$5) -> 1032.1639 | BS40: =SUMIFS($D40:$BM40,$D$6:$BM$6,">="&BS$2,$D$6:$BM$6,"<="&BS$6,$D$5:$BM$5,BS$5) -> 1074.0236 | BT40: =SUMIFS($D40:$BM40,$D$6:$BM$6,">="&BT$2,$D$6:$BM$6,"<="&BT$6,$D$5:$BM$5,BT$5) -> 1466.8814
C41: Ingreso Financiero | D41: =SUM(D38:D40) -> 45162.788 | E41: =SUM(E38:E40) -> 45105.577 | F41: =SUM(F38:F40) -> 45547.199 | G41: =SUM(G38:G40) -> 45928.039 | H41: =SUM(H38:H40) -> 46619.589 | I41: =SUM(I38:I40) -> 47843.867 | J41: =SUM(J38:J40) -> 48067.902 | K41: =SUM(K38:K40) -> 48882.165 | ... BK41: =SUM(BK38:BK40) -> 55166.771 | BO41: =SUM(BO38:BO40) -> 251236.94 | BP41: =SUM(BP38:BP40) -> 265626.23 | BQ41: =SUM(BQ38:BQ40) -> 201112.52 | BR41: =SUM(BR38:BR40) -> 264362.34 | BS41: =SUM(BS38:BS40) -> 258267.7 | BT41: =SUM(BT38:BT40) -> 228363.19
D42: ='[1]Desempeño Financiero (Evol)'!BE298 -> 45162.788 | E42: ='[1]Desempeño Financiero (Evol)'!BF298 -> 45105.577 | F42: ='[1]Desempeño Financiero (Evol)'!BG298 -> 45547.199 | G42: ='[1]Desempeño Financiero (Evol)'!BH298 -> 45928.039 | H42: ='[1]Desempeño Financiero (Evol)'!BI298 -> 46619.589 | I42: ='[1]Desempeño Financiero (Evol)'!BJ298 -> 47843.867 | J42: ='[1]Desempeño Financiero (Evol)'!BK298 -> 48067.902 | K42: ='[1]Desempeño Financiero (Evol)'!BL298 -> 48882.165 | ... AO42: ='[1]Desempeño Financiero (Evol)'!CP298 -> 50060.189 | AZ42: ='[1]Desempeño Financiero (Evol)'!DA298 -> 52859.23 | BA42: ='[1]Desempeño Financiero (Evol)'!DB298 -> 53319.441 | BB42: ='[1]Desempeño Financiero (Evol)'!DC298 -> 52897.29 | BC42: ='[1]Desempeño Financiero (Evol)'!DD298 -> 53297.064 | BD42: ='[1]Desempeño Financiero (Evol)'!DE298 -> 53253.206 | BE42: ='[1]Desempeño Financiero (Evol)'!DF298 -> 53488.787 | BF42: ='[1]Desempeño Financiero (Evol)'!DG298 -> 53867.659 | BG42: ='[1]Desempeño Financiero (Evol)'!DH298 -> 54105.408 | ... BK42: ='[1]Desempeño Financiero (Evol)'!DL298 -> 55166.771
D43: =D42-D41 -> -3.170011e-06 | E43: =E42-E41 -> -1.8699939e-06 | F43: =F42-F41 -> -1.579996e-06 | G43: =G42-G41 -> -1.750006e-06 | H43: =H42-H41 -> 2.6699927e-06 | I43: =I42-I41 -> -3.6699857e-06 | J43: =J42-J41 -> -3.5299963e-06 | K43: =K42-K41 -> -2.5599948e-06 | ... AO43: =AO42-AO41 -> 0 | AZ43: =AZ42-AZ41 -> 0 | BA43: =BA42-BA41 -> 0 | BB43: =BB42-BB41 -> 0 | BC43: =BC42-BC41 -> 0 | BD43: =BD42-BD41 -> 0 | BE43: =BE42-BE41 -> 0 | BF43: =BF42-BF41 -> 0 | BG43: =BG42-BG41 -> 0 | ... BK43: =BK42-BK41 -> 0
A44: FTP | C44: Vigente | D44: =Renta_Alta!D44+Masivo!D44+Consumo_Inicial!D44 -> -23576.554 | E44: =Renta_Alta!E44+Masivo!E44+Consumo_Inicial!E44 -> -22363.914 | F44: =Renta_Alta!F44+Masivo!F44+Consumo_Inicial!F44 -> -25973.875 | G44: =Renta_Alta!G44+Masivo!G44+Consumo_Inicial!G44 -> -26293.861 | H44: =Renta_Alta!H44+Masivo!H44+Consumo_Inicial!H44 -> -27966.932 | I44: =Renta_Alta!I44+Masivo!I44+Consumo_Inicial!I44 -> -27879.977 | J44: =Renta_Alta!J44+Masivo!J44+Consumo_Inicial!J44 -> -29438.863 | K44: =Renta_Alta!K44+Masivo!K44+Consumo_Inicial!K44 -> -30138.304 | ... BK44: =Renta_Alta!BK44+Masivo!BK44+Consumo_Inicial!BK44 -> -27545.211 | BO44: =SUMIFS($D44:$BM44,$D$6:$BM$6,">="&BO$2,$D$6:$BM$6,"<="&BO$6,$D$5:$BM$5,BO$5) -> -130984.16 | BP44: =SUMIFS($D44:$BM44,$D$6:$BM$6,">="&BP$2,$D$6:$BM$6,"<="&BP$6,$D$5:$BM$5,BP$5) -> -137334.04 | BQ44: =SUMIFS($D44:$BM44,$D$6:$BM$6,">="&BQ$2,$D$6:$BM$6,"<="&BQ$6,$D$5:$BM$5,BQ$5) -> -104423.49 | BR44: =SUMIFS($D44:$BM44,$D$6:$BM$6,">="&BR$2,$D$6:$BM$6,"<="&BR$6,$D$5:$BM$5,BR$5) -> -152303.93 | BS44: =SUMIFS($D44:$BM44,$D$6:$BM$6,">="&BS$2,$D$6:$BM$6,"<="&BS$6,$D$5:$BM$5,BS$5) -> -162572.86 | BT44: =SUMIFS($D44:$BM44,$D$6:$BM$6,">="&BT$2,$D$6:$BM$6,"<="&BT$6,$D$5:$BM$5,BT$5) -> -126175.14
A45: FTP | C45: Refinanciado | D45: =Renta_Alta!D45+Masivo!D45+Consumo_Inicial!D45 -> -130.25558 | E45: =Renta_Alta!E45+Masivo!E45+Consumo_Inicial!E45 -> -120.52135 | F45: =Renta_Alta!F45+Masivo!F45+Consumo_Inicial!F45 -> -138.9229 | G45: =Renta_Alta!G45+Masivo!G45+Consumo_Inicial!G45 -> -139.61076 | H45: =Renta_Alta!H45+Masivo!H45+Consumo_Inicial!H45 -> -143.88885 | I45: =Renta_Alta!I45+Masivo!I45+Consumo_Inicial!I45 -> -146.67886 | J45: =Renta_Alta!J45+Masivo!J45+Consumo_Inicial!J45 -> -151.32278 | K45: =Renta_Alta!K45+Masivo!K45+Consumo_Inicial!K45 -> -153.66227 | ... BK45: =Renta_Alta!BK45+Masivo!BK45+Consumo_Inicial!BK45 -> -142.90379 | BO45: =SUMIFS($D45:$BM45,$D$6:$BM$6,">="&BO$2,$D$6:$BM$6,"<="&BO$6,$D$5:$BM$5,BO$5) -> -739.96321 | BP45: =SUMIFS($D45:$BM45,$D$6:$BM$6,">="&BP$2,$D$6:$BM$6,"<="&BP$6,$D$5:$BM$5,BP$5) -> -720.86989 | BQ45: =SUMIFS($D45:$BM45,$D$6:$BM$6,">="&BQ$2,$D$6:$BM$6,"<="&BQ$6,$D$5:$BM$5,BQ$5) -> -594.3512 | BR45: =SUMIFS($D45:$BM45,$D$6:$BM$6,">="&BR$2,$D$6:$BM$6,"<="&BR$6,$D$5:$BM$5,BR$5) -> -653.39404 | BS45: =SUMIFS($D45:$BM45,$D$6:$BM$6,">="&BS$2,$D$6:$BM$6,"<="&BS$6,$D$5:$BM$5,BS$5) -> -695.33339 | BT45: =SUMIFS($D45:$BM45,$D$6:$BM$6,">="&BT$2,$D$6:$BM$6,"<="&BT$6,$D$5:$BM$5,BT$5) -> -673.19944
A46: FTP | C46: Vencido y Judicial | D46: =Renta_Alta!D46+Masivo!D46+Consumo_Inicial!D46 -> -245.94522 | E46: =Renta_Alta!E46+Masivo!E46+Consumo_Inicial!E46 -> -228.55992 | F46: =Renta_Alta!F46+Masivo!F46+Consumo_Inicial!F46 -> -275.37305 | G46: =Renta_Alta!G46+Masivo!G46+Consumo_Inicial!G46 -> -264.42386 | H46: =Renta_Alta!H46+Masivo!H46+Consumo_Inicial!H46 -> -255.16487 | I46: =Renta_Alta!I46+Masivo!I46+Consumo_Inicial!I46 -> -243.43191 | J46: =Renta_Alta!J46+Masivo!J46+Consumo_Inicial!J46 -> -254.70153 | K46: =Renta_Alta!K46+Masivo!K46+Consumo_Inicial!K46 -> -318.35863 | ... BK46: =Renta_Alta!BK46+Masivo!BK46+Consumo_Inicial!BK46 -> -550.72152 | BO46: =SUMIFS($D46:$BM46,$D$6:$BM$6,">="&BO$2,$D$6:$BM$6,"<="&BO$6,$D$5:$BM$5,BO$5) -> -2897.6575 | BP46: =SUMIFS($D46:$BM46,$D$6:$BM$6,">="&BP$2,$D$6:$BM$6,"<="&BP$6,$D$5:$BM$5,BP$5) -> -2760.8905 | BQ46: =SUMIFS($D46:$BM46,$D$6:$BM$6,">="&BQ$2,$D$6:$BM$6,"<="&BQ$6,$D$5:$BM$5,BQ$5) -> -2317.616 | BR46: =SUMIFS($D46:$BM46,$D$6:$BM$6,">="&BR$2,$D$6:$BM$6,"<="&BR$6,$D$5:$BM$5,BR$5) -> -2674.6092 | BS46: =SUMIFS($D46:$BM46,$D$6:$BM$6,">="&BS$2,$D$6:$BM$6,"<="&BS$6,$D$5:$BM$5,BS$5) -> -2089.636 | BT46: =SUMIFS($D46:$BM46,$D$6:$BM$6,">="&BT$2,$D$6:$BM$6,"<="&BT$6,$D$5:$BM$5,BT$5) -> -1269.4669
C47: Costo de Fondos | D47: =SUM(D44:D46) -> -23952.755 | E47: =SUM(E44:E46) -> -22712.996 | F47: =SUM(F44:F46) -> -26388.171 | G47: =SUM(G44:G46) -> -26697.895 | H47: =SUM(H44:H46) -> -28365.986 | I47: =SUM(I44:I46) -> -28270.087 | J47: =SUM(J44:J46) -> -29844.887 | K47: =SUM(K44:K46) -> -30610.325 | ... BK47: =SUM(BK44:BK46) -> -28238.836 | BO47: =SUM(BO44:BO46) -> -134621.78 | BP47: =SUM(BP44:BP46) -> -140815.8 | BQ47: =SUM(BQ44:BQ46) -> -107335.46 | BR47: =SUM(BR44:BR46) -> -155631.93 | BS47: =SUM(BS44:BS46) -> -165357.83 | BT47: =SUM(BT44:BT46) -> -128117.8
D48: ='[1]Desempeño Financiero (Evol)'!BE346 -> -23952.755 | E48: ='[1]Desempeño Financiero (Evol)'!BF346 -> -22712.996 | F48: ='[1]Desempeño Financiero (Evol)'!BG346 -> -26388.171 | G48: ='[1]Desempeño Financiero (Evol)'!BH346 -> -26697.895 | H48: ='[1]Desempeño Financiero (Evol)'!BI346 -> -28365.986 | I48: ='[1]Desempeño Financiero (Evol)'!BJ346 -> -28270.087 | J48: ='[1]Desempeño Financiero (Evol)'!BK346 -> -29844.887 | K48: ='[1]Desempeño Financiero (Evol)'!BL346 -> -30610.325 | ... AO48: ='[1]Desempeño Financiero (Evol)'!CP346 -> -25120.949 | AZ48: ='[1]Desempeño Financiero (Evol)'!DA346 -> -29213.938 | BA48: ='[1]Desempeño Financiero (Evol)'!DB346 -> -26215.03 | BB48: ='[1]Desempeño Financiero (Evol)'!DC346 -> -28907.316 | BC48: ='[1]Desempeño Financiero (Evol)'!DD346 -> -27838.301 | BD48: ='[1]Desempeño Financiero (Evol)'!DE346 -> -28641.217 | BE48: ='[1]Desempeño Financiero (Evol)'!DF346 -> -27618.963 | BF48: ='[1]Desempeño Financiero (Evol)'!DG346 -> -28461.838 | BG48: ='[1]Desempeño Financiero (Evol)'!DH346 -> -28397.328 | ... BK48: ='[1]Desempeño Financiero (Evol)'!DL346 -> -28238.836
D49: =D48-D47 -> 0 | E49: =E48-E47 -> 0 | F49: =F48-F47 -> 0 | G49: =G48-G47 -> 0 | H49: =H48-H47 -> 0 | I49: =I48-I47 -> 0 | J49: =J48-J47 -> 0 | K49: =K48-K47 -> 0 | ... AO49: =AO48-AO47 -> 0 | AZ49: =AZ48-AZ47 -> 0 | BA49: =BA48-BA47 -> 0 | BB49: =BB48-BB47 -> 0 | BC49: =BC48-BC47 -> 0 | BD49: =BD48-BD47 -> 0 | BE49: =BE48-BE47 -> 0 | BF49: =BF48-BF47 -> 0 | BG49: =BG48-BG47 -> 0 | ... BK49: =BK48-BK47 -> 0
C50: Vigente | D50: =D38+D44 -> 21038.503 | E50: =E38+E44 -> 22127.413 | F50: =F38+F44 -> 19073.36 | G50: =G38+G44 -> 19081.219 | H50: =H38+H44 -> 18141.084 | I50: =I38+I44 -> 19434.914 | J50: =J38+J44 -> 18148.269 | K50: =K38+K44 -> 18315.918 | ... BK50: =BK38+BK44 -> 27013.453 | BO50: =BO38+BO44 -> 117610.92 | BP50: =BP38+BP44 -> 125350.92 | BQ50: =BQ38+BQ44 -> 94540.956 | BR50: =BR38+BR44 -> 109919.46 | BS50: =BS38+BS44 -> 93509.259 | BT50: =BT38+BT44 -> 99461.58
C51: Refinanciado | D51: =D39+D45 -> 133.87723 | E51: =E39+E45 -> 135.27845 | F51: =F39+F45 -> 109.7378 | G51: =G39+G45 -> 116.3148 | H51: =H39+H45 -> 91.18717 | I51: =I39+I45 -> 100.17832 | J51: =J39+J45 -> 135.54024 | K51: =K39+K45 -> 114.27519 | ... BK51: =BK39+BK45 -> 141.0831 | BO51: =BO39+BO45 -> 559.31029 | BP51: =BP39+BP45 -> 654.21825 | BQ51: =BQ39+BQ45 -> 461.66821 | BR51: =BR39+BR45 -> 453.39782 | BS51: =BS39+BS45 -> 416.22772 | BT51: =BT39+BT45 -> 586.39545
C52: Vencido y Judicial | D52: =D40+D46 -> 37.65244 | E52: =E40+E46 -> 129.89009 | F52: =F40+F46 -> -24.07037 | G52: =G40+G46 -> 32.60992 | H52: =H40+H46 -> 21.33244 | I52: =I40+I46 -> 38.68743 | J52: =J40+J46 -> -60.79446 | K52: =K40+K46 -> -158.35358 | ... BK52: =BK40+BK46 -> -226.60086 | BO52: =BO40+BO46 -> -1555.0675 | BP52: =BP40+BP46 -> -1194.7084 | BQ52: =BQ40+BQ46 -> -1225.5592 | BR52: =BR40+BR46 -> -1642.4452 | BS52: =BS40+BS46 -> -1015.6124 | BT52: =BT40+BT46 -> 197.41452
C53: Resultado Financiero Bruto | D53: =D41+D47 -> 21210.033 | E53: =E41+E47 -> 22392.581 | F53: =F41+F47 -> 19159.028 | G53: =G41+G47 -> 19230.144 | H53: =H41+H47 -> 18253.604 | I53: =I41+I47 -> 19573.78 | J53: =J41+J47 -> 18223.015 | K53: =K41+K47 -> 18271.84 | ... BK53: =BK41+BK47 -> 26927.935 | BO53: =SUM(BO50:BO52) -> 116615.16 | BP53: =SUM(BP50:BP52) -> 124810.43 | BQ53: =SUM(BQ50:BQ52) -> 93777.065 | BR53: =SUM(BR50:BR52) -> 108730.41 | BS53: =SUM(BS50:BS52) -> 92909.875 | BT53: =SUM(BT50:BT52) -> 100245.39
A56: Gasto_Provision | C56: Provisiones Cartera | D56: =Renta_Alta!D56+Masivo!D56+Consumo_Inicial!D56 -> -11269.008 | E56: =Renta_Alta!E56+Masivo!E56+Consumo_Inicial!E56 -> -3540.0484 | F56: =Renta_Alta!F56+Masivo!F56+Consumo_Inicial!F56 -> -8011.0594 | G56: =Renta_Alta!G56+Masivo!G56+Consumo_Inicial!G56 -> -7677.8117 | H56: =Renta_Alta!H56+Masivo!H56+Consumo_Inicial!H56 -> -8448.1943 | I56: =Renta_Alta!I56+Masivo!I56+Consumo_Inicial!I56 -> -7993.2419 | J56: =Renta_Alta!J56+Masivo!J56+Consumo_Inicial!J56 -> -7775.726 | K56: =Renta_Alta!K56+Masivo!K56+Consumo_Inicial!K56 -> -12181.989 | ... BK56: =Renta_Alta!BK56+Masivo!BK56+Consumo_Inicial!BK56 -> -11288.018 | BO56: =SUMIFS($D56:$BM56,$D$6:$BM$6,">="&BO$2,$D$6:$BM$6,"<="&BO$6,$D$5:$BM$5,BO$5) -> -60623.611 | BP56: =SUMIFS($D56:$BM56,$D$6:$BM$6,">="&BP$2,$D$6:$BM$6,"<="&BP$6,$D$5:$BM$5,BP$5) -> -63589.901 | BQ56: =SUMIFS($D56:$BM56,$D$6:$BM$6,">="&BQ$2,$D$6:$BM$6,"<="&BQ$6,$D$5:$BM$5,BQ$5) -> -48352.717 | BR56: =SUMIFS($D56:$BM56,$D$6:$BM$6,">="&BR$2,$D$6:$BM$6,"<="&BR$6,$D$5:$BM$5,BR$5) -> -55698.117 | BS56: =SUMIFS($D56:$BM56,$D$6:$BM$6,">="&BS$2,$D$6:$BM$6,"<="&BS$6,$D$5:$BM$5,BS$5) -> -56705.242 | BT56: =SUMIFS($D56:$BM56,$D$6:$BM$6,">="&BT$2,$D$6:$BM$6,"<="&BT$6,$D$5:$BM$5,BT$5) -> -38946.122
A57: Recupero | C57: Recupero de Castigos | D57: =Renta_Alta!D57+Masivo!D57+Consumo_Inicial!D57 -> 2288.3841 | E57: =Renta_Alta!E57+Masivo!E57+Consumo_Inicial!E57 -> 2448.8152 | F57: =Renta_Alta!F57+Masivo!F57+Consumo_Inicial!F57 -> 2390.3711 | G57: =Renta_Alta!G57+Masivo!G57+Consumo_Inicial!G57 -> 2915.2478 | H57: =Renta_Alta!H57+Masivo!H57+Consumo_Inicial!H57 -> 3445.8707 | I57: =Renta_Alta!I57+Masivo!I57+Consumo_Inicial!I57 -> 3111.4928 | J57: =Renta_Alta!J57+Masivo!J57+Consumo_Inicial!J57 -> 2778.7596 | K57: =Renta_Alta!K57+Masivo!K57+Consumo_Inicial!K57 -> 4065.2342 | ... BK57: =Renta_Alta!BK57+Masivo!BK57+Consumo_Inicial!BK57 -> 2525.9305 | BO57: =SUMIFS($D57:$BM57,$D$6:$BM$6,">="&BO$2,$D$6:$BM$6,"<="&BO$6,$D$5:$BM$5,BO$5) -> 11355.885 | BP57: =SUMIFS($D57:$BM57,$D$6:$BM$6,">="&BP$2,$D$6:$BM$6,"<="&BP$6,$D$5:$BM$5,BP$5) -> 11183.872 | BQ57: =SUMIFS($D57:$BM57,$D$6:$BM$6,">="&BQ$2,$D$6:$BM$6,"<="&BQ$6,$D$5:$BM$5,BQ$5) -> 9297.1553 | BR57: =SUMIFS($D57:$BM57,$D$6:$BM$6,">="&BR$2,$D$6:$BM$6,"<="&BR$6,$D$5:$BM$5,BR$5) -> 12783.395 | BS57: =SUMIFS($D57:$BM57,$D$6:$BM$6,">="&BS$2,$D$6:$BM$6,"<="&BS$6,$D$5:$BM$5,BS$5) -> 13381.307 | BT57: =SUMIFS($D57:$BM57,$D$6:$BM$6,">="&BT$2,$D$6:$BM$6,"<="&BT$6,$D$5:$BM$5,BT$5) -> 13488.689
C58: Provisiones Netas | D58: =SUM(D56:D57) -> -8980.6243 | E58: =SUM(E56:E57) -> -1091.2333 | F58: =SUM(F56:F57) -> -5620.6883 | G58: =SUM(G56:G57) -> -4762.5638 | H58: =SUM(H56:H57) -> -5002.3235 | I58: =SUM(I56:I57) -> -4881.7491 | J58: =SUM(J56:J57) -> -4996.9664 | K58: =SUM(K56:K57) -> -8116.7549 | ... BK58: =SUM(BK56:BK57) -> -8762.087 | BO58: =SUM(BO56:BO57) -> -49267.727 | BP58: =SUM(BP56:BP57) -> -52406.029 | BQ58: =SUM(BQ56:BQ57) -> -39055.561 | BR58: =SUM(BR56:BR57) -> -42914.722 | BS58: =SUM(BS56:BS57) -> -43323.935 | BT58: =SUM(BT56:BT57) -> -25457.433
D59: ='[1]Desempeño Financiero (Evol)'!BE406+'[1]Desempeño Financiero (Evol)'!BE495-D58 -> 0 | E59: ='[1]Desempeño Financiero (Evol)'!BF406+'[1]Desempeño Financiero (Evol)'!BF495-E58 -> 0 | F59: ='[1]Desempeño Financiero (Evol)'!BG406+'[1]Desempeño Financiero (Evol)'!BG495-F58 -> 0 | G59: ='[1]Desempeño Financiero (Evol)'!BH406+'[1]Desempeño Financiero (Evol)'!BH495-G58 -> 0 | H59: ='[1]Desempeño Financiero (Evol)'!BI406+'[1]Desempeño Financiero (Evol)'!BI495-H58 -> 0 | I59: ='[1]Desempeño Financiero (Evol)'!BJ406+'[1]Desempeño Financiero (Evol)'!BJ495-I58 -> 0 | J59: ='[1]Desempeño Financiero (Evol)'!BK406+'[1]Desempeño Financiero (Evol)'!BK495-J58 -> 0 | K59: ='[1]Desempeño Financiero (Evol)'!BL406+'[1]Desempeño Financiero (Evol)'!BL495-K58 -> 0 | ... AO59: ='[1]Desempeño Financiero (Evol)'!CP406+'[1]Desempeño Financiero (Evol)'!CP495-AO58 -> 0 | AZ59: ='[1]Desempeño Financiero (Evol)'!DA406+'[1]Desempeño Financiero (Evol)'!DA495-AZ58 -> 0 | BA59: ='[1]Desempeño Financiero (Evol)'!DB406+'[1]Desempeño Financiero (Evol)'!DB495-BA58 -> 0 | BB59: ='[1]Desempeño Financiero (Evol)'!DC406+'[1]Desempeño Financiero (Evol)'!DC495-BB58 -> 0 | BC59: ='[1]Desempeño Financiero (Evol)'!DD406+'[1]Desempeño Financiero (Evol)'!DD495-BC58 -> 0 | BD59: ='[1]Desempeño Financiero (Evol)'!DE406+'[1]Desempeño Financiero (Evol)'!DE495-BD58 -> 0 | BE59: ='[1]Desempeño Financiero (Evol)'!DF406+'[1]Desempeño Financiero (Evol)'!DF495-BE58 -> 0 | BF59: ='[1]Desempeño Financiero (Evol)'!DG406+'[1]Desempeño Financiero (Evol)'!DG495-BF58 -> 0 | BG59: ='[1]Desempeño Financiero (Evol)'!DH406+'[1]Desempeño Financiero (Evol)'!DH495-BG58 -> 0 | ... BK59: ='[1]Desempeño Financiero (Evol)'!DL406+'[1]Desempeño Financiero (Evol)'!DL495-BK58 -> 0
C60: Resultado Financiero Neto | D60: =D53+D58 -> 12229.409 | E60: =E53+E58 -> 21301.348 | F60: =F53+F58 -> 13538.34 | G60: =G53+G58 -> 14467.58 | H60: =H53+H58 -> 13251.28 | I60: =I53+I58 -> 14692.031 | J60: =J53+J58 -> 13226.048 | K60: =K53+K58 -> 10155.085 | ... BK60: =BK53+BK58 -> 18165.848 | BO60: =BO53+BO58 -> 67347.435 | BP60: =BP53+BP58 -> 72404.4 | BQ60: =BQ53+BQ58 -> 54721.504 | BR60: =BR53+BR58 -> 65815.69 | BS60: =BS53+BS58 -> 49585.94 | BT60: =BT53+BT58 -> 74787.956
A63: INOF | C63: Seguro de Desgravamen | D63: =Renta_Alta!D63+Masivo!D63+Consumo_Inicial!D63 -> 567.64242 | E63: =Renta_Alta!E63+Masivo!E63+Consumo_Inicial!E63 -> 456.54227 | F63: =Renta_Alta!F63+Masivo!F63+Consumo_Inicial!F63 -> 489.37918 | G63: =Renta_Alta!G63+Masivo!G63+Consumo_Inicial!G63 -> 489.97764 | H63: =Renta_Alta!H63+Masivo!H63+Consumo_Inicial!H63 -> 493.20948 | I63: =Renta_Alta!I63+Masivo!I63+Consumo_Inicial!I63 -> 528.85195 | J63: =Renta_Alta!J63+Masivo!J63+Consumo_Inicial!J63 -> 529.84519 | K63: =Renta_Alta!K63+Masivo!K63+Consumo_Inicial!K63 -> 538.82969 | ... BK63: =Renta_Alta!BK63+Masivo!BK63+Consumo_Inicial!BK63 -> 589.21 | BO63: =SUMIFS($D63:$BM63,$D$6:$BM$6,">="&BO$2,$D$6:$BM$6,"<="&BO$6,$D$5:$BM$5,BO$5) -> 2657.0746 | BP63: =SUMIFS($D63:$BM63,$D$6:$BM$6,">="&BP$2,$D$6:$BM$6,"<="&BP$6,$D$5:$BM$5,BP$5) -> 2827.48 | BQ63: =SUMIFS($D63:$BM63,$D$6:$BM$6,">="&BQ$2,$D$6:$BM$6,"<="&BQ$6,$D$5:$BM$5,BQ$5) -> 2118.8089 | BR63: =SUMIFS($D63:$BM63,$D$6:$BM$6,">="&BR$2,$D$6:$BM$6,"<="&BR$6,$D$5:$BM$5,BR$5) -> 2731.0347 | BS63: =SUMIFS($D63:$BM63,$D$6:$BM$6,">="&BS$2,$D$6:$BM$6,"<="&BS$6,$D$5:$BM$5,BS$5) -> 2840.5362 | BT63: =SUMIFS($D63:$BM63,$D$6:$BM$6,">="&BT$2,$D$6:$BM$6,"<="&BT$6,$D$5:$BM$5,BT$5) -> 2496.751
A64: INOF | C64: Comisiones | D64: =Renta_Alta!D64+Masivo!D64+Consumo_Inicial!D64 -> 692.35238 | E64: =Renta_Alta!E64+Masivo!E64+Consumo_Inicial!E64 -> 687.66328 | F64: =Renta_Alta!F64+Masivo!F64+Consumo_Inicial!F64 -> 689.22883 | G64: =Renta_Alta!G64+Masivo!G64+Consumo_Inicial!G64 -> 656.934 | H64: =Renta_Alta!H64+Masivo!H64+Consumo_Inicial!H64 -> 677.1092 | I64: =Renta_Alta!I64+Masivo!I64+Consumo_Inicial!I64 -> 693.14273 | J64: =Renta_Alta!J64+Masivo!J64+Consumo_Inicial!J64 -> 700.46567 | K64: =Renta_Alta!K64+Masivo!K64+Consumo_Inicial!K64 -> 711.85328 | ... BK64: =Renta_Alta!BK64+Masivo!BK64+Consumo_Inicial!BK64 -> 713.25792 | BO64: =SUMIFS($D64:$BM64,$D$6:$BM$6,">="&BO$2,$D$6:$BM$6,"<="&BO$6,$D$5:$BM$5,BO$5) -> 3591.3921 | BP64: =SUMIFS($D64:$BM64,$D$6:$BM$6,">="&BP$2,$D$6:$BM$6,"<="&BP$6,$D$5:$BM$5,BP$5) -> 3734.3599 | BQ64: =SUMIFS($D64:$BM64,$D$6:$BM$6,">="&BQ$2,$D$6:$BM$6,"<="&BQ$6,$D$5:$BM$5,BQ$5) -> 2877.9062 | BR64: =SUMIFS($D64:$BM64,$D$6:$BM$6,">="&BR$2,$D$6:$BM$6,"<="&BR$6,$D$5:$BM$5,BR$5) -> 3823.0476 | BS64: =SUMIFS($D64:$BM64,$D$6:$BM$6,">="&BS$2,$D$6:$BM$6,"<="&BS$6,$D$5:$BM$5,BS$5) -> 3590.1603 | BT64: =SUMIFS($D64:$BM64,$D$6:$BM$6,">="&BT$2,$D$6:$BM$6,"<="&BT$6,$D$5:$BM$5,BT$5) -> 3403.2877
A65: INOF | C65: Gastos de casilleros | D65: =Renta_Alta!D65+Masivo!D65+Consumo_Inicial!D65 -> -566.15724 | E65: =Renta_Alta!E65+Masivo!E65+Consumo_Inicial!E65 -> -523.15261 | F65: =Renta_Alta!F65+Masivo!F65+Consumo_Inicial!F65 -> -574.18296 | G65: =Renta_Alta!G65+Masivo!G65+Consumo_Inicial!G65 -> -460.3984 | H65: =Renta_Alta!H65+Masivo!H65+Consumo_Inicial!H65 -> -576.71598 | I65: =Renta_Alta!I65+Masivo!I65+Consumo_Inicial!I65 -> -564.858 | J65: =Renta_Alta!J65+Masivo!J65+Consumo_Inicial!J65 -> -662.23423 | K65: =Renta_Alta!K65+Masivo!K65+Consumo_Inicial!K65 -> -680.60336 | ... BK65: =Renta_Alta!BK65+Masivo!BK65+Consumo_Inicial!BK65 -> -803 | BO65: =SUMIFS($D65:$BM65,$D$6:$BM$6,">="&BO$2,$D$6:$BM$6,"<="&BO$6,$D$5:$BM$5,BO$5) -> -1192.9396 | BP65: =SUMIFS($D65:$BM65,$D$6:$BM$6,">="&BP$2,$D$6:$BM$6,"<="&BP$6,$D$5:$BM$5,BP$5) -> -2236 | BQ65: =SUMIFS($D65:$BM65,$D$6:$BM$6,">="&BQ$2,$D$6:$BM$6,"<="&BQ$6,$D$5:$BM$5,BQ$5) -> -855.63442 | BR65: =SUMIFS($D65:$BM65,$D$6:$BM$6,">="&BR$2,$D$6:$BM$6,"<="&BR$6,$D$5:$BM$5,BR$5) -> -3385.5478 | BS65: =SUMIFS($D65:$BM65,$D$6:$BM$6,">="&BS$2,$D$6:$BM$6,"<="&BS$6,$D$5:$BM$5,BS$5) -> -3527.4263 | BT65: =SUMIFS($D65:$BM65,$D$6:$BM$6,">="&BT$2,$D$6:$BM$6,"<="&BT$6,$D$5:$BM$5,BT$5) -> -2700.6072
A66: INOF | D66: =Renta_Alta!D66+Masivo!D66+Consumo_Inicial!D66 -> 0 | E66: =Renta_Alta!E66+Masivo!E66+Consumo_Inicial!E66 -> 0 | F66: =Renta_Alta!F66+Masivo!F66+Consumo_Inicial!F66 -> 0 | G66: =Renta_Alta!G66+Masivo!G66+Consumo_Inicial!G66 -> 0 | H66: =Renta_Alta!H66+Masivo!H66+Consumo_Inicial!H66 -> 0 | I66: =Renta_Alta!I66+Masivo!I66+Consumo_Inicial!I66 -> 0 | J66: =Renta_Alta!J66+Masivo!J66+Consumo_Inicial!J66 -> 0 | K66: =Renta_Alta!K66+Masivo!K66+Consumo_Inicial!K66 -> 0 | ... BK66: =Renta_Alta!BK66+Masivo!BK66+Consumo_Inicial!BK66 -> 0 | BO66: =SUMIFS($D66:$BM66,$D$6:$BM$6,">="&BO$2,$D$6:$BM$6,"<="&BO$6,$D$5:$BM$5,BO$5) -> 0 | BP66: =SUMIFS($D66:$BM66,$D$6:$BM$6,">="&BP$2,$D$6:$BM$6,"<="&BP$6,$D$5:$BM$5,BP$5) -> 0 | BQ66: =SUMIFS($D66:$BM66,$D$6:$BM$6,">="&BQ$2,$D$6:$BM$6,"<="&BQ$6,$D$5:$BM$5,BQ$5) -> 0 | BR66: =SUMIFS($D66:$BM66,$D$6:$BM$6,">="&BR$2,$D$6:$BM$6,"<="&BR$6,$D$5:$BM$5,BR$5) -> 0 | BS66: =SUMIFS($D66:$BM66,$D$6:$BM$6,">="&BS$2,$D$6:$BM$6,"<="&BS$6,$D$5:$BM$5,BS$5) -> 0 | BT66: =SUMIFS($D66:$BM66,$D$6:$BM$6,">="&BT$2,$D$6:$BM$6,"<="&BT$6,$D$5:$BM$5,BT$5) -> 0
A67: INOF | D67: =Renta_Alta!D67+Masivo!D67+Consumo_Inicial!D67 -> 0 | E67: =Renta_Alta!E67+Masivo!E67+Consumo_Inicial!E67 -> 0 | F67: =Renta_Alta!F67+Masivo!F67+Consumo_Inicial!F67 -> 0 | G67: =Renta_Alta!G67+Masivo!G67+Consumo_Inicial!G67 -> 0 | H67: =Renta_Alta!H67+Masivo!H67+Consumo_Inicial!H67 -> 0 | I67: =Renta_Alta!I67+Masivo!I67+Consumo_Inicial!I67 -> 0 | J67: =Renta_Alta!J67+Masivo!J67+Consumo_Inicial!J67 -> 0 | K67: =Renta_Alta!K67+Masivo!K67+Consumo_Inicial!K67 -> 0 | ... BK67: =Renta_Alta!BK67+Masivo!BK67+Consumo_Inicial!BK67 -> 0 | BO67: =SUMIFS($D67:$BM67,$D$6:$BM$6,">="&BO$2,$D$6:$BM$6,"<="&BO$6,$D$5:$BM$5,BO$5) -> 0 | BP67: =SUMIFS($D67:$BM67,$D$6:$BM$6,">="&BP$2,$D$6:$BM$6,"<="&BP$6,$D$5:$BM$5,BP$5) -> 0 | BQ67: =SUMIFS($D67:$BM67,$D$6:$BM$6,">="&BQ$2,$D$6:$BM$6,"<="&BQ$6,$D$5:$BM$5,BQ$5) -> 0 | BR67: =SUMIFS($D67:$BM67,$D$6:$BM$6,">="&BR$2,$D$6:$BM$6,"<="&BR$6,$D$5:$BM$5,BR$5) -> 0 | BS67: =SUMIFS($D67:$BM67,$D$6:$BM$6,">="&BS$2,$D$6:$BM$6,"<="&BS$6,$D$5:$BM$5,BS$5) -> 0 | BT67: =SUMIFS($D67:$BM67,$D$6:$BM$6,">="&BT$2,$D$6:$BM$6,"<="&BT$6,$D$5:$BM$5,BT$5) -> 0
A68: INOF | D68: =Renta_Alta!D68+Masivo!D68+Consumo_Inicial!D68 -> 0 | E68: =Renta_Alta!E68+Masivo!E68+Consumo_Inicial!E68 -> 0 | F68: =Renta_Alta!F68+Masivo!F68+Consumo_Inicial!F68 -> 0 | G68: =Renta_Alta!G68+Masivo!G68+Consumo_Inicial!G68 -> 0 | H68: =Renta_Alta!H68+Masivo!H68+Consumo_Inicial!H68 -> 0 | I68: =Renta_Alta!I68+Masivo!I68+Consumo_Inicial!I68 -> 0 | J68: =Renta_Alta!J68+Masivo!J68+Consumo_Inicial!J68 -> 0 | K68: =Renta_Alta!K68+Masivo!K68+Consumo_Inicial!K68 -> 0 | ... BK68: =Renta_Alta!BK68+Masivo!BK68+Consumo_Inicial!BK68 -> 0 | BO68: =SUMIFS($D68:$BM68,$D$6:$BM$6,">="&BO$2,$D$6:$BM$6,"<="&BO$6,$D$5:$BM$5,BO$5) -> 0 | BP68: =SUMIFS($D68:$BM68,$D$6:$BM$6,">="&BP$2,$D$6:$BM$6,"<="&BP$6,$D$5:$BM$5,BP$5) -> 0 | BQ68: =SUMIFS($D68:$BM68,$D$6:$BM$6,">="&BQ$2,$D$6:$BM$6,"<="&BQ$6,$D$5:$BM$5,BQ$5) -> 0 | BR68: =SUMIFS($D68:$BM68,$D$6:$BM$6,">="&BR$2,$D$6:$BM$6,"<="&BR$6,$D$5:$BM$5,BR$5) -> 0 | BS68: =SUMIFS($D68:$BM68,$D$6:$BM$6,">="&BS$2,$D$6:$BM$6,"<="&BS$6,$D$5:$BM$5,BS$5) -> 0 | BT68: =SUMIFS($D68:$BM68,$D$6:$BM$6,">="&BT$2,$D$6:$BM$6,"<="&BT$6,$D$5:$BM$5,BT$5) -> 0
A69: INOF | D69: =Renta_Alta!D69+Masivo!D69+Consumo_Inicial!D69 -> 0 | E69: =Renta_Alta!E69+Masivo!E69+Consumo_Inicial!E69 -> 0 | F69: =Renta_Alta!F69+Masivo!F69+Consumo_Inicial!F69 -> 0 | G69: =Renta_Alta!G69+Masivo!G69+Consumo_Inicial!G69 -> 0 | H69: =Renta_Alta!H69+Masivo!H69+Consumo_Inicial!H69 -> 0 | I69: =Renta_Alta!I69+Masivo!I69+Consumo_Inicial!I69 -> 0 | J69: =Renta_Alta!J69+Masivo!J69+Consumo_Inicial!J69 -> 0 | K69: =Renta_Alta!K69+Masivo!K69+Consumo_Inicial!K69 -> 0 | ... BK69: =Renta_Alta!BK69+Masivo!BK69+Consumo_Inicial!BK69 -> 0 | BO69: =SUMIFS($D69:$BM69,$D$6:$BM$6,">="&BO$2,$D$6:$BM$6,"<="&BO$6,$D$5:$BM$5,BO$5) -> 0 | BP69: =SUMIFS($D69:$BM69,$D$6:$BM$6,">="&BP$2,$D$6:$BM$6,"<="&BP$6,$D$5:$BM$5,BP$5) -> 0 | BQ69: =SUMIFS($D69:$BM69,$D$6:$BM$6,">="&BQ$2,$D$6:$BM$6,"<="&BQ$6,$D$5:$BM$5,BQ$5) -> 0 | BR69: =SUMIFS($D69:$BM69,$D$6:$BM$6,">="&BR$2,$D$6:$BM$6,"<="&BR$6,$D$5:$BM$5,BR$5) -> 0 | BS69: =SUMIFS($D69:$BM69,$D$6:$BM$6,">="&BS$2,$D$6:$BM$6,"<="&BS$6,$D$5:$BM$5,BS$5) -> 0 | BT69: =SUMIFS($D69:$BM69,$D$6:$BM$6,">="&BT$2,$D$6:$BM$6,"<="&BT$6,$D$5:$BM$5,BT$5) -> 0
A70: INOF | D70: =Renta_Alta!D70+Masivo!D70+Consumo_Inicial!D70 -> 0 | E70: =Renta_Alta!E70+Masivo!E70+Consumo_Inicial!E70 -> 0 | F70: =Renta_Alta!F70+Masivo!F70+Consumo_Inicial!F70 -> 0 | G70: =Renta_Alta!G70+Masivo!G70+Consumo_Inicial!G70 -> 0 | H70: =Renta_Alta!H70+Masivo!H70+Consumo_Inicial!H70 -> 0 | I70: =Renta_Alta!I70+Masivo!I70+Consumo_Inicial!I70 -> 0 | J70: =Renta_Alta!J70+Masivo!J70+Consumo_Inicial!J70 -> 0 | K70: =Renta_Alta!K70+Masivo!K70+Consumo_Inicial!K70 -> 0 | ... BK70: =Renta_Alta!BK70+Masivo!BK70+Consumo_Inicial!BK70 -> 0 | BO70: =SUMIFS($D70:$BM70,$D$6:$BM$6,">="&BO$2,$D$6:$BM$6,"<="&BO$6,$D$5:$BM$5,BO$5) -> 0 | BP70: =SUMIFS($D70:$BM70,$D$6:$BM$6,">="&BP$2,$D$6:$BM$6,"<="&BP$6,$D$5:$BM$5,BP$5) -> 0 | BQ70: =SUMIFS($D70:$BM70,$D$6:$BM$6,">="&BQ$2,$D$6:$BM$6,"<="&BQ$6,$D$5:$BM$5,BQ$5) -> 0 | BR70: =SUMIFS($D70:$BM70,$D$6:$BM$6,">="&BR$2,$D$6:$BM$6,"<="&BR$6,$D$5:$BM$5,BR$5) -> 0 | BS70: =SUMIFS($D70:$BM70,$D$6:$BM$6,">="&BS$2,$D$6:$BM$6,"<="&BS$6,$D$5:$BM$5,BS$5) -> 0 | BT70: =SUMIFS($D70:$BM70,$D$6:$BM$6,">="&BT$2,$D$6:$BM$6,"<="&BT$6,$D$5:$BM$5,BT$5) -> 0
A71: INOF | D71: =Renta_Alta!D71+Masivo!D71+Consumo_Inicial!D71 -> 0 | E71: =Renta_Alta!E71+Masivo!E71+Consumo_Inicial!E71 -> 0 | F71: =Renta_Alta!F71+Masivo!F71+Consumo_Inicial!F71 -> 0 | G71: =Renta_Alta!G71+Masivo!G71+Consumo_Inicial!G71 -> 0 | H71: =Renta_Alta!H71+Masivo!H71+Consumo_Inicial!H71 -> 0 | I71: =Renta_Alta!I71+Masivo!I71+Consumo_Inicial!I71 -> 0 | J71: =Renta_Alta!J71+Masivo!J71+Consumo_Inicial!J71 -> 0 | K71: =Renta_Alta!K71+Masivo!K71+Consumo_Inicial!K71 -> 0 | ... BK71: =Renta_Alta!BK71+Masivo!BK71+Consumo_Inicial!BK71 -> 0 | BO71: =SUMIFS($D71:$BM71,$D$6:$BM$6,">="&BO$2,$D$6:$BM$6,"<="&BO$6,$D$5:$BM$5,BO$5) -> 0 | BP71: =SUMIFS($D71:$BM71,$D$6:$BM$6,">="&BP$2,$D$6:$BM$6,"<="&BP$6,$D$5:$BM$5,BP$5) -> 0 | BQ71: =SUMIFS($D71:$BM71,$D$6:$BM$6,">="&BQ$2,$D$6:$BM$6,"<="&BQ$6,$D$5:$BM$5,BQ$5) -> 0 | BR71: =SUMIFS($D71:$BM71,$D$6:$BM$6,">="&BR$2,$D$6:$BM$6,"<="&BR$6,$D$5:$BM$5,BR$5) -> 0 | BS71: =SUMIFS($D71:$BM71,$D$6:$BM$6,">="&BS$2,$D$6:$BM$6,"<="&BS$6,$D$5:$BM$5,BS$5) -> 0 | BT71: =SUMIFS($D71:$BM71,$D$6:$BM$6,">="&BT$2,$D$6:$BM$6,"<="&BT$6,$D$5:$BM$5,BT$5) -> 0
A72: INOF | D72: =Renta_Alta!D72+Masivo!D72+Consumo_Inicial!D72 -> 0 | E72: =Renta_Alta!E72+Masivo!E72+Consumo_Inicial!E72 -> 0 | F72: =Renta_Alta!F72+Masivo!F72+Consumo_Inicial!F72 -> 0 | G72: =Renta_Alta!G72+Masivo!G72+Consumo_Inicial!G72 -> 0 | H72: =Renta_Alta!H72+Masivo!H72+Consumo_Inicial!H72 -> 0 | I72: =Renta_Alta!I72+Masivo!I72+Consumo_Inicial!I72 -> 0 | J72: =Renta_Alta!J72+Masivo!J72+Consumo_Inicial!J72 -> 0 | K72: =Renta_Alta!K72+Masivo!K72+Consumo_Inicial!K72 -> 0 | ... BK72: =Renta_Alta!BK72+Masivo!BK72+Consumo_Inicial!BK72 -> 0 | BO72: =SUMIFS($D72:$BM72,$D$6:$BM$6,">="&BO$2,$D$6:$BM$6,"<="&BO$6,$D$5:$BM$5,BO$5) -> 0 | BP72: =SUMIFS($D72:$BM72,$D$6:$BM$6,">="&BP$2,$D$6:$BM$6,"<="&BP$6,$D$5:$BM$5,BP$5) -> 0 | BQ72: =SUMIFS($D72:$BM72,$D$6:$BM$6,">="&BQ$2,$D$6:$BM$6,"<="&BQ$6,$D$5:$BM$5,BQ$5) -> 0 | BR72: =SUMIFS($D72:$BM72,$D$6:$BM$6,">="&BR$2,$D$6:$BM$6,"<="&BR$6,$D$5:$BM$5,BR$5) -> 0 | BS72: =SUMIFS($D72:$BM72,$D$6:$BM$6,">="&BS$2,$D$6:$BM$6,"<="&BS$6,$D$5:$BM$5,BS$5) -> 0 | BT72: =SUMIFS($D72:$BM72,$D$6:$BM$6,">="&BT$2,$D$6:$BM$6,"<="&BT$6,$D$5:$BM$5,BT$5) -> 0
A73: INOF | D73: =Renta_Alta!D73+Masivo!D73+Consumo_Inicial!D73 -> 0 | E73: =Renta_Alta!E73+Masivo!E73+Consumo_Inicial!E73 -> 0 | F73: =Renta_Alta!F73+Masivo!F73+Consumo_Inicial!F73 -> 0 | G73: =Renta_Alta!G73+Masivo!G73+Consumo_Inicial!G73 -> 0 | H73: =Renta_Alta!H73+Masivo!H73+Consumo_Inicial!H73 -> 0 | I73: =Renta_Alta!I73+Masivo!I73+Consumo_Inicial!I73 -> 0 | J73: =Renta_Alta!J73+Masivo!J73+Consumo_Inicial!J73 -> 0 | K73: =Renta_Alta!K73+Masivo!K73+Consumo_Inicial!K73 -> 0 | ... BK73: =Renta_Alta!BK73+Masivo!BK73+Consumo_Inicial!BK73 -> 0 | BO73: =SUMIFS($D73:$BM73,$D$6:$BM$6,">="&BO$2,$D$6:$BM$6,"<="&BO$6,$D$5:$BM$5,BO$5) -> 0 | BP73: =SUMIFS($D73:$BM73,$D$6:$BM$6,">="&BP$2,$D$6:$BM$6,"<="&BP$6,$D$5:$BM$5,BP$5) -> 0 | BQ73: =SUMIFS($D73:$BM73,$D$6:$BM$6,">="&BQ$2,$D$6:$BM$6,"<="&BQ$6,$D$5:$BM$5,BQ$5) -> 0 | BR73: =SUMIFS($D73:$BM73,$D$6:$BM$6,">="&BR$2,$D$6:$BM$6,"<="&BR$6,$D$5:$BM$5,BR$5) -> 0 | BS73: =SUMIFS($D73:$BM73,$D$6:$BM$6,">="&BS$2,$D$6:$BM$6,"<="&BS$6,$D$5:$BM$5,BS$5) -> 0 | BT73: =SUMIFS($D73:$BM73,$D$6:$BM$6,">="&BT$2,$D$6:$BM$6,"<="&BT$6,$D$5:$BM$5,BT$5) -> 0
A74: INOF | D74: =Renta_Alta!D74+Masivo!D74+Consumo_Inicial!D74 -> 0 | E74: =Renta_Alta!E74+Masivo!E74+Consumo_Inicial!E74 -> 0 | F74: =Renta_Alta!F74+Masivo!F74+Consumo_Inicial!F74 -> 0 | G74: =Renta_Alta!G74+Masivo!G74+Consumo_Inicial!G74 -> 0 | H74: =Renta_Alta!H74+Masivo!H74+Consumo_Inicial!H74 -> 0 | I74: =Renta_Alta!I74+Masivo!I74+Consumo_Inicial!I74 -> 0 | J74: =Renta_Alta!J74+Masivo!J74+Consumo_Inicial!J74 -> 0 | K74: =Renta_Alta!K74+Masivo!K74+Consumo_Inicial!K74 -> 0 | ... BK74: =Renta_Alta!BK74+Masivo!BK74+Consumo_Inicial!BK74 -> 0 | BO74: =SUMIFS($D74:$BM74,$D$6:$BM$6,">="&BO$2,$D$6:$BM$6,"<="&BO$6,$D$5:$BM$5,BO$5) -> 0 | BP74: =SUMIFS($D74:$BM74,$D$6:$BM$6,">="&BP$2,$D$6:$BM$6,"<="&BP$6,$D$5:$BM$5,BP$5) -> 0 | BQ74: =SUMIFS($D74:$BM74,$D$6:$BM$6,">="&BQ$2,$D$6:$BM$6,"<="&BQ$6,$D$5:$BM$5,BQ$5) -> 0 | BR74: =SUMIFS($D74:$BM74,$D$6:$BM$6,">="&BR$2,$D$6:$BM$6,"<="&BR$6,$D$5:$BM$5,BR$5) -> 0 | BS74: =SUMIFS($D74:$BM74,$D$6:$BM$6,">="&BS$2,$D$6:$BM$6,"<="&BS$6,$D$5:$BM$5,BS$5) -> 0 | BT74: =SUMIFS($D74:$BM74,$D$6:$BM$6,">="&BT$2,$D$6:$BM$6,"<="&BT$6,$D$5:$BM$5,BT$5) -> 0
A75: INOF | D75: =Renta_Alta!D75+Masivo!D75+Consumo_Inicial!D75 -> 0 | E75: =Renta_Alta!E75+Masivo!E75+Consumo_Inicial!E75 -> 0 | F75: =Renta_Alta!F75+Masivo!F75+Consumo_Inicial!F75 -> 0 | G75: =Renta_Alta!G75+Masivo!G75+Consumo_Inicial!G75 -> 0 | H75: =Renta_Alta!H75+Masivo!H75+Consumo_Inicial!H75 -> 0 | I75: =Renta_Alta!I75+Masivo!I75+Consumo_Inicial!I75 -> 0 | J75: =Renta_Alta!J75+Masivo!J75+Consumo_Inicial!J75 -> 0 | K75: =Renta_Alta!K75+Masivo!K75+Consumo_Inicial!K75 -> 0 | ... BK75: =Renta_Alta!BK75+Masivo!BK75+Consumo_Inicial!BK75 -> 0 | BO75: =SUMIFS($D75:$BM75,$D$6:$BM$6,">="&BO$2,$D$6:$BM$6,"<="&BO$6,$D$5:$BM$5,BO$5) -> 0 | BP75: =SUMIFS($D75:$BM75,$D$6:$BM$6,">="&BP$2,$D$6:$BM$6,"<="&BP$6,$D$5:$BM$5,BP$5) -> 0 | BQ75: =SUMIFS($D75:$BM75,$D$6:$BM$6,">="&BQ$2,$D$6:$BM$6,"<="&BQ$6,$D$5:$BM$5,BQ$5) -> 0 | BR75: =SUMIFS($D75:$BM75,$D$6:$BM$6,">="&BR$2,$D$6:$BM$6,"<="&BR$6,$D$5:$BM$5,BR$5) -> 0 | BS75: =SUMIFS($D75:$BM75,$D$6:$BM$6,">="&BS$2,$D$6:$BM$6,"<="&BS$6,$D$5:$BM$5,BS$5) -> 0 | BT75: =SUMIFS($D75:$BM75,$D$6:$BM$6,">="&BT$2,$D$6:$BM$6,"<="&BT$6,$D$5:$BM$5,BT$5) -> 0
A76: INOF | D76: =Renta_Alta!D76+Masivo!D76+Consumo_Inicial!D76 -> 0 | E76: =Renta_Alta!E76+Masivo!E76+Consumo_Inicial!E76 -> 0 | F76: =Renta_Alta!F76+Masivo!F76+Consumo_Inicial!F76 -> 0 | G76: =Renta_Alta!G76+Masivo!G76+Consumo_Inicial!G76 -> 0 | H76: =Renta_Alta!H76+Masivo!H76+Consumo_Inicial!H76 -> 0 | I76: =Renta_Alta!I76+Masivo!I76+Consumo_Inicial!I76 -> 0 | J76: =Renta_Alta!J76+Masivo!J76+Consumo_Inicial!J76 -> 0 | K76: =Renta_Alta!K76+Masivo!K76+Consumo_Inicial!K76 -> 0 | ... BK76: =Renta_Alta!BK76+Masivo!BK76+Consumo_Inicial!BK76 -> 0 | BO76: =SUMIFS($D76:$BM76,$D$6:$BM$6,">="&BO$2,$D$6:$BM$6,"<="&BO$6,$D$5:$BM$5,BO$5) -> 0 | BP76: =SUMIFS($D76:$BM76,$D$6:$BM$6,">="&BP$2,$D$6:$BM$6,"<="&BP$6,$D$5:$BM$5,BP$5) -> 0 | BQ76: =SUMIFS($D76:$BM76,$D$6:$BM$6,">="&BQ$2,$D$6:$BM$6,"<="&BQ$6,$D$5:$BM$5,BQ$5) -> 0 | BR76: =SUMIFS($D76:$BM76,$D$6:$BM$6,">="&BR$2,$D$6:$BM$6,"<="&BR$6,$D$5:$BM$5,BR$5) -> 0 | BS76: =SUMIFS($D76:$BM76,$D$6:$BM$6,">="&BS$2,$D$6:$BM$6,"<="&BS$6,$D$5:$BM$5,BS$5) -> 0 | BT76: =SUMIFS($D76:$BM76,$D$6:$BM$6,">="&BT$2,$D$6:$BM$6,"<="&BT$6,$D$5:$BM$5,BT$5) -> 0
A77: INOF | D77: =Renta_Alta!D77+Masivo!D77+Consumo_Inicial!D77 -> 0 | E77: =Renta_Alta!E77+Masivo!E77+Consumo_Inicial!E77 -> 0 | F77: =Renta_Alta!F77+Masivo!F77+Consumo_Inicial!F77 -> 0 | G77: =Renta_Alta!G77+Masivo!G77+Consumo_Inicial!G77 -> 0 | H77: =Renta_Alta!H77+Masivo!H77+Consumo_Inicial!H77 -> 0 | I77: =Renta_Alta!I77+Masivo!I77+Consumo_Inicial!I77 -> 0 | J77: =Renta_Alta!J77+Masivo!J77+Consumo_Inicial!J77 -> 0 | K77: =Renta_Alta!K77+Masivo!K77+Consumo_Inicial!K77 -> 0 | ... BK77: =Renta_Alta!BK77+Masivo!BK77+Consumo_Inicial!BK77 -> 0 | BO77: =SUMIFS($D77:$BM77,$D$6:$BM$6,">="&BO$2,$D$6:$BM$6,"<="&BO$6,$D$5:$BM$5,BO$5) -> 0 | BP77: =SUMIFS($D77:$BM77,$D$6:$BM$6,">="&BP$2,$D$6:$BM$6,"<="&BP$6,$D$5:$BM$5,BP$5) -> 0 | BQ77: =SUMIFS($D77:$BM77,$D$6:$BM$6,">="&BQ$2,$D$6:$BM$6,"<="&BQ$6,$D$5:$BM$5,BQ$5) -> 0 | BR77: =SUMIFS($D77:$BM77,$D$6:$BM$6,">="&BR$2,$D$6:$BM$6,"<="&BR$6,$D$5:$BM$5,BR$5) -> 0 | BS77: =SUMIFS($D77:$BM77,$D$6:$BM$6,">="&BS$2,$D$6:$BM$6,"<="&BS$6,$D$5:$BM$5,BS$5) -> 0 | BT77: =SUMIFS($D77:$BM77,$D$6:$BM$6,">="&BT$2,$D$6:$BM$6,"<="&BT$6,$D$5:$BM$5,BT$5) -> 0
... A82: INOF | D82: =Renta_Alta!D82+Masivo!D82+Consumo_Inicial!D82 -> 0 | E82: =Renta_Alta!E82+Masivo!E82+Consumo_Inicial!E82 -> 0 | F82: =Renta_Alta!F82+Masivo!F82+Consumo_Inicial!F82 -> 0 | G82: =Renta_Alta!G82+Masivo!G82+Consumo_Inicial!G82 -> 0 | H82: =Renta_Alta!H82+Masivo!H82+Consumo_Inicial!H82 -> 0 | I82: =Renta_Alta!I82+Masivo!I82+Consumo_Inicial!I82 -> 0 | J82: =Renta_Alta!J82+Masivo!J82+Consumo_Inicial!J82 -> 0 | K82: =Renta_Alta!K82+Masivo!K82+Consumo_Inicial!K82 -> 0 | ... BK82: =Renta_Alta!BK82+Masivo!BK82+Consumo_Inicial!BK82 -> 0 | BO82: =SUMIFS($D82:$BM82,$D$6:$BM$6,">="&BO$2,$D$6:$BM$6,"<="&BO$6,$D$5:$BM$5,BO$5) -> 0 | BP82: =SUMIFS($D82:$BM82,$D$6:$BM$6,">="&BP$2,$D$6:$BM$6,"<="&BP$6,$D$5:$BM$5,BP$5) -> 0 | BQ82: =SUMIFS($D82:$BM82,$D$6:$BM$6,">="&BQ$2,$D$6:$BM$6,"<="&BQ$6,$D$5:$BM$5,BQ$5) -> 0 | BR82: =SUMIFS($D82:$BM82,$D$6:$BM$6,">="&BR$2,$D$6:$BM$6,"<="&BR$6,$D$5:$BM$5,BR$5) -> 0 | BS82: =SUMIFS($D82:$BM82,$D$6:$BM$6,">="&BS$2,$D$6:$BM$6,"<="&BS$6,$D$5:$BM$5,BS$5) -> 0 | BT82: =SUMIFS($D82:$BM82,$D$6:$BM$6,">="&BT$2,$D$6:$BM$6,"<="&BT$6,$D$5:$BM$5,BT$5) -> 0
C83: INOF | D83: =SUM(D63:D82) -> 693.83756 | E83: =SUM(E63:E82) -> 621.05294 | F83: =SUM(F63:F82) -> 604.42505 | G83: =SUM(G63:G82) -> 686.51324 | H83: =SUM(H63:H82) -> 593.6027 | I83: =SUM(I63:I82) -> 657.13668 | J83: =SUM(J63:J82) -> 568.07663 | K83: =SUM(K63:K82) -> 570.07961 | ... BK83: =SUM(BK63:BK82) -> 499.46792 | BO83: =SUM(BO63:BO82) -> 5055.5271 | BP83: =SUM(BP63:BP82) -> 4325.8399 | BQ83: =SUM(BQ63:BQ82) -> 4141.0807 | BR83: =SUM(BR63:BR82) -> 3168.5345 | BS83: =SUM(BS63:BS82) -> 2903.2701 | BT83: =SUM(BT63:BT82) -> 3199.4315
D84: ='[1]Desempeño Financiero (Evol)'!BE543-D83 -> 111 | E84: ='[1]Desempeño Financiero (Evol)'!BF543-E83 -> -3.870025e-08 | F84: ='[1]Desempeño Financiero (Evol)'!BG543-F83 -> -5.0200242e-08 | G84: ='[1]Desempeño Financiero (Evol)'!BH543-G83 -> -4.4999979e-08 | H84: ='[1]Desempeño Financiero (Evol)'!BI543-H83 -> 6.7999963e-08 | I84: ='[1]Desempeño Financiero (Evol)'!BJ543-I83 -> 6.200014e-08 | J84: ='[1]Desempeño Financiero (Evol)'!BK543-J83 -> 1.20001e-08 | K84: ='[1]Desempeño Financiero (Evol)'!BL543-K83 -> 2.4999963e-08 | ... AN84: ='[1]Desempeño Financiero (Evol)'!CO543-AN83 -> 0 | AZ84: ='[1]Desempeño Financiero (Evol)'!DA543-AZ83 -> 0 | BA84: ='[1]Desempeño Financiero (Evol)'!DB543-BA83 -> 0 | BB84: ='[1]Desempeño Financiero (Evol)'!DC543-BB83 -> 0 | BC84: ='[1]Desempeño Financiero (Evol)'!DD543-BC83 -> 0 | BD84: ='[1]Desempeño Financiero (Evol)'!DE543-BD83 -> 0 | BE84: ='[1]Desempeño Financiero (Evol)'!DF543-BE83 -> 0 | BF84: ='[1]Desempeño Financiero (Evol)'!DG543-BF83 -> 0 | BG84: ='[1]Desempeño Financiero (Evol)'!DH543-BG83 -> 0 | ... BK84: ='[1]Desempeño Financiero (Evol)'!DL543-BK83 -> 0
A86: Gastos Operativos | C86: Gasto Directo | D86: =Renta_Alta!D86+Masivo!D86+Consumo_Inicial!D86 -> -4676.1753 | E86: =Renta_Alta!E86+Masivo!E86+Consumo_Inicial!E86 -> -5038.1345 | F86: =Renta_Alta!F86+Masivo!F86+Consumo_Inicial!F86 -> -4773.6625 | G86: =Renta_Alta!G86+Masivo!G86+Consumo_Inicial!G86 -> -5260.4222 | H86: =Renta_Alta!H86+Masivo!H86+Consumo_Inicial!H86 -> -4543.2276 | I86: =Renta_Alta!I86+Masivo!I86+Consumo_Inicial!I86 -> -4541.3324 | J86: =Renta_Alta!J86+Masivo!J86+Consumo_Inicial!J86 -> -4717.3215 | K86: =Renta_Alta!K86+Masivo!K86+Consumo_Inicial!K86 -> -4056.022 | ... BK86: =Renta_Alta!BK86+Masivo!BK86+Consumo_Inicial!BK86 -> -5284.7888 | BO86: =SUMIFS($D86:$BM86,$D$6:$BM$6,">="&BO$2,$D$6:$BM$6,"<="&BO$6,$D$5:$BM$5,BO$5) -> -26026.556 | BP86: =SUMIFS($D86:$BM86,$D$6:$BM$6,">="&BP$2,$D$6:$BM$6,"<="&BP$6,$D$5:$BM$5,BP$5) -> -25098.612 | BQ86: =SUMIFS($D86:$BM86,$D$6:$BM$6,">="&BQ$2,$D$6:$BM$6,"<="&BQ$6,$D$5:$BM$5,BQ$5) -> -20139.35 | BR86: =SUMIFS($D86:$BM86,$D$6:$BM$6,">="&BR$2,$D$6:$BM$6,"<="&BR$6,$D$5:$BM$5,BR$5) -> -24124.101 | BS86: =SUMIFS($D86:$BM86,$D$6:$BM$6,">="&BS$2,$D$6:$BM$6,"<="&BS$6,$D$5:$BM$5,BS$5) -> -21998.807 | BT86: =SUMIFS($D86:$BM86,$D$6:$BM$6,">="&BT$2,$D$6:$BM$6,"<="&BT$6,$D$5:$BM$5,BT$5) -> -24291.622
A87: Gastos Operativos | C87: Gasto Canal | D87: =Renta_Alta!D87+Masivo!D87+Consumo_Inicial!D87 -> -282.85583 | E87: =Renta_Alta!E87+Masivo!E87+Consumo_Inicial!E87 -> -276.60549 | F87: =Renta_Alta!F87+Masivo!F87+Consumo_Inicial!F87 -> -304.13448 | G87: =Renta_Alta!G87+Masivo!G87+Consumo_Inicial!G87 -> -272.04204 | H87: =Renta_Alta!H87+Masivo!H87+Consumo_Inicial!H87 -> -295.87897 | I87: =Renta_Alta!I87+Masivo!I87+Consumo_Inicial!I87 -> -287.05405 | J87: =Renta_Alta!J87+Masivo!J87+Consumo_Inicial!J87 -> -326.0604 | K87: =Renta_Alta!K87+Masivo!K87+Consumo_Inicial!K87 -> -349.38904 | ... BK87: =Renta_Alta!BK87+Masivo!BK87+Consumo_Inicial!BK87 -> -335.75246 | BO87: =SUMIFS($D87:$BM87,$D$6:$BM$6,">="&BO$2,$D$6:$BM$6,"<="&BO$6,$D$5:$BM$5,BO$5) -> -1435.2993 | BP87: =SUMIFS($D87:$BM87,$D$6:$BM$6,">="&BP$2,$D$6:$BM$6,"<="&BP$6,$D$5:$BM$5,BP$5) -> -1838.6822 | BQ87: =SUMIFS($D87:$BM87,$D$6:$BM$6,">="&BQ$2,$D$6:$BM$6,"<="&BQ$6,$D$5:$BM$5,BQ$5) -> -1138.3641 | BR87: =SUMIFS($D87:$BM87,$D$6:$BM$6,">="&BR$2,$D$6:$BM$6,"<="&BR$6,$D$5:$BM$5,BR$5) -> -1618.3422 | BS87: =SUMIFS($D87:$BM87,$D$6:$BM$6,">="&BS$2,$D$6:$BM$6,"<="&BS$6,$D$5:$BM$5,BS$5) -> -1850.4812 | BT87: =SUMIFS($D87:$BM87,$D$6:$BM$6,">="&BT$2,$D$6:$BM$6,"<="&BT$6,$D$5:$BM$5,BT$5) -> -1431.5168
A88: Gastos Operativos | C88: Gasto Indirecto | D88: =Renta_Alta!D88+Masivo!D88+Consumo_Inicial!D88 -> -1684.735 | E88: =Renta_Alta!E88+Masivo!E88+Consumo_Inicial!E88 -> -1732.4411 | F88: =Renta_Alta!F88+Masivo!F88+Consumo_Inicial!F88 -> -1683.9126 | G88: =Renta_Alta!G88+Masivo!G88+Consumo_Inicial!G88 -> -1809.165 | H88: =Renta_Alta!H88+Masivo!H88+Consumo_Inicial!H88 -> -1682.6984 | I88: =Renta_Alta!I88+Masivo!I88+Consumo_Inicial!I88 -> -1594.0532 | J88: =Renta_Alta!J88+Masivo!J88+Consumo_Inicial!J88 -> -1716.0144 | K88: =Renta_Alta!K88+Masivo!K88+Consumo_Inicial!K88 -> -1589.3739 | ... BK88: =Renta_Alta!BK88+Masivo!BK88+Consumo_Inicial!BK88 -> -2313.3862 | BO88: =SUMIFS($D88:$BM88,$D$6:$BM$6,">="&BO$2,$D$6:$BM$6,"<="&BO$6,$D$5:$BM$5,BO$5) -> -12122.686 | BP88: =SUMIFS($D88:$BM88,$D$6:$BM$6,">="&BP$2,$D$6:$BM$6,"<="&BP$6,$D$5:$BM$5,BP$5) -> -11403.413 | BQ88: =SUMIFS($D88:$BM88,$D$6:$BM$6,">="&BQ$2,$D$6:$BM$6,"<="&BQ$6,$D$5:$BM$5,BQ$5) -> -9826.0868 | BR88: =SUMIFS($D88:$BM88,$D$6:$BM$6,">="&BR$2,$D$6:$BM$6,"<="&BR$6,$D$5:$BM$5,BR$5) -> -10593.213 | BS88: =SUMIFS($D88:$BM88,$D$6:$BM$6,">="&BS$2,$D$6:$BM$6,"<="&BS$6,$D$5:$BM$5,BS$5) -> -9313.2286 | BT88: =SUMIFS($D88:$BM88,$D$6:$BM$6,">="&BT$2,$D$6:$BM$6,"<="&BT$6,$D$5:$BM$5,BT$5) -> -8592.9521
C89: Gastos Operativos | D89: =SUM(D86:D88) -> -6643.7661 | E89: =SUM(E86:E88) -> -7047.1811 | F89: =SUM(F86:F88) -> -6761.7095 | G89: =SUM(G86:G88) -> -7341.6293 | H89: =SUM(H86:H88) -> -6521.805 | I89: =SUM(I86:I88) -> -6422.4396 | J89: =SUM(J86:J88) -> -6759.3963 | K89: =SUM(K86:K88) -> -5994.7849 | ... BK89: =SUM(BK86:BK88) -> -7933.9274 | BO89: =SUM(BO86:BO88) -> -39584.541 | BP89: =SUM(BP86:BP88) -> -38340.707 | BQ89: =SUM(BQ86:BQ88) -> -31103.801 | BR89: =SUM(BR86:BR88) -> -36335.656 | BS89: =SUM(BS86:BS88) -> -33162.517 | BT89: =SUM(BT86:BT88) -> -34316.091
D90: ='[1]Desempeño Financiero (Evol)'!BE588-D89 -> 0 | E90: ='[1]Desempeño Financiero (Evol)'!BF588-E89 -> 0 | F90: ='[1]Desempeño Financiero (Evol)'!BG588-F89 -> 0 | G90: ='[1]Desempeño Financiero (Evol)'!BH588-G89 -> 0 | H90: ='[1]Desempeño Financiero (Evol)'!BI588-H89 -> 0 | I90: ='[1]Desempeño Financiero (Evol)'!BJ588-I89 -> 0 | J90: ='[1]Desempeño Financiero (Evol)'!BK588-J89 -> 0 | K90: ='[1]Desempeño Financiero (Evol)'!BL588-K89 -> 0 | ... AN90: ='[1]Desempeño Financiero (Evol)'!CO588-AN89 -> 0 | AZ90: ='[1]Desempeño Financiero (Evol)'!DA588-AZ89 -> -160.38997 | BA90: ='[1]Desempeño Financiero (Evol)'!DB588-BA89 -> -164.96208 | BB90: ='[1]Desempeño Financiero (Evol)'!DC588-BB89 -> -168.95647 | BC90: ='[1]Desempeño Financiero (Evol)'!DD588-BC89 -> -170.5302 | BD90: ='[1]Desempeño Financiero (Evol)'!DE588-BD89 -> -179.15809 | BE90: ='[1]Desempeño Financiero (Evol)'!DF588-BE89 -> -171.42412 | BF90: ='[1]Desempeño Financiero (Evol)'!DG588-BF89 -> -174.88646 | BG90: ='[1]Desempeño Financiero (Evol)'!DH588-BG89 -> -171.603 | ... BK90: ='[1]Desempeño Financiero (Evol)'!DL588-BK89 -> -179.61829
A91: Extraordinarios | C91: Donaciones | D91: =Renta_Alta!D91+Masivo!D91+Consumo_Inicial!D91 -> -166.66642 | E91: =Renta_Alta!E91+Masivo!E91+Consumo_Inicial!E91 -> -166.66667 | F91: =Renta_Alta!F91+Masivo!F91+Consumo_Inicial!F91 -> -215.09117 | G91: =Renta_Alta!G91+Masivo!G91+Consumo_Inicial!G91 -> -185.34895 | H91: =Renta_Alta!H91+Masivo!H91+Consumo_Inicial!H91 -> -257.16412 | I91: =Renta_Alta!I91+Masivo!I91+Consumo_Inicial!I91 -> -177.76667 | J91: =Renta_Alta!J91+Masivo!J91+Consumo_Inicial!J91 -> -208.94747 | K91: =Renta_Alta!K91+Masivo!K91+Consumo_Inicial!K91 -> -180.31667 | ... BK91: =Renta_Alta!BK91+Masivo!BK91+Consumo_Inicial!BK91 -> 0 | BO91: =SUMIFS($D91:$BM91,$D$6:$BM$6,">="&BO$2,$D$6:$BM$6,"<="&BO$6,$D$5:$BM$5,BO$5) -> -995.31235 | BP91: =SUMIFS($D91:$BM91,$D$6:$BM$6,">="&BP$2,$D$6:$BM$6,"<="&BP$6,$D$5:$BM$5,BP$5) -> 0 | BQ91: =SUMIFS($D91:$BM91,$D$6:$BM$6,">="&BQ$2,$D$6:$BM$6,"<="&BQ$6,$D$5:$BM$5,BQ$5) -> -787.99168 | BR91: =SUMIFS($D91:$BM91,$D$6:$BM$6,">="&BR$2,$D$6:$BM$6,"<="&BR$6,$D$5:$BM$5,BR$5) -> -903.25848 | BS91: =SUMIFS($D91:$BM91,$D$6:$BM$6,">="&BS$2,$D$6:$BM$6,"<="&BS$6,$D$5:$BM$5,BS$5) -> -926.4686 | BT91: =SUMIFS($D91:$BM91,$D$6:$BM$6,">="&BT$2,$D$6:$BM$6,"<="&BT$6,$D$5:$BM$5,BT$5) -> -990.93733
A92: Extraordinarios | C92: Otros | D92: =Renta_Alta!D92+Masivo!D92+Consumo_Inicial!D92 -> -120.972 | E92: =Renta_Alta!E92+Masivo!E92+Consumo_Inicial!E92 -> -150.70296 | F92: =Renta_Alta!F92+Masivo!F92+Consumo_Inicial!F92 -> -244.02906 | G92: =Renta_Alta!G92+Masivo!G92+Consumo_Inicial!G92 -> -160.80277 | H92: =Renta_Alta!H92+Masivo!H92+Consumo_Inicial!H92 -> -142.99597 | I92: =Renta_Alta!I92+Masivo!I92+Consumo_Inicial!I92 -> -179.98641 | J92: =Renta_Alta!J92+Masivo!J92+Consumo_Inicial!J92 -> -275.61608 | K92: =Renta_Alta!K92+Masivo!K92+Consumo_Inicial!K92 -> -98.48996 | ... BK92: =Renta_Alta!BK92+Masivo!BK92+Consumo_Inicial!BK92 -> -466.11071 | BO92: =SUMIFS($D92:$BM92,$D$6:$BM$6,">="&BO$2,$D$6:$BM$6,"<="&BO$6,$D$5:$BM$5,BO$5) -> -1133.1584 | BP92: =SUMIFS($D92:$BM92,$D$6:$BM$6,">="&BP$2,$D$6:$BM$6,"<="&BP$6,$D$5:$BM$5,BP$5) -> -1564.0117 | BQ92: =SUMIFS($D92:$BM92,$D$6:$BM$6,">="&BQ$2,$D$6:$BM$6,"<="&BQ$6,$D$5:$BM$5,BQ$5) -> -905.74442 | BR92: =SUMIFS($D92:$BM92,$D$6:$BM$6,">="&BR$2,$D$6:$BM$6,"<="&BR$6,$D$5:$BM$5,BR$5) -> -1253.2679 | BS92: =SUMIFS($D92:$BM92,$D$6:$BM$6,">="&BS$2,$D$6:$BM$6,"<="&BS$6,$D$5:$BM$5,BS$5) -> -2627.2114 | BT92: =SUMIFS($D92:$BM92,$D$6:$BM$6,">="&BT$2,$D$6:$BM$6,"<="&BT$6,$D$5:$BM$5,BT$5) -> -819.50276
C93: Extraordinarios | D93: =SUM(D91:D92) -> -287.63842 | E93: =SUM(E91:E92) -> -317.36963 | F93: =SUM(F91:F92) -> -459.12023 | G93: =SUM(G91:G92) -> -346.15172 | H93: =SUM(H91:H92) -> -400.16009 | I93: =SUM(I91:I92) -> -357.75308 | J93: =SUM(J91:J92) -> -484.56355 | K93: =SUM(K91:K92) -> -278.80663 | ... BK93: =SUM(BK91:BK92) -> -466.11071 | BO93: =SUM(BO91:BO92) -> -2128.4708 | BP93: =SUM(BP91:BP92) -> -1564.0117 | BQ93: =SUM(BQ91:BQ92) -> -1693.7361 | BR93: =SUM(BR91:BR92) -> -2156.5264 | BS93: =SUM(BS91:BS92) -> -3553.68 | BT93: =SUM(BT91:BT92) -> -1810.4401
D94: ='[1]Desempeño Financiero (Evol)'!BE600-D93 -> 0 | E94: ='[1]Desempeño Financiero (Evol)'!BF600-E93 -> -1.5070299e-07 | F94: ='[1]Desempeño Financiero (Evol)'!BG600-F93 -> 0 | G94: ='[1]Desempeño Financiero (Evol)'!BH600-G93 -> 0 | H94: ='[1]Desempeño Financiero (Evol)'!BI600-H93 -> 0 | I94: ='[1]Desempeño Financiero (Evol)'!BJ600-I93 -> 0 | J94: ='[1]Desempeño Financiero (Evol)'!BK600-J93 -> 0 | K94: ='[1]Desempeño Financiero (Evol)'!BL600-K93 -> 0 | ... AN94: ='[1]Desempeño Financiero (Evol)'!CO600-AN93 -> 167.91667 | AZ94: ='[1]Desempeño Financiero (Evol)'!DA600-AZ93 -> 0 | BA94: ='[1]Desempeño Financiero (Evol)'!DB600-BA93 -> 0 | BB94: ='[1]Desempeño Financiero (Evol)'!DC600-BB93 -> 0 | BC94: ='[1]Desempeño Financiero (Evol)'!DD600-BC93 -> 0 | BD94: ='[1]Desempeño Financiero (Evol)'!DE600-BD93 -> 0 | BE94: ='[1]Desempeño Financiero (Evol)'!DF600-BE93 -> 0 | BF94: ='[1]Desempeño Financiero (Evol)'!DG600-BF93 -> 0 | BG94: ='[1]Desempeño Financiero (Evol)'!DH600-BG93 -> 0 | ... BK94: ='[1]Desempeño Financiero (Evol)'!DL600-BK93 -> 0
A95: ROF | C95: Venta de Cartera | D95: =Renta_Alta!D95+Masivo!D95+Consumo_Inicial!D95 -> 0 | E95: =Renta_Alta!E95+Masivo!E95+Consumo_Inicial!E95 -> 0 | F95: =Renta_Alta!F95+Masivo!F95+Consumo_Inicial!F95 -> 0 | G95: =Renta_Alta!G95+Masivo!G95+Consumo_Inicial!G95 -> 0 | H95: =Renta_Alta!H95+Masivo!H95+Consumo_Inicial!H95 -> 0 | I95: =Renta_Alta!I95+Masivo!I95+Consumo_Inicial!I95 -> 0 | J95: =Renta_Alta!J95+Masivo!J95+Consumo_Inicial!J95 -> 0 | K95: =Renta_Alta!K95+Masivo!K95+Consumo_Inicial!K95 -> 0 | ... BK95: =Renta_Alta!BK95+Masivo!BK95+Consumo_Inicial!BK95 -> 0 | BO95: =SUMIFS($D95:$BM95,$D$6:$BM$6,">="&BO$2,$D$6:$BM$6,"<="&BO$6,$D$5:$BM$5,BO$5) -> 0 | BP95: =SUMIFS($D95:$BM95,$D$6:$BM$6,">="&BP$2,$D$6:$BM$6,"<="&BP$6,$D$5:$BM$5,BP$5) -> 0 | BQ95: =SUMIFS($D95:$BM95,$D$6:$BM$6,">="&BQ$2,$D$6:$BM$6,"<="&BQ$6,$D$5:$BM$5,BQ$5) -> 0 | BR95: =SUMIFS($D95:$BM95,$D$6:$BM$6,">="&BR$2,$D$6:$BM$6,"<="&BR$6,$D$5:$BM$5,BR$5) -> 683.18679 | BS95: =SUMIFS($D95:$BM95,$D$6:$BM$6,">="&BS$2,$D$6:$BM$6,"<="&BS$6,$D$5:$BM$5,BS$5) -> 0 | BT95: =SUMIFS($D95:$BM95,$D$6:$BM$6,">="&BT$2,$D$6:$BM$6,"<="&BT$6,$D$5:$BM$5,BT$5) -> 0
C96: ROF | D96: =SUM(D95:D95) -> 0 | E96: =SUM(E95:E95) -> 0 | F96: =SUM(F95:F95) -> 0 | G96: =SUM(G95:G95) -> 0 | H96: =SUM(H95:H95) -> 0 | I96: =SUM(I95:I95) -> 0 | J96: =SUM(J95:J95) -> 0 | K96: =SUM(K95:K95) -> 0 | ... BK96: =SUM(BK95:BK95) -> 0 | BO96: =SUM(BO95) -> 0 | BP96: =SUM(BP95) -> 0 | BQ96: =SUM(BQ95) -> 0 | BR96: =SUM(BR95) -> 683.18679 | BS96: =SUM(BS95) -> 0 | BT96: =SUM(BT95) -> 0
D97: ='[1]Desempeño Financiero (Evol)'!BE531-D96 -> 0 | E97: ='[1]Desempeño Financiero (Evol)'!BF531-E96 -> 0 | F97: ='[1]Desempeño Financiero (Evol)'!BG531-F96 -> 0 | G97: ='[1]Desempeño Financiero (Evol)'!BH531-G96 -> 0 | H97: ='[1]Desempeño Financiero (Evol)'!BI531-H96 -> 0 | I97: ='[1]Desempeño Financiero (Evol)'!BJ531-I96 -> 0 | J97: ='[1]Desempeño Financiero (Evol)'!BK531-J96 -> 0 | K97: ='[1]Desempeño Financiero (Evol)'!BL531-K96 -> 0 | ... AN97: ='[1]Desempeño Financiero (Evol)'!CO531-AN96 -> 0 | AZ97: ='[1]Desempeño Financiero (Evol)'!DA531-AZ96 -> 0 | BA97: ='[1]Desempeño Financiero (Evol)'!DB531-BA96 -> 0 | BB97: ='[1]Desempeño Financiero (Evol)'!DC531-BB96 -> 0 | BC97: ='[1]Desempeño Financiero (Evol)'!DD531-BC96 -> 0 | BD97: ='[1]Desempeño Financiero (Evol)'!DE531-BD96 -> 0 | BE97: ='[1]Desempeño Financiero (Evol)'!DF531-BE96 -> 0 | BF97: ='[1]Desempeño Financiero (Evol)'!DG531-BF96 -> 0 | BG97: ='[1]Desempeño Financiero (Evol)'!DH531-BG96 -> 0 | ... BK97: ='[1]Desempeño Financiero (Evol)'!DL531-BK96 -> 0
C98: UAI | D98: =D60+D83+D89+D93+D96 -> 5991.8418 | E98: =E60+E83+E89+E93+E96 -> 14557.85 | F98: =F60+F83+F89+F93+F96 -> 6921.9349 | G98: =G60+G83+G89+G93+G96 -> 7466.3121 | H98: =H60+H83+H89+H93+H96 -> 6922.9179 | I98: =I60+I83+I89+I93+I96 -> 8568.9747 | J98: =J60+J83+J89+J93+J96 -> 6550.1651 | K98: =K60+K83+K89+K93+K96 -> 4451.5729 | ... BK98: =BK60+BK83+BK89+BK93+BK96 -> 10265.278 | BO98: =BO60+BO83+BO89+BO93+BO96 -> 30689.95 | BP98: =BP60+BP83+BP89+BP93+BP96 -> 36825.522 | BQ98: =BQ60+BQ83+BQ89+BQ93+BQ96 -> 26065.047 | BR98: =BR60+BR83+BR89+BR93+BR96 -> 31175.228 | BS98: =BS60+BS83+BS89+BS93+BS96 -> 15773.013 | BT98: =BT60+BT83+BT89+BT93+BT96 -> 41860.857
C102: Prom SFdP | D102: =D11 -> 4780954.1 | E102: =IFERROR(AVERAGE(D11:E11),0) -> 4815958.3 | F102: =IFERROR(AVERAGE(E11:F11),0) -> 4890986.4 | G102: =IFERROR(AVERAGE(F11:G11),0) -> 4953918.3 | H102: =IFERROR(AVERAGE(G11:H11),0) -> 5006463 | I102: =IFERROR(AVERAGE(H11:I11),0) -> 5065757.8 | J102: =IFERROR(AVERAGE(I11:J11),0) -> 5118555.5 | K102: =IFERROR(AVERAGE(J11:K11),0) -> 5177882.9 | L102: =IFERROR(AVERAGE(K11:L11),0) -> 5237560.6 | ... AY102: =IFERROR(AVERAGE(AX11:AY11),0) -> 0 | AZ102: =AZ11 -> 5946181.6 | BA102: =IFERROR(AVERAGE(AZ11:BA11),0) -> 5955233.2 | BB102: =IFERROR(AVERAGE(BA11:BB11),0) -> 5981941.9 | BC102: =IFERROR(AVERAGE(BB11:BC11),0) -> 6010589.9 | BD102: =IFERROR(AVERAGE(BC11:BD11),0) -> 6032744 | BE102: =IFERROR(AVERAGE(BD11:BE11),0) -> 6058815.8 | BF102: =IFERROR(AVERAGE(BE11:BF11),0) -> 6088664.5 | BG102: =IFERROR(AVERAGE(BF11:BG11),0) -> 6118212.9 | BH102: =IFERROR(AVERAGE(BG11:BH11),0) -> 6152648.9 | ... BK102: =IFERROR(AVERAGE(BJ11:BK11),0) -> 6240933.7 | BO102: =IFERROR(AVERAGEIFS($D11:$BM11,$D$6:$BM$6,">="&EOMONTH(BO$2,-1),$D$6:$BM$6,"<="&BO$6,$D$5:$BM$5,BO$5,$D11:$BM11,"<>0"),0) -> 5694660.9 | BP102: =IFERROR(AVERAGEIFS($D11:$BM11,$D$6:$BM$6,">="&EOMONTH(BP$2,-1),$D$6:$BM$6,"<="&BP$6,$D$5:$BM$5,BP$5,$D11:$BM11,"<>0"),0) -> 5995110.7 | BQ102: =IFERROR(AVERAGEIFS($D11:$BM11,$D$6:$BM$6,">="&EOMONTH(BQ$2,-1),$D$6:$BM$6,"<="&BQ$6,$D$5:$BM$5,BQ$5,$D11:$BM11,"<>0"),0) -> 5691839.6 | BR102: =IFERROR(AVERAGEIFS($D11:$BM11,$D$6:$BM$6,">="&EOMONTH(BR$2,-1),$D$6:$BM$6,"<="&BR$6,$D$5:$BM$5,BR$5,$D11:$BM11,"<>0"),0) -> 5761990.6 | BS102: =IFERROR(AVERAGEIFS($D11:$BM11,$D$6:$BM$6,">="&EOMONTH(BS$2,-1),$D$6:$BM$6,"<="&BS$6,$D$5:$BM$5,BS$5,$D11:$BM11,"<>0"),0) -> 5566568.9 | BT102: =IFERROR(AVERAGEIFS($D11:$BM11,$D$6:$BM$6,">="&EOMONTH(BT$2,-1),$D$6:$BM$6,"<="&BT$6,$D$5:$BM$5,BT$5,$D11:$BM11,"<>0"),0) -> 4915170.6

Sheet Desempeño_Financiero
B1: 46173 | D1: Mensual | W1: Acumulado
B2: Desempeño Financiero
B3: En S/. Miles | C3: N° dias T.Imp | D3: 30 | E3: 30 | F3: 30 | G3: 30 | H3: 30 | I3: 30
C4: N° dias FTP | D4: =DAY(D6) -> 31 | E4: =DAY(E6) -> 31 | F4: =DAY(F6) -> 30 | G4: =DAY(G6) -> 31 | H4: =DAY(H6) -> 31 | I4: =DAY(I6) -> 31
C5: Tipo | D5: R | E5: P | F5: R | G5: R | H5: R | I5: R | K5: Variación S/. | Q5: Variación % | AD5: Variación S/. | AJ5: Variación %
C6: Total_Producto | D6: =$B$1 -> 46173 | E6: =D6 -> 46173 | F6: =EOMONTH(D6,-1) -> 46142 | G6: =EOMONTH(D6,-12) -> 45808 | H6: =EOMONTH(D6,-24) -> 45443 | I6: =EOMONTH(D6,-36) -> 45077 | K6: =E6 -> 46173 | L6: =F6 -> 46142 | M6: =G6 -> 45808 | N6: =H6 -> 45443 | O6: =I6 -> 45077 | Q6: =K6 -> 46173 | R6: =L6 -> 46142 | S6: =M6 -> 45808 | T6: =N6 -> 45443 | U6: =O6 -> 45077 | W6: =$B$1 -> 46173 | X6: =W6 -> 46173 | Y6: =EOMONTH(W6,-1) -> 46142 | Z6: =EOMONTH(W6,-12) -> 45808 | AA6: =EOMONTH(W6,-24) -> 45443 | AB6: =EOMONTH(W6,-36) -> 45077 | AD6: =X6 -> 46173 | AE6: =Y6 -> 46142 | AF6: =Z6 -> 45808 | AG6: =AA6 -> 45443 | AH6: =AB6 -> 45077 | AJ6: =AD6 -> 46173 | AK6: =AE6 -> 46142 | AL6: =AF6 -> 45808 | AM6: =AG6 -> 45443 | AN6: =AH6 -> 45077
A8: SALDO_FDP | C8: Vigente | D8: {=_xlfn.XLOOKUP(1, (INDIRECT("'"&$C$6&"'!$6:$6")=D$6)* (INDIRECT("'"&$C$6&"'!$5:$5")=D$5), INDIRECT("'"&$C$6&"'!"&ROW()&":"&ROW()) )} -> 5562013.9 | E8: {=_xlfn.XLOOKUP(1, (INDIRECT("'"&$C$6&"'!$6:$6")=E$6)* (INDIRECT("'"&$C$6&"'!$5:$5")=E$5), INDIRECT("'"&$C$6&"'!"&ROW()&":"&ROW()) )} -> 5902822.3 | F8: {=_xlfn.XLOOKUP(1, (INDIRECT("'"&$C$6&"'!$6:$6")=F$6)* (INDIRECT("'"&$C$6&"'!$5:$5")=F$5), INDIRECT("'"&$C$6&"'!"&ROW()&":"&ROW()) )} -> 5548588.7 | G8: {=_xlfn.XLOOKUP(1, (INDIRECT("'"&$C$6&"'!$6:$6")=G$6)* (INDIRECT("'"&$C$6&"'!$5:$5")=G$5), INDIRECT("'"&$C$6&"'!"&ROW()&":"&ROW()) )} -> 5643386.7 | H8: {=_xlfn.XLOOKUP(1, (INDIRECT("'"&$C$6&"'!$6:$6")=H$6)* (INDIRECT("'"&$C$6&"'!$5:$5")=H$5), INDIRECT("'"&$C$6&"'!"&ROW()&":"&ROW()) )} -> 5684127.8 | I8: {=_xlfn.XLOOKUP(1, (INDIRECT("'"&$C$6&"'!$6:$6")=I$6)* (INDIRECT("'"&$C$6&"'!$5:$5")=I$5), INDIRECT("'"&$C$6&"'!"&ROW()&":"&ROW()) )} -> 4938857 | K8: =$D8-E8 -> -340808.41 | L8: =$D8-F8 -> 13425.239 | M8: =$D8-G8 -> -81372.774 | N8: =$D8-H8 -> -122113.9 | O8: =$D8-I8 -> 623156.91 | Q8: =IFERROR($D8/E8-1,0) -> -0.057736519 | R8: =IFERROR($D8/F8-1,0) -> 0.0024195773 | S8: =IFERROR($D8/G8-1,0) -> -0.014419139 | T8: =IFERROR($D8/H8-1,0) -> -0.021483313 | U8: =IFERROR($D8/I8-1,0) -> 0.12617432 | W8: {=INDIRECT("'"&$C$6&"'!"&ADDRESS(ROW(),COLUMN()+44))} -> 5562013.9 | X8: {=INDIRECT("'"&$C$6&"'!"&ADDRESS(ROW(),COLUMN()+44))} -> 5902822.3 | Y8: {=INDIRECT("'"&$C$6&"'!"&ADDRESS(ROW(),COLUMN()+44))} -> 5548588.7 | Z8: {=INDIRECT("'"&$C$6&"'!"&ADDRESS(ROW(),COLUMN()+44))} -> 5643386.7 | AA8: {=INDIRECT("'"&$C$6&"'!"&ADDRESS(ROW(),COLUMN()+44))} -> 5684127.8 | AB8: {=INDIRECT("'"&$C$6&"'!"&ADDRESS(ROW(),COLUMN()+44))} -> 4938857 | AD8: =$W8-X8 -> -340808.41 | AE8: =$W8-Y8 -> 13425.239 | AF8: =$W8-Z8 -> -81372.774 | AG8: =$W8-AA8 -> -122113.9 | AH8: =$W8-AB8 -> 623156.91 | AJ8: =IFERROR($W8/X8-1,0) -> -0.057736519 | AK8: =IFERROR($W8/Y8-1,0) -> 0.0024195773 | AL8: =IFERROR($W8/Z8-1,0) -> -0.014419139 | AM8: =IFERROR($W8/AA8-1,0) -> -0.021483313 | AN8: =IFERROR($W8/AB8-1,0) -> 0.12617432
A9: SALDO_FDP | C9: Refinanciado | D9: {=_xlfn.XLOOKUP(1, (INDIRECT("'"&$C$6&"'!$6:$6")=D$6)* (INDIRECT("'"&$C$6&"'!$5:$5")=D$5), INDIRECT("'"&$C$6&"'!"&ROW()&":"&ROW()) )} -> 28277.739 | E9: {=_xlfn.XLOOKUP(1, (INDIRECT("'"&$C$6&"'!$6:$6")=E$6)* (INDIRECT("'"&$C$6&"'!$5:$5")=E$5), INDIRECT("'"&$C$6&"'!"&ROW()&":"&ROW()) )} -> 30703.861 | F9: {=_xlfn.XLOOKUP(1, (INDIRECT("'"&$C$6&"'!$6:$6")=F$6)* (INDIRECT("'"&$C$6&"'!$5:$5")=F$5), INDIRECT("'"&$C$6&"'!"&ROW()&":"&ROW()) )} -> 28987.813 | G9: {=_xlfn.XLOOKUP(1, (INDIRECT("'"&$C$6&"'!$6:$6")=G$6)* (INDIRECT("'"&$C$6&"'!$5:$5")=G$5), INDIRECT("'"&$C$6&"'!"&ROW()&":"&ROW()) )} -> 28019.412 | H9: {=_xlfn.XLOOKUP(1, (INDIRECT("'"&$C$6&"'!$6:$6")=H$6)* (INDIRECT("'"&$C$6&"'!$5:$5")=H$5), INDIRECT("'"&$C$6&"'!"&ROW()&":"&ROW()) )} -> 22700.678 | I9: {=_xlfn.XLOOKUP(1, (INDIRECT("'"&$C$6&"'!$6:$6")=I$6)* (INDIRECT("'"&$C$6&"'!$5:$5")=I$5), INDIRECT("'"&$C$6&"'!"&ROW()&":"&ROW()) )} -> 29479.237 | K9: =$D9-E9 -> -2426.1219 | L9: =$D9-F9 -> -710.07357 | M9: =$D9-G9 -> 258.32699 | N9: =$D9-H9 -> 5577.0609 | O9: =$D9-I9 -> -1201.4984 | Q9: =IFERROR($D9/E9-1,0) -> -0.079016834 | R9: =IFERROR($D9/F9-1,0) -> -0.02449559 | S9: =IFERROR($D9/G9-1,0) -> 0.0092195721 | T9: =IFERROR($D9/H9-1,0) -> 0.24567816 | U9: =IFERROR($D9/I9-1,0) -> -0.040757445 | W9: {=INDIRECT("'"&$C$6&"'!"&ADDRESS(ROW(),COLUMN()+44))} -> 28277.739 | X9: {=INDIRECT("'"&$C$6&"'!"&ADDRESS(ROW(),COLUMN()+44))} -> 30703.861 | Y9: {=INDIRECT("'"&$C$6&"'!"&ADDRESS(ROW(),COLUMN()+44))} -> 28987.813 | Z9: {=INDIRECT("'"&$C$6&"'!"&ADDRESS(ROW(),COLUMN()+44))} -> 28019.412 | AA9: {=INDIRECT("'"&$C$6&"'!"&ADDRESS(ROW(),COLUMN()+44))} -> 22700.678 | AB9: {=INDIRECT("'"&$C$6&"'!"&ADDRESS(ROW(),COLUMN()+44))} -> 29479.237 | AD9: =$W9-X9 -> -2426.1219 | AE9: =$W9-Y9 -> -710.07357 | AF9: =$W9-Z9 -> 258.32699 | AG9: =$W9-AA9 -> 5577.0609 | AH9: =$W9-AB9 -> -1201.4984 | AJ9: =IFERROR($W9/X9-1,0) -> -0.079016834 | AK9: =IFERROR($W9/Y9-1,0) -> -0.02449559 | AL9: =IFERROR($W9/Z9-1,0) -> 0.0092195721 | AM9: =IFERROR($W9/AA9-1,0) -> 0.24567816 | AN9: =IFERROR($W9/AB9-1,0) -> -0.040757445
A10: SALDO_FDP | C10: Vencido y Judicial | D10: {=_xlfn.XLOOKUP(1, (INDIRECT("'"&$C$6&"'!$6:$6")=D$6)* (INDIRECT("'"&$C$6&"'!$5:$5")=D$5), INDIRECT("'"&$C$6&"'!"&ROW()&":"&ROW()) )} -> 118475.52 | E10: {=_xlfn.XLOOKUP(1, (INDIRECT("'"&$C$6&"'!$6:$6")=E$6)* (INDIRECT("'"&$C$6&"'!$5:$5")=E$5), INDIRECT("'"&$C$6&"'!"&ROW()&":"&ROW()) )} -> 110380.99 | F10: {=_xlfn.XLOOKUP(1, (INDIRECT("'"&$C$6&"'!$6:$6")=F$6)* (INDIRECT("'"&$C$6&"'!$5:$5")=F$5), INDIRECT("'"&$C$6&"'!"&ROW()&":"&ROW()) )} -> 118196.07 | G10: {=_xlfn.XLOOKUP(1, (INDIRECT("'"&$C$6&"'!$6:$6")=G$6)* (INDIRECT("'"&$C$6&"'!$5:$5")=G$5), INDIRECT("'"&$C$6&"'!"&ROW()&":"&ROW()) )} -> 92392.453 | H10: {=_xlfn.XLOOKUP(1, (INDIRECT("'"&$C$6&"'!$6:$6")=H$6)* (INDIRECT("'"&$C$6&"'!$5:$5")=H$5), INDIRECT("'"&$C$6&"'!"&ROW()&":"&ROW()) )} -> 66766.564 | I10: {=_xlfn.XLOOKUP(1, (INDIRECT("'"&$C$6&"'!$6:$6")=I$6)* (INDIRECT("'"&$C$6&"'!$5:$5")=I$5), INDIRECT("'"&$C$6&"'!"&ROW()&":"&ROW()) )} -> 67763.653 | K10: =$D10-E10 -> 8094.5256 | L10: =$D10-F10 -> 279.44567 | M10: =$D10-G10 -> 26083.062 | N10: =$D10-H10 -> 51708.951 | O10: =$D10-I10 -> 50711.862 | Q10: =IFERROR($D10/E10-1,0) -> 0.073332605 | R10: =IFERROR($D10/F10-1,0) -> 0.0023642552 | S10: =IFERROR($D10/G10-1,0) -> 0.28230728 | T10: =IFERROR($D10/H10-1,0) -> 0.77447375 | U10: =IFERROR($D10/I10-1,0) -> 0.74836375 | W10: {=INDIRECT("'"&$C$6&"'!"&ADDRESS(ROW(),COLUMN()+44))} -> 118475.52 | X10: {=INDIRECT("'"&$C$6&"'!"&ADDRESS(ROW(),COLUMN()+44))} -> 110380.99 | Y10: {=INDIRECT("'"&$C$6&"'!"&ADDRESS(ROW(),COLUMN()+44))} -> 118196.07 | Z10: {=INDIRECT("'"&$C$6&"'!"&ADDRESS(ROW(),COLUMN()+44))} -> 92392.453 | AA10: {=INDIRECT("'"&$C$6&"'!"&ADDRESS(ROW(),COLUMN()+44))} -> 66766.564 | AB10: {=INDIRECT("'"&$C$6&"'!"&ADDRESS(ROW(),COLUMN()+44))} -> 67763.653 | AD10: =$W10-X10 -> 8094.5256 | AE10: =$W10-Y10 -> 279.44567 | AF10: =$W10-Z10 -> 26083.062 | AG10: =$W10-AA10 -> 51708.951 | AH10: =$W10-AB10 -> 50711.862 | AJ10: =IFERROR($W10/X10-1,0) -> 0.073332605 | AK10: =IFERROR($W10/Y10-1,0) -> 0.0023642552 | AL10: =IFERROR($W10/Z10-1,0) -> 0.28230728 | AM10: =IFERROR($W10/AA10-1,0) -> 0.77447375 | AN10: =IFERROR($W10/AB10-1,0) -> 0.74836375
C11: Saldo FdP | D11: =SUM(D8:D10) -> 5708767.2 | E11: =SUM(E8:E10) -> 6043907.2 | F11: =SUM(F8:F10) -> 5695772.5 | G11: =SUM(G8:G10) -> 5763798.5 | H11: =SUM(H8:H10) -> 5773595 | I11: =SUM(I8:I10) -> 5036099.9 | K11: =$D11-E11 -> -335140.01 | L11: =$D11-F11 -> 12994.611 | M11: =$D11-G11 -> -55031.385 | N11: =$D11-H11 -> -64827.887 | O11: =$D11-I11 -> 672667.27 | Q11: =IFERROR($D11/E11-1,0) -> -0.055450886 | R11: =IFERROR($D11/F11-1,0) -> 0.0022814485 | S11: =IFERROR($D11/G11-1,0) -> -0.0095477634 | T11: =IFERROR($D11/H11-1,0) -> -0.01122834 | U11: =IFERROR($D11/I11-1,0) -> 0.13356909 | W11: =SUM(W8:W10) -> 5708767.2 | X11: =SUM(X8:X10) -> 6043907.2 | Y11: =SUM(Y8:Y10) -> 5695772.5 | Z11: =SUM(Z8:Z10) -> 5763798.5 | AA11: =SUM(AA8:AA10) -> 5773595 | AB11: =SUM(AB8:AB10) -> 5036099.9 | AD11: =$W11-X11 -> -335140.01 | AE11: =$W11-Y11 -> 12994.611 | AF11: =$W11-Z11 -> -55031.385 | AG11: =$W11-AA11 -> -64827.887 | AH11: =$W11-AB11 -> 672667.27 | AJ11: =IFERROR($W11/X11-1,0) -> -0.055450886 | AK11: =IFERROR($W11/Y11-1,0) -> 0.0022814485 | AL11: =IFERROR($W11/Z11-1,0) -> -0.0095477634 | AM11: =IFERROR($W11/AA11-1,0) -> -0.01122834 | AN11: =IFERROR($W11/AB11-1,0) -> 0.13356909
A14: SALDO_PROM | C14: Vigente | D14: {=_xlfn.XLOOKUP(1, (INDIRECT("'"&$C$6&"'!$6:$6")=D$6)* (INDIRECT("'"&$C$6&"'!$5:$5")=D$5), INDIRECT("'"&$C$6&"'!"&ROW()&":"&ROW()) )} -> 5520303.6 | E14: {=_xlfn.XLOOKUP(1, (INDIRECT("'"&$C$6&"'!$6:$6")=E$6)* (INDIRECT("'"&$C$6&"'!$5:$5")=E$5), INDIRECT("'"&$C$6&"'!"&ROW()&":"&ROW()) )} -> 5858551.1 | F14: {=_xlfn.XLOOKUP(1, (INDIRECT("'"&$C$6&"'!$6:$6")=F$6)* (INDIRECT("'"&$C$6&"'!$5:$5")=F$5), INDIRECT("'"&$C$6&"'!"&ROW()&":"&ROW()) )} -> 5500202.2 | G14: {=_xlfn.XLOOKUP(1, (INDIRECT("'"&$C$6&"'!$6:$6")=G$6)* (INDIRECT("'"&$C$6&"'!$5:$5")=G$5), INDIRECT("'"&$C$6&"'!"&ROW()&":"&ROW()) )} -> 5598132 | H14: {=_xlfn.XLOOKUP(1, (INDIRECT("'"&$C$6&"'!$6:$6")=H$6)* (INDIRECT("'"&$C$6&"'!$5:$5")=H$5), INDIRECT("'"&$C$6&"'!"&ROW()&":"&ROW()) )} -> 5605866.8 | I14: {=_xlfn.XLOOKUP(1, (INDIRECT("'"&$C$6&"'!$6:$6")=I$6)* (INDIRECT("'"&$C$6&"'!$5:$5")=I$5), INDIRECT("'"&$C$6&"'!"&ROW()&":"&ROW()) )} -> 4884944 | K14: =$D14-E14 -> -338247.53 | L14: =$D14-F14 -> 20101.446 | M14: =$D14-G14 -> -77828.344 | N14: =$D14-H14 -> -85563.148 | O14: =$D14-I14 -> 635359.66 | Q14: =IFERROR($D14/E14-1,0) -> -0.057735696 | R14: =IFERROR($D14/F14-1,0) -> 0.0036546739 | S14: =IFERROR($D14/G14-1,0) -> -0.013902556 | T14: =IFERROR($D14/H14-1,0) -> -0.015263143 | U14: =IFERROR($D14/I14-1,0) -> 0.13006488 | W14: {=INDIRECT("'"&$C$6&"'!"&ADDRESS(ROW(),COLUMN()+44))} -> 5501093.2 | X14: {=INDIRECT("'"&$C$6&"'!"&ADDRESS(ROW(),COLUMN()+44))} -> 5807134.7 | Y14: {=INDIRECT("'"&$C$6&"'!"&ADDRESS(ROW(),COLUMN()+44))} -> 5496290.7 | Z14: {=INDIRECT("'"&$C$6&"'!"&ADDRESS(ROW(),COLUMN()+44))} -> 5603111.6 | AA14: {=INDIRECT("'"&$C$6&"'!"&ADDRESS(ROW(),COLUMN()+44))} -> 5448981.7 | AB14: {=INDIRECT("'"&$C$6&"'!"&ADDRESS(ROW(),COLUMN()+44))} -> 4764493.8 | AD14: =$W14-X14 -> -306041.49 | AE14: =$W14-Y14 -> 4802.5934 | AF14: =$W14-Z14 -> -102018.4 | AG14: =$W14-AA14 -> 52111.507 | AH14: =$W14-AB14 -> 736599.47 | AJ14: =IFERROR($W14/X14-1,0) -> -0.052700945 | AK14: =IFERROR($W14/Y14-1,0) -> 0.0008737881 | AL14: =IFERROR($W14/Z14-1,0) -> -0.018207455 | AM14: =IFERROR($W14/AA14-1,0) -> 0.0095635312 | AN14: =IFERROR($W14/AB14-1,0) -> 0.15460183
A15: SALDO_PROM | C15: Refinanciado | D15: {=_xlfn.XLOOKUP(1, (INDIRECT("'"&$C$6&"'!$6:$6")=D$6)* (INDIRECT("'"&$C$6&"'!$5:$5")=D$5), INDIRECT("'"&$C$6&"'!"&ROW()&":"&ROW()) )} -> 28394.213 | E15: {=_xlfn.XLOOKUP(1, (INDIRECT("'"&$C$6&"'!$6:$6")=E$6)* (INDIRECT("'"&$C$6&"'!$5:$5")=E$5), INDIRECT("'"&$C$6&"'!"&ROW()&":"&ROW()) )} -> 30473.582 | F15: {=_xlfn.XLOOKUP(1, (INDIRECT("'"&$C$6&"'!$6:$6")=F$6)* (INDIRECT("'"&$C$6&"'!$5:$5")=F$5), INDIRECT("'"&$C$6&"'!"&ROW()&":"&ROW()) )} -> 29285.746 | G15: {=_xlfn.XLOOKUP(1, (INDIRECT("'"&$C$6&"'!$6:$6")=G$6)* (INDIRECT("'"&$C$6&"'!$5:$5")=G$5), INDIRECT("'"&$C$6&"'!"&ROW()&":"&ROW()) )} -> 27162.268 | H15: {=_xlfn.XLOOKUP(1, (INDIRECT("'"&$C$6&"'!$6:$6")=H$6)* (INDIRECT("'"&$C$6&"'!$5:$5")=H$5), INDIRECT("'"&$C$6&"'!"&ROW()&":"&ROW()) )} -> 23089.442 | I15: {=_xlfn.XLOOKUP(1, (INDIRECT("'"&$C$6&"'!$6:$6")=I$6)* (INDIRECT("'"&$C$6&"'!$5:$5")=I$5), INDIRECT("'"&$C$6&"'!"&ROW()&":"&ROW()) )} -> 28758.026 | K15: =$D15-E15 -> -2079.369 | L15: =$D15-F15 -> -891.53279 | M15: =$D15-G15 -> 1231.945 | N15: =$D15-H15 -> 5304.7704 | O15: =$D15-I15 -> -363.81343 | Q15: =IFERROR($D15/E15-1,0) -> -0.068235136 | R15: =IFERROR($D15/F15-1,0) -> -0.03044255 | S15: =IFERROR($D15/G15-1,0) -> 0.045355014 | T15: =IFERROR($D15/H15-1,0) -> 0.22974875 | U15: =IFERROR($D15/I15-1,0) -> -0.012650848 | W15: {=INDIRECT("'"&$C$6&"'!"&ADDRESS(ROW(),COLUMN()+44))} -> 29506.608 | X15: {=INDIRECT("'"&$C$6&"'!"&ADDRESS(ROW(),COLUMN()+44))} -> 29715.91 | Y15: {=INDIRECT("'"&$C$6&"'!"&ADDRESS(ROW(),COLUMN()+44))} -> 29784.706 | Z15: {=INDIRECT("'"&$C$6&"'!"&ADDRESS(ROW(),COLUMN()+44))} -> 24117.375 | AA15: {=INDIRECT("'"&$C$6&"'!"&ADDRESS(ROW(),COLUMN()+44))} -> 24880.929 | AB15: {=INDIRECT("'"&$C$6&"'!"&ADDRESS(ROW(),COLUMN()+44))} -> 28956.678 | AD15: =$W15-X15 -> -209.30238 | AE15: =$W15-Y15 -> -278.09871 | AF15: =$W15-Z15 -> 5389.2328 | AG15: =$W15-AA15 -> 4625.6789 | AH15: =$W15-AB15 -> 549.92983 | AJ15: =IFERROR($W15/X15-1,0) -> -0.0070434452 | AK15: =IFERROR($W15/Y15-1,0) -> -0.0093369633 | AL15: =IFERROR($W15/Z15-1,0) -> 0.22345852 | AM15: =IFERROR($W15/AA15-1,0) -> 0.18591263 | AN15: =IFERROR($W15/AB15-1,0) -> 0.018991468
A16: SALDO_PROM | C16: Vencido y Judicial | D16: {=_xlfn.XLOOKUP(1, (INDIRECT("'"&$C$6&"'!$6:$6")=D$6)* (INDIRECT("'"&$C$6&"'!$5:$5")=D$5), INDIRECT("'"&$C$6&"'!"&ROW()&":"&ROW()) )} -> 122191.48 | E16: {=_xlfn.XLOOKUP(1, (INDIRECT("'"&$C$6&"'!$6:$6")=E$6)* (INDIRECT("'"&$C$6&"'!$5:$5")=E$5), INDIRECT("'"&$C$6&"'!"&ROW()&":"&ROW()) )} -> 109553.13 | F16: {=_xlfn.XLOOKUP(1, (INDIRECT("'"&$C$6&"'!$6:$6")=F$6)* (INDIRECT("'"&$C$6&"'!$5:$5")=F$5), INDIRECT("'"&$C$6&"'!"&ROW()&":"&ROW()) )} -> 120999.42 | G16: {=_xlfn.XLOOKUP(1, (INDIRECT("'"&$C$6&"'!$6:$6")=G$6)* (INDIRECT("'"&$C$6&"'!$5:$5")=G$5), INDIRECT("'"&$C$6&"'!"&ROW()&":"&ROW()) )} -> 96660.591 | H16: {=_xlfn.XLOOKUP(1, (INDIRECT("'"&$C$6&"'!$6:$6")=H$6)* (INDIRECT("'"&$C$6&"'!$5:$5")=H$5), INDIRECT("'"&$C$6&"'!"&ROW()&":"&ROW()) )} -> 74499.618 | I16: {=_xlfn.XLOOKUP(1, (INDIRECT("'"&$C$6&"'!$6:$6")=I$6)* (INDIRECT("'"&$C$6&"'!$5:$5")=I$5), INDIRECT("'"&$C$6&"'!"&ROW()&":"&ROW()) )} -> 75534.137 | K16: =$D16-E16 -> 12638.345 | L16: =$D16-F16 -> 1192.0545 | M16: =$D16-G16 -> 25530.886 | N16: =$D16-H16 -> 47691.859 | O16: =$D16-I16 -> 46657.34 | Q16: =IFERROR($D16/E16-1,0) -> 0.11536269 | R16: =IFERROR($D16/F16-1,0) -> 0.0098517368 | S16: =IFERROR($D16/G16-1,0) -> 0.26412922 | T16: =IFERROR($D16/H16-1,0) -> 0.64016246 | U16: =IFERROR($D16/I16-1,0) -> 0.61769873 | W16: {=INDIRECT("'"&$C$6&"'!"&ADDRESS(ROW(),COLUMN()+44))} -> 126492.98 | X16: {=INDIRECT("'"&$C$6&"'!"&ADDRESS(ROW(),COLUMN()+44))} -> 113056.73 | Y16: {=INDIRECT("'"&$C$6&"'!"&ADDRESS(ROW(),COLUMN()+44))} -> 127568.35 | Z16: {=INDIRECT("'"&$C$6&"'!"&ADDRESS(ROW(),COLUMN()+44))} -> 98315.232 | AA16: {=INDIRECT("'"&$C$6&"'!"&ADDRESS(ROW(),COLUMN()+44))} -> 75622.418 | AB16: {=INDIRECT("'"&$C$6&"'!"&ADDRESS(ROW(),COLUMN()+44))} -> 78852.452 | AD16: =$W16-X16 -> 13436.25 | AE16: =$W16-Y16 -> -1075.3747 | AF16: =$W16-Z16 -> 28177.744 | AG16: =$W16-AA16 -> 50870.557 | AH16: =$W16-AB16 -> 47640.524 | AJ16: =IFERROR($W16/X16-1,0) -> 0.11884521 | AK16: =IFERROR($W16/Y16-1,0) -> -0.0084297923 | AL16: =IFERROR($W16/Z16-1,0) -> 0.28660609 | AM16: =IFERROR($W16/AA16-1,0) -> 0.67269149 | AN16: =IFERROR($W16/AB16-1,0) -> 0.60417301
C17: Saldo Prom | D17: =SUM(D14:D16) -> 5670889.3 | E17: =SUM(E14:E16) -> 5998577.9 | F17: =SUM(F14:F16) -> 5650487.3 | G17: =SUM(G14:G16) -> 5721954.8 | H17: =SUM(H14:H16) -> 5703455.8 | I17: =SUM(I14:I16) -> 4989236.1 | K17: =$D17-E17 -> -327688.55 | L17: =$D17-F17 -> 20401.967 | M17: =$D17-G17 -> -51065.513 | N17: =$D17-H17 -> -32566.519 | O17: =$D17-I17 -> 681653.19 | Q17: =IFERROR($D17/E17-1,0) -> -0.054627707 | R17: =IFERROR($D17/F17-1,0) -> 0.0036106562 | S17: =IFERROR($D17/G17-1,0) -> -0.0089244872 | T17: =IFERROR($D17/H17-1,0) -> -0.0057099625 | U17: =IFERROR($D17/I17-1,0) -> 0.13662476 | W17: =SUM(W14:W16) -> 5657092.8 | X17: =SUM(X14:X16) -> 5949907.4 | Y17: =SUM(Y14:Y16) -> 5653643.7 | Z17: =SUM(Z14:Z16) -> 5725544.3 | AA17: =SUM(AA14:AA16) -> 5549485.1 | AB17: =SUM(AB14:AB16) -> 4872302.9 | AD17: =$W17-X17 -> -292814.54 | AE17: =$W17-Y17 -> 3449.12 | AF17: =$W17-Z17 -> -68451.424 | AG17: =$W17-AA17 -> 107607.74 | AH17: =$W17-AB17 -> 784789.92 | AJ17: =IFERROR($W17/X17-1,0) -> -0.049213294 | AK17: =IFERROR($W17/Y17-1,0) -> 0.00061007027 | AL17: =IFERROR($W17/Z17-1,0) -> -0.011955444 | AM17: =IFERROR($W17/AA17-1,0) -> 0.019390582 | AN17: =IFERROR($W17/AB17-1,0) -> 0.16107166
C20: Vigente | D20: =IFERROR(((1+D38/D14)^(360/D$3))-1,0) -> 0.1133847 | E20: =IFERROR(((1+E38/E14)^(360/E$3))-1,0) -> 0.11336707 | F20: =IFERROR(((1+F38/F14)^(360/F$3))-1,0) -> 0.1136305 | G20: =IFERROR(((1+G38/G14)^(360/G$3))-1,0) -> 0.11892968 | H20: =IFERROR(((1+H38/H14)^(360/H$3))-1,0) -> 0.1183404 | I20: =IFERROR(((1+I38/I14)^(360/I$3))-1,0) -> 0.11933461 | Q20: =($D20-E20)*10000 -> 0.17628857 | R20: =($D20-F20)*10000 -> -2.4580222 | S20: =($D20-G20)*10000 -> -55.449825 | T20: =($D20-H20)*10000 -> -49.557016 | U20: =($D20-I20)*10000 -> -59.499085 | W20: {=INDIRECT("'"&$C$6&"'!"&ADDRESS(ROW(),COLUMN()+44))} -> 0.11401334 | X20: {=INDIRECT("'"&$C$6&"'!"&ADDRESS(ROW(),COLUMN()+44))} -> 0.1141319 | Y20: {=INDIRECT("'"&$C$6&"'!"&ADDRESS(ROW(),COLUMN()+44))} -> 0.11417123 | Z20: {=INDIRECT("'"&$C$6&"'!"&ADDRESS(ROW(),COLUMN()+44))} -> 0.11828543 | AA20: {=INDIRECT("'"&$C$6&"'!"&ADDRESS(ROW(),COLUMN()+44))} -> 0.11880864 | AB20: {=INDIRECT("'"&$C$6&"'!"&ADDRESS(ROW(),COLUMN()+44))} -> 0.11977102 | AJ20: =($W20-X20)*10000 -> -1.185606 | AK20: =($W20-Y20)*10000 -> -1.5789626 | AL20: =($W20-Z20)*10000 -> -42.720968 | AM20: =($W20-AA20)*10000 -> -47.953007 | AN20: =($W20-AB20)*10000 -> -57.576831
C21: Refinanciado | D21: =IFERROR(((1+D39/D15)^(360/D$3))-1,0) -> 0.1077894 | E21: =IFERROR(((1+E39/E15)^(360/E$3))-1,0) -> 0.11403591 | F21: =IFERROR(((1+F39/F15)^(360/F$3))-1,0) -> 0.11098927 | G21: =IFERROR(((1+G39/G15)^(360/G$3))-1,0) -> 0.11572727 | H21: =IFERROR(((1+H39/H15)^(360/H$3))-1,0) -> 0.11670996 | I21: =IFERROR(((1+I39/I15)^(360/I$3))-1,0) -> 0.10262374 | Q21: =($D21-E21)*10000 -> -62.465045 | R21: =($D21-F21)*10000 -> -31.998685 | S21: =($D21-G21)*10000 -> -79.378647 | T21: =($D21-H21)*10000 -> -89.205514 | U21: =($D21-I21)*10000 -> 51.656611 | W21: {=INDIRECT("'"&$C$6&"'!"&ADDRESS(ROW(),COLUMN()+44))} -> 0.110952 | X21: {=INDIRECT("'"&$C$6&"'!"&ADDRESS(ROW(),COLUMN()+44))} -> 0.11688993 | Y21: {=INDIRECT("'"&$C$6&"'!"&ADDRESS(ROW(),COLUMN()+44))} -> 0.11170696 | Z21: {=INDIRECT("'"&$C$6&"'!"&ADDRESS(ROW(),COLUMN()+44))} -> 0.11587421 | AA21: {=INDIRECT("'"&$C$6&"'!"&ADDRESS(ROW(),COLUMN()+44))} -> 0.11264979 | AB21: {=INDIRECT("'"&$C$6&"'!"&ADDRESS(ROW(),COLUMN()+44))} -> 0.10954141 | AJ21: =($W21-X21)*10000 -> -59.37925 | AK21: =($W21-Y21)*10000 -> -7.5495806 | AL21: =($W21-Z21)*10000 -> -49.222138 | AM21: =($W21-AA21)*10000 -> -16.977864 | AN21: =($W21-AB21)*10000 -> 14.105921
C22: Vencido y Judicial | D22: =IFERROR(((1+D40/D16)^(360/D$3))-1,0) -> 0.024883357 | E22: =IFERROR(((1+E40/E16)^(360/E$3))-1,0) -> 0.034926112 | F22: =IFERROR(((1+F40/F16)^(360/F$3))-1,0) -> 0.022940677 | G22: =IFERROR(((1+G40/G16)^(360/G$3))-1,0) -> 0.028044434 | H22: =IFERROR(((1+H40/H16)^(360/H$3))-1,0) -> 0.038737248 | I22: =IFERROR(((1+I40/I16)^(360/I$3))-1,0) -> 0.044821992 | Q22: =($D22-E22)*10000 -> -100.42755 | R22: =($D22-F22)*10000 -> 19.426803 | S22: =($D22-G22)*10000 -> -31.610767 | T22: =($D22-H22)*10000 -> -138.53891 | U22: =($D22-I22)*10000 -> -199.38635 | W22: {=INDIRECT("'"&$C$6&"'!"&ADDRESS(ROW(),COLUMN()+44))} -> 0.025773005 | X22: {=INDIRECT("'"&$C$6&"'!"&ADDRESS(ROW(),COLUMN()+44))} -> 0.033758698 | Y22: {=INDIRECT("'"&$C$6&"'!"&ADDRESS(ROW(),COLUMN()+44))} -> 0.025986147 | Z22: {=INDIRECT("'"&$C$6&"'!"&ADDRESS(ROW(),COLUMN()+44))} -> 0.02548946 | AA22: {=INDIRECT("'"&$C$6&"'!"&ADDRESS(ROW(),COLUMN()+44))} -> 0.034623467 | AB22: {=INDIRECT("'"&$C$6&"'!"&ADDRESS(ROW(),COLUMN()+44))} -> 0.045571915 | AJ22: =($W22-X22)*10000 -> -79.856931 | AK22: =($W22-Y22)*10000 -> -2.1314242 | AL22: =($W22-Z22)*10000 -> 2.8354466 | AM22: =($W22-AA22)*10000 -> -88.504625 | AN22: =($W22-AB22)*10000 -> -197.9891
C23: Tasa Implicita | D23: =IFERROR(((1+D41/D17)^(360/D$3))-1,0) -> 0.11137811 | E23: =IFERROR(((1+E41/E17)^(360/E$3))-1,0) -> 0.11189033 | F23: =IFERROR(((1+F41/F17)^(360/F$3))-1,0) -> 0.11159997 | G23: =IFERROR(((1+G41/G17)^(360/G$3))-1,0) -> 0.1173199 | H23: =IFERROR(((1+H41/H17)^(360/H$3))-1,0) -> 0.11725894 | I23: =IFERROR(((1+I41/I17)^(360/I$3))-1,0) -> 0.11807424 | Q23: =($D23-E23)*10000 -> -5.1222257 | R23: =($D23-F23)*10000 -> -2.2186345 | S23: =($D23-G23)*10000 -> -59.417871 | T23: =($D23-H23)*10000 -> -58.808283 | U23: =($D23-I23)*10000 -> -66.961307 | W23: {=INDIRECT("'"&$C$6&"'!"&ADDRESS(ROW(),COLUMN()+44))} -> 0.11195056 | X23: {=INDIRECT("'"&$C$6&"'!"&ADDRESS(ROW(),COLUMN()+44))} -> 0.11256651 | Y23: {=INDIRECT("'"&$C$6&"'!"&ADDRESS(ROW(),COLUMN()+44))} -> 0.11209416 | Z23: {=INDIRECT("'"&$C$6&"'!"&ADDRESS(ROW(),COLUMN()+44))} -> 0.11661895 | AA23: {=INDIRECT("'"&$C$6&"'!"&ADDRESS(ROW(),COLUMN()+44))} -> 0.1175928 | AB23: {=INDIRECT("'"&$C$6&"'!"&ADDRESS(ROW(),COLUMN()+44))} -> 0.11847174 | AJ23: =($W23-X23)*10000 -> -6.1594389 | AK23: =($W23-Y23)*10000 -> -1.4359243 | AL23: =($W23-Z23)*10000 -> -46.683888 | AM23: =($W23-AA23)*10000 -> -56.422359 | AN23: =($W23-AB23)*10000 -> -65.211794
C26: Vigente | D26: =-IFERROR(((1-D44/D14)^(360/D$4))-1,0) -> -0.057323726 | E26: =-IFERROR(((1-E44/E14)^(360/E$4))-1,0) -> -0.056793005 | F26: =-IFERROR(((1-F44/F14)^(360/F$4))-1,0) -> -0.057639055 | G26: =-IFERROR(((1-G44/G14)^(360/G$4))-1,0) -> -0.065226119 | H26: =-IFERROR(((1-H44/H14)^(360/H$4))-1,0) -> -0.072331259 | I26: =-IFERROR(((1-I44/I14)^(360/I$4))-1,0) -> -0.068542711 | Q26: =($D26-E26)*10000 -> -5.3072016 | R26: =($D26-F26)*10000 -> 3.1532902 | S26: =($D26-G26)*10000 -> 79.023938 | T26: =($D26-H26)*10000 -> 150.07534 | U26: =($D26-I26)*10000 -> 112.18985 | W26: {=INDIRECT("'"&$C$6&"'!"&ADDRESS(ROW(),COLUMN()+44))} -> -0.05826649 | X26: {=INDIRECT("'"&$C$6&"'!"&ADDRESS(ROW(),COLUMN()+44))} -> -0.057861332 | Y26: {=INDIRECT("'"&$C$6&"'!"&ADDRESS(ROW(),COLUMN()+44))} -> -0.058509488 | Z26: {=INDIRECT("'"&$C$6&"'!"&ADDRESS(ROW(),COLUMN()+44))} -> -0.066763516 | AA26: {=INDIRECT("'"&$C$6&"'!"&ADDRESS(ROW(),COLUMN()+44))} -> -0.072994066 | AB26: {=INDIRECT("'"&$C$6&"'!"&ADDRESS(ROW(),COLUMN()+44))} -> -0.064995088 | AJ26: =($W26-X26)*10000 -> -4.0515809 | AK26: =($W26-Y26)*10000 -> 2.4299791 | AL26: =($W26-Z26)*10000 -> 84.970264 | AM26: =($W26-AA26)*10000 -> 147.27576 | AN26: =($W26-AB26)*10000 -> 67.285989
C27: Refinanciado | D27: =-IFERROR(((1-D45/D15)^(360/D$4))-1,0) -> -0.061201162 | E27: =-IFERROR(((1-E45/E15)^(360/E$4))-1,0) -> -0.057238903 | F27: =-IFERROR(((1-F45/F15)^(360/F$4))-1,0) -> -0.061211608 | G27: =-IFERROR(((1-G45/G15)^(360/G$4))-1,0) -> -0.065082776 | H27: =-IFERROR(((1-H45/H15)^(360/H$4))-1,0) -> -0.069448694 | I27: =-IFERROR(((1-I45/I15)^(360/I$4))-1,0) -> -0.059672081 | Q27: =($D27-E27)*10000 -> -39.622592 | R27: =($D27-F27)*10000 -> 0.10445736 | S27: =($D27-G27)*10000 -> 38.81614 | T27: =($D27-H27)*10000 -> 82.475323 | U27: =($D27-I27)*10000 -> -15.290814 | W27: {=INDIRECT("'"&$C$6&"'!"&ADDRESS(ROW(),COLUMN()+44))} -> -0.061453176 | X27: {=INDIRECT("'"&$C$6&"'!"&ADDRESS(ROW(),COLUMN()+44))} -> -0.059392367 | Y27: {=INDIRECT("'"&$C$6&"'!"&ADDRESS(ROW(),COLUMN()+44))} -> -0.061534929 | Z27: {=INDIRECT("'"&$C$6&"'!"&ADDRESS(ROW(),COLUMN()+44))} -> -0.066536457 | AA27: {=INDIRECT("'"&$C$6&"'!"&ADDRESS(ROW(),COLUMN()+44))} -> -0.068231684 | AB27: {=INDIRECT("'"&$C$6&"'!"&ADDRESS(ROW(),COLUMN()+44))} -> -0.056855971 | AJ27: =($W27-X27)*10000 -> -20.608083 | AK27: =($W27-Y27)*10000 -> 0.81753239 | AL27: =($W27-Z27)*10000 -> 50.832815 | AM27: =($W27-AA27)*10000 -> 67.785082 | AN27: =($W27-AB27)*10000 -> -45.972045
C28: Vencido y Judicial | D28: =-IFERROR(((1-D46/D16)^(360/D$4))-1,0) -> -0.056536271 | E28: =-IFERROR(((1-E46/E16)^(360/E$4))-1,0) -> -0.061129681 | F28: =-IFERROR(((1-F46/F16)^(360/F$4))-1,0) -> -0.055789993 | G28: =-IFERROR(((1-G46/G16)^(360/G$4))-1,0) -> -0.065814475 | H28: =-IFERROR(((1-H46/H16)^(360/H$4))-1,0) -> -0.068826653 | I28: =-IFERROR(((1-I46/I16)^(360/I$4))-1,0) -> -0.039940912 | Q28: =($D28-E28)*10000 -> 45.934101 | R28: =($D28-F28)*10000 -> -7.4627811 | S28: =($D28-G28)*10000 -> 92.782036 | T28: =($D28-H28)*10000 -> 122.90382 | U28: =($D28-I28)*10000 -> -165.95359 | W28: {=INDIRECT("'"&$C$6&"'!"&ADDRESS(ROW(),COLUMN()+44))} -> -0.056001442 | X28: {=INDIRECT("'"&$C$6&"'!"&ADDRESS(ROW(),COLUMN()+44))} -> -0.059798829 | Y28: {=INDIRECT("'"&$C$6&"'!"&ADDRESS(ROW(),COLUMN()+44))} -> -0.055885258 | Z28: {=INDIRECT("'"&$C$6&"'!"&ADDRESS(ROW(),COLUMN()+44))} -> -0.066820171 | AA28: {=INDIRECT("'"&$C$6&"'!"&ADDRESS(ROW(),COLUMN()+44))} -> -0.067442074 | AB28: {=INDIRECT("'"&$C$6&"'!"&ADDRESS(ROW(),COLUMN()+44))} -> -0.039064413 | AJ28: =($W28-X28)*10000 -> 37.973873 | AK28: =($W28-Y28)*10000 -> -1.1618333 | AL28: =($W28-Z28)*10000 -> 108.1873 | AM28: =($W28-AA28)*10000 -> 114.40632 | AN28: =($W28-AB28)*10000 -> -169.37029
C29: Tasa FTP | D29: =-IFERROR(((1-D47/D17)^(360/D$4))-1,0) -> -0.057326134 | E29: =-IFERROR(((1-E47/E17)^(360/E$4))-1,0) -> -0.056874326 | F29: =-IFERROR(((1-F47/F17)^(360/F$4))-1,0) -> -0.057617915 | G29: =-IFERROR(((1-G47/G17)^(360/G$4))-1,0) -> -0.065235376 | H29: =-IFERROR(((1-H47/H17)^(360/H$4))-1,0) -> -0.07227373 | I29: =-IFERROR(((1-I47/I17)^(360/I$4))-1,0) -> -0.068053085 | Q29: =($D29-E29)*10000 -> -4.5180788 | R29: =($D29-F29)*10000 -> 2.9178041 | S29: =($D29-G29)*10000 -> 79.092412 | T29: =($D29-H29)*10000 -> 149.47596 | U29: =($D29-I29)*10000 -> 107.2695 | W29: {=INDIRECT("'"&$C$6&"'!"&ADDRESS(ROW(),COLUMN()+44))} -> -0.058232392 | X29: {=INDIRECT("'"&$C$6&"'!"&ADDRESS(ROW(),COLUMN()+44))} -> -0.057905758 | Y29: {=INDIRECT("'"&$C$6&"'!"&ADDRESS(ROW(),COLUMN()+44))} -> -0.058466126 | Z29: {=INDIRECT("'"&$C$6&"'!"&ADDRESS(ROW(),COLUMN()+44))} -> -0.066763532 | AA29: {=INDIRECT("'"&$C$6&"'!"&ADDRESS(ROW(),COLUMN()+44))} -> -0.072896838 | AB29: {=INDIRECT("'"&$C$6&"'!"&ADDRESS(ROW(),COLUMN()+44))} -> -0.064522231 | AJ29: =($W29-X29)*10000 -> -3.2663399 | AK29: =($W29-Y29)*10000 -> 2.3373374 | AL29: =($W29-Z29)*10000 -> 85.311401 | AM29: =($W29-AA29)*10000 -> 146.64446 | AN29: =($W29-AB29)*10000 -> 62.898389
C32: Vigente | D32: =D20+D26 -> 0.056060977 | E32: =E20+E26 -> 0.056574068 | F32: =F20+F26 -> 0.05599145 | G32: =G20+G26 -> 0.053703565 | H32: =H20+H26 -> 0.046009145 | I32: =I20+I26 -> 0.0507919 | Q32: =($D32-E32)*10000 -> -5.1309131 | R32: =($D32-F32)*10000 -> 0.69526796 | S32: =($D32-G32)*10000 -> 23.574114 | T32: =($D32-H32)*10000 -> 100.51832 | U32: =($D32-I32)*10000 -> 52.690767 | W32: =W20+W26 -> 0.055746847 | X32: =X20+X26 -> 0.056270565 | Y32: =Y20+Y26 -> 0.055661745 | Z32: =Z20+Z26 -> 0.051521917 | AA32: =AA20+AA26 -> 0.045814571 | AB32: =AB20+AB26 -> 0.054775931 | AJ32: =($W32-X32)*10000 -> -5.2371869 | AK32: =($W32-Y32)*10000 -> 0.85101652 | AL32: =($W32-Z32)*10000 -> 42.249296 | AM32: =($W32-AA32)*10000 -> 99.322754 | AN32: =($W32-AB32)*10000 -> 9.7091582
C33: Refinanciado | D33: =D21+D27 -> 0.046588242 | E33: =E21+E27 -> 0.056797006 | F33: =F21+F27 -> 0.049777665 | G33: =G21+G27 -> 0.050644493 | H33: =H21+H27 -> 0.047261261 | I33: =I21+I27 -> 0.042951662 | Q33: =($D33-E33)*10000 -> -102.08764 | R33: =($D33-F33)*10000 -> -31.894228 | S33: =($D33-G33)*10000 -> -40.562506 | T33: =($D33-H33)*10000 -> -6.730191 | U33: =($D33-I33)*10000 -> 36.365797 | W33: =W21+W27 -> 0.049498825 | X33: =X21+X27 -> 0.057497558 | Y33: =Y21+Y27 -> 0.05017203 | Z33: =Z21+Z27 -> 0.049337757 | AA33: =AA21+AA27 -> 0.044418103 | AB33: =AB21+AB27 -> 0.052685437 | AJ33: =($W33-X33)*10000 -> -79.987333 | AK33: =($W33-Y33)*10000 -> -6.7320482 | AL33: =($W33-Z33)*10000 -> 1.6106764 | AM33: =($W33-AA33)*10000 -> 50.807218 | AN33: =($W33-AB33)*10000 -> -31.866124
C34: Vencido y Judicial | D34: =D22+D28 -> -0.031652914 | E34: =E22+E28 -> -0.026203569 | F34: =F22+F28 -> -0.032849316 | G34: =G22+G28 -> -0.037770041 | H34: =H22+H28 -> -0.030089405 | I34: =I22+I28 -> 0.0048810798 | Q34: =($D34-E34)*10000 -> -54.493446 | R34: =($D34-F34)*10000 -> 11.964022 | S34: =($D34-G34)*10000 -> 61.17127 | T34: =($D34-H34)*10000 -> -15.635089 | U34: =($D34-I34)*10000 -> -365.33994 | W34: =W22+W28 -> -0.030228437 | X34: =X22+X28 -> -0.026040131 | Y34: =Y22+Y28 -> -0.029899111 | Z34: =Z22+Z28 -> -0.041330711 | AA34: =AA22+AA28 -> -0.032818607 | AB34: =AB22+AB28 -> 0.0065075024 | AJ34: =($W34-X34)*10000 -> -41.883058 | AK34: =($W34-Y34)*10000 -> -3.2932575 | AL34: =($W34-Z34)*10000 -> 111.02274 | AM34: =($W34-AA34)*10000 -> 25.901696 | AN34: =($W34-AB34)*10000 -> -367.35939
C35: Spread | D35: =D23+D29 -> 0.054051975 | E35: =E23+E29 -> 0.055016005 | F35: =F23+F29 -> 0.053982058 | G35: =G23+G29 -> 0.05208452 | H35: =H23+H29 -> 0.044985207 | I35: =I23+I29 -> 0.050021155 | Q35: =($D35-E35)*10000 -> -9.6403045 | R35: =($D35-F35)*10000 -> 0.6991696 | S35: =($D35-G35)*10000 -> 19.674541 | T35: =($D35-H35)*10000 -> 90.667676 | U35: =($D35-I35)*10000 -> 40.308198 | W35: =W23+W29 -> 0.053718171 | X35: =X23+X29 -> 0.054660749 | Y35: =Y23+Y29 -> 0.053628029 | Z35: =Z23+Z29 -> 0.049855419 | AA35: =AA23+AA29 -> 0.044695961 | AB35: =AB23+AB29 -> 0.053949511 | AJ35: =($W35-X35)*10000 -> -9.4257789 | AK35: =($W35-Y35)*10000 -> 0.90141315 | AL35: =($W35-Z35)*10000 -> 38.627512 | AM35: =($W35-AA35)*10000 -> 90.222098 | AN35: =($W35-AB35)*10000 -> -2.313405
A38: Ingreso_Financiero | C38: Vigente | D38: {=_xlfn.XLOOKUP(1, (INDIRECT("'"&$C$6&"'!$6:$6")=D$6)* (INDIRECT("'"&$C$6&"'!$5:$5")=D$5), INDIRECT("'"&$C$6&"'!"&ROW()&":"&ROW()) )} -> 49630.635 | E38: {=_xlfn.XLOOKUP(1, (INDIRECT("'"&$C$6&"'!$6:$6")=E$6)* (INDIRECT("'"&$C$6&"'!$5:$5")=E$5), INDIRECT("'"&$C$6&"'!"&ROW()&":"&ROW()) )} -> 52663.871 | F38: {=_xlfn.XLOOKUP(1, (INDIRECT("'"&$C$6&"'!$6:$6")=F$6)* (INDIRECT("'"&$C$6&"'!$5:$5")=F$5), INDIRECT("'"&$C$6&"'!"&ROW()&":"&ROW()) )} -> 49552.001 | G38: {=_xlfn.XLOOKUP(1, (INDIRECT("'"&$C$6&"'!$6:$6")=G$6)* (INDIRECT("'"&$C$6&"'!$5:$5")=G$5), INDIRECT("'"&$C$6&"'!"&ROW()&":"&ROW()) )} -> 52669.272 | H38: {=_xlfn.XLOOKUP(1, (INDIRECT("'"&$C$6&"'!$6:$6")=H$6)* (INDIRECT("'"&$C$6&"'!$5:$5")=H$5), INDIRECT("'"&$C$6&"'!"&ROW()&":"&ROW()) )} -> 52493.643 | I38: {=_xlfn.XLOOKUP(1, (INDIRECT("'"&$C$6&"'!$6:$6")=I$6)* (INDIRECT("'"&$C$6&"'!$5:$5")=I$5), INDIRECT("'"&$C$6&"'!"&ROW()&":"&ROW()) )} -> 46108.016 | K38: =$D38-E38 -> -3033.2359 | L38: =$D38-F38 -> 78.633793 | M38: =$D38-G38 -> -3038.6364 | N38: =$D38-H38 -> -2863.0076 | O38: =$D38-I38 -> 3522.6191 | Q38: =IFERROR($D38/E38-1,0) -> -0.057596143 | R38: =IFERROR($D38/F38-1,0) -> 0.0015868944 | S38: =IFERROR($D38/G38-1,0) -> -0.057692775 | T38: =IFERROR($D38/H38-1,0) -> -0.054540082 | U38: =IFERROR($D38/I38-1,0) -> 0.076399278 | W38: {=INDIRECT("'"&$C$6&"'!"&ADDRESS(ROW(),COLUMN()+44))} -> 248595.08 | X38: {=INDIRECT("'"&$C$6&"'!"&ADDRESS(ROW(),COLUMN()+44))} -> 262684.96 | Y38: {=INDIRECT("'"&$C$6&"'!"&ADDRESS(ROW(),COLUMN()+44))} -> 198964.45 | Z38: {=INDIRECT("'"&$C$6&"'!"&ADDRESS(ROW(),COLUMN()+44))} -> 262223.38 | AA38: {=INDIRECT("'"&$C$6&"'!"&ADDRESS(ROW(),COLUMN()+44))} -> 256082.12 | AB38: {=INDIRECT("'"&$C$6&"'!"&ADDRESS(ROW(),COLUMN()+44))} -> 225636.72 | AD38: =$W38-X38 -> -14089.881 | AE38: =$W38-Y38 -> 49630.635 | AF38: =$W38-Z38 -> -13628.305 | AG38: =$W38-AA38 -> -7487.0388 | AH38: =$W38-AB38 -> 22958.365 | AJ38: =IFERROR($W38/X38-1,0) -> -0.053637944 | AK38: =IFERROR($W38/Y38-1,0) -> 0.24944474 | AL38: =IFERROR($W38/Z38-1,0) -> -0.051972118 | AM38: =IFERROR($W38/AA38-1,0) -> -0.029236867 | AN38: =IFERROR($W38/AB38-1,0) -> 0.10174924
A39: Ingreso_Financiero | C39: Refinanciado | D39: {=_xlfn.XLOOKUP(1, (INDIRECT("'"&$C$6&"'!$6:$6")=D$6)* (INDIRECT("'"&$C$6&"'!$5:$5")=D$5), INDIRECT("'"&$C$6&"'!"&ROW()&":"&ROW()) )} -> 243.25409 | E39: {=_xlfn.XLOOKUP(1, (INDIRECT("'"&$C$6&"'!$6:$6")=E$6)* (INDIRECT("'"&$C$6&"'!$5:$5")=E$5), INDIRECT("'"&$C$6&"'!"&ROW()&":"&ROW()) )} -> 275.4729 | F39: {=_xlfn.XLOOKUP(1, (INDIRECT("'"&$C$6&"'!$6:$6")=F$6)* (INDIRECT("'"&$C$6&"'!$5:$5")=F$5), INDIRECT("'"&$C$6&"'!"&ROW()&":"&ROW()) )} -> 257.99224 | G39: {=_xlfn.XLOOKUP(1, (INDIRECT("'"&$C$6&"'!$6:$6")=G$6)* (INDIRECT("'"&$C$6&"'!$5:$5")=G$5), INDIRECT("'"&$C$6&"'!"&ROW()&":"&ROW()) )} -> 249.00472 | H39: {=_xlfn.XLOOKUP(1, (INDIRECT("'"&$C$6&"'!$6:$6")=H$6)* (INDIRECT("'"&$C$6&"'!$5:$5")=H$5), INDIRECT("'"&$C$6&"'!"&ROW()&":"&ROW()) )} -> 213.37743 | I39: {=_xlfn.XLOOKUP(1, (INDIRECT("'"&$C$6&"'!$6:$6")=I$6)* (INDIRECT("'"&$C$6&"'!$5:$5")=I$5), INDIRECT("'"&$C$6&"'!"&ROW()&":"&ROW()) )} -> 235.07602 | K39: =$D39-E39 -> -32.218812 | L39: =$D39-F39 -> -14.73815 | M39: =$D39-G39 -> -5.75063 | N39: =$D39-H39 -> 29.87666 | O39: =$D39-I39 -> 8.17807 | Q39: =IFERROR($D39/E39-1,0) -> -0.11695819 | R39: =IFERROR($D39/F39-1,0) -> -0.057126331 | S39: =IFERROR($D39/G39-1,0) -> -0.023094462 | T39: =IFERROR($D39/H39-1,0) -> 0.1400179 | U39: =IFERROR($D39/I39-1,0) -> 0.034789044 | W39: {=INDIRECT("'"&$C$6&"'!"&ADDRESS(ROW(),COLUMN()+44))} -> 1299.2735 | X39: {=INDIRECT("'"&$C$6&"'!"&ADDRESS(ROW(),COLUMN()+44))} -> 1375.0881 | Y39: {=INDIRECT("'"&$C$6&"'!"&ADDRESS(ROW(),COLUMN()+44))} -> 1056.0194 | Z39: {=INDIRECT("'"&$C$6&"'!"&ADDRESS(ROW(),COLUMN()+44))} -> 1106.7919 | AA39: {=INDIRECT("'"&$C$6&"'!"&ADDRESS(ROW(),COLUMN()+44))} -> 1111.5611 | AB39: {=INDIRECT("'"&$C$6&"'!"&ADDRESS(ROW(),COLUMN()+44))} -> 1259.5949 | AD39: =$W39-X39 -> -75.81464 | AE39: =$W39-Y39 -> 243.25409 | AF39: =$W39-Z39 -> 192.48164 | AG39: =$W39-AA39 -> 187.71239 | AH39: =$W39-AB39 -> 39.67861 | AJ39: =IFERROR($W39/X39-1,0) -> -0.055134386 | AK39: =IFERROR($W39/Y39-1,0) -> 0.23035002 | AL39: =IFERROR($W39/Z39-1,0) -> 0.17390952 | AM39: =IFERROR($W39/AA39-1,0) -> 0.16887276 | AN39: =IFERROR($W39/AB39-1,0) -> 0.031501088
A40: Ingreso_Financiero | C40: Vencido y Judicial | D40: {=_xlfn.XLOOKUP(1, (INDIRECT("'"&$C$6&"'!$6:$6")=D$6)* (INDIRECT("'"&$C$6&"'!$5:$5")=D$5), INDIRECT("'"&$C$6&"'!"&ROW()&":"&ROW()) )} -> 250.53323 | E40: {=_xlfn.XLOOKUP(1, (INDIRECT("'"&$C$6&"'!$6:$6")=E$6)* (INDIRECT("'"&$C$6&"'!$5:$5")=E$5), INDIRECT("'"&$C$6&"'!"&ROW()&":"&ROW()) )} -> 313.86231 | F40: {=_xlfn.XLOOKUP(1, (INDIRECT("'"&$C$6&"'!$6:$6")=F$6)* (INDIRECT("'"&$C$6&"'!$5:$5")=F$5), INDIRECT("'"&$C$6&"'!"&ROW()&":"&ROW()) )} -> 228.92027 | G40: {=_xlfn.XLOOKUP(1, (INDIRECT("'"&$C$6&"'!$6:$6")=G$6)* (INDIRECT("'"&$C$6&"'!$5:$5")=G$5), INDIRECT("'"&$C$6&"'!"&ROW()&":"&ROW()) )} -> 223.04664 | H40: {=_xlfn.XLOOKUP(1, (INDIRECT("'"&$C$6&"'!$6:$6")=H$6)* (INDIRECT("'"&$C$6&"'!$5:$5")=H$5), INDIRECT("'"&$C$6&"'!"&ROW()&":"&ROW()) )} -> 236.32545 | I40: {=_xlfn.XLOOKUP(1, (INDIRECT("'"&$C$6&"'!$6:$6")=I$6)* (INDIRECT("'"&$C$6&"'!$5:$5")=I$5), INDIRECT("'"&$C$6&"'!"&ROW()&":"&ROW()) )} -> 276.49731 | K40: =$D40-E40 -> -63.329082 | L40: =$D40-F40 -> 21.61296 | M40: =$D40-G40 -> 27.48659 | N40: =$D40-H40 -> 14.20778 | O40: =$D40-I40 -> -25.96408 | Q40: =IFERROR($D40/E40-1,0) -> -0.20177345 | R40: =IFERROR($D40/F40-1,0) -> 0.094412609 | S40: =IFERROR($D40/G40-1,0) -> 0.12323248 | T40: =IFERROR($D40/H40-1,0) -> 0.060119551 | U40: =IFERROR($D40/I40-1,0) -> -0.093903554 | W40: {=INDIRECT("'"&$C$6&"'!"&ADDRESS(ROW(),COLUMN()+44))} -> 1342.59 | X40: {=INDIRECT("'"&$C$6&"'!"&ADDRESS(ROW(),COLUMN()+44))} -> 1566.1821 | Y40: {=INDIRECT("'"&$C$6&"'!"&ADDRESS(ROW(),COLUMN()+44))} -> 1092.0568 | Z40: {=INDIRECT("'"&$C$6&"'!"&ADDRESS(ROW(),COLUMN()+44))} -> 1032.1639 | AA40: {=INDIRECT("'"&$C$6&"'!"&ADDRESS(ROW(),COLUMN()+44))} -> 1074.0236 | AB40: {=INDIRECT("'"&$C$6&"'!"&ADDRESS(ROW(),COLUMN()+44))} -> 1466.8814 | AD40: =$W40-X40 -> -223.59203 | AE40: =$W40-Y40 -> 250.53323 | AF40: =$W40-Z40 -> 310.4261 | AG40: =$W40-AA40 -> 268.56644 | AH40: =$W40-AB40 -> -124.2914 | AJ40: =IFERROR($W40/X40-1,0) -> -0.14276248 | AK40: =IFERROR($W40/Y40-1,0) -> 0.2294141 | AL40: =IFERROR($W40/Z40-1,0) -> 0.30075271 | AM40: =IFERROR($W40/AA40-1,0) -> 0.25005637 | AN40: =IFERROR($W40/AB40-1,0) -> -0.084731729
C41: Ingreso Financiero | D41: =SUM(D38:D40) -> 50124.422 | E41: =SUM(E38:E40) -> 53253.206 | F41: =SUM(F38:F40) -> 50038.914 | G41: =SUM(G38:G40) -> 53141.323 | H41: =SUM(H38:H40) -> 52943.346 | I41: =SUM(I38:I40) -> 46619.589 | K41: =$D41-E41 -> -3128.7837 | L41: =$D41-F41 -> 85.508603 | M41: =$D41-G41 -> -3016.9005 | N41: =$D41-H41 -> -2818.9232 | O41: =$D41-I41 -> 3504.8331 | Q41: =IFERROR($D41/E41-1,0) -> -0.058752965 | R41: =IFERROR($D41/F41-1,0) -> 0.0017088421 | S41: =IFERROR($D41/G41-1,0) -> -0.056771272 | T41: =IFERROR($D41/H41-1,0) -> -0.053244145 | U41: =IFERROR($D41/I41-1,0) -> 0.075179408 | W41: =SUM(W38:W40) -> 251236.94 | X41: =SUM(X38:X40) -> 265626.23 | Y41: =SUM(Y38:Y40) -> 201112.52 | Z41: =SUM(Z38:Z40) -> 264362.34 | AA41: =SUM(AA38:AA40) -> 258267.7 | AB41: =SUM(AB38:AB40) -> 228363.19 | AD41: =$W41-X41 -> -14389.288 | AE41: =$W41-Y41 -> 50124.422 | AF41: =$W41-Z41 -> -13125.397 | AG41: =$W41-AA41 -> -7030.76 | AH41: =$W41-AB41 -> 22873.752 | AJ41: =IFERROR($W41/X41-1,0) -> -0.054171185 | AK41: =IFERROR($W41/Y41-1,0) -> 0.24923571 | AL41: =IFERROR($W41/Z41-1,0) -> -0.049649269 | AM41: =IFERROR($W41/AA41-1,0) -> -0.027222761 | AN41: =IFERROR($W41/AB41-1,0) -> 0.10016392
A44: FTP | C44: Vigente | D44: {=_xlfn.XLOOKUP(1, (INDIRECT("'"&$C$6&"'!$6:$6")=D$6)* (INDIRECT("'"&$C$6&"'!$5:$5")=D$5), INDIRECT("'"&$C$6&"'!"&ROW()&":"&ROW()) )} -> -26560.672 | E44: {=_xlfn.XLOOKUP(1, (INDIRECT("'"&$C$6&"'!$6:$6")=E$6)* (INDIRECT("'"&$C$6&"'!$5:$5")=E$5), INDIRECT("'"&$C$6&"'!"&ROW()&":"&ROW()) )} -> -27933.632 | F44: {=_xlfn.XLOOKUP(1, (INDIRECT("'"&$C$6&"'!$6:$6")=F$6)* (INDIRECT("'"&$C$6&"'!$5:$5")=F$5), INDIRECT("'"&$C$6&"'!"&ROW()&":"&ROW()) )} -> -25745.608 | G44: {=_xlfn.XLOOKUP(1, (INDIRECT("'"&$C$6&"'!$6:$6")=G$6)* (INDIRECT("'"&$C$6&"'!$5:$5")=G$5), INDIRECT("'"&$C$6&"'!"&ROW()&":"&ROW()) )} -> -30543.076 | H44: {=_xlfn.XLOOKUP(1, (INDIRECT("'"&$C$6&"'!$6:$6")=H$6)* (INDIRECT("'"&$C$6&"'!$5:$5")=H$5), INDIRECT("'"&$C$6&"'!"&ROW()&":"&ROW()) )} -> -33812.847 | I44: {=_xlfn.XLOOKUP(1, (INDIRECT("'"&$C$6&"'!$6:$6")=I$6)* (INDIRECT("'"&$C$6&"'!$5:$5")=I$5), INDIRECT("'"&$C$6&"'!"&ROW()&":"&ROW()) )} -> -27966.932 | K44: =$D44-E44 -> 1372.9595 | L44: =$D44-F44 -> -815.06437 | M44: =$D44-G44 -> 3982.404 | N44: =$D44-H44 -> 7252.1753 | O44: =$D44-I44 -> 1406.2597 | Q44: =IFERROR($D44/E44-1,0) -> -0.049150769 | R44: =IFERROR($D44/F44-1,0) -> 0.031658385 | S44: =IFERROR($D44/G44-1,0) -> -0.13038648 | T44: =IFERROR($D44/H44-1,0) -> -0.21447988 | U44: =IFERROR($D44/I44-1,0) -> -0.050282946 | W44: {=INDIRECT("'"&$C$6&"'!"&ADDRESS(ROW(),COLUMN()+44))} -> -130984.16 | X44: {=INDIRECT("'"&$C$6&"'!"&ADDRESS(ROW(),COLUMN()+44))} -> -137334.04 | Y44: {=INDIRECT("'"&$C$6&"'!"&ADDRESS(ROW(),COLUMN()+44))} -> -104423.49 | Z44: {=INDIRECT("'"&$C$6&"'!"&ADDRESS(ROW(),COLUMN()+44))} -> -152303.93 | AA44: {=INDIRECT("'"&$C$6&"'!"&ADDRESS(ROW(),COLUMN()+44))} -> -162572.86 | AB44: {=INDIRECT("'"&$C$6&"'!"&ADDRESS(ROW(),COLUMN()+44))} -> -126175.14 | AD44: =$W44-X44 -> 6349.8804 | AE44: =$W44-Y44 -> -26560.672 | AF44: =$W44-Z44 -> 21319.765 | AG44: =$W44-AA44 -> 31588.698 | AH44: =$W44-AB44 -> -4809.0253 | AJ44: =IFERROR($W44/X44-1,0) -> -0.046236755 | AK44: =IFERROR($W44/Y44-1,0) -> 0.25435534 | AL44: =IFERROR($W44/Z44-1,0) -> -0.13998171 | AM44: =IFERROR($W44/AA44-1,0) -> -0.19430487 | AN44: =IFERROR($W44/AB44-1,0) -> 0.038113891
A45: FTP | C45: Refinanciado | D45: {=_xlfn.XLOOKUP(1, (INDIRECT("'"&$C$6&"'!$6:$6")=D$6)* (INDIRECT("'"&$C$6&"'!$5:$5")=D$5), INDIRECT("'"&$C$6&"'!"&ROW()&":"&ROW()) )} -> -145.61201 | E45: {=_xlfn.XLOOKUP(1, (INDIRECT("'"&$C$6&"'!$6:$6")=E$6)* (INDIRECT("'"&$C$6&"'!$5:$5")=E$5), INDIRECT("'"&$C$6&"'!"&ROW()&":"&ROW()) )} -> -146.41062 | F45: {=_xlfn.XLOOKUP(1, (INDIRECT("'"&$C$6&"'!$6:$6")=F$6)* (INDIRECT("'"&$C$6&"'!$5:$5")=F$5), INDIRECT("'"&$C$6&"'!"&ROW()&":"&ROW()) )} -> -145.35149 | G45: {=_xlfn.XLOOKUP(1, (INDIRECT("'"&$C$6&"'!$6:$6")=G$6)* (INDIRECT("'"&$C$6&"'!$5:$5")=G$5), INDIRECT("'"&$C$6&"'!"&ROW()&":"&ROW()) )} -> -147.87924 | H45: {=_xlfn.XLOOKUP(1, (INDIRECT("'"&$C$6&"'!$6:$6")=H$6)* (INDIRECT("'"&$C$6&"'!$5:$5")=H$5), INDIRECT("'"&$C$6&"'!"&ROW()&":"&ROW()) )} -> -133.8848 | I45: {=_xlfn.XLOOKUP(1, (INDIRECT("'"&$C$6&"'!$6:$6")=I$6)* (INDIRECT("'"&$C$6&"'!$5:$5")=I$5), INDIRECT("'"&$C$6&"'!"&ROW()&":"&ROW()) )} -> -143.88885 | K45: =$D45-E45 -> 0.79860786 | L45: =$D45-F45 -> -0.26052 | M45: =$D45-G45 -> 2.26723 | N45: =$D45-H45 -> -11.72721 | O45: =$D45-I45 -> -1.72316 | Q45: =IFERROR($D45/E45-1,0) -> -0.0054545761 | R45: =IFERROR($D45/F45-1,0) -> 0.0017923449 | S45: =IFERROR($D45/G45-1,0) -> -0.015331631 | T45: =IFERROR($D45/H45-1,0) -> 0.087591795 | U45: =IFERROR($D45/I45-1,0) -> 0.011975633 | W45: {=INDIRECT("'"&$C$6&"'!"&ADDRESS(ROW(),COLUMN()+44))} -> -739.96321 | X45: {=INDIRECT("'"&$C$6&"'!"&ADDRESS(ROW(),COLUMN()+44))} -> -720.86989 | Y45: {=INDIRECT("'"&$C$6&"'!"&ADDRESS(ROW(),COLUMN()+44))} -> -594.3512 | Z45: {=INDIRECT("'"&$C$6&"'!"&ADDRESS(ROW(),COLUMN()+44))} -> -653.39404 | AA45: {=INDIRECT("'"&$C$6&"'!"&ADDRESS(ROW(),COLUMN()+44))} -> -695.33339 | AB45: {=INDIRECT("'"&$C$6&"'!"&ADDRESS(ROW(),COLUMN()+44))} -> -673.19944 | AD45: =$W45-X45 -> -19.093324 | AE45: =$W45-Y45 -> -145.61201 | AF45: =$W45-Z45 -> -86.56917 | AG45: =$W45-AA45 -> -44.62982 | AH45: =$W45-AB45 -> -66.76377 | AJ45: =IFERROR($W45/X45-1,0) -> 0.026486506 | AK45: =IFERROR($W45/Y45-1,0) -> 0.24499321 | AL45: =IFERROR($W45/Z45-1,0) -> 0.13249152 | AM45: =IFERROR($W45/AA45-1,0) -> 0.064184779 | AN45: =IFERROR($W45/AB45-1,0) -> 0.099173835
A46: FTP | C46: Vencido y Judicial | D46: {=_xlfn.XLOOKUP(1, (INDIRECT("'"&$C$6&"'!$6:$6")=D$6)* (INDIRECT("'"&$C$6&"'!$5:$5")=D$5), INDIRECT("'"&$C$6&"'!"&ROW()&":"&ROW()) )} -> -580.04154 | E46: {=_xlfn.XLOOKUP(1, (INDIRECT("'"&$C$6&"'!$6:$6")=E$6)* (INDIRECT("'"&$C$6&"'!$5:$5")=E$5), INDIRECT("'"&$C$6&"'!"&ROW()&":"&ROW()) )} -> -561.17477 | F46: {=_xlfn.XLOOKUP(1, (INDIRECT("'"&$C$6&"'!$6:$6")=F$6)* (INDIRECT("'"&$C$6&"'!$5:$5")=F$5), INDIRECT("'"&$C$6&"'!"&ROW()&":"&ROW()) )} -> -548.6546 | G46: {=_xlfn.XLOOKUP(1, (INDIRECT("'"&$C$6&"'!$6:$6")=G$6)* (INDIRECT("'"&$C$6&"'!$5:$5")=G$5), INDIRECT("'"&$C$6&"'!"&ROW()&":"&ROW()) )} -> -531.99571 | H46: {=_xlfn.XLOOKUP(1, (INDIRECT("'"&$C$6&"'!$6:$6")=H$6)* (INDIRECT("'"&$C$6&"'!$5:$5")=H$5), INDIRECT("'"&$C$6&"'!"&ROW()&":"&ROW()) )} -> -428.23415 | I46: {=_xlfn.XLOOKUP(1, (INDIRECT("'"&$C$6&"'!$6:$6")=I$6)* (INDIRECT("'"&$C$6&"'!$5:$5")=I$5), INDIRECT("'"&$C$6&"'!"&ROW()&":"&ROW()) )} -> -255.16487 | K46: =$D46-E46 -> -18.86677 | L46: =$D46-F46 -> -31.38694 | M46: =$D46-G46 -> -48.04583 | N46: =$D46-H46 -> -151.80739 | O46: =$D46-I46 -> -324.87667 | Q46: =IFERROR($D46/E46-1,0) -> 0.033620132 | R46: =IFERROR($D46/F46-1,0) -> 0.057207103 | S46: =IFERROR($D46/G46-1,0) -> 0.090312439 | T46: =IFERROR($D46/H46-1,0) -> 0.35449623 | U46: =IFERROR($D46/I46-1,0) -> 1.273203 | W46: {=INDIRECT("'"&$C$6&"'!"&ADDRESS(ROW(),COLUMN()+44))} -> -2897.6575 | X46: {=INDIRECT("'"&$C$6&"'!"&ADDRESS(ROW(),COLUMN()+44))} -> -2760.8905 | Y46: {=INDIRECT("'"&$C$6&"'!"&ADDRESS(ROW(),COLUMN()+44))} -> -2317.616 | Z46: {=INDIRECT("'"&$C$6&"'!"&ADDRESS(ROW(),COLUMN()+44))} -> -2674.6092 | AA46: {=INDIRECT("'"&$C$6&"'!"&ADDRESS(ROW(),COLUMN()+44))} -> -2089.636 | AB46: {=INDIRECT("'"&$C$6&"'!"&ADDRESS(ROW(),COLUMN()+44))} -> -1269.4669 | AD46: =$W46-X46 -> -136.767 | AE46: =$W46-Y46 -> -580.04154 | AF46: =$W46-Z46 -> -223.04837 | AG46: =$W46-AA46 -> -808.02153 | AH46: =$W46-AB46 -> -1628.1906 | AJ46: =IFERROR($W46/X46-1,0) -> 0.049537277 | AK46: =IFERROR($W46/Y46-1,0) -> 0.25027509 | AL46: =IFERROR($W46/Z46-1,0) -> 0.083394753 | AM46: =IFERROR($W46/AA46-1,0) -> 0.38668052 | AN46: =IFERROR($W46/AB46-1,0) -> 1.2825782
C47: Costo de Fondos | D47: =SUM(D44:D46) -> -27286.326 | E47: =SUM(E44:E46) -> -28641.217 | F47: =SUM(F44:F46) -> -26439.614 | G47: =SUM(G44:G46) -> -31222.951 | H47: =SUM(H44:H46) -> -34374.966 | I47: =SUM(I44:I46) -> -28365.986 | K47: =$D47-E47 -> 1354.8913 | L47: =$D47-F47 -> -846.71183 | M47: =$D47-G47 -> 3936.6254 | N47: =$D47-H47 -> 7088.6407 | O47: =$D47-I47 -> 1079.6599 | Q47: =IFERROR($D47/E47-1,0) -> -0.047305648 | R47: =IFERROR($D47/F47-1,0) -> 0.032024365 | S47: =IFERROR($D47/G47-1,0) -> -0.12608115 | T47: =IFERROR($D47/H47-1,0) -> -0.20621521 | U47: =IFERROR($D47/I47-1,0) -> -0.038061779 | W47: =SUM(W44:W46) -> -134621.78 | X47: =SUM(X44:X46) -> -140815.8 | Y47: =SUM(Y44:Y46) -> -107335.46 | Z47: =SUM(Z44:Z46) -> -155631.93 | AA47: =SUM(AA44:AA46) -> -165357.83 | AB47: =SUM(AB44:AB46) -> -128117.8 | AD47: =$W47-X47 -> 6194.0201 | AE47: =$W47-Y47 -> -27286.326 | AF47: =$W47-Z47 -> 21010.147 | AG47: =$W47-AA47 -> 30736.047 | AH47: =$W47-AB47 -> -6503.9797 | AJ47: =IFERROR($W47/X47-1,0) -> -0.043986683 | AK47: =IFERROR($W47/Y47-1,0) -> 0.2542154 | AL47: =IFERROR($W47/Z47-1,0) -> -0.13499895 | AM47: =IFERROR($W47/AA47-1,0) -> -0.18587597 | AN47: =IFERROR($W47/AB47-1,0) -> 0.05076562
C50: Vigente | D50: =D38+D44 -> 23069.963 | E50: =E38+E44 -> 24730.239 | F50: =F38+F44 -> 23806.394 | G50: =G38+G44 -> 22126.195 | H50: =H38+H44 -> 18680.795 | I50: =I38+I44 -> 18141.084 | K50: =$D50-E50 -> -1660.2764 | L50: =$D50-F50 -> -736.43058 | M50: =$D50-G50 -> 943.76759 | N50: =$D50-H50 -> 4389.1677 | O50: =$D50-I50 -> 4928.8788 | Q50: =IFERROR($D50/E50-1,0) -> -0.067135475 | R50: =IFERROR($D50/F50-1,0) -> -0.030934151 | S50: =IFERROR($D50/G50-1,0) -> 0.042653858 | T50: =IFERROR($D50/H50-1,0) -> 0.23495615 | U50: =IFERROR($D50/I50-1,0) -> 0.27169704 | W50: =W38+W44 -> 117610.92 | X50: =X38+X44 -> 125350.92 | Y50: =Y38+Y44 -> 94540.956 | Z50: =Z38+Z44 -> 109919.46 | AA50: =AA38+AA44 -> 93509.259 | AB50: =AB38+AB44 -> 99461.58 | AD50: =$W50-X50 -> -7740.0008 | AE50: =$W50-Y50 -> 23069.963 | AF50: =$W50-Z50 -> 7691.4599 | AG50: =$W50-AA50 -> 24101.66 | AH50: =$W50-AB50 -> 18149.339 | AJ50: =IFERROR($W50/X50-1,0) -> -0.061746661 | AK50: =IFERROR($W50/Y50-1,0) -> 0.24402084 | AL50: =IFERROR($W50/Z50-1,0) -> 0.069973597 | AM50: =IFERROR($W50/AA50-1,0) -> 0.25774624 | AN50: =IFERROR($W50/AB50-1,0) -> 0.18247588
C51: Refinanciado | D51: =D39+D45 -> 97.64208 | E51: =E39+E45 -> 129.06228 | F51: =F39+F45 -> 112.64075 | G51: =G39+G45 -> 101.12548 | H51: =H39+H45 -> 79.49263 | I51: =I39+I45 -> 91.18717 | K51: =$D51-E51 -> -31.420205 | L51: =$D51-F51 -> -14.99867 | M51: =$D51-G51 -> -3.4834 | N51: =$D51-H51 -> 18.14945 | O51: =$D51-I51 -> 6.45491 | Q51: =IFERROR($D51/E51-1,0) -> -0.24344993 | R51: =IFERROR($D51/F51-1,0) -> -0.13315492 | S51: =IFERROR($D51/G51-1,0) -> -0.034446313 | T51: =IFERROR($D51/H51-1,0) -> 0.22831613 | U51: =IFERROR($D51/I51-1,0) -> 0.07078748 | W51: =W39+W45 -> 559.31029 | X51: =X39+X45 -> 654.21825 | Y51: =Y39+Y45 -> 461.66821 | Z51: =Z39+Z45 -> 453.39782 | AA51: =AA39+AA45 -> 416.22772 | AB51: =AB39+AB45 -> 586.39545 | AD51: =$W51-X51 -> -94.907964 | AE51: =$W51-Y51 -> 97.64208 | AF51: =$W51-Z51 -> 105.91247 | AG51: =$W51-AA51 -> 143.08257 | AH51: =$W51-AB51 -> -27.08516 | AJ51: =IFERROR($W51/X51-1,0) -> -0.1450708 | AK51: =IFERROR($W51/Y51-1,0) -> 0.21149838 | AL51: =IFERROR($W51/Z51-1,0) -> 0.23359722 | AM51: =IFERROR($W51/AA51-1,0) -> 0.34376031 | AN51: =IFERROR($W51/AB51-1,0) -> -0.04618924
C52: Vencido y Judicial | D52: =D40+D46 -> -329.50831 | E52: =E40+E46 -> -247.31246 | F52: =F40+F46 -> -319.73433 | G52: =G40+G46 -> -308.94907 | H52: =H40+H46 -> -191.9087 | I52: =I40+I46 -> 21.33244 | K52: =$D52-E52 -> -82.195852 | L52: =$D52-F52 -> -9.77398 | M52: =$D52-G52 -> -20.55924 | N52: =$D52-H52 -> -137.59961 | O52: =$D52-I52 -> -350.84075 | Q52: =IFERROR($D52/E52-1,0) -> 0.33235629 | R52: =IFERROR($D52/F52-1,0) -> 0.030569067 | S52: =IFERROR($D52/G52-1,0) -> 0.066545725 | T52: =IFERROR($D52/H52-1,0) -> 0.71700559 | U52: =IFERROR($D52/I52-1,0) -> -16.446349 | W52: =W40+W46 -> -1555.0675 | X52: =X40+X46 -> -1194.7084 | Y52: =Y40+Y46 -> -1225.5592 | Z52: =Z40+Z46 -> -1642.4452 | AA52: =AA40+AA46 -> -1015.6124 | AB52: =AB40+AB46 -> 197.41452 | AD52: =$W52-X52 -> -360.35903 | AE52: =$W52-Y52 -> -329.50831 | AF52: =$W52-Z52 -> 87.37773 | AG52: =$W52-AA52 -> -539.45509 | AH52: =$W52-AB52 -> -1752.482 | AJ52: =IFERROR($W52/X52-1,0) -> 0.30162927 | AK52: =IFERROR($W52/Y52-1,0) -> 0.26886365 | AL52: =IFERROR($W52/Z52-1,0) -> -0.053199784 | AM52: =IFERROR($W52/AA52-1,0) -> 0.53116238 | AN52: =IFERROR($W52/AB52-1,0) -> -8.8771687
C53: Resultado Financiero Bruto | D53: =D41+D47 -> 22838.097 | E53: =E41+E47 -> 24611.989 | F53: =F41+F47 -> 23599.3 | G53: =G41+G47 -> 21918.372 | H53: =H41+H47 -> 18568.379 | I53: =I41+I47 -> 18253.604 | K53: =$D53-E53 -> -1773.8924 | L53: =$D53-F53 -> -761.20323 | M53: =$D53-G53 -> 919.72495 | N53: =$D53-H53 -> 4269.7176 | O53: =$D53-I53 -> 4584.493 | Q53: =IFERROR($D53/E53-1,0) -> -0.072074322 | R53: =IFERROR($D53/F53-1,0) -> -0.032255331 | S53: =IFERROR($D53/G53-1,0) -> 0.041961372 | T53: =IFERROR($D53/H53-1,0) -> 0.22994563 | U53: =IFERROR($D53/I53-1,0) -> 0.2511555 | W53: =W41+W47 -> 116615.16 | X53: =X41+X47 -> 124810.43 | Y53: =Y41+Y47 -> 93777.065 | Z53: =Z41+Z47 -> 108730.41 | AA53: =AA41+AA47 -> 92909.875 | AB53: =AB41+AB47 -> 100245.39 | AD53: =$W53-X53 -> -8195.2677 | AE53: =$W53-Y53 -> 22838.097 | AF53: =$W53-Z53 -> 7884.7501 | AG53: =$W53-AA53 -> 23705.287 | AH53: =$W53-AB53 -> 16369.772 | AJ53: =IFERROR($W53/X53-1,0) -> -0.065661722 | AK53: =IFERROR($W53/Y53-1,0) -> 0.24353606 | AL53: =IFERROR($W53/Z53-1,0) -> 0.072516511 | AM53: =IFERROR($W53/AA53-1,0) -> 0.25514282 | AN53: =IFERROR($W53/AB53-1,0) -> 0.16329701
A56: Gasto_Provision | C56: Provisiones Cartera | D56: {=_xlfn.XLOOKUP(1, (INDIRECT("'"&$C$6&"'!$6:$6")=D$6)* (INDIRECT("'"&$C$6&"'!$5:$5")=D$5), INDIRECT("'"&$C$6&"'!"&ROW()&":"&ROW()) )} -> -12270.895 | E56: {=_xlfn.XLOOKUP(1, (INDIRECT("'"&$C$6&"'!$6:$6")=E$6)* (INDIRECT("'"&$C$6&"'!$5:$5")=E$5), INDIRECT("'"&$C$6&"'!"&ROW()&":"&ROW()) )} -> -11961.369 | F56: {=_xlfn.XLOOKUP(1, (INDIRECT("'"&$C$6&"'!$6:$6")=F$6)* (INDIRECT("'"&$C$6&"'!$5:$5")=F$5), INDIRECT("'"&$C$6&"'!"&ROW()&":"&ROW()) )} -> -13060.036 | G56: {=_xlfn.XLOOKUP(1, (INDIRECT("'"&$C$6&"'!$6:$6")=G$6)* (INDIRECT("'"&$C$6&"'!$5:$5")=G$5), INDIRECT("'"&$C$6&"'!"&ROW()&":"&ROW()) )} -> -11611.597 | H56: {=_xlfn.XLOOKUP(1, (INDIRECT("'"&$C$6&"'!$6:$6")=H$6)* (INDIRECT("'"&$C$6&"'!$5:$5")=H$5), INDIRECT("'"&$C$6&"'!"&ROW()&":"&ROW()) )} -> -9856.1384 | I56: {=_xlfn.XLOOKUP(1, (INDIRECT("'"&$C$6&"'!$6:$6")=I$6)* (INDIRECT("'"&$C$6&"'!$5:$5")=I$5), INDIRECT("'"&$C$6&"'!"&ROW()&":"&ROW()) )} -> -8448.1943 | K56: =$D56-E56 -> -309.52533 | L56: =$D56-F56 -> 789.14103 | M56: =$D56-G56 -> -659.29771 | N56: =$D56-H56 -> -2414.7564 | O56: =$D56-I56 -> -3822.7005 | Q56: =IFERROR($D56/E56-1,0) -> 0.025877081 | R56: =IFERROR($D56/F56-1,0) -> -0.060424109 | S56: =IFERROR($D56/G56-1,0) -> 0.056779245 | T56: =IFERROR($D56/H56-1,0) -> 0.24500025 | U56: =IFERROR($D56/I56-1,0) -> 0.45248729 | W56: {=INDIRECT("'"&$C$6&"'!"&ADDRESS(ROW(),COLUMN()+44))} -> -60623.611 | X56: {=INDIRECT("'"&$C$6&"'!"&ADDRESS(ROW(),COLUMN()+44))} -> -63589.901 | Y56: {=INDIRECT("'"&$C$6&"'!"&ADDRESS(ROW(),COLUMN()+44))} -> -48352.717 | Z56: {=INDIRECT("'"&$C$6&"'!"&ADDRESS(ROW(),COLUMN()+44))} -> -55698.117 | AA56: {=INDIRECT("'"&$C$6&"'!"&ADDRESS(ROW(),COLUMN()+44))} -> -56705.242 | AB56: {=INDIRECT("'"&$C$6&"'!"&ADDRESS(ROW(),COLUMN()+44))} -> -38946.122 | AD56: =$W56-X56 -> 2966.2899 | AE56: =$W56-Y56 -> -12270.895 | AF56: =$W56-Z56 -> -4925.4946 | AG56: =$W56-AA56 -> -3918.3694 | AH56: =$W56-AB56 -> -21677.489 | AJ56: =IFERROR($W56/X56-1,0) -> -0.046647185 | AK56: =IFERROR($W56/Y56-1,0) -> 0.25377881 | AL56: =IFERROR($W56/Z56-1,0) -> 0.088431978 | AM56: =IFERROR($W56/AA56-1,0) -> 0.069100655 | AN56: =IFERROR($W56/AB56-1,0) -> 0.55660199
A57: Recupero | C57: Recupero de Castigos | D57: {=_xlfn.XLOOKUP(1, (INDIRECT("'"&$C$6&"'!$6:$6")=D$6)* (INDIRECT("'"&$C$6&"'!$5:$5")=D$5), INDIRECT("'"&$C$6&"'!"&ROW()&":"&ROW()) )} -> 2058.7294 | E57: {=_xlfn.XLOOKUP(1, (INDIRECT("'"&$C$6&"'!$6:$6")=E$6)* (INDIRECT("'"&$C$6&"'!$5:$5")=E$5), INDIRECT("'"&$C$6&"'!"&ROW()&":"&ROW()) )} -> 2342.9858 | F57: {=_xlfn.XLOOKUP(1, (INDIRECT("'"&$C$6&"'!$6:$6")=F$6)* (INDIRECT("'"&$C$6&"'!$5:$5")=F$5), INDIRECT("'"&$C$6&"'!"&ROW()&":"&ROW()) )} -> 2202.9049 | G57: {=_xlfn.XLOOKUP(1, (INDIRECT("'"&$C$6&"'!$6:$6")=G$6)* (INDIRECT("'"&$C$6&"'!$5:$5")=G$5), INDIRECT("'"&$C$6&"'!"&ROW()&":"&ROW()) )} -> 2498.6107 | H57: {=_xlfn.XLOOKUP(1, (INDIRECT("'"&$C$6&"'!$6:$6")=H$6)* (INDIRECT("'"&$C$6&"'!$5:$5")=H$5), INDIRECT("'"&$C$6&"'!"&ROW()&":"&ROW()) )} -> 2500.0295 | I57: {=_xlfn.XLOOKUP(1, (INDIRECT("'"&$C$6&"'!$6:$6")=I$6)* (INDIRECT("'"&$C$6&"'!$5:$5")=I$5), INDIRECT("'"&$C$6&"'!"&ROW()&":"&ROW()) )} -> 3445.8707 | K57: =$D57-E57 -> -284.25643 | L57: =$D57-F57 -> -144.17547 | M57: =$D57-G57 -> -439.88128 | N57: =$D57-H57 -> -441.3001 | O57: =$D57-I57 -> -1387.1413 | Q57: =IFERROR($D57/E57-1,0) -> -0.1213223 | R57: =IFERROR($D57/F57-1,0) -> -0.065447888 | S57: =IFERROR($D57/G57-1,0) -> -0.17605035 | T57: =IFERROR($D57/H57-1,0) -> -0.17651796 | U57: =IFERROR($D57/I57-1,0) -> -0.40255176 | W57: {=INDIRECT("'"&$C$6&"'!"&ADDRESS(ROW(),COLUMN()+44))} -> 11355.885 | X57: {=INDIRECT("'"&$C$6&"'!"&ADDRESS(ROW(),COLUMN()+44))} -> 11183.872 | Y57: {=INDIRECT("'"&$C$6&"'!"&ADDRESS(ROW(),COLUMN()+44))} -> 9297.1553 | Z57: {=INDIRECT("'"&$C$6&"'!"&ADDRESS(ROW(),COLUMN()+44))} -> 12783.395 | AA57: {=INDIRECT("'"&$C$6&"'!"&ADDRESS(ROW(),COLUMN()+44))} -> 13381.307 | AB57: {=INDIRECT("'"&$C$6&"'!"&ADDRESS(ROW(),COLUMN()+44))} -> 13488.689 | AD57: =$W57-X57 -> 172.01262 | AE57: =$W57-Y57 -> 2058.7294 | AF57: =$W57-Z57 -> -1427.51 | AG57: =$W57-AA57 -> -2025.4227 | AH57: =$W57-AB57 -> -2132.8042 | AJ57: =IFERROR($W57/X57-1,0) -> 0.015380417 | AK57: =IFERROR($W57/Y57-1,0) -> 0.22143648 | AL57: =IFERROR($W57/Z57-1,0) -> -0.11166909 | AM57: =IFERROR($W57/AA57-1,0) -> -0.1513621 | AN57: =IFERROR($W57/AB57-1,0) -> -0.15811797
C58: Provisiones Netas | D58: =SUM(D56:D57) -> -10212.165 | E58: =SUM(E56:E57) -> -9618.3837 | F58: =SUM(F56:F57) -> -10857.131 | G58: =SUM(G56:G57) -> -9112.9864 | H58: =SUM(H56:H57) -> -7356.1089 | I58: =SUM(I56:I57) -> -5002.3235 | K58: =$D58-E58 -> -593.78176 | L58: =$D58-F58 -> 644.96556 | M58: =$D58-G58 -> -1099.179 | N58: =$D58-H58 -> -2856.0565 | O58: =$D58-I58 -> -5209.8419 | Q58: =IFERROR($D58/E58-1,0) -> 0.061734048 | R58: =IFERROR($D58/F58-1,0) -> -0.059404788 | S58: =IFERROR($D58/G58-1,0) -> 0.12061677 | T58: =IFERROR($D58/H58-1,0) -> 0.38825641 | U58: =IFERROR($D58/I58-1,0) -> 1.0414844 | W58: =SUM(W56:W57) -> -49267.727 | X58: =SUM(X56:X57) -> -52406.029 | Y58: =SUM(Y56:Y57) -> -39055.561 | Z58: =SUM(Z56:Z57) -> -42914.722 | AA58: =SUM(AA56:AA57) -> -43323.935 | AB58: =SUM(AB56:AB57) -> -25457.433 | AD58: =$W58-X58 -> 3138.3025 | AE58: =$W58-Y58 -> -10212.165 | AF58: =$W58-Z58 -> -6353.0046 | AG58: =$W58-AA58 -> -5943.7921 | AH58: =$W58-AB58 -> -23810.293 | AJ58: =IFERROR($W58/X58-1,0) -> -0.059884379 | AK58: =IFERROR($W58/Y58-1,0) -> 0.26147788 | AL58: =IFERROR($W58/Z58-1,0) -> 0.14803788 | AM58: =IFERROR($W58/AA58-1,0) -> 0.13719419 | AN58: =IFERROR($W58/AB58-1,0) -> 0.93529827
C60: Resultado Financiero Neto | D60: =D53+D58 -> 12625.931 | E60: =E53+E58 -> 14993.606 | F60: =F53+F58 -> 12742.169 | G60: =G53+G58 -> 12805.385 | H60: =H53+H58 -> 11212.27 | I60: =I53+I58 -> 13251.28 | K60: =$D60-E60 -> -2367.6742 | L60: =$D60-F60 -> -116.23766 | M60: =$D60-G60 -> -179.45404 | N60: =$D60-H60 -> 1413.6611 | O60: =$D60-I60 -> -625.34888 | Q60: =IFERROR($D60/E60-1,0) -> -0.15791226 | R60: =IFERROR($D60/F60-1,0) -> -0.0091222824 | S60: =IFERROR($D60/G60-1,0) -> -0.014013951 | T60: =IFERROR($D60/H60-1,0) -> 0.12608161 | U60: =IFERROR($D60/I60-1,0) -> -0.047191582 | W60: =W53+W58 -> 67347.435 | X60: =X53+X58 -> 72404.4 | Y60: =Y53+Y58 -> 54721.504 | Z60: =Z53+Z58 -> 65815.69 | AA60: =AA53+AA58 -> 49585.94 | AB60: =AB53+AB58 -> 74787.956 | AD60: =$W60-X60 -> -5056.9652 | AE60: =$W60-Y60 -> 12625.931 | AF60: =$W60-Z60 -> 1531.7455 | AG60: =$W60-AA60 -> 17761.495 | AH60: =$W60-AB60 -> -7440.5213 | AJ60: =IFERROR($W60/X60-1,0) -> -0.069843341 | AK60: =IFERROR($W60/Y60-1,0) -> 0.23073071 | AL60: =IFERROR($W60/Z60-1,0) -> 0.023273257 | AM60: =IFERROR($W60/AA60-1,0) -> 0.35819619 | AN60: =IFERROR($W60/AB60-1,0) -> -0.099488229
A63: INOF | C63: Seguro de Desgravamen | D63: {=_xlfn.XLOOKUP(1, (INDIRECT("'"&$C$6&"'!$6:$6")=D$6)* (INDIRECT("'"&$C$6&"'!$5:$5")=D$5), INDIRECT("'"&$C$6&"'!"&ROW()&":"&ROW()) )} -> 538.26567 | E63: {=_xlfn.XLOOKUP(1, (INDIRECT("'"&$C$6&"'!$6:$6")=E$6)* (INDIRECT("'"&$C$6&"'!$5:$5")=E$5), INDIRECT("'"&$C$6&"'!"&ROW()&":"&ROW()) )} -> 570.49 | F63: {=_xlfn.XLOOKUP(1, (INDIRECT("'"&$C$6&"'!$6:$6")=F$6)* (INDIRECT("'"&$C$6&"'!$5:$5")=F$5), INDIRECT("'"&$C$6&"'!"&ROW()&":"&ROW()) )} -> 531.33536 | G63: {=_xlfn.XLOOKUP(1, (INDIRECT("'"&$C$6&"'!$6:$6")=G$6)* (INDIRECT("'"&$C$6&"'!$5:$5")=G$5), INDIRECT("'"&$C$6&"'!"&ROW()&":"&ROW()) )} -> 522.19528 | H63: {=_xlfn.XLOOKUP(1, (INDIRECT("'"&$C$6&"'!$6:$6")=H$6)* (INDIRECT("'"&$C$6&"'!$5:$5")=H$5), INDIRECT("'"&$C$6&"'!"&ROW()&":"&ROW()) )} -> 553.83819 | I63: {=_xlfn.XLOOKUP(1, (INDIRECT("'"&$C$6&"'!$6:$6")=I$6)* (INDIRECT("'"&$C$6&"'!$5:$5")=I$5), INDIRECT("'"&$C$6&"'!"&ROW()&":"&ROW()) )} -> 493.20948 | K63: =$D63-E63 -> -32.22433 | L63: =$D63-F63 -> 6.93031 | M63: =$D63-G63 -> 16.07039 | N63: =$D63-H63 -> -15.57252 | O63: =$D63-I63 -> 45.05619 | Q63: =IFERROR($D63/E63-1,0) -> -0.056485355 | R63: =IFERROR($D63/F63-1,0) -> 0.013043194 | S63: =IFERROR($D63/G63-1,0) -> 0.030774675 | T63: =IFERROR($D63/H63-1,0) -> -0.028117454 | U63: =IFERROR($D63/I63-1,0) -> 0.091353049 | W63: {=INDIRECT("'"&$C$6&"'!"&ADDRESS(ROW(),COLUMN()+44))} -> 2657.0746 | X63: {=INDIRECT("'"&$C$6&"'!"&ADDRESS(ROW(),COLUMN()+44))} -> 2827.48 | Y63: {=INDIRECT("'"&$C$6&"'!"&ADDRESS(ROW(),COLUMN()+44))} -> 2118.8089 | Z63: {=INDIRECT("'"&$C$6&"'!"&ADDRESS(ROW(),COLUMN()+44))} -> 2731.0347 | AA63: {=INDIRECT("'"&$C$6&"'!"&ADDRESS(ROW(),COLUMN()+44))} -> 2840.5362 | AB63: {=INDIRECT("'"&$C$6&"'!"&ADDRESS(ROW(),COLUMN()+44))} -> 2496.751 | AD63: =$W63-X63 -> -170.40545 | AE63: =$W63-Y63 -> 538.26567 | AF63: =$W63-Z63 -> -73.96018 | AG63: =$W63-AA63 -> -183.46164 | AH63: =$W63-AB63 -> 160.32356 | AJ63: =IFERROR($W63/X63-1,0) -> -0.060267606 | AK63: =IFERROR($W63/Y63-1,0) -> 0.25404163 | AL63: =IFERROR($W63/Z63-1,0) -> -0.027081377 | AM63: =IFERROR($W63/AA63-1,0) -> -0.064586975 | AN63: =IFERROR($W63/AB63-1,0) -> 0.064212875
A64: INOF | C64: Comisiones | D64: {=_xlfn.XLOOKUP(1, (INDIRECT("'"&$C$6&"'!$6:$6")=D$6)* (INDIRECT("'"&$C$6&"'!$5:$5")=D$5), INDIRECT("'"&$C$6&"'!"&ROW()&":"&ROW()) )} -> 713.48595 | E64: {=_xlfn.XLOOKUP(1, (INDIRECT("'"&$C$6&"'!$6:$6")=E$6)* (INDIRECT("'"&$C$6&"'!$5:$5")=E$5), INDIRECT("'"&$C$6&"'!"&ROW()&":"&ROW()) )} -> 739.37663 | F64: {=_xlfn.XLOOKUP(1, (INDIRECT("'"&$C$6&"'!$6:$6")=F$6)* (INDIRECT("'"&$C$6&"'!$5:$5")=F$5), INDIRECT("'"&$C$6&"'!"&ROW()&":"&ROW()) )} -> 698.90254 | G64: {=_xlfn.XLOOKUP(1, (INDIRECT("'"&$C$6&"'!$6:$6")=G$6)* (INDIRECT("'"&$C$6&"'!$5:$5")=G$5), INDIRECT("'"&$C$6&"'!"&ROW()&":"&ROW()) )} -> 752.49437 | H64: {=_xlfn.XLOOKUP(1, (INDIRECT("'"&$C$6&"'!$6:$6")=H$6)* (INDIRECT("'"&$C$6&"'!$5:$5")=H$5), INDIRECT("'"&$C$6&"'!"&ROW()&":"&ROW()) )} -> 732.31599 | I64: {=_xlfn.XLOOKUP(1, (INDIRECT("'"&$C$6&"'!$6:$6")=I$6)* (INDIRECT("'"&$C$6&"'!$5:$5")=I$5), INDIRECT("'"&$C$6&"'!"&ROW()&":"&ROW()) )} -> 677.1092 | K64: =$D64-E64 -> -25.890684 | L64: =$D64-F64 -> 14.58341 | M64: =$D64-G64 -> -39.00842 | N64: =$D64-H64 -> -18.83004 | O64: =$D64-I64 -> 36.37675 | Q64: =IFERROR($D64/E64-1,0) -> -0.035016908 | R64: =IFERROR($D64/F64-1,0) -> 0.020866157 | S64: =IFERROR($D64/G64-1,0) -> -0.05183882 | T64: =IFERROR($D64/H64-1,0) -> -0.025712999 | U64: =IFERROR($D64/I64-1,0) -> 0.053723609 | W64: {=INDIRECT("'"&$C$6&"'!"&ADDRESS(ROW(),COLUMN()+44))} -> 3591.3921 | X64: {=INDIRECT("'"&$C$6&"'!"&ADDRESS(ROW(),COLUMN()+44))} -> 3734.3599 | Y64: {=INDIRECT("'"&$C$6&"'!"&ADDRESS(ROW(),COLUMN()+44))} -> 2877.9062 | Z64: {=INDIRECT("'"&$C$6&"'!"&ADDRESS(ROW(),COLUMN()+44))} -> 3823.0476 | AA64: {=INDIRECT("'"&$C$6&"'!"&ADDRESS(ROW(),COLUMN()+44))} -> 3590.1603 | AB64: {=INDIRECT("'"&$C$6&"'!"&ADDRESS(ROW(),COLUMN()+44))} -> 3403.2877 | AD64: =$W64-X64 -> -142.96775 | AE64: =$W64-Y64 -> 713.48595 | AF64: =$W64-Z64 -> -231.65543 | AG64: =$W64-AA64 -> 1.23189 | AH64: =$W64-AB64 -> 188.10446 | AJ64: =IFERROR($W64/X64-1,0) -> -0.038284406 | AK64: =IFERROR($W64/Y64-1,0) -> 0.24791842 | AL64: =IFERROR($W64/Z64-1,0) -> -0.060594441 | AM64: =IFERROR($W64/AA64-1,0) -> 0.00034312953 | AN64: =IFERROR($W64/AB64-1,0) -> 0.055271396
A65: INOF | C65: Gastos de casilleros | D65: {=_xlfn.XLOOKUP(1, (INDIRECT("'"&$C$6&"'!$6:$6")=D$6)* (INDIRECT("'"&$C$6&"'!$5:$5")=D$5), INDIRECT("'"&$C$6&"'!"&ROW()&":"&ROW()) )} -> -337.30522 | E65: {=_xlfn.XLOOKUP(1, (INDIRECT("'"&$C$6&"'!$6:$6")=E$6)* (INDIRECT("'"&$C$6&"'!$5:$5")=E$5), INDIRECT("'"&$C$6&"'!"&ROW()&":"&ROW()) )} -> -575 | F65: {=_xlfn.XLOOKUP(1, (INDIRECT("'"&$C$6&"'!$6:$6")=F$6)* (INDIRECT("'"&$C$6&"'!$5:$5")=F$5), INDIRECT("'"&$C$6&"'!"&ROW()&":"&ROW()) )} -> -8.17729 | G65: {=_xlfn.XLOOKUP(1, (INDIRECT("'"&$C$6&"'!$6:$6")=G$6)* (INDIRECT("'"&$C$6&"'!$5:$5")=G$5), INDIRECT("'"&$C$6&"'!"&ROW()&":"&ROW()) )} -> -205.42356 | H65: {=_xlfn.XLOOKUP(1, (INDIRECT("'"&$C$6&"'!$6:$6")=H$6)* (INDIRECT("'"&$C$6&"'!$5:$5")=H$5), INDIRECT("'"&$C$6&"'!"&ROW()&":"&ROW()) )} -> -788.67093 | I65: {=_xlfn.XLOOKUP(1, (INDIRECT("'"&$C$6&"'!$6:$6")=I$6)* (INDIRECT("'"&$C$6&"'!$5:$5")=I$5), INDIRECT("'"&$C$6&"'!"&ROW()&":"&ROW()) )} -> -576.71598 | K65: =$D65-E65 -> 237.69478 | L65: =$D65-F65 -> -329.12793 | M65: =$D65-G65 -> -131.88166 | N65: =$D65-H65 -> 451.36571 | O65: =$D65-I65 -> 239.41076 | Q65: =IFERROR($D65/E65-1,0) -> -0.41338223 | R65: =IFERROR($D65/F65-1,0) -> 40.249023 | S65: =IFERROR($D65/G65-1,0) -> 0.64199871 | T65: =IFERROR($D65/H65-1,0) -> -0.57231184 | U65: =IFERROR($D65/I65-1,0) -> -0.41512767 | W65: {=INDIRECT("'"&$C$6&"'!"&ADDRESS(ROW(),COLUMN()+44))} -> -1192.9396 | X65: {=INDIRECT("'"&$C$6&"'!"&ADDRESS(ROW(),COLUMN()+44))} -> -2236 | Y65: {=INDIRECT("'"&$C$6&"'!"&ADDRESS(ROW(),COLUMN()+44))} -> -855.63442 | Z65: {=INDIRECT("'"&$C$6&"'!"&ADDRESS(ROW(),COLUMN()+44))} -> -3385.5478 | AA65: {=INDIRECT("'"&$C$6&"'!"&ADDRESS(ROW(),COLUMN()+44))} -> -3527.4263 | AB65: {=INDIRECT("'"&$C$6&"'!"&ADDRESS(ROW(),COLUMN()+44))} -> -2700.6072 | AD65: =$W65-X65 -> 1043.0604 | AE65: =$W65-Y65 -> -337.30522 | AF65: =$W65-Z65 -> 2192.6081 | AG65: =$W65-AA65 -> 2334.4867 | AH65: =$W65-AB65 -> 1507.6676 | AJ65: =IFERROR($W65/X65-1,0) -> -0.46648496 | AK65: =IFERROR($W65/Y65-1,0) -> 0.39421652 | AL65: =IFERROR($W65/Z65-1,0) -> -0.64763763 | AM65: =IFERROR($W65/AA65-1,0) -> -0.66181019 | AN65: =IFERROR($W65/AB65-1,0) -> -0.55826984
A66: INOF | D66: {=_xlfn.XLOOKUP(1, (INDIRECT("'"&$C$6&"'!$6:$6")=D$6)* (INDIRECT("'"&$C$6&"'!$5:$5")=D$5), INDIRECT("'"&$C$6&"'!"&ROW()&":"&ROW()) )} -> 0 | E66: {=_xlfn.XLOOKUP(1, (INDIRECT("'"&$C$6&"'!$6:$6")=E$6)* (INDIRECT("'"&$C$6&"'!$5:$5")=E$5), INDIRECT("'"&$C$6&"'!"&ROW()&":"&ROW()) )} -> 0 | F66: {=_xlfn.XLOOKUP(1, (INDIRECT("'"&$C$6&"'!$6:$6")=F$6)* (INDIRECT("'"&$C$6&"'!$5:$5")=F$5), INDIRECT("'"&$C$6&"'!"&ROW()&":"&ROW()) )} -> 0 | G66: {=_xlfn.XLOOKUP(1, (INDIRECT("'"&$C$6&"'!$6:$6")=G$6)* (INDIRECT("'"&$C$6&"'!$5:$5")=G$5), INDIRECT("'"&$C$6&"'!"&ROW()&":"&ROW()) )} -> 0 | H66: {=_xlfn.XLOOKUP(1, (INDIRECT("'"&$C$6&"'!$6:$6")=H$6)* (INDIRECT("'"&$C$6&"'!$5:$5")=H$5), INDIRECT("'"&$C$6&"'!"&ROW()&":"&ROW()) )} -> 0 | I66: {=_xlfn.XLOOKUP(1, (INDIRECT("'"&$C$6&"'!$6:$6")=I$6)* (INDIRECT("'"&$C$6&"'!$5:$5")=I$5), INDIRECT("'"&$C$6&"'!"&ROW()&":"&ROW()) )} -> 0 | K66: =$D66-E66 -> 0 | L66: =$D66-F66 -> 0 | M66: =$D66-G66 -> 0 | N66: =$D66-H66 -> 0 | O66: =$D66-I66 -> 0 | Q66: =IFERROR($D66/E66-1,0) -> 0 | R66: =IFERROR($D66/F66-1,0) -> 0 | S66: =IFERROR($D66/G66-1,0) -> 0 | T66: =IFERROR($D66/H66-1,0) -> 0 | U66: =IFERROR($D66/I66-1,0) -> 0 | W66: {=INDIRECT("'"&$C$6&"'!"&ADDRESS(ROW(),COLUMN()+44))} -> 0 | X66: {=INDIRECT("'"&$C$6&"'!"&ADDRESS(ROW(),COLUMN()+44))} -> 0 | Y66: {=INDIRECT("'"&$C$6&"'!"&ADDRESS(ROW(),COLUMN()+44))} -> 0 | Z66: {=INDIRECT("'"&$C$6&"'!"&ADDRESS(ROW(),COLUMN()+44))} -> 0 | AA66: {=INDIRECT("'"&$C$6&"'!"&ADDRESS(ROW(),COLUMN()+44))} -> 0 | AB66: {=INDIRECT("'"&$C$6&"'!"&ADDRESS(ROW(),COLUMN()+44))} -> 0 | AD66: =$W66-X66 -> 0 | AE66: =$W66-Y66 -> 0 | AF66: =$W66-Z66 -> 0 | AG66: =$W66-AA66 -> 0 | AH66: =$W66-AB66 -> 0 | AJ66: =IFERROR($W66/X66-1,0) -> 0 | AK66: =IFERROR($W66/Y66-1,0) -> 0 | AL66: =IFERROR($W66/Z66-1,0) -> 0 | AM66: =IFERROR($W66/AA66-1,0) -> 0 | AN66: =IFERROR($W66/AB66-1,0) -> 0
A67: INOF | D67: {=_xlfn.XLOOKUP(1, (INDIRECT("'"&$C$6&"'!$6:$6")=D$6)* (INDIRECT("'"&$C$6&"'!$5:$5")=D$5), INDIRECT("'"&$C$6&"'!"&ROW()&":"&ROW()) )} -> 0 | E67: {=_xlfn.XLOOKUP(1, (INDIRECT("'"&$C$6&"'!$6:$6")=E$6)* (INDIRECT("'"&$C$6&"'!$5:$5")=E$5), INDIRECT("'"&$C$6&"'!"&ROW()&":"&ROW()) )} -> 0 | F67: {=_xlfn.XLOOKUP(1, (INDIRECT("'"&$C$6&"'!$6:$6")=F$6)* (INDIRECT("'"&$C$6&"'!$5:$5")=F$5), INDIRECT("'"&$C$6&"'!"&ROW()&":"&ROW()) )} -> 0 | G67: {=_xlfn.XLOOKUP(1, (INDIRECT("'"&$C$6&"'!$6:$6")=G$6)* (INDIRECT("'"&$C$6&"'!$5:$5")=G$5), INDIRECT("'"&$C$6&"'!"&ROW()&":"&ROW()) )} -> 0 | H67: {=_xlfn.XLOOKUP(1, (INDIRECT("'"&$C$6&"'!$6:$6")=H$6)* (INDIRECT("'"&$C$6&"'!$5:$5")=H$5), INDIRECT("'"&$C$6&"'!"&ROW()&":"&ROW()) )} -> 0 | I67: {=_xlfn.XLOOKUP(1, (INDIRECT("'"&$C$6&"'!$6:$6")=I$6)* (INDIRECT("'"&$C$6&"'!$5:$5")=I$5), INDIRECT("'"&$C$6&"'!"&ROW()&":"&ROW()) )} -> 0 | K67: =$D67-E67 -> 0 | L67: =$D67-F67 -> 0 | M67: =$D67-G67 -> 0 | N67: =$D67-H67 -> 0 | O67: =$D67-I67 -> 0 | Q67: =IFERROR($D67/E67-1,0) -> 0 | R67: =IFERROR($D67/F67-1,0) -> 0 | S67: =IFERROR($D67/G67-1,0) -> 0 | T67: =IFERROR($D67/H67-1,0) -> 0 | U67: =IFERROR($D67/I67-1,0) -> 0 | W67: {=INDIRECT("'"&$C$6&"'!"&ADDRESS(ROW(),COLUMN()+44))} -> 0 | X67: {=INDIRECT("'"&$C$6&"'!"&ADDRESS(ROW(),COLUMN()+44))} -> 0 | Y67: {=INDIRECT("'"&$C$6&"'!"&ADDRESS(ROW(),COLUMN()+44))} -> 0 | Z67: {=INDIRECT("'"&$C$6&"'!"&ADDRESS(ROW(),COLUMN()+44))} -> 0 | AA67: {=INDIRECT("'"&$C$6&"'!"&ADDRESS(ROW(),COLUMN()+44))} -> 0 | AB67: {=INDIRECT("'"&$C$6&"'!"&ADDRESS(ROW(),COLUMN()+44))} -> 0 | AD67: =$W67-X67 -> 0 | AE67: =$W67-Y67 -> 0 | AF67: =$W67-Z67 -> 0 | AG67: =$W67-AA67 -> 0 | AH67: =$W67-AB67 -> 0 | AJ67: =IFERROR($W67/X67-1,0) -> 0 | AK67: =IFERROR($W67/Y67-1,0) -> 0 | AL67: =IFERROR($W67/Z67-1,0) -> 0 | AM67: =IFERROR($W67/AA67-1,0) -> 0 | AN67: =IFERROR($W67/AB67-1,0) -> 0
A68: INOF | D68: {=_xlfn.XLOOKUP(1, (INDIRECT("'"&$C$6&"'!$6:$6")=D$6)* (INDIRECT("'"&$C$6&"'!$5:$5")=D$5), INDIRECT("'"&$C$6&"'!"&ROW()&":"&ROW()) )} -> 0 | E68: {=_xlfn.XLOOKUP(1, (INDIRECT("'"&$C$6&"'!$6:$6")=E$6)* (INDIRECT("'"&$C$6&"'!$5:$5")=E$5), INDIRECT("'"&$C$6&"'!"&ROW()&":"&ROW()) )} -> 0 | F68: {=_xlfn.XLOOKUP(1, (INDIRECT("'"&$C$6&"'!$6:$6")=F$6)* (INDIRECT("'"&$C$6&"'!$5:$5")=F$5), INDIRECT("'"&$C$6&"'!"&ROW()&":"&ROW()) )} -> 0 | G68: {=_xlfn.XLOOKUP(1, (INDIRECT("'"&$C$6&"'!$6:$6")=G$6)* (INDIRECT("'"&$C$6&"'!$5:$5")=G$5), INDIRECT("'"&$C$6&"'!"&ROW()&":"&ROW()) )} -> 0 | H68: {=_xlfn.XLOOKUP(1, (INDIRECT("'"&$C$6&"'!$6:$6")=H$6)* (INDIRECT("'"&$C$6&"'!$5:$5")=H$5), INDIRECT("'"&$C$6&"'!"&ROW()&":"&ROW()) )} -> 0 | I68: {=_xlfn.XLOOKUP(1, (INDIRECT("'"&$C$6&"'!$6:$6")=I$6)* (INDIRECT("'"&$C$6&"'!$5:$5")=I$5), INDIRECT("'"&$C$6&"'!"&ROW()&":"&ROW()) )} -> 0 | K68: =$D68-E68 -> 0 | L68: =$D68-F68 -> 0 | M68: =$D68-G68 -> 0 | N68: =$D68-H68 -> 0 | O68: =$D68-I68 -> 0 | Q68: =IFERROR($D68/E68-1,0) -> 0 | R68: =IFERROR($D68/F68-1,0) -> 0 | S68: =IFERROR($D68/G68-1,0) -> 0 | T68: =IFERROR($D68/H68-1,0) -> 0 | U68: =IFERROR($D68/I68-1,0) -> 0 | W68: {=INDIRECT("'"&$C$6&"'!"&ADDRESS(ROW(),COLUMN()+44))} -> 0 | X68: {=INDIRECT("'"&$C$6&"'!"&ADDRESS(ROW(),COLUMN()+44))} -> 0 | Y68: {=INDIRECT("'"&$C$6&"'!"&ADDRESS(ROW(),COLUMN()+44))} -> 0 | Z68: {=INDIRECT("'"&$C$6&"'!"&ADDRESS(ROW(),COLUMN()+44))} -> 0 | AA68: {=INDIRECT("'"&$C$6&"'!"&ADDRESS(ROW(),COLUMN()+44))} -> 0 | AB68: {=INDIRECT("'"&$C$6&"'!"&ADDRESS(ROW(),COLUMN()+44))} -> 0 | AD68: =$W68-X68 -> 0 | AE68: =$W68-Y68 -> 0 | AF68: =$W68-Z68 -> 0 | AG68: =$W68-AA68 -> 0 | AH68: =$W68-AB68 -> 0 | AJ68: =IFERROR($W68/X68-1,0) -> 0 | AK68: =IFERROR($W68/Y68-1,0) -> 0 | AL68: =IFERROR($W68/Z68-1,0) -> 0 | AM68: =IFERROR($W68/AA68-1,0) -> 0 | AN68: =IFERROR($W68/AB68-1,0) -> 0
A69: INOF | D69: {=_xlfn.XLOOKUP(1, (INDIRECT("'"&$C$6&"'!$6:$6")=D$6)* (INDIRECT("'"&$C$6&"'!$5:$5")=D$5), INDIRECT("'"&$C$6&"'!"&ROW()&":"&ROW()) )} -> 0 | E69: {=_xlfn.XLOOKUP(1, (INDIRECT("'"&$C$6&"'!$6:$6")=E$6)* (INDIRECT("'"&$C$6&"'!$5:$5")=E$5), INDIRECT("'"&$C$6&"'!"&ROW()&":"&ROW()) )} -> 0 | F69: {=_xlfn.XLOOKUP(1, (INDIRECT("'"&$C$6&"'!$6:$6")=F$6)* (INDIRECT("'"&$C$6&"'!$5:$5")=F$5), INDIRECT("'"&$C$6&"'!"&ROW()&":"&ROW()) )} -> 0 | G69: {=_xlfn.XLOOKUP(1, (INDIRECT("'"&$C$6&"'!$6:$6")=G$6)* (INDIRECT("'"&$C$6&"'!$5:$5")=G$5), INDIRECT("'"&$C$6&"'!"&ROW()&":"&ROW()) )} -> 0 | H69: {=_xlfn.XLOOKUP(1, (INDIRECT("'"&$C$6&"'!$6:$6")=H$6)* (INDIRECT("'"&$C$6&"'!$5:$5")=H$5), INDIRECT("'"&$C$6&"'!"&ROW()&":"&ROW()) )} -> 0 | I69: {=_xlfn.XLOOKUP(1, (INDIRECT("'"&$C$6&"'!$6:$6")=I$6)* (INDIRECT("'"&$C$6&"'!$5:$5")=I$5), INDIRECT("'"&$C$6&"'!"&ROW()&":"&ROW()) )} -> 0 | K69: =$D69-E69 -> 0 | L69: =$D69-F69 -> 0 | M69: =$D69-G69 -> 0 | N69: =$D69-H69 -> 0 | O69: =$D69-I69 -> 0 | Q69: =IFERROR($D69/E69-1,0) -> 0 | R69: =IFERROR($D69/F69-1,0) -> 0 | S69: =IFERROR($D69/G69-1,0) -> 0 | T69: =IFERROR($D69/H69-1,0) -> 0 | U69: =IFERROR($D69/I69-1,0) -> 0 | W69: {=INDIRECT("'"&$C$6&"'!"&ADDRESS(ROW(),COLUMN()+44))} -> 0 | X69: {=INDIRECT("'"&$C$6&"'!"&ADDRESS(ROW(),COLUMN()+44))} -> 0 | Y69: {=INDIRECT("'"&$C$6&"'!"&ADDRESS(ROW(),COLUMN()+44))} -> 0 | Z69: {=INDIRECT("'"&$C$6&"'!"&ADDRESS(ROW(),COLUMN()+44))} -> 0 | AA69: {=INDIRECT("'"&$C$6&"'!"&ADDRESS(ROW(),COLUMN()+44))} -> 0 | AB69: {=INDIRECT("'"&$C$6&"'!"&ADDRESS(ROW(),COLUMN()+44))} -> 0 | AD69: =$W69-X69 -> 0 | AE69: =$W69-Y69 -> 0 | AF69: =$W69-Z69 -> 0 | AG69: =$W69-AA69 -> 0 | AH69: =$W69-AB69 -> 0 | AJ69: =IFERROR($W69/X69-1,0) -> 0 | AK69: =IFERROR($W69/Y69-1,0) -> 0 | AL69: =IFERROR($W69/Z69-1,0) -> 0 | AM69: =IFERROR($W69/AA69-1,0) -> 0 | AN69: =IFERROR($W69/AB69-1,0) -> 0
A70: INOF | D70: {=_xlfn.XLOOKUP(1, (INDIRECT("'"&$C$6&"'!$6:$6")=D$6)* (INDIRECT("'"&$C$6&"'!$5:$5")=D$5), INDIRECT("'"&$C$6&"'!"&ROW()&":"&ROW()) )} -> 0 | E70: {=_xlfn.XLOOKUP(1, (INDIRECT("'"&$C$6&"'!$6:$6")=E$6)* (INDIRECT("'"&$C$6&"'!$5:$5")=E$5), INDIRECT("'"&$C$6&"'!"&ROW()&":"&ROW()) )} -> 0 | F70: {=_xlfn.XLOOKUP(1, (INDIRECT("'"&$C$6&"'!$6:$6")=F$6)* (INDIRECT("'"&$C$6&"'!$5:$5")=F$5), INDIRECT("'"&$C$6&"'!"&ROW()&":"&ROW()) )} -> 0 | G70: {=_xlfn.XLOOKUP(1, (INDIRECT("'"&$C$6&"'!$6:$6")=G$6)* (INDIRECT("'"&$C$6&"'!$5:$5")=G$5), INDIRECT("'"&$C$6&"'!"&ROW()&":"&ROW()) )} -> 0 | H70: {=_xlfn.XLOOKUP(1, (INDIRECT("'"&$C$6&"'!$6:$6")=H$6)* (INDIRECT("'"&$C$6&"'!$5:$5")=H$5), INDIRECT("'"&$C$6&"'!"&ROW()&":"&ROW()) )} -> 0 | I70: {=_xlfn.XLOOKUP(1, (INDIRECT("'"&$C$6&"'!$6:$6")=I$6)* (INDIRECT("'"&$C$6&"'!$5:$5")=I$5), INDIRECT("'"&$C$6&"'!"&ROW()&":"&ROW()) )} -> 0 | K70: =$D70-E70 -> 0 | L70: =$D70-F70 -> 0 | M70: =$D70-G70 -> 0 | N70: =$D70-H70 -> 0 | O70: =$D70-I70 -> 0 | Q70: =IFERROR($D70/E70-1,0) -> 0 | R70: =IFERROR($D70/F70-1,0) -> 0 | S70: =IFERROR($D70/G70-1,0) -> 0 | T70: =IFERROR($D70/H70-1,0) -> 0 | U70: =IFERROR($D70/I70-1,0) -> 0 | W70: {=INDIRECT("'"&$C$6&"'!"&ADDRESS(ROW(),COLUMN()+44))} -> 0 | X70: {=INDIRECT("'"&$C$6&"'!"&ADDRESS(ROW(),COLUMN()+44))} -> 0 | Y70: {=INDIRECT("'"&$C$6&"'!"&ADDRESS(ROW(),COLUMN()+44))} -> 0 | Z70: {=INDIRECT("'"&$C$6&"'!"&ADDRESS(ROW(),COLUMN()+44))} -> 0 | AA70: {=INDIRECT("'"&$C$6&"'!"&ADDRESS(ROW(),COLUMN()+44))} -> 0 | AB70: {=INDIRECT("'"&$C$6&"'!"&ADDRESS(ROW(),COLUMN()+44))} -> 0 | AD70: =$W70-X70 -> 0 | AE70: =$W70-Y70 -> 0 | AF70: =$W70-Z70 -> 0 | AG70: =$W70-AA70 -> 0 | AH70: =$W70-AB70 -> 0 | AJ70: =IFERROR($W70/X70-1,0) -> 0 | AK70: =IFERROR($W70/Y70-1,0) -> 0 | AL70: =IFERROR($W70/Z70-1,0) -> 0 | AM70: =IFERROR($W70/AA70-1,0) -> 0 | AN70: =IFERROR($W70/AB70-1,0) -> 0
A71: INOF | D71: {=_xlfn.XLOOKUP(1, (INDIRECT("'"&$C$6&"'!$6:$6")=D$6)* (INDIRECT("'"&$C$6&"'!$5:$5")=D$5), INDIRECT("'"&$C$6&"'!"&ROW()&":"&ROW()) )} -> 0 | E71: {=_xlfn.XLOOKUP(1, (INDIRECT("'"&$C$6&"'!$6:$6")=E$6)* (INDIRECT("'"&$C$6&"'!$5:$5")=E$5), INDIRECT("'"&$C$6&"'!"&ROW()&":"&ROW()) )} -> 0 | F71: {=_xlfn.XLOOKUP(1, (INDIRECT("'"&$C$6&"'!$6:$6")=F$6)* (INDIRECT("'"&$C$6&"'!$5:$5")=F$5), INDIRECT("'"&$C$6&"'!"&ROW()&":"&ROW()) )} -> 0 | G71: {=_xlfn.XLOOKUP(1, (INDIRECT("'"&$C$6&"'!$6:$6")=G$6)* (INDIRECT("'"&$C$6&"'!$5:$5")=G$5), INDIRECT("'"&$C$6&"'!"&ROW()&":"&ROW()) )} -> 0 | H71: {=_xlfn.XLOOKUP(1, (INDIRECT("'"&$C$6&"'!$6:$6")=H$6)* (INDIRECT("'"&$C$6&"'!$5:$5")=H$5), INDIRECT("'"&$C$6&"'!"&ROW()&":"&ROW()) )} -> 0 | I71: {=_xlfn.XLOOKUP(1, (INDIRECT("'"&$C$6&"'!$6:$6")=I$6)* (INDIRECT("'"&$C$6&"'!$5:$5")=I$5), INDIRECT("'"&$C$6&"'!"&ROW()&":"&ROW()) )} -> 0 | K71: =$D71-E71 -> 0 | L71: =$D71-F71 -> 0 | M71: =$D71-G71 -> 0 | N71: =$D71-H71 -> 0 | O71: =$D71-I71 -> 0 | Q71: =IFERROR($D71/E71-1,0) -> 0 | R71: =IFERROR($D71/F71-1,0) -> 0 | S71: =IFERROR($D71/G71-1,0) -> 0 | T71: =IFERROR($D71/H71-1,0) -> 0 | U71: =IFERROR($D71/I71-1,0) -> 0 | W71: {=INDIRECT("'"&$C$6&"'!"&ADDRESS(ROW(),COLUMN()+44))} -> 0 | X71: {=INDIRECT("'"&$C$6&"'!"&ADDRESS(ROW(),COLUMN()+44))} -> 0 | Y71: {=INDIRECT("'"&$C$6&"'!"&ADDRESS(ROW(),COLUMN()+44))} -> 0 | Z71: {=INDIRECT("'"&$C$6&"'!"&ADDRESS(ROW(),COLUMN()+44))} -> 0 | AA71: {=INDIRECT("'"&$C$6&"'!"&ADDRESS(ROW(),COLUMN()+44))} -> 0 | AB71: {=INDIRECT("'"&$C$6&"'!"&ADDRESS(ROW(),COLUMN()+44))} -> 0 | AD71: =$W71-X71 -> 0 | AE71: =$W71-Y71 -> 0 | AF71: =$W71-Z71 -> 0 | AG71: =$W71-AA71 -> 0 | AH71: =$W71-AB71 -> 0 | AJ71: =IFERROR($W71/X71-1,0) -> 0 | AK71: =IFERROR($W71/Y71-1,0) -> 0 | AL71: =IFERROR($W71/Z71-1,0) -> 0 | AM71: =IFERROR($W71/AA71-1,0) -> 0 | AN71: =IFERROR($W71/AB71-1,0) -> 0
A72: INOF | D72: {=_xlfn.XLOOKUP(1, (INDIRECT("'"&$C$6&"'!$6:$6")=D$6)* (INDIRECT("'"&$C$6&"'!$5:$5")=D$5), INDIRECT("'"&$C$6&"'!"&ROW()&":"&ROW()) )} -> 0 | E72: {=_xlfn.XLOOKUP(1, (INDIRECT("'"&$C$6&"'!$6:$6")=E$6)* (INDIRECT("'"&$C$6&"'!$5:$5")=E$5), INDIRECT("'"&$C$6&"'!"&ROW()&":"&ROW()) )} -> 0 | F72: {=_xlfn.XLOOKUP(1, (INDIRECT("'"&$C$6&"'!$6:$6")=F$6)* (INDIRECT("'"&$C$6&"'!$5:$5")=F$5), INDIRECT("'"&$C$6&"'!"&ROW()&":"&ROW()) )} -> 0 | G72: {=_xlfn.XLOOKUP(1, (INDIRECT("'"&$C$6&"'!$6:$6")=G$6)* (INDIRECT("'"&$C$6&"'!$5:$5")=G$5), INDIRECT("'"&$C$6&"'!"&ROW()&":"&ROW()) )} -> 0 | H72: {=_xlfn.XLOOKUP(1, (INDIRECT("'"&$C$6&"'!$6:$6")=H$6)* (INDIRECT("'"&$C$6&"'!$5:$5")=H$5), INDIRECT("'"&$C$6&"'!"&ROW()&":"&ROW()) )} -> 0 | I72: {=_xlfn.XLOOKUP(1, (INDIRECT("'"&$C$6&"'!$6:$6")=I$6)* (INDIRECT("'"&$C$6&"'!$5:$5")=I$5), INDIRECT("'"&$C$6&"'!"&ROW()&":"&ROW()) )} -> 0 | K72: =$D72-E72 -> 0 | L72: =$D72-F72 -> 0 | M72: =$D72-G72 -> 0 | N72: =$D72-H72 -> 0 | O72: =$D72-I72 -> 0 | Q72: =IFERROR($D72/E72-1,0) -> 0 | R72: =IFERROR($D72/F72-1,0) -> 0 | S72: =IFERROR($D72/G72-1,0) -> 0 | T72: =IFERROR($D72/H72-1,0) -> 0 | U72: =IFERROR($D72/I72-1,0) -> 0 | W72: {=INDIRECT("'"&$C$6&"'!"&ADDRESS(ROW(),COLUMN()+44))} -> 0 | X72: {=INDIRECT("'"&$C$6&"'!"&ADDRESS(ROW(),COLUMN()+44))} -> 0 | Y72: {=INDIRECT("'"&$C$6&"'!"&ADDRESS(ROW(),COLUMN()+44))} -> 0 | Z72: {=INDIRECT("'"&$C$6&"'!"&ADDRESS(ROW(),COLUMN()+44))} -> 0 | AA72: {=INDIRECT("'"&$C$6&"'!"&ADDRESS(ROW(),COLUMN()+44))} -> 0 | AB72: {=INDIRECT("'"&$C$6&"'!"&ADDRESS(ROW(),COLUMN()+44))} -> 0 | AD72: =$W72-X72 -> 0 | AE72: =$W72-Y72 -> 0 | AF72: =$W72-Z72 -> 0 | AG72: =$W72-AA72 -> 0 | AH72: =$W72-AB72 -> 0 | AJ72: =IFERROR($W72/X72-1,0) -> 0 | AK72: =IFERROR($W72/Y72-1,0) -> 0 | AL72: =IFERROR($W72/Z72-1,0) -> 0 | AM72: =IFERROR($W72/AA72-1,0) -> 0 | AN72: =IFERROR($W72/AB72-1,0) -> 0
A73: INOF | D73: {=_xlfn.XLOOKUP(1, (INDIRECT("'"&$C$6&"'!$6:$6")=D$6)* (INDIRECT("'"&$C$6&"'!$5:$5")=D$5), INDIRECT("'"&$C$6&"'!"&ROW()&":"&ROW()) )} -> 0 | E73: {=_xlfn.XLOOKUP(1, (INDIRECT("'"&$C$6&"'!$6:$6")=E$6)* (INDIRECT("'"&$C$6&"'!$5:$5")=E$5), INDIRECT("'"&$C$6&"'!"&ROW()&":"&ROW()) )} -> 0 | F73: {=_xlfn.XLOOKUP(1, (INDIRECT("'"&$C$6&"'!$6:$6")=F$6)* (INDIRECT("'"&$C$6&"'!$5:$5")=F$5), INDIRECT("'"&$C$6&"'!"&ROW()&":"&ROW()) )} -> 0 | G73: {=_xlfn.XLOOKUP(1, (INDIRECT("'"&$C$6&"'!$6:$6")=G$6)* (INDIRECT("'"&$C$6&"'!$5:$5")=G$5), INDIRECT("'"&$C$6&"'!"&ROW()&":"&ROW()) )} -> 0 | H73: {=_xlfn.XLOOKUP(1, (INDIRECT("'"&$C$6&"'!$6:$6")=H$6)* (INDIRECT("'"&$C$6&"'!$5:$5")=H$5), INDIRECT("'"&$C$6&"'!"&ROW()&":"&ROW()) )} -> 0 | I73: {=_xlfn.XLOOKUP(1, (INDIRECT("'"&$C$6&"'!$6:$6")=I$6)* (INDIRECT("'"&$C$6&"'!$5:$5")=I$5), INDIRECT("'"&$C$6&"'!"&ROW()&":"&ROW()) )} -> 0 | K73: =$D73-E73 -> 0 | L73: =$D73-F73 -> 0 | M73: =$D73-G73 -> 0 | N73: =$D73-H73 -> 0 | O73: =$D73-I73 -> 0 | Q73: =IFERROR($D73/E73-1,0) -> 0 | R73: =IFERROR($D73/F73-1,0) -> 0 | S73: =IFERROR($D73/G73-1,0) -> 0 | T73: =IFERROR($D73/H73-1,0) -> 0 | U73: =IFERROR($D73/I73-1,0) -> 0 | W73: {=INDIRECT("'"&$C$6&"'!"&ADDRESS(ROW(),COLUMN()+44))} -> 0 | X73: {=INDIRECT("'"&$C$6&"'!"&ADDRESS(ROW(),COLUMN()+44))} -> 0 | Y73: {=INDIRECT("'"&$C$6&"'!"&ADDRESS(ROW(),COLUMN()+44))} -> 0 | Z73: {=INDIRECT("'"&$C$6&"'!"&ADDRESS(ROW(),COLUMN()+44))} -> 0 | AA73: {=INDIRECT("'"&$C$6&"'!"&ADDRESS(ROW(),COLUMN()+44))} -> 0 | AB73: {=INDIRECT("'"&$C$6&"'!"&ADDRESS(ROW(),COLUMN()+44))} -> 0 | AD73: =$W73-X73 -> 0 | AE73: =$W73-Y73 -> 0 | AF73: =$W73-Z73 -> 0 | AG73: =$W73-AA73 -> 0 | AH73: =$W73-AB73 -> 0 | AJ73: =IFERROR($W73/X73-1,0) -> 0 | AK73: =IFERROR($W73/Y73-1,0) -> 0 | AL73: =IFERROR($W73/Z73-1,0) -> 0 | AM73: =IFERROR($W73/AA73-1,0) -> 0 | AN73: =IFERROR($W73/AB73-1,0) -> 0
A74: INOF | D74: {=_xlfn.XLOOKUP(1, (INDIRECT("'"&$C$6&"'!$6:$6")=D$6)* (INDIRECT("'"&$C$6&"'!$5:$5")=D$5), INDIRECT("'"&$C$6&"'!"&ROW()&":"&ROW()) )} -> 0 | E74: {=_xlfn.XLOOKUP(1, (INDIRECT("'"&$C$6&"'!$6:$6")=E$6)* (INDIRECT("'"&$C$6&"'!$5:$5")=E$5), INDIRECT("'"&$C$6&"'!"&ROW()&":"&ROW()) )} -> 0 | F74: {=_xlfn.XLOOKUP(1, (INDIRECT("'"&$C$6&"'!$6:$6")=F$6)* (INDIRECT("'"&$C$6&"'!$5:$5")=F$5), INDIRECT("'"&$C$6&"'!"&ROW()&":"&ROW()) )} -> 0 | G74: {=_xlfn.XLOOKUP(1, (INDIRECT("'"&$C$6&"'!$6:$6")=G$6)* (INDIRECT("'"&$C$6&"'!$5:$5")=G$5), INDIRECT("'"&$C$6&"'!"&ROW()&":"&ROW()) )} -> 0 | H74: {=_xlfn.XLOOKUP(1, (INDIRECT("'"&$C$6&"'!$6:$6")=H$6)* (INDIRECT("'"&$C$6&"'!$5:$5")=H$5), INDIRECT("'"&$C$6&"'!"&ROW()&":"&ROW()) )} -> 0 | I74: {=_xlfn.XLOOKUP(1, (INDIRECT("'"&$C$6&"'!$6:$6")=I$6)* (INDIRECT("'"&$C$6&"'!$5:$5")=I$5), INDIRECT("'"&$C$6&"'!"&ROW()&":"&ROW()) )} -> 0 | K74: =$D74-E74 -> 0 | L74: =$D74-F74 -> 0 | M74: =$D74-G74 -> 0 | N74: =$D74-H74 -> 0 | O74: =$D74-I74 -> 0 | Q74: =IFERROR($D74/E74-1,0) -> 0 | R74: =IFERROR($D74/F74-1,0) -> 0 | S74: =IFERROR($D74/G74-1,0) -> 0 | T74: =IFERROR($D74/H74-1,0) -> 0 | U74: =IFERROR($D74/I74-1,0) -> 0 | W74: {=INDIRECT("'"&$C$6&"'!"&ADDRESS(ROW(),COLUMN()+44))} -> 0 | X74: {=INDIRECT("'"&$C$6&"'!"&ADDRESS(ROW(),COLUMN()+44))} -> 0 | Y74: {=INDIRECT("'"&$C$6&"'!"&ADDRESS(ROW(),COLUMN()+44))} -> 0 | Z74: {=INDIRECT("'"&$C$6&"'!"&ADDRESS(ROW(),COLUMN()+44))} -> 0 | AA74: {=INDIRECT("'"&$C$6&"'!"&ADDRESS(ROW(),COLUMN()+44))} -> 0 | AB74: {=INDIRECT("'"&$C$6&"'!"&ADDRESS(ROW(),COLUMN()+44))} -> 0 | AD74: =$W74-X74 -> 0 | AE74: =$W74-Y74 -> 0 | AF74: =$W74-Z74 -> 0 | AG74: =$W74-AA74 -> 0 | AH74: =$W74-AB74 -> 0 | AJ74: =IFERROR($W74/X74-1,0) -> 0 | AK74: =IFERROR($W74/Y74-1,0) -> 0 | AL74: =IFERROR($W74/Z74-1,0) -> 0 | AM74: =IFERROR($W74/AA74-1,0) -> 0 | AN74: =IFERROR($W74/AB74-1,0) -> 0
A75: INOF | D75: {=_xlfn.XLOOKUP(1, (INDIRECT("'"&$C$6&"'!$6:$6")=D$6)* (INDIRECT("'"&$C$6&"'!$5:$5")=D$5), INDIRECT("'"&$C$6&"'!"&ROW()&":"&ROW()) )} -> 0 | E75: {=_xlfn.XLOOKUP(1, (INDIRECT("'"&$C$6&"'!$6:$6")=E$6)* (INDIRECT("'"&$C$6&"'!$5:$5")=E$5), INDIRECT("'"&$C$6&"'!"&ROW()&":"&ROW()) )} -> 0 | F75: {=_xlfn.XLOOKUP(1, (INDIRECT("'"&$C$6&"'!$6:$6")=F$6)* (INDIRECT("'"&$C$6&"'!$5:$5")=F$5), INDIRECT("'"&$C$6&"'!"&ROW()&":"&ROW()) )} -> 0 | G75: {=_xlfn.XLOOKUP(1, (INDIRECT("'"&$C$6&"'!$6:$6")=G$6)* (INDIRECT("'"&$C$6&"'!$5:$5")=G$5), INDIRECT("'"&$C$6&"'!"&ROW()&":"&ROW()) )} -> 0 | H75: {=_xlfn.XLOOKUP(1, (INDIRECT("'"&$C$6&"'!$6:$6")=H$6)* (INDIRECT("'"&$C$6&"'!$5:$5")=H$5), INDIRECT("'"&$C$6&"'!"&ROW()&":"&ROW()) )} -> 0 | I75: {=_xlfn.XLOOKUP(1, (INDIRECT("'"&$C$6&"'!$6:$6")=I$6)* (INDIRECT("'"&$C$6&"'!$5:$5")=I$5), INDIRECT("'"&$C$6&"'!"&ROW()&":"&ROW()) )} -> 0 | K75: =$D75-E75 -> 0 | L75: =$D75-F75 -> 0 | M75: =$D75-G75 -> 0 | N75: =$D75-H75 -> 0 | O75: =$D75-I75 -> 0 | Q75: =IFERROR($D75/E75-1,0) -> 0 | R75: =IFERROR($D75/F75-1,0) -> 0 | S75: =IFERROR($D75/G75-1,0) -> 0 | T75: =IFERROR($D75/H75-1,0) -> 0 | U75: =IFERROR($D75/I75-1,0) -> 0 | W75: {=INDIRECT("'"&$C$6&"'!"&ADDRESS(ROW(),COLUMN()+44))} -> 0 | X75: {=INDIRECT("'"&$C$6&"'!"&ADDRESS(ROW(),COLUMN()+44))} -> 0 | Y75: {=INDIRECT("'"&$C$6&"'!"&ADDRESS(ROW(),COLUMN()+44))} -> 0 | Z75: {=INDIRECT("'"&$C$6&"'!"&ADDRESS(ROW(),COLUMN()+44))} -> 0 | AA75: {=INDIRECT("'"&$C$6&"'!"&ADDRESS(ROW(),COLUMN()+44))} -> 0 | AB75: {=INDIRECT("'"&$C$6&"'!"&ADDRESS(ROW(),COLUMN()+44))} -> 0 | AD75: =$W75-X75 -> 0 | AE75: =$W75-Y75 -> 0 | AF75: =$W75-Z75 -> 0 | AG75: =$W75-AA75 -> 0 | AH75: =$W75-AB75 -> 0 | AJ75: =IFERROR($W75/X75-1,0) -> 0 | AK75: =IFERROR($W75/Y75-1,0) -> 0 | AL75: =IFERROR($W75/Z75-1,0) -> 0 | AM75: =IFERROR($W75/AA75-1,0) -> 0 | AN75: =IFERROR($W75/AB75-1,0) -> 0
A76: INOF | D76: {=_xlfn.XLOOKUP(1, (INDIRECT("'"&$C$6&"'!$6:$6")=D$6)* (INDIRECT("'"&$C$6&"'!$5:$5")=D$5), INDIRECT("'"&$C$6&"'!"&ROW()&":"&ROW()) )} -> 0 | E76: {=_xlfn.XLOOKUP(1, (INDIRECT("'"&$C$6&"'!$6:$6")=E$6)* (INDIRECT("'"&$C$6&"'!$5:$5")=E$5), INDIRECT("'"&$C$6&"'!"&ROW()&":"&ROW()) )} -> 0 | F76: {=_xlfn.XLOOKUP(1, (INDIRECT("'"&$C$6&"'!$6:$6")=F$6)* (INDIRECT("'"&$C$6&"'!$5:$5")=F$5), INDIRECT("'"&$C$6&"'!"&ROW()&":"&ROW()) )} -> 0 | G76: {=_xlfn.XLOOKUP(1, (INDIRECT("'"&$C$6&"'!$6:$6")=G$6)* (INDIRECT("'"&$C$6&"'!$5:$5")=G$5), INDIRECT("'"&$C$6&"'!"&ROW()&":"&ROW()) )} -> 0 | H76: {=_xlfn.XLOOKUP(1, (INDIRECT("'"&$C$6&"'!$6:$6")=H$6)* (INDIRECT("'"&$C$6&"'!$5:$5")=H$5), INDIRECT("'"&$C$6&"'!"&ROW()&":"&ROW()) )} -> 0 | I76: {=_xlfn.XLOOKUP(1, (INDIRECT("'"&$C$6&"'!$6:$6")=I$6)* (INDIRECT("'"&$C$6&"'!$5:$5")=I$5), INDIRECT("'"&$C$6&"'!"&ROW()&":"&ROW()) )} -> 0 | K76: =$D76-E76 -> 0 | L76: =$D76-F76 -> 0 | M76: =$D76-G76 -> 0 | N76: =$D76-H76 -> 0 | O76: =$D76-I76 -> 0 | Q76: =IFERROR($D76/E76-1,0) -> 0 | R76: =IFERROR($D76/F76-1,0) -> 0 | S76: =IFERROR($D76/G76-1,0) -> 0 | T76: =IFERROR($D76/H76-1,0) -> 0 | U76: =IFERROR($D76/I76-1,0) -> 0 | W76: {=INDIRECT("'"&$C$6&"'!"&ADDRESS(ROW(),COLUMN()+44))} -> 0 | X76: {=INDIRECT("'"&$C$6&"'!"&ADDRESS(ROW(),COLUMN()+44))} -> 0 | Y76: {=INDIRECT("'"&$C$6&"'!"&ADDRESS(ROW(),COLUMN()+44))} -> 0 | Z76: {=INDIRECT("'"&$C$6&"'!"&ADDRESS(ROW(),COLUMN()+44))} -> 0 | AA76: {=INDIRECT("'"&$C$6&"'!"&ADDRESS(ROW(),COLUMN()+44))} -> 0 | AB76: {=INDIRECT("'"&$C$6&"'!"&ADDRESS(ROW(),COLUMN()+44))} -> 0 | AD76: =$W76-X76 -> 0 | AE76: =$W76-Y76 -> 0 | AF76: =$W76-Z76 -> 0 | AG76: =$W76-AA76 -> 0 | AH76: =$W76-AB76 -> 0 | AJ76: =IFERROR($W76/X76-1,0) -> 0 | AK76: =IFERROR($W76/Y76-1,0) -> 0 | AL76: =IFERROR($W76/Z76-1,0) -> 0 | AM76: =IFERROR($W76/AA76-1,0) -> 0 | AN76: =IFERROR($W76/AB76-1,0) -> 0
A77: INOF | D77: {=_xlfn.XLOOKUP(1, (INDIRECT("'"&$C$6&"'!$6:$6")=D$6)* (INDIRECT("'"&$C$6&"'!$5:$5")=D$5), INDIRECT("'"&$C$6&"'!"&ROW()&":"&ROW()) )} -> 0 | E77: {=_xlfn.XLOOKUP(1, (INDIRECT("'"&$C$6&"'!$6:$6")=E$6)* (INDIRECT("'"&$C$6&"'!$5:$5")=E$5), INDIRECT("'"&$C$6&"'!"&ROW()&":"&ROW()) )} -> 0 | F77: {=_xlfn.XLOOKUP(1, (INDIRECT("'"&$C$6&"'!$6:$6")=F$6)* (INDIRECT("'"&$C$6&"'!$5:$5")=F$5), INDIRECT("'"&$C$6&"'!"&ROW()&":"&ROW()) )} -> 0 | G77: {=_xlfn.XLOOKUP(1, (INDIRECT("'"&$C$6&"'!$6:$6")=G$6)* (INDIRECT("'"&$C$6&"'!$5:$5")=G$5), INDIRECT("'"&$C$6&"'!"&ROW()&":"&ROW()) )} -> 0 | H77: {=_xlfn.XLOOKUP(1, (INDIRECT("'"&$C$6&"'!$6:$6")=H$6)* (INDIRECT("'"&$C$6&"'!$5:$5")=H$5), INDIRECT("'"&$C$6&"'!"&ROW()&":"&ROW()) )} -> 0 | I77: {=_xlfn.XLOOKUP(1, (INDIRECT("'"&$C$6&"'!$6:$6")=I$6)* (INDIRECT("'"&$C$6&"'!$5:$5")=I$5), INDIRECT("'"&$C$6&"'!"&ROW()&":"&ROW()) )} -> 0 | K77: =$D77-E77 -> 0 | L77: =$D77-F77 -> 0 | M77: =$D77-G77 -> 0 | N77: =$D77-H77 -> 0 | O77: =$D77-I77 -> 0 | Q77: =IFERROR($D77/E77-1,0) -> 0 | R77: =IFERROR($D77/F77-1,0) -> 0 | S77: =IFERROR($D77/G77-1,0) -> 0 | T77: =IFERROR($D77/H77-1,0) -> 0 | U77: =IFERROR($D77/I77-1,0) -> 0 | W77: {=INDIRECT("'"&$C$6&"'!"&ADDRESS(ROW(),COLUMN()+44))} -> 0 | X77: {=INDIRECT("'"&$C$6&"'!"&ADDRESS(ROW(),COLUMN()+44))} -> 0 | Y77: {=INDIRECT("'"&$C$6&"'!"&ADDRESS(ROW(),COLUMN()+44))} -> 0 | Z77: {=INDIRECT("'"&$C$6&"'!"&ADDRESS(ROW(),COLUMN()+44))} -> 0 | AA77: {=INDIRECT("'"&$C$6&"'!"&ADDRESS(ROW(),COLUMN()+44))} -> 0 | AB77: {=INDIRECT("'"&$C$6&"'!"&ADDRESS(ROW(),COLUMN()+44))} -> 0 | AD77: =$W77-X77 -> 0 | AE77: =$W77-Y77 -> 0 | AF77: =$W77-Z77 -> 0 | AG77: =$W77-AA77 -> 0 | AH77: =$W77-AB77 -> 0 | AJ77: =IFERROR($W77/X77-1,0) -> 0 | AK77: =IFERROR($W77/Y77-1,0) -> 0 | AL77: =IFERROR($W77/Z77-1,0) -> 0 | AM77: =IFERROR($W77/AA77-1,0) -> 0 | AN77: =IFERROR($W77/AB77-1,0) -> 0
... A82: INOF | D82: {=_xlfn.XLOOKUP(1, (INDIRECT("'"&$C$6&"'!$6:$6")=D$6)* (INDIRECT("'"&$C$6&"'!$5:$5")=D$5), INDIRECT("'"&$C$6&"'!"&ROW()&":"&ROW()) )} -> 0 | E82: {=_xlfn.XLOOKUP(1, (INDIRECT("'"&$C$6&"'!$6:$6")=E$6)* (INDIRECT("'"&$C$6&"'!$5:$5")=E$5), INDIRECT("'"&$C$6&"'!"&ROW()&":"&ROW()) )} -> 0 | F82: {=_xlfn.XLOOKUP(1, (INDIRECT("'"&$C$6&"'!$6:$6")=F$6)* (INDIRECT("'"&$C$6&"'!$5:$5")=F$5), INDIRECT("'"&$C$6&"'!"&ROW()&":"&ROW()) )} -> 0 | G82: {=_xlfn.XLOOKUP(1, (INDIRECT("'"&$C$6&"'!$6:$6")=G$6)* (INDIRECT("'"&$C$6&"'!$5:$5")=G$5), INDIRECT("'"&$C$6&"'!"&ROW()&":"&ROW()) )} -> 0 | H82: {=_xlfn.XLOOKUP(1, (INDIRECT("'"&$C$6&"'!$6:$6")=H$6)* (INDIRECT("'"&$C$6&"'!$5:$5")=H$5), INDIRECT("'"&$C$6&"'!"&ROW()&":"&ROW()) )} -> 0 | I82: {=_xlfn.XLOOKUP(1, (INDIRECT("'"&$C$6&"'!$6:$6")=I$6)* (INDIRECT("'"&$C$6&"'!$5:$5")=I$5), INDIRECT("'"&$C$6&"'!"&ROW()&":"&ROW()) )} -> 0 | K82: =$D82-E82 -> 0 | L82: =$D82-F82 -> 0 | M82: =$D82-G82 -> 0 | N82: =$D82-H82 -> 0 | O82: =$D82-I82 -> 0 | Q82: =IFERROR($D82/E82-1,0) -> 0 | R82: =IFERROR($D82/F82-1,0) -> 0 | S82: =IFERROR($D82/G82-1,0) -> 0 | T82: =IFERROR($D82/H82-1,0) -> 0 | U82: =IFERROR($D82/I82-1,0) -> 0 | W82: {=INDIRECT("'"&$C$6&"'!"&ADDRESS(ROW(),COLUMN()+44))} -> 0 | X82: {=INDIRECT("'"&$C$6&"'!"&ADDRESS(ROW(),COLUMN()+44))} -> 0 | Y82: {=INDIRECT("'"&$C$6&"'!"&ADDRESS(ROW(),COLUMN()+44))} -> 0 | Z82: {=INDIRECT("'"&$C$6&"'!"&ADDRESS(ROW(),COLUMN()+44))} -> 0 | AA82: {=INDIRECT("'"&$C$6&"'!"&ADDRESS(ROW(),COLUMN()+44))} -> 0 | AB82: {=INDIRECT("'"&$C$6&"'!"&ADDRESS(ROW(),COLUMN()+44))} -> 0 | AD82: =$W82-X82 -> 0 | AE82: =$W82-Y82 -> 0 | AF82: =$W82-Z82 -> 0 | AG82: =$W82-AA82 -> 0 | AH82: =$W82-AB82 -> 0 | AJ82: =IFERROR($W82/X82-1,0) -> 0 | AK82: =IFERROR($W82/Y82-1,0) -> 0 | AL82: =IFERROR($W82/Z82-1,0) -> 0 | AM82: =IFERROR($W82/AA82-1,0) -> 0 | AN82: =IFERROR($W82/AB82-1,0) -> 0
C83: INOF | D83: =SUM(D63:D82) -> 914.4464 | E83: =SUM(E63:E82) -> 734.86663 | F83: =SUM(F63:F82) -> 1222.0606 | G83: =SUM(G63:G82) -> 1069.2661 | H83: =SUM(H63:H82) -> 497.48325 | I83: =SUM(I63:I82) -> 593.6027 | K83: =$D83-E83 -> 179.57977 | L83: =$D83-F83 -> -307.61421 | M83: =$D83-G83 -> -154.81969 | N83: =$D83-H83 -> 416.96315 | O83: =$D83-I83 -> 320.8437 | Q83: =IFERROR($D83/E83-1,0) -> 0.24437055 | R83: =IFERROR($D83/F83-1,0) -> -0.25171764 | S83: =IFERROR($D83/G83-1,0) -> -0.14479061 | T83: =IFERROR($D83/H83-1,0) -> 0.8381451 | U83: =IFERROR($D83/I83-1,0) -> 0.54050243 | W83: =SUM(W63:W82) -> 5055.5271 | X83: =SUM(X63:X82) -> 4325.8399 | Y83: =SUM(Y63:Y82) -> 4141.0807 | Z83: =SUM(Z63:Z82) -> 3168.5345 | AA83: =SUM(AA63:AA82) -> 2903.2701 | AB83: =SUM(AB63:AB82) -> 3199.4315 | AD83: =$W83-X83 -> 729.68716 | AE83: =$W83-Y83 -> 914.4464 | AF83: =$W83-Z83 -> 1886.9925 | AG83: =$W83-AA83 -> 2152.2569 | AH83: =$W83-AB83 -> 1856.0956 | AJ83: =IFERROR($W83/X83-1,0) -> 0.16868104 | AK83: =IFERROR($W83/Y83-1,0) -> 0.22082313 | AL83: =IFERROR($W83/Z83-1,0) -> 0.5955411 | AM83: =IFERROR($W83/AA83-1,0) -> 0.74132162 | AN83: =IFERROR($W83/AB83-1,0) -> 0.58013293
A86: Gastos Operativos | C86: Gasto Directo | D86: {=_xlfn.XLOOKUP(1, (INDIRECT("'"&$C$6&"'!$6:$6")=D$6)* (INDIRECT("'"&$C$6&"'!$5:$5")=D$5), INDIRECT("'"&$C$6&"'!"&ROW()&":"&ROW()) )} -> -5887.2055 | E86: {=_xlfn.XLOOKUP(1, (INDIRECT("'"&$C$6&"'!$6:$6")=E$6)* (INDIRECT("'"&$C$6&"'!$5:$5")=E$5), INDIRECT("'"&$C$6&"'!"&ROW()&":"&ROW()) )} -> -5189.8369 | F86: {=_xlfn.XLOOKUP(1, (INDIRECT("'"&$C$6&"'!$6:$6")=F$6)* (INDIRECT("'"&$C$6&"'!$5:$5")=F$5), INDIRECT("'"&$C$6&"'!"&ROW()&":"&ROW()) )} -> -5070.3116 | G86: {=_xlfn.XLOOKUP(1, (INDIRECT("'"&$C$6&"'!$6:$6")=G$6)* (INDIRECT("'"&$C$6&"'!$5:$5")=G$5), INDIRECT("'"&$C$6&"'!"&ROW()&":"&ROW()) )} -> -5118.639 | H86: {=_xlfn.XLOOKUP(1, (INDIRECT("'"&$C$6&"'!$6:$6")=H$6)* (INDIRECT("'"&$C$6&"'!$5:$5")=H$5), INDIRECT("'"&$C$6&"'!"&ROW()&":"&ROW()) )} -> -4658.469 | I86: {=_xlfn.XLOOKUP(1, (INDIRECT("'"&$C$6&"'!$6:$6")=I$6)* (INDIRECT("'"&$C$6&"'!$5:$5")=I$5), INDIRECT("'"&$C$6&"'!"&ROW()&":"&ROW()) )} -> -4543.2276 | K86: =$D86-E86 -> -697.36856 | L86: =$D86-F86 -> -816.89381 | M86: =$D86-G86 -> -768.56647 | N86: =$D86-H86 -> -1228.7365 | O86: =$D86-I86 -> -1343.9779 | Q86: =IFERROR($D86/E86-1,0) -> 0.13437196 | R86: =IFERROR($D86/F86-1,0) -> 0.16111314 | S86: =IFERROR($D86/G86-1,0) -> 0.15015055 | T86: =IFERROR($D86/H86-1,0) -> 0.26376402 | U86: =IFERROR($D86/I86-1,0) -> 0.29582006 | W86: {=INDIRECT("'"&$C$6&"'!"&ADDRESS(ROW(),COLUMN()+44))} -> -26026.556 | X86: {=INDIRECT("'"&$C$6&"'!"&ADDRESS(ROW(),COLUMN()+44))} -> -25098.612 | Y86: {=INDIRECT("'"&$C$6&"'!"&ADDRESS(ROW(),COLUMN()+44))} -> -20139.35 | Z86: {=INDIRECT("'"&$C$6&"'!"&ADDRESS(ROW(),COLUMN()+44))} -> -24124.101 | AA86: {=INDIRECT("'"&$C$6&"'!"&ADDRESS(ROW(),COLUMN()+44))} -> -21998.807 | AB86: {=INDIRECT("'"&$C$6&"'!"&ADDRESS(ROW(),COLUMN()+44))} -> -24291.622 | AD86: =$W86-X86 -> -927.94362 | AE86: =$W86-Y86 -> -5887.2055 | AF86: =$W86-Z86 -> -1902.4544 | AG86: =$W86-AA86 -> -4027.7482 | AH86: =$W86-AB86 -> -1734.9334 | AJ86: =IFERROR($W86/X86-1,0) -> 0.03697191 | AK86: =IFERROR($W86/Y86-1,0) -> 0.29232351 | AL86: =IFERROR($W86/Z86-1,0) -> 0.078861152 | AM86: =IFERROR($W86/AA86-1,0) -> 0.18308939 | AN86: =IFERROR($W86/AB86-1,0) -> 0.071421061
A87: Gastos Operativos | C87: Gasto Canal | D87: {=_xlfn.XLOOKUP(1, (INDIRECT("'"&$C$6&"'!$6:$6")=D$6)* (INDIRECT("'"&$C$6&"'!$5:$5")=D$5), INDIRECT("'"&$C$6&"'!"&ROW()&":"&ROW()) )} -> -296.93512 | E87: {=_xlfn.XLOOKUP(1, (INDIRECT("'"&$C$6&"'!$6:$6")=E$6)* (INDIRECT("'"&$C$6&"'!$5:$5")=E$5), INDIRECT("'"&$C$6&"'!"&ROW()&":"&ROW()) )} -> -374.04956 | F87: {=_xlfn.XLOOKUP(1, (INDIRECT("'"&$C$6&"'!$6:$6")=F$6)* (INDIRECT("'"&$C$6&"'!$5:$5")=F$5), INDIRECT("'"&$C$6&"'!"&ROW()&":"&ROW()) )} -> -297.51289 | G87: {=_xlfn.XLOOKUP(1, (INDIRECT("'"&$C$6&"'!$6:$6")=G$6)* (INDIRECT("'"&$C$6&"'!$5:$5")=G$5), INDIRECT("'"&$C$6&"'!"&ROW()&":"&ROW()) )} -> -333.1908 | H87: {=_xlfn.XLOOKUP(1, (INDIRECT("'"&$C$6&"'!$6:$6")=H$6)* (INDIRECT("'"&$C$6&"'!$5:$5")=H$5), INDIRECT("'"&$C$6&"'!"&ROW()&":"&ROW()) )} -> -362.4659 | I87: {=_xlfn.XLOOKUP(1, (INDIRECT("'"&$C$6&"'!$6:$6")=I$6)* (INDIRECT("'"&$C$6&"'!$5:$5")=I$5), INDIRECT("'"&$C$6&"'!"&ROW()&":"&ROW()) )} -> -295.87897 | K87: =$D87-E87 -> 77.114433 | L87: =$D87-F87 -> 0.57776482 | M87: =$D87-G87 -> 36.255673 | N87: =$D87-H87 -> 65.530777 | O87: =$D87-I87 -> -1.0561553 | Q87: =IFERROR($D87/E87-1,0) -> -0.20616101 | R87: =IFERROR($D87/F87-1,0) -> -0.0019419825 | S87: =IFERROR($D87/G87-1,0) -> -0.10881355 | T87: =IFERROR($D87/H87-1,0) -> -0.18079156 | U87: =IFERROR($D87/I87-1,0) -> 0.0035695519 | W87: {=INDIRECT("'"&$C$6&"'!"&ADDRESS(ROW(),COLUMN()+44))} -> -1435.2993 | X87: {=INDIRECT("'"&$C$6&"'!"&ADDRESS(ROW(),COLUMN()+44))} -> -1838.6822 | Y87: {=INDIRECT("'"&$C$6&"'!"&ADDRESS(ROW(),COLUMN()+44))} -> -1138.3641 | Z87: {=INDIRECT("'"&$C$6&"'!"&ADDRESS(ROW(),COLUMN()+44))} -> -1618.3422 | AA87: {=INDIRECT("'"&$C$6&"'!"&ADDRESS(ROW(),COLUMN()+44))} -> -1850.4812 | AB87: {=INDIRECT("'"&$C$6&"'!"&ADDRESS(ROW(),COLUMN()+44))} -> -1431.5168 | AD87: =$W87-X87 -> 403.38289 | AE87: =$W87-Y87 -> -296.93512 | AF87: =$W87-Z87 -> 183.04297 | AG87: =$W87-AA87 -> 415.18191 | AH87: =$W87-AB87 -> -3.7824639 | AJ87: =IFERROR($W87/X87-1,0) -> -0.21938696 | AK87: =IFERROR($W87/Y87-1,0) -> 0.26084371 | AL87: =IFERROR($W87/Z87-1,0) -> -0.11310523 | AM87: =IFERROR($W87/AA87-1,0) -> -0.2243643 | AN87: =IFERROR($W87/AB87-1,0) -> 0.0026422769
A88: Gastos Operativos | C88: Gasto Indirecto | D88: {=_xlfn.XLOOKUP(1, (INDIRECT("'"&$C$6&"'!$6:$6")=D$6)* (INDIRECT("'"&$C$6&"'!$5:$5")=D$5), INDIRECT("'"&$C$6&"'!"&ROW()&":"&ROW()) )} -> -2296.5995 | E88: {=_xlfn.XLOOKUP(1, (INDIRECT("'"&$C$6&"'!$6:$6")=E$6)* (INDIRECT("'"&$C$6&"'!$5:$5")=E$5), INDIRECT("'"&$C$6&"'!"&ROW()&":"&ROW()) )} -> -2282.278 | F88: {=_xlfn.XLOOKUP(1, (INDIRECT("'"&$C$6&"'!$6:$6")=F$6)* (INDIRECT("'"&$C$6&"'!$5:$5")=F$5), INDIRECT("'"&$C$6&"'!"&ROW()&":"&ROW()) )} -> -2533.4182 | G88: {=_xlfn.XLOOKUP(1, (INDIRECT("'"&$C$6&"'!$6:$6")=G$6)* (INDIRECT("'"&$C$6&"'!$5:$5")=G$5), INDIRECT("'"&$C$6&"'!"&ROW()&":"&ROW()) )} -> -2223.5883 | H88: {=_xlfn.XLOOKUP(1, (INDIRECT("'"&$C$6&"'!$6:$6")=H$6)* (INDIRECT("'"&$C$6&"'!$5:$5")=H$5), INDIRECT("'"&$C$6&"'!"&ROW()&":"&ROW()) )} -> -2085.0672 | I88: {=_xlfn.XLOOKUP(1, (INDIRECT("'"&$C$6&"'!$6:$6")=I$6)* (INDIRECT("'"&$C$6&"'!$5:$5")=I$5), INDIRECT("'"&$C$6&"'!"&ROW()&":"&ROW()) )} -> -1682.6984 | K88: =$D88-E88 -> -14.321451 | L88: =$D88-F88 -> 236.81868 | M88: =$D88-G88 -> -73.01113 | N88: =$D88-H88 -> -211.53227 | O88: =$D88-I88 -> -613.90105 | Q88: =IFERROR($D88/E88-1,0) -> 0.0062750687 | R88: =IFERROR($D88/F88-1,0) -> -0.093477927 | S88: =IFERROR($D88/G88-1,0) -> 0.032834823 | T88: =IFERROR($D88/H88-1,0) -> 0.10145105 | U88: =IFERROR($D88/I88-1,0) -> 0.3648313 | W88: {=INDIRECT("'"&$C$6&"'!"&ADDRESS(ROW(),COLUMN()+44))} -> -12122.686 | X88: {=INDIRECT("'"&$C$6&"'!"&ADDRESS(ROW(),COLUMN()+44))} -> -11403.413 | Y88: {=INDIRECT("'"&$C$6&"'!"&ADDRESS(ROW(),COLUMN()+44))} -> -9826.0868 | Z88: {=INDIRECT("'"&$C$6&"'!"&ADDRESS(ROW(),COLUMN()+44))} -> -10593.213 | AA88: {=INDIRECT("'"&$C$6&"'!"&ADDRESS(ROW(),COLUMN()+44))} -> -9313.2286 | AB88: {=INDIRECT("'"&$C$6&"'!"&ADDRESS(ROW(),COLUMN()+44))} -> -8592.9521 | AD88: =$W88-X88 -> -719.27355 | AE88: =$W88-Y88 -> -2296.5995 | AF88: =$W88-Z88 -> -1529.4735 | AG88: =$W88-AA88 -> -2809.4576 | AH88: =$W88-AB88 -> -3529.7342 | AJ88: =IFERROR($W88/X88-1,0) -> 0.063075289 | AK88: =IFERROR($W88/Y88-1,0) -> 0.23372473 | AL88: =IFERROR($W88/Z88-1,0) -> 0.1443824 | AM88: =IFERROR($W88/AA88-1,0) -> 0.30166312 | AN88: =IFERROR($W88/AB88-1,0) -> 0.41077084
C89: Gastos Operativos | D89: =SUM(D86:D88) -> -8480.7401 | E89: =SUM(E86:E88) -> -7846.1645 | F89: =SUM(F86:F88) -> -7901.2427 | G89: =SUM(G86:G88) -> -7675.4181 | H89: =SUM(H86:H88) -> -7106.0021 | I89: =SUM(I86:I88) -> -6521.805 | K89: =$D89-E89 -> -634.57558 | L89: =$D89-F89 -> -579.49737 | M89: =$D89-G89 -> -805.32192 | N89: =$D89-H89 -> -1374.738 | O89: =$D89-I89 -> -1958.9351 | Q89: =IFERROR($D89/E89-1,0) -> 0.08087717 | R89: =IFERROR($D89/F89-1,0) -> 0.073342561 | S89: =IFERROR($D89/G89-1,0) -> 0.10492222 | T89: =IFERROR($D89/H89-1,0) -> 0.19346152 | U89: =IFERROR($D89/I89-1,0) -> 0.30036701 | W89: =SUM(W86:W88) -> -39584.541 | X89: =SUM(X86:X88) -> -38340.707 | Y89: =SUM(Y86:Y88) -> -31103.801 | Z89: =SUM(Z86:Z88) -> -36335.656 | AA89: =SUM(AA86:AA88) -> -33162.517 | AB89: =SUM(AB86:AB88) -> -34316.091 | AD89: =$W89-X89 -> -1243.8343 | AE89: =$W89-Y89 -> -8480.7401 | AF89: =$W89-Z89 -> -3248.8849 | AG89: =$W89-AA89 -> -6422.0239 | AH89: =$W89-AB89 -> -5268.45 | AJ89: =IFERROR($W89/X89-1,0) -> 0.03244161 | AK89: =IFERROR($W89/Y89-1,0) -> 0.27265928 | AL89: =IFERROR($W89/Z89-1,0) -> 0.089413134 | AM89: =IFERROR($W89/AA89-1,0) -> 0.19365309 | AN89: =IFERROR($W89/AB89-1,0) -> 0.1535271
A91: Extraordinarios | C91: Donaciones | D91: {=_xlfn.XLOOKUP(1, (INDIRECT("'"&$C$6&"'!$6:$6")=D$6)* (INDIRECT("'"&$C$6&"'!$5:$5")=D$5), INDIRECT("'"&$C$6&"'!"&ROW()&":"&ROW()) )} -> -207.32067 | E91: {=_xlfn.XLOOKUP(1, (INDIRECT("'"&$C$6&"'!$6:$6")=E$6)* (INDIRECT("'"&$C$6&"'!$5:$5")=E$5), INDIRECT("'"&$C$6&"'!"&ROW()&":"&ROW()) )} -> 0 | F91: {=_xlfn.XLOOKUP(1, (INDIRECT("'"&$C$6&"'!$6:$6")=F$6)* (INDIRECT("'"&$C$6&"'!$5:$5")=F$5), INDIRECT("'"&$C$6&"'!"&ROW()&":"&ROW()) )} -> -216.74167 | G91: {=_xlfn.XLOOKUP(1, (INDIRECT("'"&$C$6&"'!$6:$6")=G$6)* (INDIRECT("'"&$C$6&"'!$5:$5")=G$5), INDIRECT("'"&$C$6&"'!"&ROW()&":"&ROW()) )} -> -221.4673 | H91: {=_xlfn.XLOOKUP(1, (INDIRECT("'"&$C$6&"'!$6:$6")=H$6)* (INDIRECT("'"&$C$6&"'!$5:$5")=H$5), INDIRECT("'"&$C$6&"'!"&ROW()&":"&ROW()) )} -> -248.79139 | I91: {=_xlfn.XLOOKUP(1, (INDIRECT("'"&$C$6&"'!$6:$6")=I$6)* (INDIRECT("'"&$C$6&"'!$5:$5")=I$5), INDIRECT("'"&$C$6&"'!"&ROW()&":"&ROW()) )} -> -257.16412 | K91: =$D91-E91 -> -207.32067 | L91: =$D91-F91 -> 9.421 | M91: =$D91-G91 -> 14.14663 | N91: =$D91-H91 -> 41.47072 | O91: =$D91-I91 -> 49.84345 | Q91: =IFERROR($D91/E91-1,0) -> 0 | R91: =IFERROR($D91/F91-1,0) -> -0.043466492 | S91: =IFERROR($D91/G91-1,0) -> -0.063876834 | T91: =IFERROR($D91/H91-1,0) -> -0.16668873 | U91: =IFERROR($D91/I91-1,0) -> -0.19381961 | W91: {=INDIRECT("'"&$C$6&"'!"&ADDRESS(ROW(),COLUMN()+44))} -> -995.31235 | X91: {=INDIRECT("'"&$C$6&"'!"&ADDRESS(ROW(),COLUMN()+44))} -> 0 | Y91: {=INDIRECT("'"&$C$6&"'!"&ADDRESS(ROW(),COLUMN()+44))} -> -787.99168 | Z91: {=INDIRECT("'"&$C$6&"'!"&ADDRESS(ROW(),COLUMN()+44))} -> -903.25848 | AA91: {=INDIRECT("'"&$C$6&"'!"&ADDRESS(ROW(),COLUMN()+44))} -> -926.4686 | AB91: {=INDIRECT("'"&$C$6&"'!"&ADDRESS(ROW(),COLUMN()+44))} -> -990.93733 | AD91: =$W91-X91 -> -995.31235 | AE91: =$W91-Y91 -> -207.32067 | AF91: =$W91-Z91 -> -92.05387 | AG91: =$W91-AA91 -> -68.84375 | AH91: =$W91-AB91 -> -4.3750202 | AJ91: =IFERROR($W91/X91-1,0) -> 0 | AK91: =IFERROR($W91/Y91-1,0) -> 0.26310007 | AL91: =IFERROR($W91/Z91-1,0) -> 0.1019131 | AM91: =IFERROR($W91/AA91-1,0) -> 0.074307699 | AN91: =IFERROR($W91/AB91-1,0) -> 0.0044150321
A92: Extraordinarios | C92: Otros | D92: {=_xlfn.XLOOKUP(1, (INDIRECT("'"&$C$6&"'!$6:$6")=D$6)* (INDIRECT("'"&$C$6&"'!$5:$5")=D$5), INDIRECT("'"&$C$6&"'!"&ROW()&":"&ROW()) )} -> -227.41403 | E92: {=_xlfn.XLOOKUP(1, (INDIRECT("'"&$C$6&"'!$6:$6")=E$6)* (INDIRECT("'"&$C$6&"'!$5:$5")=E$5), INDIRECT("'"&$C$6&"'!"&ROW()&":"&ROW()) )} -> -446.7121 | F92: {=_xlfn.XLOOKUP(1, (INDIRECT("'"&$C$6&"'!$6:$6")=F$6)* (INDIRECT("'"&$C$6&"'!$5:$5")=F$5), INDIRECT("'"&$C$6&"'!"&ROW()&":"&ROW()) )} -> -302.98367 | G92: {=_xlfn.XLOOKUP(1, (INDIRECT("'"&$C$6&"'!$6:$6")=G$6)* (INDIRECT("'"&$C$6&"'!$5:$5")=G$5), INDIRECT("'"&$C$6&"'!"&ROW()&":"&ROW()) )} -> -311.59607 | H92: {=_xlfn.XLOOKUP(1, (INDIRECT("'"&$C$6&"'!$6:$6")=H$6)* (INDIRECT("'"&$C$6&"'!$5:$5")=H$5), INDIRECT("'"&$C$6&"'!"&ROW()&":"&ROW()) )} -> -596.85921 | I92: {=_xlfn.XLOOKUP(1, (INDIRECT("'"&$C$6&"'!$6:$6")=I$6)* (INDIRECT("'"&$C$6&"'!$5:$5")=I$5), INDIRECT("'"&$C$6&"'!"&ROW()&":"&ROW()) )} -> -142.99597 | K92: =$D92-E92 -> 219.29807 | L92: =$D92-F92 -> 75.569644 | M92: =$D92-G92 -> 84.182043 | N92: =$D92-H92 -> 369.44518 | O92: =$D92-I92 -> -84.41806 | Q92: =IFERROR($D92/E92-1,0) -> -0.49091589 | R92: =IFERROR($D92/F92-1,0) -> -0.2494182 | S92: =IFERROR($D92/G92-1,0) -> -0.27016401 | T92: =IFERROR($D92/H92-1,0) -> -0.61898212 | U92: =IFERROR($D92/I92-1,0) -> 0.59035272 | W92: {=INDIRECT("'"&$C$6&"'!"&ADDRESS(ROW(),COLUMN()+44))} -> -1133.1584 | X92: {=INDIRECT("'"&$C$6&"'!"&ADDRESS(ROW(),COLUMN()+44))} -> -1564.0117 | Y92: {=INDIRECT("'"&$C$6&"'!"&ADDRESS(ROW(),COLUMN()+44))} -> -905.74442 | Z92: {=INDIRECT("'"&$C$6&"'!"&ADDRESS(ROW(),COLUMN()+44))} -> -1253.2679 | AA92: {=INDIRECT("'"&$C$6&"'!"&ADDRESS(ROW(),COLUMN()+44))} -> -2627.2114 | AB92: {=INDIRECT("'"&$C$6&"'!"&ADDRESS(ROW(),COLUMN()+44))} -> -819.50276 | AD92: =$W92-X92 -> 430.85324 | AE92: =$W92-Y92 -> -227.41403 | AF92: =$W92-Z92 -> 120.10948 | AG92: =$W92-AA92 -> 1494.053 | AH92: =$W92-AB92 -> -313.65569 | AJ92: =IFERROR($W92/X92-1,0) -> -0.27547955 | AK92: =IFERROR($W92/Y92-1,0) -> 0.25107969 | AL92: =IFERROR($W92/Z92-1,0) -> -0.095837036 | AM92: =IFERROR($W92/AA92-1,0) -> -0.56868395 | AN92: =IFERROR($W92/AB92-1,0) -> 0.38273902
C93: Extraordinarios | D93: =SUM(D91:D92) -> -434.7347 | E93: =SUM(E91:E92) -> -446.7121 | F93: =SUM(F91:F92) -> -519.72534 | G93: =SUM(G91:G92) -> -533.06337 | H93: =SUM(H91:H92) -> -845.6506 | I93: =SUM(I91:I92) -> -400.16009 | K93: =$D93-E93 -> 11.977398 | L93: =$D93-F93 -> 84.990644 | M93: =$D93-G93 -> 98.328673 | N93: =$D93-H93 -> 410.9159 | O93: =$D93-I93 -> -34.57461 | Q93: =IFERROR($D93/E93-1,0) -> -0.026812343 | R93: =IFERROR($D93/F93-1,0) -> -0.16352992 | S93: =IFERROR($D93/G93-1,0) -> -0.18445963 | T93: =IFERROR($D93/H93-1,0) -> -0.48591688 | U93: =IFERROR($D93/I93-1,0) -> 0.086401945 | W93: =SUM(W91:W92) -> -2128.4708 | X93: =SUM(X91:X92) -> -1564.0117 | Y93: =SUM(Y91:Y92) -> -1693.7361 | Z93: =SUM(Z91:Z92) -> -2156.5264 | AA93: =SUM(AA91:AA92) -> -3553.68 | AB93: =SUM(AB91:AB92) -> -1810.4401 | AD93: =$W93-X93 -> -564.45911 | AE93: =$W93-Y93 -> -434.7347 | AF93: =$W93-Z93 -> 28.055614 | AG93: =$W93-AA93 -> 1425.2092 | AH93: =$W93-AB93 -> -318.03071 | AJ93: =IFERROR($W93/X93-1,0) -> 0.36090466 | AK93: =IFERROR($W93/Y93-1,0) -> 0.25667204 | AL93: =IFERROR($W93/Z93-1,0) -> -0.013009632 | AM93: =IFERROR($W93/AA93-1,0) -> -0.40105165 | AN93: =IFERROR($W93/AB93-1,0) -> 0.17566486
A95: ROF | C95: Venta de Cartera | D95: {=_xlfn.XLOOKUP(1, (INDIRECT("'"&$C$6&"'!$6:$6")=D$6)* (INDIRECT("'"&$C$6&"'!$5:$5")=D$5), INDIRECT("'"&$C$6&"'!"&ROW()&":"&ROW()) )} -> 0 | E95: {=_xlfn.XLOOKUP(1, (INDIRECT("'"&$C$6&"'!$6:$6")=E$6)* (INDIRECT("'"&$C$6&"'!$5:$5")=E$5), INDIRECT("'"&$C$6&"'!"&ROW()&":"&ROW()) )} -> 0 | F95: {=_xlfn.XLOOKUP(1, (INDIRECT("'"&$C$6&"'!$6:$6")=F$6)* (INDIRECT("'"&$C$6&"'!$5:$5")=F$5), INDIRECT("'"&$C$6&"'!"&ROW()&":"&ROW()) )} -> 0 | G95: {=_xlfn.XLOOKUP(1, (INDIRECT("'"&$C$6&"'!$6:$6")=G$6)* (INDIRECT("'"&$C$6&"'!$5:$5")=G$5), INDIRECT("'"&$C$6&"'!"&ROW()&":"&ROW()) )} -> 0 | H95: {=_xlfn.XLOOKUP(1, (INDIRECT("'"&$C$6&"'!$6:$6")=H$6)* (INDIRECT("'"&$C$6&"'!$5:$5")=H$5), INDIRECT("'"&$C$6&"'!"&ROW()&":"&ROW()) )} -> 0 | I95: {=_xlfn.XLOOKUP(1, (INDIRECT("'"&$C$6&"'!$6:$6")=I$6)* (INDIRECT("'"&$C$6&"'!$5:$5")=I$5), INDIRECT("'"&$C$6&"'!"&ROW()&":"&ROW()) )} -> 0 | K95: =$D95-E95 -> 0 | L95: =$D95-F95 -> 0 | M95: =$D95-G95 -> 0 | N95: =$D95-H95 -> 0 | O95: =$D95-I95 -> 0 | Q95: =IFERROR($D95/E95-1,0) -> 0 | R95: =IFERROR($D95/F95-1,0) -> 0 | S95: =IFERROR($D95/G95-1,0) -> 0 | T95: =IFERROR($D95/H95-1,0) -> 0 | U95: =IFERROR($D95/I95-1,0) -> 0 | W95: {=INDIRECT("'"&$C$6&"'!"&ADDRESS(ROW(),COLUMN()+44))} -> 0 | X95: {=INDIRECT("'"&$C$6&"'!"&ADDRESS(ROW(),COLUMN()+44))} -> 0 | Y95: {=INDIRECT("'"&$C$6&"'!"&ADDRESS(ROW(),COLUMN()+44))} -> 0 | Z95: {=INDIRECT("'"&$C$6&"'!"&ADDRESS(ROW(),COLUMN()+44))} -> 683.18679 | AA95: {=INDIRECT("'"&$C$6&"'!"&ADDRESS(ROW(),COLUMN()+44))} -> 0 | AB95: {=INDIRECT("'"&$C$6&"'!"&ADDRESS(ROW(),COLUMN()+44))} -> 0 | AD95: =$W95-X95 -> 0 | AE95: =$W95-Y95 -> 0 | AF95: =$W95-Z95 -> -683.18679 | AG95: =$W95-AA95 -> 0 | AH95: =$W95-AB95 -> 0 | AJ95: =IFERROR($W95/X95-1,0) -> 0 | AK95: =IFERROR($W95/Y95-1,0) -> 0 | AL95: =IFERROR($W95/Z95-1,0) -> -1 | AM95: =IFERROR($W95/AA95-1,0) -> 0 | AN95: =IFERROR($W95/AB95-1,0) -> 0
C96: ROF | D96: =SUM(D95:D95) -> 0 | E96: =SUM(E95:E95) -> 0 | F96: =SUM(F95:F95) -> 0 | G96: =SUM(G95:G95) -> 0 | H96: =SUM(H95:H95) -> 0 | I96: =SUM(I95:I95) -> 0 | K96: =$D96-E96 -> 0 | L96: =$D96-F96 -> 0 | M96: =$D96-G96 -> 0 | N96: =$D96-H96 -> 0 | O96: =$D96-I96 -> 0 | Q96: =IFERROR($D96/E96-1,0) -> 0 | R96: =IFERROR($D96/F96-1,0) -> 0 | S96: =IFERROR($D96/G96-1,0) -> 0 | T96: =IFERROR($D96/H96-1,0) -> 0 | U96: =IFERROR($D96/I96-1,0) -> 0 | W96: =SUM(W95:W95) -> 0 | X96: =SUM(X95:X95) -> 0 | Y96: =SUM(Y95:Y95) -> 0 | Z96: =SUM(Z95:Z95) -> 683.18679 | AA96: =SUM(AA95:AA95) -> 0 | AB96: =SUM(AB95:AB95) -> 0 | AD96: =$W96-X96 -> 0 | AE96: =$W96-Y96 -> 0 | AF96: =$W96-Z96 -> -683.18679 | AG96: =$W96-AA96 -> 0 | AH96: =$W96-AB96 -> 0 | AJ96: =IFERROR($W96/X96-1,0) -> 0 | AK96: =IFERROR($W96/Y96-1,0) -> 0 | AL96: =IFERROR($W96/Z96-1,0) -> -1 | AM96: =IFERROR($W96/AA96-1,0) -> 0 | AN96: =IFERROR($W96/AB96-1,0) -> 0
C98: UAI | D98: =D60+D83+D89+D93+D96 -> 4624.903 | E98: =E60+E83+E89+E93+E96 -> 7435.5956 | F98: =F60+F83+F89+F93+F96 -> 5543.2616 | G98: =G60+G83+G89+G93+G96 -> 5666.17 | H98: =H60+H83+H89+H93+H96 -> 3758.1008 | I98: =I60+I83+I89+I93+I96 -> 6922.9179 | K98: =$D98-E98 -> -2810.6926 | L98: =$D98-F98 -> -918.3586 | M98: =$D98-G98 -> -1041.267 | N98: =$D98-H98 -> 866.80218 | O98: =$D98-I98 -> -2298.0149 | Q98: =IFERROR($D98/E98-1,0) -> -0.37800504 | R98: =IFERROR($D98/F98-1,0) -> -0.16567116 | S98: =IFERROR($D98/G98-1,0) -> -0.1837691 | T98: =IFERROR($D98/H98-1,0) -> 0.230649 | U98: =IFERROR($D98/I98-1,0) -> -0.33194311 | W98: =W60+W83+W89+W93+W96 -> 30689.95 | X98: =X60+X83+X89+X93+X96 -> 36825.522 | Y98: =Y60+Y83+Y89+Y93+Y96 -> 26065.047 | Z98: =Z60+Z83+Z89+Z93+Z96 -> 31175.228 | AA98: =AA60+AA83+AA89+AA93+AA96 -> 15773.013 | AB98: =AB60+AB83+AB89+AB93+AB96 -> 41860.857 | AD98: =$W98-X98 -> -6135.5715 | AE98: =$W98-Y98 -> 4624.903 | AF98: =$W98-Z98 -> -485.27807 | AG98: =$W98-AA98 -> 14916.937 | AH98: =$W98-AB98 -> -11170.906 | AJ98: =IFERROR($W98/X98-1,0) -> -0.16661194 | AK98: =IFERROR($W98/Y98-1,0) -> 0.17743697 | AL98: =IFERROR($W98/Z98-1,0) -> -0.015566143 | AM98: =IFERROR($W98/AA98-1,0) -> 0.94572529 | AN98: =IFERROR($W98/AB98-1,0) -> -0.26685805
C102: Prom SFdP | D102: {=_xlfn.XLOOKUP(1, (INDIRECT("'"&$C$6&"'!$6:$6")=D$6)* (INDIRECT("'"&$C$6&"'!$5:$5")=D$5), INDIRECT("'"&$C$6&"'!"&ROW()&":"&ROW()) )} -> 5702269.8 | E102: {=_xlfn.XLOOKUP(1, (INDIRECT("'"&$C$6&"'!$6:$6")=E$6)* (INDIRECT("'"&$C$6&"'!$5:$5")=E$5), INDIRECT("'"&$C$6&"'!"&ROW()&":"&ROW()) )} -> 6032744 | F102: {=_xlfn.XLOOKUP(1, (INDIRECT("'"&$C$6&"'!$6:$6")=F$6)* (INDIRECT("'"&$C$6&"'!$5:$5")=F$5), INDIRECT("'"&$C$6&"'!"&ROW()&":"&ROW()) )} -> 5684672 | G102: {=_xlfn.XLOOKUP(1, (INDIRECT("'"&$C$6&"'!$6:$6")=G$6)* (INDIRECT("'"&$C$6&"'!$5:$5")=G$5), INDIRECT("'"&$C$6&"'!"&ROW()&":"&ROW()) )} -> 5757635.8 | H102: {=_xlfn.XLOOKUP(1, (INDIRECT("'"&$C$6&"'!$6:$6")=H$6)* (INDIRECT("'"&$C$6&"'!$5:$5")=H$5), INDIRECT("'"&$C$6&"'!"&ROW()&":"&ROW()) )} -> 5727513.6 | I102: {=_xlfn.XLOOKUP(1, (INDIRECT("'"&$C$6&"'!$6:$6")=I$6)* (INDIRECT("'"&$C$6&"'!$5:$5")=I$5), INDIRECT("'"&$C$6&"'!"&ROW()&":"&ROW()) )} -> 5006463 | W102: {=INDIRECT("'"&$C$6&"'!"&ADDRESS(ROW(),COLUMN()+44))} -> 5694660.9 | X102: {=INDIRECT("'"&$C$6&"'!"&ADDRESS(ROW(),COLUMN()+44))} -> 5995110.7 | Y102: {=INDIRECT("'"&$C$6&"'!"&ADDRESS(ROW(),COLUMN()+44))} -> 5691839.6 | Z102: {=INDIRECT("'"&$C$6&"'!"&ADDRESS(ROW(),COLUMN()+44))} -> 5761990.6 | AA102: {=INDIRECT("'"&$C$6&"'!"&ADDRESS(ROW(),COLUMN()+44))} -> 5566568.9 | AB102: {=INDIRECT("'"&$C$6&"'!"&ADDRESS(ROW(),COLUMN()+44))} -> 4915170.6

Sheet Indicadores
C1: Mensual | P1: Acumulado
J2: Variación % | W2: Variación %
B3: =Desempeño_Financiero!C6 -> Total_Producto | C3: =Desempeño_Financiero!D6 -> 46173 | D3: =Desempeño_Financiero!E6 -> 46173 | E3: =Desempeño_Financiero!F6 -> 46142 | F3: =Desempeño_Financiero!G6 -> 45808 | G3: =Desempeño_Financiero!H6 -> 45443 | H3: =Desempeño_Financiero!I6 -> 45077 | J3: =D3 -> 46173 | K3: =E3 -> 46142 | L3: =F3 -> 45808 | M3: =G3 -> 45443 | N3: =H3 -> 45077 | P3: =C3 -> 46173 | Q3: =D3 -> 46173 | R3: =E3 -> 46142 | S3: =F3 -> 45808 | T3: =G3 -> 45443 | U3: =H3 -> 45077 | W3: =Q3 -> 46173 | X3: =R3 -> 46142 | Y3: =S3 -> 45808 | Z3: =T3 -> 45443 | AA3: =U3 -> 45077
B5: Eficiencia | C5: =IFERROR((-Desempeño_Financiero!D89)/(Desempeño_Financiero!D53+Desempeño_Financiero!D83+Desempeño_Financiero!D96),0) -> 0.35704556 | D5: =IFERROR((-Desempeño_Financiero!E89)/(Desempeño_Financiero!E53+Desempeño_Financiero!E83+Desempeño_Financiero!E96),0) -> 0.30955179 | E5: =IFERROR((-Desempeño_Financiero!F89)/(Desempeño_Financiero!F53+Desempeño_Financiero!F83+Desempeño_Financiero!F96),0) -> 0.31832432 | F5: =IFERROR((-Desempeño_Financiero!G89)/(Desempeño_Financiero!G53+Desempeño_Financiero!G83+Desempeño_Financiero!G96),0) -> 0.33389329 | G5: =IFERROR((-Desempeño_Financiero!H89)/(Desempeño_Financiero!H53+Desempeño_Financiero!H83+Desempeño_Financiero!H96),0) -> 0.37270814 | H5: =IFERROR((-Desempeño_Financiero!I89)/(Desempeño_Financiero!I53+Desempeño_Financiero!I83+Desempeño_Financiero!I96),0) -> 0.34603563 | J5: =IFERROR(($C5-D5)*10000,0) -> 474.93774 | K5: =IFERROR(($C5-E5)*10000,0) -> 387.21241 | L5: =IFERROR(($C5-F5)*10000,0) -> 231.52266 | M5: =IFERROR(($C5-G5)*10000,0) -> -156.62579 | N5: =IFERROR(($C5-H5)*10000,0) -> 110.09928 | P5: =IFERROR((-Desempeño_Financiero!W89)/(Desempeño_Financiero!W53+Desempeño_Financiero!W83+Desempeño_Financiero!W96),0) -> 0.32534164 | Q5: =IFERROR((-Desempeño_Financiero!X89)/(Desempeño_Financiero!X53+Desempeño_Financiero!X83+Desempeño_Financiero!X96),0) -> 0.29690115 | R5: =IFERROR((-Desempeño_Financiero!Y89)/(Desempeño_Financiero!Y53+Desempeño_Financiero!Y83+Desempeño_Financiero!Y96),0) -> 0.31765104 | S5: =IFERROR((-Desempeño_Financiero!Z89)/(Desempeño_Financiero!Z53+Desempeño_Financiero!Z83+Desempeño_Financiero!Z96),0) -> 0.32274798 | T5: =IFERROR((-Desempeño_Financiero!AA89)/(Desempeño_Financiero!AA53+Desempeño_Financiero!AA83+Desempeño_Financiero!AA96),0) -> 0.34611657 | U5: =IFERROR((-Desempeño_Financiero!AB89)/(Desempeño_Financiero!AB53+Desempeño_Financiero!AB83+Desempeño_Financiero!AB96),0) -> 0.33173329 | W5: =IFERROR(($P5-Q5)*10000,0) -> 284.40488 | X5: =IFERROR(($P5-R5)*10000,0) -> 76.905947 | Y5: =IFERROR(($P5-S5)*10000,0) -> 25.936554 | Z5: =IFERROR(($P5-T5)*10000,0) -> -207.74935 | AA5: =IFERROR(($P5-U5)*10000,0) -> -63.916547
B7: Rendimiento de Colocaciones | C7: =Desempeño_Financiero!D23 -> 0.11137811 | D7: =Desempeño_Financiero!E23 -> 0.11189033 | E7: =Desempeño_Financiero!F23 -> 0.11159997 | F7: =Desempeño_Financiero!G23 -> 0.1173199 | G7: =Desempeño_Financiero!H23 -> 0.11725894 | H7: =Desempeño_Financiero!I23 -> 0.11807424 | J7: =IFERROR(($C7-D7)*10000,0) -> -5.1222257 | K7: =IFERROR(($C7-E7)*10000,0) -> -2.2186345 | L7: =IFERROR(($C7-F7)*10000,0) -> -59.417871 | M7: =IFERROR(($C7-G7)*10000,0) -> -58.808283 | N7: =IFERROR(($C7-H7)*10000,0) -> -66.961307 | P7: =Desempeño_Financiero!W23 -> 0.11195056 | Q7: =Desempeño_Financiero!X23 -> 0.11256651 | R7: =Desempeño_Financiero!Y23 -> 0.11209416 | S7: =Desempeño_Financiero!Z23 -> 0.11661895 | T7: =Desempeño_Financiero!AA23 -> 0.1175928 | U7: =Desempeño_Financiero!AB23 -> 0.11847174 | W7: =IFERROR(($P7-Q7)*10000,0) -> -6.1594389 | X7: =IFERROR(($P7-R7)*10000,0) -> -1.4359243 | Y7: =IFERROR(($P7-S7)*10000,0) -> -46.683888 | Z7: =IFERROR(($P7-T7)*10000,0) -> -56.422359 | AA7: =IFERROR(($P7-U7)*10000,0) -> -65.211794
B9: INOF / Ingresos Totales | C9: =IFERROR((Desempeño_Financiero!D83)/(Desempeño_Financiero!D53+Desempeño_Financiero!D83+Desempeño_Financiero!D96),0) -> 0.038498884 | D9: =IFERROR((Desempeño_Financiero!E83)/(Desempeño_Financiero!E53+Desempeño_Financiero!E83+Desempeño_Financiero!E96),0) -> 0.028992418 | E9: =IFERROR((Desempeño_Financiero!F83)/(Desempeño_Financiero!F53+Desempeño_Financiero!F83+Desempeño_Financiero!F96),0) -> 0.049234231 | F9: =IFERROR((Desempeño_Financiero!G83)/(Desempeño_Financiero!G53+Desempeño_Financiero!G83+Desempeño_Financiero!G96),0) -> 0.046514831 | G9: =IFERROR((Desempeño_Financiero!H83)/(Desempeño_Financiero!H53+Desempeño_Financiero!H83+Desempeño_Financiero!H96),0) -> 0.026092879 | H9: =IFERROR((Desempeño_Financiero!I83)/(Desempeño_Financiero!I53+Desempeño_Financiero!I83+Desempeño_Financiero!I96),0) -> 0.031495527 | J9: =IFERROR(($C9-D9)*10000,0) -> 95.06466 | K9: =IFERROR(($C9-E9)*10000,0) -> -107.35347 | L9: =IFERROR(($C9-F9)*10000,0) -> -80.159471 | M9: =IFERROR(($C9-G9)*10000,0) -> 124.06004 | N9: =IFERROR(($C9-H9)*10000,0) -> 70.033568 | P9: =IFERROR((Desempeño_Financiero!W83)/(Desempeño_Financiero!W53+Desempeño_Financiero!W83+Desempeño_Financiero!W96),0) -> 0.041550904 | Q9: =IFERROR((Desempeño_Financiero!X83)/(Desempeño_Financiero!X53+Desempeño_Financiero!X83+Desempeño_Financiero!X96),0) -> 0.033498257 | R9: =IFERROR((Desempeño_Financiero!Y83)/(Desempeño_Financiero!Y53+Desempeño_Financiero!Y83+Desempeño_Financiero!Y96),0) -> 0.042291249 | S9: =IFERROR((Desempeño_Financiero!Z83)/(Desempeño_Financiero!Z53+Desempeño_Financiero!Z83+Desempeño_Financiero!Z96),0) -> 0.028144204 | T9: =IFERROR((Desempeño_Financiero!AA83)/(Desempeño_Financiero!AA53+Desempeño_Financiero!AA83+Desempeño_Financiero!AA96),0) -> 0.030301376 | U9: =IFERROR((Desempeño_Financiero!AB83)/(Desempeño_Financiero!AB53+Desempeño_Financiero!AB83+Desempeño_Financiero!AB96),0) -> 0.030928871 | W9: =IFERROR(($P9-Q9)*10000,0) -> 80.526469 | X9: =IFERROR(($P9-R9)*10000,0) -> -7.4034523 | Y9: =IFERROR(($P9-S9)*10000,0) -> 134.06699 | Z9: =IFERROR(($P9-T9)*10000,0) -> 112.49527 | AA9: =IFERROR(($P9-U9)*10000,0) -> 106.22033
B11: INOF / Gasto Operativo | C11: =IFERROR((Desempeño_Financiero!D83/-Desempeño_Financiero!D89),0) -> 0.10782625 | D11: =IFERROR((Desempeño_Financiero!E83/-Desempeño_Financiero!E89),0) -> 0.093659346 | E11: =IFERROR((Desempeño_Financiero!F83/-Desempeño_Financiero!F89),0) -> 0.15466689 | F11: =IFERROR((Desempeño_Financiero!G83/-Desempeño_Financiero!G89),0) -> 0.13931047 | G11: =IFERROR((Desempeño_Financiero!H83/-Desempeño_Financiero!H89),0) -> 0.07000888 | H11: =IFERROR((Desempeño_Financiero!I83/-Desempeño_Financiero!I89),0) -> 0.091018161 | J11: =IFERROR(($C11-D11)*10000,0) -> 141.66904 | K11: =IFERROR(($C11-E11)*10000,0) -> -468.40637 | L11: =IFERROR(($C11-F11)*10000,0) -> -314.84217 | M11: =IFERROR(($C11-G11)*10000,0) -> 378.1737 | N11: =IFERROR(($C11-H11)*10000,0) -> 168.08089 | P11: =IFERROR((Desempeño_Financiero!W83/-Desempeño_Financiero!W89),0) -> 0.12771468 | Q11: =IFERROR((Desempeño_Financiero!X83/-Desempeño_Financiero!X89),0) -> 0.1128263 | R11: =IFERROR((Desempeño_Financiero!Y83/-Desempeño_Financiero!Y89),0) -> 0.13313745 | S11: =IFERROR((Desempeño_Financiero!Z83/-Desempeño_Financiero!Z89),0) -> 0.087201797 | T11: =IFERROR((Desempeño_Financiero!AA83/-Desempeño_Financiero!AA89),0) -> 0.087546736 | U11: =IFERROR((Desempeño_Financiero!AB83/-Desempeño_Financiero!AB89),0) -> 0.093234147 | W11: =IFERROR(($P11-Q11)*10000,0) -> 148.88386 | X11: =IFERROR(($P11-R11)*10000,0) -> -54.227654 | Y11: =IFERROR(($P11-S11)*10000,0) -> 405.12884 | Z11: =IFERROR(($P11-T11)*10000,0) -> 401.67946 | AA11: =IFERROR(($P11-U11)*10000,0) -> 344.80534
B13: Gasto Operativo / Activo | C13: =IFERROR(-Desempeño_Financiero!D89/Desempeño_Financiero!D17*12,0) -> 0.017945842 | D13: =IFERROR(-Desempeño_Financiero!E89/Desempeño_Financiero!E17*12,0) -> 0.015696049 | E13: =IFERROR(-Desempeño_Financiero!F89/Desempeño_Financiero!F17*12,0) -> 0.016779953 | F13: =IFERROR(-Desempeño_Financiero!G89/Desempeño_Financiero!G17*12,0) -> 0.016096775 | G13: =IFERROR(-Desempeño_Financiero!H89/Desempeño_Financiero!H17*12,0) -> 0.01495094 | H13: =IFERROR(-Desempeño_Financiero!I89/Desempeño_Financiero!I17*12,0) -> 0.015686101 | J13: =IFERROR(($C13-D13)*10000,0) -> 22.497922 | K13: =IFERROR(($C13-E13)*10000,0) -> 11.658885 | L13: =IFERROR(($C13-F13)*10000,0) -> 18.490668 | M13: =IFERROR(($C13-G13)*10000,0) -> 29.949017 | N13: =IFERROR(($C13-H13)*10000,0) -> 22.597409 | P13: =IFERROR(-Desempeño_Financiero!W89/Desempeño_Financiero!W17*12,0) -> 0.083967951 | Q13: =IFERROR(-Desempeño_Financiero!X89/Desempeño_Financiero!X17*12,0) -> 0.077326999 | R13: =IFERROR(-Desempeño_Financiero!Y89/Desempeño_Financiero!Y17*12,0) -> 0.066018595 | S13: =IFERROR(-Desempeño_Financiero!Z89/Desempeño_Financiero!Z17*12,0) -> 0.076154834 | T13: =IFERROR(-Desempeño_Financiero!AA89/Desempeño_Financiero!AA17*12,0) -> 0.071709393 | U13: =IFERROR(-Desempeño_Financiero!AB89/Desempeño_Financiero!AB17*12,0) -> 0.084517137 | W13: =IFERROR(($P13-Q13)*10000,0) -> 66.409518 | X13: =IFERROR(($P13-R13)*10000,0) -> 179.49356 | Y13: =IFERROR(($P13-S13)*10000,0) -> 78.131166 | Z13: =IFERROR(($P13-T13)*10000,0) -> 122.58558 | AA13: =IFERROR(($P13-U13)*10000,0) -> -5.4918612
B15: Provisiones Brutas / Cartera Bruta | C15: =IFERROR(-Desempeño_Financiero!D56/Desempeño_Financiero!D102,0)*12 -> 0.025823179 | D15: =IFERROR(-Desempeño_Financiero!E56/Desempeño_Financiero!E102,0)*12 -> 0.023792893 | E15: =IFERROR(-Desempeño_Financiero!F56/Desempeño_Financiero!F102,0)*12 -> 0.027568949 | F15: =IFERROR(-Desempeño_Financiero!G56/Desempeño_Financiero!G102,0)*12 -> 0.024200761 | G15: =IFERROR(-Desempeño_Financiero!H56/Desempeño_Financiero!H102,0)*12 -> 0.020650088 | H15: =IFERROR(-Desempeño_Financiero!I56/Desempeño_Financiero!I102,0)*12 -> 0.020249492 | J15: =IFERROR(($C15-D15)*10000,0) -> 20.302862 | K15: =IFERROR(($C15-E15)*10000,0) -> -17.457691 | L15: =IFERROR(($C15-F15)*10000,0) -> 16.224189 | M15: =IFERROR(($C15-G15)*10000,0) -> 51.730912 | N15: =IFERROR(($C15-H15)*10000,0) -> 55.736877 | P15: =IFERROR(-Desempeño_Financiero!W56/Desempeño_Financiero!W102,0)*12 -> 0.12774832 | Q15: =IFERROR(-Desempeño_Financiero!X56/Desempeño_Financiero!X102,0)*12 -> 0.12728352 | R15: =IFERROR(-Desempeño_Financiero!Y56/Desempeño_Financiero!Y102,0)*12 -> 0.10194114 | S15: =IFERROR(-Desempeño_Financiero!Z56/Desempeño_Financiero!Z102,0)*12 -> 0.11599766 | T15: =IFERROR(-Desempeño_Financiero!AA56/Desempeño_Financiero!AA102,0)*12 -> 0.12224099 | U15: =IFERROR(-Desempeño_Financiero!AB56/Desempeño_Financiero!AB102,0)*12 -> 0.095083875 | W15: =IFERROR(($P15-Q15)*10000,0) -> 4.6479227 | X15: =IFERROR(($P15-R15)*10000,0) -> 258.0718 | Y15: =IFERROR(($P15-S15)*10000,0) -> 117.50661 | Z15: =IFERROR(($P15-T15)*10000,0) -> 55.073245 | AA15: =IFERROR(($P15-U15)*10000,0) -> 326.64441
B17: ROE
B19: ROA

Sheet Evolutivos-->

Sheet Total_Producto
D1: REAL | AZ1: PRESUPUESTO | BO1: Acumulado | BW1: Saldo Prom Acumulado
BO2: =DATE(YEAR(BO6),1,1) -> 46023 | BP2: =DATE(YEAR(BP6),1,1) -> 46023 | BQ2: =DATE(YEAR(BQ6),1,1) -> 46023 | BR2: =DATE(YEAR(BR6),1,1) -> 45658 | BS2: =DATE(YEAR(BS6),1,1) -> 45292 | BT2: =DATE(YEAR(BT6),1,1) -> 44927
