Workbook

Sheet Parametros
B2: Producto | C2: Convenios
B4: Año | C4: 2026
B6: Lista Fechas | C6: =EOMONTH(DATE($C$4,1,1),0) -> 46053 | E6: Segmentos | F6: Renta_Alta
C7: =EOMONTH(C6,1) -> 46081 | F7: Masivo
C8: =EOMONTH(C7,1) -> 46112 | F8: Consumo_Inicial
C9: =EOMONTH(C8,1) -> 46142 | F9: Total_Producto
C10: =EOMONTH(C9,1) -> 46173
C11: =EOMONTH(C10,1) -> 46203
C12: =EOMONTH(C11,1) -> 46234
C13: =EOMONTH(C12,1) -> 46265
C14: =EOMONTH(C13,1) -> 46295
C15: =EOMONTH(C14,1) -> 46326
C16: =EOMONTH(C15,1) -> 46356
C17: =EOMONTH(C16,1) -> 46387

Sheet Total_Producto_CHECK
D1: REAL | AZ1: PRESUPUESTO | BO1: Acumulado | BW1: Saldo Prom Acumulado
BO2: =DATE(YEAR(BO6),1,1) -> 46023 | BP2: =DATE(YEAR(BP6),1,1) -> 46023 | BQ2: =DATE(YEAR(BQ6),1,1) -> 46023 | BR2: =DATE(YEAR(BR6),1,1) -> 45658 | BS2: =DATE(YEAR(BS6),1,1) -> 45292 | BT2: =DATE(YEAR(BT6),1,1) -> 44927
C3: N° dias T.Imp | D3: =DAY(D6) -> 31 | E3: =DAY(E6) -> 28 | F3: =DAY(F6) -> 31 | G3: =DAY(G6) -> 30 | H3: =DAY(H6) -> 31 | I3: =DAY(I6) -> 30 | J3: =DAY(J6) -> 31 | K3: =DAY(K6) -> 31 | ... BK3: =DAY(BK6) -> 31 | BO3: =AVERAGEIFS($D3:$BM3,$D$6:$BM$6,">="&BO$2,$D$6:$BM$6,"<="&BO$6,$D$5:$BM$5,BO$5) -> 30 | BP3: =AVERAGEIFS($D3:$BM3,$D$6:$BM$6,">="&BP$2,$D$6:$BM$6,"<="&BP$6,$D$5:$BM$5,BP$5) -> 30 | BQ3: =AVERAGEIFS($D3:$BM3,$D$6:$BM$6,">="&BQ$2,$D$6:$BM$6,"<="&BQ$6,$D$5:$BM$5,BQ$5) -> 29.5 | BR3: =AVERAGEIFS($D3:$BM3,$D$6:$BM$6,">="&BR$2,$D$6:$BM$6,"<="&BR$6,$D$5:$BM$5,BR$5) -> 30 | BS3: =AVERAGEIFS($D3:$BM3,$D$6:$BM$6,">="&BS$2,$D$6:$BM$6,"<="&BS$6,$D$5:$BM$5,BS$5) -> 30.333333 | BT3: =AVERAGEIFS($D3:$BM3,$D$6:$BM$6,">="&BT$2,$D$6:$BM$6,"<="&BT$6,$D$5:$BM$5,BT$5) -> 30
C4: N° dias FTP | D4: =DAY(D6) -> 31 | E4: =DAY(E6) -> 28 | F4: =DAY(F6) -> 31 | G4: =DAY(G6) -> 30 | H4: =DAY(H6) -> 31 | I4: =DAY(I6) -> 30 | J4: =DAY(J6) -> 31 | K4: =DAY(K6) -> 31 | ... BK4: =DAY(BK6) -> 31 | BO4: =AVERAGEIFS($D4:$BM4,$D$6:$BM$6,">="&BO$2,$D$6:$BM$6,"<="&BO$6,$D$5:$BM$5,BO$5) -> 30 | BP4: =AVERAGEIFS($D4:$BM4,$D$6:$BM$6,">="&BP$2,$D$6:$BM$6,"<="&BP$6,$D$5:$BM$5,BP$5) -> 30 | BQ4: =AVERAGEIFS($D4:$BM4,$D$6:$BM$6,">="&BQ$2,$D$6:$BM$6,"<="&BQ$6,$D$5:$BM$5,BQ$5) -> 29.5 | BR4: =AVERAGEIFS($D4:$BM4,$D$6:$BM$6,">="&BR$2,$D$6:$BM$6,"<="&BR$6,$D$5:$BM$5,BR$5) -> 30 | BS4: =AVERAGEIFS($D4:$BM4,$D$6:$BM$6,">="&BS$2,$D$6:$BM$6,"<="&BS$6,$D$5:$BM$5,BS$5) -> 30.333333 | BT4: =AVERAGEIFS($D4:$BM4,$D$6:$BM$6,">="&BT$2,$D$6:$BM$6,"<="&BT$6,$D$5:$BM$5,BT$5) -> 30
C5: Tipo | D5: R | E5: R | F5: R | G5: R | H5: R | I5: R | J5: R | K5: R | L5: R | M5: R | N5: R | O5: R | P5: R | Q5: R | R5: R | S5: R | T5: R | U5: R | V5: R | W5: R | X5: R | Y5: R | Z5: R | AA5: R | AB5: R | AC5: R | AD5: R | AE5: R | AF5: R | AG5: R | AH5: R | AI5: R | AJ5: R | AK5: R | AL5: R | AM5: R | AN5: R | AO5: R | AP5: R | AQ5: R | AR5: R | AS5: R | AT5: R | AU5: R | AV5: R | AW5: R | AX5: R | AY5: R | AZ5: P | BA5: P | BB5: P | BC5: P | BD5: P | BE5: P | BF5: P | BG5: P | BH5: P | BI5: P | BJ5: P | BK5: P | BO5: R | BP5: P | BQ5: R | BR5: R | BS5: R | BT5: R
C6: Total Préstamos | D6: 44957 | E6: 44985 | F6: 45016 | G6: 45046 | H6: 45077 | I6: 45107 | J6: 45138 | K6: 45169 | L6: 45199 | M6: 45230 | N6: 45260 | O6: 45291 | P6: 45322 | Q6: 45351 | R6: 45382 | S6: 45412 | T6: 45443 | U6: 45473 | V6: 45504 | W6: 45535 | X6: 45565 | Y6: 45596 | Z6: 45626 | AA6: 45657 | AB6: 45688 | AC6: 45716 | AD6: 45747 | AE6: 45777 | AF6: 45808 | AG6: 45838 | AH6: 45869 | AI6: 45900 | AJ6: 45930 | AK6: 45961 | AL6: 45991 | AM6: 46022 | AN6: 46053 | AO6: 46081 | AP6: 46112 | AQ6: 46142 | AR6: 46173 | AS6: 46203 | AT6: 46234 | AU6: 46265 | AV6: 46295 | AW6: 46326 | AX6: 46356 | AY6: 46387 | AZ6: 46053 | BA6: 46081 | BB6: 46112 | BC6: 46142 | BD6: 46173 | BE6: 46203 | BF6: 46234 | BG6: 46265 | BH6: 46295 | BI6: 46326 | BJ6: 46356 | BK6: 46387 | BO6: =Desempeño_Financiero!$B$1 -> 46112 | BP6: =BO6 -> 46112 | BQ6: =EOMONTH(BO6,-1) -> 46081 | BR6: =EOMONTH(BO6,-12) -> 45747 | BS6: =EOMONTH(BO6,-24) -> 45382 | BT6: =EOMONTH(BO6,-36) -> 45016 | BW6: =BO6 -> 46112 | BX6: =BP6 -> 46112 | BY6: =BQ6 -> 46081 | BZ6: =BR6 -> 45747 | CA6: =BS6 -> 45382 | CB6: =BT6 -> 45016
A8: SALDO_FDP | C8: Vigente | D8: =Renta_Alta!D8+Masivo!D8+Consumo_Inicial!D8 -> 3209375.3 | E8: =Renta_Alta!E8+Masivo!E8+Consumo_Inicial!E8 -> 3300088.8 | F8: =Renta_Alta!F8+Masivo!F8+Consumo_Inicial!F8 -> 3421266.2 | G8: =Renta_Alta!G8+Masivo!G8+Consumo_Inicial!G8 -> 3499038.9 | H8: =Renta_Alta!H8+Masivo!H8+Consumo_Inicial!H8 -> 3573142.6 | I8: =Renta_Alta!I8+Masivo!I8+Consumo_Inicial!I8 -> 3630227.9 | J8: =Renta_Alta!J8+Masivo!J8+Consumo_Inicial!J8 -> 3660638.8 | K8: =Renta_Alta!K8+Masivo!K8+Consumo_Inicial!K8 -> 3748310.6 | ... BK8: =Renta_Alta!BK8+Masivo!BK8+Consumo_Inicial!BK8 -> 3478386.4 | BO8: =_xlfn.XLOOKUP(BO$6,$D$6:$BM$6,$D8:$BM8,,0,1) -> 3199553.1 | BP8: =_xlfn.XLOOKUP(BP$6,$D$6:$BM$6,$D8:$BM8,,0,-1) -> 3121000.5 | BQ8: =_xlfn.XLOOKUP(BQ$6,$D$6:$BM$6,$D8:$BM8,,0,1) -> 3154129 | BR8: =_xlfn.XLOOKUP(BR$6,$D$6:$BM$6,$D8:$BM8,,0,1) -> 2864120.5 | BS8: =_xlfn.XLOOKUP(BS$6,$D$6:$BM$6,$D8:$BM8,,0,1) -> 3428790.2 | BT8: =_xlfn.XLOOKUP(BT$6,$D$6:$BM$6,$D8:$BM8,,0,1) -> 3421266.2
A9: SALDO_FDP | C9: Refinanciado | D9: =Renta_Alta!D9+Masivo!D9+Consumo_Inicial!D9 -> 12463.798 | E9: =Renta_Alta!E9+Masivo!E9+Consumo_Inicial!E9 -> 12950.203 | F9: =Renta_Alta!F9+Masivo!F9+Consumo_Inicial!F9 -> 12918.972 | G9: =Renta_Alta!G9+Masivo!G9+Consumo_Inicial!G9 -> 11884.581 | H9: =Renta_Alta!H9+Masivo!H9+Consumo_Inicial!H9 -> 11239.857 | I9: =Renta_Alta!I9+Masivo!I9+Consumo_Inicial!I9 -> 10375.034 | J9: =Renta_Alta!J9+Masivo!J9+Consumo_Inicial!J9 -> 9473.513 | K9: =Renta_Alta!K9+Masivo!K9+Consumo_Inicial!K9 -> 8668.61 | ... BK9: =Renta_Alta!BK9+Masivo!BK9+Consumo_Inicial!BK9 -> 24436.883 | BO9: =_xlfn.XLOOKUP(BO$6,$D$6:$BM$6,$D9:$BM9,,0,1) -> 36825.6 | BP9: =_xlfn.XLOOKUP(BP$6,$D$6:$BM$6,$D9:$BM9,,0,-1) -> 32170.33 | BQ9: =_xlfn.XLOOKUP(BQ$6,$D$6:$BM$6,$D9:$BM9,,0,1) -> 37846.73 | BR9: =_xlfn.XLOOKUP(BR$6,$D$6:$BM$6,$D9:$BM9,,0,1) -> 47040.751 | BS9: =_xlfn.XLOOKUP(BS$6,$D$6:$BM$6,$D9:$BM9,,0,1) -> 8619.8673 | BT9: =_xlfn.XLOOKUP(BT$6,$D$6:$BM$6,$D9:$BM9,,0,1) -> 12918.972
A10: SALDO_FDP | C10: Vencido y Judicial | D10: =Renta_Alta!D10+Masivo!D10+Consumo_Inicial!D10 -> 75075.645 | E10: =Renta_Alta!E10+Masivo!E10+Consumo_Inicial!E10 -> 72983.439 | F10: =Renta_Alta!F10+Masivo!F10+Consumo_Inicial!F10 -> 66041.883 | G10: =Renta_Alta!G10+Masivo!G10+Consumo_Inicial!G10 -> 60991.925 | H10: =Renta_Alta!H10+Masivo!H10+Consumo_Inicial!H10 -> 57791.376 | I10: =Renta_Alta!I10+Masivo!I10+Consumo_Inicial!I10 -> 64002.308 | J10: =Renta_Alta!J10+Masivo!J10+Consumo_Inicial!J10 -> 88094.936 | K10: =Renta_Alta!K10+Masivo!K10+Consumo_Inicial!K10 -> 128190.78 | ... BK10: =Renta_Alta!BK10+Masivo!BK10+Consumo_Inicial!BK10 -> 94244.001 | BO10: =_xlfn.XLOOKUP(BO$6,$D$6:$BM$6,$D10:$BM10,,0,1) -> 84810.02 | BP10: =_xlfn.XLOOKUP(BP$6,$D$6:$BM$6,$D10:$BM10,,0,-1) -> 92303.295 | BQ10: =_xlfn.XLOOKUP(BQ$6,$D$6:$BM$6,$D10:$BM10,,0,1) -> 88358.85 | BR10: =_xlfn.XLOOKUP(BR$6,$D$6:$BM$6,$D10:$BM10,,0,1) -> 109573.14 | BS10: =_xlfn.XLOOKUP(BS$6,$D$6:$BM$6,$D10:$BM10,,0,1) -> 171673.77 | BT10: =_xlfn.XLOOKUP(BT$6,$D$6:$BM$6,$D10:$BM10,,0,1) -> 66041.883
C11: Saldo FdP | D11: =SUM(D8:D10) -> 3296914.8 | E11: =SUM(E8:E10) -> 3386022.5 | F11: =SUM(F8:F10) -> 3500227.1 | G11: =SUM(G8:G10) -> 3571915.4 | H11: =SUM(H8:H10) -> 3642173.9 | I11: =SUM(I8:I10) -> 3704605.2 | J11: =SUM(J8:J10) -> 3758207.2 | K11: =SUM(K8:K10) -> 3885170 | ... BK11: =SUM(BK8:BK10) -> 3597067.3 | BO11: =SUM(BO8:BO10) -> 3321188.7 | BP11: =SUM(BP8:BP10) -> 3245474.1 | BQ11: =SUM(BQ8:BQ10) -> 3280334.6 | BR11: =SUM(BR8:BR10) -> 3020734.4 | BS11: =SUM(BS8:BS10) -> 3609083.8 | BT11: =SUM(BT8:BT10) -> 3500227.1
D12: =[1]Desempeño_Financiero_Evol!BA50-D11 -> -6.0379505e-05 | E12: =[1]Desempeño_Financiero_Evol!BB50-E11 -> 0.00044076005 | F12: =[1]Desempeño_Financiero_Evol!BC50-F11 -> 0.00015937956 | G12: =[1]Desempeño_Financiero_Evol!BD50-G11 -> -0.00044045085 | H12: =[1]Desempeño_Financiero_Evol!BE50-H11 -> -8.0738217e-05 | I12: =[1]Desempeño_Financiero_Evol!BF50-I11 -> 0.00036987895 | J12: =[1]Desempeño_Financiero_Evol!BG50-J11 -> 0.00022914167 | K12: =[1]Desempeño_Financiero_Evol!BH50-K11 -> -4.0450599e-05 | ... AZ12: =[1]Desempeño_Financiero_Evol!CW50-AZ11 -> 0
A14: SALDO_PROM | C14: Vigente | D14: =Renta_Alta!D14+Masivo!D14+Consumo_Inicial!D14 -> 3158143.9 | E14: =Renta_Alta!E14+Masivo!E14+Consumo_Inicial!E14 -> 3223471.9 | F14: =Renta_Alta!F14+Masivo!F14+Consumo_Inicial!F14 -> 3343878.5 | G14: =Renta_Alta!G14+Masivo!G14+Consumo_Inicial!G14 -> 3446583.5 | H14: =Renta_Alta!H14+Masivo!H14+Consumo_Inicial!H14 -> 3525126.4 | I14: =Renta_Alta!I14+Masivo!I14+Consumo_Inicial!I14 -> 3573798.3 | J14: =Renta_Alta!J14+Masivo!J14+Consumo_Inicial!J14 -> 3616394 | K14: =Renta_Alta!K14+Masivo!K14+Consumo_Inicial!K14 -> 3651568.9 | ... BK14: =Renta_Alta!BK14+Masivo!BK14+Consumo_Inicial!BK14 -> 3447409.6 | BO14: =IFERROR(AVERAGEIFS($D14:$BM14,$D$6:$BM$6,">="&BO$2,$D$6:$BM$6,"<="&BO$6,$D$5:$BM$5,BO$5,$D14:$BM14,"<>0"),0) -> 3101496 | BP14: =IFERROR(AVERAGEIFS($D14:$BM14,$D$6:$BM$6,">="&BP$2,$D$6:$BM$6,"<="&BP$6,$D$5:$BM$5,BP$5,$D14:$BM14,"<>0"),0) -> 3059754.3 | BQ14: =IFERROR(AVERAGEIFS($D14:$BM14,$D$6:$BM$6,">="&BQ$2,$D$6:$BM$6,"<="&BQ$6,$D$5:$BM$5,BQ$5,$D14:$BM14,"<>0"),0) -> 3069509.7 | BR14: =IFERROR(AVERAGEIFS($D14:$BM14,$D$6:$BM$6,">="&BR$2,$D$6:$BM$6,"<="&BR$6,$D$5:$BM$5,BR$5,$D14:$BM14,"<>0"),0) -> 2830433.6 | BS14: =IFERROR(AVERAGEIFS($D14:$BM14,$D$6:$BM$6,">="&BS$2,$D$6:$BM$6,"<="&BS$6,$D$5:$BM$5,BS$5,$D14:$BM14,"<>0"),0) -> 3524089.4 | BT14: =IFERROR(AVERAGEIFS($D14:$BM14,$D$6:$BM$6,">="&BT$2,$D$6:$BM$6,"<="&BT$6,$D$5:$BM$5,BT$5,$D14:$BM14,"<>0"),0) -> 3241831.4 | BW14: =SUMIFS($D14:$BM14,$D$6:$BM$6,">="&BO$2,$D$6:$BM$6,"<="&BO$6,$D$5:$BM$5,BO$5) -> 9304488 | BX14: =SUMIFS($D14:$BM14,$D$6:$BM$6,">="&BP$2,$D$6:$BM$6,"<="&BP$6,$D$5:$BM$5,BP$5) -> 9179262.9 | BY14: =SUMIFS($D14:$BM14,$D$6:$BM$6,">="&BQ$2,$D$6:$BM$6,"<="&BQ$6,$D$5:$BM$5,BQ$5) -> 6139019.5 | BZ14: =SUMIFS($D14:$BM14,$D$6:$BM$6,">="&BR$2,$D$6:$BM$6,"<="&BR$6,$D$5:$BM$5,BR$5) -> 8491300.7 | CA14: =SUMIFS($D14:$BM14,$D$6:$BM$6,">="&BS$2,$D$6:$BM$6,"<="&BS$6,$D$5:$BM$5,BS$5) -> 10572268 | CB14: =SUMIFS($D14:$BM14,$D$6:$BM$6,">="&BT$2,$D$6:$BM$6,"<="&BT$6,$D$5:$BM$5,BT$5) -> 9725494.3
A15: SALDO_PROM | C15: Refinanciado | D15: =Renta_Alta!D15+Masivo!D15+Consumo_Inicial!D15 -> 11558.805 | E15: =Renta_Alta!E15+Masivo!E15+Consumo_Inicial!E15 -> 12005.69 | F15: =Renta_Alta!F15+Masivo!F15+Consumo_Inicial!F15 -> 12441.221 | G15: =Renta_Alta!G15+Masivo!G15+Consumo_Inicial!G15 -> 11919.025 | H15: =Renta_Alta!H15+Masivo!H15+Consumo_Inicial!H15 -> 10988.538 | I15: =Renta_Alta!I15+Masivo!I15+Consumo_Inicial!I15 -> 10143.944 | J15: =Renta_Alta!J15+Masivo!J15+Consumo_Inicial!J15 -> 9514.0316 | K15: =Renta_Alta!K15+Masivo!K15+Consumo_Inicial!K15 -> 8636.6127 | ... BK15: =Renta_Alta!BK15+Masivo!BK15+Consumo_Inicial!BK15 -> 23625.138 | BO15: =IFERROR(AVERAGEIFS($D15:$BM15,$D$6:$BM$6,">="&BO$2,$D$6:$BM$6,"<="&BO$6,$D$5:$BM$5,BO$5,$D15:$BM15,"<>0"),0) -> 37137.887 | BP15: =IFERROR(AVERAGEIFS($D15:$BM15,$D$6:$BM$6,">="&BP$2,$D$6:$BM$6,"<="&BP$6,$D$5:$BM$5,BP$5,$D15:$BM15,"<>0"),0) -> 33358.564 | BQ15: =IFERROR(AVERAGEIFS($D15:$BM15,$D$6:$BM$6,">="&BQ$2,$D$6:$BM$6,"<="&BQ$6,$D$5:$BM$5,BQ$5,$D15:$BM15,"<>0"),0) -> 37573.085 | BR15: =IFERROR(AVERAGEIFS($D15:$BM15,$D$6:$BM$6,">="&BR$2,$D$6:$BM$6,"<="&BR$6,$D$5:$BM$5,BR$5,$D15:$BM15,"<>0"),0) -> 44410.208 | BS15: =IFERROR(AVERAGEIFS($D15:$BM15,$D$6:$BM$6,">="&BS$2,$D$6:$BM$6,"<="&BS$6,$D$5:$BM$5,BS$5,$D15:$BM15,"<>0"),0) -> 5713.7241 | BT15: =IFERROR(AVERAGEIFS($D15:$BM15,$D$6:$BM$6,">="&BT$2,$D$6:$BM$6,"<="&BT$6,$D$5:$BM$5,BT$5,$D15:$BM15,"<>0"),0) -> 12001.905 | BW15: =SUMIFS($D15:$BM15,$D$6:$BM$6,">="&BO$2,$D$6:$BM$6,"<="&BO$6,$D$5:$BM$5,BO$5) -> 111413.66 | BX15: =SUMIFS($D15:$BM15,$D$6:$BM$6,">="&BP$2,$D$6:$BM$6,"<="&BP$6,$D$5:$BM$5,BP$5) -> 100075.69 | BY15: =SUMIFS($D15:$BM15,$D$6:$BM$6,">="&BQ$2,$D$6:$BM$6,"<="&BQ$6,$D$5:$BM$5,BQ$5) -> 75146.17 | BZ15: =SUMIFS($D15:$BM15,$D$6:$BM$6,">="&BR$2,$D$6:$BM$6,"<="&BR$6,$D$5:$BM$5,BR$5) -> 133230.62 | CA15: =SUMIFS($D15:$BM15,$D$6:$BM$6,">="&BS$2,$D$6:$BM$6,"<="&BS$6,$D$5:$BM$5,BS$5) -> 17141.172 | CB15: =SUMIFS($D15:$BM15,$D$6:$BM$6,">="&BT$2,$D$6:$BM$6,"<="&BT$6,$D$5:$BM$5,BT$5) -> 36005.715
A16: SALDO_PROM | C16: Vencido y Judicial | D16: =Renta_Alta!D16+Masivo!D16+Consumo_Inicial!D16 -> 87323.449 | E16: =Renta_Alta!E16+Masivo!E16+Consumo_Inicial!E16 -> 87859.363 | F16: =Renta_Alta!F16+Masivo!F16+Consumo_Inicial!F16 -> 78613.723 | G16: =Renta_Alta!G16+Masivo!G16+Consumo_Inicial!G16 -> 75931.779 | H16: =Renta_Alta!H16+Masivo!H16+Consumo_Inicial!H16 -> 68785.835 | I16: =Renta_Alta!I16+Masivo!I16+Consumo_Inicial!I16 -> 75827.007 | J16: =Renta_Alta!J16+Masivo!J16+Consumo_Inicial!J16 -> 90692.774 | K16: =Renta_Alta!K16+Masivo!K16+Consumo_Inicial!K16 -> 138012.13 | ... BK16: =Renta_Alta!BK16+Masivo!BK16+Consumo_Inicial!BK16 -> 107280.77 | BO16: =IFERROR(AVERAGEIFS($D16:$BM16,$D$6:$BM$6,">="&BO$2,$D$6:$BM$6,"<="&BO$6,$D$5:$BM$5,BO$5,$D16:$BM16,"<>0"),0) -> 100528.69 | BP16: =IFERROR(AVERAGEIFS($D16:$BM16,$D$6:$BM$6,">="&BP$2,$D$6:$BM$6,"<="&BP$6,$D$5:$BM$5,BP$5,$D16:$BM16,"<>0"),0) -> 110684.55 | BQ16: =IFERROR(AVERAGEIFS($D16:$BM16,$D$6:$BM$6,">="&BQ$2,$D$6:$BM$6,"<="&BQ$6,$D$5:$BM$5,BQ$5,$D16:$BM16,"<>0"),0) -> 102470.95 | BR16: =IFERROR(AVERAGEIFS($D16:$BM16,$D$6:$BM$6,">="&BR$2,$D$6:$BM$6,"<="&BR$6,$D$5:$BM$5,BR$5,$D16:$BM16,"<>0"),0) -> 133756.47 | BS16: =IFERROR(AVERAGEIFS($D16:$BM16,$D$6:$BM$6,">="&BS$2,$D$6:$BM$6,"<="&BS$6,$D$5:$BM$5,BS$5,$D16:$BM16,"<>0"),0) -> 178374.56 | BT16: =IFERROR(AVERAGEIFS($D16:$BM16,$D$6:$BM$6,">="&BT$2,$D$6:$BM$6,"<="&BT$6,$D$5:$BM$5,BT$5,$D16:$BM16,"<>0"),0) -> 84598.845 | BW16: =SUMIFS($D16:$BM16,$D$6:$BM$6,">="&BO$2,$D$6:$BM$6,"<="&BO$6,$D$5:$BM$5,BO$5) -> 301586.06 | BX16: =SUMIFS($D16:$BM16,$D$6:$BM$6,">="&BP$2,$D$6:$BM$6,"<="&BP$6,$D$5:$BM$5,BP$5) -> 332053.64 | BY16: =SUMIFS($D16:$BM16,$D$6:$BM$6,">="&BQ$2,$D$6:$BM$6,"<="&BQ$6,$D$5:$BM$5,BQ$5) -> 204941.9 | BZ16: =SUMIFS($D16:$BM16,$D$6:$BM$6,">="&BR$2,$D$6:$BM$6,"<="&BR$6,$D$5:$BM$5,BR$5) -> 401269.42 | CA16: =SUMIFS($D16:$BM16,$D$6:$BM$6,">="&BS$2,$D$6:$BM$6,"<="&BS$6,$D$5:$BM$5,BS$5) -> 535123.68 | CB16: =SUMIFS($D16:$BM16,$D$6:$BM$6,">="&BT$2,$D$6:$BM$6,"<="&BT$6,$D$5:$BM$5,BT$5) -> 253796.54
C17: Saldo Prom | D17: =SUM(D14:D16) -> 3257026.1 | E17: =SUM(E14:E16) -> 3323336.9 | F17: =SUM(F14:F16) -> 3434933.5 | G17: =SUM(G14:G16) -> 3534434.3 | H17: =SUM(H14:H16) -> 3604900.7 | I17: =SUM(I14:I16) -> 3659769.2 | J17: =SUM(J14:J16) -> 3716600.8 | K17: =SUM(K14:K16) -> 3798217.6 | ... BK17: =SUM(BK14:BK16) -> 3578315.5 | BO17: =SUM(BO14:BO16) -> 3239162.6 | BP17: =SUM(BP14:BP16) -> 3203797.4 | BQ17: =SUM(BQ14:BQ16) -> 3209553.8 | BR17: =SUM(BR14:BR16) -> 3008600.2 | BS17: =SUM(BS14:BS16) -> 3708177.7 | BT17: =SUM(BT14:BT16) -> 3338432.2 | BW17: =SUM(BW14:BW16) -> 9717487.8 | BX17: =SUM(BX14:BX16) -> 9611392.3 | BY17: =SUM(BY14:BY16) -> 6419107.6 | BZ17: =SUM(BZ14:BZ16) -> 9025800.7 | CA17: =SUM(CA14:CA16) -> 11124533 | CB17: =SUM(CB14:CB16) -> 10015297
D18: =[1]Desempeño_Financiero_Evol!BA95-D17 -> 0.00010901969 | E18: =[1]Desempeño_Financiero_Evol!BB95-E17 -> 0.00057051983 | F18: =[1]Desempeño_Financiero_Evol!BC95-F17 -> 0.00040940102 | G18: =[1]Desempeño_Financiero_Evol!BD95-G17 -> -0.00050120056 | H18: =[1]Desempeño_Financiero_Evol!BE95-H17 -> 0.00011985935 | I18: =[1]Desempeño_Financiero_Evol!BF95-I17 -> -0.00047100056 | J18: =[1]Desempeño_Financiero_Evol!BG95-J17 -> 0.00043020025 | K18: =[1]Desempeño_Financiero_Evol!BH95-K17 -> 0.00027984008 | ... AZ18: =[1]Desempeño_Financiero_Evol!CW95-AZ17 -> 0
C20: Vigente | D20: =IFERROR(((1+D38/D14)^(360/D$3))-1,0) -> 0.18688844 | E20: =IFERROR(((1+E38/E14)^(360/E$3))-1,0) -> 0.18929111 | F20: =IFERROR(((1+F38/F14)^(360/F$3))-1,0) -> 0.18709846 | G20: =IFERROR(((1+G38/G14)^(360/G$3))-1,0) -> 0.18094853 | H20: =IFERROR(((1+H38/H14)^(360/H$3))-1,0) -> 0.19026482 | I20: =IFERROR(((1+I38/I14)^(360/I$3))-1,0) -> 0.18959246 | J20: =IFERROR(((1+J38/J14)^(360/J$3))-1,0) -> 0.18872508 | K20: =IFERROR(((1+K38/K14)^(360/K$3))-1,0) -> 0.18941062 | ... BK20: =IFERROR(((1+BK38/BK14)^(360/BK$3))-1,0) -> 0.17626555 | BO20: =IFERROR(((1+BO38/BW14)^(360/BO$3))-1,0) -> 0.16764934 | BP20: =IFERROR(((1+BP38/BX14)^(360/BP$3))-1,0) -> 0.16628708 | BQ20: =IFERROR(((1+BQ38/BY14)^(360/BQ$3))-1,0) -> 0.16803228 | BR20: =IFERROR(((1+BR38/BZ14)^(360/BR$3))-1,0) -> 0.17002459 | BS20: =IFERROR(((1+BS38/CA14)^(360/BS$3))-1,0) -> 0.17330211 | BT20: =IFERROR(((1+BT38/CB14)^(360/BT$3))-1,0) -> 0.18774684
C21: Refinanciado | D21: =IFERROR(((1+D39/D15)^(360/D$3))-1,0) -> 0.07153226 | E21: =IFERROR(((1+E39/E15)^(360/E$3))-1,0) -> 0.080577761 | F21: =IFERROR(((1+F39/F15)^(360/F$3))-1,0) -> 0.060315445 | G21: =IFERROR(((1+G39/G15)^(360/G$3))-1,0) -> 0.052107325 | H21: =IFERROR(((1+H39/H15)^(360/H$3))-1,0) -> 0.05691557 | I21: =IFERROR(((1+I39/I15)^(360/I$3))-1,0) -> 0.057134391 | J21: =IFERROR(((1+J39/J15)^(360/J$3))-1,0) -> 0.065817453 | K21: =IFERROR(((1+K39/K15)^(360/K$3))-1,0) -> 0.067622921 | ... BK21: =IFERROR(((1+BK39/BK15)^(360/BK$3))-1,0) -> 0.072416048 | BO21: =IFERROR(((1+BO39/BW15)^(360/BO$3))-1,0) -> 0.077494623 | BP21: =IFERROR(((1+BP39/BX15)^(360/BP$3))-1,0) -> 0.072375067 | BQ21: =IFERROR(((1+BQ39/BY15)^(360/BQ$3))-1,0) -> 0.077073241 | BR21: =IFERROR(((1+BR39/BZ15)^(360/BR$3))-1,0) -> 0.065973937 | BS21: =IFERROR(((1+BS39/CA15)^(360/BS$3))-1,0) -> 0.074294711 | BT21: =IFERROR(((1+BT39/CB15)^(360/BT$3))-1,0) -> 0.070310613
C22: Vencido y Judicial | D22: =IFERROR(((1+D40/D16)^(360/D$3))-1,0) -> 0.063222147 | E22: =IFERROR(((1+E40/E16)^(360/E$3))-1,0) -> 0.036767038 | F22: =IFERROR(((1+F40/F16)^(360/F$3))-1,0) -> 0.055202672 | G22: =IFERROR(((1+G40/G16)^(360/G$3))-1,0) -> 0.059740187 | H22: =IFERROR(((1+H40/H16)^(360/H$3))-1,0) -> 0.097736874 | I22: =IFERROR(((1+I40/I16)^(360/I$3))-1,0) -> 0.078366095 | J22: =IFERROR(((1+J40/J16)^(360/J$3))-1,0) -> 0.090724347 | K22: =IFERROR(((1+K40/K16)^(360/K$3))-1,0) -> 0.062407939 | ... BK22: =IFERROR(((1+BK40/BK16)^(360/BK$3))-1,0) -> 0.088150151 | BO22: =IFERROR(((1+BO40/BW16)^(360/BO$3))-1,0) -> 0.092717636 | BP22: =IFERROR(((1+BP40/BX16)^(360/BP$3))-1,0) -> 0.090299602 | BQ22: =IFERROR(((1+BQ40/BY16)^(360/BQ$3))-1,0) -> 0.094298888 | BR22: =IFERROR(((1+BR40/BZ16)^(360/BR$3))-1,0) -> 0.095011803 | BS22: =IFERROR(((1+BS40/CA16)^(360/BS$3))-1,0) -> 0.062221607 | BT22: =IFERROR(((1+BT40/CB16)^(360/BT$3))-1,0) -> 0.051973131
C23: Tasa Implicita | D23: =IFERROR(((1+D41/D17)^(360/D$3))-1,0) -> 0.18298074 | E23: =IFERROR(((1+E41/E17)^(360/E$3))-1,0) -> 0.18459697 | F23: =IFERROR(((1+F41/F17)^(360/F$3))-1,0) -> 0.18343664 | G23: =IFERROR(((1+G41/G17)^(360/G$3))-1,0) -> 0.17775947 | H23: =IFERROR(((1+H41/H17)^(360/H$3))-1,0) -> 0.18800632 | I23: =IFERROR(((1+I41/I17)^(360/I$3))-1,0) -> 0.18679854 | J23: =IFERROR(((1+J41/J17)^(360/J$3))-1,0) -> 0.18591102 | K23: =IFERROR(((1+K41/K17)^(360/K$3))-1,0) -> 0.18427341 | ... BK23: =IFERROR(((1+BK41/BK17)^(360/BK$3))-1,0) -> 0.17281843 | BO23: =IFERROR(((1+BO41/BW17)^(360/BO$3))-1,0) -> 0.16418505 | BP23: =IFERROR(((1+BP41/BX17)^(360/BP$3))-1,0) -> 0.1625696 | BQ23: =IFERROR(((1+BQ41/BY17)^(360/BQ$3))-1,0) -> 0.1645071 | BR23: =IFERROR(((1+BR41/BZ17)^(360/BR$3))-1,0) -> 0.16499509 | BS23: =IFERROR(((1+BS41/CA17)^(360/BS$3))-1,0) -> 0.16756622 | BT23: =IFERROR(((1+BT41/CB17)^(360/BT$3))-1,0) -> 0.18367537
C26: Vigente | D26: =-IFERROR(((1-D44/D14)^(360/D$4))-1,0) -> -0.069457728 | E26: =-IFERROR(((1-E44/E14)^(360/E$4))-1,0) -> -0.072006399 | F26: =-IFERROR(((1-F44/F14)^(360/F$4))-1,0) -> -0.073901929 | G26: =-IFERROR(((1-G44/G14)^(360/G$4))-1,0) -> -0.075135078 | H26: =-IFERROR(((1-H44/H14)^(360/H$4))-1,0) -> -0.075853357 | I26: =-IFERROR(((1-I44/I14)^(360/I$4))-1,0) -> -0.077094293 | J26: =-IFERROR(((1-J44/J14)^(360/J$4))-1,0) -> -0.07695435 | K26: =-IFERROR(((1-K44/K14)^(360/K$4))-1,0) -> -0.076826417 | ... BK26: =-IFERROR(((1-BK44/BK14)^(360/BK$4))-1,0) -> -0.060135204 | BO26: =-IFERROR(((1-BO44/BW14)^(360/BO$4))-1,0) -> -0.061733011 | BP26: =-IFERROR(((1-BP44/BX14)^(360/BP$4))-1,0) -> -0.063725702 | BQ26: =-IFERROR(((1-BQ44/BY14)^(360/BQ$4))-1,0) -> -0.062110866 | BR26: =-IFERROR(((1-BR44/BZ14)^(360/BR$4))-1,0) -> -0.07018776 | BS26: =-IFERROR(((1-BS44/CA14)^(360/BS$4))-1,0) -> -0.077652319 | BT26: =-IFERROR(((1-BT44/CB14)^(360/BT$4))-1,0) -> -0.071837695
C27: Refinanciado | D27: =-IFERROR(((1-D45/D15)^(360/D$4))-1,0) -> -0.072502366 | E27: =-IFERROR(((1-E45/E15)^(360/E$4))-1,0) -> -0.075540719 | F27: =-IFERROR(((1-F45/F15)^(360/F$4))-1,0) -> -0.077408172 | G27: =-IFERROR(((1-G45/G15)^(360/G$4))-1,0) -> -0.078030669 | H27: =-IFERROR(((1-H45/H15)^(360/H$4))-1,0) -> -0.078639826 | I27: =-IFERROR(((1-I45/I15)^(360/I$4))-1,0) -> -0.078234923 | J27: =-IFERROR(((1-J45/J15)^(360/J$4))-1,0) -> -0.077147722 | K27: =-IFERROR(((1-K45/K15)^(360/K$4))-1,0) -> -0.075473063 | ... BK27: =-IFERROR(((1-BK45/BK15)^(360/BK$4))-1,0) -> -0.01409196 | BO27: =-IFERROR(((1-BO45/BW15)^(360/BO$4))-1,0) -> -0.062334564 | BP27: =-IFERROR(((1-BP45/BX15)^(360/BP$4))-1,0) -> -0.0098278781 | BQ27: =-IFERROR(((1-BQ45/BY15)^(360/BQ$4))-1,0) -> -0.062503812 | BR27: =-IFERROR(((1-BR45/BZ15)^(360/BR$4))-1,0) -> -0.066453036 | BS27: =-IFERROR(((1-BS45/CA15)^(360/BS$4))-1,0) -> -0.075895307 | BT27: =-IFERROR(((1-BT45/CB15)^(360/BT$4))-1,0) -> -0.075197445
C28: Vencido y Judicial | D28: =-IFERROR(((1-D46/D16)^(360/D$4))-1,0) -> -0.043371127 | E28: =-IFERROR(((1-E46/E16)^(360/E$4))-1,0) -> -0.043510018 | F28: =-IFERROR(((1-F46/F16)^(360/F$4))-1,0) -> -0.044435647 | G28: =-IFERROR(((1-G46/G16)^(360/G$4))-1,0) -> -0.045703919 | H28: =-IFERROR(((1-H46/H16)^(360/H$4))-1,0) -> -0.048523676 | I28: =-IFERROR(((1-I46/I16)^(360/I$4))-1,0) -> -0.074620188 | J28: =-IFERROR(((1-J46/J16)^(360/J$4))-1,0) -> -0.058808875 | K28: =-IFERROR(((1-K46/K16)^(360/K$4))-1,0) -> -0.077288629 | ... BK28: =-IFERROR(((1-BK46/BK16)^(360/BK$4))-1,0) -> -0.051043832 | BO28: =-IFERROR(((1-BO46/BW16)^(360/BO$4))-1,0) -> -0.0695619 | BP28: =-IFERROR(((1-BP46/BX16)^(360/BP$4))-1,0) -> -0.049273724 | BQ28: =-IFERROR(((1-BQ46/BY16)^(360/BQ$4))-1,0) -> -0.069947202 | BR28: =-IFERROR(((1-BR46/BZ16)^(360/BR$4))-1,0) -> -0.076444819 | BS28: =-IFERROR(((1-BS46/CA16)^(360/BS$4))-1,0) -> -0.072862045 | BT28: =-IFERROR(((1-BT46/CB16)^(360/BT$4))-1,0) -> -0.043699913
C29: Tasa FTP | D29: =-IFERROR(((1-D47/D17)^(360/D$4))-1,0) -> -0.068761404 | E29: =-IFERROR(((1-E47/E17)^(360/E$4))-1,0) -> -0.071256634 | F29: =-IFERROR(((1-F47/F17)^(360/F$4))-1,0) -> -0.073231814 | G29: =-IFERROR(((1-G47/G17)^(360/G$4))-1,0) -> -0.074504643 | H29: =-IFERROR(((1-H47/H17)^(360/H$4))-1,0) -> -0.075334319 | I29: =-IFERROR(((1-I47/I17)^(360/I$4))-1,0) -> -0.077046139 | J29: =-IFERROR(((1-J47/J17)^(360/J$4))-1,0) -> -0.076508696 | K29: =-IFERROR(((1-K47/K17)^(360/K$4))-1,0) -> -0.07684013 | ... BK29: =-IFERROR(((1-BK47/BK17)^(360/BK$4))-1,0) -> -0.059551513 | BO29: =-IFERROR(((1-BO47/BW17)^(360/BO$4))-1,0) -> -0.061982088 | BP29: =-IFERROR(((1-BP47/BX17)^(360/BP$4))-1,0) -> -0.062649114 | BQ29: =-IFERROR(((1-BQ47/BY17)^(360/BQ$4))-1,0) -> -0.06236484 | BR29: =-IFERROR(((1-BR47/BZ17)^(360/BR$4))-1,0) -> -0.070409998 | BS29: =-IFERROR(((1-BS47/CA17)^(360/BS$4))-1,0) -> -0.077418736 | BT29: =-IFERROR(((1-BT47/CB17)^(360/BT$4))-1,0) -> -0.071128209
C32: Vigente | D32: =D20+D26 -> 0.11743071 | E32: =E20+E26 -> 0.11728471 | F32: =F20+F26 -> 0.11319653 | G32: =G20+G26 -> 0.10581345 | H32: =H20+H26 -> 0.11441147 | I32: =I20+I26 -> 0.11249816 | J32: =J20+J26 -> 0.11177073 | K32: =K20+K26 -> 0.1125842 | ... BK32: =BK20+BK26 -> 0.11613035 | BO32: =BO20+BO26 -> 0.10591633 | BP32: =BP20+BP26 -> 0.10256137 | BQ32: =BQ20+BQ26 -> 0.10592141 | BR32: =BR20+BR26 -> 0.099836833 | BS32: =BS20+BS26 -> 0.09564979 | BT32: =BT20+BT26 -> 0.11590915
C33: Refinanciado | D33: =D21+D27 -> -0.00097010657 | E33: =E21+E27 -> 0.0050370413 | F33: =F21+F27 -> -0.017092727 | G33: =G21+G27 -> -0.025923344 | H33: =H21+H27 -> -0.021724256 | I33: =I21+I27 -> -0.021100532 | J33: =J21+J27 -> -0.011330269 | K33: =K21+K27 -> -0.0078501421 | ... BK33: =BK21+BK27 -> 0.058324088 | BO33: =BO21+BO27 -> 0.015160059 | BP33: =BP21+BP27 -> 0.062547189 | BQ33: =BQ21+BQ27 -> 0.014569429 | BR33: =BR21+BR27 -> -0.00047909846 | BS33: =BS21+BS27 -> -0.0016005962 | BT33: =BT21+BT27 -> -0.0048868324
C34: Vencido y Judicial | D34: =D22+D28 -> 0.01985102 | E34: =E22+E28 -> -0.0067429794 | F34: =F22+F28 -> 0.010767026 | G34: =G22+G28 -> 0.014036268 | H34: =H22+H28 -> 0.049213197 | I34: =I22+I28 -> 0.0037459069 | J34: =J22+J28 -> 0.031915472 | K34: =K22+K28 -> -0.014880689 | ... BK34: =BK22+BK28 -> 0.037106319 | BO34: =BO22+BO28 -> 0.023155736 | BP34: =BP22+BP28 -> 0.041025878 | BQ34: =BQ22+BQ28 -> 0.024351687 | BR34: =BR22+BR28 -> 0.018566984 | BS34: =BS22+BS28 -> -0.010640438 | BT34: =BT22+BT28 -> 0.0082732183
C35: Spread | D35: =D23+D29 -> 0.11421934 | E35: =E23+E29 -> 0.11334033 | F35: =F23+F29 -> 0.11020483 | G35: =G23+G29 -> 0.10325483 | H35: =H23+H29 -> 0.112672 | I35: =I23+I29 -> 0.10975241 | J35: =J23+J29 -> 0.10940233 | K35: =K23+K29 -> 0.10743328 | ... BK35: =BK23+BK29 -> 0.11326692 | BO35: =BO23+BO29 -> 0.10220296 | BP35: =BP23+BP29 -> 0.099920484 | BQ35: =BQ23+BQ29 -> 0.10214226 | BR35: =BR23+BR29 -> 0.094585094 | BS35: =BS23+BS29 -> 0.090147487 | BT35: =BT23+BT29 -> 0.11254716
A38: Ingreso_Financiero | C38: Vigente | D38: =Renta_Alta!D38+Masivo!D38+Consumo_Inicial!D38 -> 46940.23 | E38: =Renta_Alta!E38+Masivo!E38+Consumo_Inicial!E38 -> 43757.553 | F38: =Renta_Alta!F38+Masivo!F38+Consumo_Inicial!F38 -> 49752.553 | G38: =Renta_Alta!G38+Masivo!G38+Consumo_Inicial!G38 -> 48101.629 | H38: =Renta_Alta!H38+Masivo!H38+Consumo_Inicial!H38 -> 53270 | I38: =Renta_Alta!I38+Masivo!I38+Consumo_Inicial!I38 -> 52079.985 | J38: =Renta_Alta!J38+Masivo!J38+Consumo_Inicial!J38 -> 54240.017 | K38: =Renta_Alta!K38+Masivo!K38+Consumo_Inicial!K38 -> 54951.593 | ... BK38: =Renta_Alta!BK38+Masivo!BK38+Consumo_Inicial!BK38 -> 48532.114 | BO38: =SUMIFS($D38:$BM38,$D$6:$BM$6,">="&BO$2,$D$6:$BM$6,"<="&BO$6,$D$5:$BM$5,BO$5) -> 120956.71 | BP38: =SUMIFS($D38:$BM38,$D$6:$BM$6,">="&BP$2,$D$6:$BM$6,"<="&BP$6,$D$5:$BM$5,BP$5) -> 118424.28 | BQ38: =SUMIFS($D38:$BM38,$D$6:$BM$6,">="&BQ$2,$D$6:$BM$6,"<="&BQ$6,$D$5:$BM$5,BQ$5) -> 78634.669 | BR38: =SUMIFS($D38:$BM38,$D$6:$BM$6,">="&BR$2,$D$6:$BM$6,"<="&BR$6,$D$5:$BM$5,BR$5) -> 111842.2 | BS38: =SUMIFS($D38:$BM38,$D$6:$BM$6,">="&BS$2,$D$6:$BM$6,"<="&BS$6,$D$5:$BM$5,BS$5) -> 143334.29 | BT38: =SUMIFS($D38:$BM38,$D$6:$BM$6,">="&BT$2,$D$6:$BM$6,"<="&BT$6,$D$5:$BM$5,BT$5) -> 140450.34
A39: Ingreso_Financiero | C39: Refinanciado | D39: =Renta_Alta!D39+Masivo!D39+Consumo_Inicial!D39 -> 68.97276 | E39: =Renta_Alta!E39+Masivo!E39+Consumo_Inicial!E39 -> 72.58229 | F39: =Renta_Alta!F39+Masivo!F39+Consumo_Inicial!F39 -> 62.902324 | G39: =Renta_Alta!G39+Masivo!G39+Consumo_Inicial!G39 -> 50.5593 | H39: =Renta_Alta!H39+Masivo!H39+Consumo_Inicial!H39 -> 52.503721 | I39: =Renta_Alta!I39+Masivo!I39+Consumo_Inicial!I39 -> 47.076919 | J39: =Renta_Alta!J39+Masivo!J39+Consumo_Inicial!J39 -> 52.365151 | K39: =Renta_Alta!K39+Masivo!K39+Consumo_Inicial!K39 -> 48.801623 | ... BK39: =Renta_Alta!BK39+Masivo!BK39+Consumo_Inicial!BK39 -> 142.66132 | BO39: =SUMIFS($D39:$BM39,$D$6:$BM$6,">="&BO$2,$D$6:$BM$6,"<="&BO$6,$D$5:$BM$5,BO$5) -> 695.13913 | BP39: =SUMIFS($D39:$BM39,$D$6:$BM$6,">="&BP$2,$D$6:$BM$6,"<="&BP$6,$D$5:$BM$5,BP$5) -> 584.43966 | BQ39: =SUMIFS($D39:$BM39,$D$6:$BM$6,">="&BQ$2,$D$6:$BM$6,"<="&BQ$6,$D$5:$BM$5,BQ$5) -> 458.59514 | BR39: =SUMIFS($D39:$BM39,$D$6:$BM$6,">="&BR$2,$D$6:$BM$6,"<="&BR$6,$D$5:$BM$5,BR$5) -> 711.22118 | BS39: =SUMIFS($D39:$BM39,$D$6:$BM$6,">="&BS$2,$D$6:$BM$6,"<="&BS$6,$D$5:$BM$5,BS$5) -> 103.81815 | BT39: =SUMIFS($D39:$BM39,$D$6:$BM$6,">="&BT$2,$D$6:$BM$6,"<="&BT$6,$D$5:$BM$5,BT$5) -> 204.45737
A40: Ingreso_Financiero | C40: Vencido y Judicial | D40: =Renta_Alta!D40+Masivo!D40+Consumo_Inicial!D40 -> 462.19593 | E40: =Renta_Alta!E40+Masivo!E40+Consumo_Inicial!E40 -> 247.08593 | F40: =Renta_Alta!F40+Masivo!F40+Consumo_Inicial!F40 -> 364.58819 | G40: =Renta_Alta!G40+Masivo!G40+Consumo_Inicial!G40 -> 368.0431 | H40: =Renta_Alta!H40+Masivo!H40+Consumo_Inicial!H40 -> 554.56828 | I40: =Renta_Alta!I40+Masivo!I40+Consumo_Inicial!I40 -> 478.24533 | J40: =Renta_Alta!J40+Masivo!J40+Consumo_Inicial!J40 -> 680.74838 | K40: =Renta_Alta!K40+Masivo!K40+Consumo_Inicial!K40 -> 721.33468 | ... BK40: =Renta_Alta!BK40+Masivo!BK40+Consumo_Inicial!BK40 -> 783.26951 | BO40: =SUMIFS($D40:$BM40,$D$6:$BM$6,">="&BO$2,$D$6:$BM$6,"<="&BO$6,$D$5:$BM$5,BO$5) -> 2236.6685 | BP40: =SUMIFS($D40:$BM40,$D$6:$BM$6,">="&BP$2,$D$6:$BM$6,"<="&BP$6,$D$5:$BM$5,BP$5) -> 2400.8776 | BQ40: =SUMIFS($D40:$BM40,$D$6:$BM$6,">="&BQ$2,$D$6:$BM$6,"<="&BQ$6,$D$5:$BM$5,BQ$5) -> 1518.9602 | BR40: =SUMIFS($D40:$BM40,$D$6:$BM$6,">="&BR$2,$D$6:$BM$6,"<="&BR$6,$D$5:$BM$5,BR$5) -> 3046.6137 | BS40: =SUMIFS($D40:$BM40,$D$6:$BM$6,">="&BS$2,$D$6:$BM$6,"<="&BS$6,$D$5:$BM$5,BS$5) -> 2728.6286 | BT40: =SUMIFS($D40:$BM40,$D$6:$BM$6,">="&BT$2,$D$6:$BM$6,"<="&BT$6,$D$5:$BM$5,BT$5) -> 1073.8701
C41: Ingreso Financiero | D41: =SUM(D38:D40) -> 47471.399 | E41: =SUM(E38:E40) -> 44077.222 | F41: =SUM(F38:F40) -> 50180.044 | G41: =SUM(G38:G40) -> 48520.232 | H41: =SUM(H38:H40) -> 53877.072 | I41: =SUM(I38:I40) -> 52605.307 | J41: =SUM(J38:J40) -> 54973.13 | K41: =SUM(K38:K40) -> 55721.729 | ... BK41: =SUM(BK38:BK40) -> 49458.045 | BO41: =SUM(BO38:BO40) -> 123888.52 | BP41: =SUM(BP38:BP40) -> 121409.6 | BQ41: =SUM(BQ38:BQ40) -> 80612.224 | BR41: =SUM(BR38:BR40) -> 115600.03 | BS41: =SUM(BS38:BS40) -> 146166.74 | BT41: =SUM(BT38:BT40) -> 141728.66
A44: FTP | C44: Vigente | D44: =Renta_Alta!D44+Masivo!D44+Consumo_Inicial!D44 -> -18314.899 | E44: =Renta_Alta!E44+Masivo!E44+Consumo_Inicial!E44 -> -17479.911 | F44: =Renta_Alta!F44+Masivo!F44+Consumo_Inicial!F44 -> -20593.257 | G44: =Renta_Alta!G44+Masivo!G44+Consumo_Inicial!G44 -> -20870.624 | H44: =Renta_Alta!H44+Masivo!H44+Consumo_Inicial!H44 -> -22264.005 | I44: =Renta_Alta!I44+Masivo!I44+Consumo_Inicial!I44 -> -22186.508 | J44: =Renta_Alta!J44+Masivo!J44+Consumo_Inicial!J44 -> -23160.984 | K44: =Renta_Alta!K44+Masivo!K44+Consumo_Inicial!K44 -> -23348.666 | ... BK44: =Renta_Alta!BK44+Masivo!BK44+Consumo_Inicial!BK44 -> -17379.246 | BO44: =SUMIFS($D44:$BM44,$D$6:$BM$6,">="&BO$2,$D$6:$BM$6,"<="&BO$6,$D$5:$BM$5,BO$5) -> -46562.954 | BP44: =SUMIFS($D44:$BM44,$D$6:$BM$6,">="&BP$2,$D$6:$BM$6,"<="&BP$6,$D$5:$BM$5,BP$5) -> -47377.887 | BQ44: =SUMIFS($D44:$BM44,$D$6:$BM$6,">="&BQ$2,$D$6:$BM$6,"<="&BQ$6,$D$5:$BM$5,BQ$5) -> -30388.423 | BR44: =SUMIFS($D44:$BM44,$D$6:$BM$6,">="&BR$2,$D$6:$BM$6,"<="&BR$6,$D$5:$BM$5,BR$5) -> -48135.909 | BS44: =SUMIFS($D44:$BM44,$D$6:$BM$6,">="&BS$2,$D$6:$BM$6,"<="&BS$6,$D$5:$BM$5,BS$5) -> -66829.581 | BT44: =SUMIFS($D44:$BM44,$D$6:$BM$6,">="&BT$2,$D$6:$BM$6,"<="&BT$6,$D$5:$BM$5,BT$5) -> -56388.067
A45: FTP | C45: Refinanciado | D45: =Renta_Alta!D45+Masivo!D45+Consumo_Inicial!D45 -> -69.87889 | E45: =Renta_Alta!E45+Masivo!E45+Consumo_Inicial!E45 -> -68.1938 | F45: =Renta_Alta!F45+Masivo!F45+Consumo_Inicial!F45 -> -80.133327 | G45: =Renta_Alta!G45+Masivo!G45+Consumo_Inicial!G45 -> -74.863039 | H45: =Renta_Alta!H45+Masivo!H45+Consumo_Inicial!H45 -> -71.864765 | I45: =Renta_Alta!I45+Masivo!I45+Consumo_Inicial!I45 -> -63.874961 | J45: =Renta_Alta!J45+Masivo!J45+Consumo_Inicial!J45 -> -61.080093 | K45: =Renta_Alta!K45+Masivo!K45+Consumo_Inicial!K45 -> -54.282557 | ... BK45: =Renta_Alta!BK45+Masivo!BK45+Consumo_Inicial!BK45 -> -28.485538 | BO45: =SUMIFS($D45:$BM45,$D$6:$BM$6,">="&BO$2,$D$6:$BM$6,"<="&BO$6,$D$5:$BM$5,BO$5) -> -562.83874 | BP45: =SUMIFS($D45:$BM45,$D$6:$BM$6,">="&BP$2,$D$6:$BM$6,"<="&BP$6,$D$5:$BM$5,BP$5) -> -81.594087 | BQ45: =SUMIFS($D45:$BM45,$D$6:$BM$6,">="&BQ$2,$D$6:$BM$6,"<="&BQ$6,$D$5:$BM$5,BQ$5) -> -374.266 | BR45: =SUMIFS($D45:$BM45,$D$6:$BM$6,">="&BR$2,$D$6:$BM$6,"<="&BR$6,$D$5:$BM$5,BR$5) -> -716.23679 | BS45: =SUMIFS($D45:$BM45,$D$6:$BM$6,">="&BS$2,$D$6:$BM$6,"<="&BS$6,$D$5:$BM$5,BS$5) -> -105.98158 | BT45: =SUMIFS($D45:$BM45,$D$6:$BM$6,">="&BT$2,$D$6:$BM$6,"<="&BT$6,$D$5:$BM$5,BT$5) -> -218.20602
A46: FTP | C46: Vencido y Judicial | D46: =Renta_Alta!D46+Masivo!D46+Consumo_Inicial!D46 -> -319.84008 | E46: =Renta_Alta!E46+Masivo!E46+Consumo_Inicial!E46 -> -291.52192 | F46: =Renta_Alta!F46+Masivo!F46+Consumo_Inicial!F46 -> -294.86772 | G46: =Renta_Alta!G46+Masivo!G46+Consumo_Inicial!G46 -> -283.31151 | H46: =Renta_Alta!H46+Masivo!H46+Consumo_Inicial!H46 -> -281.23442 | I46: =Renta_Alta!I46+Masivo!I46+Consumo_Inicial!I46 -> -456.1217 | J46: =Renta_Alta!J46+Masivo!J46+Consumo_Inicial!J46 -> -447.37926 | K46: =Renta_Alta!K46+Masivo!K46+Consumo_Inicial!K46 -> -887.60258 | ... BK46: =Renta_Alta!BK46+Masivo!BK46+Consumo_Inicial!BK46 -> -460.89323 | BO46: =SUMIFS($D46:$BM46,$D$6:$BM$6,">="&BO$2,$D$6:$BM$6,"<="&BO$6,$D$5:$BM$5,BO$5) -> -1694.8612 | BP46: =SUMIFS($D46:$BM46,$D$6:$BM$6,">="&BP$2,$D$6:$BM$6,"<="&BP$6,$D$5:$BM$5,BP$5) -> -1333.6037 | BQ46: =SUMIFS($D46:$BM46,$D$6:$BM$6,">="&BQ$2,$D$6:$BM$6,"<="&BQ$6,$D$5:$BM$5,BQ$5) -> -1138.5715 | BR46: =SUMIFS($D46:$BM46,$D$6:$BM$6,">="&BR$2,$D$6:$BM$6,"<="&BR$6,$D$5:$BM$5,BR$5) -> -2470.8278 | BS46: =SUMIFS($D46:$BM46,$D$6:$BM$6,">="&BS$2,$D$6:$BM$6,"<="&BS$6,$D$5:$BM$5,BS$5) -> -3180.5275 | BT46: =SUMIFS($D46:$BM46,$D$6:$BM$6,">="&BT$2,$D$6:$BM$6,"<="&BT$6,$D$5:$BM$5,BT$5) -> -906.22973
C47: Costo de Fondos | D47: =SUM(D44:D46) -> -18704.618 | E47: =SUM(E44:E46) -> -17839.626 | F47: =SUM(F44:F46) -> -20968.258 | G47: =SUM(G44:G46) -> -21228.799 | H47: =SUM(H44:H46) -> -22617.104 | I47: =SUM(I44:I46) -> -22706.505 | J47: =SUM(J44:J46) -> -23669.444 | K47: =SUM(K44:K46) -> -24290.551 | ... BK47: =SUM(BK44:BK46) -> -17868.625 | BO47: =SUM(BO44:BO46) -> -48820.654 | BP47: =SUM(BP44:BP46) -> -48793.085 | BQ47: =SUM(BQ44:BQ46) -> -31901.26 | BR47: =SUM(BR44:BR46) -> -51322.974 | BS47: =SUM(BS44:BS46) -> -70116.09 | BT47: =SUM(BT44:BT46) -> -57512.503
C50: Vigente | D50: =D38+D44 -> 28625.331 | E50: =E38+E44 -> 26277.643 | F50: =F38+F44 -> 29159.296 | G50: =G38+G44 -> 27231.005 | H50: =H38+H44 -> 31005.996 | I50: =I38+I44 -> 29893.477 | J50: =J38+J44 -> 31079.032 | K50: =K38+K44 -> 31602.927 | ... BK50: =BK38+BK44 -> 31152.868 | BO50: =BO38+BO44 -> 74393.754 | BP50: =BP38+BP44 -> 71046.397 | BQ50: =BQ38+BQ44 -> 48246.246 | BR50: =BR38+BR44 -> 63706.288 | BS50: =BS38+BS44 -> 76504.711 | BT50: =BT38+BT44 -> 84062.27
C51: Refinanciado | D51: =D39+D45 -> -0.90613 | E51: =E39+E45 -> 4.38849 | F51: =F39+F45 -> -17.231003 | G51: =G39+G45 -> -24.303739 | H51: =H39+H45 -> -19.361045 | I51: =I39+I45 -> -16.798041 | J51: =J39+J45 -> -8.7149414 | K51: =K39+K45 -> -5.4809338 | ... BK51: =BK39+BK45 -> 114.17578 | BO51: =BO39+BO45 -> 132.30039 | BP51: =BP39+BP45 -> 502.84558 | BQ51: =BQ39+BQ45 -> 84.32914 | BR51: =BR39+BR45 -> -5.0156101 | BS51: =BS39+BS45 -> -2.16343 | BT51: =BT39+BT45 -> -13.748643
C52: Vencido y Judicial | D52: =D40+D46 -> 142.35585 | E52: =E40+E46 -> -44.435994 | F52: =F40+F46 -> 69.720474 | G52: =G40+G46 -> 84.731595 | H52: =H40+H46 -> 273.33386 | I52: =I40+I46 -> 22.123629 | J52: =J40+J46 -> 233.36912 | K52: =K40+K46 -> -166.2679 | ... BK52: =BK40+BK46 -> 322.37627 | BO52: =BO40+BO46 -> 541.80728 | BP52: =BP40+BP46 -> 1067.2739 | BQ52: =BQ40+BQ46 -> 380.38869 | BR52: =BR40+BR46 -> 575.78597 | BS52: =BS40+BS46 -> -451.89887 | BT52: =BT40+BT46 -> 167.64033
C53: Resultado Financiero Bruto | D53: =D41+D47 -> 28766.781 | E53: =E41+E47 -> 26237.595 | F53: =F41+F47 -> 29211.785 | G53: =G41+G47 -> 27291.433 | H53: =H41+H47 -> 31259.968 | I53: =I41+I47 -> 29898.802 | J53: =J41+J47 -> 31303.687 | K53: =K41+K47 -> 31431.178 | ... BK53: =BK41+BK47 -> 31589.42 | BO53: =SUM(BO50:BO52) -> 75067.861 | BP53: =SUM(BP50:BP52) -> 72616.517 | BQ53: =SUM(BQ50:BQ52) -> 48710.964 | BR53: =SUM(BR50:BR52) -> 64277.059 | BS53: =SUM(BS50:BS52) -> 76050.649 | BT53: =SUM(BT50:BT52) -> 84216.161
D54: =[1]Desempeño_Financiero_Evol!BA361-D53 -> 4.3200052e-06 | E54: =[1]Desempeño_Financiero_Evol!BB361-E53 -> 3.1399977e-06 | F54: =[1]Desempeño_Financiero_Evol!BC361-F53 -> 3.0899901e-06 | G54: =[1]Desempeño_Financiero_Evol!BD361-G53 -> -2.9000148e-07 | H54: =[1]Desempeño_Financiero_Evol!BE361-H53 -> -2.5599911e-06 | I54: =[1]Desempeño_Financiero_Evol!BF361-I53 -> -2.350007e-06 | J54: =[1]Desempeño_Financiero_Evol!BG361-J53 -> -5.4299926e-06 | K54: =[1]Desempeño_Financiero_Evol!BH361-K53 -> 8.4001294e-07 | ... AZ54: =[1]Desempeño_Financiero_Evol!CW361-AZ53 -> 0
A56: Gasto_Provision | C56: Provisiones Cartera | D56: =Renta_Alta!D56+Masivo!D56+Consumo_Inicial!D56 -> -25142.899 | E56: =Renta_Alta!E56+Masivo!E56+Consumo_Inicial!E56 -> -14922.557 | F56: =Renta_Alta!F56+Masivo!F56+Consumo_Inicial!F56 -> -25857.675 | G56: =Renta_Alta!G56+Masivo!G56+Consumo_Inicial!G56 -> -23798.517 | H56: =Renta_Alta!H56+Masivo!H56+Consumo_Inicial!H56 -> -38254.202 | I56: =Renta_Alta!I56+Masivo!I56+Consumo_Inicial!I56 -> -45300.067 | J56: =Renta_Alta!J56+Masivo!J56+Consumo_Inicial!J56 -> -49076.282 | K56: =Renta_Alta!K56+Masivo!K56+Consumo_Inicial!K56 -> -66625.356 | ... BK56: =Renta_Alta!BK56+Masivo!BK56+Consumo_Inicial!BK56 -> -18836.399 | BO56: =SUMIFS($D56:$BM56,$D$6:$BM$6,">="&BO$2,$D$6:$BM$6,"<="&BO$6,$D$5:$BM$5,BO$5) -> -45656.085 | BP56: =SUMIFS($D56:$BM56,$D$6:$BM$6,">="&BP$2,$D$6:$BM$6,"<="&BP$6,$D$5:$BM$5,BP$5) -> -61138.285 | BQ56: =SUMIFS($D56:$BM56,$D$6:$BM$6,">="&BQ$2,$D$6:$BM$6,"<="&BQ$6,$D$5:$BM$5,BQ$5) -> -30820.251 | BR56: =SUMIFS($D56:$BM56,$D$6:$BM$6,">="&BR$2,$D$6:$BM$6,"<="&BR$6,$D$5:$BM$5,BR$5) -> -89731.923 | BS56: =SUMIFS($D56:$BM56,$D$6:$BM$6,">="&BS$2,$D$6:$BM$6,"<="&BS$6,$D$5:$BM$5,BS$5) -> -223843.64 | BT56: =SUMIFS($D56:$BM56,$D$6:$BM$6,">="&BT$2,$D$6:$BM$6,"<="&BT$6,$D$5:$BM$5,BT$5) -> -65923.131
A57: Recupero | C57: Recupero de Castigos | D57: =Renta_Alta!D57+Masivo!D57+Consumo_Inicial!D57 -> 1096.4763 | E57: =Renta_Alta!E57+Masivo!E57+Consumo_Inicial!E57 -> 1139.1332 | F57: =Renta_Alta!F57+Masivo!F57+Consumo_Inicial!F57 -> 1415.9338 | G57: =Renta_Alta!G57+Masivo!G57+Consumo_Inicial!G57 -> 913.59794 | H57: =Renta_Alta!H57+Masivo!H57+Consumo_Inicial!H57 -> 1021.497 | I57: =Renta_Alta!I57+Masivo!I57+Consumo_Inicial!I57 -> 1229.3772 | J57: =Renta_Alta!J57+Masivo!J57+Consumo_Inicial!J57 -> 1097.8174 | K57: =Renta_Alta!K57+Masivo!K57+Consumo_Inicial!K57 -> 1275.8261 | ... BK57: =Renta_Alta!BK57+Masivo!BK57+Consumo_Inicial!BK57 -> 1067.2731 | BO57: =SUMIFS($D57:$BM57,$D$6:$BM$6,">="&BO$2,$D$6:$BM$6,"<="&BO$6,$D$5:$BM$5,BO$5) -> 5556.1376 | BP57: =SUMIFS($D57:$BM57,$D$6:$BM$6,">="&BP$2,$D$6:$BM$6,"<="&BP$6,$D$5:$BM$5,BP$5) -> 3480.4536 | BQ57: =SUMIFS($D57:$BM57,$D$6:$BM$6,">="&BQ$2,$D$6:$BM$6,"<="&BQ$6,$D$5:$BM$5,BQ$5) -> 3567.904 | BR57: =SUMIFS($D57:$BM57,$D$6:$BM$6,">="&BR$2,$D$6:$BM$6,"<="&BR$6,$D$5:$BM$5,BR$5) -> 9433.478 | BS57: =SUMIFS($D57:$BM57,$D$6:$BM$6,">="&BS$2,$D$6:$BM$6,"<="&BS$6,$D$5:$BM$5,BS$5) -> 4206.3886 | BT57: =SUMIFS($D57:$BM57,$D$6:$BM$6,">="&BT$2,$D$6:$BM$6,"<="&BT$6,$D$5:$BM$5,BT$5) -> 3651.5433
C58: Provisiones Netas | D58: =SUM(D56:D57) -> -24046.422 | E58: =SUM(E56:E57) -> -13783.424 | F58: =SUM(F56:F57) -> -24441.742 | G58: =SUM(G56:G57) -> -22884.919 | H58: =SUM(H56:H57) -> -37232.705 | I58: =SUM(I56:I57) -> -44070.69 | J58: =SUM(J56:J57) -> -47978.464 | K58: =SUM(K56:K57) -> -65349.53 | ... BK58: =SUM(BK56:BK57) -> -17769.126 | BO58: =SUM(BO56:BO57) -> -40099.948 | BP58: =SUM(BP56:BP57) -> -57657.832 | BQ58: =SUM(BQ56:BQ57) -> -27252.347 | BR58: =SUM(BR56:BR57) -> -80298.445 | BS58: =SUM(BS56:BS57) -> -219637.25 | BT58: =SUM(BT56:BT57) -> -62271.588
C60: Resultado Financiero Neto | D60: =D53+D58 -> 4720.3588 | E60: =E53+E58 -> 12454.171 | F60: =F53+F58 -> 4770.0436 | G60: =G53+G58 -> 4406.5139 | H60: =H53+H58 -> -5972.7369 | I60: =I53+I58 -> -14171.888 | J60: =J53+J58 -> -16674.778 | K60: =K53+K58 -> -33918.352 | ... BK60: =BK53+BK58 -> 13820.294 | BO60: =BO53+BO58 -> 34967.914 | BP60: =BP53+BP58 -> 14958.685 | BQ60: =BQ53+BQ58 -> 21458.617 | BR60: =BR53+BR58 -> -16021.387 | BS60: =BS53+BS58 -> -143586.6 | BT60: =BT53+BT58 -> 21944.574
D61: =[1]Desempeño_Financiero_Evol!BA407-D60 -> -0.16823425 | E61: =[1]Desempeño_Financiero_Evol!BB407-E60 -> 3.1400014e-06 | F61: =[1]Desempeño_Financiero_Evol!BC407-F60 -> 0.19362029 | G61: =[1]Desempeño_Financiero_Evol!BD407-G60 -> -2.8999875e-07 | H61: =[1]Desempeño_Financiero_Evol!BE407-H60 -> -2.559982e-06 | I61: =[1]Desempeño_Financiero_Evol!BF407-I60 -> -2.3500143e-06 | J61: =[1]Desempeño_Financiero_Evol!BG407-J60 -> -5.4299926e-06 | K61: =[1]Desempeño_Financiero_Evol!BH407-K60 -> 8.4000203e-07 | ... AZ61: =[1]Desempeño_Financiero_Evol!CW407-AZ60 -> 0
A63: INOF | C63: Seguro de Desgravamen | D63: =Renta_Alta!D63+Masivo!D63+Consumo_Inicial!D63 -> 381.75112 | E63: =Renta_Alta!E63+Masivo!E63+Consumo_Inicial!E63 -> 355.94817 | F63: =Renta_Alta!F63+Masivo!F63+Consumo_Inicial!F63 -> 293.71883 | G63: =Renta_Alta!G63+Masivo!G63+Consumo_Inicial!G63 -> 443.65615 | H63: =Renta_Alta!H63+Masivo!H63+Consumo_Inicial!H63 -> 368.75342 | I63: =Renta_Alta!I63+Masivo!I63+Consumo_Inicial!I63 -> 429.45294 | J63: =Renta_Alta!J63+Masivo!J63+Consumo_Inicial!J63 -> 404.47894 | K63: =Renta_Alta!K63+Masivo!K63+Consumo_Inicial!K63 -> 436.98072 | ... BK63: =Renta_Alta!BK63+Masivo!BK63+Consumo_Inicial!BK63 -> 357.098 | BO63: =SUMIFS($D63:$BM63,$D$6:$BM$6,">="&BO$2,$D$6:$BM$6,"<="&BO$6,$D$5:$BM$5,BO$5) -> 913.56677 | BP63: =SUMIFS($D63:$BM63,$D$6:$BM$6,">="&BP$2,$D$6:$BM$6,"<="&BP$6,$D$5:$BM$5,BP$5) -> 935.38422 | BQ63: =SUMIFS($D63:$BM63,$D$6:$BM$6,">="&BQ$2,$D$6:$BM$6,"<="&BQ$6,$D$5:$BM$5,BQ$5) -> 627.63972 | BR63: =SUMIFS($D63:$BM63,$D$6:$BM$6,">="&BR$2,$D$6:$BM$6,"<="&BR$6,$D$5:$BM$5,BR$5) -> 780.06137 | BS63: =SUMIFS($D63:$BM63,$D$6:$BM$6,">="&BS$2,$D$6:$BM$6,"<="&BS$6,$D$5:$BM$5,BS$5) -> 1241.7416 | BT63: =SUMIFS($D63:$BM63,$D$6:$BM$6,">="&BT$2,$D$6:$BM$6,"<="&BT$6,$D$5:$BM$5,BT$5) -> 1031.4181
A64: INOF | C64: Comisión por envío EC | D64: =Renta_Alta!D64+Masivo!D64+Consumo_Inicial!D64 -> 2.67833 | E64: =Renta_Alta!E64+Masivo!E64+Consumo_Inicial!E64 -> 2.29501 | F64: =Renta_Alta!F64+Masivo!F64+Consumo_Inicial!F64 -> 2.18633 | G64: =Renta_Alta!G64+Masivo!G64+Consumo_Inicial!G64 -> 1.75663 | H64: =Renta_Alta!H64+Masivo!H64+Consumo_Inicial!H64 -> 2.007 | I64: =Renta_Alta!I64+Masivo!I64+Consumo_Inicial!I64 -> 1.715 | J64: =Renta_Alta!J64+Masivo!J64+Consumo_Inicial!J64 -> 1.47433 | K64: =Renta_Alta!K64+Masivo!K64+Consumo_Inicial!K64 -> 1.50434 | ... BK64: =Renta_Alta!BK64+Masivo!BK64+Consumo_Inicial!BK64 -> 0.90652286 | BO64: =SUMIFS($D64:$BM64,$D$6:$BM$6,">="&BO$2,$D$6:$BM$6,"<="&BO$6,$D$5:$BM$5,BO$5) -> 1.89266 | BP64: =SUMIFS($D64:$BM64,$D$6:$BM$6,">="&BP$2,$D$6:$BM$6,"<="&BP$6,$D$5:$BM$5,BP$5) -> 2.7195686 | BQ64: =SUMIFS($D64:$BM64,$D$6:$BM$6,">="&BQ$2,$D$6:$BM$6,"<="&BQ$6,$D$5:$BM$5,BQ$5) -> 1.22433 | BR64: =SUMIFS($D64:$BM64,$D$6:$BM$6,">="&BR$2,$D$6:$BM$6,"<="&BR$6,$D$5:$BM$5,BR$5) -> 3.207 | BS64: =SUMIFS($D64:$BM64,$D$6:$BM$6,">="&BS$2,$D$6:$BM$6,"<="&BS$6,$D$5:$BM$5,BS$5) -> 4.22566 | BT64: =SUMIFS($D64:$BM64,$D$6:$BM$6,">="&BT$2,$D$6:$BM$6,"<="&BT$6,$D$5:$BM$5,BT$5) -> 7.15967
A65: INOF | C65: Varios | D65: =Renta_Alta!D65+Masivo!D65+Consumo_Inicial!D65 -> 0.18 | E65: =Renta_Alta!E65+Masivo!E65+Consumo_Inicial!E65 -> 0 | F65: =Renta_Alta!F65+Masivo!F65+Consumo_Inicial!F65 -> 0 | G65: =Renta_Alta!G65+Masivo!G65+Consumo_Inicial!G65 -> 0 | H65: =Renta_Alta!H65+Masivo!H65+Consumo_Inicial!H65 -> 0 | I65: =Renta_Alta!I65+Masivo!I65+Consumo_Inicial!I65 -> 0.2 | J65: =Renta_Alta!J65+Masivo!J65+Consumo_Inicial!J65 -> 0 | K65: =Renta_Alta!K65+Masivo!K65+Consumo_Inicial!K65 -> 0 | ... BK65: =Renta_Alta!BK65+Masivo!BK65+Consumo_Inicial!BK65 -> 0 | BO65: =SUMIFS($D65:$BM65,$D$6:$BM$6,">="&BO$2,$D$6:$BM$6,"<="&BO$6,$D$5:$BM$5,BO$5) -> 0.55 | BP65: =SUMIFS($D65:$BM65,$D$6:$BM$6,">="&BP$2,$D$6:$BM$6,"<="&BP$6,$D$5:$BM$5,BP$5) -> 0 | BQ65: =SUMIFS($D65:$BM65,$D$6:$BM$6,">="&BQ$2,$D$6:$BM$6,"<="&BQ$6,$D$5:$BM$5,BQ$5) -> 0.26 | BR65: =SUMIFS($D65:$BM65,$D$6:$BM$6,">="&BR$2,$D$6:$BM$6,"<="&BR$6,$D$5:$BM$5,BR$5) -> 0.18 | BS65: =SUMIFS($D65:$BM65,$D$6:$BM$6,">="&BS$2,$D$6:$BM$6,"<="&BS$6,$D$5:$BM$5,BS$5) -> -0.14968 | BT65: =SUMIFS($D65:$BM65,$D$6:$BM$6,">="&BT$2,$D$6:$BM$6,"<="&BT$6,$D$5:$BM$5,BT$5) -> 0.18
A66: INOF | D66: =Renta_Alta!D66+Masivo!D66+Consumo_Inicial!D66 -> 0 | E66: =Renta_Alta!E66+Masivo!E66+Consumo_Inicial!E66 -> 0 | F66: =Renta_Alta!F66+Masivo!F66+Consumo_Inicial!F66 -> 0 | G66: =Renta_Alta!G66+Masivo!G66+Consumo_Inicial!G66 -> 0 | H66: =Renta_Alta!H66+Masivo!H66+Consumo_Inicial!H66 -> 0 | I66: =Renta_Alta!I66+Masivo!I66+Consumo_Inicial!I66 -> 0 | J66: =Renta_Alta!J66+Masivo!J66+Consumo_Inicial!J66 -> 0 | K66: =Renta_Alta!K66+Masivo!K66+Consumo_Inicial!K66 -> 0 | ... BK66: =Renta_Alta!BK66+Masivo!BK66+Consumo_Inicial!BK66 -> 0 | BO66: =SUMIFS($D66:$BM66,$D$6:$BM$6,">="&BO$2,$D$6:$BM$6,"<="&BO$6,$D$5:$BM$5,BO$5) -> 0 | BP66: =SUMIFS($D66:$BM66,$D$6:$BM$6,">="&BP$2,$D$6:$BM$6,"<="&BP$6,$D$5:$BM$5,BP$5) -> 0 | BQ66: =SUMIFS($D66:$BM66,$D$6:$BM$6,">="&BQ$2,$D$6:$BM$6,"<="&BQ$6,$D$5:$BM$5,BQ$5) -> 0 | BR66: =SUMIFS($D66:$BM66,$D$6:$BM$6,">="&BR$2,$D$6:$BM$6,"<="&BR$6,$D$5:$BM$5,BR$5) -> 0 | BS66: =SUMIFS($D66:$BM66,$D$6:$BM$6,">="&BS$2,$D$6:$BM$6,"<="&BS$6,$D$5:$BM$5,BS$5) -> 0 | BT66: =SUMIFS($D66:$BM66,$D$6:$BM$6,">="&BT$2,$D$6:$BM$6,"<="&BT$6,$D$5:$BM$5,BT$5) -> 0
A67: INOF | D67: =Renta_Alta!D67+Masivo!D67+Consumo_Inicial!D67 -> 0 | E67: =Renta_Alta!E67+Masivo!E67+Consumo_Inicial!E67 -> 0 | F67: =Renta_Alta!F67+Masivo!F67+Consumo_Inicial!F67 -> 0 | G67: =Renta_Alta!G67+Masivo!G67+Consumo_Inicial!G67 -> 0 | H67: =Renta_Alta!H67+Masivo!H67+Consumo_Inicial!H67 -> 0 | I67: =Renta_Alta!I67+Masivo!I67+Consumo_Inicial!I67 -> 0 | J67: =Renta_Alta!J67+Masivo!J67+Consumo_Inicial!J67 -> 0 | K67: =Renta_Alta!K67+Masivo!K67+Consumo_Inicial!K67 -> 0 | ... BK67: =Renta_Alta!BK67+Masivo!BK67+Consumo_Inicial!BK67 -> 0 | BO67: =SUMIFS($D67:$BM67,$D$6:$BM$6,">="&BO$2,$D$6:$BM$6,"<="&BO$6,$D$5:$BM$5,BO$5) -> 0 | BP67: =SUMIFS($D67:$BM67,$D$6:$BM$6,">="&BP$2,$D$6:$BM$6,"<="&BP$6,$D$5:$BM$5,BP$5) -> 0 | BQ67: =SUMIFS($D67:$BM67,$D$6:$BM$6,">="&BQ$2,$D$6:$BM$6,"<="&BQ$6,$D$5:$BM$5,BQ$5) -> 0 | BR67: =SUMIFS($D67:$BM67,$D$6:$BM$6,">="&BR$2,$D$6:$BM$6,"<="&BR$6,$D$5:$BM$5,BR$5) -> 0 | BS67: =SUMIFS($D67:$BM67,$D$6:$BM$6,">="&BS$2,$D$6:$BM$6,"<="&BS$6,$D$5:$BM$5,BS$5) -> 0 | BT67: =SUMIFS($D67:$BM67,$D$6:$BM$6,">="&BT$2,$D$6:$BM$6,"<="&BT$6,$D$5:$BM$5,BT$5) -> 0
A68: INOF | D68: =Renta_Alta!D68+Masivo!D68+Consumo_Inicial!D68 -> 0 | E68: =Renta_Alta!E68+Masivo!E68+Consumo_Inicial!E68 -> 0 | F68: =Renta_Alta!F68+Masivo!F68+Consumo_Inicial!F68 -> 0 | G68: =Renta_Alta!G68+Masivo!G68+Consumo_Inicial!G68 -> 0 | H68: =Renta_Alta!H68+Masivo!H68+Consumo_Inicial!H68 -> 0 | I68: =Renta_Alta!I68+Masivo!I68+Consumo_Inicial!I68 -> 0 | J68: =Renta_Alta!J68+Masivo!J68+Consumo_Inicial!J68 -> 0 | K68: =Renta_Alta!K68+Masivo!K68+Consumo_Inicial!K68 -> 0 | ... BK68: =Renta_Alta!BK68+Masivo!BK68+Consumo_Inicial!BK68 -> 0 | BO68: =SUMIFS($D68:$BM68,$D$6:$BM$6,">="&BO$2,$D$6:$BM$6,"<="&BO$6,$D$5:$BM$5,BO$5) -> 0 | BP68: =SUMIFS($D68:$BM68,$D$6:$BM$6,">="&BP$2,$D$6:$BM$6,"<="&BP$6,$D$5:$BM$5,BP$5) -> 0 | BQ68: =SUMIFS($D68:$BM68,$D$6:$BM$6,">="&BQ$2,$D$6:$BM$6,"<="&BQ$6,$D$5:$BM$5,BQ$5) -> 0 | BR68: =SUMIFS($D68:$BM68,$D$6:$BM$6,">="&BR$2,$D$6:$BM$6,"<="&BR$6,$D$5:$BM$5,BR$5) -> 0 | BS68: =SUMIFS($D68:$BM68,$D$6:$BM$6,">="&BS$2,$D$6:$BM$6,"<="&BS$6,$D$5:$BM$5,BS$5) -> 0 | BT68: =SUMIFS($D68:$BM68,$D$6:$BM$6,">="&BT$2,$D$6:$BM$6,"<="&BT$6,$D$5:$BM$5,BT$5) -> 0
A69: INOF | D69: =Renta_Alta!D69+Masivo!D69+Consumo_Inicial!D69 -> 0 | E69: =Renta_Alta!E69+Masivo!E69+Consumo_Inicial!E69 -> 0 | F69: =Renta_Alta!F69+Masivo!F69+Consumo_Inicial!F69 -> 0 | G69: =Renta_Alta!G69+Masivo!G69+Consumo_Inicial!G69 -> 0 | H69: =Renta_Alta!H69+Masivo!H69+Consumo_Inicial!H69 -> 0 | I69: =Renta_Alta!I69+Masivo!I69+Consumo_Inicial!I69 -> 0 | J69: =Renta_Alta!J69+Masivo!J69+Consumo_Inicial!J69 -> 0 | K69: =Renta_Alta!K69+Masivo!K69+Consumo_Inicial!K69 -> 0 | ... BK69: =Renta_Alta!BK69+Masivo!BK69+Consumo_Inicial!BK69 -> 0 | BO69: =SUMIFS($D69:$BM69,$D$6:$BM$6,">="&BO$2,$D$6:$BM$6,"<="&BO$6,$D$5:$BM$5,BO$5) -> 0 | BP69: =SUMIFS($D69:$BM69,$D$6:$BM$6,">="&BP$2,$D$6:$BM$6,"<="&BP$6,$D$5:$BM$5,BP$5) -> 0 | BQ69: =SUMIFS($D69:$BM69,$D$6:$BM$6,">="&BQ$2,$D$6:$BM$6,"<="&BQ$6,$D$5:$BM$5,BQ$5) -> 0 | BR69: =SUMIFS($D69:$BM69,$D$6:$BM$6,">="&BR$2,$D$6:$BM$6,"<="&BR$6,$D$5:$BM$5,BR$5) -> 0 | BS69: =SUMIFS($D69:$BM69,$D$6:$BM$6,">="&BS$2,$D$6:$BM$6,"<="&BS$6,$D$5:$BM$5,BS$5) -> 0 | BT69: =SUMIFS($D69:$BM69,$D$6:$BM$6,">="&BT$2,$D$6:$BM$6,"<="&BT$6,$D$5:$BM$5,BT$5) -> 0
A70: INOF | D70: =Renta_Alta!D70+Masivo!D70+Consumo_Inicial!D70 -> 0 | E70: =Renta_Alta!E70+Masivo!E70+Consumo_Inicial!E70 -> 0 | F70: =Renta_Alta!F70+Masivo!F70+Consumo_Inicial!F70 -> 0 | G70: =Renta_Alta!G70+Masivo!G70+Consumo_Inicial!G70 -> 0 | H70: =Renta_Alta!H70+Masivo!H70+Consumo_Inicial!H70 -> 0 | I70: =Renta_Alta!I70+Masivo!I70+Consumo_Inicial!I70 -> 0 | J70: =Renta_Alta!J70+Masivo!J70+Consumo_Inicial!J70 -> 0 | K70: =Renta_Alta!K70+Masivo!K70+Consumo_Inicial!K70 -> 0 | ... BK70: =Renta_Alta!BK70+Masivo!BK70+Consumo_Inicial!BK70 -> 0 | BO70: =SUMIFS($D70:$BM70,$D$6:$BM$6,">="&BO$2,$D$6:$BM$6,"<="&BO$6,$D$5:$BM$5,BO$5) -> 0 | BP70: =SUMIFS($D70:$BM70,$D$6:$BM$6,">="&BP$2,$D$6:$BM$6,"<="&BP$6,$D$5:$BM$5,BP$5) -> 0 | BQ70: =SUMIFS($D70:$BM70,$D$6:$BM$6,">="&BQ$2,$D$6:$BM$6,"<="&BQ$6,$D$5:$BM$5,BQ$5) -> 0 | BR70: =SUMIFS($D70:$BM70,$D$6:$BM$6,">="&BR$2,$D$6:$BM$6,"<="&BR$6,$D$5:$BM$5,BR$5) -> 0 | BS70: =SUMIFS($D70:$BM70,$D$6:$BM$6,">="&BS$2,$D$6:$BM$6,"<="&BS$6,$D$5:$BM$5,BS$5) -> 0 | BT70: =SUMIFS($D70:$BM70,$D$6:$BM$6,">="&BT$2,$D$6:$BM$6,"<="&BT$6,$D$5:$BM$5,BT$5) -> 0
A71: INOF | D71: =Renta_Alta!D71+Masivo!D71+Consumo_Inicial!D71 -> 0 | E71: =Renta_Alta!E71+Masivo!E71+Consumo_Inicial!E71 -> 0 | F71: =Renta_Alta!F71+Masivo!F71+Consumo_Inicial!F71 -> 0 | G71: =Renta_Alta!G71+Masivo!G71+Consumo_Inicial!G71 -> 0 | H71: =Renta_Alta!H71+Masivo!H71+Consumo_Inicial!H71 -> 0 | I71: =Renta_Alta!I71+Masivo!I71+Consumo_Inicial!I71 -> 0 | J71: =Renta_Alta!J71+Masivo!J71+Consumo_Inicial!J71 -> 0 | K71: =Renta_Alta!K71+Masivo!K71+Consumo_Inicial!K71 -> 0 | ... BK71: =Renta_Alta!BK71+Masivo!BK71+Consumo_Inicial!BK71 -> 0 | BO71: =SUMIFS($D71:$BM71,$D$6:$BM$6,">="&BO$2,$D$6:$BM$6,"<="&BO$6,$D$5:$BM$5,BO$5) -> 0 | BP71: =SUMIFS($D71:$BM71,$D$6:$BM$6,">="&BP$2,$D$6:$BM$6,"<="&BP$6,$D$5:$BM$5,BP$5) -> 0 | BQ71: =SUMIFS($D71:$BM71,$D$6:$BM$6,">="&BQ$2,$D$6:$BM$6,"<="&BQ$6,$D$5:$BM$5,BQ$5) -> 0 | BR71: =SUMIFS($D71:$BM71,$D$6:$BM$6,">="&BR$2,$D$6:$BM$6,"<="&BR$6,$D$5:$BM$5,BR$5) -> 0 | BS71: =SUMIFS($D71:$BM71,$D$6:$BM$6,">="&BS$2,$D$6:$BM$6,"<="&BS$6,$D$5:$BM$5,BS$5) -> 0 | BT71: =SUMIFS($D71:$BM71,$D$6:$BM$6,">="&BT$2,$D$6:$BM$6,"<="&BT$6,$D$5:$BM$5,BT$5) -> 0
A72: INOF | D72: =Renta_Alta!D72+Masivo!D72+Consumo_Inicial!D72 -> 0 | E72: =Renta_Alta!E72+Masivo!E72+Consumo_Inicial!E72 -> 0 | F72: =Renta_Alta!F72+Masivo!F72+Consumo_Inicial!F72 -> 0 | G72: =Renta_Alta!G72+Masivo!G72+Consumo_Inicial!G72 -> 0 | H72: =Renta_Alta!H72+Masivo!H72+Consumo_Inicial!H72 -> 0 | I72: =Renta_Alta!I72+Masivo!I72+Consumo_Inicial!I72 -> 0 | J72: =Renta_Alta!J72+Masivo!J72+Consumo_Inicial!J72 -> 0 | K72: =Renta_Alta!K72+Masivo!K72+Consumo_Inicial!K72 -> 0 | ... BK72: =Renta_Alta!BK72+Masivo!BK72+Consumo_Inicial!BK72 -> 0 | BO72: =SUMIFS($D72:$BM72,$D$6:$BM$6,">="&BO$2,$D$6:$BM$6,"<="&BO$6,$D$5:$BM$5,BO$5) -> 0 | BP72: =SUMIFS($D72:$BM72,$D$6:$BM$6,">="&BP$2,$D$6:$BM$6,"<="&BP$6,$D$5:$BM$5,BP$5) -> 0 | BQ72: =SUMIFS($D72:$BM72,$D$6:$BM$6,">="&BQ$2,$D$6:$BM$6,"<="&BQ$6,$D$5:$BM$5,BQ$5) -> 0 | BR72: =SUMIFS($D72:$BM72,$D$6:$BM$6,">="&BR$2,$D$6:$BM$6,"<="&BR$6,$D$5:$BM$5,BR$5) -> 0 | BS72: =SUMIFS($D72:$BM72,$D$6:$BM$6,">="&BS$2,$D$6:$BM$6,"<="&BS$6,$D$5:$BM$5,BS$5) -> 0 | BT72: =SUMIFS($D72:$BM72,$D$6:$BM$6,">="&BT$2,$D$6:$BM$6,"<="&BT$6,$D$5:$BM$5,BT$5) -> 0
A73: INOF | D73: =Renta_Alta!D73+Masivo!D73+Consumo_Inicial!D73 -> 0 | E73: =Renta_Alta!E73+Masivo!E73+Consumo_Inicial!E73 -> 0 | F73: =Renta_Alta!F73+Masivo!F73+Consumo_Inicial!F73 -> 0 | G73: =Renta_Alta!G73+Masivo!G73+Consumo_Inicial!G73 -> 0 | H73: =Renta_Alta!H73+Masivo!H73+Consumo_Inicial!H73 -> 0 | I73: =Renta_Alta!I73+Masivo!I73+Consumo_Inicial!I73 -> 0 | J73: =Renta_Alta!J73+Masivo!J73+Consumo_Inicial!J73 -> 0 | K73: =Renta_Alta!K73+Masivo!K73+Consumo_Inicial!K73 -> 0 | ... BK73: =Renta_Alta!BK73+Masivo!BK73+Consumo_Inicial!BK73 -> 0 | BO73: =SUMIFS($D73:$BM73,$D$6:$BM$6,">="&BO$2,$D$6:$BM$6,"<="&BO$6,$D$5:$BM$5,BO$5) -> 0 | BP73: =SUMIFS($D73:$BM73,$D$6:$BM$6,">="&BP$2,$D$6:$BM$6,"<="&BP$6,$D$5:$BM$5,BP$5) -> 0 | BQ73: =SUMIFS($D73:$BM73,$D$6:$BM$6,">="&BQ$2,$D$6:$BM$6,"<="&BQ$6,$D$5:$BM$5,BQ$5) -> 0 | BR73: =SUMIFS($D73:$BM73,$D$6:$BM$6,">="&BR$2,$D$6:$BM$6,"<="&BR$6,$D$5:$BM$5,BR$5) -> 0 | BS73: =SUMIFS($D73:$BM73,$D$6:$BM$6,">="&BS$2,$D$6:$BM$6,"<="&BS$6,$D$5:$BM$5,BS$5) -> 0 | BT73: =SUMIFS($D73:$BM73,$D$6:$BM$6,">="&BT$2,$D$6:$BM$6,"<="&BT$6,$D$5:$BM$5,BT$5) -> 0
A74: INOF | D74: =Renta_Alta!D74+Masivo!D74+Consumo_Inicial!D74 -> 0 | E74: =Renta_Alta!E74+Masivo!E74+Consumo_Inicial!E74 -> 0 | F74: =Renta_Alta!F74+Masivo!F74+Consumo_Inicial!F74 -> 0 | G74: =Renta_Alta!G74+Masivo!G74+Consumo_Inicial!G74 -> 0 | H74: =Renta_Alta!H74+Masivo!H74+Consumo_Inicial!H74 -> 0 | I74: =Renta_Alta!I74+Masivo!I74+Consumo_Inicial!I74 -> 0 | J74: =Renta_Alta!J74+Masivo!J74+Consumo_Inicial!J74 -> 0 | K74: =Renta_Alta!K74+Masivo!K74+Consumo_Inicial!K74 -> 0 | ... BK74: =Renta_Alta!BK74+Masivo!BK74+Consumo_Inicial!BK74 -> 0 | BO74: =SUMIFS($D74:$BM74,$D$6:$BM$6,">="&BO$2,$D$6:$BM$6,"<="&BO$6,$D$5:$BM$5,BO$5) -> 0 | BP74: =SUMIFS($D74:$BM74,$D$6:$BM$6,">="&BP$2,$D$6:$BM$6,"<="&BP$6,$D$5:$BM$5,BP$5) -> 0 | BQ74: =SUMIFS($D74:$BM74,$D$6:$BM$6,">="&BQ$2,$D$6:$BM$6,"<="&BQ$6,$D$5:$BM$5,BQ$5) -> 0 | BR74: =SUMIFS($D74:$BM74,$D$6:$BM$6,">="&BR$2,$D$6:$BM$6,"<="&BR$6,$D$5:$BM$5,BR$5) -> 0 | BS74: =SUMIFS($D74:$BM74,$D$6:$BM$6,">="&BS$2,$D$6:$BM$6,"<="&BS$6,$D$5:$BM$5,BS$5) -> 0 | BT74: =SUMIFS($D74:$BM74,$D$6:$BM$6,">="&BT$2,$D$6:$BM$6,"<="&BT$6,$D$5:$BM$5,BT$5) -> 0
A75: INOF | D75: =Renta_Alta!D75+Masivo!D75+Consumo_Inicial!D75 -> 0 | E75: =Renta_Alta!E75+Masivo!E75+Consumo_Inicial!E75 -> 0 | F75: =Renta_Alta!F75+Masivo!F75+Consumo_Inicial!F75 -> 0 | G75: =Renta_Alta!G75+Masivo!G75+Consumo_Inicial!G75 -> 0 | H75: =Renta_Alta!H75+Masivo!H75+Consumo_Inicial!H75 -> 0 | I75: =Renta_Alta!I75+Masivo!I75+Consumo_Inicial!I75 -> 0 | J75: =Renta_Alta!J75+Masivo!J75+Consumo_Inicial!J75 -> 0 | K75: =Renta_Alta!K75+Masivo!K75+Consumo_Inicial!K75 -> 0 | ... BK75: =Renta_Alta!BK75+Masivo!BK75+Consumo_Inicial!BK75 -> 0 | BO75: =SUMIFS($D75:$BM75,$D$6:$BM$6,">="&BO$2,$D$6:$BM$6,"<="&BO$6,$D$5:$BM$5,BO$5) -> 0 | BP75: =SUMIFS($D75:$BM75,$D$6:$BM$6,">="&BP$2,$D$6:$BM$6,"<="&BP$6,$D$5:$BM$5,BP$5) -> 0 | BQ75: =SUMIFS($D75:$BM75,$D$6:$BM$6,">="&BQ$2,$D$6:$BM$6,"<="&BQ$6,$D$5:$BM$5,BQ$5) -> 0 | BR75: =SUMIFS($D75:$BM75,$D$6:$BM$6,">="&BR$2,$D$6:$BM$6,"<="&BR$6,$D$5:$BM$5,BR$5) -> 0 | BS75: =SUMIFS($D75:$BM75,$D$6:$BM$6,">="&BS$2,$D$6:$BM$6,"<="&BS$6,$D$5:$BM$5,BS$5) -> 0 | BT75: =SUMIFS($D75:$BM75,$D$6:$BM$6,">="&BT$2,$D$6:$BM$6,"<="&BT$6,$D$5:$BM$5,BT$5) -> 0
A76: INOF | D76: =Renta_Alta!D76+Masivo!D76+Consumo_Inicial!D76 -> 0 | E76: =Renta_Alta!E76+Masivo!E76+Consumo_Inicial!E76 -> 0 | F76: =Renta_Alta!F76+Masivo!F76+Consumo_Inicial!F76 -> 0 | G76: =Renta_Alta!G76+Masivo!G76+Consumo_Inicial!G76 -> 0 | H76: =Renta_Alta!H76+Masivo!H76+Consumo_Inicial!H76 -> 0 | I76: =Renta_Alta!I76+Masivo!I76+Consumo_Inicial!I76 -> 0 | J76: =Renta_Alta!J76+Masivo!J76+Consumo_Inicial!J76 -> 0 | K76: =Renta_Alta!K76+Masivo!K76+Consumo_Inicial!K76 -> 0 | ... BK76: =Renta_Alta!BK76+Masivo!BK76+Consumo_Inicial!BK76 -> 0 | BO76: =SUMIFS($D76:$BM76,$D$6:$BM$6,">="&BO$2,$D$6:$BM$6,"<="&BO$6,$D$5:$BM$5,BO$5) -> 0 | BP76: =SUMIFS($D76:$BM76,$D$6:$BM$6,">="&BP$2,$D$6:$BM$6,"<="&BP$6,$D$5:$BM$5,BP$5) -> 0 | BQ76: =SUMIFS($D76:$BM76,$D$6:$BM$6,">="&BQ$2,$D$6:$BM$6,"<="&BQ$6,$D$5:$BM$5,BQ$5) -> 0 | BR76: =SUMIFS($D76:$BM76,$D$6:$BM$6,">="&BR$2,$D$6:$BM$6,"<="&BR$6,$D$5:$BM$5,BR$5) -> 0 | BS76: =SUMIFS($D76:$BM76,$D$6:$BM$6,">="&BS$2,$D$6:$BM$6,"<="&BS$6,$D$5:$BM$5,BS$5) -> 0 | BT76: =SUMIFS($D76:$BM76,$D$6:$BM$6,">="&BT$2,$D$6:$BM$6,"<="&BT$6,$D$5:$BM$5,BT$5) -> 0
A77: INOF | D77: =Renta_Alta!D77+Masivo!D77+Consumo_Inicial!D77 -> 0 | E77: =Renta_Alta!E77+Masivo!E77+Consumo_Inicial!E77 -> 0 | F77: =Renta_Alta!F77+Masivo!F77+Consumo_Inicial!F77 -> 0 | G77: =Renta_Alta!G77+Masivo!G77+Consumo_Inicial!G77 -> 0 | H77: =Renta_Alta!H77+Masivo!H77+Consumo_Inicial!H77 -> 0 | I77: =Renta_Alta!I77+Masivo!I77+Consumo_Inicial!I77 -> 0 | J77: =Renta_Alta!J77+Masivo!J77+Consumo_Inicial!J77 -> 0 | K77: =Renta_Alta!K77+Masivo!K77+Consumo_Inicial!K77 -> 0 | ... BK77: =Renta_Alta!BK77+Masivo!BK77+Consumo_Inicial!BK77 -> 0 | BO77: =SUMIFS($D77:$BM77,$D$6:$BM$6,">="&BO$2,$D$6:$BM$6,"<="&BO$6,$D$5:$BM$5,BO$5) -> 0 | BP77: =SUMIFS($D77:$BM77,$D$6:$BM$6,">="&BP$2,$D$6:$BM$6,"<="&BP$6,$D$5:$BM$5,BP$5) -> 0 | BQ77: =SUMIFS($D77:$BM77,$D$6:$BM$6,">="&BQ$2,$D$6:$BM$6,"<="&BQ$6,$D$5:$BM$5,BQ$5) -> 0 | BR77: =SUMIFS($D77:$BM77,$D$6:$BM$6,">="&BR$2,$D$6:$BM$6,"<="&BR$6,$D$5:$BM$5,BR$5) -> 0 | BS77: =SUMIFS($D77:$BM77,$D$6:$BM$6,">="&BS$2,$D$6:$BM$6,"<="&BS$6,$D$5:$BM$5,BS$5) -> 0 | BT77: =SUMIFS($D77:$BM77,$D$6:$BM$6,">="&BT$2,$D$6:$BM$6,"<="&BT$6,$D$5:$BM$5,BT$5) -> 0
... A82: INOF | D82: =Renta_Alta!D82+Masivo!D82+Consumo_Inicial!D82 -> 0 | E82: =Renta_Alta!E82+Masivo!E82+Consumo_Inicial!E82 -> 0 | F82: =Renta_Alta!F82+Masivo!F82+Consumo_Inicial!F82 -> 0 | G82: =Renta_Alta!G82+Masivo!G82+Consumo_Inicial!G82 -> 0 | H82: =Renta_Alta!H82+Masivo!H82+Consumo_Inicial!H82 -> 0 | I82: =Renta_Alta!I82+Masivo!I82+Consumo_Inicial!I82 -> 0 | J82: =Renta_Alta!J82+Masivo!J82+Consumo_Inicial!J82 -> 0 | K82: =Renta_Alta!K82+Masivo!K82+Consumo_Inicial!K82 -> 0 | ... BK82: =Renta_Alta!BK82+Masivo!BK82+Consumo_Inicial!BK82 -> 0 | BO82: =SUMIFS($D82:$BM82,$D$6:$BM$6,">="&BO$2,$D$6:$BM$6,"<="&BO$6,$D$5:$BM$5,BO$5) -> 0 | BP82: =SUMIFS($D82:$BM82,$D$6:$BM$6,">="&BP$2,$D$6:$BM$6,"<="&BP$6,$D$5:$BM$5,BP$5) -> 0 | BQ82: =SUMIFS($D82:$BM82,$D$6:$BM$6,">="&BQ$2,$D$6:$BM$6,"<="&BQ$6,$D$5:$BM$5,BQ$5) -> 0 | BR82: =SUMIFS($D82:$BM82,$D$6:$BM$6,">="&BR$2,$D$6:$BM$6,"<="&BR$6,$D$5:$BM$5,BR$5) -> 0 | BS82: =SUMIFS($D82:$BM82,$D$6:$BM$6,">="&BS$2,$D$6:$BM$6,"<="&BS$6,$D$5:$BM$5,BS$5) -> 0 | BT82: =SUMIFS($D82:$BM82,$D$6:$BM$6,">="&BT$2,$D$6:$BM$6,"<="&BT$6,$D$5:$BM$5,BT$5) -> 0
C83: INOF | D83: =SUM(D63:D82) -> 384.60945 | E83: =SUM(E63:E82) -> 358.24318 | F83: =SUM(F63:F82) -> 295.90516 | G83: =SUM(G63:G82) -> 445.41278 | H83: =SUM(H63:H82) -> 370.76042 | I83: =SUM(I63:I82) -> 431.36794 | J83: =SUM(J63:J82) -> 405.95327 | K83: =SUM(K63:K82) -> 438.48506 | ... BK83: =SUM(BK63:BK82) -> 358.00452 | BO83: =SUM(BO63:BO82) -> 916.00943 | BP83: =SUM(BP63:BP82) -> 938.10379 | BQ83: =SUM(BQ63:BQ82) -> 629.12405 | BR83: =SUM(BR63:BR82) -> 783.44837 | BS83: =SUM(BS63:BS82) -> 1245.8175 | BT83: =SUM(BT63:BT82) -> 1038.7578
D84: =[1]Desempeño_Financiero_Evol!BA518-D83 -> -2.2850486e-09 | E84: =[1]Desempeño_Financiero_Evol!BB518-E83 -> 1.6220042e-08 | F84: =[1]Desempeño_Financiero_Evol!BC518-F83 -> 4.5940055e-08 | G84: =[1]Desempeño_Financiero_Evol!BD518-G83 -> -4.104993e-08 | H84: =[1]Desempeño_Financiero_Evol!BE518-H83 -> -2.2060135e-08 | I84: =[1]Desempeño_Financiero_Evol!BF518-I83 -> 3.3102083e-08 | J84: =[1]Desempeño_Financiero_Evol!BG518-J83 -> -8.0398763e-09 | K84: =[1]Desempeño_Financiero_Evol!BH518-K83 -> -1.5119952e-08 | ... AP84: =[1]Desempeño_Financiero_Evol!CM518-AP83 -> 0 | AZ84: =[1]Desempeño_Financiero_Evol!CW518-AZ83 -> 0
A86: Gastos Operativos | C86: Gasto Directo | D86: =Renta_Alta!D86+Masivo!D86+Consumo_Inicial!D86 -> -1586.9911 | E86: =Renta_Alta!E86+Masivo!E86+Consumo_Inicial!E86 -> -1556.691 | F86: =Renta_Alta!F86+Masivo!F86+Consumo_Inicial!F86 -> -1604.1168 | G86: =Renta_Alta!G86+Masivo!G86+Consumo_Inicial!G86 -> -1663.1703 | H86: =Renta_Alta!H86+Masivo!H86+Consumo_Inicial!H86 -> -1672.2143 | I86: =Renta_Alta!I86+Masivo!I86+Consumo_Inicial!I86 -> -1812.6894 | J86: =Renta_Alta!J86+Masivo!J86+Consumo_Inicial!J86 -> -1455.5655 | K86: =Renta_Alta!K86+Masivo!K86+Consumo_Inicial!K86 -> -1578.0045 | ... BK86: =Renta_Alta!BK86+Masivo!BK86+Consumo_Inicial!BK86 -> -1785.5443 | BO86: =SUMIFS($D86:$BM86,$D$6:$BM$6,">="&BO$2,$D$6:$BM$6,"<="&BO$6,$D$5:$BM$5,BO$5) -> -5158.2413 | BP86: =SUMIFS($D86:$BM86,$D$6:$BM$6,">="&BP$2,$D$6:$BM$6,"<="&BP$6,$D$5:$BM$5,BP$5) -> -4987.0606 | BQ86: =SUMIFS($D86:$BM86,$D$6:$BM$6,">="&BQ$2,$D$6:$BM$6,"<="&BQ$6,$D$5:$BM$5,BQ$5) -> -3280.8482 | BR86: =SUMIFS($D86:$BM86,$D$6:$BM$6,">="&BR$2,$D$6:$BM$6,"<="&BR$6,$D$5:$BM$5,BR$5) -> -4076.5968 | BS86: =SUMIFS($D86:$BM86,$D$6:$BM$6,">="&BS$2,$D$6:$BM$6,"<="&BS$6,$D$5:$BM$5,BS$5) -> -4103.9796 | BT86: =SUMIFS($D86:$BM86,$D$6:$BM$6,">="&BT$2,$D$6:$BM$6,"<="&BT$6,$D$5:$BM$5,BT$5) -> -4747.7988
A87: Gastos Operativos | C87: Gasto Canal | D87: =Renta_Alta!D87+Masivo!D87+Consumo_Inicial!D87 -> -1021.2752 | E87: =Renta_Alta!E87+Masivo!E87+Consumo_Inicial!E87 -> -1040.6651 | F87: =Renta_Alta!F87+Masivo!F87+Consumo_Inicial!F87 -> -1206.6795 | G87: =Renta_Alta!G87+Masivo!G87+Consumo_Inicial!G87 -> -1056.4031 | H87: =Renta_Alta!H87+Masivo!H87+Consumo_Inicial!H87 -> -1175.5128 | I87: =Renta_Alta!I87+Masivo!I87+Consumo_Inicial!I87 -> -1085.036 | J87: =Renta_Alta!J87+Masivo!J87+Consumo_Inicial!J87 -> -1003.5387 | K87: =Renta_Alta!K87+Masivo!K87+Consumo_Inicial!K87 -> -1063.3876 | ... BK87: =Renta_Alta!BK87+Masivo!BK87+Consumo_Inicial!BK87 -> -1089.6759 | BO87: =SUMIFS($D87:$BM87,$D$6:$BM$6,">="&BO$2,$D$6:$BM$6,"<="&BO$6,$D$5:$BM$5,BO$5) -> -3244.5213 | BP87: =SUMIFS($D87:$BM87,$D$6:$BM$6,">="&BP$2,$D$6:$BM$6,"<="&BP$6,$D$5:$BM$5,BP$5) -> -3193.5369 | BQ87: =SUMIFS($D87:$BM87,$D$6:$BM$6,">="&BQ$2,$D$6:$BM$6,"<="&BQ$6,$D$5:$BM$5,BQ$5) -> -2104.4633 | BR87: =SUMIFS($D87:$BM87,$D$6:$BM$6,">="&BR$2,$D$6:$BM$6,"<="&BR$6,$D$5:$BM$5,BR$5) -> -2977.0087 | BS87: =SUMIFS($D87:$BM87,$D$6:$BM$6,">="&BS$2,$D$6:$BM$6,"<="&BS$6,$D$5:$BM$5,BS$5) -> -3097.5991 | BT87: =SUMIFS($D87:$BM87,$D$6:$BM$6,">="&BT$2,$D$6:$BM$6,"<="&BT$6,$D$5:$BM$5,BT$5) -> -3268.6198
A88: Gastos Operativos | C88: Gasto Indirecto | D88: =Renta_Alta!D88+Masivo!D88+Consumo_Inicial!D88 -> -1883.8883 | E88: =Renta_Alta!E88+Masivo!E88+Consumo_Inicial!E88 -> -2135.6846 | F88: =Renta_Alta!F88+Masivo!F88+Consumo_Inicial!F88 -> -1952.7376 | G88: =Renta_Alta!G88+Masivo!G88+Consumo_Inicial!G88 -> -2095.1783 | H88: =Renta_Alta!H88+Masivo!H88+Consumo_Inicial!H88 -> -2024.7599 | I88: =Renta_Alta!I88+Masivo!I88+Consumo_Inicial!I88 -> -1876.4754 | J88: =Renta_Alta!J88+Masivo!J88+Consumo_Inicial!J88 -> -2208.4679 | K88: =Renta_Alta!K88+Masivo!K88+Consumo_Inicial!K88 -> -1911.128 | ... BK88: =Renta_Alta!BK88+Masivo!BK88+Consumo_Inicial!BK88 -> -2653.9272 | BO88: =SUMIFS($D88:$BM88,$D$6:$BM$6,">="&BO$2,$D$6:$BM$6,"<="&BO$6,$D$5:$BM$5,BO$5) -> -7675.7592 | BP88: =SUMIFS($D88:$BM88,$D$6:$BM$6,">="&BP$2,$D$6:$BM$6,"<="&BP$6,$D$5:$BM$5,BP$5) -> -7517.1328 | BQ88: =SUMIFS($D88:$BM88,$D$6:$BM$6,">="&BQ$2,$D$6:$BM$6,"<="&BQ$6,$D$5:$BM$5,BQ$5) -> -5124.4075 | BR88: =SUMIFS($D88:$BM88,$D$6:$BM$6,">="&BR$2,$D$6:$BM$6,"<="&BR$6,$D$5:$BM$5,BR$5) -> -6341.9348 | BS88: =SUMIFS($D88:$BM88,$D$6:$BM$6,">="&BS$2,$D$6:$BM$6,"<="&BS$6,$D$5:$BM$5,BS$5) -> -5673.7321 | BT88: =SUMIFS($D88:$BM88,$D$6:$BM$6,">="&BT$2,$D$6:$BM$6,"<="&BT$6,$D$5:$BM$5,BT$5) -> -5972.3105
C89: Gastos Operativos | D89: =SUM(D86:D88) -> -4492.1546 | E89: =SUM(E86:E88) -> -4733.0407 | F89: =SUM(F86:F88) -> -4763.5339 | G89: =SUM(G86:G88) -> -4814.7517 | H89: =SUM(H86:H88) -> -4872.487 | I89: =SUM(I86:I88) -> -4774.2008 | J89: =SUM(J86:J88) -> -4667.5721 | K89: =SUM(K86:K88) -> -4552.52 | ... BK89: =SUM(BK86:BK88) -> -5529.1474 | BO89: =SUM(BO86:BO88) -> -16078.522 | BP89: =SUM(BP86:BP88) -> -15697.73 | BQ89: =SUM(BQ86:BQ88) -> -10509.719 | BR89: =SUM(BR86:BR88) -> -13395.54 | BS89: =SUM(BS86:BS88) -> -12875.311 | BT89: =SUM(BT86:BT88) -> -13988.729
D90: =[1]Desempeño_Financiero_Evol!BA563-D89 -> 0 | E90: =[1]Desempeño_Financiero_Evol!BB563-E89 -> 0 | F90: =[1]Desempeño_Financiero_Evol!BC563-F89 -> 0 | G90: =[1]Desempeño_Financiero_Evol!BD563-G89 -> 0 | H90: =[1]Desempeño_Financiero_Evol!BE563-H89 -> 0 | I90: =[1]Desempeño_Financiero_Evol!BF563-I89 -> 0 | J90: =[1]Desempeño_Financiero_Evol!BG563-J89 -> 0 | K90: =[1]Desempeño_Financiero_Evol!BH563-K89 -> 0 | ... AS90: =[1]Desempeño_Financiero_Evol!CP563-AS89 -> 0 | AZ90: =[1]Desempeño_Financiero_Evol!CW563-AZ89 -> 13.295606
A91: Extraordinarios | C91: Donaciones | D91: =Renta_Alta!D91+Masivo!D91+Consumo_Inicial!D91 -> 0 | E91: =Renta_Alta!E91+Masivo!E91+Consumo_Inicial!E91 -> 0 | F91: =Renta_Alta!F91+Masivo!F91+Consumo_Inicial!F91 -> 0 | G91: =Renta_Alta!G91+Masivo!G91+Consumo_Inicial!G91 -> 0 | H91: =Renta_Alta!H91+Masivo!H91+Consumo_Inicial!H91 -> 0 | I91: =Renta_Alta!I91+Masivo!I91+Consumo_Inicial!I91 -> 0 | J91: =Renta_Alta!J91+Masivo!J91+Consumo_Inicial!J91 -> 0 | K91: =Renta_Alta!K91+Masivo!K91+Consumo_Inicial!K91 -> 0 | ... BK91: =Renta_Alta!BK91+Masivo!BK91+Consumo_Inicial!BK91 -> 0 | BO91: =SUMIFS($D91:$BM91,$D$6:$BM$6,">="&BO$2,$D$6:$BM$6,"<="&BO$6,$D$5:$BM$5,BO$5) -> 0 | BP91: =SUMIFS($D91:$BM91,$D$6:$BM$6,">="&BP$2,$D$6:$BM$6,"<="&BP$6,$D$5:$BM$5,BP$5) -> 0 | BQ91: =SUMIFS($D91:$BM91,$D$6:$BM$6,">="&BQ$2,$D$6:$BM$6,"<="&BQ$6,$D$5:$BM$5,BQ$5) -> 0 | BR91: =SUMIFS($D91:$BM91,$D$6:$BM$6,">="&BR$2,$D$6:$BM$6,"<="&BR$6,$D$5:$BM$5,BR$5) -> 0 | BS91: =SUMIFS($D91:$BM91,$D$6:$BM$6,">="&BS$2,$D$6:$BM$6,"<="&BS$6,$D$5:$BM$5,BS$5) -> 0 | BT91: =SUMIFS($D91:$BM91,$D$6:$BM$6,">="&BT$2,$D$6:$BM$6,"<="&BT$6,$D$5:$BM$5,BT$5) -> 0
A92: Extraordinarios | C92: Otros | D92: =Renta_Alta!D92+Masivo!D92+Consumo_Inicial!D92 -> -182.65197 | E92: =Renta_Alta!E92+Masivo!E92+Consumo_Inicial!E92 -> -147.82116 | F92: =Renta_Alta!F92+Masivo!F92+Consumo_Inicial!F92 -> -51.149913 | G92: =Renta_Alta!G92+Masivo!G92+Consumo_Inicial!G92 -> -133.3724 | H92: =Renta_Alta!H92+Masivo!H92+Consumo_Inicial!H92 -> -97.972642 | I92: =Renta_Alta!I92+Masivo!I92+Consumo_Inicial!I92 -> -263.83044 | J92: =Renta_Alta!J92+Masivo!J92+Consumo_Inicial!J92 -> -197.57804 | K92: =Renta_Alta!K92+Masivo!K92+Consumo_Inicial!K92 -> -603.70027 | ... BK92: =Renta_Alta!BK92+Masivo!BK92+Consumo_Inicial!BK92 -> -195.22002 | BO92: =SUMIFS($D92:$BM92,$D$6:$BM$6,">="&BO$2,$D$6:$BM$6,"<="&BO$6,$D$5:$BM$5,BO$5) -> -218.11366 | BP92: =SUMIFS($D92:$BM92,$D$6:$BM$6,">="&BP$2,$D$6:$BM$6,"<="&BP$6,$D$5:$BM$5,BP$5) -> -556.11992 | BQ92: =SUMIFS($D92:$BM92,$D$6:$BM$6,">="&BQ$2,$D$6:$BM$6,"<="&BQ$6,$D$5:$BM$5,BQ$5) -> -58.040873 | BR92: =SUMIFS($D92:$BM92,$D$6:$BM$6,">="&BR$2,$D$6:$BM$6,"<="&BR$6,$D$5:$BM$5,BR$5) -> -255.74972 | BS92: =SUMIFS($D92:$BM92,$D$6:$BM$6,">="&BS$2,$D$6:$BM$6,"<="&BS$6,$D$5:$BM$5,BS$5) -> -492.06508 | BT92: =SUMIFS($D92:$BM92,$D$6:$BM$6,">="&BT$2,$D$6:$BM$6,"<="&BT$6,$D$5:$BM$5,BT$5) -> -381.62305
C93: Extraordinarios | D93: =SUM(D91:D92) -> -182.65197 | E93: =SUM(E91:E92) -> -147.82116 | F93: =SUM(F91:F92) -> -51.149913 | G93: =SUM(G91:G92) -> -133.3724 | H93: =SUM(H91:H92) -> -97.972642 | I93: =SUM(I91:I92) -> -263.83044 | J93: =SUM(J91:J92) -> -197.57804 | K93: =SUM(K91:K92) -> -603.70027 | ... BK93: =SUM(BK91:BK92) -> -195.22002 | BO93: =SUM(BO91:BO92) -> -218.11366 | BP93: =SUM(BP91:BP92) -> -556.11992 | BQ93: =SUM(BQ91:BQ92) -> -58.040873 | BR93: =SUM(BR91:BR92) -> -255.74972 | BS93: =SUM(BS91:BS92) -> -492.06508 | BT93: =SUM(BT91:BT92) -> -381.62305
D94: =[1]Desempeño_Financiero_Evol!BA609-D93 -> 0 | E94: =[1]Desempeño_Financiero_Evol!BB609-E93 -> 0 | F94: =[1]Desempeño_Financiero_Evol!BC609-F93 -> 0 | G94: =[1]Desempeño_Financiero_Evol!BD609-G93 -> 0 | H94: =[1]Desempeño_Financiero_Evol!BE609-H93 -> 0 | I94: =[1]Desempeño_Financiero_Evol!BF609-I93 -> 0 | J94: =[1]Desempeño_Financiero_Evol!BG609-J93 -> 1.9757806e-07 | K94: =[1]Desempeño_Financiero_Evol!BH609-K93 -> 0 | ... AO94: =[1]Desempeño_Financiero_Evol!CL609-AO93 -> 0 | AZ94: =[1]Desempeño_Financiero_Evol!CW609-AZ93 -> 0
A95: ROF | C95: Venta de Cartera | D95: =Renta_Alta!D95+Masivo!D95+Consumo_Inicial!D95 -> 0 | E95: =Renta_Alta!E95+Masivo!E95+Consumo_Inicial!E95 -> 0 | F95: =Renta_Alta!F95+Masivo!F95+Consumo_Inicial!F95 -> 0 | G95: =Renta_Alta!G95+Masivo!G95+Consumo_Inicial!G95 -> 0 | H95: =Renta_Alta!H95+Masivo!H95+Consumo_Inicial!H95 -> 0 | I95: =Renta_Alta!I95+Masivo!I95+Consumo_Inicial!I95 -> 0 | J95: =Renta_Alta!J95+Masivo!J95+Consumo_Inicial!J95 -> 0 | K95: =Renta_Alta!K95+Masivo!K95+Consumo_Inicial!K95 -> 2367.4772 | ... BK95: =Renta_Alta!BK95+Masivo!BK95+Consumo_Inicial!BK95 -> 0 | BO95: =SUMIFS($D95:$BM95,$D$6:$BM$6,">="&BO$2,$D$6:$BM$6,"<="&BO$6,$D$5:$BM$5,BO$5) -> 0 | BP95: =SUMIFS($D95:$BM95,$D$6:$BM$6,">="&BP$2,$D$6:$BM$6,"<="&BP$6,$D$5:$BM$5,BP$5) -> 0 | BQ95: =SUMIFS($D95:$BM95,$D$6:$BM$6,">="&BQ$2,$D$6:$BM$6,"<="&BQ$6,$D$5:$BM$5,BQ$5) -> 0 | BR95: =SUMIFS($D95:$BM95,$D$6:$BM$6,">="&BR$2,$D$6:$BM$6,"<="&BR$6,$D$5:$BM$5,BR$5) -> 2363.95 | BS95: =SUMIFS($D95:$BM95,$D$6:$BM$6,">="&BS$2,$D$6:$BM$6,"<="&BS$6,$D$5:$BM$5,BS$5) -> 0 | BT95: =SUMIFS($D95:$BM95,$D$6:$BM$6,">="&BT$2,$D$6:$BM$6,"<="&BT$6,$D$5:$BM$5,BT$5) -> 0
C96: ROF | D96: =SUM(D95:D95) -> 0 | E96: =SUM(E95:E95) -> 0 | F96: =SUM(F95:F95) -> 0 | G96: =SUM(G95:G95) -> 0 | H96: =SUM(H95:H95) -> 0 | I96: =SUM(I95:I95) -> 0 | J96: =SUM(J95:J95) -> 0 | K96: =SUM(K95:K95) -> 2367.4772 | ... BK96: =SUM(BK95:BK95) -> 0 | BO96: =SUM(BO95) -> 0 | BP96: =SUM(BP95) -> 0 | BQ96: =SUM(BQ95) -> 0 | BR96: =SUM(BR95) -> 2363.95 | BS96: =SUM(BS95) -> 0 | BT96: =SUM(BT95) -> 0
D97: =[1]Desempeño_Financiero_Evol!BA597-D96 -> 0 | E97: =[1]Desempeño_Financiero_Evol!BB597-E96 -> 0 | F97: =[1]Desempeño_Financiero_Evol!BC597-F96 -> 0 | G97: =[1]Desempeño_Financiero_Evol!BD597-G96 -> 0 | H97: =[1]Desempeño_Financiero_Evol!BE597-H96 -> 0 | I97: =[1]Desempeño_Financiero_Evol!BF597-I96 -> 0 | J97: =[1]Desempeño_Financiero_Evol!BG597-J96 -> 0 | K97: =[1]Desempeño_Financiero_Evol!BH597-K96 -> 0 | ... AP97: =[1]Desempeño_Financiero_Evol!CM597-AP96 -> 0 | AZ97: =[1]Desempeño_Financiero_Evol!CW597-AZ96 -> 0
C98: UAI | D98: =D60+D83+D89+D93+D96 -> 430.16164 | E98: =E60+E83+E89+E93+E96 -> 7931.5528 | F98: =F60+F83+F89+F93+F96 -> 251.26492 | G98: =G60+G83+G89+G93+G96 -> -96.197457 | H98: =H60+H83+H89+H93+H96 -> -10572.436 | I98: =I60+I83+I89+I93+I96 -> -18778.551 | J98: =J60+J83+J89+J93+J96 -> -21133.975 | K98: =K60+K83+K89+K93+K96 -> -36268.61 | ... BK98: =BK60+BK83+BK89+BK93+BK96 -> 8453.9307 | BO98: =BO60+BO83+BO89+BO93+BO96 -> 19587.288 | BP98: =BP60+BP83+BP89+BP93+BP96 -> -357.06172 | BQ98: =BQ60+BQ83+BQ89+BQ93+BQ96 -> 11519.981 | BR98: =BR60+BR83+BR89+BR93+BR96 -> -26525.278 | BS98: =BS60+BS83+BS89+BS93+BS96 -> -155708.16 | BT98: =BT60+BT83+BT89+BT93+BT96 -> 8612.9794
C102: Prom SFdP | D102: =D11 -> 3296914.8 | E102: =IFERROR(AVERAGE(D11:E11),0) -> 3341468.6 | F102: =IFERROR(AVERAGE(E11:F11),0) -> 3443124.8 | G102: =IFERROR(AVERAGE(F11:G11),0) -> 3536071.2 | H102: =IFERROR(AVERAGE(G11:H11),0) -> 3607044.6 | I102: =IFERROR(AVERAGE(H11:I11),0) -> 3673389.5 | J102: =IFERROR(AVERAGE(I11:J11),0) -> 3731406.2 | K102: =IFERROR(AVERAGE(J11:K11),0) -> 3821688.6 | L102: =IFERROR(AVERAGE(K11:L11),0) -> 3900284.5 | ... AY102: =IFERROR(AVERAGE(AX11:AY11),0) -> 0 | AZ102: =AZ11 -> 3206378.7 | BA102: =IFERROR(AVERAGE(AZ11:BA11),0) -> 3208160.8 | BB102: =IFERROR(AVERAGE(BA11:BB11),0) -> 3227708.5 | BC102: =IFERROR(AVERAGE(BB11:BC11),0) -> 3269328.5 | BD102: =IFERROR(AVERAGE(BC11:BD11),0) -> 3324308.6 | BE102: =IFERROR(AVERAGE(BD11:BE11),0) -> 3371614.3 | BF102: =IFERROR(AVERAGE(BE11:BF11),0) -> 3396542.3 | BG102: =IFERROR(AVERAGE(BF11:BG11),0) -> 3424733 | BH102: =IFERROR(AVERAGE(BG11:BH11),0) -> 3472215.6 | ... BK102: =IFERROR(AVERAGE(BJ11:BK11),0) -> 3589906.5 | BO102: =IFERROR(AVERAGEIFS($D11:$BM11,$D$6:$BM$6,">="&EOMONTH(BO$2,-1),$D$6:$BM$6,"<="&BO$6,$D$5:$BM$5,BO$5,$D11:$BM11,"<>0"),0) -> 3250109.5 | BP102: =IFERROR(AVERAGEIFS($D11:$BM11,$D$6:$BM$6,">="&EOMONTH(BP$2,-1),$D$6:$BM$6,"<="&BP$6,$D$5:$BM$5,BP$5,$D11:$BM11,"<>0"),0) -> 3220598.6 | BQ102: =IFERROR(AVERAGEIFS($D11:$BM11,$D$6:$BM$6,">="&EOMONTH(BQ$2,-1),$D$6:$BM$6,"<="&BQ$6,$D$5:$BM$5,BQ$5,$D11:$BM11,"<>0"),0) -> 3226416.4 | BR102: =IFERROR(AVERAGEIFS($D11:$BM11,$D$6:$BM$6,">="&EOMONTH(BR$2,-1),$D$6:$BM$6,"<="&BR$6,$D$5:$BM$5,BR$5,$D11:$BM11,"<>0"),0) -> 3013328.1 | BS102: =IFERROR(AVERAGEIFS($D11:$BM11,$D$6:$BM$6,">="&EOMONTH(BS$2,-1),$D$6:$BM$6,"<="&BS$6,$D$5:$BM$5,BS$5,$D11:$BM11,"<>0"),0) -> 3707224.3 | BT102: =IFERROR(AVERAGEIFS($D11:$BM11,$D$6:$BM$6,">="&EOMONTH(BT$2,-1),$D$6:$BM$6,"<="&BT$6,$D$5:$BM$5,BT$5,$D11:$BM11,"<>0"),0) -> 3394388.1

Sheet Desempeño_Financiero
B1: 46112 | D1: Mensual | W1: Acumulado
B2: Desempeño Financiero
B3: En S/. Miles | C3: N° dias T.Imp | D3: =DAY(D6) -> 31 | E3: =DAY(E6) -> 31 | F3: =DAY(F6) -> 28 | G3: =DAY(G6) -> 31 | H3: =DAY(H6) -> 31 | I3: =DAY(I6) -> 31
C4: N° dias FTP | D4: =DAY(D6) -> 31 | E4: =DAY(E6) -> 31 | F4: =DAY(F6) -> 28 | G4: =DAY(G6) -> 31 | H4: =DAY(H6) -> 31 | I4: =DAY(I6) -> 31
C5: Tipo | D5: R | E5: P | F5: R | G5: R | H5: R | I5: R | K5: Variación S/. | Q5: Variación % | AD5: Variación S/. | AJ5: Variación %
C6: Total_Producto | D6: =$B$1 -> 46112 | E6: =D6 -> 46112 | F6: =EOMONTH(D6,-1) -> 46081 | G6: =EOMONTH(D6,-12) -> 45747 | H6: =EOMONTH(D6,-24) -> 45382 | I6: =EOMONTH(D6,-36) -> 45016 | K6: =E6 -> 46112 | L6: =F6 -> 46081 | M6: =G6 -> 45747 | N6: =H6 -> 45382 | O6: =I6 -> 45016 | Q6: =K6 -> 46112 | R6: =L6 -> 46081 | S6: =M6 -> 45747 | T6: =N6 -> 45382 | U6: =O6 -> 45016 | W6: =$B$1 -> 46112 | X6: =W6 -> 46112 | Y6: =EOMONTH(W6,-1) -> 46081 | Z6: =EOMONTH(W6,-12) -> 45747 | AA6: =EOMONTH(W6,-24) -> 45382 | AB6: =EOMONTH(W6,-36) -> 45016 | AD6: =X6 -> 46112 | AE6: =Y6 -> 46081 | AF6: =Z6 -> 45747 | AG6: =AA6 -> 45382 | AH6: =AB6 -> 45016 | AJ6: =AD6 -> 46112 | AK6: =AE6 -> 46081 | AL6: =AF6 -> 45747 | AM6: =AG6 -> 45382 | AN6: =AH6 -> 45016
A8: SALDO_FDP | C8: Vigente | D8: {=_xlfn.XLOOKUP(1, (INDIRECT("'"&$C$6&"'!$6:$6")=D$6)* (INDIRECT("'"&$C$6&"'!$5:$5")=D$5), INDIRECT("'"&$C$6&"'!"&ROW()&":"&ROW()) )} -> 3199553.1 | E8: {=_xlfn.XLOOKUP(1, (INDIRECT("'"&$C$6&"'!$6:$6")=E$6)* (INDIRECT("'"&$C$6&"'!$5:$5")=E$5), INDIRECT("'"&$C$6&"'!"&ROW()&":"&ROW()) )} -> 3121000.5 | F8: {=_xlfn.XLOOKUP(1, (INDIRECT("'"&$C$6&"'!$6:$6")=F$6)* (INDIRECT("'"&$C$6&"'!$5:$5")=F$5), INDIRECT("'"&$C$6&"'!"&ROW()&":"&ROW()) )} -> 3154129 | G8: {=_xlfn.XLOOKUP(1, (INDIRECT("'"&$C$6&"'!$6:$6")=G$6)* (INDIRECT("'"&$C$6&"'!$5:$5")=G$5), INDIRECT("'"&$C$6&"'!"&ROW()&":"&ROW()) )} -> 2864120.5 | H8: {=_xlfn.XLOOKUP(1, (INDIRECT("'"&$C$6&"'!$6:$6")=H$6)* (INDIRECT("'"&$C$6&"'!$5:$5")=H$5), INDIRECT("'"&$C$6&"'!"&ROW()&":"&ROW()) )} -> 3428790.2 | I8: {=_xlfn.XLOOKUP(1, (INDIRECT("'"&$C$6&"'!$6:$6")=I$6)* (INDIRECT("'"&$C$6&"'!$5:$5")=I$5), INDIRECT("'"&$C$6&"'!"&ROW()&":"&ROW()) )} -> 3421266.2 | K8: =$D8-E8 -> 78552.563 | L8: =$D8-F8 -> 45424.07 | M8: =$D8-G8 -> 335432.56 | N8: =$D8-H8 -> -229237.14 | O8: =$D8-I8 -> -221713.16 | Q8: =IFERROR($D8/E8-1,0) -> 0.025169033 | R8: =IFERROR($D8/F8-1,0) -> 0.014401462 | S8: =IFERROR($D8/G8-1,0) -> 0.11711538 | T8: =IFERROR($D8/H8-1,0) -> -0.066856565 | U8: =IFERROR($D8/I8-1,0) -> -0.064804415 | W8: {=INDIRECT("'"&$C$6&"'!"&ADDRESS(ROW(),COLUMN()+44))} -> 3199553.1 | X8: {=INDIRECT("'"&$C$6&"'!"&ADDRESS(ROW(),COLUMN()+44))} -> 3121000.5 | Y8: {=INDIRECT("'"&$C$6&"'!"&ADDRESS(ROW(),COLUMN()+44))} -> 3154129 | Z8: {=INDIRECT("'"&$C$6&"'!"&ADDRESS(ROW(),COLUMN()+44))} -> 2864120.5 | AA8: {=INDIRECT("'"&$C$6&"'!"&ADDRESS(ROW(),COLUMN()+44))} -> 3428790.2 | AB8: {=INDIRECT("'"&$C$6&"'!"&ADDRESS(ROW(),COLUMN()+44))} -> 3421266.2 | AD8: =$W8-X8 -> 78552.563 | AE8: =$W8-Y8 -> 45424.07 | AF8: =$W8-Z8 -> 335432.56 | AG8: =$W8-AA8 -> -229237.14 | AH8: =$W8-AB8 -> -221713.16 | AJ8: =IFERROR($W8/X8-1,0) -> 0.025169033 | AK8: =IFERROR($W8/Y8-1,0) -> 0.014401462 | AL8: =IFERROR($W8/Z8-1,0) -> 0.11711538 | AM8: =IFERROR($W8/AA8-1,0) -> -0.066856565 | AN8: =IFERROR($W8/AB8-1,0) -> -0.064804415
A9: SALDO_FDP | C9: Refinanciado | D9: {=_xlfn.XLOOKUP(1, (INDIRECT("'"&$C$6&"'!$6:$6")=D$6)* (INDIRECT("'"&$C$6&"'!$5:$5")=D$5), INDIRECT("'"&$C$6&"'!"&ROW()&":"&ROW()) )} -> 36825.6 | E9: {=_xlfn.XLOOKUP(1, (INDIRECT("'"&$C$6&"'!$6:$6")=E$6)* (INDIRECT("'"&$C$6&"'!$5:$5")=E$5), INDIRECT("'"&$C$6&"'!"&ROW()&":"&ROW()) )} -> 32170.33 | F9: {=_xlfn.XLOOKUP(1, (INDIRECT("'"&$C$6&"'!$6:$6")=F$6)* (INDIRECT("'"&$C$6&"'!$5:$5")=F$5), INDIRECT("'"&$C$6&"'!"&ROW()&":"&ROW()) )} -> 37846.73 | G9: {=_xlfn.XLOOKUP(1, (INDIRECT("'"&$C$6&"'!$6:$6")=G$6)* (INDIRECT("'"&$C$6&"'!$5:$5")=G$5), INDIRECT("'"&$C$6&"'!"&ROW()&":"&ROW()) )} -> 47040.751 | H9: {=_xlfn.XLOOKUP(1, (INDIRECT("'"&$C$6&"'!$6:$6")=H$6)* (INDIRECT("'"&$C$6&"'!$5:$5")=H$5), INDIRECT("'"&$C$6&"'!"&ROW()&":"&ROW()) )} -> 8619.8673 | I9: {=_xlfn.XLOOKUP(1, (INDIRECT("'"&$C$6&"'!$6:$6")=I$6)* (INDIRECT("'"&$C$6&"'!$5:$5")=I$5), INDIRECT("'"&$C$6&"'!"&ROW()&":"&ROW()) )} -> 12918.972 | K9: =$D9-E9 -> 4655.2696 | L9: =$D9-F9 -> -1021.13 | M9: =$D9-G9 -> -10215.151 | N9: =$D9-H9 -> 28205.733 | O9: =$D9-I9 -> 23906.628 | Q9: =IFERROR($D9/E9-1,0) -> 0.14470692 | R9: =IFERROR($D9/F9-1,0) -> -0.026980666 | S9: =IFERROR($D9/G9-1,0) -> -0.21715535 | T9: =IFERROR($D9/H9-1,0) -> 3.2721771 | U9: =IFERROR($D9/I9-1,0) -> 1.8505053 | W9: {=INDIRECT("'"&$C$6&"'!"&ADDRESS(ROW(),COLUMN()+44))} -> 36825.6 | X9: {=INDIRECT("'"&$C$6&"'!"&ADDRESS(ROW(),COLUMN()+44))} -> 32170.33 | Y9: {=INDIRECT("'"&$C$6&"'!"&ADDRESS(ROW(),COLUMN()+44))} -> 37846.73 | Z9: {=INDIRECT("'"&$C$6&"'!"&ADDRESS(ROW(),COLUMN()+44))} -> 47040.751 | AA9: {=INDIRECT("'"&$C$6&"'!"&ADDRESS(ROW(),COLUMN()+44))} -> 8619.8673 | AB9: {=INDIRECT("'"&$C$6&"'!"&ADDRESS(ROW(),COLUMN()+44))} -> 12918.972 | AD9: =$W9-X9 -> 4655.2696 | AE9: =$W9-Y9 -> -1021.13 | AF9: =$W9-Z9 -> -10215.151 | AG9: =$W9-AA9 -> 28205.733 | AH9: =$W9-AB9 -> 23906.628 | AJ9: =IFERROR($W9/X9-1,0) -> 0.14470692 | AK9: =IFERROR($W9/Y9-1,0) -> -0.026980666 | AL9: =IFERROR($W9/Z9-1,0) -> -0.21715535 | AM9: =IFERROR($W9/AA9-1,0) -> 3.2721771 | AN9: =IFERROR($W9/AB9-1,0) -> 1.8505053
A10: SALDO_FDP | C10: Vencido y Judicial | D10: {=_xlfn.XLOOKUP(1, (INDIRECT("'"&$C$6&"'!$6:$6")=D$6)* (INDIRECT("'"&$C$6&"'!$5:$5")=D$5), INDIRECT("'"&$C$6&"'!"&ROW()&":"&ROW()) )} -> 84810.02 | E10: {=_xlfn.XLOOKUP(1, (INDIRECT("'"&$C$6&"'!$6:$6")=E$6)* (INDIRECT("'"&$C$6&"'!$5:$5")=E$5), INDIRECT("'"&$C$6&"'!"&ROW()&":"&ROW()) )} -> 92303.295 | F10: {=_xlfn.XLOOKUP(1, (INDIRECT("'"&$C$6&"'!$6:$6")=F$6)* (INDIRECT("'"&$C$6&"'!$5:$5")=F$5), INDIRECT("'"&$C$6&"'!"&ROW()&":"&ROW()) )} -> 88358.85 | G10: {=_xlfn.XLOOKUP(1, (INDIRECT("'"&$C$6&"'!$6:$6")=G$6)* (INDIRECT("'"&$C$6&"'!$5:$5")=G$5), INDIRECT("'"&$C$6&"'!"&ROW()&":"&ROW()) )} -> 109573.14 | H10: {=_xlfn.XLOOKUP(1, (INDIRECT("'"&$C$6&"'!$6:$6")=H$6)* (INDIRECT("'"&$C$6&"'!$5:$5")=H$5), INDIRECT("'"&$C$6&"'!"&ROW()&":"&ROW()) )} -> 171673.77 | I10: {=_xlfn.XLOOKUP(1, (INDIRECT("'"&$C$6&"'!$6:$6")=I$6)* (INDIRECT("'"&$C$6&"'!$5:$5")=I$5), INDIRECT("'"&$C$6&"'!"&ROW()&":"&ROW()) )} -> 66041.883 | K10: =$D10-E10 -> -7493.2753 | L10: =$D10-F10 -> -3548.83 | M10: =$D10-G10 -> -24763.117 | N10: =$D10-H10 -> -86863.754 | O10: =$D10-I10 -> 18768.137 | Q10: =IFERROR($D10/E10-1,0) -> -0.081181016 | R10: =IFERROR($D10/F10-1,0) -> -0.040163832 | S10: =IFERROR($D10/G10-1,0) -> -0.22599624 | T10: =IFERROR($D10/H10-1,0) -> -0.5059815 | U10: =IFERROR($D10/I10-1,0) -> 0.28418537 | W10: {=INDIRECT("'"&$C$6&"'!"&ADDRESS(ROW(),COLUMN()+44))} -> 84810.02 | X10: {=INDIRECT("'"&$C$6&"'!"&ADDRESS(ROW(),COLUMN()+44))} -> 92303.295 | Y10: {=INDIRECT("'"&$C$6&"'!"&ADDRESS(ROW(),COLUMN()+44))} -> 88358.85 | Z10: {=INDIRECT("'"&$C$6&"'!"&ADDRESS(ROW(),COLUMN()+44))} -> 109573.14 | AA10: {=INDIRECT("'"&$C$6&"'!"&ADDRESS(ROW(),COLUMN()+44))} -> 171673.77 | AB10: {=INDIRECT("'"&$C$6&"'!"&ADDRESS(ROW(),COLUMN()+44))} -> 66041.883 | AD10: =$W10-X10 -> -7493.2753 | AE10: =$W10-Y10 -> -3548.83 | AF10: =$W10-Z10 -> -24763.117 | AG10: =$W10-AA10 -> -86863.754 | AH10: =$W10-AB10 -> 18768.137 | AJ10: =IFERROR($W10/X10-1,0) -> -0.081181016 | AK10: =IFERROR($W10/Y10-1,0) -> -0.040163832 | AL10: =IFERROR($W10/Z10-1,0) -> -0.22599624 | AM10: =IFERROR($W10/AA10-1,0) -> -0.5059815 | AN10: =IFERROR($W10/AB10-1,0) -> 0.28418537
C11: Saldo FdP | D11: =SUM(D8:D10) -> 3321188.7 | E11: =SUM(E8:E10) -> 3245474.1 | F11: =SUM(F8:F10) -> 3280334.6 | G11: =SUM(G8:G10) -> 3020734.4 | H11: =SUM(H8:H10) -> 3609083.8 | I11: =SUM(I8:I10) -> 3500227.1 | K11: =$D11-E11 -> 75714.557 | L11: =$D11-F11 -> 40854.11 | M11: =$D11-G11 -> 300454.3 | N11: =$D11-H11 -> -287895.16 | O11: =$D11-I11 -> -179038.39 | Q11: =IFERROR($D11/E11-1,0) -> 0.023329275 | R11: =IFERROR($D11/F11-1,0) -> 0.012454251 | S11: =IFERROR($D11/G11-1,0) -> 0.099463991 | T11: =IFERROR($D11/H11-1,0) -> -0.079769595 | U11: =IFERROR($D11/I11-1,0) -> -0.051150508 | W11: =SUM(W8:W10) -> 3321188.7 | X11: =SUM(X8:X10) -> 3245474.1 | Y11: =SUM(Y8:Y10) -> 3280334.6 | Z11: =SUM(Z8:Z10) -> 3020734.4 | AA11: =SUM(AA8:AA10) -> 3609083.8 | AB11: =SUM(AB8:AB10) -> 3500227.1 | AD11: =$W11-X11 -> 75714.557 | AE11: =$W11-Y11 -> 40854.11 | AF11: =$W11-Z11 -> 300454.3 | AG11: =$W11-AA11 -> -287895.16 | AH11: =$W11-AB11 -> -179038.39 | AJ11: =IFERROR($W11/X11-1,0) -> 0.023329275 | AK11: =IFERROR($W11/Y11-1,0) -> 0.012454251 | AL11: =IFERROR($W11/Z11-1,0) -> 0.099463991 | AM11: =IFERROR($W11/AA11-1,0) -> -0.079769595 | AN11: =IFERROR($W11/AB11-1,0) -> -0.051150508
A14: SALDO_PROM | C14: Vigente | D14: {=_xlfn.XLOOKUP(1, (INDIRECT("'"&$C$6&"'!$6:$6")=D$6)* (INDIRECT("'"&$C$6&"'!$5:$5")=D$5), INDIRECT("'"&$C$6&"'!"&ROW()&":"&ROW()) )} -> 3165468.5 | E14: {=_xlfn.XLOOKUP(1, (INDIRECT("'"&$C$6&"'!$6:$6")=E$6)* (INDIRECT("'"&$C$6&"'!$5:$5")=E$5), INDIRECT("'"&$C$6&"'!"&ROW()&":"&ROW()) )} -> 3078694.6 | F14: {=_xlfn.XLOOKUP(1, (INDIRECT("'"&$C$6&"'!$6:$6")=F$6)* (INDIRECT("'"&$C$6&"'!$5:$5")=F$5), INDIRECT("'"&$C$6&"'!"&ROW()&":"&ROW()) )} -> 3096567.5 | G14: {=_xlfn.XLOOKUP(1, (INDIRECT("'"&$C$6&"'!$6:$6")=G$6)* (INDIRECT("'"&$C$6&"'!$5:$5")=G$5), INDIRECT("'"&$C$6&"'!"&ROW()&":"&ROW()) )} -> 2841610 | H14: {=_xlfn.XLOOKUP(1, (INDIRECT("'"&$C$6&"'!$6:$6")=H$6)* (INDIRECT("'"&$C$6&"'!$5:$5")=H$5), INDIRECT("'"&$C$6&"'!"&ROW()&":"&ROW()) )} -> 3450850.9 | I14: {=_xlfn.XLOOKUP(1, (INDIRECT("'"&$C$6&"'!$6:$6")=I$6)* (INDIRECT("'"&$C$6&"'!$5:$5")=I$5), INDIRECT("'"&$C$6&"'!"&ROW()&":"&ROW()) )} -> 3343878.5 | K14: =$D14-E14 -> 86773.955 | L14: =$D14-F14 -> 68900.99 | M14: =$D14-G14 -> 323858.5 | N14: =$D14-H14 -> -285382.35 | O14: =$D14-I14 -> -178409.98 | Q14: =IFERROR($D14/E14-1,0) -> 0.028185308 | R14: =IFERROR($D14/F14-1,0) -> 0.022250763 | S14: =IFERROR($D14/G14-1,0) -> 0.11397007 | T14: =IFERROR($D14/H14-1,0) -> -0.082699126 | U14: =IFERROR($D14/I14-1,0) -> -0.053354206 | W14: {=INDIRECT("'"&$C$6&"'!"&ADDRESS(ROW(),COLUMN()+44))} -> 3101496 | X14: {=INDIRECT("'"&$C$6&"'!"&ADDRESS(ROW(),COLUMN()+44))} -> 3059754.3 | Y14: {=INDIRECT("'"&$C$6&"'!"&ADDRESS(ROW(),COLUMN()+44))} -> 3069509.7 | Z14: {=INDIRECT("'"&$C$6&"'!"&ADDRESS(ROW(),COLUMN()+44))} -> 2830433.6 | AA14: {=INDIRECT("'"&$C$6&"'!"&ADDRESS(ROW(),COLUMN()+44))} -> 3524089.4 | AB14: {=INDIRECT("'"&$C$6&"'!"&ADDRESS(ROW(),COLUMN()+44))} -> 3241831.4 | AD14: =$W14-X14 -> 41741.697 | AE14: =$W14-Y14 -> 31986.265 | AF14: =$W14-Z14 -> 271062.45 | AG14: =$W14-AA14 -> -422593.4 | AH14: =$W14-AB14 -> -140335.41 | AJ14: =IFERROR($W14/X14-1,0) -> 0.013642173 | AK14: =IFERROR($W14/Y14-1,0) -> 0.010420643 | AL14: =IFERROR($W14/Z14-1,0) -> 0.095767114 | AM14: =IFERROR($W14/AA14-1,0) -> -0.11991563 | AN14: =IFERROR($W14/AB14-1,0) -> -0.04328893
A15: SALDO_PROM | C15: Refinanciado | D15: {=_xlfn.XLOOKUP(1, (INDIRECT("'"&$C$6&"'!$6:$6")=D$6)* (INDIRECT("'"&$C$6&"'!$5:$5")=D$5), INDIRECT("'"&$C$6&"'!"&ROW()&":"&ROW()) )} -> 36267.49 | E15: {=_xlfn.XLOOKUP(1, (INDIRECT("'"&$C$6&"'!$6:$6")=E$6)* (INDIRECT("'"&$C$6&"'!$5:$5")=E$5), INDIRECT("'"&$C$6&"'!"&ROW()&":"&ROW()) )} -> 31668.279 | F15: {=_xlfn.XLOOKUP(1, (INDIRECT("'"&$C$6&"'!$6:$6")=F$6)* (INDIRECT("'"&$C$6&"'!$5:$5")=F$5), INDIRECT("'"&$C$6&"'!"&ROW()&":"&ROW()) )} -> 37148 | G15: {=_xlfn.XLOOKUP(1, (INDIRECT("'"&$C$6&"'!$6:$6")=G$6)* (INDIRECT("'"&$C$6&"'!$5:$5")=G$5), INDIRECT("'"&$C$6&"'!"&ROW()&":"&ROW()) )} -> 44237.049 | H15: {=_xlfn.XLOOKUP(1, (INDIRECT("'"&$C$6&"'!$6:$6")=H$6)* (INDIRECT("'"&$C$6&"'!$5:$5")=H$5), INDIRECT("'"&$C$6&"'!"&ROW()&":"&ROW()) )} -> 6162.1973 | I15: {=_xlfn.XLOOKUP(1, (INDIRECT("'"&$C$6&"'!$6:$6")=I$6)* (INDIRECT("'"&$C$6&"'!$5:$5")=I$5), INDIRECT("'"&$C$6&"'!"&ROW()&":"&ROW()) )} -> 12441.221 | K15: =$D15-E15 -> 4599.211 | L15: =$D15-F15 -> -880.51 | M15: =$D15-G15 -> -7969.5594 | N15: =$D15-H15 -> 30105.293 | O15: =$D15-I15 -> 23826.269 | Q15: =IFERROR($D15/E15-1,0) -> 0.14523085 | R15: =IFERROR($D15/F15-1,0) -> -0.023702757 | S15: =IFERROR($D15/G15-1,0) -> -0.18015576 | T15: =IFERROR($D15/H15-1,0) -> 4.8854801 | U15: =IFERROR($D15/I15-1,0) -> 1.915107 | W15: {=INDIRECT("'"&$C$6&"'!"&ADDRESS(ROW(),COLUMN()+44))} -> 37137.887 | X15: {=INDIRECT("'"&$C$6&"'!"&ADDRESS(ROW(),COLUMN()+44))} -> 33358.564 | Y15: {=INDIRECT("'"&$C$6&"'!"&ADDRESS(ROW(),COLUMN()+44))} -> 37573.085 | Z15: {=INDIRECT("'"&$C$6&"'!"&ADDRESS(ROW(),COLUMN()+44))} -> 44410.208 | AA15: {=INDIRECT("'"&$C$6&"'!"&ADDRESS(ROW(),COLUMN()+44))} -> 5713.7241 | AB15: {=INDIRECT("'"&$C$6&"'!"&ADDRESS(ROW(),COLUMN()+44))} -> 12001.905 | AD15: =$W15-X15 -> 3779.3231 | AE15: =$W15-Y15 -> -435.19833 | AF15: =$W15-Z15 -> -7272.3209 | AG15: =$W15-AA15 -> 31424.163 | AH15: =$W15-AB15 -> 25135.982 | AJ15: =IFERROR($W15/X15-1,0) -> 0.11329394 | AK15: =IFERROR($W15/Y15-1,0) -> -0.011582715 | AL15: =IFERROR($W15/Z15-1,0) -> -0.16375336 | AM15: =IFERROR($W15/AA15-1,0) -> 5.499769 | AN15: =IFERROR($W15/AB15-1,0) -> 2.0943326
A16: SALDO_PROM | C16: Vencido y Judicial | D16: {=_xlfn.XLOOKUP(1, (INDIRECT("'"&$C$6&"'!$6:$6")=D$6)* (INDIRECT("'"&$C$6&"'!$5:$5")=D$5), INDIRECT("'"&$C$6&"'!"&ROW()&":"&ROW()) )} -> 96644.16 | E16: {=_xlfn.XLOOKUP(1, (INDIRECT("'"&$C$6&"'!$6:$6")=E$6)* (INDIRECT("'"&$C$6&"'!$5:$5")=E$5), INDIRECT("'"&$C$6&"'!"&ROW()&":"&ROW()) )} -> 108022.07 | F16: {=_xlfn.XLOOKUP(1, (INDIRECT("'"&$C$6&"'!$6:$6")=F$6)* (INDIRECT("'"&$C$6&"'!$5:$5")=F$5), INDIRECT("'"&$C$6&"'!"&ROW()&":"&ROW()) )} -> 101854.37 | G16: {=_xlfn.XLOOKUP(1, (INDIRECT("'"&$C$6&"'!$6:$6")=G$6)* (INDIRECT("'"&$C$6&"'!$5:$5")=G$5), INDIRECT("'"&$C$6&"'!"&ROW()&":"&ROW()) )} -> 122146.45 | H16: {=_xlfn.XLOOKUP(1, (INDIRECT("'"&$C$6&"'!$6:$6")=H$6)* (INDIRECT("'"&$C$6&"'!$5:$5")=H$5), INDIRECT("'"&$C$6&"'!"&ROW()&":"&ROW()) )} -> 178129.15 | I16: {=_xlfn.XLOOKUP(1, (INDIRECT("'"&$C$6&"'!$6:$6")=I$6)* (INDIRECT("'"&$C$6&"'!$5:$5")=I$5), INDIRECT("'"&$C$6&"'!"&ROW()&":"&ROW()) )} -> 78613.723 | K16: =$D16-E16 -> -11377.914 | L16: =$D16-F16 -> -5210.21 | M16: =$D16-G16 -> -25502.287 | N16: =$D16-H16 -> -81484.989 | O16: =$D16-I16 -> 18030.437 | Q16: =IFERROR($D16/E16-1,0) -> -0.10532953 | R16: =IFERROR($D16/F16-1,0) -> -0.051153524 | S16: =IFERROR($D16/G16-1,0) -> -0.20878452 | T16: =IFERROR($D16/H16-1,0) -> -0.45744893 | U16: =IFERROR($D16/I16-1,0) -> 0.22935483 | W16: {=INDIRECT("'"&$C$6&"'!"&ADDRESS(ROW(),COLUMN()+44))} -> 100528.69 | X16: {=INDIRECT("'"&$C$6&"'!"&ADDRESS(ROW(),COLUMN()+44))} -> 110684.55 | Y16: {=INDIRECT("'"&$C$6&"'!"&ADDRESS(ROW(),COLUMN()+44))} -> 102470.95 | Z16: {=INDIRECT("'"&$C$6&"'!"&ADDRESS(ROW(),COLUMN()+44))} -> 133756.47 | AA16: {=INDIRECT("'"&$C$6&"'!"&ADDRESS(ROW(),COLUMN()+44))} -> 178374.56 | AB16: {=INDIRECT("'"&$C$6&"'!"&ADDRESS(ROW(),COLUMN()+44))} -> 84598.845 | AD16: =$W16-X16 -> -10155.86 | AE16: =$W16-Y16 -> -1942.2633 | AF16: =$W16-Z16 -> -33227.787 | AG16: =$W16-AA16 -> -77845.873 | AH16: =$W16-AB16 -> 15929.842 | AJ16: =IFERROR($W16/X16-1,0) -> -0.091754995 | AK16: =IFERROR($W16/Y16-1,0) -> -0.018954282 | AL16: =IFERROR($W16/Z16-1,0) -> -0.24842003 | AM16: =IFERROR($W16/AA16-1,0) -> -0.43641803 | AN16: =IFERROR($W16/AB16-1,0) -> 0.18829857
C17: Saldo Prom | D17: =SUM(D14:D16) -> 3298380.2 | E17: =SUM(E14:E16) -> 3218384.9 | F17: =SUM(F14:F16) -> 3235569.9 | G17: =SUM(G14:G16) -> 3007993.5 | H17: =SUM(H14:H16) -> 3635142.2 | I17: =SUM(I14:I16) -> 3434933.5 | K17: =$D17-E17 -> 79995.252 | L17: =$D17-F17 -> 62810.27 | M17: =$D17-G17 -> 290386.65 | N17: =$D17-H17 -> -336762.05 | O17: =$D17-I17 -> -136553.28 | Q17: =IFERROR($D17/E17-1,0) -> 0.024855713 | R17: =IFERROR($D17/F17-1,0) -> 0.019412429 | S17: =IFERROR($D17/G17-1,0) -> 0.096538322 | T17: =IFERROR($D17/H17-1,0) -> -0.09264068 | U17: =IFERROR($D17/I17-1,0) -> -0.039754271 | W17: =SUM(W14:W16) -> 3239162.6 | X17: =SUM(X14:X16) -> 3203797.4 | Y17: =SUM(Y14:Y16) -> 3209553.8 | Z17: =SUM(Z14:Z16) -> 3008600.2 | AA17: =SUM(AA14:AA16) -> 3708177.7 | AB17: =SUM(AB14:AB16) -> 3338432.2 | AD17: =$W17-X17 -> 35365.161 | AE17: =$W17-Y17 -> 29608.803 | AF17: =$W17-Z17 -> 230562.34 | AG17: =$W17-AA17 -> -469015.11 | AH17: =$W17-AB17 -> -99269.591 | AJ17: =IFERROR($W17/X17-1,0) -> 0.011038513 | AK17: =IFERROR($W17/Y17-1,0) -> 0.0092252087 | AL17: =IFERROR($W17/Z17-1,0) -> 0.076634423 | AM17: =IFERROR($W17/AA17-1,0) -> -0.12648129 | AN17: =IFERROR($W17/AB17-1,0) -> -0.029735392
C20: Vigente | D20: =IFERROR(((1+D38/D14)^(360/D$3))-1,0) -> 0.16676474 | E20: =IFERROR(((1+E38/E14)^(360/E$3))-1,0) -> 0.16679745 | F20: =IFERROR(((1+F38/F14)^(360/F$3))-1,0) -> 0.16819333 | G20: =IFERROR(((1+G38/G14)^(360/G$3))-1,0) -> 0.16916884 | H20: =IFERROR(((1+H38/H14)^(360/H$3))-1,0) -> 0.17166177 | I20: =IFERROR(((1+I38/I14)^(360/I$3))-1,0) -> 0.18709846 | Q20: =($D20-E20)*10000 -> -0.32708434 | R20: =($D20-F20)*10000 -> -14.285908 | S20: =($D20-G20)*10000 -> -24.041055 | T20: =($D20-H20)*10000 -> -48.970353 | U20: =($D20-I20)*10000 -> -203.33726 | W20: {=INDIRECT("'"&$C$6&"'!"&ADDRESS(ROW(),COLUMN()+44))} -> 0.16764934 | X20: {=INDIRECT("'"&$C$6&"'!"&ADDRESS(ROW(),COLUMN()+44))} -> 0.16628708 | Y20: {=INDIRECT("'"&$C$6&"'!"&ADDRESS(ROW(),COLUMN()+44))} -> 0.16803228 | Z20: {=INDIRECT("'"&$C$6&"'!"&ADDRESS(ROW(),COLUMN()+44))} -> 0.17002459 | AA20: {=INDIRECT("'"&$C$6&"'!"&ADDRESS(ROW(),COLUMN()+44))} -> 0.17330211 | AB20: {=INDIRECT("'"&$C$6&"'!"&ADDRESS(ROW(),COLUMN()+44))} -> 0.18774684 | AJ20: =($W20-X20)*10000 -> 13.622664 | AK20: =($W20-Y20)*10000 -> -3.8293202 | AL20: =($W20-Z20)*10000 -> -23.752493 | AM20: =($W20-AA20)*10000 -> -56.52765 | AN20: =($W20-AB20)*10000 -> -200.975
C21: Refinanciado | D21: =IFERROR(((1+D39/D15)^(360/D$3))-1,0) -> 0.078418696 | E21: =IFERROR(((1+E39/E15)^(360/E$3))-1,0) -> 0.072561465 | F21: =IFERROR(((1+F39/F15)^(360/F$3))-1,0) -> 0.0784327 | G21: =IFERROR(((1+G39/G15)^(360/G$3))-1,0) -> 0.059813869 | H21: =IFERROR(((1+H39/H15)^(360/H$3))-1,0) -> 0.064599699 | I21: =IFERROR(((1+I39/I15)^(360/I$3))-1,0) -> 0.060315445 | Q21: =($D21-E21)*10000 -> 58.572311 | R21: =($D21-F21)*10000 -> -0.14003364 | S21: =($D21-G21)*10000 -> 186.04827 | T21: =($D21-H21)*10000 -> 138.18998 | U21: =($D21-I21)*10000 -> 181.03252 | W21: {=INDIRECT("'"&$C$6&"'!"&ADDRESS(ROW(),COLUMN()+44))} -> 0.077494623 | X21: {=INDIRECT("'"&$C$6&"'!"&ADDRESS(ROW(),COLUMN()+44))} -> 0.072375067 | Y21: {=INDIRECT("'"&$C$6&"'!"&ADDRESS(ROW(),COLUMN()+44))} -> 0.077073241 | Z21: {=INDIRECT("'"&$C$6&"'!"&ADDRESS(ROW(),COLUMN()+44))} -> 0.065973937 | AA21: {=INDIRECT("'"&$C$6&"'!"&ADDRESS(ROW(),COLUMN()+44))} -> 0.074294711 | AB21: {=INDIRECT("'"&$C$6&"'!"&ADDRESS(ROW(),COLUMN()+44))} -> 0.070310613 | AJ21: =($W21-X21)*10000 -> 51.195564 | AK21: =($W21-Y21)*10000 -> 4.2138223 | AL21: =($W21-Z21)*10000 -> 115.20686 | AM21: =($W21-AA21)*10000 -> 31.99912 | AN21: =($W21-AB21)*10000 -> 71.840104
C22: Vencido y Judicial | D22: =IFERROR(((1+D40/D16)^(360/D$3))-1,0) -> 0.08972157 | E22: =IFERROR(((1+E40/E16)^(360/E$3))-1,0) -> 0.087265586 | F22: =IFERROR(((1+F40/F16)^(360/F$3))-1,0) -> 0.097956684 | G22: =IFERROR(((1+G40/G16)^(360/G$3))-1,0) -> 0.11208224 | H22: =IFERROR(((1+H40/H16)^(360/H$3))-1,0) -> 0.064649014 | I22: =IFERROR(((1+I40/I16)^(360/I$3))-1,0) -> 0.055202672 | Q22: =($D22-E22)*10000 -> 24.55984 | R22: =($D22-F22)*10000 -> -82.351146 | S22: =($D22-G22)*10000 -> -223.60672 | T22: =($D22-H22)*10000 -> 250.72556 | U22: =($D22-I22)*10000 -> 345.18897 | W22: {=INDIRECT("'"&$C$6&"'!"&ADDRESS(ROW(),COLUMN()+44))} -> 0.092717636 | X22: {=INDIRECT("'"&$C$6&"'!"&ADDRESS(ROW(),COLUMN()+44))} -> 0.090299602 | Y22: {=INDIRECT("'"&$C$6&"'!"&ADDRESS(ROW(),COLUMN()+44))} -> 0.094298888 | Z22: {=INDIRECT("'"&$C$6&"'!"&ADDRESS(ROW(),COLUMN()+44))} -> 0.095011803 | AA22: {=INDIRECT("'"&$C$6&"'!"&ADDRESS(ROW(),COLUMN()+44))} -> 0.062221607 | AB22: {=INDIRECT("'"&$C$6&"'!"&ADDRESS(ROW(),COLUMN()+44))} -> 0.051973131 | AJ22: =($W22-X22)*10000 -> 24.180344 | AK22: =($W22-Y22)*10000 -> -15.812517 | AL22: =($W22-Z22)*10000 -> -22.941666 | AM22: =($W22-AA22)*10000 -> 304.96029 | AN22: =($W22-AB22)*10000 -> 407.44505
C23: Tasa Implicita | D23: =IFERROR(((1+D41/D17)^(360/D$3))-1,0) -> 0.16343382 | E23: =IFERROR(((1+E41/E17)^(360/E$3))-1,0) -> 0.16308314 | F23: =IFERROR(((1+F41/F17)^(360/F$3))-1,0) -> 0.16485398 | G23: =IFERROR(((1+G41/G17)^(360/G$3))-1,0) -> 0.16512237 | H23: =IFERROR(((1+H41/H17)^(360/H$3))-1,0) -> 0.16600838 | I23: =IFERROR(((1+I41/I17)^(360/I$3))-1,0) -> 0.18343664 | Q23: =($D23-E23)*10000 -> 3.5067804 | R23: =($D23-F23)*10000 -> -14.20159 | S23: =($D23-G23)*10000 -> -16.885491 | T23: =($D23-H23)*10000 -> -25.745644 | U23: =($D23-I23)*10000 -> -200.02825 | W23: {=INDIRECT("'"&$C$6&"'!"&ADDRESS(ROW(),COLUMN()+44))} -> 0.16418505 | X23: {=INDIRECT("'"&$C$6&"'!"&ADDRESS(ROW(),COLUMN()+44))} -> 0.1625696 | Y23: {=INDIRECT("'"&$C$6&"'!"&ADDRESS(ROW(),COLUMN()+44))} -> 0.1645071 | Z23: {=INDIRECT("'"&$C$6&"'!"&ADDRESS(ROW(),COLUMN()+44))} -> 0.16499509 | AA23: {=INDIRECT("'"&$C$6&"'!"&ADDRESS(ROW(),COLUMN()+44))} -> 0.16756622 | AB23: {=INDIRECT("'"&$C$6&"'!"&ADDRESS(ROW(),COLUMN()+44))} -> 0.18367537 | AJ23: =($W23-X23)*10000 -> 16.154471 | AK23: =($W23-Y23)*10000 -> -3.2205072 | AL23: =($W23-Z23)*10000 -> -8.1004627 | AM23: =($W23-AA23)*10000 -> -33.811769 | AN23: =($W23-AB23)*10000 -> -194.90319
C26: Vigente | D26: =-IFERROR(((1-D44/D14)^(360/D$4))-1,0) -> -0.060973767 | E26: =-IFERROR(((1-E44/E14)^(360/E$4))-1,0) -> -0.063250996 | F26: =-IFERROR(((1-F44/F14)^(360/F$4))-1,0) -> -0.061716172 | G26: =-IFERROR(((1-G44/G14)^(360/G$4))-1,0) -> -0.068847077 | H26: =-IFERROR(((1-H44/H14)^(360/H$4))-1,0) -> -0.077250829 | I26: =-IFERROR(((1-I44/I14)^(360/I$4))-1,0) -> -0.073901929 | Q26: =($D26-E26)*10000 -> 22.772293 | R26: =($D26-F26)*10000 -> 7.4240492 | S26: =($D26-G26)*10000 -> 78.733098 | T26: =($D26-H26)*10000 -> 162.77062 | U26: =($D26-I26)*10000 -> 129.28162 | W26: {=INDIRECT("'"&$C$6&"'!"&ADDRESS(ROW(),COLUMN()+44))} -> -0.061733011 | X26: {=INDIRECT("'"&$C$6&"'!"&ADDRESS(ROW(),COLUMN()+44))} -> -0.063725702 | Y26: {=INDIRECT("'"&$C$6&"'!"&ADDRESS(ROW(),COLUMN()+44))} -> -0.062110866 | Z26: {=INDIRECT("'"&$C$6&"'!"&ADDRESS(ROW(),COLUMN()+44))} -> -0.07018776 | AA26: {=INDIRECT("'"&$C$6&"'!"&ADDRESS(ROW(),COLUMN()+44))} -> -0.077652319 | AB26: {=INDIRECT("'"&$C$6&"'!"&ADDRESS(ROW(),COLUMN()+44))} -> -0.071837695 | AJ26: =($W26-X26)*10000 -> 19.926914 | AK26: =($W26-Y26)*10000 -> 3.7785527 | AL26: =($W26-Z26)*10000 -> 84.547486 | AM26: =($W26-AA26)*10000 -> 159.19308 | AN26: =($W26-AB26)*10000 -> 101.04684
C27: Refinanciado | D27: =-IFERROR(((1-D45/D15)^(360/D$4))-1,0) -> -0.062075309 | E27: =-IFERROR(((1-E45/E15)^(360/E$4))-1,0) -> -0.010266522 | F27: =-IFERROR(((1-F45/F15)^(360/F$4))-1,0) -> -0.062335948 | G27: =-IFERROR(((1-G45/G15)^(360/G$4))-1,0) -> -0.06580727 | H27: =-IFERROR(((1-H45/H15)^(360/H$4))-1,0) -> -0.074922107 | I27: =-IFERROR(((1-I45/I15)^(360/I$4))-1,0) -> -0.077408172 | Q27: =($D27-E27)*10000 -> -518.08787 | R27: =($D27-F27)*10000 -> 2.6063922 | S27: =($D27-G27)*10000 -> 37.319613 | T27: =($D27-H27)*10000 -> 128.46798 | U27: =($D27-I27)*10000 -> 153.32863 | W27: {=INDIRECT("'"&$C$6&"'!"&ADDRESS(ROW(),COLUMN()+44))} -> -0.062334564 | X27: {=INDIRECT("'"&$C$6&"'!"&ADDRESS(ROW(),COLUMN()+44))} -> -0.0098278781 | Y27: {=INDIRECT("'"&$C$6&"'!"&ADDRESS(ROW(),COLUMN()+44))} -> -0.062503812 | Z27: {=INDIRECT("'"&$C$6&"'!"&ADDRESS(ROW(),COLUMN()+44))} -> -0.066453036 | AA27: {=INDIRECT("'"&$C$6&"'!"&ADDRESS(ROW(),COLUMN()+44))} -> -0.075895307 | AB27: {=INDIRECT("'"&$C$6&"'!"&ADDRESS(ROW(),COLUMN()+44))} -> -0.075197445 | AJ27: =($W27-X27)*10000 -> -525.06686 | AK27: =($W27-Y27)*10000 -> 1.6924811 | AL27: =($W27-Z27)*10000 -> 41.184716 | AM27: =($W27-AA27)*10000 -> 135.60743 | AN27: =($W27-AB27)*10000 -> 128.62881
C28: Vencido y Judicial | D28: =-IFERROR(((1-D46/D16)^(360/D$4))-1,0) -> -0.068924425 | E28: =-IFERROR(((1-E46/E16)^(360/E$4))-1,0) -> -0.049994587 | F28: =-IFERROR(((1-F46/F16)^(360/F$4))-1,0) -> -0.069668886 | G28: =-IFERROR(((1-G46/G16)^(360/G$4))-1,0) -> -0.080503368 | H28: =-IFERROR(((1-H46/H16)^(360/H$4))-1,0) -> -0.074043534 | I28: =-IFERROR(((1-I46/I16)^(360/I$4))-1,0) -> -0.044435647 | Q28: =($D28-E28)*10000 -> -189.29837 | R28: =($D28-F28)*10000 -> 7.4446111 | S28: =($D28-G28)*10000 -> 115.78943 | T28: =($D28-H28)*10000 -> 51.191093 | U28: =($D28-I28)*10000 -> -244.88778 | W28: {=INDIRECT("'"&$C$6&"'!"&ADDRESS(ROW(),COLUMN()+44))} -> -0.0695619 | X28: {=INDIRECT("'"&$C$6&"'!"&ADDRESS(ROW(),COLUMN()+44))} -> -0.049273724 | Y28: {=INDIRECT("'"&$C$6&"'!"&ADDRESS(ROW(),COLUMN()+44))} -> -0.069947202 | Z28: {=INDIRECT("'"&$C$6&"'!"&ADDRESS(ROW(),COLUMN()+44))} -> -0.076444819 | AA28: {=INDIRECT("'"&$C$6&"'!"&ADDRESS(ROW(),COLUMN()+44))} -> -0.072862045 | AB28: {=INDIRECT("'"&$C$6&"'!"&ADDRESS(ROW(),COLUMN()+44))} -> -0.043699913 | AJ28: =($W28-X28)*10000 -> -202.88176 | AK28: =($W28-Y28)*10000 -> 3.8530112 | AL28: =($W28-Z28)*10000 -> 68.829188 | AM28: =($W28-AA28)*10000 -> 33.001445 | AN28: =($W28-AB28)*10000 -> -258.61987
C29: Tasa FTP | D29: =-IFERROR(((1-D47/D17)^(360/D$4))-1,0) -> -0.061218063 | E29: =-IFERROR(((1-E47/E17)^(360/E$4))-1,0) -> -0.062270295 | F29: =-IFERROR(((1-F47/F17)^(360/F$4))-1,0) -> -0.061972802 | G29: =-IFERROR(((1-G47/G17)^(360/G$4))-1,0) -> -0.069273379 | H29: =-IFERROR(((1-H47/H17)^(360/H$4))-1,0) -> -0.07708951 | I29: =-IFERROR(((1-I47/I17)^(360/I$4))-1,0) -> -0.073231814 | Q29: =($D29-E29)*10000 -> 10.522323 | R29: =($D29-F29)*10000 -> 7.5473856 | S29: =($D29-G29)*10000 -> 80.55316 | T29: =($D29-H29)*10000 -> 158.71447 | U29: =($D29-I29)*10000 -> 120.1375 | W29: {=INDIRECT("'"&$C$6&"'!"&ADDRESS(ROW(),COLUMN()+44))} -> -0.061982088 | X29: {=INDIRECT("'"&$C$6&"'!"&ADDRESS(ROW(),COLUMN()+44))} -> -0.062649114 | Y29: {=INDIRECT("'"&$C$6&"'!"&ADDRESS(ROW(),COLUMN()+44))} -> -0.06236484 | Z29: {=INDIRECT("'"&$C$6&"'!"&ADDRESS(ROW(),COLUMN()+44))} -> -0.070409998 | AA29: {=INDIRECT("'"&$C$6&"'!"&ADDRESS(ROW(),COLUMN()+44))} -> -0.077418736 | AB29: {=INDIRECT("'"&$C$6&"'!"&ADDRESS(ROW(),COLUMN()+44))} -> -0.071128209 | AJ29: =($W29-X29)*10000 -> 6.6702616 | AK29: =($W29-Y29)*10000 -> 3.8275128 | AL29: =($W29-Z29)*10000 -> 84.279094 | AM29: =($W29-AA29)*10000 -> 154.36647 | AN29: =($W29-AB29)*10000 -> 91.461211
C32: Vigente | D32: =D20+D26 -> 0.10579097 | E32: =E20+E26 -> 0.10354645 | F32: =F20+F26 -> 0.10647716 | G32: =G20+G26 -> 0.10032177 | H32: =H20+H26 -> 0.094410943 | I32: =I20+I26 -> 0.11319653 | Q32: =($D32-E32)*10000 -> 22.445209 | R32: =($D32-F32)*10000 -> -6.8618591 | S32: =($D32-G32)*10000 -> 54.692043 | T32: =($D32-H32)*10000 -> 113.80027 | U32: =($D32-I32)*10000 -> -74.055636 | W32: =W20+W26 -> 0.10591633 | X32: =X20+X26 -> 0.10256137 | Y32: =Y20+Y26 -> 0.10592141 | Z32: =Z20+Z26 -> 0.099836833 | AA32: =AA20+AA26 -> 0.09564979 | AB32: =AB20+AB26 -> 0.11590915 | AJ32: =($W32-X32)*10000 -> 33.549579 | AK32: =($W32-Y32)*10000 -> -0.050767495 | AL32: =($W32-Z32)*10000 -> 60.794993 | AM32: =($W32-AA32)*10000 -> 102.66543 | AN32: =($W32-AB32)*10000 -> -99.928161
C33: Refinanciado | D33: =D21+D27 -> 0.016343388 | E33: =E21+E27 -> 0.062294943 | F33: =F21+F27 -> 0.016096752 | G33: =G21+G27 -> -0.0059934007 | H33: =H21+H27 -> -0.010322409 | I33: =I21+I27 -> -0.017092727 | Q33: =($D33-E33)*10000 -> -459.51555 | R33: =($D33-F33)*10000 -> 2.4663586 | S33: =($D33-G33)*10000 -> 223.36788 | T33: =($D33-H33)*10000 -> 266.65796 | U33: =($D33-I33)*10000 -> 334.36115 | W33: =W21+W27 -> 0.015160059 | X33: =X21+X27 -> 0.062547189 | Y33: =Y21+Y27 -> 0.014569429 | Z33: =Z21+Z27 -> -0.00047909846 | AA33: =AA21+AA27 -> -0.0016005962 | AB33: =AB21+AB27 -> -0.0048868324 | AJ33: =($W33-X33)*10000 -> -473.8713 | AK33: =($W33-Y33)*10000 -> 5.9063034 | AL33: =($W33-Z33)*10000 -> 156.39158 | AM33: =($W33-AA33)*10000 -> 167.60655 | AN33: =($W33-AB33)*10000 -> 200.46892
C34: Vencido y Judicial | D34: =D22+D28 -> 0.020797145 | E34: =E22+E28 -> 0.037270998 | F34: =F22+F28 -> 0.028287799 | G34: =G22+G28 -> 0.031578874 | H34: =H22+H28 -> -0.0093945203 | I34: =I22+I28 -> 0.010767026 | Q34: =($D34-E34)*10000 -> -164.73853 | R34: =($D34-F34)*10000 -> -74.906535 | S34: =($D34-G34)*10000 -> -107.81729 | T34: =($D34-H34)*10000 -> 301.91665 | U34: =($D34-I34)*10000 -> 100.30119 | W34: =W22+W28 -> 0.023155736 | X34: =X22+X28 -> 0.041025878 | Y34: =Y22+Y28 -> 0.024351687 | Z34: =Z22+Z28 -> 0.018566984 | AA34: =AA22+AA28 -> -0.010640438 | AB34: =AB22+AB28 -> 0.0082732183 | AJ34: =($W34-X34)*10000 -> -178.70142 | AK34: =($W34-Y34)*10000 -> -11.959506 | AL34: =($W34-Z34)*10000 -> 45.887522 | AM34: =($W34-AA34)*10000 -> 337.96174 | AN34: =($W34-AB34)*10000 -> 148.82518
C35: Spread | D35: =D23+D29 -> 0.10221576 | E35: =E23+E29 -> 0.10081285 | F35: =F23+F29 -> 0.10288118 | G35: =G23+G29 -> 0.095848989 | H35: =H23+H29 -> 0.088918873 | I35: =I23+I29 -> 0.11020483 | Q35: =($D35-E35)*10000 -> 14.029103 | R35: =($D35-F35)*10000 -> -6.6542048 | S35: =($D35-G35)*10000 -> 63.667669 | T35: =($D35-H35)*10000 -> 132.96883 | U35: =($D35-I35)*10000 -> -79.890741 | W35: =W23+W29 -> 0.10220296 | X35: =X23+X29 -> 0.099920484 | Y35: =Y23+Y29 -> 0.10214226 | Z35: =Z23+Z29 -> 0.094585094 | AA35: =AA23+AA29 -> 0.090147487 | AB35: =AB23+AB29 -> 0.11254716 | AJ35: =($W35-X35)*10000 -> 22.824733 | AK35: =($W35-Y35)*10000 -> 0.60700565 | AL35: =($W35-Z35)*10000 -> 76.178632 | AM35: =($W35-AA35)*10000 -> 120.55471 | AN35: =($W35-AB35)*10000 -> -103.44198
A38: Ingreso_Financiero | C38: Vigente | D38: {=_xlfn.XLOOKUP(1, (INDIRECT("'"&$C$6&"'!$6:$6")=D$6)* (INDIRECT("'"&$C$6&"'!$5:$5")=D$5), INDIRECT("'"&$C$6&"'!"&ROW()&":"&ROW()) )} -> 42322.039 | E38: {=_xlfn.XLOOKUP(1, (INDIRECT("'"&$C$6&"'!$6:$6")=E$6)* (INDIRECT("'"&$C$6&"'!$5:$5")=E$5), INDIRECT("'"&$C$6&"'!"&ROW()&":"&ROW()) )} -> 41169.41 | F38: {=_xlfn.XLOOKUP(1, (INDIRECT("'"&$C$6&"'!$6:$6")=F$6)* (INDIRECT("'"&$C$6&"'!$5:$5")=F$5), INDIRECT("'"&$C$6&"'!"&ROW()&":"&ROW()) )} -> 37668.513 | G38: {=_xlfn.XLOOKUP(1, (INDIRECT("'"&$C$6&"'!$6:$6")=G$6)* (INDIRECT("'"&$C$6&"'!$5:$5")=G$5), INDIRECT("'"&$C$6&"'!"&ROW()&":"&ROW()) )} -> 38502.529 | H38: {=_xlfn.XLOOKUP(1, (INDIRECT("'"&$C$6&"'!$6:$6")=H$6)* (INDIRECT("'"&$C$6&"'!$5:$5")=H$5), INDIRECT("'"&$C$6&"'!"&ROW()&":"&ROW()) )} -> 47399.032 | I38: {=_xlfn.XLOOKUP(1, (INDIRECT("'"&$C$6&"'!$6:$6")=I$6)* (INDIRECT("'"&$C$6&"'!$5:$5")=I$5), INDIRECT("'"&$C$6&"'!"&ROW()&":"&ROW()) )} -> 49752.553 | K38: =$D38-E38 -> 1152.629 | L38: =$D38-F38 -> 4653.5263 | M38: =$D38-G38 -> 3819.5098 | N38: =$D38-H38 -> -5076.9925 | O38: =$D38-I38 -> -7430.5139 | Q38: =IFERROR($D38/E38-1,0) -> 0.02799722 | R38: =IFERROR($D38/F38-1,0) -> 0.12353889 | S38: =IFERROR($D38/G38-1,0) -> 0.099201529 | T38: =IFERROR($D38/H38-1,0) -> -0.10711173 | U38: =IFERROR($D38/I38-1,0) -> -0.1493494 | W38: {=INDIRECT("'"&$C$6&"'!"&ADDRESS(ROW(),COLUMN()+44))} -> 120956.71 | X38: {=INDIRECT("'"&$C$6&"'!"&ADDRESS(ROW(),COLUMN()+44))} -> 118424.28 | Y38: {=INDIRECT("'"&$C$6&"'!"&ADDRESS(ROW(),COLUMN()+44))} -> 78634.669 | Z38: {=INDIRECT("'"&$C$6&"'!"&ADDRESS(ROW(),COLUMN()+44))} -> 111842.2 | AA38: {=INDIRECT("'"&$C$6&"'!"&ADDRESS(ROW(),COLUMN()+44))} -> 143334.29 | AB38: {=INDIRECT("'"&$C$6&"'!"&ADDRESS(ROW(),COLUMN()+44))} -> 140450.34 | AD38: =$W38-X38 -> 2532.4236 | AE38: =$W38-Y38 -> 42322.039 | AF38: =$W38-Z38 -> 9114.5107 | AG38: =$W38-AA38 -> -22377.584 | AH38: =$W38-AB38 -> -19493.629 | AJ38: =IFERROR($W38/X38-1,0) -> 0.021384327 | AK38: =IFERROR($W38/Y38-1,0) -> 0.53821094 | AL38: =IFERROR($W38/Z38-1,0) -> 0.081494382 | AM38: =IFERROR($W38/AA38-1,0) -> -0.15612163 | AN38: =IFERROR($W38/AB38-1,0) -> -0.13879375
A39: Ingreso_Financiero | C39: Refinanciado | D39: {=_xlfn.XLOOKUP(1, (INDIRECT("'"&$C$6&"'!$6:$6")=D$6)* (INDIRECT("'"&$C$6&"'!$5:$5")=D$5), INDIRECT("'"&$C$6&"'!"&ROW()&":"&ROW()) )} -> 236.54399 | E39: {=_xlfn.XLOOKUP(1, (INDIRECT("'"&$C$6&"'!$6:$6")=E$6)* (INDIRECT("'"&$C$6&"'!$5:$5")=E$5), INDIRECT("'"&$C$6&"'!"&ROW()&":"&ROW()) )} -> 191.60212 | F39: {=_xlfn.XLOOKUP(1, (INDIRECT("'"&$C$6&"'!$6:$6")=F$6)* (INDIRECT("'"&$C$6&"'!$5:$5")=F$5), INDIRECT("'"&$C$6&"'!"&ROW()&":"&ROW()) )} -> 218.80858 | G39: {=_xlfn.XLOOKUP(1, (INDIRECT("'"&$C$6&"'!$6:$6")=G$6)* (INDIRECT("'"&$C$6&"'!$5:$5")=G$5), INDIRECT("'"&$C$6&"'!"&ROW()&":"&ROW()) )} -> 221.84932 | H39: {=_xlfn.XLOOKUP(1, (INDIRECT("'"&$C$6&"'!$6:$6")=H$6)* (INDIRECT("'"&$C$6&"'!$5:$5")=H$5), INDIRECT("'"&$C$6&"'!"&ROW()&":"&ROW()) )} -> 33.30675 | I39: {=_xlfn.XLOOKUP(1, (INDIRECT("'"&$C$6&"'!$6:$6")=I$6)* (INDIRECT("'"&$C$6&"'!$5:$5")=I$5), INDIRECT("'"&$C$6&"'!"&ROW()&":"&ROW()) )} -> 62.902324 | K39: =$D39-E39 -> 44.941867 | L39: =$D39-F39 -> 17.73541 | M39: =$D39-G39 -> 14.69467 | N39: =$D39-H39 -> 203.23724 | O39: =$D39-I39 -> 173.64167 | Q39: =IFERROR($D39/E39-1,0) -> 0.23455829 | R39: =IFERROR($D39/F39-1,0) -> 0.081054454 | S39: =IFERROR($D39/G39-1,0) -> 0.066237165 | T39: =IFERROR($D39/H39-1,0) -> 6.1019835 | U39: =IFERROR($D39/I39-1,0) -> 2.7604968 | W39: {=INDIRECT("'"&$C$6&"'!"&ADDRESS(ROW(),COLUMN()+44))} -> 695.13913 | X39: {=INDIRECT("'"&$C$6&"'!"&ADDRESS(ROW(),COLUMN()+44))} -> 584.43966 | Y39: {=INDIRECT("'"&$C$6&"'!"&ADDRESS(ROW(),COLUMN()+44))} -> 458.59514 | Z39: {=INDIRECT("'"&$C$6&"'!"&ADDRESS(ROW(),COLUMN()+44))} -> 711.22118 | AA39: {=INDIRECT("'"&$C$6&"'!"&ADDRESS(ROW(),COLUMN()+44))} -> 103.81815 | AB39: {=INDIRECT("'"&$C$6&"'!"&ADDRESS(ROW(),COLUMN()+44))} -> 204.45737 | AD39: =$W39-X39 -> 110.69947 | AE39: =$W39-Y39 -> 236.54399 | AF39: =$W39-Z39 -> -16.08205 | AG39: =$W39-AA39 -> 591.32098 | AH39: =$W39-AB39 -> 490.68176 | AJ39: =IFERROR($W39/X39-1,0) -> 0.18941128 | AK39: =IFERROR($W39/Y39-1,0) -> 0.51580134 | AL39: =IFERROR($W39/Z39-1,0) -> -0.022611883 | AM39: =IFERROR($W39/AA39-1,0) -> 5.695738 | AN39: =IFERROR($W39/AB39-1,0) -> 2.399922
A40: Ingreso_Financiero | C40: Vencido y Judicial | D40: {=_xlfn.XLOOKUP(1, (INDIRECT("'"&$C$6&"'!$6:$6")=D$6)* (INDIRECT("'"&$C$6&"'!$5:$5")=D$5), INDIRECT("'"&$C$6&"'!"&ROW()&":"&ROW()) )} -> 717.70826 | E40: {=_xlfn.XLOOKUP(1, (INDIRECT("'"&$C$6&"'!$6:$6")=E$6)* (INDIRECT("'"&$C$6&"'!$5:$5")=E$5), INDIRECT("'"&$C$6&"'!"&ROW()&":"&ROW()) )} -> 781.0622 | F40: {=_xlfn.XLOOKUP(1, (INDIRECT("'"&$C$6&"'!$6:$6")=F$6)* (INDIRECT("'"&$C$6&"'!$5:$5")=F$5), INDIRECT("'"&$C$6&"'!"&ROW()&":"&ROW()) )} -> 743.01558 | G40: {=_xlfn.XLOOKUP(1, (INDIRECT("'"&$C$6&"'!$6:$6")=G$6)* (INDIRECT("'"&$C$6&"'!$5:$5")=G$5), INDIRECT("'"&$C$6&"'!"&ROW()&":"&ROW()) )} -> 1122.515 | H40: {=_xlfn.XLOOKUP(1, (INDIRECT("'"&$C$6&"'!$6:$6")=H$6)* (INDIRECT("'"&$C$6&"'!$5:$5")=H$5), INDIRECT("'"&$C$6&"'!"&ROW()&":"&ROW()) )} -> 963.50454 | I40: {=_xlfn.XLOOKUP(1, (INDIRECT("'"&$C$6&"'!$6:$6")=I$6)* (INDIRECT("'"&$C$6&"'!$5:$5")=I$5), INDIRECT("'"&$C$6&"'!"&ROW()&":"&ROW()) )} -> 364.58819 | K40: =$D40-E40 -> -63.353939 | L40: =$D40-F40 -> -25.30732 | M40: =$D40-G40 -> -404.80673 | N40: =$D40-H40 -> -245.79628 | O40: =$D40-I40 -> 353.12007 | Q40: =IFERROR($D40/E40-1,0) -> -0.08111254 | R40: =IFERROR($D40/F40-1,0) -> -0.034060282 | S40: =IFERROR($D40/G40-1,0) -> -0.36062479 | T40: =IFERROR($D40/H40-1,0) -> -0.25510651 | U40: =IFERROR($D40/I40-1,0) -> 0.968545 | W40: {=INDIRECT("'"&$C$6&"'!"&ADDRESS(ROW(),COLUMN()+44))} -> 2236.6685 | X40: {=INDIRECT("'"&$C$6&"'!"&ADDRESS(ROW(),COLUMN()+44))} -> 2400.8776 | Y40: {=INDIRECT("'"&$C$6&"'!"&ADDRESS(ROW(),COLUMN()+44))} -> 1518.9602 | Z40: {=INDIRECT("'"&$C$6&"'!"&ADDRESS(ROW(),COLUMN()+44))} -> 3046.6137 | AA40: {=INDIRECT("'"&$C$6&"'!"&ADDRESS(ROW(),COLUMN()+44))} -> 2728.6286 | AB40: {=INDIRECT("'"&$C$6&"'!"&ADDRESS(ROW(),COLUMN()+44))} -> 1073.8701 | AD40: =$W40-X40 -> -164.2091 | AE40: =$W40-Y40 -> 717.70826 | AF40: =$W40-Z40 -> -809.94525 | AG40: =$W40-AA40 -> -491.96015 | AH40: =$W40-AB40 -> 1162.7984 | AJ40: =IFERROR($W40/X40-1,0) -> -0.068395449 | AK40: =IFERROR($W40/Y40-1,0) -> 0.4724997 | AL40: =IFERROR($W40/Z40-1,0) -> -0.26585098 | AM40: =IFERROR($W40/AA40-1,0) -> -0.18029575 | AN40: =IFERROR($W40/AB40-1,0) -> 1.0828111
C41: Ingreso Financiero | D41: =SUM(D38:D40) -> 43276.291 | E41: =SUM(E38:E40) -> 42142.075 | F41: =SUM(F38:F40) -> 38630.337 | G41: =SUM(G38:G40) -> 39846.894 | H41: =SUM(H38:H40) -> 48395.843 | I41: =SUM(I38:I40) -> 50180.044 | K41: =$D41-E41 -> 1134.2169 | L41: =$D41-F41 -> 4645.9544 | M41: =$D41-G41 -> 3429.3977 | N41: =$D41-H41 -> -5119.5515 | O41: =$D41-I41 -> -6903.7521 | Q41: =IFERROR($D41/E41-1,0) -> 0.026914122 | R41: =IFERROR($D41/F41-1,0) -> 0.12026699 | S41: =IFERROR($D41/G41-1,0) -> 0.086064368 | T41: =IFERROR($D41/H41-1,0) -> -0.10578494 | U41: =IFERROR($D41/I41-1,0) -> -0.13757964 | W41: =SUM(W38:W40) -> 123888.52 | X41: =SUM(X38:X40) -> 121409.6 | Y41: =SUM(Y38:Y40) -> 80612.224 | Z41: =SUM(Z38:Z40) -> 115600.03 | AA41: =SUM(AA38:AA40) -> 146166.74 | AB41: =SUM(AB38:AB40) -> 141728.66 | AD41: =$W41-X41 -> 2478.9139 | AE41: =$W41-Y41 -> 43276.291 | AF41: =$W41-Z41 -> 8288.4834 | AG41: =$W41-AA41 -> -22278.223 | AH41: =$W41-AB41 -> -17840.148 | AJ41: =IFERROR($W41/X41-1,0) -> 0.020417775 | AK41: =IFERROR($W41/Y41-1,0) -> 0.53684527 | AL41: =IFERROR($W41/Z41-1,0) -> 0.071699664 | AM41: =IFERROR($W41/AA41-1,0) -> -0.1524165 | AN41: =IFERROR($W41/AB41-1,0) -> -0.12587537
A44: FTP | C44: Vigente | D44: {=_xlfn.XLOOKUP(1, (INDIRECT("'"&$C$6&"'!$6:$6")=D$6)* (INDIRECT("'"&$C$6&"'!$5:$5")=D$5), INDIRECT("'"&$C$6&"'!"&ROW()&":"&ROW()) )} -> -16174.531 | E44: {=_xlfn.XLOOKUP(1, (INDIRECT("'"&$C$6&"'!$6:$6")=E$6)* (INDIRECT("'"&$C$6&"'!$5:$5")=E$5), INDIRECT("'"&$C$6&"'!"&ROW()&":"&ROW()) )} -> -16302.512 | F44: {=_xlfn.XLOOKUP(1, (INDIRECT("'"&$C$6&"'!$6:$6")=F$6)* (INDIRECT("'"&$C$6&"'!$5:$5")=F$5), INDIRECT("'"&$C$6&"'!"&ROW()&":"&ROW()) )} -> -14456.987 | G44: {=_xlfn.XLOOKUP(1, (INDIRECT("'"&$C$6&"'!$6:$6")=G$6)* (INDIRECT("'"&$C$6&"'!$5:$5")=G$5), INDIRECT("'"&$C$6&"'!"&ROW()&":"&ROW()) )} -> -16338.672 | H44: {=_xlfn.XLOOKUP(1, (INDIRECT("'"&$C$6&"'!$6:$6")=H$6)* (INDIRECT("'"&$C$6&"'!$5:$5")=H$5), INDIRECT("'"&$C$6&"'!"&ROW()&":"&ROW()) )} -> -22183.092 | I44: {=_xlfn.XLOOKUP(1, (INDIRECT("'"&$C$6&"'!$6:$6")=I$6)* (INDIRECT("'"&$C$6&"'!$5:$5")=I$5), INDIRECT("'"&$C$6&"'!"&ROW()&":"&ROW()) )} -> -20593.257 | K44: =$D44-E44 -> 127.98072 | L44: =$D44-F44 -> -1717.5445 | M44: =$D44-G44 -> 164.14033 | N44: =$D44-H44 -> 6008.5609 | O44: =$D44-I44 -> 4418.726 | Q44: =IFERROR($D44/E44-1,0) -> -0.007850368 | R44: =IFERROR($D44/F44-1,0) -> 0.11880376 | S44: =IFERROR($D44/G44-1,0) -> -0.010046124 | T44: =IFERROR($D44/H44-1,0) -> -0.27086219 | U44: =IFERROR($D44/I44-1,0) -> -0.21457149 | W44: {=INDIRECT("'"&$C$6&"'!"&ADDRESS(ROW(),COLUMN()+44))} -> -46562.954 | X44: {=INDIRECT("'"&$C$6&"'!"&ADDRESS(ROW(),COLUMN()+44))} -> -47377.887 | Y44: {=INDIRECT("'"&$C$6&"'!"&ADDRESS(ROW(),COLUMN()+44))} -> -30388.423 | Z44: {=INDIRECT("'"&$C$6&"'!"&ADDRESS(ROW(),COLUMN()+44))} -> -48135.909 | AA44: {=INDIRECT("'"&$C$6&"'!"&ADDRESS(ROW(),COLUMN()+44))} -> -66829.581 | AB44: {=INDIRECT("'"&$C$6&"'!"&ADDRESS(ROW(),COLUMN()+44))} -> -56388.067 | AD44: =$W44-X44 -> 814.93316 | AE44: =$W44-Y44 -> -16174.531 | AF44: =$W44-Z44 -> 1572.9548 | AG44: =$W44-AA44 -> 20266.627 | AH44: =$W44-AB44 -> 9825.1127 | AJ44: =IFERROR($W44/X44-1,0) -> -0.017200707 | AK44: =IFERROR($W44/Y44-1,0) -> 0.53225965 | AL44: =IFERROR($W44/Z44-1,0) -> -0.032677367 | AM44: =IFERROR($W44/AA44-1,0) -> -0.30325832 | AN44: =IFERROR($W44/AB44-1,0) -> -0.17424099
A45: FTP | C45: Refinanciado | D45: {=_xlfn.XLOOKUP(1, (INDIRECT("'"&$C$6&"'!$6:$6")=D$6)* (INDIRECT("'"&$C$6&"'!$5:$5")=D$5), INDIRECT("'"&$C$6&"'!"&ROW()&":"&ROW()) )} -> -188.57274 | E45: {=_xlfn.XLOOKUP(1, (INDIRECT("'"&$C$6&"'!$6:$6")=E$6)* (INDIRECT("'"&$C$6&"'!$5:$5")=E$5), INDIRECT("'"&$C$6&"'!"&ROW()&":"&ROW()) )} -> -27.866225 | F45: {=_xlfn.XLOOKUP(1, (INDIRECT("'"&$C$6&"'!$6:$6")=F$6)* (INDIRECT("'"&$C$6&"'!$5:$5")=F$5), INDIRECT("'"&$C$6&"'!"&ROW()&":"&ROW()) )} -> -175.12741 | G45: {=_xlfn.XLOOKUP(1, (INDIRECT("'"&$C$6&"'!$6:$6")=G$6)* (INDIRECT("'"&$C$6&"'!$5:$5")=G$5), INDIRECT("'"&$C$6&"'!"&ROW()&":"&ROW()) )} -> -243.44376 | H45: {=_xlfn.XLOOKUP(1, (INDIRECT("'"&$C$6&"'!$6:$6")=H$6)* (INDIRECT("'"&$C$6&"'!$5:$5")=H$5), INDIRECT("'"&$C$6&"'!"&ROW()&":"&ROW()) )} -> -38.45683 | I45: {=_xlfn.XLOOKUP(1, (INDIRECT("'"&$C$6&"'!$6:$6")=I$6)* (INDIRECT("'"&$C$6&"'!$5:$5")=I$5), INDIRECT("'"&$C$6&"'!"&ROW()&":"&ROW()) )} -> -80.133327 | K45: =$D45-E45 -> -160.70651 | L45: =$D45-F45 -> -13.44533 | M45: =$D45-G45 -> 54.87102 | N45: =$D45-H45 -> -150.11591 | O45: =$D45-I45 -> -108.43941 | Q45: =IFERROR($D45/E45-1,0) -> 5.7670716 | R45: =IFERROR($D45/F45-1,0) -> 0.076774561 | S45: =IFERROR($D45/G45-1,0) -> -0.22539506 | T45: =IFERROR($D45/H45-1,0) -> 3.9034915 | U45: =IFERROR($D45/I45-1,0) -> 1.3532374 | W45: {=INDIRECT("'"&$C$6&"'!"&ADDRESS(ROW(),COLUMN()+44))} -> -562.83874 | X45: {=INDIRECT("'"&$C$6&"'!"&ADDRESS(ROW(),COLUMN()+44))} -> -81.594087 | Y45: {=INDIRECT("'"&$C$6&"'!"&ADDRESS(ROW(),COLUMN()+44))} -> -374.266 | Z45: {=INDIRECT("'"&$C$6&"'!"&ADDRESS(ROW(),COLUMN()+44))} -> -716.23679 | AA45: {=INDIRECT("'"&$C$6&"'!"&ADDRESS(ROW(),COLUMN()+44))} -> -105.98158 | AB45: {=INDIRECT("'"&$C$6&"'!"&ADDRESS(ROW(),COLUMN()+44))} -> -218.20602 | AD45: =$W45-X45 -> -481.24465 | AE45: =$W45-Y45 -> -188.57274 | AF45: =$W45-Z45 -> 153.39805 | AG45: =$W45-AA45 -> -456.85716 | AH45: =$W45-AB45 -> -344.63272 | AJ45: =IFERROR($W45/X45-1,0) -> 5.8980334 | AK45: =IFERROR($W45/Y45-1,0) -> 0.50384684 | AL45: =IFERROR($W45/Z45-1,0) -> -0.21417226 | AM45: =IFERROR($W45/AA45-1,0) -> 4.3107223 | AN45: =IFERROR($W45/AB45-1,0) -> 1.5793915
A46: FTP | C46: Vencido y Judicial | D46: {=_xlfn.XLOOKUP(1, (INDIRECT("'"&$C$6&"'!$6:$6")=D$6)* (INDIRECT("'"&$C$6&"'!$5:$5")=D$5), INDIRECT("'"&$C$6&"'!"&ROW()&":"&ROW()) )} -> -556.28967 | E46: {=_xlfn.XLOOKUP(1, (INDIRECT("'"&$C$6&"'!$6:$6")=E$6)* (INDIRECT("'"&$C$6&"'!$5:$5")=E$5), INDIRECT("'"&$C$6&"'!"&ROW()&":"&ROW()) )} -> -454.74783 | F46: {=_xlfn.XLOOKUP(1, (INDIRECT("'"&$C$6&"'!$6:$6")=F$6)* (INDIRECT("'"&$C$6&"'!$5:$5")=F$5), INDIRECT("'"&$C$6&"'!"&ROW()&":"&ROW()) )} -> -534.94025 | G46: {=_xlfn.XLOOKUP(1, (INDIRECT("'"&$C$6&"'!$6:$6")=G$6)* (INDIRECT("'"&$C$6&"'!$5:$5")=G$5), INDIRECT("'"&$C$6&"'!"&ROW()&":"&ROW()) )} -> -817.11115 | H46: {=_xlfn.XLOOKUP(1, (INDIRECT("'"&$C$6&"'!$6:$6")=H$6)* (INDIRECT("'"&$C$6&"'!$5:$5")=H$5), INDIRECT("'"&$C$6&"'!"&ROW()&":"&ROW()) )} -> -1099.0423 | I46: {=_xlfn.XLOOKUP(1, (INDIRECT("'"&$C$6&"'!$6:$6")=I$6)* (INDIRECT("'"&$C$6&"'!$5:$5")=I$5), INDIRECT("'"&$C$6&"'!"&ROW()&":"&ROW()) )} -> -294.86772 | K46: =$D46-E46 -> -101.54184 | L46: =$D46-F46 -> -21.34942 | M46: =$D46-G46 -> 260.82148 | N46: =$D46-H46 -> 542.75263 | O46: =$D46-I46 -> -261.42195 | Q46: =IFERROR($D46/E46-1,0) -> 0.22329262 | R46: =IFERROR($D46/F46-1,0) -> 0.039909915 | S46: =IFERROR($D46/G46-1,0) -> -0.31919951 | T46: =IFERROR($D46/H46-1,0) -> -0.49384144 | U46: =IFERROR($D46/I46-1,0) -> 0.88657365 | W46: {=INDIRECT("'"&$C$6&"'!"&ADDRESS(ROW(),COLUMN()+44))} -> -1694.8612 | X46: {=INDIRECT("'"&$C$6&"'!"&ADDRESS(ROW(),COLUMN()+44))} -> -1333.6037 | Y46: {=INDIRECT("'"&$C$6&"'!"&ADDRESS(ROW(),COLUMN()+44))} -> -1138.5715 | Z46: {=INDIRECT("'"&$C$6&"'!"&ADDRESS(ROW(),COLUMN()+44))} -> -2470.8278 | AA46: {=INDIRECT("'"&$C$6&"'!"&ADDRESS(ROW(),COLUMN()+44))} -> -3180.5275 | AB46: {=INDIRECT("'"&$C$6&"'!"&ADDRESS(ROW(),COLUMN()+44))} -> -906.22973 | AD46: =$W46-X46 -> -361.25754 | AE46: =$W46-Y46 -> -556.28967 | AF46: =$W46-Z46 -> 775.96656 | AG46: =$W46-AA46 -> 1485.6663 | AH46: =$W46-AB46 -> -788.63149 | AJ46: =IFERROR($W46/X46-1,0) -> 0.27088823 | AK46: =IFERROR($W46/Y46-1,0) -> 0.4885856 | AL46: =IFERROR($W46/Z46-1,0) -> -0.31405125 | AM46: =IFERROR($W46/AA46-1,0) -> -0.46711317 | AN46: =IFERROR($W46/AB46-1,0) -> 0.87023353
C47: Costo de Fondos | D47: =SUM(D44:D46) -> -16919.394 | E47: =SUM(E44:E46) -> -16785.126 | F47: =SUM(F44:F46) -> -15167.055 | G47: =SUM(G44:G46) -> -17399.227 | H47: =SUM(H44:H46) -> -23320.591 | I47: =SUM(I44:I46) -> -20968.258 | K47: =$D47-E47 -> -134.26763 | L47: =$D47-F47 -> -1752.3392 | M47: =$D47-G47 -> 479.83283 | N47: =$D47-H47 -> 6401.1976 | O47: =$D47-I47 -> 4048.8646 | Q47: =IFERROR($D47/E47-1,0) -> 0.007999203 | R47: =IFERROR($D47/F47-1,0) -> 0.11553589 | S47: =IFERROR($D47/G47-1,0) -> -0.027577825 | T47: =IFERROR($D47/H47-1,0) -> -0.27448693 | U47: =IFERROR($D47/I47-1,0) -> -0.19309494 | W47: =SUM(W44:W46) -> -48820.654 | X47: =SUM(X44:X46) -> -48793.085 | Y47: =SUM(Y44:Y46) -> -31901.26 | Z47: =SUM(Z44:Z46) -> -51322.974 | AA47: =SUM(AA44:AA46) -> -70116.09 | AB47: =SUM(AB44:AB46) -> -57512.503 | AD47: =$W47-X47 -> -27.569032 | AE47: =$W47-Y47 -> -16919.394 | AF47: =$W47-Z47 -> 2502.3194 | AG47: =$W47-AA47 -> 21295.436 | AH47: =$W47-AB47 -> 8691.8485 | AJ47: =IFERROR($W47/X47-1,0) -> 0.00056501924 | AK47: =IFERROR($W47/Y47-1,0) -> 0.53036756 | AL47: =IFERROR($W47/Z47-1,0) -> -0.048756321 | AM47: =IFERROR($W47/AA47-1,0) -> -0.30371682 | AN47: =IFERROR($W47/AB47-1,0) -> -0.15112972
C50: Vigente | D50: =D38+D44 -> 26147.508 | E50: =E38+E44 -> 24866.898 | F50: =F38+F44 -> 23211.526 | G50: =G38+G44 -> 22163.858 | H50: =H38+H44 -> 25215.939 | I50: =I38+I44 -> 29159.296 | K50: =$D50-E50 -> 1280.6097 | L50: =$D50-F50 -> 2935.9818 | M50: =$D50-G50 -> 3983.6501 | N50: =$D50-H50 -> 931.56838 | O50: =$D50-I50 -> -3011.7879 | Q50: =IFERROR($D50/E50-1,0) -> 0.051498572 | R50: =IFERROR($D50/F50-1,0) -> 0.1264881 | S50: =IFERROR($D50/G50-1,0) -> 0.17973631 | T50: =IFERROR($D50/H50-1,0) -> 0.036943632 | U50: =IFERROR($D50/I50-1,0) -> -0.1032874 | W50: =W38+W44 -> 74393.754 | X50: =X38+X44 -> 71046.397 | Y50: =Y38+Y44 -> 48246.246 | Z50: =Z38+Z44 -> 63706.288 | AA50: =AA38+AA44 -> 76504.711 | AB50: =AB38+AB44 -> 84062.27 | AD50: =$W50-X50 -> 3347.3567 | AE50: =$W50-Y50 -> 26147.508 | AF50: =$W50-Z50 -> 10687.466 | AG50: =$W50-AA50 -> -2110.9571 | AH50: =$W50-AB50 -> -9668.5159 | AJ50: =IFERROR($W50/X50-1,0) -> 0.047115081 | AK50: =IFERROR($W50/Y50-1,0) -> 0.54195943 | AL50: =IFERROR($W50/Z50-1,0) -> 0.16776155 | AM50: =IFERROR($W50/AA50-1,0) -> -0.027592512 | AN50: =IFERROR($W50/AB50-1,0) -> -0.11501612
C51: Refinanciado | D51: =D39+D45 -> 47.97125 | E51: =E39+E45 -> 163.7359 | F51: =F39+F45 -> 43.68117 | G51: =G39+G45 -> -21.59444 | H51: =H39+H45 -> -5.15008 | I51: =I39+I45 -> -17.231003 | K51: =$D51-E51 -> -115.76465 | L51: =$D51-F51 -> 4.29008 | M51: =$D51-G51 -> 69.56569 | N51: =$D51-H51 -> 53.12133 | O51: =$D51-I51 -> 65.202253 | Q51: =IFERROR($D51/E51-1,0) -> -0.70702057 | R51: =IFERROR($D51/F51-1,0) -> 0.098213486 | S51: =IFERROR($D51/G51-1,0) -> -3.221463 | T51: =IFERROR($D51/H51-1,0) -> -10.314661 | U51: =IFERROR($D51/I51-1,0) -> -3.784008 | W51: =W39+W45 -> 132.30039 | X51: =X39+X45 -> 502.84558 | Y51: =Y39+Y45 -> 84.32914 | Z51: =Z39+Z45 -> -5.0156101 | AA51: =AA39+AA45 -> -2.16343 | AB51: =AB39+AB45 -> -13.748643 | AD51: =$W51-X51 -> -370.54519 | AE51: =$W51-Y51 -> 47.97125 | AF51: =$W51-Z51 -> 137.316 | AG51: =$W51-AA51 -> 134.46382 | AH51: =$W51-AB51 -> 146.04903 | AJ51: =IFERROR($W51/X51-1,0) -> -0.73689658 | AK51: =IFERROR($W51/Y51-1,0) -> 0.56885734 | AL51: =IFERROR($W51/Z51-1,0) -> -27.377726 | AM51: =IFERROR($W51/AA51-1,0) -> -62.153072 | AN51: =IFERROR($W51/AB51-1,0) -> -10.622796
C52: Vencido y Judicial | D52: =D40+D46 -> 161.41859 | E52: =E40+E46 -> 326.31437 | F52: =F40+F46 -> 208.07533 | G52: =G40+G46 -> 305.40384 | H52: =H40+H46 -> -135.53776 | I52: =I40+I46 -> 69.720474 | K52: =$D52-E52 -> -164.89577 | L52: =$D52-F52 -> -46.65674 | M52: =$D52-G52 -> -143.98524 | N52: =$D52-H52 -> 296.95635 | O52: =$D52-I52 -> 91.698119 | Q52: =IFERROR($D52/E52-1,0) -> -0.50532796 | R52: =IFERROR($D52/F52-1,0) -> -0.22423004 | S52: =IFERROR($D52/G52-1,0) -> -0.47145853 | T52: =IFERROR($D52/H52-1,0) -> -2.1909493 | U52: =IFERROR($D52/I52-1,0) -> 1.3152251 | W52: =W40+W46 -> 541.80728 | X52: =X40+X46 -> 1067.2739 | Y52: =Y40+Y46 -> 380.38869 | Z52: =Z40+Z46 -> 575.78597 | AA52: =AA40+AA46 -> -451.89887 | AB52: =AB40+AB46 -> 167.64033 | AD52: =$W52-X52 -> -525.46665 | AE52: =$W52-Y52 -> 161.41859 | AF52: =$W52-Z52 -> -33.978688 | AG52: =$W52-AA52 -> 993.70615 | AH52: =$W52-AB52 -> 374.16695 | AJ52: =IFERROR($W52/X52-1,0) -> -0.49234469 | AK52: =IFERROR($W52/Y52-1,0) -> 0.42435172 | AL52: =IFERROR($W52/Z52-1,0) -> -0.059012705 | AM52: =IFERROR($W52/AA52-1,0) -> -2.1989569 | AN52: =IFERROR($W52/AB52-1,0) -> 2.2319626
C53: Resultado Financiero Bruto | D53: =D41+D47 -> 26356.898 | E53: =E41+E47 -> 25356.948 | F53: =F41+F47 -> 23463.283 | G53: =G41+G47 -> 22447.667 | H53: =H41+H47 -> 25075.252 | I53: =I41+I47 -> 29211.785 | K53: =$D53-E53 -> 999.94932 | L53: =$D53-F53 -> 2893.6152 | M53: =$D53-G53 -> 3909.2306 | N53: =$D53-H53 -> 1281.6461 | O53: =$D53-I53 -> -2854.8875 | Q53: =IFERROR($D53/E53-1,0) -> 0.039434923 | R53: =IFERROR($D53/F53-1,0) -> 0.12332525 | S53: =IFERROR($D53/G53-1,0) -> 0.17414863 | T53: =IFERROR($D53/H53-1,0) -> 0.051111992 | U53: =IFERROR($D53/I53-1,0) -> -0.097730676 | W53: =W41+W47 -> 75067.861 | X53: =X41+X47 -> 72616.517 | Y53: =Y41+Y47 -> 48710.964 | Z53: =Z41+Z47 -> 64277.059 | AA53: =AA41+AA47 -> 76050.649 | AB53: =AB41+AB47 -> 84216.161 | AD53: =$W53-X53 -> 2451.3449 | AE53: =$W53-Y53 -> 26356.898 | AF53: =$W53-Z53 -> 10790.803 | AG53: =$W53-AA53 -> -982.78716 | AH53: =$W53-AB53 -> -9148.2999 | AJ53: =IFERROR($W53/X53-1,0) -> 0.033757402 | AK53: =IFERROR($W53/Y53-1,0) -> 0.54108758 | AL53: =IFERROR($W53/Z53-1,0) -> 0.16787954 | AM53: =IFERROR($W53/AA53-1,0) -> -0.012922798 | AN53: =IFERROR($W53/AB53-1,0) -> -0.10862879
A56: Gasto_Provision | C56: Provisiones Cartera | D56: {=_xlfn.XLOOKUP(1, (INDIRECT("'"&$C$6&"'!$6:$6")=D$6)* (INDIRECT("'"&$C$6&"'!$5:$5")=D$5), INDIRECT("'"&$C$6&"'!"&ROW()&":"&ROW()) )} -> -14835.835 | E56: {=_xlfn.XLOOKUP(1, (INDIRECT("'"&$C$6&"'!$6:$6")=E$6)* (INDIRECT("'"&$C$6&"'!$5:$5")=E$5), INDIRECT("'"&$C$6&"'!"&ROW()&":"&ROW()) )} -> -21748.988 | F56: {=_xlfn.XLOOKUP(1, (INDIRECT("'"&$C$6&"'!$6:$6")=F$6)* (INDIRECT("'"&$C$6&"'!$5:$5")=F$5), INDIRECT("'"&$C$6&"'!"&ROW()&":"&ROW()) )} -> -15838.701 | G56: {=_xlfn.XLOOKUP(1, (INDIRECT("'"&$C$6&"'!$6:$6")=G$6)* (INDIRECT("'"&$C$6&"'!$5:$5")=G$5), INDIRECT("'"&$C$6&"'!"&ROW()&":"&ROW()) )} -> -28069.95 | H56: {=_xlfn.XLOOKUP(1, (INDIRECT("'"&$C$6&"'!$6:$6")=H$6)* (INDIRECT("'"&$C$6&"'!$5:$5")=H$5), INDIRECT("'"&$C$6&"'!"&ROW()&":"&ROW()) )} -> -78548.728 | I56: {=_xlfn.XLOOKUP(1, (INDIRECT("'"&$C$6&"'!$6:$6")=I$6)* (INDIRECT("'"&$C$6&"'!$5:$5")=I$5), INDIRECT("'"&$C$6&"'!"&ROW()&":"&ROW()) )} -> -25857.675 | K56: =$D56-E56 -> 6913.1535 | L56: =$D56-F56 -> 1002.8658 | M56: =$D56-G56 -> 13234.115 | N56: =$D56-H56 -> 63712.893 | O56: =$D56-I56 -> 11021.841 | Q56: =IFERROR($D56/E56-1,0) -> -0.31786092 | R56: =IFERROR($D56/F56-1,0) -> -0.06331743 | S56: =IFERROR($D56/G56-1,0) -> -0.47146914 | T56: =IFERROR($D56/H56-1,0) -> -0.81112572 | U56: =IFERROR($D56/I56-1,0) -> -0.42625025 | W56: {=INDIRECT("'"&$C$6&"'!"&ADDRESS(ROW(),COLUMN()+44))} -> -45656.085 | X56: {=INDIRECT("'"&$C$6&"'!"&ADDRESS(ROW(),COLUMN()+44))} -> -61138.285 | Y56: {=INDIRECT("'"&$C$6&"'!"&ADDRESS(ROW(),COLUMN()+44))} -> -30820.251 | Z56: {=INDIRECT("'"&$C$6&"'!"&ADDRESS(ROW(),COLUMN()+44))} -> -89731.923 | AA56: {=INDIRECT("'"&$C$6&"'!"&ADDRESS(ROW(),COLUMN()+44))} -> -223843.64 | AB56: {=INDIRECT("'"&$C$6&"'!"&ADDRESS(ROW(),COLUMN()+44))} -> -65923.131 | AD56: =$W56-X56 -> 15482.2 | AE56: =$W56-Y56 -> -14835.835 | AF56: =$W56-Z56 -> 44075.838 | AG56: =$W56-AA56 -> 178187.55 | AH56: =$W56-AB56 -> 20267.046 | AJ56: =IFERROR($W56/X56-1,0) -> -0.25323249 | AK56: =IFERROR($W56/Y56-1,0) -> 0.48136645 | AL56: =IFERROR($W56/Z56-1,0) -> -0.49119462 | AM56: =IFERROR($W56/AA56-1,0) -> -0.79603581 | AN56: =IFERROR($W56/AB56-1,0) -> -0.30743451
A57: Recupero | C57: Recupero de Castigos | D57: {=_xlfn.XLOOKUP(1, (INDIRECT("'"&$C$6&"'!$6:$6")=D$6)* (INDIRECT("'"&$C$6&"'!$5:$5")=D$5), INDIRECT("'"&$C$6&"'!"&ROW()&":"&ROW()) )} -> 1988.2336 | E57: {=_xlfn.XLOOKUP(1, (INDIRECT("'"&$C$6&"'!$6:$6")=E$6)* (INDIRECT("'"&$C$6&"'!$5:$5")=E$5), INDIRECT("'"&$C$6&"'!"&ROW()&":"&ROW()) )} -> 1182.7463 | F57: {=_xlfn.XLOOKUP(1, (INDIRECT("'"&$C$6&"'!$6:$6")=F$6)* (INDIRECT("'"&$C$6&"'!$5:$5")=F$5), INDIRECT("'"&$C$6&"'!"&ROW()&":"&ROW()) )} -> 1726.7254 | G57: {=_xlfn.XLOOKUP(1, (INDIRECT("'"&$C$6&"'!$6:$6")=G$6)* (INDIRECT("'"&$C$6&"'!$5:$5")=G$5), INDIRECT("'"&$C$6&"'!"&ROW()&":"&ROW()) )} -> 3529.5582 | H57: {=_xlfn.XLOOKUP(1, (INDIRECT("'"&$C$6&"'!$6:$6")=H$6)* (INDIRECT("'"&$C$6&"'!$5:$5")=H$5), INDIRECT("'"&$C$6&"'!"&ROW()&":"&ROW()) )} -> 1476.2478 | I57: {=_xlfn.XLOOKUP(1, (INDIRECT("'"&$C$6&"'!$6:$6")=I$6)* (INDIRECT("'"&$C$6&"'!$5:$5")=I$5), INDIRECT("'"&$C$6&"'!"&ROW()&":"&ROW()) )} -> 1415.9338 | K57: =$D57-E57 -> 805.48732 | L57: =$D57-F57 -> 261.50816 | M57: =$D57-G57 -> -1541.3246 | N57: =$D57-H57 -> 511.98575 | O57: =$D57-I57 -> 572.29979 | Q57: =IFERROR($D57/E57-1,0) -> 0.68103137 | R57: =IFERROR($D57/F57-1,0) -> 0.15144745 | S57: =IFERROR($D57/G57-1,0) -> -0.43669052 | T57: =IFERROR($D57/H57-1,0) -> 0.34681558 | U57: =IFERROR($D57/I57-1,0) -> 0.40418541 | W57: {=INDIRECT("'"&$C$6&"'!"&ADDRESS(ROW(),COLUMN()+44))} -> 5556.1376 | X57: {=INDIRECT("'"&$C$6&"'!"&ADDRESS(ROW(),COLUMN()+44))} -> 3480.4536 | Y57: {=INDIRECT("'"&$C$6&"'!"&ADDRESS(ROW(),COLUMN()+44))} -> 3567.904 | Z57: {=INDIRECT("'"&$C$6&"'!"&ADDRESS(ROW(),COLUMN()+44))} -> 9433.478 | AA57: {=INDIRECT("'"&$C$6&"'!"&ADDRESS(ROW(),COLUMN()+44))} -> 4206.3886 | AB57: {=INDIRECT("'"&$C$6&"'!"&ADDRESS(ROW(),COLUMN()+44))} -> 3651.5433 | AD57: =$W57-X57 -> 2075.684 | AE57: =$W57-Y57 -> 1988.2336 | AF57: =$W57-Z57 -> -3877.3404 | AG57: =$W57-AA57 -> 1349.749 | AH57: =$W57-AB57 -> 1904.5943 | AJ57: =IFERROR($W57/X57-1,0) -> 0.59638317 | AK57: =IFERROR($W57/Y57-1,0) -> 0.55725535 | AL57: =IFERROR($W57/Z57-1,0) -> -0.41101918 | AM57: =IFERROR($W57/AA57-1,0) -> 0.32088073 | AN57: =IFERROR($W57/AB57-1,0) -> 0.52158612
C58: Provisiones Netas | D58: =SUM(D56:D57) -> -12847.601 | E58: =SUM(E56:E57) -> -20566.242 | F58: =SUM(F56:F57) -> -14111.975 | G58: =SUM(G56:G57) -> -24540.392 | H58: =SUM(H56:H57) -> -77072.48 | I58: =SUM(I56:I57) -> -24441.742 | K58: =$D58-E58 -> 7718.6408 | L58: =$D58-F58 -> 1264.374 | M58: =$D58-G58 -> 11692.791 | N58: =$D58-H58 -> 64224.879 | O58: =$D58-I58 -> 11594.141 | Q58: =IFERROR($D58/E58-1,0) -> -0.37530633 | R58: =IFERROR($D58/F58-1,0) -> -0.089595819 | S58: =IFERROR($D58/G58-1,0) -> -0.47647123 | T58: =IFERROR($D58/H58-1,0) -> -0.83330495 | U58: =IFERROR($D58/I58-1,0) -> -0.4743582 | W58: =SUM(W56:W57) -> -40099.948 | X58: =SUM(X56:X57) -> -57657.832 | Y58: =SUM(Y56:Y57) -> -27252.347 | Z58: =SUM(Z56:Z57) -> -80298.445 | AA58: =SUM(AA56:AA57) -> -219637.25 | AB58: =SUM(AB56:AB57) -> -62271.588 | AD58: =$W58-X58 -> 17557.884 | AE58: =$W58-Y58 -> -12847.601 | AF58: =$W58-Z58 -> 40198.498 | AG58: =$W58-AA58 -> 179537.3 | AH58: =$W58-AB58 -> 22171.64 | AJ58: =IFERROR($W58/X58-1,0) -> -0.30451863 | AK58: =IFERROR($W58/Y58-1,0) -> 0.47143101 | AL58: =IFERROR($W58/Z58-1,0) -> -0.50061365 | AM58: =IFERROR($W58/AA58-1,0) -> -0.81742647 | AN58: =IFERROR($W58/AB58-1,0) -> -0.35604745
C60: Resultado Financiero Neto | D60: =D53+D58 -> 13509.297 | E60: =E53+E58 -> 4790.7065 | F60: =F53+F58 -> 9351.3074 | G60: =G53+G58 -> -2092.7245 | H60: =H53+H58 -> -51997.228 | I60: =I53+I58 -> 4770.0436 | K60: =$D60-E60 -> 8718.5901 | L60: =$D60-F60 -> 4157.9891 | M60: =$D60-G60 -> 15602.021 | N60: =$D60-H60 -> 65506.525 | O60: =$D60-I60 -> 8739.253 | Q60: =IFERROR($D60/E60-1,0) -> 1.8198965 | R60: =IFERROR($D60/F60-1,0) -> 0.44464255 | S60: =IFERROR($D60/G60-1,0) -> -7.4553632 | T60: =IFERROR($D60/H60-1,0) -> -1.259808 | U60: =IFERROR($D60/I60-1,0) -> 1.8321118 | W60: =W53+W58 -> 34967.914 | X60: =X53+X58 -> 14958.685 | Y60: =Y53+Y58 -> 21458.617 | Z60: =Z53+Z58 -> -16021.387 | AA60: =AA53+AA58 -> -143586.6 | AB60: =AB53+AB58 -> 21944.574 | AD60: =$W60-X60 -> 20009.229 | AE60: =$W60-Y60 -> 13509.297 | AF60: =$W60-Z60 -> 50989.301 | AG60: =$W60-AA60 -> 178554.51 | AH60: =$W60-AB60 -> 13023.34 | AJ60: =IFERROR($W60/X60-1,0) -> 1.3376329 | AK60: =IFERROR($W60/Y60-1,0) -> 0.62955112 | AL60: =IFERROR($W60/Z60-1,0) -> -3.1825772 | AM60: =IFERROR($W60/AA60-1,0) -> -1.2435319 | AN60: =IFERROR($W60/AB60-1,0) -> 0.59346516
A63: INOF | C63: Seguro de Desgravamen | D63: {=_xlfn.XLOOKUP(1, (INDIRECT("'"&$C$6&"'!$6:$6")=D$6)* (INDIRECT("'"&$C$6&"'!$5:$5")=D$5), INDIRECT("'"&$C$6&"'!"&ROW()&":"&ROW()) )} -> 285.92706 | E63: {=_xlfn.XLOOKUP(1, (INDIRECT("'"&$C$6&"'!$6:$6")=E$6)* (INDIRECT("'"&$C$6&"'!$5:$5")=E$5), INDIRECT("'"&$C$6&"'!"&ROW()&":"&ROW()) )} -> 313.71389 | F63: {=_xlfn.XLOOKUP(1, (INDIRECT("'"&$C$6&"'!$6:$6")=F$6)* (INDIRECT("'"&$C$6&"'!$5:$5")=F$5), INDIRECT("'"&$C$6&"'!"&ROW()&":"&ROW()) )} -> 271.77459 | G63: {=_xlfn.XLOOKUP(1, (INDIRECT("'"&$C$6&"'!$6:$6")=G$6)* (INDIRECT("'"&$C$6&"'!$5:$5")=G$5), INDIRECT("'"&$C$6&"'!"&ROW()&":"&ROW()) )} -> 150.23105 | H63: {=_xlfn.XLOOKUP(1, (INDIRECT("'"&$C$6&"'!$6:$6")=H$6)* (INDIRECT("'"&$C$6&"'!$5:$5")=H$5), INDIRECT("'"&$C$6&"'!"&ROW()&":"&ROW()) )} -> 428.11719 | I63: {=_xlfn.XLOOKUP(1, (INDIRECT("'"&$C$6&"'!$6:$6")=I$6)* (INDIRECT("'"&$C$6&"'!$5:$5")=I$5), INDIRECT("'"&$C$6&"'!"&ROW()&":"&ROW()) )} -> 293.71883 | K63: =$D63-E63 -> -27.786837 | L63: =$D63-F63 -> 14.152465 | M63: =$D63-G63 -> 135.696 | N63: =$D63-H63 -> -142.19013 | O63: =$D63-I63 -> -7.7917691 | Q63: =IFERROR($D63/E63-1,0) -> -0.088573816 | R63: =IFERROR($D63/F63-1,0) -> 0.052074276 | S63: =IFERROR($D63/G63-1,0) -> 0.90324869 | T63: =IFERROR($D63/H63-1,0) -> -0.332129 | U63: =IFERROR($D63/I63-1,0) -> -0.026527986 | W63: {=INDIRECT("'"&$C$6&"'!"&ADDRESS(ROW(),COLUMN()+44))} -> 913.56677 | X63: {=INDIRECT("'"&$C$6&"'!"&ADDRESS(ROW(),COLUMN()+44))} -> 935.38422 | Y63: {=INDIRECT("'"&$C$6&"'!"&ADDRESS(ROW(),COLUMN()+44))} -> 627.63972 | Z63: {=INDIRECT("'"&$C$6&"'!"&ADDRESS(ROW(),COLUMN()+44))} -> 780.06137 | AA63: {=INDIRECT("'"&$C$6&"'!"&ADDRESS(ROW(),COLUMN()+44))} -> 1241.7416 | AB63: {=INDIRECT("'"&$C$6&"'!"&ADDRESS(ROW(),COLUMN()+44))} -> 1031.4181 | AD63: =$W63-X63 -> -21.81745 | AE63: =$W63-Y63 -> 285.92706 | AF63: =$W63-Z63 -> 133.5054 | AG63: =$W63-AA63 -> -328.17478 | AH63: =$W63-AB63 -> -117.85135 | AJ63: =IFERROR($W63/X63-1,0) -> -0.023324586 | AK63: =IFERROR($W63/Y63-1,0) -> 0.45555922 | AL63: =IFERROR($W63/Z63-1,0) -> 0.17114731 | AM63: =IFERROR($W63/AA63-1,0) -> -0.26428589 | AN63: =IFERROR($W63/AB63-1,0) -> -0.11426147
A64: INOF | C64: Comisiones | D64: {=_xlfn.XLOOKUP(1, (INDIRECT("'"&$C$6&"'!$6:$6")=D$6)* (INDIRECT("'"&$C$6&"'!$5:$5")=D$5), INDIRECT("'"&$C$6&"'!"&ROW()&":"&ROW()) )} -> 0.66833 | E64: {=_xlfn.XLOOKUP(1, (INDIRECT("'"&$C$6&"'!$6:$6")=E$6)* (INDIRECT("'"&$C$6&"'!$5:$5")=E$5), INDIRECT("'"&$C$6&"'!"&ROW()&":"&ROW()) )} -> 0.90652286 | F64: {=_xlfn.XLOOKUP(1, (INDIRECT("'"&$C$6&"'!$6:$6")=F$6)* (INDIRECT("'"&$C$6&"'!$5:$5")=F$5), INDIRECT("'"&$C$6&"'!"&ROW()&":"&ROW()) )} -> 0.58767 | G64: {=_xlfn.XLOOKUP(1, (INDIRECT("'"&$C$6&"'!$6:$6")=G$6)* (INDIRECT("'"&$C$6&"'!$5:$5")=G$5), INDIRECT("'"&$C$6&"'!"&ROW()&":"&ROW()) )} -> 1.11633 | H64: {=_xlfn.XLOOKUP(1, (INDIRECT("'"&$C$6&"'!$6:$6")=H$6)* (INDIRECT("'"&$C$6&"'!$5:$5")=H$5), INDIRECT("'"&$C$6&"'!"&ROW()&":"&ROW()) )} -> 1.3 | I64: {=_xlfn.XLOOKUP(1, (INDIRECT("'"&$C$6&"'!$6:$6")=I$6)* (INDIRECT("'"&$C$6&"'!$5:$5")=I$5), INDIRECT("'"&$C$6&"'!"&ROW()&":"&ROW()) )} -> 2.18633 | K64: =$D64-E64 -> -0.23819286 | L64: =$D64-F64 -> 0.08066 | M64: =$D64-G64 -> -0.448 | N64: =$D64-H64 -> -0.63167 | O64: =$D64-I64 -> -1.518 | Q64: =IFERROR($D64/E64-1,0) -> -0.26275439 | R64: =IFERROR($D64/F64-1,0) -> 0.1372539 | S64: =IFERROR($D64/G64-1,0) -> -0.40131502 | T64: =IFERROR($D64/H64-1,0) -> -0.4859 | U64: =IFERROR($D64/I64-1,0) -> -0.69431422 | W64: {=INDIRECT("'"&$C$6&"'!"&ADDRESS(ROW(),COLUMN()+44))} -> 1.89266 | X64: {=INDIRECT("'"&$C$6&"'!"&ADDRESS(ROW(),COLUMN()+44))} -> 2.7195686 | Y64: {=INDIRECT("'"&$C$6&"'!"&ADDRESS(ROW(),COLUMN()+44))} -> 1.22433 | Z64: {=INDIRECT("'"&$C$6&"'!"&ADDRESS(ROW(),COLUMN()+44))} -> 3.207 | AA64: {=INDIRECT("'"&$C$6&"'!"&ADDRESS(ROW(),COLUMN()+44))} -> 4.22566 | AB64: {=INDIRECT("'"&$C$6&"'!"&ADDRESS(ROW(),COLUMN()+44))} -> 7.15967 | AD64: =$W64-X64 -> -0.82690857 | AE64: =$W64-Y64 -> 0.66833 | AF64: =$W64-Z64 -> -1.31434 | AG64: =$W64-AA64 -> -2.333 | AH64: =$W64-AB64 -> -5.26701 | AJ64: =IFERROR($W64/X64-1,0) -> -0.30405873 | AK64: =IFERROR($W64/Y64-1,0) -> 0.54587407 | AL64: =IFERROR($W64/Z64-1,0) -> -0.40983474 | AM64: =IFERROR($W64/AA64-1,0) -> -0.5521031 | AN64: =IFERROR($W64/AB64-1,0) -> -0.73564983
A65: INOF | C65: Gastos de casilleros | D65: {=_xlfn.XLOOKUP(1, (INDIRECT("'"&$C$6&"'!$6:$6")=D$6)* (INDIRECT("'"&$C$6&"'!$5:$5")=D$5), INDIRECT("'"&$C$6&"'!"&ROW()&":"&ROW()) )} -> 0.29 | E65: {=_xlfn.XLOOKUP(1, (INDIRECT("'"&$C$6&"'!$6:$6")=E$6)* (INDIRECT("'"&$C$6&"'!$5:$5")=E$5), INDIRECT("'"&$C$6&"'!"&ROW()&":"&ROW()) )} -> 0 | F65: {=_xlfn.XLOOKUP(1, (INDIRECT("'"&$C$6&"'!$6:$6")=F$6)* (INDIRECT("'"&$C$6&"'!$5:$5")=F$5), INDIRECT("'"&$C$6&"'!"&ROW()&":"&ROW()) )} -> 0 | G65: {=_xlfn.XLOOKUP(1, (INDIRECT("'"&$C$6&"'!$6:$6")=G$6)* (INDIRECT("'"&$C$6&"'!$5:$5")=G$5), INDIRECT("'"&$C$6&"'!"&ROW()&":"&ROW()) )} -> 0 | H65: {=_xlfn.XLOOKUP(1, (INDIRECT("'"&$C$6&"'!$6:$6")=H$6)* (INDIRECT("'"&$C$6&"'!$5:$5")=H$5), INDIRECT("'"&$C$6&"'!"&ROW()&":"&ROW()) )} -> 0 | I65: {=_xlfn.XLOOKUP(1, (INDIRECT("'"&$C$6&"'!$6:$6")=I$6)* (INDIRECT("'"&$C$6&"'!$5:$5")=I$5), INDIRECT("'"&$C$6&"'!"&ROW()&":"&ROW()) )} -> 0 | K65: =$D65-E65 -> 0.29 | L65: =$D65-F65 -> 0.29 | M65: =$D65-G65 -> 0.29 | N65: =$D65-H65 -> 0.29 | O65: =$D65-I65 -> 0.29 | Q65: =IFERROR($D65/E65-1,0) -> 0 | R65: =IFERROR($D65/F65-1,0) -> 0 | S65: =IFERROR($D65/G65-1,0) -> 0 | T65: =IFERROR($D65/H65-1,0) -> 0 | U65: =IFERROR($D65/I65-1,0) -> 0 | W65: {=INDIRECT("'"&$C$6&"'!"&ADDRESS(ROW(),COLUMN()+44))} -> 0.55 | X65: {=INDIRECT("'"&$C$6&"'!"&ADDRESS(ROW(),COLUMN()+44))} -> 0 | Y65: {=INDIRECT("'"&$C$6&"'!"&ADDRESS(ROW(),COLUMN()+44))} -> 0.26 | Z65: {=INDIRECT("'"&$C$6&"'!"&ADDRESS(ROW(),COLUMN()+44))} -> 0.18 | AA65: {=INDIRECT("'"&$C$6&"'!"&ADDRESS(ROW(),COLUMN()+44))} -> -0.14968 | AB65: {=INDIRECT("'"&$C$6&"'!"&ADDRESS(ROW(),COLUMN()+44))} -> 0.18 | AD65: =$W65-X65 -> 0.55 | AE65: =$W65-Y65 -> 0.29 | AF65: =$W65-Z65 -> 0.37 | AG65: =$W65-AA65 -> 0.69968 | AH65: =$W65-AB65 -> 0.37 | AJ65: =IFERROR($W65/X65-1,0) -> 0 | AK65: =IFERROR($W65/Y65-1,0) -> 1.1153846 | AL65: =IFERROR($W65/Z65-1,0) -> 2.0555556 | AM65: =IFERROR($W65/AA65-1,0) -> -4.6745056 | AN65: =IFERROR($W65/AB65-1,0) -> 2.0555556
A66: INOF | D66: {=_xlfn.XLOOKUP(1, (INDIRECT("'"&$C$6&"'!$6:$6")=D$6)* (INDIRECT("'"&$C$6&"'!$5:$5")=D$5), INDIRECT("'"&$C$6&"'!"&ROW()&":"&ROW()) )} -> 0 | E66: {=_xlfn.XLOOKUP(1, (INDIRECT("'"&$C$6&"'!$6:$6")=E$6)* (INDIRECT("'"&$C$6&"'!$5:$5")=E$5), INDIRECT("'"&$C$6&"'!"&ROW()&":"&ROW()) )} -> 0 | F66: {=_xlfn.XLOOKUP(1, (INDIRECT("'"&$C$6&"'!$6:$6")=F$6)* (INDIRECT("'"&$C$6&"'!$5:$5")=F$5), INDIRECT("'"&$C$6&"'!"&ROW()&":"&ROW()) )} -> 0 | G66: {=_xlfn.XLOOKUP(1, (INDIRECT("'"&$C$6&"'!$6:$6")=G$6)* (INDIRECT("'"&$C$6&"'!$5:$5")=G$5), INDIRECT("'"&$C$6&"'!"&ROW()&":"&ROW()) )} -> 0 | H66: {=_xlfn.XLOOKUP(1, (INDIRECT("'"&$C$6&"'!$6:$6")=H$6)* (INDIRECT("'"&$C$6&"'!$5:$5")=H$5), INDIRECT("'"&$C$6&"'!"&ROW()&":"&ROW()) )} -> 0 | I66: {=_xlfn.XLOOKUP(1, (INDIRECT("'"&$C$6&"'!$6:$6")=I$6)* (INDIRECT("'"&$C$6&"'!$5:$5")=I$5), INDIRECT("'"&$C$6&"'!"&ROW()&":"&ROW()) )} -> 0 | K66: =$D66-E66 -> 0 | L66: =$D66-F66 -> 0 | M66: =$D66-G66 -> 0 | N66: =$D66-H66 -> 0 | O66: =$D66-I66 -> 0 | Q66: =IFERROR($D66/E66-1,0) -> 0 | R66: =IFERROR($D66/F66-1,0) -> 0 | S66: =IFERROR($D66/G66-1,0) -> 0 | T66: =IFERROR($D66/H66-1,0) -> 0 | U66: =IFERROR($D66/I66-1,0) -> 0 | W66: {=INDIRECT("'"&$C$6&"'!"&ADDRESS(ROW(),COLUMN()+44))} -> 0 | X66: {=INDIRECT("'"&$C$6&"'!"&ADDRESS(ROW(),COLUMN()+44))} -> 0 | Y66: {=INDIRECT("'"&$C$6&"'!"&ADDRESS(ROW(),COLUMN()+44))} -> 0 | Z66: {=INDIRECT("'"&$C$6&"'!"&ADDRESS(ROW(),COLUMN()+44))} -> 0 | AA66: {=INDIRECT("'"&$C$6&"'!"&ADDRESS(ROW(),COLUMN()+44))} -> 0 | AB66: {=INDIRECT("'"&$C$6&"'!"&ADDRESS(ROW(),COLUMN()+44))} -> 0 | AD66: =$W66-X66 -> 0 | AE66: =$W66-Y66 -> 0 | AF66: =$W66-Z66 -> 0 | AG66: =$W66-AA66 -> 0 | AH66: =$W66-AB66 -> 0 | AJ66: =IFERROR($W66/X66-1,0) -> 0 | AK66: =IFERROR($W66/Y66-1,0) -> 0 | AL66: =IFERROR($W66/Z66-1,0) -> 0 | AM66: =IFERROR($W66/AA66-1,0) -> 0 | AN66: =IFERROR($W66/AB66-1,0) -> 0
A67: INOF | D67: {=_xlfn.XLOOKUP(1, (INDIRECT("'"&$C$6&"'!$6:$6")=D$6)* (INDIRECT("'"&$C$6&"'!$5:$5")=D$5), INDIRECT("'"&$C$6&"'!"&ROW()&":"&ROW()) )} -> 0 | E67: {=_xlfn.XLOOKUP(1, (INDIRECT("'"&$C$6&"'!$6:$6")=E$6)* (INDIRECT("'"&$C$6&"'!$5:$5")=E$5), INDIRECT("'"&$C$6&"'!"&ROW()&":"&ROW()) )} -> 0 | F67: {=_xlfn.XLOOKUP(1, (INDIRECT("'"&$C$6&"'!$6:$6")=F$6)* (INDIRECT("'"&$C$6&"'!$5:$5")=F$5), INDIRECT("'"&$C$6&"'!"&ROW()&":"&ROW()) )} -> 0 | G67: {=_xlfn.XLOOKUP(1, (INDIRECT("'"&$C$6&"'!$6:$6")=G$6)* (INDIRECT("'"&$C$6&"'!$5:$5")=G$5), INDIRECT("'"&$C$6&"'!"&ROW()&":"&ROW()) )} -> 0 | H67: {=_xlfn.XLOOKUP(1, (INDIRECT("'"&$C$6&"'!$6:$6")=H$6)* (INDIRECT("'"&$C$6&"'!$5:$5")=H$5), INDIRECT("'"&$C$6&"'!"&ROW()&":"&ROW()) )} -> 0 | I67: {=_xlfn.XLOOKUP(1, (INDIRECT("'"&$C$6&"'!$6:$6")=I$6)* (INDIRECT("'"&$C$6&"'!$5:$5")=I$5), INDIRECT("'"&$C$6&"'!"&ROW()&":"&ROW()) )} -> 0 | K67: =$D67-E67 -> 0 | L67: =$D67-F67 -> 0 | M67: =$D67-G67 -> 0 | N67: =$D67-H67 -> 0 | O67: =$D67-I67 -> 0 | Q67: =IFERROR($D67/E67-1,0) -> 0 | R67: =IFERROR($D67/F67-1,0) -> 0 | S67: =IFERROR($D67/G67-1,0) -> 0 | T67: =IFERROR($D67/H67-1,0) -> 0 | U67: =IFERROR($D67/I67-1,0) -> 0 | W67: {=INDIRECT("'"&$C$6&"'!"&ADDRESS(ROW(),COLUMN()+44))} -> 0 | X67: {=INDIRECT("'"&$C$6&"'!"&ADDRESS(ROW(),COLUMN()+44))} -> 0 | Y67: {=INDIRECT("'"&$C$6&"'!"&ADDRESS(ROW(),COLUMN()+44))} -> 0 | Z67: {=INDIRECT("'"&$C$6&"'!"&ADDRESS(ROW(),COLUMN()+44))} -> 0 | AA67: {=INDIRECT("'"&$C$6&"'!"&ADDRESS(ROW(),COLUMN()+44))} -> 0 | AB67: {=INDIRECT("'"&$C$6&"'!"&ADDRESS(ROW(),COLUMN()+44))} -> 0 | AD67: =$W67-X67 -> 0 | AE67: =$W67-Y67 -> 0 | AF67: =$W67-Z67 -> 0 | AG67: =$W67-AA67 -> 0 | AH67: =$W67-AB67 -> 0 | AJ67: =IFERROR($W67/X67-1,0) -> 0 | AK67: =IFERROR($W67/Y67-1,0) -> 0 | AL67: =IFERROR($W67/Z67-1,0) -> 0 | AM67: =IFERROR($W67/AA67-1,0) -> 0 | AN67: =IFERROR($W67/AB67-1,0) -> 0
A68: INOF | D68: {=_xlfn.XLOOKUP(1, (INDIRECT("'"&$C$6&"'!$6:$6")=D$6)* (INDIRECT("'"&$C$6&"'!$5:$5")=D$5), INDIRECT("'"&$C$6&"'!"&ROW()&":"&ROW()) )} -> 0 | E68: {=_xlfn.XLOOKUP(1, (INDIRECT("'"&$C$6&"'!$6:$6")=E$6)* (INDIRECT("'"&$C$6&"'!$5:$5")=E$5), INDIRECT("'"&$C$6&"'!"&ROW()&":"&ROW()) )} -> 0 | F68: {=_xlfn.XLOOKUP(1, (INDIRECT("'"&$C$6&"'!$6:$6")=F$6)* (INDIRECT("'"&$C$6&"'!$5:$5")=F$5), INDIRECT("'"&$C$6&"'!"&ROW()&":"&ROW()) )} -> 0 | G68: {=_xlfn.XLOOKUP(1, (INDIRECT("'"&$C$6&"'!$6:$6")=G$6)* (INDIRECT("'"&$C$6&"'!$5:$5")=G$5), INDIRECT("'"&$C$6&"'!"&ROW()&":"&ROW()) )} -> 0 | H68: {=_xlfn.XLOOKUP(1, (INDIRECT("'"&$C$6&"'!$6:$6")=H$6)* (INDIRECT("'"&$C$6&"'!$5:$5")=H$5), INDIRECT("'"&$C$6&"'!"&ROW()&":"&ROW()) )} -> 0 | I68: {=_xlfn.XLOOKUP(1, (INDIRECT("'"&$C$6&"'!$6:$6")=I$6)* (INDIRECT("'"&$C$6&"'!$5:$5")=I$5), INDIRECT("'"&$C$6&"'!"&ROW()&":"&ROW()) )} -> 0 | K68: =$D68-E68 -> 0 | L68: =$D68-F68 -> 0 | M68: =$D68-G68 -> 0 | N68: =$D68-H68 -> 0 | O68: =$D68-I68 -> 0 | Q68: =IFERROR($D68/E68-1,0) -> 0 | R68: =IFERROR($D68/F68-1,0) -> 0 | S68: =IFERROR($D68/G68-1,0) -> 0 | T68: =IFERROR($D68/H68-1,0) -> 0 | U68: =IFERROR($D68/I68-1,0) -> 0 | W68: {=INDIRECT("'"&$C$6&"'!"&ADDRESS(ROW(),COLUMN()+44))} -> 0 | X68: {=INDIRECT("'"&$C$6&"'!"&ADDRESS(ROW(),COLUMN()+44))} -> 0 | Y68: {=INDIRECT("'"&$C$6&"'!"&ADDRESS(ROW(),COLUMN()+44))} -> 0 | Z68: {=INDIRECT("'"&$C$6&"'!"&ADDRESS(ROW(),COLUMN()+44))} -> 0 | AA68: {=INDIRECT("'"&$C$6&"'!"&ADDRESS(ROW(),COLUMN()+44))} -> 0 | AB68: {=INDIRECT("'"&$C$6&"'!"&ADDRESS(ROW(),COLUMN()+44))} -> 0 | AD68: =$W68-X68 -> 0 | AE68: =$W68-Y68 -> 0 | AF68: =$W68-Z68 -> 0 | AG68: =$W68-AA68 -> 0 | AH68: =$W68-AB68 -> 0 | AJ68: =IFERROR($W68/X68-1,0) -> 0 | AK68: =IFERROR($W68/Y68-1,0) -> 0 | AL68: =IFERROR($W68/Z68-1,0) -> 0 | AM68: =IFERROR($W68/AA68-1,0) -> 0 | AN68: =IFERROR($W68/AB68-1,0) -> 0
A69: INOF | D69: {=_xlfn.XLOOKUP(1, (INDIRECT("'"&$C$6&"'!$6:$6")=D$6)* (INDIRECT("'"&$C$6&"'!$5:$5")=D$5), INDIRECT("'"&$C$6&"'!"&ROW()&":"&ROW()) )} -> 0 | E69: {=_xlfn.XLOOKUP(1, (INDIRECT("'"&$C$6&"'!$6:$6")=E$6)* (INDIRECT("'"&$C$6&"'!$5:$5")=E$5), INDIRECT("'"&$C$6&"'!"&ROW()&":"&ROW()) )} -> 0 | F69: {=_xlfn.XLOOKUP(1, (INDIRECT("'"&$C$6&"'!$6:$6")=F$6)* (INDIRECT("'"&$C$6&"'!$5:$5")=F$5), INDIRECT("'"&$C$6&"'!"&ROW()&":"&ROW()) )} -> 0 | G69: {=_xlfn.XLOOKUP(1, (INDIRECT("'"&$C$6&"'!$6:$6")=G$6)* (INDIRECT("'"&$C$6&"'!$5:$5")=G$5), INDIRECT("'"&$C$6&"'!"&ROW()&":"&ROW()) )} -> 0 | H69: {=_xlfn.XLOOKUP(1, (INDIRECT("'"&$C$6&"'!$6:$6")=H$6)* (INDIRECT("'"&$C$6&"'!$5:$5")=H$5), INDIRECT("'"&$C$6&"'!"&ROW()&":"&ROW()) )} -> 0 | I69: {=_xlfn.XLOOKUP(1, (INDIRECT("'"&$C$6&"'!$6:$6")=I$6)* (INDIRECT("'"&$C$6&"'!$5:$5")=I$5), INDIRECT("'"&$C$6&"'!"&ROW()&":"&ROW()) )} -> 0 | K69: =$D69-E69 -> 0 | L69: =$D69-F69 -> 0 | M69: =$D69-G69 -> 0 | N69: =$D69-H69 -> 0 | O69: =$D69-I69 -> 0 | Q69: =IFERROR($D69/E69-1,0) -> 0 | R69: =IFERROR($D69/F69-1,0) -> 0 | S69: =IFERROR($D69/G69-1,0) -> 0 | T69: =IFERROR($D69/H69-1,0) -> 0 | U69: =IFERROR($D69/I69-1,0) -> 0 | W69: {=INDIRECT("'"&$C$6&"'!"&ADDRESS(ROW(),COLUMN()+44))} -> 0 | X69: {=INDIRECT("'"&$C$6&"'!"&ADDRESS(ROW(),COLUMN()+44))} -> 0 | Y69: {=INDIRECT("'"&$C$6&"'!"&ADDRESS(ROW(),COLUMN()+44))} -> 0 | Z69: {=INDIRECT("'"&$C$6&"'!"&ADDRESS(ROW(),COLUMN()+44))} -> 0 | AA69: {=INDIRECT("'"&$C$6&"'!"&ADDRESS(ROW(),COLUMN()+44))} -> 0 | AB69: {=INDIRECT("'"&$C$6&"'!"&ADDRESS(ROW(),COLUMN()+44))} -> 0 | AD69: =$W69-X69 -> 0 | AE69: =$W69-Y69 -> 0 | AF69: =$W69-Z69 -> 0 | AG69: =$W69-AA69 -> 0 | AH69: =$W69-AB69 -> 0 | AJ69: =IFERROR($W69/X69-1,0) -> 0 | AK69: =IFERROR($W69/Y69-1,0) -> 0 | AL69: =IFERROR($W69/Z69-1,0) -> 0 | AM69: =IFERROR($W69/AA69-1,0) -> 0 | AN69: =IFERROR($W69/AB69-1,0) -> 0
A70: INOF | D70: {=_xlfn.XLOOKUP(1, (INDIRECT("'"&$C$6&"'!$6:$6")=D$6)* (INDIRECT("'"&$C$6&"'!$5:$5")=D$5), INDIRECT("'"&$C$6&"'!"&ROW()&":"&ROW()) )} -> 0 | E70: {=_xlfn.XLOOKUP(1, (INDIRECT("'"&$C$6&"'!$6:$6")=E$6)* (INDIRECT("'"&$C$6&"'!$5:$5")=E$5), INDIRECT("'"&$C$6&"'!"&ROW()&":"&ROW()) )} -> 0 | F70: {=_xlfn.XLOOKUP(1, (INDIRECT("'"&$C$6&"'!$6:$6")=F$6)* (INDIRECT("'"&$C$6&"'!$5:$5")=F$5), INDIRECT("'"&$C$6&"'!"&ROW()&":"&ROW()) )} -> 0 | G70: {=_xlfn.XLOOKUP(1, (INDIRECT("'"&$C$6&"'!$6:$6")=G$6)* (INDIRECT("'"&$C$6&"'!$5:$5")=G$5), INDIRECT("'"&$C$6&"'!"&ROW()&":"&ROW()) )} -> 0 | H70: {=_xlfn.XLOOKUP(1, (INDIRECT("'"&$C$6&"'!$6:$6")=H$6)* (INDIRECT("'"&$C$6&"'!$5:$5")=H$5), INDIRECT("'"&$C$6&"'!"&ROW()&":"&ROW()) )} -> 0 | I70: {=_xlfn.XLOOKUP(1, (INDIRECT("'"&$C$6&"'!$6:$6")=I$6)* (INDIRECT("'"&$C$6&"'!$5:$5")=I$5), INDIRECT("'"&$C$6&"'!"&ROW()&":"&ROW()) )} -> 0 | K70: =$D70-E70 -> 0 | L70: =$D70-F70 -> 0 | M70: =$D70-G70 -> 0 | N70: =$D70-H70 -> 0 | O70: =$D70-I70 -> 0 | Q70: =IFERROR($D70/E70-1,0) -> 0 | R70: =IFERROR($D70/F70-1,0) -> 0 | S70: =IFERROR($D70/G70-1,0) -> 0 | T70: =IFERROR($D70/H70-1,0) -> 0 | U70: =IFERROR($D70/I70-1,0) -> 0 | W70: {=INDIRECT("'"&$C$6&"'!"&ADDRESS(ROW(),COLUMN()+44))} -> 0 | X70: {=INDIRECT("'"&$C$6&"'!"&ADDRESS(ROW(),COLUMN()+44))} -> 0 | Y70: {=INDIRECT("'"&$C$6&"'!"&ADDRESS(ROW(),COLUMN()+44))} -> 0 | Z70: {=INDIRECT("'"&$C$6&"'!"&ADDRESS(ROW(),COLUMN()+44))} -> 0 | AA70: {=INDIRECT("'"&$C$6&"'!"&ADDRESS(ROW(),COLUMN()+44))} -> 0 | AB70: {=INDIRECT("'"&$C$6&"'!"&ADDRESS(ROW(),COLUMN()+44))} -> 0 | AD70: =$W70-X70 -> 0 | AE70: =$W70-Y70 -> 0 | AF70: =$W70-Z70 -> 0 | AG70: =$W70-AA70 -> 0 | AH70: =$W70-AB70 -> 0 | AJ70: =IFERROR($W70/X70-1,0) -> 0 | AK70: =IFERROR($W70/Y70-1,0) -> 0 | AL70: =IFERROR($W70/Z70-1,0) -> 0 | AM70: =IFERROR($W70/AA70-1,0) -> 0 | AN70: =IFERROR($W70/AB70-1,0) -> 0
A71: INOF | D71: {=_xlfn.XLOOKUP(1, (INDIRECT("'"&$C$6&"'!$6:$6")=D$6)* (INDIRECT("'"&$C$6&"'!$5:$5")=D$5), INDIRECT("'"&$C$6&"'!"&ROW()&":"&ROW()) )} -> 0 | E71: {=_xlfn.XLOOKUP(1, (INDIRECT("'"&$C$6&"'!$6:$6")=E$6)* (INDIRECT("'"&$C$6&"'!$5:$5")=E$5), INDIRECT("'"&$C$6&"'!"&ROW()&":"&ROW()) )} -> 0 | F71: {=_xlfn.XLOOKUP(1, (INDIRECT("'"&$C$6&"'!$6:$6")=F$6)* (INDIRECT("'"&$C$6&"'!$5:$5")=F$5), INDIRECT("'"&$C$6&"'!"&ROW()&":"&ROW()) )} -> 0 | G71: {=_xlfn.XLOOKUP(1, (INDIRECT("'"&$C$6&"'!$6:$6")=G$6)* (INDIRECT("'"&$C$6&"'!$5:$5")=G$5), INDIRECT("'"&$C$6&"'!"&ROW()&":"&ROW()) )} -> 0 | H71: {=_xlfn.XLOOKUP(1, (INDIRECT("'"&$C$6&"'!$6:$6")=H$6)* (INDIRECT("'"&$C$6&"'!$5:$5")=H$5), INDIRECT("'"&$C$6&"'!"&ROW()&":"&ROW()) )} -> 0 | I71: {=_xlfn.XLOOKUP(1, (INDIRECT("'"&$C$6&"'!$6:$6")=I$6)* (INDIRECT("'"&$C$6&"'!$5:$5")=I$5), INDIRECT("'"&$C$6&"'!"&ROW()&":"&ROW()) )} -> 0 | K71: =$D71-E71 -> 0 | L71: =$D71-F71 -> 0 | M71: =$D71-G71 -> 0 | N71: =$D71-H71 -> 0 | O71: =$D71-I71 -> 0 | Q71: =IFERROR($D71/E71-1,0) -> 0 | R71: =IFERROR($D71/F71-1,0) -> 0 | S71: =IFERROR($D71/G71-1,0) -> 0 | T71: =IFERROR($D71/H71-1,0) -> 0 | U71: =IFERROR($D71/I71-1,0) -> 0 | W71: {=INDIRECT("'"&$C$6&"'!"&ADDRESS(ROW(),COLUMN()+44))} -> 0 | X71: {=INDIRECT("'"&$C$6&"'!"&ADDRESS(ROW(),COLUMN()+44))} -> 0 | Y71: {=INDIRECT("'"&$C$6&"'!"&ADDRESS(ROW(),COLUMN()+44))} -> 0 | Z71: {=INDIRECT("'"&$C$6&"'!"&ADDRESS(ROW(),COLUMN()+44))} -> 0 | AA71: {=INDIRECT("'"&$C$6&"'!"&ADDRESS(ROW(),COLUMN()+44))} -> 0 | AB71: {=INDIRECT("'"&$C$6&"'!"&ADDRESS(ROW(),COLUMN()+44))} -> 0 | AD71: =$W71-X71 -> 0 | AE71: =$W71-Y71 -> 0 | AF71: =$W71-Z71 -> 0 | AG71: =$W71-AA71 -> 0 | AH71: =$W71-AB71 -> 0 | AJ71: =IFERROR($W71/X71-1,0) -> 0 | AK71: =IFERROR($W71/Y71-1,0) -> 0 | AL71: =IFERROR($W71/Z71-1,0) -> 0 | AM71: =IFERROR($W71/AA71-1,0) -> 0 | AN71: =IFERROR($W71/AB71-1,0) -> 0
A72: INOF | D72: {=_xlfn.XLOOKUP(1, (INDIRECT("'"&$C$6&"'!$6:$6")=D$6)* (INDIRECT("'"&$C$6&"'!$5:$5")=D$5), INDIRECT("'"&$C$6&"'!"&ROW()&":"&ROW()) )} -> 0 | E72: {=_xlfn.XLOOKUP(1, (INDIRECT("'"&$C$6&"'!$6:$6")=E$6)* (INDIRECT("'"&$C$6&"'!$5:$5")=E$5), INDIRECT("'"&$C$6&"'!"&ROW()&":"&ROW()) )} -> 0 | F72: {=_xlfn.XLOOKUP(1, (INDIRECT("'"&$C$6&"'!$6:$6")=F$6)* (INDIRECT("'"&$C$6&"'!$5:$5")=F$5), INDIRECT("'"&$C$6&"'!"&ROW()&":"&ROW()) )} -> 0 | G72: {=_xlfn.XLOOKUP(1, (INDIRECT("'"&$C$6&"'!$6:$6")=G$6)* (INDIRECT("'"&$C$6&"'!$5:$5")=G$5), INDIRECT("'"&$C$6&"'!"&ROW()&":"&ROW()) )} -> 0 | H72: {=_xlfn.XLOOKUP(1, (INDIRECT("'"&$C$6&"'!$6:$6")=H$6)* (INDIRECT("'"&$C$6&"'!$5:$5")=H$5), INDIRECT("'"&$C$6&"'!"&ROW()&":"&ROW()) )} -> 0 | I72: {=_xlfn.XLOOKUP(1, (INDIRECT("'"&$C$6&"'!$6:$6")=I$6)* (INDIRECT("'"&$C$6&"'!$5:$5")=I$5), INDIRECT("'"&$C$6&"'!"&ROW()&":"&ROW()) )} -> 0 | K72: =$D72-E72 -> 0 | L72: =$D72-F72 -> 0 | M72: =$D72-G72 -> 0 | N72: =$D72-H72 -> 0 | O72: =$D72-I72 -> 0 | Q72: =IFERROR($D72/E72-1,0) -> 0 | R72: =IFERROR($D72/F72-1,0) -> 0 | S72: =IFERROR($D72/G72-1,0) -> 0 | T72: =IFERROR($D72/H72-1,0) -> 0 | U72: =IFERROR($D72/I72-1,0) -> 0 | W72: {=INDIRECT("'"&$C$6&"'!"&ADDRESS(ROW(),COLUMN()+44))} -> 0 | X72: {=INDIRECT("'"&$C$6&"'!"&ADDRESS(ROW(),COLUMN()+44))} -> 0 | Y72: {=INDIRECT("'"&$C$6&"'!"&ADDRESS(ROW(),COLUMN()+44))} -> 0 | Z72: {=INDIRECT("'"&$C$6&"'!"&ADDRESS(ROW(),COLUMN()+44))} -> 0 | AA72: {=INDIRECT("'"&$C$6&"'!"&ADDRESS(ROW(),COLUMN()+44))} -> 0 | AB72: {=INDIRECT("'"&$C$6&"'!"&ADDRESS(ROW(),COLUMN()+44))} -> 0 | AD72: =$W72-X72 -> 0 | AE72: =$W72-Y72 -> 0 | AF72: =$W72-Z72 -> 0 | AG72: =$W72-AA72 -> 0 | AH72: =$W72-AB72 -> 0 | AJ72: =IFERROR($W72/X72-1,0) -> 0 | AK72: =IFERROR($W72/Y72-1,0) -> 0 | AL72: =IFERROR($W72/Z72-1,0) -> 0 | AM72: =IFERROR($W72/AA72-1,0) -> 0 | AN72: =IFERROR($W72/AB72-1,0) -> 0
A73: INOF | D73: {=_xlfn.XLOOKUP(1, (INDIRECT("'"&$C$6&"'!$6:$6")=D$6)* (INDIRECT("'"&$C$6&"'!$5:$5")=D$5), INDIRECT("'"&$C$6&"'!"&ROW()&":"&ROW()) )} -> 0 | E73: {=_xlfn.XLOOKUP(1, (INDIRECT("'"&$C$6&"'!$6:$6")=E$6)* (INDIRECT("'"&$C$6&"'!$5:$5")=E$5), INDIRECT("'"&$C$6&"'!"&ROW()&":"&ROW()) )} -> 0 | F73: {=_xlfn.XLOOKUP(1, (INDIRECT("'"&$C$6&"'!$6:$6")=F$6)* (INDIRECT("'"&$C$6&"'!$5:$5")=F$5), INDIRECT("'"&$C$6&"'!"&ROW()&":"&ROW()) )} -> 0 | G73: {=_xlfn.XLOOKUP(1, (INDIRECT("'"&$C$6&"'!$6:$6")=G$6)* (INDIRECT("'"&$C$6&"'!$5:$5")=G$5), INDIRECT("'"&$C$6&"'!"&ROW()&":"&ROW()) )} -> 0 | H73: {=_xlfn.XLOOKUP(1, (INDIRECT("'"&$C$6&"'!$6:$6")=H$6)* (INDIRECT("'"&$C$6&"'!$5:$5")=H$5), INDIRECT("'"&$C$6&"'!"&ROW()&":"&ROW()) )} -> 0 | I73: {=_xlfn.XLOOKUP(1, (INDIRECT("'"&$C$6&"'!$6:$6")=I$6)* (INDIRECT("'"&$C$6&"'!$5:$5")=I$5), INDIRECT("'"&$C$6&"'!"&ROW()&":"&ROW()) )} -> 0 | K73: =$D73-E73 -> 0 | L73: =$D73-F73 -> 0 | M73: =$D73-G73 -> 0 | N73: =$D73-H73 -> 0 | O73: =$D73-I73 -> 0 | Q73: =IFERROR($D73/E73-1,0) -> 0 | R73: =IFERROR($D73/F73-1,0) -> 0 | S73: =IFERROR($D73/G73-1,0) -> 0 | T73: =IFERROR($D73/H73-1,0) -> 0 | U73: =IFERROR($D73/I73-1,0) -> 0 | W73: {=INDIRECT("'"&$C$6&"'!"&ADDRESS(ROW(),COLUMN()+44))} -> 0 | X73: {=INDIRECT("'"&$C$6&"'!"&ADDRESS(ROW(),COLUMN()+44))} -> 0 | Y73: {=INDIRECT("'"&$C$6&"'!"&ADDRESS(ROW(),COLUMN()+44))} -> 0 | Z73: {=INDIRECT("'"&$C$6&"'!"&ADDRESS(ROW(),COLUMN()+44))} -> 0 | AA73: {=INDIRECT("'"&$C$6&"'!"&ADDRESS(ROW(),COLUMN()+44))} -> 0 | AB73: {=INDIRECT("'"&$C$6&"'!"&ADDRESS(ROW(),COLUMN()+44))} -> 0 | AD73: =$W73-X73 -> 0 | AE73: =$W73-Y73 -> 0 | AF73: =$W73-Z73 -> 0 | AG73: =$W73-AA73 -> 0 | AH73: =$W73-AB73 -> 0 | AJ73: =IFERROR($W73/X73-1,0) -> 0 | AK73: =IFERROR($W73/Y73-1,0) -> 0 | AL73: =IFERROR($W73/Z73-1,0) -> 0 | AM73: =IFERROR($W73/AA73-1,0) -> 0 | AN73: =IFERROR($W73/AB73-1,0) -> 0
A74: INOF | D74: {=_xlfn.XLOOKUP(1, (INDIRECT("'"&$C$6&"'!$6:$6")=D$6)* (INDIRECT("'"&$C$6&"'!$5:$5")=D$5), INDIRECT("'"&$C$6&"'!"&ROW()&":"&ROW()) )} -> 0 | E74: {=_xlfn.XLOOKUP(1, (INDIRECT("'"&$C$6&"'!$6:$6")=E$6)* (INDIRECT("'"&$C$6&"'!$5:$5")=E$5), INDIRECT("'"&$C$6&"'!"&ROW()&":"&ROW()) )} -> 0 | F74: {=_xlfn.XLOOKUP(1, (INDIRECT("'"&$C$6&"'!$6:$6")=F$6)* (INDIRECT("'"&$C$6&"'!$5:$5")=F$5), INDIRECT("'"&$C$6&"'!"&ROW()&":"&ROW()) )} -> 0 | G74: {=_xlfn.XLOOKUP(1, (INDIRECT("'"&$C$6&"'!$6:$6")=G$6)* (INDIRECT("'"&$C$6&"'!$5:$5")=G$5), INDIRECT("'"&$C$6&"'!"&ROW()&":"&ROW()) )} -> 0 | H74: {=_xlfn.XLOOKUP(1, (INDIRECT("'"&$C$6&"'!$6:$6")=H$6)* (INDIRECT("'"&$C$6&"'!$5:$5")=H$5), INDIRECT("'"&$C$6&"'!"&ROW()&":"&ROW()) )} -> 0 | I74: {=_xlfn.XLOOKUP(1, (INDIRECT("'"&$C$6&"'!$6:$6")=I$6)* (INDIRECT("'"&$C$6&"'!$5:$5")=I$5), INDIRECT("'"&$C$6&"'!"&ROW()&":"&ROW()) )} -> 0 | K74: =$D74-E74 -> 0 | L74: =$D74-F74 -> 0 | M74: =$D74-G74 -> 0 | N74: =$D74-H74 -> 0 | O74: =$D74-I74 -> 0 | Q74: =IFERROR($D74/E74-1,0) -> 0 | R74: =IFERROR($D74/F74-1,0) -> 0 | S74: =IFERROR($D74/G74-1,0) -> 0 | T74: =IFERROR($D74/H74-1,0) -> 0 | U74: =IFERROR($D74/I74-1,0) -> 0 | W74: {=INDIRECT("'"&$C$6&"'!"&ADDRESS(ROW(),COLUMN()+44))} -> 0 | X74: {=INDIRECT("'"&$C$6&"'!"&ADDRESS(ROW(),COLUMN()+44))} -> 0 | Y74: {=INDIRECT("'"&$C$6&"'!"&ADDRESS(ROW(),COLUMN()+44))} -> 0 | Z74: {=INDIRECT("'"&$C$6&"'!"&ADDRESS(ROW(),COLUMN()+44))} -> 0 | AA74: {=INDIRECT("'"&$C$6&"'!"&ADDRESS(ROW(),COLUMN()+44))} -> 0 | AB74: {=INDIRECT("'"&$C$6&"'!"&ADDRESS(ROW(),COLUMN()+44))} -> 0 | AD74: =$W74-X74 -> 0 | AE74: =$W74-Y74 -> 0 | AF74: =$W74-Z74 -> 0 | AG74: =$W74-AA74 -> 0 | AH74: =$W74-AB74 -> 0 | AJ74: =IFERROR($W74/X74-1,0) -> 0 | AK74: =IFERROR($W74/Y74-1,0) -> 0 | AL74: =IFERROR($W74/Z74-1,0) -> 0 | AM74: =IFERROR($W74/AA74-1,0) -> 0 | AN74: =IFERROR($W74/AB74-1,0) -> 0
A75: INOF | D75: {=_xlfn.XLOOKUP(1, (INDIRECT("'"&$C$6&"'!$6:$6")=D$6)* (INDIRECT("'"&$C$6&"'!$5:$5")=D$5), INDIRECT("'"&$C$6&"'!"&ROW()&":"&ROW()) )} -> 0 | E75: {=_xlfn.XLOOKUP(1, (INDIRECT("'"&$C$6&"'!$6:$6")=E$6)* (INDIRECT("'"&$C$6&"'!$5:$5")=E$5), INDIRECT("'"&$C$6&"'!"&ROW()&":"&ROW()) )} -> 0 | F75: {=_xlfn.XLOOKUP(1, (INDIRECT("'"&$C$6&"'!$6:$6")=F$6)* (INDIRECT("'"&$C$6&"'!$5:$5")=F$5), INDIRECT("'"&$C$6&"'!"&ROW()&":"&ROW()) )} -> 0 | G75: {=_xlfn.XLOOKUP(1, (INDIRECT("'"&$C$6&"'!$6:$6")=G$6)* (INDIRECT("'"&$C$6&"'!$5:$5")=G$5), INDIRECT("'"&$C$6&"'!"&ROW()&":"&ROW()) )} -> 0 | H75: {=_xlfn.XLOOKUP(1, (INDIRECT("'"&$C$6&"'!$6:$6")=H$6)* (INDIRECT("'"&$C$6&"'!$5:$5")=H$5), INDIRECT("'"&$C$6&"'!"&ROW()&":"&ROW()) )} -> 0 | I75: {=_xlfn.XLOOKUP(1, (INDIRECT("'"&$C$6&"'!$6:$6")=I$6)* (INDIRECT("'"&$C$6&"'!$5:$5")=I$5), INDIRECT("'"&$C$6&"'!"&ROW()&":"&ROW()) )} -> 0 | K75: =$D75-E75 -> 0 | L75: =$D75-F75 -> 0 | M75: =$D75-G75 -> 0 | N75: =$D75-H75 -> 0 | O75: =$D75-I75 -> 0 | Q75: =IFERROR($D75/E75-1,0) -> 0 | R75: =IFERROR($D75/F75-1,0) -> 0 | S75: =IFERROR($D75/G75-1,0) -> 0 | T75: =IFERROR($D75/H75-1,0) -> 0 | U75: =IFERROR($D75/I75-1,0) -> 0 | W75: {=INDIRECT("'"&$C$6&"'!"&ADDRESS(ROW(),COLUMN()+44))} -> 0 | X75: {=INDIRECT("'"&$C$6&"'!"&ADDRESS(ROW(),COLUMN()+44))} -> 0 | Y75: {=INDIRECT("'"&$C$6&"'!"&ADDRESS(ROW(),COLUMN()+44))} -> 0 | Z75: {=INDIRECT("'"&$C$6&"'!"&ADDRESS(ROW(),COLUMN()+44))} -> 0 | AA75: {=INDIRECT("'"&$C$6&"'!"&ADDRESS(ROW(),COLUMN()+44))} -> 0 | AB75: {=INDIRECT("'"&$C$6&"'!"&ADDRESS(ROW(),COLUMN()+44))} -> 0 | AD75: =$W75-X75 -> 0 | AE75: =$W75-Y75 -> 0 | AF75: =$W75-Z75 -> 0 | AG75: =$W75-AA75 -> 0 | AH75: =$W75-AB75 -> 0 | AJ75: =IFERROR($W75/X75-1,0) -> 0 | AK75: =IFERROR($W75/Y75-1,0) -> 0 | AL75: =IFERROR($W75/Z75-1,0) -> 0 | AM75: =IFERROR($W75/AA75-1,0) -> 0 | AN75: =IFERROR($W75/AB75-1,0) -> 0
A76: INOF | D76: {=_xlfn.XLOOKUP(1, (INDIRECT("'"&$C$6&"'!$6:$6")=D$6)* (INDIRECT("'"&$C$6&"'!$5:$5")=D$5), INDIRECT("'"&$C$6&"'!"&ROW()&":"&ROW()) )} -> 0 | E76: {=_xlfn.XLOOKUP(1, (INDIRECT("'"&$C$6&"'!$6:$6")=E$6)* (INDIRECT("'"&$C$6&"'!$5:$5")=E$5), INDIRECT("'"&$C$6&"'!"&ROW()&":"&ROW()) )} -> 0 | F76: {=_xlfn.XLOOKUP(1, (INDIRECT("'"&$C$6&"'!$6:$6")=F$6)* (INDIRECT("'"&$C$6&"'!$5:$5")=F$5), INDIRECT("'"&$C$6&"'!"&ROW()&":"&ROW()) )} -> 0 | G76: {=_xlfn.XLOOKUP(1, (INDIRECT("'"&$C$6&"'!$6:$6")=G$6)* (INDIRECT("'"&$C$6&"'!$5:$5")=G$5), INDIRECT("'"&$C$6&"'!"&ROW()&":"&ROW()) )} -> 0 | H76: {=_xlfn.XLOOKUP(1, (INDIRECT("'"&$C$6&"'!$6:$6")=H$6)* (INDIRECT("'"&$C$6&"'!$5:$5")=H$5), INDIRECT("'"&$C$6&"'!"&ROW()&":"&ROW()) )} -> 0 | I76: {=_xlfn.XLOOKUP(1, (INDIRECT("'"&$C$6&"'!$6:$6")=I$6)* (INDIRECT("'"&$C$6&"'!$5:$5")=I$5), INDIRECT("'"&$C$6&"'!"&ROW()&":"&ROW()) )} -> 0 | K76: =$D76-E76 -> 0 | L76: =$D76-F76 -> 0 | M76: =$D76-G76 -> 0 | N76: =$D76-H76 -> 0 | O76: =$D76-I76 -> 0 | Q76: =IFERROR($D76/E76-1,0) -> 0 | R76: =IFERROR($D76/F76-1,0) -> 0 | S76: =IFERROR($D76/G76-1,0) -> 0 | T76: =IFERROR($D76/H76-1,0) -> 0 | U76: =IFERROR($D76/I76-1,0) -> 0 | W76: {=INDIRECT("'"&$C$6&"'!"&ADDRESS(ROW(),COLUMN()+44))} -> 0 | X76: {=INDIRECT("'"&$C$6&"'!"&ADDRESS(ROW(),COLUMN()+44))} -> 0 | Y76: {=INDIRECT("'"&$C$6&"'!"&ADDRESS(ROW(),COLUMN()+44))} -> 0 | Z76: {=INDIRECT("'"&$C$6&"'!"&ADDRESS(ROW(),COLUMN()+44))} -> 0 | AA76: {=INDIRECT("'"&$C$6&"'!"&ADDRESS(ROW(),COLUMN()+44))} -> 0 | AB76: {=INDIRECT("'"&$C$6&"'!"&ADDRESS(ROW(),COLUMN()+44))} -> 0 | AD76: =$W76-X76 -> 0 | AE76: =$W76-Y76 -> 0 | AF76: =$W76-Z76 -> 0 | AG76: =$W76-AA76 -> 0 | AH76: =$W76-AB76 -> 0 | AJ76: =IFERROR($W76/X76-1,0) -> 0 | AK76: =IFERROR($W76/Y76-1,0) -> 0 | AL76: =IFERROR($W76/Z76-1,0) -> 0 | AM76: =IFERROR($W76/AA76-1,0) -> 0 | AN76: =IFERROR($W76/AB76-1,0) -> 0
A77: INOF | D77: {=_xlfn.XLOOKUP(1, (INDIRECT("'"&$C$6&"'!$6:$6")=D$6)* (INDIRECT("'"&$C$6&"'!$5:$5")=D$5), INDIRECT("'"&$C$6&"'!"&ROW()&":"&ROW()) )} -> 0 | E77: {=_xlfn.XLOOKUP(1, (INDIRECT("'"&$C$6&"'!$6:$6")=E$6)* (INDIRECT("'"&$C$6&"'!$5:$5")=E$5), INDIRECT("'"&$C$6&"'!"&ROW()&":"&ROW()) )} -> 0 | F77: {=_xlfn.XLOOKUP(1, (INDIRECT("'"&$C$6&"'!$6:$6")=F$6)* (INDIRECT("'"&$C$6&"'!$5:$5")=F$5), INDIRECT("'"&$C$6&"'!"&ROW()&":"&ROW()) )} -> 0 | G77: {=_xlfn.XLOOKUP(1, (INDIRECT("'"&$C$6&"'!$6:$6")=G$6)* (INDIRECT("'"&$C$6&"'!$5:$5")=G$5), INDIRECT("'"&$C$6&"'!"&ROW()&":"&ROW()) )} -> 0 | H77: {=_xlfn.XLOOKUP(1, (INDIRECT("'"&$C$6&"'!$6:$6")=H$6)* (INDIRECT("'"&$C$6&"'!$5:$5")=H$5), INDIRECT("'"&$C$6&"'!"&ROW()&":"&ROW()) )} -> 0 | I77: {=_xlfn.XLOOKUP(1, (INDIRECT("'"&$C$6&"'!$6:$6")=I$6)* (INDIRECT("'"&$C$6&"'!$5:$5")=I$5), INDIRECT("'"&$C$6&"'!"&ROW()&":"&ROW()) )} -> 0 | K77: =$D77-E77 -> 0 | L77: =$D77-F77 -> 0 | M77: =$D77-G77 -> 0 | N77: =$D77-H77 -> 0 | O77: =$D77-I77 -> 0 | Q77: =IFERROR($D77/E77-1,0) -> 0 | R77: =IFERROR($D77/F77-1,0) -> 0 | S77: =IFERROR($D77/G77-1,0) -> 0 | T77: =IFERROR($D77/H77-1,0) -> 0 | U77: =IFERROR($D77/I77-1,0) -> 0 | W77: {=INDIRECT("'"&$C$6&"'!"&ADDRESS(ROW(),COLUMN()+44))} -> 0 | X77: {=INDIRECT("'"&$C$6&"'!"&ADDRESS(ROW(),COLUMN()+44))} -> 0 | Y77: {=INDIRECT("'"&$C$6&"'!"&ADDRESS(ROW(),COLUMN()+44))} -> 0 | Z77: {=INDIRECT("'"&$C$6&"'!"&ADDRESS(ROW(),COLUMN()+44))} -> 0 | AA77: {=INDIRECT("'"&$C$6&"'!"&ADDRESS(ROW(),COLUMN()+44))} -> 0 | AB77: {=INDIRECT("'"&$C$6&"'!"&ADDRESS(ROW(),COLUMN()+44))} -> 0 | AD77: =$W77-X77 -> 0 | AE77: =$W77-Y77 -> 0 | AF77: =$W77-Z77 -> 0 | AG77: =$W77-AA77 -> 0 | AH77: =$W77-AB77 -> 0 | AJ77: =IFERROR($W77/X77-1,0) -> 0 | AK77: =IFERROR($W77/Y77-1,0) -> 0 | AL77: =IFERROR($W77/Z77-1,0) -> 0 | AM77: =IFERROR($W77/AA77-1,0) -> 0 | AN77: =IFERROR($W77/AB77-1,0) -> 0
... A82: INOF | D82: {=_xlfn.XLOOKUP(1, (INDIRECT("'"&$C$6&"'!$6:$6")=D$6)* (INDIRECT("'"&$C$6&"'!$5:$5")=D$5), INDIRECT("'"&$C$6&"'!"&ROW()&":"&ROW()) )} -> 0 | E82: {=_xlfn.XLOOKUP(1, (INDIRECT("'"&$C$6&"'!$6:$6")=E$6)* (INDIRECT("'"&$C$6&"'!$5:$5")=E$5), INDIRECT("'"&$C$6&"'!"&ROW()&":"&ROW()) )} -> 0 | F82: {=_xlfn.XLOOKUP(1, (INDIRECT("'"&$C$6&"'!$6:$6")=F$6)* (INDIRECT("'"&$C$6&"'!$5:$5")=F$5), INDIRECT("'"&$C$6&"'!"&ROW()&":"&ROW()) )} -> 0 | G82: {=_xlfn.XLOOKUP(1, (INDIRECT("'"&$C$6&"'!$6:$6")=G$6)* (INDIRECT("'"&$C$6&"'!$5:$5")=G$5), INDIRECT("'"&$C$6&"'!"&ROW()&":"&ROW()) )} -> 0 | H82: {=_xlfn.XLOOKUP(1, (INDIRECT("'"&$C$6&"'!$6:$6")=H$6)* (INDIRECT("'"&$C$6&"'!$5:$5")=H$5), INDIRECT("'"&$C$6&"'!"&ROW()&":"&ROW()) )} -> 0 | I82: {=_xlfn.XLOOKUP(1, (INDIRECT("'"&$C$6&"'!$6:$6")=I$6)* (INDIRECT("'"&$C$6&"'!$5:$5")=I$5), INDIRECT("'"&$C$6&"'!"&ROW()&":"&ROW()) )} -> 0 | K82: =$D82-E82 -> 0 | L82: =$D82-F82 -> 0 | M82: =$D82-G82 -> 0 | N82: =$D82-H82 -> 0 | O82: =$D82-I82 -> 0 | Q82: =IFERROR($D82/E82-1,0) -> 0 | R82: =IFERROR($D82/F82-1,0) -> 0 | S82: =IFERROR($D82/G82-1,0) -> 0 | T82: =IFERROR($D82/H82-1,0) -> 0 | U82: =IFERROR($D82/I82-1,0) -> 0 | W82: {=INDIRECT("'"&$C$6&"'!"&ADDRESS(ROW(),COLUMN()+44))} -> 0 | X82: {=INDIRECT("'"&$C$6&"'!"&ADDRESS(ROW(),COLUMN()+44))} -> 0 | Y82: {=INDIRECT("'"&$C$6&"'!"&ADDRESS(ROW(),COLUMN()+44))} -> 0 | Z82: {=INDIRECT("'"&$C$6&"'!"&ADDRESS(ROW(),COLUMN()+44))} -> 0 | AA82: {=INDIRECT("'"&$C$6&"'!"&ADDRESS(ROW(),COLUMN()+44))} -> 0 | AB82: {=INDIRECT("'"&$C$6&"'!"&ADDRESS(ROW(),COLUMN()+44))} -> 0 | AD82: =$W82-X82 -> 0 | AE82: =$W82-Y82 -> 0 | AF82: =$W82-Z82 -> 0 | AG82: =$W82-AA82 -> 0 | AH82: =$W82-AB82 -> 0 | AJ82: =IFERROR($W82/X82-1,0) -> 0 | AK82: =IFERROR($W82/Y82-1,0) -> 0 | AL82: =IFERROR($W82/Z82-1,0) -> 0 | AM82: =IFERROR($W82/AA82-1,0) -> 0 | AN82: =IFERROR($W82/AB82-1,0) -> 0
C83: INOF | D83: =SUM(D63:D82) -> 286.88539 | E83: =SUM(E63:E82) -> 314.62042 | F83: =SUM(F63:F82) -> 272.36226 | G83: =SUM(G63:G82) -> 151.34738 | H83: =SUM(H63:H82) -> 429.41719 | I83: =SUM(I63:I82) -> 295.90516 | K83: =$D83-E83 -> -27.73503 | L83: =$D83-F83 -> 14.523125 | M83: =$D83-G83 -> 135.538 | N83: =$D83-H83 -> -142.5318 | O83: =$D83-I83 -> -9.0197691 | Q83: =IFERROR($D83/E83-1,0) -> -0.08815394 | R83: =IFERROR($D83/F83-1,0) -> 0.053322825 | S83: =IFERROR($D83/G83-1,0) -> 0.89554243 | T83: =IFERROR($D83/H83-1,0) -> -0.33191919 | U83: =IFERROR($D83/I83-1,0) -> -0.03048196 | W83: =SUM(W63:W82) -> 916.00943 | X83: =SUM(X63:X82) -> 938.10379 | Y83: =SUM(Y63:Y82) -> 629.12405 | Z83: =SUM(Z63:Z82) -> 783.44837 | AA83: =SUM(AA63:AA82) -> 1245.8175 | AB83: =SUM(AB63:AB82) -> 1038.7578 | AD83: =$W83-X83 -> -22.094359 | AE83: =$W83-Y83 -> 286.88539 | AF83: =$W83-Z83 -> 132.56106 | AG83: =$W83-AA83 -> -329.8081 | AH83: =$W83-AB83 -> -122.74836 | AJ83: =IFERROR($W83/X83-1,0) -> -0.023552147 | AK83: =IFERROR($W83/Y83-1,0) -> 0.45600766 | AL83: =IFERROR($W83/Z83-1,0) -> 0.16920204 | AM83: =IFERROR($W83/AA83-1,0) -> -0.26473226 | AN83: =IFERROR($W83/AB83-1,0) -> -0.11816841
A86: Gastos Operativos | C86: Gasto Directo | D86: {=_xlfn.XLOOKUP(1, (INDIRECT("'"&$C$6&"'!$6:$6")=D$6)* (INDIRECT("'"&$C$6&"'!$5:$5")=D$5), INDIRECT("'"&$C$6&"'!"&ROW()&":"&ROW()) )} -> -1877.3931 | E86: {=_xlfn.XLOOKUP(1, (INDIRECT("'"&$C$6&"'!$6:$6")=E$6)* (INDIRECT("'"&$C$6&"'!$5:$5")=E$5), INDIRECT("'"&$C$6&"'!"&ROW()&":"&ROW()) )} -> -1679.1421 | F86: {=_xlfn.XLOOKUP(1, (INDIRECT("'"&$C$6&"'!$6:$6")=F$6)* (INDIRECT("'"&$C$6&"'!$5:$5")=F$5), INDIRECT("'"&$C$6&"'!"&ROW()&":"&ROW()) )} -> -1700.9689 | G86: {=_xlfn.XLOOKUP(1, (INDIRECT("'"&$C$6&"'!$6:$6")=G$6)* (INDIRECT("'"&$C$6&"'!$5:$5")=G$5), INDIRECT("'"&$C$6&"'!"&ROW()&":"&ROW()) )} -> -1551.1616 | H86: {=_xlfn.XLOOKUP(1, (INDIRECT("'"&$C$6&"'!$6:$6")=H$6)* (INDIRECT("'"&$C$6&"'!$5:$5")=H$5), INDIRECT("'"&$C$6&"'!"&ROW()&":"&ROW()) )} -> -1318.8707 | I86: {=_xlfn.XLOOKUP(1, (INDIRECT("'"&$C$6&"'!$6:$6")=I$6)* (INDIRECT("'"&$C$6&"'!$5:$5")=I$5), INDIRECT("'"&$C$6&"'!"&ROW()&":"&ROW()) )} -> -1604.1168 | K86: =$D86-E86 -> -198.25101 | L86: =$D86-F86 -> -176.42422 | M86: =$D86-G86 -> -326.2315 | N86: =$D86-H86 -> -558.52244 | O86: =$D86-I86 -> -273.27636 | Q86: =IFERROR($D86/E86-1,0) -> 0.11806684 | R86: =IFERROR($D86/F86-1,0) -> 0.10371984 | S86: =IFERROR($D86/G86-1,0) -> 0.21031432 | T86: =IFERROR($D86/H86-1,0) -> 0.42348537 | U86: =IFERROR($D86/I86-1,0) -> 0.1703594 | W86: {=INDIRECT("'"&$C$6&"'!"&ADDRESS(ROW(),COLUMN()+44))} -> -5158.2413 | X86: {=INDIRECT("'"&$C$6&"'!"&ADDRESS(ROW(),COLUMN()+44))} -> -4987.0606 | Y86: {=INDIRECT("'"&$C$6&"'!"&ADDRESS(ROW(),COLUMN()+44))} -> -3280.8482 | Z86: {=INDIRECT("'"&$C$6&"'!"&ADDRESS(ROW(),COLUMN()+44))} -> -4076.5968 | AA86: {=INDIRECT("'"&$C$6&"'!"&ADDRESS(ROW(),COLUMN()+44))} -> -4103.9796 | AB86: {=INDIRECT("'"&$C$6&"'!"&ADDRESS(ROW(),COLUMN()+44))} -> -4747.7988 | AD86: =$W86-X86 -> -171.18073 | AE86: =$W86-Y86 -> -1877.3931 | AF86: =$W86-Z86 -> -1081.6445 | AG86: =$W86-AA86 -> -1054.2617 | AH86: =$W86-AB86 -> -410.44247 | AJ86: =IFERROR($W86/X86-1,0) -> 0.034324976 | AK86: =IFERROR($W86/Y86-1,0) -> 0.57222797 | AL86: =IFERROR($W86/Z86-1,0) -> 0.26533026 | AM86: =IFERROR($W86/AA86-1,0) -> 0.25688766 | AN86: =IFERROR($W86/AB86-1,0) -> 0.086449
A87: Gastos Operativos | C87: Gasto Canal | D87: {=_xlfn.XLOOKUP(1, (INDIRECT("'"&$C$6&"'!$6:$6")=D$6)* (INDIRECT("'"&$C$6&"'!$5:$5")=D$5), INDIRECT("'"&$C$6&"'!"&ROW()&":"&ROW()) )} -> -1140.058 | E87: {=_xlfn.XLOOKUP(1, (INDIRECT("'"&$C$6&"'!$6:$6")=E$6)* (INDIRECT("'"&$C$6&"'!$5:$5")=E$5), INDIRECT("'"&$C$6&"'!"&ROW()&":"&ROW()) )} -> -1098.7537 | F87: {=_xlfn.XLOOKUP(1, (INDIRECT("'"&$C$6&"'!$6:$6")=F$6)* (INDIRECT("'"&$C$6&"'!$5:$5")=F$5), INDIRECT("'"&$C$6&"'!"&ROW()&":"&ROW()) )} -> -1131.4858 | G87: {=_xlfn.XLOOKUP(1, (INDIRECT("'"&$C$6&"'!$6:$6")=G$6)* (INDIRECT("'"&$C$6&"'!$5:$5")=G$5), INDIRECT("'"&$C$6&"'!"&ROW()&":"&ROW()) )} -> -1011.9329 | H87: {=_xlfn.XLOOKUP(1, (INDIRECT("'"&$C$6&"'!$6:$6")=H$6)* (INDIRECT("'"&$C$6&"'!$5:$5")=H$5), INDIRECT("'"&$C$6&"'!"&ROW()&":"&ROW()) )} -> -1017.274 | I87: {=_xlfn.XLOOKUP(1, (INDIRECT("'"&$C$6&"'!$6:$6")=I$6)* (INDIRECT("'"&$C$6&"'!$5:$5")=I$5), INDIRECT("'"&$C$6&"'!"&ROW()&":"&ROW()) )} -> -1206.6795 | K87: =$D87-E87 -> -41.304284 | L87: =$D87-F87 -> -8.572177 | M87: =$D87-G87 -> -128.12512 | N87: =$D87-H87 -> -122.78398 | O87: =$D87-I87 -> 66.621544 | Q87: =IFERROR($D87/E87-1,0) -> 0.037591941 | R87: =IFERROR($D87/F87-1,0) -> 0.0075760357 | S87: =IFERROR($D87/G87-1,0) -> 0.12661425 | T87: =IFERROR($D87/H87-1,0) -> 0.12069903 | U87: =IFERROR($D87/I87-1,0) -> -0.055210635 | W87: {=INDIRECT("'"&$C$6&"'!"&ADDRESS(ROW(),COLUMN()+44))} -> -3244.5213 | X87: {=INDIRECT("'"&$C$6&"'!"&ADDRESS(ROW(),COLUMN()+44))} -> -3193.5369 | Y87: {=INDIRECT("'"&$C$6&"'!"&ADDRESS(ROW(),COLUMN()+44))} -> -2104.4633 | Z87: {=INDIRECT("'"&$C$6&"'!"&ADDRESS(ROW(),COLUMN()+44))} -> -2977.0087 | AA87: {=INDIRECT("'"&$C$6&"'!"&ADDRESS(ROW(),COLUMN()+44))} -> -3097.5991 | AB87: {=INDIRECT("'"&$C$6&"'!"&ADDRESS(ROW(),COLUMN()+44))} -> -3268.6198 | AD87: =$W87-X87 -> -50.984442 | AE87: =$W87-Y87 -> -1140.058 | AF87: =$W87-Z87 -> -267.51266 | AG87: =$W87-AA87 -> -146.92221 | AH87: =$W87-AB87 -> 24.098486 | AJ87: =IFERROR($W87/X87-1,0) -> 0.015964883 | AK87: =IFERROR($W87/Y87-1,0) -> 0.54173336 | AL87: =IFERROR($W87/Z87-1,0) -> 0.089859549 | AM87: =IFERROR($W87/AA87-1,0) -> 0.047430995 | AN87: =IFERROR($W87/AB87-1,0) -> -0.0073726795
A88: Gastos Operativos | C88: Gasto Indirecto | D88: {=_xlfn.XLOOKUP(1, (INDIRECT("'"&$C$6&"'!$6:$6")=D$6)* (INDIRECT("'"&$C$6&"'!$5:$5")=D$5), INDIRECT("'"&$C$6&"'!"&ROW()&":"&ROW()) )} -> -2551.3516 | E88: {=_xlfn.XLOOKUP(1, (INDIRECT("'"&$C$6&"'!$6:$6")=E$6)* (INDIRECT("'"&$C$6&"'!$5:$5")=E$5), INDIRECT("'"&$C$6&"'!"&ROW()&":"&ROW()) )} -> -2537.0327 | F88: {=_xlfn.XLOOKUP(1, (INDIRECT("'"&$C$6&"'!$6:$6")=F$6)* (INDIRECT("'"&$C$6&"'!$5:$5")=F$5), INDIRECT("'"&$C$6&"'!"&ROW()&":"&ROW()) )} -> -2465.975 | G88: {=_xlfn.XLOOKUP(1, (INDIRECT("'"&$C$6&"'!$6:$6")=G$6)* (INDIRECT("'"&$C$6&"'!$5:$5")=G$5), INDIRECT("'"&$C$6&"'!"&ROW()&":"&ROW()) )} -> -2089.8883 | H88: {=_xlfn.XLOOKUP(1, (INDIRECT("'"&$C$6&"'!$6:$6")=H$6)* (INDIRECT("'"&$C$6&"'!$5:$5")=H$5), INDIRECT("'"&$C$6&"'!"&ROW()&":"&ROW()) )} -> -1849.5381 | I88: {=_xlfn.XLOOKUP(1, (INDIRECT("'"&$C$6&"'!$6:$6")=I$6)* (INDIRECT("'"&$C$6&"'!$5:$5")=I$5), INDIRECT("'"&$C$6&"'!"&ROW()&":"&ROW()) )} -> -1952.7376 | K88: =$D88-E88 -> -14.318876 | L88: =$D88-F88 -> -85.376642 | M88: =$D88-G88 -> -461.46329 | N88: =$D88-H88 -> -701.81355 | O88: =$D88-I88 -> -598.61401 | Q88: =IFERROR($D88/E88-1,0) -> 0.0056439461 | R88: =IFERROR($D88/F88-1,0) -> 0.034621861 | S88: =IFERROR($D88/G88-1,0) -> 0.22080763 | T88: =IFERROR($D88/H88-1,0) -> 0.37945342 | U88: =IFERROR($D88/I88-1,0) -> 0.30655118 | W88: {=INDIRECT("'"&$C$6&"'!"&ADDRESS(ROW(),COLUMN()+44))} -> -7675.7592 | X88: {=INDIRECT("'"&$C$6&"'!"&ADDRESS(ROW(),COLUMN()+44))} -> -7517.1328 | Y88: {=INDIRECT("'"&$C$6&"'!"&ADDRESS(ROW(),COLUMN()+44))} -> -5124.4075 | Z88: {=INDIRECT("'"&$C$6&"'!"&ADDRESS(ROW(),COLUMN()+44))} -> -6341.9348 | AA88: {=INDIRECT("'"&$C$6&"'!"&ADDRESS(ROW(),COLUMN()+44))} -> -5673.7321 | AB88: {=INDIRECT("'"&$C$6&"'!"&ADDRESS(ROW(),COLUMN()+44))} -> -5972.3105 | AD88: =$W88-X88 -> -158.62633 | AE88: =$W88-Y88 -> -2551.3516 | AF88: =$W88-Z88 -> -1333.8243 | AG88: =$W88-AA88 -> -2002.0271 | AH88: =$W88-AB88 -> -1703.4486 | AJ88: =IFERROR($W88/X88-1,0) -> 0.021101973 | AK88: =IFERROR($W88/Y88-1,0) -> 0.49788226 | AL88: =IFERROR($W88/Z88-1,0) -> 0.2103182 | AM88: =IFERROR($W88/AA88-1,0) -> 0.35285894 | AN88: =IFERROR($W88/AB88-1,0) -> 0.28522439
C89: Gastos Operativos | D89: =SUM(D86:D88) -> -5568.8027 | E89: =SUM(E86:E88) -> -5314.9286 | F89: =SUM(F86:F88) -> -5298.4297 | G89: =SUM(G86:G88) -> -4652.9828 | H89: =SUM(H86:H88) -> -4185.6828 | I89: =SUM(I86:I88) -> -4763.5339 | K89: =$D89-E89 -> -253.87417 | L89: =$D89-F89 -> -270.37304 | M89: =$D89-G89 -> -915.81991 | N89: =$D89-H89 -> -1383.12 | O89: =$D89-I89 -> -805.26883 | Q89: =IFERROR($D89/E89-1,0) -> 0.047766243 | R89: =IFERROR($D89/F89-1,0) -> 0.051028899 | S89: =IFERROR($D89/G89-1,0) -> 0.19682426 | T89: =IFERROR($D89/H89-1,0) -> 0.33044071 | U89: =IFERROR($D89/I89-1,0) -> 0.16904862 | W89: =SUM(W86:W88) -> -16078.522 | X89: =SUM(X86:X88) -> -15697.73 | Y89: =SUM(Y86:Y88) -> -10509.719 | Z89: =SUM(Z86:Z88) -> -13395.54 | AA89: =SUM(AA86:AA88) -> -12875.311 | AB89: =SUM(AB86:AB88) -> -13988.729 | AD89: =$W89-X89 -> -380.79151 | AE89: =$W89-Y89 -> -5568.8027 | AF89: =$W89-Z89 -> -2682.9815 | AG89: =$W89-AA89 -> -3203.211 | AH89: =$W89-AB89 -> -2089.7926 | AJ89: =IFERROR($W89/X89-1,0) -> 0.024257743 | AK89: =IFERROR($W89/Y89-1,0) -> 0.5298717 | AL89: =IFERROR($W89/Z89-1,0) -> 0.20028916 | AM89: =IFERROR($W89/AA89-1,0) -> 0.24878708 | AN89: =IFERROR($W89/AB89-1,0) -> 0.14939117
A91: Extraordinarios | C91: Donaciones | D91: {=_xlfn.XLOOKUP(1, (INDIRECT("'"&$C$6&"'!$6:$6")=D$6)* (INDIRECT("'"&$C$6&"'!$5:$5")=D$5), INDIRECT("'"&$C$6&"'!"&ROW()&":"&ROW()) )} -> 0 | E91: {=_xlfn.XLOOKUP(1, (INDIRECT("'"&$C$6&"'!$6:$6")=E$6)* (INDIRECT("'"&$C$6&"'!$5:$5")=E$5), INDIRECT("'"&$C$6&"'!"&ROW()&":"&ROW()) )} -> 0 | F91: {=_xlfn.XLOOKUP(1, (INDIRECT("'"&$C$6&"'!$6:$6")=F$6)* (INDIRECT("'"&$C$6&"'!$5:$5")=F$5), INDIRECT("'"&$C$6&"'!"&ROW()&":"&ROW()) )} -> 0 | G91: {=_xlfn.XLOOKUP(1, (INDIRECT("'"&$C$6&"'!$6:$6")=G$6)* (INDIRECT("'"&$C$6&"'!$5:$5")=G$5), INDIRECT("'"&$C$6&"'!"&ROW()&":"&ROW()) )} -> 0 | H91: {=_xlfn.XLOOKUP(1, (INDIRECT("'"&$C$6&"'!$6:$6")=H$6)* (INDIRECT("'"&$C$6&"'!$5:$5")=H$5), INDIRECT("'"&$C$6&"'!"&ROW()&":"&ROW()) )} -> 0 | I91: {=_xlfn.XLOOKUP(1, (INDIRECT("'"&$C$6&"'!$6:$6")=I$6)* (INDIRECT("'"&$C$6&"'!$5:$5")=I$5), INDIRECT("'"&$C$6&"'!"&ROW()&":"&ROW()) )} -> 0 | K91: =$D91-E91 -> 0 | L91: =$D91-F91 -> 0 | M91: =$D91-G91 -> 0 | N91: =$D91-H91 -> 0 | O91: =$D91-I91 -> 0 | Q91: =IFERROR($D91/E91-1,0) -> 0 | R91: =IFERROR($D91/F91-1,0) -> 0 | S91: =IFERROR($D91/G91-1,0) -> 0 | T91: =IFERROR($D91/H91-1,0) -> 0 | U91: =IFERROR($D91/I91-1,0) -> 0 | W91: {=INDIRECT("'"&$C$6&"'!"&ADDRESS(ROW(),COLUMN()+44))} -> 0 | X91: {=INDIRECT("'"&$C$6&"'!"&ADDRESS(ROW(),COLUMN()+44))} -> 0 | Y91: {=INDIRECT("'"&$C$6&"'!"&ADDRESS(ROW(),COLUMN()+44))} -> 0 | Z91: {=INDIRECT("'"&$C$6&"'!"&ADDRESS(ROW(),COLUMN()+44))} -> 0 | AA91: {=INDIRECT("'"&$C$6&"'!"&ADDRESS(ROW(),COLUMN()+44))} -> 0 | AB91: {=INDIRECT("'"&$C$6&"'!"&ADDRESS(ROW(),COLUMN()+44))} -> 0 | AD91: =$W91-X91 -> 0 | AE91: =$W91-Y91 -> 0 | AF91: =$W91-Z91 -> 0 | AG91: =$W91-AA91 -> 0 | AH91: =$W91-AB91 -> 0 | AJ91: =IFERROR($W91/X91-1,0) -> 0 | AK91: =IFERROR($W91/Y91-1,0) -> 0 | AL91: =IFERROR($W91/Z91-1,0) -> 0 | AM91: =IFERROR($W91/AA91-1,0) -> 0 | AN91: =IFERROR($W91/AB91-1,0) -> 0
A92: Extraordinarios | C92: Otros | D92: {=_xlfn.XLOOKUP(1, (INDIRECT("'"&$C$6&"'!$6:$6")=D$6)* (INDIRECT("'"&$C$6&"'!$5:$5")=D$5), INDIRECT("'"&$C$6&"'!"&ROW()&":"&ROW()) )} -> -160.07279 | E92: {=_xlfn.XLOOKUP(1, (INDIRECT("'"&$C$6&"'!$6:$6")=E$6)* (INDIRECT("'"&$C$6&"'!$5:$5")=E$5), INDIRECT("'"&$C$6&"'!"&ROW()&":"&ROW()) )} -> -190.71378 | F92: {=_xlfn.XLOOKUP(1, (INDIRECT("'"&$C$6&"'!$6:$6")=F$6)* (INDIRECT("'"&$C$6&"'!$5:$5")=F$5), INDIRECT("'"&$C$6&"'!"&ROW()&":"&ROW()) )} -> -19.984786 | G92: {=_xlfn.XLOOKUP(1, (INDIRECT("'"&$C$6&"'!$6:$6")=G$6)* (INDIRECT("'"&$C$6&"'!$5:$5")=G$5), INDIRECT("'"&$C$6&"'!"&ROW()&":"&ROW()) )} -> -77.86182 | H92: {=_xlfn.XLOOKUP(1, (INDIRECT("'"&$C$6&"'!$6:$6")=H$6)* (INDIRECT("'"&$C$6&"'!$5:$5")=H$5), INDIRECT("'"&$C$6&"'!"&ROW()&":"&ROW()) )} -> -105.16542 | I92: {=_xlfn.XLOOKUP(1, (INDIRECT("'"&$C$6&"'!$6:$6")=I$6)* (INDIRECT("'"&$C$6&"'!$5:$5")=I$5), INDIRECT("'"&$C$6&"'!"&ROW()&":"&ROW()) )} -> -51.149913 | K92: =$D92-E92 -> 30.640994 | L92: =$D92-F92 -> -140.088 | M92: =$D92-G92 -> -82.210966 | N92: =$D92-H92 -> -54.907363 | O92: =$D92-I92 -> -108.92287 | Q92: =IFERROR($D92/E92-1,0) -> -0.16066481 | R92: =IFERROR($D92/F92-1,0) -> 7.0097322 | S92: =IFERROR($D92/G92-1,0) -> 1.0558572 | T92: =IFERROR($D92/H92-1,0) -> 0.52210471 | U92: =IFERROR($D92/I92-1,0) -> 2.1294831 | W92: {=INDIRECT("'"&$C$6&"'!"&ADDRESS(ROW(),COLUMN()+44))} -> -218.11366 | X92: {=INDIRECT("'"&$C$6&"'!"&ADDRESS(ROW(),COLUMN()+44))} -> -556.11992 | Y92: {=INDIRECT("'"&$C$6&"'!"&ADDRESS(ROW(),COLUMN()+44))} -> -58.040873 | Z92: {=INDIRECT("'"&$C$6&"'!"&ADDRESS(ROW(),COLUMN()+44))} -> -255.74972 | AA92: {=INDIRECT("'"&$C$6&"'!"&ADDRESS(ROW(),COLUMN()+44))} -> -492.06508 | AB92: {=INDIRECT("'"&$C$6&"'!"&ADDRESS(ROW(),COLUMN()+44))} -> -381.62305 | AD92: =$W92-X92 -> 338.00626 | AE92: =$W92-Y92 -> -160.07279 | AF92: =$W92-Z92 -> 37.636056 | AG92: =$W92-AA92 -> 273.95142 | AH92: =$W92-AB92 -> 163.50939 | AJ92: =IFERROR($W92/X92-1,0) -> -0.60779384 | AK92: =IFERROR($W92/Y92-1,0) -> 2.7579321 | AL92: =IFERROR($W92/Z92-1,0) -> -0.14715972 | AM92: =IFERROR($W92/AA92-1,0) -> -0.55673819 | AN92: =IFERROR($W92/AB92-1,0) -> -0.42845784
C93: Extraordinarios | D93: =SUM(D91:D92) -> -160.07279 | E93: =SUM(E91:E92) -> -190.71378 | F93: =SUM(F91:F92) -> -19.984786 | G93: =SUM(G91:G92) -> -77.86182 | H93: =SUM(H91:H92) -> -105.16542 | I93: =SUM(I91:I92) -> -51.149913 | K93: =$D93-E93 -> 30.640994 | L93: =$D93-F93 -> -140.088 | M93: =$D93-G93 -> -82.210966 | N93: =$D93-H93 -> -54.907363 | O93: =$D93-I93 -> -108.92287 | Q93: =IFERROR($D93/E93-1,0) -> -0.16066481 | R93: =IFERROR($D93/F93-1,0) -> 7.0097322 | S93: =IFERROR($D93/G93-1,0) -> 1.0558572 | T93: =IFERROR($D93/H93-1,0) -> 0.52210471 | U93: =IFERROR($D93/I93-1,0) -> 2.1294831 | W93: =SUM(W91:W92) -> -218.11366 | X93: =SUM(X91:X92) -> -556.11992 | Y93: =SUM(Y91:Y92) -> -58.040873 | Z93: =SUM(Z91:Z92) -> -255.74972 | AA93: =SUM(AA91:AA92) -> -492.06508 | AB93: =SUM(AB91:AB92) -> -381.62305 | AD93: =$W93-X93 -> 338.00626 | AE93: =$W93-Y93 -> -160.07279 | AF93: =$W93-Z93 -> 37.636056 | AG93: =$W93-AA93 -> 273.95142 | AH93: =$W93-AB93 -> 163.50939 | AJ93: =IFERROR($W93/X93-1,0) -> -0.60779384 | AK93: =IFERROR($W93/Y93-1,0) -> 2.7579321 | AL93: =IFERROR($W93/Z93-1,0) -> -0.14715972 | AM93: =IFERROR($W93/AA93-1,0) -> -0.55673819 | AN93: =IFERROR($W93/AB93-1,0) -> -0.42845784
A95: ROF | C95: Venta de Cartera | D95: {=_xlfn.XLOOKUP(1, (INDIRECT("'"&$C$6&"'!$6:$6")=D$6)* (INDIRECT("'"&$C$6&"'!$5:$5")=D$5), INDIRECT("'"&$C$6&"'!"&ROW()&":"&ROW()) )} -> 0 | E95: {=_xlfn.XLOOKUP(1, (INDIRECT("'"&$C$6&"'!$6:$6")=E$6)* (INDIRECT("'"&$C$6&"'!$5:$5")=E$5), INDIRECT("'"&$C$6&"'!"&ROW()&":"&ROW()) )} -> 0 | F95: {=_xlfn.XLOOKUP(1, (INDIRECT("'"&$C$6&"'!$6:$6")=F$6)* (INDIRECT("'"&$C$6&"'!$5:$5")=F$5), INDIRECT("'"&$C$6&"'!"&ROW()&":"&ROW()) )} -> 0 | G95: {=_xlfn.XLOOKUP(1, (INDIRECT("'"&$C$6&"'!$6:$6")=G$6)* (INDIRECT("'"&$C$6&"'!$5:$5")=G$5), INDIRECT("'"&$C$6&"'!"&ROW()&":"&ROW()) )} -> 2363.95 | H95: {=_xlfn.XLOOKUP(1, (INDIRECT("'"&$C$6&"'!$6:$6")=H$6)* (INDIRECT("'"&$C$6&"'!$5:$5")=H$5), INDIRECT("'"&$C$6&"'!"&ROW()&":"&ROW()) )} -> 0 | I95: {=_xlfn.XLOOKUP(1, (INDIRECT("'"&$C$6&"'!$6:$6")=I$6)* (INDIRECT("'"&$C$6&"'!$5:$5")=I$5), INDIRECT("'"&$C$6&"'!"&ROW()&":"&ROW()) )} -> 0 | K95: =$D95-E95 -> 0 | L95: =$D95-F95 -> 0 | M95: =$D95-G95 -> -2363.95 | N95: =$D95-H95 -> 0 | O95: =$D95-I95 -> 0 | Q95: =IFERROR($D95/E95-1,0) -> 0 | R95: =IFERROR($D95/F95-1,0) -> 0 | S95: =IFERROR($D95/G95-1,0) -> -1 | T95: =IFERROR($D95/H95-1,0) -> 0 | U95: =IFERROR($D95/I95-1,0) -> 0 | W95: {=INDIRECT("'"&$C$6&"'!"&ADDRESS(ROW(),COLUMN()+44))} -> 0 | X95: {=INDIRECT("'"&$C$6&"'!"&ADDRESS(ROW(),COLUMN()+44))} -> 0 | Y95: {=INDIRECT("'"&$C$6&"'!"&ADDRESS(ROW(),COLUMN()+44))} -> 0 | Z95: {=INDIRECT("'"&$C$6&"'!"&ADDRESS(ROW(),COLUMN()+44))} -> 2363.95 | AA95: {=INDIRECT("'"&$C$6&"'!"&ADDRESS(ROW(),COLUMN()+44))} -> 0 | AB95: {=INDIRECT("'"&$C$6&"'!"&ADDRESS(ROW(),COLUMN()+44))} -> 0 | AD95: =$W95-X95 -> 0 | AE95: =$W95-Y95 -> 0 | AF95: =$W95-Z95 -> -2363.95 | AG95: =$W95-AA95 -> 0 | AH95: =$W95-AB95 -> 0 | AJ95: =IFERROR($W95/X95-1,0) -> 0 | AK95: =IFERROR($W95/Y95-1,0) -> 0 | AL95: =IFERROR($W95/Z95-1,0) -> -1 | AM95: =IFERROR($W95/AA95-1,0) -> 0 | AN95: =IFERROR($W95/AB95-1,0) -> 0
C96: ROF | D96: =SUM(D95:D95) -> 0 | E96: =SUM(E95:E95) -> 0 | F96: =SUM(F95:F95) -> 0 | G96: =SUM(G95:G95) -> 2363.95 | H96: =SUM(H95:H95) -> 0 | I96: =SUM(I95:I95) -> 0 | K96: =$D96-E96 -> 0 | L96: =$D96-F96 -> 0 | M96: =$D96-G96 -> -2363.95 | N96: =$D96-H96 -> 0 | O96: =$D96-I96 -> 0 | Q96: =IFERROR($D96/E96-1,0) -> 0 | R96: =IFERROR($D96/F96-1,0) -> 0 | S96: =IFERROR($D96/G96-1,0) -> -1 | T96: =IFERROR($D96/H96-1,0) -> 0 | U96: =IFERROR($D96/I96-1,0) -> 0 | W96: =SUM(W95:W95) -> 0 | X96: =SUM(X95:X95) -> 0 | Y96: =SUM(Y95:Y95) -> 0 | Z96: =SUM(Z95:Z95) -> 2363.95 | AA96: =SUM(AA95:AA95) -> 0 | AB96: =SUM(AB95:AB95) -> 0 | AD96: =$W96-X96 -> 0 | AE96: =$W96-Y96 -> 0 | AF96: =$W96-Z96 -> -2363.95 | AG96: =$W96-AA96 -> 0 | AH96: =$W96-AB96 -> 0 | AJ96: =IFERROR($W96/X96-1,0) -> 0 | AK96: =IFERROR($W96/Y96-1,0) -> 0 | AL96: =IFERROR($W96/Z96-1,0) -> -1 | AM96: =IFERROR($W96/AA96-1,0) -> 0 | AN96: =IFERROR($W96/AB96-1,0) -> 0
C98: UAI | D98: =D60+D83+D89+D93+D96 -> 8067.3065 | E98: =E60+E83+E89+E93+E96 -> -400.31546 | F98: =F60+F83+F89+F93+F96 -> 4305.2552 | G98: =G60+G83+G89+G93+G96 -> -4308.2717 | H98: =H60+H83+H89+H93+H96 -> -55858.659 | I98: =I60+I83+I89+I93+I96 -> 251.26492 | K98: =$D98-E98 -> 8467.6219 | L98: =$D98-F98 -> 3762.0512 | M98: =$D98-G98 -> 12375.578 | N98: =$D98-H98 -> 63925.966 | O98: =$D98-I98 -> 7816.0415 | Q98: =IFERROR($D98/E98-1,0) -> -21.152373 | R98: =IFERROR($D98/F98-1,0) -> 0.87382769 | S98: =IFERROR($D98/G98-1,0) -> -2.8725157 | T98: =IFERROR($D98/H98-1,0) -> -1.1444236 | U98: =IFERROR($D98/I98-1,0) -> 31.106776 | W98: =W60+W83+W89+W93+W96 -> 19587.288 | X98: =X60+X83+X89+X93+X96 -> -357.06172 | Y98: =Y60+Y83+Y89+Y93+Y96 -> 11519.981 | Z98: =Z60+Z83+Z89+Z93+Z96 -> -26525.278 | AA98: =AA60+AA83+AA89+AA93+AA96 -> -155708.16 | AB98: =AB60+AB83+AB89+AB93+AB96 -> 8612.9794 | AD98: =$W98-X98 -> 19944.35 | AE98: =$W98-Y98 -> 8067.3065 | AF98: =$W98-Z98 -> 46112.566 | AG98: =$W98-AA98 -> 175295.45 | AH98: =$W98-AB98 -> 10974.308 | AJ98: =IFERROR($W98/X98-1,0) -> -55.856869 | AK98: =IFERROR($W98/Y98-1,0) -> 0.70028815 | AL98: =IFERROR($W98/Z98-1,0) -> -1.7384385 | AM98: =IFERROR($W98/AA98-1,0) -> -1.1257949 | AN98: =IFERROR($W98/AB98-1,0) -> 1.2741594
C102: Prom SFdP | D102: {=_xlfn.XLOOKUP(1, (INDIRECT("'"&$C$6&"'!$6:$6")=D$6)* (INDIRECT("'"&$C$6&"'!$5:$5")=D$5), INDIRECT("'"&$C$6&"'!"&ROW()&":"&ROW()) )} -> 3300761.6 | E102: {=_xlfn.XLOOKUP(1, (INDIRECT("'"&$C$6&"'!$6:$6")=E$6)* (INDIRECT("'"&$C$6&"'!$5:$5")=E$5), INDIRECT("'"&$C$6&"'!"&ROW()&":"&ROW()) )} -> 3227708.5 | F102: {=_xlfn.XLOOKUP(1, (INDIRECT("'"&$C$6&"'!$6:$6")=F$6)* (INDIRECT("'"&$C$6&"'!$5:$5")=F$5), INDIRECT("'"&$C$6&"'!"&ROW()&":"&ROW()) )} -> 3249119.6 | G102: {=_xlfn.XLOOKUP(1, (INDIRECT("'"&$C$6&"'!$6:$6")=G$6)* (INDIRECT("'"&$C$6&"'!$5:$5")=G$5), INDIRECT("'"&$C$6&"'!"&ROW()&":"&ROW()) )} -> 3006933.2 | H102: {=_xlfn.XLOOKUP(1, (INDIRECT("'"&$C$6&"'!$6:$6")=H$6)* (INDIRECT("'"&$C$6&"'!$5:$5")=H$5), INDIRECT("'"&$C$6&"'!"&ROW()&":"&ROW()) )} -> 3634287.7 | I102: {=_xlfn.XLOOKUP(1, (INDIRECT("'"&$C$6&"'!$6:$6")=I$6)* (INDIRECT("'"&$C$6&"'!$5:$5")=I$5), INDIRECT("'"&$C$6&"'!"&ROW()&":"&ROW()) )} -> 3443124.8 | W102: {=INDIRECT("'"&$C$6&"'!"&ADDRESS(ROW(),COLUMN()+44))} -> 3250109.5 | X102: {=INDIRECT("'"&$C$6&"'!"&ADDRESS(ROW(),COLUMN()+44))} -> 3220598.6 | Y102: {=INDIRECT("'"&$C$6&"'!"&ADDRESS(ROW(),COLUMN()+44))} -> 3226416.4 | Z102: {=INDIRECT("'"&$C$6&"'!"&ADDRESS(ROW(),COLUMN()+44))} -> 3013328.1 | AA102: {=INDIRECT("'"&$C$6&"'!"&ADDRESS(ROW(),COLUMN()+44))} -> 3707224.3 | AB102: {=INDIRECT("'"&$C$6&"'!"&ADDRESS(ROW(),COLUMN()+44))} -> 3394388.1

Sheet Indicadores
C1: Mensual | P1: Acumulado
J2: Variación % | W2: Variación %
B3: =Desempeño_Financiero!C6 -> Total_Producto | C3: =Desempeño_Financiero!D6 -> 46112 | D3: =Desempeño_Financiero!E6 -> 46112 | E3: =Desempeño_Financiero!F6 -> 46081 | F3: =Desempeño_Financiero!G6 -> 45747 | G3: =Desempeño_Financiero!H6 -> 45382 | H3: =Desempeño_Financiero!I6 -> 45016 | J3: =D3 -> 46112 | K3: =E3 -> 46081 | L3: =F3 -> 45747 | M3: =G3 -> 45382 | N3: =H3 -> 45016 | P3: =C3 -> 46112 | Q3: =D3 -> 46112 | R3: =E3 -> 46081 | S3: =F3 -> 45747 | T3: =G3 -> 45382 | U3: =H3 -> 45016 | W3: =Q3 -> 46112 | X3: =R3 -> 46081 | Y3: =S3 -> 45747 | Z3: =T3 -> 45382 | AA3: =U3 -> 45016
B5: Eficiencia | C5: =IFERROR((-Desempeño_Financiero!D89)/(Desempeño_Financiero!D53+Desempeño_Financiero!D83+Desempeño_Financiero!D96),0) -> 0.20900946 | D5: =IFERROR((-Desempeño_Financiero!E89)/(Desempeño_Financiero!E53+Desempeño_Financiero!E83+Desempeño_Financiero!E96),0) -> 0.2070356 | E5: =IFERROR((-Desempeño_Financiero!F89)/(Desempeño_Financiero!F53+Desempeño_Financiero!F83+Desempeño_Financiero!F96),0) -> 0.2232267 | F5: =IFERROR((-Desempeño_Financiero!G89)/(Desempeño_Financiero!G53+Desempeño_Financiero!G83+Desempeño_Financiero!G96),0) -> 0.18639544 | G5: =IFERROR((-Desempeño_Financiero!H89)/(Desempeño_Financiero!H53+Desempeño_Financiero!H83+Desempeño_Financiero!H96),0) -> 0.16411437 | H5: =IFERROR((-Desempeño_Financiero!I89)/(Desempeño_Financiero!I53+Desempeño_Financiero!I83+Desempeño_Financiero!I96),0) -> 0.16143364 | J5: =IFERROR(($C5-D5)*10000,0) -> 19.738639 | K5: =IFERROR(($C5-E5)*10000,0) -> -142.17241 | L5: =IFERROR(($C5-F5)*10000,0) -> 226.14018 | M5: =IFERROR(($C5-G5)*10000,0) -> 448.95086 | N5: =IFERROR(($C5-H5)*10000,0) -> 475.75819 | P5: =IFERROR((-Desempeño_Financiero!W89)/(Desempeño_Financiero!W53+Desempeño_Financiero!W83+Desempeño_Financiero!W96),0) -> 0.21160441 | Q5: =IFERROR((-Desempeño_Financiero!X89)/(Desempeño_Financiero!X53+Desempeño_Financiero!X83+Desempeño_Financiero!X96),0) -> 0.21341597 | R5: =IFERROR((-Desempeño_Financiero!Y89)/(Desempeño_Financiero!Y53+Desempeño_Financiero!Y83+Desempeño_Financiero!Y96),0) -> 0.21300568 | S5: =IFERROR((-Desempeño_Financiero!Z89)/(Desempeño_Financiero!Z53+Desempeño_Financiero!Z83+Desempeño_Financiero!Z96),0) -> 0.1986748 | T5: =IFERROR((-Desempeño_Financiero!AA89)/(Desempeño_Financiero!AA53+Desempeño_Financiero!AA83+Desempeño_Financiero!AA96),0) -> 0.1665705 | U5: =IFERROR((-Desempeño_Financiero!AB89)/(Desempeño_Financiero!AB53+Desempeño_Financiero!AB83+Desempeño_Financiero!AB96),0) -> 0.1640812 | W5: =IFERROR(($P5-Q5)*10000,0) -> -18.1156 | X5: =IFERROR(($P5-R5)*10000,0) -> -14.012773 | Y5: =IFERROR(($P5-S5)*10000,0) -> 129.29608 | Z5: =IFERROR(($P5-T5)*10000,0) -> 450.33908 | AA5: =IFERROR(($P5-U5)*10000,0) -> 475.23208
B7: Rendimiento de Colocaciones | C7: =Desempeño_Financiero!D23 -> 0.16343382 | D7: =Desempeño_Financiero!E23 -> 0.16308314 | E7: =Desempeño_Financiero!F23 -> 0.16485398 | F7: =Desempeño_Financiero!G23 -> 0.16512237 | G7: =Desempeño_Financiero!H23 -> 0.16600838 | H7: =Desempeño_Financiero!I23 -> 0.18343664 | J7: =IFERROR(($C7-D7)*10000,0) -> 3.5067804 | K7: =IFERROR(($C7-E7)*10000,0) -> -14.20159 | L7: =IFERROR(($C7-F7)*10000,0) -> -16.885491 | M7: =IFERROR(($C7-G7)*10000,0) -> -25.745644 | N7: =IFERROR(($C7-H7)*10000,0) -> -200.02825 | P7: =Desempeño_Financiero!W23 -> 0.16418505 | Q7: =Desempeño_Financiero!X23 -> 0.1625696 | R7: =Desempeño_Financiero!Y23 -> 0.1645071 | S7: =Desempeño_Financiero!Z23 -> 0.16499509 | T7: =Desempeño_Financiero!AA23 -> 0.16756622 | U7: =Desempeño_Financiero!AB23 -> 0.18367537 | W7: =IFERROR(($P7-Q7)*10000,0) -> 16.154471 | X7: =IFERROR(($P7-R7)*10000,0) -> -3.2205072 | Y7: =IFERROR(($P7-S7)*10000,0) -> -8.1004627 | Z7: =IFERROR(($P7-T7)*10000,0) -> -33.811769 | AA7: =IFERROR(($P7-U7)*10000,0) -> -194.90319
B9: INOF / Ingresos Totales | C9: =IFERROR((Desempeño_Financiero!D83)/(Desempeño_Financiero!D53+Desempeño_Financiero!D83+Desempeño_Financiero!D96),0) -> 0.010767442 | D9: =IFERROR((Desempeño_Financiero!E83)/(Desempeño_Financiero!E53+Desempeño_Financiero!E83+Desempeño_Financiero!E96),0) -> 0.012255598 | E9: =IFERROR((Desempeño_Financiero!F83)/(Desempeño_Financiero!F53+Desempeño_Financiero!F83+Desempeño_Financiero!F96),0) -> 0.01147482 | F9: =IFERROR((Desempeño_Financiero!G83)/(Desempeño_Financiero!G53+Desempeño_Financiero!G83+Desempeño_Financiero!G96),0) -> 0.006062877 | G9: =IFERROR((Desempeño_Financiero!H83)/(Desempeño_Financiero!H53+Desempeño_Financiero!H83+Desempeño_Financiero!H96),0) -> 0.016836807 | H9: =IFERROR((Desempeño_Financiero!I83)/(Desempeño_Financiero!I53+Desempeño_Financiero!I83+Desempeño_Financiero!I96),0) -> 0.010028069 | J9: =IFERROR(($C9-D9)*10000,0) -> -14.881557 | K9: =IFERROR(($C9-E9)*10000,0) -> -7.0737852 | L9: =IFERROR(($C9-F9)*10000,0) -> 47.045649 | M9: =IFERROR(($C9-G9)*10000,0) -> -60.693653 | N9: =IFERROR(($C9-H9)*10000,0) -> 7.3937289 | P9: =IFERROR((Desempeño_Financiero!W83)/(Desempeño_Financiero!W53+Desempeño_Financiero!W83+Desempeño_Financiero!W96),0) -> 0.012055314 | Q9: =IFERROR((Desempeño_Financiero!X83)/(Desempeño_Financiero!X53+Desempeño_Financiero!X83+Desempeño_Financiero!X96),0) -> 0.012753839 | R9: =IFERROR((Desempeño_Financiero!Y83)/(Desempeño_Financiero!Y53+Desempeño_Financiero!Y83+Desempeño_Financiero!Y96),0) -> 0.012750769 | S9: =IFERROR((Desempeño_Financiero!Z83)/(Desempeño_Financiero!Z53+Desempeño_Financiero!Z83+Desempeño_Financiero!Z96),0) -> 0.011619647 | T9: =IFERROR((Desempeño_Financiero!AA83)/(Desempeño_Financiero!AA53+Desempeño_Financiero!AA83+Desempeño_Financiero!AA96),0) -> 0.016117393 | U9: =IFERROR((Desempeño_Financiero!AB83)/(Desempeño_Financiero!AB53+Desempeño_Financiero!AB83+Desempeño_Financiero!AB96),0) -> 0.012184139 | W9: =IFERROR(($P9-Q9)*10000,0) -> -6.9852494 | X9: =IFERROR(($P9-R9)*10000,0) -> -6.9545454 | Y9: =IFERROR(($P9-S9)*10000,0) -> 4.3566741 | Z9: =IFERROR(($P9-T9)*10000,0) -> -40.620789 | AA9: =IFERROR(($P9-U9)*10000,0) -> -1.2882492
B11: INOF / Gasto Operativo | C11: =IFERROR((Desempeño_Financiero!D83/-Desempeño_Financiero!D89),0) -> 0.051516529 | D11: =IFERROR((Desempeño_Financiero!E83/-Desempeño_Financiero!E89),0) -> 0.059195606 | E11: =IFERROR((Desempeño_Financiero!F83/-Desempeño_Financiero!F89),0) -> 0.051404336 | F11: =IFERROR((Desempeño_Financiero!G83/-Desempeño_Financiero!G89),0) -> 0.03252696 | G11: =IFERROR((Desempeño_Financiero!H83/-Desempeño_Financiero!H89),0) -> 0.10259191 | H11: =IFERROR((Desempeño_Financiero!I83/-Desempeño_Financiero!I89),0) -> 0.062118831 | J11: =IFERROR(($C11-D11)*10000,0) -> -76.790769 | K11: =IFERROR(($C11-E11)*10000,0) -> 1.1219264 | L11: =IFERROR(($C11-F11)*10000,0) -> 189.89569 | M11: =IFERROR(($C11-G11)*10000,0) -> -510.75382 | N11: =IFERROR(($C11-H11)*10000,0) -> -106.02302 | P11: =IFERROR((Desempeño_Financiero!W83/-Desempeño_Financiero!W89),0) -> 0.056970998 | Q11: =IFERROR((Desempeño_Financiero!X83/-Desempeño_Financiero!X89),0) -> 0.059760473 | R11: =IFERROR((Desempeño_Financiero!Y83/-Desempeño_Financiero!Y89),0) -> 0.059861167 | S11: =IFERROR((Desempeño_Financiero!Z83/-Desempeño_Financiero!Z89),0) -> 0.058485761 | T11: =IFERROR((Desempeño_Financiero!AA83/-Desempeño_Financiero!AA89),0) -> 0.096760191 | U11: =IFERROR((Desempeño_Financiero!AB83/-Desempeño_Financiero!AB89),0) -> 0.074256766 | W11: =IFERROR(($P11-Q11)*10000,0) -> -27.894753 | X11: =IFERROR(($P11-R11)*10000,0) -> -28.901688 | Y11: =IFERROR(($P11-S11)*10000,0) -> -15.147631 | Z11: =IFERROR(($P11-T11)*10000,0) -> -397.89193 | AA11: =IFERROR(($P11-U11)*10000,0) -> -172.85768
B13: Gasto Operativo / Activo | C13: =IFERROR(-Desempeño_Financiero!D89/Desempeño_Financiero!D17*12,0) -> 0.020260136 | D13: =IFERROR(-Desempeño_Financiero!E89/Desempeño_Financiero!E17*12,0) -> 0.019817127 | E13: =IFERROR(-Desempeño_Financiero!F89/Desempeño_Financiero!F17*12,0) -> 0.019650682 | F13: =IFERROR(-Desempeño_Financiero!G89/Desempeño_Financiero!G17*12,0) -> 0.018562471 | G13: =IFERROR(-Desempeño_Financiero!H89/Desempeño_Financiero!H17*12,0) -> 0.013817394 | H13: =IFERROR(-Desempeño_Financiero!I89/Desempeño_Financiero!I17*12,0) -> 0.016641489 | J13: =IFERROR(($C13-D13)*10000,0) -> 4.4300956 | K13: =IFERROR(($C13-E13)*10000,0) -> 6.0945424 | L13: =IFERROR(($C13-F13)*10000,0) -> 16.976651 | M13: =IFERROR(($C13-G13)*10000,0) -> 64.427423 | N13: =IFERROR(($C13-H13)*10000,0) -> 36.186477 | P13: =IFERROR(-Desempeño_Financiero!W89/Desempeño_Financiero!W17*12,0) -> 0.059565476 | Q13: =IFERROR(-Desempeño_Financiero!X89/Desempeño_Financiero!X17*12,0) -> 0.058796715 | R13: =IFERROR(-Desempeño_Financiero!Y89/Desempeño_Financiero!Y17*12,0) -> 0.039294132 | S13: =IFERROR(-Desempeño_Financiero!Z89/Desempeño_Financiero!Z17*12,0) -> 0.053428994 | T13: =IFERROR(-Desempeño_Financiero!AA89/Desempeño_Financiero!AA17*12,0) -> 0.041665676 | U13: =IFERROR(-Desempeño_Financiero!AB89/Desempeño_Financiero!AB17*12,0) -> 0.05028251 | W13: =IFERROR(($P13-Q13)*10000,0) -> 7.6876131 | X13: =IFERROR(($P13-R13)*10000,0) -> 202.71344 | Y13: =IFERROR(($P13-S13)*10000,0) -> 61.364822 | Z13: =IFERROR(($P13-T13)*10000,0) -> 178.998 | AA13: =IFERROR(($P13-U13)*10000,0) -> 92.829659
B15: Provisiones Brutas / Cartera Bruta | C15: =IFERROR(-Desempeño_Financiero!D56/Desempeño_Financiero!D102,0)*12 -> 0.053936042 | D15: =IFERROR(-Desempeño_Financiero!E56/Desempeño_Financiero!E102,0)*12 -> 0.080858559 | E15: =IFERROR(-Desempeño_Financiero!F56/Desempeño_Financiero!F102,0)*12 -> 0.058497202 | F15: =IFERROR(-Desempeño_Financiero!G56/Desempeño_Financiero!G102,0)*12 -> 0.11202091 | G15: =IFERROR(-Desempeño_Financiero!H56/Desempeño_Financiero!H102,0)*12 -> 0.25935887 | H15: =IFERROR(-Desempeño_Financiero!I56/Desempeño_Financiero!I102,0)*12 -> 0.090119332 | J15: =IFERROR(($C15-D15)*10000,0) -> -269.22517 | K15: =IFERROR(($C15-E15)*10000,0) -> -45.611599 | L15: =IFERROR(($C15-F15)*10000,0) -> -580.84868 | M15: =IFERROR(($C15-G15)*10000,0) -> -2054.2283 | N15: =IFERROR(($C15-H15)*10000,0) -> -361.8329 | P15: =IFERROR(-Desempeño_Financiero!W56/Desempeño_Financiero!W102,0)*12 -> 0.16857064 | Q15: =IFERROR(-Desempeño_Financiero!X56/Desempeño_Financiero!X102,0)*12 -> 0.2278022 | R15: =IFERROR(-Desempeño_Financiero!Y56/Desempeño_Financiero!Y102,0)*12 -> 0.11462966 | S15: =IFERROR(-Desempeño_Financiero!Z56/Desempeño_Financiero!Z102,0)*12 -> 0.35734014 | T15: =IFERROR(-Desempeño_Financiero!AA56/Desempeño_Financiero!AA102,0)*12 -> 0.72456465 | U15: =IFERROR(-Desempeño_Financiero!AB56/Desempeño_Financiero!AB102,0)*12 -> 0.23305454 | W15: =IFERROR(($P15-Q15)*10000,0) -> -592.31558 | X15: =IFERROR(($P15-R15)*10000,0) -> 539.4098 | Y15: =IFERROR(($P15-S15)*10000,0) -> -1887.695 | Z15: =IFERROR(($P15-T15)*10000,0) -> -5559.9401 | AA15: =IFERROR(($P15-U15)*10000,0) -> -644.83907
B17: ROE
B19: ROA

Sheet Evolutivos-->

Sheet Total_Producto
D1: REAL | AZ1: PRESUPUESTO | BO1: Acumulado | BW1: Saldo Prom Acumulado
BO2: =DATE(YEAR(BO6),1,1) -> 46023 | BP2: =DATE(YEAR(BP6),1,1) -> 46023 | BQ2: =DATE(YEAR(BQ6),1,1) -> 46023 | BR2: =DATE(YEAR(BR6),1,1) -> 45658 | BS2: =DATE(YEAR(BS6),1,1) -> 45292 | BT2: =DATE(YEAR(BT6),1,1) -> 44927
C3: N° dias T.Imp | D3: =DAY(D6) -> 31 | E3: =DAY(E6) -> 28 | F3: =DAY(F6) -> 31 | G3: =DAY(G6) -> 30 | H3: =DAY(H6) -> 31 | I3: =DAY(I6) -> 30 | J3: =DAY(J6) -> 31 | K3: =DAY(K6) -> 31 | ... BK3: =DAY(BK6) -> 31 | BO3: =AVERAGEIFS($D3:$BM3,$D$6:$BM$6,">="&BO$2,$D$6:$BM$6,"<="&BO$6,$D$5:$BM$5,BO$5) -> 30 | BP3: =AVERAGEIFS($D3:$BM3,$D$6:$BM$6,">="&BP$2,$D$6:$BM$6,"<="&BP$6,$D$5:$BM$5,BP$5) -> 30 | BQ3: =AVERAGEIFS($D3:$BM3,$D$6:$BM$6,">="&BQ$2,$D$6:$BM$6,"<="&BQ$6,$D$5:$BM$5,BQ$5) -> 29.5 | BR3: =AVERAGEIFS($D3:$BM3,$D$6:$BM$6,">="&BR$2,$D$6:$BM$6,"<="&BR$6,$D$5:$BM$5,BR$5) -> 30 | BS3: =AVERAGEIFS($D3:$BM3,$D$6:$BM$6,">="&BS$2,$D$6:$BM$6,"<="&BS$6,$D$5:$BM$5,BS$5) -> 30.333333 | BT3: =AVERAGEIFS($D3:$BM3,$D$6:$BM$6,">="&BT$2,$D$6:$BM$6,"<="&BT$6,$D$5:$BM$5,BT$5) -> 30
C4: N° dias FTP | D4: =DAY(D6) -> 31 | E4: =DAY(E6) -> 28 | F4: =DAY(F6) -> 31 | G4: =DAY(G6) -> 30 | H4: =DAY(H6) -> 31 | I4: =DAY(I6) -> 30 | J4: =DAY(J6) -> 31 | K4: =DAY(K6) -> 31 | ... BK4: =DAY(BK6) -> 31 | BO4: =AVERAGEIFS($D4:$BM4,$D$6:$BM$6,">="&BO$2,$D$6:$BM$6,"<="&BO$6,$D$5:$BM$5,BO$5) -> 30 | BP4: =AVERAGEIFS($D4:$BM4,$D$6:$BM$6,">="&BP$2,$D$6:$BM$6,"<="&BP$6,$D$5:$BM$5,BP$5) -> 30 | BQ4: =AVERAGEIFS($D4:$BM4,$D$6:$BM$6,">="&BQ$2,$D$6:$BM$6,"<="&BQ$6,$D$5:$BM$5,BQ$5) -> 29.5 | BR4: =AVERAGEIFS($D4:$BM4,$D$6:$BM$6,">="&BR$2,$D$6:$BM$6,"<="&BR$6,$D$5:$BM$5,BR$5) -> 30 | BS4: =AVERAGEIFS($D4:$BM4,$D$6:$BM$6,">="&BS$2,$D$6:$BM$6,"<="&BS$6,$D$5:$BM$5,BS$5) -> 30.333333 | BT4: =AVERAGEIFS($D4:$BM4,$D$6:$BM$6,">="&BT$2,$D$6:$BM$6,"<="&BT$6,$D$5:$BM$5,BT$5) -> 30
C5: Tipo | D5: R | E5: R | F5: R | G5: R | H5: R | I5: R | J5: R | K5: R | L5: R | M5: R | N5: R | O5: R | P5: R | Q5: R | R5: R | S5: R | T5: R | U5: R | V5: R | W5: R | X5: R | Y5: R | Z5: R | AA5: R | AB5: R | AC5: R | AD5: R | AE5: R | AF5: R | AG5: R | AH5: R | AI5: R | AJ5: R | AK5: R | AL5: R | AM5: R | AN5: R | AO5: R | AP5: R | AQ5: R | AR5: R | AS5: R | AT5: R | AU5: R | AV5: R | AW5: R | AX5: R | AY5: R | AZ5: P | BA5: P | BB5: P | BC5: P | BD5: P | BE5: P | BF5: P | BG5: P | BH5: P | BI5: P | BJ5: P | BK5: P | BO5: R | BP5: P | BQ5: R | BR5: R | BS5: R | BT5: R
C6: Total Préstamos | D6: 44957 | E6: 44985 | F6: 45016 | G6: 45046 | H6: 45077 | I6: 45107 | J6: 45138 | K6: 45169 | L6: 45199 | M6: 45230 | N6: 45260 | O6: 45291 | P6: 45322 | Q6: 45351 | R6: 45382 | S6: 45412 | T6: 45443 | U6: 45473 | V6: 45504 | W6: 45535 | X6: 45565 | Y6: 45596 | Z6: 45626 | AA6: 45657 | AB6: 45688 | AC6: 45716 | AD6: 45747 | AE6: 45777 | AF6: 45808 | AG6: 45838 | AH6: 45869 | AI6: 45900 | AJ6: 45930 | AK6: 45961 | AL6: 45991 | AM6: 46022 | AN6: 46053 | AO6: 46081 | AP6: 46112 | AQ6: 46142 | AR6: 46173 | AS6: 46203 | AT6: 46234 | AU6: 46265 | AV6: 46295 | AW6: 46326 | AX6: 46356 | AY6: 46387 | AZ6: 46053 | BA6: 46081 | BB6: 46112 | BC6: 46142 | BD6: 46173 | BE6: 46203 | BF6: 46234 | BG6: 46265 | BH6: 46295 | BI6: 46326 | BJ6: 46356 | BK6: 46387 | BO6: =Desempeño_Financiero!$B$1 -> 46112 | BP6: =BO6 -> 46112 | BQ6: =EOMONTH(BO6,-1) -> 46081 | BR6: =EOMONTH(BO6,-12) -> 45747 | BS6: =EOMONTH(BO6,-24) -> 45382 | BT6: =EOMONTH(BO6,-36) -> 45016 | BW6: =BO6 -> 46112 | BX6: =BP6 -> 46112 | BY6: =BQ6 -> 46081 | BZ6: =BR6 -> 45747 | CA6: =BS6 -> 45382 | CB6: =BT6 -> 45016
A8: SALDO_FDP | C8: Vigente | D8: =Renta_Alta!D8+Masivo!D8+Consumo_Inicial!D8 -> 3209375.3 | E8: =Renta_Alta!E8+Masivo!E8+Consumo_Inicial!E8 -> 3300088.8 | F8: =Renta_Alta!F8+Masivo!F8+Consumo_Inicial!F8 -> 3421266.2 | G8: =Renta_Alta!G8+Masivo!G8+Consumo_Inicial!G8 -> 3499038.9 | H8: =Renta_Alta!H8+Masivo!H8+Consumo_Inicial!H8 -> 3573142.6 | I8: =Renta_Alta!I8+Masivo!I8+Consumo_Inicial!I8 -> 3630227.9 | J8: =Renta_Alta!J8+Masivo!J8+Consumo_Inicial!J8 -> 3660638.8 | K8: =Renta_Alta!K8+Masivo!K8+Consumo_Inicial!K8 -> 3748310.6 | ... BK8: =Renta_Alta!BK8+Masivo!BK8+Consumo_Inicial!BK8 -> 3478386.4 | BO8: =_xlfn.XLOOKUP(BO$6,$D$6:$BM$6,$D8:$BM8,,0,1) -> 3199553.1 | BP8: =_xlfn.XLOOKUP(BP$6,$D$6:$BM$6,$D8:$BM8,,0,-1) -> 3121000.5 | BQ8: =_xlfn.XLOOKUP(BQ$6,$D$6:$BM$6,$D8:$BM8,,0,1) -> 3154129 | BR8: =_xlfn.XLOOKUP(BR$6,$D$6:$BM$6,$D8:$BM8,,0,1) -> 2864120.5 | BS8: =_xlfn.XLOOKUP(BS$6,$D$6:$BM$6,$D8:$BM8,,0,1) -> 3428790.2 | BT8: =_xlfn.XLOOKUP(BT$6,$D$6:$BM$6,$D8:$BM8,,0,1) -> 3421266.2
A9: SALDO_FDP | C9: Refinanciado | D9: =Renta_Alta!D9+Masivo!D9+Consumo_Inicial!D9 -> 12463.798 | E9: =Renta_Alta!E9+Masivo!E9+Consumo_Inicial!E9 -> 12950.203 | F9: =Renta_Alta!F9+Masivo!F9+Consumo_Inicial!F9 -> 12918.972 | G9: =Renta_Alta!G9+Masivo!G9+Consumo_Inicial!G9 -> 11884.581 | H9: =Renta_Alta!H9+Masivo!H9+Consumo_Inicial!H9 -> 11239.857 | I9: =Renta_Alta!I9+Masivo!I9+Consumo_Inicial!I9 -> 10375.034 | J9: =Renta_Alta!J9+Masivo!J9+Consumo_Inicial!J9 -> 9473.513 | K9: =Renta_Alta!K9+Masivo!K9+Consumo_Inicial!K9 -> 8668.61 | ... BK9: =Renta_Alta!BK9+Masivo!BK9+Consumo_Inicial!BK9 -> 24436.883 | BO9: =_xlfn.XLOOKUP(BO$6,$D$6:$BM$6,$D9:$BM9,,0,1) -> 36825.6 | BP9: =_xlfn.XLOOKUP(BP$6,$D$6:$BM$6,$D9:$BM9,,0,-1) -> 32170.33 | BQ9: =_xlfn.XLOOKUP(BQ$6,$D$6:$BM$6,$D9:$BM9,,0,1) -> 37846.73 | BR9: =_xlfn.XLOOKUP(BR$6,$D$6:$BM$6,$D9:$BM9,,0,1) -> 47040.751 | BS9: =_xlfn.XLOOKUP(BS$6,$D$6:$BM$6,$D9:$BM9,,0,1) -> 8619.8673 | BT9: =_xlfn.XLOOKUP(BT$6,$D$6:$BM$6,$D9:$BM9,,0,1) -> 12918.972
A10: SALDO_FDP | C10: Vencido y Judicial | D10: =Renta_Alta!D10+Masivo!D10+Consumo_Inicial!D10 -> 75075.645 | E10: =Renta_Alta!E10+Masivo!E10+Consumo_Inicial!E10 -> 72983.439 | F10: =Renta_Alta!F10+Masivo!F10+Consumo_Inicial!F10 -> 66041.883 | G10: =Renta_Alta!G10+Masivo!G10+Consumo_Inicial!G10 -> 60991.925 | H10: =Renta_Alta!H10+Masivo!H10+Consumo_Inicial!H10 -> 57791.376 | I10: =Renta_Alta!I10+Masivo!I10+Consumo_Inicial!I10 -> 64002.308 | J10: =Renta_Alta!J10+Masivo!J10+Consumo_Inicial!J10 -> 88094.936 | K10: =Renta_Alta!K10+Masivo!K10+Consumo_Inicial!K10 -> 128190.78 | ... BK10: =Renta_Alta!BK10+Masivo!BK10+Consumo_Inicial!BK10 -> 94244.001 | BO10: =_xlfn.XLOOKUP(BO$6,$D$6:$BM$6,$D10:$BM10,,0,1) -> 84810.02 | BP10: =_xlfn.XLOOKUP(BP$6,$D$6:$BM$6,$D10:$BM10,,0,-1) -> 92303.295 | BQ10: =_xlfn.XLOOKUP(BQ$6,$D$6:$BM$6,$D10:$BM10,,0,1) -> 88358.85 | BR10: =_xlfn.XLOOKUP(BR$6,$D$6:$BM$6,$D10:$BM10,,0,1) -> 109573.14 | BS10: =_xlfn.XLOOKUP(BS$6,$D$6:$BM$6,$D10:$BM10,,0,1) -> 171673.77 | BT10: =_xlfn.XLOOKUP(BT$6,$D$6:$BM$6,$D10:$BM10,,0,1) -> 66041.883
C11: Saldo FdP | D11: =SUM(D8:D10) -> 3296914.8 | E11: =SUM(E8:E10) -> 3386022.5 | F11: =SUM(F8:F10) -> 3500227.1 | G11: =SUM(G8:G10) -> 3571915.4 | H11: =SUM(H8:H10) -> 3642173.9 | I11: =SUM(I8:I10) -> 3704605.2 | J11: =SUM(J8:J10) -> 3758207.2 | K11: =SUM(K8:K10) -> 3885170 | ... BK11: =SUM(BK8:BK10) -> 3597067.3 | BO11: =SUM(BO8:BO10) -> 3321188.7 | BP11: =SUM(BP8:BP10) -> 3245474.1 | BQ11: =SUM(BQ8:BQ10) -> 3280334.6 | BR11: =SUM(BR8:BR10) -> 3020734.4 | BS11: =SUM(BS8:BS10) -> 3609083.8 | BT11: =SUM(BT8:BT10) -> 3500227.1
A14: SALDO_PROM | C14: Vigente | D14: =Renta_Alta!D14+Masivo!D14+Consumo_Inicial!D14 -> 3158143.9 | E14: =Renta_Alta!E14+Masivo!E14+Consumo_Inicial!E14 -> 3223471.9 | F14: =Renta_Alta!F14+Masivo!F14+Consumo_Inicial!F14 -> 3343878.5 | G14: =Renta_Alta!G14+Masivo!G14+Consumo_Inicial!G14 -> 3446583.5 | H14: =Renta_Alta!H14+Masivo!H14+Consumo_Inicial!H14 -> 3525126.4 | I14: =Renta_Alta!I14+Masivo!I14+Consumo_Inicial!I14 -> 3573798.3 | J14: =Renta_Alta!J14+Masivo!J14+Consumo_Inicial!J14 -> 3616394 | K14: =Renta_Alta!K14+Masivo!K14+Consumo_Inicial!K14 -> 3651568.9 | ... BK14: =Renta_Alta!BK14+Masivo!BK14+Consumo_Inicial!BK14 -> 3447409.6 | BO14: =IFERROR(AVERAGEIFS($D14:$BM14,$D$6:$BM$6,">="&BO$2,$D$6:$BM$6,"<="&BO$6,$D$5:$BM$5,BO$5,$D14:$BM14,"<>0"),0) -> 3101496 | BP14: =IFERROR(AVERAGEIFS($D14:$BM14,$D$6:$BM$6,">="&BP$2,$D$6:$BM$6,"<="&BP$6,$D$5:$BM$5,BP$5,$D14:$BM14,"<>0"),0) -> 3059754.3 | BQ14: =IFERROR(AVERAGEIFS($D14:$BM14,$D$6:$BM$6,">="&BQ$2,$D$6:$BM$6,"<="&BQ$6,$D$5:$BM$5,BQ$5,$D14:$BM14,"<>0"),0) -> 3069509.7 | BR14: =IFERROR(AVERAGEIFS($D14:$BM14,$D$6:$BM$6,">="&BR$2,$D$6:$BM$6,"<="&BR$6,$D$5:$BM$5,BR$5,$D14:$BM14,"<>0"),0) -> 2830433.6 | BS14: =IFERROR(AVERAGEIFS($D14:$BM14,$D$6:$BM$6,">="&BS$2,$D$6:$BM$6,"<="&BS$6,$D$5:$BM$5,BS$5,$D14:$BM14,"<>0"),0) -> 3524089.4 | BT14: =IFERROR(AVERAGEIFS($D14:$BM14,$D$6:$BM$6,">="&BT$2,$D$6:$BM$6,"<="&BT$6,$D$5:$BM$5,BT$5,$D14:$BM14,"<>0"),0) -> 3241831.4 | BW14: =SUMIFS($D14:$BM14,$D$6:$BM$6,">="&BO$2,$D$6:$BM$6,"<="&BO$6,$D$5:$BM$5,BO$5) -> 9304488 | BX14: =SUMIFS($D14:$BM14,$D$6:$BM$6,">="&BP$2,$D$6:$BM$6,"<="&BP$6,$D$5:$BM$5,BP$5) -> 9179262.9 | BY14: =SUMIFS($D14:$BM14,$D$6:$BM$6,">="&BQ$2,$D$6:$BM$6,"<="&BQ$6,$D$5:$BM$5,BQ$5) -> 6139019.5 | BZ14: =SUMIFS($D14:$BM14,$D$6:$BM$6,">="&BR$2,$D$6:$BM$6,"<="&BR$6,$D$5:$BM$5,BR$5) -> 8491300.7 | CA14: =SUMIFS($D14:$BM14,$D$6:$BM$6,">="&BS$2,$D$6:$BM$6,"<="&BS$6,$D$5:$BM$5,BS$5) -> 10572268 | CB14: =SUMIFS($D14:$BM14,$D$6:$BM$6,">="&BT$2,$D$6:$BM$6,"<="&BT$6,$D$5:$BM$5,BT$5) -> 9725494.3
