Workbook

Sheet Parametros
B2: Producto | C2: Convenios
B4: Año | C4: 2026
B6: Lista Fechas | C6: =EOMONTH(DATE($C$4,1,1),0) -> 46053 | E6: Segmentos | F6: Renta_Alta
C7: =EOMONTH(C6,1) -> 46081 | F7: Masivo
C8: =EOMONTH(C7,1) -> 46112 | F8: Consumo_Inicial
C9: =EOMONTH(C8,1) -> 46142 | F9: Total_Producto
C10: =EOMONTH(C9,1) -> 46173
C11: =EOMONTH(C10,1) -> 46203
C12: =EOMONTH(C11,1) -> 46234
C13: =EOMONTH(C12,1) -> 46265
C14: =EOMONTH(C13,1) -> 46295
C15: =EOMONTH(C14,1) -> 46326
C16: =EOMONTH(C15,1) -> 46356
C17: =EOMONTH(C16,1) -> 46387

Sheet Indicadores
C1: Mensual | P1: Acumulado
J2: Variación % | W2: Variación %
B3: =Desempeño_Financiero!C6 -> Total_Producto | C3: =Desempeño_Financiero!D6 -> 46173 | D3: =Desempeño_Financiero!E6 -> 46173 | E3: =Desempeño_Financiero!F6 -> 46142 | F3: =Desempeño_Financiero!G6 -> 45808 | G3: =Desempeño_Financiero!H6 -> 45443 | H3: =Desempeño_Financiero!I6 -> 45077 | J3: =D3 -> 46173 | K3: =E3 -> 46142 | L3: =F3 -> 45808 | M3: =G3 -> 45443 | N3: =H3 -> 45077 | P3: =C3 -> 46173 | Q3: =D3 -> 46173 | R3: =E3 -> 46142 | S3: =F3 -> 45808 | T3: =G3 -> 45443 | U3: =H3 -> 45077 | W3: =Q3 -> 46173 | X3: =R3 -> 46142 | Y3: =S3 -> 45808 | Z3: =T3 -> 45443 | AA3: =U3 -> 45077
B5: Eficiencia | C5: =IFERROR((-Desempeño_Financiero!D214)/(Desempeño_Financiero!D176+Desempeño_Financiero!D195),0) -> 0 | D5: =IFERROR((-Desempeño_Financiero!E214)/(Desempeño_Financiero!E176+Desempeño_Financiero!E195),0) -> 3.8423302 | E5: =IFERROR((-Desempeño_Financiero!F214)/(Desempeño_Financiero!F176+Desempeño_Financiero!F195),0) -> 0 | F5: =IFERROR((-Desempeño_Financiero!G214)/(Desempeño_Financiero!G176+Desempeño_Financiero!G195),0) -> 0 | G5: =IFERROR((-Desempeño_Financiero!H214)/(Desempeño_Financiero!H176+Desempeño_Financiero!H195),0) -> 0 | H5: =IFERROR((-Desempeño_Financiero!I214)/(Desempeño_Financiero!I176+Desempeño_Financiero!I195),0) -> 0 | J5: =IFERROR(($C5-D5)*10000,0) -> -38423.302 | K5: =IFERROR(($C5-E5)*10000,0) -> 0 | L5: =IFERROR(($C5-F5)*10000,0) -> 0 | M5: =IFERROR(($C5-G5)*10000,0) -> 0 | N5: =IFERROR(($C5-H5)*10000,0) -> 0 | P5: =IFERROR((-Desempeño_Financiero!W214)/(Desempeño_Financiero!W176+Desempeño_Financiero!W195),0) -> 0 | Q5: =IFERROR((-Desempeño_Financiero!X214)/(Desempeño_Financiero!X176+Desempeño_Financiero!X195),0) -> 3.9536841 | R5: =IFERROR((-Desempeño_Financiero!Y214)/(Desempeño_Financiero!Y176+Desempeño_Financiero!Y195),0) -> 0 | S5: =IFERROR((-Desempeño_Financiero!Z214)/(Desempeño_Financiero!Z176+Desempeño_Financiero!Z195),0) -> 0 | T5: =IFERROR((-Desempeño_Financiero!AA214)/(Desempeño_Financiero!AA176+Desempeño_Financiero!AA195),0) -> 0 | U5: =IFERROR((-Desempeño_Financiero!AB214)/(Desempeño_Financiero!AB176+Desempeño_Financiero!AB195),0) -> 0 | W5: =IFERROR(($P5-Q5)*10000,0) -> -39536.841 | X5: =IFERROR(($P5-R5)*10000,0) -> 0 | Y5: =IFERROR(($P5-S5)*10000,0) -> 0 | Z5: =IFERROR(($P5-T5)*10000,0) -> 0 | AA5: =IFERROR(($P5-U5)*10000,0) -> 0
B7: Rendimiento de Colocaciones | C7: =Desempeño_Financiero!D100 -> 0 | D7: =Desempeño_Financiero!E100 -> 0.042497138 | E7: =Desempeño_Financiero!F100 -> 0 | F7: =Desempeño_Financiero!G100 -> 0 | G7: =Desempeño_Financiero!H100 -> 0 | H7: =Desempeño_Financiero!I100 -> 0 | J7: =IFERROR(($C7-D7)*10000,0) -> -424.97138 | K7: =IFERROR(($C7-E7)*10000,0) -> 0 | L7: =IFERROR(($C7-F7)*10000,0) -> 0 | M7: =IFERROR(($C7-G7)*10000,0) -> 0 | N7: =IFERROR(($C7-H7)*10000,0) -> 0 | P7: =Desempeño_Financiero!W100 -> 0 | Q7: =Desempeño_Financiero!X100 -> 0.04252755 | R7: =Desempeño_Financiero!Y100 -> 0 | S7: =Desempeño_Financiero!Z100 -> 0 | T7: =Desempeño_Financiero!AA100 -> 0 | U7: =Desempeño_Financiero!AB100 -> 0 | W7: =IFERROR(($P7-Q7)*10000,0) -> -425.2755 | X7: =IFERROR(($P7-R7)*10000,0) -> 0 | Y7: =IFERROR(($P7-S7)*10000,0) -> 0 | Z7: =IFERROR(($P7-T7)*10000,0) -> 0 | AA7: =IFERROR(($P7-U7)*10000,0) -> 0
B9: INOF / Ingresos Totales | C9: =IFERROR((Desempeño_Financiero!D195)/(Desempeño_Financiero!D119+Desempeño_Financiero!D195),0) -> 0 | D9: =IFERROR((Desempeño_Financiero!E195)/(Desempeño_Financiero!E119+Desempeño_Financiero!E195),0) -> -0.21797554 | E9: =IFERROR((Desempeño_Financiero!F195)/(Desempeño_Financiero!F119+Desempeño_Financiero!F195),0) -> 0 | F9: =IFERROR((Desempeño_Financiero!G195)/(Desempeño_Financiero!G119+Desempeño_Financiero!G195),0) -> 0 | G9: =IFERROR((Desempeño_Financiero!H195)/(Desempeño_Financiero!H119+Desempeño_Financiero!H195),0) -> 0 | H9: =IFERROR((Desempeño_Financiero!I195)/(Desempeño_Financiero!I119+Desempeño_Financiero!I195),0) -> 0 | J9: =IFERROR(($C9-D9)*10000,0) -> 2179.7554 | K9: =IFERROR(($C9-E9)*10000,0) -> 0 | L9: =IFERROR(($C9-F9)*10000,0) -> 0 | M9: =IFERROR(($C9-G9)*10000,0) -> 0 | N9: =IFERROR(($C9-H9)*10000,0) -> 0 | P9: =IFERROR((Desempeño_Financiero!W195)/(Desempeño_Financiero!W119+Desempeño_Financiero!W195),0) -> 0 | Q9: =IFERROR((Desempeño_Financiero!X195)/(Desempeño_Financiero!X119+Desempeño_Financiero!X195),0) -> -0.26479328 | R9: =IFERROR((Desempeño_Financiero!Y195)/(Desempeño_Financiero!Y119+Desempeño_Financiero!Y195),0) -> 0 | S9: =IFERROR((Desempeño_Financiero!Z195)/(Desempeño_Financiero!Z119+Desempeño_Financiero!Z195),0) -> 0 | T9: =IFERROR((Desempeño_Financiero!AA195)/(Desempeño_Financiero!AA119+Desempeño_Financiero!AA195),0) -> 0 | U9: =IFERROR((Desempeño_Financiero!AB195)/(Desempeño_Financiero!AB119+Desempeño_Financiero!AB195),0) -> 0 | W9: =IFERROR(($P9-Q9)*10000,0) -> 2647.9328 | X9: =IFERROR(($P9-R9)*10000,0) -> 0 | Y9: =IFERROR(($P9-S9)*10000,0) -> 0 | Z9: =IFERROR(($P9-T9)*10000,0) -> 0 | AA9: =IFERROR(($P9-U9)*10000,0) -> 0
B11: INOF / Gasto Operativo | C11: =IFERROR((Desempeño_Financiero!D195/Desempeño_Financiero!D214),0) -> 0 | D11: =IFERROR((Desempeño_Financiero!E195/Desempeño_Financiero!E214),0) -> 0.068773845 | E11: =IFERROR((Desempeño_Financiero!F195/Desempeño_Financiero!F214),0) -> 0 | F11: =IFERROR((Desempeño_Financiero!G195/Desempeño_Financiero!G214),0) -> 0 | G11: =IFERROR((Desempeño_Financiero!H195/Desempeño_Financiero!H214),0) -> 0 | H11: =IFERROR((Desempeño_Financiero!I195/Desempeño_Financiero!I214),0) -> 0 | J11: =IFERROR(($C11-D11)*10000,0) -> -687.73845 | K11: =IFERROR(($C11-E11)*10000,0) -> 0 | L11: =IFERROR(($C11-F11)*10000,0) -> 0 | M11: =IFERROR(($C11-G11)*10000,0) -> 0 | N11: =IFERROR(($C11-H11)*10000,0) -> 0 | P11: =IFERROR((Desempeño_Financiero!W195/Desempeño_Financiero!W214),0) -> 0 | Q11: =IFERROR((Desempeño_Financiero!X195/Desempeño_Financiero!X214),0) -> 0.082357865 | R11: =IFERROR((Desempeño_Financiero!Y195/Desempeño_Financiero!Y214),0) -> 0 | S11: =IFERROR((Desempeño_Financiero!Z195/Desempeño_Financiero!Z214),0) -> 0 | T11: =IFERROR((Desempeño_Financiero!AA195/Desempeño_Financiero!AA214),0) -> 0 | U11: =IFERROR((Desempeño_Financiero!AB195/Desempeño_Financiero!AB214),0) -> 0 | W11: =IFERROR(($P11-Q11)*10000,0) -> -823.57865 | X11: =IFERROR(($P11-R11)*10000,0) -> 0 | Y11: =IFERROR(($P11-S11)*10000,0) -> 0 | Z11: =IFERROR(($P11-T11)*10000,0) -> 0 | AA11: =IFERROR(($P11-U11)*10000,0) -> 0
B13: Gasto Operativo / Activo | C13: =IFERROR(-Desempeño_Financiero!D214/Desempeño_Financiero!D43*12,0) -> 0 | D13: =IFERROR(-Desempeño_Financiero!E214/Desempeño_Financiero!E43*12,0) -> 0.11211293 | E13: =IFERROR(-Desempeño_Financiero!F214/Desempeño_Financiero!F43*12,0) -> 0 | F13: =IFERROR(-Desempeño_Financiero!G214/Desempeño_Financiero!G43*12,0) -> 0 | G13: =IFERROR(-Desempeño_Financiero!H214/Desempeño_Financiero!H43*12,0) -> 0 | H13: =IFERROR(-Desempeño_Financiero!I214/Desempeño_Financiero!I43*12,0) -> 0 | J13: =IFERROR(($C13-D13)*10000,0) -> -1121.1293 | K13: =IFERROR(($C13-E13)*10000,0) -> 0 | L13: =IFERROR(($C13-F13)*10000,0) -> 0 | M13: =IFERROR(($C13-G13)*10000,0) -> 0 | N13: =IFERROR(($C13-H13)*10000,0) -> 0 | P13: =IFERROR(-Desempeño_Financiero!W214/Desempeño_Financiero!W43*12,0) -> 0 | Q13: =IFERROR(-Desempeño_Financiero!X214/Desempeño_Financiero!X43*12,0) -> 0.53381666 | R13: =IFERROR(-Desempeño_Financiero!Y214/Desempeño_Financiero!Y43*12,0) -> 0 | S13: =IFERROR(-Desempeño_Financiero!Z214/Desempeño_Financiero!Z43*12,0) -> 0 | T13: =IFERROR(-Desempeño_Financiero!AA214/Desempeño_Financiero!AA43*12,0) -> 0 | U13: =IFERROR(-Desempeño_Financiero!AB214/Desempeño_Financiero!AB43*12,0) -> 0 | W13: =IFERROR(($P13-Q13)*10000,0) -> -5338.1666 | X13: =IFERROR(($P13-R13)*10000,0) -> 0 | Y13: =IFERROR(($P13-S13)*10000,0) -> 0 | Z13: =IFERROR(($P13-T13)*10000,0) -> 0 | AA13: =IFERROR(($P13-U13)*10000,0) -> 0
B15: ROE
B17: ROA

Sheet Desempeño_Financiero
B1: 46173 | D1: Mensual | W1: Acumulado
B2: Desempeño Financiero
B3: En S/. Miles | C3: N° dias T.Imp | D3: =DAY(D6) -> 31 | E3: =DAY(E6) -> 31 | F3: =DAY(F6) -> 30 | G3: =DAY(G6) -> 31 | H3: =DAY(H6) -> 31 | I3: =DAY(I6) -> 31
C4: N° dias FTP | D4: =DAY(D6) -> 31 | E4: =DAY(E6) -> 31 | F4: =DAY(F6) -> 30 | G4: =DAY(G6) -> 31 | H4: =DAY(H6) -> 31 | I4: =DAY(I6) -> 31
C5: Tipo | D5: R | E5: P | F5: R | G5: R | H5: R | I5: R | K5: Variación S/. | Q5: Variación % | AD5: Variación S/. | AJ5: Variación %
C6: Total_Producto | D6: =$B$1 -> 46173 | E6: =D6 -> 46173 | F6: =EOMONTH(D6,-1) -> 46142 | G6: =EOMONTH(D6,-12) -> 45808 | H6: =EOMONTH(D6,-24) -> 45443 | I6: =EOMONTH(D6,-36) -> 45077 | K6: =E6 -> 46173 | L6: =F6 -> 46142 | M6: =G6 -> 45808 | N6: =H6 -> 45443 | O6: =I6 -> 45077 | Q6: =K6 -> 46173 | R6: =L6 -> 46142 | S6: =M6 -> 45808 | T6: =N6 -> 45443 | U6: =O6 -> 45077 | W6: =$B$1 -> 46173 | X6: =W6 -> 46173 | Y6: =EOMONTH(W6,-1) -> 46142 | Z6: =EOMONTH(W6,-12) -> 45808 | AA6: =EOMONTH(W6,-24) -> 45443 | AB6: =EOMONTH(W6,-36) -> 45077 | AD6: =X6 -> 46173 | AE6: =Y6 -> 46142 | AF6: =Z6 -> 45808 | AG6: =AA6 -> 45443 | AH6: =AB6 -> 45077 | AJ6: =AD6 -> 46173 | AK6: =AE6 -> 46142 | AL6: =AF6 -> 45808 | AM6: =AG6 -> 45443 | AN6: =AH6 -> 45077
A8: SALDO_FDP | C8: Cuenta Sueldo | D8: {=_xlfn.XLOOKUP(1, (INDIRECT("'"&$C$6&"'!$6:$6")=D$6)* (INDIRECT("'"&$C$6&"'!$5:$5")=D$5), INDIRECT("'"&$C$6&"'!"&ROW()&":"&ROW()) )} -> 0 | E8: {=_xlfn.XLOOKUP(1, (INDIRECT("'"&$C$6&"'!$6:$6")=E$6)* (INDIRECT("'"&$C$6&"'!$5:$5")=E$5), INDIRECT("'"&$C$6&"'!"&ROW()&":"&ROW()) )} -> 1963709.7 | F8: {=_xlfn.XLOOKUP(1, (INDIRECT("'"&$C$6&"'!$6:$6")=F$6)* (INDIRECT("'"&$C$6&"'!$5:$5")=F$5), INDIRECT("'"&$C$6&"'!"&ROW()&":"&ROW()) )} -> 0 | G8: {=_xlfn.XLOOKUP(1, (INDIRECT("'"&$C$6&"'!$6:$6")=G$6)* (INDIRECT("'"&$C$6&"'!$5:$5")=G$5), INDIRECT("'"&$C$6&"'!"&ROW()&":"&ROW()) )} -> 0 | H8: {=_xlfn.XLOOKUP(1, (INDIRECT("'"&$C$6&"'!$6:$6")=H$6)* (INDIRECT("'"&$C$6&"'!$5:$5")=H$5), INDIRECT("'"&$C$6&"'!"&ROW()&":"&ROW()) )} -> 0 | I8: {=_xlfn.XLOOKUP(1, (INDIRECT("'"&$C$6&"'!$6:$6")=I$6)* (INDIRECT("'"&$C$6&"'!$5:$5")=I$5), INDIRECT("'"&$C$6&"'!"&ROW()&":"&ROW()) )} -> 0 | K8: =$D8-E8 -> -1963709.7 | L8: =$D8-F8 -> 0 | M8: =$D8-G8 -> 0 | N8: =$D8-H8 -> 0 | O8: =$D8-I8 -> 0 | Q8: =IFERROR($D8/E8-1,0) -> -1 | R8: =IFERROR($D8/F8-1,0) -> 0 | S8: =IFERROR($D8/G8-1,0) -> 0 | T8: =IFERROR($D8/H8-1,0) -> 0 | U8: =IFERROR($D8/I8-1,0) -> 0 | W8: {=INDIRECT("'"&$C$6&"'!"&ADDRESS(ROW(),COLUMN()+44))} -> 0 | X8: {=INDIRECT("'"&$C$6&"'!"&ADDRESS(ROW(),COLUMN()+44))} -> 1963709.7 | Y8: {=INDIRECT("'"&$C$6&"'!"&ADDRESS(ROW(),COLUMN()+44))} -> 0 | Z8: {=INDIRECT("'"&$C$6&"'!"&ADDRESS(ROW(),COLUMN()+44))} -> 0 | AA8: {=INDIRECT("'"&$C$6&"'!"&ADDRESS(ROW(),COLUMN()+44))} -> 0 | AB8: {=INDIRECT("'"&$C$6&"'!"&ADDRESS(ROW(),COLUMN()+44))} -> 0 | AD8: =$W8-X8 -> -1963709.7 | AE8: =$W8-Y8 -> 0 | AF8: =$W8-Z8 -> 0 | AG8: =$W8-AA8 -> 0 | AH8: =$W8-AB8 -> 0 | AJ8: =IFERROR($W8/X8-1,0) -> -1 | AK8: =IFERROR($W8/Y8-1,0) -> 0 | AL8: =IFERROR($W8/Z8-1,0) -> 0 | AM8: =IFERROR($W8/AA8-1,0) -> 0 | AN8: =IFERROR($W8/AB8-1,0) -> 0
A9: SALDO_FDP | D9: {=_xlfn.XLOOKUP(1, (INDIRECT("'"&$C$6&"'!$6:$6")=D$6)* (INDIRECT("'"&$C$6&"'!$5:$5")=D$5), INDIRECT("'"&$C$6&"'!"&ROW()&":"&ROW()) )} -> 0 | E9: {=_xlfn.XLOOKUP(1, (INDIRECT("'"&$C$6&"'!$6:$6")=E$6)* (INDIRECT("'"&$C$6&"'!$5:$5")=E$5), INDIRECT("'"&$C$6&"'!"&ROW()&":"&ROW()) )} -> 0 | F9: {=_xlfn.XLOOKUP(1, (INDIRECT("'"&$C$6&"'!$6:$6")=F$6)* (INDIRECT("'"&$C$6&"'!$5:$5")=F$5), INDIRECT("'"&$C$6&"'!"&ROW()&":"&ROW()) )} -> 0 | G9: {=_xlfn.XLOOKUP(1, (INDIRECT("'"&$C$6&"'!$6:$6")=G$6)* (INDIRECT("'"&$C$6&"'!$5:$5")=G$5), INDIRECT("'"&$C$6&"'!"&ROW()&":"&ROW()) )} -> 0 | H9: {=_xlfn.XLOOKUP(1, (INDIRECT("'"&$C$6&"'!$6:$6")=H$6)* (INDIRECT("'"&$C$6&"'!$5:$5")=H$5), INDIRECT("'"&$C$6&"'!"&ROW()&":"&ROW()) )} -> 0 | I9: {=_xlfn.XLOOKUP(1, (INDIRECT("'"&$C$6&"'!$6:$6")=I$6)* (INDIRECT("'"&$C$6&"'!$5:$5")=I$5), INDIRECT("'"&$C$6&"'!"&ROW()&":"&ROW()) )} -> 0 | K9: =$D9-E9 -> 0 | L9: =$D9-F9 -> 0 | M9: =$D9-G9 -> 0 | N9: =$D9-H9 -> 0 | O9: =$D9-I9 -> 0 | Q9: =IFERROR($D9/E9-1,0) -> 0 | R9: =IFERROR($D9/F9-1,0) -> 0 | S9: =IFERROR($D9/G9-1,0) -> 0 | T9: =IFERROR($D9/H9-1,0) -> 0 | U9: =IFERROR($D9/I9-1,0) -> 0 | W9: {=INDIRECT("'"&$C$6&"'!"&ADDRESS(ROW(),COLUMN()+44))} -> 0 | X9: {=INDIRECT("'"&$C$6&"'!"&ADDRESS(ROW(),COLUMN()+44))} -> 0 | Y9: {=INDIRECT("'"&$C$6&"'!"&ADDRESS(ROW(),COLUMN()+44))} -> 0 | Z9: {=INDIRECT("'"&$C$6&"'!"&ADDRESS(ROW(),COLUMN()+44))} -> 0 | AA9: {=INDIRECT("'"&$C$6&"'!"&ADDRESS(ROW(),COLUMN()+44))} -> 0 | AB9: {=INDIRECT("'"&$C$6&"'!"&ADDRESS(ROW(),COLUMN()+44))} -> 0 | AD9: =$W9-X9 -> 0 | AE9: =$W9-Y9 -> 0 | AF9: =$W9-Z9 -> 0 | AG9: =$W9-AA9 -> 0 | AH9: =$W9-AB9 -> 0 | AJ9: =IFERROR($W9/X9-1,0) -> 0 | AK9: =IFERROR($W9/Y9-1,0) -> 0 | AL9: =IFERROR($W9/Z9-1,0) -> 0 | AM9: =IFERROR($W9/AA9-1,0) -> 0 | AN9: =IFERROR($W9/AB9-1,0) -> 0
A10: SALDO_FDP | D10: {=_xlfn.XLOOKUP(1, (INDIRECT("'"&$C$6&"'!$6:$6")=D$6)* (INDIRECT("'"&$C$6&"'!$5:$5")=D$5), INDIRECT("'"&$C$6&"'!"&ROW()&":"&ROW()) )} -> 0 | E10: {=_xlfn.XLOOKUP(1, (INDIRECT("'"&$C$6&"'!$6:$6")=E$6)* (INDIRECT("'"&$C$6&"'!$5:$5")=E$5), INDIRECT("'"&$C$6&"'!"&ROW()&":"&ROW()) )} -> 0 | F10: {=_xlfn.XLOOKUP(1, (INDIRECT("'"&$C$6&"'!$6:$6")=F$6)* (INDIRECT("'"&$C$6&"'!$5:$5")=F$5), INDIRECT("'"&$C$6&"'!"&ROW()&":"&ROW()) )} -> 0 | G10: {=_xlfn.XLOOKUP(1, (INDIRECT("'"&$C$6&"'!$6:$6")=G$6)* (INDIRECT("'"&$C$6&"'!$5:$5")=G$5), INDIRECT("'"&$C$6&"'!"&ROW()&":"&ROW()) )} -> 0 | H10: {=_xlfn.XLOOKUP(1, (INDIRECT("'"&$C$6&"'!$6:$6")=H$6)* (INDIRECT("'"&$C$6&"'!$5:$5")=H$5), INDIRECT("'"&$C$6&"'!"&ROW()&":"&ROW()) )} -> 0 | I10: {=_xlfn.XLOOKUP(1, (INDIRECT("'"&$C$6&"'!$6:$6")=I$6)* (INDIRECT("'"&$C$6&"'!$5:$5")=I$5), INDIRECT("'"&$C$6&"'!"&ROW()&":"&ROW()) )} -> 0 | K10: =$D10-E10 -> 0 | L10: =$D10-F10 -> 0 | M10: =$D10-G10 -> 0 | N10: =$D10-H10 -> 0 | O10: =$D10-I10 -> 0 | Q10: =IFERROR($D10/E10-1,0) -> 0 | R10: =IFERROR($D10/F10-1,0) -> 0 | S10: =IFERROR($D10/G10-1,0) -> 0 | T10: =IFERROR($D10/H10-1,0) -> 0 | U10: =IFERROR($D10/I10-1,0) -> 0 | W10: {=INDIRECT("'"&$C$6&"'!"&ADDRESS(ROW(),COLUMN()+44))} -> 0 | X10: {=INDIRECT("'"&$C$6&"'!"&ADDRESS(ROW(),COLUMN()+44))} -> 0 | Y10: {=INDIRECT("'"&$C$6&"'!"&ADDRESS(ROW(),COLUMN()+44))} -> 0 | Z10: {=INDIRECT("'"&$C$6&"'!"&ADDRESS(ROW(),COLUMN()+44))} -> 0 | AA10: {=INDIRECT("'"&$C$6&"'!"&ADDRESS(ROW(),COLUMN()+44))} -> 0 | AB10: {=INDIRECT("'"&$C$6&"'!"&ADDRESS(ROW(),COLUMN()+44))} -> 0 | AD10: =$W10-X10 -> 0 | AE10: =$W10-Y10 -> 0 | AF10: =$W10-Z10 -> 0 | AG10: =$W10-AA10 -> 0 | AH10: =$W10-AB10 -> 0 | AJ10: =IFERROR($W10/X10-1,0) -> 0 | AK10: =IFERROR($W10/Y10-1,0) -> 0 | AL10: =IFERROR($W10/Z10-1,0) -> 0 | AM10: =IFERROR($W10/AA10-1,0) -> 0 | AN10: =IFERROR($W10/AB10-1,0) -> 0
A11: SALDO_FDP | D11: {=_xlfn.XLOOKUP(1, (INDIRECT("'"&$C$6&"'!$6:$6")=D$6)* (INDIRECT("'"&$C$6&"'!$5:$5")=D$5), INDIRECT("'"&$C$6&"'!"&ROW()&":"&ROW()) )} -> 0 | E11: {=_xlfn.XLOOKUP(1, (INDIRECT("'"&$C$6&"'!$6:$6")=E$6)* (INDIRECT("'"&$C$6&"'!$5:$5")=E$5), INDIRECT("'"&$C$6&"'!"&ROW()&":"&ROW()) )} -> 0 | F11: {=_xlfn.XLOOKUP(1, (INDIRECT("'"&$C$6&"'!$6:$6")=F$6)* (INDIRECT("'"&$C$6&"'!$5:$5")=F$5), INDIRECT("'"&$C$6&"'!"&ROW()&":"&ROW()) )} -> 0 | G11: {=_xlfn.XLOOKUP(1, (INDIRECT("'"&$C$6&"'!$6:$6")=G$6)* (INDIRECT("'"&$C$6&"'!$5:$5")=G$5), INDIRECT("'"&$C$6&"'!"&ROW()&":"&ROW()) )} -> 0 | H11: {=_xlfn.XLOOKUP(1, (INDIRECT("'"&$C$6&"'!$6:$6")=H$6)* (INDIRECT("'"&$C$6&"'!$5:$5")=H$5), INDIRECT("'"&$C$6&"'!"&ROW()&":"&ROW()) )} -> 0 | I11: {=_xlfn.XLOOKUP(1, (INDIRECT("'"&$C$6&"'!$6:$6")=I$6)* (INDIRECT("'"&$C$6&"'!$5:$5")=I$5), INDIRECT("'"&$C$6&"'!"&ROW()&":"&ROW()) )} -> 0 | K11: =$D11-E11 -> 0 | L11: =$D11-F11 -> 0 | M11: =$D11-G11 -> 0 | N11: =$D11-H11 -> 0 | O11: =$D11-I11 -> 0 | Q11: =IFERROR($D11/E11-1,0) -> 0 | R11: =IFERROR($D11/F11-1,0) -> 0 | S11: =IFERROR($D11/G11-1,0) -> 0 | T11: =IFERROR($D11/H11-1,0) -> 0 | U11: =IFERROR($D11/I11-1,0) -> 0 | W11: {=INDIRECT("'"&$C$6&"'!"&ADDRESS(ROW(),COLUMN()+44))} -> 0 | X11: {=INDIRECT("'"&$C$6&"'!"&ADDRESS(ROW(),COLUMN()+44))} -> 0 | Y11: {=INDIRECT("'"&$C$6&"'!"&ADDRESS(ROW(),COLUMN()+44))} -> 0 | Z11: {=INDIRECT("'"&$C$6&"'!"&ADDRESS(ROW(),COLUMN()+44))} -> 0 | AA11: {=INDIRECT("'"&$C$6&"'!"&ADDRESS(ROW(),COLUMN()+44))} -> 0 | AB11: {=INDIRECT("'"&$C$6&"'!"&ADDRESS(ROW(),COLUMN()+44))} -> 0 | AD11: =$W11-X11 -> 0 | AE11: =$W11-Y11 -> 0 | AF11: =$W11-Z11 -> 0 | AG11: =$W11-AA11 -> 0 | AH11: =$W11-AB11 -> 0 | AJ11: =IFERROR($W11/X11-1,0) -> 0 | AK11: =IFERROR($W11/Y11-1,0) -> 0 | AL11: =IFERROR($W11/Z11-1,0) -> 0 | AM11: =IFERROR($W11/AA11-1,0) -> 0 | AN11: =IFERROR($W11/AB11-1,0) -> 0
A12: SALDO_FDP | D12: {=_xlfn.XLOOKUP(1, (INDIRECT("'"&$C$6&"'!$6:$6")=D$6)* (INDIRECT("'"&$C$6&"'!$5:$5")=D$5), INDIRECT("'"&$C$6&"'!"&ROW()&":"&ROW()) )} -> 0 | E12: {=_xlfn.XLOOKUP(1, (INDIRECT("'"&$C$6&"'!$6:$6")=E$6)* (INDIRECT("'"&$C$6&"'!$5:$5")=E$5), INDIRECT("'"&$C$6&"'!"&ROW()&":"&ROW()) )} -> 0 | F12: {=_xlfn.XLOOKUP(1, (INDIRECT("'"&$C$6&"'!$6:$6")=F$6)* (INDIRECT("'"&$C$6&"'!$5:$5")=F$5), INDIRECT("'"&$C$6&"'!"&ROW()&":"&ROW()) )} -> 0 | G12: {=_xlfn.XLOOKUP(1, (INDIRECT("'"&$C$6&"'!$6:$6")=G$6)* (INDIRECT("'"&$C$6&"'!$5:$5")=G$5), INDIRECT("'"&$C$6&"'!"&ROW()&":"&ROW()) )} -> 0 | H12: {=_xlfn.XLOOKUP(1, (INDIRECT("'"&$C$6&"'!$6:$6")=H$6)* (INDIRECT("'"&$C$6&"'!$5:$5")=H$5), INDIRECT("'"&$C$6&"'!"&ROW()&":"&ROW()) )} -> 0 | I12: {=_xlfn.XLOOKUP(1, (INDIRECT("'"&$C$6&"'!$6:$6")=I$6)* (INDIRECT("'"&$C$6&"'!$5:$5")=I$5), INDIRECT("'"&$C$6&"'!"&ROW()&":"&ROW()) )} -> 0 | K12: =$D12-E12 -> 0 | L12: =$D12-F12 -> 0 | M12: =$D12-G12 -> 0 | N12: =$D12-H12 -> 0 | O12: =$D12-I12 -> 0 | Q12: =IFERROR($D12/E12-1,0) -> 0 | R12: =IFERROR($D12/F12-1,0) -> 0 | S12: =IFERROR($D12/G12-1,0) -> 0 | T12: =IFERROR($D12/H12-1,0) -> 0 | U12: =IFERROR($D12/I12-1,0) -> 0 | W12: {=INDIRECT("'"&$C$6&"'!"&ADDRESS(ROW(),COLUMN()+44))} -> 0 | X12: {=INDIRECT("'"&$C$6&"'!"&ADDRESS(ROW(),COLUMN()+44))} -> 0 | Y12: {=INDIRECT("'"&$C$6&"'!"&ADDRESS(ROW(),COLUMN()+44))} -> 0 | Z12: {=INDIRECT("'"&$C$6&"'!"&ADDRESS(ROW(),COLUMN()+44))} -> 0 | AA12: {=INDIRECT("'"&$C$6&"'!"&ADDRESS(ROW(),COLUMN()+44))} -> 0 | AB12: {=INDIRECT("'"&$C$6&"'!"&ADDRESS(ROW(),COLUMN()+44))} -> 0 | AD12: =$W12-X12 -> 0 | AE12: =$W12-Y12 -> 0 | AF12: =$W12-Z12 -> 0 | AG12: =$W12-AA12 -> 0 | AH12: =$W12-AB12 -> 0 | AJ12: =IFERROR($W12/X12-1,0) -> 0 | AK12: =IFERROR($W12/Y12-1,0) -> 0 | AL12: =IFERROR($W12/Z12-1,0) -> 0 | AM12: =IFERROR($W12/AA12-1,0) -> 0 | AN12: =IFERROR($W12/AB12-1,0) -> 0
A13: SALDO_FDP | D13: {=_xlfn.XLOOKUP(1, (INDIRECT("'"&$C$6&"'!$6:$6")=D$6)* (INDIRECT("'"&$C$6&"'!$5:$5")=D$5), INDIRECT("'"&$C$6&"'!"&ROW()&":"&ROW()) )} -> 0 | E13: {=_xlfn.XLOOKUP(1, (INDIRECT("'"&$C$6&"'!$6:$6")=E$6)* (INDIRECT("'"&$C$6&"'!$5:$5")=E$5), INDIRECT("'"&$C$6&"'!"&ROW()&":"&ROW()) )} -> 0 | F13: {=_xlfn.XLOOKUP(1, (INDIRECT("'"&$C$6&"'!$6:$6")=F$6)* (INDIRECT("'"&$C$6&"'!$5:$5")=F$5), INDIRECT("'"&$C$6&"'!"&ROW()&":"&ROW()) )} -> 0 | G13: {=_xlfn.XLOOKUP(1, (INDIRECT("'"&$C$6&"'!$6:$6")=G$6)* (INDIRECT("'"&$C$6&"'!$5:$5")=G$5), INDIRECT("'"&$C$6&"'!"&ROW()&":"&ROW()) )} -> 0 | H13: {=_xlfn.XLOOKUP(1, (INDIRECT("'"&$C$6&"'!$6:$6")=H$6)* (INDIRECT("'"&$C$6&"'!$5:$5")=H$5), INDIRECT("'"&$C$6&"'!"&ROW()&":"&ROW()) )} -> 0 | I13: {=_xlfn.XLOOKUP(1, (INDIRECT("'"&$C$6&"'!$6:$6")=I$6)* (INDIRECT("'"&$C$6&"'!$5:$5")=I$5), INDIRECT("'"&$C$6&"'!"&ROW()&":"&ROW()) )} -> 0 | K13: =$D13-E13 -> 0 | L13: =$D13-F13 -> 0 | M13: =$D13-G13 -> 0 | N13: =$D13-H13 -> 0 | O13: =$D13-I13 -> 0 | Q13: =IFERROR($D13/E13-1,0) -> 0 | R13: =IFERROR($D13/F13-1,0) -> 0 | S13: =IFERROR($D13/G13-1,0) -> 0 | T13: =IFERROR($D13/H13-1,0) -> 0 | U13: =IFERROR($D13/I13-1,0) -> 0 | W13: {=INDIRECT("'"&$C$6&"'!"&ADDRESS(ROW(),COLUMN()+44))} -> 0 | X13: {=INDIRECT("'"&$C$6&"'!"&ADDRESS(ROW(),COLUMN()+44))} -> 0 | Y13: {=INDIRECT("'"&$C$6&"'!"&ADDRESS(ROW(),COLUMN()+44))} -> 0 | Z13: {=INDIRECT("'"&$C$6&"'!"&ADDRESS(ROW(),COLUMN()+44))} -> 0 | AA13: {=INDIRECT("'"&$C$6&"'!"&ADDRESS(ROW(),COLUMN()+44))} -> 0 | AB13: {=INDIRECT("'"&$C$6&"'!"&ADDRESS(ROW(),COLUMN()+44))} -> 0 | AD13: =$W13-X13 -> 0 | AE13: =$W13-Y13 -> 0 | AF13: =$W13-Z13 -> 0 | AG13: =$W13-AA13 -> 0 | AH13: =$W13-AB13 -> 0 | AJ13: =IFERROR($W13/X13-1,0) -> 0 | AK13: =IFERROR($W13/Y13-1,0) -> 0 | AL13: =IFERROR($W13/Z13-1,0) -> 0 | AM13: =IFERROR($W13/AA13-1,0) -> 0 | AN13: =IFERROR($W13/AB13-1,0) -> 0
A14: SALDO_FDP | D14: {=_xlfn.XLOOKUP(1, (INDIRECT("'"&$C$6&"'!$6:$6")=D$6)* (INDIRECT("'"&$C$6&"'!$5:$5")=D$5), INDIRECT("'"&$C$6&"'!"&ROW()&":"&ROW()) )} -> 0 | E14: {=_xlfn.XLOOKUP(1, (INDIRECT("'"&$C$6&"'!$6:$6")=E$6)* (INDIRECT("'"&$C$6&"'!$5:$5")=E$5), INDIRECT("'"&$C$6&"'!"&ROW()&":"&ROW()) )} -> 0 | F14: {=_xlfn.XLOOKUP(1, (INDIRECT("'"&$C$6&"'!$6:$6")=F$6)* (INDIRECT("'"&$C$6&"'!$5:$5")=F$5), INDIRECT("'"&$C$6&"'!"&ROW()&":"&ROW()) )} -> 0 | G14: {=_xlfn.XLOOKUP(1, (INDIRECT("'"&$C$6&"'!$6:$6")=G$6)* (INDIRECT("'"&$C$6&"'!$5:$5")=G$5), INDIRECT("'"&$C$6&"'!"&ROW()&":"&ROW()) )} -> 0 | H14: {=_xlfn.XLOOKUP(1, (INDIRECT("'"&$C$6&"'!$6:$6")=H$6)* (INDIRECT("'"&$C$6&"'!$5:$5")=H$5), INDIRECT("'"&$C$6&"'!"&ROW()&":"&ROW()) )} -> 0 | I14: {=_xlfn.XLOOKUP(1, (INDIRECT("'"&$C$6&"'!$6:$6")=I$6)* (INDIRECT("'"&$C$6&"'!$5:$5")=I$5), INDIRECT("'"&$C$6&"'!"&ROW()&":"&ROW()) )} -> 0 | K14: =$D14-E14 -> 0 | L14: =$D14-F14 -> 0 | M14: =$D14-G14 -> 0 | N14: =$D14-H14 -> 0 | O14: =$D14-I14 -> 0 | Q14: =IFERROR($D14/E14-1,0) -> 0 | R14: =IFERROR($D14/F14-1,0) -> 0 | S14: =IFERROR($D14/G14-1,0) -> 0 | T14: =IFERROR($D14/H14-1,0) -> 0 | U14: =IFERROR($D14/I14-1,0) -> 0 | W14: {=INDIRECT("'"&$C$6&"'!"&ADDRESS(ROW(),COLUMN()+44))} -> 0 | X14: {=INDIRECT("'"&$C$6&"'!"&ADDRESS(ROW(),COLUMN()+44))} -> 0 | Y14: {=INDIRECT("'"&$C$6&"'!"&ADDRESS(ROW(),COLUMN()+44))} -> 0 | Z14: {=INDIRECT("'"&$C$6&"'!"&ADDRESS(ROW(),COLUMN()+44))} -> 0 | AA14: {=INDIRECT("'"&$C$6&"'!"&ADDRESS(ROW(),COLUMN()+44))} -> 0 | AB14: {=INDIRECT("'"&$C$6&"'!"&ADDRESS(ROW(),COLUMN()+44))} -> 0 | AD14: =$W14-X14 -> 0 | AE14: =$W14-Y14 -> 0 | AF14: =$W14-Z14 -> 0 | AG14: =$W14-AA14 -> 0 | AH14: =$W14-AB14 -> 0 | AJ14: =IFERROR($W14/X14-1,0) -> 0 | AK14: =IFERROR($W14/Y14-1,0) -> 0 | AL14: =IFERROR($W14/Z14-1,0) -> 0 | AM14: =IFERROR($W14/AA14-1,0) -> 0 | AN14: =IFERROR($W14/AB14-1,0) -> 0
A15: SALDO_FDP | D15: {=_xlfn.XLOOKUP(1, (INDIRECT("'"&$C$6&"'!$6:$6")=D$6)* (INDIRECT("'"&$C$6&"'!$5:$5")=D$5), INDIRECT("'"&$C$6&"'!"&ROW()&":"&ROW()) )} -> 0 | E15: {=_xlfn.XLOOKUP(1, (INDIRECT("'"&$C$6&"'!$6:$6")=E$6)* (INDIRECT("'"&$C$6&"'!$5:$5")=E$5), INDIRECT("'"&$C$6&"'!"&ROW()&":"&ROW()) )} -> 0 | F15: {=_xlfn.XLOOKUP(1, (INDIRECT("'"&$C$6&"'!$6:$6")=F$6)* (INDIRECT("'"&$C$6&"'!$5:$5")=F$5), INDIRECT("'"&$C$6&"'!"&ROW()&":"&ROW()) )} -> 0 | G15: {=_xlfn.XLOOKUP(1, (INDIRECT("'"&$C$6&"'!$6:$6")=G$6)* (INDIRECT("'"&$C$6&"'!$5:$5")=G$5), INDIRECT("'"&$C$6&"'!"&ROW()&":"&ROW()) )} -> 0 | H15: {=_xlfn.XLOOKUP(1, (INDIRECT("'"&$C$6&"'!$6:$6")=H$6)* (INDIRECT("'"&$C$6&"'!$5:$5")=H$5), INDIRECT("'"&$C$6&"'!"&ROW()&":"&ROW()) )} -> 0 | I15: {=_xlfn.XLOOKUP(1, (INDIRECT("'"&$C$6&"'!$6:$6")=I$6)* (INDIRECT("'"&$C$6&"'!$5:$5")=I$5), INDIRECT("'"&$C$6&"'!"&ROW()&":"&ROW()) )} -> 0 | K15: =$D15-E15 -> 0 | L15: =$D15-F15 -> 0 | M15: =$D15-G15 -> 0 | N15: =$D15-H15 -> 0 | O15: =$D15-I15 -> 0 | Q15: =IFERROR($D15/E15-1,0) -> 0 | R15: =IFERROR($D15/F15-1,0) -> 0 | S15: =IFERROR($D15/G15-1,0) -> 0 | T15: =IFERROR($D15/H15-1,0) -> 0 | U15: =IFERROR($D15/I15-1,0) -> 0 | W15: {=INDIRECT("'"&$C$6&"'!"&ADDRESS(ROW(),COLUMN()+44))} -> 0 | X15: {=INDIRECT("'"&$C$6&"'!"&ADDRESS(ROW(),COLUMN()+44))} -> 0 | Y15: {=INDIRECT("'"&$C$6&"'!"&ADDRESS(ROW(),COLUMN()+44))} -> 0 | Z15: {=INDIRECT("'"&$C$6&"'!"&ADDRESS(ROW(),COLUMN()+44))} -> 0 | AA15: {=INDIRECT("'"&$C$6&"'!"&ADDRESS(ROW(),COLUMN()+44))} -> 0 | AB15: {=INDIRECT("'"&$C$6&"'!"&ADDRESS(ROW(),COLUMN()+44))} -> 0 | AD15: =$W15-X15 -> 0 | AE15: =$W15-Y15 -> 0 | AF15: =$W15-Z15 -> 0 | AG15: =$W15-AA15 -> 0 | AH15: =$W15-AB15 -> 0 | AJ15: =IFERROR($W15/X15-1,0) -> 0 | AK15: =IFERROR($W15/Y15-1,0) -> 0 | AL15: =IFERROR($W15/Z15-1,0) -> 0 | AM15: =IFERROR($W15/AA15-1,0) -> 0 | AN15: =IFERROR($W15/AB15-1,0) -> 0
A16: SALDO_FDP | D16: =SUM(D8:D15) -> 0 | E16: =SUM(E8:E15) -> 1963709.7 | F16: =SUM(F8:F15) -> 0 | G16: =SUM(G8:G15) -> 0 | H16: =SUM(H8:H15) -> 0 | I16: =SUM(I8:I15) -> 0 | K16: =$D16-E16 -> -1963709.7 | L16: =$D16-F16 -> 0 | M16: =$D16-G16 -> 0 | N16: =$D16-H16 -> 0 | O16: =$D16-I16 -> 0 | Q16: =IFERROR($D16/E16-1,0) -> -1 | R16: =IFERROR($D16/F16-1,0) -> 0 | S16: =IFERROR($D16/G16-1,0) -> 0 | T16: =IFERROR($D16/H16-1,0) -> 0 | U16: =IFERROR($D16/I16-1,0) -> 0 | W16: =SUM(W8:W15) -> 0 | X16: =SUM(X8:X15) -> 1963709.7 | Y16: =SUM(Y8:Y15) -> 0 | Z16: =SUM(Z8:Z15) -> 0 | AA16: =SUM(AA8:AA15) -> 0 | AB16: =SUM(AB8:AB15) -> 0 | AD16: =$W16-X16 -> -1963709.7 | AE16: =$W16-Y16 -> 0 | AF16: =$W16-Z16 -> 0 | AG16: =$W16-AA16 -> 0 | AH16: =$W16-AB16 -> 0 | AJ16: =IFERROR($W16/X16-1,0) -> -1 | AK16: =IFERROR($W16/Y16-1,0) -> 0 | AL16: =IFERROR($W16/Z16-1,0) -> 0 | AM16: =IFERROR($W16/AA16-1,0) -> 0 | AN16: =IFERROR($W16/AB16-1,0) -> 0
A17: SALDO_FDP | D17: {=_xlfn.XLOOKUP(1, (INDIRECT("'"&$C$6&"'!$6:$6")=D$6)* (INDIRECT("'"&$C$6&"'!$5:$5")=D$5), INDIRECT("'"&$C$6&"'!"&ROW()&":"&ROW()) )} -> 0 | E17: {=_xlfn.XLOOKUP(1, (INDIRECT("'"&$C$6&"'!$6:$6")=E$6)* (INDIRECT("'"&$C$6&"'!$5:$5")=E$5), INDIRECT("'"&$C$6&"'!"&ROW()&":"&ROW()) )} -> 0 | F17: {=_xlfn.XLOOKUP(1, (INDIRECT("'"&$C$6&"'!$6:$6")=F$6)* (INDIRECT("'"&$C$6&"'!$5:$5")=F$5), INDIRECT("'"&$C$6&"'!"&ROW()&":"&ROW()) )} -> 0 | G17: {=_xlfn.XLOOKUP(1, (INDIRECT("'"&$C$6&"'!$6:$6")=G$6)* (INDIRECT("'"&$C$6&"'!$5:$5")=G$5), INDIRECT("'"&$C$6&"'!"&ROW()&":"&ROW()) )} -> 0 | H17: {=_xlfn.XLOOKUP(1, (INDIRECT("'"&$C$6&"'!$6:$6")=H$6)* (INDIRECT("'"&$C$6&"'!$5:$5")=H$5), INDIRECT("'"&$C$6&"'!"&ROW()&":"&ROW()) )} -> 0 | I17: {=_xlfn.XLOOKUP(1, (INDIRECT("'"&$C$6&"'!$6:$6")=I$6)* (INDIRECT("'"&$C$6&"'!$5:$5")=I$5), INDIRECT("'"&$C$6&"'!"&ROW()&":"&ROW()) )} -> 0 | K17: =$D17-E17 -> 0 | L17: =$D17-F17 -> 0 | M17: =$D17-G17 -> 0 | N17: =$D17-H17 -> 0 | O17: =$D17-I17 -> 0 | Q17: =IFERROR($D17/E17-1,0) -> 0 | R17: =IFERROR($D17/F17-1,0) -> 0 | S17: =IFERROR($D17/G17-1,0) -> 0 | T17: =IFERROR($D17/H17-1,0) -> 0 | U17: =IFERROR($D17/I17-1,0) -> 0 | W17: {=INDIRECT("'"&$C$6&"'!"&ADDRESS(ROW(),COLUMN()+44))} -> 0 | X17: {=INDIRECT("'"&$C$6&"'!"&ADDRESS(ROW(),COLUMN()+44))} -> 0 | Y17: {=INDIRECT("'"&$C$6&"'!"&ADDRESS(ROW(),COLUMN()+44))} -> 0 | Z17: {=INDIRECT("'"&$C$6&"'!"&ADDRESS(ROW(),COLUMN()+44))} -> 0 | AA17: {=INDIRECT("'"&$C$6&"'!"&ADDRESS(ROW(),COLUMN()+44))} -> 0 | AB17: {=INDIRECT("'"&$C$6&"'!"&ADDRESS(ROW(),COLUMN()+44))} -> 0 | AD17: =$W17-X17 -> 0 | AE17: =$W17-Y17 -> 0 | AF17: =$W17-Z17 -> 0 | AG17: =$W17-AA17 -> 0 | AH17: =$W17-AB17 -> 0 | AJ17: =IFERROR($W17/X17-1,0) -> 0 | AK17: =IFERROR($W17/Y17-1,0) -> 0 | AL17: =IFERROR($W17/Z17-1,0) -> 0 | AM17: =IFERROR($W17/AA17-1,0) -> 0 | AN17: =IFERROR($W17/AB17-1,0) -> 0
A18: SALDO_FDP | D18: {=_xlfn.XLOOKUP(1, (INDIRECT("'"&$C$6&"'!$6:$6")=D$6)* (INDIRECT("'"&$C$6&"'!$5:$5")=D$5), INDIRECT("'"&$C$6&"'!"&ROW()&":"&ROW()) )} -> 0 | E18: {=_xlfn.XLOOKUP(1, (INDIRECT("'"&$C$6&"'!$6:$6")=E$6)* (INDIRECT("'"&$C$6&"'!$5:$5")=E$5), INDIRECT("'"&$C$6&"'!"&ROW()&":"&ROW()) )} -> 0 | F18: {=_xlfn.XLOOKUP(1, (INDIRECT("'"&$C$6&"'!$6:$6")=F$6)* (INDIRECT("'"&$C$6&"'!$5:$5")=F$5), INDIRECT("'"&$C$6&"'!"&ROW()&":"&ROW()) )} -> 0 | G18: {=_xlfn.XLOOKUP(1, (INDIRECT("'"&$C$6&"'!$6:$6")=G$6)* (INDIRECT("'"&$C$6&"'!$5:$5")=G$5), INDIRECT("'"&$C$6&"'!"&ROW()&":"&ROW()) )} -> 0 | H18: {=_xlfn.XLOOKUP(1, (INDIRECT("'"&$C$6&"'!$6:$6")=H$6)* (INDIRECT("'"&$C$6&"'!$5:$5")=H$5), INDIRECT("'"&$C$6&"'!"&ROW()&":"&ROW()) )} -> 0 | I18: {=_xlfn.XLOOKUP(1, (INDIRECT("'"&$C$6&"'!$6:$6")=I$6)* (INDIRECT("'"&$C$6&"'!$5:$5")=I$5), INDIRECT("'"&$C$6&"'!"&ROW()&":"&ROW()) )} -> 0 | K18: =$D18-E18 -> 0 | L18: =$D18-F18 -> 0 | M18: =$D18-G18 -> 0 | N18: =$D18-H18 -> 0 | O18: =$D18-I18 -> 0 | Q18: =IFERROR($D18/E18-1,0) -> 0 | R18: =IFERROR($D18/F18-1,0) -> 0 | S18: =IFERROR($D18/G18-1,0) -> 0 | T18: =IFERROR($D18/H18-1,0) -> 0 | U18: =IFERROR($D18/I18-1,0) -> 0 | W18: {=INDIRECT("'"&$C$6&"'!"&ADDRESS(ROW(),COLUMN()+44))} -> 0 | X18: {=INDIRECT("'"&$C$6&"'!"&ADDRESS(ROW(),COLUMN()+44))} -> 0 | Y18: {=INDIRECT("'"&$C$6&"'!"&ADDRESS(ROW(),COLUMN()+44))} -> 0 | Z18: {=INDIRECT("'"&$C$6&"'!"&ADDRESS(ROW(),COLUMN()+44))} -> 0 | AA18: {=INDIRECT("'"&$C$6&"'!"&ADDRESS(ROW(),COLUMN()+44))} -> 0 | AB18: {=INDIRECT("'"&$C$6&"'!"&ADDRESS(ROW(),COLUMN()+44))} -> 0 | AD18: =$W18-X18 -> 0 | AE18: =$W18-Y18 -> 0 | AF18: =$W18-Z18 -> 0 | AG18: =$W18-AA18 -> 0 | AH18: =$W18-AB18 -> 0 | AJ18: =IFERROR($W18/X18-1,0) -> 0 | AK18: =IFERROR($W18/Y18-1,0) -> 0 | AL18: =IFERROR($W18/Z18-1,0) -> 0 | AM18: =IFERROR($W18/AA18-1,0) -> 0 | AN18: =IFERROR($W18/AB18-1,0) -> 0
A19: SALDO_FDP | D19: {=_xlfn.XLOOKUP(1, (INDIRECT("'"&$C$6&"'!$6:$6")=D$6)* (INDIRECT("'"&$C$6&"'!$5:$5")=D$5), INDIRECT("'"&$C$6&"'!"&ROW()&":"&ROW()) )} -> 0 | E19: {=_xlfn.XLOOKUP(1, (INDIRECT("'"&$C$6&"'!$6:$6")=E$6)* (INDIRECT("'"&$C$6&"'!$5:$5")=E$5), INDIRECT("'"&$C$6&"'!"&ROW()&":"&ROW()) )} -> 0 | F19: {=_xlfn.XLOOKUP(1, (INDIRECT("'"&$C$6&"'!$6:$6")=F$6)* (INDIRECT("'"&$C$6&"'!$5:$5")=F$5), INDIRECT("'"&$C$6&"'!"&ROW()&":"&ROW()) )} -> 0 | G19: {=_xlfn.XLOOKUP(1, (INDIRECT("'"&$C$6&"'!$6:$6")=G$6)* (INDIRECT("'"&$C$6&"'!$5:$5")=G$5), INDIRECT("'"&$C$6&"'!"&ROW()&":"&ROW()) )} -> 0 | H19: {=_xlfn.XLOOKUP(1, (INDIRECT("'"&$C$6&"'!$6:$6")=H$6)* (INDIRECT("'"&$C$6&"'!$5:$5")=H$5), INDIRECT("'"&$C$6&"'!"&ROW()&":"&ROW()) )} -> 0 | I19: {=_xlfn.XLOOKUP(1, (INDIRECT("'"&$C$6&"'!$6:$6")=I$6)* (INDIRECT("'"&$C$6&"'!$5:$5")=I$5), INDIRECT("'"&$C$6&"'!"&ROW()&":"&ROW()) )} -> 0 | K19: =$D19-E19 -> 0 | L19: =$D19-F19 -> 0 | M19: =$D19-G19 -> 0 | N19: =$D19-H19 -> 0 | O19: =$D19-I19 -> 0 | Q19: =IFERROR($D19/E19-1,0) -> 0 | R19: =IFERROR($D19/F19-1,0) -> 0 | S19: =IFERROR($D19/G19-1,0) -> 0 | T19: =IFERROR($D19/H19-1,0) -> 0 | U19: =IFERROR($D19/I19-1,0) -> 0 | W19: {=INDIRECT("'"&$C$6&"'!"&ADDRESS(ROW(),COLUMN()+44))} -> 0 | X19: {=INDIRECT("'"&$C$6&"'!"&ADDRESS(ROW(),COLUMN()+44))} -> 0 | Y19: {=INDIRECT("'"&$C$6&"'!"&ADDRESS(ROW(),COLUMN()+44))} -> 0 | Z19: {=INDIRECT("'"&$C$6&"'!"&ADDRESS(ROW(),COLUMN()+44))} -> 0 | AA19: {=INDIRECT("'"&$C$6&"'!"&ADDRESS(ROW(),COLUMN()+44))} -> 0 | AB19: {=INDIRECT("'"&$C$6&"'!"&ADDRESS(ROW(),COLUMN()+44))} -> 0 | AD19: =$W19-X19 -> 0 | AE19: =$W19-Y19 -> 0 | AF19: =$W19-Z19 -> 0 | AG19: =$W19-AA19 -> 0 | AH19: =$W19-AB19 -> 0 | AJ19: =IFERROR($W19/X19-1,0) -> 0 | AK19: =IFERROR($W19/Y19-1,0) -> 0 | AL19: =IFERROR($W19/Z19-1,0) -> 0 | AM19: =IFERROR($W19/AA19-1,0) -> 0 | AN19: =IFERROR($W19/AB19-1,0) -> 0
A20: SALDO_FDP | D20: {=_xlfn.XLOOKUP(1, (INDIRECT("'"&$C$6&"'!$6:$6")=D$6)* (INDIRECT("'"&$C$6&"'!$5:$5")=D$5), INDIRECT("'"&$C$6&"'!"&ROW()&":"&ROW()) )} -> 0 | E20: {=_xlfn.XLOOKUP(1, (INDIRECT("'"&$C$6&"'!$6:$6")=E$6)* (INDIRECT("'"&$C$6&"'!$5:$5")=E$5), INDIRECT("'"&$C$6&"'!"&ROW()&":"&ROW()) )} -> 0 | F20: {=_xlfn.XLOOKUP(1, (INDIRECT("'"&$C$6&"'!$6:$6")=F$6)* (INDIRECT("'"&$C$6&"'!$5:$5")=F$5), INDIRECT("'"&$C$6&"'!"&ROW()&":"&ROW()) )} -> 0 | G20: {=_xlfn.XLOOKUP(1, (INDIRECT("'"&$C$6&"'!$6:$6")=G$6)* (INDIRECT("'"&$C$6&"'!$5:$5")=G$5), INDIRECT("'"&$C$6&"'!"&ROW()&":"&ROW()) )} -> 0 | H20: {=_xlfn.XLOOKUP(1, (INDIRECT("'"&$C$6&"'!$6:$6")=H$6)* (INDIRECT("'"&$C$6&"'!$5:$5")=H$5), INDIRECT("'"&$C$6&"'!"&ROW()&":"&ROW()) )} -> 0 | I20: {=_xlfn.XLOOKUP(1, (INDIRECT("'"&$C$6&"'!$6:$6")=I$6)* (INDIRECT("'"&$C$6&"'!$5:$5")=I$5), INDIRECT("'"&$C$6&"'!"&ROW()&":"&ROW()) )} -> 0 | K20: =$D20-E20 -> 0 | L20: =$D20-F20 -> 0 | M20: =$D20-G20 -> 0 | N20: =$D20-H20 -> 0 | O20: =$D20-I20 -> 0 | Q20: =IFERROR($D20/E20-1,0) -> 0 | R20: =IFERROR($D20/F20-1,0) -> 0 | S20: =IFERROR($D20/G20-1,0) -> 0 | T20: =IFERROR($D20/H20-1,0) -> 0 | U20: =IFERROR($D20/I20-1,0) -> 0 | W20: {=INDIRECT("'"&$C$6&"'!"&ADDRESS(ROW(),COLUMN()+44))} -> 0 | X20: {=INDIRECT("'"&$C$6&"'!"&ADDRESS(ROW(),COLUMN()+44))} -> 0 | Y20: {=INDIRECT("'"&$C$6&"'!"&ADDRESS(ROW(),COLUMN()+44))} -> 0 | Z20: {=INDIRECT("'"&$C$6&"'!"&ADDRESS(ROW(),COLUMN()+44))} -> 0 | AA20: {=INDIRECT("'"&$C$6&"'!"&ADDRESS(ROW(),COLUMN()+44))} -> 0 | AB20: {=INDIRECT("'"&$C$6&"'!"&ADDRESS(ROW(),COLUMN()+44))} -> 0 | AD20: =$W20-X20 -> 0 | AE20: =$W20-Y20 -> 0 | AF20: =$W20-Z20 -> 0 | AG20: =$W20-AA20 -> 0 | AH20: =$W20-AB20 -> 0 | AJ20: =IFERROR($W20/X20-1,0) -> 0 | AK20: =IFERROR($W20/Y20-1,0) -> 0 | AL20: =IFERROR($W20/Z20-1,0) -> 0 | AM20: =IFERROR($W20/AA20-1,0) -> 0 | AN20: =IFERROR($W20/AB20-1,0) -> 0
A21: SALDO_FDP | D21: {=_xlfn.XLOOKUP(1, (INDIRECT("'"&$C$6&"'!$6:$6")=D$6)* (INDIRECT("'"&$C$6&"'!$5:$5")=D$5), INDIRECT("'"&$C$6&"'!"&ROW()&":"&ROW()) )} -> 0 | E21: {=_xlfn.XLOOKUP(1, (INDIRECT("'"&$C$6&"'!$6:$6")=E$6)* (INDIRECT("'"&$C$6&"'!$5:$5")=E$5), INDIRECT("'"&$C$6&"'!"&ROW()&":"&ROW()) )} -> 0 | F21: {=_xlfn.XLOOKUP(1, (INDIRECT("'"&$C$6&"'!$6:$6")=F$6)* (INDIRECT("'"&$C$6&"'!$5:$5")=F$5), INDIRECT("'"&$C$6&"'!"&ROW()&":"&ROW()) )} -> 0 | G21: {=_xlfn.XLOOKUP(1, (INDIRECT("'"&$C$6&"'!$6:$6")=G$6)* (INDIRECT("'"&$C$6&"'!$5:$5")=G$5), INDIRECT("'"&$C$6&"'!"&ROW()&":"&ROW()) )} -> 0 | H21: {=_xlfn.XLOOKUP(1, (INDIRECT("'"&$C$6&"'!$6:$6")=H$6)* (INDIRECT("'"&$C$6&"'!$5:$5")=H$5), INDIRECT("'"&$C$6&"'!"&ROW()&":"&ROW()) )} -> 0 | I21: {=_xlfn.XLOOKUP(1, (INDIRECT("'"&$C$6&"'!$6:$6")=I$6)* (INDIRECT("'"&$C$6&"'!$5:$5")=I$5), INDIRECT("'"&$C$6&"'!"&ROW()&":"&ROW()) )} -> 0 | K21: =$D21-E21 -> 0 | L21: =$D21-F21 -> 0 | M21: =$D21-G21 -> 0 | N21: =$D21-H21 -> 0 | O21: =$D21-I21 -> 0 | Q21: =IFERROR($D21/E21-1,0) -> 0 | R21: =IFERROR($D21/F21-1,0) -> 0 | S21: =IFERROR($D21/G21-1,0) -> 0 | T21: =IFERROR($D21/H21-1,0) -> 0 | U21: =IFERROR($D21/I21-1,0) -> 0 | W21: {=INDIRECT("'"&$C$6&"'!"&ADDRESS(ROW(),COLUMN()+44))} -> 0 | X21: {=INDIRECT("'"&$C$6&"'!"&ADDRESS(ROW(),COLUMN()+44))} -> 0 | Y21: {=INDIRECT("'"&$C$6&"'!"&ADDRESS(ROW(),COLUMN()+44))} -> 0 | Z21: {=INDIRECT("'"&$C$6&"'!"&ADDRESS(ROW(),COLUMN()+44))} -> 0 | AA21: {=INDIRECT("'"&$C$6&"'!"&ADDRESS(ROW(),COLUMN()+44))} -> 0 | AB21: {=INDIRECT("'"&$C$6&"'!"&ADDRESS(ROW(),COLUMN()+44))} -> 0 | AD21: =$W21-X21 -> 0 | AE21: =$W21-Y21 -> 0 | AF21: =$W21-Z21 -> 0 | AG21: =$W21-AA21 -> 0 | AH21: =$W21-AB21 -> 0 | AJ21: =IFERROR($W21/X21-1,0) -> 0 | AK21: =IFERROR($W21/Y21-1,0) -> 0 | AL21: =IFERROR($W21/Z21-1,0) -> 0 | AM21: =IFERROR($W21/AA21-1,0) -> 0 | AN21: =IFERROR($W21/AB21-1,0) -> 0
A22: SALDO_FDP | D22: {=_xlfn.XLOOKUP(1, (INDIRECT("'"&$C$6&"'!$6:$6")=D$6)* (INDIRECT("'"&$C$6&"'!$5:$5")=D$5), INDIRECT("'"&$C$6&"'!"&ROW()&":"&ROW()) )} -> 0 | E22: {=_xlfn.XLOOKUP(1, (INDIRECT("'"&$C$6&"'!$6:$6")=E$6)* (INDIRECT("'"&$C$6&"'!$5:$5")=E$5), INDIRECT("'"&$C$6&"'!"&ROW()&":"&ROW()) )} -> 0 | F22: {=_xlfn.XLOOKUP(1, (INDIRECT("'"&$C$6&"'!$6:$6")=F$6)* (INDIRECT("'"&$C$6&"'!$5:$5")=F$5), INDIRECT("'"&$C$6&"'!"&ROW()&":"&ROW()) )} -> 0 | G22: {=_xlfn.XLOOKUP(1, (INDIRECT("'"&$C$6&"'!$6:$6")=G$6)* (INDIRECT("'"&$C$6&"'!$5:$5")=G$5), INDIRECT("'"&$C$6&"'!"&ROW()&":"&ROW()) )} -> 0 | H22: {=_xlfn.XLOOKUP(1, (INDIRECT("'"&$C$6&"'!$6:$6")=H$6)* (INDIRECT("'"&$C$6&"'!$5:$5")=H$5), INDIRECT("'"&$C$6&"'!"&ROW()&":"&ROW()) )} -> 0 | I22: {=_xlfn.XLOOKUP(1, (INDIRECT("'"&$C$6&"'!$6:$6")=I$6)* (INDIRECT("'"&$C$6&"'!$5:$5")=I$5), INDIRECT("'"&$C$6&"'!"&ROW()&":"&ROW()) )} -> 0 | K22: =$D22-E22 -> 0 | L22: =$D22-F22 -> 0 | M22: =$D22-G22 -> 0 | N22: =$D22-H22 -> 0 | O22: =$D22-I22 -> 0 | Q22: =IFERROR($D22/E22-1,0) -> 0 | R22: =IFERROR($D22/F22-1,0) -> 0 | S22: =IFERROR($D22/G22-1,0) -> 0 | T22: =IFERROR($D22/H22-1,0) -> 0 | U22: =IFERROR($D22/I22-1,0) -> 0 | W22: {=INDIRECT("'"&$C$6&"'!"&ADDRESS(ROW(),COLUMN()+44))} -> 0 | X22: {=INDIRECT("'"&$C$6&"'!"&ADDRESS(ROW(),COLUMN()+44))} -> 0 | Y22: {=INDIRECT("'"&$C$6&"'!"&ADDRESS(ROW(),COLUMN()+44))} -> 0 | Z22: {=INDIRECT("'"&$C$6&"'!"&ADDRESS(ROW(),COLUMN()+44))} -> 0 | AA22: {=INDIRECT("'"&$C$6&"'!"&ADDRESS(ROW(),COLUMN()+44))} -> 0 | AB22: {=INDIRECT("'"&$C$6&"'!"&ADDRESS(ROW(),COLUMN()+44))} -> 0 | AD22: =$W22-X22 -> 0 | AE22: =$W22-Y22 -> 0 | AF22: =$W22-Z22 -> 0 | AG22: =$W22-AA22 -> 0 | AH22: =$W22-AB22 -> 0 | AJ22: =IFERROR($W22/X22-1,0) -> 0 | AK22: =IFERROR($W22/Y22-1,0) -> 0 | AL22: =IFERROR($W22/Z22-1,0) -> 0 | AM22: =IFERROR($W22/AA22-1,0) -> 0 | AN22: =IFERROR($W22/AB22-1,0) -> 0
A23: SALDO_FDP | D23: =SUM(D21:D22) -> 0 | E23: =SUM(E21:E22) -> 0 | F23: =SUM(F21:F22) -> 0 | G23: =SUM(G21:G22) -> 0 | H23: =SUM(H21:H22) -> 0 | I23: =SUM(I21:I22) -> 0 | K23: =$D23-E23 -> 0 | L23: =$D23-F23 -> 0 | M23: =$D23-G23 -> 0 | N23: =$D23-H23 -> 0 | O23: =$D23-I23 -> 0 | Q23: =IFERROR($D23/E23-1,0) -> 0 | R23: =IFERROR($D23/F23-1,0) -> 0 | S23: =IFERROR($D23/G23-1,0) -> 0 | T23: =IFERROR($D23/H23-1,0) -> 0 | U23: =IFERROR($D23/I23-1,0) -> 0 | W23: =SUM(W21:W22) -> 0 | X23: =SUM(X21:X22) -> 0 | Y23: =SUM(Y21:Y22) -> 0 | Z23: =SUM(Z21:Z22) -> 0 | AA23: =SUM(AA21:AA22) -> 0 | AB23: =SUM(AB21:AB22) -> 0 | AD23: =$W23-X23 -> 0 | AE23: =$W23-Y23 -> 0 | AF23: =$W23-Z23 -> 0 | AG23: =$W23-AA23 -> 0 | AH23: =$W23-AB23 -> 0 | AJ23: =IFERROR($W23/X23-1,0) -> 0 | AK23: =IFERROR($W23/Y23-1,0) -> 0 | AL23: =IFERROR($W23/Z23-1,0) -> 0 | AM23: =IFERROR($W23/AA23-1,0) -> 0 | AN23: =IFERROR($W23/AB23-1,0) -> 0
C24: Saldo FdP | D24: =SUM(D16,D17:D20,D23) -> 0 | E24: =SUM(E16,E17:E20,E23) -> 1963709.7 | F24: =SUM(F16,F17:F20,F23) -> 0 | G24: =SUM(G16,G17:G20,G23) -> 0 | H24: =SUM(H16,H17:H20,H23) -> 0 | I24: =SUM(I16,I17:I20,I23) -> 0 | K24: =$D24-E24 -> -1963709.7 | L24: =$D24-F24 -> 0 | M24: =$D24-G24 -> 0 | N24: =$D24-H24 -> 0 | O24: =$D24-I24 -> 0 | Q24: =IFERROR($D24/E24-1,0) -> -1 | R24: =IFERROR($D24/F24-1,0) -> 0 | S24: =IFERROR($D24/G24-1,0) -> 0 | T24: =IFERROR($D24/H24-1,0) -> 0 | U24: =IFERROR($D24/I24-1,0) -> 0 | W24: =SUM(W16,W17:W20,W23) -> 0 | X24: =SUM(X16,X17:X20,X23) -> 1963709.7 | Y24: =SUM(Y16,Y17:Y20,Y23) -> 0 | Z24: =SUM(Z16,Z17:Z20,Z23) -> 0 | AA24: =SUM(AA16,AA17:AA20,AA23) -> 0 | AB24: =SUM(AB16,AB17:AB20,AB23) -> 0 | AD24: =$W24-X24 -> -1963709.7 | AE24: =$W24-Y24 -> 0 | AF24: =$W24-Z24 -> 0 | AG24: =$W24-AA24 -> 0 | AH24: =$W24-AB24 -> 0 | AJ24: =IFERROR($W24/X24-1,0) -> -1 | AK24: =IFERROR($W24/Y24-1,0) -> 0 | AL24: =IFERROR($W24/Z24-1,0) -> 0 | AM24: =IFERROR($W24/AA24-1,0) -> 0 | AN24: =IFERROR($W24/AB24-1,0) -> 0
A27: SALDO_PROM | C27: Cuenta Sueldo | D27: {=_xlfn.XLOOKUP(1, (INDIRECT("'"&$C$6&"'!$6:$6")=D$6)* (INDIRECT("'"&$C$6&"'!$5:$5")=D$5), INDIRECT("'"&$C$6&"'!"&ROW()&":"&ROW()) )} -> 0 | E27: {=_xlfn.XLOOKUP(1, (INDIRECT("'"&$C$6&"'!$6:$6")=E$6)* (INDIRECT("'"&$C$6&"'!$5:$5")=E$5), INDIRECT("'"&$C$6&"'!"&ROW()&":"&ROW()) )} -> 1758240.1 | F27: {=_xlfn.XLOOKUP(1, (INDIRECT("'"&$C$6&"'!$6:$6")=F$6)* (INDIRECT("'"&$C$6&"'!$5:$5")=F$5), INDIRECT("'"&$C$6&"'!"&ROW()&":"&ROW()) )} -> 0 | G27: {=_xlfn.XLOOKUP(1, (INDIRECT("'"&$C$6&"'!$6:$6")=G$6)* (INDIRECT("'"&$C$6&"'!$5:$5")=G$5), INDIRECT("'"&$C$6&"'!"&ROW()&":"&ROW()) )} -> 0 | H27: {=_xlfn.XLOOKUP(1, (INDIRECT("'"&$C$6&"'!$6:$6")=H$6)* (INDIRECT("'"&$C$6&"'!$5:$5")=H$5), INDIRECT("'"&$C$6&"'!"&ROW()&":"&ROW()) )} -> 0 | I27: {=_xlfn.XLOOKUP(1, (INDIRECT("'"&$C$6&"'!$6:$6")=I$6)* (INDIRECT("'"&$C$6&"'!$5:$5")=I$5), INDIRECT("'"&$C$6&"'!"&ROW()&":"&ROW()) )} -> 0 | K27: =$D27-E27 -> -1758240.1 | L27: =$D27-F27 -> 0 | M27: =$D27-G27 -> 0 | N27: =$D27-H27 -> 0 | O27: =$D27-I27 -> 0 | Q27: =IFERROR($D27/E27-1,0) -> -1 | R27: =IFERROR($D27/F27-1,0) -> 0 | S27: =IFERROR($D27/G27-1,0) -> 0 | T27: =IFERROR($D27/H27-1,0) -> 0 | U27: =IFERROR($D27/I27-1,0) -> 0 | W27: {=INDIRECT("'"&$C$6&"'!"&ADDRESS(ROW(),COLUMN()+44))} -> 0 | X27: {=INDIRECT("'"&$C$6&"'!"&ADDRESS(ROW(),COLUMN()+44))} -> 1777154.7 | Y27: {=INDIRECT("'"&$C$6&"'!"&ADDRESS(ROW(),COLUMN()+44))} -> 0 | Z27: {=INDIRECT("'"&$C$6&"'!"&ADDRESS(ROW(),COLUMN()+44))} -> 0 | AA27: {=INDIRECT("'"&$C$6&"'!"&ADDRESS(ROW(),COLUMN()+44))} -> 0 | AB27: {=INDIRECT("'"&$C$6&"'!"&ADDRESS(ROW(),COLUMN()+44))} -> 0 | AD27: =$W27-X27 -> -1777154.7 | AE27: =$W27-Y27 -> 0 | AF27: =$W27-Z27 -> 0 | AG27: =$W27-AA27 -> 0 | AH27: =$W27-AB27 -> 0 | AJ27: =IFERROR($W27/X27-1,0) -> -1 | AK27: =IFERROR($W27/Y27-1,0) -> 0 | AL27: =IFERROR($W27/Z27-1,0) -> 0 | AM27: =IFERROR($W27/AA27-1,0) -> 0 | AN27: =IFERROR($W27/AB27-1,0) -> 0
A28: SALDO_PROM | D28: {=_xlfn.XLOOKUP(1, (INDIRECT("'"&$C$6&"'!$6:$6")=D$6)* (INDIRECT("'"&$C$6&"'!$5:$5")=D$5), INDIRECT("'"&$C$6&"'!"&ROW()&":"&ROW()) )} -> 0 | E28: {=_xlfn.XLOOKUP(1, (INDIRECT("'"&$C$6&"'!$6:$6")=E$6)* (INDIRECT("'"&$C$6&"'!$5:$5")=E$5), INDIRECT("'"&$C$6&"'!"&ROW()&":"&ROW()) )} -> 0 | F28: {=_xlfn.XLOOKUP(1, (INDIRECT("'"&$C$6&"'!$6:$6")=F$6)* (INDIRECT("'"&$C$6&"'!$5:$5")=F$5), INDIRECT("'"&$C$6&"'!"&ROW()&":"&ROW()) )} -> 0 | G28: {=_xlfn.XLOOKUP(1, (INDIRECT("'"&$C$6&"'!$6:$6")=G$6)* (INDIRECT("'"&$C$6&"'!$5:$5")=G$5), INDIRECT("'"&$C$6&"'!"&ROW()&":"&ROW()) )} -> 0 | H28: {=_xlfn.XLOOKUP(1, (INDIRECT("'"&$C$6&"'!$6:$6")=H$6)* (INDIRECT("'"&$C$6&"'!$5:$5")=H$5), INDIRECT("'"&$C$6&"'!"&ROW()&":"&ROW()) )} -> 0 | I28: {=_xlfn.XLOOKUP(1, (INDIRECT("'"&$C$6&"'!$6:$6")=I$6)* (INDIRECT("'"&$C$6&"'!$5:$5")=I$5), INDIRECT("'"&$C$6&"'!"&ROW()&":"&ROW()) )} -> 0 | K28: =$D28-E28 -> 0 | L28: =$D28-F28 -> 0 | M28: =$D28-G28 -> 0 | N28: =$D28-H28 -> 0 | O28: =$D28-I28 -> 0 | Q28: =IFERROR($D28/E28-1,0) -> 0 | R28: =IFERROR($D28/F28-1,0) -> 0 | S28: =IFERROR($D28/G28-1,0) -> 0 | T28: =IFERROR($D28/H28-1,0) -> 0 | U28: =IFERROR($D28/I28-1,0) -> 0 | W28: {=INDIRECT("'"&$C$6&"'!"&ADDRESS(ROW(),COLUMN()+44))} -> 0 | X28: {=INDIRECT("'"&$C$6&"'!"&ADDRESS(ROW(),COLUMN()+44))} -> 0 | Y28: {=INDIRECT("'"&$C$6&"'!"&ADDRESS(ROW(),COLUMN()+44))} -> 0 | Z28: {=INDIRECT("'"&$C$6&"'!"&ADDRESS(ROW(),COLUMN()+44))} -> 0 | AA28: {=INDIRECT("'"&$C$6&"'!"&ADDRESS(ROW(),COLUMN()+44))} -> 0 | AB28: {=INDIRECT("'"&$C$6&"'!"&ADDRESS(ROW(),COLUMN()+44))} -> 0 | AD28: =$W28-X28 -> 0 | AE28: =$W28-Y28 -> 0 | AF28: =$W28-Z28 -> 0 | AG28: =$W28-AA28 -> 0 | AH28: =$W28-AB28 -> 0 | AJ28: =IFERROR($W28/X28-1,0) -> 0 | AK28: =IFERROR($W28/Y28-1,0) -> 0 | AL28: =IFERROR($W28/Z28-1,0) -> 0 | AM28: =IFERROR($W28/AA28-1,0) -> 0 | AN28: =IFERROR($W28/AB28-1,0) -> 0
A29: SALDO_PROM | D29: {=_xlfn.XLOOKUP(1, (INDIRECT("'"&$C$6&"'!$6:$6")=D$6)* (INDIRECT("'"&$C$6&"'!$5:$5")=D$5), INDIRECT("'"&$C$6&"'!"&ROW()&":"&ROW()) )} -> 0 | E29: {=_xlfn.XLOOKUP(1, (INDIRECT("'"&$C$6&"'!$6:$6")=E$6)* (INDIRECT("'"&$C$6&"'!$5:$5")=E$5), INDIRECT("'"&$C$6&"'!"&ROW()&":"&ROW()) )} -> 0 | F29: {=_xlfn.XLOOKUP(1, (INDIRECT("'"&$C$6&"'!$6:$6")=F$6)* (INDIRECT("'"&$C$6&"'!$5:$5")=F$5), INDIRECT("'"&$C$6&"'!"&ROW()&":"&ROW()) )} -> 0 | G29: {=_xlfn.XLOOKUP(1, (INDIRECT("'"&$C$6&"'!$6:$6")=G$6)* (INDIRECT("'"&$C$6&"'!$5:$5")=G$5), INDIRECT("'"&$C$6&"'!"&ROW()&":"&ROW()) )} -> 0 | H29: {=_xlfn.XLOOKUP(1, (INDIRECT("'"&$C$6&"'!$6:$6")=H$6)* (INDIRECT("'"&$C$6&"'!$5:$5")=H$5), INDIRECT("'"&$C$6&"'!"&ROW()&":"&ROW()) )} -> 0 | I29: {=_xlfn.XLOOKUP(1, (INDIRECT("'"&$C$6&"'!$6:$6")=I$6)* (INDIRECT("'"&$C$6&"'!$5:$5")=I$5), INDIRECT("'"&$C$6&"'!"&ROW()&":"&ROW()) )} -> 0 | K29: =$D29-E29 -> 0 | L29: =$D29-F29 -> 0 | M29: =$D29-G29 -> 0 | N29: =$D29-H29 -> 0 | O29: =$D29-I29 -> 0 | Q29: =IFERROR($D29/E29-1,0) -> 0 | R29: =IFERROR($D29/F29-1,0) -> 0 | S29: =IFERROR($D29/G29-1,0) -> 0 | T29: =IFERROR($D29/H29-1,0) -> 0 | U29: =IFERROR($D29/I29-1,0) -> 0 | W29: {=INDIRECT("'"&$C$6&"'!"&ADDRESS(ROW(),COLUMN()+44))} -> 0 | X29: {=INDIRECT("'"&$C$6&"'!"&ADDRESS(ROW(),COLUMN()+44))} -> 0 | Y29: {=INDIRECT("'"&$C$6&"'!"&ADDRESS(ROW(),COLUMN()+44))} -> 0 | Z29: {=INDIRECT("'"&$C$6&"'!"&ADDRESS(ROW(),COLUMN()+44))} -> 0 | AA29: {=INDIRECT("'"&$C$6&"'!"&ADDRESS(ROW(),COLUMN()+44))} -> 0 | AB29: {=INDIRECT("'"&$C$6&"'!"&ADDRESS(ROW(),COLUMN()+44))} -> 0 | AD29: =$W29-X29 -> 0 | AE29: =$W29-Y29 -> 0 | AF29: =$W29-Z29 -> 0 | AG29: =$W29-AA29 -> 0 | AH29: =$W29-AB29 -> 0 | AJ29: =IFERROR($W29/X29-1,0) -> 0 | AK29: =IFERROR($W29/Y29-1,0) -> 0 | AL29: =IFERROR($W29/Z29-1,0) -> 0 | AM29: =IFERROR($W29/AA29-1,0) -> 0 | AN29: =IFERROR($W29/AB29-1,0) -> 0
A30: SALDO_PROM | D30: {=_xlfn.XLOOKUP(1, (INDIRECT("'"&$C$6&"'!$6:$6")=D$6)* (INDIRECT("'"&$C$6&"'!$5:$5")=D$5), INDIRECT("'"&$C$6&"'!"&ROW()&":"&ROW()) )} -> 0 | E30: {=_xlfn.XLOOKUP(1, (INDIRECT("'"&$C$6&"'!$6:$6")=E$6)* (INDIRECT("'"&$C$6&"'!$5:$5")=E$5), INDIRECT("'"&$C$6&"'!"&ROW()&":"&ROW()) )} -> 0 | F30: {=_xlfn.XLOOKUP(1, (INDIRECT("'"&$C$6&"'!$6:$6")=F$6)* (INDIRECT("'"&$C$6&"'!$5:$5")=F$5), INDIRECT("'"&$C$6&"'!"&ROW()&":"&ROW()) )} -> 0 | G30: {=_xlfn.XLOOKUP(1, (INDIRECT("'"&$C$6&"'!$6:$6")=G$6)* (INDIRECT("'"&$C$6&"'!$5:$5")=G$5), INDIRECT("'"&$C$6&"'!"&ROW()&":"&ROW()) )} -> 0 | H30: {=_xlfn.XLOOKUP(1, (INDIRECT("'"&$C$6&"'!$6:$6")=H$6)* (INDIRECT("'"&$C$6&"'!$5:$5")=H$5), INDIRECT("'"&$C$6&"'!"&ROW()&":"&ROW()) )} -> 0 | I30: {=_xlfn.XLOOKUP(1, (INDIRECT("'"&$C$6&"'!$6:$6")=I$6)* (INDIRECT("'"&$C$6&"'!$5:$5")=I$5), INDIRECT("'"&$C$6&"'!"&ROW()&":"&ROW()) )} -> 0 | K30: =$D30-E30 -> 0 | L30: =$D30-F30 -> 0 | M30: =$D30-G30 -> 0 | N30: =$D30-H30 -> 0 | O30: =$D30-I30 -> 0 | Q30: =IFERROR($D30/E30-1,0) -> 0 | R30: =IFERROR($D30/F30-1,0) -> 0 | S30: =IFERROR($D30/G30-1,0) -> 0 | T30: =IFERROR($D30/H30-1,0) -> 0 | U30: =IFERROR($D30/I30-1,0) -> 0 | W30: {=INDIRECT("'"&$C$6&"'!"&ADDRESS(ROW(),COLUMN()+44))} -> 0 | X30: {=INDIRECT("'"&$C$6&"'!"&ADDRESS(ROW(),COLUMN()+44))} -> 0 | Y30: {=INDIRECT("'"&$C$6&"'!"&ADDRESS(ROW(),COLUMN()+44))} -> 0 | Z30: {=INDIRECT("'"&$C$6&"'!"&ADDRESS(ROW(),COLUMN()+44))} -> 0 | AA30: {=INDIRECT("'"&$C$6&"'!"&ADDRESS(ROW(),COLUMN()+44))} -> 0 | AB30: {=INDIRECT("'"&$C$6&"'!"&ADDRESS(ROW(),COLUMN()+44))} -> 0 | AD30: =$W30-X30 -> 0 | AE30: =$W30-Y30 -> 0 | AF30: =$W30-Z30 -> 0 | AG30: =$W30-AA30 -> 0 | AH30: =$W30-AB30 -> 0 | AJ30: =IFERROR($W30/X30-1,0) -> 0 | AK30: =IFERROR($W30/Y30-1,0) -> 0 | AL30: =IFERROR($W30/Z30-1,0) -> 0 | AM30: =IFERROR($W30/AA30-1,0) -> 0 | AN30: =IFERROR($W30/AB30-1,0) -> 0
A31: SALDO_PROM | D31: {=_xlfn.XLOOKUP(1, (INDIRECT("'"&$C$6&"'!$6:$6")=D$6)* (INDIRECT("'"&$C$6&"'!$5:$5")=D$5), INDIRECT("'"&$C$6&"'!"&ROW()&":"&ROW()) )} -> 0 | E31: {=_xlfn.XLOOKUP(1, (INDIRECT("'"&$C$6&"'!$6:$6")=E$6)* (INDIRECT("'"&$C$6&"'!$5:$5")=E$5), INDIRECT("'"&$C$6&"'!"&ROW()&":"&ROW()) )} -> 0 | F31: {=_xlfn.XLOOKUP(1, (INDIRECT("'"&$C$6&"'!$6:$6")=F$6)* (INDIRECT("'"&$C$6&"'!$5:$5")=F$5), INDIRECT("'"&$C$6&"'!"&ROW()&":"&ROW()) )} -> 0 | G31: {=_xlfn.XLOOKUP(1, (INDIRECT("'"&$C$6&"'!$6:$6")=G$6)* (INDIRECT("'"&$C$6&"'!$5:$5")=G$5), INDIRECT("'"&$C$6&"'!"&ROW()&":"&ROW()) )} -> 0 | H31: {=_xlfn.XLOOKUP(1, (INDIRECT("'"&$C$6&"'!$6:$6")=H$6)* (INDIRECT("'"&$C$6&"'!$5:$5")=H$5), INDIRECT("'"&$C$6&"'!"&ROW()&":"&ROW()) )} -> 0 | I31: {=_xlfn.XLOOKUP(1, (INDIRECT("'"&$C$6&"'!$6:$6")=I$6)* (INDIRECT("'"&$C$6&"'!$5:$5")=I$5), INDIRECT("'"&$C$6&"'!"&ROW()&":"&ROW()) )} -> 0 | K31: =$D31-E31 -> 0 | L31: =$D31-F31 -> 0 | M31: =$D31-G31 -> 0 | N31: =$D31-H31 -> 0 | O31: =$D31-I31 -> 0 | Q31: =IFERROR($D31/E31-1,0) -> 0 | R31: =IFERROR($D31/F31-1,0) -> 0 | S31: =IFERROR($D31/G31-1,0) -> 0 | T31: =IFERROR($D31/H31-1,0) -> 0 | U31: =IFERROR($D31/I31-1,0) -> 0 | W31: {=INDIRECT("'"&$C$6&"'!"&ADDRESS(ROW(),COLUMN()+44))} -> 0 | X31: {=INDIRECT("'"&$C$6&"'!"&ADDRESS(ROW(),COLUMN()+44))} -> 0 | Y31: {=INDIRECT("'"&$C$6&"'!"&ADDRESS(ROW(),COLUMN()+44))} -> 0 | Z31: {=INDIRECT("'"&$C$6&"'!"&ADDRESS(ROW(),COLUMN()+44))} -> 0 | AA31: {=INDIRECT("'"&$C$6&"'!"&ADDRESS(ROW(),COLUMN()+44))} -> 0 | AB31: {=INDIRECT("'"&$C$6&"'!"&ADDRESS(ROW(),COLUMN()+44))} -> 0 | AD31: =$W31-X31 -> 0 | AE31: =$W31-Y31 -> 0 | AF31: =$W31-Z31 -> 0 | AG31: =$W31-AA31 -> 0 | AH31: =$W31-AB31 -> 0 | AJ31: =IFERROR($W31/X31-1,0) -> 0 | AK31: =IFERROR($W31/Y31-1,0) -> 0 | AL31: =IFERROR($W31/Z31-1,0) -> 0 | AM31: =IFERROR($W31/AA31-1,0) -> 0 | AN31: =IFERROR($W31/AB31-1,0) -> 0
A32: SALDO_PROM | D32: {=_xlfn.XLOOKUP(1, (INDIRECT("'"&$C$6&"'!$6:$6")=D$6)* (INDIRECT("'"&$C$6&"'!$5:$5")=D$5), INDIRECT("'"&$C$6&"'!"&ROW()&":"&ROW()) )} -> 0 | E32: {=_xlfn.XLOOKUP(1, (INDIRECT("'"&$C$6&"'!$6:$6")=E$6)* (INDIRECT("'"&$C$6&"'!$5:$5")=E$5), INDIRECT("'"&$C$6&"'!"&ROW()&":"&ROW()) )} -> 0 | F32: {=_xlfn.XLOOKUP(1, (INDIRECT("'"&$C$6&"'!$6:$6")=F$6)* (INDIRECT("'"&$C$6&"'!$5:$5")=F$5), INDIRECT("'"&$C$6&"'!"&ROW()&":"&ROW()) )} -> 0 | G32: {=_xlfn.XLOOKUP(1, (INDIRECT("'"&$C$6&"'!$6:$6")=G$6)* (INDIRECT("'"&$C$6&"'!$5:$5")=G$5), INDIRECT("'"&$C$6&"'!"&ROW()&":"&ROW()) )} -> 0 | H32: {=_xlfn.XLOOKUP(1, (INDIRECT("'"&$C$6&"'!$6:$6")=H$6)* (INDIRECT("'"&$C$6&"'!$5:$5")=H$5), INDIRECT("'"&$C$6&"'!"&ROW()&":"&ROW()) )} -> 0 | I32: {=_xlfn.XLOOKUP(1, (INDIRECT("'"&$C$6&"'!$6:$6")=I$6)* (INDIRECT("'"&$C$6&"'!$5:$5")=I$5), INDIRECT("'"&$C$6&"'!"&ROW()&":"&ROW()) )} -> 0 | K32: =$D32-E32 -> 0 | L32: =$D32-F32 -> 0 | M32: =$D32-G32 -> 0 | N32: =$D32-H32 -> 0 | O32: =$D32-I32 -> 0 | Q32: =IFERROR($D32/E32-1,0) -> 0 | R32: =IFERROR($D32/F32-1,0) -> 0 | S32: =IFERROR($D32/G32-1,0) -> 0 | T32: =IFERROR($D32/H32-1,0) -> 0 | U32: =IFERROR($D32/I32-1,0) -> 0 | W32: {=INDIRECT("'"&$C$6&"'!"&ADDRESS(ROW(),COLUMN()+44))} -> 0 | X32: {=INDIRECT("'"&$C$6&"'!"&ADDRESS(ROW(),COLUMN()+44))} -> 0 | Y32: {=INDIRECT("'"&$C$6&"'!"&ADDRESS(ROW(),COLUMN()+44))} -> 0 | Z32: {=INDIRECT("'"&$C$6&"'!"&ADDRESS(ROW(),COLUMN()+44))} -> 0 | AA32: {=INDIRECT("'"&$C$6&"'!"&ADDRESS(ROW(),COLUMN()+44))} -> 0 | AB32: {=INDIRECT("'"&$C$6&"'!"&ADDRESS(ROW(),COLUMN()+44))} -> 0 | AD32: =$W32-X32 -> 0 | AE32: =$W32-Y32 -> 0 | AF32: =$W32-Z32 -> 0 | AG32: =$W32-AA32 -> 0 | AH32: =$W32-AB32 -> 0 | AJ32: =IFERROR($W32/X32-1,0) -> 0 | AK32: =IFERROR($W32/Y32-1,0) -> 0 | AL32: =IFERROR($W32/Z32-1,0) -> 0 | AM32: =IFERROR($W32/AA32-1,0) -> 0 | AN32: =IFERROR($W32/AB32-1,0) -> 0
A33: SALDO_PROM | D33: {=_xlfn.XLOOKUP(1, (INDIRECT("'"&$C$6&"'!$6:$6")=D$6)* (INDIRECT("'"&$C$6&"'!$5:$5")=D$5), INDIRECT("'"&$C$6&"'!"&ROW()&":"&ROW()) )} -> 0 | E33: {=_xlfn.XLOOKUP(1, (INDIRECT("'"&$C$6&"'!$6:$6")=E$6)* (INDIRECT("'"&$C$6&"'!$5:$5")=E$5), INDIRECT("'"&$C$6&"'!"&ROW()&":"&ROW()) )} -> 0 | F33: {=_xlfn.XLOOKUP(1, (INDIRECT("'"&$C$6&"'!$6:$6")=F$6)* (INDIRECT("'"&$C$6&"'!$5:$5")=F$5), INDIRECT("'"&$C$6&"'!"&ROW()&":"&ROW()) )} -> 0 | G33: {=_xlfn.XLOOKUP(1, (INDIRECT("'"&$C$6&"'!$6:$6")=G$6)* (INDIRECT("'"&$C$6&"'!$5:$5")=G$5), INDIRECT("'"&$C$6&"'!"&ROW()&":"&ROW()) )} -> 0 | H33: {=_xlfn.XLOOKUP(1, (INDIRECT("'"&$C$6&"'!$6:$6")=H$6)* (INDIRECT("'"&$C$6&"'!$5:$5")=H$5), INDIRECT("'"&$C$6&"'!"&ROW()&":"&ROW()) )} -> 0 | I33: {=_xlfn.XLOOKUP(1, (INDIRECT("'"&$C$6&"'!$6:$6")=I$6)* (INDIRECT("'"&$C$6&"'!$5:$5")=I$5), INDIRECT("'"&$C$6&"'!"&ROW()&":"&ROW()) )} -> 0 | K33: =$D33-E33 -> 0 | L33: =$D33-F33 -> 0 | M33: =$D33-G33 -> 0 | N33: =$D33-H33 -> 0 | O33: =$D33-I33 -> 0 | Q33: =IFERROR($D33/E33-1,0) -> 0 | R33: =IFERROR($D33/F33-1,0) -> 0 | S33: =IFERROR($D33/G33-1,0) -> 0 | T33: =IFERROR($D33/H33-1,0) -> 0 | U33: =IFERROR($D33/I33-1,0) -> 0 | W33: {=INDIRECT("'"&$C$6&"'!"&ADDRESS(ROW(),COLUMN()+44))} -> 0 | X33: {=INDIRECT("'"&$C$6&"'!"&ADDRESS(ROW(),COLUMN()+44))} -> 0 | Y33: {=INDIRECT("'"&$C$6&"'!"&ADDRESS(ROW(),COLUMN()+44))} -> 0 | Z33: {=INDIRECT("'"&$C$6&"'!"&ADDRESS(ROW(),COLUMN()+44))} -> 0 | AA33: {=INDIRECT("'"&$C$6&"'!"&ADDRESS(ROW(),COLUMN()+44))} -> 0 | AB33: {=INDIRECT("'"&$C$6&"'!"&ADDRESS(ROW(),COLUMN()+44))} -> 0 | AD33: =$W33-X33 -> 0 | AE33: =$W33-Y33 -> 0 | AF33: =$W33-Z33 -> 0 | AG33: =$W33-AA33 -> 0 | AH33: =$W33-AB33 -> 0 | AJ33: =IFERROR($W33/X33-1,0) -> 0 | AK33: =IFERROR($W33/Y33-1,0) -> 0 | AL33: =IFERROR($W33/Z33-1,0) -> 0 | AM33: =IFERROR($W33/AA33-1,0) -> 0 | AN33: =IFERROR($W33/AB33-1,0) -> 0
A34: SALDO_PROM | D34: {=_xlfn.XLOOKUP(1, (INDIRECT("'"&$C$6&"'!$6:$6")=D$6)* (INDIRECT("'"&$C$6&"'!$5:$5")=D$5), INDIRECT("'"&$C$6&"'!"&ROW()&":"&ROW()) )} -> 0 | E34: {=_xlfn.XLOOKUP(1, (INDIRECT("'"&$C$6&"'!$6:$6")=E$6)* (INDIRECT("'"&$C$6&"'!$5:$5")=E$5), INDIRECT("'"&$C$6&"'!"&ROW()&":"&ROW()) )} -> 0 | F34: {=_xlfn.XLOOKUP(1, (INDIRECT("'"&$C$6&"'!$6:$6")=F$6)* (INDIRECT("'"&$C$6&"'!$5:$5")=F$5), INDIRECT("'"&$C$6&"'!"&ROW()&":"&ROW()) )} -> 0 | G34: {=_xlfn.XLOOKUP(1, (INDIRECT("'"&$C$6&"'!$6:$6")=G$6)* (INDIRECT("'"&$C$6&"'!$5:$5")=G$5), INDIRECT("'"&$C$6&"'!"&ROW()&":"&ROW()) )} -> 0 | H34: {=_xlfn.XLOOKUP(1, (INDIRECT("'"&$C$6&"'!$6:$6")=H$6)* (INDIRECT("'"&$C$6&"'!$5:$5")=H$5), INDIRECT("'"&$C$6&"'!"&ROW()&":"&ROW()) )} -> 0 | I34: {=_xlfn.XLOOKUP(1, (INDIRECT("'"&$C$6&"'!$6:$6")=I$6)* (INDIRECT("'"&$C$6&"'!$5:$5")=I$5), INDIRECT("'"&$C$6&"'!"&ROW()&":"&ROW()) )} -> 0 | K34: =$D34-E34 -> 0 | L34: =$D34-F34 -> 0 | M34: =$D34-G34 -> 0 | N34: =$D34-H34 -> 0 | O34: =$D34-I34 -> 0 | Q34: =IFERROR($D34/E34-1,0) -> 0 | R34: =IFERROR($D34/F34-1,0) -> 0 | S34: =IFERROR($D34/G34-1,0) -> 0 | T34: =IFERROR($D34/H34-1,0) -> 0 | U34: =IFERROR($D34/I34-1,0) -> 0 | W34: {=INDIRECT("'"&$C$6&"'!"&ADDRESS(ROW(),COLUMN()+44))} -> 0 | X34: {=INDIRECT("'"&$C$6&"'!"&ADDRESS(ROW(),COLUMN()+44))} -> 0 | Y34: {=INDIRECT("'"&$C$6&"'!"&ADDRESS(ROW(),COLUMN()+44))} -> 0 | Z34: {=INDIRECT("'"&$C$6&"'!"&ADDRESS(ROW(),COLUMN()+44))} -> 0 | AA34: {=INDIRECT("'"&$C$6&"'!"&ADDRESS(ROW(),COLUMN()+44))} -> 0 | AB34: {=INDIRECT("'"&$C$6&"'!"&ADDRESS(ROW(),COLUMN()+44))} -> 0 | AD34: =$W34-X34 -> 0 | AE34: =$W34-Y34 -> 0 | AF34: =$W34-Z34 -> 0 | AG34: =$W34-AA34 -> 0 | AH34: =$W34-AB34 -> 0 | AJ34: =IFERROR($W34/X34-1,0) -> 0 | AK34: =IFERROR($W34/Y34-1,0) -> 0 | AL34: =IFERROR($W34/Z34-1,0) -> 0 | AM34: =IFERROR($W34/AA34-1,0) -> 0 | AN34: =IFERROR($W34/AB34-1,0) -> 0
A35: SALDO_PROM | D35: =SUM(D27:D34) -> 0 | E35: =SUM(E27:E34) -> 1758240.1 | F35: =SUM(F27:F34) -> 0 | G35: =SUM(G27:G34) -> 0 | H35: =SUM(H27:H34) -> 0 | I35: =SUM(I27:I34) -> 0 | K35: =$D35-E35 -> -1758240.1 | L35: =$D35-F35 -> 0 | M35: =$D35-G35 -> 0 | N35: =$D35-H35 -> 0 | O35: =$D35-I35 -> 0 | Q35: =IFERROR($D35/E35-1,0) -> -1 | R35: =IFERROR($D35/F35-1,0) -> 0 | S35: =IFERROR($D35/G35-1,0) -> 0 | T35: =IFERROR($D35/H35-1,0) -> 0 | U35: =IFERROR($D35/I35-1,0) -> 0 | W35: =SUM(W27:W34) -> 0 | X35: =SUM(X27:X34) -> 1777154.7 | Y35: =SUM(Y27:Y34) -> 0 | Z35: =SUM(Z27:Z34) -> 0 | AA35: =SUM(AA27:AA34) -> 0 | AB35: =SUM(AB27:AB34) -> 0 | AD35: =$W35-X35 -> -1777154.7 | AE35: =$W35-Y35 -> 0 | AF35: =$W35-Z35 -> 0 | AG35: =$W35-AA35 -> 0 | AH35: =$W35-AB35 -> 0 | AJ35: =IFERROR($W35/X35-1,0) -> -1 | AK35: =IFERROR($W35/Y35-1,0) -> 0 | AL35: =IFERROR($W35/Z35-1,0) -> 0 | AM35: =IFERROR($W35/AA35-1,0) -> 0 | AN35: =IFERROR($W35/AB35-1,0) -> 0
A36: SALDO_PROM | D36: {=_xlfn.XLOOKUP(1, (INDIRECT("'"&$C$6&"'!$6:$6")=D$6)* (INDIRECT("'"&$C$6&"'!$5:$5")=D$5), INDIRECT("'"&$C$6&"'!"&ROW()&":"&ROW()) )} -> 0 | E36: {=_xlfn.XLOOKUP(1, (INDIRECT("'"&$C$6&"'!$6:$6")=E$6)* (INDIRECT("'"&$C$6&"'!$5:$5")=E$5), INDIRECT("'"&$C$6&"'!"&ROW()&":"&ROW()) )} -> 0 | F36: {=_xlfn.XLOOKUP(1, (INDIRECT("'"&$C$6&"'!$6:$6")=F$6)* (INDIRECT("'"&$C$6&"'!$5:$5")=F$5), INDIRECT("'"&$C$6&"'!"&ROW()&":"&ROW()) )} -> 0 | G36: {=_xlfn.XLOOKUP(1, (INDIRECT("'"&$C$6&"'!$6:$6")=G$6)* (INDIRECT("'"&$C$6&"'!$5:$5")=G$5), INDIRECT("'"&$C$6&"'!"&ROW()&":"&ROW()) )} -> 0 | H36: {=_xlfn.XLOOKUP(1, (INDIRECT("'"&$C$6&"'!$6:$6")=H$6)* (INDIRECT("'"&$C$6&"'!$5:$5")=H$5), INDIRECT("'"&$C$6&"'!"&ROW()&":"&ROW()) )} -> 0 | I36: {=_xlfn.XLOOKUP(1, (INDIRECT("'"&$C$6&"'!$6:$6")=I$6)* (INDIRECT("'"&$C$6&"'!$5:$5")=I$5), INDIRECT("'"&$C$6&"'!"&ROW()&":"&ROW()) )} -> 0 | K36: =$D36-E36 -> 0 | L36: =$D36-F36 -> 0 | M36: =$D36-G36 -> 0 | N36: =$D36-H36 -> 0 | O36: =$D36-I36 -> 0 | Q36: =IFERROR($D36/E36-1,0) -> 0 | R36: =IFERROR($D36/F36-1,0) -> 0 | S36: =IFERROR($D36/G36-1,0) -> 0 | T36: =IFERROR($D36/H36-1,0) -> 0 | U36: =IFERROR($D36/I36-1,0) -> 0 | W36: {=INDIRECT("'"&$C$6&"'!"&ADDRESS(ROW(),COLUMN()+44))} -> 0 | X36: {=INDIRECT("'"&$C$6&"'!"&ADDRESS(ROW(),COLUMN()+44))} -> 0 | Y36: {=INDIRECT("'"&$C$6&"'!"&ADDRESS(ROW(),COLUMN()+44))} -> 0 | Z36: {=INDIRECT("'"&$C$6&"'!"&ADDRESS(ROW(),COLUMN()+44))} -> 0 | AA36: {=INDIRECT("'"&$C$6&"'!"&ADDRESS(ROW(),COLUMN()+44))} -> 0 | AB36: {=INDIRECT("'"&$C$6&"'!"&ADDRESS(ROW(),COLUMN()+44))} -> 0 | AD36: =$W36-X36 -> 0 | AE36: =$W36-Y36 -> 0 | AF36: =$W36-Z36 -> 0 | AG36: =$W36-AA36 -> 0 | AH36: =$W36-AB36 -> 0 | AJ36: =IFERROR($W36/X36-1,0) -> 0 | AK36: =IFERROR($W36/Y36-1,0) -> 0 | AL36: =IFERROR($W36/Z36-1,0) -> 0 | AM36: =IFERROR($W36/AA36-1,0) -> 0 | AN36: =IFERROR($W36/AB36-1,0) -> 0
A37: SALDO_PROM | D37: {=_xlfn.XLOOKUP(1, (INDIRECT("'"&$C$6&"'!$6:$6")=D$6)* (INDIRECT("'"&$C$6&"'!$5:$5")=D$5), INDIRECT("'"&$C$6&"'!"&ROW()&":"&ROW()) )} -> 0 | E37: {=_xlfn.XLOOKUP(1, (INDIRECT("'"&$C$6&"'!$6:$6")=E$6)* (INDIRECT("'"&$C$6&"'!$5:$5")=E$5), INDIRECT("'"&$C$6&"'!"&ROW()&":"&ROW()) )} -> 0 | F37: {=_xlfn.XLOOKUP(1, (INDIRECT("'"&$C$6&"'!$6:$6")=F$6)* (INDIRECT("'"&$C$6&"'!$5:$5")=F$5), INDIRECT("'"&$C$6&"'!"&ROW()&":"&ROW()) )} -> 0 | G37: {=_xlfn.XLOOKUP(1, (INDIRECT("'"&$C$6&"'!$6:$6")=G$6)* (INDIRECT("'"&$C$6&"'!$5:$5")=G$5), INDIRECT("'"&$C$6&"'!"&ROW()&":"&ROW()) )} -> 0 | H37: {=_xlfn.XLOOKUP(1, (INDIRECT("'"&$C$6&"'!$6:$6")=H$6)* (INDIRECT("'"&$C$6&"'!$5:$5")=H$5), INDIRECT("'"&$C$6&"'!"&ROW()&":"&ROW()) )} -> 0 | I37: {=_xlfn.XLOOKUP(1, (INDIRECT("'"&$C$6&"'!$6:$6")=I$6)* (INDIRECT("'"&$C$6&"'!$5:$5")=I$5), INDIRECT("'"&$C$6&"'!"&ROW()&":"&ROW()) )} -> 0 | K37: =$D37-E37 -> 0 | L37: =$D37-F37 -> 0 | M37: =$D37-G37 -> 0 | N37: =$D37-H37 -> 0 | O37: =$D37-I37 -> 0 | Q37: =IFERROR($D37/E37-1,0) -> 0 | R37: =IFERROR($D37/F37-1,0) -> 0 | S37: =IFERROR($D37/G37-1,0) -> 0 | T37: =IFERROR($D37/H37-1,0) -> 0 | U37: =IFERROR($D37/I37-1,0) -> 0 | W37: {=INDIRECT("'"&$C$6&"'!"&ADDRESS(ROW(),COLUMN()+44))} -> 0 | X37: {=INDIRECT("'"&$C$6&"'!"&ADDRESS(ROW(),COLUMN()+44))} -> 0 | Y37: {=INDIRECT("'"&$C$6&"'!"&ADDRESS(ROW(),COLUMN()+44))} -> 0 | Z37: {=INDIRECT("'"&$C$6&"'!"&ADDRESS(ROW(),COLUMN()+44))} -> 0 | AA37: {=INDIRECT("'"&$C$6&"'!"&ADDRESS(ROW(),COLUMN()+44))} -> 0 | AB37: {=INDIRECT("'"&$C$6&"'!"&ADDRESS(ROW(),COLUMN()+44))} -> 0 | AD37: =$W37-X37 -> 0 | AE37: =$W37-Y37 -> 0 | AF37: =$W37-Z37 -> 0 | AG37: =$W37-AA37 -> 0 | AH37: =$W37-AB37 -> 0 | AJ37: =IFERROR($W37/X37-1,0) -> 0 | AK37: =IFERROR($W37/Y37-1,0) -> 0 | AL37: =IFERROR($W37/Z37-1,0) -> 0 | AM37: =IFERROR($W37/AA37-1,0) -> 0 | AN37: =IFERROR($W37/AB37-1,0) -> 0
A38: SALDO_PROM | D38: {=_xlfn.XLOOKUP(1, (INDIRECT("'"&$C$6&"'!$6:$6")=D$6)* (INDIRECT("'"&$C$6&"'!$5:$5")=D$5), INDIRECT("'"&$C$6&"'!"&ROW()&":"&ROW()) )} -> 0 | E38: {=_xlfn.XLOOKUP(1, (INDIRECT("'"&$C$6&"'!$6:$6")=E$6)* (INDIRECT("'"&$C$6&"'!$5:$5")=E$5), INDIRECT("'"&$C$6&"'!"&ROW()&":"&ROW()) )} -> 0 | F38: {=_xlfn.XLOOKUP(1, (INDIRECT("'"&$C$6&"'!$6:$6")=F$6)* (INDIRECT("'"&$C$6&"'!$5:$5")=F$5), INDIRECT("'"&$C$6&"'!"&ROW()&":"&ROW()) )} -> 0 | G38: {=_xlfn.XLOOKUP(1, (INDIRECT("'"&$C$6&"'!$6:$6")=G$6)* (INDIRECT("'"&$C$6&"'!$5:$5")=G$5), INDIRECT("'"&$C$6&"'!"&ROW()&":"&ROW()) )} -> 0 | H38: {=_xlfn.XLOOKUP(1, (INDIRECT("'"&$C$6&"'!$6:$6")=H$6)* (INDIRECT("'"&$C$6&"'!$5:$5")=H$5), INDIRECT("'"&$C$6&"'!"&ROW()&":"&ROW()) )} -> 0 | I38: {=_xlfn.XLOOKUP(1, (INDIRECT("'"&$C$6&"'!$6:$6")=I$6)* (INDIRECT("'"&$C$6&"'!$5:$5")=I$5), INDIRECT("'"&$C$6&"'!"&ROW()&":"&ROW()) )} -> 0 | K38: =$D38-E38 -> 0 | L38: =$D38-F38 -> 0 | M38: =$D38-G38 -> 0 | N38: =$D38-H38 -> 0 | O38: =$D38-I38 -> 0 | Q38: =IFERROR($D38/E38-1,0) -> 0 | R38: =IFERROR($D38/F38-1,0) -> 0 | S38: =IFERROR($D38/G38-1,0) -> 0 | T38: =IFERROR($D38/H38-1,0) -> 0 | U38: =IFERROR($D38/I38-1,0) -> 0 | W38: {=INDIRECT("'"&$C$6&"'!"&ADDRESS(ROW(),COLUMN()+44))} -> 0 | X38: {=INDIRECT("'"&$C$6&"'!"&ADDRESS(ROW(),COLUMN()+44))} -> 0 | Y38: {=INDIRECT("'"&$C$6&"'!"&ADDRESS(ROW(),COLUMN()+44))} -> 0 | Z38: {=INDIRECT("'"&$C$6&"'!"&ADDRESS(ROW(),COLUMN()+44))} -> 0 | AA38: {=INDIRECT("'"&$C$6&"'!"&ADDRESS(ROW(),COLUMN()+44))} -> 0 | AB38: {=INDIRECT("'"&$C$6&"'!"&ADDRESS(ROW(),COLUMN()+44))} -> 0 | AD38: =$W38-X38 -> 0 | AE38: =$W38-Y38 -> 0 | AF38: =$W38-Z38 -> 0 | AG38: =$W38-AA38 -> 0 | AH38: =$W38-AB38 -> 0 | AJ38: =IFERROR($W38/X38-1,0) -> 0 | AK38: =IFERROR($W38/Y38-1,0) -> 0 | AL38: =IFERROR($W38/Z38-1,0) -> 0 | AM38: =IFERROR($W38/AA38-1,0) -> 0 | AN38: =IFERROR($W38/AB38-1,0) -> 0
A39: SALDO_PROM | D39: {=_xlfn.XLOOKUP(1, (INDIRECT("'"&$C$6&"'!$6:$6")=D$6)* (INDIRECT("'"&$C$6&"'!$5:$5")=D$5), INDIRECT("'"&$C$6&"'!"&ROW()&":"&ROW()) )} -> 0 | E39: {=_xlfn.XLOOKUP(1, (INDIRECT("'"&$C$6&"'!$6:$6")=E$6)* (INDIRECT("'"&$C$6&"'!$5:$5")=E$5), INDIRECT("'"&$C$6&"'!"&ROW()&":"&ROW()) )} -> 0 | F39: {=_xlfn.XLOOKUP(1, (INDIRECT("'"&$C$6&"'!$6:$6")=F$6)* (INDIRECT("'"&$C$6&"'!$5:$5")=F$5), INDIRECT("'"&$C$6&"'!"&ROW()&":"&ROW()) )} -> 0 | G39: {=_xlfn.XLOOKUP(1, (INDIRECT("'"&$C$6&"'!$6:$6")=G$6)* (INDIRECT("'"&$C$6&"'!$5:$5")=G$5), INDIRECT("'"&$C$6&"'!"&ROW()&":"&ROW()) )} -> 0 | H39: {=_xlfn.XLOOKUP(1, (INDIRECT("'"&$C$6&"'!$6:$6")=H$6)* (INDIRECT("'"&$C$6&"'!$5:$5")=H$5), INDIRECT("'"&$C$6&"'!"&ROW()&":"&ROW()) )} -> 0 | I39: {=_xlfn.XLOOKUP(1, (INDIRECT("'"&$C$6&"'!$6:$6")=I$6)* (INDIRECT("'"&$C$6&"'!$5:$5")=I$5), INDIRECT("'"&$C$6&"'!"&ROW()&":"&ROW()) )} -> 0 | K39: =$D39-E39 -> 0 | L39: =$D39-F39 -> 0 | M39: =$D39-G39 -> 0 | N39: =$D39-H39 -> 0 | O39: =$D39-I39 -> 0 | Q39: =IFERROR($D39/E39-1,0) -> 0 | R39: =IFERROR($D39/F39-1,0) -> 0 | S39: =IFERROR($D39/G39-1,0) -> 0 | T39: =IFERROR($D39/H39-1,0) -> 0 | U39: =IFERROR($D39/I39-1,0) -> 0 | W39: {=INDIRECT("'"&$C$6&"'!"&ADDRESS(ROW(),COLUMN()+44))} -> 0 | X39: {=INDIRECT("'"&$C$6&"'!"&ADDRESS(ROW(),COLUMN()+44))} -> 0 | Y39: {=INDIRECT("'"&$C$6&"'!"&ADDRESS(ROW(),COLUMN()+44))} -> 0 | Z39: {=INDIRECT("'"&$C$6&"'!"&ADDRESS(ROW(),COLUMN()+44))} -> 0 | AA39: {=INDIRECT("'"&$C$6&"'!"&ADDRESS(ROW(),COLUMN()+44))} -> 0 | AB39: {=INDIRECT("'"&$C$6&"'!"&ADDRESS(ROW(),COLUMN()+44))} -> 0 | AD39: =$W39-X39 -> 0 | AE39: =$W39-Y39 -> 0 | AF39: =$W39-Z39 -> 0 | AG39: =$W39-AA39 -> 0 | AH39: =$W39-AB39 -> 0 | AJ39: =IFERROR($W39/X39-1,0) -> 0 | AK39: =IFERROR($W39/Y39-1,0) -> 0 | AL39: =IFERROR($W39/Z39-1,0) -> 0 | AM39: =IFERROR($W39/AA39-1,0) -> 0 | AN39: =IFERROR($W39/AB39-1,0) -> 0
A40: SALDO_PROM | D40: {=_xlfn.XLOOKUP(1, (INDIRECT("'"&$C$6&"'!$6:$6")=D$6)* (INDIRECT("'"&$C$6&"'!$5:$5")=D$5), INDIRECT("'"&$C$6&"'!"&ROW()&":"&ROW()) )} -> 0 | E40: {=_xlfn.XLOOKUP(1, (INDIRECT("'"&$C$6&"'!$6:$6")=E$6)* (INDIRECT("'"&$C$6&"'!$5:$5")=E$5), INDIRECT("'"&$C$6&"'!"&ROW()&":"&ROW()) )} -> 0 | F40: {=_xlfn.XLOOKUP(1, (INDIRECT("'"&$C$6&"'!$6:$6")=F$6)* (INDIRECT("'"&$C$6&"'!$5:$5")=F$5), INDIRECT("'"&$C$6&"'!"&ROW()&":"&ROW()) )} -> 0 | G40: {=_xlfn.XLOOKUP(1, (INDIRECT("'"&$C$6&"'!$6:$6")=G$6)* (INDIRECT("'"&$C$6&"'!$5:$5")=G$5), INDIRECT("'"&$C$6&"'!"&ROW()&":"&ROW()) )} -> 0 | H40: {=_xlfn.XLOOKUP(1, (INDIRECT("'"&$C$6&"'!$6:$6")=H$6)* (INDIRECT("'"&$C$6&"'!$5:$5")=H$5), INDIRECT("'"&$C$6&"'!"&ROW()&":"&ROW()) )} -> 0 | I40: {=_xlfn.XLOOKUP(1, (INDIRECT("'"&$C$6&"'!$6:$6")=I$6)* (INDIRECT("'"&$C$6&"'!$5:$5")=I$5), INDIRECT("'"&$C$6&"'!"&ROW()&":"&ROW()) )} -> 0 | K40: =$D40-E40 -> 0 | L40: =$D40-F40 -> 0 | M40: =$D40-G40 -> 0 | N40: =$D40-H40 -> 0 | O40: =$D40-I40 -> 0 | Q40: =IFERROR($D40/E40-1,0) -> 0 | R40: =IFERROR($D40/F40-1,0) -> 0 | S40: =IFERROR($D40/G40-1,0) -> 0 | T40: =IFERROR($D40/H40-1,0) -> 0 | U40: =IFERROR($D40/I40-1,0) -> 0 | W40: {=INDIRECT("'"&$C$6&"'!"&ADDRESS(ROW(),COLUMN()+44))} -> 0 | X40: {=INDIRECT("'"&$C$6&"'!"&ADDRESS(ROW(),COLUMN()+44))} -> 0 | Y40: {=INDIRECT("'"&$C$6&"'!"&ADDRESS(ROW(),COLUMN()+44))} -> 0 | Z40: {=INDIRECT("'"&$C$6&"'!"&ADDRESS(ROW(),COLUMN()+44))} -> 0 | AA40: {=INDIRECT("'"&$C$6&"'!"&ADDRESS(ROW(),COLUMN()+44))} -> 0 | AB40: {=INDIRECT("'"&$C$6&"'!"&ADDRESS(ROW(),COLUMN()+44))} -> 0 | AD40: =$W40-X40 -> 0 | AE40: =$W40-Y40 -> 0 | AF40: =$W40-Z40 -> 0 | AG40: =$W40-AA40 -> 0 | AH40: =$W40-AB40 -> 0 | AJ40: =IFERROR($W40/X40-1,0) -> 0 | AK40: =IFERROR($W40/Y40-1,0) -> 0 | AL40: =IFERROR($W40/Z40-1,0) -> 0 | AM40: =IFERROR($W40/AA40-1,0) -> 0 | AN40: =IFERROR($W40/AB40-1,0) -> 0
A41: SALDO_PROM | D41: {=_xlfn.XLOOKUP(1, (INDIRECT("'"&$C$6&"'!$6:$6")=D$6)* (INDIRECT("'"&$C$6&"'!$5:$5")=D$5), INDIRECT("'"&$C$6&"'!"&ROW()&":"&ROW()) )} -> 0 | E41: {=_xlfn.XLOOKUP(1, (INDIRECT("'"&$C$6&"'!$6:$6")=E$6)* (INDIRECT("'"&$C$6&"'!$5:$5")=E$5), INDIRECT("'"&$C$6&"'!"&ROW()&":"&ROW()) )} -> 0 | F41: {=_xlfn.XLOOKUP(1, (INDIRECT("'"&$C$6&"'!$6:$6")=F$6)* (INDIRECT("'"&$C$6&"'!$5:$5")=F$5), INDIRECT("'"&$C$6&"'!"&ROW()&":"&ROW()) )} -> 0 | G41: {=_xlfn.XLOOKUP(1, (INDIRECT("'"&$C$6&"'!$6:$6")=G$6)* (INDIRECT("'"&$C$6&"'!$5:$5")=G$5), INDIRECT("'"&$C$6&"'!"&ROW()&":"&ROW()) )} -> 0 | H41: {=_xlfn.XLOOKUP(1, (INDIRECT("'"&$C$6&"'!$6:$6")=H$6)* (INDIRECT("'"&$C$6&"'!$5:$5")=H$5), INDIRECT("'"&$C$6&"'!"&ROW()&":"&ROW()) )} -> 0 | I41: {=_xlfn.XLOOKUP(1, (INDIRECT("'"&$C$6&"'!$6:$6")=I$6)* (INDIRECT("'"&$C$6&"'!$5:$5")=I$5), INDIRECT("'"&$C$6&"'!"&ROW()&":"&ROW()) )} -> 0 | K41: =$D41-E41 -> 0 | L41: =$D41-F41 -> 0 | M41: =$D41-G41 -> 0 | N41: =$D41-H41 -> 0 | O41: =$D41-I41 -> 0 | Q41: =IFERROR($D41/E41-1,0) -> 0 | R41: =IFERROR($D41/F41-1,0) -> 0 | S41: =IFERROR($D41/G41-1,0) -> 0 | T41: =IFERROR($D41/H41-1,0) -> 0 | U41: =IFERROR($D41/I41-1,0) -> 0 | W41: {=INDIRECT("'"&$C$6&"'!"&ADDRESS(ROW(),COLUMN()+44))} -> 0 | X41: {=INDIRECT("'"&$C$6&"'!"&ADDRESS(ROW(),COLUMN()+44))} -> 0 | Y41: {=INDIRECT("'"&$C$6&"'!"&ADDRESS(ROW(),COLUMN()+44))} -> 0 | Z41: {=INDIRECT("'"&$C$6&"'!"&ADDRESS(ROW(),COLUMN()+44))} -> 0 | AA41: {=INDIRECT("'"&$C$6&"'!"&ADDRESS(ROW(),COLUMN()+44))} -> 0 | AB41: {=INDIRECT("'"&$C$6&"'!"&ADDRESS(ROW(),COLUMN()+44))} -> 0 | AD41: =$W41-X41 -> 0 | AE41: =$W41-Y41 -> 0 | AF41: =$W41-Z41 -> 0 | AG41: =$W41-AA41 -> 0 | AH41: =$W41-AB41 -> 0 | AJ41: =IFERROR($W41/X41-1,0) -> 0 | AK41: =IFERROR($W41/Y41-1,0) -> 0 | AL41: =IFERROR($W41/Z41-1,0) -> 0 | AM41: =IFERROR($W41/AA41-1,0) -> 0 | AN41: =IFERROR($W41/AB41-1,0) -> 0
A42: SALDO_PROM | D42: =SUM(D40:D41) -> 0 | E42: =SUM(E40:E41) -> 0 | F42: =SUM(F40:F41) -> 0 | G42: =SUM(G40:G41) -> 0 | H42: =SUM(H40:H41) -> 0 | I42: =SUM(I40:I41) -> 0 | K42: =$D42-E42 -> 0 | L42: =$D42-F42 -> 0 | M42: =$D42-G42 -> 0 | N42: =$D42-H42 -> 0 | O42: =$D42-I42 -> 0 | Q42: =IFERROR($D42/E42-1,0) -> 0 | R42: =IFERROR($D42/F42-1,0) -> 0 | S42: =IFERROR($D42/G42-1,0) -> 0 | T42: =IFERROR($D42/H42-1,0) -> 0 | U42: =IFERROR($D42/I42-1,0) -> 0 | W42: =SUM(W40:W41) -> 0 | X42: =SUM(X40:X41) -> 0 | Y42: =SUM(Y40:Y41) -> 0 | Z42: =SUM(Z40:Z41) -> 0 | AA42: =SUM(AA40:AA41) -> 0 | AB42: =SUM(AB40:AB41) -> 0 | AD42: =$W42-X42 -> 0 | AE42: =$W42-Y42 -> 0 | AF42: =$W42-Z42 -> 0 | AG42: =$W42-AA42 -> 0 | AH42: =$W42-AB42 -> 0 | AJ42: =IFERROR($W42/X42-1,0) -> 0 | AK42: =IFERROR($W42/Y42-1,0) -> 0 | AL42: =IFERROR($W42/Z42-1,0) -> 0 | AM42: =IFERROR($W42/AA42-1,0) -> 0 | AN42: =IFERROR($W42/AB42-1,0) -> 0
C43: Saldo Prom | D43: =SUM(D35,D36:D39,D42) -> 0 | E43: =SUM(E35,E36:E39,E42) -> 1758240.1 | F43: =SUM(F35,F36:F39,F42) -> 0 | G43: =SUM(G35,G36:G39,G42) -> 0 | H43: =SUM(H35,H36:H39,H42) -> 0 | I43: =SUM(I35,I36:I39,I42) -> 0 | K43: =$D43-E43 -> -1758240.1 | L43: =$D43-F43 -> 0 | M43: =$D43-G43 -> 0 | N43: =$D43-H43 -> 0 | O43: =$D43-I43 -> 0 | Q43: =IFERROR($D43/E43-1,0) -> -1 | R43: =IFERROR($D43/F43-1,0) -> 0 | S43: =IFERROR($D43/G43-1,0) -> 0 | T43: =IFERROR($D43/H43-1,0) -> 0 | U43: =IFERROR($D43/I43-1,0) -> 0 | W43: =SUM(W35,W36:W39,W42) -> 0 | X43: =SUM(X35,X36:X39,X42) -> 1777154.7 | Y43: =SUM(Y35,Y36:Y39,Y42) -> 0 | Z43: =SUM(Z35,Z36:Z39,Z42) -> 0 | AA43: =SUM(AA35,AA36:AA39,AA42) -> 0 | AB43: =SUM(AB35,AB36:AB39,AB42) -> 0 | AD43: =$W43-X43 -> -1777154.7 | AE43: =$W43-Y43 -> 0 | AF43: =$W43-Z43 -> 0 | AG43: =$W43-AA43 -> 0 | AH43: =$W43-AB43 -> 0 | AJ43: =IFERROR($W43/X43-1,0) -> -1 | AK43: =IFERROR($W43/Y43-1,0) -> 0 | AL43: =IFERROR($W43/Z43-1,0) -> 0 | AM43: =IFERROR($W43/AA43-1,0) -> 0 | AN43: =IFERROR($W43/AB43-1,0) -> 0
C46: Cuenta Sueldo | D46: =IFERROR(((1+D103/D27)^(360/D$3))-1,0) -> 0 | E46: =IFERROR(((1+E103/E27)^(360/E$3))-1,0) -> 0.042497138 | F46: =IFERROR(((1+F103/F27)^(360/F$3))-1,0) -> 0 | G46: =IFERROR(((1+G103/G27)^(360/G$3))-1,0) -> 0 | H46: =IFERROR(((1+H103/H27)^(360/H$3))-1,0) -> 0 | I46: =IFERROR(((1+I103/I27)^(360/I$3))-1,0) -> 0 | Q46: =($D46-E46)*10000 -> -424.97138 | R46: =($D46-F46)*10000 -> 0 | S46: =($D46-G46)*10000 -> 0 | T46: =($D46-H46)*10000 -> 0 | U46: =($D46-I46)*10000 -> 0 | W46: {=INDIRECT("'"&$C$6&"'!"&ADDRESS(ROW(),COLUMN()+44))} -> 0 | X46: {=INDIRECT("'"&$C$6&"'!"&ADDRESS(ROW(),COLUMN()+44))} -> 0.04252755 | Y46: {=INDIRECT("'"&$C$6&"'!"&ADDRESS(ROW(),COLUMN()+44))} -> 0 | Z46: {=INDIRECT("'"&$C$6&"'!"&ADDRESS(ROW(),COLUMN()+44))} -> 0 | AA46: {=INDIRECT("'"&$C$6&"'!"&ADDRESS(ROW(),COLUMN()+44))} -> 0 | AB46: {=INDIRECT("'"&$C$6&"'!"&ADDRESS(ROW(),COLUMN()+44))} -> 0 | AJ46: =($W46-X46)*10000 -> -425.2755 | AK46: =($W46-Y46)*10000 -> 0 | AL46: =($W46-Z46)*10000 -> 0 | AM46: =($W46-AA46)*10000 -> 0 | AN46: =($W46-AB46)*10000 -> 0
D47: =IFERROR(((1+D104/D28)^(360/D$3))-1,0) -> 0 | E47: =IFERROR(((1+E104/E28)^(360/E$3))-1,0) -> 0 | F47: =IFERROR(((1+F104/F28)^(360/F$3))-1,0) -> 0 | G47: =IFERROR(((1+G104/G28)^(360/G$3))-1,0) -> 0 | H47: =IFERROR(((1+H104/H28)^(360/H$3))-1,0) -> 0 | I47: =IFERROR(((1+I104/I28)^(360/I$3))-1,0) -> 0 | Q47: =($D47-E47)*10000 -> 0 | R47: =($D47-F47)*10000 -> 0 | S47: =($D47-G47)*10000 -> 0 | T47: =($D47-H47)*10000 -> 0 | U47: =($D47-I47)*10000 -> 0 | W47: {=INDIRECT("'"&$C$6&"'!"&ADDRESS(ROW(),COLUMN()+44))} -> 0 | X47: {=INDIRECT("'"&$C$6&"'!"&ADDRESS(ROW(),COLUMN()+44))} -> 0 | Y47: {=INDIRECT("'"&$C$6&"'!"&ADDRESS(ROW(),COLUMN()+44))} -> 0 | Z47: {=INDIRECT("'"&$C$6&"'!"&ADDRESS(ROW(),COLUMN()+44))} -> 0 | AA47: {=INDIRECT("'"&$C$6&"'!"&ADDRESS(ROW(),COLUMN()+44))} -> 0 | AB47: {=INDIRECT("'"&$C$6&"'!"&ADDRESS(ROW(),COLUMN()+44))} -> 0 | AJ47: =($W47-X47)*10000 -> 0 | AK47: =($W47-Y47)*10000 -> 0 | AL47: =($W47-Z47)*10000 -> 0 | AM47: =($W47-AA47)*10000 -> 0 | AN47: =($W47-AB47)*10000 -> 0
D48: =IFERROR(((1+D105/D29)^(360/D$3))-1,0) -> 0 | E48: =IFERROR(((1+E105/E29)^(360/E$3))-1,0) -> 0 | F48: =IFERROR(((1+F105/F29)^(360/F$3))-1,0) -> 0 | G48: =IFERROR(((1+G105/G29)^(360/G$3))-1,0) -> 0 | H48: =IFERROR(((1+H105/H29)^(360/H$3))-1,0) -> 0 | I48: =IFERROR(((1+I105/I29)^(360/I$3))-1,0) -> 0 | Q48: =($D48-E48)*10000 -> 0 | R48: =($D48-F48)*10000 -> 0 | S48: =($D48-G48)*10000 -> 0 | T48: =($D48-H48)*10000 -> 0 | U48: =($D48-I48)*10000 -> 0 | W48: {=INDIRECT("'"&$C$6&"'!"&ADDRESS(ROW(),COLUMN()+44))} -> 0 | X48: {=INDIRECT("'"&$C$6&"'!"&ADDRESS(ROW(),COLUMN()+44))} -> 0 | Y48: {=INDIRECT("'"&$C$6&"'!"&ADDRESS(ROW(),COLUMN()+44))} -> 0 | Z48: {=INDIRECT("'"&$C$6&"'!"&ADDRESS(ROW(),COLUMN()+44))} -> 0 | AA48: {=INDIRECT("'"&$C$6&"'!"&ADDRESS(ROW(),COLUMN()+44))} -> 0 | AB48: {=INDIRECT("'"&$C$6&"'!"&ADDRESS(ROW(),COLUMN()+44))} -> 0 | AJ48: =($W48-X48)*10000 -> 0 | AK48: =($W48-Y48)*10000 -> 0 | AL48: =($W48-Z48)*10000 -> 0 | AM48: =($W48-AA48)*10000 -> 0 | AN48: =($W48-AB48)*10000 -> 0
D49: =IFERROR(((1+D106/D30)^(360/D$3))-1,0) -> 0 | E49: =IFERROR(((1+E106/E30)^(360/E$3))-1,0) -> 0 | F49: =IFERROR(((1+F106/F30)^(360/F$3))-1,0) -> 0 | G49: =IFERROR(((1+G106/G30)^(360/G$3))-1,0) -> 0 | H49: =IFERROR(((1+H106/H30)^(360/H$3))-1,0) -> 0 | I49: =IFERROR(((1+I106/I30)^(360/I$3))-1,0) -> 0 | Q49: =($D49-E49)*10000 -> 0 | R49: =($D49-F49)*10000 -> 0 | S49: =($D49-G49)*10000 -> 0 | T49: =($D49-H49)*10000 -> 0 | U49: =($D49-I49)*10000 -> 0 | W49: {=INDIRECT("'"&$C$6&"'!"&ADDRESS(ROW(),COLUMN()+44))} -> 0 | X49: {=INDIRECT("'"&$C$6&"'!"&ADDRESS(ROW(),COLUMN()+44))} -> 0 | Y49: {=INDIRECT("'"&$C$6&"'!"&ADDRESS(ROW(),COLUMN()+44))} -> 0 | Z49: {=INDIRECT("'"&$C$6&"'!"&ADDRESS(ROW(),COLUMN()+44))} -> 0 | AA49: {=INDIRECT("'"&$C$6&"'!"&ADDRESS(ROW(),COLUMN()+44))} -> 0 | AB49: {=INDIRECT("'"&$C$6&"'!"&ADDRESS(ROW(),COLUMN()+44))} -> 0 | AJ49: =($W49-X49)*10000 -> 0 | AK49: =($W49-Y49)*10000 -> 0 | AL49: =($W49-Z49)*10000 -> 0 | AM49: =($W49-AA49)*10000 -> 0 | AN49: =($W49-AB49)*10000 -> 0
D50: =IFERROR(((1+D107/D31)^(360/D$3))-1,0) -> 0 | E50: =IFERROR(((1+E107/E31)^(360/E$3))-1,0) -> 0 | F50: =IFERROR(((1+F107/F31)^(360/F$3))-1,0) -> 0 | G50: =IFERROR(((1+G107/G31)^(360/G$3))-1,0) -> 0 | H50: =IFERROR(((1+H107/H31)^(360/H$3))-1,0) -> 0 | I50: =IFERROR(((1+I107/I31)^(360/I$3))-1,0) -> 0 | Q50: =($D50-E50)*10000 -> 0 | R50: =($D50-F50)*10000 -> 0 | S50: =($D50-G50)*10000 -> 0 | T50: =($D50-H50)*10000 -> 0 | U50: =($D50-I50)*10000 -> 0 | W50: {=INDIRECT("'"&$C$6&"'!"&ADDRESS(ROW(),COLUMN()+44))} -> 0 | X50: {=INDIRECT("'"&$C$6&"'!"&ADDRESS(ROW(),COLUMN()+44))} -> 0 | Y50: {=INDIRECT("'"&$C$6&"'!"&ADDRESS(ROW(),COLUMN()+44))} -> 0 | Z50: {=INDIRECT("'"&$C$6&"'!"&ADDRESS(ROW(),COLUMN()+44))} -> 0 | AA50: {=INDIRECT("'"&$C$6&"'!"&ADDRESS(ROW(),COLUMN()+44))} -> 0 | AB50: {=INDIRECT("'"&$C$6&"'!"&ADDRESS(ROW(),COLUMN()+44))} -> 0 | AJ50: =($W50-X50)*10000 -> 0 | AK50: =($W50-Y50)*10000 -> 0 | AL50: =($W50-Z50)*10000 -> 0 | AM50: =($W50-AA50)*10000 -> 0 | AN50: =($W50-AB50)*10000 -> 0
D51: =IFERROR(((1+D108/D32)^(360/D$3))-1,0) -> 0 | E51: =IFERROR(((1+E108/E32)^(360/E$3))-1,0) -> 0 | F51: =IFERROR(((1+F108/F32)^(360/F$3))-1,0) -> 0 | G51: =IFERROR(((1+G108/G32)^(360/G$3))-1,0) -> 0 | H51: =IFERROR(((1+H108/H32)^(360/H$3))-1,0) -> 0 | I51: =IFERROR(((1+I108/I32)^(360/I$3))-1,0) -> 0 | Q51: =($D51-E51)*10000 -> 0 | R51: =($D51-F51)*10000 -> 0 | S51: =($D51-G51)*10000 -> 0 | T51: =($D51-H51)*10000 -> 0 | U51: =($D51-I51)*10000 -> 0 | W51: {=INDIRECT("'"&$C$6&"'!"&ADDRESS(ROW(),COLUMN()+44))} -> 0 | X51: {=INDIRECT("'"&$C$6&"'!"&ADDRESS(ROW(),COLUMN()+44))} -> 0 | Y51: {=INDIRECT("'"&$C$6&"'!"&ADDRESS(ROW(),COLUMN()+44))} -> 0 | Z51: {=INDIRECT("'"&$C$6&"'!"&ADDRESS(ROW(),COLUMN()+44))} -> 0 | AA51: {=INDIRECT("'"&$C$6&"'!"&ADDRESS(ROW(),COLUMN()+44))} -> 0 | AB51: {=INDIRECT("'"&$C$6&"'!"&ADDRESS(ROW(),COLUMN()+44))} -> 0 | AJ51: =($W51-X51)*10000 -> 0 | AK51: =($W51-Y51)*10000 -> 0 | AL51: =($W51-Z51)*10000 -> 0 | AM51: =($W51-AA51)*10000 -> 0 | AN51: =($W51-AB51)*10000 -> 0
D52: =IFERROR(((1+D109/D33)^(360/D$3))-1,0) -> 0 | E52: =IFERROR(((1+E109/E33)^(360/E$3))-1,0) -> 0 | F52: =IFERROR(((1+F109/F33)^(360/F$3))-1,0) -> 0 | G52: =IFERROR(((1+G109/G33)^(360/G$3))-1,0) -> 0 | H52: =IFERROR(((1+H109/H33)^(360/H$3))-1,0) -> 0 | I52: =IFERROR(((1+I109/I33)^(360/I$3))-1,0) -> 0 | Q52: =($D52-E52)*10000 -> 0 | R52: =($D52-F52)*10000 -> 0 | S52: =($D52-G52)*10000 -> 0 | T52: =($D52-H52)*10000 -> 0 | U52: =($D52-I52)*10000 -> 0 | W52: {=INDIRECT("'"&$C$6&"'!"&ADDRESS(ROW(),COLUMN()+44))} -> 0 | X52: {=INDIRECT("'"&$C$6&"'!"&ADDRESS(ROW(),COLUMN()+44))} -> 0 | Y52: {=INDIRECT("'"&$C$6&"'!"&ADDRESS(ROW(),COLUMN()+44))} -> 0 | Z52: {=INDIRECT("'"&$C$6&"'!"&ADDRESS(ROW(),COLUMN()+44))} -> 0 | AA52: {=INDIRECT("'"&$C$6&"'!"&ADDRESS(ROW(),COLUMN()+44))} -> 0 | AB52: {=INDIRECT("'"&$C$6&"'!"&ADDRESS(ROW(),COLUMN()+44))} -> 0 | AJ52: =($W52-X52)*10000 -> 0 | AK52: =($W52-Y52)*10000 -> 0 | AL52: =($W52-Z52)*10000 -> 0 | AM52: =($W52-AA52)*10000 -> 0 | AN52: =($W52-AB52)*10000 -> 0
D53: =IFERROR(((1+D110/D34)^(360/D$3))-1,0) -> 0 | E53: =IFERROR(((1+E110/E34)^(360/E$3))-1,0) -> 0 | F53: =IFERROR(((1+F110/F34)^(360/F$3))-1,0) -> 0 | G53: =IFERROR(((1+G110/G34)^(360/G$3))-1,0) -> 0 | H53: =IFERROR(((1+H110/H34)^(360/H$3))-1,0) -> 0 | I53: =IFERROR(((1+I110/I34)^(360/I$3))-1,0) -> 0 | Q53: =($D53-E53)*10000 -> 0 | R53: =($D53-F53)*10000 -> 0 | S53: =($D53-G53)*10000 -> 0 | T53: =($D53-H53)*10000 -> 0 | U53: =($D53-I53)*10000 -> 0 | W53: {=INDIRECT("'"&$C$6&"'!"&ADDRESS(ROW(),COLUMN()+44))} -> 0 | X53: {=INDIRECT("'"&$C$6&"'!"&ADDRESS(ROW(),COLUMN()+44))} -> 0 | Y53: {=INDIRECT("'"&$C$6&"'!"&ADDRESS(ROW(),COLUMN()+44))} -> 0 | Z53: {=INDIRECT("'"&$C$6&"'!"&ADDRESS(ROW(),COLUMN()+44))} -> 0 | AA53: {=INDIRECT("'"&$C$6&"'!"&ADDRESS(ROW(),COLUMN()+44))} -> 0 | AB53: {=INDIRECT("'"&$C$6&"'!"&ADDRESS(ROW(),COLUMN()+44))} -> 0 | AJ53: =($W53-X53)*10000 -> 0 | AK53: =($W53-Y53)*10000 -> 0 | AL53: =($W53-Z53)*10000 -> 0 | AM53: =($W53-AA53)*10000 -> 0 | AN53: =($W53-AB53)*10000 -> 0
D54: =IFERROR(((1+D111/D35)^(360/D$3))-1,0) -> 0 | E54: =IFERROR(((1+E111/E35)^(360/E$3))-1,0) -> 0.042497138 | F54: =IFERROR(((1+F111/F35)^(360/F$3))-1,0) -> 0 | G54: =IFERROR(((1+G111/G35)^(360/G$3))-1,0) -> 0 | H54: =IFERROR(((1+H111/H35)^(360/H$3))-1,0) -> 0 | I54: =IFERROR(((1+I111/I35)^(360/I$3))-1,0) -> 0 | Q54: =($D54-E54)*10000 -> -424.97138 | R54: =($D54-F54)*10000 -> 0 | S54: =($D54-G54)*10000 -> 0 | T54: =($D54-H54)*10000 -> 0 | U54: =($D54-I54)*10000 -> 0 | W54: {=INDIRECT("'"&$C$6&"'!"&ADDRESS(ROW(),COLUMN()+44))} -> 0 | X54: {=INDIRECT("'"&$C$6&"'!"&ADDRESS(ROW(),COLUMN()+44))} -> 0.04252755 | Y54: {=INDIRECT("'"&$C$6&"'!"&ADDRESS(ROW(),COLUMN()+44))} -> 0 | Z54: {=INDIRECT("'"&$C$6&"'!"&ADDRESS(ROW(),COLUMN()+44))} -> 0 | AA54: {=INDIRECT("'"&$C$6&"'!"&ADDRESS(ROW(),COLUMN()+44))} -> 0 | AB54: {=INDIRECT("'"&$C$6&"'!"&ADDRESS(ROW(),COLUMN()+44))} -> 0 | AJ54: =($W54-X54)*10000 -> -425.2755 | AK54: =($W54-Y54)*10000 -> 0 | AL54: =($W54-Z54)*10000 -> 0 | AM54: =($W54-AA54)*10000 -> 0 | AN54: =($W54-AB54)*10000 -> 0
D55: =IFERROR(((1+D112/D36)^(360/D$3))-1,0) -> 0 | E55: =IFERROR(((1+E112/E36)^(360/E$3))-1,0) -> 0 | F55: =IFERROR(((1+F112/F36)^(360/F$3))-1,0) -> 0 | G55: =IFERROR(((1+G112/G36)^(360/G$3))-1,0) -> 0 | H55: =IFERROR(((1+H112/H36)^(360/H$3))-1,0) -> 0 | I55: =IFERROR(((1+I112/I36)^(360/I$3))-1,0) -> 0 | Q55: =($D55-E55)*10000 -> 0 | R55: =($D55-F55)*10000 -> 0 | S55: =($D55-G55)*10000 -> 0 | T55: =($D55-H55)*10000 -> 0 | U55: =($D55-I55)*10000 -> 0 | W55: {=INDIRECT("'"&$C$6&"'!"&ADDRESS(ROW(),COLUMN()+44))} -> 0 | X55: {=INDIRECT("'"&$C$6&"'!"&ADDRESS(ROW(),COLUMN()+44))} -> 0 | Y55: {=INDIRECT("'"&$C$6&"'!"&ADDRESS(ROW(),COLUMN()+44))} -> 0 | Z55: {=INDIRECT("'"&$C$6&"'!"&ADDRESS(ROW(),COLUMN()+44))} -> 0 | AA55: {=INDIRECT("'"&$C$6&"'!"&ADDRESS(ROW(),COLUMN()+44))} -> 0 | AB55: {=INDIRECT("'"&$C$6&"'!"&ADDRESS(ROW(),COLUMN()+44))} -> 0 | AJ55: =($W55-X55)*10000 -> 0 | AK55: =($W55-Y55)*10000 -> 0 | AL55: =($W55-Z55)*10000 -> 0 | AM55: =($W55-AA55)*10000 -> 0 | AN55: =($W55-AB55)*10000 -> 0
D56: =IFERROR(((1+D113/D37)^(360/D$3))-1,0) -> 0 | E56: =IFERROR(((1+E113/E37)^(360/E$3))-1,0) -> 0 | F56: =IFERROR(((1+F113/F37)^(360/F$3))-1,0) -> 0 | G56: =IFERROR(((1+G113/G37)^(360/G$3))-1,0) -> 0 | H56: =IFERROR(((1+H113/H37)^(360/H$3))-1,0) -> 0 | I56: =IFERROR(((1+I113/I37)^(360/I$3))-1,0) -> 0 | Q56: =($D56-E56)*10000 -> 0 | R56: =($D56-F56)*10000 -> 0 | S56: =($D56-G56)*10000 -> 0 | T56: =($D56-H56)*10000 -> 0 | U56: =($D56-I56)*10000 -> 0 | W56: {=INDIRECT("'"&$C$6&"'!"&ADDRESS(ROW(),COLUMN()+44))} -> 0 | X56: {=INDIRECT("'"&$C$6&"'!"&ADDRESS(ROW(),COLUMN()+44))} -> 0 | Y56: {=INDIRECT("'"&$C$6&"'!"&ADDRESS(ROW(),COLUMN()+44))} -> 0 | Z56: {=INDIRECT("'"&$C$6&"'!"&ADDRESS(ROW(),COLUMN()+44))} -> 0 | AA56: {=INDIRECT("'"&$C$6&"'!"&ADDRESS(ROW(),COLUMN()+44))} -> 0 | AB56: {=INDIRECT("'"&$C$6&"'!"&ADDRESS(ROW(),COLUMN()+44))} -> 0 | AJ56: =($W56-X56)*10000 -> 0 | AK56: =($W56-Y56)*10000 -> 0 | AL56: =($W56-Z56)*10000 -> 0 | AM56: =($W56-AA56)*10000 -> 0 | AN56: =($W56-AB56)*10000 -> 0
D57: =IFERROR(((1+D114/D38)^(360/D$3))-1,0) -> 0 | E57: =IFERROR(((1+E114/E38)^(360/E$3))-1,0) -> 0 | F57: =IFERROR(((1+F114/F38)^(360/F$3))-1,0) -> 0 | G57: =IFERROR(((1+G114/G38)^(360/G$3))-1,0) -> 0 | H57: =IFERROR(((1+H114/H38)^(360/H$3))-1,0) -> 0 | I57: =IFERROR(((1+I114/I38)^(360/I$3))-1,0) -> 0 | Q57: =($D57-E57)*10000 -> 0 | R57: =($D57-F57)*10000 -> 0 | S57: =($D57-G57)*10000 -> 0 | T57: =($D57-H57)*10000 -> 0 | U57: =($D57-I57)*10000 -> 0 | W57: {=INDIRECT("'"&$C$6&"'!"&ADDRESS(ROW(),COLUMN()+44))} -> 0 | X57: {=INDIRECT("'"&$C$6&"'!"&ADDRESS(ROW(),COLUMN()+44))} -> 0 | Y57: {=INDIRECT("'"&$C$6&"'!"&ADDRESS(ROW(),COLUMN()+44))} -> 0 | Z57: {=INDIRECT("'"&$C$6&"'!"&ADDRESS(ROW(),COLUMN()+44))} -> 0 | AA57: {=INDIRECT("'"&$C$6&"'!"&ADDRESS(ROW(),COLUMN()+44))} -> 0 | AB57: {=INDIRECT("'"&$C$6&"'!"&ADDRESS(ROW(),COLUMN()+44))} -> 0 | AJ57: =($W57-X57)*10000 -> 0 | AK57: =($W57-Y57)*10000 -> 0 | AL57: =($W57-Z57)*10000 -> 0 | AM57: =($W57-AA57)*10000 -> 0 | AN57: =($W57-AB57)*10000 -> 0
D58: =IFERROR(((1+D115/D39)^(360/D$3))-1,0) -> 0 | E58: =IFERROR(((1+E115/E39)^(360/E$3))-1,0) -> 0 | F58: =IFERROR(((1+F115/F39)^(360/F$3))-1,0) -> 0 | G58: =IFERROR(((1+G115/G39)^(360/G$3))-1,0) -> 0 | H58: =IFERROR(((1+H115/H39)^(360/H$3))-1,0) -> 0 | I58: =IFERROR(((1+I115/I39)^(360/I$3))-1,0) -> 0 | Q58: =($D58-E58)*10000 -> 0 | R58: =($D58-F58)*10000 -> 0 | S58: =($D58-G58)*10000 -> 0 | T58: =($D58-H58)*10000 -> 0 | U58: =($D58-I58)*10000 -> 0 | W58: {=INDIRECT("'"&$C$6&"'!"&ADDRESS(ROW(),COLUMN()+44))} -> 0 | X58: {=INDIRECT("'"&$C$6&"'!"&ADDRESS(ROW(),COLUMN()+44))} -> 0 | Y58: {=INDIRECT("'"&$C$6&"'!"&ADDRESS(ROW(),COLUMN()+44))} -> 0 | Z58: {=INDIRECT("'"&$C$6&"'!"&ADDRESS(ROW(),COLUMN()+44))} -> 0 | AA58: {=INDIRECT("'"&$C$6&"'!"&ADDRESS(ROW(),COLUMN()+44))} -> 0 | AB58: {=INDIRECT("'"&$C$6&"'!"&ADDRESS(ROW(),COLUMN()+44))} -> 0 | AJ58: =($W58-X58)*10000 -> 0 | AK58: =($W58-Y58)*10000 -> 0 | AL58: =($W58-Z58)*10000 -> 0 | AM58: =($W58-AA58)*10000 -> 0 | AN58: =($W58-AB58)*10000 -> 0
... D61: =IFERROR(((1+D118/D42)^(360/D$3))-1,0) -> 0 | E61: =IFERROR(((1+E118/E42)^(360/E$3))-1,0) -> 0 | F61: =IFERROR(((1+F118/F42)^(360/F$3))-1,0) -> 0 | G61: =IFERROR(((1+G118/G42)^(360/G$3))-1,0) -> 0 | H61: =IFERROR(((1+H118/H42)^(360/H$3))-1,0) -> 0 | I61: =IFERROR(((1+I118/I42)^(360/I$3))-1,0) -> 0 | Q61: =($D61-E61)*10000 -> 0 | R61: =($D61-F61)*10000 -> 0 | S61: =($D61-G61)*10000 -> 0 | T61: =($D61-H61)*10000 -> 0 | U61: =($D61-I61)*10000 -> 0 | W61: {=INDIRECT("'"&$C$6&"'!"&ADDRESS(ROW(),COLUMN()+44))} -> 0 | X61: {=INDIRECT("'"&$C$6&"'!"&ADDRESS(ROW(),COLUMN()+44))} -> 0 | Y61: {=INDIRECT("'"&$C$6&"'!"&ADDRESS(ROW(),COLUMN()+44))} -> 0 | Z61: {=INDIRECT("'"&$C$6&"'!"&ADDRESS(ROW(),COLUMN()+44))} -> 0 | AA61: {=INDIRECT("'"&$C$6&"'!"&ADDRESS(ROW(),COLUMN()+44))} -> 0 | AB61: {=INDIRECT("'"&$C$6&"'!"&ADDRESS(ROW(),COLUMN()+44))} -> 0 | AJ61: =($W61-X61)*10000 -> 0 | AK61: =($W61-Y61)*10000 -> 0 | AL61: =($W61-Z61)*10000 -> 0 | AM61: =($W61-AA61)*10000 -> 0 | AN61: =($W61-AB61)*10000 -> 0
C62: Tasa FTP | D62: =IFERROR(((1+D119/D43)^(360/D$3))-1,0) -> 0 | E62: =IFERROR(((1+E119/E43)^(360/E$3))-1,0) -> 0.042497138 | F62: =IFERROR(((1+F119/F43)^(360/F$3))-1,0) -> 0 | G62: =IFERROR(((1+G119/G43)^(360/G$3))-1,0) -> 0 | H62: =IFERROR(((1+H119/H43)^(360/H$3))-1,0) -> 0 | I62: =IFERROR(((1+I119/I43)^(360/I$3))-1,0) -> 0 | Q62: =($D62-E62)*10000 -> -424.97138 | R62: =($D62-F62)*10000 -> 0 | S62: =($D62-G62)*10000 -> 0 | T62: =($D62-H62)*10000 -> 0 | U62: =($D62-I62)*10000 -> 0 | W62: {=INDIRECT("'"&$C$6&"'!"&ADDRESS(ROW(),COLUMN()+44))} -> 0 | X62: {=INDIRECT("'"&$C$6&"'!"&ADDRESS(ROW(),COLUMN()+44))} -> 0.04252755 | Y62: {=INDIRECT("'"&$C$6&"'!"&ADDRESS(ROW(),COLUMN()+44))} -> 0 | Z62: {=INDIRECT("'"&$C$6&"'!"&ADDRESS(ROW(),COLUMN()+44))} -> 0 | AA62: {=INDIRECT("'"&$C$6&"'!"&ADDRESS(ROW(),COLUMN()+44))} -> 0 | AB62: {=INDIRECT("'"&$C$6&"'!"&ADDRESS(ROW(),COLUMN()+44))} -> 0 | AJ62: =($W62-X62)*10000 -> -425.2755 | AK62: =($W62-Y62)*10000 -> 0 | AL62: =($W62-Z62)*10000 -> 0 | AM62: =($W62-AA62)*10000 -> 0 | AN62: =($W62-AB62)*10000 -> 0
C65: Cuenta Sueldo | D65: =-IFERROR(((1-D122/D27)^(360/D$4))-1,0) -> 0 | E65: =-IFERROR(((1-E122/E27)^(360/E$4))-1,0) -> 0 | F65: =-IFERROR(((1-F122/F27)^(360/F$4))-1,0) -> 0 | G65: =-IFERROR(((1-G122/G27)^(360/G$4))-1,0) -> 0 | H65: =-IFERROR(((1-H122/H27)^(360/H$4))-1,0) -> 0 | I65: =-IFERROR(((1-I122/I27)^(360/I$4))-1,0) -> 0 | Q65: =($D65-E65)*10000 -> 0 | R65: =($D65-F65)*10000 -> 0 | S65: =($D65-G65)*10000 -> 0 | T65: =($D65-H65)*10000 -> 0 | U65: =($D65-I65)*10000 -> 0 | W65: {=INDIRECT("'"&$C$6&"'!"&ADDRESS(ROW(),COLUMN()+44))} -> 0 | X65: {=INDIRECT("'"&$C$6&"'!"&ADDRESS(ROW(),COLUMN()+44))} -> 0 | Y65: {=INDIRECT("'"&$C$6&"'!"&ADDRESS(ROW(),COLUMN()+44))} -> 0 | Z65: {=INDIRECT("'"&$C$6&"'!"&ADDRESS(ROW(),COLUMN()+44))} -> 0 | AA65: {=INDIRECT("'"&$C$6&"'!"&ADDRESS(ROW(),COLUMN()+44))} -> 0 | AB65: {=INDIRECT("'"&$C$6&"'!"&ADDRESS(ROW(),COLUMN()+44))} -> 0 | AJ65: =($W65-X65)*10000 -> 0 | AK65: =($W65-Y65)*10000 -> 0 | AL65: =($W65-Z65)*10000 -> 0 | AM65: =($W65-AA65)*10000 -> 0 | AN65: =($W65-AB65)*10000 -> 0
D66: =-IFERROR(((1-D123/D28)^(360/D$4))-1,0) -> 0 | E66: =-IFERROR(((1-E123/E28)^(360/E$4))-1,0) -> 0 | F66: =-IFERROR(((1-F123/F28)^(360/F$4))-1,0) -> 0 | G66: =-IFERROR(((1-G123/G28)^(360/G$4))-1,0) -> 0 | H66: =-IFERROR(((1-H123/H28)^(360/H$4))-1,0) -> 0 | I66: =-IFERROR(((1-I123/I28)^(360/I$4))-1,0) -> 0 | Q66: =($D66-E66)*10000 -> 0 | R66: =($D66-F66)*10000 -> 0 | S66: =($D66-G66)*10000 -> 0 | T66: =($D66-H66)*10000 -> 0 | U66: =($D66-I66)*10000 -> 0 | W66: {=INDIRECT("'"&$C$6&"'!"&ADDRESS(ROW(),COLUMN()+44))} -> 0 | X66: {=INDIRECT("'"&$C$6&"'!"&ADDRESS(ROW(),COLUMN()+44))} -> 0 | Y66: {=INDIRECT("'"&$C$6&"'!"&ADDRESS(ROW(),COLUMN()+44))} -> 0 | Z66: {=INDIRECT("'"&$C$6&"'!"&ADDRESS(ROW(),COLUMN()+44))} -> 0 | AA66: {=INDIRECT("'"&$C$6&"'!"&ADDRESS(ROW(),COLUMN()+44))} -> 0 | AB66: {=INDIRECT("'"&$C$6&"'!"&ADDRESS(ROW(),COLUMN()+44))} -> 0 | AJ66: =($W66-X66)*10000 -> 0 | AK66: =($W66-Y66)*10000 -> 0 | AL66: =($W66-Z66)*10000 -> 0 | AM66: =($W66-AA66)*10000 -> 0 | AN66: =($W66-AB66)*10000 -> 0
D67: =-IFERROR(((1-D124/D29)^(360/D$4))-1,0) -> 0 | E67: =-IFERROR(((1-E124/E29)^(360/E$4))-1,0) -> 0 | F67: =-IFERROR(((1-F124/F29)^(360/F$4))-1,0) -> 0 | G67: =-IFERROR(((1-G124/G29)^(360/G$4))-1,0) -> 0 | H67: =-IFERROR(((1-H124/H29)^(360/H$4))-1,0) -> 0 | I67: =-IFERROR(((1-I124/I29)^(360/I$4))-1,0) -> 0 | Q67: =($D67-E67)*10000 -> 0 | R67: =($D67-F67)*10000 -> 0 | S67: =($D67-G67)*10000 -> 0 | T67: =($D67-H67)*10000 -> 0 | U67: =($D67-I67)*10000 -> 0 | W67: {=INDIRECT("'"&$C$6&"'!"&ADDRESS(ROW(),COLUMN()+44))} -> 0 | X67: {=INDIRECT("'"&$C$6&"'!"&ADDRESS(ROW(),COLUMN()+44))} -> 0 | Y67: {=INDIRECT("'"&$C$6&"'!"&ADDRESS(ROW(),COLUMN()+44))} -> 0 | Z67: {=INDIRECT("'"&$C$6&"'!"&ADDRESS(ROW(),COLUMN()+44))} -> 0 | AA67: {=INDIRECT("'"&$C$6&"'!"&ADDRESS(ROW(),COLUMN()+44))} -> 0 | AB67: {=INDIRECT("'"&$C$6&"'!"&ADDRESS(ROW(),COLUMN()+44))} -> 0 | AJ67: =($W67-X67)*10000 -> 0 | AK67: =($W67-Y67)*10000 -> 0 | AL67: =($W67-Z67)*10000 -> 0 | AM67: =($W67-AA67)*10000 -> 0 | AN67: =($W67-AB67)*10000 -> 0
D68: =-IFERROR(((1-D125/D30)^(360/D$4))-1,0) -> 0 | E68: =-IFERROR(((1-E125/E30)^(360/E$4))-1,0) -> 0 | F68: =-IFERROR(((1-F125/F30)^(360/F$4))-1,0) -> 0 | G68: =-IFERROR(((1-G125/G30)^(360/G$4))-1,0) -> 0 | H68: =-IFERROR(((1-H125/H30)^(360/H$4))-1,0) -> 0 | I68: =-IFERROR(((1-I125/I30)^(360/I$4))-1,0) -> 0 | Q68: =($D68-E68)*10000 -> 0 | R68: =($D68-F68)*10000 -> 0 | S68: =($D68-G68)*10000 -> 0 | T68: =($D68-H68)*10000 -> 0 | U68: =($D68-I68)*10000 -> 0 | W68: {=INDIRECT("'"&$C$6&"'!"&ADDRESS(ROW(),COLUMN()+44))} -> 0 | X68: {=INDIRECT("'"&$C$6&"'!"&ADDRESS(ROW(),COLUMN()+44))} -> 0 | Y68: {=INDIRECT("'"&$C$6&"'!"&ADDRESS(ROW(),COLUMN()+44))} -> 0 | Z68: {=INDIRECT("'"&$C$6&"'!"&ADDRESS(ROW(),COLUMN()+44))} -> 0 | AA68: {=INDIRECT("'"&$C$6&"'!"&ADDRESS(ROW(),COLUMN()+44))} -> 0 | AB68: {=INDIRECT("'"&$C$6&"'!"&ADDRESS(ROW(),COLUMN()+44))} -> 0 | AJ68: =($W68-X68)*10000 -> 0 | AK68: =($W68-Y68)*10000 -> 0 | AL68: =($W68-Z68)*10000 -> 0 | AM68: =($W68-AA68)*10000 -> 0 | AN68: =($W68-AB68)*10000 -> 0
D69: =-IFERROR(((1-D126/D31)^(360/D$4))-1,0) -> 0 | E69: =-IFERROR(((1-E126/E31)^(360/E$4))-1,0) -> 0 | F69: =-IFERROR(((1-F126/F31)^(360/F$4))-1,0) -> 0 | G69: =-IFERROR(((1-G126/G31)^(360/G$4))-1,0) -> 0 | H69: =-IFERROR(((1-H126/H31)^(360/H$4))-1,0) -> 0 | I69: =-IFERROR(((1-I126/I31)^(360/I$4))-1,0) -> 0 | Q69: =($D69-E69)*10000 -> 0 | R69: =($D69-F69)*10000 -> 0 | S69: =($D69-G69)*10000 -> 0 | T69: =($D69-H69)*10000 -> 0 | U69: =($D69-I69)*10000 -> 0 | W69: {=INDIRECT("'"&$C$6&"'!"&ADDRESS(ROW(),COLUMN()+44))} -> 0 | X69: {=INDIRECT("'"&$C$6&"'!"&ADDRESS(ROW(),COLUMN()+44))} -> 0 | Y69: {=INDIRECT("'"&$C$6&"'!"&ADDRESS(ROW(),COLUMN()+44))} -> 0 | Z69: {=INDIRECT("'"&$C$6&"'!"&ADDRESS(ROW(),COLUMN()+44))} -> 0 | AA69: {=INDIRECT("'"&$C$6&"'!"&ADDRESS(ROW(),COLUMN()+44))} -> 0 | AB69: {=INDIRECT("'"&$C$6&"'!"&ADDRESS(ROW(),COLUMN()+44))} -> 0 | AJ69: =($W69-X69)*10000 -> 0 | AK69: =($W69-Y69)*10000 -> 0 | AL69: =($W69-Z69)*10000 -> 0 | AM69: =($W69-AA69)*10000 -> 0 | AN69: =($W69-AB69)*10000 -> 0
D70: =-IFERROR(((1-D127/D32)^(360/D$4))-1,0) -> 0 | E70: =-IFERROR(((1-E127/E32)^(360/E$4))-1,0) -> 0 | F70: =-IFERROR(((1-F127/F32)^(360/F$4))-1,0) -> 0 | G70: =-IFERROR(((1-G127/G32)^(360/G$4))-1,0) -> 0 | H70: =-IFERROR(((1-H127/H32)^(360/H$4))-1,0) -> 0 | I70: =-IFERROR(((1-I127/I32)^(360/I$4))-1,0) -> 0 | Q70: =($D70-E70)*10000 -> 0 | R70: =($D70-F70)*10000 -> 0 | S70: =($D70-G70)*10000 -> 0 | T70: =($D70-H70)*10000 -> 0 | U70: =($D70-I70)*10000 -> 0 | W70: {=INDIRECT("'"&$C$6&"'!"&ADDRESS(ROW(),COLUMN()+44))} -> 0 | X70: {=INDIRECT("'"&$C$6&"'!"&ADDRESS(ROW(),COLUMN()+44))} -> 0 | Y70: {=INDIRECT("'"&$C$6&"'!"&ADDRESS(ROW(),COLUMN()+44))} -> 0 | Z70: {=INDIRECT("'"&$C$6&"'!"&ADDRESS(ROW(),COLUMN()+44))} -> 0 | AA70: {=INDIRECT("'"&$C$6&"'!"&ADDRESS(ROW(),COLUMN()+44))} -> 0 | AB70: {=INDIRECT("'"&$C$6&"'!"&ADDRESS(ROW(),COLUMN()+44))} -> 0 | AJ70: =($W70-X70)*10000 -> 0 | AK70: =($W70-Y70)*10000 -> 0 | AL70: =($W70-Z70)*10000 -> 0 | AM70: =($W70-AA70)*10000 -> 0 | AN70: =($W70-AB70)*10000 -> 0
D71: =-IFERROR(((1-D128/D33)^(360/D$4))-1,0) -> 0 | E71: =-IFERROR(((1-E128/E33)^(360/E$4))-1,0) -> 0 | F71: =-IFERROR(((1-F128/F33)^(360/F$4))-1,0) -> 0 | G71: =-IFERROR(((1-G128/G33)^(360/G$4))-1,0) -> 0 | H71: =-IFERROR(((1-H128/H33)^(360/H$4))-1,0) -> 0 | I71: =-IFERROR(((1-I128/I33)^(360/I$4))-1,0) -> 0 | Q71: =($D71-E71)*10000 -> 0 | R71: =($D71-F71)*10000 -> 0 | S71: =($D71-G71)*10000 -> 0 | T71: =($D71-H71)*10000 -> 0 | U71: =($D71-I71)*10000 -> 0 | W71: {=INDIRECT("'"&$C$6&"'!"&ADDRESS(ROW(),COLUMN()+44))} -> 0 | X71: {=INDIRECT("'"&$C$6&"'!"&ADDRESS(ROW(),COLUMN()+44))} -> 0 | Y71: {=INDIRECT("'"&$C$6&"'!"&ADDRESS(ROW(),COLUMN()+44))} -> 0 | Z71: {=INDIRECT("'"&$C$6&"'!"&ADDRESS(ROW(),COLUMN()+44))} -> 0 | AA71: {=INDIRECT("'"&$C$6&"'!"&ADDRESS(ROW(),COLUMN()+44))} -> 0 | AB71: {=INDIRECT("'"&$C$6&"'!"&ADDRESS(ROW(),COLUMN()+44))} -> 0 | AJ71: =($W71-X71)*10000 -> 0 | AK71: =($W71-Y71)*10000 -> 0 | AL71: =($W71-Z71)*10000 -> 0 | AM71: =($W71-AA71)*10000 -> 0 | AN71: =($W71-AB71)*10000 -> 0
D72: =-IFERROR(((1-D129/D34)^(360/D$4))-1,0) -> 0 | E72: =-IFERROR(((1-E129/E34)^(360/E$4))-1,0) -> 0 | F72: =-IFERROR(((1-F129/F34)^(360/F$4))-1,0) -> 0 | G72: =-IFERROR(((1-G129/G34)^(360/G$4))-1,0) -> 0 | H72: =-IFERROR(((1-H129/H34)^(360/H$4))-1,0) -> 0 | I72: =-IFERROR(((1-I129/I34)^(360/I$4))-1,0) -> 0 | Q72: =($D72-E72)*10000 -> 0 | R72: =($D72-F72)*10000 -> 0 | S72: =($D72-G72)*10000 -> 0 | T72: =($D72-H72)*10000 -> 0 | U72: =($D72-I72)*10000 -> 0 | W72: {=INDIRECT("'"&$C$6&"'!"&ADDRESS(ROW(),COLUMN()+44))} -> 0 | X72: {=INDIRECT("'"&$C$6&"'!"&ADDRESS(ROW(),COLUMN()+44))} -> 0 | Y72: {=INDIRECT("'"&$C$6&"'!"&ADDRESS(ROW(),COLUMN()+44))} -> 0 | Z72: {=INDIRECT("'"&$C$6&"'!"&ADDRESS(ROW(),COLUMN()+44))} -> 0 | AA72: {=INDIRECT("'"&$C$6&"'!"&ADDRESS(ROW(),COLUMN()+44))} -> 0 | AB72: {=INDIRECT("'"&$C$6&"'!"&ADDRESS(ROW(),COLUMN()+44))} -> 0 | AJ72: =($W72-X72)*10000 -> 0 | AK72: =($W72-Y72)*10000 -> 0 | AL72: =($W72-Z72)*10000 -> 0 | AM72: =($W72-AA72)*10000 -> 0 | AN72: =($W72-AB72)*10000 -> 0
D73: =-IFERROR(((1-D130/D35)^(360/D$4))-1,0) -> 0 | E73: =-IFERROR(((1-E130/E35)^(360/E$4))-1,0) -> 0 | F73: =-IFERROR(((1-F130/F35)^(360/F$4))-1,0) -> 0 | G73: =-IFERROR(((1-G130/G35)^(360/G$4))-1,0) -> 0 | H73: =-IFERROR(((1-H130/H35)^(360/H$4))-1,0) -> 0 | I73: =-IFERROR(((1-I130/I35)^(360/I$4))-1,0) -> 0 | Q73: =($D73-E73)*10000 -> 0 | R73: =($D73-F73)*10000 -> 0 | S73: =($D73-G73)*10000 -> 0 | T73: =($D73-H73)*10000 -> 0 | U73: =($D73-I73)*10000 -> 0 | W73: {=INDIRECT("'"&$C$6&"'!"&ADDRESS(ROW(),COLUMN()+44))} -> 0 | X73: {=INDIRECT("'"&$C$6&"'!"&ADDRESS(ROW(),COLUMN()+44))} -> 0 | Y73: {=INDIRECT("'"&$C$6&"'!"&ADDRESS(ROW(),COLUMN()+44))} -> 0 | Z73: {=INDIRECT("'"&$C$6&"'!"&ADDRESS(ROW(),COLUMN()+44))} -> 0 | AA73: {=INDIRECT("'"&$C$6&"'!"&ADDRESS(ROW(),COLUMN()+44))} -> 0 | AB73: {=INDIRECT("'"&$C$6&"'!"&ADDRESS(ROW(),COLUMN()+44))} -> 0 | AJ73: =($W73-X73)*10000 -> 0 | AK73: =($W73-Y73)*10000 -> 0 | AL73: =($W73-Z73)*10000 -> 0 | AM73: =($W73-AA73)*10000 -> 0 | AN73: =($W73-AB73)*10000 -> 0
D74: =-IFERROR(((1-D131/D36)^(360/D$4))-1,0) -> 0 | E74: =-IFERROR(((1-E131/E36)^(360/E$4))-1,0) -> 0 | F74: =-IFERROR(((1-F131/F36)^(360/F$4))-1,0) -> 0 | G74: =-IFERROR(((1-G131/G36)^(360/G$4))-1,0) -> 0 | H74: =-IFERROR(((1-H131/H36)^(360/H$4))-1,0) -> 0 | I74: =-IFERROR(((1-I131/I36)^(360/I$4))-1,0) -> 0 | Q74: =($D74-E74)*10000 -> 0 | R74: =($D74-F74)*10000 -> 0 | S74: =($D74-G74)*10000 -> 0 | T74: =($D74-H74)*10000 -> 0 | U74: =($D74-I74)*10000 -> 0 | W74: {=INDIRECT("'"&$C$6&"'!"&ADDRESS(ROW(),COLUMN()+44))} -> 0 | X74: {=INDIRECT("'"&$C$6&"'!"&ADDRESS(ROW(),COLUMN()+44))} -> 0 | Y74: {=INDIRECT("'"&$C$6&"'!"&ADDRESS(ROW(),COLUMN()+44))} -> 0 | Z74: {=INDIRECT("'"&$C$6&"'!"&ADDRESS(ROW(),COLUMN()+44))} -> 0 | AA74: {=INDIRECT("'"&$C$6&"'!"&ADDRESS(ROW(),COLUMN()+44))} -> 0 | AB74: {=INDIRECT("'"&$C$6&"'!"&ADDRESS(ROW(),COLUMN()+44))} -> 0 | AJ74: =($W74-X74)*10000 -> 0 | AK74: =($W74-Y74)*10000 -> 0 | AL74: =($W74-Z74)*10000 -> 0 | AM74: =($W74-AA74)*10000 -> 0 | AN74: =($W74-AB74)*10000 -> 0
D75: =-IFERROR(((1-D132/D37)^(360/D$4))-1,0) -> 0 | E75: =-IFERROR(((1-E132/E37)^(360/E$4))-1,0) -> 0 | F75: =-IFERROR(((1-F132/F37)^(360/F$4))-1,0) -> 0 | G75: =-IFERROR(((1-G132/G37)^(360/G$4))-1,0) -> 0 | H75: =-IFERROR(((1-H132/H37)^(360/H$4))-1,0) -> 0 | I75: =-IFERROR(((1-I132/I37)^(360/I$4))-1,0) -> 0 | Q75: =($D75-E75)*10000 -> 0 | R75: =($D75-F75)*10000 -> 0 | S75: =($D75-G75)*10000 -> 0 | T75: =($D75-H75)*10000 -> 0 | U75: =($D75-I75)*10000 -> 0 | W75: {=INDIRECT("'"&$C$6&"'!"&ADDRESS(ROW(),COLUMN()+44))} -> 0 | X75: {=INDIRECT("'"&$C$6&"'!"&ADDRESS(ROW(),COLUMN()+44))} -> 0 | Y75: {=INDIRECT("'"&$C$6&"'!"&ADDRESS(ROW(),COLUMN()+44))} -> 0 | Z75: {=INDIRECT("'"&$C$6&"'!"&ADDRESS(ROW(),COLUMN()+44))} -> 0 | AA75: {=INDIRECT("'"&$C$6&"'!"&ADDRESS(ROW(),COLUMN()+44))} -> 0 | AB75: {=INDIRECT("'"&$C$6&"'!"&ADDRESS(ROW(),COLUMN()+44))} -> 0 | AJ75: =($W75-X75)*10000 -> 0 | AK75: =($W75-Y75)*10000 -> 0 | AL75: =($W75-Z75)*10000 -> 0 | AM75: =($W75-AA75)*10000 -> 0 | AN75: =($W75-AB75)*10000 -> 0
D76: =-IFERROR(((1-D133/D38)^(360/D$4))-1,0) -> 0 | E76: =-IFERROR(((1-E133/E38)^(360/E$4))-1,0) -> 0 | F76: =-IFERROR(((1-F133/F38)^(360/F$4))-1,0) -> 0 | G76: =-IFERROR(((1-G133/G38)^(360/G$4))-1,0) -> 0 | H76: =-IFERROR(((1-H133/H38)^(360/H$4))-1,0) -> 0 | I76: =-IFERROR(((1-I133/I38)^(360/I$4))-1,0) -> 0 | Q76: =($D76-E76)*10000 -> 0 | R76: =($D76-F76)*10000 -> 0 | S76: =($D76-G76)*10000 -> 0 | T76: =($D76-H76)*10000 -> 0 | U76: =($D76-I76)*10000 -> 0 | W76: {=INDIRECT("'"&$C$6&"'!"&ADDRESS(ROW(),COLUMN()+44))} -> 0 | X76: {=INDIRECT("'"&$C$6&"'!"&ADDRESS(ROW(),COLUMN()+44))} -> 0 | Y76: {=INDIRECT("'"&$C$6&"'!"&ADDRESS(ROW(),COLUMN()+44))} -> 0 | Z76: {=INDIRECT("'"&$C$6&"'!"&ADDRESS(ROW(),COLUMN()+44))} -> 0 | AA76: {=INDIRECT("'"&$C$6&"'!"&ADDRESS(ROW(),COLUMN()+44))} -> 0 | AB76: {=INDIRECT("'"&$C$6&"'!"&ADDRESS(ROW(),COLUMN()+44))} -> 0 | AJ76: =($W76-X76)*10000 -> 0 | AK76: =($W76-Y76)*10000 -> 0 | AL76: =($W76-Z76)*10000 -> 0 | AM76: =($W76-AA76)*10000 -> 0 | AN76: =($W76-AB76)*10000 -> 0
D77: =-IFERROR(((1-D134/D39)^(360/D$4))-1,0) -> 0 | E77: =-IFERROR(((1-E134/E39)^(360/E$4))-1,0) -> 0 | F77: =-IFERROR(((1-F134/F39)^(360/F$4))-1,0) -> 0 | G77: =-IFERROR(((1-G134/G39)^(360/G$4))-1,0) -> 0 | H77: =-IFERROR(((1-H134/H39)^(360/H$4))-1,0) -> 0 | I77: =-IFERROR(((1-I134/I39)^(360/I$4))-1,0) -> 0 | Q77: =($D77-E77)*10000 -> 0 | R77: =($D77-F77)*10000 -> 0 | S77: =($D77-G77)*10000 -> 0 | T77: =($D77-H77)*10000 -> 0 | U77: =($D77-I77)*10000 -> 0 | W77: {=INDIRECT("'"&$C$6&"'!"&ADDRESS(ROW(),COLUMN()+44))} -> 0 | X77: {=INDIRECT("'"&$C$6&"'!"&ADDRESS(ROW(),COLUMN()+44))} -> 0 | Y77: {=INDIRECT("'"&$C$6&"'!"&ADDRESS(ROW(),COLUMN()+44))} -> 0 | Z77: {=INDIRECT("'"&$C$6&"'!"&ADDRESS(ROW(),COLUMN()+44))} -> 0 | AA77: {=INDIRECT("'"&$C$6&"'!"&ADDRESS(ROW(),COLUMN()+44))} -> 0 | AB77: {=INDIRECT("'"&$C$6&"'!"&ADDRESS(ROW(),COLUMN()+44))} -> 0 | AJ77: =($W77-X77)*10000 -> 0 | AK77: =($W77-Y77)*10000 -> 0 | AL77: =($W77-Z77)*10000 -> 0 | AM77: =($W77-AA77)*10000 -> 0 | AN77: =($W77-AB77)*10000 -> 0
... D80: =-IFERROR(((1-D137/D42)^(360/D$4))-1,0) -> 0 | E80: =-IFERROR(((1-E137/E42)^(360/E$4))-1,0) -> 0 | F80: =-IFERROR(((1-F137/F42)^(360/F$4))-1,0) -> 0 | G80: =-IFERROR(((1-G137/G42)^(360/G$4))-1,0) -> 0 | H80: =-IFERROR(((1-H137/H42)^(360/H$4))-1,0) -> 0 | I80: =-IFERROR(((1-I137/I42)^(360/I$4))-1,0) -> 0 | Q80: =($D80-E80)*10000 -> 0 | R80: =($D80-F80)*10000 -> 0 | S80: =($D80-G80)*10000 -> 0 | T80: =($D80-H80)*10000 -> 0 | U80: =($D80-I80)*10000 -> 0 | W80: {=INDIRECT("'"&$C$6&"'!"&ADDRESS(ROW(),COLUMN()+44))} -> 0 | X80: {=INDIRECT("'"&$C$6&"'!"&ADDRESS(ROW(),COLUMN()+44))} -> 0 | Y80: {=INDIRECT("'"&$C$6&"'!"&ADDRESS(ROW(),COLUMN()+44))} -> 0 | Z80: {=INDIRECT("'"&$C$6&"'!"&ADDRESS(ROW(),COLUMN()+44))} -> 0 | AA80: {=INDIRECT("'"&$C$6&"'!"&ADDRESS(ROW(),COLUMN()+44))} -> 0 | AB80: {=INDIRECT("'"&$C$6&"'!"&ADDRESS(ROW(),COLUMN()+44))} -> 0 | AJ80: =($W80-X80)*10000 -> 0 | AK80: =($W80-Y80)*10000 -> 0 | AL80: =($W80-Z80)*10000 -> 0 | AM80: =($W80-AA80)*10000 -> 0 | AN80: =($W80-AB80)*10000 -> 0
C81: Tasa Implicita | D81: =-IFERROR(((1-D138/D43)^(360/D$4))-1,0) -> 0 | E81: =-IFERROR(((1-E138/E43)^(360/E$4))-1,0) -> 0 | F81: =-IFERROR(((1-F138/F43)^(360/F$4))-1,0) -> 0 | G81: =-IFERROR(((1-G138/G43)^(360/G$4))-1,0) -> 0 | H81: =-IFERROR(((1-H138/H43)^(360/H$4))-1,0) -> 0 | I81: =-IFERROR(((1-I138/I43)^(360/I$4))-1,0) -> 0 | Q81: =($D81-E81)*10000 -> 0 | R81: =($D81-F81)*10000 -> 0 | S81: =($D81-G81)*10000 -> 0 | T81: =($D81-H81)*10000 -> 0 | U81: =($D81-I81)*10000 -> 0 | W81: {=INDIRECT("'"&$C$6&"'!"&ADDRESS(ROW(),COLUMN()+44))} -> 0 | X81: {=INDIRECT("'"&$C$6&"'!"&ADDRESS(ROW(),COLUMN()+44))} -> 0 | Y81: {=INDIRECT("'"&$C$6&"'!"&ADDRESS(ROW(),COLUMN()+44))} -> 0 | Z81: {=INDIRECT("'"&$C$6&"'!"&ADDRESS(ROW(),COLUMN()+44))} -> 0 | AA81: {=INDIRECT("'"&$C$6&"'!"&ADDRESS(ROW(),COLUMN()+44))} -> 0 | AB81: {=INDIRECT("'"&$C$6&"'!"&ADDRESS(ROW(),COLUMN()+44))} -> 0 | AJ81: =($W81-X81)*10000 -> 0 | AK81: =($W81-Y81)*10000 -> 0 | AL81: =($W81-Z81)*10000 -> 0 | AM81: =($W81-AA81)*10000 -> 0 | AN81: =($W81-AB81)*10000 -> 0
C84: Cuenta Sueldo | D84: =D46+D65 -> 0 | E84: =E46+E65 -> 0.042497138 | F84: =F46+F65 -> 0 | G84: =G46+G65 -> 0 | H84: =H46+H65 -> 0 | I84: =I46+I65 -> 0 | Q84: =($D84-E84)*10000 -> -424.97138 | R84: =($D84-F84)*10000 -> 0 | S84: =($D84-G84)*10000 -> 0 | T84: =($D84-H84)*10000 -> 0 | U84: =($D84-I84)*10000 -> 0 | W84: =W46+W65 -> 0 | X84: =X46+X65 -> 0.04252755 | Y84: =Y46+Y65 -> 0 | Z84: =Z46+Z65 -> 0 | AA84: =AA46+AA65 -> 0 | AB84: =AB46+AB65 -> 0 | AJ84: =($W84-X84)*10000 -> -425.2755 | AK84: =($W84-Y84)*10000 -> 0 | AL84: =($W84-Z84)*10000 -> 0 | AM84: =($W84-AA84)*10000 -> 0 | AN84: =($W84-AB84)*10000 -> 0
D85: =D47+D66 -> 0 | E85: =E47+E66 -> 0 | F85: =F47+F66 -> 0 | G85: =G47+G66 -> 0 | H85: =H47+H66 -> 0 | I85: =I47+I66 -> 0 | Q85: =($D85-E85)*10000 -> 0 | R85: =($D85-F85)*10000 -> 0 | S85: =($D85-G85)*10000 -> 0 | T85: =($D85-H85)*10000 -> 0 | U85: =($D85-I85)*10000 -> 0 | W85: =W47+W66 -> 0 | X85: =X47+X66 -> 0 | Y85: =Y47+Y66 -> 0 | Z85: =Z47+Z66 -> 0 | AA85: =AA47+AA66 -> 0 | AB85: =AB47+AB66 -> 0 | AJ85: =($W85-X85)*10000 -> 0 | AK85: =($W85-Y85)*10000 -> 0 | AL85: =($W85-Z85)*10000 -> 0 | AM85: =($W85-AA85)*10000 -> 0 | AN85: =($W85-AB85)*10000 -> 0
D86: =D48+D67 -> 0 | E86: =E48+E67 -> 0 | F86: =F48+F67 -> 0 | G86: =G48+G67 -> 0 | H86: =H48+H67 -> 0 | I86: =I48+I67 -> 0 | Q86: =($D86-E86)*10000 -> 0 | R86: =($D86-F86)*10000 -> 0 | S86: =($D86-G86)*10000 -> 0 | T86: =($D86-H86)*10000 -> 0 | U86: =($D86-I86)*10000 -> 0 | W86: =W48+W67 -> 0 | X86: =X48+X67 -> 0 | Y86: =Y48+Y67 -> 0 | Z86: =Z48+Z67 -> 0 | AA86: =AA48+AA67 -> 0 | AB86: =AB48+AB67 -> 0 | AJ86: =($W86-X86)*10000 -> 0 | AK86: =($W86-Y86)*10000 -> 0 | AL86: =($W86-Z86)*10000 -> 0 | AM86: =($W86-AA86)*10000 -> 0 | AN86: =($W86-AB86)*10000 -> 0
D87: =D49+D68 -> 0 | E87: =E49+E68 -> 0 | F87: =F49+F68 -> 0 | G87: =G49+G68 -> 0 | H87: =H49+H68 -> 0 | I87: =I49+I68 -> 0 | Q87: =($D87-E87)*10000 -> 0 | R87: =($D87-F87)*10000 -> 0 | S87: =($D87-G87)*10000 -> 0 | T87: =($D87-H87)*10000 -> 0 | U87: =($D87-I87)*10000 -> 0 | W87: =W49+W68 -> 0 | X87: =X49+X68 -> 0 | Y87: =Y49+Y68 -> 0 | Z87: =Z49+Z68 -> 0 | AA87: =AA49+AA68 -> 0 | AB87: =AB49+AB68 -> 0 | AJ87: =($W87-X87)*10000 -> 0 | AK87: =($W87-Y87)*10000 -> 0 | AL87: =($W87-Z87)*10000 -> 0 | AM87: =($W87-AA87)*10000 -> 0 | AN87: =($W87-AB87)*10000 -> 0
D88: =D50+D69 -> 0 | E88: =E50+E69 -> 0 | F88: =F50+F69 -> 0 | G88: =G50+G69 -> 0 | H88: =H50+H69 -> 0 | I88: =I50+I69 -> 0 | Q88: =($D88-E88)*10000 -> 0 | R88: =($D88-F88)*10000 -> 0 | S88: =($D88-G88)*10000 -> 0 | T88: =($D88-H88)*10000 -> 0 | U88: =($D88-I88)*10000 -> 0 | W88: =W50+W69 -> 0 | X88: =X50+X69 -> 0 | Y88: =Y50+Y69 -> 0 | Z88: =Z50+Z69 -> 0 | AA88: =AA50+AA69 -> 0 | AB88: =AB50+AB69 -> 0 | AJ88: =($W88-X88)*10000 -> 0 | AK88: =($W88-Y88)*10000 -> 0 | AL88: =($W88-Z88)*10000 -> 0 | AM88: =($W88-AA88)*10000 -> 0 | AN88: =($W88-AB88)*10000 -> 0
D89: =D51+D70 -> 0 | E89: =E51+E70 -> 0 | F89: =F51+F70 -> 0 | G89: =G51+G70 -> 0 | H89: =H51+H70 -> 0 | I89: =I51+I70 -> 0 | Q89: =($D89-E89)*10000 -> 0 | R89: =($D89-F89)*10000 -> 0 | S89: =($D89-G89)*10000 -> 0 | T89: =($D89-H89)*10000 -> 0 | U89: =($D89-I89)*10000 -> 0 | W89: =W51+W70 -> 0 | X89: =X51+X70 -> 0 | Y89: =Y51+Y70 -> 0 | Z89: =Z51+Z70 -> 0 | AA89: =AA51+AA70 -> 0 | AB89: =AB51+AB70 -> 0 | AJ89: =($W89-X89)*10000 -> 0 | AK89: =($W89-Y89)*10000 -> 0 | AL89: =($W89-Z89)*10000 -> 0 | AM89: =($W89-AA89)*10000 -> 0 | AN89: =($W89-AB89)*10000 -> 0
D90: =D52+D71 -> 0 | E90: =E52+E71 -> 0 | F90: =F52+F71 -> 0 | G90: =G52+G71 -> 0 | H90: =H52+H71 -> 0 | I90: =I52+I71 -> 0 | Q90: =($D90-E90)*10000 -> 0 | R90: =($D90-F90)*10000 -> 0 | S90: =($D90-G90)*10000 -> 0 | T90: =($D90-H90)*10000 -> 0 | U90: =($D90-I90)*10000 -> 0 | W90: =W52+W71 -> 0 | X90: =X52+X71 -> 0 | Y90: =Y52+Y71 -> 0 | Z90: =Z52+Z71 -> 0 | AA90: =AA52+AA71 -> 0 | AB90: =AB52+AB71 -> 0 | AJ90: =($W90-X90)*10000 -> 0 | AK90: =($W90-Y90)*10000 -> 0 | AL90: =($W90-Z90)*10000 -> 0 | AM90: =($W90-AA90)*10000 -> 0 | AN90: =($W90-AB90)*10000 -> 0
D91: =D53+D72 -> 0 | E91: =E53+E72 -> 0 | F91: =F53+F72 -> 0 | G91: =G53+G72 -> 0 | H91: =H53+H72 -> 0 | I91: =I53+I72 -> 0 | Q91: =($D91-E91)*10000 -> 0 | R91: =($D91-F91)*10000 -> 0 | S91: =($D91-G91)*10000 -> 0 | T91: =($D91-H91)*10000 -> 0 | U91: =($D91-I91)*10000 -> 0 | W91: =W53+W72 -> 0 | X91: =X53+X72 -> 0 | Y91: =Y53+Y72 -> 0 | Z91: =Z53+Z72 -> 0 | AA91: =AA53+AA72 -> 0 | AB91: =AB53+AB72 -> 0 | AJ91: =($W91-X91)*10000 -> 0 | AK91: =($W91-Y91)*10000 -> 0 | AL91: =($W91-Z91)*10000 -> 0 | AM91: =($W91-AA91)*10000 -> 0 | AN91: =($W91-AB91)*10000 -> 0
D92: =D54+D73 -> 0 | E92: =E54+E73 -> 0.042497138 | F92: =F54+F73 -> 0 | G92: =G54+G73 -> 0 | H92: =H54+H73 -> 0 | I92: =I54+I73 -> 0 | Q92: =($D92-E92)*10000 -> -424.97138 | R92: =($D92-F92)*10000 -> 0 | S92: =($D92-G92)*10000 -> 0 | T92: =($D92-H92)*10000 -> 0 | U92: =($D92-I92)*10000 -> 0 | W92: =W54+W73 -> 0 | X92: =X54+X73 -> 0.04252755 | Y92: =Y54+Y73 -> 0 | Z92: =Z54+Z73 -> 0 | AA92: =AA54+AA73 -> 0 | AB92: =AB54+AB73 -> 0 | AJ92: =($W92-X92)*10000 -> -425.2755 | AK92: =($W92-Y92)*10000 -> 0 | AL92: =($W92-Z92)*10000 -> 0 | AM92: =($W92-AA92)*10000 -> 0 | AN92: =($W92-AB92)*10000 -> 0
D93: =D55+D74 -> 0 | E93: =E55+E74 -> 0 | F93: =F55+F74 -> 0 | G93: =G55+G74 -> 0 | H93: =H55+H74 -> 0 | I93: =I55+I74 -> 0 | Q93: =($D93-E93)*10000 -> 0 | R93: =($D93-F93)*10000 -> 0 | S93: =($D93-G93)*10000 -> 0 | T93: =($D93-H93)*10000 -> 0 | U93: =($D93-I93)*10000 -> 0 | W93: =W55+W74 -> 0 | X93: =X55+X74 -> 0 | Y93: =Y55+Y74 -> 0 | Z93: =Z55+Z74 -> 0 | AA93: =AA55+AA74 -> 0 | AB93: =AB55+AB74 -> 0 | AJ93: =($W93-X93)*10000 -> 0 | AK93: =($W93-Y93)*10000 -> 0 | AL93: =($W93-Z93)*10000 -> 0 | AM93: =($W93-AA93)*10000 -> 0 | AN93: =($W93-AB93)*10000 -> 0
D94: =D56+D75 -> 0 | E94: =E56+E75 -> 0 | F94: =F56+F75 -> 0 | G94: =G56+G75 -> 0 | H94: =H56+H75 -> 0 | I94: =I56+I75 -> 0 | Q94: =($D94-E94)*10000 -> 0 | R94: =($D94-F94)*10000 -> 0 | S94: =($D94-G94)*10000 -> 0 | T94: =($D94-H94)*10000 -> 0 | U94: =($D94-I94)*10000 -> 0 | W94: =W56+W75 -> 0 | X94: =X56+X75 -> 0 | Y94: =Y56+Y75 -> 0 | Z94: =Z56+Z75 -> 0 | AA94: =AA56+AA75 -> 0 | AB94: =AB56+AB75 -> 0 | AJ94: =($W94-X94)*10000 -> 0 | AK94: =($W94-Y94)*10000 -> 0 | AL94: =($W94-Z94)*10000 -> 0 | AM94: =($W94-AA94)*10000 -> 0 | AN94: =($W94-AB94)*10000 -> 0
D95: =D57+D76 -> 0 | E95: =E57+E76 -> 0 | F95: =F57+F76 -> 0 | G95: =G57+G76 -> 0 | H95: =H57+H76 -> 0 | I95: =I57+I76 -> 0 | Q95: =($D95-E95)*10000 -> 0 | R95: =($D95-F95)*10000 -> 0 | S95: =($D95-G95)*10000 -> 0 | T95: =($D95-H95)*10000 -> 0 | U95: =($D95-I95)*10000 -> 0 | W95: =W57+W76 -> 0 | X95: =X57+X76 -> 0 | Y95: =Y57+Y76 -> 0 | Z95: =Z57+Z76 -> 0 | AA95: =AA57+AA76 -> 0 | AB95: =AB57+AB76 -> 0 | AJ95: =($W95-X95)*10000 -> 0 | AK95: =($W95-Y95)*10000 -> 0 | AL95: =($W95-Z95)*10000 -> 0 | AM95: =($W95-AA95)*10000 -> 0 | AN95: =($W95-AB95)*10000 -> 0
D96: =D58+D77 -> 0 | E96: =E58+E77 -> 0 | F96: =F58+F77 -> 0 | G96: =G58+G77 -> 0 | H96: =H58+H77 -> 0 | I96: =I58+I77 -> 0 | Q96: =($D96-E96)*10000 -> 0 | R96: =($D96-F96)*10000 -> 0 | S96: =($D96-G96)*10000 -> 0 | T96: =($D96-H96)*10000 -> 0 | U96: =($D96-I96)*10000 -> 0 | W96: =W58+W77 -> 0 | X96: =X58+X77 -> 0 | Y96: =Y58+Y77 -> 0 | Z96: =Z58+Z77 -> 0 | AA96: =AA58+AA77 -> 0 | AB96: =AB58+AB77 -> 0 | AJ96: =($W96-X96)*10000 -> 0 | AK96: =($W96-Y96)*10000 -> 0 | AL96: =($W96-Z96)*10000 -> 0 | AM96: =($W96-AA96)*10000 -> 0 | AN96: =($W96-AB96)*10000 -> 0
... D99: =D61+D80 -> 0 | E99: =E61+E80 -> 0 | F99: =F61+F80 -> 0 | G99: =G61+G80 -> 0 | H99: =H61+H80 -> 0 | I99: =I61+I80 -> 0 | Q99: =($D99-E99)*10000 -> 0 | R99: =($D99-F99)*10000 -> 0 | S99: =($D99-G99)*10000 -> 0 | T99: =($D99-H99)*10000 -> 0 | U99: =($D99-I99)*10000 -> 0 | W99: =W61+W80 -> 0 | X99: =X61+X80 -> 0 | Y99: =Y61+Y80 -> 0 | Z99: =Z61+Z80 -> 0 | AA99: =AA61+AA80 -> 0 | AB99: =AB61+AB80 -> 0 | AJ99: =($W99-X99)*10000 -> 0 | AK99: =($W99-Y99)*10000 -> 0 | AL99: =($W99-Z99)*10000 -> 0 | AM99: =($W99-AA99)*10000 -> 0 | AN99: =($W99-AB99)*10000 -> 0
C100: Spread | D100: =D62+D81 -> 0 | E100: =E62+E81 -> 0.042497138 | F100: =F62+F81 -> 0 | G100: =G62+G81 -> 0 | H100: =H62+H81 -> 0 | I100: =I62+I81 -> 0 | Q100: =($D100-E100)*10000 -> -424.97138 | R100: =($D100-F100)*10000 -> 0 | S100: =($D100-G100)*10000 -> 0 | T100: =($D100-H100)*10000 -> 0 | U100: =($D100-I100)*10000 -> 0 | W100: =W62+W81 -> 0 | X100: =X62+X81 -> 0.04252755 | Y100: =Y62+Y81 -> 0 | Z100: =Z62+Z81 -> 0 | AA100: =AA62+AA81 -> 0 | AB100: =AB62+AB81 -> 0 | AJ100: =($W100-X100)*10000 -> -425.2755 | AK100: =($W100-Y100)*10000 -> 0 | AL100: =($W100-Z100)*10000 -> 0 | AM100: =($W100-AA100)*10000 -> 0 | AN100: =($W100-AB100)*10000 -> 0
A103: Ingreso_Financiero | C103: Cuenta Sueldo | D103: {=_xlfn.XLOOKUP(1, (INDIRECT("'"&$C$6&"'!$6:$6")=D$6)* (INDIRECT("'"&$C$6&"'!$5:$5")=D$5), INDIRECT("'"&$C$6&"'!"&ROW()&":"&ROW()) )} -> 0 | E103: {=_xlfn.XLOOKUP(1, (INDIRECT("'"&$C$6&"'!$6:$6")=E$6)* (INDIRECT("'"&$C$6&"'!$5:$5")=E$5), INDIRECT("'"&$C$6&"'!"&ROW()&":"&ROW()) )} -> 6312.5778 | F103: {=_xlfn.XLOOKUP(1, (INDIRECT("'"&$C$6&"'!$6:$6")=F$6)* (INDIRECT("'"&$C$6&"'!$5:$5")=F$5), INDIRECT("'"&$C$6&"'!"&ROW()&":"&ROW()) )} -> 0 | G103: {=_xlfn.XLOOKUP(1, (INDIRECT("'"&$C$6&"'!$6:$6")=G$6)* (INDIRECT("'"&$C$6&"'!$5:$5")=G$5), INDIRECT("'"&$C$6&"'!"&ROW()&":"&ROW()) )} -> 0 | H103: {=_xlfn.XLOOKUP(1, (INDIRECT("'"&$C$6&"'!$6:$6")=H$6)* (INDIRECT("'"&$C$6&"'!$5:$5")=H$5), INDIRECT("'"&$C$6&"'!"&ROW()&":"&ROW()) )} -> 0 | I103: {=_xlfn.XLOOKUP(1, (INDIRECT("'"&$C$6&"'!$6:$6")=I$6)* (INDIRECT("'"&$C$6&"'!$5:$5")=I$5), INDIRECT("'"&$C$6&"'!"&ROW()&":"&ROW()) )} -> 0 | K103: =$D103-E103 -> -6312.5778 | L103: =$D103-F103 -> 0 | M103: =$D103-G103 -> 0 | N103: =$D103-H103 -> 0 | O103: =$D103-I103 -> 0 | Q103: =IFERROR($D103/E103-1,0) -> -1 | R103: =IFERROR($D103/F103-1,0) -> 0 | S103: =IFERROR($D103/G103-1,0) -> 0 | T103: =IFERROR($D103/H103-1,0) -> 0 | U103: =IFERROR($D103/I103-1,0) -> 0 | W103: {=INDIRECT("'"&$C$6&"'!"&ADDRESS(ROW(),COLUMN()+44))} -> 0 | X103: {=INDIRECT("'"&$C$6&"'!"&ADDRESS(ROW(),COLUMN()+44))} -> 31099.526 | Y103: {=INDIRECT("'"&$C$6&"'!"&ADDRESS(ROW(),COLUMN()+44))} -> 0 | Z103: {=INDIRECT("'"&$C$6&"'!"&ADDRESS(ROW(),COLUMN()+44))} -> 0 | AA103: {=INDIRECT("'"&$C$6&"'!"&ADDRESS(ROW(),COLUMN()+44))} -> 0 | AB103: {=INDIRECT("'"&$C$6&"'!"&ADDRESS(ROW(),COLUMN()+44))} -> 0 | AD103: =$W103-X103 -> -31099.526 | AE103: =$W103-Y103 -> 0 | AF103: =$W103-Z103 -> 0 | AG103: =$W103-AA103 -> 0 | AH103: =$W103-AB103 -> 0 | AJ103: =IFERROR($W103/X103-1,0) -> -1 | AK103: =IFERROR($W103/Y103-1,0) -> 0 | AL103: =IFERROR($W103/Z103-1,0) -> 0 | AM103: =IFERROR($W103/AA103-1,0) -> 0 | AN103: =IFERROR($W103/AB103-1,0) -> 0
A104: Ingreso_Financiero | D104: {=_xlfn.XLOOKUP(1, (INDIRECT("'"&$C$6&"'!$6:$6")=D$6)* (INDIRECT("'"&$C$6&"'!$5:$5")=D$5), INDIRECT("'"&$C$6&"'!"&ROW()&":"&ROW()) )} -> 0 | E104: {=_xlfn.XLOOKUP(1, (INDIRECT("'"&$C$6&"'!$6:$6")=E$6)* (INDIRECT("'"&$C$6&"'!$5:$5")=E$5), INDIRECT("'"&$C$6&"'!"&ROW()&":"&ROW()) )} -> 0 | F104: {=_xlfn.XLOOKUP(1, (INDIRECT("'"&$C$6&"'!$6:$6")=F$6)* (INDIRECT("'"&$C$6&"'!$5:$5")=F$5), INDIRECT("'"&$C$6&"'!"&ROW()&":"&ROW()) )} -> 0 | G104: {=_xlfn.XLOOKUP(1, (INDIRECT("'"&$C$6&"'!$6:$6")=G$6)* (INDIRECT("'"&$C$6&"'!$5:$5")=G$5), INDIRECT("'"&$C$6&"'!"&ROW()&":"&ROW()) )} -> 0 | H104: {=_xlfn.XLOOKUP(1, (INDIRECT("'"&$C$6&"'!$6:$6")=H$6)* (INDIRECT("'"&$C$6&"'!$5:$5")=H$5), INDIRECT("'"&$C$6&"'!"&ROW()&":"&ROW()) )} -> 0 | I104: {=_xlfn.XLOOKUP(1, (INDIRECT("'"&$C$6&"'!$6:$6")=I$6)* (INDIRECT("'"&$C$6&"'!$5:$5")=I$5), INDIRECT("'"&$C$6&"'!"&ROW()&":"&ROW()) )} -> 0 | K104: =$D104-E104 -> 0 | L104: =$D104-F104 -> 0 | M104: =$D104-G104 -> 0 | N104: =$D104-H104 -> 0 | O104: =$D104-I104 -> 0 | Q104: =IFERROR($D104/E104-1,0) -> 0 | R104: =IFERROR($D104/F104-1,0) -> 0 | S104: =IFERROR($D104/G104-1,0) -> 0 | T104: =IFERROR($D104/H104-1,0) -> 0 | U104: =IFERROR($D104/I104-1,0) -> 0 | W104: {=INDIRECT("'"&$C$6&"'!"&ADDRESS(ROW(),COLUMN()+44))} -> 0 | X104: {=INDIRECT("'"&$C$6&"'!"&ADDRESS(ROW(),COLUMN()+44))} -> 0 | Y104: {=INDIRECT("'"&$C$6&"'!"&ADDRESS(ROW(),COLUMN()+44))} -> 0 | Z104: {=INDIRECT("'"&$C$6&"'!"&ADDRESS(ROW(),COLUMN()+44))} -> 0 | AA104: {=INDIRECT("'"&$C$6&"'!"&ADDRESS(ROW(),COLUMN()+44))} -> 0 | AB104: {=INDIRECT("'"&$C$6&"'!"&ADDRESS(ROW(),COLUMN()+44))} -> 0 | AD104: =$W104-X104 -> 0 | AE104: =$W104-Y104 -> 0 | AF104: =$W104-Z104 -> 0 | AG104: =$W104-AA104 -> 0 | AH104: =$W104-AB104 -> 0 | AJ104: =IFERROR($W104/X104-1,0) -> 0 | AK104: =IFERROR($W104/Y104-1,0) -> 0 | AL104: =IFERROR($W104/Z104-1,0) -> 0 | AM104: =IFERROR($W104/AA104-1,0) -> 0 | AN104: =IFERROR($W104/AB104-1,0) -> 0
A105: Ingreso_Financiero | D105: {=_xlfn.XLOOKUP(1, (INDIRECT("'"&$C$6&"'!$6:$6")=D$6)* (INDIRECT("'"&$C$6&"'!$5:$5")=D$5), INDIRECT("'"&$C$6&"'!"&ROW()&":"&ROW()) )} -> 0 | E105: {=_xlfn.XLOOKUP(1, (INDIRECT("'"&$C$6&"'!$6:$6")=E$6)* (INDIRECT("'"&$C$6&"'!$5:$5")=E$5), INDIRECT("'"&$C$6&"'!"&ROW()&":"&ROW()) )} -> 0 | F105: {=_xlfn.XLOOKUP(1, (INDIRECT("'"&$C$6&"'!$6:$6")=F$6)* (INDIRECT("'"&$C$6&"'!$5:$5")=F$5), INDIRECT("'"&$C$6&"'!"&ROW()&":"&ROW()) )} -> 0 | G105: {=_xlfn.XLOOKUP(1, (INDIRECT("'"&$C$6&"'!$6:$6")=G$6)* (INDIRECT("'"&$C$6&"'!$5:$5")=G$5), INDIRECT("'"&$C$6&"'!"&ROW()&":"&ROW()) )} -> 0 | H105: {=_xlfn.XLOOKUP(1, (INDIRECT("'"&$C$6&"'!$6:$6")=H$6)* (INDIRECT("'"&$C$6&"'!$5:$5")=H$5), INDIRECT("'"&$C$6&"'!"&ROW()&":"&ROW()) )} -> 0 | I105: {=_xlfn.XLOOKUP(1, (INDIRECT("'"&$C$6&"'!$6:$6")=I$6)* (INDIRECT("'"&$C$6&"'!$5:$5")=I$5), INDIRECT("'"&$C$6&"'!"&ROW()&":"&ROW()) )} -> 0 | K105: =$D105-E105 -> 0 | L105: =$D105-F105 -> 0 | M105: =$D105-G105 -> 0 | N105: =$D105-H105 -> 0 | O105: =$D105-I105 -> 0 | Q105: =IFERROR($D105/E105-1,0) -> 0 | R105: =IFERROR($D105/F105-1,0) -> 0 | S105: =IFERROR($D105/G105-1,0) -> 0 | T105: =IFERROR($D105/H105-1,0) -> 0 | U105: =IFERROR($D105/I105-1,0) -> 0 | W105: {=INDIRECT("'"&$C$6&"'!"&ADDRESS(ROW(),COLUMN()+44))} -> 0 | X105: {=INDIRECT("'"&$C$6&"'!"&ADDRESS(ROW(),COLUMN()+44))} -> 0 | Y105: {=INDIRECT("'"&$C$6&"'!"&ADDRESS(ROW(),COLUMN()+44))} -> 0 | Z105: {=INDIRECT("'"&$C$6&"'!"&ADDRESS(ROW(),COLUMN()+44))} -> 0 | AA105: {=INDIRECT("'"&$C$6&"'!"&ADDRESS(ROW(),COLUMN()+44))} -> 0 | AB105: {=INDIRECT("'"&$C$6&"'!"&ADDRESS(ROW(),COLUMN()+44))} -> 0 | AD105: =$W105-X105 -> 0 | AE105: =$W105-Y105 -> 0 | AF105: =$W105-Z105 -> 0 | AG105: =$W105-AA105 -> 0 | AH105: =$W105-AB105 -> 0 | AJ105: =IFERROR($W105/X105-1,0) -> 0 | AK105: =IFERROR($W105/Y105-1,0) -> 0 | AL105: =IFERROR($W105/Z105-1,0) -> 0 | AM105: =IFERROR($W105/AA105-1,0) -> 0 | AN105: =IFERROR($W105/AB105-1,0) -> 0
A106: Ingreso_Financiero | D106: {=_xlfn.XLOOKUP(1, (INDIRECT("'"&$C$6&"'!$6:$6")=D$6)* (INDIRECT("'"&$C$6&"'!$5:$5")=D$5), INDIRECT("'"&$C$6&"'!"&ROW()&":"&ROW()) )} -> 0 | E106: {=_xlfn.XLOOKUP(1, (INDIRECT("'"&$C$6&"'!$6:$6")=E$6)* (INDIRECT("'"&$C$6&"'!$5:$5")=E$5), INDIRECT("'"&$C$6&"'!"&ROW()&":"&ROW()) )} -> 0 | F106: {=_xlfn.XLOOKUP(1, (INDIRECT("'"&$C$6&"'!$6:$6")=F$6)* (INDIRECT("'"&$C$6&"'!$5:$5")=F$5), INDIRECT("'"&$C$6&"'!"&ROW()&":"&ROW()) )} -> 0 | G106: {=_xlfn.XLOOKUP(1, (INDIRECT("'"&$C$6&"'!$6:$6")=G$6)* (INDIRECT("'"&$C$6&"'!$5:$5")=G$5), INDIRECT("'"&$C$6&"'!"&ROW()&":"&ROW()) )} -> 0 | H106: {=_xlfn.XLOOKUP(1, (INDIRECT("'"&$C$6&"'!$6:$6")=H$6)* (INDIRECT("'"&$C$6&"'!$5:$5")=H$5), INDIRECT("'"&$C$6&"'!"&ROW()&":"&ROW()) )} -> 0 | I106: {=_xlfn.XLOOKUP(1, (INDIRECT("'"&$C$6&"'!$6:$6")=I$6)* (INDIRECT("'"&$C$6&"'!$5:$5")=I$5), INDIRECT("'"&$C$6&"'!"&ROW()&":"&ROW()) )} -> 0 | K106: =$D106-E106 -> 0 | L106: =$D106-F106 -> 0 | M106: =$D106-G106 -> 0 | N106: =$D106-H106 -> 0 | O106: =$D106-I106 -> 0 | Q106: =IFERROR($D106/E106-1,0) -> 0 | R106: =IFERROR($D106/F106-1,0) -> 0 | S106: =IFERROR($D106/G106-1,0) -> 0 | T106: =IFERROR($D106/H106-1,0) -> 0 | U106: =IFERROR($D106/I106-1,0) -> 0 | W106: {=INDIRECT("'"&$C$6&"'!"&ADDRESS(ROW(),COLUMN()+44))} -> 0 | X106: {=INDIRECT("'"&$C$6&"'!"&ADDRESS(ROW(),COLUMN()+44))} -> 0 | Y106: {=INDIRECT("'"&$C$6&"'!"&ADDRESS(ROW(),COLUMN()+44))} -> 0 | Z106: {=INDIRECT("'"&$C$6&"'!"&ADDRESS(ROW(),COLUMN()+44))} -> 0 | AA106: {=INDIRECT("'"&$C$6&"'!"&ADDRESS(ROW(),COLUMN()+44))} -> 0 | AB106: {=INDIRECT("'"&$C$6&"'!"&ADDRESS(ROW(),COLUMN()+44))} -> 0 | AD106: =$W106-X106 -> 0 | AE106: =$W106-Y106 -> 0 | AF106: =$W106-Z106 -> 0 | AG106: =$W106-AA106 -> 0 | AH106: =$W106-AB106 -> 0 | AJ106: =IFERROR($W106/X106-1,0) -> 0 | AK106: =IFERROR($W106/Y106-1,0) -> 0 | AL106: =IFERROR($W106/Z106-1,0) -> 0 | AM106: =IFERROR($W106/AA106-1,0) -> 0 | AN106: =IFERROR($W106/AB106-1,0) -> 0
A107: Ingreso_Financiero | D107: {=_xlfn.XLOOKUP(1, (INDIRECT("'"&$C$6&"'!$6:$6")=D$6)* (INDIRECT("'"&$C$6&"'!$5:$5")=D$5), INDIRECT("'"&$C$6&"'!"&ROW()&":"&ROW()) )} -> 0 | E107: {=_xlfn.XLOOKUP(1, (INDIRECT("'"&$C$6&"'!$6:$6")=E$6)* (INDIRECT("'"&$C$6&"'!$5:$5")=E$5), INDIRECT("'"&$C$6&"'!"&ROW()&":"&ROW()) )} -> 0 | F107: {=_xlfn.XLOOKUP(1, (INDIRECT("'"&$C$6&"'!$6:$6")=F$6)* (INDIRECT("'"&$C$6&"'!$5:$5")=F$5), INDIRECT("'"&$C$6&"'!"&ROW()&":"&ROW()) )} -> 0 | G107: {=_xlfn.XLOOKUP(1, (INDIRECT("'"&$C$6&"'!$6:$6")=G$6)* (INDIRECT("'"&$C$6&"'!$5:$5")=G$5), INDIRECT("'"&$C$6&"'!"&ROW()&":"&ROW()) )} -> 0 | H107: {=_xlfn.XLOOKUP(1, (INDIRECT("'"&$C$6&"'!$6:$6")=H$6)* (INDIRECT("'"&$C$6&"'!$5:$5")=H$5), INDIRECT("'"&$C$6&"'!"&ROW()&":"&ROW()) )} -> 0 | I107: {=_xlfn.XLOOKUP(1, (INDIRECT("'"&$C$6&"'!$6:$6")=I$6)* (INDIRECT("'"&$C$6&"'!$5:$5")=I$5), INDIRECT("'"&$C$6&"'!"&ROW()&":"&ROW()) )} -> 0 | K107: =$D107-E107 -> 0 | L107: =$D107-F107 -> 0 | M107: =$D107-G107 -> 0 | N107: =$D107-H107 -> 0 | O107: =$D107-I107 -> 0 | Q107: =IFERROR($D107/E107-1,0) -> 0 | R107: =IFERROR($D107/F107-1,0) -> 0 | S107: =IFERROR($D107/G107-1,0) -> 0 | T107: =IFERROR($D107/H107-1,0) -> 0 | U107: =IFERROR($D107/I107-1,0) -> 0 | W107: {=INDIRECT("'"&$C$6&"'!"&ADDRESS(ROW(),COLUMN()+44))} -> 0 | X107: {=INDIRECT("'"&$C$6&"'!"&ADDRESS(ROW(),COLUMN()+44))} -> 0 | Y107: {=INDIRECT("'"&$C$6&"'!"&ADDRESS(ROW(),COLUMN()+44))} -> 0 | Z107: {=INDIRECT("'"&$C$6&"'!"&ADDRESS(ROW(),COLUMN()+44))} -> 0 | AA107: {=INDIRECT("'"&$C$6&"'!"&ADDRESS(ROW(),COLUMN()+44))} -> 0 | AB107: {=INDIRECT("'"&$C$6&"'!"&ADDRESS(ROW(),COLUMN()+44))} -> 0 | AD107: =$W107-X107 -> 0 | AE107: =$W107-Y107 -> 0 | AF107: =$W107-Z107 -> 0 | AG107: =$W107-AA107 -> 0 | AH107: =$W107-AB107 -> 0 | AJ107: =IFERROR($W107/X107-1,0) -> 0 | AK107: =IFERROR($W107/Y107-1,0) -> 0 | AL107: =IFERROR($W107/Z107-1,0) -> 0 | AM107: =IFERROR($W107/AA107-1,0) -> 0 | AN107: =IFERROR($W107/AB107-1,0) -> 0
A108: Ingreso_Financiero | D108: {=_xlfn.XLOOKUP(1, (INDIRECT("'"&$C$6&"'!$6:$6")=D$6)* (INDIRECT("'"&$C$6&"'!$5:$5")=D$5), INDIRECT("'"&$C$6&"'!"&ROW()&":"&ROW()) )} -> 0 | E108: {=_xlfn.XLOOKUP(1, (INDIRECT("'"&$C$6&"'!$6:$6")=E$6)* (INDIRECT("'"&$C$6&"'!$5:$5")=E$5), INDIRECT("'"&$C$6&"'!"&ROW()&":"&ROW()) )} -> 0 | F108: {=_xlfn.XLOOKUP(1, (INDIRECT("'"&$C$6&"'!$6:$6")=F$6)* (INDIRECT("'"&$C$6&"'!$5:$5")=F$5), INDIRECT("'"&$C$6&"'!"&ROW()&":"&ROW()) )} -> 0 | G108: {=_xlfn.XLOOKUP(1, (INDIRECT("'"&$C$6&"'!$6:$6")=G$6)* (INDIRECT("'"&$C$6&"'!$5:$5")=G$5), INDIRECT("'"&$C$6&"'!"&ROW()&":"&ROW()) )} -> 0 | H108: {=_xlfn.XLOOKUP(1, (INDIRECT("'"&$C$6&"'!$6:$6")=H$6)* (INDIRECT("'"&$C$6&"'!$5:$5")=H$5), INDIRECT("'"&$C$6&"'!"&ROW()&":"&ROW()) )} -> 0 | I108: {=_xlfn.XLOOKUP(1, (INDIRECT("'"&$C$6&"'!$6:$6")=I$6)* (INDIRECT("'"&$C$6&"'!$5:$5")=I$5), INDIRECT("'"&$C$6&"'!"&ROW()&":"&ROW()) )} -> 0 | K108: =$D108-E108 -> 0 | L108: =$D108-F108 -> 0 | M108: =$D108-G108 -> 0 | N108: =$D108-H108 -> 0 | O108: =$D108-I108 -> 0 | Q108: =IFERROR($D108/E108-1,0) -> 0 | R108: =IFERROR($D108/F108-1,0) -> 0 | S108: =IFERROR($D108/G108-1,0) -> 0 | T108: =IFERROR($D108/H108-1,0) -> 0 | U108: =IFERROR($D108/I108-1,0) -> 0 | W108: {=INDIRECT("'"&$C$6&"'!"&ADDRESS(ROW(),COLUMN()+44))} -> 0 | X108: {=INDIRECT("'"&$C$6&"'!"&ADDRESS(ROW(),COLUMN()+44))} -> 0 | Y108: {=INDIRECT("'"&$C$6&"'!"&ADDRESS(ROW(),COLUMN()+44))} -> 0 | Z108: {=INDIRECT("'"&$C$6&"'!"&ADDRESS(ROW(),COLUMN()+44))} -> 0 | AA108: {=INDIRECT("'"&$C$6&"'!"&ADDRESS(ROW(),COLUMN()+44))} -> 0 | AB108: {=INDIRECT("'"&$C$6&"'!"&ADDRESS(ROW(),COLUMN()+44))} -> 0 | AD108: =$W108-X108 -> 0 | AE108: =$W108-Y108 -> 0 | AF108: =$W108-Z108 -> 0 | AG108: =$W108-AA108 -> 0 | AH108: =$W108-AB108 -> 0 | AJ108: =IFERROR($W108/X108-1,0) -> 0 | AK108: =IFERROR($W108/Y108-1,0) -> 0 | AL108: =IFERROR($W108/Z108-1,0) -> 0 | AM108: =IFERROR($W108/AA108-1,0) -> 0 | AN108: =IFERROR($W108/AB108-1,0) -> 0
A109: Ingreso_Financiero | D109: {=_xlfn.XLOOKUP(1, (INDIRECT("'"&$C$6&"'!$6:$6")=D$6)* (INDIRECT("'"&$C$6&"'!$5:$5")=D$5), INDIRECT("'"&$C$6&"'!"&ROW()&":"&ROW()) )} -> 0 | E109: {=_xlfn.XLOOKUP(1, (INDIRECT("'"&$C$6&"'!$6:$6")=E$6)* (INDIRECT("'"&$C$6&"'!$5:$5")=E$5), INDIRECT("'"&$C$6&"'!"&ROW()&":"&ROW()) )} -> 0 | F109: {=_xlfn.XLOOKUP(1, (INDIRECT("'"&$C$6&"'!$6:$6")=F$6)* (INDIRECT("'"&$C$6&"'!$5:$5")=F$5), INDIRECT("'"&$C$6&"'!"&ROW()&":"&ROW()) )} -> 0 | G109: {=_xlfn.XLOOKUP(1, (INDIRECT("'"&$C$6&"'!$6:$6")=G$6)* (INDIRECT("'"&$C$6&"'!$5:$5")=G$5), INDIRECT("'"&$C$6&"'!"&ROW()&":"&ROW()) )} -> 0 | H109: {=_xlfn.XLOOKUP(1, (INDIRECT("'"&$C$6&"'!$6:$6")=H$6)* (INDIRECT("'"&$C$6&"'!$5:$5")=H$5), INDIRECT("'"&$C$6&"'!"&ROW()&":"&ROW()) )} -> 0 | I109: {=_xlfn.XLOOKUP(1, (INDIRECT("'"&$C$6&"'!$6:$6")=I$6)* (INDIRECT("'"&$C$6&"'!$5:$5")=I$5), INDIRECT("'"&$C$6&"'!"&ROW()&":"&ROW()) )} -> 0 | K109: =$D109-E109 -> 0 | L109: =$D109-F109 -> 0 | M109: =$D109-G109 -> 0 | N109: =$D109-H109 -> 0 | O109: =$D109-I109 -> 0 | Q109: =IFERROR($D109/E109-1,0) -> 0 | R109: =IFERROR($D109/F109-1,0) -> 0 | S109: =IFERROR($D109/G109-1,0) -> 0 | T109: =IFERROR($D109/H109-1,0) -> 0 | U109: =IFERROR($D109/I109-1,0) -> 0 | W109: {=INDIRECT("'"&$C$6&"'!"&ADDRESS(ROW(),COLUMN()+44))} -> 0 | X109: {=INDIRECT("'"&$C$6&"'!"&ADDRESS(ROW(),COLUMN()+44))} -> 0 | Y109: {=INDIRECT("'"&$C$6&"'!"&ADDRESS(ROW(),COLUMN()+44))} -> 0 | Z109: {=INDIRECT("'"&$C$6&"'!"&ADDRESS(ROW(),COLUMN()+44))} -> 0 | AA109: {=INDIRECT("'"&$C$6&"'!"&ADDRESS(ROW(),COLUMN()+44))} -> 0 | AB109: {=INDIRECT("'"&$C$6&"'!"&ADDRESS(ROW(),COLUMN()+44))} -> 0 | AD109: =$W109-X109 -> 0 | AE109: =$W109-Y109 -> 0 | AF109: =$W109-Z109 -> 0 | AG109: =$W109-AA109 -> 0 | AH109: =$W109-AB109 -> 0 | AJ109: =IFERROR($W109/X109-1,0) -> 0 | AK109: =IFERROR($W109/Y109-1,0) -> 0 | AL109: =IFERROR($W109/Z109-1,0) -> 0 | AM109: =IFERROR($W109/AA109-1,0) -> 0 | AN109: =IFERROR($W109/AB109-1,0) -> 0
A110: Ingreso_Financiero | D110: {=_xlfn.XLOOKUP(1, (INDIRECT("'"&$C$6&"'!$6:$6")=D$6)* (INDIRECT("'"&$C$6&"'!$5:$5")=D$5), INDIRECT("'"&$C$6&"'!"&ROW()&":"&ROW()) )} -> 0 | E110: {=_xlfn.XLOOKUP(1, (INDIRECT("'"&$C$6&"'!$6:$6")=E$6)* (INDIRECT("'"&$C$6&"'!$5:$5")=E$5), INDIRECT("'"&$C$6&"'!"&ROW()&":"&ROW()) )} -> 0 | F110: {=_xlfn.XLOOKUP(1, (INDIRECT("'"&$C$6&"'!$6:$6")=F$6)* (INDIRECT("'"&$C$6&"'!$5:$5")=F$5), INDIRECT("'"&$C$6&"'!"&ROW()&":"&ROW()) )} -> 0 | G110: {=_xlfn.XLOOKUP(1, (INDIRECT("'"&$C$6&"'!$6:$6")=G$6)* (INDIRECT("'"&$C$6&"'!$5:$5")=G$5), INDIRECT("'"&$C$6&"'!"&ROW()&":"&ROW()) )} -> 0 | H110: {=_xlfn.XLOOKUP(1, (INDIRECT("'"&$C$6&"'!$6:$6")=H$6)* (INDIRECT("'"&$C$6&"'!$5:$5")=H$5), INDIRECT("'"&$C$6&"'!"&ROW()&":"&ROW()) )} -> 0 | I110: {=_xlfn.XLOOKUP(1, (INDIRECT("'"&$C$6&"'!$6:$6")=I$6)* (INDIRECT("'"&$C$6&"'!$5:$5")=I$5), INDIRECT("'"&$C$6&"'!"&ROW()&":"&ROW()) )} -> 0 | K110: =$D110-E110 -> 0 | L110: =$D110-F110 -> 0 | M110: =$D110-G110 -> 0 | N110: =$D110-H110 -> 0 | O110: =$D110-I110 -> 0 | Q110: =IFERROR($D110/E110-1,0) -> 0 | R110: =IFERROR($D110/F110-1,0) -> 0 | S110: =IFERROR($D110/G110-1,0) -> 0 | T110: =IFERROR($D110/H110-1,0) -> 0 | U110: =IFERROR($D110/I110-1,0) -> 0 | W110: {=INDIRECT("'"&$C$6&"'!"&ADDRESS(ROW(),COLUMN()+44))} -> 0 | X110: {=INDIRECT("'"&$C$6&"'!"&ADDRESS(ROW(),COLUMN()+44))} -> 0 | Y110: {=INDIRECT("'"&$C$6&"'!"&ADDRESS(ROW(),COLUMN()+44))} -> 0 | Z110: {=INDIRECT("'"&$C$6&"'!"&ADDRESS(ROW(),COLUMN()+44))} -> 0 | AA110: {=INDIRECT("'"&$C$6&"'!"&ADDRESS(ROW(),COLUMN()+44))} -> 0 | AB110: {=INDIRECT("'"&$C$6&"'!"&ADDRESS(ROW(),COLUMN()+44))} -> 0 | AD110: =$W110-X110 -> 0 | AE110: =$W110-Y110 -> 0 | AF110: =$W110-Z110 -> 0 | AG110: =$W110-AA110 -> 0 | AH110: =$W110-AB110 -> 0 | AJ110: =IFERROR($W110/X110-1,0) -> 0 | AK110: =IFERROR($W110/Y110-1,0) -> 0 | AL110: =IFERROR($W110/Z110-1,0) -> 0 | AM110: =IFERROR($W110/AA110-1,0) -> 0 | AN110: =IFERROR($W110/AB110-1,0) -> 0
A111: Ingreso_Financiero | D111: =SUM(D103:D110) -> 0 | E111: =SUM(E103:E110) -> 6312.5778 | F111: =SUM(F103:F110) -> 0 | G111: =SUM(G103:G110) -> 0 | H111: =SUM(H103:H110) -> 0 | I111: =SUM(I103:I110) -> 0 | K111: =$D111-E111 -> -6312.5778 | L111: =$D111-F111 -> 0 | M111: =$D111-G111 -> 0 | N111: =$D111-H111 -> 0 | O111: =$D111-I111 -> 0 | Q111: =IFERROR($D111/E111-1,0) -> -1 | R111: =IFERROR($D111/F111-1,0) -> 0 | S111: =IFERROR($D111/G111-1,0) -> 0 | T111: =IFERROR($D111/H111-1,0) -> 0 | U111: =IFERROR($D111/I111-1,0) -> 0 | W111: =SUM(W103:W110) -> 0 | X111: =SUM(X103:X110) -> 31099.526 | Y111: =SUM(Y103:Y110) -> 0 | Z111: =SUM(Z103:Z110) -> 0 | AA111: =SUM(AA103:AA110) -> 0 | AB111: =SUM(AB103:AB110) -> 0 | AD111: =$W111-X111 -> -31099.526 | AE111: =$W111-Y111 -> 0 | AF111: =$W111-Z111 -> 0 | AG111: =$W111-AA111 -> 0 | AH111: =$W111-AB111 -> 0 | AJ111: =IFERROR($W111/X111-1,0) -> -1 | AK111: =IFERROR($W111/Y111-1,0) -> 0 | AL111: =IFERROR($W111/Z111-1,0) -> 0 | AM111: =IFERROR($W111/AA111-1,0) -> 0 | AN111: =IFERROR($W111/AB111-1,0) -> 0
A112: Ingreso_Financiero | D112: {=_xlfn.XLOOKUP(1, (INDIRECT("'"&$C$6&"'!$6:$6")=D$6)* (INDIRECT("'"&$C$6&"'!$5:$5")=D$5), INDIRECT("'"&$C$6&"'!"&ROW()&":"&ROW()) )} -> 0 | E112: {=_xlfn.XLOOKUP(1, (INDIRECT("'"&$C$6&"'!$6:$6")=E$6)* (INDIRECT("'"&$C$6&"'!$5:$5")=E$5), INDIRECT("'"&$C$6&"'!"&ROW()&":"&ROW()) )} -> 0 | F112: {=_xlfn.XLOOKUP(1, (INDIRECT("'"&$C$6&"'!$6:$6")=F$6)* (INDIRECT("'"&$C$6&"'!$5:$5")=F$5), INDIRECT("'"&$C$6&"'!"&ROW()&":"&ROW()) )} -> 0 | G112: {=_xlfn.XLOOKUP(1, (INDIRECT("'"&$C$6&"'!$6:$6")=G$6)* (INDIRECT("'"&$C$6&"'!$5:$5")=G$5), INDIRECT("'"&$C$6&"'!"&ROW()&":"&ROW()) )} -> 0 | H112: {=_xlfn.XLOOKUP(1, (INDIRECT("'"&$C$6&"'!$6:$6")=H$6)* (INDIRECT("'"&$C$6&"'!$5:$5")=H$5), INDIRECT("'"&$C$6&"'!"&ROW()&":"&ROW()) )} -> 0 | I112: {=_xlfn.XLOOKUP(1, (INDIRECT("'"&$C$6&"'!$6:$6")=I$6)* (INDIRECT("'"&$C$6&"'!$5:$5")=I$5), INDIRECT("'"&$C$6&"'!"&ROW()&":"&ROW()) )} -> 0 | K112: =$D112-E112 -> 0 | L112: =$D112-F112 -> 0 | M112: =$D112-G112 -> 0 | N112: =$D112-H112 -> 0 | O112: =$D112-I112 -> 0 | Q112: =IFERROR($D112/E112-1,0) -> 0 | R112: =IFERROR($D112/F112-1,0) -> 0 | S112: =IFERROR($D112/G112-1,0) -> 0 | T112: =IFERROR($D112/H112-1,0) -> 0 | U112: =IFERROR($D112/I112-1,0) -> 0 | W112: {=INDIRECT("'"&$C$6&"'!"&ADDRESS(ROW(),COLUMN()+44))} -> 0 | X112: {=INDIRECT("'"&$C$6&"'!"&ADDRESS(ROW(),COLUMN()+44))} -> 0 | Y112: {=INDIRECT("'"&$C$6&"'!"&ADDRESS(ROW(),COLUMN()+44))} -> 0 | Z112: {=INDIRECT("'"&$C$6&"'!"&ADDRESS(ROW(),COLUMN()+44))} -> 0 | AA112: {=INDIRECT("'"&$C$6&"'!"&ADDRESS(ROW(),COLUMN()+44))} -> 0 | AB112: {=INDIRECT("'"&$C$6&"'!"&ADDRESS(ROW(),COLUMN()+44))} -> 0 | AD112: =$W112-X112 -> 0 | AE112: =$W112-Y112 -> 0 | AF112: =$W112-Z112 -> 0 | AG112: =$W112-AA112 -> 0 | AH112: =$W112-AB112 -> 0 | AJ112: =IFERROR($W112/X112-1,0) -> 0 | AK112: =IFERROR($W112/Y112-1,0) -> 0 | AL112: =IFERROR($W112/Z112-1,0) -> 0 | AM112: =IFERROR($W112/AA112-1,0) -> 0 | AN112: =IFERROR($W112/AB112-1,0) -> 0
A113: Ingreso_Financiero | D113: {=_xlfn.XLOOKUP(1, (INDIRECT("'"&$C$6&"'!$6:$6")=D$6)* (INDIRECT("'"&$C$6&"'!$5:$5")=D$5), INDIRECT("'"&$C$6&"'!"&ROW()&":"&ROW()) )} -> 0 | E113: {=_xlfn.XLOOKUP(1, (INDIRECT("'"&$C$6&"'!$6:$6")=E$6)* (INDIRECT("'"&$C$6&"'!$5:$5")=E$5), INDIRECT("'"&$C$6&"'!"&ROW()&":"&ROW()) )} -> 0 | F113: {=_xlfn.XLOOKUP(1, (INDIRECT("'"&$C$6&"'!$6:$6")=F$6)* (INDIRECT("'"&$C$6&"'!$5:$5")=F$5), INDIRECT("'"&$C$6&"'!"&ROW()&":"&ROW()) )} -> 0 | G113: {=_xlfn.XLOOKUP(1, (INDIRECT("'"&$C$6&"'!$6:$6")=G$6)* (INDIRECT("'"&$C$6&"'!$5:$5")=G$5), INDIRECT("'"&$C$6&"'!"&ROW()&":"&ROW()) )} -> 0 | H113: {=_xlfn.XLOOKUP(1, (INDIRECT("'"&$C$6&"'!$6:$6")=H$6)* (INDIRECT("'"&$C$6&"'!$5:$5")=H$5), INDIRECT("'"&$C$6&"'!"&ROW()&":"&ROW()) )} -> 0 | I113: {=_xlfn.XLOOKUP(1, (INDIRECT("'"&$C$6&"'!$6:$6")=I$6)* (INDIRECT("'"&$C$6&"'!$5:$5")=I$5), INDIRECT("'"&$C$6&"'!"&ROW()&":"&ROW()) )} -> 0 | K113: =$D113-E113 -> 0 | L113: =$D113-F113 -> 0 | M113: =$D113-G113 -> 0 | N113: =$D113-H113 -> 0 | O113: =$D113-I113 -> 0 | Q113: =IFERROR($D113/E113-1,0) -> 0 | R113: =IFERROR($D113/F113-1,0) -> 0 | S113: =IFERROR($D113/G113-1,0) -> 0 | T113: =IFERROR($D113/H113-1,0) -> 0 | U113: =IFERROR($D113/I113-1,0) -> 0 | W113: {=INDIRECT("'"&$C$6&"'!"&ADDRESS(ROW(),COLUMN()+44))} -> 0 | X113: {=INDIRECT("'"&$C$6&"'!"&ADDRESS(ROW(),COLUMN()+44))} -> 0 | Y113: {=INDIRECT("'"&$C$6&"'!"&ADDRESS(ROW(),COLUMN()+44))} -> 0 | Z113: {=INDIRECT("'"&$C$6&"'!"&ADDRESS(ROW(),COLUMN()+44))} -> 0 | AA113: {=INDIRECT("'"&$C$6&"'!"&ADDRESS(ROW(),COLUMN()+44))} -> 0 | AB113: {=INDIRECT("'"&$C$6&"'!"&ADDRESS(ROW(),COLUMN()+44))} -> 0 | AD113: =$W113-X113 -> 0 | AE113: =$W113-Y113 -> 0 | AF113: =$W113-Z113 -> 0 | AG113: =$W113-AA113 -> 0 | AH113: =$W113-AB113 -> 0 | AJ113: =IFERROR($W113/X113-1,0) -> 0 | AK113: =IFERROR($W113/Y113-1,0) -> 0 | AL113: =IFERROR($W113/Z113-1,0) -> 0 | AM113: =IFERROR($W113/AA113-1,0) -> 0 | AN113: =IFERROR($W113/AB113-1,0) -> 0
A114: Ingreso_Financiero | D114: {=_xlfn.XLOOKUP(1, (INDIRECT("'"&$C$6&"'!$6:$6")=D$6)* (INDIRECT("'"&$C$6&"'!$5:$5")=D$5), INDIRECT("'"&$C$6&"'!"&ROW()&":"&ROW()) )} -> 0 | E114: {=_xlfn.XLOOKUP(1, (INDIRECT("'"&$C$6&"'!$6:$6")=E$6)* (INDIRECT("'"&$C$6&"'!$5:$5")=E$5), INDIRECT("'"&$C$6&"'!"&ROW()&":"&ROW()) )} -> 0 | F114: {=_xlfn.XLOOKUP(1, (INDIRECT("'"&$C$6&"'!$6:$6")=F$6)* (INDIRECT("'"&$C$6&"'!$5:$5")=F$5), INDIRECT("'"&$C$6&"'!"&ROW()&":"&ROW()) )} -> 0 | G114: {=_xlfn.XLOOKUP(1, (INDIRECT("'"&$C$6&"'!$6:$6")=G$6)* (INDIRECT("'"&$C$6&"'!$5:$5")=G$5), INDIRECT("'"&$C$6&"'!"&ROW()&":"&ROW()) )} -> 0 | H114: {=_xlfn.XLOOKUP(1, (INDIRECT("'"&$C$6&"'!$6:$6")=H$6)* (INDIRECT("'"&$C$6&"'!$5:$5")=H$5), INDIRECT("'"&$C$6&"'!"&ROW()&":"&ROW()) )} -> 0 | I114: {=_xlfn.XLOOKUP(1, (INDIRECT("'"&$C$6&"'!$6:$6")=I$6)* (INDIRECT("'"&$C$6&"'!$5:$5")=I$5), INDIRECT("'"&$C$6&"'!"&ROW()&":"&ROW()) )} -> 0 | K114: =$D114-E114 -> 0 | L114: =$D114-F114 -> 0 | M114: =$D114-G114 -> 0 | N114: =$D114-H114 -> 0 | O114: =$D114-I114 -> 0 | Q114: =IFERROR($D114/E114-1,0) -> 0 | R114: =IFERROR($D114/F114-1,0) -> 0 | S114: =IFERROR($D114/G114-1,0) -> 0 | T114: =IFERROR($D114/H114-1,0) -> 0 | U114: =IFERROR($D114/I114-1,0) -> 0 | W114: {=INDIRECT("'"&$C$6&"'!"&ADDRESS(ROW(),COLUMN()+44))} -> 0 | X114: {=INDIRECT("'"&$C$6&"'!"&ADDRESS(ROW(),COLUMN()+44))} -> 0 | Y114: {=INDIRECT("'"&$C$6&"'!"&ADDRESS(ROW(),COLUMN()+44))} -> 0 | Z114: {=INDIRECT("'"&$C$6&"'!"&ADDRESS(ROW(),COLUMN()+44))} -> 0 | AA114: {=INDIRECT("'"&$C$6&"'!"&ADDRESS(ROW(),COLUMN()+44))} -> 0 | AB114: {=INDIRECT("'"&$C$6&"'!"&ADDRESS(ROW(),COLUMN()+44))} -> 0 | AD114: =$W114-X114 -> 0 | AE114: =$W114-Y114 -> 0 | AF114: =$W114-Z114 -> 0 | AG114: =$W114-AA114 -> 0 | AH114: =$W114-AB114 -> 0 | AJ114: =IFERROR($W114/X114-1,0) -> 0 | AK114: =IFERROR($W114/Y114-1,0) -> 0 | AL114: =IFERROR($W114/Z114-1,0) -> 0 | AM114: =IFERROR($W114/AA114-1,0) -> 0 | AN114: =IFERROR($W114/AB114-1,0) -> 0
A115: Ingreso_Financiero | D115: {=_xlfn.XLOOKUP(1, (INDIRECT("'"&$C$6&"'!$6:$6")=D$6)* (INDIRECT("'"&$C$6&"'!$5:$5")=D$5), INDIRECT("'"&$C$6&"'!"&ROW()&":"&ROW()) )} -> 0 | E115: {=_xlfn.XLOOKUP(1, (INDIRECT("'"&$C$6&"'!$6:$6")=E$6)* (INDIRECT("'"&$C$6&"'!$5:$5")=E$5), INDIRECT("'"&$C$6&"'!"&ROW()&":"&ROW()) )} -> 0 | F115: {=_xlfn.XLOOKUP(1, (INDIRECT("'"&$C$6&"'!$6:$6")=F$6)* (INDIRECT("'"&$C$6&"'!$5:$5")=F$5), INDIRECT("'"&$C$6&"'!"&ROW()&":"&ROW()) )} -> 0 | G115: {=_xlfn.XLOOKUP(1, (INDIRECT("'"&$C$6&"'!$6:$6")=G$6)* (INDIRECT("'"&$C$6&"'!$5:$5")=G$5), INDIRECT("'"&$C$6&"'!"&ROW()&":"&ROW()) )} -> 0 | H115: {=_xlfn.XLOOKUP(1, (INDIRECT("'"&$C$6&"'!$6:$6")=H$6)* (INDIRECT("'"&$C$6&"'!$5:$5")=H$5), INDIRECT("'"&$C$6&"'!"&ROW()&":"&ROW()) )} -> 0 | I115: {=_xlfn.XLOOKUP(1, (INDIRECT("'"&$C$6&"'!$6:$6")=I$6)* (INDIRECT("'"&$C$6&"'!$5:$5")=I$5), INDIRECT("'"&$C$6&"'!"&ROW()&":"&ROW()) )} -> 0 | K115: =$D115-E115 -> 0 | L115: =$D115-F115 -> 0 | M115: =$D115-G115 -> 0 | N115: =$D115-H115 -> 0 | O115: =$D115-I115 -> 0 | Q115: =IFERROR($D115/E115-1,0) -> 0 | R115: =IFERROR($D115/F115-1,0) -> 0 | S115: =IFERROR($D115/G115-1,0) -> 0 | T115: =IFERROR($D115/H115-1,0) -> 0 | U115: =IFERROR($D115/I115-1,0) -> 0 | W115: {=INDIRECT("'"&$C$6&"'!"&ADDRESS(ROW(),COLUMN()+44))} -> 0 | X115: {=INDIRECT("'"&$C$6&"'!"&ADDRESS(ROW(),COLUMN()+44))} -> 0 | Y115: {=INDIRECT("'"&$C$6&"'!"&ADDRESS(ROW(),COLUMN()+44))} -> 0 | Z115: {=INDIRECT("'"&$C$6&"'!"&ADDRESS(ROW(),COLUMN()+44))} -> 0 | AA115: {=INDIRECT("'"&$C$6&"'!"&ADDRESS(ROW(),COLUMN()+44))} -> 0 | AB115: {=INDIRECT("'"&$C$6&"'!"&ADDRESS(ROW(),COLUMN()+44))} -> 0 | AD115: =$W115-X115 -> 0 | AE115: =$W115-Y115 -> 0 | AF115: =$W115-Z115 -> 0 | AG115: =$W115-AA115 -> 0 | AH115: =$W115-AB115 -> 0 | AJ115: =IFERROR($W115/X115-1,0) -> 0 | AK115: =IFERROR($W115/Y115-1,0) -> 0 | AL115: =IFERROR($W115/Z115-1,0) -> 0 | AM115: =IFERROR($W115/AA115-1,0) -> 0 | AN115: =IFERROR($W115/AB115-1,0) -> 0
A116: Ingreso_Financiero | D116: {=_xlfn.XLOOKUP(1, (INDIRECT("'"&$C$6&"'!$6:$6")=D$6)* (INDIRECT("'"&$C$6&"'!$5:$5")=D$5), INDIRECT("'"&$C$6&"'!"&ROW()&":"&ROW()) )} -> 0 | E116: {=_xlfn.XLOOKUP(1, (INDIRECT("'"&$C$6&"'!$6:$6")=E$6)* (INDIRECT("'"&$C$6&"'!$5:$5")=E$5), INDIRECT("'"&$C$6&"'!"&ROW()&":"&ROW()) )} -> 0 | F116: {=_xlfn.XLOOKUP(1, (INDIRECT("'"&$C$6&"'!$6:$6")=F$6)* (INDIRECT("'"&$C$6&"'!$5:$5")=F$5), INDIRECT("'"&$C$6&"'!"&ROW()&":"&ROW()) )} -> 0 | G116: {=_xlfn.XLOOKUP(1, (INDIRECT("'"&$C$6&"'!$6:$6")=G$6)* (INDIRECT("'"&$C$6&"'!$5:$5")=G$5), INDIRECT("'"&$C$6&"'!"&ROW()&":"&ROW()) )} -> 0 | H116: {=_xlfn.XLOOKUP(1, (INDIRECT("'"&$C$6&"'!$6:$6")=H$6)* (INDIRECT("'"&$C$6&"'!$5:$5")=H$5), INDIRECT("'"&$C$6&"'!"&ROW()&":"&ROW()) )} -> 0 | I116: {=_xlfn.XLOOKUP(1, (INDIRECT("'"&$C$6&"'!$6:$6")=I$6)* (INDIRECT("'"&$C$6&"'!$5:$5")=I$5), INDIRECT("'"&$C$6&"'!"&ROW()&":"&ROW()) )} -> 0 | K116: =$D116-E116 -> 0 | L116: =$D116-F116 -> 0 | M116: =$D116-G116 -> 0 | N116: =$D116-H116 -> 0 | O116: =$D116-I116 -> 0 | Q116: =IFERROR($D116/E116-1,0) -> 0 | R116: =IFERROR($D116/F116-1,0) -> 0 | S116: =IFERROR($D116/G116-1,0) -> 0 | T116: =IFERROR($D116/H116-1,0) -> 0 | U116: =IFERROR($D116/I116-1,0) -> 0 | W116: {=INDIRECT("'"&$C$6&"'!"&ADDRESS(ROW(),COLUMN()+44))} -> 0 | X116: {=INDIRECT("'"&$C$6&"'!"&ADDRESS(ROW(),COLUMN()+44))} -> 0 | Y116: {=INDIRECT("'"&$C$6&"'!"&ADDRESS(ROW(),COLUMN()+44))} -> 0 | Z116: {=INDIRECT("'"&$C$6&"'!"&ADDRESS(ROW(),COLUMN()+44))} -> 0 | AA116: {=INDIRECT("'"&$C$6&"'!"&ADDRESS(ROW(),COLUMN()+44))} -> 0 | AB116: {=INDIRECT("'"&$C$6&"'!"&ADDRESS(ROW(),COLUMN()+44))} -> 0 | AD116: =$W116-X116 -> 0 | AE116: =$W116-Y116 -> 0 | AF116: =$W116-Z116 -> 0 | AG116: =$W116-AA116 -> 0 | AH116: =$W116-AB116 -> 0 | AJ116: =IFERROR($W116/X116-1,0) -> 0 | AK116: =IFERROR($W116/Y116-1,0) -> 0 | AL116: =IFERROR($W116/Z116-1,0) -> 0 | AM116: =IFERROR($W116/AA116-1,0) -> 0 | AN116: =IFERROR($W116/AB116-1,0) -> 0
A117: Ingreso_Financiero | D117: {=_xlfn.XLOOKUP(1, (INDIRECT("'"&$C$6&"'!$6:$6")=D$6)* (INDIRECT("'"&$C$6&"'!$5:$5")=D$5), INDIRECT("'"&$C$6&"'!"&ROW()&":"&ROW()) )} -> 0 | E117: {=_xlfn.XLOOKUP(1, (INDIRECT("'"&$C$6&"'!$6:$6")=E$6)* (INDIRECT("'"&$C$6&"'!$5:$5")=E$5), INDIRECT("'"&$C$6&"'!"&ROW()&":"&ROW()) )} -> 0 | F117: {=_xlfn.XLOOKUP(1, (INDIRECT("'"&$C$6&"'!$6:$6")=F$6)* (INDIRECT("'"&$C$6&"'!$5:$5")=F$5), INDIRECT("'"&$C$6&"'!"&ROW()&":"&ROW()) )} -> 0 | G117: {=_xlfn.XLOOKUP(1, (INDIRECT("'"&$C$6&"'!$6:$6")=G$6)* (INDIRECT("'"&$C$6&"'!$5:$5")=G$5), INDIRECT("'"&$C$6&"'!"&ROW()&":"&ROW()) )} -> 0 | H117: {=_xlfn.XLOOKUP(1, (INDIRECT("'"&$C$6&"'!$6:$6")=H$6)* (INDIRECT("'"&$C$6&"'!$5:$5")=H$5), INDIRECT("'"&$C$6&"'!"&ROW()&":"&ROW()) )} -> 0 | I117: {=_xlfn.XLOOKUP(1, (INDIRECT("'"&$C$6&"'!$6:$6")=I$6)* (INDIRECT("'"&$C$6&"'!$5:$5")=I$5), INDIRECT("'"&$C$6&"'!"&ROW()&":"&ROW()) )} -> 0 | K117: =$D117-E117 -> 0 | L117: =$D117-F117 -> 0 | M117: =$D117-G117 -> 0 | N117: =$D117-H117 -> 0 | O117: =$D117-I117 -> 0 | Q117: =IFERROR($D117/E117-1,0) -> 0 | R117: =IFERROR($D117/F117-1,0) -> 0 | S117: =IFERROR($D117/G117-1,0) -> 0 | T117: =IFERROR($D117/H117-1,0) -> 0 | U117: =IFERROR($D117/I117-1,0) -> 0 | W117: {=INDIRECT("'"&$C$6&"'!"&ADDRESS(ROW(),COLUMN()+44))} -> 0 | X117: {=INDIRECT("'"&$C$6&"'!"&ADDRESS(ROW(),COLUMN()+44))} -> 0 | Y117: {=INDIRECT("'"&$C$6&"'!"&ADDRESS(ROW(),COLUMN()+44))} -> 0 | Z117: {=INDIRECT("'"&$C$6&"'!"&ADDRESS(ROW(),COLUMN()+44))} -> 0 | AA117: {=INDIRECT("'"&$C$6&"'!"&ADDRESS(ROW(),COLUMN()+44))} -> 0 | AB117: {=INDIRECT("'"&$C$6&"'!"&ADDRESS(ROW(),COLUMN()+44))} -> 0 | AD117: =$W117-X117 -> 0 | AE117: =$W117-Y117 -> 0 | AF117: =$W117-Z117 -> 0 | AG117: =$W117-AA117 -> 0 | AH117: =$W117-AB117 -> 0 | AJ117: =IFERROR($W117/X117-1,0) -> 0 | AK117: =IFERROR($W117/Y117-1,0) -> 0 | AL117: =IFERROR($W117/Z117-1,0) -> 0 | AM117: =IFERROR($W117/AA117-1,0) -> 0 | AN117: =IFERROR($W117/AB117-1,0) -> 0
...

Sheet Evolutivos-->

Sheet Total_Producto
D1: REAL | AZ1: PRESUPUESTO | BO1: Acumulado | BW1: Saldo Prom Acumulado
BO2: =DATE(YEAR(BO6),1,1) -> 46023 | BP2: =DATE(YEAR(BP6),1,1) -> 46023 | BQ2: =DATE(YEAR(BQ6),1,1) -> 46023 | BR2: =DATE(YEAR(BR6),1,1) -> 45658 | BS2: =DATE(YEAR(BS6),1,1) -> 45292 | BT2: =DATE(YEAR(BT6),1,1) -> 44927
C3: N° dias T.Imp | D3: =DAY(D6) -> 31 | E3: =DAY(E6) -> 28 | F3: =DAY(F6) -> 31 | G3: =DAY(G6) -> 30 | H3: =DAY(H6) -> 31 | I3: =DAY(I6) -> 30 | J3: =DAY(J6) -> 31 | K3: =DAY(K6) -> 31 | ... BK3: =DAY(BK6) -> 31 | BO3: =AVERAGEIFS($D3:$BM3,$D$6:$BM$6,">="&BO$2,$D$6:$BM$6,"<="&BO$6,$D$5:$BM$5,BO$5) -> 30.2 | BP3: =AVERAGEIFS($D3:$BM3,$D$6:$BM$6,">="&BP$2,$D$6:$BM$6,"<="&BP$6,$D$5:$BM$5,BP$5) -> 30.2 | BQ3: =AVERAGEIFS($D3:$BM3,$D$6:$BM$6,">="&BQ$2,$D$6:$BM$6,"<="&BQ$6,$D$5:$BM$5,BQ$5) -> 30 | BR3: =AVERAGEIFS($D3:$BM3,$D$6:$BM$6,">="&BR$2,$D$6:$BM$6,"<="&BR$6,$D$5:$BM$5,BR$5) -> 30.2 | BS3: =AVERAGEIFS($D3:$BM3,$D$6:$BM$6,">="&BS$2,$D$6:$BM$6,"<="&BS$6,$D$5:$BM$5,BS$5) -> 30.4 | BT3: =AVERAGEIFS($D3:$BM3,$D$6:$BM$6,">="&BT$2,$D$6:$BM$6,"<="&BT$6,$D$5:$BM$5,BT$5) -> 30.2
C4: N° dias FTP | D4: =DAY(D6) -> 31 | E4: =DAY(E6) -> 28 | F4: =DAY(F6) -> 31 | G4: =DAY(G6) -> 30 | H4: =DAY(H6) -> 31 | I4: =DAY(I6) -> 30 | J4: =DAY(J6) -> 31 | K4: =DAY(K6) -> 31 | ... BK4: =DAY(BK6) -> 31 | BO4: =AVERAGEIFS($D4:$BM4,$D$6:$BM$6,">="&BO$2,$D$6:$BM$6,"<="&BO$6,$D$5:$BM$5,BO$5) -> 30.2 | BP4: =AVERAGEIFS($D4:$BM4,$D$6:$BM$6,">="&BP$2,$D$6:$BM$6,"<="&BP$6,$D$5:$BM$5,BP$5) -> 30.2 | BQ4: =AVERAGEIFS($D4:$BM4,$D$6:$BM$6,">="&BQ$2,$D$6:$BM$6,"<="&BQ$6,$D$5:$BM$5,BQ$5) -> 30 | BR4: =AVERAGEIFS($D4:$BM4,$D$6:$BM$6,">="&BR$2,$D$6:$BM$6,"<="&BR$6,$D$5:$BM$5,BR$5) -> 30.2 | BS4: =AVERAGEIFS($D4:$BM4,$D$6:$BM$6,">="&BS$2,$D$6:$BM$6,"<="&BS$6,$D$5:$BM$5,BS$5) -> 30.4 | BT4: =AVERAGEIFS($D4:$BM4,$D$6:$BM$6,">="&BT$2,$D$6:$BM$6,"<="&BT$6,$D$5:$BM$5,BT$5) -> 30.2
C5: Tipo | D5: R | E5: R | F5: R | G5: R | H5: R | I5: R | J5: R | K5: R | L5: R | M5: R | N5: R | O5: R | P5: R | Q5: R | R5: R | S5: R | T5: R | U5: R | V5: R | W5: R | X5: R | Y5: R | Z5: R | AA5: R | AB5: R | AC5: R | AD5: R | AE5: R | AF5: R | AG5: R | AH5: R | AI5: R | AJ5: R | AK5: R | AL5: R | AM5: R | AN5: R | AO5: R | AP5: R | AQ5: R | AR5: R | AS5: R | AT5: R | AU5: R | AV5: R | AW5: R | AX5: R | AY5: R | AZ5: P | BA5: P | BB5: P | BC5: P | BD5: P | BE5: P | BF5: P | BG5: P | BH5: P | BI5: P | BJ5: P | BK5: P | BO5: R | BP5: P | BQ5: R | BR5: R | BS5: R | BT5: R
A6: Solarizado | C6: Total Producto | D6: 44957 | E6: 44985 | F6: 45016 | G6: 45046 | H6: 45077 | I6: 45107 | J6: 45138 | K6: 45169 | L6: 45199 | M6: 45230 | N6: 45260 | O6: 45291 | P6: 45322 | Q6: 45351 | R6: 45382 | S6: 45412 | T6: 45443 | U6: 45473 | V6: 45504 | W6: 45535 | X6: 45565 | Y6: 45596 | Z6: 45626 | AA6: 45657 | AB6: 45688 | AC6: 45716 | AD6: 45747 | AE6: 45777 | AF6: 45808 | AG6: 45838 | AH6: 45869 | AI6: 45900 | AJ6: 45930 | AK6: 45961 | AL6: 45991 | AM6: 46022 | AN6: 46053 | AO6: 46081 | AP6: 46112 | AQ6: 46142 | AR6: 46173 | AS6: 46203 | AT6: 46234 | AU6: 46265 | AV6: 46295 | AW6: 46326 | AX6: 46356 | AY6: 46387 | AZ6: 46053 | BA6: 46081 | BB6: 46112 | BC6: 46142 | BD6: 46173 | BE6: 46203 | BF6: 46234 | BG6: 46265 | BH6: 46295 | BI6: 46326 | BJ6: 46356 | BK6: 46387 | BO6: =Desempeño_Financiero!$B$1 -> 46173 | BP6: =BO6 -> 46173 | BQ6: =EOMONTH(BO6,-1) -> 46142 | BR6: =EOMONTH(BO6,-12) -> 45808 | BS6: =EOMONTH(BO6,-24) -> 45443 | BT6: =EOMONTH(BO6,-36) -> 45077 | BW6: =BO6 -> 46173 | BX6: =BP6 -> 46173 | BY6: =BQ6 -> 46142 | BZ6: =BR6 -> 45808 | CA6: =BS6 -> 45443 | CB6: =BT6 -> 45077
A8: SALDO_FDP | C8: Cuenta Sueldo | D8: =+Renta_Alta!D8+Masivo!D8+Consumo_Inicial!D8 -> 0 | E8: =+Renta_Alta!E8+Masivo!E8+Consumo_Inicial!E8 -> 0 | F8: =+Renta_Alta!F8+Masivo!F8+Consumo_Inicial!F8 -> 0 | G8: =+Renta_Alta!G8+Masivo!G8+Consumo_Inicial!G8 -> 0 | H8: =+Renta_Alta!H8+Masivo!H8+Consumo_Inicial!H8 -> 0 | I8: =+Renta_Alta!I8+Masivo!I8+Consumo_Inicial!I8 -> 0 | J8: =+Renta_Alta!J8+Masivo!J8+Consumo_Inicial!J8 -> 0 | K8: =+Renta_Alta!K8+Masivo!K8+Consumo_Inicial!K8 -> 0 | ... BK8: =+Renta_Alta!BK8+Masivo!BK8+Consumo_Inicial!BK8 -> 2207528.2 | BO8: =_xlfn.XLOOKUP(BO$6,$D$6:$BM$6,$D8:$BM8,,0,1) -> 0 | BP8: =_xlfn.XLOOKUP(BP$6,$D$6:$BM$6,$D8:$BM8,,0,-1) -> 1963709.7 | BQ8: =_xlfn.XLOOKUP(BQ$6,$D$6:$BM$6,$D8:$BM8,,0,1) -> 0 | BR8: =_xlfn.XLOOKUP(BR$6,$D$6:$BM$6,$D8:$BM8,,0,1) -> 0 | BS8: =_xlfn.XLOOKUP(BS$6,$D$6:$BM$6,$D8:$BM8,,0,1) -> 0 | BT8: =_xlfn.XLOOKUP(BT$6,$D$6:$BM$6,$D8:$BM8,,0,1) -> 0
A9: SALDO_FDP | D9: =+Renta_Alta!D9+Masivo!D9+Consumo_Inicial!D9 -> 0 | E9: =+Renta_Alta!E9+Masivo!E9+Consumo_Inicial!E9 -> 0 | F9: =+Renta_Alta!F9+Masivo!F9+Consumo_Inicial!F9 -> 0 | G9: =+Renta_Alta!G9+Masivo!G9+Consumo_Inicial!G9 -> 0 | H9: =+Renta_Alta!H9+Masivo!H9+Consumo_Inicial!H9 -> 0 | I9: =+Renta_Alta!I9+Masivo!I9+Consumo_Inicial!I9 -> 0 | J9: =+Renta_Alta!J9+Masivo!J9+Consumo_Inicial!J9 -> 0 | K9: =+Renta_Alta!K9+Masivo!K9+Consumo_Inicial!K9 -> 0 | ... BK9: =+Renta_Alta!BK9+Masivo!BK9+Consumo_Inicial!BK9 -> 0 | BO9: =_xlfn.XLOOKUP(BO$6,$D$6:$BM$6,$D9:$BM9,,0,1) -> 0 | BP9: =_xlfn.XLOOKUP(BP$6,$D$6:$BM$6,$D9:$BM9,,0,-1) -> 0 | BQ9: =_xlfn.XLOOKUP(BQ$6,$D$6:$BM$6,$D9:$BM9,,0,1) -> 0 | BR9: =_xlfn.XLOOKUP(BR$6,$D$6:$BM$6,$D9:$BM9,,0,1) -> 0 | BS9: =_xlfn.XLOOKUP(BS$6,$D$6:$BM$6,$D9:$BM9,,0,1) -> 0 | BT9: =_xlfn.XLOOKUP(BT$6,$D$6:$BM$6,$D9:$BM9,,0,1) -> 0
A10: SALDO_FDP | D10: =+Renta_Alta!D10+Masivo!D10+Consumo_Inicial!D10 -> 0 | E10: =+Renta_Alta!E10+Masivo!E10+Consumo_Inicial!E10 -> 0 | F10: =+Renta_Alta!F10+Masivo!F10+Consumo_Inicial!F10 -> 0 | G10: =+Renta_Alta!G10+Masivo!G10+Consumo_Inicial!G10 -> 0 | H10: =+Renta_Alta!H10+Masivo!H10+Consumo_Inicial!H10 -> 0 | I10: =+Renta_Alta!I10+Masivo!I10+Consumo_Inicial!I10 -> 0 | J10: =+Renta_Alta!J10+Masivo!J10+Consumo_Inicial!J10 -> 0 | K10: =+Renta_Alta!K10+Masivo!K10+Consumo_Inicial!K10 -> 0 | ... BK10: =+Renta_Alta!BK10+Masivo!BK10+Consumo_Inicial!BK10 -> 0 | BO10: =_xlfn.XLOOKUP(BO$6,$D$6:$BM$6,$D10:$BM10,,0,1) -> 0 | BP10: =_xlfn.XLOOKUP(BP$6,$D$6:$BM$6,$D10:$BM10,,0,-1) -> 0 | BQ10: =_xlfn.XLOOKUP(BQ$6,$D$6:$BM$6,$D10:$BM10,,0,1) -> 0 | BR10: =_xlfn.XLOOKUP(BR$6,$D$6:$BM$6,$D10:$BM10,,0,1) -> 0 | BS10: =_xlfn.XLOOKUP(BS$6,$D$6:$BM$6,$D10:$BM10,,0,1) -> 0 | BT10: =_xlfn.XLOOKUP(BT$6,$D$6:$BM$6,$D10:$BM10,,0,1) -> 0
A11: SALDO_FDP | D11: =+Renta_Alta!D11+Masivo!D11+Consumo_Inicial!D11 -> 0 | E11: =+Renta_Alta!E11+Masivo!E11+Consumo_Inicial!E11 -> 0 | F11: =+Renta_Alta!F11+Masivo!F11+Consumo_Inicial!F11 -> 0 | G11: =+Renta_Alta!G11+Masivo!G11+Consumo_Inicial!G11 -> 0 | H11: =+Renta_Alta!H11+Masivo!H11+Consumo_Inicial!H11 -> 0 | I11: =+Renta_Alta!I11+Masivo!I11+Consumo_Inicial!I11 -> 0 | J11: =+Renta_Alta!J11+Masivo!J11+Consumo_Inicial!J11 -> 0 | K11: =+Renta_Alta!K11+Masivo!K11+Consumo_Inicial!K11 -> 0 | ... BK11: =+Renta_Alta!BK11+Masivo!BK11+Consumo_Inicial!BK11 -> 0 | BO11: =_xlfn.XLOOKUP(BO$6,$D$6:$BM$6,$D11:$BM11,,0,1) -> 0 | BP11: =_xlfn.XLOOKUP(BP$6,$D$6:$BM$6,$D11:$BM11,,0,-1) -> 0 | BQ11: =_xlfn.XLOOKUP(BQ$6,$D$6:$BM$6,$D11:$BM11,,0,1) -> 0 | BR11: =_xlfn.XLOOKUP(BR$6,$D$6:$BM$6,$D11:$BM11,,0,1) -> 0 | BS11: =_xlfn.XLOOKUP(BS$6,$D$6:$BM$6,$D11:$BM11,,0,1) -> 0 | BT11: =_xlfn.XLOOKUP(BT$6,$D$6:$BM$6,$D11:$BM11,,0,1) -> 0
A12: SALDO_FDP | D12: =+Renta_Alta!D12+Masivo!D12+Consumo_Inicial!D12 -> 0 | E12: =+Renta_Alta!E12+Masivo!E12+Consumo_Inicial!E12 -> 0 | F12: =+Renta_Alta!F12+Masivo!F12+Consumo_Inicial!F12 -> 0 | G12: =+Renta_Alta!G12+Masivo!G12+Consumo_Inicial!G12 -> 0 | H12: =+Renta_Alta!H12+Masivo!H12+Consumo_Inicial!H12 -> 0 | I12: =+Renta_Alta!I12+Masivo!I12+Consumo_Inicial!I12 -> 0 | J12: =+Renta_Alta!J12+Masivo!J12+Consumo_Inicial!J12 -> 0 | K12: =+Renta_Alta!K12+Masivo!K12+Consumo_Inicial!K12 -> 0 | ... BK12: =+Renta_Alta!BK12+Masivo!BK12+Consumo_Inicial!BK12 -> 0 | BO12: =_xlfn.XLOOKUP(BO$6,$D$6:$BM$6,$D12:$BM12,,0,1) -> 0 | BP12: =_xlfn.XLOOKUP(BP$6,$D$6:$BM$6,$D12:$BM12,,0,-1) -> 0 | BQ12: =_xlfn.XLOOKUP(BQ$6,$D$6:$BM$6,$D12:$BM12,,0,1) -> 0 | BR12: =_xlfn.XLOOKUP(BR$6,$D$6:$BM$6,$D12:$BM12,,0,1) -> 0 | BS12: =_xlfn.XLOOKUP(BS$6,$D$6:$BM$6,$D12:$BM12,,0,1) -> 0 | BT12: =_xlfn.XLOOKUP(BT$6,$D$6:$BM$6,$D12:$BM12,,0,1) -> 0
A13: SALDO_FDP | D13: =+Renta_Alta!D13+Masivo!D13+Consumo_Inicial!D13 -> 0 | E13: =+Renta_Alta!E13+Masivo!E13+Consumo_Inicial!E13 -> 0 | F13: =+Renta_Alta!F13+Masivo!F13+Consumo_Inicial!F13 -> 0 | G13: =+Renta_Alta!G13+Masivo!G13+Consumo_Inicial!G13 -> 0 | H13: =+Renta_Alta!H13+Masivo!H13+Consumo_Inicial!H13 -> 0 | I13: =+Renta_Alta!I13+Masivo!I13+Consumo_Inicial!I13 -> 0 | J13: =+Renta_Alta!J13+Masivo!J13+Consumo_Inicial!J13 -> 0 | K13: =+Renta_Alta!K13+Masivo!K13+Consumo_Inicial!K13 -> 0 | ... BK13: =+Renta_Alta!BK13+Masivo!BK13+Consumo_Inicial!BK13 -> 0 | BO13: =_xlfn.XLOOKUP(BO$6,$D$6:$BM$6,$D13:$BM13,,0,1) -> 0 | BP13: =_xlfn.XLOOKUP(BP$6,$D$6:$BM$6,$D13:$BM13,,0,-1) -> 0 | BQ13: =_xlfn.XLOOKUP(BQ$6,$D$6:$BM$6,$D13:$BM13,,0,1) -> 0 | BR13: =_xlfn.XLOOKUP(BR$6,$D$6:$BM$6,$D13:$BM13,,0,1) -> 0 | BS13: =_xlfn.XLOOKUP(BS$6,$D$6:$BM$6,$D13:$BM13,,0,1) -> 0 | BT13: =_xlfn.XLOOKUP(BT$6,$D$6:$BM$6,$D13:$BM13,,0,1) -> 0
A14: SALDO_FDP | D14: =+Renta_Alta!D14+Masivo!D14+Consumo_Inicial!D14 -> 0 | E14: =+Renta_Alta!E14+Masivo!E14+Consumo_Inicial!E14 -> 0 | F14: =+Renta_Alta!F14+Masivo!F14+Consumo_Inicial!F14 -> 0 | G14: =+Renta_Alta!G14+Masivo!G14+Consumo_Inicial!G14 -> 0 | H14: =+Renta_Alta!H14+Masivo!H14+Consumo_Inicial!H14 -> 0 | I14: =+Renta_Alta!I14+Masivo!I14+Consumo_Inicial!I14 -> 0 | J14: =+Renta_Alta!J14+Masivo!J14+Consumo_Inicial!J14 -> 0 | K14: =+Renta_Alta!K14+Masivo!K14+Consumo_Inicial!K14 -> 0 | ... BK14: =+Renta_Alta!BK14+Masivo!BK14+Consumo_Inicial!BK14 -> 0 | BO14: =_xlfn.XLOOKUP(BO$6,$D$6:$BM$6,$D14:$BM14,,0,1) -> 0 | BP14: =_xlfn.XLOOKUP(BP$6,$D$6:$BM$6,$D14:$BM14,,0,-1) -> 0 | BQ14: =_xlfn.XLOOKUP(BQ$6,$D$6:$BM$6,$D14:$BM14,,0,1) -> 0 | BR14: =_xlfn.XLOOKUP(BR$6,$D$6:$BM$6,$D14:$BM14,,0,1) -> 0 | BS14: =_xlfn.XLOOKUP(BS$6,$D$6:$BM$6,$D14:$BM14,,0,1) -> 0 | BT14: =_xlfn.XLOOKUP(BT$6,$D$6:$BM$6,$D14:$BM14,,0,1) -> 0
A15: SALDO_FDP | D15: =+Renta_Alta!D15+Masivo!D15+Consumo_Inicial!D15 -> 0 | E15: =+Renta_Alta!E15+Masivo!E15+Consumo_Inicial!E15 -> 0 | F15: =+Renta_Alta!F15+Masivo!F15+Consumo_Inicial!F15 -> 0 | G15: =+Renta_Alta!G15+Masivo!G15+Consumo_Inicial!G15 -> 0 | H15: =+Renta_Alta!H15+Masivo!H15+Consumo_Inicial!H15 -> 0 | I15: =+Renta_Alta!I15+Masivo!I15+Consumo_Inicial!I15 -> 0 | J15: =+Renta_Alta!J15+Masivo!J15+Consumo_Inicial!J15 -> 0 | K15: =+Renta_Alta!K15+Masivo!K15+Consumo_Inicial!K15 -> 0 | ... BK15: =+Renta_Alta!BK15+Masivo!BK15+Consumo_Inicial!BK15 -> 0 | BO15: =_xlfn.XLOOKUP(BO$6,$D$6:$BM$6,$D15:$BM15,,0,1) -> 0 | BP15: =_xlfn.XLOOKUP(BP$6,$D$6:$BM$6,$D15:$BM15,,0,-1) -> 0 | BQ15: =_xlfn.XLOOKUP(BQ$6,$D$6:$BM$6,$D15:$BM15,,0,1) -> 0 | BR15: =_xlfn.XLOOKUP(BR$6,$D$6:$BM$6,$D15:$BM15,,0,1) -> 0 | BS15: =_xlfn.XLOOKUP(BS$6,$D$6:$BM$6,$D15:$BM15,,0,1) -> 0 | BT15: =_xlfn.XLOOKUP(BT$6,$D$6:$BM$6,$D15:$BM15,,0,1) -> 0
A16: SALDO_FDP | D16: =SUM(D8:D15) -> 0 | E16: =SUM(E8:E15) -> 0 | F16: =SUM(F8:F15) -> 0 | G16: =SUM(G8:G15) -> 0 | H16: =SUM(H8:H15) -> 0 | I16: =SUM(I8:I15) -> 0 | J16: =SUM(J8:J15) -> 0 | K16: =SUM(K8:K15) -> 0 | ... BK16: =SUM(BK8:BK15) -> 2207528.2 | BO16: =SUM(BO8:BO15) -> 0 | BP16: =SUM(BP8:BP15) -> 1963709.7 | BQ16: =SUM(BQ8:BQ15) -> 0 | BR16: =SUM(BR8:BR15) -> 0 | BS16: =SUM(BS8:BS15) -> 0 | BT16: =SUM(BT8:BT15) -> 0
A17: SALDO_FDP | D17: =+Renta_Alta!D17+Masivo!D17+Consumo_Inicial!D17 -> 0 | E17: =+Renta_Alta!E17+Masivo!E17+Consumo_Inicial!E17 -> 0 | F17: =+Renta_Alta!F17+Masivo!F17+Consumo_Inicial!F17 -> 0 | G17: =+Renta_Alta!G17+Masivo!G17+Consumo_Inicial!G17 -> 0 | H17: =+Renta_Alta!H17+Masivo!H17+Consumo_Inicial!H17 -> 0 | I17: =+Renta_Alta!I17+Masivo!I17+Consumo_Inicial!I17 -> 0 | J17: =+Renta_Alta!J17+Masivo!J17+Consumo_Inicial!J17 -> 0 | K17: =+Renta_Alta!K17+Masivo!K17+Consumo_Inicial!K17 -> 0 | ... BK17: =+Renta_Alta!BK17+Masivo!BK17+Consumo_Inicial!BK17 -> 0 | BO17: =_xlfn.XLOOKUP(BO$6,$D$6:$BM$6,$D17:$BM17,,0,1) -> 0 | BP17: =_xlfn.XLOOKUP(BP$6,$D$6:$BM$6,$D17:$BM17,,0,-1) -> 0 | BQ17: =_xlfn.XLOOKUP(BQ$6,$D$6:$BM$6,$D17:$BM17,,0,1) -> 0 | BR17: =_xlfn.XLOOKUP(BR$6,$D$6:$BM$6,$D17:$BM17,,0,1) -> 0 | BS17: =_xlfn.XLOOKUP(BS$6,$D$6:$BM$6,$D17:$BM17,,0,1) -> 0 | BT17: =_xlfn.XLOOKUP(BT$6,$D$6:$BM$6,$D17:$BM17,,0,1) -> 0
A18: SALDO_FDP | D18: =+Renta_Alta!D18+Masivo!D18+Consumo_Inicial!D18 -> 0 | E18: =+Renta_Alta!E18+Masivo!E18+Consumo_Inicial!E18 -> 0 | F18: =+Renta_Alta!F18+Masivo!F18+Consumo_Inicial!F18 -> 0 | G18: =+Renta_Alta!G18+Masivo!G18+Consumo_Inicial!G18 -> 0 | H18: =+Renta_Alta!H18+Masivo!H18+Consumo_Inicial!H18 -> 0 | I18: =+Renta_Alta!I18+Masivo!I18+Consumo_Inicial!I18 -> 0 | J18: =+Renta_Alta!J18+Masivo!J18+Consumo_Inicial!J18 -> 0 | K18: =+Renta_Alta!K18+Masivo!K18+Consumo_Inicial!K18 -> 0 | ... BK18: =+Renta_Alta!BK18+Masivo!BK18+Consumo_Inicial!BK18 -> 0 | BO18: =_xlfn.XLOOKUP(BO$6,$D$6:$BM$6,$D18:$BM18,,0,1) -> 0 | BP18: =_xlfn.XLOOKUP(BP$6,$D$6:$BM$6,$D18:$BM18,,0,-1) -> 0 | BQ18: =_xlfn.XLOOKUP(BQ$6,$D$6:$BM$6,$D18:$BM18,,0,1) -> 0 | BR18: =_xlfn.XLOOKUP(BR$6,$D$6:$BM$6,$D18:$BM18,,0,1) -> 0 | BS18: =_xlfn.XLOOKUP(BS$6,$D$6:$BM$6,$D18:$BM18,,0,1) -> 0 | BT18: =_xlfn.XLOOKUP(BT$6,$D$6:$BM$6,$D18:$BM18,,0,1) -> 0
A19: SALDO_FDP | D19: =+Renta_Alta!D19+Masivo!D19+Consumo_Inicial!D19 -> 0 | E19: =+Renta_Alta!E19+Masivo!E19+Consumo_Inicial!E19 -> 0 | F19: =+Renta_Alta!F19+Masivo!F19+Consumo_Inicial!F19 -> 0 | G19: =+Renta_Alta!G19+Masivo!G19+Consumo_Inicial!G19 -> 0 | H19: =+Renta_Alta!H19+Masivo!H19+Consumo_Inicial!H19 -> 0 | I19: =+Renta_Alta!I19+Masivo!I19+Consumo_Inicial!I19 -> 0 | J19: =+Renta_Alta!J19+Masivo!J19+Consumo_Inicial!J19 -> 0 | K19: =+Renta_Alta!K19+Masivo!K19+Consumo_Inicial!K19 -> 0 | ... BK19: =+Renta_Alta!BK19+Masivo!BK19+Consumo_Inicial!BK19 -> 0 | BO19: =_xlfn.XLOOKUP(BO$6,$D$6:$BM$6,$D19:$BM19,,0,1) -> 0 | BP19: =_xlfn.XLOOKUP(BP$6,$D$6:$BM$6,$D19:$BM19,,0,-1) -> 0 | BQ19: =_xlfn.XLOOKUP(BQ$6,$D$6:$BM$6,$D19:$BM19,,0,1) -> 0 | BR19: =_xlfn.XLOOKUP(BR$6,$D$6:$BM$6,$D19:$BM19,,0,1) -> 0 | BS19: =_xlfn.XLOOKUP(BS$6,$D$6:$BM$6,$D19:$BM19,,0,1) -> 0 | BT19: =_xlfn.XLOOKUP(BT$6,$D$6:$BM$6,$D19:$BM19,,0,1) -> 0
A20: SALDO_FDP | D20: =+Renta_Alta!D20+Masivo!D20+Consumo_Inicial!D20 -> 0 | E20: =+Renta_Alta!E20+Masivo!E20+Consumo_Inicial!E20 -> 0 | F20: =+Renta_Alta!F20+Masivo!F20+Consumo_Inicial!F20 -> 0 | G20: =+Renta_Alta!G20+Masivo!G20+Consumo_Inicial!G20 -> 0 | H20: =+Renta_Alta!H20+Masivo!H20+Consumo_Inicial!H20 -> 0 | I20: =+Renta_Alta!I20+Masivo!I20+Consumo_Inicial!I20 -> 0 | J20: =+Renta_Alta!J20+Masivo!J20+Consumo_Inicial!J20 -> 0 | K20: =+Renta_Alta!K20+Masivo!K20+Consumo_Inicial!K20 -> 0 | ... BK20: =+Renta_Alta!BK20+Masivo!BK20+Consumo_Inicial!BK20 -> 0 | BO20: =_xlfn.XLOOKUP(BO$6,$D$6:$BM$6,$D20:$BM20,,0,1) -> 0 | BP20: =_xlfn.XLOOKUP(BP$6,$D$6:$BM$6,$D20:$BM20,,0,-1) -> 0 | BQ20: =_xlfn.XLOOKUP(BQ$6,$D$6:$BM$6,$D20:$BM20,,0,1) -> 0 | BR20: =_xlfn.XLOOKUP(BR$6,$D$6:$BM$6,$D20:$BM20,,0,1) -> 0 | BS20: =_xlfn.XLOOKUP(BS$6,$D$6:$BM$6,$D20:$BM20,,0,1) -> 0 | BT20: =_xlfn.XLOOKUP(BT$6,$D$6:$BM$6,$D20:$BM20,,0,1) -> 0
A21: SALDO_FDP | D21: =+Renta_Alta!D21+Masivo!D21+Consumo_Inicial!D21 -> 0 | E21: =+Renta_Alta!E21+Masivo!E21+Consumo_Inicial!E21 -> 0 | F21: =+Renta_Alta!F21+Masivo!F21+Consumo_Inicial!F21 -> 0 | G21: =+Renta_Alta!G21+Masivo!G21+Consumo_Inicial!G21 -> 0 | H21: =+Renta_Alta!H21+Masivo!H21+Consumo_Inicial!H21 -> 0 | I21: =+Renta_Alta!I21+Masivo!I21+Consumo_Inicial!I21 -> 0 | J21: =+Renta_Alta!J21+Masivo!J21+Consumo_Inicial!J21 -> 0 | K21: =+Renta_Alta!K21+Masivo!K21+Consumo_Inicial!K21 -> 0 | ... BK21: =+Renta_Alta!BK21+Masivo!BK21+Consumo_Inicial!BK21 -> 0 | BO21: =_xlfn.XLOOKUP(BO$6,$D$6:$BM$6,$D21:$BM21,,0,1) -> 0 | BP21: =_xlfn.XLOOKUP(BP$6,$D$6:$BM$6,$D21:$BM21,,0,-1) -> 0 | BQ21: =_xlfn.XLOOKUP(BQ$6,$D$6:$BM$6,$D21:$BM21,,0,1) -> 0 | BR21: =_xlfn.XLOOKUP(BR$6,$D$6:$BM$6,$D21:$BM21,,0,1) -> 0 | BS21: =_xlfn.XLOOKUP(BS$6,$D$6:$BM$6,$D21:$BM21,,0,1) -> 0 | BT21: =_xlfn.XLOOKUP(BT$6,$D$6:$BM$6,$D21:$BM21,,0,1) -> 0
A22: SALDO_FDP | D22: =+Renta_Alta!D22+Masivo!D22+Consumo_Inicial!D22 -> 0 | E22: =+Renta_Alta!E22+Masivo!E22+Consumo_Inicial!E22 -> 0 | F22: =+Renta_Alta!F22+Masivo!F22+Consumo_Inicial!F22 -> 0 | G22: =+Renta_Alta!G22+Masivo!G22+Consumo_Inicial!G22 -> 0 | H22: =+Renta_Alta!H22+Masivo!H22+Consumo_Inicial!H22 -> 0 | I22: =+Renta_Alta!I22+Masivo!I22+Consumo_Inicial!I22 -> 0 | J22: =+Renta_Alta!J22+Masivo!J22+Consumo_Inicial!J22 -> 0 | K22: =+Renta_Alta!K22+Masivo!K22+Consumo_Inicial!K22 -> 0 | ... BK22: =+Renta_Alta!BK22+Masivo!BK22+Consumo_Inicial!BK22 -> 0 | BO22: =_xlfn.XLOOKUP(BO$6,$D$6:$BM$6,$D22:$BM22,,0,1) -> 0 | BP22: =_xlfn.XLOOKUP(BP$6,$D$6:$BM$6,$D22:$BM22,,0,-1) -> 0 | BQ22: =_xlfn.XLOOKUP(BQ$6,$D$6:$BM$6,$D22:$BM22,,0,1) -> 0 | BR22: =_xlfn.XLOOKUP(BR$6,$D$6:$BM$6,$D22:$BM22,,0,1) -> 0 | BS22: =_xlfn.XLOOKUP(BS$6,$D$6:$BM$6,$D22:$BM22,,0,1) -> 0 | BT22: =_xlfn.XLOOKUP(BT$6,$D$6:$BM$6,$D22:$BM22,,0,1) -> 0
A23: SALDO_FDP | D23: =SUM(D21:D22) -> 0 | E23: =SUM(E21:E22) -> 0 | F23: =SUM(F21:F22) -> 0 | G23: =SUM(G21:G22) -> 0 | H23: =SUM(H21:H22) -> 0 | I23: =SUM(I21:I22) -> 0 | J23: =SUM(J21:J22) -> 0 | K23: =SUM(K21:K22) -> 0 | ... BK23: =SUM(BK21:BK22) -> 0 | BO23: =SUM(BO21:BO22) -> 0 | BP23: =SUM(BP21:BP22) -> 0 | BQ23: =SUM(BQ21:BQ22) -> 0 | BR23: =SUM(BR21:BR22) -> 0 | BS23: =SUM(BS21:BS22) -> 0 | BT23: =SUM(BT21:BT22) -> 0
C24: Saldo FdP | D24: =SUM(D16,D17:D20,D23) -> 0 | E24: =SUM(E16,E17:E20,E23) -> 0 | F24: =SUM(F16,F17:F20,F23) -> 0 | G24: =SUM(G16,G17:G20,G23) -> 0 | H24: =SUM(H16,H17:H20,H23) -> 0 | I24: =SUM(I16,I17:I20,I23) -> 0 | J24: =SUM(J16,J17:J20,J23) -> 0 | K24: =SUM(K16,K17:K20,K23) -> 0 | ... BK24: =SUM(BK16,BK17:BK20,BK23) -> 2207528.2 | BO24: =SUM(BO16,BO17:BO20,BO23) -> 0 | BP24: =SUM(BP16,BP17:BP20,BP23) -> 1963709.7 | BQ24: =SUM(BQ16,BQ17:BQ20,BQ23) -> 0 | BR24: =SUM(BR16,BR17:BR20,BR23) -> 0 | BS24: =SUM(BS16,BS17:BS20,BS23) -> 0 | BT24: =SUM(BT16,BT17:BT20,BT23) -> 0
A27: SALDO_PROM | C27: Cuenta Sueldo | D27: =+Renta_Alta!D27+Masivo!D27+Consumo_Inicial!D27 -> 0 | E27: =+Renta_Alta!E27+Masivo!E27+Consumo_Inicial!E27 -> 0 | F27: =+Renta_Alta!F27+Masivo!F27+Consumo_Inicial!F27 -> 0 | G27: =+Renta_Alta!G27+Masivo!G27+Consumo_Inicial!G27 -> 0 | H27: =+Renta_Alta!H27+Masivo!H27+Consumo_Inicial!H27 -> 0 | I27: =+Renta_Alta!I27+Masivo!I27+Consumo_Inicial!I27 -> 0 | J27: =+Renta_Alta!J27+Masivo!J27+Consumo_Inicial!J27 -> 0 | K27: =+Renta_Alta!K27+Masivo!K27+Consumo_Inicial!K27 -> 0 | ... BK27: =+Renta_Alta!BK27+Masivo!BK27+Consumo_Inicial!BK27 -> 2053001.2 | BO27: =IFERROR(AVERAGEIFS($D27:$BM27,$D$6:$BM$6,">="&BO$2,$D$6:$BM$6,"<="&BO$6,$D$5:$BM$5,BO$5,$D27:$BM27,"<>0"),0) -> 0 | BP27: =IFERROR(AVERAGEIFS($D27:$BM27,$D$6:$BM$6,">="&BP$2,$D$6:$BM$6,"<="&BP$6,$D$5:$BM$5,BP$5,$D27:$BM27,"<>0"),0) -> 1777154.7 | BQ27: =IFERROR(AVERAGEIFS($D27:$BM27,$D$6:$BM$6,">="&BQ$2,$D$6:$BM$6,"<="&BQ$6,$D$5:$BM$5,BQ$5,$D27:$BM27,"<>0"),0) -> 0 | BR27: =IFERROR(AVERAGEIFS($D27:$BM27,$D$6:$BM$6,">="&BR$2,$D$6:$BM$6,"<="&BR$6,$D$5:$BM$5,BR$5,$D27:$BM27,"<>0"),0) -> 0 | BS27: =IFERROR(AVERAGEIFS($D27:$BM27,$D$6:$BM$6,">="&BS$2,$D$6:$BM$6,"<="&BS$6,$D$5:$BM$5,BS$5,$D27:$BM27,"<>0"),0) -> 0 | BT27: =IFERROR(AVERAGEIFS($D27:$BM27,$D$6:$BM$6,">="&BT$2,$D$6:$BM$6,"<="&BT$6,$D$5:$BM$5,BT$5,$D27:$BM27,"<>0"),0) -> 0 | BW27: =SUMIFS($D27:$BM27,$D$6:$BM$6,">="&BO$2,$D$6:$BM$6,"<="&BO$6,$D$5:$BM$5,BO$5) -> 0 | BX27: =SUMIFS($D27:$BM27,$D$6:$BM$6,">="&BP$2,$D$6:$BM$6,"<="&BP$6,$D$5:$BM$5,BP$5) -> 8885773.4 | BY27: =SUMIFS($D27:$BM27,$D$6:$BM$6,">="&BQ$2,$D$6:$BM$6,"<="&BQ$6,$D$5:$BM$5,BQ$5) -> 0 | BZ27: =SUMIFS($D27:$BM27,$D$6:$BM$6,">="&BR$2,$D$6:$BM$6,"<="&BR$6,$D$5:$BM$5,BR$5) -> 0 | CA27: =SUMIFS($D27:$BM27,$D$6:$BM$6,">="&BS$2,$D$6:$BM$6,"<="&BS$6,$D$5:$BM$5,BS$5) -> 0 | CB27: =SUMIFS($D27:$BM27,$D$6:$BM$6,">="&BT$2,$D$6:$BM$6,"<="&BT$6,$D$5:$BM$5,BT$5) -> 0
A28: SALDO_PROM | D28: =+Renta_Alta!D28+Masivo!D28+Consumo_Inicial!D28 -> 0 | E28: =+Renta_Alta!E28+Masivo!E28+Consumo_Inicial!E28 -> 0 | F28: =+Renta_Alta!F28+Masivo!F28+Consumo_Inicial!F28 -> 0 | G28: =+Renta_Alta!G28+Masivo!G28+Consumo_Inicial!G28 -> 0 | H28: =+Renta_Alta!H28+Masivo!H28+Consumo_Inicial!H28 -> 0 | I28: =+Renta_Alta!I28+Masivo!I28+Consumo_Inicial!I28 -> 0 | J28: =+Renta_Alta!J28+Masivo!J28+Consumo_Inicial!J28 -> 0 | K28: =+Renta_Alta!K28+Masivo!K28+Consumo_Inicial!K28 -> 0 | ... BK28: =+Renta_Alta!BK28+Masivo!BK28+Consumo_Inicial!BK28 -> 0 | BO28: =IFERROR(AVERAGEIFS($D28:$BM28,$D$6:$BM$6,">="&BO$2,$D$6:$BM$6,"<="&BO$6,$D$5:$BM$5,BO$5,$D28:$BM28,"<>0"),0) -> 0 | BP28: =IFERROR(AVERAGEIFS($D28:$BM28,$D$6:$BM$6,">="&BP$2,$D$6:$BM$6,"<="&BP$6,$D$5:$BM$5,BP$5,$D28:$BM28,"<>0"),0) -> 0 | BQ28: =IFERROR(AVERAGEIFS($D28:$BM28,$D$6:$BM$6,">="&BQ$2,$D$6:$BM$6,"<="&BQ$6,$D$5:$BM$5,BQ$5,$D28:$BM28,"<>0"),0) -> 0 | BR28: =IFERROR(AVERAGEIFS($D28:$BM28,$D$6:$BM$6,">="&BR$2,$D$6:$BM$6,"<="&BR$6,$D$5:$BM$5,BR$5,$D28:$BM28,"<>0"),0) -> 0 | BS28: =IFERROR(AVERAGEIFS($D28:$BM28,$D$6:$BM$6,">="&BS$2,$D$6:$BM$6,"<="&BS$6,$D$5:$BM$5,BS$5,$D28:$BM28,"<>0"),0) -> 0 | BT28: =IFERROR(AVERAGEIFS($D28:$BM28,$D$6:$BM$6,">="&BT$2,$D$6:$BM$6,"<="&BT$6,$D$5:$BM$5,BT$5,$D28:$BM28,"<>0"),0) -> 0 | BW28: =SUMIFS($D28:$BM28,$D$6:$BM$6,">="&BO$2,$D$6:$BM$6,"<="&BO$6,$D$5:$BM$5,BO$5) -> 0 | BX28: =SUMIFS($D28:$BM28,$D$6:$BM$6,">="&BP$2,$D$6:$BM$6,"<="&BP$6,$D$5:$BM$5,BP$5) -> 0 | BY28: =SUMIFS($D28:$BM28,$D$6:$BM$6,">="&BQ$2,$D$6:$BM$6,"<="&BQ$6,$D$5:$BM$5,BQ$5) -> 0 | BZ28: =SUMIFS($D28:$BM28,$D$6:$BM$6,">="&BR$2,$D$6:$BM$6,"<="&BR$6,$D$5:$BM$5,BR$5) -> 0 | CA28: =SUMIFS($D28:$BM28,$D$6:$BM$6,">="&BS$2,$D$6:$BM$6,"<="&BS$6,$D$5:$BM$5,BS$5) -> 0 | CB28: =SUMIFS($D28:$BM28,$D$6:$BM$6,">="&BT$2,$D$6:$BM$6,"<="&BT$6,$D$5:$BM$5,BT$5) -> 0
A29: SALDO_PROM | D29: =+Renta_Alta!D29+Masivo!D29+Consumo_Inicial!D29 -> 0 | E29: =+Renta_Alta!E29+Masivo!E29+Consumo_Inicial!E29 -> 0 | F29: =+Renta_Alta!F29+Masivo!F29+Consumo_Inicial!F29 -> 0 | G29: =+Renta_Alta!G29+Masivo!G29+Consumo_Inicial!G29 -> 0 | H29: =+Renta_Alta!H29+Masivo!H29+Consumo_Inicial!H29 -> 0 | I29: =+Renta_Alta!I29+Masivo!I29+Consumo_Inicial!I29 -> 0 | J29: =+Renta_Alta!J29+Masivo!J29+Consumo_Inicial!J29 -> 0 | K29: =+Renta_Alta!K29+Masivo!K29+Consumo_Inicial!K29 -> 0 | ... BK29: =+Renta_Alta!BK29+Masivo!BK29+Consumo_Inicial!BK29 -> 0 | BO29: =IFERROR(AVERAGEIFS($D29:$BM29,$D$6:$BM$6,">="&BO$2,$D$6:$BM$6,"<="&BO$6,$D$5:$BM$5,BO$5,$D29:$BM29,"<>0"),0) -> 0 | BP29: =IFERROR(AVERAGEIFS($D29:$BM29,$D$6:$BM$6,">="&BP$2,$D$6:$BM$6,"<="&BP$6,$D$5:$BM$5,BP$5,$D29:$BM29,"<>0"),0) -> 0 | BQ29: =IFERROR(AVERAGEIFS($D29:$BM29,$D$6:$BM$6,">="&BQ$2,$D$6:$BM$6,"<="&BQ$6,$D$5:$BM$5,BQ$5,$D29:$BM29,"<>0"),0) -> 0 | BR29: =IFERROR(AVERAGEIFS($D29:$BM29,$D$6:$BM$6,">="&BR$2,$D$6:$BM$6,"<="&BR$6,$D$5:$BM$5,BR$5,$D29:$BM29,"<>0"),0) -> 0 | BS29: =IFERROR(AVERAGEIFS($D29:$BM29,$D$6:$BM$6,">="&BS$2,$D$6:$BM$6,"<="&BS$6,$D$5:$BM$5,BS$5,$D29:$BM29,"<>0"),0) -> 0 | BT29: =IFERROR(AVERAGEIFS($D29:$BM29,$D$6:$BM$6,">="&BT$2,$D$6:$BM$6,"<="&BT$6,$D$5:$BM$5,BT$5,$D29:$BM29,"<>0"),0) -> 0 | BW29: =SUMIFS($D29:$BM29,$D$6:$BM$6,">="&BO$2,$D$6:$BM$6,"<="&BO$6,$D$5:$BM$5,BO$5) -> 0 | BX29: =SUMIFS($D29:$BM29,$D$6:$BM$6,">="&BP$2,$D$6:$BM$6,"<="&BP$6,$D$5:$BM$5,BP$5) -> 0 | BY29: =SUMIFS($D29:$BM29,$D$6:$BM$6,">="&BQ$2,$D$6:$BM$6,"<="&BQ$6,$D$5:$BM$5,BQ$5) -> 0 | BZ29: =SUMIFS($D29:$BM29,$D$6:$BM$6,">="&BR$2,$D$6:$BM$6,"<="&BR$6,$D$5:$BM$5,BR$5) -> 0 | CA29: =SUMIFS($D29:$BM29,$D$6:$BM$6,">="&BS$2,$D$6:$BM$6,"<="&BS$6,$D$5:$BM$5,BS$5) -> 0 | CB29: =SUMIFS($D29:$BM29,$D$6:$BM$6,">="&BT$2,$D$6:$BM$6,"<="&BT$6,$D$5:$BM$5,BT$5) -> 0
A30: SALDO_PROM | D30: =+Renta_Alta!D30+Masivo!D30+Consumo_Inicial!D30 -> 0 | E30: =+Renta_Alta!E30+Masivo!E30+Consumo_Inicial!E30 -> 0 | F30: =+Renta_Alta!F30+Masivo!F30+Consumo_Inicial!F30 -> 0 | G30: =+Renta_Alta!G30+Masivo!G30+Consumo_Inicial!G30 -> 0 | H30: =+Renta_Alta!H30+Masivo!H30+Consumo_Inicial!H30 -> 0 | I30: =+Renta_Alta!I30+Masivo!I30+Consumo_Inicial!I30 -> 0 | J30: =+Renta_Alta!J30+Masivo!J30+Consumo_Inicial!J30 -> 0 | K30: =+Renta_Alta!K30+Masivo!K30+Consumo_Inicial!K30 -> 0 | ... BK30: =+Renta_Alta!BK30+Masivo!BK30+Consumo_Inicial!BK30 -> 0 | BO30: =IFERROR(AVERAGEIFS($D30:$BM30,$D$6:$BM$6,">="&BO$2,$D$6:$BM$6,"<="&BO$6,$D$5:$BM$5,BO$5,$D30:$BM30,"<>0"),0) -> 0 | BP30: =IFERROR(AVERAGEIFS($D30:$BM30,$D$6:$BM$6,">="&BP$2,$D$6:$BM$6,"<="&BP$6,$D$5:$BM$5,BP$5,$D30:$BM30,"<>0"),0) -> 0 | BQ30: =IFERROR(AVERAGEIFS($D30:$BM30,$D$6:$BM$6,">="&BQ$2,$D$6:$BM$6,"<="&BQ$6,$D$5:$BM$5,BQ$5,$D30:$BM30,"<>0"),0) -> 0 | BR30: =IFERROR(AVERAGEIFS($D30:$BM30,$D$6:$BM$6,">="&BR$2,$D$6:$BM$6,"<="&BR$6,$D$5:$BM$5,BR$5,$D30:$BM30,"<>0"),0) -> 0 | BS30: =IFERROR(AVERAGEIFS($D30:$BM30,$D$6:$BM$6,">="&BS$2,$D$6:$BM$6,"<="&BS$6,$D$5:$BM$5,BS$5,$D30:$BM30,"<>0"),0) -> 0 | BT30: =IFERROR(AVERAGEIFS($D30:$BM30,$D$6:$BM$6,">="&BT$2,$D$6:$BM$6,"<="&BT$6,$D$5:$BM$5,BT$5,$D30:$BM30,"<>0"),0) -> 0 | BW30: =SUMIFS($D30:$BM30,$D$6:$BM$6,">="&BO$2,$D$6:$BM$6,"<="&BO$6,$D$5:$BM$5,BO$5) -> 0 | BX30: =SUMIFS($D30:$BM30,$D$6:$BM$6,">="&BP$2,$D$6:$BM$6,"<="&BP$6,$D$5:$BM$5,BP$5) -> 0 | BY30: =SUMIFS($D30:$BM30,$D$6:$BM$6,">="&BQ$2,$D$6:$BM$6,"<="&BQ$6,$D$5:$BM$5,BQ$5) -> 0 | BZ30: =SUMIFS($D30:$BM30,$D$6:$BM$6,">="&BR$2,$D$6:$BM$6,"<="&BR$6,$D$5:$BM$5,BR$5) -> 0 | CA30: =SUMIFS($D30:$BM30,$D$6:$BM$6,">="&BS$2,$D$6:$BM$6,"<="&BS$6,$D$5:$BM$5,BS$5) -> 0 | CB30: =SUMIFS($D30:$BM30,$D$6:$BM$6,">="&BT$2,$D$6:$BM$6,"<="&BT$6,$D$5:$BM$5,BT$5) -> 0
A31: SALDO_PROM | D31: =+Renta_Alta!D31+Masivo!D31+Consumo_Inicial!D31 -> 0 | E31: =+Renta_Alta!E31+Masivo!E31+Consumo_Inicial!E31 -> 0 | F31: =+Renta_Alta!F31+Masivo!F31+Consumo_Inicial!F31 -> 0 | G31: =+Renta_Alta!G31+Masivo!G31+Consumo_Inicial!G31 -> 0 | H31: =+Renta_Alta!H31+Masivo!H31+Consumo_Inicial!H31 -> 0 | I31: =+Renta_Alta!I31+Masivo!I31+Consumo_Inicial!I31 -> 0 | J31: =+Renta_Alta!J31+Masivo!J31+Consumo_Inicial!J31 -> 0 | K31: =+Renta_Alta!K31+Masivo!K31+Consumo_Inicial!K31 -> 0 | ... BK31: =+Renta_Alta!BK31+Masivo!BK31+Consumo_Inicial!BK31 -> 0 | BO31: =IFERROR(AVERAGEIFS($D31:$BM31,$D$6:$BM$6,">="&BO$2,$D$6:$BM$6,"<="&BO$6,$D$5:$BM$5,BO$5,$D31:$BM31,"<>0"),0) -> 0 | BP31: =IFERROR(AVERAGEIFS($D31:$BM31,$D$6:$BM$6,">="&BP$2,$D$6:$BM$6,"<="&BP$6,$D$5:$BM$5,BP$5,$D31:$BM31,"<>0"),0) -> 0 | BQ31: =IFERROR(AVERAGEIFS($D31:$BM31,$D$6:$BM$6,">="&BQ$2,$D$6:$BM$6,"<="&BQ$6,$D$5:$BM$5,BQ$5,$D31:$BM31,"<>0"),0) -> 0 | BR31: =IFERROR(AVERAGEIFS($D31:$BM31,$D$6:$BM$6,">="&BR$2,$D$6:$BM$6,"<="&BR$6,$D$5:$BM$5,BR$5,$D31:$BM31,"<>0"),0) -> 0 | BS31: =IFERROR(AVERAGEIFS($D31:$BM31,$D$6:$BM$6,">="&BS$2,$D$6:$BM$6,"<="&BS$6,$D$5:$BM$5,BS$5,$D31:$BM31,"<>0"),0) -> 0 | BT31: =IFERROR(AVERAGEIFS($D31:$BM31,$D$6:$BM$6,">="&BT$2,$D$6:$BM$6,"<="&BT$6,$D$5:$BM$5,BT$5,$D31:$BM31,"<>0"),0) -> 0 | BW31: =SUMIFS($D31:$BM31,$D$6:$BM$6,">="&BO$2,$D$6:$BM$6,"<="&BO$6,$D$5:$BM$5,BO$5) -> 0 | BX31: =SUMIFS($D31:$BM31,$D$6:$BM$6,">="&BP$2,$D$6:$BM$6,"<="&BP$6,$D$5:$BM$5,BP$5) -> 0 | BY31: =SUMIFS($D31:$BM31,$D$6:$BM$6,">="&BQ$2,$D$6:$BM$6,"<="&BQ$6,$D$5:$BM$5,BQ$5) -> 0 | BZ31: =SUMIFS($D31:$BM31,$D$6:$BM$6,">="&BR$2,$D$6:$BM$6,"<="&BR$6,$D$5:$BM$5,BR$5) -> 0 | CA31: =SUMIFS($D31:$BM31,$D$6:$BM$6,">="&BS$2,$D$6:$BM$6,"<="&BS$6,$D$5:$BM$5,BS$5) -> 0 | CB31: =SUMIFS($D31:$BM31,$D$6:$BM$6,">="&BT$2,$D$6:$BM$6,"<="&BT$6,$D$5:$BM$5,BT$5) -> 0
A32: SALDO_PROM | D32: =+Renta_Alta!D32+Masivo!D32+Consumo_Inicial!D32 -> 0 | E32: =+Renta_Alta!E32+Masivo!E32+Consumo_Inicial!E32 -> 0 | F32: =+Renta_Alta!F32+Masivo!F32+Consumo_Inicial!F32 -> 0 | G32: =+Renta_Alta!G32+Masivo!G32+Consumo_Inicial!G32 -> 0 | H32: =+Renta_Alta!H32+Masivo!H32+Consumo_Inicial!H32 -> 0 | I32: =+Renta_Alta!I32+Masivo!I32+Consumo_Inicial!I32 -> 0 | J32: =+Renta_Alta!J32+Masivo!J32+Consumo_Inicial!J32 -> 0 | K32: =+Renta_Alta!K32+Masivo!K32+Consumo_Inicial!K32 -> 0 | ... BK32: =+Renta_Alta!BK32+Masivo!BK32+Consumo_Inicial!BK32 -> 0 | BO32: =IFERROR(AVERAGEIFS($D32:$BM32,$D$6:$BM$6,">="&BO$2,$D$6:$BM$6,"<="&BO$6,$D$5:$BM$5,BO$5,$D32:$BM32,"<>0"),0) -> 0 | BP32: =IFERROR(AVERAGEIFS($D32:$BM32,$D$6:$BM$6,">="&BP$2,$D$6:$BM$6,"<="&BP$6,$D$5:$BM$5,BP$5,$D32:$BM32,"<>0"),0) -> 0 | BQ32: =IFERROR(AVERAGEIFS($D32:$BM32,$D$6:$BM$6,">="&BQ$2,$D$6:$BM$6,"<="&BQ$6,$D$5:$BM$5,BQ$5,$D32:$BM32,"<>0"),0) -> 0 | BR32: =IFERROR(AVERAGEIFS($D32:$BM32,$D$6:$BM$6,">="&BR$2,$D$6:$BM$6,"<="&BR$6,$D$5:$BM$5,BR$5,$D32:$BM32,"<>0"),0) -> 0 | BS32: =IFERROR(AVERAGEIFS($D32:$BM32,$D$6:$BM$6,">="&BS$2,$D$6:$BM$6,"<="&BS$6,$D$5:$BM$5,BS$5,$D32:$BM32,"<>0"),0) -> 0 | BT32: =IFERROR(AVERAGEIFS($D32:$BM32,$D$6:$BM$6,">="&BT$2,$D$6:$BM$6,"<="&BT$6,$D$5:$BM$5,BT$5,$D32:$BM32,"<>0"),0) -> 0 | BW32: =SUMIFS($D32:$BM32,$D$6:$BM$6,">="&BO$2,$D$6:$BM$6,"<="&BO$6,$D$5:$BM$5,BO$5) -> 0 | BX32: =SUMIFS($D32:$BM32,$D$6:$BM$6,">="&BP$2,$D$6:$BM$6,"<="&BP$6,$D$5:$BM$5,BP$5) -> 0 | BY32: =SUMIFS($D32:$BM32,$D$6:$BM$6,">="&BQ$2,$D$6:$BM$6,"<="&BQ$6,$D$5:$BM$5,BQ$5) -> 0 | BZ32: =SUMIFS($D32:$BM32,$D$6:$BM$6,">="&BR$2,$D$6:$BM$6,"<="&BR$6,$D$5:$BM$5,BR$5) -> 0 | CA32: =SUMIFS($D32:$BM32,$D$6:$BM$6,">="&BS$2,$D$6:$BM$6,"<="&BS$6,$D$5:$BM$5,BS$5) -> 0 | CB32: =SUMIFS($D32:$BM32,$D$6:$BM$6,">="&BT$2,$D$6:$BM$6,"<="&BT$6,$D$5:$BM$5,BT$5) -> 0
A33: SALDO_PROM | D33: =+Renta_Alta!D33+Masivo!D33+Consumo_Inicial!D33 -> 0 | E33: =+Renta_Alta!E33+Masivo!E33+Consumo_Inicial!E33 -> 0 | F33: =+Renta_Alta!F33+Masivo!F33+Consumo_Inicial!F33 -> 0 | G33: =+Renta_Alta!G33+Masivo!G33+Consumo_Inicial!G33 -> 0 | H33: =+Renta_Alta!H33+Masivo!H33+Consumo_Inicial!H33 -> 0 | I33: =+Renta_Alta!I33+Masivo!I33+Consumo_Inicial!I33 -> 0 | J33: =+Renta_Alta!J33+Masivo!J33+Consumo_Inicial!J33 -> 0 | K33: =+Renta_Alta!K33+Masivo!K33+Consumo_Inicial!K33 -> 0 | ... BK33: =+Renta_Alta!BK33+Masivo!BK33+Consumo_Inicial!BK33 -> 0 | BO33: =IFERROR(AVERAGEIFS($D33:$BM33,$D$6:$BM$6,">="&BO$2,$D$6:$BM$6,"<="&BO$6,$D$5:$BM$5,BO$5,$D33:$BM33,"<>0"),0) -> 0 | BP33: =IFERROR(AVERAGEIFS($D33:$BM33,$D$6:$BM$6,">="&BP$2,$D$6:$BM$6,"<="&BP$6,$D$5:$BM$5,BP$5,$D33:$BM33,"<>0"),0) -> 0 | BQ33: =IFERROR(AVERAGEIFS($D33:$BM33,$D$6:$BM$6,">="&BQ$2,$D$6:$BM$6,"<="&BQ$6,$D$5:$BM$5,BQ$5,$D33:$BM33,"<>0"),0) -> 0 | BR33: =IFERROR(AVERAGEIFS($D33:$BM33,$D$6:$BM$6,">="&BR$2,$D$6:$BM$6,"<="&BR$6,$D$5:$BM$5,BR$5,$D33:$BM33,"<>0"),0) -> 0 | BS33: =IFERROR(AVERAGEIFS($D33:$BM33,$D$6:$BM$6,">="&BS$2,$D$6:$BM$6,"<="&BS$6,$D$5:$BM$5,BS$5,$D33:$BM33,"<>0"),0) -> 0 | BT33: =IFERROR(AVERAGEIFS($D33:$BM33,$D$6:$BM$6,">="&BT$2,$D$6:$BM$6,"<="&BT$6,$D$5:$BM$5,BT$5,$D33:$BM33,"<>0"),0) -> 0 | BW33: =SUMIFS($D33:$BM33,$D$6:$BM$6,">="&BO$2,$D$6:$BM$6,"<="&BO$6,$D$5:$BM$5,BO$5) -> 0 | BX33: =SUMIFS($D33:$BM33,$D$6:$BM$6,">="&BP$2,$D$6:$BM$6,"<="&BP$6,$D$5:$BM$5,BP$5) -> 0 | BY33: =SUMIFS($D33:$BM33,$D$6:$BM$6,">="&BQ$2,$D$6:$BM$6,"<="&BQ$6,$D$5:$BM$5,BQ$5) -> 0 | BZ33: =SUMIFS($D33:$BM33,$D$6:$BM$6,">="&BR$2,$D$6:$BM$6,"<="&BR$6,$D$5:$BM$5,BR$5) -> 0 | CA33: =SUMIFS($D33:$BM33,$D$6:$BM$6,">="&BS$2,$D$6:$BM$6,"<="&BS$6,$D$5:$BM$5,BS$5) -> 0 | CB33: =SUMIFS($D33:$BM33,$D$6:$BM$6,">="&BT$2,$D$6:$BM$6,"<="&BT$6,$D$5:$BM$5,BT$5) -> 0
A34: SALDO_PROM | D34: =+Renta_Alta!D34+Masivo!D34+Consumo_Inicial!D34 -> 0 | E34: =+Renta_Alta!E34+Masivo!E34+Consumo_Inicial!E34 -> 0 | F34: =+Renta_Alta!F34+Masivo!F34+Consumo_Inicial!F34 -> 0 | G34: =+Renta_Alta!G34+Masivo!G34+Consumo_Inicial!G34 -> 0 | H34: =+Renta_Alta!H34+Masivo!H34+Consumo_Inicial!H34 -> 0 | I34: =+Renta_Alta!I34+Masivo!I34+Consumo_Inicial!I34 -> 0 | J34: =+Renta_Alta!J34+Masivo!J34+Consumo_Inicial!J34 -> 0 | K34: =+Renta_Alta!K34+Masivo!K34+Consumo_Inicial!K34 -> 0 | ... BK34: =+Renta_Alta!BK34+Masivo!BK34+Consumo_Inicial!BK34 -> 0 | BO34: =IFERROR(AVERAGEIFS($D34:$BM34,$D$6:$BM$6,">="&BO$2,$D$6:$BM$6,"<="&BO$6,$D$5:$BM$5,BO$5,$D34:$BM34,"<>0"),0) -> 0 | BP34: =IFERROR(AVERAGEIFS($D34:$BM34,$D$6:$BM$6,">="&BP$2,$D$6:$BM$6,"<="&BP$6,$D$5:$BM$5,BP$5,$D34:$BM34,"<>0"),0) -> 0 | BQ34: =IFERROR(AVERAGEIFS($D34:$BM34,$D$6:$BM$6,">="&BQ$2,$D$6:$BM$6,"<="&BQ$6,$D$5:$BM$5,BQ$5,$D34:$BM34,"<>0"),0) -> 0 | BR34: =IFERROR(AVERAGEIFS($D34:$BM34,$D$6:$BM$6,">="&BR$2,$D$6:$BM$6,"<="&BR$6,$D$5:$BM$5,BR$5,$D34:$BM34,"<>0"),0) -> 0 | BS34: =IFERROR(AVERAGEIFS($D34:$BM34,$D$6:$BM$6,">="&BS$2,$D$6:$BM$6,"<="&BS$6,$D$5:$BM$5,BS$5,$D34:$BM34,"<>0"),0) -> 0 | BT34: =IFERROR(AVERAGEIFS($D34:$BM34,$D$6:$BM$6,">="&BT$2,$D$6:$BM$6,"<="&BT$6,$D$5:$BM$5,BT$5,$D34:$BM34,"<>0"),0) -> 0 | BW34: =SUMIFS($D34:$BM34,$D$6:$BM$6,">="&BO$2,$D$6:$BM$6,"<="&BO$6,$D$5:$BM$5,BO$5) -> 0 | BX34: =SUMIFS($D34:$BM34,$D$6:$BM$6,">="&BP$2,$D$6:$BM$6,"<="&BP$6,$D$5:$BM$5,BP$5) -> 0 | BY34: =SUMIFS($D34:$BM34,$D$6:$BM$6,">="&BQ$2,$D$6:$BM$6,"<="&BQ$6,$D$5:$BM$5,BQ$5) -> 0 | BZ34: =SUMIFS($D34:$BM34,$D$6:$BM$6,">="&BR$2,$D$6:$BM$6,"<="&BR$6,$D$5:$BM$5,BR$5) -> 0 | CA34: =SUMIFS($D34:$BM34,$D$6:$BM$6,">="&BS$2,$D$6:$BM$6,"<="&BS$6,$D$5:$BM$5,BS$5) -> 0 | CB34: =SUMIFS($D34:$BM34,$D$6:$BM$6,">="&BT$2,$D$6:$BM$6,"<="&BT$6,$D$5:$BM$5,BT$5) -> 0
A35: SALDO_PROM | D35: =SUM(D27:D34) -> 0 | E35: =SUM(E27:E34) -> 0 | F35: =SUM(F27:F34) -> 0 | G35: =SUM(G27:G34) -> 0 | H35: =SUM(H27:H34) -> 0 | I35: =SUM(I27:I34) -> 0 | J35: =SUM(J27:J34) -> 0 | K35: =SUM(K27:K34) -> 0 | ... BK35: =SUM(BK27:BK34) -> 2053001.2 | BO35: =SUM(BO27:BO34) -> 0 | BP35: =SUM(BP27:BP34) -> 1777154.7 | BQ35: =SUM(BQ27:BQ34) -> 0 | BR35: =SUM(BR27:BR34) -> 0 | BS35: =SUM(BS27:BS34) -> 0 | BT35: =SUM(BT27:BT34) -> 0 | BW35: =SUM(BW27:BW34) -> 0 | BX35: =SUM(BX27:BX34) -> 8885773.4 | BY35: =SUM(BY27:BY34) -> 0 | BZ35: =SUM(BZ27:BZ34) -> 0 | CA35: =SUM(CA27:CA34) -> 0 | CB35: =SUM(CB27:CB34) -> 0
A36: SALDO_PROM | D36: =+Renta_Alta!D36+Masivo!D36+Consumo_Inicial!D36 -> 0 | E36: =+Renta_Alta!E36+Masivo!E36+Consumo_Inicial!E36 -> 0 | F36: =+Renta_Alta!F36+Masivo!F36+Consumo_Inicial!F36 -> 0 | G36: =+Renta_Alta!G36+Masivo!G36+Consumo_Inicial!G36 -> 0 | H36: =+Renta_Alta!H36+Masivo!H36+Consumo_Inicial!H36 -> 0 | I36: =+Renta_Alta!I36+Masivo!I36+Consumo_Inicial!I36 -> 0 | J36: =+Renta_Alta!J36+Masivo!J36+Consumo_Inicial!J36 -> 0 | K36: =+Renta_Alta!K36+Masivo!K36+Consumo_Inicial!K36 -> 0 | ... BK36: =+Renta_Alta!BK36+Masivo!BK36+Consumo_Inicial!BK36 -> 0 | BO36: =IFERROR(AVERAGEIFS($D36:$BM36,$D$6:$BM$6,">="&BO$2,$D$6:$BM$6,"<="&BO$6,$D$5:$BM$5,BO$5,$D36:$BM36,"<>0"),0) -> 0 | BP36: =IFERROR(AVERAGEIFS($D36:$BM36,$D$6:$BM$6,">="&BP$2,$D$6:$BM$6,"<="&BP$6,$D$5:$BM$5,BP$5,$D36:$BM36,"<>0"),0) -> 0 | BQ36: =IFERROR(AVERAGEIFS($D36:$BM36,$D$6:$BM$6,">="&BQ$2,$D$6:$BM$6,"<="&BQ$6,$D$5:$BM$5,BQ$5,$D36:$BM36,"<>0"),0) -> 0 | BR36: =IFERROR(AVERAGEIFS($D36:$BM36,$D$6:$BM$6,">="&BR$2,$D$6:$BM$6,"<="&BR$6,$D$5:$BM$5,BR$5,$D36:$BM36,"<>0"),0) -> 0 | BS36: =IFERROR(AVERAGEIFS($D36:$BM36,$D$6:$BM$6,">="&BS$2,$D$6:$BM$6,"<="&BS$6,$D$5:$BM$5,BS$5,$D36:$BM36,"<>0"),0) -> 0 | BT36: =IFERROR(AVERAGEIFS($D36:$BM36,$D$6:$BM$6,">="&BT$2,$D$6:$BM$6,"<="&BT$6,$D$5:$BM$5,BT$5,$D36:$BM36,"<>0"),0) -> 0 | BW36: =SUMIFS($D36:$BM36,$D$6:$BM$6,">="&BO$2,$D$6:$BM$6,"<="&BO$6,$D$5:$BM$5,BO$5) -> 0 | BX36: =SUMIFS($D36:$BM36,$D$6:$BM$6,">="&BP$2,$D$6:$BM$6,"<="&BP$6,$D$5:$BM$5,BP$5) -> 0 | BY36: =SUMIFS($D36:$BM36,$D$6:$BM$6,">="&BQ$2,$D$6:$BM$6,"<="&BQ$6,$D$5:$BM$5,BQ$5) -> 0 | BZ36: =SUMIFS($D36:$BM36,$D$6:$BM$6,">="&BR$2,$D$6:$BM$6,"<="&BR$6,$D$5:$BM$5,BR$5) -> 0 | CA36: =SUMIFS($D36:$BM36,$D$6:$BM$6,">="&BS$2,$D$6:$BM$6,"<="&BS$6,$D$5:$BM$5,BS$5) -> 0 | CB36: =SUMIFS($D36:$BM36,$D$6:$BM$6,">="&BT$2,$D$6:$BM$6,"<="&BT$6,$D$5:$BM$5,BT$5) -> 0
A37: SALDO_PROM | D37: =+Renta_Alta!D37+Masivo!D37+Consumo_Inicial!D37 -> 0 | E37: =+Renta_Alta!E37+Masivo!E37+Consumo_Inicial!E37 -> 0 | F37: =+Renta_Alta!F37+Masivo!F37+Consumo_Inicial!F37 -> 0 | G37: =+Renta_Alta!G37+Masivo!G37+Consumo_Inicial!G37 -> 0 | H37: =+Renta_Alta!H37+Masivo!H37+Consumo_Inicial!H37 -> 0 | I37: =+Renta_Alta!I37+Masivo!I37+Consumo_Inicial!I37 -> 0 | J37: =+Renta_Alta!J37+Masivo!J37+Consumo_Inicial!J37 -> 0 | K37: =+Renta_Alta!K37+Masivo!K37+Consumo_Inicial!K37 -> 0 | ... BK37: =+Renta_Alta!BK37+Masivo!BK37+Consumo_Inicial!BK37 -> 0 | BO37: =IFERROR(AVERAGEIFS($D37:$BM37,$D$6:$BM$6,">="&BO$2,$D$6:$BM$6,"<="&BO$6,$D$5:$BM$5,BO$5,$D37:$BM37,"<>0"),0) -> 0 | BP37: =IFERROR(AVERAGEIFS($D37:$BM37,$D$6:$BM$6,">="&BP$2,$D$6:$BM$6,"<="&BP$6,$D$5:$BM$5,BP$5,$D37:$BM37,"<>0"),0) -> 0 | BQ37: =IFERROR(AVERAGEIFS($D37:$BM37,$D$6:$BM$6,">="&BQ$2,$D$6:$BM$6,"<="&BQ$6,$D$5:$BM$5,BQ$5,$D37:$BM37,"<>0"),0) -> 0 | BR37: =IFERROR(AVERAGEIFS($D37:$BM37,$D$6:$BM$6,">="&BR$2,$D$6:$BM$6,"<="&BR$6,$D$5:$BM$5,BR$5,$D37:$BM37,"<>0"),0) -> 0 | BS37: =IFERROR(AVERAGEIFS($D37:$BM37,$D$6:$BM$6,">="&BS$2,$D$6:$BM$6,"<="&BS$6,$D$5:$BM$5,BS$5,$D37:$BM37,"<>0"),0) -> 0 | BT37: =IFERROR(AVERAGEIFS($D37:$BM37,$D$6:$BM$6,">="&BT$2,$D$6:$BM$6,"<="&BT$6,$D$5:$BM$5,BT$5,$D37:$BM37,"<>0"),0) -> 0 | BW37: =SUMIFS($D37:$BM37,$D$6:$BM$6,">="&BO$2,$D$6:$BM$6,"<="&BO$6,$D$5:$BM$5,BO$5) -> 0 | BX37: =SUMIFS($D37:$BM37,$D$6:$BM$6,">="&BP$2,$D$6:$BM$6,"<="&BP$6,$D$5:$BM$5,BP$5) -> 0 | BY37: =SUMIFS($D37:$BM37,$D$6:$BM$6,">="&BQ$2,$D$6:$BM$6,"<="&BQ$6,$D$5:$BM$5,BQ$5) -> 0 | BZ37: =SUMIFS($D37:$BM37,$D$6:$BM$6,">="&BR$2,$D$6:$BM$6,"<="&BR$6,$D$5:$BM$5,BR$5) -> 0 | CA37: =SUMIFS($D37:$BM37,$D$6:$BM$6,">="&BS$2,$D$6:$BM$6,"<="&BS$6,$D$5:$BM$5,BS$5) -> 0 | CB37: =SUMIFS($D37:$BM37,$D$6:$BM$6,">="&BT$2,$D$6:$BM$6,"<="&BT$6,$D$5:$BM$5,BT$5) -> 0
A38: SALDO_PROM | D38: =+Renta_Alta!D38+Masivo!D38+Consumo_Inicial!D38 -> 0 | E38: =+Renta_Alta!E38+Masivo!E38+Consumo_Inicial!E38 -> 0 | F38: =+Renta_Alta!F38+Masivo!F38+Consumo_Inicial!F38 -> 0 | G38: =+Renta_Alta!G38+Masivo!G38+Consumo_Inicial!G38 -> 0 | H38: =+Renta_Alta!H38+Masivo!H38+Consumo_Inicial!H38 -> 0 | I38: =+Renta_Alta!I38+Masivo!I38+Consumo_Inicial!I38 -> 0 | J38: =+Renta_Alta!J38+Masivo!J38+Consumo_Inicial!J38 -> 0 | K38: =+Renta_Alta!K38+Masivo!K38+Consumo_Inicial!K38 -> 0 | ... BK38: =+Renta_Alta!BK38+Masivo!BK38+Consumo_Inicial!BK38 -> 0 | BO38: =IFERROR(AVERAGEIFS($D38:$BM38,$D$6:$BM$6,">="&BO$2,$D$6:$BM$6,"<="&BO$6,$D$5:$BM$5,BO$5,$D38:$BM38,"<>0"),0) -> 0 | BP38: =IFERROR(AVERAGEIFS($D38:$BM38,$D$6:$BM$6,">="&BP$2,$D$6:$BM$6,"<="&BP$6,$D$5:$BM$5,BP$5,$D38:$BM38,"<>0"),0) -> 0 | BQ38: =IFERROR(AVERAGEIFS($D38:$BM38,$D$6:$BM$6,">="&BQ$2,$D$6:$BM$6,"<="&BQ$6,$D$5:$BM$5,BQ$5,$D38:$BM38,"<>0"),0) -> 0 | BR38: =IFERROR(AVERAGEIFS($D38:$BM38,$D$6:$BM$6,">="&BR$2,$D$6:$BM$6,"<="&BR$6,$D$5:$BM$5,BR$5,$D38:$BM38,"<>0"),0) -> 0 | BS38: =IFERROR(AVERAGEIFS($D38:$BM38,$D$6:$BM$6,">="&BS$2,$D$6:$BM$6,"<="&BS$6,$D$5:$BM$5,BS$5,$D38:$BM38,"<>0"),0) -> 0 | BT38: =IFERROR(AVERAGEIFS($D38:$BM38,$D$6:$BM$6,">="&BT$2,$D$6:$BM$6,"<="&BT$6,$D$5:$BM$5,BT$5,$D38:$BM38,"<>0"),0) -> 0 | BW38: =SUMIFS($D38:$BM38,$D$6:$BM$6,">="&BO$2,$D$6:$BM$6,"<="&BO$6,$D$5:$BM$5,BO$5) -> 0 | BX38: =SUMIFS($D38:$BM38,$D$6:$BM$6,">="&BP$2,$D$6:$BM$6,"<="&BP$6,$D$5:$BM$5,BP$5) -> 0 | BY38: =SUMIFS($D38:$BM38,$D$6:$BM$6,">="&BQ$2,$D$6:$BM$6,"<="&BQ$6,$D$5:$BM$5,BQ$5) -> 0 | BZ38: =SUMIFS($D38:$BM38,$D$6:$BM$6,">="&BR$2,$D$6:$BM$6,"<="&BR$6,$D$5:$BM$5,BR$5) -> 0 | CA38: =SUMIFS($D38:$BM38,$D$6:$BM$6,">="&BS$2,$D$6:$BM$6,"<="&BS$6,$D$5:$BM$5,BS$5) -> 0 | CB38: =SUMIFS($D38:$BM38,$D$6:$BM$6,">="&BT$2,$D$6:$BM$6,"<="&BT$6,$D$5:$BM$5,BT$5) -> 0
A39: SALDO_PROM | D39: =+Renta_Alta!D39+Masivo!D39+Consumo_Inicial!D39 -> 0 | E39: =+Renta_Alta!E39+Masivo!E39+Consumo_Inicial!E39 -> 0 | F39: =+Renta_Alta!F39+Masivo!F39+Consumo_Inicial!F39 -> 0 | G39: =+Renta_Alta!G39+Masivo!G39+Consumo_Inicial!G39 -> 0 | H39: =+Renta_Alta!H39+Masivo!H39+Consumo_Inicial!H39 -> 0 | I39: =+Renta_Alta!I39+Masivo!I39+Consumo_Inicial!I39 -> 0 | J39: =+Renta_Alta!J39+Masivo!J39+Consumo_Inicial!J39 -> 0 | K39: =+Renta_Alta!K39+Masivo!K39+Consumo_Inicial!K39 -> 0 | ... BK39: =+Renta_Alta!BK39+Masivo!BK39+Consumo_Inicial!BK39 -> 0 | BO39: =IFERROR(AVERAGEIFS($D39:$BM39,$D$6:$BM$6,">="&BO$2,$D$6:$BM$6,"<="&BO$6,$D$5:$BM$5,BO$5,$D39:$BM39,"<>0"),0) -> 0 | BP39: =IFERROR(AVERAGEIFS($D39:$BM39,$D$6:$BM$6,">="&BP$2,$D$6:$BM$6,"<="&BP$6,$D$5:$BM$5,BP$5,$D39:$BM39,"<>0"),0) -> 0 | BQ39: =IFERROR(AVERAGEIFS($D39:$BM39,$D$6:$BM$6,">="&BQ$2,$D$6:$BM$6,"<="&BQ$6,$D$5:$BM$5,BQ$5,$D39:$BM39,"<>0"),0) -> 0 | BR39: =IFERROR(AVERAGEIFS($D39:$BM39,$D$6:$BM$6,">="&BR$2,$D$6:$BM$6,"<="&BR$6,$D$5:$BM$5,BR$5,$D39:$BM39,"<>0"),0) -> 0 | BS39: =IFERROR(AVERAGEIFS($D39:$BM39,$D$6:$BM$6,">="&BS$2,$D$6:$BM$6,"<="&BS$6,$D$5:$BM$5,BS$5,$D39:$BM39,"<>0"),0) -> 0 | BT39: =IFERROR(AVERAGEIFS($D39:$BM39,$D$6:$BM$6,">="&BT$2,$D$6:$BM$6,"<="&BT$6,$D$5:$BM$5,BT$5,$D39:$BM39,"<>0"),0) -> 0 | BW39: =SUMIFS($D39:$BM39,$D$6:$BM$6,">="&BO$2,$D$6:$BM$6,"<="&BO$6,$D$5:$BM$5,BO$5) -> 0 | BX39: =SUMIFS($D39:$BM39,$D$6:$BM$6,">="&BP$2,$D$6:$BM$6,"<="&BP$6,$D$5:$BM$5,BP$5) -> 0 | BY39: =SUMIFS($D39:$BM39,$D$6:$BM$6,">="&BQ$2,$D$6:$BM$6,"<="&BQ$6,$D$5:$BM$5,BQ$5) -> 0 | BZ39: =SUMIFS($D39:$BM39,$D$6:$BM$6,">="&BR$2,$D$6:$BM$6,"<="&BR$6,$D$5:$BM$5,BR$5) -> 0 | CA39: =SUMIFS($D39:$BM39,$D$6:$BM$6,">="&BS$2,$D$6:$BM$6,"<="&BS$6,$D$5:$BM$5,BS$5) -> 0 | CB39: =SUMIFS($D39:$BM39,$D$6:$BM$6,">="&BT$2,$D$6:$BM$6,"<="&BT$6,$D$5:$BM$5,BT$5) -> 0
A40: SALDO_PROM | D40: =+Renta_Alta!D40+Masivo!D40+Consumo_Inicial!D40 -> 0 | E40: =+Renta_Alta!E40+Masivo!E40+Consumo_Inicial!E40 -> 0 | F40: =+Renta_Alta!F40+Masivo!F40+Consumo_Inicial!F40 -> 0 | G40: =+Renta_Alta!G40+Masivo!G40+Consumo_Inicial!G40 -> 0 | H40: =+Renta_Alta!H40+Masivo!H40+Consumo_Inicial!H40 -> 0 | I40: =+Renta_Alta!I40+Masivo!I40+Consumo_Inicial!I40 -> 0 | J40: =+Renta_Alta!J40+Masivo!J40+Consumo_Inicial!J40 -> 0 | K40: =+Renta_Alta!K40+Masivo!K40+Consumo_Inicial!K40 -> 0 | ... BK40: =+Renta_Alta!BK40+Masivo!BK40+Consumo_Inicial!BK40 -> 0 | BO40: =IFERROR(AVERAGEIFS($D40:$BM40,$D$6:$BM$6,">="&BO$2,$D$6:$BM$6,"<="&BO$6,$D$5:$BM$5,BO$5,$D40:$BM40,"<>0"),0) -> 0 | BP40: =IFERROR(AVERAGEIFS($D40:$BM40,$D$6:$BM$6,">="&BP$2,$D$6:$BM$6,"<="&BP$6,$D$5:$BM$5,BP$5,$D40:$BM40,"<>0"),0) -> 0 | BQ40: =IFERROR(AVERAGEIFS($D40:$BM40,$D$6:$BM$6,">="&BQ$2,$D$6:$BM$6,"<="&BQ$6,$D$5:$BM$5,BQ$5,$D40:$BM40,"<>0"),0) -> 0 | BR40: =IFERROR(AVERAGEIFS($D40:$BM40,$D$6:$BM$6,">="&BR$2,$D$6:$BM$6,"<="&BR$6,$D$5:$BM$5,BR$5,$D40:$BM40,"<>0"),0) -> 0 | BS40: =IFERROR(AVERAGEIFS($D40:$BM40,$D$6:$BM$6,">="&BS$2,$D$6:$BM$6,"<="&BS$6,$D$5:$BM$5,BS$5,$D40:$BM40,"<>0"),0) -> 0 | BT40: =IFERROR(AVERAGEIFS($D40:$BM40,$D$6:$BM$6,">="&BT$2,$D$6:$BM$6,"<="&BT$6,$D$5:$BM$5,BT$5,$D40:$BM40,"<>0"),0) -> 0 | BW40: =SUMIFS($D40:$BM40,$D$6:$BM$6,">="&BO$2,$D$6:$BM$6,"<="&BO$6,$D$5:$BM$5,BO$5) -> 0 | BX40: =SUMIFS($D40:$BM40,$D$6:$BM$6,">="&BP$2,$D$6:$BM$6,"<="&BP$6,$D$5:$BM$5,BP$5) -> 0 | BY40: =SUMIFS($D40:$BM40,$D$6:$BM$6,">="&BQ$2,$D$6:$BM$6,"<="&BQ$6,$D$5:$BM$5,BQ$5) -> 0 | BZ40: =SUMIFS($D40:$BM40,$D$6:$BM$6,">="&BR$2,$D$6:$BM$6,"<="&BR$6,$D$5:$BM$5,BR$5) -> 0 | CA40: =SUMIFS($D40:$BM40,$D$6:$BM$6,">="&BS$2,$D$6:$BM$6,"<="&BS$6,$D$5:$BM$5,BS$5) -> 0 | CB40: =SUMIFS($D40:$BM40,$D$6:$BM$6,">="&BT$2,$D$6:$BM$6,"<="&BT$6,$D$5:$BM$5,BT$5) -> 0
A41: SALDO_PROM | D41: =+Renta_Alta!D41+Masivo!D41+Consumo_Inicial!D41 -> 0 | E41: =+Renta_Alta!E41+Masivo!E41+Consumo_Inicial!E41 -> 0 | F41: =+Renta_Alta!F41+Masivo!F41+Consumo_Inicial!F41 -> 0 | G41: =+Renta_Alta!G41+Masivo!G41+Consumo_Inicial!G41 -> 0 | H41: =+Renta_Alta!H41+Masivo!H41+Consumo_Inicial!H41 -> 0 | I41: =+Renta_Alta!I41+Masivo!I41+Consumo_Inicial!I41 -> 0 | J41: =+Renta_Alta!J41+Masivo!J41+Consumo_Inicial!J41 -> 0 | K41: =+Renta_Alta!K41+Masivo!K41+Consumo_Inicial!K41 -> 0 | ... BK41: =+Renta_Alta!BK41+Masivo!BK41+Consumo_Inicial!BK41 -> 0 | BO41: =IFERROR(AVERAGEIFS($D41:$BM41,$D$6:$BM$6,">="&BO$2,$D$6:$BM$6,"<="&BO$6,$D$5:$BM$5,BO$5,$D41:$BM41,"<>0"),0) -> 0 | BP41: =IFERROR(AVERAGEIFS($D41:$BM41,$D$6:$BM$6,">="&BP$2,$D$6:$BM$6,"<="&BP$6,$D$5:$BM$5,BP$5,$D41:$BM41,"<>0"),0) -> 0 | BQ41: =IFERROR(AVERAGEIFS($D41:$BM41,$D$6:$BM$6,">="&BQ$2,$D$6:$BM$6,"<="&BQ$6,$D$5:$BM$5,BQ$5,$D41:$BM41,"<>0"),0) -> 0 | BR41: =IFERROR(AVERAGEIFS($D41:$BM41,$D$6:$BM$6,">="&BR$2,$D$6:$BM$6,"<="&BR$6,$D$5:$BM$5,BR$5,$D41:$BM41,"<>0"),0) -> 0 | BS41: =IFERROR(AVERAGEIFS($D41:$BM41,$D$6:$BM$6,">="&BS$2,$D$6:$BM$6,"<="&BS$6,$D$5:$BM$5,BS$5,$D41:$BM41,"<>0"),0) -> 0 | BT41: =IFERROR(AVERAGEIFS($D41:$BM41,$D$6:$BM$6,">="&BT$2,$D$6:$BM$6,"<="&BT$6,$D$5:$BM$5,BT$5,$D41:$BM41,"<>0"),0) -> 0 | BW41: =SUMIFS($D41:$BM41,$D$6:$BM$6,">="&BO$2,$D$6:$BM$6,"<="&BO$6,$D$5:$BM$5,BO$5) -> 0 | BX41: =SUMIFS($D41:$BM41,$D$6:$BM$6,">="&BP$2,$D$6:$BM$6,"<="&BP$6,$D$5:$BM$5,BP$5) -> 0 | BY41: =SUMIFS($D41:$BM41,$D$6:$BM$6,">="&BQ$2,$D$6:$BM$6,"<="&BQ$6,$D$5:$BM$5,BQ$5) -> 0 | BZ41: =SUMIFS($D41:$BM41,$D$6:$BM$6,">="&BR$2,$D$6:$BM$6,"<="&BR$6,$D$5:$BM$5,BR$5) -> 0 | CA41: =SUMIFS($D41:$BM41,$D$6:$BM$6,">="&BS$2,$D$6:$BM$6,"<="&BS$6,$D$5:$BM$5,BS$5) -> 0 | CB41: =SUMIFS($D41:$BM41,$D$6:$BM$6,">="&BT$2,$D$6:$BM$6,"<="&BT$6,$D$5:$BM$5,BT$5) -> 0
A42: SALDO_PROM | D42: =SUM(D40:D41) -> 0 | E42: =SUM(E40:E41) -> 0 | F42: =SUM(F40:F41) -> 0 | G42: =SUM(G40:G41) -> 0 | H42: =SUM(H40:H41) -> 0 | I42: =SUM(I40:I41) -> 0 | J42: =SUM(J40:J41) -> 0 | K42: =SUM(K40:K41) -> 0 | ... BK42: =SUM(BK40:BK41) -> 0 | BO42: =SUM(BO40:BO41) -> 0 | BP42: =SUM(BP40:BP41) -> 0 | BQ42: =SUM(BQ40:BQ41) -> 0 | BR42: =SUM(BR40:BR41) -> 0 | BS42: =SUM(BS40:BS41) -> 0 | BT42: =SUM(BT40:BT41) -> 0 | BW42: =SUM(BW40:BW41) -> 0 | BX42: =SUM(BX40:BX41) -> 0 | BY42: =SUM(BY40:BY41) -> 0 | BZ42: =SUM(BZ40:BZ41) -> 0 | CA42: =SUM(CA40:CA41) -> 0 | CB42: =SUM(CB40:CB41) -> 0
C43: Saldo Prom | D43: =SUM(D35,D36:D39,D42) -> 0 | E43: =SUM(E35,E36:E39,E42) -> 0 | F43: =SUM(F35,F36:F39,F42) -> 0 | G43: =SUM(G35,G36:G39,G42) -> 0 | H43: =SUM(H35,H36:H39,H42) -> 0 | I43: =SUM(I35,I36:I39,I42) -> 0 | J43: =SUM(J35,J36:J39,J42) -> 0 | K43: =SUM(K35,K36:K39,K42) -> 0 | ... BK43: =SUM(BK35,BK36:BK39,BK42) -> 2053001.2 | BO43: =SUM(BO35,BO36:BO39,BO42) -> 0 | BP43: =SUM(BP35,BP36:BP39,BP42) -> 1777154.7 | BQ43: =SUM(BQ35,BQ36:BQ39,BQ42) -> 0 | BR43: =SUM(BR35,BR36:BR39,BR42) -> 0 | BS43: =SUM(BS35,BS36:BS39,BS42) -> 0 | BT43: =SUM(BT35,BT36:BT39,BT42) -> 0 | BW43: =SUM(BW35,BW36:BW39,BW42) -> 0 | BX43: =SUM(BX35,BX36:BX39,BX42) -> 8885773.4 | BY43: =SUM(BY35,BY36:BY39,BY42) -> 0 | BZ43: =SUM(BZ35,BZ36:BZ39,BZ42) -> 0 | CA43: =SUM(CA35,CA36:CA39,CA42) -> 0 | CB43: =SUM(CB35,CB36:CB39,CB42) -> 0
C46: Cuenta Sueldo | D46: =IFERROR(((1+D103/D27)^(360/D$3))-1,0) -> 0 | E46: =IFERROR(((1+E103/E27)^(360/E$3))-1,0) -> 0 | F46: =IFERROR(((1+F103/F27)^(360/F$3))-1,0) -> 0 | G46: =IFERROR(((1+G103/G27)^(360/G$3))-1,0) -> 0 | H46: =IFERROR(((1+H103/H27)^(360/H$3))-1,0) -> 0 | I46: =IFERROR(((1+I103/I27)^(360/I$3))-1,0) -> 0 | J46: =IFERROR(((1+J103/J27)^(360/J$3))-1,0) -> 0 | K46: =IFERROR(((1+K103/K27)^(360/K$3))-1,0) -> 0 | ... BK46: =IFERROR(((1+BK103/BK27)^(360/BK$3))-1,0) -> 0.042558659 | BO46: =IFERROR(((1+BO103/BW27)^(360/BO$3))-1,0) -> 0 | BP46: =IFERROR(((1+BP103/BX27)^(360/BP$3))-1,0) -> 0.04252755 | BQ46: =IFERROR(((1+BQ103/BY27)^(360/BQ$3))-1,0) -> 0 | BR46: =IFERROR(((1+BR103/BZ27)^(360/BR$3))-1,0) -> 0 | BS46: =IFERROR(((1+BS103/CA27)^(360/BS$3))-1,0) -> 0 | BT46: =IFERROR(((1+BT103/CB27)^(360/BT$3))-1,0) -> 0
D47: =IFERROR(((1+D104/D28)^(360/D$3))-1,0) -> 0 | E47: =IFERROR(((1+E104/E28)^(360/E$3))-1,0) -> 0 | F47: =IFERROR(((1+F104/F28)^(360/F$3))-1,0) -> 0 | G47: =IFERROR(((1+G104/G28)^(360/G$3))-1,0) -> 0 | H47: =IFERROR(((1+H104/H28)^(360/H$3))-1,0) -> 0 | I47: =IFERROR(((1+I104/I28)^(360/I$3))-1,0) -> 0 | J47: =IFERROR(((1+J104/J28)^(360/J$3))-1,0) -> 0 | K47: =IFERROR(((1+K104/K28)^(360/K$3))-1,0) -> 0 | ... BK47: =IFERROR(((1+BK104/BK28)^(360/BK$3))-1,0) -> 0 | BO47: =IFERROR(((1+BO104/BW28)^(360/BO$3))-1,0) -> 0 | BP47: =IFERROR(((1+BP104/BX28)^(360/BP$3))-1,0) -> 0 | BQ47: =IFERROR(((1+BQ104/BY28)^(360/BQ$3))-1,0) -> 0 | BR47: =IFERROR(((1+BR104/BZ28)^(360/BR$3))-1,0) -> 0 | BS47: =IFERROR(((1+BS104/CA28)^(360/BS$3))-1,0) -> 0 | BT47: =IFERROR(((1+BT104/CB28)^(360/BT$3))-1,0) -> 0
D48: =IFERROR(((1+D105/D29)^(360/D$3))-1,0) -> 0 | E48: =IFERROR(((1+E105/E29)^(360/E$3))-1,0) -> 0 | F48: =IFERROR(((1+F105/F29)^(360/F$3))-1,0) -> 0 | G48: =IFERROR(((1+G105/G29)^(360/G$3))-1,0) -> 0 | H48: =IFERROR(((1+H105/H29)^(360/H$3))-1,0) -> 0 | I48: =IFERROR(((1+I105/I29)^(360/I$3))-1,0) -> 0 | J48: =IFERROR(((1+J105/J29)^(360/J$3))-1,0) -> 0 | K48: =IFERROR(((1+K105/K29)^(360/K$3))-1,0) -> 0 | ... BK48: =IFERROR(((1+BK105/BK29)^(360/BK$3))-1,0) -> 0 | BO48: =IFERROR(((1+BO105/BW29)^(360/BO$3))-1,0) -> 0 | BP48: =IFERROR(((1+BP105/BX29)^(360/BP$3))-1,0) -> 0 | BQ48: =IFERROR(((1+BQ105/BY29)^(360/BQ$3))-1,0) -> 0 | BR48: =IFERROR(((1+BR105/BZ29)^(360/BR$3))-1,0) -> 0 | BS48: =IFERROR(((1+BS105/CA29)^(360/BS$3))-1,0) -> 0 | BT48: =IFERROR(((1+BT105/CB29)^(360/BT$3))-1,0) -> 0
D49: =IFERROR(((1+D108/D30)^(360/D$3))-1,0) -> 0 | E49: =IFERROR(((1+E108/E30)^(360/E$3))-1,0) -> 0 | F49: =IFERROR(((1+F108/F30)^(360/F$3))-1,0) -> 0 | G49: =IFERROR(((1+G108/G30)^(360/G$3))-1,0) -> 0 | H49: =IFERROR(((1+H108/H30)^(360/H$3))-1,0) -> 0 | I49: =IFERROR(((1+I108/I30)^(360/I$3))-1,0) -> 0 | J49: =IFERROR(((1+J108/J30)^(360/J$3))-1,0) -> 0 | K49: =IFERROR(((1+K108/K30)^(360/K$3))-1,0) -> 0 | ... BK49: =IFERROR(((1+BK108/BK30)^(360/BK$3))-1,0) -> 0 | BO49: =IFERROR(((1+BO106/BW30)^(360/BO$3))-1,0) -> 0 | BP49: =IFERROR(((1+BP106/BX30)^(360/BP$3))-1,0) -> 0 | BQ49: =IFERROR(((1+BQ106/BY30)^(360/BQ$3))-1,0) -> 0 | BR49: =IFERROR(((1+BR106/BZ30)^(360/BR$3))-1,0) -> 0 | BS49: =IFERROR(((1+BS106/CA30)^(360/BS$3))-1,0) -> 0 | BT49: =IFERROR(((1+BT106/CB30)^(360/BT$3))-1,0) -> 0
D50: =IFERROR(((1+D109/D31)^(360/D$3))-1,0) -> 0 | E50: =IFERROR(((1+E109/E31)^(360/E$3))-1,0) -> 0 | F50: =IFERROR(((1+F109/F31)^(360/F$3))-1,0) -> 0 | G50: =IFERROR(((1+G109/G31)^(360/G$3))-1,0) -> 0 | H50: =IFERROR(((1+H109/H31)^(360/H$3))-1,0) -> 0 | I50: =IFERROR(((1+I109/I31)^(360/I$3))-1,0) -> 0 | J50: =IFERROR(((1+J109/J31)^(360/J$3))-1,0) -> 0 | K50: =IFERROR(((1+K109/K31)^(360/K$3))-1,0) -> 0 | ... BK50: =IFERROR(((1+BK109/BK31)^(360/BK$3))-1,0) -> 0 | BO50: =IFERROR(((1+BO107/BW31)^(360/BO$3))-1,0) -> 0 | BP50: =IFERROR(((1+BP107/BX31)^(360/BP$3))-1,0) -> 0 | BQ50: =IFERROR(((1+BQ107/BY31)^(360/BQ$3))-1,0) -> 0 | BR50: =IFERROR(((1+BR107/BZ31)^(360/BR$3))-1,0) -> 0 | BS50: =IFERROR(((1+BS107/CA31)^(360/BS$3))-1,0) -> 0 | BT50: =IFERROR(((1+BT107/CB31)^(360/BT$3))-1,0) -> 0
D51: =IFERROR(((1+D108/D32)^(360/D$3))-1,0) -> 0 | E51: =IFERROR(((1+E108/E32)^(360/E$3))-1,0) -> 0 | F51: =IFERROR(((1+F108/F32)^(360/F$3))-1,0) -> 0 | G51: =IFERROR(((1+G108/G32)^(360/G$3))-1,0) -> 0 | H51: =IFERROR(((1+H108/H32)^(360/H$3))-1,0) -> 0 | I51: =IFERROR(((1+I108/I32)^(360/I$3))-1,0) -> 0 | J51: =IFERROR(((1+J108/J32)^(360/J$3))-1,0) -> 0 | K51: =IFERROR(((1+K108/K32)^(360/K$3))-1,0) -> 0 | ... BK51: =IFERROR(((1+BK108/BK32)^(360/BK$3))-1,0) -> 0 | BO51: =IFERROR(((1+BO108/BW32)^(360/BO$3))-1,0) -> 0 | BP51: =IFERROR(((1+BP108/BX32)^(360/BP$3))-1,0) -> 0 | BQ51: =IFERROR(((1+BQ108/BY32)^(360/BQ$3))-1,0) -> 0 | BR51: =IFERROR(((1+BR108/BZ32)^(360/BR$3))-1,0) -> 0 | BS51: =IFERROR(((1+BS108/CA32)^(360/BS$3))-1,0) -> 0 | BT51: =IFERROR(((1+BT108/CB32)^(360/BT$3))-1,0) -> 0
D52: =IFERROR(((1+D109/D33)^(360/D$3))-1,0) -> 0 | E52: =IFERROR(((1+E109/E33)^(360/E$3))-1,0) -> 0 | F52: =IFERROR(((1+F109/F33)^(360/F$3))-1,0) -> 0 | G52: =IFERROR(((1+G109/G33)^(360/G$3))-1,0) -> 0 | H52: =IFERROR(((1+H109/H33)^(360/H$3))-1,0) -> 0 | I52: =IFERROR(((1+I109/I33)^(360/I$3))-1,0) -> 0 | J52: =IFERROR(((1+J109/J33)^(360/J$3))-1,0) -> 0 | K52: =IFERROR(((1+K109/K33)^(360/K$3))-1,0) -> 0 | ... BK52: =IFERROR(((1+BK109/BK33)^(360/BK$3))-1,0) -> 0 | BO52: =IFERROR(((1+BO109/BW33)^(360/BO$3))-1,0) -> 0 | BP52: =IFERROR(((1+BP109/BX33)^(360/BP$3))-1,0) -> 0 | BQ52: =IFERROR(((1+BQ109/BY33)^(360/BQ$3))-1,0) -> 0 | BR52: =IFERROR(((1+BR109/BZ33)^(360/BR$3))-1,0) -> 0 | BS52: =IFERROR(((1+BS109/CA33)^(360/BS$3))-1,0) -> 0 | BT52: =IFERROR(((1+BT109/CB33)^(360/BT$3))-1,0) -> 0
D53: =IFERROR(((1+D110/D34)^(360/D$3))-1,0) -> 0 | E53: =IFERROR(((1+E110/E34)^(360/E$3))-1,0) -> 0 | F53: =IFERROR(((1+F110/F34)^(360/F$3))-1,0) -> 0 | G53: =IFERROR(((1+G110/G34)^(360/G$3))-1,0) -> 0 | H53: =IFERROR(((1+H110/H34)^(360/H$3))-1,0) -> 0 | I53: =IFERROR(((1+I110/I34)^(360/I$3))-1,0) -> 0 | J53: =IFERROR(((1+J110/J34)^(360/J$3))-1,0) -> 0 | K53: =IFERROR(((1+K110/K34)^(360/K$3))-1,0) -> 0 | ... BK53: =IFERROR(((1+BK110/BK34)^(360/BK$3))-1,0) -> 0 | BO53: =IFERROR(((1+BO110/BW34)^(360/BO$3))-1,0) -> 0 | BP53: =IFERROR(((1+BP110/BX34)^(360/BP$3))-1,0) -> 0 | BQ53: =IFERROR(((1+BQ110/BY34)^(360/BQ$3))-1,0) -> 0 | BR53: =IFERROR(((1+BR110/BZ34)^(360/BR$3))-1,0) -> 0 | BS53: =IFERROR(((1+BS110/CA34)^(360/BS$3))-1,0) -> 0 | BT53: =IFERROR(((1+BT110/CB34)^(360/BT$3))-1,0) -> 0
D54: =IFERROR(((1+D111/D35)^(360/D$3))-1,0) -> 0 | E54: =IFERROR(((1+E111/E35)^(360/E$3))-1,0) -> 0 | F54: =IFERROR(((1+F111/F35)^(360/F$3))-1,0) -> 0 | G54: =IFERROR(((1+G111/G35)^(360/G$3))-1,0) -> 0 | H54: =IFERROR(((1+H111/H35)^(360/H$3))-1,0) -> 0 | I54: =IFERROR(((1+I111/I35)^(360/I$3))-1,0) -> 0 | J54: =IFERROR(((1+J111/J35)^(360/J$3))-1,0) -> 0 | K54: =IFERROR(((1+K111/K35)^(360/K$3))-1,0) -> 0 | ... BK54: =IFERROR(((1+BK111/BK35)^(360/BK$3))-1,0) -> 0.042558659 | BO54: =IFERROR(((1+BO111/BW35)^(360/BO$3))-1,0) -> 0 | BP54: =IFERROR(((1+BP111/BX35)^(360/BP$3))-1,0) -> 0.04252755 | BQ54: =IFERROR(((1+BQ111/BY35)^(360/BQ$3))-1,0) -> 0 | BR54: =IFERROR(((1+BR111/BZ35)^(360/BR$3))-1,0) -> 0 | BS54: =IFERROR(((1+BS111/CA35)^(360/BS$3))-1,0) -> 0 | BT54: =IFERROR(((1+BT111/CB35)^(360/BT$3))-1,0) -> 0
D55: =IFERROR(((1+D112/D36)^(360/D$3))-1,0) -> 0 | E55: =IFERROR(((1+E112/E36)^(360/E$3))-1,0) -> 0 | F55: =IFERROR(((1+F112/F36)^(360/F$3))-1,0) -> 0 | G55: =IFERROR(((1+G112/G36)^(360/G$3))-1,0) -> 0 | H55: =IFERROR(((1+H112/H36)^(360/H$3))-1,0) -> 0 | I55: =IFERROR(((1+I112/I36)^(360/I$3))-1,0) -> 0 | J55: =IFERROR(((1+J112/J36)^(360/J$3))-1,0) -> 0 | K55: =IFERROR(((1+K112/K36)^(360/K$3))-1,0) -> 0 | ... BK55: =IFERROR(((1+BK112/BK36)^(360/BK$3))-1,0) -> 0 | BO55: =IFERROR(((1+BO112/BW36)^(360/BO$3))-1,0) -> 0 | BP55: =IFERROR(((1+BP112/BX36)^(360/BP$3))-1,0) -> 0 | BQ55: =IFERROR(((1+BQ112/BY36)^(360/BQ$3))-1,0) -> 0 | BR55: =IFERROR(((1+BR112/BZ36)^(360/BR$3))-1,0) -> 0 | BS55: =IFERROR(((1+BS112/CA36)^(360/BS$3))-1,0) -> 0 | BT55: =IFERROR(((1+BT112/CB36)^(360/BT$3))-1,0) -> 0
D56: =IFERROR(((1+D113/D37)^(360/D$3))-1,0) -> 0 | E56: =IFERROR(((1+E113/E37)^(360/E$3))-1,0) -> 0 | F56: =IFERROR(((1+F113/F37)^(360/F$3))-1,0) -> 0 | G56: =IFERROR(((1+G113/G37)^(360/G$3))-1,0) -> 0 | H56: =IFERROR(((1+H113/H37)^(360/H$3))-1,0) -> 0 | I56: =IFERROR(((1+I113/I37)^(360/I$3))-1,0) -> 0 | J56: =IFERROR(((1+J113/J37)^(360/J$3))-1,0) -> 0 | K56: =IFERROR(((1+K113/K37)^(360/K$3))-1,0) -> 0 | ... BK56: =IFERROR(((1+BK113/BK37)^(360/BK$3))-1,0) -> 0 | BO56: =IFERROR(((1+BO113/BW37)^(360/BO$3))-1,0) -> 0 | BP56: =IFERROR(((1+BP113/BX37)^(360/BP$3))-1,0) -> 0 | BQ56: =IFERROR(((1+BQ113/BY37)^(360/BQ$3))-1,0) -> 0 | BR56: =IFERROR(((1+BR113/BZ37)^(360/BR$3))-1,0) -> 0 | BS56: =IFERROR(((1+BS113/CA37)^(360/BS$3))-1,0) -> 0 | BT56: =IFERROR(((1+BT113/CB37)^(360/BT$3))-1,0) -> 0
D57: =IFERROR(((1+D114/D38)^(360/D$3))-1,0) -> 0 | E57: =IFERROR(((1+E114/E38)^(360/E$3))-1,0) -> 0 | F57: =IFERROR(((1+F114/F38)^(360/F$3))-1,0) -> 0 | G57: =IFERROR(((1+G114/G38)^(360/G$3))-1,0) -> 0 | H57: =IFERROR(((1+H114/H38)^(360/H$3))-1,0) -> 0 | I57: =IFERROR(((1+I114/I38)^(360/I$3))-1,0) -> 0 | J57: =IFERROR(((1+J114/J38)^(360/J$3))-1,0) -> 0 | K57: =IFERROR(((1+K114/K38)^(360/K$3))-1,0) -> 0 | ... BK57: =IFERROR(((1+BK114/BK38)^(360/BK$3))-1,0) -> 0 | BO57: =IFERROR(((1+BO114/BW38)^(360/BO$3))-1,0) -> 0 | BP57: =IFERROR(((1+BP114/BX38)^(360/BP$3))-1,0) -> 0 | BQ57: =IFERROR(((1+BQ114/BY38)^(360/BQ$3))-1,0) -> 0 | BR57: =IFERROR(((1+BR114/BZ38)^(360/BR$3))-1,0) -> 0 | BS57: =IFERROR(((1+BS114/CA38)^(360/BS$3))-1,0) -> 0 | BT57: =IFERROR(((1+BT114/CB38)^(360/BT$3))-1,0) -> 0
D58: =IFERROR(((1+D115/D39)^(360/D$3))-1,0) -> 0 | E58: =IFERROR(((1+E115/E39)^(360/E$3))-1,0) -> 0 | F58: =IFERROR(((1+F115/F39)^(360/F$3))-1,0) -> 0 | G58: =IFERROR(((1+G115/G39)^(360/G$3))-1,0) -> 0 | H58: =IFERROR(((1+H115/H39)^(360/H$3))-1,0) -> 0 | I58: =IFERROR(((1+I115/I39)^(360/I$3))-1,0) -> 0 | J58: =IFERROR(((1+J115/J39)^(360/J$3))-1,0) -> 0 | K58: =IFERROR(((1+K115/K39)^(360/K$3))-1,0) -> 0 | ... BK58: =IFERROR(((1+BK115/BK39)^(360/BK$3))-1,0) -> 0 | BO58: =IFERROR(((1+BO115/BW39)^(360/BO$3))-1,0) -> 0 | BP58: =IFERROR(((1+BP115/BX39)^(360/BP$3))-1,0) -> 0 | BQ58: =IFERROR(((1+BQ115/BY39)^(360/BQ$3))-1,0) -> 0 | BR58: =IFERROR(((1+BR115/BZ39)^(360/BR$3))-1,0) -> 0 | BS58: =IFERROR(((1+BS115/CA39)^(360/BS$3))-1,0) -> 0 | BT58: =IFERROR(((1+BT115/CB39)^(360/BT$3))-1,0) -> 0
D59: =IFERROR(((1+D116/D40)^(360/D$3))-1,0) -> 0 | E59: =IFERROR(((1+E116/E40)^(360/E$3))-1,0) -> 0 | F59: =IFERROR(((1+F116/F40)^(360/F$3))-1,0) -> 0 | G59: =IFERROR(((1+G116/G40)^(360/G$3))-1,0) -> 0 | H59: =IFERROR(((1+H116/H40)^(360/H$3))-1,0) -> 0 | I59: =IFERROR(((1+I116/I40)^(360/I$3))-1,0) -> 0 | J59: =IFERROR(((1+J116/J40)^(360/J$3))-1,0) -> 0 | K59: =IFERROR(((1+K116/K40)^(360/K$3))-1,0) -> 0 | ... BK59: =IFERROR(((1+BK116/BK40)^(360/BK$3))-1,0) -> 0 | BO59: =IFERROR(((1+BO116/BW40)^(360/BO$3))-1,0) -> 0 | BP59: =IFERROR(((1+BP116/BX40)^(360/BP$3))-1,0) -> 0 | BQ59: =IFERROR(((1+BQ116/BY40)^(360/BQ$3))-1,0) -> 0 | BR59: =IFERROR(((1+BR116/BZ40)^(360/BR$3))-1,0) -> 0 | BS59: =IFERROR(((1+BS116/CA40)^(360/BS$3))-1,0) -> 0 | BT59: =IFERROR(((1+BT116/CB40)^(360/BT$3))-1,0) -> 0
D60: =IFERROR(((1+D117/D41)^(360/D$3))-1,0) -> 0 | E60: =IFERROR(((1+E117/E41)^(360/E$3))-1,0) -> 0 | F60: =IFERROR(((1+F117/F41)^(360/F$3))-1,0) -> 0 | G60: =IFERROR(((1+G117/G41)^(360/G$3))-1,0) -> 0 | H60: =IFERROR(((1+H117/H41)^(360/H$3))-1,0) -> 0 | I60: =IFERROR(((1+I117/I41)^(360/I$3))-1,0) -> 0 | J60: =IFERROR(((1+J117/J41)^(360/J$3))-1,0) -> 0 | K60: =IFERROR(((1+K117/K41)^(360/K$3))-1,0) -> 0 | ... BK60: =IFERROR(((1+BK117/BK41)^(360/BK$3))-1,0) -> 0 | BO60: =IFERROR(((1+BO117/BW41)^(360/BO$3))-1,0) -> 0 | BP60: =IFERROR(((1+BP117/BX41)^(360/BP$3))-1,0) -> 0 | BQ60: =IFERROR(((1+BQ117/BY41)^(360/BQ$3))-1,0) -> 0 | BR60: =IFERROR(((1+BR117/BZ41)^(360/BR$3))-1,0) -> 0 | BS60: =IFERROR(((1+BS117/CA41)^(360/BS$3))-1,0) -> 0 | BT60: =IFERROR(((1+BT117/CB41)^(360/BT$3))-1,0) -> 0
D61: =IFERROR(((1+D118/D42)^(360/D$3))-1,0) -> 0 | E61: =IFERROR(((1+E118/E42)^(360/E$3))-1,0) -> 0 | F61: =IFERROR(((1+F118/F42)^(360/F$3))-1,0) -> 0 | G61: =IFERROR(((1+G118/G42)^(360/G$3))-1,0) -> 0 | H61: =IFERROR(((1+H118/H42)^(360/H$3))-1,0) -> 0 | I61: =IFERROR(((1+I118/I42)^(360/I$3))-1,0) -> 0 | J61: =IFERROR(((1+J118/J42)^(360/J$3))-1,0) -> 0 | K61: =IFERROR(((1+K118/K42)^(360/K$3))-1,0) -> 0 | ... BK61: =IFERROR(((1+BK118/BK42)^(360/BK$3))-1,0) -> 0 | BO61: =IFERROR(((1+BO118/BW42)^(360/BO$3))-1,0) -> 0 | BP61: =IFERROR(((1+BP118/BX42)^(360/BP$3))-1,0) -> 0 | BQ61: =IFERROR(((1+BQ118/BY42)^(360/BQ$3))-1,0) -> 0 | BR61: =IFERROR(((1+BR118/BZ42)^(360/BR$3))-1,0) -> 0 | BS61: =IFERROR(((1+BS118/CA42)^(360/BS$3))-1,0) -> 0 | BT61: =IFERROR(((1+BT118/CB42)^(360/BT$3))-1,0) -> 0
C62: Tasa FTP | D62: =IFERROR(((1+D119/D43)^(360/D$3))-1,0) -> 0 | E62: =IFERROR(((1+E119/E43)^(360/E$3))-1,0) -> 0 | F62: =IFERROR(((1+F119/F43)^(360/F$3))-1,0) -> 0 | G62: =IFERROR(((1+G119/G43)^(360/G$3))-1,0) -> 0 | H62: =IFERROR(((1+H119/H43)^(360/H$3))-1,0) -> 0 | I62: =IFERROR(((1+I119/I43)^(360/I$3))-1,0) -> 0 | J62: =IFERROR(((1+J119/J43)^(360/J$3))-1,0) -> 0 | K62: =IFERROR(((1+K119/K43)^(360/K$3))-1,0) -> 0 | ... BK62: =IFERROR(((1+BK119/BK43)^(360/BK$3))-1,0) -> 0.042558659 | BO62: =IFERROR(((1+BO119/BW43)^(360/BO$3))-1,0) -> 0 | BP62: =IFERROR(((1+BP119/BX43)^(360/BP$3))-1,0) -> 0.04252755 | BQ62: =IFERROR(((1+BQ119/BY43)^(360/BQ$3))-1,0) -> 0 | BR62: =IFERROR(((1+BR119/BZ43)^(360/BR$3))-1,0) -> 0 | BS62: =IFERROR(((1+BS119/CA43)^(360/BS$3))-1,0) -> 0 | BT62: =IFERROR(((1+BT119/CB43)^(360/BT$3))-1,0) -> 0
C65: Cuenta Sueldo | D65: =-IFERROR(((1-D122/D27)^(360/D$4))-1,0) -> 0 | E65: =-IFERROR(((1-E122/E27)^(360/E$4))-1,0) -> 0 | F65: =-IFERROR(((1-F122/F27)^(360/F$4))-1,0) -> 0 | G65: =-IFERROR(((1-G122/G27)^(360/G$4))-1,0) -> 0 | H65: =-IFERROR(((1-H122/H27)^(360/H$4))-1,0) -> 0 | I65: =-IFERROR(((1-I122/I27)^(360/I$4))-1,0) -> 0 | J65: =-IFERROR(((1-J122/J27)^(360/J$4))-1,0) -> 0 | K65: =-IFERROR(((1-K122/K27)^(360/K$4))-1,0) -> 0 | ... BK65: =-IFERROR(((1-BK122/BK27)^(360/BK$4))-1,0) -> 0 | BO65: =-IFERROR(((1-BO122/BW27)^(360/BO$4))-1,0) -> 0 | BP65: =-IFERROR(((1-BP122/BX27)^(360/BP$4))-1,0) -> 0 | BQ65: =-IFERROR(((1-BQ122/BY27)^(360/BQ$4))-1,0) -> 0 | BR65: =-IFERROR(((1-BR122/BZ27)^(360/BR$4))-1,0) -> 0 | BS65: =-IFERROR(((1-BS122/CA27)^(360/BS$4))-1,0) -> 0 | BT65: =-IFERROR(((1-BT122/CB27)^(360/BT$4))-1,0) -> 0
D66: =-IFERROR(((1-D123/D28)^(360/D$4))-1,0) -> 0 | E66: =-IFERROR(((1-E123/E28)^(360/E$4))-1,0) -> 0 | F66: =-IFERROR(((1-F123/F28)^(360/F$4))-1,0) -> 0 | G66: =-IFERROR(((1-G123/G28)^(360/G$4))-1,0) -> 0 | H66: =-IFERROR(((1-H123/H28)^(360/H$4))-1,0) -> 0 | I66: =-IFERROR(((1-I123/I28)^(360/I$4))-1,0) -> 0 | J66: =-IFERROR(((1-J123/J28)^(360/J$4))-1,0) -> 0 | K66: =-IFERROR(((1-K123/K28)^(360/K$4))-1,0) -> 0 | ... BK66: =-IFERROR(((1-BK123/BK28)^(360/BK$4))-1,0) -> 0 | BO66: =-IFERROR(((1-BO123/BW28)^(360/BO$4))-1,0) -> 0 | BP66: =-IFERROR(((1-BP123/BX28)^(360/BP$4))-1,0) -> 0 | BQ66: =-IFERROR(((1-BQ123/BY28)^(360/BQ$4))-1,0) -> 0 | BR66: =-IFERROR(((1-BR123/BZ28)^(360/BR$4))-1,0) -> 0 | BS66: =-IFERROR(((1-BS123/CA28)^(360/BS$4))-1,0) -> 0 | BT66: =-IFERROR(((1-BT123/CB28)^(360/BT$4))-1,0) -> 0
D67: =-IFERROR(((1-D124/D29)^(360/D$4))-1,0) -> 0 | E67: =-IFERROR(((1-E124/E29)^(360/E$4))-1,0) -> 0 | F67: =-IFERROR(((1-F124/F29)^(360/F$4))-1,0) -> 0 | G67: =-IFERROR(((1-G124/G29)^(360/G$4))-1,0) -> 0 | H67: =-IFERROR(((1-H124/H29)^(360/H$4))-1,0) -> 0 | I67: =-IFERROR(((1-I124/I29)^(360/I$4))-1,0) -> 0 | J67: =-IFERROR(((1-J124/J29)^(360/J$4))-1,0) -> 0 | K67: =-IFERROR(((1-K124/K29)^(360/K$4))-1,0) -> 0 | ... BK67: =-IFERROR(((1-BK124/BK29)^(360/BK$4))-1,0) -> 0 | BO67: =-IFERROR(((1-BO124/BW29)^(360/BO$4))-1,0) -> 0 | BP67: =-IFERROR(((1-BP124/BX29)^(360/BP$4))-1,0) -> 0 | BQ67: =-IFERROR(((1-BQ124/BY29)^(360/BQ$4))-1,0) -> 0 | BR67: =-IFERROR(((1-BR124/BZ29)^(360/BR$4))-1,0) -> 0 | BS67: =-IFERROR(((1-BS124/CA29)^(360/BS$4))-1,0) -> 0 | BT67: =-IFERROR(((1-BT124/CB29)^(360/BT$4))-1,0) -> 0
D68: =-IFERROR(((1-D127/D30)^(360/D$4))-1,0) -> 0 | E68: =-IFERROR(((1-E127/E30)^(360/E$4))-1,0) -> 0 | F68: =-IFERROR(((1-F127/F30)^(360/F$4))-1,0) -> 0 | G68: =-IFERROR(((1-G127/G30)^(360/G$4))-1,0) -> 0 | H68: =-IFERROR(((1-H127/H30)^(360/H$4))-1,0) -> 0 | I68: =-IFERROR(((1-I127/I30)^(360/I$4))-1,0) -> 0 | J68: =-IFERROR(((1-J127/J30)^(360/J$4))-1,0) -> 0 | K68: =-IFERROR(((1-K127/K30)^(360/K$4))-1,0) -> 0 | ... BK68: =-IFERROR(((1-BK127/BK30)^(360/BK$4))-1,0) -> 0 | BO68: =-IFERROR(((1-BO125/BW30)^(360/BO$4))-1,0) -> 0 | BP68: =-IFERROR(((1-BP125/BX30)^(360/BP$4))-1,0) -> 0 | BQ68: =-IFERROR(((1-BQ125/BY30)^(360/BQ$4))-1,0) -> 0 | BR68: =-IFERROR(((1-BR125/BZ30)^(360/BR$4))-1,0) -> 0 | BS68: =-IFERROR(((1-BS125/CA30)^(360/BS$4))-1,0) -> 0 | BT68: =-IFERROR(((1-BT125/CB30)^(360/BT$4))-1,0) -> 0
D69: =-IFERROR(((1-D128/D31)^(360/D$4))-1,0) -> 0 | E69: =-IFERROR(((1-E128/E31)^(360/E$4))-1,0) -> 0 | F69: =-IFERROR(((1-F128/F31)^(360/F$4))-1,0) -> 0 | G69: =-IFERROR(((1-G128/G31)^(360/G$4))-1,0) -> 0 | H69: =-IFERROR(((1-H128/H31)^(360/H$4))-1,0) -> 0 | I69: =-IFERROR(((1-I128/I31)^(360/I$4))-1,0) -> 0 | J69: =-IFERROR(((1-J128/J31)^(360/J$4))-1,0) -> 0 | K69: =-IFERROR(((1-K128/K31)^(360/K$4))-1,0) -> 0 | ... BK69: =-IFERROR(((1-BK128/BK31)^(360/BK$4))-1,0) -> 0 | BO69: =-IFERROR(((1-BO126/BW31)^(360/BO$4))-1,0) -> 0 | BP69: =-IFERROR(((1-BP126/BX31)^(360/BP$4))-1,0) -> 0 | BQ69: =-IFERROR(((1-BQ126/BY31)^(360/BQ$4))-1,0) -> 0 | BR69: =-IFERROR(((1-BR126/BZ31)^(360/BR$4))-1,0) -> 0 | BS69: =-IFERROR(((1-BS126/CA31)^(360/BS$4))-1,0) -> 0 | BT69: =-IFERROR(((1-BT126/CB31)^(360/BT$4))-1,0) -> 0
