Workbook

Sheet Parametros
B2: Producto | C2: Convenios
B4: Año | C4: 2026
B6: Lista Fechas | C6: =EOMONTH(DATE($C$4,1,1),0) -> 46053 | E6: Segmentos | F6: Renta_Alta
C7: =EOMONTH(C6,1) -> 46081 | F7: Masivo
C8: =EOMONTH(C7,1) -> 46112 | F8: Consumo_Inicial
C9: =EOMONTH(C8,1) -> 46142 | F9: Total_Producto
C10: =EOMONTH(C9,1) -> 46173
C11: =EOMONTH(C10,1) -> 46203
C12: =EOMONTH(C11,1) -> 46234
C13: =EOMONTH(C12,1) -> 46265
C14: =EOMONTH(C13,1) -> 46295
C15: =EOMONTH(C14,1) -> 46326
C16: =EOMONTH(C15,1) -> 46356
C17: =EOMONTH(C16,1) -> 46387

Sheet Total_Producto_CHECK
D1: REAL | AZ1: PRESUPUESTO | BO1: Acumulado | BW1: Saldo Prom Acumulado
BO2: =DATE(YEAR(BO6),1,1) -> 46023 | BP2: =DATE(YEAR(BP6),1,1) -> 46023 | BQ2: =DATE(YEAR(BQ6),1,1) -> 46023 | BR2: =DATE(YEAR(BR6),1,1) -> 45658 | BS2: =DATE(YEAR(BS6),1,1) -> 45292 | BT2: =DATE(YEAR(BT6),1,1) -> 44927
C3: N° dias T.Imp | D3: =DAY(D6) -> 31 | E3: =DAY(E6) -> 28 | F3: =DAY(F6) -> 31 | G3: =DAY(G6) -> 30 | H3: =DAY(H6) -> 31 | I3: =DAY(I6) -> 30 | J3: =DAY(J6) -> 31 | K3: =DAY(K6) -> 31 | ... BK3: =DAY(BK6) -> 31 | BO3: =AVERAGEIFS($D3:$BM3,$D$6:$BM$6,">="&BO$2,$D$6:$BM$6,"<="&BO$6,$D$5:$BM$5,BO$5) -> 30 | BP3: =AVERAGEIFS($D3:$BM3,$D$6:$BM$6,">="&BP$2,$D$6:$BM$6,"<="&BP$6,$D$5:$BM$5,BP$5) -> 30 | BQ3: =AVERAGEIFS($D3:$BM3,$D$6:$BM$6,">="&BQ$2,$D$6:$BM$6,"<="&BQ$6,$D$5:$BM$5,BQ$5) -> 29.5 | BR3: =AVERAGEIFS($D3:$BM3,$D$6:$BM$6,">="&BR$2,$D$6:$BM$6,"<="&BR$6,$D$5:$BM$5,BR$5) -> 30 | BS3: =AVERAGEIFS($D3:$BM3,$D$6:$BM$6,">="&BS$2,$D$6:$BM$6,"<="&BS$6,$D$5:$BM$5,BS$5) -> 30.333333 | BT3: =AVERAGEIFS($D3:$BM3,$D$6:$BM$6,">="&BT$2,$D$6:$BM$6,"<="&BT$6,$D$5:$BM$5,BT$5) -> 30
C4: N° dias FTP | D4: 30 | E4: 30 | F4: 30 | G4: 30 | H4: 30 | I4: 30 | J4: 30 | K4: 30 | L4: 30 | M4: 30 | N4: 30 | O4: 30 | P4: 30 | Q4: 30 | R4: 30 | S4: 30 | T4: 30 | U4: 30 | V4: 30 | W4: 30 | X4: 30 | Y4: 30 | Z4: 30 | AA4: 30 | AB4: 30 | AC4: 30 | AD4: 30 | AE4: 30 | AF4: 30 | AG4: 30 | AH4: 30 | AI4: 30 | AJ4: 30 | AK4: 30 | AL4: 30 | AM4: 30 | AN4: 30 | AO4: 30 | AP4: 30 | AQ4: 30 | AR4: 30 | AS4: 30 | AT4: 30 | AU4: 30 | AV4: 30 | AW4: 30 | AX4: 30 | AY4: 30 | AZ4: 30 | BA4: 30 | BB4: 30 | BC4: 30 | BD4: 30 | BE4: 30 | BF4: 30 | BG4: 30 | BH4: 30 | BI4: 30 | BJ4: 30 | BK4: 30 | BO4: =AVERAGEIFS($D4:$BM4,$D$6:$BM$6,">="&BO$2,$D$6:$BM$6,"<="&BO$6,$D$5:$BM$5,BO$5) -> 30 | BP4: =AVERAGEIFS($D4:$BM4,$D$6:$BM$6,">="&BP$2,$D$6:$BM$6,"<="&BP$6,$D$5:$BM$5,BP$5) -> 30 | BQ4: =AVERAGEIFS($D4:$BM4,$D$6:$BM$6,">="&BQ$2,$D$6:$BM$6,"<="&BQ$6,$D$5:$BM$5,BQ$5) -> 30 | BR4: =AVERAGEIFS($D4:$BM4,$D$6:$BM$6,">="&BR$2,$D$6:$BM$6,"<="&BR$6,$D$5:$BM$5,BR$5) -> 30 | BS4: =AVERAGEIFS($D4:$BM4,$D$6:$BM$6,">="&BS$2,$D$6:$BM$6,"<="&BS$6,$D$5:$BM$5,BS$5) -> 30 | BT4: =AVERAGEIFS($D4:$BM4,$D$6:$BM$6,">="&BT$2,$D$6:$BM$6,"<="&BT$6,$D$5:$BM$5,BT$5) -> 30
C5: Tipo | D5: R | E5: R | F5: R | G5: R | H5: R | I5: R | J5: R | K5: R | L5: R | M5: R | N5: R | O5: R | P5: R | Q5: R | R5: R | S5: R | T5: R | U5: R | V5: R | W5: R | X5: R | Y5: R | Z5: R | AA5: R | AB5: R | AC5: R | AD5: R | AE5: R | AF5: R | AG5: R | AH5: R | AI5: R | AJ5: R | AK5: R | AL5: R | AM5: R | AN5: R | AO5: R | AP5: R | AQ5: R | AR5: R | AS5: R | AT5: R | AU5: R | AV5: R | AW5: R | AX5: R | AY5: R | AZ5: P | BA5: P | BB5: P | BC5: P | BD5: P | BE5: P | BF5: P | BG5: P | BH5: P | BI5: P | BJ5: P | BK5: P | BO5: R | BP5: P | BQ5: R | BR5: R | BS5: R | BT5: R
C6: Total Hipotecario | D6: 44957 | E6: 44985 | F6: 45016 | G6: 45046 | H6: 45077 | I6: 45107 | J6: 45138 | K6: 45169 | L6: 45199 | M6: 45230 | N6: 45260 | O6: 45291 | P6: 45322 | Q6: 45351 | R6: 45382 | S6: 45412 | T6: 45443 | U6: 45473 | V6: 45504 | W6: 45535 | X6: 45565 | Y6: 45596 | Z6: 45626 | AA6: 45657 | AB6: 45688 | AC6: 45716 | AD6: 45747 | AE6: 45777 | AF6: 45808 | AG6: 45838 | AH6: 45869 | AI6: 45900 | AJ6: 45930 | AK6: 45961 | AL6: 45991 | AM6: 46022 | AN6: 46053 | AO6: 46081 | AP6: 46112 | AQ6: 46142 | AR6: 46173 | AS6: 46203 | AT6: 46234 | AU6: 46265 | AV6: 46295 | AW6: 46326 | AX6: 46356 | AY6: 46387 | AZ6: 46053 | BA6: 46081 | BB6: 46112 | BC6: 46142 | BD6: 46173 | BE6: 46203 | BF6: 46234 | BG6: 46265 | BH6: 46295 | BI6: 46326 | BJ6: 46356 | BK6: 46387 | BO6: =Desempeño_Financiero!$B$1 -> 46112 | BP6: =BO6 -> 46112 | BQ6: =EOMONTH(BO6,-1) -> 46081 | BR6: =EOMONTH(BO6,-12) -> 45747 | BS6: =EOMONTH(BO6,-24) -> 45382 | BT6: =EOMONTH(BO6,-36) -> 45016 | BW6: =BO6 -> 46112 | BX6: =BP6 -> 46112 | BY6: =BQ6 -> 46081 | BZ6: =BR6 -> 45747 | CA6: =BS6 -> 45382 | CB6: =BT6 -> 45016
A8: SALDO_FDP | C8: Vigente | D8: =Renta_Alta!D8+Masivo!D8+Consumo_Inicial!D8 -> 9306979.2 | E8: =Renta_Alta!E8+Masivo!E8+Consumo_Inicial!E8 -> 9343837 | F8: =Renta_Alta!F8+Masivo!F8+Consumo_Inicial!F8 -> 9379816.8 | G8: =Renta_Alta!G8+Masivo!G8+Consumo_Inicial!G8 -> 9428101.8 | H8: =Renta_Alta!H8+Masivo!H8+Consumo_Inicial!H8 -> 9463606.7 | I8: =Renta_Alta!I8+Masivo!I8+Consumo_Inicial!I8 -> 9512554.1 | J8: =Renta_Alta!J8+Masivo!J8+Consumo_Inicial!J8 -> 9520520.3 | K8: =Renta_Alta!K8+Masivo!K8+Consumo_Inicial!K8 -> 9581896.8 | ... BK8: =Renta_Alta!BK8+Masivo!BK8+Consumo_Inicial!BK8 -> 12221963 | BO8: =_xlfn.XLOOKUP(BO$6,$D$6:$BM$6,$D8:$BM8,,0,1) -> 11525777 | BP8: =_xlfn.XLOOKUP(BP$6,$D$6:$BM$6,$D8:$BM8,,0,-1) -> 11438229 | BQ8: =_xlfn.XLOOKUP(BQ$6,$D$6:$BM$6,$D8:$BM8,,0,1) -> 11478076 | BR8: =_xlfn.XLOOKUP(BR$6,$D$6:$BM$6,$D8:$BM8,,0,1) -> 10587478 | BS8: =_xlfn.XLOOKUP(BS$6,$D$6:$BM$6,$D8:$BM8,,0,1) -> 9915549.8 | BT8: =_xlfn.XLOOKUP(BT$6,$D$6:$BM$6,$D8:$BM8,,0,1) -> 9379816.8
A9: SALDO_FDP | C9: Refinanciado | D9: =Renta_Alta!D9+Masivo!D9+Consumo_Inicial!D9 -> 34450.126 | E9: =Renta_Alta!E9+Masivo!E9+Consumo_Inicial!E9 -> 33830.323 | F9: =Renta_Alta!F9+Masivo!F9+Consumo_Inicial!F9 -> 36652.88 | G9: =Renta_Alta!G9+Masivo!G9+Consumo_Inicial!G9 -> 33483.419 | H9: =Renta_Alta!H9+Masivo!H9+Consumo_Inicial!H9 -> 32226.636 | I9: =Renta_Alta!I9+Masivo!I9+Consumo_Inicial!I9 -> 32526.535 | J9: =Renta_Alta!J9+Masivo!J9+Consumo_Inicial!J9 -> 32175.432 | K9: =Renta_Alta!K9+Masivo!K9+Consumo_Inicial!K9 -> 31298.089 | ... BK9: =Renta_Alta!BK9+Masivo!BK9+Consumo_Inicial!BK9 -> 25869.388 | BO9: =_xlfn.XLOOKUP(BO$6,$D$6:$BM$6,$D9:$BM9,,0,1) -> 34203.92 | BP9: =_xlfn.XLOOKUP(BP$6,$D$6:$BM$6,$D9:$BM9,,0,-1) -> 29770.187 | BQ9: =_xlfn.XLOOKUP(BQ$6,$D$6:$BM$6,$D9:$BM9,,0,1) -> 32640.44 | BR9: =_xlfn.XLOOKUP(BR$6,$D$6:$BM$6,$D9:$BM9,,0,1) -> 29921.003 | BS9: =_xlfn.XLOOKUP(BS$6,$D$6:$BM$6,$D9:$BM9,,0,1) -> 31857.707 | BT9: =_xlfn.XLOOKUP(BT$6,$D$6:$BM$6,$D9:$BM9,,0,1) -> 36652.88
A10: SALDO_FDP | C10: Vencido y Judicial | D10: =Renta_Alta!D10+Masivo!D10+Consumo_Inicial!D10 -> 246802.44 | E10: =Renta_Alta!E10+Masivo!E10+Consumo_Inicial!E10 -> 248460.62 | F10: =Renta_Alta!F10+Masivo!F10+Consumo_Inicial!F10 -> 249639.32 | G10: =Renta_Alta!G10+Masivo!G10+Consumo_Inicial!G10 -> 253224.17 | H10: =Renta_Alta!H10+Masivo!H10+Consumo_Inicial!H10 -> 265429.48 | I10: =Renta_Alta!I10+Masivo!I10+Consumo_Inicial!I10 -> 265953.3 | J10: =Renta_Alta!J10+Masivo!J10+Consumo_Inicial!J10 -> 266312.9 | K10: =Renta_Alta!K10+Masivo!K10+Consumo_Inicial!K10 -> 270309.73 | ... BK10: =Renta_Alta!BK10+Masivo!BK10+Consumo_Inicial!BK10 -> 391039.79 | BO10: =_xlfn.XLOOKUP(BO$6,$D$6:$BM$6,$D10:$BM10,,0,1) -> 346980.86 | BP10: =_xlfn.XLOOKUP(BP$6,$D$6:$BM$6,$D10:$BM10,,0,-1) -> 375811.31 | BQ10: =_xlfn.XLOOKUP(BQ$6,$D$6:$BM$6,$D10:$BM10,,0,1) -> 338634.42 | BR10: =_xlfn.XLOOKUP(BR$6,$D$6:$BM$6,$D10:$BM10,,0,1) -> 343769.54 | BS10: =_xlfn.XLOOKUP(BS$6,$D$6:$BM$6,$D10:$BM10,,0,1) -> 294205.11 | BT10: =_xlfn.XLOOKUP(BT$6,$D$6:$BM$6,$D10:$BM10,,0,1) -> 249639.32
C11: Saldo FdP | D11: =SUM(D8:D10) -> 9588231.8 | E11: =SUM(E8:E10) -> 9626127.9 | F11: =SUM(F8:F10) -> 9666109 | G11: =SUM(G8:G10) -> 9714809.4 | H11: =SUM(H8:H10) -> 9761262.8 | I11: =SUM(I8:I10) -> 9811033.9 | J11: =SUM(J8:J10) -> 9819008.6 | K11: =SUM(K8:K10) -> 9883504.6 | ... BK11: =SUM(BK8:BK10) -> 12638872 | BO11: =SUM(BO8:BO10) -> 11906961 | BP11: =SUM(BP8:BP10) -> 11843810 | BQ11: =SUM(BQ8:BQ10) -> 11849351 | BR11: =SUM(BR8:BR10) -> 10961168 | BS11: =SUM(BS8:BS10) -> 10241613 | BT11: =SUM(BT8:BT10) -> 9666109
D12: =[1]Base_Evolutivo!BE166-D11 -> 0.00070990063 | E12: =[1]Base_Evolutivo!BF166-E11 -> -0.00050620176 | F12: =[1]Base_Evolutivo!BG166-F11 -> -0.00017984025 | G12: =[1]Base_Evolutivo!BH166-G11 -> 0.00057735108 | H12: =[1]Base_Evolutivo!BI166-H11 -> 0.00041825883 | I12: =[1]Base_Evolutivo!BJ166-I11 -> 2.16607e-05 | J12: =[1]Base_Evolutivo!BK166-J11 -> 0.00019318238 | K12: =[1]Base_Evolutivo!BL166-K11 -> -0.00086499751 | ... BK12: =[1]Base_Evolutivo!DL166-BK11 -> -12638872
A14: SALDO_PROM | C14: Vigente | D14: =Renta_Alta!D14+Masivo!D14+Consumo_Inicial!D14 -> 9257226.1 | E14: =Renta_Alta!E14+Masivo!E14+Consumo_Inicial!E14 -> 9300808 | F14: =Renta_Alta!F14+Masivo!F14+Consumo_Inicial!F14 -> 9331212.8 | G14: =Renta_Alta!G14+Masivo!G14+Consumo_Inicial!G14 -> 9371473.2 | H14: =Renta_Alta!H14+Masivo!H14+Consumo_Inicial!H14 -> 9412260.9 | I14: =Renta_Alta!I14+Masivo!I14+Consumo_Inicial!I14 -> 9461220.7 | J14: =Renta_Alta!J14+Masivo!J14+Consumo_Inicial!J14 -> 9506413.6 | K14: =Renta_Alta!K14+Masivo!K14+Consumo_Inicial!K14 -> 9526935.6 | ... BK14: =Renta_Alta!BK14+Masivo!BK14+Consumo_Inicial!BK14 -> 12122645 | BO14: =IFERROR(AVERAGEIFS($D14:$BM14,$D$6:$BM$6,">="&BO$2,$D$6:$BM$6,"<="&BO$6,$D$5:$BM$5,BO$5,$D14:$BM14,"<>0"),0) -> 11375136 | BP14: =IFERROR(AVERAGEIFS($D14:$BM14,$D$6:$BM$6,">="&BP$2,$D$6:$BM$6,"<="&BP$6,$D$5:$BM$5,BP$5,$D14:$BM14,"<>0"),0) -> 11296486 | BQ14: =IFERROR(AVERAGEIFS($D14:$BM14,$D$6:$BM$6,">="&BQ$2,$D$6:$BM$6,"<="&BQ$6,$D$5:$BM$5,BQ$5,$D14:$BM14,"<>0"),0) -> 11336870 | BR14: =IFERROR(AVERAGEIFS($D14:$BM14,$D$6:$BM$6,">="&BR$2,$D$6:$BM$6,"<="&BR$6,$D$5:$BM$5,BR$5,$D14:$BM14,"<>0"),0) -> 10480867 | BS14: =IFERROR(AVERAGEIFS($D14:$BM14,$D$6:$BM$6,">="&BS$2,$D$6:$BM$6,"<="&BS$6,$D$5:$BM$5,BS$5,$D14:$BM14,"<>0"),0) -> 9799459.6 | BT14: =IFERROR(AVERAGEIFS($D14:$BM14,$D$6:$BM$6,">="&BT$2,$D$6:$BM$6,"<="&BT$6,$D$5:$BM$5,BT$5,$D14:$BM14,"<>0"),0) -> 9296415.6 | BW14: =SUMIFS($D14:$BM14,$D$6:$BM$6,">="&BO$2,$D$6:$BM$6,"<="&BO$6,$D$5:$BM$5,BO$5) -> 34125409 | BX14: =SUMIFS($D14:$BM14,$D$6:$BM$6,">="&BP$2,$D$6:$BM$6,"<="&BP$6,$D$5:$BM$5,BP$5) -> 33889459 | BY14: =SUMIFS($D14:$BM14,$D$6:$BM$6,">="&BQ$2,$D$6:$BM$6,"<="&BQ$6,$D$5:$BM$5,BQ$5) -> 22673740 | BZ14: =SUMIFS($D14:$BM14,$D$6:$BM$6,">="&BR$2,$D$6:$BM$6,"<="&BR$6,$D$5:$BM$5,BR$5) -> 31442602 | CA14: =SUMIFS($D14:$BM14,$D$6:$BM$6,">="&BS$2,$D$6:$BM$6,"<="&BS$6,$D$5:$BM$5,BS$5) -> 29398379 | CB14: =SUMIFS($D14:$BM14,$D$6:$BM$6,">="&BT$2,$D$6:$BM$6,"<="&BT$6,$D$5:$BM$5,BT$5) -> 27889247
A15: SALDO_PROM | C15: Refinanciado | D15: =Renta_Alta!D15+Masivo!D15+Consumo_Inicial!D15 -> 33664.688 | E15: =Renta_Alta!E15+Masivo!E15+Consumo_Inicial!E15 -> 33016.354 | F15: =Renta_Alta!F15+Masivo!F15+Consumo_Inicial!F15 -> 33680.968 | G15: =Renta_Alta!G15+Masivo!G15+Consumo_Inicial!G15 -> 35462.042 | H15: =Renta_Alta!H15+Masivo!H15+Consumo_Inicial!H15 -> 32168.942 | I15: =Renta_Alta!I15+Masivo!I15+Consumo_Inicial!I15 -> 31816.475 | J15: =Renta_Alta!J15+Masivo!J15+Consumo_Inicial!J15 -> 31950.15 | K15: =Renta_Alta!K15+Masivo!K15+Consumo_Inicial!K15 -> 31049.962 | ... BK15: =Renta_Alta!BK15+Masivo!BK15+Consumo_Inicial!BK15 -> 25645.238 | BO15: =IFERROR(AVERAGEIFS($D15:$BM15,$D$6:$BM$6,">="&BO$2,$D$6:$BM$6,"<="&BO$6,$D$5:$BM$5,BO$5,$D15:$BM15,"<>0"),0) -> 32543.543 | BP15: =IFERROR(AVERAGEIFS($D15:$BM15,$D$6:$BM$6,">="&BP$2,$D$6:$BM$6,"<="&BP$6,$D$5:$BM$5,BP$5,$D15:$BM15,"<>0"),0) -> 29423.438 | BQ15: =IFERROR(AVERAGEIFS($D15:$BM15,$D$6:$BM$6,">="&BQ$2,$D$6:$BM$6,"<="&BQ$6,$D$5:$BM$5,BQ$5,$D15:$BM15,"<>0"),0) -> 31968.95 | BR15: =IFERROR(AVERAGEIFS($D15:$BM15,$D$6:$BM$6,">="&BR$2,$D$6:$BM$6,"<="&BR$6,$D$5:$BM$5,BR$5,$D15:$BM15,"<>0"),0) -> 29449.772 | BS15: =IFERROR(AVERAGEIFS($D15:$BM15,$D$6:$BM$6,">="&BS$2,$D$6:$BM$6,"<="&BS$6,$D$5:$BM$5,BS$5,$D15:$BM15,"<>0"),0) -> 31300.342 | BT15: =IFERROR(AVERAGEIFS($D15:$BM15,$D$6:$BM$6,">="&BT$2,$D$6:$BM$6,"<="&BT$6,$D$5:$BM$5,BT$5,$D15:$BM15,"<>0"),0) -> 33454.003 | BW15: =SUMIFS($D15:$BM15,$D$6:$BM$6,">="&BO$2,$D$6:$BM$6,"<="&BO$6,$D$5:$BM$5,BO$5) -> 97630.63 | BX15: =SUMIFS($D15:$BM15,$D$6:$BM$6,">="&BP$2,$D$6:$BM$6,"<="&BP$6,$D$5:$BM$5,BP$5) -> 88270.314 | BY15: =SUMIFS($D15:$BM15,$D$6:$BM$6,">="&BQ$2,$D$6:$BM$6,"<="&BQ$6,$D$5:$BM$5,BQ$5) -> 63937.9 | BZ15: =SUMIFS($D15:$BM15,$D$6:$BM$6,">="&BR$2,$D$6:$BM$6,"<="&BR$6,$D$5:$BM$5,BR$5) -> 88349.315 | CA15: =SUMIFS($D15:$BM15,$D$6:$BM$6,">="&BS$2,$D$6:$BM$6,"<="&BS$6,$D$5:$BM$5,BS$5) -> 93901.025 | CB15: =SUMIFS($D15:$BM15,$D$6:$BM$6,">="&BT$2,$D$6:$BM$6,"<="&BT$6,$D$5:$BM$5,BT$5) -> 100362.01
A16: SALDO_PROM | C16: Vencido y Judicial | D16: =Renta_Alta!D16+Masivo!D16+Consumo_Inicial!D16 -> 250475.73 | E16: =Renta_Alta!E16+Masivo!E16+Consumo_Inicial!E16 -> 250988.21 | F16: =Renta_Alta!F16+Masivo!F16+Consumo_Inicial!F16 -> 256054.8 | G16: =Renta_Alta!G16+Masivo!G16+Consumo_Inicial!G16 -> 258747.32 | H16: =Renta_Alta!H16+Masivo!H16+Consumo_Inicial!H16 -> 266957.02 | I16: =Renta_Alta!I16+Masivo!I16+Consumo_Inicial!I16 -> 269070.22 | J16: =Renta_Alta!J16+Masivo!J16+Consumo_Inicial!J16 -> 264874.7 | K16: =Renta_Alta!K16+Masivo!K16+Consumo_Inicial!K16 -> 270189.03 | ... BK16: =Renta_Alta!BK16+Masivo!BK16+Consumo_Inicial!BK16 -> 387844.3 | BO16: =IFERROR(AVERAGEIFS($D16:$BM16,$D$6:$BM$6,">="&BO$2,$D$6:$BM$6,"<="&BO$6,$D$5:$BM$5,BO$5,$D16:$BM16,"<>0"),0) -> 358023.76 | BP16: =IFERROR(AVERAGEIFS($D16:$BM16,$D$6:$BM$6,">="&BP$2,$D$6:$BM$6,"<="&BP$6,$D$5:$BM$5,BP$5,$D16:$BM16,"<>0"),0) -> 369759.67 | BQ16: =IFERROR(AVERAGEIFS($D16:$BM16,$D$6:$BM$6,">="&BQ$2,$D$6:$BM$6,"<="&BQ$6,$D$5:$BM$5,BQ$5,$D16:$BM16,"<>0"),0) -> 360564.81 | BR16: =IFERROR(AVERAGEIFS($D16:$BM16,$D$6:$BM$6,">="&BR$2,$D$6:$BM$6,"<="&BR$6,$D$5:$BM$5,BR$5,$D16:$BM16,"<>0"),0) -> 340976.31 | BS16: =IFERROR(AVERAGEIFS($D16:$BM16,$D$6:$BM$6,">="&BS$2,$D$6:$BM$6,"<="&BS$6,$D$5:$BM$5,BS$5,$D16:$BM16,"<>0"),0) -> 304066.03 | BT16: =IFERROR(AVERAGEIFS($D16:$BM16,$D$6:$BM$6,">="&BT$2,$D$6:$BM$6,"<="&BT$6,$D$5:$BM$5,BT$5,$D16:$BM16,"<>0"),0) -> 252506.24 | BW16: =SUMIFS($D16:$BM16,$D$6:$BM$6,">="&BO$2,$D$6:$BM$6,"<="&BO$6,$D$5:$BM$5,BO$5) -> 1074071.3 | BX16: =SUMIFS($D16:$BM16,$D$6:$BM$6,">="&BP$2,$D$6:$BM$6,"<="&BP$6,$D$5:$BM$5,BP$5) -> 1109279 | BY16: =SUMIFS($D16:$BM16,$D$6:$BM$6,">="&BQ$2,$D$6:$BM$6,"<="&BQ$6,$D$5:$BM$5,BQ$5) -> 721129.62 | BZ16: =SUMIFS($D16:$BM16,$D$6:$BM$6,">="&BR$2,$D$6:$BM$6,"<="&BR$6,$D$5:$BM$5,BR$5) -> 1022928.9 | CA16: =SUMIFS($D16:$BM16,$D$6:$BM$6,">="&BS$2,$D$6:$BM$6,"<="&BS$6,$D$5:$BM$5,BS$5) -> 912198.1 | CB16: =SUMIFS($D16:$BM16,$D$6:$BM$6,">="&BT$2,$D$6:$BM$6,"<="&BT$6,$D$5:$BM$5,BT$5) -> 757518.73
C17: Saldo Prom | D17: =SUM(D14:D16) -> 9541366.5 | E17: =SUM(E14:E16) -> 9584812.6 | F17: =SUM(F14:F16) -> 9620948.6 | G17: =SUM(G14:G16) -> 9665682.6 | H17: =SUM(H14:H16) -> 9711386.8 | I17: =SUM(I14:I16) -> 9762107.4 | J17: =SUM(J14:J16) -> 9803238.4 | K17: =SUM(K14:K16) -> 9828174.6 | ... BK17: =SUM(BK14:BK16) -> 12536134 | BO17: =SUM(BO14:BO16) -> 11765704 | BP17: =SUM(BP14:BP16) -> 11695669 | BQ17: =SUM(BQ14:BQ16) -> 11729404 | BR17: =SUM(BR14:BR16) -> 10851293 | BS17: =SUM(BS14:BS16) -> 10134826 | BT17: =SUM(BT14:BT16) -> 9582375.9 | BW17: =SUM(BW14:BW16) -> 35297111 | BX17: =SUM(BX14:BX16) -> 35087008 | BY17: =SUM(BY14:BY16) -> 23458807 | BZ17: =SUM(BZ14:BZ16) -> 32553880 | CA17: =SUM(CA14:CA16) -> 30404478 | CB17: =SUM(CB14:CB16) -> 28747128
D18: =[1]Base_Evolutivo!BE322-D17 -> -8.578971e-05 | E18: =[1]Base_Evolutivo!BF322-E17 -> 0.00020773336 | F18: =[1]Base_Evolutivo!BG322-F17 -> -0.0005581975 | G18: =[1]Base_Evolutivo!BH322-G17 -> 0.00067692064 | H18: =[1]Base_Evolutivo!BI322-H17 -> 0.0005341582 | I18: =[1]Base_Evolutivo!BJ322-I17 -> 0.0003280025 | J18: =[1]Base_Evolutivo!BK322-J17 -> 0.00024420023 | K18: =[1]Base_Evolutivo!BL322-K17 -> -0.00022026151 | ... BK18: =[1]Base_Evolutivo!DL322-BK17 -> -12536134
C20: Vigente | D20: =IFERROR(((1+D38/D14)^(360/D$3))-1,0) -> 0.070556703 | E20: =IFERROR(((1+E38/E14)^(360/E$3))-1,0) -> 0.070993744 | F20: =IFERROR(((1+F38/F14)^(360/F$3))-1,0) -> 0.071198038 | G20: =IFERROR(((1+G38/G14)^(360/G$3))-1,0) -> 0.071633161 | H20: =IFERROR(((1+H38/H14)^(360/H$3))-1,0) -> 0.071853462 | I20: =IFERROR(((1+I38/I14)^(360/I$3))-1,0) -> 0.07185422 | J20: =IFERROR(((1+J38/J14)^(360/J$3))-1,0) -> 0.072268829 | K20: =IFERROR(((1+K38/K14)^(360/K$3))-1,0) -> 0.072101273 | ... BK20: =IFERROR(((1+BK38/BK14)^(360/BK$3))-1,0) -> 0.074236709 | BO20: =IFERROR(((1+BO38/BW14)^(360/BO$3))-1,0) -> 0.07450647 | BP20: =IFERROR(((1+BP38/BX14)^(360/BP$3))-1,0) -> 0.073578815 | BQ20: =IFERROR(((1+BQ38/BY14)^(360/BQ$3))-1,0) -> 0.07457484 | BR20: =IFERROR(((1+BR38/BZ14)^(360/BR$3))-1,0) -> 0.074039433 | BS20: =IFERROR(((1+BS38/CA14)^(360/BS$3))-1,0) -> 0.073188903 | BT20: =IFERROR(((1+BT38/CB14)^(360/BT$3))-1,0) -> 0.070913737
C21: Refinanciado | D21: =IFERROR(((1+D39/D15)^(360/D$3))-1,0) -> 0 | E21: =IFERROR(((1+E39/E15)^(360/E$3))-1,0) -> 0 | F21: =IFERROR(((1+F39/F15)^(360/F$3))-1,0) -> 0 | G21: =IFERROR(((1+G39/G15)^(360/G$3))-1,0) -> 0 | H21: =IFERROR(((1+H39/H15)^(360/H$3))-1,0) -> 0 | I21: =IFERROR(((1+I39/I15)^(360/I$3))-1,0) -> 0 | J21: =IFERROR(((1+J39/J15)^(360/J$3))-1,0) -> 0 | K21: =IFERROR(((1+K39/K15)^(360/K$3))-1,0) -> 0 | ... BK21: =IFERROR(((1+BK39/BK15)^(360/BK$3))-1,0) -> 0 | BO21: =IFERROR(((1+BO39/BW15)^(360/BO$3))-1,0) -> 0 | BP21: =IFERROR(((1+BP39/BX15)^(360/BP$3))-1,0) -> 0 | BQ21: =IFERROR(((1+BQ39/BY15)^(360/BQ$3))-1,0) -> 0 | BR21: =IFERROR(((1+BR39/BZ15)^(360/BR$3))-1,0) -> 0 | BS21: =IFERROR(((1+BS39/CA15)^(360/BS$3))-1,0) -> 0 | BT21: =IFERROR(((1+BT39/CB15)^(360/BT$3))-1,0) -> 0
C22: Vencido y Judicial | D22: =IFERROR(((1+D40/D16)^(360/D$3))-1,0) -> 0.088464748 | E22: =IFERROR(((1+E40/E16)^(360/E$3))-1,0) -> 0.084267311 | F22: =IFERROR(((1+F40/F16)^(360/F$3))-1,0) -> 0.106308 | G22: =IFERROR(((1+G40/G16)^(360/G$3))-1,0) -> 0.082116297 | H22: =IFERROR(((1+H40/H16)^(360/H$3))-1,0) -> 0.097043008 | I22: =IFERROR(((1+I40/I16)^(360/I$3))-1,0) -> 0.10549496 | J22: =IFERROR(((1+J40/J16)^(360/J$3))-1,0) -> 0.10728553 | K22: =IFERROR(((1+K40/K16)^(360/K$3))-1,0) -> 0.096635794 | ... BK22: =IFERROR(((1+BK40/BK16)^(360/BK$3))-1,0) -> 0.12575293 | BO22: =IFERROR(((1+BO40/BW16)^(360/BO$3))-1,0) -> 0.10159883 | BP22: =IFERROR(((1+BP40/BX16)^(360/BP$3))-1,0) -> 0.11974894 | BQ22: =IFERROR(((1+BQ40/BY16)^(360/BQ$3))-1,0) -> 0.096260819 | BR22: =IFERROR(((1+BR40/BZ16)^(360/BR$3))-1,0) -> 0.10408722 | BS22: =IFERROR(((1+BS40/CA16)^(360/BS$3))-1,0) -> 0.10317897 | BT22: =IFERROR(((1+BT40/CB16)^(360/BT$3))-1,0) -> 0.093382026
C23: Tasa Implicita | D23: =IFERROR(((1+D41/D17)^(360/D$3))-1,0) -> 0.070766508 | E23: =IFERROR(((1+E41/E17)^(360/E$3))-1,0) -> 0.071087002 | F23: =IFERROR(((1+F41/F17)^(360/F$3))-1,0) -> 0.071861786 | G23: =IFERROR(((1+G41/G17)^(360/G$3))-1,0) -> 0.071641316 | H23: =IFERROR(((1+H41/H17)^(360/H$3))-1,0) -> 0.072293022 | I23: =IFERROR(((1+I41/I17)^(360/I$3))-1,0) -> 0.072526862 | J23: =IFERROR(((1+J41/J17)^(360/J$3))-1,0) -> 0.072958204 | K23: =IFERROR(((1+K41/K17)^(360/K$3))-1,0) -> 0.072533782 | ... BK23: =IFERROR(((1+BK41/BK17)^(360/BK$3))-1,0) -> 0.075640583 | BO23: =IFERROR(((1+BO41/BW17)^(360/BO$3))-1,0) -> 0.075108716 | BP23: =IFERROR(((1+BP41/BX17)^(360/BP$3))-1,0) -> 0.074819951 | BQ23: =IFERROR(((1+BQ41/BY17)^(360/BQ$3))-1,0) -> 0.075025428 | BR23: =IFERROR(((1+BR41/BZ17)^(360/BR$3))-1,0) -> 0.074764361 | BS23: =IFERROR(((1+BS41/CA17)^(360/BS$3))-1,0) -> 0.073844122 | BT23: =IFERROR(((1+BT41/CB17)^(360/BT$3))-1,0) -> 0.071244808
D24: =+'[1]Desempeño_Financiero (Evol)-Seg'!BE442-D23 -> 4.5565773e-12 | E24: =+'[1]Desempeño_Financiero (Evol)-Seg'!BF442-E23 -> -1.9890756e-12 | F24: =+'[1]Desempeño_Financiero (Evol)-Seg'!BG442-F23 -> 6.7339467e-12 | G24: =+'[1]Desempeño_Financiero (Evol)-Seg'!BH442-G23 -> 2.3074875e-12 | H24: =+'[1]Desempeño_Financiero (Evol)-Seg'!BI442-H23 -> 3.6333159e-12 | I24: =+'[1]Desempeño_Financiero (Evol)-Seg'!BJ442-I23 -> -1.0120571e-11 | J24: =+'[1]Desempeño_Financiero (Evol)-Seg'!BK442-J23 -> -9.861445e-12 | K24: =+'[1]Desempeño_Financiero (Evol)-Seg'!BL442-K23 -> 1.0227375e-12 | ... AS24: =+'[1]Desempeño_Financiero (Evol)-Seg'!CT442-AS23 -> 0
C26: Vigente | D26: =-IFERROR(((1-D44/D14)^(360/D$4))-1,0) -> -0.049635424 | E26: =-IFERROR(((1-E44/E14)^(360/E$4))-1,0) -> -0.049978926 | F26: =-IFERROR(((1-F44/F14)^(360/F$4))-1,0) -> -0.050379357 | G26: =-IFERROR(((1-G44/G14)^(360/G$4))-1,0) -> -0.050860042 | H26: =-IFERROR(((1-H44/H14)^(360/H$4))-1,0) -> -0.051126729 | I26: =-IFERROR(((1-I44/I14)^(360/I$4))-1,0) -> -0.051459916 | J26: =-IFERROR(((1-J44/J14)^(360/J$4))-1,0) -> -0.051756526 | K26: =-IFERROR(((1-K44/K14)^(360/K$4))-1,0) -> -0.051952891 | ... BK26: =-IFERROR(((1-BK44/BK14)^(360/BK$4))-1,0) -> -0.056630361 | BO26: =-IFERROR(((1-BO44/BW14)^(360/BO$4))-1,0) -> -0.056239683 | BP26: =-IFERROR(((1-BP44/BX14)^(360/BP$4))-1,0) -> -0.056482252 | BQ26: =-IFERROR(((1-BQ44/BY14)^(360/BQ$4))-1,0) -> -0.05624434 | BR26: =-IFERROR(((1-BR44/BZ14)^(360/BR$4))-1,0) -> -0.05550907 | BS26: =-IFERROR(((1-BS44/CA14)^(360/BS$4))-1,0) -> -0.053367564 | BT26: =-IFERROR(((1-BT44/CB14)^(360/BT$4))-1,0) -> -0.049998844
C27: Refinanciado | D27: =-IFERROR(((1-D45/D15)^(360/D$4))-1,0) -> -0.049774856 | E27: =-IFERROR(((1-E45/E15)^(360/E$4))-1,0) -> -0.04915199 | F27: =-IFERROR(((1-F45/F15)^(360/F$4))-1,0) -> -0.049487574 | G27: =-IFERROR(((1-G45/G15)^(360/G$4))-1,0) -> -0.049914999 | H27: =-IFERROR(((1-H45/H15)^(360/H$4))-1,0) -> -0.050471537 | I27: =-IFERROR(((1-I45/I15)^(360/I$4))-1,0) -> -0.050609898 | J27: =-IFERROR(((1-J45/J15)^(360/J$4))-1,0) -> -0.050602731 | K27: =-IFERROR(((1-K45/K15)^(360/K$4))-1,0) -> -0.050042799 | ... BK27: =-IFERROR(((1-BK45/BK15)^(360/BK$4))-1,0) -> -0.072265954 | BO27: =-IFERROR(((1-BO45/BW15)^(360/BO$4))-1,0) -> -0.054758314 | BP27: =-IFERROR(((1-BP45/BX15)^(360/BP$4))-1,0) -> -0.057133437 | BQ27: =-IFERROR(((1-BQ45/BY15)^(360/BQ$4))-1,0) -> -0.054570349 | BR27: =-IFERROR(((1-BR45/BZ15)^(360/BR$4))-1,0) -> -0.052077723 | BS27: =-IFERROR(((1-BS45/CA15)^(360/BS$4))-1,0) -> -0.04998486 | BT27: =-IFERROR(((1-BT45/CB15)^(360/BT$4))-1,0) -> -0.049473512
C28: Vencido y Judicial | D28: =-IFERROR(((1-D46/D16)^(360/D$4))-1,0) -> -0.051621537 | E28: =-IFERROR(((1-E46/E16)^(360/E$4))-1,0) -> -0.051707903 | F28: =-IFERROR(((1-F46/F16)^(360/F$4))-1,0) -> -0.051812921 | G28: =-IFERROR(((1-G46/G16)^(360/G$4))-1,0) -> -0.051979734 | H28: =-IFERROR(((1-H46/H16)^(360/H$4))-1,0) -> -0.051971154 | I28: =-IFERROR(((1-I46/I16)^(360/I$4))-1,0) -> -0.051615817 | J28: =-IFERROR(((1-J46/J16)^(360/J$4))-1,0) -> -0.051380332 | K28: =-IFERROR(((1-K46/K16)^(360/K$4))-1,0) -> -0.051678709 | ... BK28: =-IFERROR(((1-BK46/BK16)^(360/BK$4))-1,0) -> -0.058254451 | BO28: =-IFERROR(((1-BO46/BW16)^(360/BO$4))-1,0) -> -0.054860101 | BP28: =-IFERROR(((1-BP46/BX16)^(360/BP$4))-1,0) -> -0.055983092 | BQ28: =-IFERROR(((1-BQ46/BY16)^(360/BQ$4))-1,0) -> -0.054855937 | BR28: =-IFERROR(((1-BR46/BZ16)^(360/BR$4))-1,0) -> -0.053122545 | BS28: =-IFERROR(((1-BS46/CA16)^(360/BS$4))-1,0) -> -0.052963824 | BT28: =-IFERROR(((1-BT46/CB16)^(360/BT$4))-1,0) -> -0.051714841
C29: Tasa FTP | D29: =-IFERROR(((1-D47/D17)^(360/D$4))-1,0) -> -0.04968801 | E29: =-IFERROR(((1-E47/E17)^(360/E$4))-1,0) -> -0.050021318 | F29: =-IFERROR(((1-F47/F17)^(360/F$4))-1,0) -> -0.050414363 | G29: =-IFERROR(((1-G47/G17)^(360/G$4))-1,0) -> -0.050886533 | H29: =-IFERROR(((1-H47/H17)^(360/H$4))-1,0) -> -0.051147762 | I29: =-IFERROR(((1-I47/I17)^(360/I$4))-1,0) -> -0.051461441 | J29: =-IFERROR(((1-J47/J17)^(360/J$4))-1,0) -> -0.051742597 | K29: =-IFERROR(((1-K47/K17)^(360/K$4))-1,0) -> -0.051939313 | ... BK29: =-IFERROR(((1-BK47/BK17)^(360/BK$4))-1,0) -> -0.056712346 | BO29: =-IFERROR(((1-BO47/BW17)^(360/BO$4))-1,0) -> -0.056193579 | BP29: =-IFERROR(((1-BP47/BX17)^(360/BP$4))-1,0) -> -0.056468105 | BQ29: =-IFERROR(((1-BQ47/BY17)^(360/BQ$4))-1,0) -> -0.05619707 | BR29: =-IFERROR(((1-BR47/BZ17)^(360/BR$4))-1,0) -> -0.055424678 | BS29: =-IFERROR(((1-BS47/CA17)^(360/BS$4))-1,0) -> -0.053344987 | BT29: =-IFERROR(((1-BT47/CB17)^(360/BT$4))-1,0) -> -0.050042195
D30: =+'[1]Desempeño_Financiero (Evol)-Seg'!BE586-D29 -> -9.1038288e-15 | E30: =+'[1]Desempeño_Financiero (Evol)-Seg'!BF586-E29 -> 6.7723605e-13 | F30: =+'[1]Desempeño_Financiero (Evol)-Seg'!BG586-F29 -> -3.5127456e-12 | G30: =+'[1]Desempeño_Financiero (Evol)-Seg'!BH586-G29 -> 3.5171865e-12 | H30: =+'[1]Desempeño_Financiero (Evol)-Seg'!BI586-H29 -> 3.4230396e-12 | I30: =+'[1]Desempeño_Financiero (Evol)-Seg'!BJ586-I29 -> 1.7679191e-12 | J30: =+'[1]Desempeño_Financiero (Evol)-Seg'!BK586-J29 -> 9.8809849e-13 | K30: =+'[1]Desempeño_Financiero (Evol)-Seg'!BL586-K29 -> -1.2911894e-12 | ... AS30: =+'[1]Desempeño_Financiero (Evol)-Seg'!CT586-AS29 -> 0
C32: Vigente | D32: =D20+D26 -> 0.020921279 | E32: =E20+E26 -> 0.021014818 | F32: =F20+F26 -> 0.020818681 | G32: =G20+G26 -> 0.020773119 | H32: =H20+H26 -> 0.020726733 | I32: =I20+I26 -> 0.020394305 | J32: =J20+J26 -> 0.020512303 | K32: =K20+K26 -> 0.020148382 | ... BK32: =BK20+BK26 -> 0.017606348 | BO32: =BO20+BO26 -> 0.018266787 | BP32: =BP20+BP26 -> 0.017096563 | BQ32: =BQ20+BQ26 -> 0.018330499 | BR32: =BR20+BR26 -> 0.018530363 | BS32: =BS20+BS26 -> 0.019821339 | BT32: =BT20+BT26 -> 0.020914892
C33: Refinanciado | D33: =D21+D27 -> -0.049774856 | E33: =E21+E27 -> -0.04915199 | F33: =F21+F27 -> -0.049487574 | G33: =G21+G27 -> -0.049914999 | H33: =H21+H27 -> -0.050471537 | I33: =I21+I27 -> -0.050609898 | J33: =J21+J27 -> -0.050602731 | K33: =K21+K27 -> -0.050042799 | ... BK33: =BK21+BK27 -> -0.072265954 | BO33: =BO21+BO27 -> -0.054758314 | BP33: =BP21+BP27 -> -0.057133437 | BQ33: =BQ21+BQ27 -> -0.054570349 | BR33: =BR21+BR27 -> -0.052077723 | BS33: =BS21+BS27 -> -0.04998486 | BT33: =BT21+BT27 -> -0.049473512
C34: Vencido y Judicial | D34: =D22+D28 -> 0.036843211 | E34: =E22+E28 -> 0.032559408 | F34: =F22+F28 -> 0.054495077 | G34: =G22+G28 -> 0.030136563 | H34: =H22+H28 -> 0.045071853 | I34: =I22+I28 -> 0.053879145 | J34: =J22+J28 -> 0.0559052 | K34: =K22+K28 -> 0.044957086 | ... BK34: =BK22+BK28 -> 0.067498479 | BO34: =BO22+BO28 -> 0.046738726 | BP34: =BP22+BP28 -> 0.063765852 | BQ34: =BQ22+BQ28 -> 0.041404881 | BR34: =BR22+BR28 -> 0.050964675 | BS34: =BS22+BS28 -> 0.050215145 | BT34: =BT22+BT28 -> 0.041667186
C35: Spread | D35: =D23+D29 -> 0.021078497 | E35: =E23+E29 -> 0.021065683 | F35: =F23+F29 -> 0.021447423 | G35: =G23+G29 -> 0.020754783 | H35: =H23+H29 -> 0.02114526 | I35: =I23+I29 -> 0.021065421 | J35: =J23+J29 -> 0.021215607 | K35: =K23+K29 -> 0.020594469 | ... BK35: =BK23+BK29 -> 0.018928238 | BO35: =BO23+BO29 -> 0.018915137 | BP35: =BP23+BP29 -> 0.018351846 | BQ35: =BQ23+BQ29 -> 0.018828358 | BR35: =BR23+BR29 -> 0.019339683 | BS35: =BS23+BS29 -> 0.020499136 | BT35: =BT23+BT29 -> 0.021202613
A38: Ingreso_Financiero | C38: Vigente | D38: =Renta_Alta!D38+Masivo!D38+Consumo_Inicial!D38 -> 54508.581 | E38: =Renta_Alta!E38+Masivo!E38+Consumo_Inicial!E38 -> 49748.111 | F38: =Renta_Alta!F38+Masivo!F38+Consumo_Inicial!F38 -> 55428.296 | G38: =Renta_Alta!G38+Masivo!G38+Consumo_Inicial!G38 -> 54185.562 | H38: =Renta_Alta!H38+Masivo!H38+Consumo_Inicial!H38 -> 56408.449 | I38: =Renta_Alta!I38+Masivo!I38+Consumo_Inicial!I38 -> 54868.044 | J38: =Renta_Alta!J38+Masivo!J38+Consumo_Inicial!J38 -> 57291.787 | K38: =Renta_Alta!K38+Masivo!K38+Consumo_Inicial!K38 -> 57286.49 | ... BK38: =Renta_Alta!BK38+Masivo!BK38+Consumo_Inicial!BK38 -> 74984.622 | BO38: =SUMIFS($D38:$BM38,$D$6:$BM$6,">="&BO$2,$D$6:$BM$6,"<="&BO$6,$D$5:$BM$5,BO$5) -> 204971.59 | BP38: =SUMIFS($D38:$BM38,$D$6:$BM$6,">="&BP$2,$D$6:$BM$6,"<="&BP$6,$D$5:$BM$5,BP$5) -> 201100.61 | BQ38: =SUMIFS($D38:$BM38,$D$6:$BM$6,">="&BQ$2,$D$6:$BM$6,"<="&BQ$6,$D$5:$BM$5,BQ$5) -> 134030.46 | BR38: =SUMIFS($D38:$BM38,$D$6:$BM$6,">="&BR$2,$D$6:$BM$6,"<="&BR$6,$D$5:$BM$5,BR$5) -> 187711.57 | BS38: =SUMIFS($D38:$BM38,$D$6:$BM$6,">="&BS$2,$D$6:$BM$6,"<="&BS$6,$D$5:$BM$5,BS$5) -> 175489.41 | BT38: =SUMIFS($D38:$BM38,$D$6:$BM$6,">="&BT$2,$D$6:$BM$6,"<="&BT$6,$D$5:$BM$5,BT$5) -> 159684.99
A39: Ingreso_Financiero | C39: Refinanciado | D39: =Renta_Alta!D39+Masivo!D39+Consumo_Inicial!D39 -> 0 | E39: =Renta_Alta!E39+Masivo!E39+Consumo_Inicial!E39 -> 0 | F39: =Renta_Alta!F39+Masivo!F39+Consumo_Inicial!F39 -> 0 | G39: =Renta_Alta!G39+Masivo!G39+Consumo_Inicial!G39 -> 0 | H39: =Renta_Alta!H39+Masivo!H39+Consumo_Inicial!H39 -> 0 | I39: =Renta_Alta!I39+Masivo!I39+Consumo_Inicial!I39 -> 0 | J39: =Renta_Alta!J39+Masivo!J39+Consumo_Inicial!J39 -> 0 | K39: =Renta_Alta!K39+Masivo!K39+Consumo_Inicial!K39 -> 0 | ... BK39: =Renta_Alta!BK39+Masivo!BK39+Consumo_Inicial!BK39 -> 0 | BO39: =SUMIFS($D39:$BM39,$D$6:$BM$6,">="&BO$2,$D$6:$BM$6,"<="&BO$6,$D$5:$BM$5,BO$5) -> 0 | BP39: =SUMIFS($D39:$BM39,$D$6:$BM$6,">="&BP$2,$D$6:$BM$6,"<="&BP$6,$D$5:$BM$5,BP$5) -> 0 | BQ39: =SUMIFS($D39:$BM39,$D$6:$BM$6,">="&BQ$2,$D$6:$BM$6,"<="&BQ$6,$D$5:$BM$5,BQ$5) -> 0 | BR39: =SUMIFS($D39:$BM39,$D$6:$BM$6,">="&BR$2,$D$6:$BM$6,"<="&BR$6,$D$5:$BM$5,BR$5) -> 0 | BS39: =SUMIFS($D39:$BM39,$D$6:$BM$6,">="&BS$2,$D$6:$BM$6,"<="&BS$6,$D$5:$BM$5,BS$5) -> 0 | BT39: =SUMIFS($D39:$BM39,$D$6:$BM$6,">="&BT$2,$D$6:$BM$6,"<="&BT$6,$D$5:$BM$5,BT$5) -> 0
A40: Ingreso_Financiero | C40: Vencido y Judicial | D40: =Renta_Alta!D40+Masivo!D40+Consumo_Inicial!D40 -> 1835.0331 | E40: =Renta_Alta!E40+Masivo!E40+Consumo_Inicial!E40 -> 1584.3404 | F40: =Renta_Alta!F40+Masivo!F40+Consumo_Inicial!F40 -> 2237.3082 | G40: =Renta_Alta!G40+Masivo!G40+Consumo_Inicial!G40 -> 1707.2738 | H40: =Renta_Alta!H40+Masivo!H40+Consumo_Inicial!H40 -> 2137.6212 | I40: =Renta_Alta!I40+Masivo!I40+Consumo_Inicial!I40 -> 2258.2491 | J40: =Renta_Alta!J40+Masivo!J40+Consumo_Inicial!J40 -> 2334.6948 | K40: =Renta_Alta!K40+Masivo!K40+Consumo_Inicial!K40 -> 2154.7942 | ... BK40: =Renta_Alta!BK40+Masivo!BK40+Consumo_Inicial!BK40 -> 3976.2722 | BO40: =SUMIFS($D40:$BM40,$D$6:$BM$6,">="&BO$2,$D$6:$BM$6,"<="&BO$6,$D$5:$BM$5,BO$5) -> 8695.8404 | BP40: =SUMIFS($D40:$BM40,$D$6:$BM$6,">="&BP$2,$D$6:$BM$6,"<="&BP$6,$D$5:$BM$5,BP$5) -> 10504.799 | BQ40: =SUMIFS($D40:$BM40,$D$6:$BM$6,">="&BQ$2,$D$6:$BM$6,"<="&BQ$6,$D$5:$BM$5,BQ$5) -> 5451.412 | BR40: =SUMIFS($D40:$BM40,$D$6:$BM$6,">="&BR$2,$D$6:$BM$6,"<="&BR$6,$D$5:$BM$5,BR$5) -> 8475.6998 | BS40: =SUMIFS($D40:$BM40,$D$6:$BM$6,">="&BS$2,$D$6:$BM$6,"<="&BS$6,$D$5:$BM$5,BS$5) -> 7578.7647 | BT40: =SUMIFS($D40:$BM40,$D$6:$BM$6,">="&BT$2,$D$6:$BM$6,"<="&BT$6,$D$5:$BM$5,BT$5) -> 5656.6817
C41: Ingreso Financiero | D41: =SUM(D38:D40) -> 56343.614 | E41: =SUM(E38:E40) -> 51332.452 | F41: =SUM(F38:F40) -> 57665.604 | G41: =SUM(G38:G40) -> 55892.836 | H41: =SUM(H38:H40) -> 58546.07 | I41: =SUM(I38:I40) -> 57126.294 | J41: =SUM(J38:J40) -> 59626.482 | K41: =SUM(K38:K40) -> 59441.284 | ... BK41: =SUM(BK38:BK40) -> 78960.894 | BO41: =SUM(BO38:BO40) -> 213667.43 | BP41: =SUM(BP38:BP40) -> 211605.41 | BQ41: =SUM(BQ38:BQ40) -> 139481.88 | BR41: =SUM(BR38:BR40) -> 196187.27 | BS41: =SUM(BS38:BS40) -> 183068.17 | BT41: =SUM(BT38:BT40) -> 165341.67
A44: FTP | C44: Vigente | D44: =Renta_Alta!D44+Masivo!D44+Consumo_Inicial!D44 -> -37446.097 | E44: =Renta_Alta!E44+Masivo!E44+Consumo_Inicial!E44 -> -37877.024 | F44: =Renta_Alta!F44+Masivo!F44+Consumo_Inicial!F44 -> -38298.555 | G44: =Renta_Alta!G44+Masivo!G44+Consumo_Inicial!G44 -> -38822.579 | H44: =Renta_Alta!H44+Masivo!H44+Consumo_Inicial!H44 -> -39191.402 | I44: =Renta_Alta!I44+Masivo!I44+Consumo_Inicial!I44 -> -39646.187 | J44: =Renta_Alta!J44+Masivo!J44+Consumo_Inicial!J44 -> -40059.944 | K44: =Renta_Alta!K44+Masivo!K44+Consumo_Inicial!K44 -> -40295.261 | ... BK44: =Renta_Alta!BK44+Masivo!BK44+Consumo_Inicial!BK44 -> -55775.848 | BO44: =SUMIFS($D44:$BM44,$D$6:$BM$6,">="&BO$2,$D$6:$BM$6,"<="&BO$6,$D$5:$BM$5,BO$5) -> -155953.3 | BP44: =SUMIFS($D44:$BM44,$D$6:$BM$6,">="&BP$2,$D$6:$BM$6,"<="&BP$6,$D$5:$BM$5,BP$5) -> -155526.46 | BQ44: =SUMIFS($D44:$BM44,$D$6:$BM$6,">="&BQ$2,$D$6:$BM$6,"<="&BQ$6,$D$5:$BM$5,BQ$5) -> -103627.48 | BR44: =SUMIFS($D44:$BM44,$D$6:$BM$6,">="&BR$2,$D$6:$BM$6,"<="&BR$6,$D$5:$BM$5,BR$5) -> -141871.56 | BS44: =SUMIFS($D44:$BM44,$D$6:$BM$6,">="&BS$2,$D$6:$BM$6,"<="&BS$6,$D$5:$BM$5,BS$5) -> -127650.29 | BT44: =SUMIFS($D44:$BM44,$D$6:$BM$6,">="&BT$2,$D$6:$BM$6,"<="&BT$6,$D$5:$BM$5,BT$5) -> -113621.68
A45: FTP | C45: Refinanciado | D45: =Renta_Alta!D45+Masivo!D45+Consumo_Inicial!D45 -> -136.55005 | E45: =Renta_Alta!E45+Masivo!E45+Consumo_Inicial!E45 -> -132.28075 | F45: =Renta_Alta!F45+Masivo!F45+Consumo_Inicial!F45 -> -135.84478 | G45: =Renta_Alta!G45+Masivo!G45+Consumo_Inicial!G45 -> -144.23654 | H45: =Renta_Alta!H45+Masivo!H45+Consumo_Inicial!H45 -> -132.26878 | I45: =Renta_Alta!I45+Masivo!I45+Consumo_Inicial!I45 -> -131.17019 | J45: =Renta_Alta!J45+Masivo!J45+Consumo_Inicial!J45 -> -131.70305 | K45: =Renta_Alta!K45+Masivo!K45+Consumo_Inicial!K45 -> -126.60729 | ... BK45: =Renta_Alta!BK45+Masivo!BK45+Consumo_Inicial!BK45 -> -149.54885 | BO45: =SUMIFS($D45:$BM45,$D$6:$BM$6,">="&BO$2,$D$6:$BM$6,"<="&BO$6,$D$5:$BM$5,BO$5) -> -434.70243 | BP45: =SUMIFS($D45:$BM45,$D$6:$BM$6,">="&BP$2,$D$6:$BM$6,"<="&BP$6,$D$5:$BM$5,BP$5) -> -409.64609 | BQ45: =SUMIFS($D45:$BM45,$D$6:$BM$6,">="&BQ$2,$D$6:$BM$6,"<="&BQ$6,$D$5:$BM$5,BQ$5) -> -283.73102 | BR45: =SUMIFS($D45:$BM45,$D$6:$BM$6,">="&BR$2,$D$6:$BM$6,"<="&BR$6,$D$5:$BM$5,BR$5) -> -374.56083 | BS45: =SUMIFS($D45:$BM45,$D$6:$BM$6,">="&BS$2,$D$6:$BM$6,"<="&BS$6,$D$5:$BM$5,BS$5) -> -382.45111 | BT45: =SUMIFS($D45:$BM45,$D$6:$BM$6,">="&BT$2,$D$6:$BM$6,"<="&BT$6,$D$5:$BM$5,BT$5) -> -404.67559
A46: FTP | C46: Vencido y Judicial | D46: =Renta_Alta!D46+Masivo!D46+Consumo_Inicial!D46 -> -1052.8121 | E46: =Renta_Alta!E46+Masivo!E46+Consumo_Inicial!E46 -> -1056.6911 | F46: =Renta_Alta!F46+Masivo!F46+Consumo_Inicial!F46 -> -1080.1616 | G46: =Renta_Alta!G46+Masivo!G46+Consumo_Inicial!G46 -> -1094.9538 | H46: =Renta_Alta!H46+Masivo!H46+Consumo_Inicial!H46 -> -1129.513 | I46: =Renta_Alta!I46+Masivo!I46+Consumo_Inicial!I46 -> -1130.847 | J46: =Renta_Alta!J46+Masivo!J46+Consumo_Inicial!J46 -> -1108.2501 | K46: =Renta_Alta!K46+Masivo!K46+Consumo_Inicial!K46 -> -1136.9013 | ... BK46: =Renta_Alta!BK46+Masivo!BK46+Consumo_Inicial!BK46 -> -1834.3289 | BO46: =SUMIFS($D46:$BM46,$D$6:$BM$6,">="&BO$2,$D$6:$BM$6,"<="&BO$6,$D$5:$BM$5,BO$5) -> -4791.0005 | BP46: =SUMIFS($D46:$BM46,$D$6:$BM$6,">="&BP$2,$D$6:$BM$6,"<="&BP$6,$D$5:$BM$5,BP$5) -> -5046.8493 | BQ46: =SUMIFS($D46:$BM46,$D$6:$BM$6,">="&BQ$2,$D$6:$BM$6,"<="&BQ$6,$D$5:$BM$5,BQ$5) -> -3216.4313 | BR46: =SUMIFS($D46:$BM46,$D$6:$BM$6,">="&BR$2,$D$6:$BM$6,"<="&BR$6,$D$5:$BM$5,BR$5) -> -4421.7289 | BS46: =SUMIFS($D46:$BM46,$D$6:$BM$6,">="&BS$2,$D$6:$BM$6,"<="&BS$6,$D$5:$BM$5,BS$5) -> -3931.5749 | BT46: =SUMIFS($D46:$BM46,$D$6:$BM$6,">="&BT$2,$D$6:$BM$6,"<="&BT$6,$D$5:$BM$5,BT$5) -> -3189.6649
C47: Costo de Fondos | D47: =SUM(D44:D46) -> -38635.459 | E47: =SUM(E44:E46) -> -39065.996 | F47: =SUM(F44:F46) -> -39514.561 | G47: =SUM(G44:G46) -> -40061.769 | H47: =SUM(H44:H46) -> -40453.184 | I47: =SUM(I44:I46) -> -40908.204 | J47: =SUM(J44:J46) -> -41299.898 | K47: =SUM(K44:K46) -> -41558.77 | ... BK47: =SUM(BK44:BK46) -> -57759.726 | BO47: =SUM(BO44:BO46) -> -161179 | BP47: =SUM(BP44:BP46) -> -160982.96 | BQ47: =SUM(BQ44:BQ46) -> -107127.64 | BR47: =SUM(BR44:BR46) -> -146667.85 | BS47: =SUM(BS44:BS46) -> -131964.31 | BT47: =SUM(BT44:BT46) -> -117216.02
C50: Vigente | D50: =D38+D44 -> 17062.484 | E50: =E38+E44 -> 11871.088 | F50: =F38+F44 -> 17129.741 | G50: =G38+G44 -> 15362.983 | H50: =H38+H44 -> 17217.047 | I50: =I38+I44 -> 15221.858 | J50: =J38+J44 -> 17231.843 | K50: =K38+K44 -> 16991.229 | ... BK50: =BK38+BK44 -> 19208.774 | BO50: =BO38+BO44 -> 49018.297 | BP50: =BP38+BP44 -> 45574.143 | BQ50: =BQ38+BQ44 -> 30402.988 | BR50: =BR38+BR44 -> 45840.01 | BS50: =BS38+BS44 -> 47839.119 | BT50: =BT38+BT44 -> 46063.313
C51: Refinanciado | D51: =D39+D45 -> -136.55005 | E51: =E39+E45 -> -132.28075 | F51: =F39+F45 -> -135.84478 | G51: =G39+G45 -> -144.23654 | H51: =H39+H45 -> -132.26878 | I51: =I39+I45 -> -131.17019 | J51: =J39+J45 -> -131.70305 | K51: =K39+K45 -> -126.60729 | ... BK51: =BK39+BK45 -> -149.54885 | BO51: =BO39+BO45 -> -434.70243 | BP51: =BP39+BP45 -> -409.64609 | BQ51: =BQ39+BQ45 -> -283.73102 | BR51: =BR39+BR45 -> -374.56083 | BS51: =BS39+BS45 -> -382.45111 | BT51: =BT39+BT45 -> -404.67559
C52: Vencido y Judicial | D52: =D40+D46 -> 782.221 | E52: =E40+E46 -> 527.64928 | F52: =F40+F46 -> 1157.1466 | G52: =G40+G46 -> 612.31993 | H52: =H40+H46 -> 1008.1082 | I52: =I40+I46 -> 1127.4022 | J52: =J40+J46 -> 1226.4447 | K52: =K40+K46 -> 1017.8929 | ... BK52: =BK40+BK46 -> 2141.9433 | BO52: =BO40+BO46 -> 3904.8398 | BP52: =BP40+BP46 -> 5457.9497 | BQ52: =BQ40+BQ46 -> 2234.9807 | BR52: =BR40+BR46 -> 4053.9709 | BS52: =BS40+BS46 -> 3647.1898 | BT52: =BT40+BT46 -> 2467.0169
C53: Resultado Financiero Bruto | D53: =D41+D47 -> 17708.155 | E53: =E41+E47 -> 12266.456 | F53: =F41+F47 -> 18151.042 | G53: =G41+G47 -> 15831.067 | H53: =H41+H47 -> 18092.886 | I53: =I41+I47 -> 16218.09 | J53: =J41+J47 -> 18326.584 | K53: =K41+K47 -> 17882.514 | ... BK53: =BK41+BK47 -> 21201.168 | BO53: =SUM(BO50:BO52) -> 52488.435 | BP53: =SUM(BP50:BP52) -> 50622.447 | BQ53: =SUM(BQ50:BQ52) -> 32354.238 | BR53: =SUM(BR50:BR52) -> 49519.421 | BS53: =SUM(BS50:BS52) -> 51103.858 | BT53: =SUM(BT50:BT52) -> 48125.654
D54: =[1]Base_Evolutivo!BE1258-D53 -> 3.35e-06 | E54: =[1]Base_Evolutivo!BF1258-E53 -> -6.0998718e-07 | F54: =[1]Base_Evolutivo!BG1258-F53 -> 1.4899888e-06 | G54: =[1]Base_Evolutivo!BH1258-G53 -> 5.5600249e-06 | H54: =[1]Base_Evolutivo!BI1258-H53 -> 6.4899868e-06 | I54: =[1]Base_Evolutivo!BJ1258-I53 -> -5.7999932e-06 | J54: =[1]Base_Evolutivo!BK1258-J53 -> -6.5799868e-06 | K54: =[1]Base_Evolutivo!BL1258-K53 -> -5.9998638e-07 | ... BK54: =[1]Base_Evolutivo!DL1258-BK53 -> -21201.168
A56: Gasto_Provision | C56: Provisiones Cartera | D56: =Renta_Alta!D56+Masivo!D56+Consumo_Inicial!D56 -> -2170.5901 | E56: =Renta_Alta!E56+Masivo!E56+Consumo_Inicial!E56 -> -2366.106 | F56: =Renta_Alta!F56+Masivo!F56+Consumo_Inicial!F56 -> -1002.9986 | G56: =Renta_Alta!G56+Masivo!G56+Consumo_Inicial!G56 -> -2464.603 | H56: =Renta_Alta!H56+Masivo!H56+Consumo_Inicial!H56 -> -4418.9796 | I56: =Renta_Alta!I56+Masivo!I56+Consumo_Inicial!I56 -> -2147.6603 | J56: =Renta_Alta!J56+Masivo!J56+Consumo_Inicial!J56 -> 2525.2174 | K56: =Renta_Alta!K56+Masivo!K56+Consumo_Inicial!K56 -> -1735.5362 | ... BK56: =Renta_Alta!BK56+Masivo!BK56+Consumo_Inicial!BK56 -> -271.33506 | BO56: =SUMIFS($D56:$BM56,$D$6:$BM$6,">="&BO$2,$D$6:$BM$6,"<="&BO$6,$D$5:$BM$5,BO$5) -> -613.56855 | BP56: =SUMIFS($D56:$BM56,$D$6:$BM$6,">="&BP$2,$D$6:$BM$6,"<="&BP$6,$D$5:$BM$5,BP$5) -> -11935.066 | BQ56: =SUMIFS($D56:$BM56,$D$6:$BM$6,">="&BQ$2,$D$6:$BM$6,"<="&BQ$6,$D$5:$BM$5,BQ$5) -> 1748.9502 | BR56: =SUMIFS($D56:$BM56,$D$6:$BM$6,">="&BR$2,$D$6:$BM$6,"<="&BR$6,$D$5:$BM$5,BR$5) -> -9021.4881 | BS56: =SUMIFS($D56:$BM56,$D$6:$BM$6,">="&BS$2,$D$6:$BM$6,"<="&BS$6,$D$5:$BM$5,BS$5) -> -11150.787 | BT56: =SUMIFS($D56:$BM56,$D$6:$BM$6,">="&BT$2,$D$6:$BM$6,"<="&BT$6,$D$5:$BM$5,BT$5) -> -5539.6947
A57: Recupero | C57: Recupero de Castigos | D57: =Renta_Alta!D57+Masivo!D57+Consumo_Inicial!D57 -> 0.7 | E57: =Renta_Alta!E57+Masivo!E57+Consumo_Inicial!E57 -> 0 | F57: =Renta_Alta!F57+Masivo!F57+Consumo_Inicial!F57 -> 44.15912 | G57: =Renta_Alta!G57+Masivo!G57+Consumo_Inicial!G57 -> 153.17811 | H57: =Renta_Alta!H57+Masivo!H57+Consumo_Inicial!H57 -> 16.87885 | I57: =Renta_Alta!I57+Masivo!I57+Consumo_Inicial!I57 -> 65.14363 | J57: =Renta_Alta!J57+Masivo!J57+Consumo_Inicial!J57 -> 74.585 | K57: =Renta_Alta!K57+Masivo!K57+Consumo_Inicial!K57 -> 66.29776 | ... BK57: =Renta_Alta!BK57+Masivo!BK57+Consumo_Inicial!BK57 -> 0 | BO57: =SUMIFS($D57:$BM57,$D$6:$BM$6,">="&BO$2,$D$6:$BM$6,"<="&BO$6,$D$5:$BM$5,BO$5) -> 20.57519 | BP57: =SUMIFS($D57:$BM57,$D$6:$BM$6,">="&BP$2,$D$6:$BM$6,"<="&BP$6,$D$5:$BM$5,BP$5) -> 0 | BQ57: =SUMIFS($D57:$BM57,$D$6:$BM$6,">="&BQ$2,$D$6:$BM$6,"<="&BQ$6,$D$5:$BM$5,BQ$5) -> 20.095 | BR57: =SUMIFS($D57:$BM57,$D$6:$BM$6,">="&BR$2,$D$6:$BM$6,"<="&BR$6,$D$5:$BM$5,BR$5) -> 64.10855 | BS57: =SUMIFS($D57:$BM57,$D$6:$BM$6,">="&BS$2,$D$6:$BM$6,"<="&BS$6,$D$5:$BM$5,BS$5) -> 3.37 | BT57: =SUMIFS($D57:$BM57,$D$6:$BM$6,">="&BT$2,$D$6:$BM$6,"<="&BT$6,$D$5:$BM$5,BT$5) -> 44.85912
C58: Provisiones Netas | D58: =SUM(D56:D57) -> -2169.8901 | E58: =SUM(E56:E57) -> -2366.106 | F58: =SUM(F56:F57) -> -958.83948 | G58: =SUM(G56:G57) -> -2311.4249 | H58: =SUM(H56:H57) -> -4402.1007 | I58: =SUM(I56:I57) -> -2082.5166 | J58: =SUM(J56:J57) -> 2599.8024 | K58: =SUM(K56:K57) -> -1669.2384 | ... BK58: =SUM(BK56:BK57) -> -271.33506 | BO58: =SUM(BO56:BO57) -> -592.99336 | BP58: =SUM(BP56:BP57) -> -11935.066 | BQ58: =SUM(BQ56:BQ57) -> 1769.0452 | BR58: =SUM(BR56:BR57) -> -8957.3795 | BS58: =SUM(BS56:BS57) -> -11147.417 | BT58: =SUM(BT56:BT57) -> -5494.8356
D59: =[1]Base_Evolutivo!BE1621-D58 -> 0 | E59: =[1]Base_Evolutivo!BF1621-E58 -> 0 | F59: =[1]Base_Evolutivo!BG1621-F58 -> 0 | G59: =[1]Base_Evolutivo!BH1621-G58 -> 0 | H59: =[1]Base_Evolutivo!BI1621-H58 -> 0 | I59: =[1]Base_Evolutivo!BJ1621-I58 -> 0 | J59: =[1]Base_Evolutivo!BK1621-J58 -> 0 | K59: =[1]Base_Evolutivo!BL1621-K58 -> 0 | ... BK59: =[1]Base_Evolutivo!DL1621-BK58 -> 271.33506
C60: Resultado Financiero Neto | D60: =D53+D58 -> 15538.265 | E60: =E53+E58 -> 9900.3502 | F60: =F53+F58 -> 17192.203 | G60: =G53+G58 -> 13519.642 | H60: =H53+H58 -> 13690.786 | I60: =I53+I58 -> 14135.573 | J60: =J53+J58 -> 20926.387 | K60: =K53+K58 -> 16213.276 | ... BK60: =BK53+BK58 -> 20929.833 | BO60: =BO53+BO58 -> 51895.441 | BP60: =BP53+BP58 -> 38687.38 | BQ60: =BQ53+BQ58 -> 34123.283 | BR60: =BR53+BR58 -> 40562.041 | BS60: =BS53+BS58 -> 39956.441 | BT60: =BT53+BT58 -> 42630.818
A63: INOF | C63: Garantías | D63: =Renta_Alta!D63+Masivo!D63+Consumo_Inicial!D63 -> 676.75345 | E63: =Renta_Alta!E63+Masivo!E63+Consumo_Inicial!E63 -> 585.94255 | F63: =Renta_Alta!F63+Masivo!F63+Consumo_Inicial!F63 -> 787.93693 | G63: =Renta_Alta!G63+Masivo!G63+Consumo_Inicial!G63 -> 642.14555 | H63: =Renta_Alta!H63+Masivo!H63+Consumo_Inicial!H63 -> 700.3357 | I63: =Renta_Alta!I63+Masivo!I63+Consumo_Inicial!I63 -> 605.07015 | J63: =Renta_Alta!J63+Masivo!J63+Consumo_Inicial!J63 -> 687.9477 | K63: =Renta_Alta!K63+Masivo!K63+Consumo_Inicial!K63 -> 617.56673 | ... BK63: =Renta_Alta!BK63+Masivo!BK63+Consumo_Inicial!BK63 -> 657.15694 | BO63: =SUMIFS($D63:$BM63,$D$6:$BM$6,">="&BO$2,$D$6:$BM$6,"<="&BO$6,$D$5:$BM$5,BO$5) -> 2118.398 | BP63: =SUMIFS($D63:$BM63,$D$6:$BM$6,">="&BP$2,$D$6:$BM$6,"<="&BP$6,$D$5:$BM$5,BP$5) -> 1971.4708 | BQ63: =SUMIFS($D63:$BM63,$D$6:$BM$6,">="&BQ$2,$D$6:$BM$6,"<="&BQ$6,$D$5:$BM$5,BQ$5) -> 1100.2614 | BR63: =SUMIFS($D63:$BM63,$D$6:$BM$6,">="&BR$2,$D$6:$BM$6,"<="&BR$6,$D$5:$BM$5,BR$5) -> 1906.6406 | BS63: =SUMIFS($D63:$BM63,$D$6:$BM$6,">="&BS$2,$D$6:$BM$6,"<="&BS$6,$D$5:$BM$5,BS$5) -> 1322.2734 | BT63: =SUMIFS($D63:$BM63,$D$6:$BM$6,">="&BT$2,$D$6:$BM$6,"<="&BT$6,$D$5:$BM$5,BT$5) -> 2050.6329
A64: INOF | C64: Seguro de Desgravamen | D64: =Renta_Alta!D64+Masivo!D64+Consumo_Inicial!D64 -> 489.61538 | E64: =Renta_Alta!E64+Masivo!E64+Consumo_Inicial!E64 -> 457.32786 | F64: =Renta_Alta!F64+Masivo!F64+Consumo_Inicial!F64 -> 373.30377 | G64: =Renta_Alta!G64+Masivo!G64+Consumo_Inicial!G64 -> 520.30578 | H64: =Renta_Alta!H64+Masivo!H64+Consumo_Inicial!H64 -> 421.60794 | I64: =Renta_Alta!I64+Masivo!I64+Consumo_Inicial!I64 -> 488.25423 | J64: =Renta_Alta!J64+Masivo!J64+Consumo_Inicial!J64 -> 433.12008 | K64: =Renta_Alta!K64+Masivo!K64+Consumo_Inicial!K64 -> 478.7634 | ... BK64: =Renta_Alta!BK64+Masivo!BK64+Consumo_Inicial!BK64 -> 440.50267 | BO64: =SUMIFS($D64:$BM64,$D$6:$BM$6,">="&BO$2,$D$6:$BM$6,"<="&BO$6,$D$5:$BM$5,BO$5) -> 1314.3344 | BP64: =SUMIFS($D64:$BM64,$D$6:$BM$6,">="&BP$2,$D$6:$BM$6,"<="&BP$6,$D$5:$BM$5,BP$5) -> 1235.6628 | BQ64: =SUMIFS($D64:$BM64,$D$6:$BM$6,">="&BQ$2,$D$6:$BM$6,"<="&BQ$6,$D$5:$BM$5,BQ$5) -> 937.65317 | BR64: =SUMIFS($D64:$BM64,$D$6:$BM$6,">="&BR$2,$D$6:$BM$6,"<="&BR$6,$D$5:$BM$5,BR$5) -> 1247.9668 | BS64: =SUMIFS($D64:$BM64,$D$6:$BM$6,">="&BS$2,$D$6:$BM$6,"<="&BS$6,$D$5:$BM$5,BS$5) -> 1317.3101 | BT64: =SUMIFS($D64:$BM64,$D$6:$BM$6,">="&BT$2,$D$6:$BM$6,"<="&BT$6,$D$5:$BM$5,BT$5) -> 1320.247
A65: INOF | C65: Servicios Legales y Tasación Hipotecario | D65: =Renta_Alta!D65+Masivo!D65+Consumo_Inicial!D65 -> 6.6012188 | E65: =Renta_Alta!E65+Masivo!E65+Consumo_Inicial!E65 -> -6.4091689 | F65: =Renta_Alta!F65+Masivo!F65+Consumo_Inicial!F65 -> -49.958925 | G65: =Renta_Alta!G65+Masivo!G65+Consumo_Inicial!G65 -> -42.770495 | H65: =Renta_Alta!H65+Masivo!H65+Consumo_Inicial!H65 -> -164.72577 | I65: =Renta_Alta!I65+Masivo!I65+Consumo_Inicial!I65 -> -318.96141 | J65: =Renta_Alta!J65+Masivo!J65+Consumo_Inicial!J65 -> -343.31529 | K65: =Renta_Alta!K65+Masivo!K65+Consumo_Inicial!K65 -> -303.25101 | ... BK65: =Renta_Alta!BK65+Masivo!BK65+Consumo_Inicial!BK65 -> -12 | BO65: =SUMIFS($D65:$BM65,$D$6:$BM$6,">="&BO$2,$D$6:$BM$6,"<="&BO$6,$D$5:$BM$5,BO$5) -> 97.82804 | BP65: =SUMIFS($D65:$BM65,$D$6:$BM$6,">="&BP$2,$D$6:$BM$6,"<="&BP$6,$D$5:$BM$5,BP$5) -> -24 | BQ65: =SUMIFS($D65:$BM65,$D$6:$BM$6,">="&BQ$2,$D$6:$BM$6,"<="&BQ$6,$D$5:$BM$5,BQ$5) -> 87.747625 | BR65: =SUMIFS($D65:$BM65,$D$6:$BM$6,">="&BR$2,$D$6:$BM$6,"<="&BR$6,$D$5:$BM$5,BR$5) -> -179.06191 | BS65: =SUMIFS($D65:$BM65,$D$6:$BM$6,">="&BS$2,$D$6:$BM$6,"<="&BS$6,$D$5:$BM$5,BS$5) -> -707.60814 | BT65: =SUMIFS($D65:$BM65,$D$6:$BM$6,">="&BT$2,$D$6:$BM$6,"<="&BT$6,$D$5:$BM$5,BT$5) -> -49.766875
A66: INOF | C66: Comisiones Credito Hipotecario | D66: =Renta_Alta!D66+Masivo!D66+Consumo_Inicial!D66 -> 2.0924043 | E66: =Renta_Alta!E66+Masivo!E66+Consumo_Inicial!E66 -> -0.51473526 | F66: =Renta_Alta!F66+Masivo!F66+Consumo_Inicial!F66 -> -1.4854462 | G66: =Renta_Alta!G66+Masivo!G66+Consumo_Inicial!G66 -> 1.9338806 | H66: =Renta_Alta!H66+Masivo!H66+Consumo_Inicial!H66 -> -1.2184441 | I66: =Renta_Alta!I66+Masivo!I66+Consumo_Inicial!I66 -> 1.224208 | J66: =Renta_Alta!J66+Masivo!J66+Consumo_Inicial!J66 -> -1.5812399 | K66: =Renta_Alta!K66+Masivo!K66+Consumo_Inicial!K66 -> -12.068054 | ... BK66: =Renta_Alta!BK66+Masivo!BK66+Consumo_Inicial!BK66 -> 1.7596129 | BO66: =SUMIFS($D66:$BM66,$D$6:$BM$6,">="&BO$2,$D$6:$BM$6,"<="&BO$6,$D$5:$BM$5,BO$5) -> 8.6162502 | BP66: =SUMIFS($D66:$BM66,$D$6:$BM$6,">="&BP$2,$D$6:$BM$6,"<="&BP$6,$D$5:$BM$5,BP$5) -> 4.9359254 | BQ66: =SUMIFS($D66:$BM66,$D$6:$BM$6,">="&BQ$2,$D$6:$BM$6,"<="&BQ$6,$D$5:$BM$5,BQ$5) -> 5.0404557 | BR66: =SUMIFS($D66:$BM66,$D$6:$BM$6,">="&BR$2,$D$6:$BM$6,"<="&BR$6,$D$5:$BM$5,BR$5) -> 6.3520381 | BS66: =SUMIFS($D66:$BM66,$D$6:$BM$6,">="&BS$2,$D$6:$BM$6,"<="&BS$6,$D$5:$BM$5,BS$5) -> 2.8265034 | BT66: =SUMIFS($D66:$BM66,$D$6:$BM$6,">="&BT$2,$D$6:$BM$6,"<="&BT$6,$D$5:$BM$5,BT$5) -> 0.09222281
A67: INOF | D67: =Renta_Alta!D67+Masivo!D67+Consumo_Inicial!D67 -> 0 | E67: =Renta_Alta!E67+Masivo!E67+Consumo_Inicial!E67 -> 0 | F67: =Renta_Alta!F67+Masivo!F67+Consumo_Inicial!F67 -> 0 | G67: =Renta_Alta!G67+Masivo!G67+Consumo_Inicial!G67 -> 0 | H67: =Renta_Alta!H67+Masivo!H67+Consumo_Inicial!H67 -> 0 | I67: =Renta_Alta!I67+Masivo!I67+Consumo_Inicial!I67 -> 0 | J67: =Renta_Alta!J67+Masivo!J67+Consumo_Inicial!J67 -> 0 | K67: =Renta_Alta!K67+Masivo!K67+Consumo_Inicial!K67 -> 0 | ... BK67: =Renta_Alta!BK67+Masivo!BK67+Consumo_Inicial!BK67 -> 0 | BO67: =SUMIFS($D67:$BM67,$D$6:$BM$6,">="&BO$2,$D$6:$BM$6,"<="&BO$6,$D$5:$BM$5,BO$5) -> 0 | BP67: =SUMIFS($D67:$BM67,$D$6:$BM$6,">="&BP$2,$D$6:$BM$6,"<="&BP$6,$D$5:$BM$5,BP$5) -> 0 | BQ67: =SUMIFS($D67:$BM67,$D$6:$BM$6,">="&BQ$2,$D$6:$BM$6,"<="&BQ$6,$D$5:$BM$5,BQ$5) -> 0 | BR67: =SUMIFS($D67:$BM67,$D$6:$BM$6,">="&BR$2,$D$6:$BM$6,"<="&BR$6,$D$5:$BM$5,BR$5) -> 0 | BS67: =SUMIFS($D67:$BM67,$D$6:$BM$6,">="&BS$2,$D$6:$BM$6,"<="&BS$6,$D$5:$BM$5,BS$5) -> 0 | BT67: =SUMIFS($D67:$BM67,$D$6:$BM$6,">="&BT$2,$D$6:$BM$6,"<="&BT$6,$D$5:$BM$5,BT$5) -> 0
A68: INOF | D68: =Renta_Alta!D68+Masivo!D68+Consumo_Inicial!D68 -> 0 | E68: =Renta_Alta!E68+Masivo!E68+Consumo_Inicial!E68 -> 0 | F68: =Renta_Alta!F68+Masivo!F68+Consumo_Inicial!F68 -> 0 | G68: =Renta_Alta!G68+Masivo!G68+Consumo_Inicial!G68 -> 0 | H68: =Renta_Alta!H68+Masivo!H68+Consumo_Inicial!H68 -> 0 | I68: =Renta_Alta!I68+Masivo!I68+Consumo_Inicial!I68 -> 0 | J68: =Renta_Alta!J68+Masivo!J68+Consumo_Inicial!J68 -> 0 | K68: =Renta_Alta!K68+Masivo!K68+Consumo_Inicial!K68 -> 0 | ... BK68: =Renta_Alta!BK68+Masivo!BK68+Consumo_Inicial!BK68 -> 0 | BO68: =SUMIFS($D68:$BM68,$D$6:$BM$6,">="&BO$2,$D$6:$BM$6,"<="&BO$6,$D$5:$BM$5,BO$5) -> 0 | BP68: =SUMIFS($D68:$BM68,$D$6:$BM$6,">="&BP$2,$D$6:$BM$6,"<="&BP$6,$D$5:$BM$5,BP$5) -> 0 | BQ68: =SUMIFS($D68:$BM68,$D$6:$BM$6,">="&BQ$2,$D$6:$BM$6,"<="&BQ$6,$D$5:$BM$5,BQ$5) -> 0 | BR68: =SUMIFS($D68:$BM68,$D$6:$BM$6,">="&BR$2,$D$6:$BM$6,"<="&BR$6,$D$5:$BM$5,BR$5) -> 0 | BS68: =SUMIFS($D68:$BM68,$D$6:$BM$6,">="&BS$2,$D$6:$BM$6,"<="&BS$6,$D$5:$BM$5,BS$5) -> 0 | BT68: =SUMIFS($D68:$BM68,$D$6:$BM$6,">="&BT$2,$D$6:$BM$6,"<="&BT$6,$D$5:$BM$5,BT$5) -> 0
A69: INOF | D69: =Renta_Alta!D69+Masivo!D69+Consumo_Inicial!D69 -> 0 | E69: =Renta_Alta!E69+Masivo!E69+Consumo_Inicial!E69 -> 0 | F69: =Renta_Alta!F69+Masivo!F69+Consumo_Inicial!F69 -> 0 | G69: =Renta_Alta!G69+Masivo!G69+Consumo_Inicial!G69 -> 0 | H69: =Renta_Alta!H69+Masivo!H69+Consumo_Inicial!H69 -> 0 | I69: =Renta_Alta!I69+Masivo!I69+Consumo_Inicial!I69 -> 0 | J69: =Renta_Alta!J69+Masivo!J69+Consumo_Inicial!J69 -> 0 | K69: =Renta_Alta!K69+Masivo!K69+Consumo_Inicial!K69 -> 0 | ... BK69: =Renta_Alta!BK69+Masivo!BK69+Consumo_Inicial!BK69 -> 0 | BO69: =SUMIFS($D69:$BM69,$D$6:$BM$6,">="&BO$2,$D$6:$BM$6,"<="&BO$6,$D$5:$BM$5,BO$5) -> 0 | BP69: =SUMIFS($D69:$BM69,$D$6:$BM$6,">="&BP$2,$D$6:$BM$6,"<="&BP$6,$D$5:$BM$5,BP$5) -> 0 | BQ69: =SUMIFS($D69:$BM69,$D$6:$BM$6,">="&BQ$2,$D$6:$BM$6,"<="&BQ$6,$D$5:$BM$5,BQ$5) -> 0 | BR69: =SUMIFS($D69:$BM69,$D$6:$BM$6,">="&BR$2,$D$6:$BM$6,"<="&BR$6,$D$5:$BM$5,BR$5) -> 0 | BS69: =SUMIFS($D69:$BM69,$D$6:$BM$6,">="&BS$2,$D$6:$BM$6,"<="&BS$6,$D$5:$BM$5,BS$5) -> 0 | BT69: =SUMIFS($D69:$BM69,$D$6:$BM$6,">="&BT$2,$D$6:$BM$6,"<="&BT$6,$D$5:$BM$5,BT$5) -> 0
A70: INOF | D70: =Renta_Alta!D70+Masivo!D70+Consumo_Inicial!D70 -> 0 | E70: =Renta_Alta!E70+Masivo!E70+Consumo_Inicial!E70 -> 0 | F70: =Renta_Alta!F70+Masivo!F70+Consumo_Inicial!F70 -> 0 | G70: =Renta_Alta!G70+Masivo!G70+Consumo_Inicial!G70 -> 0 | H70: =Renta_Alta!H70+Masivo!H70+Consumo_Inicial!H70 -> 0 | I70: =Renta_Alta!I70+Masivo!I70+Consumo_Inicial!I70 -> 0 | J70: =Renta_Alta!J70+Masivo!J70+Consumo_Inicial!J70 -> 0 | K70: =Renta_Alta!K70+Masivo!K70+Consumo_Inicial!K70 -> 0 | ... BK70: =Renta_Alta!BK70+Masivo!BK70+Consumo_Inicial!BK70 -> 0 | BO70: =SUMIFS($D70:$BM70,$D$6:$BM$6,">="&BO$2,$D$6:$BM$6,"<="&BO$6,$D$5:$BM$5,BO$5) -> 0 | BP70: =SUMIFS($D70:$BM70,$D$6:$BM$6,">="&BP$2,$D$6:$BM$6,"<="&BP$6,$D$5:$BM$5,BP$5) -> 0 | BQ70: =SUMIFS($D70:$BM70,$D$6:$BM$6,">="&BQ$2,$D$6:$BM$6,"<="&BQ$6,$D$5:$BM$5,BQ$5) -> 0 | BR70: =SUMIFS($D70:$BM70,$D$6:$BM$6,">="&BR$2,$D$6:$BM$6,"<="&BR$6,$D$5:$BM$5,BR$5) -> 0 | BS70: =SUMIFS($D70:$BM70,$D$6:$BM$6,">="&BS$2,$D$6:$BM$6,"<="&BS$6,$D$5:$BM$5,BS$5) -> 0 | BT70: =SUMIFS($D70:$BM70,$D$6:$BM$6,">="&BT$2,$D$6:$BM$6,"<="&BT$6,$D$5:$BM$5,BT$5) -> 0
A71: INOF | D71: =Renta_Alta!D71+Masivo!D71+Consumo_Inicial!D71 -> 0 | E71: =Renta_Alta!E71+Masivo!E71+Consumo_Inicial!E71 -> 0 | F71: =Renta_Alta!F71+Masivo!F71+Consumo_Inicial!F71 -> 0 | G71: =Renta_Alta!G71+Masivo!G71+Consumo_Inicial!G71 -> 0 | H71: =Renta_Alta!H71+Masivo!H71+Consumo_Inicial!H71 -> 0 | I71: =Renta_Alta!I71+Masivo!I71+Consumo_Inicial!I71 -> 0 | J71: =Renta_Alta!J71+Masivo!J71+Consumo_Inicial!J71 -> 0 | K71: =Renta_Alta!K71+Masivo!K71+Consumo_Inicial!K71 -> 0 | ... BK71: =Renta_Alta!BK71+Masivo!BK71+Consumo_Inicial!BK71 -> 0 | BO71: =SUMIFS($D71:$BM71,$D$6:$BM$6,">="&BO$2,$D$6:$BM$6,"<="&BO$6,$D$5:$BM$5,BO$5) -> 0 | BP71: =SUMIFS($D71:$BM71,$D$6:$BM$6,">="&BP$2,$D$6:$BM$6,"<="&BP$6,$D$5:$BM$5,BP$5) -> 0 | BQ71: =SUMIFS($D71:$BM71,$D$6:$BM$6,">="&BQ$2,$D$6:$BM$6,"<="&BQ$6,$D$5:$BM$5,BQ$5) -> 0 | BR71: =SUMIFS($D71:$BM71,$D$6:$BM$6,">="&BR$2,$D$6:$BM$6,"<="&BR$6,$D$5:$BM$5,BR$5) -> 0 | BS71: =SUMIFS($D71:$BM71,$D$6:$BM$6,">="&BS$2,$D$6:$BM$6,"<="&BS$6,$D$5:$BM$5,BS$5) -> 0 | BT71: =SUMIFS($D71:$BM71,$D$6:$BM$6,">="&BT$2,$D$6:$BM$6,"<="&BT$6,$D$5:$BM$5,BT$5) -> 0
A72: INOF | D72: =Renta_Alta!D72+Masivo!D72+Consumo_Inicial!D72 -> 0 | E72: =Renta_Alta!E72+Masivo!E72+Consumo_Inicial!E72 -> 0 | F72: =Renta_Alta!F72+Masivo!F72+Consumo_Inicial!F72 -> 0 | G72: =Renta_Alta!G72+Masivo!G72+Consumo_Inicial!G72 -> 0 | H72: =Renta_Alta!H72+Masivo!H72+Consumo_Inicial!H72 -> 0 | I72: =Renta_Alta!I72+Masivo!I72+Consumo_Inicial!I72 -> 0 | J72: =Renta_Alta!J72+Masivo!J72+Consumo_Inicial!J72 -> 0 | K72: =Renta_Alta!K72+Masivo!K72+Consumo_Inicial!K72 -> 0 | ... BK72: =Renta_Alta!BK72+Masivo!BK72+Consumo_Inicial!BK72 -> 0 | BO72: =SUMIFS($D72:$BM72,$D$6:$BM$6,">="&BO$2,$D$6:$BM$6,"<="&BO$6,$D$5:$BM$5,BO$5) -> 0 | BP72: =SUMIFS($D72:$BM72,$D$6:$BM$6,">="&BP$2,$D$6:$BM$6,"<="&BP$6,$D$5:$BM$5,BP$5) -> 0 | BQ72: =SUMIFS($D72:$BM72,$D$6:$BM$6,">="&BQ$2,$D$6:$BM$6,"<="&BQ$6,$D$5:$BM$5,BQ$5) -> 0 | BR72: =SUMIFS($D72:$BM72,$D$6:$BM$6,">="&BR$2,$D$6:$BM$6,"<="&BR$6,$D$5:$BM$5,BR$5) -> 0 | BS72: =SUMIFS($D72:$BM72,$D$6:$BM$6,">="&BS$2,$D$6:$BM$6,"<="&BS$6,$D$5:$BM$5,BS$5) -> 0 | BT72: =SUMIFS($D72:$BM72,$D$6:$BM$6,">="&BT$2,$D$6:$BM$6,"<="&BT$6,$D$5:$BM$5,BT$5) -> 0
A73: INOF | D73: =Renta_Alta!D73+Masivo!D73+Consumo_Inicial!D73 -> 0 | E73: =Renta_Alta!E73+Masivo!E73+Consumo_Inicial!E73 -> 0 | F73: =Renta_Alta!F73+Masivo!F73+Consumo_Inicial!F73 -> 0 | G73: =Renta_Alta!G73+Masivo!G73+Consumo_Inicial!G73 -> 0 | H73: =Renta_Alta!H73+Masivo!H73+Consumo_Inicial!H73 -> 0 | I73: =Renta_Alta!I73+Masivo!I73+Consumo_Inicial!I73 -> 0 | J73: =Renta_Alta!J73+Masivo!J73+Consumo_Inicial!J73 -> 0 | K73: =Renta_Alta!K73+Masivo!K73+Consumo_Inicial!K73 -> 0 | ... BK73: =Renta_Alta!BK73+Masivo!BK73+Consumo_Inicial!BK73 -> 0 | BO73: =SUMIFS($D73:$BM73,$D$6:$BM$6,">="&BO$2,$D$6:$BM$6,"<="&BO$6,$D$5:$BM$5,BO$5) -> 0 | BP73: =SUMIFS($D73:$BM73,$D$6:$BM$6,">="&BP$2,$D$6:$BM$6,"<="&BP$6,$D$5:$BM$5,BP$5) -> 0 | BQ73: =SUMIFS($D73:$BM73,$D$6:$BM$6,">="&BQ$2,$D$6:$BM$6,"<="&BQ$6,$D$5:$BM$5,BQ$5) -> 0 | BR73: =SUMIFS($D73:$BM73,$D$6:$BM$6,">="&BR$2,$D$6:$BM$6,"<="&BR$6,$D$5:$BM$5,BR$5) -> 0 | BS73: =SUMIFS($D73:$BM73,$D$6:$BM$6,">="&BS$2,$D$6:$BM$6,"<="&BS$6,$D$5:$BM$5,BS$5) -> 0 | BT73: =SUMIFS($D73:$BM73,$D$6:$BM$6,">="&BT$2,$D$6:$BM$6,"<="&BT$6,$D$5:$BM$5,BT$5) -> 0
A74: INOF | D74: =Renta_Alta!D74+Masivo!D74+Consumo_Inicial!D74 -> 0 | E74: =Renta_Alta!E74+Masivo!E74+Consumo_Inicial!E74 -> 0 | F74: =Renta_Alta!F74+Masivo!F74+Consumo_Inicial!F74 -> 0 | G74: =Renta_Alta!G74+Masivo!G74+Consumo_Inicial!G74 -> 0 | H74: =Renta_Alta!H74+Masivo!H74+Consumo_Inicial!H74 -> 0 | I74: =Renta_Alta!I74+Masivo!I74+Consumo_Inicial!I74 -> 0 | J74: =Renta_Alta!J74+Masivo!J74+Consumo_Inicial!J74 -> 0 | K74: =Renta_Alta!K74+Masivo!K74+Consumo_Inicial!K74 -> 0 | ... BK74: =Renta_Alta!BK74+Masivo!BK74+Consumo_Inicial!BK74 -> 0 | BO74: =SUMIFS($D74:$BM74,$D$6:$BM$6,">="&BO$2,$D$6:$BM$6,"<="&BO$6,$D$5:$BM$5,BO$5) -> 0 | BP74: =SUMIFS($D74:$BM74,$D$6:$BM$6,">="&BP$2,$D$6:$BM$6,"<="&BP$6,$D$5:$BM$5,BP$5) -> 0 | BQ74: =SUMIFS($D74:$BM74,$D$6:$BM$6,">="&BQ$2,$D$6:$BM$6,"<="&BQ$6,$D$5:$BM$5,BQ$5) -> 0 | BR74: =SUMIFS($D74:$BM74,$D$6:$BM$6,">="&BR$2,$D$6:$BM$6,"<="&BR$6,$D$5:$BM$5,BR$5) -> 0 | BS74: =SUMIFS($D74:$BM74,$D$6:$BM$6,">="&BS$2,$D$6:$BM$6,"<="&BS$6,$D$5:$BM$5,BS$5) -> 0 | BT74: =SUMIFS($D74:$BM74,$D$6:$BM$6,">="&BT$2,$D$6:$BM$6,"<="&BT$6,$D$5:$BM$5,BT$5) -> 0
A75: INOF | D75: =Renta_Alta!D75+Masivo!D75+Consumo_Inicial!D75 -> 0 | E75: =Renta_Alta!E75+Masivo!E75+Consumo_Inicial!E75 -> 0 | F75: =Renta_Alta!F75+Masivo!F75+Consumo_Inicial!F75 -> 0 | G75: =Renta_Alta!G75+Masivo!G75+Consumo_Inicial!G75 -> 0 | H75: =Renta_Alta!H75+Masivo!H75+Consumo_Inicial!H75 -> 0 | I75: =Renta_Alta!I75+Masivo!I75+Consumo_Inicial!I75 -> 0 | J75: =Renta_Alta!J75+Masivo!J75+Consumo_Inicial!J75 -> 0 | K75: =Renta_Alta!K75+Masivo!K75+Consumo_Inicial!K75 -> 0 | ... BK75: =Renta_Alta!BK75+Masivo!BK75+Consumo_Inicial!BK75 -> 0 | BO75: =SUMIFS($D75:$BM75,$D$6:$BM$6,">="&BO$2,$D$6:$BM$6,"<="&BO$6,$D$5:$BM$5,BO$5) -> 0 | BP75: =SUMIFS($D75:$BM75,$D$6:$BM$6,">="&BP$2,$D$6:$BM$6,"<="&BP$6,$D$5:$BM$5,BP$5) -> 0 | BQ75: =SUMIFS($D75:$BM75,$D$6:$BM$6,">="&BQ$2,$D$6:$BM$6,"<="&BQ$6,$D$5:$BM$5,BQ$5) -> 0 | BR75: =SUMIFS($D75:$BM75,$D$6:$BM$6,">="&BR$2,$D$6:$BM$6,"<="&BR$6,$D$5:$BM$5,BR$5) -> 0 | BS75: =SUMIFS($D75:$BM75,$D$6:$BM$6,">="&BS$2,$D$6:$BM$6,"<="&BS$6,$D$5:$BM$5,BS$5) -> 0 | BT75: =SUMIFS($D75:$BM75,$D$6:$BM$6,">="&BT$2,$D$6:$BM$6,"<="&BT$6,$D$5:$BM$5,BT$5) -> 0
A76: INOF | D76: =Renta_Alta!D76+Masivo!D76+Consumo_Inicial!D76 -> 0 | E76: =Renta_Alta!E76+Masivo!E76+Consumo_Inicial!E76 -> 0 | F76: =Renta_Alta!F76+Masivo!F76+Consumo_Inicial!F76 -> 0 | G76: =Renta_Alta!G76+Masivo!G76+Consumo_Inicial!G76 -> 0 | H76: =Renta_Alta!H76+Masivo!H76+Consumo_Inicial!H76 -> 0 | I76: =Renta_Alta!I76+Masivo!I76+Consumo_Inicial!I76 -> 0 | J76: =Renta_Alta!J76+Masivo!J76+Consumo_Inicial!J76 -> 0 | K76: =Renta_Alta!K76+Masivo!K76+Consumo_Inicial!K76 -> 0 | ... BK76: =Renta_Alta!BK76+Masivo!BK76+Consumo_Inicial!BK76 -> 0 | BO76: =SUMIFS($D76:$BM76,$D$6:$BM$6,">="&BO$2,$D$6:$BM$6,"<="&BO$6,$D$5:$BM$5,BO$5) -> 0 | BP76: =SUMIFS($D76:$BM76,$D$6:$BM$6,">="&BP$2,$D$6:$BM$6,"<="&BP$6,$D$5:$BM$5,BP$5) -> 0 | BQ76: =SUMIFS($D76:$BM76,$D$6:$BM$6,">="&BQ$2,$D$6:$BM$6,"<="&BQ$6,$D$5:$BM$5,BQ$5) -> 0 | BR76: =SUMIFS($D76:$BM76,$D$6:$BM$6,">="&BR$2,$D$6:$BM$6,"<="&BR$6,$D$5:$BM$5,BR$5) -> 0 | BS76: =SUMIFS($D76:$BM76,$D$6:$BM$6,">="&BS$2,$D$6:$BM$6,"<="&BS$6,$D$5:$BM$5,BS$5) -> 0 | BT76: =SUMIFS($D76:$BM76,$D$6:$BM$6,">="&BT$2,$D$6:$BM$6,"<="&BT$6,$D$5:$BM$5,BT$5) -> 0
A77: INOF | D77: =Renta_Alta!D77+Masivo!D77+Consumo_Inicial!D77 -> 0 | E77: =Renta_Alta!E77+Masivo!E77+Consumo_Inicial!E77 -> 0 | F77: =Renta_Alta!F77+Masivo!F77+Consumo_Inicial!F77 -> 0 | G77: =Renta_Alta!G77+Masivo!G77+Consumo_Inicial!G77 -> 0 | H77: =Renta_Alta!H77+Masivo!H77+Consumo_Inicial!H77 -> 0 | I77: =Renta_Alta!I77+Masivo!I77+Consumo_Inicial!I77 -> 0 | J77: =Renta_Alta!J77+Masivo!J77+Consumo_Inicial!J77 -> 0 | K77: =Renta_Alta!K77+Masivo!K77+Consumo_Inicial!K77 -> 0 | ... BK77: =Renta_Alta!BK77+Masivo!BK77+Consumo_Inicial!BK77 -> 0 | BO77: =SUMIFS($D77:$BM77,$D$6:$BM$6,">="&BO$2,$D$6:$BM$6,"<="&BO$6,$D$5:$BM$5,BO$5) -> 0 | BP77: =SUMIFS($D77:$BM77,$D$6:$BM$6,">="&BP$2,$D$6:$BM$6,"<="&BP$6,$D$5:$BM$5,BP$5) -> 0 | BQ77: =SUMIFS($D77:$BM77,$D$6:$BM$6,">="&BQ$2,$D$6:$BM$6,"<="&BQ$6,$D$5:$BM$5,BQ$5) -> 0 | BR77: =SUMIFS($D77:$BM77,$D$6:$BM$6,">="&BR$2,$D$6:$BM$6,"<="&BR$6,$D$5:$BM$5,BR$5) -> 0 | BS77: =SUMIFS($D77:$BM77,$D$6:$BM$6,">="&BS$2,$D$6:$BM$6,"<="&BS$6,$D$5:$BM$5,BS$5) -> 0 | BT77: =SUMIFS($D77:$BM77,$D$6:$BM$6,">="&BT$2,$D$6:$BM$6,"<="&BT$6,$D$5:$BM$5,BT$5) -> 0
A78: INOF | D78: =Renta_Alta!D78+Masivo!D78+Consumo_Inicial!D78 -> 0 | E78: =Renta_Alta!E78+Masivo!E78+Consumo_Inicial!E78 -> 0 | F78: =Renta_Alta!F78+Masivo!F78+Consumo_Inicial!F78 -> 0 | G78: =Renta_Alta!G78+Masivo!G78+Consumo_Inicial!G78 -> 0 | H78: =Renta_Alta!H78+Masivo!H78+Consumo_Inicial!H78 -> 0 | I78: =Renta_Alta!I78+Masivo!I78+Consumo_Inicial!I78 -> 0 | J78: =Renta_Alta!J78+Masivo!J78+Consumo_Inicial!J78 -> 0 | K78: =Renta_Alta!K78+Masivo!K78+Consumo_Inicial!K78 -> 0 | ... BK78: =Renta_Alta!BK78+Masivo!BK78+Consumo_Inicial!BK78 -> 0 | BO78: =SUMIFS($D78:$BM78,$D$6:$BM$6,">="&BO$2,$D$6:$BM$6,"<="&BO$6,$D$5:$BM$5,BO$5) -> 0 | BP78: =SUMIFS($D78:$BM78,$D$6:$BM$6,">="&BP$2,$D$6:$BM$6,"<="&BP$6,$D$5:$BM$5,BP$5) -> 0 | BQ78: =SUMIFS($D78:$BM78,$D$6:$BM$6,">="&BQ$2,$D$6:$BM$6,"<="&BQ$6,$D$5:$BM$5,BQ$5) -> 0 | BR78: =SUMIFS($D78:$BM78,$D$6:$BM$6,">="&BR$2,$D$6:$BM$6,"<="&BR$6,$D$5:$BM$5,BR$5) -> 0 | BS78: =SUMIFS($D78:$BM78,$D$6:$BM$6,">="&BS$2,$D$6:$BM$6,"<="&BS$6,$D$5:$BM$5,BS$5) -> 0 | BT78: =SUMIFS($D78:$BM78,$D$6:$BM$6,">="&BT$2,$D$6:$BM$6,"<="&BT$6,$D$5:$BM$5,BT$5) -> 0
... A82: INOF | D82: =Renta_Alta!D82+Masivo!D82+Consumo_Inicial!D82 -> 0 | E82: =Renta_Alta!E82+Masivo!E82+Consumo_Inicial!E82 -> 0 | F82: =Renta_Alta!F82+Masivo!F82+Consumo_Inicial!F82 -> 0 | G82: =Renta_Alta!G82+Masivo!G82+Consumo_Inicial!G82 -> 0 | H82: =Renta_Alta!H82+Masivo!H82+Consumo_Inicial!H82 -> 0 | I82: =Renta_Alta!I82+Masivo!I82+Consumo_Inicial!I82 -> 0 | J82: =Renta_Alta!J82+Masivo!J82+Consumo_Inicial!J82 -> 0 | K82: =Renta_Alta!K82+Masivo!K82+Consumo_Inicial!K82 -> 0 | ... BK82: =Renta_Alta!BK82+Masivo!BK82+Consumo_Inicial!BK82 -> 0 | BO82: =SUMIFS($D82:$BM82,$D$6:$BM$6,">="&BO$2,$D$6:$BM$6,"<="&BO$6,$D$5:$BM$5,BO$5) -> 0 | BP82: =SUMIFS($D82:$BM82,$D$6:$BM$6,">="&BP$2,$D$6:$BM$6,"<="&BP$6,$D$5:$BM$5,BP$5) -> 0 | BQ82: =SUMIFS($D82:$BM82,$D$6:$BM$6,">="&BQ$2,$D$6:$BM$6,"<="&BQ$6,$D$5:$BM$5,BQ$5) -> 0 | BR82: =SUMIFS($D82:$BM82,$D$6:$BM$6,">="&BR$2,$D$6:$BM$6,"<="&BR$6,$D$5:$BM$5,BR$5) -> 0 | BS82: =SUMIFS($D82:$BM82,$D$6:$BM$6,">="&BS$2,$D$6:$BM$6,"<="&BS$6,$D$5:$BM$5,BS$5) -> 0 | BT82: =SUMIFS($D82:$BM82,$D$6:$BM$6,">="&BT$2,$D$6:$BM$6,"<="&BT$6,$D$5:$BM$5,BT$5) -> 0
C83: INOF | D83: =SUM(D63:D82) -> 1175.0625 | E83: =SUM(E63:E82) -> 1036.3465 | F83: =SUM(F63:F82) -> 1109.7963 | G83: =SUM(G63:G82) -> 1121.6147 | H83: =SUM(H63:H82) -> 955.99944 | I83: =SUM(I63:I82) -> 775.58718 | J83: =SUM(J63:J82) -> 776.17125 | K83: =SUM(K63:K82) -> 781.01107 | ... BK83: =SUM(BK63:BK82) -> 1087.4192 | BO83: =SUM(BO63:BO82) -> 3539.1767 | BP83: =SUM(BP63:BP82) -> 3188.0696 | BQ83: =SUM(BQ63:BQ82) -> 2130.7027 | BR83: =SUM(BR63:BR82) -> 2981.8976 | BS83: =SUM(BS63:BS82) -> 1934.8019 | BT83: =SUM(BT63:BT82) -> 3321.2053
D84: =[1]Base_Evolutivo!BE1767-D83 -> -1.8467358e-07 | E84: =[1]Base_Evolutivo!BF1767-E83 -> -1.328126e-07 | F84: =[1]Base_Evolutivo!BG1767-F83 -> 3.1720629e-07 | G84: =[1]Base_Evolutivo!BH1767-G83 -> 3.7396899e-07 | H84: =[1]Base_Evolutivo!BI1767-H83 -> -4.1599696e-07 | I84: =[1]Base_Evolutivo!BJ1767-I83 -> -4.3545651e-07 | J84: =[1]Base_Evolutivo!BK1767-J83 -> -2.6532962e-07 | K84: =[1]Base_Evolutivo!BL1767-K83 -> 3.71488e-07 | ... BK84: =[1]Base_Evolutivo!DL1767-BK83 -> -1087.4192
A86: Gastos Operativos | C86: Gasto Directo | D86: =Renta_Alta!D86+Masivo!D86+Consumo_Inicial!D86 -> -3441.8771 | E86: =Renta_Alta!E86+Masivo!E86+Consumo_Inicial!E86 -> -3422.4239 | F86: =Renta_Alta!F86+Masivo!F86+Consumo_Inicial!F86 -> -3786.9534 | G86: =Renta_Alta!G86+Masivo!G86+Consumo_Inicial!G86 -> -3850.8541 | H86: =Renta_Alta!H86+Masivo!H86+Consumo_Inicial!H86 -> -3732.0762 | I86: =Renta_Alta!I86+Masivo!I86+Consumo_Inicial!I86 -> -3815.6451 | J86: =Renta_Alta!J86+Masivo!J86+Consumo_Inicial!J86 -> -3507.4621 | K86: =Renta_Alta!K86+Masivo!K86+Consumo_Inicial!K86 -> -3271.5761 | ... BK86: =Renta_Alta!BK86+Masivo!BK86+Consumo_Inicial!BK86 -> -4960.3928 | BO86: =SUMIFS($D86:$BM86,$D$6:$BM$6,">="&BO$2,$D$6:$BM$6,"<="&BO$6,$D$5:$BM$5,BO$5) -> -13513 | BP86: =SUMIFS($D86:$BM86,$D$6:$BM$6,">="&BP$2,$D$6:$BM$6,"<="&BP$6,$D$5:$BM$5,BP$5) -> -14229.523 | BQ86: =SUMIFS($D86:$BM86,$D$6:$BM$6,">="&BQ$2,$D$6:$BM$6,"<="&BQ$6,$D$5:$BM$5,BQ$5) -> -8738.1638 | BR86: =SUMIFS($D86:$BM86,$D$6:$BM$6,">="&BR$2,$D$6:$BM$6,"<="&BR$6,$D$5:$BM$5,BR$5) -> -13221.309 | BS86: =SUMIFS($D86:$BM86,$D$6:$BM$6,">="&BS$2,$D$6:$BM$6,"<="&BS$6,$D$5:$BM$5,BS$5) -> -10681.847 | BT86: =SUMIFS($D86:$BM86,$D$6:$BM$6,">="&BT$2,$D$6:$BM$6,"<="&BT$6,$D$5:$BM$5,BT$5) -> -10651.254
A87: Gastos Operativos | C87: Gasto Canal | D87: =Renta_Alta!D87+Masivo!D87+Consumo_Inicial!D87 -> -541.6368 | E87: =Renta_Alta!E87+Masivo!E87+Consumo_Inicial!E87 -> -539.37349 | F87: =Renta_Alta!F87+Masivo!F87+Consumo_Inicial!F87 -> -604.01876 | G87: =Renta_Alta!G87+Masivo!G87+Consumo_Inicial!G87 -> -561.7849 | H87: =Renta_Alta!H87+Masivo!H87+Consumo_Inicial!H87 -> -588.53277 | I87: =Renta_Alta!I87+Masivo!I87+Consumo_Inicial!I87 -> -576.11848 | J87: =Renta_Alta!J87+Masivo!J87+Consumo_Inicial!J87 -> -550.83365 | K87: =Renta_Alta!K87+Masivo!K87+Consumo_Inicial!K87 -> -570.20256 | ... BK87: =Renta_Alta!BK87+Masivo!BK87+Consumo_Inicial!BK87 -> -779.05146 | BO87: =SUMIFS($D87:$BM87,$D$6:$BM$6,">="&BO$2,$D$6:$BM$6,"<="&BO$6,$D$5:$BM$5,BO$5) -> -2083.8899 | BP87: =SUMIFS($D87:$BM87,$D$6:$BM$6,">="&BP$2,$D$6:$BM$6,"<="&BP$6,$D$5:$BM$5,BP$5) -> -2290.9509 | BQ87: =SUMIFS($D87:$BM87,$D$6:$BM$6,">="&BQ$2,$D$6:$BM$6,"<="&BQ$6,$D$5:$BM$5,BQ$5) -> -1353.7053 | BR87: =SUMIFS($D87:$BM87,$D$6:$BM$6,">="&BR$2,$D$6:$BM$6,"<="&BR$6,$D$5:$BM$5,BR$5) -> -1939.4395 | BS87: =SUMIFS($D87:$BM87,$D$6:$BM$6,">="&BS$2,$D$6:$BM$6,"<="&BS$6,$D$5:$BM$5,BS$5) -> -1818.9476 | BT87: =SUMIFS($D87:$BM87,$D$6:$BM$6,">="&BT$2,$D$6:$BM$6,"<="&BT$6,$D$5:$BM$5,BT$5) -> -1685.029
A88: Gastos Operativos | C88: Gasto Indirecto | D88: =Renta_Alta!D88+Masivo!D88+Consumo_Inicial!D88 -> -1949.8759 | E88: =Renta_Alta!E88+Masivo!E88+Consumo_Inicial!E88 -> -1943.7463 | F88: =Renta_Alta!F88+Masivo!F88+Consumo_Inicial!F88 -> -2023.505 | G88: =Renta_Alta!G88+Masivo!G88+Consumo_Inicial!G88 -> -2087.6898 | H88: =Renta_Alta!H88+Masivo!H88+Consumo_Inicial!H88 -> -1983.1263 | I88: =Renta_Alta!I88+Masivo!I88+Consumo_Inicial!I88 -> -1831.9622 | J88: =Renta_Alta!J88+Masivo!J88+Consumo_Inicial!J88 -> -2009.4875 | K88: =Renta_Alta!K88+Masivo!K88+Consumo_Inicial!K88 -> -1873.7229 | ... BK88: =Renta_Alta!BK88+Masivo!BK88+Consumo_Inicial!BK88 -> -2825.9055 | BO88: =SUMIFS($D88:$BM88,$D$6:$BM$6,">="&BO$2,$D$6:$BM$6,"<="&BO$6,$D$5:$BM$5,BO$5) -> -8058.6295 | BP88: =SUMIFS($D88:$BM88,$D$6:$BM$6,">="&BP$2,$D$6:$BM$6,"<="&BP$6,$D$5:$BM$5,BP$5) -> -8093.368 | BQ88: =SUMIFS($D88:$BM88,$D$6:$BM$6,">="&BQ$2,$D$6:$BM$6,"<="&BQ$6,$D$5:$BM$5,BQ$5) -> -5566.5519 | BR88: =SUMIFS($D88:$BM88,$D$6:$BM$6,">="&BR$2,$D$6:$BM$6,"<="&BR$6,$D$5:$BM$5,BR$5) -> -7400.2938 | BS88: =SUMIFS($D88:$BM88,$D$6:$BM$6,">="&BS$2,$D$6:$BM$6,"<="&BS$6,$D$5:$BM$5,BS$5) -> -5907.3542 | BT88: =SUMIFS($D88:$BM88,$D$6:$BM$6,">="&BT$2,$D$6:$BM$6,"<="&BT$6,$D$5:$BM$5,BT$5) -> -5917.1271
C89: Gastos Operativos | D89: =SUM(D86:D88) -> -5933.3897 | E89: =SUM(E86:E88) -> -5905.5436 | F89: =SUM(F86:F88) -> -6414.4772 | G89: =SUM(G86:G88) -> -6500.3288 | H89: =SUM(H86:H88) -> -6303.7352 | I89: =SUM(I86:I88) -> -6223.7258 | J89: =SUM(J86:J88) -> -6067.7832 | K89: =SUM(K86:K88) -> -5715.5015 | ... BK89: =SUM(BK86:BK88) -> -8565.3498 | BO89: =SUM(BO86:BO88) -> -23655.52 | BP89: =SUM(BP86:BP88) -> -24613.842 | BQ89: =SUM(BQ86:BQ88) -> -15658.421 | BR89: =SUM(BR86:BR88) -> -22561.043 | BS89: =SUM(BS86:BS88) -> -18408.149 | BT89: =SUM(BT86:BT88) -> -18253.411
D90: =[1]Base_Evolutivo!BE1914-D89 -> 0 | E90: =[1]Base_Evolutivo!BF1914-E89 -> 0 | F90: =[1]Base_Evolutivo!BG1914-F89 -> 0 | G90: =[1]Base_Evolutivo!BH1914-G89 -> 0 | H90: =[1]Base_Evolutivo!BI1914-H89 -> 0 | I90: =[1]Base_Evolutivo!BJ1914-I89 -> 0 | J90: =[1]Base_Evolutivo!BK1914-J89 -> 0 | K90: =[1]Base_Evolutivo!BL1914-K89 -> 0 | ... BK90: =[1]Base_Evolutivo!DL1914-BK89 -> 8565.3498
A91: Extraordinarios | C91: Donaciones | D91: =Renta_Alta!D91+Masivo!D91+Consumo_Inicial!D91 -> 0 | E91: =Renta_Alta!E91+Masivo!E91+Consumo_Inicial!E91 -> 0 | F91: =Renta_Alta!F91+Masivo!F91+Consumo_Inicial!F91 -> 0 | G91: =Renta_Alta!G91+Masivo!G91+Consumo_Inicial!G91 -> 0 | H91: =Renta_Alta!H91+Masivo!H91+Consumo_Inicial!H91 -> 0 | I91: =Renta_Alta!I91+Masivo!I91+Consumo_Inicial!I91 -> 0 | J91: =Renta_Alta!J91+Masivo!J91+Consumo_Inicial!J91 -> 0 | K91: =Renta_Alta!K91+Masivo!K91+Consumo_Inicial!K91 -> 0 | ... BK91: =Renta_Alta!BK91+Masivo!BK91+Consumo_Inicial!BK91 -> 0 | BO91: =SUMIFS($D91:$BM91,$D$6:$BM$6,">="&BO$2,$D$6:$BM$6,"<="&BO$6,$D$5:$BM$5,BO$5) -> 0 | BP91: =SUMIFS($D91:$BM91,$D$6:$BM$6,">="&BP$2,$D$6:$BM$6,"<="&BP$6,$D$5:$BM$5,BP$5) -> 0 | BQ91: =SUMIFS($D91:$BM91,$D$6:$BM$6,">="&BQ$2,$D$6:$BM$6,"<="&BQ$6,$D$5:$BM$5,BQ$5) -> 0 | BR91: =SUMIFS($D91:$BM91,$D$6:$BM$6,">="&BR$2,$D$6:$BM$6,"<="&BR$6,$D$5:$BM$5,BR$5) -> 0 | BS91: =SUMIFS($D91:$BM91,$D$6:$BM$6,">="&BS$2,$D$6:$BM$6,"<="&BS$6,$D$5:$BM$5,BS$5) -> 0 | BT91: =SUMIFS($D91:$BM91,$D$6:$BM$6,">="&BT$2,$D$6:$BM$6,"<="&BT$6,$D$5:$BM$5,BT$5) -> 0
A92: Extraordinarios | C92: Otros | D92: =Renta_Alta!D92+Masivo!D92+Consumo_Inicial!D92 -> 21.58891 | E92: =Renta_Alta!E92+Masivo!E92+Consumo_Inicial!E92 -> 21.39255 | F92: =Renta_Alta!F92+Masivo!F92+Consumo_Inicial!F92 -> 21.18704 | G92: =Renta_Alta!G92+Masivo!G92+Consumo_Inicial!G92 -> 20.96748 | H92: =Renta_Alta!H92+Masivo!H92+Consumo_Inicial!H92 -> 149.72308 | I92: =Renta_Alta!I92+Masivo!I92+Consumo_Inicial!I92 -> 334.01483 | J92: =Renta_Alta!J92+Masivo!J92+Consumo_Inicial!J92 -> 19.92447 | K92: =Renta_Alta!K92+Masivo!K92+Consumo_Inicial!K92 -> 179 | ... BK92: =Renta_Alta!BK92+Masivo!BK92+Consumo_Inicial!BK92 -> -35.312285 | BO92: =SUMIFS($D92:$BM92,$D$6:$BM$6,">="&BO$2,$D$6:$BM$6,"<="&BO$6,$D$5:$BM$5,BO$5) -> -102.84692 | BP92: =SUMIFS($D92:$BM92,$D$6:$BM$6,">="&BP$2,$D$6:$BM$6,"<="&BP$6,$D$5:$BM$5,BP$5) -> -203.04532 | BQ92: =SUMIFS($D92:$BM92,$D$6:$BM$6,">="&BQ$2,$D$6:$BM$6,"<="&BQ$6,$D$5:$BM$5,BQ$5) -> 46.002579 | BR92: =SUMIFS($D92:$BM92,$D$6:$BM$6,">="&BR$2,$D$6:$BM$6,"<="&BR$6,$D$5:$BM$5,BR$5) -> -314.18419 | BS92: =SUMIFS($D92:$BM92,$D$6:$BM$6,">="&BS$2,$D$6:$BM$6,"<="&BS$6,$D$5:$BM$5,BS$5) -> 122.01108 | BT92: =SUMIFS($D92:$BM92,$D$6:$BM$6,">="&BT$2,$D$6:$BM$6,"<="&BT$6,$D$5:$BM$5,BT$5) -> 64.1685
C93: Extraordinarios | D93: =SUM(D91:D92) -> 21.58891 | E93: =SUM(E91:E92) -> 21.39255 | F93: =SUM(F91:F92) -> 21.18704 | G93: =SUM(G91:G92) -> 20.96748 | H93: =SUM(H91:H92) -> 149.72308 | I93: =SUM(I91:I92) -> 334.01483 | J93: =SUM(J91:J92) -> 19.92447 | K93: =SUM(K91:K92) -> 179 | ... BK93: =SUM(BK91:BK92) -> -35.312285 | BO93: =SUM(BO91:BO92) -> -102.84692 | BP93: =SUM(BP91:BP92) -> -203.04532 | BQ93: =SUM(BQ91:BQ92) -> 46.002579 | BR93: =SUM(BR91:BR92) -> -314.18419 | BS93: =SUM(BS91:BS92) -> 122.01108 | BT93: =SUM(BT91:BT92) -> 64.1685
D94: =[1]Base_Evolutivo!BE1951-D93 -> 0 | E94: =[1]Base_Evolutivo!BF1951-E93 -> 0 | F94: =[1]Base_Evolutivo!BG1951-F93 -> 0 | G94: =[1]Base_Evolutivo!BH1951-G93 -> 0 | H94: =[1]Base_Evolutivo!BI1951-H93 -> 0 | I94: =[1]Base_Evolutivo!BJ1951-I93 -> 0 | J94: =[1]Base_Evolutivo!BK1951-J93 -> 0 | K94: =[1]Base_Evolutivo!BL1951-K93 -> 0 | ... BK94: =[1]Base_Evolutivo!DL1951-BK93 -> 35.312285
A95: ROF | C95: Venta de Cartera | D95: =Renta_Alta!D95+Masivo!D95+Consumo_Inicial!D95 -> 0 | E95: =Renta_Alta!E95+Masivo!E95+Consumo_Inicial!E95 -> 0 | F95: =Renta_Alta!F95+Masivo!F95+Consumo_Inicial!F95 -> 0 | G95: =Renta_Alta!G95+Masivo!G95+Consumo_Inicial!G95 -> 0 | H95: =Renta_Alta!H95+Masivo!H95+Consumo_Inicial!H95 -> 0 | I95: =Renta_Alta!I95+Masivo!I95+Consumo_Inicial!I95 -> 0 | J95: =Renta_Alta!J95+Masivo!J95+Consumo_Inicial!J95 -> 0 | K95: =Renta_Alta!K95+Masivo!K95+Consumo_Inicial!K95 -> 0 | ... BK95: =Renta_Alta!BK95+Masivo!BK95+Consumo_Inicial!BK95 -> 0 | BO95: =SUMIFS($D95:$BM95,$D$6:$BM$6,">="&BO$2,$D$6:$BM$6,"<="&BO$6,$D$5:$BM$5,BO$5) -> 1078.1838 | BP95: =SUMIFS($D95:$BM95,$D$6:$BM$6,">="&BP$2,$D$6:$BM$6,"<="&BP$6,$D$5:$BM$5,BP$5) -> 0 | BQ95: =SUMIFS($D95:$BM95,$D$6:$BM$6,">="&BQ$2,$D$6:$BM$6,"<="&BQ$6,$D$5:$BM$5,BQ$5) -> 60.14 | BR95: =SUMIFS($D95:$BM95,$D$6:$BM$6,">="&BR$2,$D$6:$BM$6,"<="&BR$6,$D$5:$BM$5,BR$5) -> 317.56935 | BS95: =SUMIFS($D95:$BM95,$D$6:$BM$6,">="&BS$2,$D$6:$BM$6,"<="&BS$6,$D$5:$BM$5,BS$5) -> 0 | BT95: =SUMIFS($D95:$BM95,$D$6:$BM$6,">="&BT$2,$D$6:$BM$6,"<="&BT$6,$D$5:$BM$5,BT$5) -> 0
C96: ROF | D96: =SUM(D95:D95) -> 0 | E96: =SUM(E95:E95) -> 0 | F96: =SUM(F95:F95) -> 0 | G96: =SUM(G95:G95) -> 0 | H96: =SUM(H95:H95) -> 0 | I96: =SUM(I95:I95) -> 0 | J96: =SUM(J95:J95) -> 0 | K96: =SUM(K95:K95) -> 0 | ... BK96: =SUM(BK95:BK95) -> 0 | BO96: =SUM(BO95) -> 1078.1838 | BP96: =SUM(BP95) -> 0 | BQ96: =SUM(BQ95) -> 60.14 | BR96: =SUM(BR95) -> 317.56935 | BS96: =SUM(BS95) -> 0 | BT96: =SUM(BT95) -> 0
D97: =[1]Base_Evolutivo!BE1730-D96 -> 0 | E97: =[1]Base_Evolutivo!BF1730-E96 -> 0 | F97: =[1]Base_Evolutivo!BG1730-F96 -> 0 | G97: =[1]Base_Evolutivo!BH1730-G96 -> 0 | H97: =[1]Base_Evolutivo!BI1730-H96 -> 0 | I97: =[1]Base_Evolutivo!BJ1730-I96 -> 0 | J97: =[1]Base_Evolutivo!BK1730-J96 -> 0 | K97: =[1]Base_Evolutivo!BL1730-K96 -> 0 | ... BK97: =[1]Base_Evolutivo!DL1730-BK96 -> 0
C98: UAI | D98: =D60+D83+D89+D93+D96 -> 10801.527 | E98: =E60+E83+E89+E93+E96 -> 5052.5456 | F98: =F60+F83+F89+F93+F96 -> 11908.709 | G98: =G60+G83+G89+G93+G96 -> 8161.8952 | H98: =H60+H83+H89+H93+H96 -> 8492.7729 | I98: =I60+I83+I89+I93+I96 -> 9021.4494 | J98: =J60+J83+J89+J93+J96 -> 15654.699 | K98: =K60+K83+K89+K93+K96 -> 11457.785 | ... BK98: =BK60+BK83+BK89+BK93+BK96 -> 13416.59 | BO98: =BO60+BO83+BO89+BO93+BO96 -> 32754.435 | BP98: =BP60+BP83+BP89+BP93+BP96 -> 17058.563 | BQ98: =BQ60+BQ83+BQ89+BQ93+BQ96 -> 20701.708 | BR98: =BR60+BR83+BR89+BR93+BR96 -> 20986.281 | BS98: =BS60+BS83+BS89+BS93+BS96 -> 23605.105 | BT98: =BT60+BT83+BT89+BT93+BT96 -> 27762.782
C102: Prom SFdP | D102: =D11 -> 9588231.8 | E102: =IFERROR(AVERAGE(D11:E11),0) -> 9607179.8 | F102: =IFERROR(AVERAGE(E11:F11),0) -> 9646118.5 | G102: =IFERROR(AVERAGE(F11:G11),0) -> 9690459.2 | H102: =IFERROR(AVERAGE(G11:H11),0) -> 9738036.1 | I102: =IFERROR(AVERAGE(H11:I11),0) -> 9786148.3 | J102: =IFERROR(AVERAGE(I11:J11),0) -> 9815021.3 | K102: =IFERROR(AVERAGE(J11:K11),0) -> 9851256.6 | L102: =IFERROR(AVERAGE(K11:L11),0) -> 9927887.8 | ... AY102: =IFERROR(AVERAGE(AX11:AY11),0) -> 0 | AZ102: =AZ11 -> 11728966 | BA102: =IFERROR(AVERAGE(AZ11:BA11),0) -> 11765257 | BB102: =IFERROR(AVERAGE(BA11:BB11),0) -> 11822680 | BC102: =IFERROR(AVERAGE(BB11:BC11),0) -> 11874078 | BD102: =IFERROR(AVERAGE(BC11:BD11),0) -> 11939241 | BE102: =IFERROR(AVERAGE(BD11:BE11),0) -> 12018631 | BF102: =IFERROR(AVERAGE(BE11:BF11),0) -> 12098524 | BG102: =IFERROR(AVERAGE(BF11:BG11),0) -> 12188337 | BH102: =IFERROR(AVERAGE(BG11:BH11),0) -> 12292233 | ... BK102: =IFERROR(AVERAGE(BJ11:BK11),0) -> 12597580 | BO102: =IFERROR(AVERAGEIFS($D11:$BM11,$D$6:$BM$6,">="&EOMONTH(BO$2,-1),$D$6:$BM$6,"<="&BO$6,$D$5:$BM$5,BO$5,$D11:$BM11,"<>0"),0) -> 11811182 | BP102: =IFERROR(AVERAGEIFS($D11:$BM11,$D$6:$BM$6,">="&EOMONTH(BP$2,-1),$D$6:$BM$6,"<="&BP$6,$D$5:$BM$5,BP$5,$D11:$BM11,"<>0"),0) -> 11791442 | BQ102: =IFERROR(AVERAGEIFS($D11:$BM11,$D$6:$BM$6,">="&EOMONTH(BQ$2,-1),$D$6:$BM$6,"<="&BQ$6,$D$5:$BM$5,BQ$5,$D11:$BM11,"<>0"),0) -> 11779256 | BR102: =IFERROR(AVERAGEIFS($D11:$BM11,$D$6:$BM$6,">="&EOMONTH(BR$2,-1),$D$6:$BM$6,"<="&BR$6,$D$5:$BM$5,BR$5,$D11:$BM11,"<>0"),0) -> 10891487 | BS102: =IFERROR(AVERAGEIFS($D11:$BM11,$D$6:$BM$6,">="&EOMONTH(BS$2,-1),$D$6:$BM$6,"<="&BS$6,$D$5:$BM$5,BS$5,$D11:$BM11,"<>0"),0) -> 10163458 | BT102: =IFERROR(AVERAGEIFS($D11:$BM11,$D$6:$BM$6,">="&EOMONTH(BT$2,-1),$D$6:$BM$6,"<="&BT$6,$D$5:$BM$5,BT$5,$D11:$BM11,"<>0"),0) -> 9626822.9

Sheet Desempeño_Financiero
B1: 46112 | D1: Mensual | W1: Acumulado
B2: Desempeño Financiero
B3: En S/. Miles | C3: N° dias T.Imp | D3: =DAY(D6) -> 31 | E3: =DAY(E6) -> 31 | F3: =DAY(F6) -> 28 | G3: =DAY(G6) -> 31 | H3: =DAY(H6) -> 31 | I3: =DAY(I6) -> 31
C4: N° dias FTP | D4: =DAY(D6) -> 31 | E4: =DAY(E6) -> 31 | F4: =DAY(F6) -> 28 | G4: =DAY(G6) -> 31 | H4: =DAY(H6) -> 31 | I4: =DAY(I6) -> 31
C5: Tipo | D5: R | E5: P | F5: R | G5: R | H5: R | I5: R | K5: Variación S/. | Q5: Variación % | AD5: Variación S/. | AJ5: Variación %
C6: Total_Producto | D6: =$B$1 -> 46112 | E6: =D6 -> 46112 | F6: =EOMONTH(D6,-1) -> 46081 | G6: =EOMONTH(D6,-12) -> 45747 | H6: =EOMONTH(D6,-24) -> 45382 | I6: =EOMONTH(D6,-36) -> 45016 | K6: =E6 -> 46112 | L6: =F6 -> 46081 | M6: =G6 -> 45747 | N6: =H6 -> 45382 | O6: =I6 -> 45016 | Q6: =K6 -> 46112 | R6: =L6 -> 46081 | S6: =M6 -> 45747 | T6: =N6 -> 45382 | U6: =O6 -> 45016 | W6: =$B$1 -> 46112 | X6: =W6 -> 46112 | Y6: =EOMONTH(W6,-1) -> 46081 | Z6: =EOMONTH(W6,-12) -> 45747 | AA6: =EOMONTH(W6,-24) -> 45382 | AB6: =EOMONTH(W6,-36) -> 45016 | AD6: =X6 -> 46112 | AE6: =Y6 -> 46081 | AF6: =Z6 -> 45747 | AG6: =AA6 -> 45382 | AH6: =AB6 -> 45016 | AJ6: =AD6 -> 46112 | AK6: =AE6 -> 46081 | AL6: =AF6 -> 45747 | AM6: =AG6 -> 45382 | AN6: =AH6 -> 45016
A8: SALDO_FDP | C8: Vigente | D8: {=_xlfn.XLOOKUP(1, (INDIRECT("'"&$C$6&"'!$6:$6")=D$6)* (INDIRECT("'"&$C$6&"'!$5:$5")=D$5), INDIRECT("'"&$C$6&"'!"&ROW()&":"&ROW()) )} -> 11525777 | E8: {=_xlfn.XLOOKUP(1, (INDIRECT("'"&$C$6&"'!$6:$6")=E$6)* (INDIRECT("'"&$C$6&"'!$5:$5")=E$5), INDIRECT("'"&$C$6&"'!"&ROW()&":"&ROW()) )} -> 11438229 | F8: {=_xlfn.XLOOKUP(1, (INDIRECT("'"&$C$6&"'!$6:$6")=F$6)* (INDIRECT("'"&$C$6&"'!$5:$5")=F$5), INDIRECT("'"&$C$6&"'!"&ROW()&":"&ROW()) )} -> 11478076 | G8: {=_xlfn.XLOOKUP(1, (INDIRECT("'"&$C$6&"'!$6:$6")=G$6)* (INDIRECT("'"&$C$6&"'!$5:$5")=G$5), INDIRECT("'"&$C$6&"'!"&ROW()&":"&ROW()) )} -> 10587478 | H8: {=_xlfn.XLOOKUP(1, (INDIRECT("'"&$C$6&"'!$6:$6")=H$6)* (INDIRECT("'"&$C$6&"'!$5:$5")=H$5), INDIRECT("'"&$C$6&"'!"&ROW()&":"&ROW()) )} -> 9915549.8 | I8: {=_xlfn.XLOOKUP(1, (INDIRECT("'"&$C$6&"'!$6:$6")=I$6)* (INDIRECT("'"&$C$6&"'!$5:$5")=I$5), INDIRECT("'"&$C$6&"'!"&ROW()&":"&ROW()) )} -> 9379816.8 | K8: =$D8-E8 -> 87547.535 | L8: =$D8-F8 -> 47700.74 | M8: =$D8-G8 -> 938298.64 | N8: =$D8-H8 -> 1610226.7 | O8: =$D8-I8 -> 2145959.7 | Q8: =IFERROR($D8/E8-1,0) -> 0.0076539415 | R8: =IFERROR($D8/F8-1,0) -> 0.0041558133 | S8: =IFERROR($D8/G8-1,0) -> 0.088623434 | T8: =IFERROR($D8/H8-1,0) -> 0.16239409 | U8: =IFERROR($D8/I8-1,0) -> 0.22878482 | W8: {=INDIRECT("'"&$C$6&"'!"&ADDRESS(ROW(),COLUMN()+44))} -> 11525777 | X8: {=INDIRECT("'"&$C$6&"'!"&ADDRESS(ROW(),COLUMN()+44))} -> 11438229 | Y8: {=INDIRECT("'"&$C$6&"'!"&ADDRESS(ROW(),COLUMN()+44))} -> 11478076 | Z8: {=INDIRECT("'"&$C$6&"'!"&ADDRESS(ROW(),COLUMN()+44))} -> 10587478 | AA8: {=INDIRECT("'"&$C$6&"'!"&ADDRESS(ROW(),COLUMN()+44))} -> 9915549.8 | AB8: {=INDIRECT("'"&$C$6&"'!"&ADDRESS(ROW(),COLUMN()+44))} -> 9379816.8 | AD8: =$W8-X8 -> 87547.535 | AE8: =$W8-Y8 -> 47700.74 | AF8: =$W8-Z8 -> 938298.64 | AG8: =$W8-AA8 -> 1610226.7 | AH8: =$W8-AB8 -> 2145959.7 | AJ8: =IFERROR($W8/X8-1,0) -> 0.0076539415 | AK8: =IFERROR($W8/Y8-1,0) -> 0.0041558133 | AL8: =IFERROR($W8/Z8-1,0) -> 0.088623434 | AM8: =IFERROR($W8/AA8-1,0) -> 0.16239409 | AN8: =IFERROR($W8/AB8-1,0) -> 0.22878482
A9: SALDO_FDP | C9: Refinanciado | D9: {=_xlfn.XLOOKUP(1, (INDIRECT("'"&$C$6&"'!$6:$6")=D$6)* (INDIRECT("'"&$C$6&"'!$5:$5")=D$5), INDIRECT("'"&$C$6&"'!"&ROW()&":"&ROW()) )} -> 34203.92 | E9: {=_xlfn.XLOOKUP(1, (INDIRECT("'"&$C$6&"'!$6:$6")=E$6)* (INDIRECT("'"&$C$6&"'!$5:$5")=E$5), INDIRECT("'"&$C$6&"'!"&ROW()&":"&ROW()) )} -> 29770.187 | F9: {=_xlfn.XLOOKUP(1, (INDIRECT("'"&$C$6&"'!$6:$6")=F$6)* (INDIRECT("'"&$C$6&"'!$5:$5")=F$5), INDIRECT("'"&$C$6&"'!"&ROW()&":"&ROW()) )} -> 32640.44 | G9: {=_xlfn.XLOOKUP(1, (INDIRECT("'"&$C$6&"'!$6:$6")=G$6)* (INDIRECT("'"&$C$6&"'!$5:$5")=G$5), INDIRECT("'"&$C$6&"'!"&ROW()&":"&ROW()) )} -> 29921.003 | H9: {=_xlfn.XLOOKUP(1, (INDIRECT("'"&$C$6&"'!$6:$6")=H$6)* (INDIRECT("'"&$C$6&"'!$5:$5")=H$5), INDIRECT("'"&$C$6&"'!"&ROW()&":"&ROW()) )} -> 31857.707 | I9: {=_xlfn.XLOOKUP(1, (INDIRECT("'"&$C$6&"'!$6:$6")=I$6)* (INDIRECT("'"&$C$6&"'!$5:$5")=I$5), INDIRECT("'"&$C$6&"'!"&ROW()&":"&ROW()) )} -> 36652.88 | K9: =$D9-E9 -> 4433.7333 | L9: =$D9-F9 -> 1563.48 | M9: =$D9-G9 -> 4282.9173 | N9: =$D9-H9 -> 2346.213 | O9: =$D9-I9 -> -2448.9601 | Q9: =IFERROR($D9/E9-1,0) -> 0.148932 | R9: =IFERROR($D9/F9-1,0) -> 0.04790009 | S9: =IFERROR($D9/G9-1,0) -> 0.14314083 | T9: =IFERROR($D9/H9-1,0) -> 0.073646639 | U9: =IFERROR($D9/I9-1,0) -> -0.066814944 | W9: {=INDIRECT("'"&$C$6&"'!"&ADDRESS(ROW(),COLUMN()+44))} -> 34203.92 | X9: {=INDIRECT("'"&$C$6&"'!"&ADDRESS(ROW(),COLUMN()+44))} -> 29770.187 | Y9: {=INDIRECT("'"&$C$6&"'!"&ADDRESS(ROW(),COLUMN()+44))} -> 32640.44 | Z9: {=INDIRECT("'"&$C$6&"'!"&ADDRESS(ROW(),COLUMN()+44))} -> 29921.003 | AA9: {=INDIRECT("'"&$C$6&"'!"&ADDRESS(ROW(),COLUMN()+44))} -> 31857.707 | AB9: {=INDIRECT("'"&$C$6&"'!"&ADDRESS(ROW(),COLUMN()+44))} -> 36652.88 | AD9: =$W9-X9 -> 4433.7333 | AE9: =$W9-Y9 -> 1563.48 | AF9: =$W9-Z9 -> 4282.9173 | AG9: =$W9-AA9 -> 2346.213 | AH9: =$W9-AB9 -> -2448.9601 | AJ9: =IFERROR($W9/X9-1,0) -> 0.148932 | AK9: =IFERROR($W9/Y9-1,0) -> 0.04790009 | AL9: =IFERROR($W9/Z9-1,0) -> 0.14314083 | AM9: =IFERROR($W9/AA9-1,0) -> 0.073646639 | AN9: =IFERROR($W9/AB9-1,0) -> -0.066814944
A10: SALDO_FDP | C10: Vencido y Judicial | D10: {=_xlfn.XLOOKUP(1, (INDIRECT("'"&$C$6&"'!$6:$6")=D$6)* (INDIRECT("'"&$C$6&"'!$5:$5")=D$5), INDIRECT("'"&$C$6&"'!"&ROW()&":"&ROW()) )} -> 346980.86 | E10: {=_xlfn.XLOOKUP(1, (INDIRECT("'"&$C$6&"'!$6:$6")=E$6)* (INDIRECT("'"&$C$6&"'!$5:$5")=E$5), INDIRECT("'"&$C$6&"'!"&ROW()&":"&ROW()) )} -> 375811.31 | F10: {=_xlfn.XLOOKUP(1, (INDIRECT("'"&$C$6&"'!$6:$6")=F$6)* (INDIRECT("'"&$C$6&"'!$5:$5")=F$5), INDIRECT("'"&$C$6&"'!"&ROW()&":"&ROW()) )} -> 338634.42 | G10: {=_xlfn.XLOOKUP(1, (INDIRECT("'"&$C$6&"'!$6:$6")=G$6)* (INDIRECT("'"&$C$6&"'!$5:$5")=G$5), INDIRECT("'"&$C$6&"'!"&ROW()&":"&ROW()) )} -> 343769.54 | H10: {=_xlfn.XLOOKUP(1, (INDIRECT("'"&$C$6&"'!$6:$6")=H$6)* (INDIRECT("'"&$C$6&"'!$5:$5")=H$5), INDIRECT("'"&$C$6&"'!"&ROW()&":"&ROW()) )} -> 294205.11 | I10: {=_xlfn.XLOOKUP(1, (INDIRECT("'"&$C$6&"'!$6:$6")=I$6)* (INDIRECT("'"&$C$6&"'!$5:$5")=I$5), INDIRECT("'"&$C$6&"'!"&ROW()&":"&ROW()) )} -> 249639.32 | K10: =$D10-E10 -> -28830.446 | L10: =$D10-F10 -> 8346.44 | M10: =$D10-G10 -> 3211.3158 | N10: =$D10-H10 -> 52775.75 | O10: =$D10-I10 -> 97341.545 | Q10: =IFERROR($D10/E10-1,0) -> -0.076715218 | R10: =IFERROR($D10/F10-1,0) -> 0.024647347 | S10: =IFERROR($D10/G10-1,0) -> 0.0093414785 | T10: =IFERROR($D10/H10-1,0) -> 0.17938421 | U10: =IFERROR($D10/I10-1,0) -> 0.38992874 | W10: {=INDIRECT("'"&$C$6&"'!"&ADDRESS(ROW(),COLUMN()+44))} -> 346980.86 | X10: {=INDIRECT("'"&$C$6&"'!"&ADDRESS(ROW(),COLUMN()+44))} -> 375811.31 | Y10: {=INDIRECT("'"&$C$6&"'!"&ADDRESS(ROW(),COLUMN()+44))} -> 338634.42 | Z10: {=INDIRECT("'"&$C$6&"'!"&ADDRESS(ROW(),COLUMN()+44))} -> 343769.54 | AA10: {=INDIRECT("'"&$C$6&"'!"&ADDRESS(ROW(),COLUMN()+44))} -> 294205.11 | AB10: {=INDIRECT("'"&$C$6&"'!"&ADDRESS(ROW(),COLUMN()+44))} -> 249639.32 | AD10: =$W10-X10 -> -28830.446 | AE10: =$W10-Y10 -> 8346.44 | AF10: =$W10-Z10 -> 3211.3158 | AG10: =$W10-AA10 -> 52775.75 | AH10: =$W10-AB10 -> 97341.545 | AJ10: =IFERROR($W10/X10-1,0) -> -0.076715218 | AK10: =IFERROR($W10/Y10-1,0) -> 0.024647347 | AL10: =IFERROR($W10/Z10-1,0) -> 0.0093414785 | AM10: =IFERROR($W10/AA10-1,0) -> 0.17938421 | AN10: =IFERROR($W10/AB10-1,0) -> 0.38992874
C11: Saldo FdP | D11: =SUM(D8:D10) -> 11906961 | E11: =SUM(E8:E10) -> 11843810 | F11: =SUM(F8:F10) -> 11849351 | G11: =SUM(G8:G10) -> 10961168 | H11: =SUM(H8:H10) -> 10241613 | I11: =SUM(I8:I10) -> 9666109 | K11: =$D11-E11 -> 63150.823 | L11: =$D11-F11 -> 57610.66 | M11: =$D11-G11 -> 945792.88 | N11: =$D11-H11 -> 1665348.7 | O11: =$D11-I11 -> 2240852.3 | Q11: =IFERROR($D11/E11-1,0) -> 0.0053319683 | R11: =IFERROR($D11/F11-1,0) -> 0.0048619255 | S11: =IFERROR($D11/G11-1,0) -> 0.086285772 | T11: =IFERROR($D11/H11-1,0) -> 0.1626061 | U11: =IFERROR($D11/I11-1,0) -> 0.23182568 | W11: =SUM(W8:W10) -> 11906961 | X11: =SUM(X8:X10) -> 11843810 | Y11: =SUM(Y8:Y10) -> 11849351 | Z11: =SUM(Z8:Z10) -> 10961168 | AA11: =SUM(AA8:AA10) -> 10241613 | AB11: =SUM(AB8:AB10) -> 9666109 | AD11: =$W11-X11 -> 63150.823 | AE11: =$W11-Y11 -> 57610.66 | AF11: =$W11-Z11 -> 945792.88 | AG11: =$W11-AA11 -> 1665348.7 | AH11: =$W11-AB11 -> 2240852.3 | AJ11: =IFERROR($W11/X11-1,0) -> 0.0053319683 | AK11: =IFERROR($W11/Y11-1,0) -> 0.0048619255 | AL11: =IFERROR($W11/Z11-1,0) -> 0.086285772 | AM11: =IFERROR($W11/AA11-1,0) -> 0.1626061 | AN11: =IFERROR($W11/AB11-1,0) -> 0.23182568
A14: SALDO_PROM | C14: Vigente | D14: {=_xlfn.XLOOKUP(1, (INDIRECT("'"&$C$6&"'!$6:$6")=D$6)* (INDIRECT("'"&$C$6&"'!$5:$5")=D$5), INDIRECT("'"&$C$6&"'!"&ROW()&":"&ROW()) )} -> 11451670 | E14: {=_xlfn.XLOOKUP(1, (INDIRECT("'"&$C$6&"'!$6:$6")=E$6)* (INDIRECT("'"&$C$6&"'!$5:$5")=E$5), INDIRECT("'"&$C$6&"'!"&ROW()&":"&ROW()) )} -> 11344716 | F14: {=_xlfn.XLOOKUP(1, (INDIRECT("'"&$C$6&"'!$6:$6")=F$6)* (INDIRECT("'"&$C$6&"'!$5:$5")=F$5), INDIRECT("'"&$C$6&"'!"&ROW()&":"&ROW()) )} -> 11375328 | G14: {=_xlfn.XLOOKUP(1, (INDIRECT("'"&$C$6&"'!$6:$6")=G$6)* (INDIRECT("'"&$C$6&"'!$5:$5")=G$5), INDIRECT("'"&$C$6&"'!"&ROW()&":"&ROW()) )} -> 10528771 | H14: {=_xlfn.XLOOKUP(1, (INDIRECT("'"&$C$6&"'!$6:$6")=H$6)* (INDIRECT("'"&$C$6&"'!$5:$5")=H$5), INDIRECT("'"&$C$6&"'!"&ROW()&":"&ROW()) )} -> 9850997.1 | I14: {=_xlfn.XLOOKUP(1, (INDIRECT("'"&$C$6&"'!$6:$6")=I$6)* (INDIRECT("'"&$C$6&"'!$5:$5")=I$5), INDIRECT("'"&$C$6&"'!"&ROW()&":"&ROW()) )} -> 9331212.8 | K14: =$D14-E14 -> 106953.22 | L14: =$D14-F14 -> 76341.22 | M14: =$D14-G14 -> 922898.23 | N14: =$D14-H14 -> 1600672.4 | O14: =$D14-I14 -> 2120456.8 | Q14: =IFERROR($D14/E14-1,0) -> 0.0094275796 | R14: =IFERROR($D14/F14-1,0) -> 0.0067111223 | S14: =IFERROR($D14/G14-1,0) -> 0.087654883 | T14: =IFERROR($D14/H14-1,0) -> 0.16248837 | U14: =IFERROR($D14/I14-1,0) -> 0.22724343 | W14: {=INDIRECT("'"&$C$6&"'!"&ADDRESS(ROW(),COLUMN()+44))} -> 11375136 | X14: {=INDIRECT("'"&$C$6&"'!"&ADDRESS(ROW(),COLUMN()+44))} -> 11296486 | Y14: {=INDIRECT("'"&$C$6&"'!"&ADDRESS(ROW(),COLUMN()+44))} -> 11336870 | Z14: {=INDIRECT("'"&$C$6&"'!"&ADDRESS(ROW(),COLUMN()+44))} -> 10480867 | AA14: {=INDIRECT("'"&$C$6&"'!"&ADDRESS(ROW(),COLUMN()+44))} -> 9799459.6 | AB14: {=INDIRECT("'"&$C$6&"'!"&ADDRESS(ROW(),COLUMN()+44))} -> 9296415.6 | AD14: =$W14-X14 -> 78650.09 | AE14: =$W14-Y14 -> 38266.585 | AF14: =$W14-Z14 -> 894268.99 | AG14: =$W14-AA14 -> 1575676.8 | AH14: =$W14-AB14 -> 2078720.8 | AJ14: =IFERROR($W14/X14-1,0) -> 0.0069623499 | AK14: =IFERROR($W14/Y14-1,0) -> 0.0033754101 | AL14: =IFERROR($W14/Z14-1,0) -> 0.085323948 | AM14: =IFERROR($W14/AA14-1,0) -> 0.16079222 | AN14: =IFERROR($W14/AB14-1,0) -> 0.22360454
A15: SALDO_PROM | C15: Refinanciado | D15: {=_xlfn.XLOOKUP(1, (INDIRECT("'"&$C$6&"'!$6:$6")=D$6)* (INDIRECT("'"&$C$6&"'!$5:$5")=D$5), INDIRECT("'"&$C$6&"'!"&ROW()&":"&ROW()) )} -> 33692.73 | E15: {=_xlfn.XLOOKUP(1, (INDIRECT("'"&$C$6&"'!$6:$6")=E$6)* (INDIRECT("'"&$C$6&"'!$5:$5")=E$5), INDIRECT("'"&$C$6&"'!"&ROW()&":"&ROW()) )} -> 29533.241 | F15: {=_xlfn.XLOOKUP(1, (INDIRECT("'"&$C$6&"'!$6:$6")=F$6)* (INDIRECT("'"&$C$6&"'!$5:$5")=F$5), INDIRECT("'"&$C$6&"'!"&ROW()&":"&ROW()) )} -> 31737.91 | G15: {=_xlfn.XLOOKUP(1, (INDIRECT("'"&$C$6&"'!$6:$6")=G$6)* (INDIRECT("'"&$C$6&"'!$5:$5")=G$5), INDIRECT("'"&$C$6&"'!"&ROW()&":"&ROW()) )} -> 29133.809 | H15: {=_xlfn.XLOOKUP(1, (INDIRECT("'"&$C$6&"'!$6:$6")=H$6)* (INDIRECT("'"&$C$6&"'!$5:$5")=H$5), INDIRECT("'"&$C$6&"'!"&ROW()&":"&ROW()) )} -> 31397.627 | I15: {=_xlfn.XLOOKUP(1, (INDIRECT("'"&$C$6&"'!$6:$6")=I$6)* (INDIRECT("'"&$C$6&"'!$5:$5")=I$5), INDIRECT("'"&$C$6&"'!"&ROW()&":"&ROW()) )} -> 33680.968 | K15: =$D15-E15 -> 4159.4893 | L15: =$D15-F15 -> 1954.82 | M15: =$D15-G15 -> 4558.9213 | N15: =$D15-H15 -> 2295.1028 | O15: =$D15-I15 -> 11.762297 | Q15: =IFERROR($D15/E15-1,0) -> 0.14084094 | R15: =IFERROR($D15/F15-1,0) -> 0.061592588 | S15: =IFERROR($D15/G15-1,0) -> 0.15648216 | T15: =IFERROR($D15/H15-1,0) -> 0.073097969 | U15: =IFERROR($D15/I15-1,0) -> 0.00034922681 | W15: {=INDIRECT("'"&$C$6&"'!"&ADDRESS(ROW(),COLUMN()+44))} -> 32543.543 | X15: {=INDIRECT("'"&$C$6&"'!"&ADDRESS(ROW(),COLUMN()+44))} -> 29423.438 | Y15: {=INDIRECT("'"&$C$6&"'!"&ADDRESS(ROW(),COLUMN()+44))} -> 31968.95 | Z15: {=INDIRECT("'"&$C$6&"'!"&ADDRESS(ROW(),COLUMN()+44))} -> 29449.772 | AA15: {=INDIRECT("'"&$C$6&"'!"&ADDRESS(ROW(),COLUMN()+44))} -> 31300.342 | AB15: {=INDIRECT("'"&$C$6&"'!"&ADDRESS(ROW(),COLUMN()+44))} -> 33454.003 | AD15: =$W15-X15 -> 3120.1052 | AE15: =$W15-Y15 -> 574.59333 | AF15: =$W15-Z15 -> 3093.7717 | AG15: =$W15-AA15 -> 1243.2017 | AH15: =$W15-AB15 -> -910.45962 | AJ15: =IFERROR($W15/X15-1,0) -> 0.10604149 | AK15: =IFERROR($W15/Y15-1,0) -> 0.017973482 | AL15: =IFERROR($W15/Z15-1,0) -> 0.10505248 | AM15: =IFERROR($W15/AA15-1,0) -> 0.03971847 | AN15: =IFERROR($W15/AB15-1,0) -> -0.027215267
A16: SALDO_PROM | C16: Vencido y Judicial | D16: {=_xlfn.XLOOKUP(1, (INDIRECT("'"&$C$6&"'!$6:$6")=D$6)* (INDIRECT("'"&$C$6&"'!$5:$5")=D$5), INDIRECT("'"&$C$6&"'!"&ROW()&":"&ROW()) )} -> 352941.66 | E16: {=_xlfn.XLOOKUP(1, (INDIRECT("'"&$C$6&"'!$6:$6")=E$6)* (INDIRECT("'"&$C$6&"'!$5:$5")=E$5), INDIRECT("'"&$C$6&"'!"&ROW()&":"&ROW()) )} -> 372710.8 | F16: {=_xlfn.XLOOKUP(1, (INDIRECT("'"&$C$6&"'!$6:$6")=F$6)* (INDIRECT("'"&$C$6&"'!$5:$5")=F$5), INDIRECT("'"&$C$6&"'!"&ROW()&":"&ROW()) )} -> 357954.66 | G16: {=_xlfn.XLOOKUP(1, (INDIRECT("'"&$C$6&"'!$6:$6")=G$6)* (INDIRECT("'"&$C$6&"'!$5:$5")=G$5), INDIRECT("'"&$C$6&"'!"&ROW()&":"&ROW()) )} -> 347248.65 | H16: {=_xlfn.XLOOKUP(1, (INDIRECT("'"&$C$6&"'!$6:$6")=H$6)* (INDIRECT("'"&$C$6&"'!$5:$5")=H$5), INDIRECT("'"&$C$6&"'!"&ROW()&":"&ROW()) )} -> 306654.19 | I16: {=_xlfn.XLOOKUP(1, (INDIRECT("'"&$C$6&"'!$6:$6")=I$6)* (INDIRECT("'"&$C$6&"'!$5:$5")=I$5), INDIRECT("'"&$C$6&"'!"&ROW()&":"&ROW()) )} -> 256054.8 | K16: =$D16-E16 -> -19769.145 | L16: =$D16-F16 -> -5013 | M16: =$D16-G16 -> 5693.0116 | N16: =$D16-H16 -> 46287.468 | O16: =$D16-I16 -> 96886.865 | Q16: =IFERROR($D16/E16-1,0) -> -0.053041512 | R16: =IFERROR($D16/F16-1,0) -> -0.014004567 | S16: =IFERROR($D16/G16-1,0) -> 0.016394626 | T16: =IFERROR($D16/H16-1,0) -> 0.15094354 | U16: =IFERROR($D16/I16-1,0) -> 0.37838332 | W16: {=INDIRECT("'"&$C$6&"'!"&ADDRESS(ROW(),COLUMN()+44))} -> 358023.76 | X16: {=INDIRECT("'"&$C$6&"'!"&ADDRESS(ROW(),COLUMN()+44))} -> 369759.67 | Y16: {=INDIRECT("'"&$C$6&"'!"&ADDRESS(ROW(),COLUMN()+44))} -> 360564.81 | Z16: {=INDIRECT("'"&$C$6&"'!"&ADDRESS(ROW(),COLUMN()+44))} -> 340976.31 | AA16: {=INDIRECT("'"&$C$6&"'!"&ADDRESS(ROW(),COLUMN()+44))} -> 304066.03 | AB16: {=INDIRECT("'"&$C$6&"'!"&ADDRESS(ROW(),COLUMN()+44))} -> 252506.24 | AD16: =$W16-X16 -> -11735.908 | AE16: =$W16-Y16 -> -2541.05 | AF16: =$W16-Z16 -> 17047.449 | AG16: =$W16-AA16 -> 53957.727 | AH16: =$W16-AB16 -> 105517.52 | AJ16: =IFERROR($W16/X16-1,0) -> -0.031739288 | AK16: =IFERROR($W16/Y16-1,0) -> -0.0070474154 | AL16: =IFERROR($W16/Z16-1,0) -> 0.049995992 | AM16: =IFERROR($W16/AA16-1,0) -> 0.17745398 | AN16: =IFERROR($W16/AB16-1,0) -> 0.41788081
C17: Saldo Prom | D17: =SUM(D14:D16) -> 11838304 | E17: =SUM(E14:E16) -> 11746960 | F17: =SUM(F14:F16) -> 11765021 | G17: =SUM(G14:G16) -> 10905154 | H17: =SUM(H14:H16) -> 10189049 | I17: =SUM(I14:I16) -> 9620948.6 | K17: =$D17-E17 -> 91343.561 | L17: =$D17-F17 -> 73283.04 | M17: =$D17-G17 -> 933150.16 | N17: =$D17-H17 -> 1649255 | O17: =$D17-I17 -> 2217355.4 | Q17: =IFERROR($D17/E17-1,0) -> 0.0077759317 | R17: =IFERROR($D17/F17-1,0) -> 0.0062288916 | S17: =IFERROR($D17/G17-1,0) -> 0.085569647 | T17: =IFERROR($D17/H17-1,0) -> 0.16186545 | U17: =IFERROR($D17/I17-1,0) -> 0.2304716 | W17: =SUM(W14:W16) -> 11765704 | X17: =SUM(X14:X16) -> 11695669 | Y17: =SUM(Y14:Y16) -> 11729404 | Z17: =SUM(Z14:Z16) -> 10851293 | AA17: =SUM(AA14:AA16) -> 10134826 | AB17: =SUM(AB14:AB16) -> 9582375.9 | AD17: =$W17-X17 -> 70034.287 | AE17: =$W17-Y17 -> 36300.128 | AF17: =$W17-Z17 -> 914410.21 | AG17: =$W17-AA17 -> 1630877.8 | AH17: =$W17-AB17 -> 2183327.8 | AJ17: =IFERROR($W17/X17-1,0) -> 0.0059880529 | AK17: =IFERROR($W17/Y17-1,0) -> 0.0030947975 | AL17: =IFERROR($W17/Z17-1,0) -> 0.084267393 | AM17: =IFERROR($W17/AA17-1,0) -> 0.16091818 | AN17: =IFERROR($W17/AB17-1,0) -> 0.22784828
C20: Vigente | D20: =IFERROR(((1+D38/D14)^(360/D$3))-1,0) -> 0.074352368 | E20: =IFERROR(((1+E38/E14)^(360/E$3))-1,0) -> 0.073317783 | F20: =IFERROR(((1+F38/F14)^(360/F$3))-1,0) -> 0.074713591 | G20: =IFERROR(((1+G38/G14)^(360/G$3))-1,0) -> 0.073833102 | H20: =IFERROR(((1+H38/H14)^(360/H$3))-1,0) -> 0.073558084 | I20: =IFERROR(((1+I38/I14)^(360/I$3))-1,0) -> 0.071198038 | Q20: =($D20-E20)*10000 -> 10.345857 | R20: =($D20-F20)*10000 -> -3.6122308 | S20: =($D20-G20)*10000 -> 5.1926654 | T20: =($D20-H20)*10000 -> 7.9428443 | U20: =($D20-I20)*10000 -> 31.543308 | W20: {=INDIRECT("'"&$C$6&"'!"&ADDRESS(ROW(),COLUMN()+44))} -> 0.07450647 | X20: {=INDIRECT("'"&$C$6&"'!"&ADDRESS(ROW(),COLUMN()+44))} -> 0.073578815 | Y20: {=INDIRECT("'"&$C$6&"'!"&ADDRESS(ROW(),COLUMN()+44))} -> 0.07457484 | Z20: {=INDIRECT("'"&$C$6&"'!"&ADDRESS(ROW(),COLUMN()+44))} -> 0.074039433 | AA20: {=INDIRECT("'"&$C$6&"'!"&ADDRESS(ROW(),COLUMN()+44))} -> 0.073188903 | AB20: {=INDIRECT("'"&$C$6&"'!"&ADDRESS(ROW(),COLUMN()+44))} -> 0.070913737 | AJ20: =($W20-X20)*10000 -> 9.2765552 | AK20: =($W20-Y20)*10000 -> -0.68369404 | AL20: =($W20-Z20)*10000 -> 4.6703774 | AM20: =($W20-AA20)*10000 -> 13.175669 | AN20: =($W20-AB20)*10000 -> 35.927338
C21: Refinanciado | D21: =IFERROR(((1+D39/D15)^(360/D$3))-1,0) -> 0 | E21: =IFERROR(((1+E39/E15)^(360/E$3))-1,0) -> 0 | F21: =IFERROR(((1+F39/F15)^(360/F$3))-1,0) -> 0 | G21: =IFERROR(((1+G39/G15)^(360/G$3))-1,0) -> 0 | H21: =IFERROR(((1+H39/H15)^(360/H$3))-1,0) -> 0 | I21: =IFERROR(((1+I39/I15)^(360/I$3))-1,0) -> 0 | Q21: =($D21-E21)*10000 -> 0 | R21: =($D21-F21)*10000 -> 0 | S21: =($D21-G21)*10000 -> 0 | T21: =($D21-H21)*10000 -> 0 | U21: =($D21-I21)*10000 -> 0 | W21: {=INDIRECT("'"&$C$6&"'!"&ADDRESS(ROW(),COLUMN()+44))} -> 0 | X21: {=INDIRECT("'"&$C$6&"'!"&ADDRESS(ROW(),COLUMN()+44))} -> 0 | Y21: {=INDIRECT("'"&$C$6&"'!"&ADDRESS(ROW(),COLUMN()+44))} -> 0 | Z21: {=INDIRECT("'"&$C$6&"'!"&ADDRESS(ROW(),COLUMN()+44))} -> 0 | AA21: {=INDIRECT("'"&$C$6&"'!"&ADDRESS(ROW(),COLUMN()+44))} -> 0 | AB21: {=INDIRECT("'"&$C$6&"'!"&ADDRESS(ROW(),COLUMN()+44))} -> 0 | AJ21: =($W21-X21)*10000 -> 0 | AK21: =($W21-Y21)*10000 -> 0 | AL21: =($W21-Z21)*10000 -> 0 | AM21: =($W21-AA21)*10000 -> 0 | AN21: =($W21-AB21)*10000 -> 0
C22: Vencido y Judicial | D22: =IFERROR(((1+D40/D16)^(360/D$3))-1,0) -> 0.11211581 | E22: =IFERROR(((1+E40/E16)^(360/E$3))-1,0) -> 0.11903353 | F22: =IFERROR(((1+F40/F16)^(360/F$3))-1,0) -> 0.098066155 | G22: =IFERROR(((1+G40/G16)^(360/G$3))-1,0) -> 0.11095813 | H22: =IFERROR(((1+H40/H16)^(360/H$3))-1,0) -> 0.10315959 | I22: =IFERROR(((1+I40/I16)^(360/I$3))-1,0) -> 0.106308 | Q22: =($D22-E22)*10000 -> -69.177165 | R22: =($D22-F22)*10000 -> 140.49657 | S22: =($D22-G22)*10000 -> 11.576859 | T22: =($D22-H22)*10000 -> 89.562183 | U22: =($D22-I22)*10000 -> 58.07814 | W22: {=INDIRECT("'"&$C$6&"'!"&ADDRESS(ROW(),COLUMN()+44))} -> 0.10159883 | X22: {=INDIRECT("'"&$C$6&"'!"&ADDRESS(ROW(),COLUMN()+44))} -> 0.11974894 | Y22: {=INDIRECT("'"&$C$6&"'!"&ADDRESS(ROW(),COLUMN()+44))} -> 0.096260819 | Z22: {=INDIRECT("'"&$C$6&"'!"&ADDRESS(ROW(),COLUMN()+44))} -> 0.10408722 | AA22: {=INDIRECT("'"&$C$6&"'!"&ADDRESS(ROW(),COLUMN()+44))} -> 0.10317897 | AB22: {=INDIRECT("'"&$C$6&"'!"&ADDRESS(ROW(),COLUMN()+44))} -> 0.093382026 | AJ22: =($W22-X22)*10000 -> -181.50118 | AK22: =($W22-Y22)*10000 -> 53.380085 | AL22: =($W22-Z22)*10000 -> -24.883933 | AM22: =($W22-AA22)*10000 -> -15.80142 | AN22: =($W22-AB22)*10000 -> 82.168005
C23: Tasa Implicita | D23: =IFERROR(((1+D41/D17)^(360/D$3))-1,0) -> 0.075242263 | E23: =IFERROR(((1+E41/E17)^(360/E$3))-1,0) -> 0.074551078 | F23: =IFERROR(((1+F41/F17)^(360/F$3))-1,0) -> 0.075208869 | G23: =IFERROR(((1+G41/G17)^(360/G$3))-1,0) -> 0.074793645 | H23: =IFERROR(((1+H41/H17)^(360/H$3))-1,0) -> 0.074204037 | I23: =IFERROR(((1+I41/I17)^(360/I$3))-1,0) -> 0.071861786 | Q23: =($D23-E23)*10000 -> 6.9118474 | R23: =($D23-F23)*10000 -> 0.3339378 | S23: =($D23-G23)*10000 -> 4.4861776 | T23: =($D23-H23)*10000 -> 10.382258 | U23: =($D23-I23)*10000 -> 33.80477 | W23: {=INDIRECT("'"&$C$6&"'!"&ADDRESS(ROW(),COLUMN()+44))} -> 0.075108716 | X23: {=INDIRECT("'"&$C$6&"'!"&ADDRESS(ROW(),COLUMN()+44))} -> 0.074819951 | Y23: {=INDIRECT("'"&$C$6&"'!"&ADDRESS(ROW(),COLUMN()+44))} -> 0.075025428 | Z23: {=INDIRECT("'"&$C$6&"'!"&ADDRESS(ROW(),COLUMN()+44))} -> 0.074764361 | AA23: {=INDIRECT("'"&$C$6&"'!"&ADDRESS(ROW(),COLUMN()+44))} -> 0.073844122 | AB23: {=INDIRECT("'"&$C$6&"'!"&ADDRESS(ROW(),COLUMN()+44))} -> 0.071244808 | AJ23: =($W23-X23)*10000 -> 2.8876539 | AK23: =($W23-Y23)*10000 -> 0.83288631 | AL23: =($W23-Z23)*10000 -> 3.4435522 | AM23: =($W23-AA23)*10000 -> 12.64594 | AN23: =($W23-AB23)*10000 -> 38.639086
C26: Vigente | D26: =-IFERROR(((1-D44/D14)^(360/D$4))-1,0) -> -0.054368153 | E26: =-IFERROR(((1-E44/E14)^(360/E$4))-1,0) -> -0.05464475 | F26: =-IFERROR(((1-F44/F14)^(360/F$4))-1,0) -> -0.060334376 | G26: =-IFERROR(((1-G44/G14)^(360/G$4))-1,0) -> -0.053830678 | H26: =-IFERROR(((1-H44/H14)^(360/H$4))-1,0) -> -0.051851671 | I26: =-IFERROR(((1-I44/I14)^(360/I$4))-1,0) -> -0.04871527 | Q26: =($D26-E26)*10000 -> 2.7659744 | R26: =($D26-F26)*10000 -> 59.662232 | S26: =($D26-G26)*10000 -> -5.3747458 | T26: =($D26-H26)*10000 -> -25.16482 | U26: =($D26-I26)*10000 -> -56.528832 | W26: {=INDIRECT("'"&$C$6&"'!"&ADDRESS(ROW(),COLUMN()+44))} -> -0.056239683 | X26: {=INDIRECT("'"&$C$6&"'!"&ADDRESS(ROW(),COLUMN()+44))} -> -0.056482252 | Y26: {=INDIRECT("'"&$C$6&"'!"&ADDRESS(ROW(),COLUMN()+44))} -> -0.05624434 | Z26: {=INDIRECT("'"&$C$6&"'!"&ADDRESS(ROW(),COLUMN()+44))} -> -0.05550907 | AA26: {=INDIRECT("'"&$C$6&"'!"&ADDRESS(ROW(),COLUMN()+44))} -> -0.053367564 | AB26: {=INDIRECT("'"&$C$6&"'!"&ADDRESS(ROW(),COLUMN()+44))} -> -0.049998844 | AJ26: =($W26-X26)*10000 -> 2.4256817 | AK26: =($W26-Y26)*10000 -> 0.046570139 | AL26: =($W26-Z26)*10000 -> -7.3061363 | AM26: =($W26-AA26)*10000 -> -28.721194 | AN26: =($W26-AB26)*10000 -> -62.408393
C27: Refinanciado | D27: =-IFERROR(((1-D45/D15)^(360/D$4))-1,0) -> -0.05329065 | E27: =-IFERROR(((1-E45/E15)^(360/E$4))-1,0) -> -0.055451064 | F27: =-IFERROR(((1-F45/F15)^(360/F$4))-1,0) -> -0.058217736 | G27: =-IFERROR(((1-G45/G15)^(360/G$4))-1,0) -> -0.050702078 | H27: =-IFERROR(((1-H45/H15)^(360/H$4))-1,0) -> -0.048797725 | I27: =-IFERROR(((1-I45/I15)^(360/I$4))-1,0) -> -0.04785361 | Q27: =($D27-E27)*10000 -> 21.604146 | R27: =($D27-F27)*10000 -> 49.270863 | S27: =($D27-G27)*10000 -> -25.885719 | T27: =($D27-H27)*10000 -> -44.929243 | U27: =($D27-I27)*10000 -> -54.370399 | W27: {=INDIRECT("'"&$C$6&"'!"&ADDRESS(ROW(),COLUMN()+44))} -> -0.054758314 | X27: {=INDIRECT("'"&$C$6&"'!"&ADDRESS(ROW(),COLUMN()+44))} -> -0.057133437 | Y27: {=INDIRECT("'"&$C$6&"'!"&ADDRESS(ROW(),COLUMN()+44))} -> -0.054570349 | Z27: {=INDIRECT("'"&$C$6&"'!"&ADDRESS(ROW(),COLUMN()+44))} -> -0.052077723 | AA27: {=INDIRECT("'"&$C$6&"'!"&ADDRESS(ROW(),COLUMN()+44))} -> -0.04998486 | AB27: {=INDIRECT("'"&$C$6&"'!"&ADDRESS(ROW(),COLUMN()+44))} -> -0.049473512 | AJ27: =($W27-X27)*10000 -> 23.75123 | AK27: =($W27-Y27)*10000 -> -1.8796512 | AL27: =($W27-Z27)*10000 -> -26.805911 | AM27: =($W27-AA27)*10000 -> -47.734543 | AN27: =($W27-AB27)*10000 -> -52.848021
C28: Vencido y Judicial | D28: =-IFERROR(((1-D46/D16)^(360/D$4))-1,0) -> -0.053052524 | E28: =-IFERROR(((1-E46/E16)^(360/E$4))-1,0) -> -0.054080404 | F28: =-IFERROR(((1-F46/F16)^(360/F$4))-1,0) -> -0.05873716 | G28: =-IFERROR(((1-G46/G16)^(360/G$4))-1,0) -> -0.050240859 | H28: =-IFERROR(((1-H46/H16)^(360/H$4))-1,0) -> -0.05156935 | I28: =-IFERROR(((1-I46/I16)^(360/I$4))-1,0) -> -0.050100362 | Q28: =($D28-E28)*10000 -> 10.278805 | R28: =($D28-F28)*10000 -> 56.846357 | S28: =($D28-G28)*10000 -> -28.116646 | T28: =($D28-H28)*10000 -> -14.831737 | U28: =($D28-I28)*10000 -> -29.521621 | W28: {=INDIRECT("'"&$C$6&"'!"&ADDRESS(ROW(),COLUMN()+44))} -> -0.054860101 | X28: {=INDIRECT("'"&$C$6&"'!"&ADDRESS(ROW(),COLUMN()+44))} -> -0.055983092 | Y28: {=INDIRECT("'"&$C$6&"'!"&ADDRESS(ROW(),COLUMN()+44))} -> -0.054855937 | Z28: {=INDIRECT("'"&$C$6&"'!"&ADDRESS(ROW(),COLUMN()+44))} -> -0.053122545 | AA28: {=INDIRECT("'"&$C$6&"'!"&ADDRESS(ROW(),COLUMN()+44))} -> -0.052963824 | AB28: {=INDIRECT("'"&$C$6&"'!"&ADDRESS(ROW(),COLUMN()+44))} -> -0.051714841 | AJ28: =($W28-X28)*10000 -> 11.229918 | AK28: =($W28-Y28)*10000 -> -0.041632191 | AL28: =($W28-Z28)*10000 -> -17.375556 | AM28: =($W28-AA28)*10000 -> -18.962767 | AN28: =($W28-AB28)*10000 -> -31.452596
C29: Tasa FTP | D29: =-IFERROR(((1-D47/D17)^(360/D$4))-1,0) -> -0.054325839 | E29: =-IFERROR(((1-E47/E17)^(360/E$4))-1,0) -> -0.054628867 | F29: =-IFERROR(((1-F47/F17)^(360/F$4))-1,0) -> -0.060280032 | G29: =-IFERROR(((1-G47/G17)^(360/G$4))-1,0) -> -0.053707828 | H29: =-IFERROR(((1-H47/H17)^(360/H$4))-1,0) -> -0.05183375 | I29: =-IFERROR(((1-I47/I17)^(360/I$4))-1,0) -> -0.048749093 | Q29: =($D29-E29)*10000 -> 3.0302715 | R29: =($D29-F29)*10000 -> 59.541928 | S29: =($D29-G29)*10000 -> -6.1801196 | T29: =($D29-H29)*10000 -> -24.920897 | U29: =($D29-I29)*10000 -> -55.76746 | W29: {=INDIRECT("'"&$C$6&"'!"&ADDRESS(ROW(),COLUMN()+44))} -> -0.056193579 | X29: {=INDIRECT("'"&$C$6&"'!"&ADDRESS(ROW(),COLUMN()+44))} -> -0.056468105 | Y29: {=INDIRECT("'"&$C$6&"'!"&ADDRESS(ROW(),COLUMN()+44))} -> -0.05619707 | Z29: {=INDIRECT("'"&$C$6&"'!"&ADDRESS(ROW(),COLUMN()+44))} -> -0.055424678 | AA29: {=INDIRECT("'"&$C$6&"'!"&ADDRESS(ROW(),COLUMN()+44))} -> -0.053344987 | AB29: {=INDIRECT("'"&$C$6&"'!"&ADDRESS(ROW(),COLUMN()+44))} -> -0.050042195 | AJ29: =($W29-X29)*10000 -> 2.7452586 | AK29: =($W29-Y29)*10000 -> 0.034907581 | AL29: =($W29-Z29)*10000 -> -7.6890144 | AM29: =($W29-AA29)*10000 -> -28.485926 | AN29: =($W29-AB29)*10000 -> -61.513841
C32: Vigente | D32: =D20+D26 -> 0.019984216 | E32: =E20+E26 -> 0.018673033 | F32: =F20+F26 -> 0.014379216 | G32: =G20+G26 -> 0.020002424 | H32: =H20+H26 -> 0.021706413 | I32: =I20+I26 -> 0.022482768 | Q32: =($D32-E32)*10000 -> 13.111831 | R32: =($D32-F32)*10000 -> 56.050001 | S32: =($D32-G32)*10000 -> -0.18208043 | T32: =($D32-H32)*10000 -> -17.221975 | U32: =($D32-I32)*10000 -> -24.985524 | W32: =W20+W26 -> 0.018266787 | X32: =X20+X26 -> 0.017096563 | Y32: =Y20+Y26 -> 0.018330499 | Z32: =Z20+Z26 -> 0.018530363 | AA32: =AA20+AA26 -> 0.019821339 | AB32: =AB20+AB26 -> 0.020914892 | AJ32: =($W32-X32)*10000 -> 11.702237 | AK32: =($W32-Y32)*10000 -> -0.6371239 | AL32: =($W32-Z32)*10000 -> -2.6357589 | AM32: =($W32-AA32)*10000 -> -15.545524 | AN32: =($W32-AB32)*10000 -> -26.481055
C33: Refinanciado | D33: =D21+D27 -> -0.05329065 | E33: =E21+E27 -> -0.055451064 | F33: =F21+F27 -> -0.058217736 | G33: =G21+G27 -> -0.050702078 | H33: =H21+H27 -> -0.048797725 | I33: =I21+I27 -> -0.04785361 | Q33: =($D33-E33)*10000 -> 21.604146 | R33: =($D33-F33)*10000 -> 49.270863 | S33: =($D33-G33)*10000 -> -25.885719 | T33: =($D33-H33)*10000 -> -44.929243 | U33: =($D33-I33)*10000 -> -54.370399 | W33: =W21+W27 -> -0.054758314 | X33: =X21+X27 -> -0.057133437 | Y33: =Y21+Y27 -> -0.054570349 | Z33: =Z21+Z27 -> -0.052077723 | AA33: =AA21+AA27 -> -0.04998486 | AB33: =AB21+AB27 -> -0.049473512 | AJ33: =($W33-X33)*10000 -> 23.75123 | AK33: =($W33-Y33)*10000 -> -1.8796512 | AL33: =($W33-Z33)*10000 -> -26.805911 | AM33: =($W33-AA33)*10000 -> -47.734543 | AN33: =($W33-AB33)*10000 -> -52.848021
C34: Vencido y Judicial | D34: =D22+D28 -> 0.059063288 | E34: =E22+E28 -> 0.064953124 | F34: =F22+F28 -> 0.039328996 | G34: =G22+G28 -> 0.060717267 | H34: =H22+H28 -> 0.051590243 | I34: =I22+I28 -> 0.056207636 | Q34: =($D34-E34)*10000 -> -58.89836 | R34: =($D34-F34)*10000 -> 197.34292 | S34: =($D34-G34)*10000 -> -16.539787 | T34: =($D34-H34)*10000 -> 74.730446 | U34: =($D34-I34)*10000 -> 28.556519 | W34: =W22+W28 -> 0.046738726 | X34: =X22+X28 -> 0.063765852 | Y34: =Y22+Y28 -> 0.041404881 | Z34: =Z22+Z28 -> 0.050964675 | AA34: =AA22+AA28 -> 0.050215145 | AB34: =AB22+AB28 -> 0.041667186 | AJ34: =($W34-X34)*10000 -> -170.27126 | AK34: =($W34-Y34)*10000 -> 53.338453 | AL34: =($W34-Z34)*10000 -> -42.259489 | AM34: =($W34-AA34)*10000 -> -34.764187 | AN34: =($W34-AB34)*10000 -> 50.71541
C35: Spread | D35: =D23+D29 -> 0.020916424 | E35: =E23+E29 -> 0.019922212 | F35: =F23+F29 -> 0.014928837 | G35: =G23+G29 -> 0.021085818 | H35: =H23+H29 -> 0.022370288 | I35: =I23+I29 -> 0.023112693 | Q35: =($D35-E35)*10000 -> 9.9421189 | R35: =($D35-F35)*10000 -> 59.875866 | S35: =($D35-G35)*10000 -> -1.693942 | T35: =($D35-H35)*10000 -> -14.53864 | U35: =($D35-I35)*10000 -> -21.962691 | W35: =W23+W29 -> 0.018915137 | X35: =X23+X29 -> 0.018351846 | Y35: =Y23+Y29 -> 0.018828358 | Z35: =Z23+Z29 -> 0.019339683 | AA35: =AA23+AA29 -> 0.020499136 | AB35: =AB23+AB29 -> 0.021202613 | AJ35: =($W35-X35)*10000 -> 5.6329124 | AK35: =($W35-Y35)*10000 -> 0.86779389 | AL35: =($W35-Z35)*10000 -> -4.2454622 | AM35: =($W35-AA35)*10000 -> -15.839986 | AN35: =($W35-AB35)*10000 -> -22.874755
A38: Ingreso_Financiero | C38: Vigente | D38: {=_xlfn.XLOOKUP(1, (INDIRECT("'"&$C$6&"'!$6:$6")=D$6)* (INDIRECT("'"&$C$6&"'!$5:$5")=D$5), INDIRECT("'"&$C$6&"'!"&ROW()&":"&ROW()) )} -> 70941.129 | E38: {=_xlfn.XLOOKUP(1, (INDIRECT("'"&$C$6&"'!$6:$6")=E$6)* (INDIRECT("'"&$C$6&"'!$5:$5")=E$5), INDIRECT("'"&$C$6&"'!"&ROW()&":"&ROW()) )} -> 69331.581 | F38: {=_xlfn.XLOOKUP(1, (INDIRECT("'"&$C$6&"'!$6:$6")=F$6)* (INDIRECT("'"&$C$6&"'!$5:$5")=F$5), INDIRECT("'"&$C$6&"'!"&ROW()&":"&ROW()) )} -> 63928.76 | G38: {=_xlfn.XLOOKUP(1, (INDIRECT("'"&$C$6&"'!$6:$6")=G$6)* (INDIRECT("'"&$C$6&"'!$5:$5")=G$5), INDIRECT("'"&$C$6&"'!"&ROW()&":"&ROW()) )} -> 64782.913 | H38: {=_xlfn.XLOOKUP(1, (INDIRECT("'"&$C$6&"'!$6:$6")=H$6)* (INDIRECT("'"&$C$6&"'!$5:$5")=H$5), INDIRECT("'"&$C$6&"'!"&ROW()&":"&ROW()) )} -> 60393.993 | I38: {=_xlfn.XLOOKUP(1, (INDIRECT("'"&$C$6&"'!$6:$6")=I$6)* (INDIRECT("'"&$C$6&"'!$5:$5")=I$5), INDIRECT("'"&$C$6&"'!"&ROW()&":"&ROW()) )} -> 55428.296 | K38: =$D38-E38 -> 1609.5477 | L38: =$D38-F38 -> 7012.3693 | M38: =$D38-G38 -> 6158.2164 | N38: =$D38-H38 -> 10547.136 | O38: =$D38-I38 -> 15512.833 | Q38: =IFERROR($D38/E38-1,0) -> 0.023215218 | R38: =IFERROR($D38/F38-1,0) -> 0.10969037 | S38: =IFERROR($D38/G38-1,0) -> 0.095059271 | T38: =IFERROR($D38/H38-1,0) -> 0.17463882 | U38: =IFERROR($D38/I38-1,0) -> 0.2798721 | W38: {=INDIRECT("'"&$C$6&"'!"&ADDRESS(ROW(),COLUMN()+44))} -> 204971.59 | X38: {=INDIRECT("'"&$C$6&"'!"&ADDRESS(ROW(),COLUMN()+44))} -> 201100.61 | Y38: {=INDIRECT("'"&$C$6&"'!"&ADDRESS(ROW(),COLUMN()+44))} -> 134030.46 | Z38: {=INDIRECT("'"&$C$6&"'!"&ADDRESS(ROW(),COLUMN()+44))} -> 187711.57 | AA38: {=INDIRECT("'"&$C$6&"'!"&ADDRESS(ROW(),COLUMN()+44))} -> 175489.41 | AB38: {=INDIRECT("'"&$C$6&"'!"&ADDRESS(ROW(),COLUMN()+44))} -> 159684.99 | AD38: =$W38-X38 -> 3870.9862 | AE38: =$W38-Y38 -> 70941.129 | AF38: =$W38-Z38 -> 17260.024 | AG38: =$W38-AA38 -> 29482.186 | AH38: =$W38-AB38 -> 45286.605 | AJ38: =IFERROR($W38/X38-1,0) -> 0.019249003 | AK38: =IFERROR($W38/Y38-1,0) -> 0.52929108 | AL38: =IFERROR($W38/Z38-1,0) -> 0.09194971 | AM38: =IFERROR($W38/AA38-1,0) -> 0.1679998 | AN38: =IFERROR($W38/AB38-1,0) -> 0.28359964
A39: Ingreso_Financiero | C39: Refinanciado | D39: {=_xlfn.XLOOKUP(1, (INDIRECT("'"&$C$6&"'!$6:$6")=D$6)* (INDIRECT("'"&$C$6&"'!$5:$5")=D$5), INDIRECT("'"&$C$6&"'!"&ROW()&":"&ROW()) )} -> 0 | E39: {=_xlfn.XLOOKUP(1, (INDIRECT("'"&$C$6&"'!$6:$6")=E$6)* (INDIRECT("'"&$C$6&"'!$5:$5")=E$5), INDIRECT("'"&$C$6&"'!"&ROW()&":"&ROW()) )} -> 0 | F39: {=_xlfn.XLOOKUP(1, (INDIRECT("'"&$C$6&"'!$6:$6")=F$6)* (INDIRECT("'"&$C$6&"'!$5:$5")=F$5), INDIRECT("'"&$C$6&"'!"&ROW()&":"&ROW()) )} -> 0 | G39: {=_xlfn.XLOOKUP(1, (INDIRECT("'"&$C$6&"'!$6:$6")=G$6)* (INDIRECT("'"&$C$6&"'!$5:$5")=G$5), INDIRECT("'"&$C$6&"'!"&ROW()&":"&ROW()) )} -> 0 | H39: {=_xlfn.XLOOKUP(1, (INDIRECT("'"&$C$6&"'!$6:$6")=H$6)* (INDIRECT("'"&$C$6&"'!$5:$5")=H$5), INDIRECT("'"&$C$6&"'!"&ROW()&":"&ROW()) )} -> 0 | I39: {=_xlfn.XLOOKUP(1, (INDIRECT("'"&$C$6&"'!$6:$6")=I$6)* (INDIRECT("'"&$C$6&"'!$5:$5")=I$5), INDIRECT("'"&$C$6&"'!"&ROW()&":"&ROW()) )} -> 0 | K39: =$D39-E39 -> 0 | L39: =$D39-F39 -> 0 | M39: =$D39-G39 -> 0 | N39: =$D39-H39 -> 0 | O39: =$D39-I39 -> 0 | Q39: =IFERROR($D39/E39-1,0) -> 0 | R39: =IFERROR($D39/F39-1,0) -> 0 | S39: =IFERROR($D39/G39-1,0) -> 0 | T39: =IFERROR($D39/H39-1,0) -> 0 | U39: =IFERROR($D39/I39-1,0) -> 0 | W39: {=INDIRECT("'"&$C$6&"'!"&ADDRESS(ROW(),COLUMN()+44))} -> 0 | X39: {=INDIRECT("'"&$C$6&"'!"&ADDRESS(ROW(),COLUMN()+44))} -> 0 | Y39: {=INDIRECT("'"&$C$6&"'!"&ADDRESS(ROW(),COLUMN()+44))} -> 0 | Z39: {=INDIRECT("'"&$C$6&"'!"&ADDRESS(ROW(),COLUMN()+44))} -> 0 | AA39: {=INDIRECT("'"&$C$6&"'!"&ADDRESS(ROW(),COLUMN()+44))} -> 0 | AB39: {=INDIRECT("'"&$C$6&"'!"&ADDRESS(ROW(),COLUMN()+44))} -> 0 | AD39: =$W39-X39 -> 0 | AE39: =$W39-Y39 -> 0 | AF39: =$W39-Z39 -> 0 | AG39: =$W39-AA39 -> 0 | AH39: =$W39-AB39 -> 0 | AJ39: =IFERROR($W39/X39-1,0) -> 0 | AK39: =IFERROR($W39/Y39-1,0) -> 0 | AL39: =IFERROR($W39/Z39-1,0) -> 0 | AM39: =IFERROR($W39/AA39-1,0) -> 0 | AN39: =IFERROR($W39/AB39-1,0) -> 0
A40: Ingreso_Financiero | C40: Vencido y Judicial | D40: {=_xlfn.XLOOKUP(1, (INDIRECT("'"&$C$6&"'!$6:$6")=D$6)* (INDIRECT("'"&$C$6&"'!$5:$5")=D$5), INDIRECT("'"&$C$6&"'!"&ROW()&":"&ROW()) )} -> 3244.4283 | E40: {=_xlfn.XLOOKUP(1, (INDIRECT("'"&$C$6&"'!$6:$6")=E$6)* (INDIRECT("'"&$C$6&"'!$5:$5")=E$5), INDIRECT("'"&$C$6&"'!"&ROW()&":"&ROW()) )} -> 3627.06 | F40: {=_xlfn.XLOOKUP(1, (INDIRECT("'"&$C$6&"'!$6:$6")=F$6)* (INDIRECT("'"&$C$6&"'!$5:$5")=F$5), INDIRECT("'"&$C$6&"'!"&ROW()&":"&ROW()) )} -> 2614.0329 | G40: {=_xlfn.XLOOKUP(1, (INDIRECT("'"&$C$6&"'!$6:$6")=G$6)* (INDIRECT("'"&$C$6&"'!$5:$5")=G$5), INDIRECT("'"&$C$6&"'!"&ROW()&":"&ROW()) )} -> 3160.6668 | H40: {=_xlfn.XLOOKUP(1, (INDIRECT("'"&$C$6&"'!$6:$6")=H$6)* (INDIRECT("'"&$C$6&"'!$5:$5")=H$5), INDIRECT("'"&$C$6&"'!"&ROW()&":"&ROW()) )} -> 2603.522 | I40: {=_xlfn.XLOOKUP(1, (INDIRECT("'"&$C$6&"'!$6:$6")=I$6)* (INDIRECT("'"&$C$6&"'!$5:$5")=I$5), INDIRECT("'"&$C$6&"'!"&ROW()&":"&ROW()) )} -> 2237.3082 | K40: =$D40-E40 -> -382.63166 | L40: =$D40-F40 -> 630.39546 | M40: =$D40-G40 -> 83.761527 | N40: =$D40-H40 -> 640.90636 | O40: =$D40-I40 -> 1007.1201 | Q40: =IFERROR($D40/E40-1,0) -> -0.10549361 | R40: =IFERROR($D40/F40-1,0) -> 0.2411582 | S40: =IFERROR($D40/G40-1,0) -> 0.02650122 | T40: =IFERROR($D40/H40-1,0) -> 0.24616898 | U40: =IFERROR($D40/I40-1,0) -> 0.45014814 | W40: {=INDIRECT("'"&$C$6&"'!"&ADDRESS(ROW(),COLUMN()+44))} -> 8695.8404 | X40: {=INDIRECT("'"&$C$6&"'!"&ADDRESS(ROW(),COLUMN()+44))} -> 10504.799 | Y40: {=INDIRECT("'"&$C$6&"'!"&ADDRESS(ROW(),COLUMN()+44))} -> 5451.412 | Z40: {=INDIRECT("'"&$C$6&"'!"&ADDRESS(ROW(),COLUMN()+44))} -> 8475.6998 | AA40: {=INDIRECT("'"&$C$6&"'!"&ADDRESS(ROW(),COLUMN()+44))} -> 7578.7647 | AB40: {=INDIRECT("'"&$C$6&"'!"&ADDRESS(ROW(),COLUMN()+44))} -> 5656.6817 | AD40: =$W40-X40 -> -1808.9587 | AE40: =$W40-Y40 -> 3244.4283 | AF40: =$W40-Z40 -> 220.14053 | AG40: =$W40-AA40 -> 1117.0757 | AH40: =$W40-AB40 -> 3039.1586 | AJ40: =IFERROR($W40/X40-1,0) -> -0.17220307 | AK40: =IFERROR($W40/Y40-1,0) -> 0.59515376 | AL40: =IFERROR($W40/Z40-1,0) -> 0.025973139 | AM40: =IFERROR($W40/AA40-1,0) -> 0.14739548 | AN40: =IFERROR($W40/AB40-1,0) -> 0.5372688
C41: Ingreso Financiero | D41: =SUM(D38:D40) -> 74185.557 | E41: =SUM(E38:E40) -> 72958.641 | F41: =SUM(F38:F40) -> 66542.792 | G41: =SUM(G38:G40) -> 67943.579 | H41: =SUM(H38:H40) -> 62997.515 | I41: =SUM(I38:I40) -> 57665.604 | K41: =$D41-E41 -> 1226.9161 | L41: =$D41-F41 -> 7642.7648 | M41: =$D41-G41 -> 6241.978 | N41: =$D41-H41 -> 11188.042 | O41: =$D41-I41 -> 16519.953 | Q41: =IFERROR($D41/E41-1,0) -> 0.016816597 | R41: =IFERROR($D41/F41-1,0) -> 0.11485489 | S41: =IFERROR($D41/G41-1,0) -> 0.09187002 | T41: =IFERROR($D41/H41-1,0) -> 0.17759497 | U41: =IFERROR($D41/I41-1,0) -> 0.28647846 | W41: =SUM(W38:W40) -> 213667.43 | X41: =SUM(X38:X40) -> 211605.41 | Y41: =SUM(Y38:Y40) -> 139481.88 | Z41: =SUM(Z38:Z40) -> 196187.27 | AA41: =SUM(AA38:AA40) -> 183068.17 | AB41: =SUM(AB38:AB40) -> 165341.67 | AD41: =$W41-X41 -> 2062.0276 | AE41: =$W41-Y41 -> 74185.557 | AF41: =$W41-Z41 -> 17480.165 | AG41: =$W41-AA41 -> 30599.261 | AH41: =$W41-AB41 -> 48325.764 | AJ41: =IFERROR($W41/X41-1,0) -> 0.0097446828 | AK41: =IFERROR($W41/Y41-1,0) -> 0.53186521 | AL41: =IFERROR($W41/Z41-1,0) -> 0.089099384 | AM41: =IFERROR($W41/AA41-1,0) -> 0.16714681 | AN41: =IFERROR($W41/AB41-1,0) -> 0.29227819
A44: FTP | C44: Vigente | D44: {=_xlfn.XLOOKUP(1, (INDIRECT("'"&$C$6&"'!$6:$6")=D$6)* (INDIRECT("'"&$C$6&"'!$5:$5")=D$5), INDIRECT("'"&$C$6&"'!"&ROW()&":"&ROW()) )} -> -52325.82 | E44: {=_xlfn.XLOOKUP(1, (INDIRECT("'"&$C$6&"'!$6:$6")=E$6)* (INDIRECT("'"&$C$6&"'!$5:$5")=E$5), INDIRECT("'"&$C$6&"'!"&ROW()&":"&ROW()) )} -> -52094.538 | F44: {=_xlfn.XLOOKUP(1, (INDIRECT("'"&$C$6&"'!$6:$6")=F$6)* (INDIRECT("'"&$C$6&"'!$5:$5")=F$5), INDIRECT("'"&$C$6&"'!"&ROW()&":"&ROW()) )} -> -51950.603 | G44: {=_xlfn.XLOOKUP(1, (INDIRECT("'"&$C$6&"'!$6:$6")=G$6)* (INDIRECT("'"&$C$6&"'!$5:$5")=G$5), INDIRECT("'"&$C$6&"'!"&ROW()&":"&ROW()) )} -> -47644.454 | H44: {=_xlfn.XLOOKUP(1, (INDIRECT("'"&$C$6&"'!$6:$6")=H$6)* (INDIRECT("'"&$C$6&"'!$5:$5")=H$5), INDIRECT("'"&$C$6&"'!"&ROW()&":"&ROW()) )} -> -42975.828 | I44: {=_xlfn.XLOOKUP(1, (INDIRECT("'"&$C$6&"'!$6:$6")=I$6)* (INDIRECT("'"&$C$6&"'!$5:$5")=I$5), INDIRECT("'"&$C$6&"'!"&ROW()&":"&ROW()) )} -> -38298.555 | K44: =$D44-E44 -> -231.28199 | L44: =$D44-F44 -> -375.21719 | M44: =$D44-G44 -> -4681.366 | N44: =$D44-H44 -> -9349.9919 | O44: =$D44-I44 -> -14027.265 | Q44: =IFERROR($D44/E44-1,0) -> 0.0044396591 | R44: =IFERROR($D44/F44-1,0) -> 0.0072225763 | S44: =IFERROR($D44/G44-1,0) -> 0.098256263 | T44: =IFERROR($D44/H44-1,0) -> 0.21756397 | U44: =IFERROR($D44/I44-1,0) -> 0.36626095 | W44: {=INDIRECT("'"&$C$6&"'!"&ADDRESS(ROW(),COLUMN()+44))} -> -155953.3 | X44: {=INDIRECT("'"&$C$6&"'!"&ADDRESS(ROW(),COLUMN()+44))} -> -155526.46 | Y44: {=INDIRECT("'"&$C$6&"'!"&ADDRESS(ROW(),COLUMN()+44))} -> -103627.48 | Z44: {=INDIRECT("'"&$C$6&"'!"&ADDRESS(ROW(),COLUMN()+44))} -> -141871.56 | AA44: {=INDIRECT("'"&$C$6&"'!"&ADDRESS(ROW(),COLUMN()+44))} -> -127650.29 | AB44: {=INDIRECT("'"&$C$6&"'!"&ADDRESS(ROW(),COLUMN()+44))} -> -113621.68 | AD44: =$W44-X44 -> -426.83174 | AE44: =$W44-Y44 -> -52325.82 | AF44: =$W44-Z44 -> -14081.737 | AG44: =$W44-AA44 -> -28303.008 | AH44: =$W44-AB44 -> -42331.62 | AJ44: =IFERROR($W44/X44-1,0) -> 0.0027444316 | AK44: =IFERROR($W44/Y44-1,0) -> 0.50494157 | AL44: =IFERROR($W44/Z44-1,0) -> 0.099256944 | AM44: =IFERROR($W44/AA44-1,0) -> 0.22172302 | AN44: =IFERROR($W44/AB44-1,0) -> 0.37256642
A45: FTP | C45: Refinanciado | D45: {=_xlfn.XLOOKUP(1, (INDIRECT("'"&$C$6&"'!$6:$6")=D$6)* (INDIRECT("'"&$C$6&"'!$5:$5")=D$5), INDIRECT("'"&$C$6&"'!"&ROW()&":"&ROW()) )} -> -150.97141 | E45: {=_xlfn.XLOOKUP(1, (INDIRECT("'"&$C$6&"'!$6:$6")=E$6)* (INDIRECT("'"&$C$6&"'!$5:$5")=E$5), INDIRECT("'"&$C$6&"'!"&ROW()&":"&ROW()) )} -> -137.56817 | F45: {=_xlfn.XLOOKUP(1, (INDIRECT("'"&$C$6&"'!$6:$6")=F$6)* (INDIRECT("'"&$C$6&"'!$5:$5")=F$5), INDIRECT("'"&$C$6&"'!"&ROW()&":"&ROW()) )} -> -139.99088 | G45: {=_xlfn.XLOOKUP(1, (INDIRECT("'"&$C$6&"'!$6:$6")=G$6)* (INDIRECT("'"&$C$6&"'!$5:$5")=G$5), INDIRECT("'"&$C$6&"'!"&ROW()&":"&ROW()) )} -> -124.34356 | H45: {=_xlfn.XLOOKUP(1, (INDIRECT("'"&$C$6&"'!$6:$6")=H$6)* (INDIRECT("'"&$C$6&"'!$5:$5")=H$5), INDIRECT("'"&$C$6&"'!"&ROW()&":"&ROW()) )} -> -129.08027 | I45: {=_xlfn.XLOOKUP(1, (INDIRECT("'"&$C$6&"'!$6:$6")=I$6)* (INDIRECT("'"&$C$6&"'!$5:$5")=I$5), INDIRECT("'"&$C$6&"'!"&ROW()&":"&ROW()) )} -> -135.84478 | K45: =$D45-E45 -> -13.403238 | L45: =$D45-F45 -> -10.980524 | M45: =$D45-G45 -> -26.627848 | N45: =$D45-H45 -> -21.891141 | O45: =$D45-I45 -> -15.126627 | Q45: =IFERROR($D45/E45-1,0) -> 0.097429791 | R45: =IFERROR($D45/F45-1,0) -> 0.078437425 | S45: =IFERROR($D45/G45-1,0) -> 0.21414738 | T45: =IFERROR($D45/H45-1,0) -> 0.16959324 | U45: =IFERROR($D45/I45-1,0) -> 0.11135228 | W45: {=INDIRECT("'"&$C$6&"'!"&ADDRESS(ROW(),COLUMN()+44))} -> -434.70243 | X45: {=INDIRECT("'"&$C$6&"'!"&ADDRESS(ROW(),COLUMN()+44))} -> -409.64609 | Y45: {=INDIRECT("'"&$C$6&"'!"&ADDRESS(ROW(),COLUMN()+44))} -> -283.73102 | Z45: {=INDIRECT("'"&$C$6&"'!"&ADDRESS(ROW(),COLUMN()+44))} -> -374.56083 | AA45: {=INDIRECT("'"&$C$6&"'!"&ADDRESS(ROW(),COLUMN()+44))} -> -382.45111 | AB45: {=INDIRECT("'"&$C$6&"'!"&ADDRESS(ROW(),COLUMN()+44))} -> -404.67559 | AD45: =$W45-X45 -> -25.056346 | AE45: =$W45-Y45 -> -150.97141 | AF45: =$W45-Z45 -> -60.1416 | AG45: =$W45-AA45 -> -52.251325 | AH45: =$W45-AB45 -> -30.026841 | AJ45: =IFERROR($W45/X45-1,0) -> 0.061165837 | AK45: =IFERROR($W45/Y45-1,0) -> 0.53209341 | AL45: =IFERROR($W45/Z45-1,0) -> 0.16056564 | AM45: =IFERROR($W45/AA45-1,0) -> 0.13662224 | AN45: =IFERROR($W45/AB45-1,0) -> 0.074199783
A46: FTP | C46: Vencido y Judicial | D46: {=_xlfn.XLOOKUP(1, (INDIRECT("'"&$C$6&"'!$6:$6")=D$6)* (INDIRECT("'"&$C$6&"'!$5:$5")=D$5), INDIRECT("'"&$C$6&"'!"&ROW()&":"&ROW()) )} -> -1574.5692 | E46: {=_xlfn.XLOOKUP(1, (INDIRECT("'"&$C$6&"'!$6:$6")=E$6)* (INDIRECT("'"&$C$6&"'!$5:$5")=E$5), INDIRECT("'"&$C$6&"'!"&ROW()&":"&ROW()) )} -> -1694.2179 | F46: {=_xlfn.XLOOKUP(1, (INDIRECT("'"&$C$6&"'!$6:$6")=F$6)* (INDIRECT("'"&$C$6&"'!$5:$5")=F$5), INDIRECT("'"&$C$6&"'!"&ROW()&":"&ROW()) )} -> -1592.604 | G46: {=_xlfn.XLOOKUP(1, (INDIRECT("'"&$C$6&"'!$6:$6")=G$6)* (INDIRECT("'"&$C$6&"'!$5:$5")=G$5), INDIRECT("'"&$C$6&"'!"&ROW()&":"&ROW()) )} -> -1468.8783 | H46: {=_xlfn.XLOOKUP(1, (INDIRECT("'"&$C$6&"'!$6:$6")=H$6)* (INDIRECT("'"&$C$6&"'!$5:$5")=H$5), INDIRECT("'"&$C$6&"'!"&ROW()&":"&ROW()) )} -> -1330.6861 | I46: {=_xlfn.XLOOKUP(1, (INDIRECT("'"&$C$6&"'!$6:$6")=I$6)* (INDIRECT("'"&$C$6&"'!$5:$5")=I$5), INDIRECT("'"&$C$6&"'!"&ROW()&":"&ROW()) )} -> -1080.1616 | K46: =$D46-E46 -> 119.64865 | L46: =$D46-F46 -> 18.034805 | M46: =$D46-G46 -> -105.69093 | N46: =$D46-H46 -> -243.88308 | O46: =$D46-I46 -> -494.40758 | Q46: =IFERROR($D46/E46-1,0) -> -0.070621761 | R46: =IFERROR($D46/F46-1,0) -> -0.011324098 | S46: =IFERROR($D46/G46-1,0) -> 0.071953499 | T46: =IFERROR($D46/H46-1,0) -> 0.18327619 | U46: =IFERROR($D46/I46-1,0) -> 0.45771629 | W46: {=INDIRECT("'"&$C$6&"'!"&ADDRESS(ROW(),COLUMN()+44))} -> -4791.0005 | X46: {=INDIRECT("'"&$C$6&"'!"&ADDRESS(ROW(),COLUMN()+44))} -> -5046.8493 | Y46: {=INDIRECT("'"&$C$6&"'!"&ADDRESS(ROW(),COLUMN()+44))} -> -3216.4313 | Z46: {=INDIRECT("'"&$C$6&"'!"&ADDRESS(ROW(),COLUMN()+44))} -> -4421.7289 | AA46: {=INDIRECT("'"&$C$6&"'!"&ADDRESS(ROW(),COLUMN()+44))} -> -3931.5749 | AB46: {=INDIRECT("'"&$C$6&"'!"&ADDRESS(ROW(),COLUMN()+44))} -> -3189.6649 | AD46: =$W46-X46 -> 255.84876 | AE46: =$W46-Y46 -> -1574.5692 | AF46: =$W46-Z46 -> -369.27163 | AG46: =$W46-AA46 -> -859.42562 | AH46: =$W46-AB46 -> -1601.3357 | AJ46: =IFERROR($W46/X46-1,0) -> -0.050694748 | AK46: =IFERROR($W46/Y46-1,0) -> 0.48953919 | AL46: =IFERROR($W46/Z46-1,0) -> 0.08351295 | AM46: =IFERROR($W46/AA46-1,0) -> 0.21859576 | AN46: =IFERROR($W46/AB46-1,0) -> 0.50203885
C47: Costo de Fondos | D47: =SUM(D44:D46) -> -54051.361 | E47: =SUM(E44:E46) -> -53926.324 | F47: =SUM(F44:F46) -> -53683.198 | G47: =SUM(G44:G46) -> -49237.676 | H47: =SUM(H44:H46) -> -44435.594 | I47: =SUM(I44:I46) -> -39514.561 | K47: =$D47-E47 -> -125.03658 | L47: =$D47-F47 -> -368.16291 | M47: =$D47-G47 -> -4813.6848 | N47: =$D47-H47 -> -9615.7661 | O47: =$D47-I47 -> -14536.799 | Q47: =IFERROR($D47/E47-1,0) -> 0.0023186557 | R47: =IFERROR($D47/F47-1,0) -> 0.006858066 | S47: =IFERROR($D47/G47-1,0) -> 0.097764256 | T47: =IFERROR($D47/H47-1,0) -> 0.21639783 | U47: =IFERROR($D47/I47-1,0) -> 0.36788462 | W47: =SUM(W44:W46) -> -161179 | X47: =SUM(X44:X46) -> -160982.96 | Y47: =SUM(Y44:Y46) -> -107127.64 | Z47: =SUM(Z44:Z46) -> -146667.85 | AA47: =SUM(AA44:AA46) -> -131964.31 | AB47: =SUM(AB44:AB46) -> -117216.02 | AD47: =$W47-X47 -> -196.03933 | AE47: =$W47-Y47 -> -54051.361 | AF47: =$W47-Z47 -> -14511.151 | AG47: =$W47-AA47 -> -29214.684 | AH47: =$W47-AB47 -> -43962.983 | AJ47: =IFERROR($W47/X47-1,0) -> 0.0012177645 | AK47: =IFERROR($W47/Y47-1,0) -> 0.50455103 | AL47: =IFERROR($W47/Z47-1,0) -> 0.098938866 | AM47: =IFERROR($W47/AA47-1,0) -> 0.22138322 | AN47: =IFERROR($W47/AB47-1,0) -> 0.37505952
C50: Vigente | D50: =D38+D44 -> 18615.309 | E50: =E38+E44 -> 17237.043 | F50: =F38+F44 -> 11978.157 | G50: =G38+G44 -> 17138.459 | H50: =H38+H44 -> 17418.165 | I50: =I38+I44 -> 17129.741 | K50: =$D50-E50 -> 1378.2657 | L50: =$D50-F50 -> 6637.1521 | M50: =$D50-G50 -> 1476.8505 | N50: =$D50-H50 -> 1197.1437 | O50: =$D50-I50 -> 1485.5683 | Q50: =IFERROR($D50/E50-1,0) -> 0.079959523 | R50: =IFERROR($D50/F50-1,0) -> 0.55410463 | S50: =IFERROR($D50/G50-1,0) -> 0.08617172 | T50: =IFERROR($D50/H50-1,0) -> 0.06872961 | U50: =IFERROR($D50/I50-1,0) -> 0.086724507 | W50: =W38+W44 -> 49018.297 | X50: =X38+X44 -> 45574.143 | Y50: =Y38+Y44 -> 30402.988 | Z50: =Z38+Z44 -> 45840.01 | AA50: =AA38+AA44 -> 47839.119 | AB50: =AB38+AB44 -> 46063.313 | AD50: =$W50-X50 -> 3444.1545 | AE50: =$W50-Y50 -> 18615.309 | AF50: =$W50-Z50 -> 3178.287 | AG50: =$W50-AA50 -> 1179.1782 | AH50: =$W50-AB50 -> 2954.9848 | AJ50: =IFERROR($W50/X50-1,0) -> 0.075572556 | AK50: =IFERROR($W50/Y50-1,0) -> 0.6122855 | AL50: =IFERROR($W50/Z50-1,0) -> 0.069334342 | AM50: =IFERROR($W50/AA50-1,0) -> 0.024648827 | AN50: =IFERROR($W50/AB50-1,0) -> 0.064150506
C51: Refinanciado | D51: =D39+D45 -> -150.97141 | E51: =E39+E45 -> -137.56817 | F51: =F39+F45 -> -139.99088 | G51: =G39+G45 -> -124.34356 | H51: =H39+H45 -> -129.08027 | I51: =I39+I45 -> -135.84478 | K51: =$D51-E51 -> -13.403238 | L51: =$D51-F51 -> -10.980524 | M51: =$D51-G51 -> -26.627848 | N51: =$D51-H51 -> -21.891141 | O51: =$D51-I51 -> -15.126627 | Q51: =IFERROR($D51/E51-1,0) -> 0.097429791 | R51: =IFERROR($D51/F51-1,0) -> 0.078437425 | S51: =IFERROR($D51/G51-1,0) -> 0.21414738 | T51: =IFERROR($D51/H51-1,0) -> 0.16959324 | U51: =IFERROR($D51/I51-1,0) -> 0.11135228 | W51: =W39+W45 -> -434.70243 | X51: =X39+X45 -> -409.64609 | Y51: =Y39+Y45 -> -283.73102 | Z51: =Z39+Z45 -> -374.56083 | AA51: =AA39+AA45 -> -382.45111 | AB51: =AB39+AB45 -> -404.67559 | AD51: =$W51-X51 -> -25.056346 | AE51: =$W51-Y51 -> -150.97141 | AF51: =$W51-Z51 -> -60.1416 | AG51: =$W51-AA51 -> -52.251325 | AH51: =$W51-AB51 -> -30.026841 | AJ51: =IFERROR($W51/X51-1,0) -> 0.061165837 | AK51: =IFERROR($W51/Y51-1,0) -> 0.53209341 | AL51: =IFERROR($W51/Z51-1,0) -> 0.16056564 | AM51: =IFERROR($W51/AA51-1,0) -> 0.13662224 | AN51: =IFERROR($W51/AB51-1,0) -> 0.074199783
C52: Vencido y Judicial | D52: =D40+D46 -> 1669.8591 | E52: =E40+E46 -> 1932.8421 | F52: =F40+F46 -> 1021.4289 | G52: =G40+G46 -> 1691.7885 | H52: =H40+H46 -> 1272.8359 | I52: =I40+I46 -> 1157.1466 | K52: =$D52-E52 -> -262.98301 | L52: =$D52-F52 -> 648.43027 | M52: =$D52-G52 -> -21.929405 | N52: =$D52-H52 -> 397.02328 | O52: =$D52-I52 -> 512.71256 | Q52: =IFERROR($D52/E52-1,0) -> -0.13606026 | R52: =IFERROR($D52/F52-1,0) -> 0.63482665 | S52: =IFERROR($D52/G52-1,0) -> -0.012962261 | T52: =IFERROR($D52/H52-1,0) -> 0.31192025 | U52: =IFERROR($D52/I52-1,0) -> 0.4430835 | W52: =W40+W46 -> 3904.8398 | X52: =X40+X46 -> 5457.9497 | Y52: =Y40+Y46 -> 2234.9807 | Z52: =Z40+Z46 -> 4053.9709 | AA52: =AA40+AA46 -> 3647.1898 | AB52: =AB40+AB46 -> 2467.0169 | AD52: =$W52-X52 -> -1553.1099 | AE52: =$W52-Y52 -> 1669.8591 | AF52: =$W52-Z52 -> -149.13109 | AG52: =$W52-AA52 -> 257.65004 | AH52: =$W52-AB52 -> 1437.8229 | AJ52: =IFERROR($W52/X52-1,0) -> -0.28455922 | AK52: =IFERROR($W52/Y52-1,0) -> 0.74714702 | AL52: =IFERROR($W52/Z52-1,0) -> -0.036786424 | AM52: =IFERROR($W52/AA52-1,0) -> 0.070643443 | AN52: =IFERROR($W52/AB52-1,0) -> 0.58281845
C53: Resultado Financiero Bruto | D53: =D41+D47 -> 20134.197 | E53: =E41+E47 -> 19032.317 | F53: =F41+F47 -> 12859.595 | G53: =G41+G47 -> 18705.904 | H53: =H41+H47 -> 18561.921 | I53: =I41+I47 -> 18151.042 | K53: =$D53-E53 -> 1101.8795 | L53: =$D53-F53 -> 7274.6019 | M53: =$D53-G53 -> 1428.2932 | N53: =$D53-H53 -> 1572.2758 | O53: =$D53-I53 -> 1983.1543 | Q53: =IFERROR($D53/E53-1,0) -> 0.057895184 | R53: =IFERROR($D53/F53-1,0) -> 0.56569449 | S53: =IFERROR($D53/G53-1,0) -> 0.07635521 | T53: =IFERROR($D53/H53-1,0) -> 0.084704371 | U53: =IFERROR($D53/I53-1,0) -> 0.10925842 | W53: =W41+W47 -> 52488.435 | X53: =X41+X47 -> 50622.447 | Y53: =Y41+Y47 -> 32354.238 | Z53: =Z41+Z47 -> 49519.421 | AA53: =AA41+AA47 -> 51103.858 | AB53: =AB41+AB47 -> 48125.654 | AD53: =$W53-X53 -> 1865.9882 | AE53: =$W53-Y53 -> 20134.197 | AF53: =$W53-Z53 -> 2969.0143 | AG53: =$W53-AA53 -> 1384.5769 | AH53: =$W53-AB53 -> 4362.7809 | AJ53: =IFERROR($W53/X53-1,0) -> 0.036860886 | AK53: =IFERROR($W53/Y53-1,0) -> 0.62230477 | AL53: =IFERROR($W53/Z53-1,0) -> 0.059956564 | AM53: =IFERROR($W53/AA53-1,0) -> 0.027093392 | AN53: =IFERROR($W53/AB53-1,0) -> 0.090653956
A56: Gasto_Provision | C56: Provisiones Cartera | D56: {=_xlfn.XLOOKUP(1, (INDIRECT("'"&$C$6&"'!$6:$6")=D$6)* (INDIRECT("'"&$C$6&"'!$5:$5")=D$5), INDIRECT("'"&$C$6&"'!"&ROW()&":"&ROW()) )} -> -2362.5188 | E56: {=_xlfn.XLOOKUP(1, (INDIRECT("'"&$C$6&"'!$6:$6")=E$6)* (INDIRECT("'"&$C$6&"'!$5:$5")=E$5), INDIRECT("'"&$C$6&"'!"&ROW()&":"&ROW()) )} -> -5342.0107 | F56: {=_xlfn.XLOOKUP(1, (INDIRECT("'"&$C$6&"'!$6:$6")=F$6)* (INDIRECT("'"&$C$6&"'!$5:$5")=F$5), INDIRECT("'"&$C$6&"'!"&ROW()&":"&ROW()) )} -> 1220.19 | G56: {=_xlfn.XLOOKUP(1, (INDIRECT("'"&$C$6&"'!$6:$6")=G$6)* (INDIRECT("'"&$C$6&"'!$5:$5")=G$5), INDIRECT("'"&$C$6&"'!"&ROW()&":"&ROW()) )} -> -1775.784 | H56: {=_xlfn.XLOOKUP(1, (INDIRECT("'"&$C$6&"'!$6:$6")=H$6)* (INDIRECT("'"&$C$6&"'!$5:$5")=H$5), INDIRECT("'"&$C$6&"'!"&ROW()&":"&ROW()) )} -> -1164.9272 | I56: {=_xlfn.XLOOKUP(1, (INDIRECT("'"&$C$6&"'!$6:$6")=I$6)* (INDIRECT("'"&$C$6&"'!$5:$5")=I$5), INDIRECT("'"&$C$6&"'!"&ROW()&":"&ROW()) )} -> -1002.9986 | K56: =$D56-E56 -> 2979.4919 | L56: =$D56-F56 -> -3582.7088 | M56: =$D56-G56 -> -586.73479 | N56: =$D56-H56 -> -1197.5915 | O56: =$D56-I56 -> -1359.5202 | Q56: =IFERROR($D56/E56-1,0) -> -0.55774728 | R56: =IFERROR($D56/F56-1,0) -> -2.9361893 | S56: =IFERROR($D56/G56-1,0) -> 0.33040887 | T56: =IFERROR($D56/H56-1,0) -> 1.0280398 | U56: =IFERROR($D56/I56-1,0) -> 1.3554557 | W56: {=INDIRECT("'"&$C$6&"'!"&ADDRESS(ROW(),COLUMN()+44))} -> -613.56855 | X56: {=INDIRECT("'"&$C$6&"'!"&ADDRESS(ROW(),COLUMN()+44))} -> -11935.066 | Y56: {=INDIRECT("'"&$C$6&"'!"&ADDRESS(ROW(),COLUMN()+44))} -> 1748.9502 | Z56: {=INDIRECT("'"&$C$6&"'!"&ADDRESS(ROW(),COLUMN()+44))} -> -9021.4881 | AA56: {=INDIRECT("'"&$C$6&"'!"&ADDRESS(ROW(),COLUMN()+44))} -> -11150.787 | AB56: {=INDIRECT("'"&$C$6&"'!"&ADDRESS(ROW(),COLUMN()+44))} -> -5539.6947 | AD56: =$W56-X56 -> 11321.498 | AE56: =$W56-Y56 -> -2362.5188 | AF56: =$W56-Z56 -> 8407.9195 | AG56: =$W56-AA56 -> 10537.219 | AH56: =$W56-AB56 -> 4926.1261 | AJ56: =IFERROR($W56/X56-1,0) -> -0.94859111 | AK56: =IFERROR($W56/Y56-1,0) -> -1.350821 | AL56: =IFERROR($W56/Z56-1,0) -> -0.9319881 | AM56: =IFERROR($W56/AA56-1,0) -> -0.94497531 | AN56: =IFERROR($W56/AB56-1,0) -> -0.88924145
A57: Recupero | C57: Recupero de Castigos | D57: {=_xlfn.XLOOKUP(1, (INDIRECT("'"&$C$6&"'!$6:$6")=D$6)* (INDIRECT("'"&$C$6&"'!$5:$5")=D$5), INDIRECT("'"&$C$6&"'!"&ROW()&":"&ROW()) )} -> 0.48019 | E57: {=_xlfn.XLOOKUP(1, (INDIRECT("'"&$C$6&"'!$6:$6")=E$6)* (INDIRECT("'"&$C$6&"'!$5:$5")=E$5), INDIRECT("'"&$C$6&"'!"&ROW()&":"&ROW()) )} -> 0 | F57: {=_xlfn.XLOOKUP(1, (INDIRECT("'"&$C$6&"'!$6:$6")=F$6)* (INDIRECT("'"&$C$6&"'!$5:$5")=F$5), INDIRECT("'"&$C$6&"'!"&ROW()&":"&ROW()) )} -> 20.095 | G57: {=_xlfn.XLOOKUP(1, (INDIRECT("'"&$C$6&"'!$6:$6")=G$6)* (INDIRECT("'"&$C$6&"'!$5:$5")=G$5), INDIRECT("'"&$C$6&"'!"&ROW()&":"&ROW()) )} -> 60.70376 | H57: {=_xlfn.XLOOKUP(1, (INDIRECT("'"&$C$6&"'!$6:$6")=H$6)* (INDIRECT("'"&$C$6&"'!$5:$5")=H$5), INDIRECT("'"&$C$6&"'!"&ROW()&":"&ROW()) )} -> 0 | I57: {=_xlfn.XLOOKUP(1, (INDIRECT("'"&$C$6&"'!$6:$6")=I$6)* (INDIRECT("'"&$C$6&"'!$5:$5")=I$5), INDIRECT("'"&$C$6&"'!"&ROW()&":"&ROW()) )} -> 44.15912 | K57: =$D57-E57 -> 0.48019 | L57: =$D57-F57 -> -19.61481 | M57: =$D57-G57 -> -60.22357 | N57: =$D57-H57 -> 0.48019 | O57: =$D57-I57 -> -43.67893 | Q57: =IFERROR($D57/E57-1,0) -> 0 | R57: =IFERROR($D57/F57-1,0) -> -0.97610401 | S57: =IFERROR($D57/G57-1,0) -> -0.99208962 | T57: =IFERROR($D57/H57-1,0) -> 0 | U57: =IFERROR($D57/I57-1,0) -> -0.98912592 | W57: {=INDIRECT("'"&$C$6&"'!"&ADDRESS(ROW(),COLUMN()+44))} -> 20.57519 | X57: {=INDIRECT("'"&$C$6&"'!"&ADDRESS(ROW(),COLUMN()+44))} -> 0 | Y57: {=INDIRECT("'"&$C$6&"'!"&ADDRESS(ROW(),COLUMN()+44))} -> 20.095 | Z57: {=INDIRECT("'"&$C$6&"'!"&ADDRESS(ROW(),COLUMN()+44))} -> 64.10855 | AA57: {=INDIRECT("'"&$C$6&"'!"&ADDRESS(ROW(),COLUMN()+44))} -> 3.37 | AB57: {=INDIRECT("'"&$C$6&"'!"&ADDRESS(ROW(),COLUMN()+44))} -> 44.85912 | AD57: =$W57-X57 -> 20.57519 | AE57: =$W57-Y57 -> 0.48019 | AF57: =$W57-Z57 -> -43.53336 | AG57: =$W57-AA57 -> 17.20519 | AH57: =$W57-AB57 -> -24.28393 | AJ57: =IFERROR($W57/X57-1,0) -> 0 | AK57: =IFERROR($W57/Y57-1,0) -> 0.023895994 | AL57: =IFERROR($W57/Z57-1,0) -> -0.67905701 | AM57: =IFERROR($W57/AA57-1,0) -> 5.1053976 | AN57: =IFERROR($W57/AB57-1,0) -> -0.54133764
C58: Provisiones Netas | D58: =SUM(D56:D57) -> -2362.0386 | E58: =SUM(E56:E57) -> -5342.0107 | F58: =SUM(F56:F57) -> 1240.285 | G58: =SUM(G56:G57) -> -1715.0802 | H58: =SUM(H56:H57) -> -1164.9272 | I58: =SUM(I56:I57) -> -958.83948 | K58: =$D58-E58 -> 2979.9721 | L58: =$D58-F58 -> -3602.3236 | M58: =$D58-G58 -> -646.95836 | N58: =$D58-H58 -> -1197.1114 | O58: =$D58-I58 -> -1403.1991 | Q58: =IFERROR($D58/E58-1,0) -> -0.55783717 | R58: =IFERROR($D58/F58-1,0) -> -2.9044321 | S58: =IFERROR($D58/G58-1,0) -> 0.37721755 | T58: =IFERROR($D58/H58-1,0) -> 1.0276276 | U58: =IFERROR($D58/I58-1,0) -> 1.4634348 | W58: =SUM(W56:W57) -> -592.99336 | X58: =SUM(X56:X57) -> -11935.066 | Y58: =SUM(Y56:Y57) -> 1769.0452 | Z58: =SUM(Z56:Z57) -> -8957.3795 | AA58: =SUM(AA56:AA57) -> -11147.417 | AB58: =SUM(AB56:AB57) -> -5494.8356 | AD58: =$W58-X58 -> 11342.073 | AE58: =$W58-Y58 -> -2362.0386 | AF58: =$W58-Z58 -> 8364.3861 | AG58: =$W58-AA58 -> 10554.424 | AH58: =$W58-AB58 -> 4901.8422 | AJ58: =IFERROR($W58/X58-1,0) -> -0.95031503 | AK58: =IFERROR($W58/Y58-1,0) -> -1.3352053 | AL58: =IFERROR($W58/Z58-1,0) -> -0.93379834 | AM58: =IFERROR($W58/AA58-1,0) -> -0.94680442 | AN58: =IFERROR($W58/AB58-1,0) -> -0.89208169
C60: Resultado Financiero Neto | D60: =D53+D58 -> 17772.158 | E60: =E53+E58 -> 13690.306 | F60: =F53+F58 -> 14099.88 | G60: =G53+G58 -> 16990.823 | H60: =H53+H58 -> 17396.994 | I60: =I53+I58 -> 17192.203 | K60: =$D60-E60 -> 4081.8516 | L60: =$D60-F60 -> 3672.2783 | M60: =$D60-G60 -> 781.33484 | N60: =$D60-H60 -> 375.16448 | O60: =$D60-I60 -> 579.95514 | Q60: =IFERROR($D60/E60-1,0) -> 0.29815634 | R60: =IFERROR($D60/F60-1,0) -> 0.26044749 | S60: =IFERROR($D60/G60-1,0) -> 0.045985696 | T60: =IFERROR($D60/H60-1,0) -> 0.021564903 | U60: =IFERROR($D60/I60-1,0) -> 0.033733614 | W60: =W53+W58 -> 51895.441 | X60: =X53+X58 -> 38687.38 | Y60: =Y53+Y58 -> 34123.283 | Z60: =Z53+Z58 -> 40562.041 | AA60: =AA53+AA58 -> 39956.441 | AB60: =AB53+AB58 -> 42630.818 | AD60: =$W60-X60 -> 13208.061 | AE60: =$W60-Y60 -> 17772.158 | AF60: =$W60-Z60 -> 11333.4 | AG60: =$W60-AA60 -> 11939.001 | AH60: =$W60-AB60 -> 9264.6231 | AJ60: =IFERROR($W60/X60-1,0) -> 0.3414049 | AK60: =IFERROR($W60/Y60-1,0) -> 0.52082204 | AL60: =IFERROR($W60/Z60-1,0) -> 0.27940903 | AM60: =IFERROR($W60/AA60-1,0) -> 0.2988004 | AN60: =IFERROR($W60/AB60-1,0) -> 0.2173222
A63: INOF | C63: Seguro de Desgravamen | D63: {=_xlfn.XLOOKUP(1, (INDIRECT("'"&$C$6&"'!$6:$6")=D$6)* (INDIRECT("'"&$C$6&"'!$5:$5")=D$5), INDIRECT("'"&$C$6&"'!"&ROW()&":"&ROW()) )} -> 1018.1366 | E63: {=_xlfn.XLOOKUP(1, (INDIRECT("'"&$C$6&"'!$6:$6")=E$6)* (INDIRECT("'"&$C$6&"'!$5:$5")=E$5), INDIRECT("'"&$C$6&"'!"&ROW()&":"&ROW()) )} -> 657.15694 | F63: {=_xlfn.XLOOKUP(1, (INDIRECT("'"&$C$6&"'!$6:$6")=F$6)* (INDIRECT("'"&$C$6&"'!$5:$5")=F$5), INDIRECT("'"&$C$6&"'!"&ROW()&":"&ROW()) )} -> 259.69512 | G63: {=_xlfn.XLOOKUP(1, (INDIRECT("'"&$C$6&"'!$6:$6")=G$6)* (INDIRECT("'"&$C$6&"'!$5:$5")=G$5), INDIRECT("'"&$C$6&"'!"&ROW()&":"&ROW()) )} -> 814.49953 | H63: {=_xlfn.XLOOKUP(1, (INDIRECT("'"&$C$6&"'!$6:$6")=H$6)* (INDIRECT("'"&$C$6&"'!$5:$5")=H$5), INDIRECT("'"&$C$6&"'!"&ROW()&":"&ROW()) )} -> 529.90471 | I63: {=_xlfn.XLOOKUP(1, (INDIRECT("'"&$C$6&"'!$6:$6")=I$6)* (INDIRECT("'"&$C$6&"'!$5:$5")=I$5), INDIRECT("'"&$C$6&"'!"&ROW()&":"&ROW()) )} -> 787.93693 | K63: =$D63-E63 -> 360.97966 | L63: =$D63-F63 -> 758.44148 | M63: =$D63-G63 -> 203.63707 | N63: =$D63-H63 -> 488.23189 | O63: =$D63-I63 -> 230.19967 | Q63: =IFERROR($D63/E63-1,0) -> 0.5493051 | R63: =IFERROR($D63/F63-1,0) -> 2.9205072 | S63: =IFERROR($D63/G63-1,0) -> 0.25001496 | T63: =IFERROR($D63/H63-1,0) -> 0.9213579 | U63: =IFERROR($D63/I63-1,0) -> 0.29215494 | W63: {=INDIRECT("'"&$C$6&"'!"&ADDRESS(ROW(),COLUMN()+44))} -> 2118.398 | X63: {=INDIRECT("'"&$C$6&"'!"&ADDRESS(ROW(),COLUMN()+44))} -> 1971.4708 | Y63: {=INDIRECT("'"&$C$6&"'!"&ADDRESS(ROW(),COLUMN()+44))} -> 1100.2614 | Z63: {=INDIRECT("'"&$C$6&"'!"&ADDRESS(ROW(),COLUMN()+44))} -> 1906.6406 | AA63: {=INDIRECT("'"&$C$6&"'!"&ADDRESS(ROW(),COLUMN()+44))} -> 1322.2734 | AB63: {=INDIRECT("'"&$C$6&"'!"&ADDRESS(ROW(),COLUMN()+44))} -> 2050.6329 | AD63: =$W63-X63 -> 146.92718 | AE63: =$W63-Y63 -> 1018.1366 | AF63: =$W63-Z63 -> 211.75736 | AG63: =$W63-AA63 -> 796.1246 | AH63: =$W63-AB63 -> 67.76508 | AJ63: =IFERROR($W63/X63-1,0) -> 0.074526684 | AK63: =IFERROR($W63/Y63-1,0) -> 0.92535882 | AL63: =IFERROR($W63/Z63-1,0) -> 0.11106307 | AM63: =IFERROR($W63/AA63-1,0) -> 0.60208773 | AN63: =IFERROR($W63/AB63-1,0) -> 0.033045934
A64: INOF | C64: Comisiones | D64: {=_xlfn.XLOOKUP(1, (INDIRECT("'"&$C$6&"'!$6:$6")=D$6)* (INDIRECT("'"&$C$6&"'!$5:$5")=D$5), INDIRECT("'"&$C$6&"'!"&ROW()&":"&ROW()) )} -> 376.68121 | E64: {=_xlfn.XLOOKUP(1, (INDIRECT("'"&$C$6&"'!$6:$6")=E$6)* (INDIRECT("'"&$C$6&"'!$5:$5")=E$5), INDIRECT("'"&$C$6&"'!"&ROW()&":"&ROW()) )} -> 413.71093 | F64: {=_xlfn.XLOOKUP(1, (INDIRECT("'"&$C$6&"'!$6:$6")=F$6)* (INDIRECT("'"&$C$6&"'!$5:$5")=F$5), INDIRECT("'"&$C$6&"'!"&ROW()&":"&ROW()) )} -> 449.58389 | G64: {=_xlfn.XLOOKUP(1, (INDIRECT("'"&$C$6&"'!$6:$6")=G$6)* (INDIRECT("'"&$C$6&"'!$5:$5")=G$5), INDIRECT("'"&$C$6&"'!"&ROW()&":"&ROW()) )} -> 318.50246 | H64: {=_xlfn.XLOOKUP(1, (INDIRECT("'"&$C$6&"'!$6:$6")=H$6)* (INDIRECT("'"&$C$6&"'!$5:$5")=H$5), INDIRECT("'"&$C$6&"'!"&ROW()&":"&ROW()) )} -> 385.38059 | I64: {=_xlfn.XLOOKUP(1, (INDIRECT("'"&$C$6&"'!$6:$6")=I$6)* (INDIRECT("'"&$C$6&"'!$5:$5")=I$5), INDIRECT("'"&$C$6&"'!"&ROW()&":"&ROW()) )} -> 373.30377 | K64: =$D64-E64 -> -37.029729 | L64: =$D64-F64 -> -72.90268 | M64: =$D64-G64 -> 58.178749 | N64: =$D64-H64 -> -8.6993855 | O64: =$D64-I64 -> 3.3774333 | Q64: =IFERROR($D64/E64-1,0) -> -0.089506286 | R64: =IFERROR($D64/F64-1,0) -> -0.1621559 | S64: =IFERROR($D64/G64-1,0) -> 0.18266342 | T64: =IFERROR($D64/H64-1,0) -> -0.022573491 | U64: =IFERROR($D64/I64-1,0) -> 0.0090474128 | W64: {=INDIRECT("'"&$C$6&"'!"&ADDRESS(ROW(),COLUMN()+44))} -> 1314.3344 | X64: {=INDIRECT("'"&$C$6&"'!"&ADDRESS(ROW(),COLUMN()+44))} -> 1235.6628 | Y64: {=INDIRECT("'"&$C$6&"'!"&ADDRESS(ROW(),COLUMN()+44))} -> 937.65317 | Z64: {=INDIRECT("'"&$C$6&"'!"&ADDRESS(ROW(),COLUMN()+44))} -> 1247.9668 | AA64: {=INDIRECT("'"&$C$6&"'!"&ADDRESS(ROW(),COLUMN()+44))} -> 1317.3101 | AB64: {=INDIRECT("'"&$C$6&"'!"&ADDRESS(ROW(),COLUMN()+44))} -> 1320.247 | AD64: =$W64-X64 -> 78.671542 | AE64: =$W64-Y64 -> 376.68121 | AF64: =$W64-Z64 -> 66.36758 | AG64: =$W64-AA64 -> -2.9757293 | AH64: =$W64-AB64 -> -5.9126358 | AJ64: =IFERROR($W64/X64-1,0) -> 0.063667483 | AK64: =IFERROR($W64/Y64-1,0) -> 0.40172765 | AL64: =IFERROR($W64/Z64-1,0) -> 0.053180566 | AM64: =IFERROR($W64/AA64-1,0) -> -0.0022589436 | AN64: =IFERROR($W64/AB64-1,0) -> -0.0044784315
A65: INOF | C65: Gastos de casilleros | D65: {=_xlfn.XLOOKUP(1, (INDIRECT("'"&$C$6&"'!$6:$6")=D$6)* (INDIRECT("'"&$C$6&"'!$5:$5")=D$5), INDIRECT("'"&$C$6&"'!"&ROW()&":"&ROW()) )} -> 10.080415 | E65: {=_xlfn.XLOOKUP(1, (INDIRECT("'"&$C$6&"'!$6:$6")=E$6)* (INDIRECT("'"&$C$6&"'!$5:$5")=E$5), INDIRECT("'"&$C$6&"'!"&ROW()&":"&ROW()) )} -> -8 | F65: {=_xlfn.XLOOKUP(1, (INDIRECT("'"&$C$6&"'!$6:$6")=F$6)* (INDIRECT("'"&$C$6&"'!$5:$5")=F$5), INDIRECT("'"&$C$6&"'!"&ROW()&":"&ROW()) )} -> 195.99659 | G65: {=_xlfn.XLOOKUP(1, (INDIRECT("'"&$C$6&"'!$6:$6")=G$6)* (INDIRECT("'"&$C$6&"'!$5:$5")=G$5), INDIRECT("'"&$C$6&"'!"&ROW()&":"&ROW()) )} -> -94.255726 | H65: {=_xlfn.XLOOKUP(1, (INDIRECT("'"&$C$6&"'!$6:$6")=H$6)* (INDIRECT("'"&$C$6&"'!$5:$5")=H$5), INDIRECT("'"&$C$6&"'!"&ROW()&":"&ROW()) )} -> -237.32362 | I65: {=_xlfn.XLOOKUP(1, (INDIRECT("'"&$C$6&"'!$6:$6")=I$6)* (INDIRECT("'"&$C$6&"'!$5:$5")=I$5), INDIRECT("'"&$C$6&"'!"&ROW()&":"&ROW()) )} -> -49.958925 | K65: =$D65-E65 -> 18.080415 | L65: =$D65-F65 -> -185.91618 | M65: =$D65-G65 -> 104.33614 | N65: =$D65-H65 -> 247.40404 | O65: =$D65-I65 -> 60.03934 | Q65: =IFERROR($D65/E65-1,0) -> -2.2600519 | R65: =IFERROR($D65/F65-1,0) -> -0.94856842 | S65: =IFERROR($D65/G65-1,0) -> -1.1069475 | T65: =IFERROR($D65/H65-1,0) -> -1.0424754 | U65: =IFERROR($D65/I65-1,0) -> -1.2017741 | W65: {=INDIRECT("'"&$C$6&"'!"&ADDRESS(ROW(),COLUMN()+44))} -> 97.82804 | X65: {=INDIRECT("'"&$C$6&"'!"&ADDRESS(ROW(),COLUMN()+44))} -> -24 | Y65: {=INDIRECT("'"&$C$6&"'!"&ADDRESS(ROW(),COLUMN()+44))} -> 87.747625 | Z65: {=INDIRECT("'"&$C$6&"'!"&ADDRESS(ROW(),COLUMN()+44))} -> -179.06191 | AA65: {=INDIRECT("'"&$C$6&"'!"&ADDRESS(ROW(),COLUMN()+44))} -> -707.60814 | AB65: {=INDIRECT("'"&$C$6&"'!"&ADDRESS(ROW(),COLUMN()+44))} -> -49.766875 | AD65: =$W65-X65 -> 121.82804 | AE65: =$W65-Y65 -> 10.080415 | AF65: =$W65-Z65 -> 276.88995 | AG65: =$W65-AA65 -> 805.43618 | AH65: =$W65-AB65 -> 147.59491 | AJ65: =IFERROR($W65/X65-1,0) -> -5.0761683 | AK65: =IFERROR($W65/Y65-1,0) -> 0.11487964 | AL65: =IFERROR($W65/Z65-1,0) -> -1.5463364 | AM65: =IFERROR($W65/AA65-1,0) -> -1.1382517 | AN65: =IFERROR($W65/AB65-1,0) -> -2.965726
A66: INOF | D66: {=_xlfn.XLOOKUP(1, (INDIRECT("'"&$C$6&"'!$6:$6")=D$6)* (INDIRECT("'"&$C$6&"'!$5:$5")=D$5), INDIRECT("'"&$C$6&"'!"&ROW()&":"&ROW()) )} -> 3.5757945 | E66: {=_xlfn.XLOOKUP(1, (INDIRECT("'"&$C$6&"'!$6:$6")=E$6)* (INDIRECT("'"&$C$6&"'!$5:$5")=E$5), INDIRECT("'"&$C$6&"'!"&ROW()&":"&ROW()) )} -> 1.6525918 | F66: {=_xlfn.XLOOKUP(1, (INDIRECT("'"&$C$6&"'!$6:$6")=F$6)* (INDIRECT("'"&$C$6&"'!$5:$5")=F$5), INDIRECT("'"&$C$6&"'!"&ROW()&":"&ROW()) )} -> 2.2528964 | G66: {=_xlfn.XLOOKUP(1, (INDIRECT("'"&$C$6&"'!$6:$6")=G$6)* (INDIRECT("'"&$C$6&"'!$5:$5")=G$5), INDIRECT("'"&$C$6&"'!"&ROW()&":"&ROW()) )} -> 3.4410434 | H66: {=_xlfn.XLOOKUP(1, (INDIRECT("'"&$C$6&"'!$6:$6")=H$6)* (INDIRECT("'"&$C$6&"'!$5:$5")=H$5), INDIRECT("'"&$C$6&"'!"&ROW()&":"&ROW()) )} -> 1.7143404 | I66: {=_xlfn.XLOOKUP(1, (INDIRECT("'"&$C$6&"'!$6:$6")=I$6)* (INDIRECT("'"&$C$6&"'!$5:$5")=I$5), INDIRECT("'"&$C$6&"'!"&ROW()&":"&ROW()) )} -> -1.4854462 | K66: =$D66-E66 -> 1.9232027 | L66: =$D66-F66 -> 1.3228981 | M66: =$D66-G66 -> 0.13475114 | N66: =$D66-H66 -> 1.8614541 | O66: =$D66-I66 -> 5.0612407 | Q66: =IFERROR($D66/E66-1,0) -> 1.1637494 | R66: =IFERROR($D66/F66-1,0) -> 0.58719879 | S66: =IFERROR($D66/G66-1,0) -> 0.039159966 | T66: =IFERROR($D66/H66-1,0) -> 1.0858136 | U66: =IFERROR($D66/I66-1,0) -> -3.4072191 | W66: {=INDIRECT("'"&$C$6&"'!"&ADDRESS(ROW(),COLUMN()+44))} -> 8.6162502 | X66: {=INDIRECT("'"&$C$6&"'!"&ADDRESS(ROW(),COLUMN()+44))} -> 4.9359254 | Y66: {=INDIRECT("'"&$C$6&"'!"&ADDRESS(ROW(),COLUMN()+44))} -> 5.0404557 | Z66: {=INDIRECT("'"&$C$6&"'!"&ADDRESS(ROW(),COLUMN()+44))} -> 6.3520381 | AA66: {=INDIRECT("'"&$C$6&"'!"&ADDRESS(ROW(),COLUMN()+44))} -> 2.8265034 | AB66: {=INDIRECT("'"&$C$6&"'!"&ADDRESS(ROW(),COLUMN()+44))} -> 0.09222281 | AD66: =$W66-X66 -> 3.6803249 | AE66: =$W66-Y66 -> 3.5757945 | AF66: =$W66-Z66 -> 2.2642121 | AG66: =$W66-AA66 -> 5.7897469 | AH66: =$W66-AB66 -> 8.5240274 | AJ66: =IFERROR($W66/X66-1,0) -> 0.74562004 | AK66: =IFERROR($W66/Y66-1,0) -> 0.70941889 | AL66: =IFERROR($W66/Z66-1,0) -> 0.35645443 | AM66: =IFERROR($W66/AA66-1,0) -> 2.0483778 | AN66: =IFERROR($W66/AB66-1,0) -> 92.428624
A67: INOF | D67: {=_xlfn.XLOOKUP(1, (INDIRECT("'"&$C$6&"'!$6:$6")=D$6)* (INDIRECT("'"&$C$6&"'!$5:$5")=D$5), INDIRECT("'"&$C$6&"'!"&ROW()&":"&ROW()) )} -> 0 | E67: {=_xlfn.XLOOKUP(1, (INDIRECT("'"&$C$6&"'!$6:$6")=E$6)* (INDIRECT("'"&$C$6&"'!$5:$5")=E$5), INDIRECT("'"&$C$6&"'!"&ROW()&":"&ROW()) )} -> 0 | F67: {=_xlfn.XLOOKUP(1, (INDIRECT("'"&$C$6&"'!$6:$6")=F$6)* (INDIRECT("'"&$C$6&"'!$5:$5")=F$5), INDIRECT("'"&$C$6&"'!"&ROW()&":"&ROW()) )} -> 0 | G67: {=_xlfn.XLOOKUP(1, (INDIRECT("'"&$C$6&"'!$6:$6")=G$6)* (INDIRECT("'"&$C$6&"'!$5:$5")=G$5), INDIRECT("'"&$C$6&"'!"&ROW()&":"&ROW()) )} -> 0 | H67: {=_xlfn.XLOOKUP(1, (INDIRECT("'"&$C$6&"'!$6:$6")=H$6)* (INDIRECT("'"&$C$6&"'!$5:$5")=H$5), INDIRECT("'"&$C$6&"'!"&ROW()&":"&ROW()) )} -> 0 | I67: {=_xlfn.XLOOKUP(1, (INDIRECT("'"&$C$6&"'!$6:$6")=I$6)* (INDIRECT("'"&$C$6&"'!$5:$5")=I$5), INDIRECT("'"&$C$6&"'!"&ROW()&":"&ROW()) )} -> 0 | K67: =$D67-E67 -> 0 | L67: =$D67-F67 -> 0 | M67: =$D67-G67 -> 0 | N67: =$D67-H67 -> 0 | O67: =$D67-I67 -> 0 | Q67: =IFERROR($D67/E67-1,0) -> 0 | R67: =IFERROR($D67/F67-1,0) -> 0 | S67: =IFERROR($D67/G67-1,0) -> 0 | T67: =IFERROR($D67/H67-1,0) -> 0 | U67: =IFERROR($D67/I67-1,0) -> 0 | W67: {=INDIRECT("'"&$C$6&"'!"&ADDRESS(ROW(),COLUMN()+44))} -> 0 | X67: {=INDIRECT("'"&$C$6&"'!"&ADDRESS(ROW(),COLUMN()+44))} -> 0 | Y67: {=INDIRECT("'"&$C$6&"'!"&ADDRESS(ROW(),COLUMN()+44))} -> 0 | Z67: {=INDIRECT("'"&$C$6&"'!"&ADDRESS(ROW(),COLUMN()+44))} -> 0 | AA67: {=INDIRECT("'"&$C$6&"'!"&ADDRESS(ROW(),COLUMN()+44))} -> 0 | AB67: {=INDIRECT("'"&$C$6&"'!"&ADDRESS(ROW(),COLUMN()+44))} -> 0 | AD67: =$W67-X67 -> 0 | AE67: =$W67-Y67 -> 0 | AF67: =$W67-Z67 -> 0 | AG67: =$W67-AA67 -> 0 | AH67: =$W67-AB67 -> 0 | AJ67: =IFERROR($W67/X67-1,0) -> 0 | AK67: =IFERROR($W67/Y67-1,0) -> 0 | AL67: =IFERROR($W67/Z67-1,0) -> 0 | AM67: =IFERROR($W67/AA67-1,0) -> 0 | AN67: =IFERROR($W67/AB67-1,0) -> 0
A68: INOF | D68: {=_xlfn.XLOOKUP(1, (INDIRECT("'"&$C$6&"'!$6:$6")=D$6)* (INDIRECT("'"&$C$6&"'!$5:$5")=D$5), INDIRECT("'"&$C$6&"'!"&ROW()&":"&ROW()) )} -> 0 | E68: {=_xlfn.XLOOKUP(1, (INDIRECT("'"&$C$6&"'!$6:$6")=E$6)* (INDIRECT("'"&$C$6&"'!$5:$5")=E$5), INDIRECT("'"&$C$6&"'!"&ROW()&":"&ROW()) )} -> 0 | F68: {=_xlfn.XLOOKUP(1, (INDIRECT("'"&$C$6&"'!$6:$6")=F$6)* (INDIRECT("'"&$C$6&"'!$5:$5")=F$5), INDIRECT("'"&$C$6&"'!"&ROW()&":"&ROW()) )} -> 0 | G68: {=_xlfn.XLOOKUP(1, (INDIRECT("'"&$C$6&"'!$6:$6")=G$6)* (INDIRECT("'"&$C$6&"'!$5:$5")=G$5), INDIRECT("'"&$C$6&"'!"&ROW()&":"&ROW()) )} -> 0 | H68: {=_xlfn.XLOOKUP(1, (INDIRECT("'"&$C$6&"'!$6:$6")=H$6)* (INDIRECT("'"&$C$6&"'!$5:$5")=H$5), INDIRECT("'"&$C$6&"'!"&ROW()&":"&ROW()) )} -> 0 | I68: {=_xlfn.XLOOKUP(1, (INDIRECT("'"&$C$6&"'!$6:$6")=I$6)* (INDIRECT("'"&$C$6&"'!$5:$5")=I$5), INDIRECT("'"&$C$6&"'!"&ROW()&":"&ROW()) )} -> 0 | K68: =$D68-E68 -> 0 | L68: =$D68-F68 -> 0 | M68: =$D68-G68 -> 0 | N68: =$D68-H68 -> 0 | O68: =$D68-I68 -> 0 | Q68: =IFERROR($D68/E68-1,0) -> 0 | R68: =IFERROR($D68/F68-1,0) -> 0 | S68: =IFERROR($D68/G68-1,0) -> 0 | T68: =IFERROR($D68/H68-1,0) -> 0 | U68: =IFERROR($D68/I68-1,0) -> 0 | W68: {=INDIRECT("'"&$C$6&"'!"&ADDRESS(ROW(),COLUMN()+44))} -> 0 | X68: {=INDIRECT("'"&$C$6&"'!"&ADDRESS(ROW(),COLUMN()+44))} -> 0 | Y68: {=INDIRECT("'"&$C$6&"'!"&ADDRESS(ROW(),COLUMN()+44))} -> 0 | Z68: {=INDIRECT("'"&$C$6&"'!"&ADDRESS(ROW(),COLUMN()+44))} -> 0 | AA68: {=INDIRECT("'"&$C$6&"'!"&ADDRESS(ROW(),COLUMN()+44))} -> 0 | AB68: {=INDIRECT("'"&$C$6&"'!"&ADDRESS(ROW(),COLUMN()+44))} -> 0 | AD68: =$W68-X68 -> 0 | AE68: =$W68-Y68 -> 0 | AF68: =$W68-Z68 -> 0 | AG68: =$W68-AA68 -> 0 | AH68: =$W68-AB68 -> 0 | AJ68: =IFERROR($W68/X68-1,0) -> 0 | AK68: =IFERROR($W68/Y68-1,0) -> 0 | AL68: =IFERROR($W68/Z68-1,0) -> 0 | AM68: =IFERROR($W68/AA68-1,0) -> 0 | AN68: =IFERROR($W68/AB68-1,0) -> 0
A69: INOF | D69: {=_xlfn.XLOOKUP(1, (INDIRECT("'"&$C$6&"'!$6:$6")=D$6)* (INDIRECT("'"&$C$6&"'!$5:$5")=D$5), INDIRECT("'"&$C$6&"'!"&ROW()&":"&ROW()) )} -> 0 | E69: {=_xlfn.XLOOKUP(1, (INDIRECT("'"&$C$6&"'!$6:$6")=E$6)* (INDIRECT("'"&$C$6&"'!$5:$5")=E$5), INDIRECT("'"&$C$6&"'!"&ROW()&":"&ROW()) )} -> 0 | F69: {=_xlfn.XLOOKUP(1, (INDIRECT("'"&$C$6&"'!$6:$6")=F$6)* (INDIRECT("'"&$C$6&"'!$5:$5")=F$5), INDIRECT("'"&$C$6&"'!"&ROW()&":"&ROW()) )} -> 0 | G69: {=_xlfn.XLOOKUP(1, (INDIRECT("'"&$C$6&"'!$6:$6")=G$6)* (INDIRECT("'"&$C$6&"'!$5:$5")=G$5), INDIRECT("'"&$C$6&"'!"&ROW()&":"&ROW()) )} -> 0 | H69: {=_xlfn.XLOOKUP(1, (INDIRECT("'"&$C$6&"'!$6:$6")=H$6)* (INDIRECT("'"&$C$6&"'!$5:$5")=H$5), INDIRECT("'"&$C$6&"'!"&ROW()&":"&ROW()) )} -> 0 | I69: {=_xlfn.XLOOKUP(1, (INDIRECT("'"&$C$6&"'!$6:$6")=I$6)* (INDIRECT("'"&$C$6&"'!$5:$5")=I$5), INDIRECT("'"&$C$6&"'!"&ROW()&":"&ROW()) )} -> 0 | K69: =$D69-E69 -> 0 | L69: =$D69-F69 -> 0 | M69: =$D69-G69 -> 0 | N69: =$D69-H69 -> 0 | O69: =$D69-I69 -> 0 | Q69: =IFERROR($D69/E69-1,0) -> 0 | R69: =IFERROR($D69/F69-1,0) -> 0 | S69: =IFERROR($D69/G69-1,0) -> 0 | T69: =IFERROR($D69/H69-1,0) -> 0 | U69: =IFERROR($D69/I69-1,0) -> 0 | W69: {=INDIRECT("'"&$C$6&"'!"&ADDRESS(ROW(),COLUMN()+44))} -> 0 | X69: {=INDIRECT("'"&$C$6&"'!"&ADDRESS(ROW(),COLUMN()+44))} -> 0 | Y69: {=INDIRECT("'"&$C$6&"'!"&ADDRESS(ROW(),COLUMN()+44))} -> 0 | Z69: {=INDIRECT("'"&$C$6&"'!"&ADDRESS(ROW(),COLUMN()+44))} -> 0 | AA69: {=INDIRECT("'"&$C$6&"'!"&ADDRESS(ROW(),COLUMN()+44))} -> 0 | AB69: {=INDIRECT("'"&$C$6&"'!"&ADDRESS(ROW(),COLUMN()+44))} -> 0 | AD69: =$W69-X69 -> 0 | AE69: =$W69-Y69 -> 0 | AF69: =$W69-Z69 -> 0 | AG69: =$W69-AA69 -> 0 | AH69: =$W69-AB69 -> 0 | AJ69: =IFERROR($W69/X69-1,0) -> 0 | AK69: =IFERROR($W69/Y69-1,0) -> 0 | AL69: =IFERROR($W69/Z69-1,0) -> 0 | AM69: =IFERROR($W69/AA69-1,0) -> 0 | AN69: =IFERROR($W69/AB69-1,0) -> 0
A70: INOF | D70: {=_xlfn.XLOOKUP(1, (INDIRECT("'"&$C$6&"'!$6:$6")=D$6)* (INDIRECT("'"&$C$6&"'!$5:$5")=D$5), INDIRECT("'"&$C$6&"'!"&ROW()&":"&ROW()) )} -> 0 | E70: {=_xlfn.XLOOKUP(1, (INDIRECT("'"&$C$6&"'!$6:$6")=E$6)* (INDIRECT("'"&$C$6&"'!$5:$5")=E$5), INDIRECT("'"&$C$6&"'!"&ROW()&":"&ROW()) )} -> 0 | F70: {=_xlfn.XLOOKUP(1, (INDIRECT("'"&$C$6&"'!$6:$6")=F$6)* (INDIRECT("'"&$C$6&"'!$5:$5")=F$5), INDIRECT("'"&$C$6&"'!"&ROW()&":"&ROW()) )} -> 0 | G70: {=_xlfn.XLOOKUP(1, (INDIRECT("'"&$C$6&"'!$6:$6")=G$6)* (INDIRECT("'"&$C$6&"'!$5:$5")=G$5), INDIRECT("'"&$C$6&"'!"&ROW()&":"&ROW()) )} -> 0 | H70: {=_xlfn.XLOOKUP(1, (INDIRECT("'"&$C$6&"'!$6:$6")=H$6)* (INDIRECT("'"&$C$6&"'!$5:$5")=H$5), INDIRECT("'"&$C$6&"'!"&ROW()&":"&ROW()) )} -> 0 | I70: {=_xlfn.XLOOKUP(1, (INDIRECT("'"&$C$6&"'!$6:$6")=I$6)* (INDIRECT("'"&$C$6&"'!$5:$5")=I$5), INDIRECT("'"&$C$6&"'!"&ROW()&":"&ROW()) )} -> 0 | K70: =$D70-E70 -> 0 | L70: =$D70-F70 -> 0 | M70: =$D70-G70 -> 0 | N70: =$D70-H70 -> 0 | O70: =$D70-I70 -> 0 | Q70: =IFERROR($D70/E70-1,0) -> 0 | R70: =IFERROR($D70/F70-1,0) -> 0 | S70: =IFERROR($D70/G70-1,0) -> 0 | T70: =IFERROR($D70/H70-1,0) -> 0 | U70: =IFERROR($D70/I70-1,0) -> 0 | W70: {=INDIRECT("'"&$C$6&"'!"&ADDRESS(ROW(),COLUMN()+44))} -> 0 | X70: {=INDIRECT("'"&$C$6&"'!"&ADDRESS(ROW(),COLUMN()+44))} -> 0 | Y70: {=INDIRECT("'"&$C$6&"'!"&ADDRESS(ROW(),COLUMN()+44))} -> 0 | Z70: {=INDIRECT("'"&$C$6&"'!"&ADDRESS(ROW(),COLUMN()+44))} -> 0 | AA70: {=INDIRECT("'"&$C$6&"'!"&ADDRESS(ROW(),COLUMN()+44))} -> 0 | AB70: {=INDIRECT("'"&$C$6&"'!"&ADDRESS(ROW(),COLUMN()+44))} -> 0 | AD70: =$W70-X70 -> 0 | AE70: =$W70-Y70 -> 0 | AF70: =$W70-Z70 -> 0 | AG70: =$W70-AA70 -> 0 | AH70: =$W70-AB70 -> 0 | AJ70: =IFERROR($W70/X70-1,0) -> 0 | AK70: =IFERROR($W70/Y70-1,0) -> 0 | AL70: =IFERROR($W70/Z70-1,0) -> 0 | AM70: =IFERROR($W70/AA70-1,0) -> 0 | AN70: =IFERROR($W70/AB70-1,0) -> 0
A71: INOF | D71: {=_xlfn.XLOOKUP(1, (INDIRECT("'"&$C$6&"'!$6:$6")=D$6)* (INDIRECT("'"&$C$6&"'!$5:$5")=D$5), INDIRECT("'"&$C$6&"'!"&ROW()&":"&ROW()) )} -> 0 | E71: {=_xlfn.XLOOKUP(1, (INDIRECT("'"&$C$6&"'!$6:$6")=E$6)* (INDIRECT("'"&$C$6&"'!$5:$5")=E$5), INDIRECT("'"&$C$6&"'!"&ROW()&":"&ROW()) )} -> 0 | F71: {=_xlfn.XLOOKUP(1, (INDIRECT("'"&$C$6&"'!$6:$6")=F$6)* (INDIRECT("'"&$C$6&"'!$5:$5")=F$5), INDIRECT("'"&$C$6&"'!"&ROW()&":"&ROW()) )} -> 0 | G71: {=_xlfn.XLOOKUP(1, (INDIRECT("'"&$C$6&"'!$6:$6")=G$6)* (INDIRECT("'"&$C$6&"'!$5:$5")=G$5), INDIRECT("'"&$C$6&"'!"&ROW()&":"&ROW()) )} -> 0 | H71: {=_xlfn.XLOOKUP(1, (INDIRECT("'"&$C$6&"'!$6:$6")=H$6)* (INDIRECT("'"&$C$6&"'!$5:$5")=H$5), INDIRECT("'"&$C$6&"'!"&ROW()&":"&ROW()) )} -> 0 | I71: {=_xlfn.XLOOKUP(1, (INDIRECT("'"&$C$6&"'!$6:$6")=I$6)* (INDIRECT("'"&$C$6&"'!$5:$5")=I$5), INDIRECT("'"&$C$6&"'!"&ROW()&":"&ROW()) )} -> 0 | K71: =$D71-E71 -> 0 | L71: =$D71-F71 -> 0 | M71: =$D71-G71 -> 0 | N71: =$D71-H71 -> 0 | O71: =$D71-I71 -> 0 | Q71: =IFERROR($D71/E71-1,0) -> 0 | R71: =IFERROR($D71/F71-1,0) -> 0 | S71: =IFERROR($D71/G71-1,0) -> 0 | T71: =IFERROR($D71/H71-1,0) -> 0 | U71: =IFERROR($D71/I71-1,0) -> 0 | W71: {=INDIRECT("'"&$C$6&"'!"&ADDRESS(ROW(),COLUMN()+44))} -> 0 | X71: {=INDIRECT("'"&$C$6&"'!"&ADDRESS(ROW(),COLUMN()+44))} -> 0 | Y71: {=INDIRECT("'"&$C$6&"'!"&ADDRESS(ROW(),COLUMN()+44))} -> 0 | Z71: {=INDIRECT("'"&$C$6&"'!"&ADDRESS(ROW(),COLUMN()+44))} -> 0 | AA71: {=INDIRECT("'"&$C$6&"'!"&ADDRESS(ROW(),COLUMN()+44))} -> 0 | AB71: {=INDIRECT("'"&$C$6&"'!"&ADDRESS(ROW(),COLUMN()+44))} -> 0 | AD71: =$W71-X71 -> 0 | AE71: =$W71-Y71 -> 0 | AF71: =$W71-Z71 -> 0 | AG71: =$W71-AA71 -> 0 | AH71: =$W71-AB71 -> 0 | AJ71: =IFERROR($W71/X71-1,0) -> 0 | AK71: =IFERROR($W71/Y71-1,0) -> 0 | AL71: =IFERROR($W71/Z71-1,0) -> 0 | AM71: =IFERROR($W71/AA71-1,0) -> 0 | AN71: =IFERROR($W71/AB71-1,0) -> 0
A72: INOF | D72: {=_xlfn.XLOOKUP(1, (INDIRECT("'"&$C$6&"'!$6:$6")=D$6)* (INDIRECT("'"&$C$6&"'!$5:$5")=D$5), INDIRECT("'"&$C$6&"'!"&ROW()&":"&ROW()) )} -> 0 | E72: {=_xlfn.XLOOKUP(1, (INDIRECT("'"&$C$6&"'!$6:$6")=E$6)* (INDIRECT("'"&$C$6&"'!$5:$5")=E$5), INDIRECT("'"&$C$6&"'!"&ROW()&":"&ROW()) )} -> 0 | F72: {=_xlfn.XLOOKUP(1, (INDIRECT("'"&$C$6&"'!$6:$6")=F$6)* (INDIRECT("'"&$C$6&"'!$5:$5")=F$5), INDIRECT("'"&$C$6&"'!"&ROW()&":"&ROW()) )} -> 0 | G72: {=_xlfn.XLOOKUP(1, (INDIRECT("'"&$C$6&"'!$6:$6")=G$6)* (INDIRECT("'"&$C$6&"'!$5:$5")=G$5), INDIRECT("'"&$C$6&"'!"&ROW()&":"&ROW()) )} -> 0 | H72: {=_xlfn.XLOOKUP(1, (INDIRECT("'"&$C$6&"'!$6:$6")=H$6)* (INDIRECT("'"&$C$6&"'!$5:$5")=H$5), INDIRECT("'"&$C$6&"'!"&ROW()&":"&ROW()) )} -> 0 | I72: {=_xlfn.XLOOKUP(1, (INDIRECT("'"&$C$6&"'!$6:$6")=I$6)* (INDIRECT("'"&$C$6&"'!$5:$5")=I$5), INDIRECT("'"&$C$6&"'!"&ROW()&":"&ROW()) )} -> 0 | K72: =$D72-E72 -> 0 | L72: =$D72-F72 -> 0 | M72: =$D72-G72 -> 0 | N72: =$D72-H72 -> 0 | O72: =$D72-I72 -> 0 | Q72: =IFERROR($D72/E72-1,0) -> 0 | R72: =IFERROR($D72/F72-1,0) -> 0 | S72: =IFERROR($D72/G72-1,0) -> 0 | T72: =IFERROR($D72/H72-1,0) -> 0 | U72: =IFERROR($D72/I72-1,0) -> 0 | W72: {=INDIRECT("'"&$C$6&"'!"&ADDRESS(ROW(),COLUMN()+44))} -> 0 | X72: {=INDIRECT("'"&$C$6&"'!"&ADDRESS(ROW(),COLUMN()+44))} -> 0 | Y72: {=INDIRECT("'"&$C$6&"'!"&ADDRESS(ROW(),COLUMN()+44))} -> 0 | Z72: {=INDIRECT("'"&$C$6&"'!"&ADDRESS(ROW(),COLUMN()+44))} -> 0 | AA72: {=INDIRECT("'"&$C$6&"'!"&ADDRESS(ROW(),COLUMN()+44))} -> 0 | AB72: {=INDIRECT("'"&$C$6&"'!"&ADDRESS(ROW(),COLUMN()+44))} -> 0 | AD72: =$W72-X72 -> 0 | AE72: =$W72-Y72 -> 0 | AF72: =$W72-Z72 -> 0 | AG72: =$W72-AA72 -> 0 | AH72: =$W72-AB72 -> 0 | AJ72: =IFERROR($W72/X72-1,0) -> 0 | AK72: =IFERROR($W72/Y72-1,0) -> 0 | AL72: =IFERROR($W72/Z72-1,0) -> 0 | AM72: =IFERROR($W72/AA72-1,0) -> 0 | AN72: =IFERROR($W72/AB72-1,0) -> 0
A73: INOF | D73: {=_xlfn.XLOOKUP(1, (INDIRECT("'"&$C$6&"'!$6:$6")=D$6)* (INDIRECT("'"&$C$6&"'!$5:$5")=D$5), INDIRECT("'"&$C$6&"'!"&ROW()&":"&ROW()) )} -> 0 | E73: {=_xlfn.XLOOKUP(1, (INDIRECT("'"&$C$6&"'!$6:$6")=E$6)* (INDIRECT("'"&$C$6&"'!$5:$5")=E$5), INDIRECT("'"&$C$6&"'!"&ROW()&":"&ROW()) )} -> 0 | F73: {=_xlfn.XLOOKUP(1, (INDIRECT("'"&$C$6&"'!$6:$6")=F$6)* (INDIRECT("'"&$C$6&"'!$5:$5")=F$5), INDIRECT("'"&$C$6&"'!"&ROW()&":"&ROW()) )} -> 0 | G73: {=_xlfn.XLOOKUP(1, (INDIRECT("'"&$C$6&"'!$6:$6")=G$6)* (INDIRECT("'"&$C$6&"'!$5:$5")=G$5), INDIRECT("'"&$C$6&"'!"&ROW()&":"&ROW()) )} -> 0 | H73: {=_xlfn.XLOOKUP(1, (INDIRECT("'"&$C$6&"'!$6:$6")=H$6)* (INDIRECT("'"&$C$6&"'!$5:$5")=H$5), INDIRECT("'"&$C$6&"'!"&ROW()&":"&ROW()) )} -> 0 | I73: {=_xlfn.XLOOKUP(1, (INDIRECT("'"&$C$6&"'!$6:$6")=I$6)* (INDIRECT("'"&$C$6&"'!$5:$5")=I$5), INDIRECT("'"&$C$6&"'!"&ROW()&":"&ROW()) )} -> 0 | K73: =$D73-E73 -> 0 | L73: =$D73-F73 -> 0 | M73: =$D73-G73 -> 0 | N73: =$D73-H73 -> 0 | O73: =$D73-I73 -> 0 | Q73: =IFERROR($D73/E73-1,0) -> 0 | R73: =IFERROR($D73/F73-1,0) -> 0 | S73: =IFERROR($D73/G73-1,0) -> 0 | T73: =IFERROR($D73/H73-1,0) -> 0 | U73: =IFERROR($D73/I73-1,0) -> 0 | W73: {=INDIRECT("'"&$C$6&"'!"&ADDRESS(ROW(),COLUMN()+44))} -> 0 | X73: {=INDIRECT("'"&$C$6&"'!"&ADDRESS(ROW(),COLUMN()+44))} -> 0 | Y73: {=INDIRECT("'"&$C$6&"'!"&ADDRESS(ROW(),COLUMN()+44))} -> 0 | Z73: {=INDIRECT("'"&$C$6&"'!"&ADDRESS(ROW(),COLUMN()+44))} -> 0 | AA73: {=INDIRECT("'"&$C$6&"'!"&ADDRESS(ROW(),COLUMN()+44))} -> 0 | AB73: {=INDIRECT("'"&$C$6&"'!"&ADDRESS(ROW(),COLUMN()+44))} -> 0 | AD73: =$W73-X73 -> 0 | AE73: =$W73-Y73 -> 0 | AF73: =$W73-Z73 -> 0 | AG73: =$W73-AA73 -> 0 | AH73: =$W73-AB73 -> 0 | AJ73: =IFERROR($W73/X73-1,0) -> 0 | AK73: =IFERROR($W73/Y73-1,0) -> 0 | AL73: =IFERROR($W73/Z73-1,0) -> 0 | AM73: =IFERROR($W73/AA73-1,0) -> 0 | AN73: =IFERROR($W73/AB73-1,0) -> 0
A74: INOF | D74: {=_xlfn.XLOOKUP(1, (INDIRECT("'"&$C$6&"'!$6:$6")=D$6)* (INDIRECT("'"&$C$6&"'!$5:$5")=D$5), INDIRECT("'"&$C$6&"'!"&ROW()&":"&ROW()) )} -> 0 | E74: {=_xlfn.XLOOKUP(1, (INDIRECT("'"&$C$6&"'!$6:$6")=E$6)* (INDIRECT("'"&$C$6&"'!$5:$5")=E$5), INDIRECT("'"&$C$6&"'!"&ROW()&":"&ROW()) )} -> 0 | F74: {=_xlfn.XLOOKUP(1, (INDIRECT("'"&$C$6&"'!$6:$6")=F$6)* (INDIRECT("'"&$C$6&"'!$5:$5")=F$5), INDIRECT("'"&$C$6&"'!"&ROW()&":"&ROW()) )} -> 0 | G74: {=_xlfn.XLOOKUP(1, (INDIRECT("'"&$C$6&"'!$6:$6")=G$6)* (INDIRECT("'"&$C$6&"'!$5:$5")=G$5), INDIRECT("'"&$C$6&"'!"&ROW()&":"&ROW()) )} -> 0 | H74: {=_xlfn.XLOOKUP(1, (INDIRECT("'"&$C$6&"'!$6:$6")=H$6)* (INDIRECT("'"&$C$6&"'!$5:$5")=H$5), INDIRECT("'"&$C$6&"'!"&ROW()&":"&ROW()) )} -> 0 | I74: {=_xlfn.XLOOKUP(1, (INDIRECT("'"&$C$6&"'!$6:$6")=I$6)* (INDIRECT("'"&$C$6&"'!$5:$5")=I$5), INDIRECT("'"&$C$6&"'!"&ROW()&":"&ROW()) )} -> 0 | K74: =$D74-E74 -> 0 | L74: =$D74-F74 -> 0 | M74: =$D74-G74 -> 0 | N74: =$D74-H74 -> 0 | O74: =$D74-I74 -> 0 | Q74: =IFERROR($D74/E74-1,0) -> 0 | R74: =IFERROR($D74/F74-1,0) -> 0 | S74: =IFERROR($D74/G74-1,0) -> 0 | T74: =IFERROR($D74/H74-1,0) -> 0 | U74: =IFERROR($D74/I74-1,0) -> 0 | W74: {=INDIRECT("'"&$C$6&"'!"&ADDRESS(ROW(),COLUMN()+44))} -> 0 | X74: {=INDIRECT("'"&$C$6&"'!"&ADDRESS(ROW(),COLUMN()+44))} -> 0 | Y74: {=INDIRECT("'"&$C$6&"'!"&ADDRESS(ROW(),COLUMN()+44))} -> 0 | Z74: {=INDIRECT("'"&$C$6&"'!"&ADDRESS(ROW(),COLUMN()+44))} -> 0 | AA74: {=INDIRECT("'"&$C$6&"'!"&ADDRESS(ROW(),COLUMN()+44))} -> 0 | AB74: {=INDIRECT("'"&$C$6&"'!"&ADDRESS(ROW(),COLUMN()+44))} -> 0 | AD74: =$W74-X74 -> 0 | AE74: =$W74-Y74 -> 0 | AF74: =$W74-Z74 -> 0 | AG74: =$W74-AA74 -> 0 | AH74: =$W74-AB74 -> 0 | AJ74: =IFERROR($W74/X74-1,0) -> 0 | AK74: =IFERROR($W74/Y74-1,0) -> 0 | AL74: =IFERROR($W74/Z74-1,0) -> 0 | AM74: =IFERROR($W74/AA74-1,0) -> 0 | AN74: =IFERROR($W74/AB74-1,0) -> 0
A75: INOF | D75: {=_xlfn.XLOOKUP(1, (INDIRECT("'"&$C$6&"'!$6:$6")=D$6)* (INDIRECT("'"&$C$6&"'!$5:$5")=D$5), INDIRECT("'"&$C$6&"'!"&ROW()&":"&ROW()) )} -> 0 | E75: {=_xlfn.XLOOKUP(1, (INDIRECT("'"&$C$6&"'!$6:$6")=E$6)* (INDIRECT("'"&$C$6&"'!$5:$5")=E$5), INDIRECT("'"&$C$6&"'!"&ROW()&":"&ROW()) )} -> 0 | F75: {=_xlfn.XLOOKUP(1, (INDIRECT("'"&$C$6&"'!$6:$6")=F$6)* (INDIRECT("'"&$C$6&"'!$5:$5")=F$5), INDIRECT("'"&$C$6&"'!"&ROW()&":"&ROW()) )} -> 0 | G75: {=_xlfn.XLOOKUP(1, (INDIRECT("'"&$C$6&"'!$6:$6")=G$6)* (INDIRECT("'"&$C$6&"'!$5:$5")=G$5), INDIRECT("'"&$C$6&"'!"&ROW()&":"&ROW()) )} -> 0 | H75: {=_xlfn.XLOOKUP(1, (INDIRECT("'"&$C$6&"'!$6:$6")=H$6)* (INDIRECT("'"&$C$6&"'!$5:$5")=H$5), INDIRECT("'"&$C$6&"'!"&ROW()&":"&ROW()) )} -> 0 | I75: {=_xlfn.XLOOKUP(1, (INDIRECT("'"&$C$6&"'!$6:$6")=I$6)* (INDIRECT("'"&$C$6&"'!$5:$5")=I$5), INDIRECT("'"&$C$6&"'!"&ROW()&":"&ROW()) )} -> 0 | K75: =$D75-E75 -> 0 | L75: =$D75-F75 -> 0 | M75: =$D75-G75 -> 0 | N75: =$D75-H75 -> 0 | O75: =$D75-I75 -> 0 | Q75: =IFERROR($D75/E75-1,0) -> 0 | R75: =IFERROR($D75/F75-1,0) -> 0 | S75: =IFERROR($D75/G75-1,0) -> 0 | T75: =IFERROR($D75/H75-1,0) -> 0 | U75: =IFERROR($D75/I75-1,0) -> 0 | W75: {=INDIRECT("'"&$C$6&"'!"&ADDRESS(ROW(),COLUMN()+44))} -> 0 | X75: {=INDIRECT("'"&$C$6&"'!"&ADDRESS(ROW(),COLUMN()+44))} -> 0 | Y75: {=INDIRECT("'"&$C$6&"'!"&ADDRESS(ROW(),COLUMN()+44))} -> 0 | Z75: {=INDIRECT("'"&$C$6&"'!"&ADDRESS(ROW(),COLUMN()+44))} -> 0 | AA75: {=INDIRECT("'"&$C$6&"'!"&ADDRESS(ROW(),COLUMN()+44))} -> 0 | AB75: {=INDIRECT("'"&$C$6&"'!"&ADDRESS(ROW(),COLUMN()+44))} -> 0 | AD75: =$W75-X75 -> 0 | AE75: =$W75-Y75 -> 0 | AF75: =$W75-Z75 -> 0 | AG75: =$W75-AA75 -> 0 | AH75: =$W75-AB75 -> 0 | AJ75: =IFERROR($W75/X75-1,0) -> 0 | AK75: =IFERROR($W75/Y75-1,0) -> 0 | AL75: =IFERROR($W75/Z75-1,0) -> 0 | AM75: =IFERROR($W75/AA75-1,0) -> 0 | AN75: =IFERROR($W75/AB75-1,0) -> 0
A76: INOF | D76: {=_xlfn.XLOOKUP(1, (INDIRECT("'"&$C$6&"'!$6:$6")=D$6)* (INDIRECT("'"&$C$6&"'!$5:$5")=D$5), INDIRECT("'"&$C$6&"'!"&ROW()&":"&ROW()) )} -> 0 | E76: {=_xlfn.XLOOKUP(1, (INDIRECT("'"&$C$6&"'!$6:$6")=E$6)* (INDIRECT("'"&$C$6&"'!$5:$5")=E$5), INDIRECT("'"&$C$6&"'!"&ROW()&":"&ROW()) )} -> 0 | F76: {=_xlfn.XLOOKUP(1, (INDIRECT("'"&$C$6&"'!$6:$6")=F$6)* (INDIRECT("'"&$C$6&"'!$5:$5")=F$5), INDIRECT("'"&$C$6&"'!"&ROW()&":"&ROW()) )} -> 0 | G76: {=_xlfn.XLOOKUP(1, (INDIRECT("'"&$C$6&"'!$6:$6")=G$6)* (INDIRECT("'"&$C$6&"'!$5:$5")=G$5), INDIRECT("'"&$C$6&"'!"&ROW()&":"&ROW()) )} -> 0 | H76: {=_xlfn.XLOOKUP(1, (INDIRECT("'"&$C$6&"'!$6:$6")=H$6)* (INDIRECT("'"&$C$6&"'!$5:$5")=H$5), INDIRECT("'"&$C$6&"'!"&ROW()&":"&ROW()) )} -> 0 | I76: {=_xlfn.XLOOKUP(1, (INDIRECT("'"&$C$6&"'!$6:$6")=I$6)* (INDIRECT("'"&$C$6&"'!$5:$5")=I$5), INDIRECT("'"&$C$6&"'!"&ROW()&":"&ROW()) )} -> 0 | K76: =$D76-E76 -> 0 | L76: =$D76-F76 -> 0 | M76: =$D76-G76 -> 0 | N76: =$D76-H76 -> 0 | O76: =$D76-I76 -> 0 | Q76: =IFERROR($D76/E76-1,0) -> 0 | R76: =IFERROR($D76/F76-1,0) -> 0 | S76: =IFERROR($D76/G76-1,0) -> 0 | T76: =IFERROR($D76/H76-1,0) -> 0 | U76: =IFERROR($D76/I76-1,0) -> 0 | W76: {=INDIRECT("'"&$C$6&"'!"&ADDRESS(ROW(),COLUMN()+44))} -> 0 | X76: {=INDIRECT("'"&$C$6&"'!"&ADDRESS(ROW(),COLUMN()+44))} -> 0 | Y76: {=INDIRECT("'"&$C$6&"'!"&ADDRESS(ROW(),COLUMN()+44))} -> 0 | Z76: {=INDIRECT("'"&$C$6&"'!"&ADDRESS(ROW(),COLUMN()+44))} -> 0 | AA76: {=INDIRECT("'"&$C$6&"'!"&ADDRESS(ROW(),COLUMN()+44))} -> 0 | AB76: {=INDIRECT("'"&$C$6&"'!"&ADDRESS(ROW(),COLUMN()+44))} -> 0 | AD76: =$W76-X76 -> 0 | AE76: =$W76-Y76 -> 0 | AF76: =$W76-Z76 -> 0 | AG76: =$W76-AA76 -> 0 | AH76: =$W76-AB76 -> 0 | AJ76: =IFERROR($W76/X76-1,0) -> 0 | AK76: =IFERROR($W76/Y76-1,0) -> 0 | AL76: =IFERROR($W76/Z76-1,0) -> 0 | AM76: =IFERROR($W76/AA76-1,0) -> 0 | AN76: =IFERROR($W76/AB76-1,0) -> 0
A77: INOF | D77: {=_xlfn.XLOOKUP(1, (INDIRECT("'"&$C$6&"'!$6:$6")=D$6)* (INDIRECT("'"&$C$6&"'!$5:$5")=D$5), INDIRECT("'"&$C$6&"'!"&ROW()&":"&ROW()) )} -> 0 | E77: {=_xlfn.XLOOKUP(1, (INDIRECT("'"&$C$6&"'!$6:$6")=E$6)* (INDIRECT("'"&$C$6&"'!$5:$5")=E$5), INDIRECT("'"&$C$6&"'!"&ROW()&":"&ROW()) )} -> 0 | F77: {=_xlfn.XLOOKUP(1, (INDIRECT("'"&$C$6&"'!$6:$6")=F$6)* (INDIRECT("'"&$C$6&"'!$5:$5")=F$5), INDIRECT("'"&$C$6&"'!"&ROW()&":"&ROW()) )} -> 0 | G77: {=_xlfn.XLOOKUP(1, (INDIRECT("'"&$C$6&"'!$6:$6")=G$6)* (INDIRECT("'"&$C$6&"'!$5:$5")=G$5), INDIRECT("'"&$C$6&"'!"&ROW()&":"&ROW()) )} -> 0 | H77: {=_xlfn.XLOOKUP(1, (INDIRECT("'"&$C$6&"'!$6:$6")=H$6)* (INDIRECT("'"&$C$6&"'!$5:$5")=H$5), INDIRECT("'"&$C$6&"'!"&ROW()&":"&ROW()) )} -> 0 | I77: {=_xlfn.XLOOKUP(1, (INDIRECT("'"&$C$6&"'!$6:$6")=I$6)* (INDIRECT("'"&$C$6&"'!$5:$5")=I$5), INDIRECT("'"&$C$6&"'!"&ROW()&":"&ROW()) )} -> 0 | K77: =$D77-E77 -> 0 | L77: =$D77-F77 -> 0 | M77: =$D77-G77 -> 0 | N77: =$D77-H77 -> 0 | O77: =$D77-I77 -> 0 | Q77: =IFERROR($D77/E77-1,0) -> 0 | R77: =IFERROR($D77/F77-1,0) -> 0 | S77: =IFERROR($D77/G77-1,0) -> 0 | T77: =IFERROR($D77/H77-1,0) -> 0 | U77: =IFERROR($D77/I77-1,0) -> 0 | W77: {=INDIRECT("'"&$C$6&"'!"&ADDRESS(ROW(),COLUMN()+44))} -> 0 | X77: {=INDIRECT("'"&$C$6&"'!"&ADDRESS(ROW(),COLUMN()+44))} -> 0 | Y77: {=INDIRECT("'"&$C$6&"'!"&ADDRESS(ROW(),COLUMN()+44))} -> 0 | Z77: {=INDIRECT("'"&$C$6&"'!"&ADDRESS(ROW(),COLUMN()+44))} -> 0 | AA77: {=INDIRECT("'"&$C$6&"'!"&ADDRESS(ROW(),COLUMN()+44))} -> 0 | AB77: {=INDIRECT("'"&$C$6&"'!"&ADDRESS(ROW(),COLUMN()+44))} -> 0 | AD77: =$W77-X77 -> 0 | AE77: =$W77-Y77 -> 0 | AF77: =$W77-Z77 -> 0 | AG77: =$W77-AA77 -> 0 | AH77: =$W77-AB77 -> 0 | AJ77: =IFERROR($W77/X77-1,0) -> 0 | AK77: =IFERROR($W77/Y77-1,0) -> 0 | AL77: =IFERROR($W77/Z77-1,0) -> 0 | AM77: =IFERROR($W77/AA77-1,0) -> 0 | AN77: =IFERROR($W77/AB77-1,0) -> 0
... A82: INOF | D82: {=_xlfn.XLOOKUP(1, (INDIRECT("'"&$C$6&"'!$6:$6")=D$6)* (INDIRECT("'"&$C$6&"'!$5:$5")=D$5), INDIRECT("'"&$C$6&"'!"&ROW()&":"&ROW()) )} -> 0 | E82: {=_xlfn.XLOOKUP(1, (INDIRECT("'"&$C$6&"'!$6:$6")=E$6)* (INDIRECT("'"&$C$6&"'!$5:$5")=E$5), INDIRECT("'"&$C$6&"'!"&ROW()&":"&ROW()) )} -> 0 | F82: {=_xlfn.XLOOKUP(1, (INDIRECT("'"&$C$6&"'!$6:$6")=F$6)* (INDIRECT("'"&$C$6&"'!$5:$5")=F$5), INDIRECT("'"&$C$6&"'!"&ROW()&":"&ROW()) )} -> 0 | G82: {=_xlfn.XLOOKUP(1, (INDIRECT("'"&$C$6&"'!$6:$6")=G$6)* (INDIRECT("'"&$C$6&"'!$5:$5")=G$5), INDIRECT("'"&$C$6&"'!"&ROW()&":"&ROW()) )} -> 0 | H82: {=_xlfn.XLOOKUP(1, (INDIRECT("'"&$C$6&"'!$6:$6")=H$6)* (INDIRECT("'"&$C$6&"'!$5:$5")=H$5), INDIRECT("'"&$C$6&"'!"&ROW()&":"&ROW()) )} -> 0 | I82: {=_xlfn.XLOOKUP(1, (INDIRECT("'"&$C$6&"'!$6:$6")=I$6)* (INDIRECT("'"&$C$6&"'!$5:$5")=I$5), INDIRECT("'"&$C$6&"'!"&ROW()&":"&ROW()) )} -> 0 | K82: =$D82-E82 -> 0 | L82: =$D82-F82 -> 0 | M82: =$D82-G82 -> 0 | N82: =$D82-H82 -> 0 | O82: =$D82-I82 -> 0 | Q82: =IFERROR($D82/E82-1,0) -> 0 | R82: =IFERROR($D82/F82-1,0) -> 0 | S82: =IFERROR($D82/G82-1,0) -> 0 | T82: =IFERROR($D82/H82-1,0) -> 0 | U82: =IFERROR($D82/I82-1,0) -> 0 | W82: {=INDIRECT("'"&$C$6&"'!"&ADDRESS(ROW(),COLUMN()+44))} -> 0 | X82: {=INDIRECT("'"&$C$6&"'!"&ADDRESS(ROW(),COLUMN()+44))} -> 0 | Y82: {=INDIRECT("'"&$C$6&"'!"&ADDRESS(ROW(),COLUMN()+44))} -> 0 | Z82: {=INDIRECT("'"&$C$6&"'!"&ADDRESS(ROW(),COLUMN()+44))} -> 0 | AA82: {=INDIRECT("'"&$C$6&"'!"&ADDRESS(ROW(),COLUMN()+44))} -> 0 | AB82: {=INDIRECT("'"&$C$6&"'!"&ADDRESS(ROW(),COLUMN()+44))} -> 0 | AD82: =$W82-X82 -> 0 | AE82: =$W82-Y82 -> 0 | AF82: =$W82-Z82 -> 0 | AG82: =$W82-AA82 -> 0 | AH82: =$W82-AB82 -> 0 | AJ82: =IFERROR($W82/X82-1,0) -> 0 | AK82: =IFERROR($W82/Y82-1,0) -> 0 | AL82: =IFERROR($W82/Z82-1,0) -> 0 | AM82: =IFERROR($W82/AA82-1,0) -> 0 | AN82: =IFERROR($W82/AB82-1,0) -> 0
C83: INOF | D83: =SUM(D63:D82) -> 1408.474 | E83: =SUM(E63:E82) -> 1064.5205 | F83: =SUM(F63:F82) -> 907.52849 | G83: =SUM(G63:G82) -> 1042.1873 | H83: =SUM(H63:H82) -> 679.67602 | I83: =SUM(I63:I82) -> 1109.7963 | K83: =$D83-E83 -> 343.95355 | L83: =$D83-F83 -> 500.94552 | M83: =$D83-G83 -> 366.28671 | N83: =$D83-H83 -> 728.798 | O83: =$D83-I83 -> 298.67768 | Q83: =IFERROR($D83/E83-1,0) -> 0.32310656 | R83: =IFERROR($D83/F83-1,0) -> 0.55198875 | S83: =IFERROR($D83/G83-1,0) -> 0.35145958 | T83: =IFERROR($D83/H83-1,0) -> 1.0722726 | U83: =IFERROR($D83/I83-1,0) -> 0.26912838 | W83: =SUM(W63:W82) -> 3539.1767 | X83: =SUM(X63:X82) -> 3188.0696 | Y83: =SUM(Y63:Y82) -> 2130.7027 | Z83: =SUM(Z63:Z82) -> 2981.8976 | AA83: =SUM(AA63:AA82) -> 1934.8019 | AB83: =SUM(AB63:AB82) -> 3321.2053 | AD83: =$W83-X83 -> 351.10709 | AE83: =$W83-Y83 -> 1408.474 | AF83: =$W83-Z83 -> 557.2791 | AG83: =$W83-AA83 -> 1604.3748 | AH83: =$W83-AB83 -> 217.97139 | AJ83: =IFERROR($W83/X83-1,0) -> 0.11013156 | AK83: =IFERROR($W83/Y83-1,0) -> 0.66103734 | AL83: =IFERROR($W83/Z83-1,0) -> 0.1868874 | AM83: =IFERROR($W83/AA83-1,0) -> 0.82921916 | AN83: =IFERROR($W83/AB83-1,0) -> 0.065630206
A86: Gastos Operativos | C86: Gasto Directo | D86: {=_xlfn.XLOOKUP(1, (INDIRECT("'"&$C$6&"'!$6:$6")=D$6)* (INDIRECT("'"&$C$6&"'!$5:$5")=D$5), INDIRECT("'"&$C$6&"'!"&ROW()&":"&ROW()) )} -> -4774.8364 | E86: {=_xlfn.XLOOKUP(1, (INDIRECT("'"&$C$6&"'!$6:$6")=E$6)* (INDIRECT("'"&$C$6&"'!$5:$5")=E$5), INDIRECT("'"&$C$6&"'!"&ROW()&":"&ROW()) )} -> -4781.4027 | F86: {=_xlfn.XLOOKUP(1, (INDIRECT("'"&$C$6&"'!$6:$6")=F$6)* (INDIRECT("'"&$C$6&"'!$5:$5")=F$5), INDIRECT("'"&$C$6&"'!"&ROW()&":"&ROW()) )} -> -4301.1419 | G86: {=_xlfn.XLOOKUP(1, (INDIRECT("'"&$C$6&"'!$6:$6")=G$6)* (INDIRECT("'"&$C$6&"'!$5:$5")=G$5), INDIRECT("'"&$C$6&"'!"&ROW()&":"&ROW()) )} -> -4514.4542 | H86: {=_xlfn.XLOOKUP(1, (INDIRECT("'"&$C$6&"'!$6:$6")=H$6)* (INDIRECT("'"&$C$6&"'!$5:$5")=H$5), INDIRECT("'"&$C$6&"'!"&ROW()&":"&ROW()) )} -> -3717.2689 | I86: {=_xlfn.XLOOKUP(1, (INDIRECT("'"&$C$6&"'!$6:$6")=I$6)* (INDIRECT("'"&$C$6&"'!$5:$5")=I$5), INDIRECT("'"&$C$6&"'!"&ROW()&":"&ROW()) )} -> -3786.9534 | K86: =$D86-E86 -> 6.5663428 | L86: =$D86-F86 -> -473.69446 | M86: =$D86-G86 -> -260.38221 | N86: =$D86-H86 -> -1057.5675 | O86: =$D86-I86 -> -987.88299 | Q86: =IFERROR($D86/E86-1,0) -> -0.0013733089 | R86: =IFERROR($D86/F86-1,0) -> 0.11013225 | S86: =IFERROR($D86/G86-1,0) -> 0.057677451 | T86: =IFERROR($D86/H86-1,0) -> 0.2845012 | U86: =IFERROR($D86/I86-1,0) -> 0.26086484 | W86: {=INDIRECT("'"&$C$6&"'!"&ADDRESS(ROW(),COLUMN()+44))} -> -13513 | X86: {=INDIRECT("'"&$C$6&"'!"&ADDRESS(ROW(),COLUMN()+44))} -> -14229.523 | Y86: {=INDIRECT("'"&$C$6&"'!"&ADDRESS(ROW(),COLUMN()+44))} -> -8738.1638 | Z86: {=INDIRECT("'"&$C$6&"'!"&ADDRESS(ROW(),COLUMN()+44))} -> -13221.309 | AA86: {=INDIRECT("'"&$C$6&"'!"&ADDRESS(ROW(),COLUMN()+44))} -> -10681.847 | AB86: {=INDIRECT("'"&$C$6&"'!"&ADDRESS(ROW(),COLUMN()+44))} -> -10651.254 | AD86: =$W86-X86 -> 716.52276 | AE86: =$W86-Y86 -> -4774.8364 | AF86: =$W86-Z86 -> -291.69089 | AG86: =$W86-AA86 -> -2831.1531 | AH86: =$W86-AB86 -> -2861.7458 | AJ86: =IFERROR($W86/X86-1,0) -> -0.050354658 | AK86: =IFERROR($W86/Y86-1,0) -> 0.54643476 | AL86: =IFERROR($W86/Z86-1,0) -> 0.022062179 | AM86: =IFERROR($W86/AA86-1,0) -> 0.2650434 | AN86: =IFERROR($W86/AB86-1,0) -> 0.26867688
A87: Gastos Operativos | C87: Gasto Canal | D87: {=_xlfn.XLOOKUP(1, (INDIRECT("'"&$C$6&"'!$6:$6")=D$6)* (INDIRECT("'"&$C$6&"'!$5:$5")=D$5), INDIRECT("'"&$C$6&"'!"&ROW()&":"&ROW()) )} -> -730.18465 | E87: {=_xlfn.XLOOKUP(1, (INDIRECT("'"&$C$6&"'!$6:$6")=E$6)* (INDIRECT("'"&$C$6&"'!$5:$5")=E$5), INDIRECT("'"&$C$6&"'!"&ROW()&":"&ROW()) )} -> -766.83168 | F87: {=_xlfn.XLOOKUP(1, (INDIRECT("'"&$C$6&"'!$6:$6")=F$6)* (INDIRECT("'"&$C$6&"'!$5:$5")=F$5), INDIRECT("'"&$C$6&"'!"&ROW()&":"&ROW()) )} -> -728.86034 | G87: {=_xlfn.XLOOKUP(1, (INDIRECT("'"&$C$6&"'!$6:$6")=G$6)* (INDIRECT("'"&$C$6&"'!$5:$5")=G$5), INDIRECT("'"&$C$6&"'!"&ROW()&":"&ROW()) )} -> -647.23176 | H87: {=_xlfn.XLOOKUP(1, (INDIRECT("'"&$C$6&"'!$6:$6")=H$6)* (INDIRECT("'"&$C$6&"'!$5:$5")=H$5), INDIRECT("'"&$C$6&"'!"&ROW()&":"&ROW()) )} -> -632.85735 | I87: {=_xlfn.XLOOKUP(1, (INDIRECT("'"&$C$6&"'!$6:$6")=I$6)* (INDIRECT("'"&$C$6&"'!$5:$5")=I$5), INDIRECT("'"&$C$6&"'!"&ROW()&":"&ROW()) )} -> -604.01876 | K87: =$D87-E87 -> 36.647032 | L87: =$D87-F87 -> -1.3243052 | M87: =$D87-G87 -> -82.952889 | N87: =$D87-H87 -> -97.327295 | O87: =$D87-I87 -> -126.16589 | Q87: =IFERROR($D87/E87-1,0) -> -0.04779019 | R87: =IFERROR($D87/F87-1,0) -> 0.0018169533 | S87: =IFERROR($D87/G87-1,0) -> 0.12816567 | T87: =IFERROR($D87/H87-1,0) -> 0.15379026 | U87: =IFERROR($D87/I87-1,0) -> 0.20887744 | W87: {=INDIRECT("'"&$C$6&"'!"&ADDRESS(ROW(),COLUMN()+44))} -> -2083.8899 | X87: {=INDIRECT("'"&$C$6&"'!"&ADDRESS(ROW(),COLUMN()+44))} -> -2290.9509 | Y87: {=INDIRECT("'"&$C$6&"'!"&ADDRESS(ROW(),COLUMN()+44))} -> -1353.7053 | Z87: {=INDIRECT("'"&$C$6&"'!"&ADDRESS(ROW(),COLUMN()+44))} -> -1939.4395 | AA87: {=INDIRECT("'"&$C$6&"'!"&ADDRESS(ROW(),COLUMN()+44))} -> -1818.9476 | AB87: {=INDIRECT("'"&$C$6&"'!"&ADDRESS(ROW(),COLUMN()+44))} -> -1685.029 | AD87: =$W87-X87 -> 207.06097 | AE87: =$W87-Y87 -> -730.18465 | AF87: =$W87-Z87 -> -144.45043 | AG87: =$W87-AA87 -> -264.94231 | AH87: =$W87-AB87 -> -398.86086 | AJ87: =IFERROR($W87/X87-1,0) -> -0.090382107 | AK87: =IFERROR($W87/Y87-1,0) -> 0.53939707 | AL87: =IFERROR($W87/Z87-1,0) -> 0.074480504 | AM87: =IFERROR($W87/AA87-1,0) -> 0.14565692 | AN87: =IFERROR($W87/AB87-1,0) -> 0.2367086
A88: Gastos Operativos | C88: Gasto Indirecto | D88: {=_xlfn.XLOOKUP(1, (INDIRECT("'"&$C$6&"'!$6:$6")=D$6)* (INDIRECT("'"&$C$6&"'!$5:$5")=D$5), INDIRECT("'"&$C$6&"'!"&ROW()&":"&ROW()) )} -> -2492.0776 | E88: {=_xlfn.XLOOKUP(1, (INDIRECT("'"&$C$6&"'!$6:$6")=E$6)* (INDIRECT("'"&$C$6&"'!$5:$5")=E$5), INDIRECT("'"&$C$6&"'!"&ROW()&":"&ROW()) )} -> -2772.346 | F88: {=_xlfn.XLOOKUP(1, (INDIRECT("'"&$C$6&"'!$6:$6")=F$6)* (INDIRECT("'"&$C$6&"'!$5:$5")=F$5), INDIRECT("'"&$C$6&"'!"&ROW()&":"&ROW()) )} -> -2714.7322 | G88: {=_xlfn.XLOOKUP(1, (INDIRECT("'"&$C$6&"'!$6:$6")=G$6)* (INDIRECT("'"&$C$6&"'!$5:$5")=G$5), INDIRECT("'"&$C$6&"'!"&ROW()&":"&ROW()) )} -> -2358.5742 | H88: {=_xlfn.XLOOKUP(1, (INDIRECT("'"&$C$6&"'!$6:$6")=H$6)* (INDIRECT("'"&$C$6&"'!$5:$5")=H$5), INDIRECT("'"&$C$6&"'!"&ROW()&":"&ROW()) )} -> -1919.7328 | I88: {=_xlfn.XLOOKUP(1, (INDIRECT("'"&$C$6&"'!$6:$6")=I$6)* (INDIRECT("'"&$C$6&"'!$5:$5")=I$5), INDIRECT("'"&$C$6&"'!"&ROW()&":"&ROW()) )} -> -2023.505 | K88: =$D88-E88 -> 280.26843 | L88: =$D88-F88 -> 222.65456 | M88: =$D88-G88 -> -133.50343 | N88: =$D88-H88 -> -572.34482 | O88: =$D88-I88 -> -468.57261 | Q88: =IFERROR($D88/E88-1,0) -> -0.10109432 | R88: =IFERROR($D88/F88-1,0) -> -0.082017135 | S88: =IFERROR($D88/G88-1,0) -> 0.056603446 | T88: =IFERROR($D88/H88-1,0) -> 0.29813775 | U88: =IFERROR($D88/I88-1,0) -> 0.23156484 | W88: {=INDIRECT("'"&$C$6&"'!"&ADDRESS(ROW(),COLUMN()+44))} -> -8058.6295 | X88: {=INDIRECT("'"&$C$6&"'!"&ADDRESS(ROW(),COLUMN()+44))} -> -8093.368 | Y88: {=INDIRECT("'"&$C$6&"'!"&ADDRESS(ROW(),COLUMN()+44))} -> -5566.5519 | Z88: {=INDIRECT("'"&$C$6&"'!"&ADDRESS(ROW(),COLUMN()+44))} -> -7400.2938 | AA88: {=INDIRECT("'"&$C$6&"'!"&ADDRESS(ROW(),COLUMN()+44))} -> -5907.3542 | AB88: {=INDIRECT("'"&$C$6&"'!"&ADDRESS(ROW(),COLUMN()+44))} -> -5917.1271 | AD88: =$W88-X88 -> 34.738436 | AE88: =$W88-Y88 -> -2492.0776 | AF88: =$W88-Z88 -> -658.33575 | AG88: =$W88-AA88 -> -2151.2753 | AH88: =$W88-AB88 -> -2141.5024 | AJ88: =IFERROR($W88/X88-1,0) -> -0.0042922102 | AK88: =IFERROR($W88/Y88-1,0) -> 0.44768784 | AL88: =IFERROR($W88/Z88-1,0) -> 0.088960759 | AM88: =IFERROR($W88/AA88-1,0) -> 0.36416901 | AN88: =IFERROR($W88/AB88-1,0) -> 0.36191591
C89: Gastos Operativos | D89: =SUM(D86:D88) -> -7997.0987 | E89: =SUM(E86:E88) -> -8320.5805 | F89: =SUM(F86:F88) -> -7744.7345 | G89: =SUM(G86:G88) -> -7520.2601 | H89: =SUM(H86:H88) -> -6269.8591 | I89: =SUM(I86:I88) -> -6414.4772 | K89: =$D89-E89 -> 323.48181 | L89: =$D89-F89 -> -252.36421 | M89: =$D89-G89 -> -476.83853 | N89: =$D89-H89 -> -1727.2396 | O89: =$D89-I89 -> -1582.6215 | Q89: =IFERROR($D89/E89-1,0) -> -0.038877312 | R89: =IFERROR($D89/F89-1,0) -> 0.032585262 | S89: =IFERROR($D89/G89-1,0) -> 0.063407186 | T89: =IFERROR($D89/H89-1,0) -> 0.275483 | U89: =IFERROR($D89/I89-1,0) -> 0.2467265 | W89: =SUM(W86:W88) -> -23655.52 | X89: =SUM(X86:X88) -> -24613.842 | Y89: =SUM(Y86:Y88) -> -15658.421 | Z89: =SUM(Z86:Z88) -> -22561.043 | AA89: =SUM(AA86:AA88) -> -18408.149 | AB89: =SUM(AB86:AB88) -> -18253.411 | AD89: =$W89-X89 -> 958.32216 | AE89: =$W89-Y89 -> -7997.0987 | AF89: =$W89-Z89 -> -1094.4771 | AG89: =$W89-AA89 -> -5247.3707 | AH89: =$W89-AB89 -> -5402.1091 | AJ89: =IFERROR($W89/X89-1,0) -> -0.038934278 | AK89: =IFERROR($W89/Y89-1,0) -> 0.51072191 | AL89: =IFERROR($W89/Z89-1,0) -> 0.048511813 | AM89: =IFERROR($W89/AA89-1,0) -> 0.28505695 | AN89: =IFERROR($W89/AB89-1,0) -> 0.29595067
A91: Extraordinarios | C91: Donaciones | D91: {=_xlfn.XLOOKUP(1, (INDIRECT("'"&$C$6&"'!$6:$6")=D$6)* (INDIRECT("'"&$C$6&"'!$5:$5")=D$5), INDIRECT("'"&$C$6&"'!"&ROW()&":"&ROW()) )} -> 0 | E91: {=_xlfn.XLOOKUP(1, (INDIRECT("'"&$C$6&"'!$6:$6")=E$6)* (INDIRECT("'"&$C$6&"'!$5:$5")=E$5), INDIRECT("'"&$C$6&"'!"&ROW()&":"&ROW()) )} -> 0 | F91: {=_xlfn.XLOOKUP(1, (INDIRECT("'"&$C$6&"'!$6:$6")=F$6)* (INDIRECT("'"&$C$6&"'!$5:$5")=F$5), INDIRECT("'"&$C$6&"'!"&ROW()&":"&ROW()) )} -> 0 | G91: {=_xlfn.XLOOKUP(1, (INDIRECT("'"&$C$6&"'!$6:$6")=G$6)* (INDIRECT("'"&$C$6&"'!$5:$5")=G$5), INDIRECT("'"&$C$6&"'!"&ROW()&":"&ROW()) )} -> 0 | H91: {=_xlfn.XLOOKUP(1, (INDIRECT("'"&$C$6&"'!$6:$6")=H$6)* (INDIRECT("'"&$C$6&"'!$5:$5")=H$5), INDIRECT("'"&$C$6&"'!"&ROW()&":"&ROW()) )} -> 0 | I91: {=_xlfn.XLOOKUP(1, (INDIRECT("'"&$C$6&"'!$6:$6")=I$6)* (INDIRECT("'"&$C$6&"'!$5:$5")=I$5), INDIRECT("'"&$C$6&"'!"&ROW()&":"&ROW()) )} -> 0 | K91: =$D91-E91 -> 0 | L91: =$D91-F91 -> 0 | M91: =$D91-G91 -> 0 | N91: =$D91-H91 -> 0 | O91: =$D91-I91 -> 0 | Q91: =IFERROR($D91/E91-1,0) -> 0 | R91: =IFERROR($D91/F91-1,0) -> 0 | S91: =IFERROR($D91/G91-1,0) -> 0 | T91: =IFERROR($D91/H91-1,0) -> 0 | U91: =IFERROR($D91/I91-1,0) -> 0 | W91: {=INDIRECT("'"&$C$6&"'!"&ADDRESS(ROW(),COLUMN()+44))} -> 0 | X91: {=INDIRECT("'"&$C$6&"'!"&ADDRESS(ROW(),COLUMN()+44))} -> 0 | Y91: {=INDIRECT("'"&$C$6&"'!"&ADDRESS(ROW(),COLUMN()+44))} -> 0 | Z91: {=INDIRECT("'"&$C$6&"'!"&ADDRESS(ROW(),COLUMN()+44))} -> 0 | AA91: {=INDIRECT("'"&$C$6&"'!"&ADDRESS(ROW(),COLUMN()+44))} -> 0 | AB91: {=INDIRECT("'"&$C$6&"'!"&ADDRESS(ROW(),COLUMN()+44))} -> 0 | AD91: =$W91-X91 -> 0 | AE91: =$W91-Y91 -> 0 | AF91: =$W91-Z91 -> 0 | AG91: =$W91-AA91 -> 0 | AH91: =$W91-AB91 -> 0 | AJ91: =IFERROR($W91/X91-1,0) -> 0 | AK91: =IFERROR($W91/Y91-1,0) -> 0 | AL91: =IFERROR($W91/Z91-1,0) -> 0 | AM91: =IFERROR($W91/AA91-1,0) -> 0 | AN91: =IFERROR($W91/AB91-1,0) -> 0
A92: Extraordinarios | C92: Otros | D92: {=_xlfn.XLOOKUP(1, (INDIRECT("'"&$C$6&"'!$6:$6")=D$6)* (INDIRECT("'"&$C$6&"'!$5:$5")=D$5), INDIRECT("'"&$C$6&"'!"&ROW()&":"&ROW()) )} -> -148.8495 | E92: {=_xlfn.XLOOKUP(1, (INDIRECT("'"&$C$6&"'!$6:$6")=E$6)* (INDIRECT("'"&$C$6&"'!$5:$5")=E$5), INDIRECT("'"&$C$6&"'!"&ROW()&":"&ROW()) )} -> -35.039595 | F92: {=_xlfn.XLOOKUP(1, (INDIRECT("'"&$C$6&"'!$6:$6")=F$6)* (INDIRECT("'"&$C$6&"'!$5:$5")=F$5), INDIRECT("'"&$C$6&"'!"&ROW()&":"&ROW()) )} -> 70.527749 | G92: {=_xlfn.XLOOKUP(1, (INDIRECT("'"&$C$6&"'!$6:$6")=G$6)* (INDIRECT("'"&$C$6&"'!$5:$5")=G$5), INDIRECT("'"&$C$6&"'!"&ROW()&":"&ROW()) )} -> -217.94625 | H92: {=_xlfn.XLOOKUP(1, (INDIRECT("'"&$C$6&"'!$6:$6")=H$6)* (INDIRECT("'"&$C$6&"'!$5:$5")=H$5), INDIRECT("'"&$C$6&"'!"&ROW()&":"&ROW()) )} -> 156.21771 | I92: {=_xlfn.XLOOKUP(1, (INDIRECT("'"&$C$6&"'!$6:$6")=I$6)* (INDIRECT("'"&$C$6&"'!$5:$5")=I$5), INDIRECT("'"&$C$6&"'!"&ROW()&":"&ROW()) )} -> 21.18704 | K92: =$D92-E92 -> -113.80991 | L92: =$D92-F92 -> -219.37725 | M92: =$D92-G92 -> 69.09675 | N92: =$D92-H92 -> -305.06721 | O92: =$D92-I92 -> -170.03654 | Q92: =IFERROR($D92/E92-1,0) -> 3.2480371 | R92: =IFERROR($D92/F92-1,0) -> -3.1105097 | S92: =IFERROR($D92/G92-1,0) -> -0.31703574 | T92: =IFERROR($D92/H92-1,0) -> -1.9528337 | U92: =IFERROR($D92/I92-1,0) -> -8.0254977 | W92: {=INDIRECT("'"&$C$6&"'!"&ADDRESS(ROW(),COLUMN()+44))} -> -102.84692 | X92: {=INDIRECT("'"&$C$6&"'!"&ADDRESS(ROW(),COLUMN()+44))} -> -203.04532 | Y92: {=INDIRECT("'"&$C$6&"'!"&ADDRESS(ROW(),COLUMN()+44))} -> 46.002579 | Z92: {=INDIRECT("'"&$C$6&"'!"&ADDRESS(ROW(),COLUMN()+44))} -> -314.18419 | AA92: {=INDIRECT("'"&$C$6&"'!"&ADDRESS(ROW(),COLUMN()+44))} -> 122.01108 | AB92: {=INDIRECT("'"&$C$6&"'!"&ADDRESS(ROW(),COLUMN()+44))} -> 64.1685 | AD92: =$W92-X92 -> 100.19839 | AE92: =$W92-Y92 -> -148.8495 | AF92: =$W92-Z92 -> 211.33727 | AG92: =$W92-AA92 -> -224.858 | AH92: =$W92-AB92 -> -167.01542 | AJ92: =IFERROR($W92/X92-1,0) -> -0.49347799 | AK92: =IFERROR($W92/Y92-1,0) -> -3.2356773 | AL92: =IFERROR($W92/Z92-1,0) -> -0.67265405 | AM92: =IFERROR($W92/AA92-1,0) -> -1.842931 | AN92: =IFERROR($W92/AB92-1,0) -> -2.6027634
C93: Extraordinarios | D93: =SUM(D91:D92) -> -148.8495 | E93: =SUM(E91:E92) -> -35.039595 | F93: =SUM(F91:F92) -> 70.527749 | G93: =SUM(G91:G92) -> -217.94625 | H93: =SUM(H91:H92) -> 156.21771 | I93: =SUM(I91:I92) -> 21.18704 | K93: =$D93-E93 -> -113.80991 | L93: =$D93-F93 -> -219.37725 | M93: =$D93-G93 -> 69.09675 | N93: =$D93-H93 -> -305.06721 | O93: =$D93-I93 -> -170.03654 | Q93: =IFERROR($D93/E93-1,0) -> 3.2480371 | R93: =IFERROR($D93/F93-1,0) -> -3.1105097 | S93: =IFERROR($D93/G93-1,0) -> -0.31703574 | T93: =IFERROR($D93/H93-1,0) -> -1.9528337 | U93: =IFERROR($D93/I93-1,0) -> -8.0254977 | W93: =SUM(W91:W92) -> -102.84692 | X93: =SUM(X91:X92) -> -203.04532 | Y93: =SUM(Y91:Y92) -> 46.002579 | Z93: =SUM(Z91:Z92) -> -314.18419 | AA93: =SUM(AA91:AA92) -> 122.01108 | AB93: =SUM(AB91:AB92) -> 64.1685 | AD93: =$W93-X93 -> 100.19839 | AE93: =$W93-Y93 -> -148.8495 | AF93: =$W93-Z93 -> 211.33727 | AG93: =$W93-AA93 -> -224.858 | AH93: =$W93-AB93 -> -167.01542 | AJ93: =IFERROR($W93/X93-1,0) -> -0.49347799 | AK93: =IFERROR($W93/Y93-1,0) -> -3.2356773 | AL93: =IFERROR($W93/Z93-1,0) -> -0.67265405 | AM93: =IFERROR($W93/AA93-1,0) -> -1.842931 | AN93: =IFERROR($W93/AB93-1,0) -> -2.6027634
A95: ROF | C95: Venta de Cartera | D95: {=_xlfn.XLOOKUP(1, (INDIRECT("'"&$C$6&"'!$6:$6")=D$6)* (INDIRECT("'"&$C$6&"'!$5:$5")=D$5), INDIRECT("'"&$C$6&"'!"&ROW()&":"&ROW()) )} -> 1018.0438 | E95: {=_xlfn.XLOOKUP(1, (INDIRECT("'"&$C$6&"'!$6:$6")=E$6)* (INDIRECT("'"&$C$6&"'!$5:$5")=E$5), INDIRECT("'"&$C$6&"'!"&ROW()&":"&ROW()) )} -> 0 | F95: {=_xlfn.XLOOKUP(1, (INDIRECT("'"&$C$6&"'!$6:$6")=F$6)* (INDIRECT("'"&$C$6&"'!$5:$5")=F$5), INDIRECT("'"&$C$6&"'!"&ROW()&":"&ROW()) )} -> 60.14 | G95: {=_xlfn.XLOOKUP(1, (INDIRECT("'"&$C$6&"'!$6:$6")=G$6)* (INDIRECT("'"&$C$6&"'!$5:$5")=G$5), INDIRECT("'"&$C$6&"'!"&ROW()&":"&ROW()) )} -> 317.56935 | H95: {=_xlfn.XLOOKUP(1, (INDIRECT("'"&$C$6&"'!$6:$6")=H$6)* (INDIRECT("'"&$C$6&"'!$5:$5")=H$5), INDIRECT("'"&$C$6&"'!"&ROW()&":"&ROW()) )} -> 0 | I95: {=_xlfn.XLOOKUP(1, (INDIRECT("'"&$C$6&"'!$6:$6")=I$6)* (INDIRECT("'"&$C$6&"'!$5:$5")=I$5), INDIRECT("'"&$C$6&"'!"&ROW()&":"&ROW()) )} -> 0 | K95: =$D95-E95 -> 1018.0438 | L95: =$D95-F95 -> 957.90375 | M95: =$D95-G95 -> 700.4744 | N95: =$D95-H95 -> 1018.0438 | O95: =$D95-I95 -> 1018.0438 | Q95: =IFERROR($D95/E95-1,0) -> 0 | R95: =IFERROR($D95/F95-1,0) -> 15.927897 | S95: =IFERROR($D95/G95-1,0) -> 2.2057368 | T95: =IFERROR($D95/H95-1,0) -> 0 | U95: =IFERROR($D95/I95-1,0) -> 0 | W95: {=INDIRECT("'"&$C$6&"'!"&ADDRESS(ROW(),COLUMN()+44))} -> 1078.1838 | X95: {=INDIRECT("'"&$C$6&"'!"&ADDRESS(ROW(),COLUMN()+44))} -> 0 | Y95: {=INDIRECT("'"&$C$6&"'!"&ADDRESS(ROW(),COLUMN()+44))} -> 60.14 | Z95: {=INDIRECT("'"&$C$6&"'!"&ADDRESS(ROW(),COLUMN()+44))} -> 317.56935 | AA95: {=INDIRECT("'"&$C$6&"'!"&ADDRESS(ROW(),COLUMN()+44))} -> 0 | AB95: {=INDIRECT("'"&$C$6&"'!"&ADDRESS(ROW(),COLUMN()+44))} -> 0 | AD95: =$W95-X95 -> 1078.1838 | AE95: =$W95-Y95 -> 1018.0438 | AF95: =$W95-Z95 -> 760.6144 | AG95: =$W95-AA95 -> 1078.1838 | AH95: =$W95-AB95 -> 1078.1838 | AJ95: =IFERROR($W95/X95-1,0) -> 0 | AK95: =IFERROR($W95/Y95-1,0) -> 16.927897 | AL95: =IFERROR($W95/Z95-1,0) -> 2.3951128 | AM95: =IFERROR($W95/AA95-1,0) -> 0 | AN95: =IFERROR($W95/AB95-1,0) -> 0
C96: ROF | D96: =SUM(D95:D95) -> 1018.0438 | E96: =SUM(E95:E95) -> 0 | F96: =SUM(F95:F95) -> 60.14 | G96: =SUM(G95:G95) -> 317.56935 | H96: =SUM(H95:H95) -> 0 | I96: =SUM(I95:I95) -> 0 | K96: =$D96-E96 -> 1018.0438 | L96: =$D96-F96 -> 957.90375 | M96: =$D96-G96 -> 700.4744 | N96: =$D96-H96 -> 1018.0438 | O96: =$D96-I96 -> 1018.0438 | Q96: =IFERROR($D96/E96-1,0) -> 0 | R96: =IFERROR($D96/F96-1,0) -> 15.927897 | S96: =IFERROR($D96/G96-1,0) -> 2.2057368 | T96: =IFERROR($D96/H96-1,0) -> 0 | U96: =IFERROR($D96/I96-1,0) -> 0 | W96: =SUM(W95:W95) -> 1078.1838 | X96: =SUM(X95:X95) -> 0 | Y96: =SUM(Y95:Y95) -> 60.14 | Z96: =SUM(Z95:Z95) -> 317.56935 | AA96: =SUM(AA95:AA95) -> 0 | AB96: =SUM(AB95:AB95) -> 0 | AD96: =$W96-X96 -> 1078.1838 | AE96: =$W96-Y96 -> 1018.0438 | AF96: =$W96-Z96 -> 760.6144 | AG96: =$W96-AA96 -> 1078.1838 | AH96: =$W96-AB96 -> 1078.1838 | AJ96: =IFERROR($W96/X96-1,0) -> 0 | AK96: =IFERROR($W96/Y96-1,0) -> 16.927897 | AL96: =IFERROR($W96/Z96-1,0) -> 2.3951128 | AM96: =IFERROR($W96/AA96-1,0) -> 0 | AN96: =IFERROR($W96/AB96-1,0) -> 0
C98: UAI | D98: =D60+D83+D89+D93+D96 -> 12052.728 | E98: =E60+E83+E89+E93+E96 -> 6399.2069 | F98: =F60+F83+F89+F93+F96 -> 7393.3416 | G98: =G60+G83+G89+G93+G96 -> 10612.374 | H98: =H60+H83+H89+H93+H96 -> 11963.028 | I98: =I60+I83+I89+I93+I96 -> 11908.709 | K98: =$D98-E98 -> 5653.5208 | L98: =$D98-F98 -> 4659.3861 | M98: =$D98-G98 -> 1440.3542 | N98: =$D98-H98 -> 89.699434 | O98: =$D98-I98 -> 144.01855 | Q98: =IFERROR($D98/E98-1,0) -> 0.88347211 | R98: =IFERROR($D98/F98-1,0) -> 0.63021383 | S98: =IFERROR($D98/G98-1,0) -> 0.13572404 | T98: =IFERROR($D98/H98-1,0) -> 0.0074980541 | U98: =IFERROR($D98/I98-1,0) -> 0.012093548 | W98: =W60+W83+W89+W93+W96 -> 32754.435 | X98: =X60+X83+X89+X93+X96 -> 17058.563 | Y98: =Y60+Y83+Y89+Y93+Y96 -> 20701.708 | Z98: =Z60+Z83+Z89+Z93+Z96 -> 20986.281 | AA98: =AA60+AA83+AA89+AA93+AA96 -> 23605.105 | AB98: =AB60+AB83+AB89+AB93+AB96 -> 27762.782 | AD98: =$W98-X98 -> 15695.873 | AE98: =$W98-Y98 -> 12052.728 | AF98: =$W98-Z98 -> 11768.154 | AG98: =$W98-AA98 -> 9149.3305 | AH98: =$W98-AB98 -> 4991.6537 | AJ98: =IFERROR($W98/X98-1,0) -> 0.92011694 | AK98: =IFERROR($W98/Y98-1,0) -> 0.58220935 | AL98: =IFERROR($W98/Z98-1,0) -> 0.56075462 | AM98: =IFERROR($W98/AA98-1,0) -> 0.38759966 | AN98: =IFERROR($W98/AB98-1,0) -> 0.1797966
C102: Prom SFdP | D102: {=_xlfn.XLOOKUP(1, (INDIRECT("'"&$C$6&"'!$6:$6")=D$6)* (INDIRECT("'"&$C$6&"'!$5:$5")=D$5), INDIRECT("'"&$C$6&"'!"&ROW()&":"&ROW()) )} -> 11878156 | E102: {=_xlfn.XLOOKUP(1, (INDIRECT("'"&$C$6&"'!$6:$6")=E$6)* (INDIRECT("'"&$C$6&"'!$5:$5")=E$5), INDIRECT("'"&$C$6&"'!"&ROW()&":"&ROW()) )} -> 11822680 | F102: {=_xlfn.XLOOKUP(1, (INDIRECT("'"&$C$6&"'!$6:$6")=F$6)* (INDIRECT("'"&$C$6&"'!$5:$5")=F$5), INDIRECT("'"&$C$6&"'!"&ROW()&":"&ROW()) )} -> 11810463 | G102: {=_xlfn.XLOOKUP(1, (INDIRECT("'"&$C$6&"'!$6:$6")=G$6)* (INDIRECT("'"&$C$6&"'!$5:$5")=G$5), INDIRECT("'"&$C$6&"'!"&ROW()&":"&ROW()) )} -> 10940802 | H102: {=_xlfn.XLOOKUP(1, (INDIRECT("'"&$C$6&"'!$6:$6")=H$6)* (INDIRECT("'"&$C$6&"'!$5:$5")=H$5), INDIRECT("'"&$C$6&"'!"&ROW()&":"&ROW()) )} -> 10217267 | I102: {=_xlfn.XLOOKUP(1, (INDIRECT("'"&$C$6&"'!$6:$6")=I$6)* (INDIRECT("'"&$C$6&"'!$5:$5")=I$5), INDIRECT("'"&$C$6&"'!"&ROW()&":"&ROW()) )} -> 9646118.5 | W102: {=INDIRECT("'"&$C$6&"'!"&ADDRESS(ROW(),COLUMN()+44))} -> 11811182 | X102: {=INDIRECT("'"&$C$6&"'!"&ADDRESS(ROW(),COLUMN()+44))} -> 11791442 | Y102: {=INDIRECT("'"&$C$6&"'!"&ADDRESS(ROW(),COLUMN()+44))} -> 11779256 | Z102: {=INDIRECT("'"&$C$6&"'!"&ADDRESS(ROW(),COLUMN()+44))} -> 10891487 | AA102: {=INDIRECT("'"&$C$6&"'!"&ADDRESS(ROW(),COLUMN()+44))} -> 10163458 | AB102: {=INDIRECT("'"&$C$6&"'!"&ADDRESS(ROW(),COLUMN()+44))} -> 9626822.9

Sheet Indicadores
C1: Mensual | P1: Acumulado
J2: Variación % | W2: Variación %
B3: =Desempeño_Financiero!C6 -> Total_Producto | C3: =Desempeño_Financiero!D6 -> 46112 | D3: =Desempeño_Financiero!E6 -> 46112 | E3: =Desempeño_Financiero!F6 -> 46081 | F3: =Desempeño_Financiero!G6 -> 45747 | G3: =Desempeño_Financiero!H6 -> 45382 | H3: =Desempeño_Financiero!I6 -> 45016 | J3: =D3 -> 46112 | K3: =E3 -> 46081 | L3: =F3 -> 45747 | M3: =G3 -> 45382 | N3: =H3 -> 45016 | P3: =C3 -> 46112 | Q3: =D3 -> 46112 | R3: =E3 -> 46081 | S3: =F3 -> 45747 | T3: =G3 -> 45382 | U3: =H3 -> 45016 | W3: =Q3 -> 46112 | X3: =R3 -> 46081 | Y3: =S3 -> 45747 | Z3: =T3 -> 45382 | AA3: =U3 -> 45016
B5: Eficiencia | C5: =IFERROR((-Desempeño_Financiero!D89)/(Desempeño_Financiero!D53+Desempeño_Financiero!D83+Desempeño_Financiero!D96),0) -> 0.3544701 | D5: =IFERROR((-Desempeño_Financiero!E89)/(Desempeño_Financiero!E53+Desempeño_Financiero!E83+Desempeño_Financiero!E96),0) -> 0.41402437 | E5: =IFERROR((-Desempeño_Financiero!F89)/(Desempeño_Financiero!F53+Desempeño_Financiero!F83+Desempeño_Financiero!F96),0) -> 0.56010609 | F5: =IFERROR((-Desempeño_Financiero!G89)/(Desempeño_Financiero!G53+Desempeño_Financiero!G83+Desempeño_Financiero!G96),0) -> 0.37478259 | G5: =IFERROR((-Desempeño_Financiero!H89)/(Desempeño_Financiero!H53+Desempeño_Financiero!H83+Desempeño_Financiero!H96),0) -> 0.32584921 | H5: =IFERROR((-Desempeño_Financiero!I89)/(Desempeño_Financiero!I53+Desempeño_Financiero!I83+Desempeño_Financiero!I96),0) -> 0.33303208 | J5: =IFERROR(($C5-D5)*10000,0) -> -595.54268 | K5: =IFERROR(($C5-E5)*10000,0) -> -2056.36 | L5: =IFERROR(($C5-F5)*10000,0) -> -203.12495 | M5: =IFERROR(($C5-G5)*10000,0) -> 286.20891 | N5: =IFERROR(($C5-H5)*10000,0) -> 214.38019 | P5: =IFERROR((-Desempeño_Financiero!W89)/(Desempeño_Financiero!W53+Desempeño_Financiero!W83+Desempeño_Financiero!W96),0) -> 0.41424026 | Q5: =IFERROR((-Desempeño_Financiero!X89)/(Desempeño_Financiero!X53+Desempeño_Financiero!X83+Desempeño_Financiero!X96),0) -> 0.45741694 | R5: =IFERROR((-Desempeño_Financiero!Y89)/(Desempeño_Financiero!Y53+Desempeño_Financiero!Y83+Desempeño_Financiero!Y96),0) -> 0.45327498 | S5: =IFERROR((-Desempeño_Financiero!Z89)/(Desempeño_Financiero!Z53+Desempeño_Financiero!Z83+Desempeño_Financiero!Z96),0) -> 0.42713968 | T5: =IFERROR((-Desempeño_Financiero!AA89)/(Desempeño_Financiero!AA53+Desempeño_Financiero!AA83+Desempeño_Financiero!AA96),0) -> 0.3470704 | U5: =IFERROR((-Desempeño_Financiero!AB89)/(Desempeño_Financiero!AB53+Desempeño_Financiero!AB83+Desempeño_Financiero!AB96),0) -> 0.35480126 | W5: =IFERROR(($P5-Q5)*10000,0) -> -431.7668 | X5: =IFERROR(($P5-R5)*10000,0) -> -390.34722 | Y5: =IFERROR(($P5-S5)*10000,0) -> -128.99415 | Z5: =IFERROR(($P5-T5)*10000,0) -> 671.69862 | AA5: =IFERROR(($P5-U5)*10000,0) -> 594.39001
B7: Rendimiento de Colocaciones | C7: =Desempeño_Financiero!D23 -> 0.075242263 | D7: =Desempeño_Financiero!E23 -> 0.074551078 | E7: =Desempeño_Financiero!F23 -> 0.075208869 | F7: =Desempeño_Financiero!G23 -> 0.074793645 | G7: =Desempeño_Financiero!H23 -> 0.074204037 | H7: =Desempeño_Financiero!I23 -> 0.071861786 | J7: =IFERROR(($C7-D7)*10000,0) -> 6.9118474 | K7: =IFERROR(($C7-E7)*10000,0) -> 0.3339378 | L7: =IFERROR(($C7-F7)*10000,0) -> 4.4861776 | M7: =IFERROR(($C7-G7)*10000,0) -> 10.382258 | N7: =IFERROR(($C7-H7)*10000,0) -> 33.80477 | P7: =Desempeño_Financiero!W23 -> 0.075108716 | Q7: =Desempeño_Financiero!X23 -> 0.074819951 | R7: =Desempeño_Financiero!Y23 -> 0.075025428 | S7: =Desempeño_Financiero!Z23 -> 0.074764361 | T7: =Desempeño_Financiero!AA23 -> 0.073844122 | U7: =Desempeño_Financiero!AB23 -> 0.071244808 | W7: =IFERROR(($P7-Q7)*10000,0) -> 2.8876539 | X7: =IFERROR(($P7-R7)*10000,0) -> 0.83288631 | Y7: =IFERROR(($P7-S7)*10000,0) -> 3.4435522 | Z7: =IFERROR(($P7-T7)*10000,0) -> 12.64594 | AA7: =IFERROR(($P7-U7)*10000,0) -> 38.639086
B9: INOF / Ingresos Totales | C9: =IFERROR((Desempeño_Financiero!D83)/(Desempeño_Financiero!D53+Desempeño_Financiero!D83+Desempeño_Financiero!D96),0) -> 0.062430382 | D9: =IFERROR((Desempeño_Financiero!E83)/(Desempeño_Financiero!E53+Desempeño_Financiero!E83+Desempeño_Financiero!E96),0) -> 0.052969551 | E9: =IFERROR((Desempeño_Financiero!F83)/(Desempeño_Financiero!F53+Desempeño_Financiero!F83+Desempeño_Financiero!F96),0) -> 0.065633269 | F9: =IFERROR((Desempeño_Financiero!G83)/(Desempeño_Financiero!G53+Desempeño_Financiero!G83+Desempeño_Financiero!G96),0) -> 0.051938849 | G9: =IFERROR((Desempeño_Financiero!H83)/(Desempeño_Financiero!H53+Desempeño_Financiero!H83+Desempeño_Financiero!H96),0) -> 0.035323265 | H9: =IFERROR((Desempeño_Financiero!I83)/(Desempeño_Financiero!I53+Desempeño_Financiero!I83+Desempeño_Financiero!I96),0) -> 0.057619315 | J9: =IFERROR(($C9-D9)*10000,0) -> 94.608306 | K9: =IFERROR(($C9-E9)*10000,0) -> -32.028875 | L9: =IFERROR(($C9-F9)*10000,0) -> 104.91532 | M9: =IFERROR(($C9-G9)*10000,0) -> 271.07117 | N9: =IFERROR(($C9-H9)*10000,0) -> 48.11067 | P9: =IFERROR((Desempeño_Financiero!W83)/(Desempeño_Financiero!W53+Desempeño_Financiero!W83+Desempeño_Financiero!W96),0) -> 0.061975788 | Q9: =IFERROR((Desempeño_Financiero!X83)/(Desempeño_Financiero!X53+Desempeño_Financiero!X83+Desempeño_Financiero!X96),0) -> 0.059246218 | R9: =IFERROR((Desempeño_Financiero!Y83)/(Desempeño_Financiero!Y53+Desempeño_Financiero!Y83+Desempeño_Financiero!Y96),0) -> 0.061678902 | S9: =IFERROR((Desempeño_Financiero!Z83)/(Desempeño_Financiero!Z53+Desempeño_Financiero!Z83+Desempeño_Financiero!Z96),0) -> 0.056455138 | T9: =IFERROR((Desempeño_Financiero!AA83)/(Desempeño_Financiero!AA53+Desempeño_Financiero!AA83+Desempeño_Financiero!AA96),0) -> 0.036479087 | U9: =IFERROR((Desempeño_Financiero!AB83)/(Desempeño_Financiero!AB53+Desempeño_Financiero!AB83+Desempeño_Financiero!AB96),0) -> 0.064556036 | W9: =IFERROR(($P9-Q9)*10000,0) -> 27.2957 | X9: =IFERROR(($P9-R9)*10000,0) -> 2.9688598 | Y9: =IFERROR(($P9-S9)*10000,0) -> 55.206503 | Z9: =IFERROR(($P9-T9)*10000,0) -> 254.96701 | AA9: =IFERROR(($P9-U9)*10000,0) -> -25.802476
B11: INOF / Gasto Operativo | C11: =IFERROR((Desempeño_Financiero!D83/-Desempeño_Financiero!D89),0) -> 0.17612313 | D11: =IFERROR((Desempeño_Financiero!E83/-Desempeño_Financiero!E89),0) -> 0.12793825 | E11: =IFERROR((Desempeño_Financiero!F83/-Desempeño_Financiero!F89),0) -> 0.11718007 | F11: =IFERROR((Desempeño_Financiero!G83/-Desempeño_Financiero!G89),0) -> 0.13858394 | G11: =IFERROR((Desempeño_Financiero!H83/-Desempeño_Financiero!H89),0) -> 0.10840372 | H11: =IFERROR((Desempeño_Financiero!I83/-Desempeño_Financiero!I89),0) -> 0.17301431 | J11: =IFERROR(($C11-D11)*10000,0) -> 481.8488 | K11: =IFERROR(($C11-E11)*10000,0) -> 589.4306 | L11: =IFERROR(($C11-F11)*10000,0) -> 375.39183 | M11: =IFERROR(($C11-G11)*10000,0) -> 677.19411 | N11: =IFERROR(($C11-H11)*10000,0) -> 31.088177 | P11: =IFERROR((Desempeño_Financiero!W83/-Desempeño_Financiero!W89),0) -> 0.14961314 | Q11: =IFERROR((Desempeño_Financiero!X83/-Desempeño_Financiero!X89),0) -> 0.12952345 | R11: =IFERROR((Desempeño_Financiero!Y83/-Desempeño_Financiero!Y89),0) -> 0.13607392 | S11: =IFERROR((Desempeño_Financiero!Z83/-Desempeño_Financiero!Z89),0) -> 0.1321702 | T11: =IFERROR((Desempeño_Financiero!AA83/-Desempeño_Financiero!AA89),0) -> 0.10510573 | U11: =IFERROR((Desempeño_Financiero!AB83/-Desempeño_Financiero!AB89),0) -> 0.18194985 | W11: =IFERROR(($P11-Q11)*10000,0) -> 200.89699 | X11: =IFERROR(($P11-R11)*10000,0) -> 135.39228 | Y11: =IFERROR(($P11-S11)*10000,0) -> 174.42941 | Z11: =IFERROR(($P11-T11)*10000,0) -> 445.07417 | AA11: =IFERROR(($P11-U11)*10000,0) -> -323.36704
B13: Gasto Operativo / Activo | C13: =IFERROR(-Desempeño_Financiero!D89/Desempeño_Financiero!D17*12,0) -> 0.0081063288 | D13: =IFERROR(-Desempeño_Financiero!E89/Desempeño_Financiero!E17*12,0) -> 0.0084998129 | E13: =IFERROR(-Desempeño_Financiero!F89/Desempeño_Financiero!F17*12,0) -> 0.0078994176 | F13: =IFERROR(-Desempeño_Financiero!G89/Desempeño_Financiero!G17*12,0) -> 0.0082752727 | G13: =IFERROR(-Desempeño_Financiero!H89/Desempeño_Financiero!H17*12,0) -> 0.0073842328 | H13: =IFERROR(-Desempeño_Financiero!I89/Desempeño_Financiero!I17*12,0) -> 0.0080006379 | J13: =IFERROR(($C13-D13)*10000,0) -> -3.9348414 | K13: =IFERROR(($C13-E13)*10000,0) -> 2.0691115 | L13: =IFERROR(($C13-F13)*10000,0) -> -1.6894394 | M13: =IFERROR(($C13-G13)*10000,0) -> 7.2209602 | N13: =IFERROR(($C13-H13)*10000,0) -> 1.0569083 | P13: =IFERROR(-Desempeño_Financiero!W89/Desempeño_Financiero!W17*12,0) -> 0.024126584 | Q13: =IFERROR(-Desempeño_Financiero!X89/Desempeño_Financiero!X17*12,0) -> 0.025254313 | R13: =IFERROR(-Desempeño_Financiero!Y89/Desempeño_Financiero!Y17*12,0) -> 0.016019659 | S13: =IFERROR(-Desempeño_Financiero!Z89/Desempeño_Financiero!Z17*12,0) -> 0.024949331 | T13: =IFERROR(-Desempeño_Financiero!AA89/Desempeño_Financiero!AA17*12,0) -> 0.021795913 | U13: =IFERROR(-Desempeño_Financiero!AB89/Desempeño_Financiero!AB17*12,0) -> 0.022858728 | W13: =IFERROR(($P13-Q13)*10000,0) -> -11.277297 | X13: =IFERROR(($P13-R13)*10000,0) -> 81.069242 | Y13: =IFERROR(($P13-S13)*10000,0) -> -8.2274704 | Z13: =IFERROR(($P13-T13)*10000,0) -> 23.306704 | AA13: =IFERROR(($P13-U13)*10000,0) -> 12.678554
B15: Provisiones Brutas / Cartera Bruta | C15: =IFERROR(-Desempeño_Financiero!D56/Desempeño_Financiero!D102,0)*12 -> 0.0023867531 | D15: =IFERROR(-Desempeño_Financiero!E56/Desempeño_Financiero!E102,0)*12 -> 0.005422132 | E15: =IFERROR(-Desempeño_Financiero!F56/Desempeño_Financiero!F102,0)*12 -> -0.0012397719 | F15: =IFERROR(-Desempeño_Financiero!G56/Desempeño_Financiero!G102,0)*12 -> 0.0019477008 | G15: =IFERROR(-Desempeño_Financiero!H56/Desempeño_Financiero!H102,0)*12 -> 0.0013681865 | H15: =IFERROR(-Desempeño_Financiero!I56/Desempeño_Financiero!I102,0)*12 -> 0.001247754 | J15: =IFERROR(($C15-D15)*10000,0) -> -30.353789 | K15: =IFERROR(($C15-E15)*10000,0) -> 36.26525 | L15: =IFERROR(($C15-F15)*10000,0) -> 4.3905228 | M15: =IFERROR(($C15-G15)*10000,0) -> 10.185666 | N15: =IFERROR(($C15-H15)*10000,0) -> 11.38999 | P15: =IFERROR(-Desempeño_Financiero!W56/Desempeño_Financiero!W102,0)*12 -> 0.00062337729 | Q15: =IFERROR(-Desempeño_Financiero!X56/Desempeño_Financiero!X102,0)*12 -> 0.012146165 | R15: =IFERROR(-Desempeño_Financiero!Y56/Desempeño_Financiero!Y102,0)*12 -> -0.0017817257 | S15: =IFERROR(-Desempeño_Financiero!Z56/Desempeño_Financiero!Z102,0)*12 -> 0.009939676 | T15: =IFERROR(-Desempeño_Financiero!AA56/Desempeño_Financiero!AA102,0)*12 -> 0.01316574 | U15: =IFERROR(-Desempeño_Financiero!AB56/Desempeño_Financiero!AB102,0)*12 -> 0.0069053245 | W15: =IFERROR(($P15-Q15)*10000,0) -> -115.22788 | X15: =IFERROR(($P15-R15)*10000,0) -> 24.05103 | Y15: =IFERROR(($P15-S15)*10000,0) -> -93.162987 | Z15: =IFERROR(($P15-T15)*10000,0) -> -125.42363 | AA15: =IFERROR(($P15-U15)*10000,0) -> -62.819472
B17: ROE
B19: ROA

Sheet Evolutivos-->

Sheet Total_Producto
D1: REAL | AZ1: PRESUPUESTO | BO1: Acumulado | BW1: Saldo Prom Acumulado
BO2: =DATE(YEAR(BO6),1,1) -> 46023 | BP2: =DATE(YEAR(BP6),1,1) -> 46023 | BQ2: =DATE(YEAR(BQ6),1,1) -> 46023 | BR2: =DATE(YEAR(BR6),1,1) -> 45658 | BS2: =DATE(YEAR(BS6),1,1) -> 45292 | BT2: =DATE(YEAR(BT6),1,1) -> 44927
C3: N° dias T.Imp | D3: =DAY(D6) -> 31 | E3: =DAY(E6) -> 28 | F3: =DAY(F6) -> 31 | G3: =DAY(G6) -> 30 | H3: =DAY(H6) -> 31 | I3: =DAY(I6) -> 30 | J3: =DAY(J6) -> 31 | K3: =DAY(K6) -> 31 | ... BK3: =DAY(BK6) -> 31 | BO3: =AVERAGEIFS($D3:$BM3,$D$6:$BM$6,">="&BO$2,$D$6:$BM$6,"<="&BO$6,$D$5:$BM$5,BO$5) -> 30 | BP3: =AVERAGEIFS($D3:$BM3,$D$6:$BM$6,">="&BP$2,$D$6:$BM$6,"<="&BP$6,$D$5:$BM$5,BP$5) -> 30 | BQ3: =AVERAGEIFS($D3:$BM3,$D$6:$BM$6,">="&BQ$2,$D$6:$BM$6,"<="&BQ$6,$D$5:$BM$5,BQ$5) -> 29.5 | BR3: =AVERAGEIFS($D3:$BM3,$D$6:$BM$6,">="&BR$2,$D$6:$BM$6,"<="&BR$6,$D$5:$BM$5,BR$5) -> 30 | BS3: =AVERAGEIFS($D3:$BM3,$D$6:$BM$6,">="&BS$2,$D$6:$BM$6,"<="&BS$6,$D$5:$BM$5,BS$5) -> 30.333333 | BT3: =AVERAGEIFS($D3:$BM3,$D$6:$BM$6,">="&BT$2,$D$6:$BM$6,"<="&BT$6,$D$5:$BM$5,BT$5) -> 30
C4: N° dias FTP | D4: 30 | E4: 30 | F4: 30 | G4: 30 | H4: 30 | I4: 30 | J4: 30 | K4: 30 | L4: 30 | M4: 30 | N4: 30 | O4: 30 | P4: 30 | Q4: 30 | R4: 30 | S4: 30 | T4: 30 | U4: 30 | V4: 30 | W4: 30 | X4: 30 | Y4: 30 | Z4: 30 | AA4: 30 | AB4: 30 | AC4: 30 | AD4: 30 | AE4: 30 | AF4: 30 | AG4: 30 | AH4: 30 | AI4: 30 | AJ4: 30 | AK4: 30 | AL4: 30 | AM4: 30 | AN4: 30 | AO4: 30 | AP4: 30 | AQ4: 30 | AR4: 30 | AS4: 30 | AT4: 30 | AU4: 30 | AV4: 30 | AW4: 30 | AX4: 30 | AY4: 30 | AZ4: 30 | BA4: 30 | BB4: 30 | BC4: 30 | BD4: 30 | BE4: 30 | BF4: 30 | BG4: 30 | BH4: 30 | BI4: 30 | BJ4: 30 | BK4: 30 | BO4: =AVERAGEIFS($D4:$BM4,$D$6:$BM$6,">="&BO$2,$D$6:$BM$6,"<="&BO$6,$D$5:$BM$5,BO$5) -> 30 | BP4: =AVERAGEIFS($D4:$BM4,$D$6:$BM$6,">="&BP$2,$D$6:$BM$6,"<="&BP$6,$D$5:$BM$5,BP$5) -> 30 | BQ4: =AVERAGEIFS($D4:$BM4,$D$6:$BM$6,">="&BQ$2,$D$6:$BM$6,"<="&BQ$6,$D$5:$BM$5,BQ$5) -> 30 | BR4: =AVERAGEIFS($D4:$BM4,$D$6:$BM$6,">="&BR$2,$D$6:$BM$6,"<="&BR$6,$D$5:$BM$5,BR$5) -> 30 | BS4: =AVERAGEIFS($D4:$BM4,$D$6:$BM$6,">="&BS$2,$D$6:$BM$6,"<="&BS$6,$D$5:$BM$5,BS$5) -> 30 | BT4: =AVERAGEIFS($D4:$BM4,$D$6:$BM$6,">="&BT$2,$D$6:$BM$6,"<="&BT$6,$D$5:$BM$5,BT$5) -> 30
C5: Tipo | D5: R | E5: R | F5: R | G5: R | H5: R | I5: R | J5: R | K5: R | L5: R | M5: R | N5: R | O5: R | P5: R | Q5: R | R5: R | S5: R | T5: R | U5: R | V5: R | W5: R | X5: R | Y5: R | Z5: R | AA5: R | AB5: R | AC5: R | AD5: R | AE5: R | AF5: R | AG5: R | AH5: R | AI5: R | AJ5: R | AK5: R | AL5: R | AM5: R | AN5: R | AO5: R | AP5: R | AQ5: R | AR5: R | AS5: R | AT5: R | AU5: R | AV5: R | AW5: R | AX5: R | AY5: R | AZ5: P | BA5: P | BB5: P | BC5: P | BD5: P | BE5: P | BF5: P | BG5: P | BH5: P | BI5: P | BJ5: P | BK5: P | BO5: R | BP5: P | BQ5: R | BR5: R | BS5: R | BT5: R
C6: Total Hipotecario | D6: 44957 | E6: 44985 | F6: 45016 | G6: 45046 | H6: 45077 | I6: 45107 | J6: 45138 | K6: 45169 | L6: 45199 | M6: 45230 | N6: 45260 | O6: 45291 | P6: 45322 | Q6: 45351 | R6: 45382 | S6: 45412 | T6: 45443 | U6: 45473 | V6: 45504 | W6: 45535 | X6: 45565 | Y6: 45596 | Z6: 45626 | AA6: 45657 | AB6: 45688 | AC6: 45716 | AD6: 45747 | AE6: 45777 | AF6: 45808 | AG6: 45838 | AH6: 45869 | AI6: 45900 | AJ6: 45930 | AK6: 45961 | AL6: 45991 | AM6: 46022 | AN6: 46053 | AO6: 46081 | AP6: 46112 | AQ6: 46142 | AR6: 46173 | AS6: 46203 | AT6: 46234 | AU6: 46265 | AV6: 46295 | AW6: 46326 | AX6: 46356 | AY6: 46387 | AZ6: 46053 | BA6: 46081 | BB6: 46112 | BC6: 46142 | BD6: 46173 | BE6: 46203 | BF6: 46234 | BG6: 46265 | BH6: 46295 | BI6: 46326 | BJ6: 46356 | BK6: 46387 | BO6: =Desempeño_Financiero!$B$1 -> 46112 | BP6: =BO6 -> 46112 | BQ6: =EOMONTH(BO6,-1) -> 46081 | BR6: =EOMONTH(BO6,-12) -> 45747 | BS6: =EOMONTH(BO6,-24) -> 45382 | BT6: =EOMONTH(BO6,-36) -> 45016 | BW6: =BO6 -> 46112 | BX6: =BP6 -> 46112 | BY6: =BQ6 -> 46081 | BZ6: =BR6 -> 45747 | CA6: =BS6 -> 45382 | CB6: =BT6 -> 45016
A8: SALDO_FDP | C8: Vigente | D8: =Renta_Alta!D8+Masivo!D8+Consumo_Inicial!D8 -> 9306979.2 | E8: =Renta_Alta!E8+Masivo!E8+Consumo_Inicial!E8 -> 9343837 | F8: =Renta_Alta!F8+Masivo!F8+Consumo_Inicial!F8 -> 9379816.8 | G8: =Renta_Alta!G8+Masivo!G8+Consumo_Inicial!G8 -> 9428101.8 | H8: =Renta_Alta!H8+Masivo!H8+Consumo_Inicial!H8 -> 9463606.7 | I8: =Renta_Alta!I8+Masivo!I8+Consumo_Inicial!I8 -> 9512554.1 | J8: =Renta_Alta!J8+Masivo!J8+Consumo_Inicial!J8 -> 9520520.3 | K8: =Renta_Alta!K8+Masivo!K8+Consumo_Inicial!K8 -> 9581896.8 | ... BK8: =Renta_Alta!BK8+Masivo!BK8+Consumo_Inicial!BK8 -> 12221963 | BO8: =_xlfn.XLOOKUP(BO$6,$D$6:$BM$6,$D8:$BM8,,0,1) -> 11525777 | BP8: =_xlfn.XLOOKUP(BP$6,$D$6:$BM$6,$D8:$BM8,,0,-1) -> 11438229 | BQ8: =_xlfn.XLOOKUP(BQ$6,$D$6:$BM$6,$D8:$BM8,,0,1) -> 11478076 | BR8: =_xlfn.XLOOKUP(BR$6,$D$6:$BM$6,$D8:$BM8,,0,1) -> 10587478 | BS8: =_xlfn.XLOOKUP(BS$6,$D$6:$BM$6,$D8:$BM8,,0,1) -> 9915549.8 | BT8: =_xlfn.XLOOKUP(BT$6,$D$6:$BM$6,$D8:$BM8,,0,1) -> 9379816.8
A9: SALDO_FDP | C9: Refinanciado | D9: =Renta_Alta!D9+Masivo!D9+Consumo_Inicial!D9 -> 34450.126 | E9: =Renta_Alta!E9+Masivo!E9+Consumo_Inicial!E9 -> 33830.323 | F9: =Renta_Alta!F9+Masivo!F9+Consumo_Inicial!F9 -> 36652.88 | G9: =Renta_Alta!G9+Masivo!G9+Consumo_Inicial!G9 -> 33483.419 | H9: =Renta_Alta!H9+Masivo!H9+Consumo_Inicial!H9 -> 32226.636 | I9: =Renta_Alta!I9+Masivo!I9+Consumo_Inicial!I9 -> 32526.535 | J9: =Renta_Alta!J9+Masivo!J9+Consumo_Inicial!J9 -> 32175.432 | K9: =Renta_Alta!K9+Masivo!K9+Consumo_Inicial!K9 -> 31298.089 | ... BK9: =Renta_Alta!BK9+Masivo!BK9+Consumo_Inicial!BK9 -> 25869.388 | BO9: =_xlfn.XLOOKUP(BO$6,$D$6:$BM$6,$D9:$BM9,,0,1) -> 34203.92 | BP9: =_xlfn.XLOOKUP(BP$6,$D$6:$BM$6,$D9:$BM9,,0,-1) -> 29770.187 | BQ9: =_xlfn.XLOOKUP(BQ$6,$D$6:$BM$6,$D9:$BM9,,0,1) -> 32640.44 | BR9: =_xlfn.XLOOKUP(BR$6,$D$6:$BM$6,$D9:$BM9,,0,1) -> 29921.003 | BS9: =_xlfn.XLOOKUP(BS$6,$D$6:$BM$6,$D9:$BM9,,0,1) -> 31857.707 | BT9: =_xlfn.XLOOKUP(BT$6,$D$6:$BM$6,$D9:$BM9,,0,1) -> 36652.88
A10: SALDO_FDP | C10: Vencido y Judicial | D10: =Renta_Alta!D10+Masivo!D10+Consumo_Inicial!D10 -> 246802.44 | E10: =Renta_Alta!E10+Masivo!E10+Consumo_Inicial!E10 -> 248460.62 | F10: =Renta_Alta!F10+Masivo!F10+Consumo_Inicial!F10 -> 249639.32 | G10: =Renta_Alta!G10+Masivo!G10+Consumo_Inicial!G10 -> 253224.17 | H10: =Renta_Alta!H10+Masivo!H10+Consumo_Inicial!H10 -> 265429.48 | I10: =Renta_Alta!I10+Masivo!I10+Consumo_Inicial!I10 -> 265953.3 | J10: =Renta_Alta!J10+Masivo!J10+Consumo_Inicial!J10 -> 266312.9 | K10: =Renta_Alta!K10+Masivo!K10+Consumo_Inicial!K10 -> 270309.73 | ... BK10: =Renta_Alta!BK10+Masivo!BK10+Consumo_Inicial!BK10 -> 391039.79 | BO10: =_xlfn.XLOOKUP(BO$6,$D$6:$BM$6,$D10:$BM10,,0,1) -> 346980.86 | BP10: =_xlfn.XLOOKUP(BP$6,$D$6:$BM$6,$D10:$BM10,,0,-1) -> 375811.31 | BQ10: =_xlfn.XLOOKUP(BQ$6,$D$6:$BM$6,$D10:$BM10,,0,1) -> 338634.42 | BR10: =_xlfn.XLOOKUP(BR$6,$D$6:$BM$6,$D10:$BM10,,0,1) -> 343769.54 | BS10: =_xlfn.XLOOKUP(BS$6,$D$6:$BM$6,$D10:$BM10,,0,1) -> 294205.11 | BT10: =_xlfn.XLOOKUP(BT$6,$D$6:$BM$6,$D10:$BM10,,0,1) -> 249639.32
C11: Saldo FdP | D11: =SUM(D8:D10) -> 9588231.8 | E11: =SUM(E8:E10) -> 9626127.9 | F11: =SUM(F8:F10) -> 9666109 | G11: =SUM(G8:G10) -> 9714809.4 | H11: =SUM(H8:H10) -> 9761262.8 | I11: =SUM(I8:I10) -> 9811033.9 | J11: =SUM(J8:J10) -> 9819008.6 | K11: =SUM(K8:K10) -> 9883504.6 | ... BK11: =SUM(BK8:BK10) -> 12638872 | BO11: =SUM(BO8:BO10) -> 11906961 | BP11: =SUM(BP8:BP10) -> 11843810 | BQ11: =SUM(BQ8:BQ10) -> 11849351 | BR11: =SUM(BR8:BR10) -> 10961168 | BS11: =SUM(BS8:BS10) -> 10241613 | BT11: =SUM(BT8:BT10) -> 9666109
